Compiled from "MethodGraph.java"
public final class org.modelmapper.internal.bytebuddy.dynamic.scaffold.MethodGraph$Node$Unresolved extends java.lang.Enum<org.modelmapper.internal.bytebuddy.dynamic.scaffold.MethodGraph$Node$Unresolved> implements org.modelmapper.internal.bytebuddy.dynamic.scaffold.MethodGraph$Node {
  public static final org.modelmapper.internal.bytebuddy.dynamic.scaffold.MethodGraph$Node$Unresolved INSTANCE;

  private static final org.modelmapper.internal.bytebuddy.dynamic.scaffold.MethodGraph$Node$Unresolved[] $VALUES;

  public static org.modelmapper.internal.bytebuddy.dynamic.scaffold.MethodGraph$Node$Unresolved[] values();
    Code:
       0: getstatic     #28                 // Field $VALUES:[Lorg/modelmapper/internal/bytebuddy/dynamic/scaffold/MethodGraph$Node$Unresolved;
       3: invokevirtual #33                 // Method "[Lorg/modelmapper/internal/bytebuddy/dynamic/scaffold/MethodGraph$Node$Unresolved;".clone:()Ljava/lang/Object;
       6: checkcast     #29                 // class "[Lorg/modelmapper/internal/bytebuddy/dynamic/scaffold/MethodGraph$Node$Unresolved;"
       9: areturn

  public static org.modelmapper.internal.bytebuddy.dynamic.scaffold.MethodGraph$Node$Unresolved valueOf(java.lang.String);
    Code:
       0: ldc           #2                  // class org/modelmapper/internal/bytebuddy/dynamic/scaffold/MethodGraph$Node$Unresolved
       2: aload_0
       3: invokestatic  #38                 // Method java/lang/Enum.valueOf:(Ljava/lang/Class;Ljava/lang/String;)Ljava/lang/Enum;
       6: checkcast     #2                  // class org/modelmapper/internal/bytebuddy/dynamic/scaffold/MethodGraph$Node$Unresolved
       9: areturn

  private org.modelmapper.internal.bytebuddy.dynamic.scaffold.MethodGraph$Node$Unresolved();
    Code:
       0: aload_0
       1: aload_1
       2: iload_2
       3: invokespecial #44                 // Method java/lang/Enum."<init>":(Ljava/lang/String;I)V
       6: return

  public org.modelmapper.internal.bytebuddy.dynamic.scaffold.MethodGraph$Node$Sort getSort();
    Code:
       0: getstatic     #51                 // Field org/modelmapper/internal/bytebuddy/dynamic/scaffold/MethodGraph$Node$Sort.UNRESOLVED:Lorg/modelmapper/internal/bytebuddy/dynamic/scaffold/MethodGraph$Node$Sort;
       3: areturn

  public org.modelmapper.internal.bytebuddy.description.method.MethodDescription getRepresentative();
    Code:
       0: new           #55                 // class java/lang/IllegalStateException
       3: dup
       4: ldc           #57                 // String Cannot resolve the method of an illegal node
       6: invokespecial #60                 // Method java/lang/IllegalStateException."<init>":(Ljava/lang/String;)V
       9: athrow

  public java.util.Set<org.modelmapper.internal.bytebuddy.description.method.MethodDescription$TypeToken> getMethodTypes();
    Code:
       0: new           #55                 // class java/lang/IllegalStateException
       3: dup
       4: ldc           #64                 // String Cannot resolve bridge method of an illegal node
       6: invokespecial #60                 // Method java/lang/IllegalStateException."<init>":(Ljava/lang/String;)V
       9: athrow

  public org.modelmapper.internal.bytebuddy.description.modifier.Visibility getVisibility();
    Code:
       0: new           #55                 // class java/lang/IllegalStateException
       3: dup
       4: ldc           #68                 // String Cannot resolve visibility of an illegal node
       6: invokespecial #60                 // Method java/lang/IllegalStateException."<init>":(Ljava/lang/String;)V
       9: athrow

  static {};
    Code:
       0: new           #2                  // class org/modelmapper/internal/bytebuddy/dynamic/scaffold/MethodGraph$Node$Unresolved
       3: dup
       4: ldc           #71                 // String INSTANCE
       6: iconst_0
       7: invokespecial #72                 // Method "<init>":(Ljava/lang/String;I)V
      10: putstatic     #74                 // Field INSTANCE:Lorg/modelmapper/internal/bytebuddy/dynamic/scaffold/MethodGraph$Node$Unresolved;
      13: iconst_1
      14: anewarray     #2                  // class org/modelmapper/internal/bytebuddy/dynamic/scaffold/MethodGraph$Node$Unresolved
      17: dup
      18: iconst_0
      19: getstatic     #74                 // Field INSTANCE:Lorg/modelmapper/internal/bytebuddy/dynamic/scaffold/MethodGraph$Node$Unresolved;
      22: aastore
      23: putstatic     #28                 // Field $VALUES:[Lorg/modelmapper/internal/bytebuddy/dynamic/scaffold/MethodGraph$Node$Unresolved;
      26: return
}
