Compiled from "TypeWriter.java"
public class org.modelmapper.internal.bytebuddy.dynamic.scaffold.TypeWriter$Default$ForCreation<U> extends org.modelmapper.internal.bytebuddy.dynamic.scaffold.TypeWriter$Default<U> {
  private final org.modelmapper.internal.bytebuddy.dynamic.scaffold.TypeWriter$MethodPool methodPool;

  protected org.modelmapper.internal.bytebuddy.dynamic.scaffold.TypeWriter$Default$ForCreation(org.modelmapper.internal.bytebuddy.description.type.TypeDescription, org.modelmapper.internal.bytebuddy.ClassFileVersion, org.modelmapper.internal.bytebuddy.dynamic.scaffold.TypeWriter$FieldPool, org.modelmapper.internal.bytebuddy.dynamic.scaffold.TypeWriter$MethodPool, java.util.List<? extends org.modelmapper.internal.bytebuddy.dynamic.DynamicType>, org.modelmapper.internal.bytebuddy.description.field.FieldList<org.modelmapper.internal.bytebuddy.description.field.FieldDescription$InDefinedShape>, org.modelmapper.internal.bytebuddy.description.method.MethodList<?>, org.modelmapper.internal.bytebuddy.description.method.MethodList<?>, org.modelmapper.internal.bytebuddy.implementation.LoadedTypeInitializer, org.modelmapper.internal.bytebuddy.dynamic.scaffold.TypeInitializer, org.modelmapper.internal.bytebuddy.implementation.attribute.TypeAttributeAppender, org.modelmapper.internal.bytebuddy.asm.AsmVisitorWrapper, org.modelmapper.internal.bytebuddy.implementation.attribute.AnnotationValueFilter$Factory, org.modelmapper.internal.bytebuddy.implementation.attribute.AnnotationRetention, org.modelmapper.internal.bytebuddy.implementation.auxiliary.AuxiliaryType$NamingStrategy, org.modelmapper.internal.bytebuddy.implementation.Implementation$Context$Factory, org.modelmapper.internal.bytebuddy.dynamic.scaffold.TypeValidation, org.modelmapper.internal.bytebuddy.pool.TypePool);
    Code:
       0: aload_0
       1: aload_1
       2: aload_2
       3: aload_3
       4: aload         5
       6: aload         6
       8: aload         7
      10: aload         8
      12: aload         9
      14: aload         10
      16: aload         11
      18: aload         12
      20: aload         13
      22: aload         14
      24: aload         15
      26: aload         16
      28: aload         17
      30: aload         18
      32: invokespecial #84                 // Method org/modelmapper/internal/bytebuddy/dynamic/scaffold/TypeWriter$Default."<init>":(Lorg/modelmapper/internal/bytebuddy/description/type/TypeDescription;Lorg/modelmapper/internal/bytebuddy/ClassFileVersion;Lorg/modelmapper/internal/bytebuddy/dynamic/scaffold/TypeWriter$FieldPool;Ljava/util/List;Lorg/modelmapper/internal/bytebuddy/description/field/FieldList;Lorg/modelmapper/internal/bytebuddy/description/method/MethodList;Lorg/modelmapper/internal/bytebuddy/description/method/MethodList;Lorg/modelmapper/internal/bytebuddy/implementation/LoadedTypeInitializer;Lorg/modelmapper/internal/bytebuddy/dynamic/scaffold/TypeInitializer;Lorg/modelmapper/internal/bytebuddy/implementation/attribute/TypeAttributeAppender;Lorg/modelmapper/internal/bytebuddy/asm/AsmVisitorWrapper;Lorg/modelmapper/internal/bytebuddy/implementation/attribute/AnnotationValueFilter$Factory;Lorg/modelmapper/internal/bytebuddy/implementation/attribute/AnnotationRetention;Lorg/modelmapper/internal/bytebuddy/implementation/auxiliary/AuxiliaryType$NamingStrategy;Lorg/modelmapper/internal/bytebuddy/implementation/Implementation$Context$Factory;Lorg/modelmapper/internal/bytebuddy/dynamic/scaffold/TypeValidation;Lorg/modelmapper/internal/bytebuddy/pool/TypePool;)V
      35: aload_0
      36: aload         4
      38: putfield      #86                 // Field methodPool:Lorg/modelmapper/internal/bytebuddy/dynamic/scaffold/TypeWriter$MethodPool;
      41: return

  protected org.modelmapper.internal.bytebuddy.dynamic.scaffold.TypeWriter$Default<U>.UnresolvedType create(org.modelmapper.internal.bytebuddy.dynamic.scaffold.TypeInitializer);
    Code:
       0: aload_0
       1: getfield      #129                // Field asmVisitorWrapper:Lorg/modelmapper/internal/bytebuddy/asm/AsmVisitorWrapper;
       4: iconst_0
       5: invokeinterface #135,  2          // InterfaceMethod org/modelmapper/internal/bytebuddy/asm/AsmVisitorWrapper.mergeWriter:(I)I
      10: istore_2
      11: new           #52                 // class org/modelmapper/internal/bytebuddy/dynamic/scaffold/TypeWriter$Default$FrameComputingClassWriter
      14: dup
      15: iload_2
      16: aload_0
      17: getfield      #137                // Field typePool:Lorg/modelmapper/internal/bytebuddy/pool/TypePool;
      20: invokespecial #140                // Method org/modelmapper/internal/bytebuddy/dynamic/scaffold/TypeWriter$Default$FrameComputingClassWriter."<init>":(ILorg/modelmapper/internal/bytebuddy/pool/TypePool;)V
      23: astore_3
      24: aload_0
      25: getfield      #142                // Field implementationContextFactory:Lorg/modelmapper/internal/bytebuddy/implementation/Implementation$Context$Factory;
      28: aload_0
      29: getfield      #144                // Field instrumentedType:Lorg/modelmapper/internal/bytebuddy/description/type/TypeDescription;
      32: aload_0
      33: getfield      #146                // Field auxiliaryTypeNamingStrategy:Lorg/modelmapper/internal/bytebuddy/implementation/auxiliary/AuxiliaryType$NamingStrategy;
      36: aload_1
      37: aload_0
      38: getfield      #148                // Field classFileVersion:Lorg/modelmapper/internal/bytebuddy/ClassFileVersion;
      41: aload_0
      42: getfield      #148                // Field classFileVersion:Lorg/modelmapper/internal/bytebuddy/ClassFileVersion;
      45: invokeinterface #152,  6          // InterfaceMethod org/modelmapper/internal/bytebuddy/implementation/Implementation$Context$Factory.make:(Lorg/modelmapper/internal/bytebuddy/description/type/TypeDescription;Lorg/modelmapper/internal/bytebuddy/implementation/auxiliary/AuxiliaryType$NamingStrategy;Lorg/modelmapper/internal/bytebuddy/dynamic/scaffold/TypeInitializer;Lorg/modelmapper/internal/bytebuddy/ClassFileVersion;Lorg/modelmapper/internal/bytebuddy/ClassFileVersion;)Lorg/modelmapper/internal/bytebuddy/implementation/Implementation$Context$ExtractableView;
      50: astore        4
      52: aload_0
      53: getfield      #129                // Field asmVisitorWrapper:Lorg/modelmapper/internal/bytebuddy/asm/AsmVisitorWrapper;
      56: aload_0
      57: getfield      #144                // Field instrumentedType:Lorg/modelmapper/internal/bytebuddy/description/type/TypeDescription;
      60: aload_3
      61: aload_0
      62: getfield      #154                // Field typeValidation:Lorg/modelmapper/internal/bytebuddy/dynamic/scaffold/TypeValidation;
      65: invokestatic  #158                // Method org/modelmapper/internal/bytebuddy/dynamic/scaffold/TypeWriter$Default$ValidatingClassVisitor.of:(Lorg/modelmapper/internal/asm/ClassVisitor;Lorg/modelmapper/internal/bytebuddy/dynamic/scaffold/TypeValidation;)Lorg/modelmapper/internal/asm/ClassVisitor;
      68: aload         4
      70: aload_0
      71: getfield      #137                // Field typePool:Lorg/modelmapper/internal/bytebuddy/pool/TypePool;
      74: aload_0
      75: getfield      #160                // Field fields:Lorg/modelmapper/internal/bytebuddy/description/field/FieldList;
      78: aload_0
      79: getfield      #162                // Field methods:Lorg/modelmapper/internal/bytebuddy/description/method/MethodList;
      82: iload_2
      83: aload_0
      84: getfield      #129                // Field asmVisitorWrapper:Lorg/modelmapper/internal/bytebuddy/asm/AsmVisitorWrapper;
      87: iconst_0
      88: invokeinterface #165,  2          // InterfaceMethod org/modelmapper/internal/bytebuddy/asm/AsmVisitorWrapper.mergeReader:(I)I
      93: invokeinterface #169,  9          // InterfaceMethod org/modelmapper/internal/bytebuddy/asm/AsmVisitorWrapper.wrap:(Lorg/modelmapper/internal/bytebuddy/description/type/TypeDescription;Lorg/modelmapper/internal/asm/ClassVisitor;Lorg/modelmapper/internal/bytebuddy/implementation/Implementation$Context;Lorg/modelmapper/internal/bytebuddy/pool/TypePool;Lorg/modelmapper/internal/bytebuddy/description/field/FieldList;Lorg/modelmapper/internal/bytebuddy/description/method/MethodList;II)Lorg/modelmapper/internal/asm/ClassVisitor;
      98: astore        5
     100: aload         5
     102: aload_0
     103: getfield      #148                // Field classFileVersion:Lorg/modelmapper/internal/bytebuddy/ClassFileVersion;
     106: invokevirtual #175                // Method org/modelmapper/internal/bytebuddy/ClassFileVersion.getMinorMajorVersion:()I
     109: aload_0
     110: getfield      #144                // Field instrumentedType:Lorg/modelmapper/internal/bytebuddy/description/type/TypeDescription;
     113: aload_0
     114: getfield      #144                // Field instrumentedType:Lorg/modelmapper/internal/bytebuddy/description/type/TypeDescription;
     117: invokeinterface #179,  1          // InterfaceMethod org/modelmapper/internal/bytebuddy/description/type/TypeDescription.isInterface:()Z
     122: ifne          129
     125: iconst_1
     126: goto          130
     129: iconst_0
     130: invokeinterface #187,  2          // InterfaceMethod org/modelmapper/internal/bytebuddy/description/type/TypeDescription.getActualModifiers:(Z)I
     135: aload_0
     136: getfield      #144                // Field instrumentedType:Lorg/modelmapper/internal/bytebuddy/description/type/TypeDescription;
     139: invokeinterface #191,  1          // InterfaceMethod org/modelmapper/internal/bytebuddy/description/type/TypeDescription.getInternalName:()Ljava/lang/String;
     144: aload_0
     145: getfield      #144                // Field instrumentedType:Lorg/modelmapper/internal/bytebuddy/description/type/TypeDescription;
     148: invokeinterface #194,  1          // InterfaceMethod org/modelmapper/internal/bytebuddy/description/type/TypeDescription.getGenericSignature:()Ljava/lang/String;
     153: aload_0
     154: getfield      #144                // Field instrumentedType:Lorg/modelmapper/internal/bytebuddy/description/type/TypeDescription;
     157: invokeinterface #198,  1          // InterfaceMethod org/modelmapper/internal/bytebuddy/description/type/TypeDescription.getSuperClass:()Lorg/modelmapper/internal/bytebuddy/description/type/TypeDescription$Generic;
     162: ifnonnull     171
     165: getstatic     #201                // Field org/modelmapper/internal/bytebuddy/description/type/TypeDescription.OBJECT:Lorg/modelmapper/internal/bytebuddy/description/type/TypeDescription;
     168: goto          185
     171: aload_0
     172: getfield      #144                // Field instrumentedType:Lorg/modelmapper/internal/bytebuddy/description/type/TypeDescription;
     175: invokeinterface #198,  1          // InterfaceMethod org/modelmapper/internal/bytebuddy/description/type/TypeDescription.getSuperClass:()Lorg/modelmapper/internal/bytebuddy/description/type/TypeDescription$Generic;
     180: invokeinterface #207,  1          // InterfaceMethod org/modelmapper/internal/bytebuddy/description/type/TypeDescription$Generic.asErasure:()Lorg/modelmapper/internal/bytebuddy/description/type/TypeDescription;
     185: invokeinterface #191,  1          // InterfaceMethod org/modelmapper/internal/bytebuddy/description/type/TypeDescription.getInternalName:()Ljava/lang/String;
     190: aload_0
     191: getfield      #144                // Field instrumentedType:Lorg/modelmapper/internal/bytebuddy/description/type/TypeDescription;
     194: invokeinterface #211,  1          // InterfaceMethod org/modelmapper/internal/bytebuddy/description/type/TypeDescription.getInterfaces:()Lorg/modelmapper/internal/bytebuddy/description/type/TypeList$Generic;
     199: invokeinterface #215,  1          // InterfaceMethod org/modelmapper/internal/bytebuddy/description/type/TypeList$Generic.asErasures:()Lorg/modelmapper/internal/bytebuddy/description/type/TypeList;
     204: invokeinterface #219,  1          // InterfaceMethod org/modelmapper/internal/bytebuddy/description/type/TypeList.toInternalNames:()[Ljava/lang/String;
     209: invokevirtual #223                // Method org/modelmapper/internal/asm/ClassVisitor.visit:(IILjava/lang/String;Ljava/lang/String;Ljava/lang/String;[Ljava/lang/String;)V
     212: aload_0
     213: getfield      #225                // Field typeAttributeAppender:Lorg/modelmapper/internal/bytebuddy/implementation/attribute/TypeAttributeAppender;
     216: aload         5
     218: aload_0
     219: getfield      #144                // Field instrumentedType:Lorg/modelmapper/internal/bytebuddy/description/type/TypeDescription;
     222: aload_0
     223: getfield      #227                // Field annotationValueFilterFactory:Lorg/modelmapper/internal/bytebuddy/implementation/attribute/AnnotationValueFilter$Factory;
     226: aload_0
     227: getfield      #144                // Field instrumentedType:Lorg/modelmapper/internal/bytebuddy/description/type/TypeDescription;
     230: invokeinterface #231,  2          // InterfaceMethod org/modelmapper/internal/bytebuddy/implementation/attribute/AnnotationValueFilter$Factory.on:(Lorg/modelmapper/internal/bytebuddy/description/type/TypeDescription;)Lorg/modelmapper/internal/bytebuddy/implementation/attribute/AnnotationValueFilter;
     235: invokeinterface #237,  4          // InterfaceMethod org/modelmapper/internal/bytebuddy/implementation/attribute/TypeAttributeAppender.apply:(Lorg/modelmapper/internal/asm/ClassVisitor;Lorg/modelmapper/internal/bytebuddy/description/type/TypeDescription;Lorg/modelmapper/internal/bytebuddy/implementation/attribute/AnnotationValueFilter;)V
     240: aload_0
     241: getfield      #160                // Field fields:Lorg/modelmapper/internal/bytebuddy/description/field/FieldList;
     244: invokeinterface #243,  1          // InterfaceMethod org/modelmapper/internal/bytebuddy/description/field/FieldList.iterator:()Ljava/util/Iterator;
     249: astore        6
     251: aload         6
     253: invokeinterface #248,  1          // InterfaceMethod java/util/Iterator.hasNext:()Z
     258: ifeq          298
     261: aload         6
     263: invokeinterface #252,  1          // InterfaceMethod java/util/Iterator.next:()Ljava/lang/Object;
     268: checkcast     #38                 // class org/modelmapper/internal/bytebuddy/description/field/FieldDescription
     271: astore        7
     273: aload_0
     274: getfield      #254                // Field fieldPool:Lorg/modelmapper/internal/bytebuddy/dynamic/scaffold/TypeWriter$FieldPool;
     277: aload         7
     279: invokeinterface #258,  2          // InterfaceMethod org/modelmapper/internal/bytebuddy/dynamic/scaffold/TypeWriter$FieldPool.target:(Lorg/modelmapper/internal/bytebuddy/description/field/FieldDescription;)Lorg/modelmapper/internal/bytebuddy/dynamic/scaffold/TypeWriter$FieldPool$Record;
     284: aload         5
     286: aload_0
     287: getfield      #227                // Field annotationValueFilterFactory:Lorg/modelmapper/internal/bytebuddy/implementation/attribute/AnnotationValueFilter$Factory;
     290: invokeinterface #261,  3          // InterfaceMethod org/modelmapper/internal/bytebuddy/dynamic/scaffold/TypeWriter$FieldPool$Record.apply:(Lorg/modelmapper/internal/asm/ClassVisitor;Lorg/modelmapper/internal/bytebuddy/implementation/attribute/AnnotationValueFilter$Factory;)V
     295: goto          251
     298: aload_0
     299: getfield      #263                // Field instrumentedMethods:Lorg/modelmapper/internal/bytebuddy/description/method/MethodList;
     302: invokeinterface #266,  1          // InterfaceMethod org/modelmapper/internal/bytebuddy/description/method/MethodList.iterator:()Ljava/util/Iterator;
     307: astore        6
     309: aload         6
     311: invokeinterface #248,  1          // InterfaceMethod java/util/Iterator.hasNext:()Z
     316: ifeq          358
     319: aload         6
     321: invokeinterface #252,  1          // InterfaceMethod java/util/Iterator.next:()Ljava/lang/Object;
     326: checkcast     #268                // class org/modelmapper/internal/bytebuddy/description/method/MethodDescription
     329: astore        7
     331: aload_0
     332: getfield      #86                 // Field methodPool:Lorg/modelmapper/internal/bytebuddy/dynamic/scaffold/TypeWriter$MethodPool;
     335: aload         7
     337: invokeinterface #271,  2          // InterfaceMethod org/modelmapper/internal/bytebuddy/dynamic/scaffold/TypeWriter$MethodPool.target:(Lorg/modelmapper/internal/bytebuddy/description/method/MethodDescription;)Lorg/modelmapper/internal/bytebuddy/dynamic/scaffold/TypeWriter$MethodPool$Record;
     342: aload         5
     344: aload         4
     346: aload_0
     347: getfield      #227                // Field annotationValueFilterFactory:Lorg/modelmapper/internal/bytebuddy/implementation/attribute/AnnotationValueFilter$Factory;
     350: invokeinterface #274,  4          // InterfaceMethod org/modelmapper/internal/bytebuddy/dynamic/scaffold/TypeWriter$MethodPool$Record.apply:(Lorg/modelmapper/internal/asm/ClassVisitor;Lorg/modelmapper/internal/bytebuddy/implementation/Implementation$Context;Lorg/modelmapper/internal/bytebuddy/implementation/attribute/AnnotationValueFilter$Factory;)V
     355: goto          309
     358: aload         4
     360: new           #60                 // class org/modelmapper/internal/bytebuddy/dynamic/scaffold/TypeInitializer$Drain$Default
     363: dup
     364: aload_0
     365: getfield      #144                // Field instrumentedType:Lorg/modelmapper/internal/bytebuddy/description/type/TypeDescription;
     368: aload_0
     369: getfield      #86                 // Field methodPool:Lorg/modelmapper/internal/bytebuddy/dynamic/scaffold/TypeWriter$MethodPool;
     372: aload_0
     373: getfield      #227                // Field annotationValueFilterFactory:Lorg/modelmapper/internal/bytebuddy/implementation/attribute/AnnotationValueFilter$Factory;
     376: invokespecial #277                // Method org/modelmapper/internal/bytebuddy/dynamic/scaffold/TypeInitializer$Drain$Default."<init>":(Lorg/modelmapper/internal/bytebuddy/description/type/TypeDescription;Lorg/modelmapper/internal/bytebuddy/dynamic/scaffold/TypeWriter$MethodPool;Lorg/modelmapper/internal/bytebuddy/implementation/attribute/AnnotationValueFilter$Factory;)V
     379: aload         5
     381: aload_0
     382: getfield      #227                // Field annotationValueFilterFactory:Lorg/modelmapper/internal/bytebuddy/implementation/attribute/AnnotationValueFilter$Factory;
     385: invokeinterface #281,  4          // InterfaceMethod org/modelmapper/internal/bytebuddy/implementation/Implementation$Context$ExtractableView.drain:(Lorg/modelmapper/internal/bytebuddy/dynamic/scaffold/TypeInitializer$Drain;Lorg/modelmapper/internal/asm/ClassVisitor;Lorg/modelmapper/internal/bytebuddy/implementation/attribute/AnnotationValueFilter$Factory;)V
     390: aload         5
     392: invokevirtual #285                // Method org/modelmapper/internal/asm/ClassVisitor.visitEnd:()V
     395: new           #41                 // class org/modelmapper/internal/bytebuddy/dynamic/scaffold/TypeWriter$Default$UnresolvedType
     398: dup
     399: aload_0
     400: aload_3
     401: invokevirtual #289                // Method org/modelmapper/internal/asm/ClassWriter.toByteArray:()[B
     404: aload         4
     406: invokeinterface #293,  1          // InterfaceMethod org/modelmapper/internal/bytebuddy/implementation/Implementation$Context$ExtractableView.getAuxiliaryTypes:()Ljava/util/List;
     411: invokespecial #296                // Method org/modelmapper/internal/bytebuddy/dynamic/scaffold/TypeWriter$Default$UnresolvedType."<init>":(Lorg/modelmapper/internal/bytebuddy/dynamic/scaffold/TypeWriter$Default;[BLjava/util/List;)V
     414: areturn

  public boolean equals(java.lang.Object);
    Code:
       0: aload_0
       1: aload_1
       2: invokespecial #312                // Method org/modelmapper/internal/bytebuddy/dynamic/scaffold/TypeWriter$Default.equals:(Ljava/lang/Object;)Z
       5: ifne          10
       8: iconst_0
       9: ireturn
      10: aload_0
      11: aload_1
      12: if_acmpne     17
      15: iconst_1
      16: ireturn
      17: aload_1
      18: ifnonnull     23
      21: iconst_0
      22: ireturn
      23: aload_0
      24: invokevirtual #318                // Method java/lang/Object.getClass:()Ljava/lang/Class;
      27: aload_1
      28: invokevirtual #318                // Method java/lang/Object.getClass:()Ljava/lang/Class;
      31: if_acmpeq     36
      34: iconst_0
      35: ireturn
      36: aload_0
      37: getfield      #86                 // Field methodPool:Lorg/modelmapper/internal/bytebuddy/dynamic/scaffold/TypeWriter$MethodPool;
      40: aload_1
      41: checkcast     #2                  // class org/modelmapper/internal/bytebuddy/dynamic/scaffold/TypeWriter$Default$ForCreation
      44: getfield      #86                 // Field methodPool:Lorg/modelmapper/internal/bytebuddy/dynamic/scaffold/TypeWriter$MethodPool;
      47: invokeinterface #319,  2          // InterfaceMethod org/modelmapper/internal/bytebuddy/dynamic/scaffold/TypeWriter$MethodPool.equals:(Ljava/lang/Object;)Z
      52: ifne          57
      55: iconst_0
      56: ireturn
      57: iconst_1
      58: ireturn

  public int hashCode();
    Code:
       0: aload_0
       1: invokespecial #322                // Method org/modelmapper/internal/bytebuddy/dynamic/scaffold/TypeWriter$Default.hashCode:()I
       4: bipush        31
       6: imul
       7: aload_0
       8: getfield      #86                 // Field methodPool:Lorg/modelmapper/internal/bytebuddy/dynamic/scaffold/TypeWriter$MethodPool;
      11: invokeinterface #323,  1          // InterfaceMethod org/modelmapper/internal/bytebuddy/dynamic/scaffold/TypeWriter$MethodPool.hashCode:()I
      16: iadd
      17: ireturn
}
