Compiled from "TypeWriter.java"
public class org.modelmapper.internal.bytebuddy.dynamic.scaffold.TypeWriter$Default$FrameComputingClassWriter extends org.modelmapper.internal.asm.ClassWriter {
  private final org.modelmapper.internal.bytebuddy.pool.TypePool typePool;

  protected org.modelmapper.internal.bytebuddy.dynamic.scaffold.TypeWriter$Default$FrameComputingClassWriter(int, org.modelmapper.internal.bytebuddy.pool.TypePool);
    Code:
       0: aload_0
       1: iload_1
       2: invokespecial #28                 // Method org/modelmapper/internal/asm/ClassWriter."<init>":(I)V
       5: aload_0
       6: aload_2
       7: putfield      #30                 // Field typePool:Lorg/modelmapper/internal/bytebuddy/pool/TypePool;
      10: return

  protected org.modelmapper.internal.bytebuddy.dynamic.scaffold.TypeWriter$Default$FrameComputingClassWriter(org.modelmapper.internal.asm.ClassReader, int, org.modelmapper.internal.bytebuddy.pool.TypePool);
    Code:
       0: aload_0
       1: aload_1
       2: iload_2
       3: invokespecial #38                 // Method org/modelmapper/internal/asm/ClassWriter."<init>":(Lorg/modelmapper/internal/asm/ClassReader;I)V
       6: aload_0
       7: aload_3
       8: putfield      #30                 // Field typePool:Lorg/modelmapper/internal/bytebuddy/pool/TypePool;
      11: return

  protected java.lang.String getCommonSuperClass(java.lang.String, java.lang.String);
    Code:
       0: aload_0
       1: getfield      #30                 // Field typePool:Lorg/modelmapper/internal/bytebuddy/pool/TypePool;
       4: aload_1
       5: bipush        47
       7: bipush        46
       9: invokevirtual #48                 // Method java/lang/String.replace:(CC)Ljava/lang/String;
      12: invokeinterface #52,  2           // InterfaceMethod org/modelmapper/internal/bytebuddy/pool/TypePool.describe:(Ljava/lang/String;)Lorg/modelmapper/internal/bytebuddy/pool/TypePool$Resolution;
      17: invokeinterface #56,  1           // InterfaceMethod org/modelmapper/internal/bytebuddy/pool/TypePool$Resolution.resolve:()Lorg/modelmapper/internal/bytebuddy/description/type/TypeDescription;
      22: astore_3
      23: aload_0
      24: getfield      #30                 // Field typePool:Lorg/modelmapper/internal/bytebuddy/pool/TypePool;
      27: aload_2
      28: bipush        47
      30: bipush        46
      32: invokevirtual #48                 // Method java/lang/String.replace:(CC)Ljava/lang/String;
      35: invokeinterface #52,  2           // InterfaceMethod org/modelmapper/internal/bytebuddy/pool/TypePool.describe:(Ljava/lang/String;)Lorg/modelmapper/internal/bytebuddy/pool/TypePool$Resolution;
      40: invokeinterface #56,  1           // InterfaceMethod org/modelmapper/internal/bytebuddy/pool/TypePool$Resolution.resolve:()Lorg/modelmapper/internal/bytebuddy/description/type/TypeDescription;
      45: astore        4
      47: aload_3
      48: aload         4
      50: invokeinterface #60,  2           // InterfaceMethod org/modelmapper/internal/bytebuddy/description/type/TypeDescription.isAssignableFrom:(Lorg/modelmapper/internal/bytebuddy/description/type/TypeDescription;)Z
      55: ifeq          65
      58: aload_3
      59: invokeinterface #64,  1           // InterfaceMethod org/modelmapper/internal/bytebuddy/description/type/TypeDescription.getInternalName:()Ljava/lang/String;
      64: areturn
      65: aload_3
      66: aload         4
      68: invokeinterface #67,  2           // InterfaceMethod org/modelmapper/internal/bytebuddy/description/type/TypeDescription.isAssignableTo:(Lorg/modelmapper/internal/bytebuddy/description/type/TypeDescription;)Z
      73: ifeq          84
      76: aload         4
      78: invokeinterface #64,  1           // InterfaceMethod org/modelmapper/internal/bytebuddy/description/type/TypeDescription.getInternalName:()Ljava/lang/String;
      83: areturn
      84: aload_3
      85: invokeinterface #71,  1           // InterfaceMethod org/modelmapper/internal/bytebuddy/description/type/TypeDescription.isInterface:()Z
      90: ifne          103
      93: aload         4
      95: invokeinterface #71,  1           // InterfaceMethod org/modelmapper/internal/bytebuddy/description/type/TypeDescription.isInterface:()Z
     100: ifeq          112
     103: getstatic     #75                 // Field org/modelmapper/internal/bytebuddy/description/type/TypeDescription.OBJECT:Lorg/modelmapper/internal/bytebuddy/description/type/TypeDescription;
     106: invokeinterface #64,  1           // InterfaceMethod org/modelmapper/internal/bytebuddy/description/type/TypeDescription.getInternalName:()Ljava/lang/String;
     111: areturn
     112: aload_3
     113: invokeinterface #79,  1           // InterfaceMethod org/modelmapper/internal/bytebuddy/description/type/TypeDescription.getSuperClass:()Lorg/modelmapper/internal/bytebuddy/description/type/TypeDescription$Generic;
     118: invokeinterface #82,  1           // InterfaceMethod org/modelmapper/internal/bytebuddy/description/type/TypeDescription$Generic.asErasure:()Lorg/modelmapper/internal/bytebuddy/description/type/TypeDescription;
     123: astore_3
     124: aload_3
     125: aload         4
     127: invokeinterface #60,  2           // InterfaceMethod org/modelmapper/internal/bytebuddy/description/type/TypeDescription.isAssignableFrom:(Lorg/modelmapper/internal/bytebuddy/description/type/TypeDescription;)Z
     132: ifeq          112
     135: aload_3
     136: invokeinterface #64,  1           // InterfaceMethod org/modelmapper/internal/bytebuddy/description/type/TypeDescription.getInternalName:()Ljava/lang/String;
     141: areturn
}
