Compiled from "TypedStringValue.java"
public class org.springframework.beans.factory.config.TypedStringValue implements org.springframework.beans.BeanMetadataElement {
  private java.lang.String value;

  private volatile java.lang.Object targetType;

  private java.lang.Object source;

  private java.lang.String specifiedTypeName;

  private volatile boolean dynamic;

  public org.springframework.beans.factory.config.TypedStringValue(java.lang.String);
    Code:
       0: aload_0
       1: invokespecial #1                  // Method java/lang/Object."<init>":()V
       4: aload_0
       5: aload_1
       6: invokevirtual #2                  // Method setValue:(Ljava/lang/String;)V
       9: return

  public org.springframework.beans.factory.config.TypedStringValue(java.lang.String, java.lang.Class<?>);
    Code:
       0: aload_0
       1: invokespecial #1                  // Method java/lang/Object."<init>":()V
       4: aload_0
       5: aload_1
       6: invokevirtual #2                  // Method setValue:(Ljava/lang/String;)V
       9: aload_0
      10: aload_2
      11: invokevirtual #3                  // Method setTargetType:(Ljava/lang/Class;)V
      14: return

  public org.springframework.beans.factory.config.TypedStringValue(java.lang.String, java.lang.String);
    Code:
       0: aload_0
       1: invokespecial #1                  // Method java/lang/Object."<init>":()V
       4: aload_0
       5: aload_1
       6: invokevirtual #2                  // Method setValue:(Ljava/lang/String;)V
       9: aload_0
      10: aload_2
      11: invokevirtual #4                  // Method setTargetTypeName:(Ljava/lang/String;)V
      14: return

  public void setValue(java.lang.String);
    Code:
       0: aload_0
       1: aload_1
       2: putfield      #5                  // Field value:Ljava/lang/String;
       5: return

  public java.lang.String getValue();
    Code:
       0: aload_0
       1: getfield      #5                  // Field value:Ljava/lang/String;
       4: areturn

  public void setTargetType(java.lang.Class<?>);
    Code:
       0: aload_1
       1: ldc           #6                  // String \'targetType\' must not be null
       3: invokestatic  #7                  // Method org/springframework/util/Assert.notNull:(Ljava/lang/Object;Ljava/lang/String;)V
       6: aload_0
       7: aload_1
       8: putfield      #8                  // Field targetType:Ljava/lang/Object;
      11: return

  public java.lang.Class<?> getTargetType();
    Code:
       0: aload_0
       1: getfield      #8                  // Field targetType:Ljava/lang/Object;
       4: astore_1
       5: aload_1
       6: instanceof    #9                  // class java/lang/Class
       9: ifne          22
      12: new           #10                 // class java/lang/IllegalStateException
      15: dup
      16: ldc           #11                 // String Typed String value does not carry a resolved target type
      18: invokespecial #12                 // Method java/lang/IllegalStateException."<init>":(Ljava/lang/String;)V
      21: athrow
      22: aload_1
      23: checkcast     #9                  // class java/lang/Class
      26: areturn

  public void setTargetTypeName(java.lang.String);
    Code:
       0: aload_1
       1: ldc           #13                 // String \'targetTypeName\' must not be null
       3: invokestatic  #7                  // Method org/springframework/util/Assert.notNull:(Ljava/lang/Object;Ljava/lang/String;)V
       6: aload_0
       7: aload_1
       8: putfield      #8                  // Field targetType:Ljava/lang/Object;
      11: return

  public java.lang.String getTargetTypeName();
    Code:
       0: aload_0
       1: getfield      #8                  // Field targetType:Ljava/lang/Object;
       4: astore_1
       5: aload_1
       6: instanceof    #9                  // class java/lang/Class
       9: ifeq          20
      12: aload_1
      13: checkcast     #9                  // class java/lang/Class
      16: invokevirtual #14                 // Method java/lang/Class.getName:()Ljava/lang/String;
      19: areturn
      20: aload_1
      21: checkcast     #15                 // class java/lang/String
      24: areturn

  public boolean hasTargetType();
    Code:
       0: aload_0
       1: getfield      #8                  // Field targetType:Ljava/lang/Object;
       4: instanceof    #9                  // class java/lang/Class
       7: ireturn

  public java.lang.Class<?> resolveTargetType(java.lang.ClassLoader) throws java.lang.ClassNotFoundException;
    Code:
       0: aload_0
       1: getfield      #8                  // Field targetType:Ljava/lang/Object;
       4: ifnonnull     9
       7: aconst_null
       8: areturn
       9: aload_0
      10: invokevirtual #16                 // Method getTargetTypeName:()Ljava/lang/String;
      13: aload_1
      14: invokestatic  #17                 // Method org/springframework/util/ClassUtils.forName:(Ljava/lang/String;Ljava/lang/ClassLoader;)Ljava/lang/Class;
      17: astore_2
      18: aload_0
      19: aload_2
      20: putfield      #8                  // Field targetType:Ljava/lang/Object;
      23: aload_2
      24: areturn

  public void setSource(java.lang.Object);
    Code:
       0: aload_0
       1: aload_1
       2: putfield      #18                 // Field source:Ljava/lang/Object;
       5: return

  public java.lang.Object getSource();
    Code:
       0: aload_0
       1: getfield      #18                 // Field source:Ljava/lang/Object;
       4: areturn

  public void setSpecifiedTypeName(java.lang.String);
    Code:
       0: aload_0
       1: aload_1
       2: putfield      #19                 // Field specifiedTypeName:Ljava/lang/String;
       5: return

  public java.lang.String getSpecifiedTypeName();
    Code:
       0: aload_0
       1: getfield      #19                 // Field specifiedTypeName:Ljava/lang/String;
       4: areturn

  public void setDynamic();
    Code:
       0: aload_0
       1: iconst_1
       2: putfield      #20                 // Field dynamic:Z
       5: return

  public boolean isDynamic();
    Code:
       0: aload_0
       1: getfield      #20                 // Field dynamic:Z
       4: ireturn

  public boolean equals(java.lang.Object);
    Code:
       0: aload_0
       1: aload_1
       2: if_acmpne     7
       5: iconst_1
       6: ireturn
       7: aload_1
       8: instanceof    #21                 // class org/springframework/beans/factory/config/TypedStringValue
      11: ifne          16
      14: iconst_0
      15: ireturn
      16: aload_1
      17: checkcast     #21                 // class org/springframework/beans/factory/config/TypedStringValue
      20: astore_2
      21: aload_0
      22: getfield      #5                  // Field value:Ljava/lang/String;
      25: aload_2
      26: getfield      #5                  // Field value:Ljava/lang/String;
      29: invokestatic  #22                 // Method org/springframework/util/ObjectUtils.nullSafeEquals:(Ljava/lang/Object;Ljava/lang/Object;)Z
      32: ifeq          53
      35: aload_0
      36: getfield      #8                  // Field targetType:Ljava/lang/Object;
      39: aload_2
      40: getfield      #8                  // Field targetType:Ljava/lang/Object;
      43: invokestatic  #22                 // Method org/springframework/util/ObjectUtils.nullSafeEquals:(Ljava/lang/Object;Ljava/lang/Object;)Z
      46: ifeq          53
      49: iconst_1
      50: goto          54
      53: iconst_0
      54: ireturn

  public int hashCode();
    Code:
       0: aload_0
       1: getfield      #5                  // Field value:Ljava/lang/String;
       4: invokestatic  #23                 // Method org/springframework/util/ObjectUtils.nullSafeHashCode:(Ljava/lang/Object;)I
       7: bipush        29
       9: imul
      10: aload_0
      11: getfield      #8                  // Field targetType:Ljava/lang/Object;
      14: invokestatic  #23                 // Method org/springframework/util/ObjectUtils.nullSafeHashCode:(Ljava/lang/Object;)I
      17: iadd
      18: ireturn

  public java.lang.String toString();
    Code:
       0: new           #24                 // class java/lang/StringBuilder
       3: dup
       4: invokespecial #25                 // Method java/lang/StringBuilder."<init>":()V
       7: ldc           #26                 // String TypedStringValue: value [
       9: invokevirtual #27                 // Method java/lang/StringBuilder.append:(Ljava/lang/String;)Ljava/lang/StringBuilder;
      12: aload_0
      13: getfield      #5                  // Field value:Ljava/lang/String;
      16: invokevirtual #27                 // Method java/lang/StringBuilder.append:(Ljava/lang/String;)Ljava/lang/StringBuilder;
      19: ldc           #28                 // String ], target type [
      21: invokevirtual #27                 // Method java/lang/StringBuilder.append:(Ljava/lang/String;)Ljava/lang/StringBuilder;
      24: aload_0
      25: getfield      #8                  // Field targetType:Ljava/lang/Object;
      28: invokevirtual #29                 // Method java/lang/StringBuilder.append:(Ljava/lang/Object;)Ljava/lang/StringBuilder;
      31: ldc           #30                 // String ]
      33: invokevirtual #27                 // Method java/lang/StringBuilder.append:(Ljava/lang/String;)Ljava/lang/StringBuilder;
      36: invokevirtual #31                 // Method java/lang/StringBuilder.toString:()Ljava/lang/String;
      39: areturn
}
