Compiled from "WebSocketFrameAggregator.java"
public class io.netty.handler.codec.http.websocketx.WebSocketFrameAggregator extends io.netty.handler.codec.MessageToMessageDecoder<io.netty.handler.codec.http.websocketx.WebSocketFrame> {
  private final int maxFrameSize;

  private io.netty.handler.codec.http.websocketx.WebSocketFrame currentFrame;

  private boolean tooLongFrameFound;

  public io.netty.handler.codec.http.websocketx.WebSocketFrameAggregator(int);
    Code:
       0: aload_0
       1: invokespecial #1                  // Method io/netty/handler/codec/MessageToMessageDecoder."<init>":()V
       4: iload_1
       5: iconst_1
       6: if_icmpge     19
       9: new           #2                  // class java/lang/IllegalArgumentException
      12: dup
      13: ldc           #3                  // String maxFrameSize must be > 0
      15: invokespecial #4                  // Method java/lang/IllegalArgumentException."<init>":(Ljava/lang/String;)V
      18: athrow
      19: aload_0
      20: iload_1
      21: putfield      #5                  // Field maxFrameSize:I
      24: return

  protected void decode(io.netty.channel.ChannelHandlerContext, io.netty.handler.codec.http.websocketx.WebSocketFrame, java.util.List<java.lang.Object>) throws java.lang.Exception;
    Code:
       0: aload_0
       1: getfield      #6                  // Field currentFrame:Lio/netty/handler/codec/http/websocketx/WebSocketFrame;
       4: ifnonnull     146
       7: aload_0
       8: iconst_0
       9: putfield      #7                  // Field tooLongFrameFound:Z
      12: aload_2
      13: invokevirtual #8                  // Method io/netty/handler/codec/http/websocketx/WebSocketFrame.isFinalFragment:()Z
      16: ifeq          31
      19: aload_3
      20: aload_2
      21: invokevirtual #9                  // Method io/netty/handler/codec/http/websocketx/WebSocketFrame.retain:()Lio/netty/handler/codec/http/websocketx/WebSocketFrame;
      24: invokeinterface #10,  2           // InterfaceMethod java/util/List.add:(Ljava/lang/Object;)Z
      29: pop
      30: return
      31: aload_1
      32: invokeinterface #11,  1           // InterfaceMethod io/netty/channel/ChannelHandlerContext.alloc:()Lio/netty/buffer/ByteBufAllocator;
      37: invokeinterface #12,  1           // InterfaceMethod io/netty/buffer/ByteBufAllocator.compositeBuffer:()Lio/netty/buffer/CompositeByteBuf;
      42: aload_2
      43: invokevirtual #13                 // Method io/netty/handler/codec/http/websocketx/WebSocketFrame.content:()Lio/netty/buffer/ByteBuf;
      46: invokevirtual #14                 // Method io/netty/buffer/ByteBuf.retain:()Lio/netty/buffer/ByteBuf;
      49: invokevirtual #15                 // Method io/netty/buffer/CompositeByteBuf.addComponent:(Lio/netty/buffer/ByteBuf;)Lio/netty/buffer/CompositeByteBuf;
      52: astore        4
      54: aload         4
      56: aload         4
      58: invokevirtual #16                 // Method io/netty/buffer/ByteBuf.writerIndex:()I
      61: aload_2
      62: invokevirtual #13                 // Method io/netty/handler/codec/http/websocketx/WebSocketFrame.content:()Lio/netty/buffer/ByteBuf;
      65: invokevirtual #17                 // Method io/netty/buffer/ByteBuf.readableBytes:()I
      68: iadd
      69: invokevirtual #18                 // Method io/netty/buffer/ByteBuf.writerIndex:(I)Lio/netty/buffer/ByteBuf;
      72: pop
      73: aload_2
      74: instanceof    #19                 // class io/netty/handler/codec/http/websocketx/TextWebSocketFrame
      77: ifeq          101
      80: aload_0
      81: new           #19                 // class io/netty/handler/codec/http/websocketx/TextWebSocketFrame
      84: dup
      85: iconst_1
      86: aload_2
      87: invokevirtual #20                 // Method io/netty/handler/codec/http/websocketx/WebSocketFrame.rsv:()I
      90: aload         4
      92: invokespecial #21                 // Method io/netty/handler/codec/http/websocketx/TextWebSocketFrame."<init>":(ZILio/netty/buffer/ByteBuf;)V
      95: putfield      #6                  // Field currentFrame:Lio/netty/handler/codec/http/websocketx/WebSocketFrame;
      98: goto          145
     101: aload_2
     102: instanceof    #22                 // class io/netty/handler/codec/http/websocketx/BinaryWebSocketFrame
     105: ifeq          129
     108: aload_0
     109: new           #22                 // class io/netty/handler/codec/http/websocketx/BinaryWebSocketFrame
     112: dup
     113: iconst_1
     114: aload_2
     115: invokevirtual #20                 // Method io/netty/handler/codec/http/websocketx/WebSocketFrame.rsv:()I
     118: aload         4
     120: invokespecial #23                 // Method io/netty/handler/codec/http/websocketx/BinaryWebSocketFrame."<init>":(ZILio/netty/buffer/ByteBuf;)V
     123: putfield      #6                  // Field currentFrame:Lio/netty/handler/codec/http/websocketx/WebSocketFrame;
     126: goto          145
     129: aload         4
     131: invokevirtual #24                 // Method io/netty/buffer/ByteBuf.release:()Z
     134: pop
     135: new           #25                 // class java/lang/IllegalStateException
     138: dup
     139: ldc           #26                 // String WebSocket frame was not of type TextWebSocketFrame or BinaryWebSocketFrame
     141: invokespecial #27                 // Method java/lang/IllegalStateException."<init>":(Ljava/lang/String;)V
     144: athrow
     145: return
     146: aload_2
     147: instanceof    #28                 // class io/netty/handler/codec/http/websocketx/ContinuationWebSocketFrame
     150: ifeq          312
     153: aload_0
     154: getfield      #7                  // Field tooLongFrameFound:Z
     157: ifeq          173
     160: aload_2
     161: invokevirtual #8                  // Method io/netty/handler/codec/http/websocketx/WebSocketFrame.isFinalFragment:()Z
     164: ifeq          172
     167: aload_0
     168: aconst_null
     169: putfield      #6                  // Field currentFrame:Lio/netty/handler/codec/http/websocketx/WebSocketFrame;
     172: return
     173: aload_0
     174: getfield      #6                  // Field currentFrame:Lio/netty/handler/codec/http/websocketx/WebSocketFrame;
     177: invokevirtual #13                 // Method io/netty/handler/codec/http/websocketx/WebSocketFrame.content:()Lio/netty/buffer/ByteBuf;
     180: checkcast     #29                 // class io/netty/buffer/CompositeByteBuf
     183: astore        4
     185: aload         4
     187: invokevirtual #30                 // Method io/netty/buffer/CompositeByteBuf.readableBytes:()I
     190: aload_0
     191: getfield      #5                  // Field maxFrameSize:I
     194: aload_2
     195: invokevirtual #13                 // Method io/netty/handler/codec/http/websocketx/WebSocketFrame.content:()Lio/netty/buffer/ByteBuf;
     198: invokevirtual #17                 // Method io/netty/buffer/ByteBuf.readableBytes:()I
     201: isub
     202: if_icmple     251
     205: aload_0
     206: getfield      #6                  // Field currentFrame:Lio/netty/handler/codec/http/websocketx/WebSocketFrame;
     209: invokevirtual #31                 // Method io/netty/handler/codec/http/websocketx/WebSocketFrame.release:()Z
     212: pop
     213: aload_0
     214: iconst_1
     215: putfield      #7                  // Field tooLongFrameFound:Z
     218: new           #32                 // class io/netty/handler/codec/TooLongFrameException
     221: dup
     222: new           #33                 // class java/lang/StringBuilder
     225: dup
     226: invokespecial #34                 // Method java/lang/StringBuilder."<init>":()V
     229: ldc           #35                 // String WebSocketFrame length exceeded
     231: invokevirtual #36                 // Method java/lang/StringBuilder.append:(Ljava/lang/String;)Ljava/lang/StringBuilder;
     234: aload         4
     236: invokevirtual #37                 // Method java/lang/StringBuilder.append:(Ljava/lang/Object;)Ljava/lang/StringBuilder;
     239: ldc           #38                 // String  bytes.
     241: invokevirtual #36                 // Method java/lang/StringBuilder.append:(Ljava/lang/String;)Ljava/lang/StringBuilder;
     244: invokevirtual #39                 // Method java/lang/StringBuilder.toString:()Ljava/lang/String;
     247: invokespecial #40                 // Method io/netty/handler/codec/TooLongFrameException."<init>":(Ljava/lang/String;)V
     250: athrow
     251: aload         4
     253: aload_2
     254: invokevirtual #13                 // Method io/netty/handler/codec/http/websocketx/WebSocketFrame.content:()Lio/netty/buffer/ByteBuf;
     257: invokevirtual #14                 // Method io/netty/buffer/ByteBuf.retain:()Lio/netty/buffer/ByteBuf;
     260: invokevirtual #15                 // Method io/netty/buffer/CompositeByteBuf.addComponent:(Lio/netty/buffer/ByteBuf;)Lio/netty/buffer/CompositeByteBuf;
     263: pop
     264: aload         4
     266: aload         4
     268: invokevirtual #41                 // Method io/netty/buffer/CompositeByteBuf.writerIndex:()I
     271: aload_2
     272: invokevirtual #13                 // Method io/netty/handler/codec/http/websocketx/WebSocketFrame.content:()Lio/netty/buffer/ByteBuf;
     275: invokevirtual #17                 // Method io/netty/buffer/ByteBuf.readableBytes:()I
     278: iadd
     279: invokevirtual #42                 // Method io/netty/buffer/CompositeByteBuf.writerIndex:(I)Lio/netty/buffer/CompositeByteBuf;
     282: pop
     283: aload_2
     284: invokevirtual #8                  // Method io/netty/handler/codec/http/websocketx/WebSocketFrame.isFinalFragment:()Z
     287: ifeq          311
     290: aload_0
     291: getfield      #6                  // Field currentFrame:Lio/netty/handler/codec/http/websocketx/WebSocketFrame;
     294: astore        5
     296: aload_0
     297: aconst_null
     298: putfield      #6                  // Field currentFrame:Lio/netty/handler/codec/http/websocketx/WebSocketFrame;
     301: aload_3
     302: aload         5
     304: invokeinterface #10,  2           // InterfaceMethod java/util/List.add:(Ljava/lang/Object;)Z
     309: pop
     310: return
     311: return
     312: aload_3
     313: aload_2
     314: invokevirtual #9                  // Method io/netty/handler/codec/http/websocketx/WebSocketFrame.retain:()Lio/netty/handler/codec/http/websocketx/WebSocketFrame;
     317: invokeinterface #10,  2           // InterfaceMethod java/util/List.add:(Ljava/lang/Object;)Z
     322: pop
     323: return

  public void channelInactive(io.netty.channel.ChannelHandlerContext) throws java.lang.Exception;
    Code:
       0: aload_0
       1: aload_1
       2: invokespecial #43                 // Method io/netty/handler/codec/MessageToMessageDecoder.channelInactive:(Lio/netty/channel/ChannelHandlerContext;)V
       5: aload_0
       6: getfield      #6                  // Field currentFrame:Lio/netty/handler/codec/http/websocketx/WebSocketFrame;
       9: ifnull        25
      12: aload_0
      13: getfield      #6                  // Field currentFrame:Lio/netty/handler/codec/http/websocketx/WebSocketFrame;
      16: invokevirtual #31                 // Method io/netty/handler/codec/http/websocketx/WebSocketFrame.release:()Z
      19: pop
      20: aload_0
      21: aconst_null
      22: putfield      #6                  // Field currentFrame:Lio/netty/handler/codec/http/websocketx/WebSocketFrame;
      25: return

  public void handlerRemoved(io.netty.channel.ChannelHandlerContext) throws java.lang.Exception;
    Code:
       0: aload_0
       1: aload_1
       2: invokespecial #44                 // Method io/netty/handler/codec/MessageToMessageDecoder.handlerRemoved:(Lio/netty/channel/ChannelHandlerContext;)V
       5: aload_0
       6: getfield      #6                  // Field currentFrame:Lio/netty/handler/codec/http/websocketx/WebSocketFrame;
       9: ifnull        25
      12: aload_0
      13: getfield      #6                  // Field currentFrame:Lio/netty/handler/codec/http/websocketx/WebSocketFrame;
      16: invokevirtual #31                 // Method io/netty/handler/codec/http/websocketx/WebSocketFrame.release:()Z
      19: pop
      20: aload_0
      21: aconst_null
      22: putfield      #6                  // Field currentFrame:Lio/netty/handler/codec/http/websocketx/WebSocketFrame;
      25: return

  protected void decode(io.netty.channel.ChannelHandlerContext, java.lang.Object, java.util.List) throws java.lang.Exception;
    Code:
       0: aload_0
       1: aload_1
       2: aload_2
       3: checkcast     #45                 // class io/netty/handler/codec/http/websocketx/WebSocketFrame
       6: aload_3
       7: invokevirtual #46                 // Method decode:(Lio/netty/channel/ChannelHandlerContext;Lio/netty/handler/codec/http/websocketx/WebSocketFrame;Ljava/util/List;)V
      10: return
}
