Compiled from "ConfigurationsListResourceHandler.java"
public class org.sonatype.nexus.rest.configurations.ConfigurationsListResourceHandler extends org.sonatype.nexus.rest.AbstractNexusResourceHandler {
  public org.sonatype.nexus.rest.configurations.ConfigurationsListResourceHandler(org.restlet.Context, org.restlet.data.Request, org.restlet.data.Response);
    Code:
       0: aload_0
       1: aload_1
       2: aload_2
       3: aload_3
       4: invokespecial #1                  // Method org/sonatype/nexus/rest/AbstractNexusResourceHandler."<init>":(Lorg/restlet/Context;Lorg/restlet/data/Request;Lorg/restlet/data/Response;)V
       7: return

  public org.restlet.resource.Representation getRepresentationHandler(org.restlet.resource.Variant) throws java.io.IOException;
    Code:
       0: new           #2                  // class org/sonatype/nexus/rest/model/ConfigurationsListResourceResponse
       3: dup
       4: invokespecial #3                  // Method org/sonatype/nexus/rest/model/ConfigurationsListResourceResponse."<init>":()V
       7: astore_2
       8: new           #4                  // class org/sonatype/nexus/rest/model/ConfigurationsListResource
      11: dup
      12: invokespecial #5                  // Method org/sonatype/nexus/rest/model/ConfigurationsListResource."<init>":()V
      15: astore_3
      16: aload_3
      17: aload_0
      18: ldc           #6                  // String default
      20: invokevirtual #7                  // Method calculateSubReference:(Ljava/lang/String;)Lorg/restlet/data/Reference;
      23: invokevirtual #8                  // Method org/restlet/data/Reference.toString:()Ljava/lang/String;
      26: invokevirtual #9                  // Method org/sonatype/nexus/rest/model/ConfigurationsListResource.setResourceURI:(Ljava/lang/String;)V
      29: aload_3
      30: ldc           #6                  // String default
      32: invokevirtual #10                 // Method org/sonatype/nexus/rest/model/ConfigurationsListResource.setName:(Ljava/lang/String;)V
      35: aload_2
      36: aload_3
      37: invokevirtual #11                 // Method org/sonatype/nexus/rest/model/ConfigurationsListResourceResponse.addData:(Lorg/sonatype/nexus/rest/model/ConfigurationsListResource;)V
      40: new           #4                  // class org/sonatype/nexus/rest/model/ConfigurationsListResource
      43: dup
      44: invokespecial #5                  // Method org/sonatype/nexus/rest/model/ConfigurationsListResource."<init>":()V
      47: astore_3
      48: aload_3
      49: aload_0
      50: ldc           #12                 // String current
      52: invokevirtual #7                  // Method calculateSubReference:(Ljava/lang/String;)Lorg/restlet/data/Reference;
      55: invokevirtual #8                  // Method org/restlet/data/Reference.toString:()Ljava/lang/String;
      58: invokevirtual #9                  // Method org/sonatype/nexus/rest/model/ConfigurationsListResource.setResourceURI:(Ljava/lang/String;)V
      61: aload_3
      62: ldc           #12                 // String current
      64: invokevirtual #10                 // Method org/sonatype/nexus/rest/model/ConfigurationsListResource.setName:(Ljava/lang/String;)V
      67: aload_2
      68: aload_3
      69: invokevirtual #11                 // Method org/sonatype/nexus/rest/model/ConfigurationsListResourceResponse.addData:(Lorg/sonatype/nexus/rest/model/ConfigurationsListResource;)V
      72: aload_0
      73: aload_1
      74: aload_2
      75: invokevirtual #13                 // Method serialize:(Lorg/restlet/resource/Variant;Ljava/lang/Object;)Lorg/restlet/resource/Representation;
      78: areturn
}
