Compiled from "JdbcSessionContextImpl.java"
public class org.hibernate.internal.JdbcSessionContextImpl implements org.hibernate.resource.jdbc.spi.JdbcSessionContext {
  private final org.hibernate.engine.spi.SessionFactoryImplementor sessionFactory;

  private final org.hibernate.resource.jdbc.spi.StatementInspector statementInspector;

  private final org.hibernate.resource.jdbc.spi.PhysicalConnectionHandlingMode connectionHandlingMode;

  private final transient org.hibernate.service.ServiceRegistry serviceRegistry;

  private final transient org.hibernate.resource.jdbc.spi.JdbcObserver jdbcObserver;

  public org.hibernate.internal.JdbcSessionContextImpl(org.hibernate.engine.spi.SharedSessionContractImplementor, org.hibernate.resource.jdbc.spi.StatementInspector);
    Code:
       0: aload_0
       1: invokespecial #1                  // Method java/lang/Object."<init>":()V
       4: aload_0
       5: aload_1
       6: invokeinterface #2,  1            // InterfaceMethod org/hibernate/engine/spi/SharedSessionContractImplementor.getFactory:()Lorg/hibernate/engine/spi/SessionFactoryImplementor;
      11: putfield      #3                  // Field sessionFactory:Lorg/hibernate/engine/spi/SessionFactoryImplementor;
      14: aload_0
      15: aload_2
      16: putfield      #4                  // Field statementInspector:Lorg/hibernate/resource/jdbc/spi/StatementInspector;
      19: aload_0
      20: aload_0
      21: invokespecial #5                  // Method settings:()Lorg/hibernate/boot/spi/SessionFactoryOptions;
      24: invokeinterface #6,  1            // InterfaceMethod org/hibernate/boot/spi/SessionFactoryOptions.getPhysicalConnectionHandlingMode:()Lorg/hibernate/resource/jdbc/spi/PhysicalConnectionHandlingMode;
      29: putfield      #7                  // Field connectionHandlingMode:Lorg/hibernate/resource/jdbc/spi/PhysicalConnectionHandlingMode;
      32: aload_0
      33: aload_0
      34: getfield      #3                  // Field sessionFactory:Lorg/hibernate/engine/spi/SessionFactoryImplementor;
      37: invokeinterface #8,  1            // InterfaceMethod org/hibernate/engine/spi/SessionFactoryImplementor.getServiceRegistry:()Lorg/hibernate/service/spi/ServiceRegistryImplementor;
      42: putfield      #9                  // Field serviceRegistry:Lorg/hibernate/service/ServiceRegistry;
      45: aload_0
      46: new           #10                 // class org/hibernate/internal/JdbcObserverImpl
      49: dup
      50: aload_1
      51: invokespecial #11                 // Method org/hibernate/internal/JdbcObserverImpl."<init>":(Lorg/hibernate/engine/spi/SharedSessionContractImplementor;)V
      54: putfield      #12                 // Field jdbcObserver:Lorg/hibernate/resource/jdbc/spi/JdbcObserver;
      57: aload_0
      58: getfield      #4                  // Field statementInspector:Lorg/hibernate/resource/jdbc/spi/StatementInspector;
      61: ifnonnull     74
      64: new           #13                 // class java/lang/IllegalArgumentException
      67: dup
      68: ldc           #14                 // String StatementInspector cannot be null
      70: invokespecial #15                 // Method java/lang/IllegalArgumentException."<init>":(Ljava/lang/String;)V
      73: athrow
      74: return

  public boolean isScrollableResultSetsEnabled();
    Code:
       0: aload_0
       1: invokespecial #5                  // Method settings:()Lorg/hibernate/boot/spi/SessionFactoryOptions;
       4: invokeinterface #16,  1           // InterfaceMethod org/hibernate/boot/spi/SessionFactoryOptions.isScrollableResultSetsEnabled:()Z
       9: ireturn

  public boolean isGetGeneratedKeysEnabled();
    Code:
       0: aload_0
       1: invokespecial #5                  // Method settings:()Lorg/hibernate/boot/spi/SessionFactoryOptions;
       4: invokeinterface #17,  1           // InterfaceMethod org/hibernate/boot/spi/SessionFactoryOptions.isGetGeneratedKeysEnabled:()Z
       9: ireturn

  public int getFetchSize();
    Code:
       0: aload_0
       1: invokespecial #5                  // Method settings:()Lorg/hibernate/boot/spi/SessionFactoryOptions;
       4: invokeinterface #18,  1           // InterfaceMethod org/hibernate/boot/spi/SessionFactoryOptions.getJdbcFetchSize:()Ljava/lang/Integer;
       9: invokevirtual #19                 // Method java/lang/Integer.intValue:()I
      12: ireturn

  public org.hibernate.resource.jdbc.spi.PhysicalConnectionHandlingMode getPhysicalConnectionHandlingMode();
    Code:
       0: aload_0
       1: getfield      #7                  // Field connectionHandlingMode:Lorg/hibernate/resource/jdbc/spi/PhysicalConnectionHandlingMode;
       4: areturn

  public org.hibernate.ConnectionReleaseMode getConnectionReleaseMode();
    Code:
       0: aload_0
       1: getfield      #7                  // Field connectionHandlingMode:Lorg/hibernate/resource/jdbc/spi/PhysicalConnectionHandlingMode;
       4: invokevirtual #20                 // Method org/hibernate/resource/jdbc/spi/PhysicalConnectionHandlingMode.getReleaseMode:()Lorg/hibernate/ConnectionReleaseMode;
       7: areturn

  public org.hibernate.ConnectionAcquisitionMode getConnectionAcquisitionMode();
    Code:
       0: aload_0
       1: getfield      #7                  // Field connectionHandlingMode:Lorg/hibernate/resource/jdbc/spi/PhysicalConnectionHandlingMode;
       4: invokevirtual #21                 // Method org/hibernate/resource/jdbc/spi/PhysicalConnectionHandlingMode.getAcquisitionMode:()Lorg/hibernate/ConnectionAcquisitionMode;
       7: areturn

  public org.hibernate.resource.jdbc.spi.StatementInspector getStatementInspector();
    Code:
       0: aload_0
       1: getfield      #4                  // Field statementInspector:Lorg/hibernate/resource/jdbc/spi/StatementInspector;
       4: areturn

  public org.hibernate.resource.jdbc.spi.JdbcObserver getObserver();
    Code:
       0: aload_0
       1: getfield      #12                 // Field jdbcObserver:Lorg/hibernate/resource/jdbc/spi/JdbcObserver;
       4: areturn

  public org.hibernate.engine.spi.SessionFactoryImplementor getSessionFactory();
    Code:
       0: aload_0
       1: getfield      #3                  // Field sessionFactory:Lorg/hibernate/engine/spi/SessionFactoryImplementor;
       4: areturn

  public org.hibernate.service.ServiceRegistry getServiceRegistry();
    Code:
       0: aload_0
       1: getfield      #9                  // Field serviceRegistry:Lorg/hibernate/service/ServiceRegistry;
       4: areturn

  private org.hibernate.boot.spi.SessionFactoryOptions settings();
    Code:
       0: aload_0
       1: getfield      #3                  // Field sessionFactory:Lorg/hibernate/engine/spi/SessionFactoryImplementor;
       4: invokeinterface #22,  1           // InterfaceMethod org/hibernate/engine/spi/SessionFactoryImplementor.getSessionFactoryOptions:()Lorg/hibernate/boot/spi/SessionFactoryOptions;
       9: areturn
}
