Compiled from "ProcessedServices.java"
public class de.theitshop.model.container.ProcessedServices {
  private java.util.Map<java.lang.String, de.theitshop.model.container.RunningContainer> processedServices;

  public java.util.Map<java.lang.String, de.theitshop.model.container.RunningContainer> getProcessedServices();
    Code:
       0: aload_0
       1: getfield      #1                  // Field processedServices:Ljava/util/Map;
       4: areturn

  public void setProcessedServices(java.util.Map<java.lang.String, de.theitshop.model.container.RunningContainer>);
    Code:
       0: aload_0
       1: aload_1
       2: putfield      #1                  // Field processedServices:Ljava/util/Map;
       5: return

  public boolean equals(java.lang.Object);
    Code:
       0: aload_1
       1: aload_0
       2: if_acmpne     7
       5: iconst_1
       6: ireturn
       7: aload_1
       8: instanceof    #2                  // class de/theitshop/model/container/ProcessedServices
      11: ifne          16
      14: iconst_0
      15: ireturn
      16: aload_1
      17: checkcast     #2                  // class de/theitshop/model/container/ProcessedServices
      20: astore_2
      21: aload_2
      22: aload_0
      23: invokevirtual #3                  // Method canEqual:(Ljava/lang/Object;)Z
      26: ifne          31
      29: iconst_0
      30: ireturn
      31: aload_0
      32: invokevirtual #4                  // Method getProcessedServices:()Ljava/util/Map;
      35: astore_3
      36: aload_2
      37: invokevirtual #4                  // Method getProcessedServices:()Ljava/util/Map;
      40: astore        4
      42: aload_3
      43: ifnonnull     54
      46: aload         4
      48: ifnull        65
      51: goto          63
      54: aload_3
      55: aload         4
      57: invokevirtual #5                  // Method java/lang/Object.equals:(Ljava/lang/Object;)Z
      60: ifne          65
      63: iconst_0
      64: ireturn
      65: iconst_1
      66: ireturn

  protected boolean canEqual(java.lang.Object);
    Code:
       0: aload_1
       1: instanceof    #2                  // class de/theitshop/model/container/ProcessedServices
       4: ireturn

  public int hashCode();
    Code:
       0: bipush        59
       2: istore_1
       3: iconst_1
       4: istore_2
       5: aload_0
       6: invokevirtual #4                  // Method getProcessedServices:()Ljava/util/Map;
       9: astore_3
      10: iload_2
      11: bipush        59
      13: imul
      14: aload_3
      15: ifnonnull     23
      18: bipush        43
      20: goto          27
      23: aload_3
      24: invokevirtual #6                  // Method java/lang/Object.hashCode:()I
      27: iadd
      28: istore_2
      29: iload_2
      30: ireturn

  public java.lang.String toString();
    Code:
       0: aload_0
       1: invokevirtual #4                  // Method getProcessedServices:()Ljava/util/Map;
       4: invokedynamic #7,  0              // InvokeDynamic #0:makeConcatWithConstants:(Ljava/util/Map;)Ljava/lang/String;
       9: areturn

  public de.theitshop.model.container.ProcessedServices(java.util.Map<java.lang.String, de.theitshop.model.container.RunningContainer>);
    Code:
       0: aload_0
       1: invokespecial #8                  // Method java/lang/Object."<init>":()V
       4: aload_0
       5: aload_1
       6: putfield      #1                  // Field processedServices:Ljava/util/Map;
       9: return
}
