Compiled from "Plugin.java"
public abstract class net.bytebuddy.build.Plugin$Engine$Listener$Adapter implements net.bytebuddy.build.Plugin$Engine$Listener {
  public net.bytebuddy.build.Plugin$Engine$Listener$Adapter();
    Code:
       0: aload_0
       1: invokespecial #18                 // Method java/lang/Object."<init>":()V
       4: return

  public void onDiscovery(java.lang.String);
    Code:
       0: return

  public void onTransformation(net.bytebuddy.description.type.TypeDescription, net.bytebuddy.build.Plugin);
    Code:
       0: return

  public void onTransformation(net.bytebuddy.description.type.TypeDescription, java.util.List<net.bytebuddy.build.Plugin>);
    Code:
       0: return

  public void onIgnored(net.bytebuddy.description.type.TypeDescription, net.bytebuddy.build.Plugin);
    Code:
       0: return

  public void onIgnored(net.bytebuddy.description.type.TypeDescription, java.util.List<net.bytebuddy.build.Plugin>);
    Code:
       0: return

  public void onError(net.bytebuddy.description.type.TypeDescription, net.bytebuddy.build.Plugin, java.lang.Throwable);
    Code:
       0: return

  public void onError(net.bytebuddy.description.type.TypeDescription, java.util.List<java.lang.Throwable>);
    Code:
       0: return

  public void onError(java.util.Map<net.bytebuddy.description.type.TypeDescription, java.util.List<java.lang.Throwable>>);
    Code:
       0: return

  public void onError(net.bytebuddy.build.Plugin, java.lang.Throwable);
    Code:
       0: return

  public void onLiveInitializer(net.bytebuddy.description.type.TypeDescription, net.bytebuddy.description.type.TypeDescription);
    Code:
       0: return

  public void onComplete(net.bytebuddy.description.type.TypeDescription);
    Code:
       0: return

  public void onUnresolved(java.lang.String);
    Code:
       0: return

  public void onManifest(java.util.jar.Manifest);
    Code:
       0: return

  public void onResource(java.lang.String);
    Code:
       0: return
}
