Compiled from "SSLConfig.java"
public class org.wso2.transport.http.netty.contractimpl.common.ssl.SSLConfig {
  private static final org.slf4j.Logger LOG;

  private static final java.lang.String SEPARATOR;

  private java.io.File keyStore;

  private java.lang.String keyStorePass;

  private java.lang.String certPass;

  private java.io.File trustStore;

  private java.lang.String trustStorePass;

  private java.lang.String sslProtocol;

  private java.lang.String tlsStoreType;

  private java.lang.String[] cipherSuites;

  private java.lang.String[] enableProtocols;

  private boolean enableSessionCreation;

  private boolean needClientAuth;

  private boolean wantClientAuth;

  private java.lang.String[] serverNames;

  private java.lang.String[] sniMatchers;

  private boolean validateCertEnabled;

  private int cacheSize;

  private int cacheValidityPeriod;

  private boolean ocspStaplingEnabled;

  private boolean hostNameVerificationEnabled;

  private java.io.File serverKeyFile;

  private java.io.File serverCertificates;

  private java.io.File clientKeyFile;

  private java.io.File clientCertificates;

  private java.io.File serverTrustCertificates;

  private java.io.File clientTrustCertificates;

  private java.lang.String serverKeyPassword;

  private java.lang.String clientKeyPassword;

  public org.wso2.transport.http.netty.contractimpl.common.ssl.SSLConfig();
    Code:
       0: aload_0
       1: invokespecial #1                  // Method java/lang/Object."<init>":()V
       4: aload_0
       5: iconst_1
       6: putfield      #2                  // Field enableSessionCreation:Z
       9: aload_0
      10: bipush        50
      12: putfield      #3                  // Field cacheSize:I
      15: aload_0
      16: bipush        15
      18: putfield      #4                  // Field cacheValidityPeriod:I
      21: aload_0
      22: iconst_0
      23: putfield      #5                  // Field ocspStaplingEnabled:Z
      26: aload_0
      27: iconst_1
      28: putfield      #6                  // Field hostNameVerificationEnabled:Z
      31: return

  public java.lang.String getCertPass();
    Code:
       0: aload_0
       1: getfield      #7                  // Field certPass:Ljava/lang/String;
       4: areturn

  public org.wso2.transport.http.netty.contractimpl.common.ssl.SSLConfig setCertPass(java.lang.String);
    Code:
       0: aload_0
       1: aload_1
       2: putfield      #7                  // Field certPass:Ljava/lang/String;
       5: aload_0
       6: areturn

  public java.io.File getTrustStore();
    Code:
       0: aload_0
       1: getfield      #8                  // Field trustStore:Ljava/io/File;
       4: areturn

  public org.wso2.transport.http.netty.contractimpl.common.ssl.SSLConfig setTrustStore(java.io.File);
    Code:
       0: getstatic     #9                  // Field LOG:Lorg/slf4j/Logger;
       3: invokeinterface #10,  1           // InterfaceMethod org/slf4j/Logger.isDebugEnabled:()Z
       8: ifeq          22
      11: getstatic     #9                  // Field LOG:Lorg/slf4j/Logger;
      14: ldc           #11                 // String Using trust store {}
      16: aload_1
      17: invokeinterface #12,  3           // InterfaceMethod org/slf4j/Logger.debug:(Ljava/lang/String;Ljava/lang/Object;)V
      22: aload_0
      23: aload_1
      24: putfield      #8                  // Field trustStore:Ljava/io/File;
      27: aload_0
      28: areturn

  public java.lang.String getTrustStorePass();
    Code:
       0: aload_0
       1: getfield      #13                 // Field trustStorePass:Ljava/lang/String;
       4: areturn

  public org.wso2.transport.http.netty.contractimpl.common.ssl.SSLConfig setTrustStorePass(java.lang.String);
    Code:
       0: aload_0
       1: aload_1
       2: putfield      #13                 // Field trustStorePass:Ljava/lang/String;
       5: aload_0
       6: areturn

  public java.io.File getKeyStore();
    Code:
       0: aload_0
       1: getfield      #14                 // Field keyStore:Ljava/io/File;
       4: areturn

  public java.lang.String getKeyStorePass();
    Code:
       0: aload_0
       1: getfield      #15                 // Field keyStorePass:Ljava/lang/String;
       4: areturn

  public java.lang.String[] getSniMatchers();
    Code:
       0: aload_0
       1: getfield      #16                 // Field sniMatchers:[Ljava/lang/String;
       4: ifnonnull     11
       7: aconst_null
       8: goto          21
      11: aload_0
      12: getfield      #16                 // Field sniMatchers:[Ljava/lang/String;
      15: invokevirtual #17                 // Method "[Ljava/lang/String;".clone:()Ljava/lang/Object;
      18: checkcast     #18                 // class "[Ljava/lang/String;"
      21: areturn

  public void setSniMatchers(java.lang.String);
    Code:
       0: getstatic     #9                  // Field LOG:Lorg/slf4j/Logger;
       3: invokeinterface #10,  1           // InterfaceMethod org/slf4j/Logger.isDebugEnabled:()Z
       8: ifeq          22
      11: getstatic     #9                  // Field LOG:Lorg/slf4j/Logger;
      14: ldc           #19                 // String Using sniMatchers {}
      16: aload_1
      17: invokeinterface #12,  3           // InterfaceMethod org/slf4j/Logger.debug:(Ljava/lang/String;Ljava/lang/Object;)V
      22: aload_0
      23: aload_1
      24: ldc           #21                 // String ,
      26: invokevirtual #22                 // Method java/lang/String.split:(Ljava/lang/String;)[Ljava/lang/String;
      29: putfield      #16                 // Field sniMatchers:[Ljava/lang/String;
      32: return

  public java.lang.String[] getServerNames();
    Code:
       0: aload_0
       1: getfield      #23                 // Field serverNames:[Ljava/lang/String;
       4: ifnonnull     11
       7: aconst_null
       8: goto          21
      11: aload_0
      12: getfield      #23                 // Field serverNames:[Ljava/lang/String;
      15: invokevirtual #24                 // Method "[Ljava/lang/String;".clone:()Ljava/lang/Object;
      18: checkcast     #18                 // class "[Ljava/lang/String;"
      21: areturn

  public void setServerNames(java.lang.String);
    Code:
       0: getstatic     #9                  // Field LOG:Lorg/slf4j/Logger;
       3: invokeinterface #10,  1           // InterfaceMethod org/slf4j/Logger.isDebugEnabled:()Z
       8: ifeq          22
      11: getstatic     #9                  // Field LOG:Lorg/slf4j/Logger;
      14: ldc           #25                 // String Using serverNames {}
      16: aload_1
      17: invokeinterface #12,  3           // InterfaceMethod org/slf4j/Logger.debug:(Ljava/lang/String;Ljava/lang/Object;)V
      22: aload_0
      23: aload_1
      24: ldc           #26                 // String \\s+
      26: ldc           #27                 // String
      28: invokevirtual #28                 // Method java/lang/String.replaceAll:(Ljava/lang/String;Ljava/lang/String;)Ljava/lang/String;
      31: ldc           #21                 // String ,
      33: invokevirtual #22                 // Method java/lang/String.split:(Ljava/lang/String;)[Ljava/lang/String;
      36: putfield      #23                 // Field serverNames:[Ljava/lang/String;
      39: return

  public boolean isWantClientAuth();
    Code:
       0: aload_0
       1: getfield      #29                 // Field wantClientAuth:Z
       4: ireturn

  public void setWantClientAuth(boolean);
    Code:
       0: getstatic     #9                  // Field LOG:Lorg/slf4j/Logger;
       3: invokeinterface #10,  1           // InterfaceMethod org/slf4j/Logger.isDebugEnabled:()Z
       8: ifeq          25
      11: getstatic     #9                  // Field LOG:Lorg/slf4j/Logger;
      14: ldc           #30                 // String Set WantClientAuth {}
      16: iload_1
      17: invokestatic  #31                 // Method java/lang/Boolean.valueOf:(Z)Ljava/lang/Boolean;
      20: invokeinterface #12,  3           // InterfaceMethod org/slf4j/Logger.debug:(Ljava/lang/String;Ljava/lang/Object;)V
      25: aload_0
      26: iload_1
      27: putfield      #29                 // Field wantClientAuth:Z
      30: return

  public boolean isNeedClientAuth();
    Code:
       0: aload_0
       1: getfield      #32                 // Field needClientAuth:Z
       4: ireturn

  public void setNeedClientAuth(boolean);
    Code:
       0: getstatic     #9                  // Field LOG:Lorg/slf4j/Logger;
       3: invokeinterface #10,  1           // InterfaceMethod org/slf4j/Logger.isDebugEnabled:()Z
       8: ifeq          25
      11: getstatic     #9                  // Field LOG:Lorg/slf4j/Logger;
      14: ldc           #33                 // String Set NeedClientAuth {}
      16: iload_1
      17: invokestatic  #31                 // Method java/lang/Boolean.valueOf:(Z)Ljava/lang/Boolean;
      20: invokeinterface #12,  3           // InterfaceMethod org/slf4j/Logger.debug:(Ljava/lang/String;Ljava/lang/Object;)V
      25: aload_0
      26: iload_1
      27: putfield      #32                 // Field needClientAuth:Z
      30: return

  public void setSSLProtocol(java.lang.String);
    Code:
       0: getstatic     #9                  // Field LOG:Lorg/slf4j/Logger;
       3: invokeinterface #10,  1           // InterfaceMethod org/slf4j/Logger.isDebugEnabled:()Z
       8: ifeq          22
      11: getstatic     #9                  // Field LOG:Lorg/slf4j/Logger;
      14: ldc           #34                 // String Set SSLProtocol {}
      16: aload_1
      17: invokeinterface #12,  3           // InterfaceMethod org/slf4j/Logger.debug:(Ljava/lang/String;Ljava/lang/Object;)V
      22: aload_0
      23: aload_1
      24: putfield      #35                 // Field sslProtocol:Ljava/lang/String;
      27: return

  public java.lang.String getSSLProtocol();
    Code:
       0: aload_0
       1: getfield      #35                 // Field sslProtocol:Ljava/lang/String;
       4: areturn

  public java.lang.String getTLSStoreType();
    Code:
       0: aload_0
       1: getfield      #36                 // Field tlsStoreType:Ljava/lang/String;
       4: areturn

  public void setTLSStoreType(java.lang.String);
    Code:
       0: aload_0
       1: aload_1
       2: putfield      #36                 // Field tlsStoreType:Ljava/lang/String;
       5: return

  public boolean isEnableSessionCreation();
    Code:
       0: aload_0
       1: getfield      #2                  // Field enableSessionCreation:Z
       4: ireturn

  public void setEnableSessionCreation(boolean);
    Code:
       0: getstatic     #9                  // Field LOG:Lorg/slf4j/Logger;
       3: invokeinterface #10,  1           // InterfaceMethod org/slf4j/Logger.isDebugEnabled:()Z
       8: ifeq          25
      11: getstatic     #9                  // Field LOG:Lorg/slf4j/Logger;
      14: ldc           #37                 // String Enable Session Creation {}
      16: iload_1
      17: invokestatic  #31                 // Method java/lang/Boolean.valueOf:(Z)Ljava/lang/Boolean;
      20: invokeinterface #12,  3           // InterfaceMethod org/slf4j/Logger.debug:(Ljava/lang/String;Ljava/lang/Object;)V
      25: aload_0
      26: iload_1
      27: putfield      #2                  // Field enableSessionCreation:Z
      30: return

  public java.lang.String[] getEnableProtocols();
    Code:
       0: aload_0
       1: getfield      #38                 // Field enableProtocols:[Ljava/lang/String;
       4: ifnonnull     11
       7: aconst_null
       8: goto          21
      11: aload_0
      12: getfield      #38                 // Field enableProtocols:[Ljava/lang/String;
      15: invokevirtual #39                 // Method "[Ljava/lang/String;".clone:()Ljava/lang/Object;
      18: checkcast     #18                 // class "[Ljava/lang/String;"
      21: areturn

  public void setEnableProtocols(java.lang.String);
    Code:
       0: getstatic     #9                  // Field LOG:Lorg/slf4j/Logger;
       3: invokeinterface #10,  1           // InterfaceMethod org/slf4j/Logger.isDebugEnabled:()Z
       8: ifeq          22
      11: getstatic     #9                  // Field LOG:Lorg/slf4j/Logger;
      14: ldc           #40                 // String Set enable protocols {}
      16: aload_1
      17: invokeinterface #12,  3           // InterfaceMethod org/slf4j/Logger.debug:(Ljava/lang/String;Ljava/lang/Object;)V
      22: aload_0
      23: aload_1
      24: ldc           #26                 // String \\s+
      26: ldc           #27                 // String
      28: invokevirtual #28                 // Method java/lang/String.replaceAll:(Ljava/lang/String;Ljava/lang/String;)Ljava/lang/String;
      31: ldc           #21                 // String ,
      33: invokevirtual #22                 // Method java/lang/String.split:(Ljava/lang/String;)[Ljava/lang/String;
      36: putfield      #38                 // Field enableProtocols:[Ljava/lang/String;
      39: return

  public java.lang.String[] getCipherSuites();
    Code:
       0: aload_0
       1: getfield      #41                 // Field cipherSuites:[Ljava/lang/String;
       4: ifnonnull     11
       7: aconst_null
       8: goto          21
      11: aload_0
      12: getfield      #41                 // Field cipherSuites:[Ljava/lang/String;
      15: invokevirtual #42                 // Method "[Ljava/lang/String;".clone:()Ljava/lang/Object;
      18: checkcast     #18                 // class "[Ljava/lang/String;"
      21: areturn

  public void setCipherSuites(java.lang.String);
    Code:
       0: getstatic     #9                  // Field LOG:Lorg/slf4j/Logger;
       3: invokeinterface #10,  1           // InterfaceMethod org/slf4j/Logger.isDebugEnabled:()Z
       8: ifeq          22
      11: getstatic     #9                  // Field LOG:Lorg/slf4j/Logger;
      14: ldc           #43                 // String Set supported cipherSuites {}
      16: aload_1
      17: invokeinterface #12,  3           // InterfaceMethod org/slf4j/Logger.debug:(Ljava/lang/String;Ljava/lang/Object;)V
      22: aload_0
      23: aload_1
      24: ldc           #26                 // String \\s+
      26: ldc           #27                 // String
      28: invokevirtual #28                 // Method java/lang/String.replaceAll:(Ljava/lang/String;Ljava/lang/String;)Ljava/lang/String;
      31: ldc           #21                 // String ,
      33: invokevirtual #22                 // Method java/lang/String.split:(Ljava/lang/String;)[Ljava/lang/String;
      36: putfield      #41                 // Field cipherSuites:[Ljava/lang/String;
      39: return

  public void setKeyStore(java.io.File);
    Code:
       0: aload_0
       1: aload_1
       2: putfield      #14                 // Field keyStore:Ljava/io/File;
       5: return

  public void setKeyStorePass(java.lang.String);
    Code:
       0: aload_0
       1: aload_1
       2: putfield      #15                 // Field keyStorePass:Ljava/lang/String;
       5: return

  public boolean isValidateCertEnabled();
    Code:
       0: aload_0
       1: getfield      #44                 // Field validateCertEnabled:Z
       4: ireturn

  public void setValidateCertEnabled(boolean);
    Code:
       0: aload_0
       1: iload_1
       2: putfield      #44                 // Field validateCertEnabled:Z
       5: return

  public int getCacheSize();
    Code:
       0: aload_0
       1: getfield      #3                  // Field cacheSize:I
       4: ireturn

  public void setCacheSize(int);
    Code:
       0: aload_0
       1: iload_1
       2: putfield      #3                  // Field cacheSize:I
       5: return

  public int getCacheValidityPeriod();
    Code:
       0: aload_0
       1: getfield      #4                  // Field cacheValidityPeriod:I
       4: ireturn

  public void setCacheValidityPeriod(int);
    Code:
       0: aload_0
       1: iload_1
       2: putfield      #4                  // Field cacheValidityPeriod:I
       5: return

  public boolean isOcspStaplingEnabled();
    Code:
       0: aload_0
       1: getfield      #5                  // Field ocspStaplingEnabled:Z
       4: ireturn

  public void setOcspStaplingEnabled(boolean);
    Code:
       0: aload_0
       1: iload_1
       2: putfield      #5                  // Field ocspStaplingEnabled:Z
       5: return

  public boolean isHostNameVerificationEnabled();
    Code:
       0: aload_0
       1: getfield      #6                  // Field hostNameVerificationEnabled:Z
       4: ireturn

  public void setHostNameVerificationEnabled(boolean);
    Code:
       0: aload_0
       1: iload_1
       2: putfield      #6                  // Field hostNameVerificationEnabled:Z
       5: return

  public java.io.File getServerKeyFile();
    Code:
       0: aload_0
       1: getfield      #45                 // Field serverKeyFile:Ljava/io/File;
       4: areturn

  public java.io.File getServerCertificates();
    Code:
       0: aload_0
       1: getfield      #46                 // Field serverCertificates:Ljava/io/File;
       4: areturn

  public java.io.File getClientKeyFile();
    Code:
       0: aload_0
       1: getfield      #47                 // Field clientKeyFile:Ljava/io/File;
       4: areturn

  public java.io.File getClientCertificates();
    Code:
       0: aload_0
       1: getfield      #48                 // Field clientCertificates:Ljava/io/File;
       4: areturn

  public java.io.File getServerTrustCertificates();
    Code:
       0: aload_0
       1: getfield      #49                 // Field serverTrustCertificates:Ljava/io/File;
       4: areturn

  public java.io.File getClientTrustCertificates();
    Code:
       0: aload_0
       1: getfield      #50                 // Field clientTrustCertificates:Ljava/io/File;
       4: areturn

  public void setServerKeyFile(java.io.File);
    Code:
       0: aload_0
       1: aload_1
       2: putfield      #45                 // Field serverKeyFile:Ljava/io/File;
       5: return

  public void setServerCertificates(java.io.File);
    Code:
       0: aload_0
       1: aload_1
       2: putfield      #46                 // Field serverCertificates:Ljava/io/File;
       5: return

  public void setClientKeyFile(java.io.File);
    Code:
       0: aload_0
       1: aload_1
       2: putfield      #47                 // Field clientKeyFile:Ljava/io/File;
       5: return

  public void setClientCertificates(java.io.File);
    Code:
       0: aload_0
       1: aload_1
       2: putfield      #48                 // Field clientCertificates:Ljava/io/File;
       5: return

  public void setServerTrustCertificates(java.io.File);
    Code:
       0: aload_0
       1: aload_1
       2: putfield      #49                 // Field serverTrustCertificates:Ljava/io/File;
       5: return

  public void setClientTrustCertificates(java.io.File);
    Code:
       0: aload_0
       1: aload_1
       2: putfield      #50                 // Field clientTrustCertificates:Ljava/io/File;
       5: return

  public java.lang.String getServerKeyPassword();
    Code:
       0: aload_0
       1: getfield      #51                 // Field serverKeyPassword:Ljava/lang/String;
       4: areturn

  public void setServerKeyPassword(java.lang.String);
    Code:
       0: aload_0
       1: aload_1
       2: putfield      #51                 // Field serverKeyPassword:Ljava/lang/String;
       5: return

  public java.lang.String getClientKeyPassword();
    Code:
       0: aload_0
       1: getfield      #52                 // Field clientKeyPassword:Ljava/lang/String;
       4: areturn

  public void setClientKeyPassword(java.lang.String);
    Code:
       0: aload_0
       1: aload_1
       2: putfield      #52                 // Field clientKeyPassword:Ljava/lang/String;
       5: return

  static {};
    Code:
       0: ldc           #20                 // class org/wso2/transport/http/netty/contractimpl/common/ssl/SSLConfig
       2: invokestatic  #53                 // Method org/slf4j/LoggerFactory.getLogger:(Ljava/lang/Class;)Lorg/slf4j/Logger;
       5: putstatic     #9                  // Field LOG:Lorg/slf4j/Logger;
       8: return
}
