Compiled from "SimpleSessionStatus.java"
public class org.springframework.web.bind.support.SimpleSessionStatus implements org.springframework.web.bind.support.SessionStatus {
  private boolean complete;

  public org.springframework.web.bind.support.SimpleSessionStatus();
    Code:
       0: aload_0
       1: invokespecial #1                  // Method java/lang/Object."<init>":()V
       4: aload_0
       5: iconst_0
       6: putfield      #2                  // Field complete:Z
       9: return

  public void setComplete();
    Code:
       0: aload_0
       1: iconst_1
       2: putfield      #2                  // Field complete:Z
       5: return

  public boolean isComplete();
    Code:
       0: aload_0
       1: getfield      #2                  // Field complete:Z
       4: ireturn
}
