Compiled from "TreeExpressionEvaluator.java"
public class nl.basjes.parse.useragent.analyze.treewalker.TreeExpressionEvaluator implements java.io.Serializable {
  private static final org.apache.logging.log4j.Logger LOG;

  private final boolean verbose;

  private final java.lang.String requiredPatternText;

  private final nl.basjes.parse.useragent.analyze.treewalker.steps.WalkList walkList;

  private final java.lang.String fixedValue;

  private nl.basjes.parse.useragent.analyze.treewalker.TreeExpressionEvaluator();
    Code:
       0: aload_0
       1: invokespecial #27                 // Method java/lang/Object."<init>":()V
       4: aload_0
       5: aconst_null
       6: putfield      #29                 // Field requiredPatternText:Ljava/lang/String;
       9: aload_0
      10: iconst_0
      11: putfield      #31                 // Field verbose:Z
      14: aload_0
      15: aconst_null
      16: putfield      #33                 // Field fixedValue:Ljava/lang/String;
      19: aload_0
      20: aconst_null
      21: putfield      #35                 // Field walkList:Lnl/basjes/parse/useragent/analyze/treewalker/steps/WalkList;
      24: return

  public nl.basjes.parse.useragent.analyze.treewalker.TreeExpressionEvaluator(nl.basjes.shaded.org.antlr.v4.runtime.ParserRuleContext, nl.basjes.parse.useragent.analyze.Matcher, boolean);
    Code:
       0: aload_0
       1: invokespecial #27                 // Method java/lang/Object."<init>":()V
       4: aload_0
       5: aload_1
       6: invokevirtual #44                 // Method nl/basjes/shaded/org/antlr/v4/runtime/ParserRuleContext.getText:()Ljava/lang/String;
       9: putfield      #29                 // Field requiredPatternText:Ljava/lang/String;
      12: aload_0
      13: iload_3
      14: putfield      #31                 // Field verbose:Z
      17: aload_0
      18: aload_0
      19: aload_1
      20: invokespecial #48                 // Method calculateFixedValue:(Lnl/basjes/shaded/org/antlr/v4/runtime/ParserRuleContext;)Ljava/lang/String;
      23: putfield      #33                 // Field fixedValue:Ljava/lang/String;
      26: aload_0
      27: new           #13                 // class nl/basjes/parse/useragent/analyze/treewalker/steps/WalkList
      30: dup
      31: aload_1
      32: aload_2
      33: invokevirtual #54                 // Method nl/basjes/parse/useragent/analyze/Matcher.getLookups:()Ljava/util/Map;
      36: aload_2
      37: invokevirtual #57                 // Method nl/basjes/parse/useragent/analyze/Matcher.getLookupSets:()Ljava/util/Map;
      40: iload_3
      41: invokespecial #60                 // Method nl/basjes/parse/useragent/analyze/treewalker/steps/WalkList."<init>":(Lnl/basjes/shaded/org/antlr/v4/runtime/ParserRuleContext;Ljava/util/Map;Ljava/util/Map;Z)V
      44: putfield      #35                 // Field walkList:Lnl/basjes/parse/useragent/analyze/treewalker/steps/WalkList;
      47: return

  public boolean isEmpty();
    Code:
       0: aload_0
       1: getfield      #35                 // Field walkList:Lnl/basjes/parse/useragent/analyze/treewalker/steps/WalkList;
       4: invokevirtual #68                 // Method nl/basjes/parse/useragent/analyze/treewalker/steps/WalkList.isEmpty:()Z
       7: ireturn

  public void destroy();
    Code:
       0: aload_0
       1: getfield      #35                 // Field walkList:Lnl/basjes/parse/useragent/analyze/treewalker/steps/WalkList;
       4: invokevirtual #71                 // Method nl/basjes/parse/useragent/analyze/treewalker/steps/WalkList.destroy:()V
       7: return

  public java.lang.String getFixedValue();
    Code:
       0: aload_0
       1: getfield      #33                 // Field fixedValue:Ljava/lang/String;
       4: areturn

  private java.lang.String calculateFixedValue(nl.basjes.shaded.org.antlr.v4.runtime.ParserRuleContext);
    Code:
       0: new           #9                  // class nl/basjes/parse/useragent/analyze/treewalker/TreeExpressionEvaluator$1
       3: dup
       4: aload_0
       5: invokespecial #75                 // Method nl/basjes/parse/useragent/analyze/treewalker/TreeExpressionEvaluator$1."<init>":(Lnl/basjes/parse/useragent/analyze/treewalker/TreeExpressionEvaluator;)V
       8: aload_1
       9: invokevirtual #79                 // Method nl/basjes/parse/useragent/analyze/treewalker/TreeExpressionEvaluator$1.visit:(Lnl/basjes/shaded/org/antlr/v4/runtime/tree/ParseTree;)Ljava/lang/Object;
      12: checkcast     #81                 // class java/lang/String
      15: areturn

  public nl.basjes.parse.useragent.analyze.treewalker.steps.WalkList$WalkResult evaluate(nl.basjes.shaded.org.antlr.v4.runtime.tree.ParseTree, java.lang.String, java.lang.String);
    Code:
       0: aload_0
       1: getfield      #31                 // Field verbose:Z
       4: ifeq          47
       7: getstatic     #85                 // Field LOG:Lorg/apache/logging/log4j/Logger;
      10: ldc           #87                 // String Evaluate: {} => {}
      12: aload_2
      13: aload_3
      14: invokeinterface #93,  4           // InterfaceMethod org/apache/logging/log4j/Logger.info:(Ljava/lang/String;Ljava/lang/Object;Ljava/lang/Object;)V
      19: getstatic     #85                 // Field LOG:Lorg/apache/logging/log4j/Logger;
      22: ldc           #95                 // String Pattern : {}
      24: aload_0
      25: getfield      #29                 // Field requiredPatternText:Ljava/lang/String;
      28: invokeinterface #98,  3           // InterfaceMethod org/apache/logging/log4j/Logger.info:(Ljava/lang/String;Ljava/lang/Object;)V
      33: getstatic     #85                 // Field LOG:Lorg/apache/logging/log4j/Logger;
      36: ldc           #100                // String WalkList: {}
      38: aload_0
      39: getfield      #35                 // Field walkList:Lnl/basjes/parse/useragent/analyze/treewalker/steps/WalkList;
      42: invokeinterface #98,  3           // InterfaceMethod org/apache/logging/log4j/Logger.info:(Ljava/lang/String;Ljava/lang/Object;)V
      47: aload_0
      48: getfield      #35                 // Field walkList:Lnl/basjes/parse/useragent/analyze/treewalker/steps/WalkList;
      51: aload_1
      52: aload_3
      53: invokevirtual #104                // Method nl/basjes/parse/useragent/analyze/treewalker/steps/WalkList.walk:(Lnl/basjes/shaded/org/antlr/v4/runtime/tree/ParseTree;Ljava/lang/String;)Lnl/basjes/parse/useragent/analyze/treewalker/steps/WalkList$WalkResult;
      56: astore        4
      58: aload_0
      59: getfield      #31                 // Field verbose:Z
      62: ifeq          90
      65: getstatic     #85                 // Field LOG:Lorg/apache/logging/log4j/Logger;
      68: ldc           #106                // String Evaluate: Result = {}
      70: aload         4
      72: ifnonnull     80
      75: ldc           #108                // String null
      77: goto          85
      80: aload         4
      82: invokevirtual #113                // Method nl/basjes/parse/useragent/analyze/treewalker/steps/WalkList$WalkResult.getValue:()Ljava/lang/String;
      85: invokeinterface #98,  3           // InterfaceMethod org/apache/logging/log4j/Logger.info:(Ljava/lang/String;Ljava/lang/Object;)V
      90: aload         4
      92: areturn

  public boolean mustHaveMatches();
    Code:
       0: aload_0
       1: getfield      #35                 // Field walkList:Lnl/basjes/parse/useragent/analyze/treewalker/steps/WalkList;
       4: invokevirtual #122                // Method nl/basjes/parse/useragent/analyze/treewalker/steps/WalkList.mustHaveMatches:()Z
       7: ireturn

  public nl.basjes.parse.useragent.analyze.treewalker.steps.WalkList getWalkListForUnitTesting();
    Code:
       0: aload_0
       1: getfield      #35                 // Field walkList:Lnl/basjes/parse/useragent/analyze/treewalker/steps/WalkList;
       4: areturn

  public long pruneTrailingStepsThatCannotFail();
    Code:
       0: aload_0
       1: getfield      #35                 // Field walkList:Lnl/basjes/parse/useragent/analyze/treewalker/steps/WalkList;
       4: invokevirtual #128                // Method nl/basjes/parse/useragent/analyze/treewalker/steps/WalkList.pruneTrailingStepsThatCannotFail:()J
       7: lreturn

  static {};
    Code:
       0: ldc           #2                  // class nl/basjes/parse/useragent/analyze/treewalker/TreeExpressionEvaluator
       2: invokestatic  #135                // Method org/apache/logging/log4j/LogManager.getLogger:(Ljava/lang/Class;)Lorg/apache/logging/log4j/Logger;
       5: putstatic     #85                 // Field LOG:Lorg/apache/logging/log4j/Logger;
       8: return
}
