Compiled from "EmbeddedContainer.java"
public class org.jboss.resteasy.test.EmbeddedContainer {
  private static java.lang.Class<?> bootstrap;

  public org.jboss.resteasy.test.EmbeddedContainer();
    Code:
       0: aload_0
       1: invokespecial #1                  // Method java/lang/Object."<init>":()V
       4: return

  public static java.lang.Class getBootstrap();
    Code:
       0: getstatic     #2                  // Field bootstrap:Ljava/lang/Class;
       3: areturn

  public static boolean isServlet();
    Code:
       0: iconst_1
       1: ireturn

  public static void setBootstrap(java.lang.Class);
    Code:
       0: aload_0
       1: putstatic     #2                  // Field bootstrap:Ljava/lang/Class;
       4: return

  public static org.jboss.resteasy.spi.ResteasyDeployment start() throws java.lang.Exception;
    Code:
       0: ldc           #3                  // String /
       2: aconst_null
       3: checkcast     #4                  // class java/util/Hashtable
       6: invokestatic  #5                  // Method start:(Ljava/lang/String;Ljava/util/Hashtable;)Lorg/jboss/resteasy/spi/ResteasyDeployment;
       9: areturn

  public static org.jboss.resteasy.spi.ResteasyDeployment start(java.lang.String) throws java.lang.Exception;
    Code:
       0: aload_0
       1: aconst_null
       2: aconst_null
       3: invokestatic  #6                  // Method start:(Ljava/lang/String;Ljava/util/Hashtable;Ljava/util/Hashtable;)Lorg/jboss/resteasy/spi/ResteasyDeployment;
       6: areturn

  public static org.jboss.resteasy.spi.ResteasyDeployment start(java.util.Hashtable<java.lang.String, java.lang.String>) throws java.lang.Exception;
    Code:
       0: ldc           #3                  // String /
       2: aload_0
       3: invokestatic  #5                  // Method start:(Ljava/lang/String;Ljava/util/Hashtable;)Lorg/jboss/resteasy/spi/ResteasyDeployment;
       6: areturn

  public static org.jboss.resteasy.spi.ResteasyDeployment start(java.util.Hashtable<java.lang.String, java.lang.String>, java.util.Hashtable<java.lang.String, java.lang.String>) throws java.lang.Exception;
    Code:
       0: ldc           #3                  // String /
       2: aload_0
       3: aload_1
       4: invokestatic  #6                  // Method start:(Ljava/lang/String;Ljava/util/Hashtable;Ljava/util/Hashtable;)Lorg/jboss/resteasy/spi/ResteasyDeployment;
       7: areturn

  public static org.jboss.resteasy.spi.ResteasyDeployment start(java.lang.String, java.util.Hashtable<java.lang.String, java.lang.String>) throws java.lang.Exception;
    Code:
       0: getstatic     #2                  // Field bootstrap:Ljava/lang/Class;
       3: ldc           #7                  // String start
       5: iconst_2
       6: anewarray     #8                  // class java/lang/Class
       9: dup
      10: iconst_0
      11: ldc           #9                  // class java/lang/String
      13: aastore
      14: dup
      15: iconst_1
      16: ldc           #4                  // class java/util/Hashtable
      18: aastore
      19: invokevirtual #10                 // Method java/lang/Class.getMethod:(Ljava/lang/String;[Ljava/lang/Class;)Ljava/lang/reflect/Method;
      22: astore_2
      23: aload_2
      24: aconst_null
      25: iconst_2
      26: anewarray     #11                 // class java/lang/Object
      29: dup
      30: iconst_0
      31: aload_0
      32: aastore
      33: dup
      34: iconst_1
      35: aload_1
      36: aastore
      37: invokevirtual #12                 // Method java/lang/reflect/Method.invoke:(Ljava/lang/Object;[Ljava/lang/Object;)Ljava/lang/Object;
      40: checkcast     #13                 // class org/jboss/resteasy/spi/ResteasyDeployment
      43: areturn

  public static org.jboss.resteasy.spi.ResteasyDeployment start(java.lang.String, java.util.Hashtable<java.lang.String, java.lang.String>, java.util.Hashtable<java.lang.String, java.lang.String>) throws java.lang.Exception;
    Code:
       0: getstatic     #2                  // Field bootstrap:Ljava/lang/Class;
       3: ldc           #7                  // String start
       5: iconst_3
       6: anewarray     #8                  // class java/lang/Class
       9: dup
      10: iconst_0
      11: ldc           #9                  // class java/lang/String
      13: aastore
      14: dup
      15: iconst_1
      16: ldc           #4                  // class java/util/Hashtable
      18: aastore
      19: dup
      20: iconst_2
      21: ldc           #4                  // class java/util/Hashtable
      23: aastore
      24: invokevirtual #10                 // Method java/lang/Class.getMethod:(Ljava/lang/String;[Ljava/lang/Class;)Ljava/lang/reflect/Method;
      27: astore_3
      28: aload_3
      29: aconst_null
      30: iconst_3
      31: anewarray     #11                 // class java/lang/Object
      34: dup
      35: iconst_0
      36: aload_0
      37: aastore
      38: dup
      39: iconst_1
      40: aload_1
      41: aastore
      42: dup
      43: iconst_2
      44: aload_2
      45: aastore
      46: invokevirtual #12                 // Method java/lang/reflect/Method.invoke:(Ljava/lang/Object;[Ljava/lang/Object;)Ljava/lang/Object;
      49: checkcast     #13                 // class org/jboss/resteasy/spi/ResteasyDeployment
      52: areturn

  public static org.jboss.resteasy.spi.ResteasyDeployment start(java.lang.String, org.jboss.resteasy.plugins.server.embedded.SecurityDomain) throws java.lang.Exception;
    Code:
       0: getstatic     #2                  // Field bootstrap:Ljava/lang/Class;
       3: ldc           #7                  // String start
       5: iconst_2
       6: anewarray     #8                  // class java/lang/Class
       9: dup
      10: iconst_0
      11: ldc           #9                  // class java/lang/String
      13: aastore
      14: dup
      15: iconst_1
      16: ldc           #14                 // class org/jboss/resteasy/plugins/server/embedded/SecurityDomain
      18: aastore
      19: invokevirtual #10                 // Method java/lang/Class.getMethod:(Ljava/lang/String;[Ljava/lang/Class;)Ljava/lang/reflect/Method;
      22: astore_2
      23: aload_2
      24: aconst_null
      25: iconst_2
      26: anewarray     #11                 // class java/lang/Object
      29: dup
      30: iconst_0
      31: aload_0
      32: aastore
      33: dup
      34: iconst_1
      35: aload_1
      36: aastore
      37: invokevirtual #12                 // Method java/lang/reflect/Method.invoke:(Ljava/lang/Object;[Ljava/lang/Object;)Ljava/lang/Object;
      40: checkcast     #13                 // class org/jboss/resteasy/spi/ResteasyDeployment
      43: areturn

  public static void start(org.jboss.resteasy.spi.ResteasyDeployment) throws java.lang.Exception;
    Code:
       0: getstatic     #2                  // Field bootstrap:Ljava/lang/Class;
       3: ldc           #7                  // String start
       5: iconst_1
       6: anewarray     #8                  // class java/lang/Class
       9: dup
      10: iconst_0
      11: ldc           #13                 // class org/jboss/resteasy/spi/ResteasyDeployment
      13: aastore
      14: invokevirtual #10                 // Method java/lang/Class.getMethod:(Ljava/lang/String;[Ljava/lang/Class;)Ljava/lang/reflect/Method;
      17: astore_1
      18: aload_1
      19: aconst_null
      20: iconst_1
      21: anewarray     #11                 // class java/lang/Object
      24: dup
      25: iconst_0
      26: aload_0
      27: aastore
      28: invokevirtual #12                 // Method java/lang/reflect/Method.invoke:(Ljava/lang/Object;[Ljava/lang/Object;)Ljava/lang/Object;
      31: pop
      32: return

  public static void stop() throws java.lang.Exception;
    Code:
       0: getstatic     #2                  // Field bootstrap:Ljava/lang/Class;
       3: ldc           #15                 // String stop
       5: iconst_0
       6: anewarray     #8                  // class java/lang/Class
       9: invokevirtual #10                 // Method java/lang/Class.getMethod:(Ljava/lang/String;[Ljava/lang/Class;)Ljava/lang/reflect/Method;
      12: astore_0
      13: aload_0
      14: aconst_null
      15: iconst_0
      16: anewarray     #11                 // class java/lang/Object
      19: invokevirtual #12                 // Method java/lang/reflect/Method.invoke:(Ljava/lang/Object;[Ljava/lang/Object;)Ljava/lang/Object;
      22: pop
      23: return

  static {};
    Code:
       0: ldc           #16                 // class org/jboss/resteasy/test/TJWSServletContainer
       2: putstatic     #2                  // Field bootstrap:Ljava/lang/Class;
       5: ldc           #17                 // String org.resteasy.test.embedded.container
       7: invokestatic  #18                 // Method java/lang/System.getProperty:(Ljava/lang/String;)Ljava/lang/String;
      10: astore_0
      11: aload_0
      12: ifnull        41
      15: invokestatic  #19                 // Method java/lang/Thread.currentThread:()Ljava/lang/Thread;
      18: invokevirtual #20                 // Method java/lang/Thread.getContextClassLoader:()Ljava/lang/ClassLoader;
      21: aload_0
      22: invokevirtual #21                 // Method java/lang/ClassLoader.loadClass:(Ljava/lang/String;)Ljava/lang/Class;
      25: putstatic     #2                  // Field bootstrap:Ljava/lang/Class;
      28: goto          41
      31: astore_1
      32: new           #23                 // class java/lang/RuntimeException
      35: dup
      36: aload_1
      37: invokespecial #24                 // Method java/lang/RuntimeException."<init>":(Ljava/lang/Throwable;)V
      40: athrow
      41: return
    Exception table:
       from    to  target type
          15    28    31   Class java/lang/ClassNotFoundException
}
