Compiled from "ChainedRepositoryListener.java"
public class org.sonatype.aether.util.listener.ChainedRepositoryListener extends org.sonatype.aether.AbstractRepositoryListener {
  private final java.util.List<org.sonatype.aether.RepositoryListener> listeners;

  public static org.sonatype.aether.RepositoryListener newInstance(org.sonatype.aether.RepositoryListener, org.sonatype.aether.RepositoryListener);
    Code:
       0: aload_0
       1: ifnonnull     6
       4: aload_1
       5: areturn
       6: aload_1
       7: ifnonnull     12
      10: aload_0
      11: areturn
      12: new           #1                  // class org/sonatype/aether/util/listener/ChainedRepositoryListener
      15: dup
      16: iconst_2
      17: anewarray     #2                  // class org/sonatype/aether/RepositoryListener
      20: dup
      21: iconst_0
      22: aload_0
      23: aastore
      24: dup
      25: iconst_1
      26: aload_1
      27: aastore
      28: invokespecial #3                  // Method "<init>":([Lorg/sonatype/aether/RepositoryListener;)V
      31: areturn

  public org.sonatype.aether.util.listener.ChainedRepositoryListener(org.sonatype.aether.RepositoryListener...);
    Code:
       0: aload_0
       1: invokespecial #4                  // Method org/sonatype/aether/AbstractRepositoryListener."<init>":()V
       4: aload_0
       5: new           #5                  // class java/util/concurrent/CopyOnWriteArrayList
       8: dup
       9: invokespecial #6                  // Method java/util/concurrent/CopyOnWriteArrayList."<init>":()V
      12: putfield      #7                  // Field listeners:Ljava/util/List;
      15: aload_1
      16: ifnull        27
      19: aload_0
      20: aload_1
      21: invokestatic  #8                  // Method java/util/Arrays.asList:([Ljava/lang/Object;)Ljava/util/List;
      24: invokevirtual #9                  // Method add:(Ljava/util/Collection;)V
      27: return

  public org.sonatype.aether.util.listener.ChainedRepositoryListener(java.util.Collection<org.sonatype.aether.RepositoryListener>);
    Code:
       0: aload_0
       1: invokespecial #4                  // Method org/sonatype/aether/AbstractRepositoryListener."<init>":()V
       4: aload_0
       5: new           #5                  // class java/util/concurrent/CopyOnWriteArrayList
       8: dup
       9: invokespecial #6                  // Method java/util/concurrent/CopyOnWriteArrayList."<init>":()V
      12: putfield      #7                  // Field listeners:Ljava/util/List;
      15: aload_0
      16: aload_1
      17: invokevirtual #9                  // Method add:(Ljava/util/Collection;)V
      20: return

  public void add(java.util.Collection<org.sonatype.aether.RepositoryListener>);
    Code:
       0: aload_1
       1: ifnull        38
       4: aload_1
       5: invokeinterface #10,  1           // InterfaceMethod java/util/Collection.iterator:()Ljava/util/Iterator;
      10: astore_2
      11: aload_2
      12: invokeinterface #11,  1           // InterfaceMethod java/util/Iterator.hasNext:()Z
      17: ifeq          38
      20: aload_2
      21: invokeinterface #12,  1           // InterfaceMethod java/util/Iterator.next:()Ljava/lang/Object;
      26: checkcast     #2                  // class org/sonatype/aether/RepositoryListener
      29: astore_3
      30: aload_0
      31: aload_3
      32: invokevirtual #13                 // Method add:(Lorg/sonatype/aether/RepositoryListener;)V
      35: goto          11
      38: return

  public void add(org.sonatype.aether.RepositoryListener);
    Code:
       0: aload_1
       1: ifnull        15
       4: aload_0
       5: getfield      #7                  // Field listeners:Ljava/util/List;
       8: aload_1
       9: invokeinterface #14,  2           // InterfaceMethod java/util/List.add:(Ljava/lang/Object;)Z
      14: pop
      15: return

  public void remove(org.sonatype.aether.RepositoryListener);
    Code:
       0: aload_1
       1: ifnull        15
       4: aload_0
       5: getfield      #7                  // Field listeners:Ljava/util/List;
       8: aload_1
       9: invokeinterface #15,  2           // InterfaceMethod java/util/List.remove:(Ljava/lang/Object;)Z
      14: pop
      15: return

  protected void handleError(org.sonatype.aether.RepositoryEvent, org.sonatype.aether.RepositoryListener, java.lang.RuntimeException);
    Code:
       0: return

  public void artifactDeployed(org.sonatype.aether.RepositoryEvent);
    Code:
       0: aload_0
       1: getfield      #7                  // Field listeners:Ljava/util/List;
       4: invokeinterface #16,  1           // InterfaceMethod java/util/List.iterator:()Ljava/util/Iterator;
       9: astore_2
      10: aload_2
      11: invokeinterface #11,  1           // InterfaceMethod java/util/Iterator.hasNext:()Z
      16: ifeq          52
      19: aload_2
      20: invokeinterface #12,  1           // InterfaceMethod java/util/Iterator.next:()Ljava/lang/Object;
      25: checkcast     #2                  // class org/sonatype/aether/RepositoryListener
      28: astore_3
      29: aload_3
      30: aload_1
      31: invokeinterface #17,  2           // InterfaceMethod org/sonatype/aether/RepositoryListener.artifactDeployed:(Lorg/sonatype/aether/RepositoryEvent;)V
      36: goto          49
      39: astore        4
      41: aload_0
      42: aload_1
      43: aload_3
      44: aload         4
      46: invokevirtual #19                 // Method handleError:(Lorg/sonatype/aether/RepositoryEvent;Lorg/sonatype/aether/RepositoryListener;Ljava/lang/RuntimeException;)V
      49: goto          10
      52: return
    Exception table:
       from    to  target type
          29    36    39   Class java/lang/RuntimeException

  public void artifactDeploying(org.sonatype.aether.RepositoryEvent);
    Code:
       0: aload_0
       1: getfield      #7                  // Field listeners:Ljava/util/List;
       4: invokeinterface #16,  1           // InterfaceMethod java/util/List.iterator:()Ljava/util/Iterator;
       9: astore_2
      10: aload_2
      11: invokeinterface #11,  1           // InterfaceMethod java/util/Iterator.hasNext:()Z
      16: ifeq          52
      19: aload_2
      20: invokeinterface #12,  1           // InterfaceMethod java/util/Iterator.next:()Ljava/lang/Object;
      25: checkcast     #2                  // class org/sonatype/aether/RepositoryListener
      28: astore_3
      29: aload_3
      30: aload_1
      31: invokeinterface #20,  2           // InterfaceMethod org/sonatype/aether/RepositoryListener.artifactDeploying:(Lorg/sonatype/aether/RepositoryEvent;)V
      36: goto          49
      39: astore        4
      41: aload_0
      42: aload_1
      43: aload_3
      44: aload         4
      46: invokevirtual #19                 // Method handleError:(Lorg/sonatype/aether/RepositoryEvent;Lorg/sonatype/aether/RepositoryListener;Ljava/lang/RuntimeException;)V
      49: goto          10
      52: return
    Exception table:
       from    to  target type
          29    36    39   Class java/lang/RuntimeException

  public void artifactDescriptorInvalid(org.sonatype.aether.RepositoryEvent);
    Code:
       0: aload_0
       1: getfield      #7                  // Field listeners:Ljava/util/List;
       4: invokeinterface #16,  1           // InterfaceMethod java/util/List.iterator:()Ljava/util/Iterator;
       9: astore_2
      10: aload_2
      11: invokeinterface #11,  1           // InterfaceMethod java/util/Iterator.hasNext:()Z
      16: ifeq          52
      19: aload_2
      20: invokeinterface #12,  1           // InterfaceMethod java/util/Iterator.next:()Ljava/lang/Object;
      25: checkcast     #2                  // class org/sonatype/aether/RepositoryListener
      28: astore_3
      29: aload_3
      30: aload_1
      31: invokeinterface #21,  2           // InterfaceMethod org/sonatype/aether/RepositoryListener.artifactDescriptorInvalid:(Lorg/sonatype/aether/RepositoryEvent;)V
      36: goto          49
      39: astore        4
      41: aload_0
      42: aload_1
      43: aload_3
      44: aload         4
      46: invokevirtual #19                 // Method handleError:(Lorg/sonatype/aether/RepositoryEvent;Lorg/sonatype/aether/RepositoryListener;Ljava/lang/RuntimeException;)V
      49: goto          10
      52: return
    Exception table:
       from    to  target type
          29    36    39   Class java/lang/RuntimeException

  public void artifactDescriptorMissing(org.sonatype.aether.RepositoryEvent);
    Code:
       0: aload_0
       1: getfield      #7                  // Field listeners:Ljava/util/List;
       4: invokeinterface #16,  1           // InterfaceMethod java/util/List.iterator:()Ljava/util/Iterator;
       9: astore_2
      10: aload_2
      11: invokeinterface #11,  1           // InterfaceMethod java/util/Iterator.hasNext:()Z
      16: ifeq          52
      19: aload_2
      20: invokeinterface #12,  1           // InterfaceMethod java/util/Iterator.next:()Ljava/lang/Object;
      25: checkcast     #2                  // class org/sonatype/aether/RepositoryListener
      28: astore_3
      29: aload_3
      30: aload_1
      31: invokeinterface #22,  2           // InterfaceMethod org/sonatype/aether/RepositoryListener.artifactDescriptorMissing:(Lorg/sonatype/aether/RepositoryEvent;)V
      36: goto          49
      39: astore        4
      41: aload_0
      42: aload_1
      43: aload_3
      44: aload         4
      46: invokevirtual #19                 // Method handleError:(Lorg/sonatype/aether/RepositoryEvent;Lorg/sonatype/aether/RepositoryListener;Ljava/lang/RuntimeException;)V
      49: goto          10
      52: return
    Exception table:
       from    to  target type
          29    36    39   Class java/lang/RuntimeException

  public void artifactDownloaded(org.sonatype.aether.RepositoryEvent);
    Code:
       0: aload_0
       1: getfield      #7                  // Field listeners:Ljava/util/List;
       4: invokeinterface #16,  1           // InterfaceMethod java/util/List.iterator:()Ljava/util/Iterator;
       9: astore_2
      10: aload_2
      11: invokeinterface #11,  1           // InterfaceMethod java/util/Iterator.hasNext:()Z
      16: ifeq          52
      19: aload_2
      20: invokeinterface #12,  1           // InterfaceMethod java/util/Iterator.next:()Ljava/lang/Object;
      25: checkcast     #2                  // class org/sonatype/aether/RepositoryListener
      28: astore_3
      29: aload_3
      30: aload_1
      31: invokeinterface #23,  2           // InterfaceMethod org/sonatype/aether/RepositoryListener.artifactDownloaded:(Lorg/sonatype/aether/RepositoryEvent;)V
      36: goto          49
      39: astore        4
      41: aload_0
      42: aload_1
      43: aload_3
      44: aload         4
      46: invokevirtual #19                 // Method handleError:(Lorg/sonatype/aether/RepositoryEvent;Lorg/sonatype/aether/RepositoryListener;Ljava/lang/RuntimeException;)V
      49: goto          10
      52: return
    Exception table:
       from    to  target type
          29    36    39   Class java/lang/RuntimeException

  public void artifactDownloading(org.sonatype.aether.RepositoryEvent);
    Code:
       0: aload_0
       1: getfield      #7                  // Field listeners:Ljava/util/List;
       4: invokeinterface #16,  1           // InterfaceMethod java/util/List.iterator:()Ljava/util/Iterator;
       9: astore_2
      10: aload_2
      11: invokeinterface #11,  1           // InterfaceMethod java/util/Iterator.hasNext:()Z
      16: ifeq          52
      19: aload_2
      20: invokeinterface #12,  1           // InterfaceMethod java/util/Iterator.next:()Ljava/lang/Object;
      25: checkcast     #2                  // class org/sonatype/aether/RepositoryListener
      28: astore_3
      29: aload_3
      30: aload_1
      31: invokeinterface #24,  2           // InterfaceMethod org/sonatype/aether/RepositoryListener.artifactDownloading:(Lorg/sonatype/aether/RepositoryEvent;)V
      36: goto          49
      39: astore        4
      41: aload_0
      42: aload_1
      43: aload_3
      44: aload         4
      46: invokevirtual #19                 // Method handleError:(Lorg/sonatype/aether/RepositoryEvent;Lorg/sonatype/aether/RepositoryListener;Ljava/lang/RuntimeException;)V
      49: goto          10
      52: return
    Exception table:
       from    to  target type
          29    36    39   Class java/lang/RuntimeException

  public void artifactInstalled(org.sonatype.aether.RepositoryEvent);
    Code:
       0: aload_0
       1: getfield      #7                  // Field listeners:Ljava/util/List;
       4: invokeinterface #16,  1           // InterfaceMethod java/util/List.iterator:()Ljava/util/Iterator;
       9: astore_2
      10: aload_2
      11: invokeinterface #11,  1           // InterfaceMethod java/util/Iterator.hasNext:()Z
      16: ifeq          52
      19: aload_2
      20: invokeinterface #12,  1           // InterfaceMethod java/util/Iterator.next:()Ljava/lang/Object;
      25: checkcast     #2                  // class org/sonatype/aether/RepositoryListener
      28: astore_3
      29: aload_3
      30: aload_1
      31: invokeinterface #25,  2           // InterfaceMethod org/sonatype/aether/RepositoryListener.artifactInstalled:(Lorg/sonatype/aether/RepositoryEvent;)V
      36: goto          49
      39: astore        4
      41: aload_0
      42: aload_1
      43: aload_3
      44: aload         4
      46: invokevirtual #19                 // Method handleError:(Lorg/sonatype/aether/RepositoryEvent;Lorg/sonatype/aether/RepositoryListener;Ljava/lang/RuntimeException;)V
      49: goto          10
      52: return
    Exception table:
       from    to  target type
          29    36    39   Class java/lang/RuntimeException

  public void artifactInstalling(org.sonatype.aether.RepositoryEvent);
    Code:
       0: aload_0
       1: getfield      #7                  // Field listeners:Ljava/util/List;
       4: invokeinterface #16,  1           // InterfaceMethod java/util/List.iterator:()Ljava/util/Iterator;
       9: astore_2
      10: aload_2
      11: invokeinterface #11,  1           // InterfaceMethod java/util/Iterator.hasNext:()Z
      16: ifeq          52
      19: aload_2
      20: invokeinterface #12,  1           // InterfaceMethod java/util/Iterator.next:()Ljava/lang/Object;
      25: checkcast     #2                  // class org/sonatype/aether/RepositoryListener
      28: astore_3
      29: aload_3
      30: aload_1
      31: invokeinterface #26,  2           // InterfaceMethod org/sonatype/aether/RepositoryListener.artifactInstalling:(Lorg/sonatype/aether/RepositoryEvent;)V
      36: goto          49
      39: astore        4
      41: aload_0
      42: aload_1
      43: aload_3
      44: aload         4
      46: invokevirtual #19                 // Method handleError:(Lorg/sonatype/aether/RepositoryEvent;Lorg/sonatype/aether/RepositoryListener;Ljava/lang/RuntimeException;)V
      49: goto          10
      52: return
    Exception table:
       from    to  target type
          29    36    39   Class java/lang/RuntimeException

  public void artifactResolved(org.sonatype.aether.RepositoryEvent);
    Code:
       0: aload_0
       1: getfield      #7                  // Field listeners:Ljava/util/List;
       4: invokeinterface #16,  1           // InterfaceMethod java/util/List.iterator:()Ljava/util/Iterator;
       9: astore_2
      10: aload_2
      11: invokeinterface #11,  1           // InterfaceMethod java/util/Iterator.hasNext:()Z
      16: ifeq          52
      19: aload_2
      20: invokeinterface #12,  1           // InterfaceMethod java/util/Iterator.next:()Ljava/lang/Object;
      25: checkcast     #2                  // class org/sonatype/aether/RepositoryListener
      28: astore_3
      29: aload_3
      30: aload_1
      31: invokeinterface #27,  2           // InterfaceMethod org/sonatype/aether/RepositoryListener.artifactResolved:(Lorg/sonatype/aether/RepositoryEvent;)V
      36: goto          49
      39: astore        4
      41: aload_0
      42: aload_1
      43: aload_3
      44: aload         4
      46: invokevirtual #19                 // Method handleError:(Lorg/sonatype/aether/RepositoryEvent;Lorg/sonatype/aether/RepositoryListener;Ljava/lang/RuntimeException;)V
      49: goto          10
      52: return
    Exception table:
       from    to  target type
          29    36    39   Class java/lang/RuntimeException

  public void artifactResolving(org.sonatype.aether.RepositoryEvent);
    Code:
       0: aload_0
       1: getfield      #7                  // Field listeners:Ljava/util/List;
       4: invokeinterface #16,  1           // InterfaceMethod java/util/List.iterator:()Ljava/util/Iterator;
       9: astore_2
      10: aload_2
      11: invokeinterface #11,  1           // InterfaceMethod java/util/Iterator.hasNext:()Z
      16: ifeq          52
      19: aload_2
      20: invokeinterface #12,  1           // InterfaceMethod java/util/Iterator.next:()Ljava/lang/Object;
      25: checkcast     #2                  // class org/sonatype/aether/RepositoryListener
      28: astore_3
      29: aload_3
      30: aload_1
      31: invokeinterface #28,  2           // InterfaceMethod org/sonatype/aether/RepositoryListener.artifactResolving:(Lorg/sonatype/aether/RepositoryEvent;)V
      36: goto          49
      39: astore        4
      41: aload_0
      42: aload_1
      43: aload_3
      44: aload         4
      46: invokevirtual #19                 // Method handleError:(Lorg/sonatype/aether/RepositoryEvent;Lorg/sonatype/aether/RepositoryListener;Ljava/lang/RuntimeException;)V
      49: goto          10
      52: return
    Exception table:
       from    to  target type
          29    36    39   Class java/lang/RuntimeException

  public void metadataDeployed(org.sonatype.aether.RepositoryEvent);
    Code:
       0: aload_0
       1: getfield      #7                  // Field listeners:Ljava/util/List;
       4: invokeinterface #16,  1           // InterfaceMethod java/util/List.iterator:()Ljava/util/Iterator;
       9: astore_2
      10: aload_2
      11: invokeinterface #11,  1           // InterfaceMethod java/util/Iterator.hasNext:()Z
      16: ifeq          52
      19: aload_2
      20: invokeinterface #12,  1           // InterfaceMethod java/util/Iterator.next:()Ljava/lang/Object;
      25: checkcast     #2                  // class org/sonatype/aether/RepositoryListener
      28: astore_3
      29: aload_3
      30: aload_1
      31: invokeinterface #29,  2           // InterfaceMethod org/sonatype/aether/RepositoryListener.metadataDeployed:(Lorg/sonatype/aether/RepositoryEvent;)V
      36: goto          49
      39: astore        4
      41: aload_0
      42: aload_1
      43: aload_3
      44: aload         4
      46: invokevirtual #19                 // Method handleError:(Lorg/sonatype/aether/RepositoryEvent;Lorg/sonatype/aether/RepositoryListener;Ljava/lang/RuntimeException;)V
      49: goto          10
      52: return
    Exception table:
       from    to  target type
          29    36    39   Class java/lang/RuntimeException

  public void metadataDeploying(org.sonatype.aether.RepositoryEvent);
    Code:
       0: aload_0
       1: getfield      #7                  // Field listeners:Ljava/util/List;
       4: invokeinterface #16,  1           // InterfaceMethod java/util/List.iterator:()Ljava/util/Iterator;
       9: astore_2
      10: aload_2
      11: invokeinterface #11,  1           // InterfaceMethod java/util/Iterator.hasNext:()Z
      16: ifeq          52
      19: aload_2
      20: invokeinterface #12,  1           // InterfaceMethod java/util/Iterator.next:()Ljava/lang/Object;
      25: checkcast     #2                  // class org/sonatype/aether/RepositoryListener
      28: astore_3
      29: aload_3
      30: aload_1
      31: invokeinterface #30,  2           // InterfaceMethod org/sonatype/aether/RepositoryListener.metadataDeploying:(Lorg/sonatype/aether/RepositoryEvent;)V
      36: goto          49
      39: astore        4
      41: aload_0
      42: aload_1
      43: aload_3
      44: aload         4
      46: invokevirtual #19                 // Method handleError:(Lorg/sonatype/aether/RepositoryEvent;Lorg/sonatype/aether/RepositoryListener;Ljava/lang/RuntimeException;)V
      49: goto          10
      52: return
    Exception table:
       from    to  target type
          29    36    39   Class java/lang/RuntimeException

  public void metadataDownloaded(org.sonatype.aether.RepositoryEvent);
    Code:
       0: aload_0
       1: getfield      #7                  // Field listeners:Ljava/util/List;
       4: invokeinterface #16,  1           // InterfaceMethod java/util/List.iterator:()Ljava/util/Iterator;
       9: astore_2
      10: aload_2
      11: invokeinterface #11,  1           // InterfaceMethod java/util/Iterator.hasNext:()Z
      16: ifeq          52
      19: aload_2
      20: invokeinterface #12,  1           // InterfaceMethod java/util/Iterator.next:()Ljava/lang/Object;
      25: checkcast     #2                  // class org/sonatype/aether/RepositoryListener
      28: astore_3
      29: aload_3
      30: aload_1
      31: invokeinterface #31,  2           // InterfaceMethod org/sonatype/aether/RepositoryListener.metadataDownloaded:(Lorg/sonatype/aether/RepositoryEvent;)V
      36: goto          49
      39: astore        4
      41: aload_0
      42: aload_1
      43: aload_3
      44: aload         4
      46: invokevirtual #19                 // Method handleError:(Lorg/sonatype/aether/RepositoryEvent;Lorg/sonatype/aether/RepositoryListener;Ljava/lang/RuntimeException;)V
      49: goto          10
      52: return
    Exception table:
       from    to  target type
          29    36    39   Class java/lang/RuntimeException

  public void metadataDownloading(org.sonatype.aether.RepositoryEvent);
    Code:
       0: aload_0
       1: getfield      #7                  // Field listeners:Ljava/util/List;
       4: invokeinterface #16,  1           // InterfaceMethod java/util/List.iterator:()Ljava/util/Iterator;
       9: astore_2
      10: aload_2
      11: invokeinterface #11,  1           // InterfaceMethod java/util/Iterator.hasNext:()Z
      16: ifeq          52
      19: aload_2
      20: invokeinterface #12,  1           // InterfaceMethod java/util/Iterator.next:()Ljava/lang/Object;
      25: checkcast     #2                  // class org/sonatype/aether/RepositoryListener
      28: astore_3
      29: aload_3
      30: aload_1
      31: invokeinterface #32,  2           // InterfaceMethod org/sonatype/aether/RepositoryListener.metadataDownloading:(Lorg/sonatype/aether/RepositoryEvent;)V
      36: goto          49
      39: astore        4
      41: aload_0
      42: aload_1
      43: aload_3
      44: aload         4
      46: invokevirtual #19                 // Method handleError:(Lorg/sonatype/aether/RepositoryEvent;Lorg/sonatype/aether/RepositoryListener;Ljava/lang/RuntimeException;)V
      49: goto          10
      52: return
    Exception table:
       from    to  target type
          29    36    39   Class java/lang/RuntimeException

  public void metadataInstalled(org.sonatype.aether.RepositoryEvent);
    Code:
       0: aload_0
       1: getfield      #7                  // Field listeners:Ljava/util/List;
       4: invokeinterface #16,  1           // InterfaceMethod java/util/List.iterator:()Ljava/util/Iterator;
       9: astore_2
      10: aload_2
      11: invokeinterface #11,  1           // InterfaceMethod java/util/Iterator.hasNext:()Z
      16: ifeq          52
      19: aload_2
      20: invokeinterface #12,  1           // InterfaceMethod java/util/Iterator.next:()Ljava/lang/Object;
      25: checkcast     #2                  // class org/sonatype/aether/RepositoryListener
      28: astore_3
      29: aload_3
      30: aload_1
      31: invokeinterface #33,  2           // InterfaceMethod org/sonatype/aether/RepositoryListener.metadataInstalled:(Lorg/sonatype/aether/RepositoryEvent;)V
      36: goto          49
      39: astore        4
      41: aload_0
      42: aload_1
      43: aload_3
      44: aload         4
      46: invokevirtual #19                 // Method handleError:(Lorg/sonatype/aether/RepositoryEvent;Lorg/sonatype/aether/RepositoryListener;Ljava/lang/RuntimeException;)V
      49: goto          10
      52: return
    Exception table:
       from    to  target type
          29    36    39   Class java/lang/RuntimeException

  public void metadataInstalling(org.sonatype.aether.RepositoryEvent);
    Code:
       0: aload_0
       1: getfield      #7                  // Field listeners:Ljava/util/List;
       4: invokeinterface #16,  1           // InterfaceMethod java/util/List.iterator:()Ljava/util/Iterator;
       9: astore_2
      10: aload_2
      11: invokeinterface #11,  1           // InterfaceMethod java/util/Iterator.hasNext:()Z
      16: ifeq          52
      19: aload_2
      20: invokeinterface #12,  1           // InterfaceMethod java/util/Iterator.next:()Ljava/lang/Object;
      25: checkcast     #2                  // class org/sonatype/aether/RepositoryListener
      28: astore_3
      29: aload_3
      30: aload_1
      31: invokeinterface #34,  2           // InterfaceMethod org/sonatype/aether/RepositoryListener.metadataInstalling:(Lorg/sonatype/aether/RepositoryEvent;)V
      36: goto          49
      39: astore        4
      41: aload_0
      42: aload_1
      43: aload_3
      44: aload         4
      46: invokevirtual #19                 // Method handleError:(Lorg/sonatype/aether/RepositoryEvent;Lorg/sonatype/aether/RepositoryListener;Ljava/lang/RuntimeException;)V
      49: goto          10
      52: return
    Exception table:
       from    to  target type
          29    36    39   Class java/lang/RuntimeException

  public void metadataInvalid(org.sonatype.aether.RepositoryEvent);
    Code:
       0: aload_0
       1: getfield      #7                  // Field listeners:Ljava/util/List;
       4: invokeinterface #16,  1           // InterfaceMethod java/util/List.iterator:()Ljava/util/Iterator;
       9: astore_2
      10: aload_2
      11: invokeinterface #11,  1           // InterfaceMethod java/util/Iterator.hasNext:()Z
      16: ifeq          52
      19: aload_2
      20: invokeinterface #12,  1           // InterfaceMethod java/util/Iterator.next:()Ljava/lang/Object;
      25: checkcast     #2                  // class org/sonatype/aether/RepositoryListener
      28: astore_3
      29: aload_3
      30: aload_1
      31: invokeinterface #35,  2           // InterfaceMethod org/sonatype/aether/RepositoryListener.metadataInvalid:(Lorg/sonatype/aether/RepositoryEvent;)V
      36: goto          49
      39: astore        4
      41: aload_0
      42: aload_1
      43: aload_3
      44: aload         4
      46: invokevirtual #19                 // Method handleError:(Lorg/sonatype/aether/RepositoryEvent;Lorg/sonatype/aether/RepositoryListener;Ljava/lang/RuntimeException;)V
      49: goto          10
      52: return
    Exception table:
       from    to  target type
          29    36    39   Class java/lang/RuntimeException

  public void metadataResolved(org.sonatype.aether.RepositoryEvent);
    Code:
       0: aload_0
       1: getfield      #7                  // Field listeners:Ljava/util/List;
       4: invokeinterface #16,  1           // InterfaceMethod java/util/List.iterator:()Ljava/util/Iterator;
       9: astore_2
      10: aload_2
      11: invokeinterface #11,  1           // InterfaceMethod java/util/Iterator.hasNext:()Z
      16: ifeq          52
      19: aload_2
      20: invokeinterface #12,  1           // InterfaceMethod java/util/Iterator.next:()Ljava/lang/Object;
      25: checkcast     #2                  // class org/sonatype/aether/RepositoryListener
      28: astore_3
      29: aload_3
      30: aload_1
      31: invokeinterface #36,  2           // InterfaceMethod org/sonatype/aether/RepositoryListener.metadataResolved:(Lorg/sonatype/aether/RepositoryEvent;)V
      36: goto          49
      39: astore        4
      41: aload_0
      42: aload_1
      43: aload_3
      44: aload         4
      46: invokevirtual #19                 // Method handleError:(Lorg/sonatype/aether/RepositoryEvent;Lorg/sonatype/aether/RepositoryListener;Ljava/lang/RuntimeException;)V
      49: goto          10
      52: return
    Exception table:
       from    to  target type
          29    36    39   Class java/lang/RuntimeException

  public void metadataResolving(org.sonatype.aether.RepositoryEvent);
    Code:
       0: aload_0
       1: getfield      #7                  // Field listeners:Ljava/util/List;
       4: invokeinterface #16,  1           // InterfaceMethod java/util/List.iterator:()Ljava/util/Iterator;
       9: astore_2
      10: aload_2
      11: invokeinterface #11,  1           // InterfaceMethod java/util/Iterator.hasNext:()Z
      16: ifeq          52
      19: aload_2
      20: invokeinterface #12,  1           // InterfaceMethod java/util/Iterator.next:()Ljava/lang/Object;
      25: checkcast     #2                  // class org/sonatype/aether/RepositoryListener
      28: astore_3
      29: aload_3
      30: aload_1
      31: invokeinterface #37,  2           // InterfaceMethod org/sonatype/aether/RepositoryListener.metadataResolving:(Lorg/sonatype/aether/RepositoryEvent;)V
      36: goto          49
      39: astore        4
      41: aload_0
      42: aload_1
      43: aload_3
      44: aload         4
      46: invokevirtual #19                 // Method handleError:(Lorg/sonatype/aether/RepositoryEvent;Lorg/sonatype/aether/RepositoryListener;Ljava/lang/RuntimeException;)V
      49: goto          10
      52: return
    Exception table:
       from    to  target type
          29    36    39   Class java/lang/RuntimeException
}
