Compiled from "AnnotationUtil.java"
class org.atmosphere.annotation.AnnotationUtil$1 extends java.util.LinkedList<java.lang.Class<? extends org.atmosphere.cpr.AtmosphereInterceptor>> {
  org.atmosphere.annotation.AnnotationUtil$1();
    Code:
       0: aload_0
       1: invokespecial #1                  // Method java/util/LinkedList."<init>":()V
       4: aload_0
       5: ldc           #2                  // class org/atmosphere/interceptor/AtmosphereResourceLifecycleInterceptor
       7: invokevirtual #3                  // Method add:(Ljava/lang/Object;)Z
      10: pop
      11: aload_0
      12: ldc           #4                  // class org/atmosphere/client/TrackMessageSizeInterceptor
      14: invokevirtual #3                  // Method add:(Ljava/lang/Object;)Z
      17: pop
      18: aload_0
      19: ldc           #5                  // class org/atmosphere/interceptor/SuspendTrackerInterceptor
      21: invokevirtual #3                  // Method add:(Ljava/lang/Object;)Z
      24: pop
      25: aload_0
      26: ldc           #6                  // class org/atmosphere/config/managed/ManagedServiceInterceptor
      28: invokevirtual #3                  // Method add:(Ljava/lang/Object;)Z
      31: pop
      32: return
}
