Compiled from "ReusableParameterizedMessage.java"
public class org.apache.logging.log4j.message.ReusableParameterizedMessage implements org.apache.logging.log4j.message.ReusableMessage,org.apache.logging.log4j.message.ParameterVisitable,org.apache.logging.log4j.message.Clearable {
  private static final int MIN_BUILDER_SIZE;

  private static final int MAX_PARMS;

  private static final long serialVersionUID;

  private transient java.lang.ThreadLocal<java.lang.StringBuilder> buffer;

  private java.lang.String messagePattern;

  private int argCount;

  private int usedCount;

  private final int[] indices;

  private transient java.lang.Object[] varargs;

  private transient java.lang.Object[] params;

  private transient java.lang.Throwable throwable;

  transient boolean reserved;

  public org.apache.logging.log4j.message.ReusableParameterizedMessage();
    Code:
       0: aload_0
       1: invokespecial #1                  // Method java/lang/Object."<init>":()V
       4: aload_0
       5: sipush        256
       8: newarray       int
      10: putfield      #2                  // Field indices:[I
      13: aload_0
      14: bipush        10
      16: anewarray     #4                  // class java/lang/Object
      19: putfield      #5                  // Field params:[Ljava/lang/Object;
      22: aload_0
      23: iconst_0
      24: putfield      #6                  // Field reserved:Z
      27: return

  private java.lang.Object[] getTrimmedParams();
    Code:
       0: aload_0
       1: getfield      #7                  // Field varargs:[Ljava/lang/Object;
       4: ifnonnull     21
       7: aload_0
       8: getfield      #5                  // Field params:[Ljava/lang/Object;
      11: aload_0
      12: getfield      #8                  // Field argCount:I
      15: invokestatic  #9                  // Method java/util/Arrays.copyOf:([Ljava/lang/Object;I)[Ljava/lang/Object;
      18: goto          25
      21: aload_0
      22: getfield      #7                  // Field varargs:[Ljava/lang/Object;
      25: areturn

  private java.lang.Object[] getParams();
    Code:
       0: aload_0
       1: getfield      #7                  // Field varargs:[Ljava/lang/Object;
       4: ifnonnull     14
       7: aload_0
       8: getfield      #5                  // Field params:[Ljava/lang/Object;
      11: goto          18
      14: aload_0
      15: getfield      #7                  // Field varargs:[Ljava/lang/Object;
      18: areturn

  public java.lang.Object[] swapParameters(java.lang.Object[]);
    Code:
       0: aload_0
       1: getfield      #7                  // Field varargs:[Ljava/lang/Object;
       4: ifnonnull     90
       7: aload_0
       8: getfield      #5                  // Field params:[Ljava/lang/Object;
      11: astore_2
      12: aload_1
      13: arraylength
      14: bipush        10
      16: if_icmplt     27
      19: aload_0
      20: aload_1
      21: putfield      #5                  // Field params:[Ljava/lang/Object;
      24: goto          126
      27: aload_0
      28: getfield      #8                  // Field argCount:I
      31: aload_1
      32: arraylength
      33: if_icmpgt     78
      36: aload_0
      37: getfield      #5                  // Field params:[Ljava/lang/Object;
      40: iconst_0
      41: aload_1
      42: iconst_0
      43: aload_0
      44: getfield      #8                  // Field argCount:I
      47: invokestatic  #10                 // Method java/lang/System.arraycopy:(Ljava/lang/Object;ILjava/lang/Object;II)V
      50: iconst_0
      51: istore_3
      52: iload_3
      53: aload_0
      54: getfield      #8                  // Field argCount:I
      57: if_icmpge     73
      60: aload_0
      61: getfield      #5                  // Field params:[Ljava/lang/Object;
      64: iload_3
      65: aconst_null
      66: aastore
      67: iinc          3, 1
      70: goto          52
      73: aload_1
      74: astore_2
      75: goto          126
      78: aload_0
      79: bipush        10
      81: anewarray     #4                  // class java/lang/Object
      84: putfield      #5                  // Field params:[Ljava/lang/Object;
      87: goto          126
      90: aload_0
      91: getfield      #8                  // Field argCount:I
      94: aload_1
      95: arraylength
      96: if_icmpgt     104
      99: aload_1
     100: astore_2
     101: goto          112
     104: aload_0
     105: getfield      #8                  // Field argCount:I
     108: anewarray     #4                  // class java/lang/Object
     111: astore_2
     112: aload_0
     113: getfield      #7                  // Field varargs:[Ljava/lang/Object;
     116: iconst_0
     117: aload_2
     118: iconst_0
     119: aload_0
     120: getfield      #8                  // Field argCount:I
     123: invokestatic  #10                 // Method java/lang/System.arraycopy:(Ljava/lang/Object;ILjava/lang/Object;II)V
     126: aload_2
     127: areturn

  public short getParameterCount();
    Code:
       0: aload_0
       1: getfield      #8                  // Field argCount:I
       4: i2s
       5: ireturn

  public <S> void forEachParameter(org.apache.logging.log4j.message.ParameterConsumer<S>, S);
    Code:
       0: aload_0
       1: invokespecial #11                 // Method getParams:()[Ljava/lang/Object;
       4: astore_3
       5: iconst_0
       6: istore        4
       8: iload         4
      10: aload_0
      11: getfield      #8                  // Field argCount:I
      14: if_icmpge     40
      17: aload_1
      18: aload_3
      19: iload         4
      21: aaload
      22: iload         4
      24: aload_2
      25: invokeinterface #12,  4           // InterfaceMethod org/apache/logging/log4j/message/ParameterConsumer.accept:(Ljava/lang/Object;ILjava/lang/Object;)V
      30: iload         4
      32: iconst_1
      33: iadd
      34: i2s
      35: istore        4
      37: goto          8
      40: return

  public org.apache.logging.log4j.message.Message memento();
    Code:
       0: new           #13                 // class org/apache/logging/log4j/message/ParameterizedMessage
       3: dup
       4: aload_0
       5: getfield      #14                 // Field messagePattern:Ljava/lang/String;
       8: aload_0
       9: invokespecial #15                 // Method getTrimmedParams:()[Ljava/lang/Object;
      12: invokespecial #16                 // Method org/apache/logging/log4j/message/ParameterizedMessage."<init>":(Ljava/lang/String;[Ljava/lang/Object;)V
      15: areturn

  private void init(java.lang.String, int, java.lang.Object[]);
    Code:
       0: aload_0
       1: aconst_null
       2: putfield      #7                  // Field varargs:[Ljava/lang/Object;
       5: aload_0
       6: aload_1
       7: putfield      #14                 // Field messagePattern:Ljava/lang/String;
      10: aload_0
      11: iload_2
      12: putfield      #8                  // Field argCount:I
      15: aload_1
      16: aload_0
      17: getfield      #2                  // Field indices:[I
      20: invokestatic  #17                 // Method count:(Ljava/lang/String;[I)I
      23: istore        4
      25: aload_0
      26: aload_3
      27: iload_2
      28: iload         4
      30: invokespecial #18                 // Method initThrowable:([Ljava/lang/Object;II)V
      33: aload_0
      34: iload         4
      36: iload_2
      37: invokestatic  #19                 // Method java/lang/Math.min:(II)I
      40: putfield      #20                 // Field usedCount:I
      43: return

  private static int count(java.lang.String, int[]);
    Code:
       0: aload_0
       1: aload_1
       2: invokestatic  #21                 // Method org/apache/logging/log4j/message/ParameterFormatter.countArgumentPlaceholders2:(Ljava/lang/String;[I)I
       5: ireturn
       6: astore_2
       7: aload_0
       8: invokestatic  #23                 // Method org/apache/logging/log4j/message/ParameterFormatter.countArgumentPlaceholders:(Ljava/lang/String;)I
      11: ireturn
    Exception table:
       from    to  target type
           0     5     6   Class java/lang/Exception

  private void initThrowable(java.lang.Object[], int, int);
    Code:
       0: iload_3
       1: iload_2
       2: if_icmpge     31
       5: aload_1
       6: iload_2
       7: iconst_1
       8: isub
       9: aaload
      10: instanceof    #24                 // class java/lang/Throwable
      13: ifeq          31
      16: aload_0
      17: aload_1
      18: iload_2
      19: iconst_1
      20: isub
      21: aaload
      22: checkcast     #24                 // class java/lang/Throwable
      25: putfield      #25                 // Field throwable:Ljava/lang/Throwable;
      28: goto          36
      31: aload_0
      32: aconst_null
      33: putfield      #25                 // Field throwable:Ljava/lang/Throwable;
      36: return

  org.apache.logging.log4j.message.ReusableParameterizedMessage set(java.lang.String, java.lang.Object...);
    Code:
       0: aload_0
       1: aload_1
       2: aload_2
       3: ifnonnull     10
       6: iconst_0
       7: goto          12
      10: aload_2
      11: arraylength
      12: aload_2
      13: invokespecial #26                 // Method init:(Ljava/lang/String;I[Ljava/lang/Object;)V
      16: aload_0
      17: aload_2
      18: putfield      #7                  // Field varargs:[Ljava/lang/Object;
      21: aload_0
      22: areturn

  org.apache.logging.log4j.message.ReusableParameterizedMessage set(java.lang.String, java.lang.Object);
    Code:
       0: aload_0
       1: getfield      #5                  // Field params:[Ljava/lang/Object;
       4: iconst_0
       5: aload_2
       6: aastore
       7: aload_0
       8: aload_1
       9: iconst_1
      10: aload_0
      11: getfield      #5                  // Field params:[Ljava/lang/Object;
      14: invokespecial #26                 // Method init:(Ljava/lang/String;I[Ljava/lang/Object;)V
      17: aload_0
      18: areturn

  org.apache.logging.log4j.message.ReusableParameterizedMessage set(java.lang.String, java.lang.Object, java.lang.Object);
    Code:
       0: aload_0
       1: getfield      #5                  // Field params:[Ljava/lang/Object;
       4: iconst_0
       5: aload_2
       6: aastore
       7: aload_0
       8: getfield      #5                  // Field params:[Ljava/lang/Object;
      11: iconst_1
      12: aload_3
      13: aastore
      14: aload_0
      15: aload_1
      16: iconst_2
      17: aload_0
      18: getfield      #5                  // Field params:[Ljava/lang/Object;
      21: invokespecial #26                 // Method init:(Ljava/lang/String;I[Ljava/lang/Object;)V
      24: aload_0
      25: areturn

  org.apache.logging.log4j.message.ReusableParameterizedMessage set(java.lang.String, java.lang.Object, java.lang.Object, java.lang.Object);
    Code:
       0: aload_0
       1: getfield      #5                  // Field params:[Ljava/lang/Object;
       4: iconst_0
       5: aload_2
       6: aastore
       7: aload_0
       8: getfield      #5                  // Field params:[Ljava/lang/Object;
      11: iconst_1
      12: aload_3
      13: aastore
      14: aload_0
      15: getfield      #5                  // Field params:[Ljava/lang/Object;
      18: iconst_2
      19: aload         4
      21: aastore
      22: aload_0
      23: aload_1
      24: iconst_3
      25: aload_0
      26: getfield      #5                  // Field params:[Ljava/lang/Object;
      29: invokespecial #26                 // Method init:(Ljava/lang/String;I[Ljava/lang/Object;)V
      32: aload_0
      33: areturn

  org.apache.logging.log4j.message.ReusableParameterizedMessage set(java.lang.String, java.lang.Object, java.lang.Object, java.lang.Object, java.lang.Object);
    Code:
       0: aload_0
       1: getfield      #5                  // Field params:[Ljava/lang/Object;
       4: iconst_0
       5: aload_2
       6: aastore
       7: aload_0
       8: getfield      #5                  // Field params:[Ljava/lang/Object;
      11: iconst_1
      12: aload_3
      13: aastore
      14: aload_0
      15: getfield      #5                  // Field params:[Ljava/lang/Object;
      18: iconst_2
      19: aload         4
      21: aastore
      22: aload_0
      23: getfield      #5                  // Field params:[Ljava/lang/Object;
      26: iconst_3
      27: aload         5
      29: aastore
      30: aload_0
      31: aload_1
      32: iconst_4
      33: aload_0
      34: getfield      #5                  // Field params:[Ljava/lang/Object;
      37: invokespecial #26                 // Method init:(Ljava/lang/String;I[Ljava/lang/Object;)V
      40: aload_0
      41: areturn

  org.apache.logging.log4j.message.ReusableParameterizedMessage set(java.lang.String, java.lang.Object, java.lang.Object, java.lang.Object, java.lang.Object, java.lang.Object);
    Code:
       0: aload_0
       1: getfield      #5                  // Field params:[Ljava/lang/Object;
       4: iconst_0
       5: aload_2
       6: aastore
       7: aload_0
       8: getfield      #5                  // Field params:[Ljava/lang/Object;
      11: iconst_1
      12: aload_3
      13: aastore
      14: aload_0
      15: getfield      #5                  // Field params:[Ljava/lang/Object;
      18: iconst_2
      19: aload         4
      21: aastore
      22: aload_0
      23: getfield      #5                  // Field params:[Ljava/lang/Object;
      26: iconst_3
      27: aload         5
      29: aastore
      30: aload_0
      31: getfield      #5                  // Field params:[Ljava/lang/Object;
      34: iconst_4
      35: aload         6
      37: aastore
      38: aload_0
      39: aload_1
      40: iconst_5
      41: aload_0
      42: getfield      #5                  // Field params:[Ljava/lang/Object;
      45: invokespecial #26                 // Method init:(Ljava/lang/String;I[Ljava/lang/Object;)V
      48: aload_0
      49: areturn

  org.apache.logging.log4j.message.ReusableParameterizedMessage set(java.lang.String, java.lang.Object, java.lang.Object, java.lang.Object, java.lang.Object, java.lang.Object, java.lang.Object);
    Code:
       0: aload_0
       1: getfield      #5                  // Field params:[Ljava/lang/Object;
       4: iconst_0
       5: aload_2
       6: aastore
       7: aload_0
       8: getfield      #5                  // Field params:[Ljava/lang/Object;
      11: iconst_1
      12: aload_3
      13: aastore
      14: aload_0
      15: getfield      #5                  // Field params:[Ljava/lang/Object;
      18: iconst_2
      19: aload         4
      21: aastore
      22: aload_0
      23: getfield      #5                  // Field params:[Ljava/lang/Object;
      26: iconst_3
      27: aload         5
      29: aastore
      30: aload_0
      31: getfield      #5                  // Field params:[Ljava/lang/Object;
      34: iconst_4
      35: aload         6
      37: aastore
      38: aload_0
      39: getfield      #5                  // Field params:[Ljava/lang/Object;
      42: iconst_5
      43: aload         7
      45: aastore
      46: aload_0
      47: aload_1
      48: bipush        6
      50: aload_0
      51: getfield      #5                  // Field params:[Ljava/lang/Object;
      54: invokespecial #26                 // Method init:(Ljava/lang/String;I[Ljava/lang/Object;)V
      57: aload_0
      58: areturn

  org.apache.logging.log4j.message.ReusableParameterizedMessage set(java.lang.String, java.lang.Object, java.lang.Object, java.lang.Object, java.lang.Object, java.lang.Object, java.lang.Object, java.lang.Object);
    Code:
       0: aload_0
       1: getfield      #5                  // Field params:[Ljava/lang/Object;
       4: iconst_0
       5: aload_2
       6: aastore
       7: aload_0
       8: getfield      #5                  // Field params:[Ljava/lang/Object;
      11: iconst_1
      12: aload_3
      13: aastore
      14: aload_0
      15: getfield      #5                  // Field params:[Ljava/lang/Object;
      18: iconst_2
      19: aload         4
      21: aastore
      22: aload_0
      23: getfield      #5                  // Field params:[Ljava/lang/Object;
      26: iconst_3
      27: aload         5
      29: aastore
      30: aload_0
      31: getfield      #5                  // Field params:[Ljava/lang/Object;
      34: iconst_4
      35: aload         6
      37: aastore
      38: aload_0
      39: getfield      #5                  // Field params:[Ljava/lang/Object;
      42: iconst_5
      43: aload         7
      45: aastore
      46: aload_0
      47: getfield      #5                  // Field params:[Ljava/lang/Object;
      50: bipush        6
      52: aload         8
      54: aastore
      55: aload_0
      56: aload_1
      57: bipush        7
      59: aload_0
      60: getfield      #5                  // Field params:[Ljava/lang/Object;
      63: invokespecial #26                 // Method init:(Ljava/lang/String;I[Ljava/lang/Object;)V
      66: aload_0
      67: areturn

  org.apache.logging.log4j.message.ReusableParameterizedMessage set(java.lang.String, java.lang.Object, java.lang.Object, java.lang.Object, java.lang.Object, java.lang.Object, java.lang.Object, java.lang.Object, java.lang.Object);
    Code:
       0: aload_0
       1: getfield      #5                  // Field params:[Ljava/lang/Object;
       4: iconst_0
       5: aload_2
       6: aastore
       7: aload_0
       8: getfield      #5                  // Field params:[Ljava/lang/Object;
      11: iconst_1
      12: aload_3
      13: aastore
      14: aload_0
      15: getfield      #5                  // Field params:[Ljava/lang/Object;
      18: iconst_2
      19: aload         4
      21: aastore
      22: aload_0
      23: getfield      #5                  // Field params:[Ljava/lang/Object;
      26: iconst_3
      27: aload         5
      29: aastore
      30: aload_0
      31: getfield      #5                  // Field params:[Ljava/lang/Object;
      34: iconst_4
      35: aload         6
      37: aastore
      38: aload_0
      39: getfield      #5                  // Field params:[Ljava/lang/Object;
      42: iconst_5
      43: aload         7
      45: aastore
      46: aload_0
      47: getfield      #5                  // Field params:[Ljava/lang/Object;
      50: bipush        6
      52: aload         8
      54: aastore
      55: aload_0
      56: getfield      #5                  // Field params:[Ljava/lang/Object;
      59: bipush        7
      61: aload         9
      63: aastore
      64: aload_0
      65: aload_1
      66: bipush        8
      68: aload_0
      69: getfield      #5                  // Field params:[Ljava/lang/Object;
      72: invokespecial #26                 // Method init:(Ljava/lang/String;I[Ljava/lang/Object;)V
      75: aload_0
      76: areturn

  org.apache.logging.log4j.message.ReusableParameterizedMessage set(java.lang.String, java.lang.Object, java.lang.Object, java.lang.Object, java.lang.Object, java.lang.Object, java.lang.Object, java.lang.Object, java.lang.Object, java.lang.Object);
    Code:
       0: aload_0
       1: getfield      #5                  // Field params:[Ljava/lang/Object;
       4: iconst_0
       5: aload_2
       6: aastore
       7: aload_0
       8: getfield      #5                  // Field params:[Ljava/lang/Object;
      11: iconst_1
      12: aload_3
      13: aastore
      14: aload_0
      15: getfield      #5                  // Field params:[Ljava/lang/Object;
      18: iconst_2
      19: aload         4
      21: aastore
      22: aload_0
      23: getfield      #5                  // Field params:[Ljava/lang/Object;
      26: iconst_3
      27: aload         5
      29: aastore
      30: aload_0
      31: getfield      #5                  // Field params:[Ljava/lang/Object;
      34: iconst_4
      35: aload         6
      37: aastore
      38: aload_0
      39: getfield      #5                  // Field params:[Ljava/lang/Object;
      42: iconst_5
      43: aload         7
      45: aastore
      46: aload_0
      47: getfield      #5                  // Field params:[Ljava/lang/Object;
      50: bipush        6
      52: aload         8
      54: aastore
      55: aload_0
      56: getfield      #5                  // Field params:[Ljava/lang/Object;
      59: bipush        7
      61: aload         9
      63: aastore
      64: aload_0
      65: getfield      #5                  // Field params:[Ljava/lang/Object;
      68: bipush        8
      70: aload         10
      72: aastore
      73: aload_0
      74: aload_1
      75: bipush        9
      77: aload_0
      78: getfield      #5                  // Field params:[Ljava/lang/Object;
      81: invokespecial #26                 // Method init:(Ljava/lang/String;I[Ljava/lang/Object;)V
      84: aload_0
      85: areturn

  org.apache.logging.log4j.message.ReusableParameterizedMessage set(java.lang.String, java.lang.Object, java.lang.Object, java.lang.Object, java.lang.Object, java.lang.Object, java.lang.Object, java.lang.Object, java.lang.Object, java.lang.Object, java.lang.Object);
    Code:
       0: aload_0
       1: getfield      #5                  // Field params:[Ljava/lang/Object;
       4: iconst_0
       5: aload_2
       6: aastore
       7: aload_0
       8: getfield      #5                  // Field params:[Ljava/lang/Object;
      11: iconst_1
      12: aload_3
      13: aastore
      14: aload_0
      15: getfield      #5                  // Field params:[Ljava/lang/Object;
      18: iconst_2
      19: aload         4
      21: aastore
      22: aload_0
      23: getfield      #5                  // Field params:[Ljava/lang/Object;
      26: iconst_3
      27: aload         5
      29: aastore
      30: aload_0
      31: getfield      #5                  // Field params:[Ljava/lang/Object;
      34: iconst_4
      35: aload         6
      37: aastore
      38: aload_0
      39: getfield      #5                  // Field params:[Ljava/lang/Object;
      42: iconst_5
      43: aload         7
      45: aastore
      46: aload_0
      47: getfield      #5                  // Field params:[Ljava/lang/Object;
      50: bipush        6
      52: aload         8
      54: aastore
      55: aload_0
      56: getfield      #5                  // Field params:[Ljava/lang/Object;
      59: bipush        7
      61: aload         9
      63: aastore
      64: aload_0
      65: getfield      #5                  // Field params:[Ljava/lang/Object;
      68: bipush        8
      70: aload         10
      72: aastore
      73: aload_0
      74: getfield      #5                  // Field params:[Ljava/lang/Object;
      77: bipush        9
      79: aload         11
      81: aastore
      82: aload_0
      83: aload_1
      84: bipush        10
      86: aload_0
      87: getfield      #5                  // Field params:[Ljava/lang/Object;
      90: invokespecial #26                 // Method init:(Ljava/lang/String;I[Ljava/lang/Object;)V
      93: aload_0
      94: areturn

  public java.lang.String getFormat();
    Code:
       0: aload_0
       1: getfield      #14                 // Field messagePattern:Ljava/lang/String;
       4: areturn

  public java.lang.Object[] getParameters();
    Code:
       0: aload_0
       1: invokespecial #15                 // Method getTrimmedParams:()[Ljava/lang/Object;
       4: areturn

  public java.lang.Throwable getThrowable();
    Code:
       0: aload_0
       1: getfield      #25                 // Field throwable:Ljava/lang/Throwable;
       4: areturn

  public java.lang.String getFormattedMessage();
    Code:
       0: aload_0
       1: invokespecial #27                 // Method getBuffer:()Ljava/lang/StringBuilder;
       4: astore_1
       5: aload_0
       6: aload_1
       7: invokevirtual #28                 // Method formatTo:(Ljava/lang/StringBuilder;)V
      10: aload_1
      11: invokevirtual #29                 // Method java/lang/StringBuilder.toString:()Ljava/lang/String;
      14: astore_2
      15: aload_1
      16: getstatic     #30                 // Field org/apache/logging/log4j/util/Constants.MAX_REUSABLE_MESSAGE_SIZE:I
      19: invokestatic  #31                 // Method org/apache/logging/log4j/util/StringBuilders.trimToMaxSize:(Ljava/lang/StringBuilder;I)V
      22: aload_2
      23: areturn

  private java.lang.StringBuilder getBuffer();
    Code:
       0: aload_0
       1: getfield      #32                 // Field buffer:Ljava/lang/ThreadLocal;
       4: ifnonnull     18
       7: aload_0
       8: new           #33                 // class java/lang/ThreadLocal
      11: dup
      12: invokespecial #34                 // Method java/lang/ThreadLocal."<init>":()V
      15: putfield      #32                 // Field buffer:Ljava/lang/ThreadLocal;
      18: aload_0
      19: getfield      #32                 // Field buffer:Ljava/lang/ThreadLocal;
      22: invokevirtual #35                 // Method java/lang/ThreadLocal.get:()Ljava/lang/Object;
      25: checkcast     #36                 // class java/lang/StringBuilder
      28: astore_1
      29: aload_1
      30: ifnonnull     77
      33: aload_0
      34: getfield      #14                 // Field messagePattern:Ljava/lang/String;
      37: ifnonnull     44
      40: iconst_0
      41: goto          51
      44: aload_0
      45: getfield      #14                 // Field messagePattern:Ljava/lang/String;
      48: invokevirtual #37                 // Method java/lang/String.length:()I
      51: istore_2
      52: new           #36                 // class java/lang/StringBuilder
      55: dup
      56: sipush        512
      59: iload_2
      60: iconst_2
      61: imul
      62: invokestatic  #38                 // Method java/lang/Math.max:(II)I
      65: invokespecial #39                 // Method java/lang/StringBuilder."<init>":(I)V
      68: astore_1
      69: aload_0
      70: getfield      #32                 // Field buffer:Ljava/lang/ThreadLocal;
      73: aload_1
      74: invokevirtual #40                 // Method java/lang/ThreadLocal.set:(Ljava/lang/Object;)V
      77: aload_1
      78: iconst_0
      79: invokevirtual #41                 // Method java/lang/StringBuilder.setLength:(I)V
      82: aload_1
      83: areturn

  public void formatTo(java.lang.StringBuilder);
    Code:
       0: aload_0
       1: getfield      #2                  // Field indices:[I
       4: iconst_0
       5: iaload
       6: ifge          28
       9: aload_1
      10: aload_0
      11: getfield      #14                 // Field messagePattern:Ljava/lang/String;
      14: aload_0
      15: invokespecial #11                 // Method getParams:()[Ljava/lang/Object;
      18: aload_0
      19: getfield      #8                  // Field argCount:I
      22: invokestatic  #42                 // Method org/apache/logging/log4j/message/ParameterFormatter.formatMessage:(Ljava/lang/StringBuilder;Ljava/lang/String;[Ljava/lang/Object;I)V
      25: goto          48
      28: aload_1
      29: aload_0
      30: getfield      #14                 // Field messagePattern:Ljava/lang/String;
      33: aload_0
      34: invokespecial #11                 // Method getParams:()[Ljava/lang/Object;
      37: aload_0
      38: getfield      #20                 // Field usedCount:I
      41: aload_0
      42: getfield      #2                  // Field indices:[I
      45: invokestatic  #43                 // Method org/apache/logging/log4j/message/ParameterFormatter.formatMessage2:(Ljava/lang/StringBuilder;Ljava/lang/String;[Ljava/lang/Object;I[I)V
      48: return

  org.apache.logging.log4j.message.ReusableParameterizedMessage reserve();
    Code:
       0: aload_0
       1: iconst_1
       2: putfield      #6                  // Field reserved:Z
       5: aload_0
       6: areturn

  public java.lang.String toString();
    Code:
       0: new           #36                 // class java/lang/StringBuilder
       3: dup
       4: invokespecial #44                 // Method java/lang/StringBuilder."<init>":()V
       7: ldc           #45                 // String ReusableParameterizedMessage[messagePattern=
       9: invokevirtual #46                 // Method java/lang/StringBuilder.append:(Ljava/lang/String;)Ljava/lang/StringBuilder;
      12: aload_0
      13: invokevirtual #47                 // Method getFormat:()Ljava/lang/String;
      16: invokevirtual #46                 // Method java/lang/StringBuilder.append:(Ljava/lang/String;)Ljava/lang/StringBuilder;
      19: ldc           #48                 // String , stringArgs=
      21: invokevirtual #46                 // Method java/lang/StringBuilder.append:(Ljava/lang/String;)Ljava/lang/StringBuilder;
      24: aload_0
      25: invokevirtual #49                 // Method getParameters:()[Ljava/lang/Object;
      28: invokestatic  #50                 // Method java/util/Arrays.toString:([Ljava/lang/Object;)Ljava/lang/String;
      31: invokevirtual #46                 // Method java/lang/StringBuilder.append:(Ljava/lang/String;)Ljava/lang/StringBuilder;
      34: ldc           #51                 // String , throwable=
      36: invokevirtual #46                 // Method java/lang/StringBuilder.append:(Ljava/lang/String;)Ljava/lang/StringBuilder;
      39: aload_0
      40: invokevirtual #52                 // Method getThrowable:()Ljava/lang/Throwable;
      43: invokevirtual #53                 // Method java/lang/StringBuilder.append:(Ljava/lang/Object;)Ljava/lang/StringBuilder;
      46: bipush        93
      48: invokevirtual #54                 // Method java/lang/StringBuilder.append:(C)Ljava/lang/StringBuilder;
      51: invokevirtual #29                 // Method java/lang/StringBuilder.toString:()Ljava/lang/String;
      54: areturn

  public void clear();
    Code:
       0: aload_0
       1: iconst_0
       2: putfield      #6                  // Field reserved:Z
       5: aload_0
       6: aconst_null
       7: putfield      #7                  // Field varargs:[Ljava/lang/Object;
      10: aload_0
      11: aconst_null
      12: putfield      #14                 // Field messagePattern:Ljava/lang/String;
      15: aload_0
      16: aconst_null
      17: putfield      #25                 // Field throwable:Ljava/lang/Throwable;
      20: return
}
