Compiled from "WebSocketClient13TestCase.java"
final class io.undertow.websockets.client.version13.WebSocketClient13TestCase$2 implements io.undertow.server.HttpHandler {
  final io.undertow.server.handlers.ConnectHandler val$handler;

  io.undertow.websockets.client.version13.WebSocketClient13TestCase$2(io.undertow.server.handlers.ConnectHandler);
    Code:
       0: aload_0
       1: aload_1
       2: putfield      #1                  // Field val$handler:Lio/undertow/server/handlers/ConnectHandler;
       5: aload_0
       6: invokespecial #2                  // Method java/lang/Object."<init>":()V
       9: return

  public void handleRequest(io.undertow.server.HttpServerExchange) throws java.lang.Exception;
    Code:
       0: invokestatic  #3                  // Method io/undertow/websockets/client/version13/WebSocketClient13TestCase.access$000:()Ljava/util/Deque;
       3: new           #4                  // class java/lang/StringBuilder
       6: dup
       7: invokespecial #5                  // Method java/lang/StringBuilder."<init>":()V
      10: aload_1
      11: invokevirtual #6                  // Method io/undertow/server/HttpServerExchange.getRequestMethod:()Lio/undertow/util/HttpString;
      14: invokevirtual #7                  // Method java/lang/StringBuilder.append:(Ljava/lang/Object;)Ljava/lang/StringBuilder;
      17: ldc           #8                  // String
      19: invokevirtual #9                  // Method java/lang/StringBuilder.append:(Ljava/lang/String;)Ljava/lang/StringBuilder;
      22: aload_1
      23: invokevirtual #10                 // Method io/undertow/server/HttpServerExchange.getRelativePath:()Ljava/lang/String;
      26: invokevirtual #9                  // Method java/lang/StringBuilder.append:(Ljava/lang/String;)Ljava/lang/StringBuilder;
      29: invokevirtual #11                 // Method java/lang/StringBuilder.toString:()Ljava/lang/String;
      32: invokeinterface #12,  2           // InterfaceMethod java/util/Deque.add:(Ljava/lang/Object;)Z
      37: pop
      38: aload_0
      39: getfield      #1                  // Field val$handler:Lio/undertow/server/handlers/ConnectHandler;
      42: aload_1
      43: invokevirtual #13                 // Method io/undertow/server/handlers/ConnectHandler.handleRequest:(Lio/undertow/server/HttpServerExchange;)V
      46: return
}
