Compiled from "AbstractEntitySourceImpl.java"
public abstract class org.hibernate.boot.model.source.internal.hbm.AbstractEntitySourceImpl extends org.hibernate.boot.model.source.internal.hbm.AbstractHbmSourceNode implements org.hibernate.boot.model.source.spi.EntitySource,org.hibernate.boot.model.source.internal.hbm.Helper$InLineViewNameInferrer {
  private static final org.hibernate.boot.model.source.spi.FilterSource[] NO_FILTER_SOURCES;

  private final org.hibernate.boot.jaxb.hbm.spi.JaxbHbmEntityBaseDefinition jaxbEntityMapping;

  private final org.hibernate.boot.model.source.spi.EntityNamingSource entityNamingSource;

  private final org.hibernate.boot.model.source.spi.AttributeRole attributeRoleBase;

  private final org.hibernate.boot.model.source.spi.AttributePath attributePathBase;

  private java.util.List<org.hibernate.boot.model.source.spi.IdentifiableTypeSource> subclassEntitySources;

  private int inLineViewCount;

  private java.util.List<org.hibernate.boot.model.source.spi.AttributeSource> attributeSources;

  private java.util.Map<java.lang.String, org.hibernate.boot.model.source.spi.SecondaryTableSource> secondaryTableMap;

  private final org.hibernate.boot.model.source.spi.FilterSource[] filterSources;

  private final java.util.Map<org.hibernate.EntityMode, java.lang.String> tuplizerClassMap;

  private final org.hibernate.boot.model.source.spi.ToolingHintContext toolingHintContext;

  private org.hibernate.boot.model.source.internal.hbm.EntityHierarchySourceImpl entityHierarchy;

  protected org.hibernate.boot.model.source.internal.hbm.AbstractEntitySourceImpl(org.hibernate.boot.model.source.internal.hbm.MappingDocument, org.hibernate.boot.jaxb.hbm.spi.JaxbHbmEntityBaseDefinition);
    Code:
       0: aload_0
       1: aload_1
       2: invokespecial #2                  // Method org/hibernate/boot/model/source/internal/hbm/AbstractHbmSourceNode."<init>":(Lorg/hibernate/boot/model/source/internal/hbm/MappingDocument;)V
       5: aload_0
       6: new           #3                  // class java/util/ArrayList
       9: dup
      10: invokespecial #4                  // Method java/util/ArrayList."<init>":()V
      13: putfield      #5                  // Field subclassEntitySources:Ljava/util/List;
      16: aload_0
      17: iconst_0
      18: putfield      #6                  // Field inLineViewCount:I
      21: aload_0
      22: aload_2
      23: putfield      #7                  // Field jaxbEntityMapping:Lorg/hibernate/boot/jaxb/hbm/spi/JaxbHbmEntityBaseDefinition;
      26: aload_0
      27: aload_1
      28: aload_2
      29: invokestatic  #8                  // Method extractEntityNamingSource:(Lorg/hibernate/boot/model/source/internal/hbm/MappingDocument;Lorg/hibernate/boot/jaxb/hbm/spi/EntityInfo;)Lorg/hibernate/boot/model/source/internal/hbm/EntityNamingSourceImpl;
      32: putfield      #9                  // Field entityNamingSource:Lorg/hibernate/boot/model/source/spi/EntityNamingSource;
      35: aload_0
      36: new           #10                 // class org/hibernate/boot/model/source/spi/AttributePath
      39: dup
      40: invokespecial #11                 // Method org/hibernate/boot/model/source/spi/AttributePath."<init>":()V
      43: putfield      #12                 // Field attributePathBase:Lorg/hibernate/boot/model/source/spi/AttributePath;
      46: aload_0
      47: new           #13                 // class org/hibernate/boot/model/source/spi/AttributeRole
      50: dup
      51: aload_0
      52: getfield      #9                  // Field entityNamingSource:Lorg/hibernate/boot/model/source/spi/EntityNamingSource;
      55: invokeinterface #14,  1           // InterfaceMethod org/hibernate/boot/model/source/spi/EntityNamingSource.getEntityName:()Ljava/lang/String;
      60: invokespecial #15                 // Method org/hibernate/boot/model/source/spi/AttributeRole."<init>":(Ljava/lang/String;)V
      63: putfield      #16                 // Field attributeRoleBase:Lorg/hibernate/boot/model/source/spi/AttributeRole;
      66: aload_0
      67: aload_2
      68: invokestatic  #17                 // Method extractTuplizers:(Lorg/hibernate/boot/jaxb/hbm/spi/JaxbHbmEntityBaseDefinition;)Ljava/util/Map;
      71: putfield      #18                 // Field tuplizerClassMap:Ljava/util/Map;
      74: aload_0
      75: aload_0
      76: invokespecial #19                 // Method buildFilterSources:()[Lorg/hibernate/boot/model/source/spi/FilterSource;
      79: putfield      #20                 // Field filterSources:[Lorg/hibernate/boot/model/source/spi/FilterSource;
      82: aload_2
      83: invokevirtual #21                 // Method org/hibernate/boot/jaxb/hbm/spi/JaxbHbmEntityBaseDefinition.getFetchProfile:()Ljava/util/List;
      86: invokeinterface #22,  1           // InterfaceMethod java/util/List.iterator:()Ljava/util/Iterator;
      91: astore_3
      92: aload_3
      93: invokeinterface #23,  1           // InterfaceMethod java/util/Iterator.hasNext:()Z
      98: ifeq          154
     101: aload_3
     102: invokeinterface #24,  1           // InterfaceMethod java/util/Iterator.next:()Ljava/lang/Object;
     107: checkcast     #25                 // class org/hibernate/boot/jaxb/hbm/spi/JaxbHbmFetchProfileType
     110: astore        4
     112: aload_1
     113: aload         4
     115: aload_0
     116: getfield      #9                  // Field entityNamingSource:Lorg/hibernate/boot/model/source/spi/EntityNamingSource;
     119: invokeinterface #26,  1           // InterfaceMethod org/hibernate/boot/model/source/spi/EntityNamingSource.getClassName:()Ljava/lang/String;
     124: ifnull        139
     127: aload_0
     128: getfield      #9                  // Field entityNamingSource:Lorg/hibernate/boot/model/source/spi/EntityNamingSource;
     131: invokeinterface #26,  1           // InterfaceMethod org/hibernate/boot/model/source/spi/EntityNamingSource.getClassName:()Ljava/lang/String;
     136: goto          148
     139: aload_0
     140: getfield      #9                  // Field entityNamingSource:Lorg/hibernate/boot/model/source/spi/EntityNamingSource;
     143: invokeinterface #14,  1           // InterfaceMethod org/hibernate/boot/model/source/spi/EntityNamingSource.getEntityName:()Ljava/lang/String;
     148: invokestatic  #27                 // Method org/hibernate/boot/model/source/internal/hbm/FetchProfileBinder.processFetchProfile:(Lorg/hibernate/boot/model/source/internal/hbm/HbmLocalMetadataBuildingContext;Lorg/hibernate/boot/jaxb/hbm/spi/JaxbHbmFetchProfileType;Ljava/lang/String;)V
     151: goto          92
     154: aload_0
     155: aload_1
     156: invokevirtual #28                 // Method org/hibernate/boot/model/source/internal/hbm/MappingDocument.getToolingHintContext:()Lorg/hibernate/boot/model/source/spi/ToolingHintContext;
     159: aload_2
     160: invokestatic  #29                 // Method org/hibernate/boot/model/source/internal/hbm/Helper.collectToolingHints:(Lorg/hibernate/boot/model/source/spi/ToolingHintContext;Lorg/hibernate/boot/jaxb/hbm/spi/ToolingHintContainer;)Lorg/hibernate/boot/model/source/spi/ToolingHintContext;
     163: putfield      #30                 // Field toolingHintContext:Lorg/hibernate/boot/model/source/spi/ToolingHintContext;
     166: return

  public static org.hibernate.boot.model.source.internal.hbm.EntityNamingSourceImpl extractEntityNamingSource(org.hibernate.boot.model.source.internal.hbm.MappingDocument, org.hibernate.boot.jaxb.hbm.spi.EntityInfo);
    Code:
       0: aload_0
       1: aload_1
       2: invokeinterface #31,  1           // InterfaceMethod org/hibernate/boot/jaxb/hbm/spi/EntityInfo.getName:()Ljava/lang/String;
       7: invokevirtual #32                 // Method org/hibernate/boot/model/source/internal/hbm/MappingDocument.qualifyClassName:(Ljava/lang/String;)Ljava/lang/String;
      10: astore_2
      11: aload_1
      12: invokeinterface #33,  1           // InterfaceMethod org/hibernate/boot/jaxb/hbm/spi/EntityInfo.getEntityName:()Ljava/lang/String;
      17: invokestatic  #34                 // Method org/hibernate/internal/util/StringHelper.isNotEmpty:(Ljava/lang/String;)Z
      20: ifeq          41
      23: aload_1
      24: invokeinterface #33,  1           // InterfaceMethod org/hibernate/boot/jaxb/hbm/spi/EntityInfo.getEntityName:()Ljava/lang/String;
      29: astore_3
      30: aload_1
      31: invokeinterface #33,  1           // InterfaceMethod org/hibernate/boot/jaxb/hbm/spi/EntityInfo.getEntityName:()Ljava/lang/String;
      36: astore        4
      38: goto          49
      41: aload_2
      42: astore_3
      43: aload_2
      44: invokestatic  #35                 // Method org/hibernate/internal/util/StringHelper.unqualify:(Ljava/lang/String;)Ljava/lang/String;
      47: astore        4
      49: new           #36                 // class org/hibernate/boot/model/source/internal/hbm/EntityNamingSourceImpl
      52: dup
      53: aload_3
      54: aload_2
      55: aload         4
      57: invokespecial #37                 // Method org/hibernate/boot/model/source/internal/hbm/EntityNamingSourceImpl."<init>":(Ljava/lang/String;Ljava/lang/String;Ljava/lang/String;)V
      60: areturn

  private static java.util.Map<org.hibernate.EntityMode, java.lang.String> extractTuplizers(org.hibernate.boot.jaxb.hbm.spi.JaxbHbmEntityBaseDefinition);
    Code:
       0: aload_0
       1: invokevirtual #38                 // Method org/hibernate/boot/jaxb/hbm/spi/JaxbHbmEntityBaseDefinition.getTuplizer:()Ljava/util/List;
       4: ifnonnull     11
       7: invokestatic  #39                 // Method java/util/Collections.emptyMap:()Ljava/util/Map;
      10: areturn
      11: new           #40                 // class java/util/HashMap
      14: dup
      15: invokespecial #41                 // Method java/util/HashMap."<init>":()V
      18: astore_1
      19: aload_0
      20: invokevirtual #38                 // Method org/hibernate/boot/jaxb/hbm/spi/JaxbHbmEntityBaseDefinition.getTuplizer:()Ljava/util/List;
      23: invokeinterface #22,  1           // InterfaceMethod java/util/List.iterator:()Ljava/util/Iterator;
      28: astore_2
      29: aload_2
      30: invokeinterface #23,  1           // InterfaceMethod java/util/Iterator.hasNext:()Z
      35: ifeq          66
      38: aload_2
      39: invokeinterface #24,  1           // InterfaceMethod java/util/Iterator.next:()Ljava/lang/Object;
      44: checkcast     #42                 // class org/hibernate/boot/jaxb/hbm/spi/JaxbHbmTuplizerType
      47: astore_3
      48: aload_1
      49: aload_3
      50: invokevirtual #43                 // Method org/hibernate/boot/jaxb/hbm/spi/JaxbHbmTuplizerType.getEntityMode:()Lorg/hibernate/EntityMode;
      53: aload_3
      54: invokevirtual #44                 // Method org/hibernate/boot/jaxb/hbm/spi/JaxbHbmTuplizerType.getClazz:()Ljava/lang/String;
      57: invokeinterface #45,  3           // InterfaceMethod java/util/Map.put:(Ljava/lang/Object;Ljava/lang/Object;)Ljava/lang/Object;
      62: pop
      63: goto          29
      66: aload_1
      67: areturn

  private org.hibernate.boot.model.source.spi.FilterSource[] buildFilterSources();
    Code:
       0: ldc           #46                 // class org/hibernate/boot/jaxb/hbm/spi/JaxbHbmRootEntityType
       2: aload_0
       3: invokevirtual #47                 // Method jaxbEntityMapping:()Lorg/hibernate/boot/jaxb/hbm/spi/JaxbHbmEntityBaseDefinition;
       6: invokevirtual #48                 // Method java/lang/Class.isInstance:(Ljava/lang/Object;)Z
       9: ifeq          93
      12: aload_0
      13: invokevirtual #47                 // Method jaxbEntityMapping:()Lorg/hibernate/boot/jaxb/hbm/spi/JaxbHbmEntityBaseDefinition;
      16: checkcast     #46                 // class org/hibernate/boot/jaxb/hbm/spi/JaxbHbmRootEntityType
      19: astore_1
      20: aload_1
      21: invokevirtual #49                 // Method org/hibernate/boot/jaxb/hbm/spi/JaxbHbmRootEntityType.getFilter:()Ljava/util/List;
      24: invokeinterface #50,  1           // InterfaceMethod java/util/List.size:()I
      29: istore_2
      30: iload_2
      31: ifne          38
      34: getstatic     #51                 // Field NO_FILTER_SOURCES:[Lorg/hibernate/boot/model/source/spi/FilterSource;
      37: areturn
      38: iload_2
      39: anewarray     #52                 // class org/hibernate/boot/model/source/spi/FilterSource
      42: astore_3
      43: iconst_0
      44: istore        4
      46: iload         4
      48: iload_2
      49: if_icmpge     91
      52: aload_1
      53: invokevirtual #49                 // Method org/hibernate/boot/jaxb/hbm/spi/JaxbHbmRootEntityType.getFilter:()Ljava/util/List;
      56: iload         4
      58: invokeinterface #53,  2           // InterfaceMethod java/util/List.get:(I)Ljava/lang/Object;
      63: checkcast     #54                 // class org/hibernate/boot/jaxb/hbm/spi/JaxbHbmFilterType
      66: astore        5
      68: aload_3
      69: iload         4
      71: new           #55                 // class org/hibernate/boot/model/source/internal/hbm/FilterSourceImpl
      74: dup
      75: aload_0
      76: invokevirtual #56                 // Method sourceMappingDocument:()Lorg/hibernate/boot/model/source/internal/hbm/MappingDocument;
      79: aload         5
      81: invokespecial #57                 // Method org/hibernate/boot/model/source/internal/hbm/FilterSourceImpl."<init>":(Lorg/hibernate/boot/model/source/internal/hbm/MappingDocument;Lorg/hibernate/boot/jaxb/hbm/spi/JaxbHbmFilterType;)V
      84: aastore
      85: iinc          4, 1
      88: goto          46
      91: aload_3
      92: areturn
      93: getstatic     #51                 // Field NO_FILTER_SOURCES:[Lorg/hibernate/boot/model/source/spi/FilterSource;
      96: areturn

  public java.lang.String getXmlNodeName();
    Code:
       0: aload_0
       1: getfield      #7                  // Field jaxbEntityMapping:Lorg/hibernate/boot/jaxb/hbm/spi/JaxbHbmEntityBaseDefinition;
       4: invokevirtual #58                 // Method org/hibernate/boot/jaxb/hbm/spi/JaxbHbmEntityBaseDefinition.getNode:()Ljava/lang/String;
       7: areturn

  public org.hibernate.boot.model.source.spi.LocalMetadataBuildingContext getLocalMetadataBuildingContext();
    Code:
       0: aload_0
       1: invokespecial #59                 // Method org/hibernate/boot/model/source/internal/hbm/AbstractHbmSourceNode.metadataBuildingContext:()Lorg/hibernate/boot/model/source/internal/hbm/HbmLocalMetadataBuildingContext;
       4: areturn

  public java.lang.String getTypeName();
    Code:
       0: aload_0
       1: getfield      #9                  // Field entityNamingSource:Lorg/hibernate/boot/model/source/spi/EntityNamingSource;
       4: invokeinterface #60,  1           // InterfaceMethod org/hibernate/boot/model/source/spi/EntityNamingSource.getTypeName:()Ljava/lang/String;
       9: areturn

  public org.hibernate.boot.model.source.spi.AttributePath getAttributePathBase();
    Code:
       0: aload_0
       1: getfield      #12                 // Field attributePathBase:Lorg/hibernate/boot/model/source/spi/AttributePath;
       4: areturn

  public org.hibernate.boot.model.source.spi.AttributeRole getAttributeRoleBase();
    Code:
       0: aload_0
       1: getfield      #16                 // Field attributeRoleBase:Lorg/hibernate/boot/model/source/spi/AttributeRole;
       4: areturn

  public java.util.Collection<org.hibernate.boot.model.source.spi.IdentifiableTypeSource> getSubTypes();
    Code:
       0: aload_0
       1: getfield      #5                  // Field subclassEntitySources:Ljava/util/List;
       4: areturn

  public org.hibernate.boot.model.source.spi.FilterSource[] getFilterSources();
    Code:
       0: aload_0
       1: getfield      #20                 // Field filterSources:[Lorg/hibernate/boot/model/source/spi/FilterSource;
       4: areturn

  public java.lang.String inferInLineViewName();
    Code:
       0: new           #61                 // class java/lang/StringBuilder
       3: dup
       4: invokespecial #62                 // Method java/lang/StringBuilder."<init>":()V
       7: aload_0
       8: getfield      #9                  // Field entityNamingSource:Lorg/hibernate/boot/model/source/spi/EntityNamingSource;
      11: invokeinterface #14,  1           // InterfaceMethod org/hibernate/boot/model/source/spi/EntityNamingSource.getEntityName:()Ljava/lang/String;
      16: invokevirtual #63                 // Method java/lang/StringBuilder.append:(Ljava/lang/String;)Ljava/lang/StringBuilder;
      19: bipush        35
      21: invokevirtual #64                 // Method java/lang/StringBuilder.append:(C)Ljava/lang/StringBuilder;
      24: aload_0
      25: dup
      26: getfield      #6                  // Field inLineViewCount:I
      29: iconst_1
      30: iadd
      31: dup_x1
      32: putfield      #6                  // Field inLineViewCount:I
      35: invokevirtual #65                 // Method java/lang/StringBuilder.append:(I)Ljava/lang/StringBuilder;
      38: invokevirtual #66                 // Method java/lang/StringBuilder.toString:()Ljava/lang/String;
      41: areturn

  protected void afterInstantiation();
    Code:
       0: aload_0
       1: aload_0
       2: invokevirtual #67                 // Method buildAttributeSources:()Ljava/util/List;
       5: putfield      #1                  // Field attributeSources:Ljava/util/List;
       8: aload_0
       9: aload_0
      10: invokespecial #68                 // Method buildSecondaryTableMap:()Ljava/util/Map;
      13: putfield      #69                 // Field secondaryTableMap:Ljava/util/Map;
      16: return

  protected java.util.List<org.hibernate.boot.model.source.spi.AttributeSource> buildAttributeSources();
    Code:
       0: new           #3                  // class java/util/ArrayList
       3: dup
       4: invokespecial #4                  // Method java/util/ArrayList."<init>":()V
       7: astore_1
       8: new           #70                 // class org/hibernate/boot/model/source/internal/hbm/AbstractEntitySourceImpl$1
      11: dup
      12: aload_0
      13: aload_1
      14: invokespecial #71                 // Method org/hibernate/boot/model/source/internal/hbm/AbstractEntitySourceImpl$1."<init>":(Lorg/hibernate/boot/model/source/internal/hbm/AbstractEntitySourceImpl;Ljava/util/List;)V
      17: astore_2
      18: aload_0
      19: aload_2
      20: invokevirtual #72                 // Method buildAttributeSources:(Lorg/hibernate/boot/model/source/internal/hbm/AttributesHelper$Callback;)V
      23: aload_1
      24: areturn

  protected void buildAttributeSources(org.hibernate.boot.model.source.internal.hbm.AttributesHelper$Callback);
    Code:
       0: aload_0
       1: invokevirtual #56                 // Method sourceMappingDocument:()Lorg/hibernate/boot/model/source/internal/hbm/MappingDocument;
       4: aload_1
       5: aload_0
       6: getfield      #7                  // Field jaxbEntityMapping:Lorg/hibernate/boot/jaxb/hbm/spi/JaxbHbmEntityBaseDefinition;
       9: invokevirtual #73                 // Method org/hibernate/boot/jaxb/hbm/spi/JaxbHbmEntityBaseDefinition.getAttributes:()Ljava/util/List;
      12: aconst_null
      13: getstatic     #74                 // Field org/hibernate/boot/model/source/spi/NaturalIdMutability.NOT_NATURAL_ID:Lorg/hibernate/boot/model/source/spi/NaturalIdMutability;
      16: invokestatic  #75                 // Method org/hibernate/boot/model/source/internal/hbm/AttributesHelper.processAttributes:(Lorg/hibernate/boot/model/source/internal/hbm/MappingDocument;Lorg/hibernate/boot/model/source/internal/hbm/AttributesHelper$Callback;Ljava/util/List;Ljava/lang/String;Lorg/hibernate/boot/model/source/spi/NaturalIdMutability;)V
      19: return

  private java.util.Map<java.lang.String, org.hibernate.boot.model.source.spi.SecondaryTableSource> buildSecondaryTableMap();
    Code:
       0: ldc           #76                 // class org/hibernate/boot/jaxb/hbm/spi/SecondaryTableContainer
       2: aload_0
       3: getfield      #7                  // Field jaxbEntityMapping:Lorg/hibernate/boot/jaxb/hbm/spi/JaxbHbmEntityBaseDefinition;
       6: invokevirtual #48                 // Method java/lang/Class.isInstance:(Ljava/lang/Object;)Z
       9: ifne          16
      12: invokestatic  #39                 // Method java/util/Collections.emptyMap:()Ljava/util/Map;
      15: areturn
      16: new           #40                 // class java/util/HashMap
      19: dup
      20: invokespecial #41                 // Method java/util/HashMap."<init>":()V
      23: astore_1
      24: aload_0
      25: getfield      #7                  // Field jaxbEntityMapping:Lorg/hibernate/boot/jaxb/hbm/spi/JaxbHbmEntityBaseDefinition;
      28: checkcast     #76                 // class org/hibernate/boot/jaxb/hbm/spi/SecondaryTableContainer
      31: invokeinterface #77,  1           // InterfaceMethod org/hibernate/boot/jaxb/hbm/spi/SecondaryTableContainer.getJoin:()Ljava/util/List;
      36: invokeinterface #22,  1           // InterfaceMethod java/util/List.iterator:()Ljava/util/Iterator;
      41: astore_2
      42: aload_2
      43: invokeinterface #23,  1           // InterfaceMethod java/util/Iterator.hasNext:()Z
      48: ifeq          123
      51: aload_2
      52: invokeinterface #24,  1           // InterfaceMethod java/util/Iterator.next:()Ljava/lang/Object;
      57: checkcast     #78                 // class org/hibernate/boot/jaxb/hbm/spi/JaxbHbmSecondaryTableType
      60: astore_3
      61: new           #79                 // class org/hibernate/boot/model/source/internal/hbm/SecondaryTableSourceImpl
      64: dup
      65: aload_0
      66: invokevirtual #56                 // Method sourceMappingDocument:()Lorg/hibernate/boot/model/source/internal/hbm/MappingDocument;
      69: aload_3
      70: aload_0
      71: invokevirtual #80                 // Method getEntityNamingSource:()Lorg/hibernate/boot/model/source/spi/EntityNamingSource;
      74: aload_0
      75: invokespecial #81                 // Method org/hibernate/boot/model/source/internal/hbm/SecondaryTableSourceImpl."<init>":(Lorg/hibernate/boot/model/source/internal/hbm/MappingDocument;Lorg/hibernate/boot/jaxb/hbm/spi/JaxbHbmSecondaryTableType;Lorg/hibernate/boot/model/source/spi/EntityNamingSource;Lorg/hibernate/boot/model/source/internal/hbm/Helper$InLineViewNameInferrer;)V
      78: astore        4
      80: aload         4
      82: invokevirtual #82                 // Method org/hibernate/boot/model/source/internal/hbm/SecondaryTableSourceImpl.getLogicalTableNameForContainedColumns:()Ljava/lang/String;
      85: astore        5
      87: aload_1
      88: aload         5
      90: aload         4
      92: invokevirtual #83                 // Method java/util/HashMap.put:(Ljava/lang/Object;Ljava/lang/Object;)Ljava/lang/Object;
      95: pop
      96: aload_0
      97: invokevirtual #56                 // Method sourceMappingDocument:()Lorg/hibernate/boot/model/source/internal/hbm/MappingDocument;
     100: new           #84                 // class org/hibernate/boot/model/source/internal/hbm/AbstractEntitySourceImpl$2
     103: dup
     104: aload_0
     105: invokespecial #85                 // Method org/hibernate/boot/model/source/internal/hbm/AbstractEntitySourceImpl$2."<init>":(Lorg/hibernate/boot/model/source/internal/hbm/AbstractEntitySourceImpl;)V
     108: aload_3
     109: invokevirtual #86                 // Method org/hibernate/boot/jaxb/hbm/spi/JaxbHbmSecondaryTableType.getAttributes:()Ljava/util/List;
     112: aload         5
     114: getstatic     #74                 // Field org/hibernate/boot/model/source/spi/NaturalIdMutability.NOT_NATURAL_ID:Lorg/hibernate/boot/model/source/spi/NaturalIdMutability;
     117: invokestatic  #75                 // Method org/hibernate/boot/model/source/internal/hbm/AttributesHelper.processAttributes:(Lorg/hibernate/boot/model/source/internal/hbm/MappingDocument;Lorg/hibernate/boot/model/source/internal/hbm/AttributesHelper$Callback;Ljava/util/List;Ljava/lang/String;Lorg/hibernate/boot/model/source/spi/NaturalIdMutability;)V
     120: goto          42
     123: aload_1
     124: areturn

  protected org.hibernate.boot.jaxb.hbm.spi.JaxbHbmEntityBaseDefinition jaxbEntityMapping();
    Code:
       0: aload_0
       1: getfield      #7                  // Field jaxbEntityMapping:Lorg/hibernate/boot/jaxb/hbm/spi/JaxbHbmEntityBaseDefinition;
       4: areturn

  public org.hibernate.boot.jaxb.Origin getOrigin();
    Code:
       0: aload_0
       1: invokevirtual #87                 // Method origin:()Lorg/hibernate/boot/jaxb/Origin;
       4: areturn

  public org.hibernate.boot.model.source.spi.EntityNamingSource getEntityNamingSource();
    Code:
       0: aload_0
       1: getfield      #9                  // Field entityNamingSource:Lorg/hibernate/boot/model/source/spi/EntityNamingSource;
       4: areturn

  public java.lang.Boolean isAbstract();
    Code:
       0: aload_0
       1: invokevirtual #47                 // Method jaxbEntityMapping:()Lorg/hibernate/boot/jaxb/hbm/spi/JaxbHbmEntityBaseDefinition;
       4: invokevirtual #88                 // Method org/hibernate/boot/jaxb/hbm/spi/JaxbHbmEntityBaseDefinition.isAbstract:()Ljava/lang/Boolean;
       7: areturn

  public boolean isLazy();
    Code:
       0: aload_0
       1: getfield      #7                  // Field jaxbEntityMapping:Lorg/hibernate/boot/jaxb/hbm/spi/JaxbHbmEntityBaseDefinition;
       4: invokevirtual #89                 // Method org/hibernate/boot/jaxb/hbm/spi/JaxbHbmEntityBaseDefinition.isLazy:()Ljava/lang/Boolean;
       7: ifnonnull     25
      10: aload_0
      11: invokevirtual #90                 // Method metadataBuildingContext:()Lorg/hibernate/boot/model/source/internal/hbm/HbmLocalMetadataBuildingContext;
      14: invokeinterface #91,  1           // InterfaceMethod org/hibernate/boot/model/source/internal/hbm/HbmLocalMetadataBuildingContext.getMappingDefaults:()Lorg/hibernate/boot/spi/MappingDefaults;
      19: invokeinterface #92,  1           // InterfaceMethod org/hibernate/boot/spi/MappingDefaults.areEntitiesImplicitlyLazy:()Z
      24: ireturn
      25: aload_0
      26: invokevirtual #47                 // Method jaxbEntityMapping:()Lorg/hibernate/boot/jaxb/hbm/spi/JaxbHbmEntityBaseDefinition;
      29: invokevirtual #89                 // Method org/hibernate/boot/jaxb/hbm/spi/JaxbHbmEntityBaseDefinition.isLazy:()Ljava/lang/Boolean;
      32: invokevirtual #93                 // Method java/lang/Boolean.booleanValue:()Z
      35: ireturn

  public java.lang.String getProxy();
    Code:
       0: aload_0
       1: getfield      #7                  // Field jaxbEntityMapping:Lorg/hibernate/boot/jaxb/hbm/spi/JaxbHbmEntityBaseDefinition;
       4: invokevirtual #94                 // Method org/hibernate/boot/jaxb/hbm/spi/JaxbHbmEntityBaseDefinition.getProxy:()Ljava/lang/String;
       7: areturn

  public int getBatchSize();
    Code:
       0: aload_0
       1: getfield      #7                  // Field jaxbEntityMapping:Lorg/hibernate/boot/jaxb/hbm/spi/JaxbHbmEntityBaseDefinition;
       4: invokevirtual #95                 // Method org/hibernate/boot/jaxb/hbm/spi/JaxbHbmEntityBaseDefinition.getBatchSize:()I
       7: ireturn

  public boolean isDynamicInsert();
    Code:
       0: aload_0
       1: getfield      #7                  // Field jaxbEntityMapping:Lorg/hibernate/boot/jaxb/hbm/spi/JaxbHbmEntityBaseDefinition;
       4: invokevirtual #96                 // Method org/hibernate/boot/jaxb/hbm/spi/JaxbHbmEntityBaseDefinition.isDynamicInsert:()Z
       7: ireturn

  public boolean isDynamicUpdate();
    Code:
       0: aload_0
       1: getfield      #7                  // Field jaxbEntityMapping:Lorg/hibernate/boot/jaxb/hbm/spi/JaxbHbmEntityBaseDefinition;
       4: invokevirtual #97                 // Method org/hibernate/boot/jaxb/hbm/spi/JaxbHbmEntityBaseDefinition.isDynamicUpdate:()Z
       7: ireturn

  public boolean isSelectBeforeUpdate();
    Code:
       0: aload_0
       1: getfield      #7                  // Field jaxbEntityMapping:Lorg/hibernate/boot/jaxb/hbm/spi/JaxbHbmEntityBaseDefinition;
       4: invokevirtual #98                 // Method org/hibernate/boot/jaxb/hbm/spi/JaxbHbmEntityBaseDefinition.isSelectBeforeUpdate:()Z
       7: ireturn

  protected org.hibernate.EntityMode determineEntityMode();
    Code:
       0: aload_0
       1: getfield      #9                  // Field entityNamingSource:Lorg/hibernate/boot/model/source/spi/EntityNamingSource;
       4: invokeinterface #26,  1           // InterfaceMethod org/hibernate/boot/model/source/spi/EntityNamingSource.getClassName:()Ljava/lang/String;
       9: invokestatic  #34                 // Method org/hibernate/internal/util/StringHelper.isNotEmpty:(Ljava/lang/String;)Z
      12: ifeq          21
      15: getstatic     #99                 // Field org/hibernate/EntityMode.POJO:Lorg/hibernate/EntityMode;
      18: goto          24
      21: getstatic     #100                // Field org/hibernate/EntityMode.MAP:Lorg/hibernate/EntityMode;
      24: areturn

  public java.util.Map<org.hibernate.EntityMode, java.lang.String> getTuplizerClassMap();
    Code:
       0: aload_0
       1: getfield      #18                 // Field tuplizerClassMap:Ljava/util/Map;
       4: areturn

  public java.lang.String getCustomPersisterClassName();
    Code:
       0: aload_0
       1: invokevirtual #90                 // Method metadataBuildingContext:()Lorg/hibernate/boot/model/source/internal/hbm/HbmLocalMetadataBuildingContext;
       4: aload_0
       5: getfield      #7                  // Field jaxbEntityMapping:Lorg/hibernate/boot/jaxb/hbm/spi/JaxbHbmEntityBaseDefinition;
       8: invokevirtual #101                // Method org/hibernate/boot/jaxb/hbm/spi/JaxbHbmEntityBaseDefinition.getPersister:()Ljava/lang/String;
      11: invokeinterface #102,  2          // InterfaceMethod org/hibernate/boot/model/source/internal/hbm/HbmLocalMetadataBuildingContext.qualifyClassName:(Ljava/lang/String;)Ljava/lang/String;
      16: areturn

  public java.lang.String getCustomLoaderName();
    Code:
       0: aload_0
       1: getfield      #7                  // Field jaxbEntityMapping:Lorg/hibernate/boot/jaxb/hbm/spi/JaxbHbmEntityBaseDefinition;
       4: invokevirtual #103                // Method org/hibernate/boot/jaxb/hbm/spi/JaxbHbmEntityBaseDefinition.getLoader:()Lorg/hibernate/boot/jaxb/hbm/spi/JaxbHbmLoaderType;
       7: ifnull        23
      10: aload_0
      11: getfield      #7                  // Field jaxbEntityMapping:Lorg/hibernate/boot/jaxb/hbm/spi/JaxbHbmEntityBaseDefinition;
      14: invokevirtual #103                // Method org/hibernate/boot/jaxb/hbm/spi/JaxbHbmEntityBaseDefinition.getLoader:()Lorg/hibernate/boot/jaxb/hbm/spi/JaxbHbmLoaderType;
      17: invokevirtual #104                // Method org/hibernate/boot/jaxb/hbm/spi/JaxbHbmLoaderType.getQueryRef:()Ljava/lang/String;
      20: goto          24
      23: aconst_null
      24: areturn

  public org.hibernate.boot.model.CustomSql getCustomSqlInsert();
    Code:
       0: aload_0
       1: getfield      #7                  // Field jaxbEntityMapping:Lorg/hibernate/boot/jaxb/hbm/spi/JaxbHbmEntityBaseDefinition;
       4: invokevirtual #105                // Method org/hibernate/boot/jaxb/hbm/spi/JaxbHbmEntityBaseDefinition.getSqlInsert:()Lorg/hibernate/boot/jaxb/hbm/spi/JaxbHbmCustomSqlDmlType;
       7: invokestatic  #106                // Method org/hibernate/boot/model/source/internal/hbm/Helper.buildCustomSql:(Lorg/hibernate/boot/jaxb/hbm/spi/JaxbHbmCustomSqlDmlType;)Lorg/hibernate/boot/model/CustomSql;
      10: areturn

  public org.hibernate.boot.model.CustomSql getCustomSqlUpdate();
    Code:
       0: aload_0
       1: getfield      #7                  // Field jaxbEntityMapping:Lorg/hibernate/boot/jaxb/hbm/spi/JaxbHbmEntityBaseDefinition;
       4: invokevirtual #107                // Method org/hibernate/boot/jaxb/hbm/spi/JaxbHbmEntityBaseDefinition.getSqlUpdate:()Lorg/hibernate/boot/jaxb/hbm/spi/JaxbHbmCustomSqlDmlType;
       7: invokestatic  #106                // Method org/hibernate/boot/model/source/internal/hbm/Helper.buildCustomSql:(Lorg/hibernate/boot/jaxb/hbm/spi/JaxbHbmCustomSqlDmlType;)Lorg/hibernate/boot/model/CustomSql;
      10: areturn

  public org.hibernate.boot.model.CustomSql getCustomSqlDelete();
    Code:
       0: aload_0
       1: getfield      #7                  // Field jaxbEntityMapping:Lorg/hibernate/boot/jaxb/hbm/spi/JaxbHbmEntityBaseDefinition;
       4: invokevirtual #108                // Method org/hibernate/boot/jaxb/hbm/spi/JaxbHbmEntityBaseDefinition.getSqlDelete:()Lorg/hibernate/boot/jaxb/hbm/spi/JaxbHbmCustomSqlDmlType;
       7: invokestatic  #106                // Method org/hibernate/boot/model/source/internal/hbm/Helper.buildCustomSql:(Lorg/hibernate/boot/jaxb/hbm/spi/JaxbHbmCustomSqlDmlType;)Lorg/hibernate/boot/model/CustomSql;
      10: areturn

  public java.lang.String[] getSynchronizedTableNames();
    Code:
       0: aload_0
       1: getfield      #7                  // Field jaxbEntityMapping:Lorg/hibernate/boot/jaxb/hbm/spi/JaxbHbmEntityBaseDefinition;
       4: invokevirtual #109                // Method org/hibernate/boot/jaxb/hbm/spi/JaxbHbmEntityBaseDefinition.getSynchronize:()Ljava/util/List;
       7: invokestatic  #110                // Method org/hibernate/internal/util/collections/CollectionHelper.isEmpty:(Ljava/util/Collection;)Z
      10: ifeq          17
      13: getstatic     #111                // Field org/hibernate/internal/util/StringHelper.EMPTY_STRINGS:[Ljava/lang/String;
      16: areturn
      17: aload_0
      18: getfield      #7                  // Field jaxbEntityMapping:Lorg/hibernate/boot/jaxb/hbm/spi/JaxbHbmEntityBaseDefinition;
      21: invokevirtual #109                // Method org/hibernate/boot/jaxb/hbm/spi/JaxbHbmEntityBaseDefinition.getSynchronize:()Ljava/util/List;
      24: invokeinterface #50,  1           // InterfaceMethod java/util/List.size:()I
      29: istore_1
      30: iload_1
      31: anewarray     #112                // class java/lang/String
      34: astore_2
      35: iconst_0
      36: istore_3
      37: iload_3
      38: iload_1
      39: if_icmpge     70
      42: aload_2
      43: iload_3
      44: aload_0
      45: getfield      #7                  // Field jaxbEntityMapping:Lorg/hibernate/boot/jaxb/hbm/spi/JaxbHbmEntityBaseDefinition;
      48: invokevirtual #109                // Method org/hibernate/boot/jaxb/hbm/spi/JaxbHbmEntityBaseDefinition.getSynchronize:()Ljava/util/List;
      51: iload_3
      52: invokeinterface #53,  2           // InterfaceMethod java/util/List.get:(I)Ljava/lang/Object;
      57: checkcast     #113                // class org/hibernate/boot/jaxb/hbm/spi/JaxbHbmSynchronizeType
      60: invokevirtual #114                // Method org/hibernate/boot/jaxb/hbm/spi/JaxbHbmSynchronizeType.getTable:()Ljava/lang/String;
      63: aastore
      64: iinc          3, 1
      67: goto          37
      70: aload_2
      71: areturn

  public org.hibernate.boot.model.source.spi.ToolingHintContext getToolingHintContext();
    Code:
       0: aload_0
       1: getfield      #30                 // Field toolingHintContext:Lorg/hibernate/boot/model/source/spi/ToolingHintContext;
       4: areturn

  public java.util.List<org.hibernate.boot.model.source.spi.AttributeSource> attributeSources();
    Code:
       0: aload_0
       1: getfield      #1                  // Field attributeSources:Ljava/util/List;
       4: areturn

  public void injectHierarchy(org.hibernate.boot.model.source.internal.hbm.EntityHierarchySourceImpl);
    Code:
       0: aload_0
       1: aload_1
       2: putfield      #115                // Field entityHierarchy:Lorg/hibernate/boot/model/source/internal/hbm/EntityHierarchySourceImpl;
       5: return

  public org.hibernate.boot.model.source.spi.EntityHierarchySource getHierarchy();
    Code:
       0: aload_0
       1: getfield      #115                // Field entityHierarchy:Lorg/hibernate/boot/model/source/internal/hbm/EntityHierarchySourceImpl;
       4: areturn

  void add(org.hibernate.boot.model.source.spi.SubclassEntitySource);
    Code:
       0: aload_0
       1: aload_1
       2: checkcast     #116                // class org/hibernate/boot/model/source/internal/hbm/SubclassEntitySourceImpl
       5: invokevirtual #117                // Method add:(Lorg/hibernate/boot/model/source/internal/hbm/SubclassEntitySourceImpl;)V
       8: return

  void add(org.hibernate.boot.model.source.internal.hbm.SubclassEntitySourceImpl);
    Code:
       0: aload_1
       1: aload_0
       2: getfield      #115                // Field entityHierarchy:Lorg/hibernate/boot/model/source/internal/hbm/EntityHierarchySourceImpl;
       5: invokevirtual #118                // Method org/hibernate/boot/model/source/internal/hbm/SubclassEntitySourceImpl.injectHierarchy:(Lorg/hibernate/boot/model/source/internal/hbm/EntityHierarchySourceImpl;)V
       8: aload_0
       9: getfield      #115                // Field entityHierarchy:Lorg/hibernate/boot/model/source/internal/hbm/EntityHierarchySourceImpl;
      12: aload_1
      13: invokevirtual #119                // Method org/hibernate/boot/model/source/internal/hbm/EntityHierarchySourceImpl.processSubclass:(Lorg/hibernate/boot/model/source/internal/hbm/SubclassEntitySourceImpl;)V
      16: aload_0
      17: getfield      #5                  // Field subclassEntitySources:Ljava/util/List;
      20: aload_1
      21: invokeinterface #120,  2          // InterfaceMethod java/util/List.add:(Ljava/lang/Object;)Z
      26: pop
      27: return

  public java.util.Map<java.lang.String, org.hibernate.boot.model.source.spi.SecondaryTableSource> getSecondaryTableMap();
    Code:
       0: aload_0
       1: getfield      #69                 // Field secondaryTableMap:Ljava/util/Map;
       4: areturn

  public java.util.List<org.hibernate.boot.model.source.spi.JpaCallbackSource> getJpaCallbackClasses();
    Code:
       0: invokestatic  #121                // Method java/util/Collections.emptyList:()Ljava/util/List;
       3: areturn

  public java.util.List<org.hibernate.boot.jaxb.hbm.spi.JaxbHbmNamedQueryType> getNamedQueries();
    Code:
       0: aload_0
       1: getfield      #7                  // Field jaxbEntityMapping:Lorg/hibernate/boot/jaxb/hbm/spi/JaxbHbmEntityBaseDefinition;
       4: invokevirtual #122                // Method org/hibernate/boot/jaxb/hbm/spi/JaxbHbmEntityBaseDefinition.getQuery:()Ljava/util/List;
       7: areturn

  public java.util.List<org.hibernate.boot.jaxb.hbm.spi.JaxbHbmNamedNativeQueryType> getNamedNativeQueries();
    Code:
       0: aload_0
       1: getfield      #7                  // Field jaxbEntityMapping:Lorg/hibernate/boot/jaxb/hbm/spi/JaxbHbmEntityBaseDefinition;
       4: invokevirtual #123                // Method org/hibernate/boot/jaxb/hbm/spi/JaxbHbmEntityBaseDefinition.getSqlQuery:()Ljava/util/List;
       7: areturn

  public org.hibernate.boot.model.TruthValue quoteIdentifiersLocalToEntity();
    Code:
       0: getstatic     #124                // Field org/hibernate/boot/model/TruthValue.UNKNOWN:Lorg/hibernate/boot/model/TruthValue;
       3: areturn

  static java.util.List access$000(org.hibernate.boot.model.source.internal.hbm.AbstractEntitySourceImpl);
    Code:
       0: aload_0
       1: getfield      #1                  // Field attributeSources:Ljava/util/List;
       4: areturn

  static {};
    Code:
       0: iconst_0
       1: anewarray     #52                 // class org/hibernate/boot/model/source/spi/FilterSource
       4: putstatic     #51                 // Field NO_FILTER_SOURCES:[Lorg/hibernate/boot/model/source/spi/FilterSource;
       7: return
}
