Compiled from "EntityHierarchySourceImpl.java"
public class org.hibernate.boot.model.source.internal.hbm.EntityHierarchySourceImpl implements org.hibernate.boot.model.source.spi.EntityHierarchySource {
  private final org.hibernate.boot.model.source.internal.hbm.RootEntitySourceImpl rootEntitySource;

  private final org.hibernate.boot.model.source.spi.IdentifierSource identifierSource;

  private final org.hibernate.boot.model.source.spi.VersionAttributeSource versionAttributeSource;

  private final org.hibernate.boot.model.source.spi.DiscriminatorSource discriminatorSource;

  private final org.hibernate.boot.model.source.spi.MultiTenancySource multiTenancySource;

  private final org.hibernate.boot.model.Caching caching;

  private final org.hibernate.boot.model.Caching naturalIdCaching;

  private org.hibernate.boot.model.source.spi.InheritanceType hierarchyInheritanceType;

  private java.util.Set<java.lang.String> collectedEntityNames;

  public org.hibernate.boot.model.source.internal.hbm.EntityHierarchySourceImpl(org.hibernate.boot.model.source.internal.hbm.RootEntitySourceImpl);
    Code:
       0: aload_0
       1: invokespecial #1                  // Method java/lang/Object."<init>":()V
       4: aload_0
       5: getstatic     #2                  // Field org/hibernate/boot/model/source/spi/InheritanceType.NO_INHERITANCE:Lorg/hibernate/boot/model/source/spi/InheritanceType;
       8: putfield      #3                  // Field hierarchyInheritanceType:Lorg/hibernate/boot/model/source/spi/InheritanceType;
      11: aload_0
      12: new           #4                  // class java/util/HashSet
      15: dup
      16: invokespecial #5                  // Method java/util/HashSet."<init>":()V
      19: putfield      #6                  // Field collectedEntityNames:Ljava/util/Set;
      22: aload_0
      23: aload_1
      24: putfield      #7                  // Field rootEntitySource:Lorg/hibernate/boot/model/source/internal/hbm/RootEntitySourceImpl;
      27: aload_0
      28: getfield      #7                  // Field rootEntitySource:Lorg/hibernate/boot/model/source/internal/hbm/RootEntitySourceImpl;
      31: aload_0
      32: invokevirtual #8                  // Method org/hibernate/boot/model/source/internal/hbm/RootEntitySourceImpl.injectHierarchy:(Lorg/hibernate/boot/model/source/internal/hbm/EntityHierarchySourceImpl;)V
      35: aload_0
      36: aload_1
      37: invokestatic  #9                  // Method interpretIdentifierSource:(Lorg/hibernate/boot/model/source/internal/hbm/RootEntitySourceImpl;)Lorg/hibernate/boot/model/source/spi/IdentifierSource;
      40: putfield      #10                 // Field identifierSource:Lorg/hibernate/boot/model/source/spi/IdentifierSource;
      43: aload_0
      44: aload_1
      45: invokestatic  #11                 // Method interpretVersionSource:(Lorg/hibernate/boot/model/source/internal/hbm/RootEntitySourceImpl;)Lorg/hibernate/boot/model/source/spi/VersionAttributeSource;
      48: putfield      #12                 // Field versionAttributeSource:Lorg/hibernate/boot/model/source/spi/VersionAttributeSource;
      51: aload_0
      52: aload_1
      53: invokestatic  #13                 // Method interpretDiscriminatorSource:(Lorg/hibernate/boot/model/source/internal/hbm/RootEntitySourceImpl;)Lorg/hibernate/boot/model/source/spi/DiscriminatorSource;
      56: putfield      #14                 // Field discriminatorSource:Lorg/hibernate/boot/model/source/spi/DiscriminatorSource;
      59: aload_0
      60: aload_1
      61: invokestatic  #15                 // Method interpretMultiTenancySource:(Lorg/hibernate/boot/model/source/internal/hbm/RootEntitySourceImpl;)Lorg/hibernate/boot/model/source/spi/MultiTenancySource;
      64: putfield      #16                 // Field multiTenancySource:Lorg/hibernate/boot/model/source/spi/MultiTenancySource;
      67: aload_0
      68: aload_0
      69: invokevirtual #17                 // Method entityElement:()Lorg/hibernate/boot/jaxb/hbm/spi/JaxbHbmRootEntityType;
      72: invokevirtual #18                 // Method org/hibernate/boot/jaxb/hbm/spi/JaxbHbmRootEntityType.getCache:()Lorg/hibernate/boot/jaxb/hbm/spi/JaxbHbmCacheType;
      75: invokestatic  #19                 // Method org/hibernate/boot/model/source/internal/hbm/Helper.createCaching:(Lorg/hibernate/boot/jaxb/hbm/spi/JaxbHbmCacheType;)Lorg/hibernate/boot/model/Caching;
      78: putfield      #20                 // Field caching:Lorg/hibernate/boot/model/Caching;
      81: aload_0
      82: aload_1
      83: invokevirtual #21                 // Method org/hibernate/boot/model/source/internal/hbm/RootEntitySourceImpl.jaxbEntityMapping:()Lorg/hibernate/boot/jaxb/hbm/spi/JaxbHbmRootEntityType;
      86: invokevirtual #22                 // Method org/hibernate/boot/jaxb/hbm/spi/JaxbHbmRootEntityType.getNaturalIdCache:()Lorg/hibernate/boot/jaxb/hbm/spi/JaxbHbmNaturalIdCacheType;
      89: invokestatic  #23                 // Method org/hibernate/boot/model/source/internal/hbm/Helper.createNaturalIdCaching:(Lorg/hibernate/boot/jaxb/hbm/spi/JaxbHbmNaturalIdCacheType;)Lorg/hibernate/boot/model/Caching;
      92: putfield      #24                 // Field naturalIdCaching:Lorg/hibernate/boot/model/Caching;
      95: aload_0
      96: getfield      #6                  // Field collectedEntityNames:Ljava/util/Set;
      99: aload_1
     100: invokevirtual #25                 // Method org/hibernate/boot/model/source/internal/hbm/RootEntitySourceImpl.getEntityNamingSource:()Lorg/hibernate/boot/model/source/spi/EntityNamingSource;
     103: invokeinterface #26,  1           // InterfaceMethod org/hibernate/boot/model/source/spi/EntityNamingSource.getEntityName:()Ljava/lang/String;
     108: invokeinterface #27,  2           // InterfaceMethod java/util/Set.add:(Ljava/lang/Object;)Z
     113: pop
     114: return

  private static org.hibernate.boot.model.source.spi.IdentifierSource interpretIdentifierSource(org.hibernate.boot.model.source.internal.hbm.RootEntitySourceImpl);
    Code:
       0: aload_0
       1: invokevirtual #21                 // Method org/hibernate/boot/model/source/internal/hbm/RootEntitySourceImpl.jaxbEntityMapping:()Lorg/hibernate/boot/jaxb/hbm/spi/JaxbHbmRootEntityType;
       4: invokevirtual #28                 // Method org/hibernate/boot/jaxb/hbm/spi/JaxbHbmRootEntityType.getId:()Lorg/hibernate/boot/jaxb/hbm/spi/JaxbHbmSimpleIdType;
       7: ifnonnull     56
      10: aload_0
      11: invokevirtual #21                 // Method org/hibernate/boot/model/source/internal/hbm/RootEntitySourceImpl.jaxbEntityMapping:()Lorg/hibernate/boot/jaxb/hbm/spi/JaxbHbmRootEntityType;
      14: invokevirtual #29                 // Method org/hibernate/boot/jaxb/hbm/spi/JaxbHbmRootEntityType.getCompositeId:()Lorg/hibernate/boot/jaxb/hbm/spi/JaxbHbmCompositeIdType;
      17: ifnonnull     56
      20: new           #30                 // class org/hibernate/boot/MappingException
      23: dup
      24: getstatic     #31                 // Field java/util/Locale.ENGLISH:Ljava/util/Locale;
      27: ldc           #32                 // String Entity [%s] did not define an identifier
      29: iconst_1
      30: anewarray     #33                 // class java/lang/Object
      33: dup
      34: iconst_0
      35: aload_0
      36: invokevirtual #25                 // Method org/hibernate/boot/model/source/internal/hbm/RootEntitySourceImpl.getEntityNamingSource:()Lorg/hibernate/boot/model/source/spi/EntityNamingSource;
      39: invokeinterface #26,  1           // InterfaceMethod org/hibernate/boot/model/source/spi/EntityNamingSource.getEntityName:()Ljava/lang/String;
      44: aastore
      45: invokestatic  #34                 // Method java/lang/String.format:(Ljava/util/Locale;Ljava/lang/String;[Ljava/lang/Object;)Ljava/lang/String;
      48: aload_0
      49: invokevirtual #35                 // Method org/hibernate/boot/model/source/internal/hbm/RootEntitySourceImpl.origin:()Lorg/hibernate/boot/jaxb/Origin;
      52: invokespecial #36                 // Method org/hibernate/boot/MappingException."<init>":(Ljava/lang/String;Lorg/hibernate/boot/jaxb/Origin;)V
      55: athrow
      56: aload_0
      57: invokevirtual #21                 // Method org/hibernate/boot/model/source/internal/hbm/RootEntitySourceImpl.jaxbEntityMapping:()Lorg/hibernate/boot/jaxb/hbm/spi/JaxbHbmRootEntityType;
      60: invokevirtual #28                 // Method org/hibernate/boot/jaxb/hbm/spi/JaxbHbmRootEntityType.getId:()Lorg/hibernate/boot/jaxb/hbm/spi/JaxbHbmSimpleIdType;
      63: ifnull        75
      66: new           #37                 // class org/hibernate/boot/model/source/internal/hbm/IdentifierSourceSimpleImpl
      69: dup
      70: aload_0
      71: invokespecial #38                 // Method org/hibernate/boot/model/source/internal/hbm/IdentifierSourceSimpleImpl."<init>":(Lorg/hibernate/boot/model/source/internal/hbm/RootEntitySourceImpl;)V
      74: areturn
      75: aload_0
      76: invokevirtual #21                 // Method org/hibernate/boot/model/source/internal/hbm/RootEntitySourceImpl.jaxbEntityMapping:()Lorg/hibernate/boot/jaxb/hbm/spi/JaxbHbmRootEntityType;
      79: invokevirtual #29                 // Method org/hibernate/boot/jaxb/hbm/spi/JaxbHbmRootEntityType.getCompositeId:()Lorg/hibernate/boot/jaxb/hbm/spi/JaxbHbmCompositeIdType;
      82: invokevirtual #39                 // Method org/hibernate/boot/jaxb/hbm/spi/JaxbHbmCompositeIdType.getName:()Ljava/lang/String;
      85: invokestatic  #40                 // Method org/hibernate/internal/util/StringHelper.isEmpty:(Ljava/lang/String;)Z
      88: ifeq          143
      91: aload_0
      92: invokevirtual #21                 // Method org/hibernate/boot/model/source/internal/hbm/RootEntitySourceImpl.jaxbEntityMapping:()Lorg/hibernate/boot/jaxb/hbm/spi/JaxbHbmRootEntityType;
      95: invokevirtual #29                 // Method org/hibernate/boot/jaxb/hbm/spi/JaxbHbmRootEntityType.getCompositeId:()Lorg/hibernate/boot/jaxb/hbm/spi/JaxbHbmCompositeIdType;
      98: invokevirtual #41                 // Method org/hibernate/boot/jaxb/hbm/spi/JaxbHbmCompositeIdType.isMapped:()Z
     101: ifeq          134
     104: aload_0
     105: invokevirtual #21                 // Method org/hibernate/boot/model/source/internal/hbm/RootEntitySourceImpl.jaxbEntityMapping:()Lorg/hibernate/boot/jaxb/hbm/spi/JaxbHbmRootEntityType;
     108: invokevirtual #29                 // Method org/hibernate/boot/jaxb/hbm/spi/JaxbHbmRootEntityType.getCompositeId:()Lorg/hibernate/boot/jaxb/hbm/spi/JaxbHbmCompositeIdType;
     111: invokevirtual #42                 // Method org/hibernate/boot/jaxb/hbm/spi/JaxbHbmCompositeIdType.getClazz:()Ljava/lang/String;
     114: invokestatic  #40                 // Method org/hibernate/internal/util/StringHelper.isEmpty:(Ljava/lang/String;)Z
     117: ifeq          134
     120: new           #30                 // class org/hibernate/boot/MappingException
     123: dup
     124: ldc           #43                 // String mapped composite identifier must name component class to use.
     126: aload_0
     127: invokevirtual #35                 // Method org/hibernate/boot/model/source/internal/hbm/RootEntitySourceImpl.origin:()Lorg/hibernate/boot/jaxb/Origin;
     130: invokespecial #36                 // Method org/hibernate/boot/MappingException."<init>":(Ljava/lang/String;Lorg/hibernate/boot/jaxb/Origin;)V
     133: athrow
     134: new           #44                 // class org/hibernate/boot/model/source/internal/hbm/IdentifierSourceNonAggregatedCompositeImpl
     137: dup
     138: aload_0
     139: invokespecial #45                 // Method org/hibernate/boot/model/source/internal/hbm/IdentifierSourceNonAggregatedCompositeImpl."<init>":(Lorg/hibernate/boot/model/source/internal/hbm/RootEntitySourceImpl;)V
     142: areturn
     143: aload_0
     144: invokevirtual #21                 // Method org/hibernate/boot/model/source/internal/hbm/RootEntitySourceImpl.jaxbEntityMapping:()Lorg/hibernate/boot/jaxb/hbm/spi/JaxbHbmRootEntityType;
     147: invokevirtual #29                 // Method org/hibernate/boot/jaxb/hbm/spi/JaxbHbmRootEntityType.getCompositeId:()Lorg/hibernate/boot/jaxb/hbm/spi/JaxbHbmCompositeIdType;
     150: invokevirtual #41                 // Method org/hibernate/boot/jaxb/hbm/spi/JaxbHbmCompositeIdType.isMapped:()Z
     153: ifeq          170
     156: new           #30                 // class org/hibernate/boot/MappingException
     159: dup
     160: ldc           #46                 // String cannot combine mapped=\"true\" with specified name
     162: aload_0
     163: invokevirtual #35                 // Method org/hibernate/boot/model/source/internal/hbm/RootEntitySourceImpl.origin:()Lorg/hibernate/boot/jaxb/Origin;
     166: invokespecial #36                 // Method org/hibernate/boot/MappingException."<init>":(Ljava/lang/String;Lorg/hibernate/boot/jaxb/Origin;)V
     169: athrow
     170: new           #47                 // class org/hibernate/boot/model/source/internal/hbm/IdentifierSourceAggregatedCompositeImpl
     173: dup
     174: aload_0
     175: invokespecial #48                 // Method org/hibernate/boot/model/source/internal/hbm/IdentifierSourceAggregatedCompositeImpl."<init>":(Lorg/hibernate/boot/model/source/internal/hbm/RootEntitySourceImpl;)V
     178: areturn

  private static org.hibernate.boot.model.source.spi.VersionAttributeSource interpretVersionSource(org.hibernate.boot.model.source.internal.hbm.RootEntitySourceImpl);
    Code:
       0: aload_0
       1: invokevirtual #21                 // Method org/hibernate/boot/model/source/internal/hbm/RootEntitySourceImpl.jaxbEntityMapping:()Lorg/hibernate/boot/jaxb/hbm/spi/JaxbHbmRootEntityType;
       4: astore_1
       5: aload_1
       6: invokevirtual #49                 // Method org/hibernate/boot/jaxb/hbm/spi/JaxbHbmRootEntityType.getVersion:()Lorg/hibernate/boot/jaxb/hbm/spi/JaxbHbmVersionAttributeType;
       9: ifnull        29
      12: new           #50                 // class org/hibernate/boot/model/source/internal/hbm/VersionAttributeSourceImpl
      15: dup
      16: aload_0
      17: invokevirtual #51                 // Method org/hibernate/boot/model/source/internal/hbm/RootEntitySourceImpl.sourceMappingDocument:()Lorg/hibernate/boot/model/source/internal/hbm/MappingDocument;
      20: aload_0
      21: aload_1
      22: invokevirtual #49                 // Method org/hibernate/boot/jaxb/hbm/spi/JaxbHbmRootEntityType.getVersion:()Lorg/hibernate/boot/jaxb/hbm/spi/JaxbHbmVersionAttributeType;
      25: invokespecial #52                 // Method org/hibernate/boot/model/source/internal/hbm/VersionAttributeSourceImpl."<init>":(Lorg/hibernate/boot/model/source/internal/hbm/MappingDocument;Lorg/hibernate/boot/model/source/internal/hbm/RootEntitySourceImpl;Lorg/hibernate/boot/jaxb/hbm/spi/JaxbHbmVersionAttributeType;)V
      28: areturn
      29: aload_1
      30: invokevirtual #53                 // Method org/hibernate/boot/jaxb/hbm/spi/JaxbHbmRootEntityType.getTimestamp:()Lorg/hibernate/boot/jaxb/hbm/spi/JaxbHbmTimestampAttributeType;
      33: ifnull        53
      36: new           #54                 // class org/hibernate/boot/model/source/internal/hbm/TimestampAttributeSourceImpl
      39: dup
      40: aload_0
      41: invokevirtual #51                 // Method org/hibernate/boot/model/source/internal/hbm/RootEntitySourceImpl.sourceMappingDocument:()Lorg/hibernate/boot/model/source/internal/hbm/MappingDocument;
      44: aload_0
      45: aload_1
      46: invokevirtual #53                 // Method org/hibernate/boot/jaxb/hbm/spi/JaxbHbmRootEntityType.getTimestamp:()Lorg/hibernate/boot/jaxb/hbm/spi/JaxbHbmTimestampAttributeType;
      49: invokespecial #55                 // Method org/hibernate/boot/model/source/internal/hbm/TimestampAttributeSourceImpl."<init>":(Lorg/hibernate/boot/model/source/internal/hbm/MappingDocument;Lorg/hibernate/boot/model/source/internal/hbm/RootEntitySourceImpl;Lorg/hibernate/boot/jaxb/hbm/spi/JaxbHbmTimestampAttributeType;)V
      52: areturn
      53: aconst_null
      54: areturn

  private static org.hibernate.boot.model.source.spi.DiscriminatorSource interpretDiscriminatorSource(org.hibernate.boot.model.source.internal.hbm.RootEntitySourceImpl);
    Code:
       0: aload_0
       1: invokevirtual #21                 // Method org/hibernate/boot/model/source/internal/hbm/RootEntitySourceImpl.jaxbEntityMapping:()Lorg/hibernate/boot/jaxb/hbm/spi/JaxbHbmRootEntityType;
       4: invokevirtual #56                 // Method org/hibernate/boot/jaxb/hbm/spi/JaxbHbmRootEntityType.getDiscriminator:()Lorg/hibernate/boot/jaxb/hbm/spi/JaxbHbmEntityDiscriminatorType;
       7: astore_1
       8: aload_1
       9: ifnonnull     14
      12: aconst_null
      13: areturn
      14: aload_0
      15: invokevirtual #51                 // Method org/hibernate/boot/model/source/internal/hbm/RootEntitySourceImpl.sourceMappingDocument:()Lorg/hibernate/boot/model/source/internal/hbm/MappingDocument;
      18: aconst_null
      19: new           #57                 // class org/hibernate/boot/model/source/internal/hbm/EntityHierarchySourceImpl$1
      22: dup
      23: aload_1
      24: aload_0
      25: invokespecial #58                 // Method org/hibernate/boot/model/source/internal/hbm/EntityHierarchySourceImpl$1."<init>":(Lorg/hibernate/boot/jaxb/hbm/spi/JaxbHbmEntityDiscriminatorType;Lorg/hibernate/boot/model/source/internal/hbm/RootEntitySourceImpl;)V
      28: invokestatic  #59                 // Method org/hibernate/boot/model/source/internal/hbm/RelationalValueSourceHelper.buildValueSource:(Lorg/hibernate/boot/model/source/internal/hbm/MappingDocument;Ljava/lang/String;Lorg/hibernate/boot/model/source/internal/hbm/RelationalValueSourceHelper$ColumnsAndFormulasSource;)Lorg/hibernate/boot/model/source/spi/RelationalValueSource;
      31: astore_2
      32: new           #60                 // class org/hibernate/boot/model/source/internal/hbm/EntityHierarchySourceImpl$2
      35: dup
      36: aload_0
      37: aload_2
      38: aload_1
      39: invokespecial #61                 // Method org/hibernate/boot/model/source/internal/hbm/EntityHierarchySourceImpl$2."<init>":(Lorg/hibernate/boot/model/source/internal/hbm/RootEntitySourceImpl;Lorg/hibernate/boot/model/source/spi/RelationalValueSource;Lorg/hibernate/boot/jaxb/hbm/spi/JaxbHbmEntityDiscriminatorType;)V
      42: areturn

  private static org.hibernate.boot.model.source.spi.MultiTenancySource interpretMultiTenancySource(org.hibernate.boot.model.source.internal.hbm.RootEntitySourceImpl);
    Code:
       0: aload_0
       1: invokevirtual #21                 // Method org/hibernate/boot/model/source/internal/hbm/RootEntitySourceImpl.jaxbEntityMapping:()Lorg/hibernate/boot/jaxb/hbm/spi/JaxbHbmRootEntityType;
       4: invokevirtual #62                 // Method org/hibernate/boot/jaxb/hbm/spi/JaxbHbmRootEntityType.getMultiTenancy:()Lorg/hibernate/boot/jaxb/hbm/spi/JaxbHbmMultiTenancyType;
       7: astore_1
       8: aload_1
       9: ifnonnull     14
      12: aconst_null
      13: areturn
      14: aload_0
      15: invokevirtual #51                 // Method org/hibernate/boot/model/source/internal/hbm/RootEntitySourceImpl.sourceMappingDocument:()Lorg/hibernate/boot/model/source/internal/hbm/MappingDocument;
      18: aconst_null
      19: new           #63                 // class org/hibernate/boot/model/source/internal/hbm/EntityHierarchySourceImpl$3
      22: dup
      23: aload_1
      24: aload_0
      25: invokespecial #64                 // Method org/hibernate/boot/model/source/internal/hbm/EntityHierarchySourceImpl$3."<init>":(Lorg/hibernate/boot/jaxb/hbm/spi/JaxbHbmMultiTenancyType;Lorg/hibernate/boot/model/source/internal/hbm/RootEntitySourceImpl;)V
      28: invokestatic  #59                 // Method org/hibernate/boot/model/source/internal/hbm/RelationalValueSourceHelper.buildValueSource:(Lorg/hibernate/boot/model/source/internal/hbm/MappingDocument;Ljava/lang/String;Lorg/hibernate/boot/model/source/internal/hbm/RelationalValueSourceHelper$ColumnsAndFormulasSource;)Lorg/hibernate/boot/model/source/spi/RelationalValueSource;
      31: astore_2
      32: new           #65                 // class org/hibernate/boot/model/source/internal/hbm/EntityHierarchySourceImpl$4
      35: dup
      36: aload_2
      37: aload_1
      38: invokespecial #66                 // Method org/hibernate/boot/model/source/internal/hbm/EntityHierarchySourceImpl$4."<init>":(Lorg/hibernate/boot/model/source/spi/RelationalValueSource;Lorg/hibernate/boot/jaxb/hbm/spi/JaxbHbmMultiTenancyType;)V
      41: areturn

  public org.hibernate.boot.model.source.spi.InheritanceType getHierarchyInheritanceType();
    Code:
       0: aload_0
       1: getfield      #3                  // Field hierarchyInheritanceType:Lorg/hibernate/boot/model/source/spi/InheritanceType;
       4: areturn

  public org.hibernate.boot.model.source.internal.hbm.RootEntitySourceImpl getRoot();
    Code:
       0: aload_0
       1: getfield      #7                  // Field rootEntitySource:Lorg/hibernate/boot/model/source/internal/hbm/RootEntitySourceImpl;
       4: areturn

  public void processSubclass(org.hibernate.boot.model.source.internal.hbm.SubclassEntitySourceImpl);
    Code:
       0: aload_1
       1: invokevirtual #67                 // Method org/hibernate/boot/model/source/internal/hbm/SubclassEntitySourceImpl.jaxbEntityMapping:()Lorg/hibernate/boot/jaxb/hbm/spi/JaxbHbmEntityBaseDefinition;
       4: invokestatic  #68                 // Method org/hibernate/boot/model/source/internal/hbm/Helper.interpretInheritanceType:(Lorg/hibernate/boot/jaxb/hbm/spi/JaxbHbmEntityBaseDefinition;)Lorg/hibernate/boot/model/source/spi/InheritanceType;
       7: astore_2
       8: aload_0
       9: getfield      #3                  // Field hierarchyInheritanceType:Lorg/hibernate/boot/model/source/spi/InheritanceType;
      12: getstatic     #2                  // Field org/hibernate/boot/model/source/spi/InheritanceType.NO_INHERITANCE:Lorg/hibernate/boot/model/source/spi/InheritanceType;
      15: if_acmpne     26
      18: aload_0
      19: aload_2
      20: putfield      #3                  // Field hierarchyInheritanceType:Lorg/hibernate/boot/model/source/spi/InheritanceType;
      23: goto          48
      26: aload_0
      27: getfield      #3                  // Field hierarchyInheritanceType:Lorg/hibernate/boot/model/source/spi/InheritanceType;
      30: aload_2
      31: if_acmpeq     48
      34: new           #30                 // class org/hibernate/boot/MappingException
      37: dup
      38: ldc           #69                 // String Mixed inheritance strategies not supported
      40: aload_1
      41: invokevirtual #70                 // Method org/hibernate/boot/model/source/internal/hbm/SubclassEntitySourceImpl.getOrigin:()Lorg/hibernate/boot/jaxb/Origin;
      44: invokespecial #36                 // Method org/hibernate/boot/MappingException."<init>":(Ljava/lang/String;Lorg/hibernate/boot/jaxb/Origin;)V
      47: athrow
      48: aload_0
      49: getfield      #6                  // Field collectedEntityNames:Ljava/util/Set;
      52: aload_1
      53: invokevirtual #71                 // Method org/hibernate/boot/model/source/internal/hbm/SubclassEntitySourceImpl.getEntityNamingSource:()Lorg/hibernate/boot/model/source/spi/EntityNamingSource;
      56: invokeinterface #26,  1           // InterfaceMethod org/hibernate/boot/model/source/spi/EntityNamingSource.getEntityName:()Ljava/lang/String;
      61: invokeinterface #27,  2           // InterfaceMethod java/util/Set.add:(Ljava/lang/Object;)Z
      66: pop
      67: return

  protected org.hibernate.boot.jaxb.hbm.spi.JaxbHbmRootEntityType entityElement();
    Code:
       0: aload_0
       1: getfield      #7                  // Field rootEntitySource:Lorg/hibernate/boot/model/source/internal/hbm/RootEntitySourceImpl;
       4: invokevirtual #21                 // Method org/hibernate/boot/model/source/internal/hbm/RootEntitySourceImpl.jaxbEntityMapping:()Lorg/hibernate/boot/jaxb/hbm/spi/JaxbHbmRootEntityType;
       7: areturn

  public org.hibernate.boot.model.source.spi.IdentifierSource getIdentifierSource();
    Code:
       0: aload_0
       1: getfield      #10                 // Field identifierSource:Lorg/hibernate/boot/model/source/spi/IdentifierSource;
       4: areturn

  public org.hibernate.boot.model.source.spi.VersionAttributeSource getVersionAttributeSource();
    Code:
       0: aload_0
       1: getfield      #12                 // Field versionAttributeSource:Lorg/hibernate/boot/model/source/spi/VersionAttributeSource;
       4: areturn

  public org.hibernate.EntityMode getEntityMode();
    Code:
       0: aload_0
       1: getfield      #7                  // Field rootEntitySource:Lorg/hibernate/boot/model/source/internal/hbm/RootEntitySourceImpl;
       4: invokevirtual #72                 // Method org/hibernate/boot/model/source/internal/hbm/RootEntitySourceImpl.determineEntityMode:()Lorg/hibernate/EntityMode;
       7: areturn

  public boolean isMutable();
    Code:
       0: aload_0
       1: invokevirtual #17                 // Method entityElement:()Lorg/hibernate/boot/jaxb/hbm/spi/JaxbHbmRootEntityType;
       4: invokevirtual #73                 // Method org/hibernate/boot/jaxb/hbm/spi/JaxbHbmRootEntityType.isMutable:()Z
       7: ireturn

  public boolean isExplicitPolymorphism();
    Code:
       0: getstatic     #74                 // Field org/hibernate/boot/jaxb/hbm/spi/JaxbHbmPolymorphismEnum.EXPLICIT:Lorg/hibernate/boot/jaxb/hbm/spi/JaxbHbmPolymorphismEnum;
       3: aload_0
       4: invokevirtual #17                 // Method entityElement:()Lorg/hibernate/boot/jaxb/hbm/spi/JaxbHbmRootEntityType;
       7: invokevirtual #75                 // Method org/hibernate/boot/jaxb/hbm/spi/JaxbHbmRootEntityType.getPolymorphism:()Lorg/hibernate/boot/jaxb/hbm/spi/JaxbHbmPolymorphismEnum;
      10: if_acmpne     17
      13: iconst_1
      14: goto          18
      17: iconst_0
      18: ireturn

  public java.lang.String getWhere();
    Code:
       0: aload_0
       1: invokevirtual #17                 // Method entityElement:()Lorg/hibernate/boot/jaxb/hbm/spi/JaxbHbmRootEntityType;
       4: invokevirtual #76                 // Method org/hibernate/boot/jaxb/hbm/spi/JaxbHbmRootEntityType.getWhere:()Ljava/lang/String;
       7: areturn

  public java.lang.String getRowId();
    Code:
       0: aload_0
       1: invokevirtual #17                 // Method entityElement:()Lorg/hibernate/boot/jaxb/hbm/spi/JaxbHbmRootEntityType;
       4: invokevirtual #77                 // Method org/hibernate/boot/jaxb/hbm/spi/JaxbHbmRootEntityType.getRowid:()Ljava/lang/String;
       7: areturn

  public org.hibernate.engine.OptimisticLockStyle getOptimisticLockStyle();
    Code:
       0: aload_0
       1: invokevirtual #17                 // Method entityElement:()Lorg/hibernate/boot/jaxb/hbm/spi/JaxbHbmRootEntityType;
       4: invokevirtual #78                 // Method org/hibernate/boot/jaxb/hbm/spi/JaxbHbmRootEntityType.getOptimisticLock:()Lorg/hibernate/engine/OptimisticLockStyle;
       7: areturn

  public org.hibernate.boot.model.Caching getCaching();
    Code:
       0: aload_0
       1: getfield      #20                 // Field caching:Lorg/hibernate/boot/model/Caching;
       4: areturn

  public org.hibernate.boot.model.Caching getNaturalIdCaching();
    Code:
       0: aload_0
       1: getfield      #24                 // Field naturalIdCaching:Lorg/hibernate/boot/model/Caching;
       4: areturn

  public org.hibernate.boot.model.source.spi.DiscriminatorSource getDiscriminatorSource();
    Code:
       0: aload_0
       1: getfield      #14                 // Field discriminatorSource:Lorg/hibernate/boot/model/source/spi/DiscriminatorSource;
       4: areturn

  public org.hibernate.boot.model.source.spi.MultiTenancySource getMultiTenancySource();
    Code:
       0: aload_0
       1: getfield      #16                 // Field multiTenancySource:Lorg/hibernate/boot/model/source/spi/MultiTenancySource;
       4: areturn

  static org.hibernate.boot.model.IdentifierGeneratorDefinition interpretGeneratorDefinition(org.hibernate.boot.model.source.internal.hbm.MappingDocument, org.hibernate.boot.model.source.spi.EntityNamingSource, org.hibernate.boot.jaxb.hbm.spi.JaxbHbmGeneratorSpecificationType);
    Code:
       0: aload_2
       1: ifnonnull     6
       4: aconst_null
       5: areturn
       6: aload_2
       7: invokevirtual #79                 // Method org/hibernate/boot/jaxb/hbm/spi/JaxbHbmGeneratorSpecificationType.getClazz:()Ljava/lang/String;
      10: astore_3
      11: aload_0
      12: invokevirtual #80                 // Method org/hibernate/boot/model/source/internal/hbm/MappingDocument.getMetadataCollector:()Lorg/hibernate/boot/spi/InFlightMetadataCollector;
      15: aload_3
      16: invokeinterface #81,  2           // InterfaceMethod org/hibernate/boot/spi/InFlightMetadataCollector.getIdentifierGenerator:(Ljava/lang/String;)Lorg/hibernate/boot/model/IdentifierGeneratorDefinition;
      21: astore        4
      23: aload         4
      25: ifnonnull     73
      28: new           #82                 // class org/hibernate/boot/model/IdentifierGeneratorDefinition
      31: dup
      32: new           #83                 // class java/lang/StringBuilder
      35: dup
      36: invokespecial #84                 // Method java/lang/StringBuilder."<init>":()V
      39: aload_1
      40: invokeinterface #26,  1           // InterfaceMethod org/hibernate/boot/model/source/spi/EntityNamingSource.getEntityName:()Ljava/lang/String;
      45: invokevirtual #85                 // Method java/lang/StringBuilder.append:(Ljava/lang/String;)Ljava/lang/StringBuilder;
      48: bipush        46
      50: invokevirtual #86                 // Method java/lang/StringBuilder.append:(C)Ljava/lang/StringBuilder;
      53: aload_3
      54: invokevirtual #85                 // Method java/lang/StringBuilder.append:(Ljava/lang/String;)Ljava/lang/StringBuilder;
      57: invokevirtual #87                 // Method java/lang/StringBuilder.toString:()Ljava/lang/String;
      60: aload_3
      61: aload_2
      62: invokevirtual #88                 // Method org/hibernate/boot/jaxb/hbm/spi/JaxbHbmGeneratorSpecificationType.getConfigParameters:()Ljava/util/List;
      65: invokestatic  #89                 // Method org/hibernate/boot/model/source/internal/hbm/Helper.extractParameters:(Ljava/util/List;)Ljava/util/Map;
      68: invokespecial #90                 // Method org/hibernate/boot/model/IdentifierGeneratorDefinition."<init>":(Ljava/lang/String;Ljava/lang/String;Ljava/util/Map;)V
      71: astore        4
      73: aload         4
      75: areturn

  public java.util.Set<java.lang.String> getContainedEntityNames();
    Code:
       0: aload_0
       1: getfield      #6                  // Field collectedEntityNames:Ljava/util/Set;
       4: areturn

  public org.hibernate.boot.model.source.spi.EntitySource getRoot();
    Code:
       0: aload_0
       1: invokevirtual #91                 // Method getRoot:()Lorg/hibernate/boot/model/source/internal/hbm/RootEntitySourceImpl;
       4: areturn
}
