Compiled from "MPerfRpc.java"
public class org.jgroups.tests.perf.MPerfRpc$MperfMarshaller implements org.jgroups.blocks.RpcDispatcher$Marshaller {
  final org.jgroups.tests.perf.MPerfRpc this$0;

  protected org.jgroups.tests.perf.MPerfRpc$MperfMarshaller(org.jgroups.tests.perf.MPerfRpc);
    Code:
       0: aload_0
       1: aload_1
       2: putfield      #1                  // Field this$0:Lorg/jgroups/tests/perf/MPerfRpc;
       5: aload_0
       6: invokespecial #2                  // Method java/lang/Object."<init>":()V
       9: return

  public org.jgroups.util.Buffer objectToBuffer(java.lang.Object) throws java.lang.Exception;
    Code:
       0: new           #3                  // class org/jgroups/util/ByteArrayDataOutputStream
       3: dup
       4: aload_0
       5: getfield      #1                  // Field this$0:Lorg/jgroups/tests/perf/MPerfRpc;
       8: getfield      #4                  // Field org/jgroups/tests/perf/MPerfRpc.msg_size:I
      11: bipush        100
      13: iadd
      14: invokespecial #5                  // Method org/jgroups/util/ByteArrayDataOutputStream."<init>":(I)V
      17: astore_2
      18: aload_1
      19: instanceof    #6                  // class org/jgroups/blocks/MethodCall
      22: istore_3
      23: aload_2
      24: iload_3
      25: invokevirtual #7                  // Method org/jgroups/util/ByteArrayDataOutputStream.writeBoolean:(Z)V
      28: iload_3
      29: ifne          40
      32: aload_1
      33: aload_2
      34: invokestatic  #8                  // Method org/jgroups/util/Util.objectToStream:(Ljava/lang/Object;Ljava/io/DataOutput;)V
      37: goto          107
      40: aload_1
      41: checkcast     #6                  // class org/jgroups/blocks/MethodCall
      44: astore        4
      46: aload_2
      47: aload         4
      49: invokevirtual #9                  // Method org/jgroups/blocks/MethodCall.getId:()S
      52: invokevirtual #10                 // Method org/jgroups/util/ByteArrayDataOutputStream.writeShort:(I)V
      55: aload         4
      57: invokevirtual #11                 // Method org/jgroups/blocks/MethodCall.getArgs:()[Ljava/lang/Object;
      60: astore        5
      62: aload         5
      64: ifnonnull     71
      67: iconst_0
      68: goto          74
      71: aload         5
      73: arraylength
      74: istore        6
      76: aload_2
      77: iload         6
      79: invokevirtual #10                 // Method org/jgroups/util/ByteArrayDataOutputStream.writeShort:(I)V
      82: iconst_0
      83: istore        7
      85: iload         7
      87: iload         6
      89: if_icmpge     107
      92: aload         5
      94: iload         7
      96: aaload
      97: aload_2
      98: invokestatic  #8                  // Method org/jgroups/util/Util.objectToStream:(Ljava/lang/Object;Ljava/io/DataOutput;)V
     101: iinc          7, 1
     104: goto          85
     107: aload_2
     108: invokevirtual #12                 // Method org/jgroups/util/ByteArrayDataOutputStream.getBuffer:()Lorg/jgroups/util/Buffer;
     111: areturn

  public java.lang.Object objectFromBuffer(byte[], int, int) throws java.lang.Exception;
    Code:
       0: new           #13                 // class org/jgroups/util/ByteArrayDataInputStream
       3: dup
       4: aload_1
       5: iload_2
       6: iload_3
       7: invokespecial #14                 // Method org/jgroups/util/ByteArrayDataInputStream."<init>":([BII)V
      10: astore        4
      12: aload         4
      14: invokeinterface #15,  1           // InterfaceMethod java/io/DataInput.readBoolean:()Z
      19: ifne          28
      22: aload         4
      24: invokestatic  #16                 // Method org/jgroups/util/Util.objectFromStream:(Ljava/io/DataInput;)Ljava/lang/Object;
      27: areturn
      28: aload         4
      30: invokeinterface #17,  1           // InterfaceMethod java/io/DataInput.readShort:()S
      35: istore        5
      37: aload         4
      39: invokeinterface #17,  1           // InterfaceMethod java/io/DataInput.readShort:()S
      44: istore        6
      46: iload         6
      48: ifle          59
      51: iload         6
      53: anewarray     #18                 // class java/lang/Object
      56: goto          60
      59: aconst_null
      60: astore        7
      62: aload         7
      64: ifnull        94
      67: iconst_0
      68: istore        8
      70: iload         8
      72: aload         7
      74: arraylength
      75: if_icmpge     94
      78: aload         7
      80: iload         8
      82: aload         4
      84: invokestatic  #16                 // Method org/jgroups/util/Util.objectFromStream:(Ljava/io/DataInput;)Ljava/lang/Object;
      87: aastore
      88: iinc          8, 1
      91: goto          70
      94: new           #6                  // class org/jgroups/blocks/MethodCall
      97: dup
      98: iload         5
     100: aload         7
     102: invokespecial #19                 // Method org/jgroups/blocks/MethodCall."<init>":(S[Ljava/lang/Object;)V
     105: areturn
}
