Compiled from "MPerf.java"
public class org.jgroups.tests.perf.MPerf$Sender extends java.lang.Thread {
  protected final java.util.concurrent.CyclicBarrier barrier;

  protected final java.util.concurrent.atomic.AtomicInteger num_msgs_sent;

  protected final java.util.concurrent.atomic.AtomicInteger actually_sent;

  protected final java.util.concurrent.atomic.AtomicLong seqno;

  protected final byte[] payload;

  final org.jgroups.tests.perf.MPerf this$0;

  protected org.jgroups.tests.perf.MPerf$Sender(org.jgroups.tests.perf.MPerf, java.util.concurrent.CyclicBarrier, java.util.concurrent.atomic.AtomicInteger, java.util.concurrent.atomic.AtomicInteger, java.util.concurrent.atomic.AtomicLong, byte[]);
    Code:
       0: aload_0
       1: aload_1
       2: putfield      #1                  // Field this$0:Lorg/jgroups/tests/perf/MPerf;
       5: aload_0
       6: invokespecial #2                  // Method java/lang/Thread."<init>":()V
       9: aload_0
      10: aload_2
      11: putfield      #3                  // Field barrier:Ljava/util/concurrent/CyclicBarrier;
      14: aload_0
      15: aload_3
      16: putfield      #4                  // Field num_msgs_sent:Ljava/util/concurrent/atomic/AtomicInteger;
      19: aload_0
      20: aload         4
      22: putfield      #5                  // Field actually_sent:Ljava/util/concurrent/atomic/AtomicInteger;
      25: aload_0
      26: aload         5
      28: putfield      #6                  // Field seqno:Ljava/util/concurrent/atomic/AtomicLong;
      31: aload_0
      32: aload         6
      34: putfield      #7                  // Field payload:[B
      37: return

  public void run();
    Code:
       0: aload_0
       1: getfield      #3                  // Field barrier:Ljava/util/concurrent/CyclicBarrier;
       4: invokevirtual #8                  // Method java/util/concurrent/CyclicBarrier.await:()I
       7: pop
       8: goto          17
      11: astore_1
      12: aload_1
      13: invokevirtual #10                 // Method java/lang/Exception.printStackTrace:()V
      16: return
      17: aload_0
      18: getfield      #4                  // Field num_msgs_sent:Ljava/util/concurrent/atomic/AtomicInteger;
      21: invokevirtual #11                 // Method java/util/concurrent/atomic/AtomicInteger.incrementAndGet:()I
      24: istore_1
      25: iload_1
      26: aload_0
      27: getfield      #1                  // Field this$0:Lorg/jgroups/tests/perf/MPerf;
      30: getfield      #12                 // Field org/jgroups/tests/perf/MPerf.num_msgs:I
      33: if_icmpgt     46
      36: aload_0
      37: getfield      #1                  // Field this$0:Lorg/jgroups/tests/perf/MPerf;
      40: getfield      #13                 // Field org/jgroups/tests/perf/MPerf.cancelled:Z
      43: ifeq          49
      46: goto          207
      49: aload_0
      50: getfield      #6                  // Field seqno:Ljava/util/concurrent/atomic/AtomicLong;
      53: invokevirtual #14                 // Method java/util/concurrent/atomic/AtomicLong.getAndIncrement:()J
      56: lstore_2
      57: new           #15                 // class org/jgroups/Message
      60: dup
      61: aconst_null
      62: aload_0
      63: getfield      #7                  // Field payload:[B
      66: invokespecial #16                 // Method org/jgroups/Message."<init>":(Lorg/jgroups/Address;[B)V
      69: getstatic     #17                 // Field org/jgroups/tests/perf/MPerf.ID:S
      72: new           #18                 // class org/jgroups/tests/perf/MPerf$MPerfHeader
      75: dup
      76: iconst_1
      77: lload_2
      78: invokespecial #19                 // Method org/jgroups/tests/perf/MPerf$MPerfHeader."<init>":(BJ)V
      81: invokevirtual #20                 // Method org/jgroups/Message.putHeader:(SLorg/jgroups/Header;)Lorg/jgroups/Message;
      84: astore        4
      86: aload_0
      87: getfield      #1                  // Field this$0:Lorg/jgroups/tests/perf/MPerf;
      90: getfield      #21                 // Field org/jgroups/tests/perf/MPerf.oob:Z
      93: ifeq          112
      96: aload         4
      98: iconst_1
      99: anewarray     #22                 // class org/jgroups/Message$Flag
     102: dup
     103: iconst_0
     104: getstatic     #23                 // Field org/jgroups/Message$Flag.OOB:Lorg/jgroups/Message$Flag;
     107: aastore
     108: invokevirtual #24                 // Method org/jgroups/Message.setFlag:([Lorg/jgroups/Message$Flag;)Lorg/jgroups/Message;
     111: pop
     112: aload_0
     113: getfield      #1                  // Field this$0:Lorg/jgroups/tests/perf/MPerf;
     116: getfield      #25                 // Field org/jgroups/tests/perf/MPerf.channel:Lorg/jgroups/JChannel;
     119: aload         4
     121: invokevirtual #26                 // Method org/jgroups/JChannel.send:(Lorg/jgroups/Message;)V
     124: iload_1
     125: aload_0
     126: getfield      #1                  // Field this$0:Lorg/jgroups/tests/perf/MPerf;
     129: getfield      #27                 // Field org/jgroups/tests/perf/MPerf.log_interval:I
     132: irem
     133: ifne          161
     136: getstatic     #28                 // Field java/lang/System.out:Ljava/io/PrintStream;
     139: new           #29                 // class java/lang/StringBuilder
     142: dup
     143: invokespecial #30                 // Method java/lang/StringBuilder."<init>":()V
     146: ldc           #31                 // String ++ sent
     148: invokevirtual #32                 // Method java/lang/StringBuilder.append:(Ljava/lang/String;)Ljava/lang/StringBuilder;
     151: iload_1
     152: invokevirtual #33                 // Method java/lang/StringBuilder.append:(I)Ljava/lang/StringBuilder;
     155: invokevirtual #34                 // Method java/lang/StringBuilder.toString:()Ljava/lang/String;
     158: invokevirtual #35                 // Method java/io/PrintStream.println:(Ljava/lang/String;)V
     161: aload_0
     162: getfield      #5                  // Field actually_sent:Ljava/util/concurrent/atomic/AtomicInteger;
     165: invokevirtual #11                 // Method java/util/concurrent/atomic/AtomicInteger.incrementAndGet:()I
     168: istore_1
     169: iload_1
     170: aload_0
     171: getfield      #1                  // Field this$0:Lorg/jgroups/tests/perf/MPerf;
     174: getfield      #12                 // Field org/jgroups/tests/perf/MPerf.num_msgs:I
     177: if_icmpne     200
     180: aload_0
     181: getfield      #1                  // Field this$0:Lorg/jgroups/tests/perf/MPerf;
     184: aconst_null
     185: aconst_null
     186: iconst_3
     187: iconst_1
     188: anewarray     #22                 // class org/jgroups/Message$Flag
     191: dup
     192: iconst_0
     193: getstatic     #36                 // Field org/jgroups/Message$Flag.RSVP:Lorg/jgroups/Message$Flag;
     196: aastore
     197: invokevirtual #37                 // Method org/jgroups/tests/perf/MPerf.send:(Lorg/jgroups/Address;Ljava/lang/Object;B[Lorg/jgroups/Message$Flag;)V
     200: goto          17
     203: astore_1
     204: goto          17
     207: return
    Exception table:
       from    to  target type
           0     8    11   Class java/lang/Exception
          17    46   203   Class java/lang/Exception
          49   200   203   Class java/lang/Exception
}
