Compiled from "UPerf.java"
public class org.jgroups.tests.perf.UPerf$Config implements org.jgroups.util.Streamable {
  protected java.util.Map<java.lang.String, java.lang.Object> values;

  public org.jgroups.tests.perf.UPerf$Config();
    Code:
       0: aload_0
       1: invokespecial #1                  // Method java/lang/Object."<init>":()V
       4: aload_0
       5: new           #2                  // class java/util/HashMap
       8: dup
       9: invokespecial #3                  // Method java/util/HashMap."<init>":()V
      12: putfield      #4                  // Field values:Ljava/util/Map;
      15: return

  public org.jgroups.tests.perf.UPerf$Config add(java.lang.String, java.lang.Object);
    Code:
       0: aload_0
       1: getfield      #4                  // Field values:Ljava/util/Map;
       4: aload_1
       5: aload_2
       6: invokeinterface #5,  3            // InterfaceMethod java/util/Map.put:(Ljava/lang/Object;Ljava/lang/Object;)Ljava/lang/Object;
      11: pop
      12: aload_0
      13: areturn

  public void writeTo(java.io.DataOutput) throws java.lang.Exception;
    Code:
       0: aload_1
       1: aload_0
       2: getfield      #4                  // Field values:Ljava/util/Map;
       5: invokeinterface #6,  1            // InterfaceMethod java/util/Map.size:()I
      10: invokeinterface #7,  2            // InterfaceMethod java/io/DataOutput.writeInt:(I)V
      15: aload_0
      16: getfield      #4                  // Field values:Ljava/util/Map;
      19: invokeinterface #8,  1            // InterfaceMethod java/util/Map.entrySet:()Ljava/util/Set;
      24: invokeinterface #9,  1            // InterfaceMethod java/util/Set.iterator:()Ljava/util/Iterator;
      29: astore_2
      30: aload_2
      31: invokeinterface #10,  1           // InterfaceMethod java/util/Iterator.hasNext:()Z
      36: ifeq          75
      39: aload_2
      40: invokeinterface #11,  1           // InterfaceMethod java/util/Iterator.next:()Ljava/lang/Object;
      45: checkcast     #12                 // class java/util/Map$Entry
      48: astore_3
      49: aload_3
      50: invokeinterface #13,  1           // InterfaceMethod java/util/Map$Entry.getKey:()Ljava/lang/Object;
      55: checkcast     #14                 // class java/lang/String
      58: aload_1
      59: invokestatic  #15                 // Method org/jgroups/util/Bits.writeString:(Ljava/lang/String;Ljava/io/DataOutput;)V
      62: aload_3
      63: invokeinterface #16,  1           // InterfaceMethod java/util/Map$Entry.getValue:()Ljava/lang/Object;
      68: aload_1
      69: invokestatic  #17                 // Method org/jgroups/util/Util.objectToStream:(Ljava/lang/Object;Ljava/io/DataOutput;)V
      72: goto          30
      75: return

  public void readFrom(java.io.DataInput) throws java.lang.Exception;
    Code:
       0: aload_1
       1: invokeinterface #18,  1           // InterfaceMethod java/io/DataInput.readInt:()I
       6: istore_2
       7: iconst_0
       8: istore_3
       9: iload_3
      10: iload_2
      11: if_icmpge     54
      14: aload_1
      15: invokestatic  #19                 // Method org/jgroups/util/Bits.readString:(Ljava/io/DataInput;)Ljava/lang/String;
      18: astore        4
      20: aload_1
      21: invokestatic  #20                 // Method org/jgroups/util/Util.objectFromStream:(Ljava/io/DataInput;)Ljava/lang/Object;
      24: astore        5
      26: aload         4
      28: ifnonnull     34
      31: goto          48
      34: aload_0
      35: getfield      #4                  // Field values:Ljava/util/Map;
      38: aload         4
      40: aload         5
      42: invokeinterface #5,  3            // InterfaceMethod java/util/Map.put:(Ljava/lang/Object;Ljava/lang/Object;)Ljava/lang/Object;
      47: pop
      48: iinc          3, 1
      51: goto          9
      54: return

  public java.lang.String toString();
    Code:
       0: aload_0
       1: getfield      #4                  // Field values:Ljava/util/Map;
       4: invokevirtual #21                 // Method java/lang/Object.toString:()Ljava/lang/String;
       7: areturn
}
