Compiled from "BigIntegerStringConverter.java"
public class javafx.util.converter.BigIntegerStringConverter extends javafx.util.StringConverter<java.math.BigInteger> {
  public javafx.util.converter.BigIntegerStringConverter();
    Code:
       0: aload_0
       1: invokespecial #1                  // Method javafx/util/StringConverter."<init>":()V
       4: return

  public java.math.BigInteger fromString(java.lang.String);
    Code:
       0: aload_1
       1: ifnonnull     6
       4: aconst_null
       5: areturn
       6: aload_1
       7: invokevirtual #2                  // Method java/lang/String.trim:()Ljava/lang/String;
      10: astore_1
      11: aload_1
      12: invokevirtual #3                  // Method java/lang/String.length:()I
      15: iconst_1
      16: if_icmpge     21
      19: aconst_null
      20: areturn
      21: new           #4                  // class java/math/BigInteger
      24: dup
      25: aload_1
      26: invokespecial #5                  // Method java/math/BigInteger."<init>":(Ljava/lang/String;)V
      29: areturn

  public java.lang.String toString(java.math.BigInteger);
    Code:
       0: aload_1
       1: ifnonnull     7
       4: ldc           #6                  // String
       6: areturn
       7: aload_1
       8: invokevirtual #7                  // Method java/math/BigInteger.toString:()Ljava/lang/String;
      11: areturn

  public java.lang.Object fromString(java.lang.String);
    Code:
       0: aload_0
       1: aload_1
       2: invokevirtual #8                  // Method fromString:(Ljava/lang/String;)Ljava/math/BigInteger;
       5: areturn

  public java.lang.String toString(java.lang.Object);
    Code:
       0: aload_0
       1: aload_1
       2: checkcast     #4                  // class java/math/BigInteger
       5: invokevirtual #9                  // Method toString:(Ljava/math/BigInteger;)Ljava/lang/String;
       8: areturn
}
