Compiled from "PolynomialsUtils.java"
final class org.apache.commons.math3.analysis.polynomials.PolynomialsUtils$1 implements org.apache.commons.math3.analysis.polynomials.PolynomialsUtils$RecurrenceCoefficientsGenerator {
  private final org.apache.commons.math3.fraction.BigFraction[] coeffs;

  org.apache.commons.math3.analysis.polynomials.PolynomialsUtils$1();
    Code:
       0: aload_0
       1: invokespecial #1                  // Method java/lang/Object."<init>":()V
       4: aload_0
       5: iconst_3
       6: anewarray     #2                  // class org/apache/commons/math3/fraction/BigFraction
       9: dup
      10: iconst_0
      11: getstatic     #3                  // Field org/apache/commons/math3/fraction/BigFraction.ZERO:Lorg/apache/commons/math3/fraction/BigFraction;
      14: aastore
      15: dup
      16: iconst_1
      17: getstatic     #4                  // Field org/apache/commons/math3/fraction/BigFraction.TWO:Lorg/apache/commons/math3/fraction/BigFraction;
      20: aastore
      21: dup
      22: iconst_2
      23: getstatic     #5                  // Field org/apache/commons/math3/fraction/BigFraction.ONE:Lorg/apache/commons/math3/fraction/BigFraction;
      26: aastore
      27: putfield      #6                  // Field coeffs:[Lorg/apache/commons/math3/fraction/BigFraction;
      30: return

  public org.apache.commons.math3.fraction.BigFraction[] generate(int);
    Code:
       0: aload_0
       1: getfield      #6                  // Field coeffs:[Lorg/apache/commons/math3/fraction/BigFraction;
       4: areturn
}
