Compiled from "MultivariateNormalMixtureExpectationMaximization.java"
public class org.apache.commons.math3.distribution.fitting.MultivariateNormalMixtureExpectationMaximization {
  private static final int DEFAULT_MAX_ITERATIONS;

  private static final double DEFAULT_THRESHOLD;

  private final double[][] data;

  private org.apache.commons.math3.distribution.MixtureMultivariateNormalDistribution fittedModel;

  private double logLikelihood;

  public org.apache.commons.math3.distribution.fitting.MultivariateNormalMixtureExpectationMaximization(double[][]) throws org.apache.commons.math3.exception.NotStrictlyPositiveException, org.apache.commons.math3.exception.DimensionMismatchException, org.apache.commons.math3.exception.NumberIsTooSmallException;
    Code:
       0: aload_0
       1: invokespecial #1                  // Method java/lang/Object."<init>":()V
       4: aload_0
       5: dconst_0
       6: putfield      #2                  // Field logLikelihood:D
       9: aload_1
      10: arraylength
      11: iconst_1
      12: if_icmpge     28
      15: new           #3                  // class org/apache/commons/math3/exception/NotStrictlyPositiveException
      18: dup
      19: aload_1
      20: arraylength
      21: invokestatic  #4                  // Method java/lang/Integer.valueOf:(I)Ljava/lang/Integer;
      24: invokespecial #5                  // Method org/apache/commons/math3/exception/NotStrictlyPositiveException."<init>":(Ljava/lang/Number;)V
      27: athrow
      28: aload_0
      29: aload_1
      30: arraylength
      31: aload_1
      32: iconst_0
      33: aaload
      34: arraylength
      35: multianewarray #6,  2             // class "[[D"
      39: putfield      #7                  // Field data:[[D
      42: iconst_0
      43: istore_2
      44: iload_2
      45: aload_1
      46: arraylength
      47: if_icmpge     130
      50: aload_1
      51: iload_2
      52: aaload
      53: arraylength
      54: aload_1
      55: iconst_0
      56: aaload
      57: arraylength
      58: if_icmpeq     77
      61: new           #8                  // class org/apache/commons/math3/exception/DimensionMismatchException
      64: dup
      65: aload_1
      66: iload_2
      67: aaload
      68: arraylength
      69: aload_1
      70: iconst_0
      71: aaload
      72: arraylength
      73: invokespecial #9                  // Method org/apache/commons/math3/exception/DimensionMismatchException."<init>":(II)V
      76: athrow
      77: aload_1
      78: iload_2
      79: aaload
      80: arraylength
      81: iconst_2
      82: if_icmpge     108
      85: new           #10                 // class org/apache/commons/math3/exception/NumberIsTooSmallException
      88: dup
      89: getstatic     #11                 // Field org/apache/commons/math3/exception/util/LocalizedFormats.NUMBER_TOO_SMALL:Lorg/apache/commons/math3/exception/util/LocalizedFormats;
      92: aload_1
      93: iload_2
      94: aaload
      95: arraylength
      96: invokestatic  #4                  // Method java/lang/Integer.valueOf:(I)Ljava/lang/Integer;
      99: iconst_2
     100: invokestatic  #4                  // Method java/lang/Integer.valueOf:(I)Ljava/lang/Integer;
     103: iconst_1
     104: invokespecial #12                 // Method org/apache/commons/math3/exception/NumberIsTooSmallException."<init>":(Lorg/apache/commons/math3/exception/util/Localizable;Ljava/lang/Number;Ljava/lang/Number;Z)V
     107: athrow
     108: aload_0
     109: getfield      #7                  // Field data:[[D
     112: iload_2
     113: aload_1
     114: iload_2
     115: aaload
     116: aload_1
     117: iload_2
     118: aaload
     119: arraylength
     120: invokestatic  #13                 // Method org/apache/commons/math3/util/MathArrays.copyOf:([DI)[D
     123: aastore
     124: iinc          2, 1
     127: goto          44
     130: return

  public void fit(org.apache.commons.math3.distribution.MixtureMultivariateNormalDistribution, int, double) throws org.apache.commons.math3.linear.SingularMatrixException, org.apache.commons.math3.exception.NotStrictlyPositiveException, org.apache.commons.math3.exception.DimensionMismatchException;
    Code:
       0: iload_2
       1: iconst_1
       2: if_icmpge     17
       5: new           #3                  // class org/apache/commons/math3/exception/NotStrictlyPositiveException
       8: dup
       9: iload_2
      10: invokestatic  #4                  // Method java/lang/Integer.valueOf:(I)Ljava/lang/Integer;
      13: invokespecial #5                  // Method org/apache/commons/math3/exception/NotStrictlyPositiveException."<init>":(Ljava/lang/Number;)V
      16: athrow
      17: dload_3
      18: ldc2_w        #14                 // double 4.9E-324d
      21: dcmpg
      22: ifge          37
      25: new           #3                  // class org/apache/commons/math3/exception/NotStrictlyPositiveException
      28: dup
      29: dload_3
      30: invokestatic  #16                 // Method java/lang/Double.valueOf:(D)Ljava/lang/Double;
      33: invokespecial #5                  // Method org/apache/commons/math3/exception/NotStrictlyPositiveException."<init>":(Ljava/lang/Number;)V
      36: athrow
      37: aload_0
      38: getfield      #7                  // Field data:[[D
      41: arraylength
      42: istore        5
      44: aload_0
      45: getfield      #7                  // Field data:[[D
      48: iconst_0
      49: aaload
      50: arraylength
      51: istore        6
      53: aload_1
      54: invokevirtual #17                 // Method org/apache/commons/math3/distribution/MixtureMultivariateNormalDistribution.getComponents:()Ljava/util/List;
      57: invokeinterface #18,  1           // InterfaceMethod java/util/List.size:()I
      62: istore        7
      64: aload_1
      65: invokevirtual #17                 // Method org/apache/commons/math3/distribution/MixtureMultivariateNormalDistribution.getComponents:()Ljava/util/List;
      68: iconst_0
      69: invokeinterface #19,  2           // InterfaceMethod java/util/List.get:(I)Ljava/lang/Object;
      74: checkcast     #20                 // class org/apache/commons/math3/util/Pair
      77: invokevirtual #21                 // Method org/apache/commons/math3/util/Pair.getSecond:()Ljava/lang/Object;
      80: checkcast     #22                 // class org/apache/commons/math3/distribution/MultivariateNormalDistribution
      83: invokevirtual #23                 // Method org/apache/commons/math3/distribution/MultivariateNormalDistribution.getMeans:()[D
      86: arraylength
      87: istore        8
      89: iload         8
      91: iload         6
      93: if_icmpeq     108
      96: new           #8                  // class org/apache/commons/math3/exception/DimensionMismatchException
      99: dup
     100: iload         8
     102: iload         6
     104: invokespecial #9                  // Method org/apache/commons/math3/exception/DimensionMismatchException."<init>":(II)V
     107: athrow
     108: iconst_0
     109: istore        9
     111: dconst_0
     112: dstore        10
     114: aload_0
     115: ldc2_w        #24                 // double -Infinityd
     118: putfield      #2                  // Field logLikelihood:D
     121: aload_0
     122: new           #26                 // class org/apache/commons/math3/distribution/MixtureMultivariateNormalDistribution
     125: dup
     126: aload_1
     127: invokevirtual #17                 // Method org/apache/commons/math3/distribution/MixtureMultivariateNormalDistribution.getComponents:()Ljava/util/List;
     130: invokespecial #27                 // Method org/apache/commons/math3/distribution/MixtureMultivariateNormalDistribution."<init>":(Ljava/util/List;)V
     133: putfield      #28                 // Field fittedModel:Lorg/apache/commons/math3/distribution/MixtureMultivariateNormalDistribution;
     136: iload         9
     138: iinc          9, 1
     141: iload_2
     142: if_icmpgt     754
     145: dload         10
     147: aload_0
     148: getfield      #2                  // Field logLikelihood:D
     151: dsub
     152: invokestatic  #29                 // Method org/apache/commons/math3/util/FastMath.abs:(D)D
     155: dload_3
     156: dcmpl
     157: ifle          754
     160: aload_0
     161: getfield      #2                  // Field logLikelihood:D
     164: dstore        10
     166: dconst_0
     167: dstore        12
     169: aload_0
     170: getfield      #28                 // Field fittedModel:Lorg/apache/commons/math3/distribution/MixtureMultivariateNormalDistribution;
     173: invokevirtual #17                 // Method org/apache/commons/math3/distribution/MixtureMultivariateNormalDistribution.getComponents:()Ljava/util/List;
     176: astore        14
     178: iload         7
     180: newarray       double
     182: astore        15
     184: iload         7
     186: anewarray     #22                 // class org/apache/commons/math3/distribution/MultivariateNormalDistribution
     189: astore        16
     191: iconst_0
     192: istore        17
     194: iload         17
     196: iload         7
     198: if_icmpge     256
     201: aload         15
     203: iload         17
     205: aload         14
     207: iload         17
     209: invokeinterface #19,  2           // InterfaceMethod java/util/List.get:(I)Ljava/lang/Object;
     214: checkcast     #20                 // class org/apache/commons/math3/util/Pair
     217: invokevirtual #30                 // Method org/apache/commons/math3/util/Pair.getFirst:()Ljava/lang/Object;
     220: checkcast     #31                 // class java/lang/Double
     223: invokevirtual #32                 // Method java/lang/Double.doubleValue:()D
     226: dastore
     227: aload         16
     229: iload         17
     231: aload         14
     233: iload         17
     235: invokeinterface #19,  2           // InterfaceMethod java/util/List.get:(I)Ljava/lang/Object;
     240: checkcast     #20                 // class org/apache/commons/math3/util/Pair
     243: invokevirtual #21                 // Method org/apache/commons/math3/util/Pair.getSecond:()Ljava/lang/Object;
     246: checkcast     #22                 // class org/apache/commons/math3/distribution/MultivariateNormalDistribution
     249: aastore
     250: iinc          17, 1
     253: goto          194
     256: iload         5
     258: iload         7
     260: multianewarray #6,  2             // class "[[D"
     264: astore        17
     266: iload         7
     268: newarray       double
     270: astore        18
     272: iload         7
     274: iload         6
     276: multianewarray #6,  2             // class "[[D"
     280: astore        19
     282: iconst_0
     283: istore        20
     285: iload         20
     287: iload         5
     289: if_icmpge     434
     292: aload_0
     293: getfield      #28                 // Field fittedModel:Lorg/apache/commons/math3/distribution/MixtureMultivariateNormalDistribution;
     296: aload_0
     297: getfield      #7                  // Field data:[[D
     300: iload         20
     302: aaload
     303: invokevirtual #33                 // Method org/apache/commons/math3/distribution/MixtureMultivariateNormalDistribution.density:([D)D
     306: dstore        21
     308: dload         12
     310: dload         21
     312: invokestatic  #34                 // Method org/apache/commons/math3/util/FastMath.log:(D)D
     315: dadd
     316: dstore        12
     318: iconst_0
     319: istore        23
     321: iload         23
     323: iload         7
     325: if_icmpge     428
     328: aload         17
     330: iload         20
     332: aaload
     333: iload         23
     335: aload         15
     337: iload         23
     339: daload
     340: aload         16
     342: iload         23
     344: aaload
     345: aload_0
     346: getfield      #7                  // Field data:[[D
     349: iload         20
     351: aaload
     352: invokevirtual #35                 // Method org/apache/commons/math3/distribution/MultivariateNormalDistribution.density:([D)D
     355: dmul
     356: dload         21
     358: ddiv
     359: dastore
     360: aload         18
     362: iload         23
     364: dup2
     365: daload
     366: aload         17
     368: iload         20
     370: aaload
     371: iload         23
     373: daload
     374: dadd
     375: dastore
     376: iconst_0
     377: istore        24
     379: iload         24
     381: iload         6
     383: if_icmpge     422
     386: aload         19
     388: iload         23
     390: aaload
     391: iload         24
     393: dup2
     394: daload
     395: aload         17
     397: iload         20
     399: aaload
     400: iload         23
     402: daload
     403: aload_0
     404: getfield      #7                  // Field data:[[D
     407: iload         20
     409: aaload
     410: iload         24
     412: daload
     413: dmul
     414: dadd
     415: dastore
     416: iinc          24, 1
     419: goto          379
     422: iinc          23, 1
     425: goto          321
     428: iinc          20, 1
     431: goto          285
     434: aload_0
     435: dload         12
     437: iload         5
     439: i2d
     440: ddiv
     441: putfield      #2                  // Field logLikelihood:D
     444: iload         7
     446: newarray       double
     448: astore        20
     450: iload         7
     452: iload         6
     454: multianewarray #6,  2             // class "[[D"
     458: astore        21
     460: iconst_0
     461: istore        22
     463: iload         22
     465: iload         7
     467: if_icmpge     528
     470: aload         20
     472: iload         22
     474: aload         18
     476: iload         22
     478: daload
     479: iload         5
     481: i2d
     482: ddiv
     483: dastore
     484: iconst_0
     485: istore        23
     487: iload         23
     489: iload         6
     491: if_icmpge     522
     494: aload         21
     496: iload         22
     498: aaload
     499: iload         23
     501: aload         19
     503: iload         22
     505: aaload
     506: iload         23
     508: daload
     509: aload         18
     511: iload         22
     513: daload
     514: ddiv
     515: dastore
     516: iinc          23, 1
     519: goto          487
     522: iinc          22, 1
     525: goto          463
     528: iload         7
     530: anewarray     #36                 // class org/apache/commons/math3/linear/RealMatrix
     533: astore        22
     535: iconst_0
     536: istore        23
     538: iload         23
     540: iload         7
     542: if_icmpge     567
     545: aload         22
     547: iload         23
     549: new           #37                 // class org/apache/commons/math3/linear/Array2DRowRealMatrix
     552: dup
     553: iload         6
     555: iload         6
     557: invokespecial #38                 // Method org/apache/commons/math3/linear/Array2DRowRealMatrix."<init>":(II)V
     560: aastore
     561: iinc          23, 1
     564: goto          538
     567: iconst_0
     568: istore        23
     570: iload         23
     572: iload         5
     574: if_icmpge     669
     577: iconst_0
     578: istore        24
     580: iload         24
     582: iload         7
     584: if_icmpge     663
     587: new           #37                 // class org/apache/commons/math3/linear/Array2DRowRealMatrix
     590: dup
     591: aload_0
     592: getfield      #7                  // Field data:[[D
     595: iload         23
     597: aaload
     598: aload         21
     600: iload         24
     602: aaload
     603: invokestatic  #39                 // Method org/apache/commons/math3/util/MathArrays.ebeSubtract:([D[D)[D
     606: invokespecial #40                 // Method org/apache/commons/math3/linear/Array2DRowRealMatrix."<init>":([D)V
     609: astore        25
     611: aload         25
     613: aload         25
     615: invokeinterface #41,  1           // InterfaceMethod org/apache/commons/math3/linear/RealMatrix.transpose:()Lorg/apache/commons/math3/linear/RealMatrix;
     620: invokeinterface #42,  2           // InterfaceMethod org/apache/commons/math3/linear/RealMatrix.multiply:(Lorg/apache/commons/math3/linear/RealMatrix;)Lorg/apache/commons/math3/linear/RealMatrix;
     625: aload         17
     627: iload         23
     629: aaload
     630: iload         24
     632: daload
     633: invokeinterface #43,  3           // InterfaceMethod org/apache/commons/math3/linear/RealMatrix.scalarMultiply:(D)Lorg/apache/commons/math3/linear/RealMatrix;
     638: astore        26
     640: aload         22
     642: iload         24
     644: aload         22
     646: iload         24
     648: aaload
     649: aload         26
     651: invokeinterface #44,  2           // InterfaceMethod org/apache/commons/math3/linear/RealMatrix.add:(Lorg/apache/commons/math3/linear/RealMatrix;)Lorg/apache/commons/math3/linear/RealMatrix;
     656: aastore
     657: iinc          24, 1
     660: goto          580
     663: iinc          23, 1
     666: goto          570
     669: iload         7
     671: iload         6
     673: iload         6
     675: multianewarray #45,  3            // class "[[[D"
     679: astore        23
     681: iconst_0
     682: istore        24
     684: iload         24
     686: iload         7
     688: if_icmpge     734
     691: aload         22
     693: iload         24
     695: aload         22
     697: iload         24
     699: aaload
     700: dconst_1
     701: aload         18
     703: iload         24
     705: daload
     706: ddiv
     707: invokeinterface #43,  3           // InterfaceMethod org/apache/commons/math3/linear/RealMatrix.scalarMultiply:(D)Lorg/apache/commons/math3/linear/RealMatrix;
     712: aastore
     713: aload         23
     715: iload         24
     717: aload         22
     719: iload         24
     721: aaload
     722: invokeinterface #46,  1           // InterfaceMethod org/apache/commons/math3/linear/RealMatrix.getData:()[[D
     727: aastore
     728: iinc          24, 1
     731: goto          684
     734: aload_0
     735: new           #26                 // class org/apache/commons/math3/distribution/MixtureMultivariateNormalDistribution
     738: dup
     739: aload         20
     741: aload         21
     743: aload         23
     745: invokespecial #47                 // Method org/apache/commons/math3/distribution/MixtureMultivariateNormalDistribution."<init>":([D[[D[[[D)V
     748: putfield      #28                 // Field fittedModel:Lorg/apache/commons/math3/distribution/MixtureMultivariateNormalDistribution;
     751: goto          136
     754: dload         10
     756: aload_0
     757: getfield      #2                  // Field logLikelihood:D
     760: dsub
     761: invokestatic  #29                 // Method org/apache/commons/math3/util/FastMath.abs:(D)D
     764: dload_3
     765: dcmpl
     766: ifle          777
     769: new           #48                 // class org/apache/commons/math3/exception/ConvergenceException
     772: dup
     773: invokespecial #49                 // Method org/apache/commons/math3/exception/ConvergenceException."<init>":()V
     776: athrow
     777: return

  public void fit(org.apache.commons.math3.distribution.MixtureMultivariateNormalDistribution) throws org.apache.commons.math3.linear.SingularMatrixException, org.apache.commons.math3.exception.NotStrictlyPositiveException;
    Code:
       0: aload_0
       1: aload_1
       2: sipush        1000
       5: ldc2_w        #50                 // double 1.0E-5d
       8: invokevirtual #52                 // Method fit:(Lorg/apache/commons/math3/distribution/MixtureMultivariateNormalDistribution;ID)V
      11: return

  public static org.apache.commons.math3.distribution.MixtureMultivariateNormalDistribution estimate(double[][], int) throws org.apache.commons.math3.exception.NotStrictlyPositiveException, org.apache.commons.math3.exception.DimensionMismatchException;
    Code:
       0: aload_0
       1: arraylength
       2: iconst_2
       3: if_icmpge     19
       6: new           #3                  // class org/apache/commons/math3/exception/NotStrictlyPositiveException
       9: dup
      10: aload_0
      11: arraylength
      12: invokestatic  #4                  // Method java/lang/Integer.valueOf:(I)Ljava/lang/Integer;
      15: invokespecial #5                  // Method org/apache/commons/math3/exception/NotStrictlyPositiveException."<init>":(Ljava/lang/Number;)V
      18: athrow
      19: iload_1
      20: iconst_2
      21: if_icmpge     41
      24: new           #10                 // class org/apache/commons/math3/exception/NumberIsTooSmallException
      27: dup
      28: iload_1
      29: invokestatic  #4                  // Method java/lang/Integer.valueOf:(I)Ljava/lang/Integer;
      32: iconst_2
      33: invokestatic  #4                  // Method java/lang/Integer.valueOf:(I)Ljava/lang/Integer;
      36: iconst_1
      37: invokespecial #53                 // Method org/apache/commons/math3/exception/NumberIsTooSmallException."<init>":(Ljava/lang/Number;Ljava/lang/Number;Z)V
      40: athrow
      41: iload_1
      42: aload_0
      43: arraylength
      44: if_icmple     65
      47: new           #54                 // class org/apache/commons/math3/exception/NumberIsTooLargeException
      50: dup
      51: iload_1
      52: invokestatic  #4                  // Method java/lang/Integer.valueOf:(I)Ljava/lang/Integer;
      55: aload_0
      56: arraylength
      57: invokestatic  #4                  // Method java/lang/Integer.valueOf:(I)Ljava/lang/Integer;
      60: iconst_1
      61: invokespecial #55                 // Method org/apache/commons/math3/exception/NumberIsTooLargeException."<init>":(Ljava/lang/Number;Ljava/lang/Number;Z)V
      64: athrow
      65: aload_0
      66: arraylength
      67: istore_2
      68: aload_0
      69: iconst_0
      70: aaload
      71: arraylength
      72: istore_3
      73: iload_2
      74: anewarray     #56                 // class org/apache/commons/math3/distribution/fitting/MultivariateNormalMixtureExpectationMaximization$DataRow
      77: astore        4
      79: iconst_0
      80: istore        5
      82: iload         5
      84: iload_2
      85: if_icmpge     110
      88: aload         4
      90: iload         5
      92: new           #56                 // class org/apache/commons/math3/distribution/fitting/MultivariateNormalMixtureExpectationMaximization$DataRow
      95: dup
      96: aload_0
      97: iload         5
      99: aaload
     100: invokespecial #57                 // Method org/apache/commons/math3/distribution/fitting/MultivariateNormalMixtureExpectationMaximization$DataRow."<init>":([D)V
     103: aastore
     104: iinc          5, 1
     107: goto          82
     110: aload         4
     112: invokestatic  #58                 // Method java/util/Arrays.sort:([Ljava/lang/Object;)V
     115: dconst_1
     116: iload_1
     117: i2d
     118: ddiv
     119: dstore        5
     121: new           #59                 // class java/util/ArrayList
     124: dup
     125: iload_1
     126: invokespecial #60                 // Method java/util/ArrayList."<init>":(I)V
     129: astore        7
     131: iconst_0
     132: istore        8
     134: iload         8
     136: iload_1
     137: if_icmpge     320
     140: iload         8
     142: iload_2
     143: imul
     144: iload_1
     145: idiv
     146: istore        9
     148: iload         8
     150: iconst_1
     151: iadd
     152: iload_2
     153: imul
     154: iload_1
     155: idiv
     156: istore        10
     158: iload         10
     160: iload         9
     162: isub
     163: istore        11
     165: iload         11
     167: iload_3
     168: multianewarray #6,  2             // class "[[D"
     172: astore        12
     174: iload_3
     175: newarray       double
     177: astore        13
     179: iload         9
     181: istore        14
     183: iconst_0
     184: istore        15
     186: iload         14
     188: iload         10
     190: if_icmpge     250
     193: iconst_0
     194: istore        16
     196: iload         16
     198: iload_3
     199: if_icmpge     241
     202: aload         4
     204: iload         14
     206: aaload
     207: invokevirtual #61                 // Method org/apache/commons/math3/distribution/fitting/MultivariateNormalMixtureExpectationMaximization$DataRow.getRow:()[D
     210: iload         16
     212: daload
     213: dstore        17
     215: aload         13
     217: iload         16
     219: dup2
     220: daload
     221: dload         17
     223: dadd
     224: dastore
     225: aload         12
     227: iload         15
     229: aaload
     230: iload         16
     232: dload         17
     234: dastore
     235: iinc          16, 1
     238: goto          196
     241: iinc          14, 1
     244: iinc          15, 1
     247: goto          186
     250: dconst_1
     251: iload         11
     253: i2d
     254: ddiv
     255: aload         13
     257: invokestatic  #62                 // Method org/apache/commons/math3/util/MathArrays.scaleInPlace:(D[D)V
     260: new           #63                 // class org/apache/commons/math3/stat/correlation/Covariance
     263: dup
     264: aload         12
     266: invokespecial #64                 // Method org/apache/commons/math3/stat/correlation/Covariance."<init>":([[D)V
     269: invokevirtual #65                 // Method org/apache/commons/math3/stat/correlation/Covariance.getCovarianceMatrix:()Lorg/apache/commons/math3/linear/RealMatrix;
     272: invokeinterface #46,  1           // InterfaceMethod org/apache/commons/math3/linear/RealMatrix.getData:()[[D
     277: astore        14
     279: new           #22                 // class org/apache/commons/math3/distribution/MultivariateNormalDistribution
     282: dup
     283: aload         13
     285: aload         14
     287: invokespecial #66                 // Method org/apache/commons/math3/distribution/MultivariateNormalDistribution."<init>":([D[[D)V
     290: astore        15
     292: aload         7
     294: new           #20                 // class org/apache/commons/math3/util/Pair
     297: dup
     298: dload         5
     300: invokestatic  #16                 // Method java/lang/Double.valueOf:(D)Ljava/lang/Double;
     303: aload         15
     305: invokespecial #67                 // Method org/apache/commons/math3/util/Pair."<init>":(Ljava/lang/Object;Ljava/lang/Object;)V
     308: invokeinterface #68,  2           // InterfaceMethod java/util/List.add:(Ljava/lang/Object;)Z
     313: pop
     314: iinc          8, 1
     317: goto          134
     320: new           #26                 // class org/apache/commons/math3/distribution/MixtureMultivariateNormalDistribution
     323: dup
     324: aload         7
     326: invokespecial #27                 // Method org/apache/commons/math3/distribution/MixtureMultivariateNormalDistribution."<init>":(Ljava/util/List;)V
     329: areturn

  public double getLogLikelihood();
    Code:
       0: aload_0
       1: getfield      #2                  // Field logLikelihood:D
       4: dreturn

  public org.apache.commons.math3.distribution.MixtureMultivariateNormalDistribution getFittedModel();
    Code:
       0: new           #26                 // class org/apache/commons/math3/distribution/MixtureMultivariateNormalDistribution
       3: dup
       4: aload_0
       5: getfield      #28                 // Field fittedModel:Lorg/apache/commons/math3/distribution/MixtureMultivariateNormalDistribution;
       8: invokevirtual #17                 // Method org/apache/commons/math3/distribution/MixtureMultivariateNormalDistribution.getComponents:()Ljava/util/List;
      11: invokespecial #27                 // Method org/apache/commons/math3/distribution/MixtureMultivariateNormalDistribution."<init>":(Ljava/util/List;)V
      14: areturn
}
