Compiled from "AnnotationValue.java"
final class org.jboss.jandex.AnnotationValue$NestedAnnotation extends org.jboss.jandex.AnnotationValue {
  private final org.jboss.jandex.AnnotationInstance value;

  org.jboss.jandex.AnnotationValue$NestedAnnotation(java.lang.String, org.jboss.jandex.AnnotationInstance);
    Code:
       0: aload_0
       1: aload_1
       2: invokespecial #1                  // Method org/jboss/jandex/AnnotationValue."<init>":(Ljava/lang/String;)V
       5: aload_0
       6: aload_2
       7: putfield      #2                  // Field value:Lorg/jboss/jandex/AnnotationInstance;
      10: return

  public org.jboss.jandex.AnnotationInstance value();
    Code:
       0: aload_0
       1: getfield      #2                  // Field value:Lorg/jboss/jandex/AnnotationInstance;
       4: areturn

  public org.jboss.jandex.AnnotationInstance asNested();
    Code:
       0: aload_0
       1: getfield      #2                  // Field value:Lorg/jboss/jandex/AnnotationInstance;
       4: areturn

  public java.lang.Object value();
    Code:
       0: aload_0
       1: invokevirtual #3                  // Method value:()Lorg/jboss/jandex/AnnotationInstance;
       4: areturn
}
