Compiled from "ClassInfo.java"
public final class org.jboss.jandex.ClassInfo implements org.jboss.jandex.AnnotationTarget {
  private final org.jboss.jandex.DotName name;

  private short flags;

  private final org.jboss.jandex.DotName superName;

  private final org.jboss.jandex.DotName[] interfaces;

  private final java.util.Map<org.jboss.jandex.DotName, java.util.List<org.jboss.jandex.AnnotationInstance>> annotations;

  org.jboss.jandex.ClassInfo(org.jboss.jandex.DotName, org.jboss.jandex.DotName, short, org.jboss.jandex.DotName[], java.util.Map<org.jboss.jandex.DotName, java.util.List<org.jboss.jandex.AnnotationInstance>>);
    Code:
       0: aload_0
       1: invokespecial #1                  // Method java/lang/Object."<init>":()V
       4: aload_0
       5: aload_1
       6: putfield      #2                  // Field name:Lorg/jboss/jandex/DotName;
       9: aload_0
      10: aload_2
      11: putfield      #3                  // Field superName:Lorg/jboss/jandex/DotName;
      14: aload_0
      15: iload_3
      16: putfield      #4                  // Field flags:S
      19: aload_0
      20: aload         4
      22: putfield      #5                  // Field interfaces:[Lorg/jboss/jandex/DotName;
      25: aload_0
      26: aload         5
      28: invokestatic  #6                  // Method java/util/Collections.unmodifiableMap:(Ljava/util/Map;)Ljava/util/Map;
      31: putfield      #7                  // Field annotations:Ljava/util/Map;
      34: return

  public static final org.jboss.jandex.ClassInfo create(org.jboss.jandex.DotName, org.jboss.jandex.DotName, short, org.jboss.jandex.DotName[], java.util.Map<org.jboss.jandex.DotName, java.util.List<org.jboss.jandex.AnnotationInstance>>);
    Code:
       0: new           #8                  // class org/jboss/jandex/ClassInfo
       3: dup
       4: aload_0
       5: aload_1
       6: iload_2
       7: aload_3
       8: aload         4
      10: invokespecial #9                  // Method "<init>":(Lorg/jboss/jandex/DotName;Lorg/jboss/jandex/DotName;S[Lorg/jboss/jandex/DotName;Ljava/util/Map;)V
      13: areturn

  public java.lang.String toString();
    Code:
       0: aload_0
       1: getfield      #2                  // Field name:Lorg/jboss/jandex/DotName;
       4: invokevirtual #10                 // Method org/jboss/jandex/DotName.toString:()Ljava/lang/String;
       7: areturn

  public final org.jboss.jandex.DotName name();
    Code:
       0: aload_0
       1: getfield      #2                  // Field name:Lorg/jboss/jandex/DotName;
       4: areturn

  public final short flags();
    Code:
       0: aload_0
       1: getfield      #4                  // Field flags:S
       4: ireturn

  public final org.jboss.jandex.DotName superName();
    Code:
       0: aload_0
       1: getfield      #3                  // Field superName:Lorg/jboss/jandex/DotName;
       4: areturn

  public final org.jboss.jandex.DotName[] interfaces();
    Code:
       0: aload_0
       1: getfield      #5                  // Field interfaces:[Lorg/jboss/jandex/DotName;
       4: areturn

  public final java.util.Map<org.jboss.jandex.DotName, java.util.List<org.jboss.jandex.AnnotationInstance>> annotations();
    Code:
       0: aload_0
       1: getfield      #7                  // Field annotations:Ljava/util/Map;
       4: areturn
}
