Compiled from "CompositeParameterList.java"
class org.postgresql.core.v3.CompositeParameterList implements org.postgresql.core.v3.V3ParameterList {
  private final int total;

  private final org.postgresql.core.v3.SimpleParameterList[] subparams;

  private final int[] offsets;

  org.postgresql.core.v3.CompositeParameterList(org.postgresql.core.v3.SimpleParameterList[], int[]);
    Code:
       0: aload_0
       1: invokespecial #18                 // Method java/lang/Object."<init>":()V
       4: aload_0
       5: aload_1
       6: putfield      #20                 // Field subparams:[Lorg/postgresql/core/v3/SimpleParameterList;
       9: aload_0
      10: aload_2
      11: putfield      #22                 // Field offsets:[I
      14: aload_0
      15: aload_2
      16: aload_2
      17: arraylength
      18: iconst_1
      19: isub
      20: iaload
      21: aload_1
      22: aload_2
      23: arraylength
      24: iconst_1
      25: isub
      26: aaload
      27: invokevirtual #28                 // Method org/postgresql/core/v3/SimpleParameterList.getInParameterCount:()I
      30: iadd
      31: putfield      #30                 // Field total:I
      34: return

  private int findSubParam(int) throws java.sql.SQLException;
    Code:
       0: iload_1
       1: iconst_1
       2: if_icmplt     13
       5: iload_1
       6: aload_0
       7: getfield      #30                 // Field total:I
      10: if_icmple     50
      13: new           #38                 // class org/postgresql/util/PSQLException
      16: dup
      17: ldc           #40                 // String The column index is out of range: {0}, number of columns: {1}.
      19: iconst_2
      20: anewarray     #4                  // class java/lang/Object
      23: dup
      24: iconst_0
      25: iload_1
      26: invokestatic  #46                 // Method java/lang/Integer.valueOf:(I)Ljava/lang/Integer;
      29: aastore
      30: dup
      31: iconst_1
      32: aload_0
      33: getfield      #30                 // Field total:I
      36: invokestatic  #46                 // Method java/lang/Integer.valueOf:(I)Ljava/lang/Integer;
      39: aastore
      40: invokestatic  #52                 // Method org/postgresql/util/GT.tr:(Ljava/lang/String;[Ljava/lang/Object;)Ljava/lang/String;
      43: getstatic     #58                 // Field org/postgresql/util/PSQLState.INVALID_PARAMETER_VALUE:Lorg/postgresql/util/PSQLState;
      46: invokespecial #61                 // Method org/postgresql/util/PSQLException."<init>":(Ljava/lang/String;Lorg/postgresql/util/PSQLState;)V
      49: athrow
      50: aload_0
      51: getfield      #22                 // Field offsets:[I
      54: arraylength
      55: iconst_1
      56: isub
      57: istore_2
      58: iload_2
      59: iflt          80
      62: aload_0
      63: getfield      #22                 // Field offsets:[I
      66: iload_2
      67: iaload
      68: iload_1
      69: if_icmpge     74
      72: iload_2
      73: ireturn
      74: iinc          2, -1
      77: goto          58
      80: new           #63                 // class java/lang/IllegalArgumentException
      83: dup
      84: new           #65                 // class java/lang/StringBuilder
      87: dup
      88: invokespecial #66                 // Method java/lang/StringBuilder."<init>":()V
      91: ldc           #68                 // String I am confused; can\'t find a subparam for index
      93: invokevirtual #72                 // Method java/lang/StringBuilder.append:(Ljava/lang/String;)Ljava/lang/StringBuilder;
      96: iload_1
      97: invokevirtual #75                 // Method java/lang/StringBuilder.append:(I)Ljava/lang/StringBuilder;
     100: invokevirtual #79                 // Method java/lang/StringBuilder.toString:()Ljava/lang/String;
     103: invokespecial #82                 // Method java/lang/IllegalArgumentException."<init>":(Ljava/lang/String;)V
     106: athrow

  public void registerOutParameter(int, int);
    Code:
       0: return

  public int getDirection(int);
    Code:
       0: iconst_0
       1: ireturn

  public int getParameterCount();
    Code:
       0: aload_0
       1: getfield      #30                 // Field total:I
       4: ireturn

  public int getInParameterCount();
    Code:
       0: aload_0
       1: getfield      #30                 // Field total:I
       4: ireturn

  public int getOutParameterCount();
    Code:
       0: iconst_0
       1: ireturn

  public int[] getTypeOIDs();
    Code:
       0: aload_0
       1: getfield      #30                 // Field total:I
       4: newarray       int
       6: astore_1
       7: iconst_0
       8: istore_2
       9: iload_2
      10: aload_0
      11: getfield      #22                 // Field offsets:[I
      14: arraylength
      15: if_icmpge     48
      18: aload_0
      19: getfield      #20                 // Field subparams:[Lorg/postgresql/core/v3/SimpleParameterList;
      22: iload_2
      23: aaload
      24: invokevirtual #95                 // Method org/postgresql/core/v3/SimpleParameterList.getTypeOIDs:()[I
      27: astore_3
      28: aload_3
      29: iconst_0
      30: aload_1
      31: aload_0
      32: getfield      #22                 // Field offsets:[I
      35: iload_2
      36: iaload
      37: aload_3
      38: arraylength
      39: invokestatic  #101                // Method java/lang/System.arraycopy:(Ljava/lang/Object;ILjava/lang/Object;II)V
      42: iinc          2, 1
      45: goto          9
      48: aload_1
      49: areturn

  public void setIntParameter(int, int) throws java.sql.SQLException;
    Code:
       0: aload_0
       1: iload_1
       2: invokespecial #106                // Method findSubParam:(I)I
       5: istore_3
       6: aload_0
       7: getfield      #20                 // Field subparams:[Lorg/postgresql/core/v3/SimpleParameterList;
      10: iload_3
      11: aaload
      12: iload_1
      13: aload_0
      14: getfield      #22                 // Field offsets:[I
      17: iload_3
      18: iaload
      19: isub
      20: iload_2
      21: invokevirtual #108                // Method org/postgresql/core/v3/SimpleParameterList.setIntParameter:(II)V
      24: return

  public void setLiteralParameter(int, java.lang.String, int) throws java.sql.SQLException;
    Code:
       0: aload_0
       1: iload_1
       2: invokespecial #106                // Method findSubParam:(I)I
       5: istore        4
       7: aload_0
       8: getfield      #20                 // Field subparams:[Lorg/postgresql/core/v3/SimpleParameterList;
      11: iload         4
      13: aaload
      14: iload_1
      15: aload_0
      16: getfield      #22                 // Field offsets:[I
      19: iload         4
      21: iaload
      22: isub
      23: aload_2
      24: iload_3
      25: invokevirtual #115                // Method org/postgresql/core/v3/SimpleParameterList.setStringParameter:(ILjava/lang/String;I)V
      28: return

  public void setStringParameter(int, java.lang.String, int) throws java.sql.SQLException;
    Code:
       0: aload_0
       1: iload_1
       2: invokespecial #106                // Method findSubParam:(I)I
       5: istore        4
       7: aload_0
       8: getfield      #20                 // Field subparams:[Lorg/postgresql/core/v3/SimpleParameterList;
      11: iload         4
      13: aaload
      14: iload_1
      15: aload_0
      16: getfield      #22                 // Field offsets:[I
      19: iload         4
      21: iaload
      22: isub
      23: aload_2
      24: iload_3
      25: invokevirtual #115                // Method org/postgresql/core/v3/SimpleParameterList.setStringParameter:(ILjava/lang/String;I)V
      28: return

  public void setBinaryParameter(int, byte[], int) throws java.sql.SQLException;
    Code:
       0: aload_0
       1: iload_1
       2: invokespecial #106                // Method findSubParam:(I)I
       5: istore        4
       7: aload_0
       8: getfield      #20                 // Field subparams:[Lorg/postgresql/core/v3/SimpleParameterList;
      11: iload         4
      13: aaload
      14: iload_1
      15: aload_0
      16: getfield      #22                 // Field offsets:[I
      19: iload         4
      21: iaload
      22: isub
      23: aload_2
      24: iload_3
      25: invokevirtual #121                // Method org/postgresql/core/v3/SimpleParameterList.setBinaryParameter:(I[BI)V
      28: return

  public void setBytea(int, byte[], int, int) throws java.sql.SQLException;
    Code:
       0: aload_0
       1: iload_1
       2: invokespecial #106                // Method findSubParam:(I)I
       5: istore        5
       7: aload_0
       8: getfield      #20                 // Field subparams:[Lorg/postgresql/core/v3/SimpleParameterList;
      11: iload         5
      13: aaload
      14: iload_1
      15: aload_0
      16: getfield      #22                 // Field offsets:[I
      19: iload         5
      21: iaload
      22: isub
      23: aload_2
      24: iload_3
      25: iload         4
      27: invokevirtual #126                // Method org/postgresql/core/v3/SimpleParameterList.setBytea:(I[BII)V
      30: return

  public void setBytea(int, java.io.InputStream, int) throws java.sql.SQLException;
    Code:
       0: aload_0
       1: iload_1
       2: invokespecial #106                // Method findSubParam:(I)I
       5: istore        4
       7: aload_0
       8: getfield      #20                 // Field subparams:[Lorg/postgresql/core/v3/SimpleParameterList;
      11: iload         4
      13: aaload
      14: iload_1
      15: aload_0
      16: getfield      #22                 // Field offsets:[I
      19: iload         4
      21: iaload
      22: isub
      23: aload_2
      24: iload_3
      25: invokevirtual #132                // Method org/postgresql/core/v3/SimpleParameterList.setBytea:(ILjava/io/InputStream;I)V
      28: return

  public void setBytea(int, java.io.InputStream) throws java.sql.SQLException;
    Code:
       0: aload_0
       1: iload_1
       2: invokespecial #106                // Method findSubParam:(I)I
       5: istore_3
       6: aload_0
       7: getfield      #20                 // Field subparams:[Lorg/postgresql/core/v3/SimpleParameterList;
      10: iload_3
      11: aaload
      12: iload_1
      13: aload_0
      14: getfield      #22                 // Field offsets:[I
      17: iload_3
      18: iaload
      19: isub
      20: aload_2
      21: invokevirtual #137                // Method org/postgresql/core/v3/SimpleParameterList.setBytea:(ILjava/io/InputStream;)V
      24: return

  public void setText(int, java.io.InputStream) throws java.sql.SQLException;
    Code:
       0: aload_0
       1: iload_1
       2: invokespecial #106                // Method findSubParam:(I)I
       5: istore_3
       6: aload_0
       7: getfield      #20                 // Field subparams:[Lorg/postgresql/core/v3/SimpleParameterList;
      10: iload_3
      11: aaload
      12: iload_1
      13: aload_0
      14: getfield      #22                 // Field offsets:[I
      17: iload_3
      18: iaload
      19: isub
      20: aload_2
      21: invokevirtual #140                // Method org/postgresql/core/v3/SimpleParameterList.setText:(ILjava/io/InputStream;)V
      24: return

  public void setNull(int, int) throws java.sql.SQLException;
    Code:
       0: aload_0
       1: iload_1
       2: invokespecial #106                // Method findSubParam:(I)I
       5: istore_3
       6: aload_0
       7: getfield      #20                 // Field subparams:[Lorg/postgresql/core/v3/SimpleParameterList;
      10: iload_3
      11: aaload
      12: iload_1
      13: aload_0
      14: getfield      #22                 // Field offsets:[I
      17: iload_3
      18: iaload
      19: isub
      20: iload_2
      21: invokevirtual #143                // Method org/postgresql/core/v3/SimpleParameterList.setNull:(II)V
      24: return

  public java.lang.String toString(int, boolean);
    Code:
       0: aload_0
       1: iload_1
       2: invokespecial #106                // Method findSubParam:(I)I
       5: istore_3
       6: aload_0
       7: getfield      #20                 // Field subparams:[Lorg/postgresql/core/v3/SimpleParameterList;
      10: iload_3
      11: aaload
      12: iload_1
      13: aload_0
      14: getfield      #22                 // Field offsets:[I
      17: iload_3
      18: iaload
      19: isub
      20: iload_2
      21: invokevirtual #146                // Method org/postgresql/core/v3/SimpleParameterList.toString:(IZ)Ljava/lang/String;
      24: areturn
      25: astore_3
      26: new           #148                // class java/lang/IllegalStateException
      29: dup
      30: aload_3
      31: invokevirtual #151                // Method java/sql/SQLException.getMessage:()Ljava/lang/String;
      34: invokespecial #152                // Method java/lang/IllegalStateException."<init>":(Ljava/lang/String;)V
      37: athrow
    Exception table:
       from    to  target type
           0    24    25   Class java/sql/SQLException

  public org.postgresql.core.ParameterList copy();
    Code:
       0: aload_0
       1: getfield      #20                 // Field subparams:[Lorg/postgresql/core/v3/SimpleParameterList;
       4: arraylength
       5: anewarray     #24                 // class org/postgresql/core/v3/SimpleParameterList
       8: astore_1
       9: iconst_0
      10: istore_2
      11: iload_2
      12: aload_0
      13: getfield      #20                 // Field subparams:[Lorg/postgresql/core/v3/SimpleParameterList;
      16: arraylength
      17: if_icmpge     41
      20: aload_1
      21: iload_2
      22: aload_0
      23: getfield      #20                 // Field subparams:[Lorg/postgresql/core/v3/SimpleParameterList;
      26: iload_2
      27: aaload
      28: invokevirtual #161                // Method org/postgresql/core/v3/SimpleParameterList.copy:()Lorg/postgresql/core/ParameterList;
      31: checkcast     #24                 // class org/postgresql/core/v3/SimpleParameterList
      34: aastore
      35: iinc          2, 1
      38: goto          11
      41: new           #2                  // class org/postgresql/core/v3/CompositeParameterList
      44: dup
      45: aload_1
      46: aload_0
      47: getfield      #22                 // Field offsets:[I
      50: invokespecial #163                // Method "<init>":([Lorg/postgresql/core/v3/SimpleParameterList;[I)V
      53: areturn

  public void clear();
    Code:
       0: aload_0
       1: getfield      #20                 // Field subparams:[Lorg/postgresql/core/v3/SimpleParameterList;
       4: astore_1
       5: aload_1
       6: arraylength
       7: istore_2
       8: iconst_0
       9: istore_3
      10: iload_3
      11: iload_2
      12: if_icmpge     31
      15: aload_1
      16: iload_3
      17: aaload
      18: astore        4
      20: aload         4
      22: invokevirtual #167                // Method org/postgresql/core/v3/SimpleParameterList.clear:()V
      25: iinc          3, 1
      28: goto          10
      31: return

  public org.postgresql.core.v3.SimpleParameterList[] getSubparams();
    Code:
       0: aload_0
       1: getfield      #20                 // Field subparams:[Lorg/postgresql/core/v3/SimpleParameterList;
       4: areturn

  public void checkAllParametersSet() throws java.sql.SQLException;
    Code:
       0: aload_0
       1: getfield      #20                 // Field subparams:[Lorg/postgresql/core/v3/SimpleParameterList;
       4: astore_1
       5: aload_1
       6: arraylength
       7: istore_2
       8: iconst_0
       9: istore_3
      10: iload_3
      11: iload_2
      12: if_icmpge     31
      15: aload_1
      16: iload_3
      17: aaload
      18: astore        4
      20: aload         4
      22: invokevirtual #174                // Method org/postgresql/core/v3/SimpleParameterList.checkAllParametersSet:()V
      25: iinc          3, 1
      28: goto          10
      31: return

  public byte[][] getEncoding();
    Code:
       0: aconst_null
       1: checkcast     #178                // class "[[B"
       4: areturn

  public byte[] getFlags();
    Code:
       0: aconst_null
       1: areturn

  public int[] getParamTypes();
    Code:
       0: aconst_null
       1: areturn

  public java.lang.Object[] getValues();
    Code:
       0: aconst_null
       1: areturn

  public void appendAll(org.postgresql.core.ParameterList) throws java.sql.SQLException;
    Code:
       0: return

  public void convertFunctionOutParameters();
    Code:
       0: aload_0
       1: getfield      #20                 // Field subparams:[Lorg/postgresql/core/v3/SimpleParameterList;
       4: astore_1
       5: aload_1
       6: arraylength
       7: istore_2
       8: iconst_0
       9: istore_3
      10: iload_3
      11: iload_2
      12: if_icmpge     31
      15: aload_1
      16: iload_3
      17: aaload
      18: astore        4
      20: aload         4
      22: invokevirtual #190                // Method org/postgresql/core/v3/SimpleParameterList.convertFunctionOutParameters:()V
      25: iinc          3, 1
      28: goto          10
      31: return
}
