Compiled from "OpenSSLSessionContext.java"
final class org.apache.tomcat.util.net.openssl.OpenSSLSessionContext$EmptyEnumeration implements java.util.Enumeration<byte[]> {
  private org.apache.tomcat.util.net.openssl.OpenSSLSessionContext$EmptyEnumeration();
    Code:
       0: aload_0
       1: invokespecial #2                  // Method java/lang/Object."<init>":()V
       4: return

  public boolean hasMoreElements();
    Code:
       0: iconst_0
       1: ireturn

  public byte[] nextElement();
    Code:
       0: new           #3                  // class java/util/NoSuchElementException
       3: dup
       4: invokespecial #4                  // Method java/util/NoSuchElementException."<init>":()V
       7: athrow

  public java.lang.Object nextElement();
    Code:
       0: aload_0
       1: invokevirtual #5                  // Method nextElement:()[B
       4: areturn

  org.apache.tomcat.util.net.openssl.OpenSSLSessionContext$EmptyEnumeration(org.apache.tomcat.util.net.openssl.OpenSSLSessionContext$1);
    Code:
       0: aload_0
       1: invokespecial #1                  // Method "<init>":()V
       4: return
}
