Compiled from "WritePropertyIfAbsentAction.java"
public final class org.wildfly.security.manager.action.WritePropertyIfAbsentAction implements java.security.PrivilegedAction<java.lang.String> {
  private final java.lang.String propertyName;

  private final java.lang.String value;

  public org.wildfly.security.manager.action.WritePropertyIfAbsentAction(java.lang.String, java.lang.String);
    Code:
       0: aload_0
       1: invokespecial #1                  // Method java/lang/Object."<init>":()V
       4: aload_0
       5: aload_1
       6: putfield      #2                  // Field propertyName:Ljava/lang/String;
       9: aload_0
      10: aload_2
      11: putfield      #3                  // Field value:Ljava/lang/String;
      14: return

  public java.lang.String run();
    Code:
       0: invokestatic  #4                  // Method java/lang/System.getProperties:()Ljava/util/Properties;
       3: astore_1
       4: aload_1
       5: dup
       6: astore_2
       7: monitorenter
       8: aload_1
       9: aload_0
      10: getfield      #2                  // Field propertyName:Ljava/lang/String;
      13: invokevirtual #5                  // Method java/util/Properties.containsKey:(Ljava/lang/Object;)Z
      16: ifeq          30
      19: aload_1
      20: aload_0
      21: getfield      #2                  // Field propertyName:Ljava/lang/String;
      24: invokevirtual #6                  // Method java/util/Properties.getProperty:(Ljava/lang/String;)Ljava/lang/String;
      27: aload_2
      28: monitorexit
      29: areturn
      30: aload_1
      31: aload_0
      32: getfield      #2                  // Field propertyName:Ljava/lang/String;
      35: aload_0
      36: getfield      #3                  // Field value:Ljava/lang/String;
      39: invokevirtual #7                  // Method java/util/Properties.setProperty:(Ljava/lang/String;Ljava/lang/String;)Ljava/lang/Object;
      42: checkcast     #8                  // class java/lang/String
      45: aload_2
      46: monitorexit
      47: areturn
      48: astore_3
      49: aload_2
      50: monitorexit
      51: aload_3
      52: athrow
    Exception table:
       from    to  target type
           8    29    48   any
          30    47    48   any
          48    51    48   any

  public java.lang.Object run();
    Code:
       0: aload_0
       1: invokevirtual #9                  // Method run:()Ljava/lang/String;
       4: areturn
}
