Compiled from "SAXProperty.java"
public final class com.ctc.wstx.sax.SAXProperty {
  public static final java.lang.String STD_PROPERTY_PREFIX;

  static final java.util.HashMap sInstances;

  public static final com.ctc.wstx.sax.SAXProperty DECLARATION_HANDLER;

  public static final com.ctc.wstx.sax.SAXProperty DOCUMENT_XML_VERSION;

  public static final com.ctc.wstx.sax.SAXProperty DOM_NODE;

  public static final com.ctc.wstx.sax.SAXProperty LEXICAL_HANDLER;

  static final com.ctc.wstx.sax.SAXProperty XML_STRING;

  private final java.lang.String mSuffix;

  private com.ctc.wstx.sax.SAXProperty(java.lang.String);
    Code:
       0: aload_0
       1: invokespecial #1                  // Method java/lang/Object."<init>":()V
       4: aload_0
       5: aload_1
       6: putfield      #2                  // Field mSuffix:Ljava/lang/String;
       9: getstatic     #3                  // Field sInstances:Ljava/util/HashMap;
      12: aload_1
      13: aload_0
      14: invokevirtual #4                  // Method java/util/HashMap.put:(Ljava/lang/Object;Ljava/lang/Object;)Ljava/lang/Object;
      17: pop
      18: return

  public static com.ctc.wstx.sax.SAXProperty findByUri(java.lang.String);
    Code:
       0: aload_0
       1: ldc           #5                  // String http://xml.org/sax/properties/
       3: invokevirtual #6                  // Method java/lang/String.startsWith:(Ljava/lang/String;)Z
       6: ifeq          22
       9: aload_0
      10: ldc           #5                  // String http://xml.org/sax/properties/
      12: invokevirtual #7                  // Method java/lang/String.length:()I
      15: invokevirtual #8                  // Method java/lang/String.substring:(I)Ljava/lang/String;
      18: invokestatic  #9                  // Method findBySuffix:(Ljava/lang/String;)Lcom/ctc/wstx/sax/SAXProperty;
      21: areturn
      22: aconst_null
      23: areturn

  public static com.ctc.wstx.sax.SAXProperty findBySuffix(java.lang.String);
    Code:
       0: getstatic     #3                  // Field sInstances:Ljava/util/HashMap;
       3: aload_0
       4: invokevirtual #10                 // Method java/util/HashMap.get:(Ljava/lang/Object;)Ljava/lang/Object;
       7: checkcast     #11                 // class com/ctc/wstx/sax/SAXProperty
      10: areturn

  public java.lang.String getSuffix();
    Code:
       0: aload_0
       1: getfield      #2                  // Field mSuffix:Ljava/lang/String;
       4: areturn

  public java.lang.String toString();
    Code:
       0: new           #12                 // class java/lang/StringBuffer
       3: dup
       4: invokespecial #13                 // Method java/lang/StringBuffer."<init>":()V
       7: ldc           #5                  // String http://xml.org/sax/properties/
       9: invokevirtual #14                 // Method java/lang/StringBuffer.append:(Ljava/lang/String;)Ljava/lang/StringBuffer;
      12: aload_0
      13: getfield      #2                  // Field mSuffix:Ljava/lang/String;
      16: invokevirtual #14                 // Method java/lang/StringBuffer.append:(Ljava/lang/String;)Ljava/lang/StringBuffer;
      19: invokevirtual #15                 // Method java/lang/StringBuffer.toString:()Ljava/lang/String;
      22: areturn

  static {};
    Code:
       0: new           #16                 // class java/util/HashMap
       3: dup
       4: invokespecial #17                 // Method java/util/HashMap."<init>":()V
       7: putstatic     #3                  // Field sInstances:Ljava/util/HashMap;
      10: new           #11                 // class com/ctc/wstx/sax/SAXProperty
      13: dup
      14: ldc           #18                 // String declaration-handler
      16: invokespecial #19                 // Method "<init>":(Ljava/lang/String;)V
      19: putstatic     #20                 // Field DECLARATION_HANDLER:Lcom/ctc/wstx/sax/SAXProperty;
      22: new           #11                 // class com/ctc/wstx/sax/SAXProperty
      25: dup
      26: ldc           #21                 // String document-xml-version
      28: invokespecial #19                 // Method "<init>":(Ljava/lang/String;)V
      31: putstatic     #22                 // Field DOCUMENT_XML_VERSION:Lcom/ctc/wstx/sax/SAXProperty;
      34: new           #11                 // class com/ctc/wstx/sax/SAXProperty
      37: dup
      38: ldc           #23                 // String dom-node
      40: invokespecial #19                 // Method "<init>":(Ljava/lang/String;)V
      43: putstatic     #24                 // Field DOM_NODE:Lcom/ctc/wstx/sax/SAXProperty;
      46: new           #11                 // class com/ctc/wstx/sax/SAXProperty
      49: dup
      50: ldc           #25                 // String lexical-handler
      52: invokespecial #19                 // Method "<init>":(Ljava/lang/String;)V
      55: putstatic     #26                 // Field LEXICAL_HANDLER:Lcom/ctc/wstx/sax/SAXProperty;
      58: new           #11                 // class com/ctc/wstx/sax/SAXProperty
      61: dup
      62: ldc           #27                 // String xml-string
      64: invokespecial #19                 // Method "<init>":(Ljava/lang/String;)V
      67: putstatic     #28                 // Field XML_STRING:Lcom/ctc/wstx/sax/SAXProperty;
      70: return
}
