Compiled from "Yaml.java"
class io.kubernetes.client.util.Yaml$CustomRepresenter$RepresentDateTime implements org.yaml.snakeyaml.representer.Represent {
  final io.kubernetes.client.util.Yaml$CustomRepresenter this$0;

  private io.kubernetes.client.util.Yaml$CustomRepresenter$RepresentDateTime(io.kubernetes.client.util.Yaml$CustomRepresenter);
    Code:
       0: aload_0
       1: aload_1
       2: putfield      #2                  // Field this$0:Lio/kubernetes/client/util/Yaml$CustomRepresenter;
       5: aload_0
       6: invokespecial #3                  // Method java/lang/Object."<init>":()V
       9: return

  public org.yaml.snakeyaml.nodes.Node representData(java.lang.Object);
    Code:
       0: aload_0
       1: getfield      #2                  // Field this$0:Lio/kubernetes/client/util/Yaml$CustomRepresenter;
       4: aload_1
       5: invokevirtual #4                  // Method java/lang/Object.toString:()Ljava/lang/String;
       8: invokestatic  #5                  // Method io/kubernetes/client/util/Yaml$CustomRepresenter.access$400:(Lio/kubernetes/client/util/Yaml$CustomRepresenter;Ljava/lang/Object;)Lorg/yaml/snakeyaml/nodes/Node;
      11: areturn

  io.kubernetes.client.util.Yaml$CustomRepresenter$RepresentDateTime(io.kubernetes.client.util.Yaml$CustomRepresenter, io.kubernetes.client.util.Yaml$1);
    Code:
       0: aload_0
       1: aload_1
       2: invokespecial #1                  // Method "<init>":(Lio/kubernetes/client/util/Yaml$CustomRepresenter;)V
       5: return
}
