Compiled from "RemovePrefixMappingAction.java"
public class org.protege.editor.owl.ui.prefix.RemovePrefixMappingAction extends javax.swing.AbstractAction {
  private static final long serialVersionUID;

  private org.protege.editor.owl.ui.prefix.PrefixMapperTables tables;

  private org.protege.editor.owl.ui.prefix.PrefixMapperTable table;

  private javax.swing.event.ListSelectionListener tableSelectionListener;

  private org.protege.editor.owl.ui.prefix.PrefixMapperTables$SelectedOntologyListener ontologySelectionListener;

  public org.protege.editor.owl.ui.prefix.RemovePrefixMappingAction(org.protege.editor.owl.ui.prefix.PrefixMapperTables);
    Code:
       0: aload_0
       1: ldc           #5                  // String Remove prefix
       3: ldc           #6                  // String prefix.remove.png
       5: invokestatic  #7                  // Method org/protege/editor/owl/ui/OWLIcons.getIcon:(Ljava/lang/String;)Ljavax/swing/Icon;
       8: invokespecial #8                  // Method javax/swing/AbstractAction."<init>":(Ljava/lang/String;Ljavax/swing/Icon;)V
      11: aload_0
      12: aload_0
      13: invokedynamic #9,  0              // InvokeDynamic #0:valueChanged:(Lorg/protege/editor/owl/ui/prefix/RemovePrefixMappingAction;)Ljavax/swing/event/ListSelectionListener;
      18: putfield      #2                  // Field tableSelectionListener:Ljavax/swing/event/ListSelectionListener;
      21: aload_0
      22: new           #10                 // class org/protege/editor/owl/ui/prefix/RemovePrefixMappingAction$1
      25: dup
      26: aload_0
      27: invokespecial #11                 // Method org/protege/editor/owl/ui/prefix/RemovePrefixMappingAction$1."<init>":(Lorg/protege/editor/owl/ui/prefix/RemovePrefixMappingAction;)V
      30: putfield      #12                 // Field ontologySelectionListener:Lorg/protege/editor/owl/ui/prefix/PrefixMapperTables$SelectedOntologyListener;
      33: aload_0
      34: aload_1
      35: putfield      #1                  // Field tables:Lorg/protege/editor/owl/ui/prefix/PrefixMapperTables;
      38: aload_0
      39: aload_1
      40: invokevirtual #13                 // Method org/protege/editor/owl/ui/prefix/PrefixMapperTables.getPrefixMapperTable:()Lorg/protege/editor/owl/ui/prefix/PrefixMapperTable;
      43: putfield      #3                  // Field table:Lorg/protege/editor/owl/ui/prefix/PrefixMapperTable;
      46: aload_0
      47: getfield      #3                  // Field table:Lorg/protege/editor/owl/ui/prefix/PrefixMapperTable;
      50: invokevirtual #14                 // Method org/protege/editor/owl/ui/prefix/PrefixMapperTable.getSelectionModel:()Ljavax/swing/ListSelectionModel;
      53: aload_0
      54: getfield      #2                  // Field tableSelectionListener:Ljavax/swing/event/ListSelectionListener;
      57: invokeinterface #15,  2           // InterfaceMethod javax/swing/ListSelectionModel.addListSelectionListener:(Ljavax/swing/event/ListSelectionListener;)V
      62: aload_0
      63: invokespecial #4                  // Method updateEnabled:()V
      66: aload_1
      67: aload_0
      68: getfield      #12                 // Field ontologySelectionListener:Lorg/protege/editor/owl/ui/prefix/PrefixMapperTables$SelectedOntologyListener;
      71: invokevirtual #16                 // Method org/protege/editor/owl/ui/prefix/PrefixMapperTables.addListener:(Lorg/protege/editor/owl/ui/prefix/PrefixMapperTables$SelectedOntologyListener;)V
      74: return

  private void updateEnabled();
    Code:
       0: aload_0
       1: getfield      #1                  // Field tables:Lorg/protege/editor/owl/ui/prefix/PrefixMapperTables;
       4: invokevirtual #13                 // Method org/protege/editor/owl/ui/prefix/PrefixMapperTables.getPrefixMapperTable:()Lorg/protege/editor/owl/ui/prefix/PrefixMapperTable;
       7: astore_1
       8: aload_1
       9: ifnonnull     18
      12: aload_0
      13: iconst_0
      14: invokevirtual #17                 // Method setEnabled:(Z)V
      17: return
      18: aload_1
      19: invokevirtual #18                 // Method org/protege/editor/owl/ui/prefix/PrefixMapperTable.getSelectedRow:()I
      22: istore_2
      23: iload_2
      24: iconst_m1
      25: if_icmpne     34
      28: aload_0
      29: iconst_0
      30: invokevirtual #17                 // Method setEnabled:(Z)V
      33: return
      34: aload_1
      35: invokevirtual #19                 // Method org/protege/editor/owl/ui/prefix/PrefixMapperTable.getModel:()Lorg/protege/editor/owl/ui/prefix/PrefixMapperTableModel;
      38: iload_2
      39: iconst_0
      40: invokevirtual #20                 // Method org/protege/editor/owl/ui/prefix/PrefixMapperTableModel.getValueAt:(II)Ljava/lang/Object;
      43: checkcast     #21                 // class java/lang/String
      46: astore_3
      47: aload_0
      48: aload_3
      49: invokestatic  #22                 // Method org/protege/editor/owl/ui/prefix/PrefixUtilities.isStandardPrefix:(Ljava/lang/String;)Z
      52: ifne          59
      55: iconst_1
      56: goto          60
      59: iconst_0
      60: invokevirtual #17                 // Method setEnabled:(Z)V
      63: return

  public void actionPerformed(java.awt.event.ActionEvent);
    Code:
       0: aload_0
       1: getfield      #1                  // Field tables:Lorg/protege/editor/owl/ui/prefix/PrefixMapperTables;
       4: invokevirtual #13                 // Method org/protege/editor/owl/ui/prefix/PrefixMapperTables.getPrefixMapperTable:()Lorg/protege/editor/owl/ui/prefix/PrefixMapperTable;
       7: astore_2
       8: aload_2
       9: invokevirtual #23                 // Method org/protege/editor/owl/ui/prefix/PrefixMapperTable.getSelectedRows:()[I
      12: astore_3
      13: new           #24                 // class java/util/ArrayList
      16: dup
      17: invokespecial #25                 // Method java/util/ArrayList."<init>":()V
      20: astore        4
      22: aload_3
      23: astore        5
      25: aload         5
      27: arraylength
      28: istore        6
      30: iconst_0
      31: istore        7
      33: iload         7
      35: iload         6
      37: if_icmpge     74
      40: aload         5
      42: iload         7
      44: iaload
      45: istore        8
      47: aload         4
      49: aload_2
      50: invokevirtual #19                 // Method org/protege/editor/owl/ui/prefix/PrefixMapperTable.getModel:()Lorg/protege/editor/owl/ui/prefix/PrefixMapperTableModel;
      53: iload         8
      55: iconst_0
      56: invokevirtual #20                 // Method org/protege/editor/owl/ui/prefix/PrefixMapperTableModel.getValueAt:(II)Ljava/lang/Object;
      59: invokevirtual #26                 // Method java/lang/Object.toString:()Ljava/lang/String;
      62: invokeinterface #27,  2           // InterfaceMethod java/util/List.add:(Ljava/lang/Object;)Z
      67: pop
      68: iinc          7, 1
      71: goto          33
      74: aload         4
      76: invokeinterface #28,  1           // InterfaceMethod java/util/List.iterator:()Ljava/util/Iterator;
      81: astore        5
      83: aload         5
      85: invokeinterface #29,  1           // InterfaceMethod java/util/Iterator.hasNext:()Z
      90: ifeq          117
      93: aload         5
      95: invokeinterface #30,  1           // InterfaceMethod java/util/Iterator.next:()Ljava/lang/Object;
     100: checkcast     #21                 // class java/lang/String
     103: astore        6
     105: aload_2
     106: invokevirtual #19                 // Method org/protege/editor/owl/ui/prefix/PrefixMapperTable.getModel:()Lorg/protege/editor/owl/ui/prefix/PrefixMapperTableModel;
     109: aload         6
     111: invokevirtual #31                 // Method org/protege/editor/owl/ui/prefix/PrefixMapperTableModel.removeMapping:(Ljava/lang/String;)V
     114: goto          83
     117: return

  private void lambda$new$0(javax.swing.event.ListSelectionEvent);
    Code:
       0: aload_0
       1: invokespecial #4                  // Method updateEnabled:()V
       4: return

  static void access$000(org.protege.editor.owl.ui.prefix.RemovePrefixMappingAction);
    Code:
       0: aload_0
       1: invokespecial #4                  // Method updateEnabled:()V
       4: return

  static org.protege.editor.owl.ui.prefix.PrefixMapperTable access$100(org.protege.editor.owl.ui.prefix.RemovePrefixMappingAction);
    Code:
       0: aload_0
       1: getfield      #3                  // Field table:Lorg/protege/editor/owl/ui/prefix/PrefixMapperTable;
       4: areturn

  static javax.swing.event.ListSelectionListener access$200(org.protege.editor.owl.ui.prefix.RemovePrefixMappingAction);
    Code:
       0: aload_0
       1: getfield      #2                  // Field tableSelectionListener:Ljavax/swing/event/ListSelectionListener;
       4: areturn

  static org.protege.editor.owl.ui.prefix.PrefixMapperTable access$102(org.protege.editor.owl.ui.prefix.RemovePrefixMappingAction, org.protege.editor.owl.ui.prefix.PrefixMapperTable);
    Code:
       0: aload_0
       1: aload_1
       2: dup_x1
       3: putfield      #3                  // Field table:Lorg/protege/editor/owl/ui/prefix/PrefixMapperTable;
       6: areturn

  static org.protege.editor.owl.ui.prefix.PrefixMapperTables access$300(org.protege.editor.owl.ui.prefix.RemovePrefixMappingAction);
    Code:
       0: aload_0
       1: getfield      #1                  // Field tables:Lorg/protege/editor/owl/ui/prefix/PrefixMapperTables;
       4: areturn
}
