Compiled from "JsCodeGenerator.java"
class net.jangaroo.jooc.backend.JsCodeGenerator$3 implements net.jangaroo.jooc.CodeGenerator {
  final net.jangaroo.jooc.ast.ForInStatement val$forInStatement;

  final boolean val$isForEach;

  final net.jangaroo.jooc.ast.Ide val$exprAuxIde;

  final net.jangaroo.jooc.backend.JsCodeGenerator this$0;

  net.jangaroo.jooc.backend.JsCodeGenerator$3(net.jangaroo.jooc.backend.JsCodeGenerator, net.jangaroo.jooc.ast.ForInStatement, boolean, net.jangaroo.jooc.ast.Ide);
    Code:
       0: aload_0
       1: aload_1
       2: putfield      #1                  // Field this$0:Lnet/jangaroo/jooc/backend/JsCodeGenerator;
       5: aload_0
       6: aload_2
       7: putfield      #2                  // Field val$forInStatement:Lnet/jangaroo/jooc/ast/ForInStatement;
      10: aload_0
      11: iload_3
      12: putfield      #3                  // Field val$isForEach:Z
      15: aload_0
      16: aload         4
      18: putfield      #4                  // Field val$exprAuxIde:Lnet/jangaroo/jooc/ast/Ide;
      21: aload_0
      22: invokespecial #5                  // Method java/lang/Object."<init>":()V
      25: return

  public void generate(net.jangaroo.jooc.JsWriter, boolean) throws java.io.IOException;
    Code:
       0: aload_0
       1: getfield      #2                  // Field val$forInStatement:Lnet/jangaroo/jooc/ast/ForInStatement;
       4: invokevirtual #6                  // Method net/jangaroo/jooc/ast/ForInStatement.getDecl:()Lnet/jangaroo/jooc/ast/VariableDeclaration;
       7: ifnull        27
      10: aload_0
      11: getfield      #2                  // Field val$forInStatement:Lnet/jangaroo/jooc/ast/ForInStatement;
      14: invokevirtual #6                  // Method net/jangaroo/jooc/ast/ForInStatement.getDecl:()Lnet/jangaroo/jooc/ast/VariableDeclaration;
      17: aload_0
      18: getfield      #1                  // Field this$0:Lnet/jangaroo/jooc/backend/JsCodeGenerator;
      21: invokevirtual #7                  // Method net/jangaroo/jooc/ast/VariableDeclaration.visit:(Lnet/jangaroo/jooc/ast/AstVisitor;)V
      24: goto          41
      27: aload_0
      28: getfield      #2                  // Field val$forInStatement:Lnet/jangaroo/jooc/ast/ForInStatement;
      31: invokevirtual #8                  // Method net/jangaroo/jooc/ast/ForInStatement.getLValue:()Lnet/jangaroo/jooc/ast/Expr;
      34: aload_0
      35: getfield      #1                  // Field this$0:Lnet/jangaroo/jooc/backend/JsCodeGenerator;
      38: invokevirtual #9                  // Method net/jangaroo/jooc/ast/Expr.visit:(Lnet/jangaroo/jooc/ast/AstVisitor;)V
      41: aload_1
      42: ldc           #10                 // String =
      44: invokevirtual #11                 // Method net/jangaroo/jooc/JsWriter.writeToken:(Ljava/lang/String;)Lnet/jangaroo/jooc/util/FilePosition;
      47: pop
      48: aload_0
      49: getfield      #3                  // Field val$isForEach:Z
      52: ifne          95
      55: aload_1
      56: new           #12                 // class java/lang/StringBuilder
      59: dup
      60: invokespecial #13                 // Method java/lang/StringBuilder."<init>":()V
      63: ldc           #14                 // String String(
      65: invokevirtual #15                 // Method java/lang/StringBuilder.append:(Ljava/lang/String;)Ljava/lang/StringBuilder;
      68: aload_0
      69: getfield      #2                  // Field val$forInStatement:Lnet/jangaroo/jooc/ast/ForInStatement;
      72: invokevirtual #16                 // Method net/jangaroo/jooc/ast/ForInStatement.getAuxIde:()Lnet/jangaroo/jooc/ast/Ide;
      75: invokevirtual #17                 // Method net/jangaroo/jooc/ast/Ide.getName:()Ljava/lang/String;
      78: invokevirtual #15                 // Method java/lang/StringBuilder.append:(Ljava/lang/String;)Ljava/lang/StringBuilder;
      81: ldc           #18                 // String )
      83: invokevirtual #15                 // Method java/lang/StringBuilder.append:(Ljava/lang/String;)Ljava/lang/StringBuilder;
      86: invokevirtual #19                 // Method java/lang/StringBuilder.toString:()Ljava/lang/String;
      89: invokevirtual #20                 // Method net/jangaroo/jooc/JsWriter.write:(Ljava/lang/String;)V
      92: goto          167
      95: aload_0
      96: getfield      #4                  // Field val$exprAuxIde:Lnet/jangaroo/jooc/ast/Ide;
      99: ifnonnull     119
     102: aload_0
     103: getfield      #2                  // Field val$forInStatement:Lnet/jangaroo/jooc/ast/ForInStatement;
     106: invokevirtual #21                 // Method net/jangaroo/jooc/ast/ForInStatement.getExpr:()Lnet/jangaroo/jooc/ast/Expr;
     109: aload_0
     110: getfield      #1                  // Field this$0:Lnet/jangaroo/jooc/backend/JsCodeGenerator;
     113: invokevirtual #9                  // Method net/jangaroo/jooc/ast/Expr.visit:(Lnet/jangaroo/jooc/ast/AstVisitor;)V
     116: goto          130
     119: aload_1
     120: aload_0
     121: getfield      #4                  // Field val$exprAuxIde:Lnet/jangaroo/jooc/ast/Ide;
     124: invokevirtual #17                 // Method net/jangaroo/jooc/ast/Ide.getName:()Ljava/lang/String;
     127: invokevirtual #20                 // Method net/jangaroo/jooc/JsWriter.write:(Ljava/lang/String;)V
     130: aload_1
     131: new           #12                 // class java/lang/StringBuilder
     134: dup
     135: invokespecial #13                 // Method java/lang/StringBuilder."<init>":()V
     138: ldc           #22                 // String [
     140: invokevirtual #15                 // Method java/lang/StringBuilder.append:(Ljava/lang/String;)Ljava/lang/StringBuilder;
     143: aload_0
     144: getfield      #2                  // Field val$forInStatement:Lnet/jangaroo/jooc/ast/ForInStatement;
     147: invokevirtual #16                 // Method net/jangaroo/jooc/ast/ForInStatement.getAuxIde:()Lnet/jangaroo/jooc/ast/Ide;
     150: invokevirtual #17                 // Method net/jangaroo/jooc/ast/Ide.getName:()Ljava/lang/String;
     153: invokevirtual #15                 // Method java/lang/StringBuilder.append:(Ljava/lang/String;)Ljava/lang/StringBuilder;
     156: ldc           #23                 // String ]
     158: invokevirtual #15                 // Method java/lang/StringBuilder.append:(Ljava/lang/String;)Ljava/lang/StringBuilder;
     161: invokevirtual #19                 // Method java/lang/StringBuilder.toString:()Ljava/lang/String;
     164: invokevirtual #20                 // Method net/jangaroo/jooc/JsWriter.write:(Ljava/lang/String;)V
     167: aload_1
     168: ldc           #24                 // String ;
     170: invokevirtual #20                 // Method net/jangaroo/jooc/JsWriter.write:(Ljava/lang/String;)V
     173: return
}
