Compiled from "EuclideanDoublePoint.java"
public class org.apache.commons.math3.stat.clustering.EuclideanDoublePoint implements org.apache.commons.math3.stat.clustering.Clusterable<org.apache.commons.math3.stat.clustering.EuclideanDoublePoint>, java.io.Serializable {
  private static final long serialVersionUID;

  private final double[] point;

  public org.apache.commons.math3.stat.clustering.EuclideanDoublePoint(double[]);
    Code:
       0: aload_0
       1: invokespecial #1                  // Method java/lang/Object."<init>":()V
       4: aload_0
       5: aload_1
       6: putfield      #2                  // Field point:[D
       9: return

  public org.apache.commons.math3.stat.clustering.EuclideanDoublePoint centroidOf(java.util.Collection<org.apache.commons.math3.stat.clustering.EuclideanDoublePoint>);
    Code:
       0: aload_0
       1: invokevirtual #3                  // Method getPoint:()[D
       4: arraylength
       5: newarray       double
       7: astore_2
       8: aload_1
       9: invokeinterface #4,  1            // InterfaceMethod java/util/Collection.iterator:()Ljava/util/Iterator;
      14: astore_3
      15: aload_3
      16: invokeinterface #5,  1            // InterfaceMethod java/util/Iterator.hasNext:()Z
      21: ifeq          69
      24: aload_3
      25: invokeinterface #6,  1            // InterfaceMethod java/util/Iterator.next:()Ljava/lang/Object;
      30: checkcast     #7                  // class org/apache/commons/math3/stat/clustering/EuclideanDoublePoint
      33: astore        4
      35: iconst_0
      36: istore        5
      38: iload         5
      40: aload_2
      41: arraylength
      42: if_icmpge     66
      45: aload_2
      46: iload         5
      48: dup2
      49: daload
      50: aload         4
      52: invokevirtual #3                  // Method getPoint:()[D
      55: iload         5
      57: daload
      58: dadd
      59: dastore
      60: iinc          5, 1
      63: goto          38
      66: goto          15
      69: iconst_0
      70: istore_3
      71: iload_3
      72: aload_2
      73: arraylength
      74: if_icmpge     96
      77: aload_2
      78: iload_3
      79: dup2
      80: daload
      81: aload_1
      82: invokeinterface #8,  1            // InterfaceMethod java/util/Collection.size:()I
      87: i2d
      88: ddiv
      89: dastore
      90: iinc          3, 1
      93: goto          71
      96: new           #7                  // class org/apache/commons/math3/stat/clustering/EuclideanDoublePoint
      99: dup
     100: aload_2
     101: invokespecial #9                  // Method "<init>":([D)V
     104: areturn

  public double distanceFrom(org.apache.commons.math3.stat.clustering.EuclideanDoublePoint);
    Code:
       0: aload_0
       1: getfield      #2                  // Field point:[D
       4: aload_1
       5: invokevirtual #3                  // Method getPoint:()[D
       8: invokestatic  #10                 // Method org/apache/commons/math3/util/MathArrays.distance:([D[D)D
      11: dreturn

  public boolean equals(java.lang.Object);
    Code:
       0: aload_1
       1: instanceof    #7                  // class org/apache/commons/math3/stat/clustering/EuclideanDoublePoint
       4: ifne          9
       7: iconst_0
       8: ireturn
       9: aload_0
      10: getfield      #2                  // Field point:[D
      13: aload_1
      14: checkcast     #7                  // class org/apache/commons/math3/stat/clustering/EuclideanDoublePoint
      17: getfield      #2                  // Field point:[D
      20: invokestatic  #11                 // Method java/util/Arrays.equals:([D[D)Z
      23: ireturn

  public double[] getPoint();
    Code:
       0: aload_0
       1: getfield      #2                  // Field point:[D
       4: areturn

  public int hashCode();
    Code:
       0: aload_0
       1: getfield      #2                  // Field point:[D
       4: invokestatic  #12                 // Method java/util/Arrays.hashCode:([D)I
       7: ireturn

  public java.lang.String toString();
    Code:
       0: aload_0
       1: getfield      #2                  // Field point:[D
       4: invokestatic  #13                 // Method java/util/Arrays.toString:([D)Ljava/lang/String;
       7: areturn

  public java.lang.Object centroidOf(java.util.Collection);
    Code:
       0: aload_0
       1: aload_1
       2: invokevirtual #14                 // Method centroidOf:(Ljava/util/Collection;)Lorg/apache/commons/math3/stat/clustering/EuclideanDoublePoint;
       5: areturn

  public double distanceFrom(java.lang.Object);
    Code:
       0: aload_0
       1: aload_1
       2: checkcast     #7                  // class org/apache/commons/math3/stat/clustering/EuclideanDoublePoint
       5: invokevirtual #15                 // Method distanceFrom:(Lorg/apache/commons/math3/stat/clustering/EuclideanDoublePoint;)D
       8: dreturn
}
