public class org.bouncycastle.crypto.engines.Salsa20Engine implements org.bouncycastle.crypto.SkippingStreamCipher {
  public static final int DEFAULT_ROUNDS;

  private static final int STATE_SIZE;

  private static final int[] TAU_SIGMA;

  protected static final byte[] sigma;

  protected static final byte[] tau;

  protected int rounds;

  private int index;

  protected int[] engineState;

  protected int[] x;

  private byte[] keyStream;

  private boolean initialised;

  private int cW0;

  private int cW1;

  private int cW2;

  protected void packTauOrSigma(int, int[], int);
    Code:
       0: iload_1
       1: bipush        16
       3: isub
       4: iconst_4
       5: idiv
       6: istore        4
       8: aload_2
       9: iload_3
      10: getstatic     #198                // Field TAU_SIGMA:[I
      13: iload         4
      15: iaload
      16: iastore
      17: aload_2
      18: iload_3
      19: iconst_1
      20: iadd
      21: getstatic     #198                // Field TAU_SIGMA:[I
      24: iload         4
      26: iconst_1
      27: iadd
      28: iaload
      29: iastore
      30: aload_2
      31: iload_3
      32: iconst_2
      33: iadd
      34: getstatic     #198                // Field TAU_SIGMA:[I
      37: iload         4
      39: iconst_2
      40: iadd
      41: iaload
      42: iastore
      43: aload_2
      44: iload_3
      45: iconst_3
      46: iadd
      47: getstatic     #198                // Field TAU_SIGMA:[I
      50: iload         4
      52: iconst_3
      53: iadd
      54: iaload
      55: iastore
      56: return

  public org.bouncycastle.crypto.engines.Salsa20Engine();
    Code:
       0: aload_0
       1: bipush        20
       3: invokespecial #220                // Method "<init>":(I)V
       6: return

  public org.bouncycastle.crypto.engines.Salsa20Engine(int);
    Code:
       0: aload_0
       1: invokespecial #204                // Method java/lang/Object."<init>":()V
       4: aload_0
       5: iconst_0
       6: putfield      #192                // Field index:I
       9: aload_0
      10: bipush        16
      12: newarray       int
      14: putfield      #199                // Field engineState:[I
      17: aload_0
      18: bipush        16
      20: newarray       int
      22: putfield      #200                // Field x:[I
      25: aload_0
      26: bipush        64
      28: newarray       byte
      30: putfield      #195                // Field keyStream:[B
      33: aload_0
      34: iconst_0
      35: putfield      #194                // Field initialised:Z
      38: iload_1
      39: ifle          48
      42: iload_1
      43: iconst_1
      44: iand
      45: ifeq          58
      48: new           #126                // class java/lang/IllegalArgumentException
      51: dup
      52: ldc           #8                  // String \'rounds\' must be a positive, even number
      54: invokespecial #202                // Method java/lang/IllegalArgumentException."<init>":(Ljava/lang/String;)V
      57: athrow
      58: aload_0
      59: iload_1
      60: putfield      #193                // Field rounds:I
      63: return

  public void init(boolean, org.bouncycastle.crypto.CipherParameters);
    Code:
       0: aload_2
       1: instanceof    #136                // class org/bouncycastle/crypto/params/ParametersWithIV
       4: ifne          37
       7: new           #126                // class java/lang/IllegalArgumentException
      10: dup
      11: new           #129                // class java/lang/StringBuilder
      14: dup
      15: invokespecial #205                // Method java/lang/StringBuilder."<init>":()V
      18: aload_0
      19: invokevirtual #228                // Method getAlgorithmName:()Ljava/lang/String;
      22: invokevirtual #208                // Method java/lang/StringBuilder.append:(Ljava/lang/String;)Ljava/lang/StringBuilder;
      25: ldc           #2                  // String  Init parameters must include an IV
      27: invokevirtual #208                // Method java/lang/StringBuilder.append:(Ljava/lang/String;)Ljava/lang/StringBuilder;
      30: invokevirtual #206                // Method java/lang/StringBuilder.toString:()Ljava/lang/String;
      33: invokespecial #202                // Method java/lang/IllegalArgumentException."<init>":(Ljava/lang/String;)V
      36: athrow
      37: aload_2
      38: checkcast     #136                // class org/bouncycastle/crypto/params/ParametersWithIV
      41: astore_3
      42: aload_3
      43: invokevirtual #230                // Method org/bouncycastle/crypto/params/ParametersWithIV.getIV:()[B
      46: astore        4
      48: aload         4
      50: ifnull        63
      53: aload         4
      55: arraylength
      56: aload_0
      57: invokevirtual #212                // Method getNonceSize:()I
      60: if_icmpeq     105
      63: new           #126                // class java/lang/IllegalArgumentException
      66: dup
      67: new           #129                // class java/lang/StringBuilder
      70: dup
      71: invokespecial #205                // Method java/lang/StringBuilder."<init>":()V
      74: aload_0
      75: invokevirtual #228                // Method getAlgorithmName:()Ljava/lang/String;
      78: invokevirtual #208                // Method java/lang/StringBuilder.append:(Ljava/lang/String;)Ljava/lang/StringBuilder;
      81: ldc           #7                  // String  requires exactly
      83: invokevirtual #208                // Method java/lang/StringBuilder.append:(Ljava/lang/String;)Ljava/lang/StringBuilder;
      86: aload_0
      87: invokevirtual #212                // Method getNonceSize:()I
      90: invokevirtual #207                // Method java/lang/StringBuilder.append:(I)Ljava/lang/StringBuilder;
      93: ldc           #4                  // String  bytes of IV
      95: invokevirtual #208                // Method java/lang/StringBuilder.append:(Ljava/lang/String;)Ljava/lang/StringBuilder;
      98: invokevirtual #206                // Method java/lang/StringBuilder.toString:()Ljava/lang/String;
     101: invokespecial #202                // Method java/lang/IllegalArgumentException."<init>":(Ljava/lang/String;)V
     104: athrow
     105: aload_3
     106: invokevirtual #231                // Method org/bouncycastle/crypto/params/ParametersWithIV.getParameters:()Lorg/bouncycastle/crypto/CipherParameters;
     109: astore        5
     111: aload         5
     113: ifnonnull     163
     116: aload_0
     117: getfield      #194                // Field initialised:Z
     120: ifne          153
     123: new           #127                // class java/lang/IllegalStateException
     126: dup
     127: new           #129                // class java/lang/StringBuilder
     130: dup
     131: invokespecial #205                // Method java/lang/StringBuilder."<init>":()V
     134: aload_0
     135: invokevirtual #228                // Method getAlgorithmName:()Ljava/lang/String;
     138: invokevirtual #208                // Method java/lang/StringBuilder.append:(Ljava/lang/String;)Ljava/lang/StringBuilder;
     141: ldc           #3                  // String  KeyParameter can not be null for first initialisation
     143: invokevirtual #208                // Method java/lang/StringBuilder.append:(Ljava/lang/String;)Ljava/lang/StringBuilder;
     146: invokevirtual #206                // Method java/lang/StringBuilder.toString:()Ljava/lang/String;
     149: invokespecial #203                // Method java/lang/IllegalStateException."<init>":(Ljava/lang/String;)V
     152: athrow
     153: aload_0
     154: aconst_null
     155: aload         4
     157: invokevirtual #227                // Method setKey:([B[B)V
     160: goto          218
     163: aload         5
     165: instanceof    #135                // class org/bouncycastle/crypto/params/KeyParameter
     168: ifeq          188
     171: aload_0
     172: aload         5
     174: checkcast     #135                // class org/bouncycastle/crypto/params/KeyParameter
     177: invokevirtual #229                // Method org/bouncycastle/crypto/params/KeyParameter.getKey:()[B
     180: aload         4
     182: invokevirtual #227                // Method setKey:([B[B)V
     185: goto          218
     188: new           #126                // class java/lang/IllegalArgumentException
     191: dup
     192: new           #129                // class java/lang/StringBuilder
     195: dup
     196: invokespecial #205                // Method java/lang/StringBuilder."<init>":()V
     199: aload_0
     200: invokevirtual #228                // Method getAlgorithmName:()Ljava/lang/String;
     203: invokevirtual #208                // Method java/lang/StringBuilder.append:(Ljava/lang/String;)Ljava/lang/StringBuilder;
     206: ldc           #1                  // String  Init parameters must contain a KeyParameter (or null for re-init)
     208: invokevirtual #208                // Method java/lang/StringBuilder.append:(Ljava/lang/String;)Ljava/lang/StringBuilder;
     211: invokevirtual #206                // Method java/lang/StringBuilder.toString:()Ljava/lang/String;
     214: invokespecial #202                // Method java/lang/IllegalArgumentException."<init>":(Ljava/lang/String;)V
     217: athrow
     218: aload_0
     219: invokevirtual #215                // Method reset:()V
     222: aload_0
     223: iconst_1
     224: putfield      #194                // Field initialised:Z
     227: return

  protected int getNonceSize();
    Code:
       0: bipush        8
       2: ireturn

  public java.lang.String getAlgorithmName();
    Code:
       0: ldc           #13                 // String Salsa20
       2: astore_1
       3: aload_0
       4: getfield      #193                // Field rounds:I
       7: bipush        20
       9: if_icmpeq     39
      12: new           #129                // class java/lang/StringBuilder
      15: dup
      16: invokespecial #205                // Method java/lang/StringBuilder."<init>":()V
      19: aload_1
      20: invokevirtual #208                // Method java/lang/StringBuilder.append:(Ljava/lang/String;)Ljava/lang/StringBuilder;
      23: ldc           #9                  // String /
      25: invokevirtual #208                // Method java/lang/StringBuilder.append:(Ljava/lang/String;)Ljava/lang/StringBuilder;
      28: aload_0
      29: getfield      #193                // Field rounds:I
      32: invokevirtual #207                // Method java/lang/StringBuilder.append:(I)Ljava/lang/StringBuilder;
      35: invokevirtual #206                // Method java/lang/StringBuilder.toString:()Ljava/lang/String;
      38: astore_1
      39: aload_1
      40: areturn

  public byte returnByte(byte);
    Code:
       0: aload_0
       1: invokespecial #219                // Method limitExceeded:()Z
       4: ifeq          17
       7: new           #131                // class org/bouncycastle/crypto/MaxBytesExceededException
      10: dup
      11: ldc           #11                 // String 2^70 byte limit per IV; Change IV
      13: invokespecial #210                // Method org/bouncycastle/crypto/MaxBytesExceededException."<init>":(Ljava/lang/String;)V
      16: athrow
      17: aload_0
      18: getfield      #195                // Field keyStream:[B
      21: aload_0
      22: getfield      #192                // Field index:I
      25: baload
      26: iload_1
      27: ixor
      28: i2b
      29: istore_2
      30: aload_0
      31: aload_0
      32: getfield      #192                // Field index:I
      35: iconst_1
      36: iadd
      37: bipush        63
      39: iand
      40: putfield      #192                // Field index:I
      43: aload_0
      44: getfield      #192                // Field index:I
      47: ifne          62
      50: aload_0
      51: invokevirtual #214                // Method advanceCounter:()V
      54: aload_0
      55: aload_0
      56: getfield      #195                // Field keyStream:[B
      59: invokevirtual #226                // Method generateKeyStream:([B)V
      62: iload_2
      63: ireturn

  protected void advanceCounter(long);
    Code:
       0: lload_1
       1: bipush        32
       3: lushr
       4: l2i
       5: istore_3
       6: lload_1
       7: l2i
       8: istore        4
      10: iload_3
      11: ifle          25
      14: aload_0
      15: getfield      #199                // Field engineState:[I
      18: bipush        9
      20: dup2
      21: iaload
      22: iload_3
      23: iadd
      24: iastore
      25: aload_0
      26: getfield      #199                // Field engineState:[I
      29: bipush        8
      31: iaload
      32: istore        5
      34: aload_0
      35: getfield      #199                // Field engineState:[I
      38: bipush        8
      40: dup2
      41: iaload
      42: iload         4
      44: iadd
      45: iastore
      46: iload         5
      48: ifeq          74
      51: aload_0
      52: getfield      #199                // Field engineState:[I
      55: bipush        8
      57: iaload
      58: iload         5
      60: if_icmpge     74
      63: aload_0
      64: getfield      #199                // Field engineState:[I
      67: bipush        9
      69: dup2
      70: iaload
      71: iconst_1
      72: iadd
      73: iastore
      74: return

  protected void advanceCounter();
    Code:
       0: aload_0
       1: getfield      #199                // Field engineState:[I
       4: bipush        8
       6: dup2
       7: iaload
       8: iconst_1
       9: iadd
      10: dup_x2
      11: iastore
      12: ifne          26
      15: aload_0
      16: getfield      #199                // Field engineState:[I
      19: bipush        9
      21: dup2
      22: iaload
      23: iconst_1
      24: iadd
      25: iastore
      26: return

  protected void retreatCounter(long);
    Code:
       0: lload_1
       1: bipush        32
       3: lushr
       4: l2i
       5: istore_3
       6: lload_1
       7: l2i
       8: istore        4
      10: iload_3
      11: ifeq          60
      14: aload_0
      15: getfield      #199                // Field engineState:[I
      18: bipush        9
      20: iaload
      21: i2l
      22: ldc2_w        #124                // long 4294967295l
      25: land
      26: iload_3
      27: i2l
      28: ldc2_w        #124                // long 4294967295l
      31: land
      32: lcmp
      33: iflt          50
      36: aload_0
      37: getfield      #199                // Field engineState:[I
      40: bipush        9
      42: dup2
      43: iaload
      44: iload_3
      45: isub
      46: iastore
      47: goto          60
      50: new           #127                // class java/lang/IllegalStateException
      53: dup
      54: ldc           #14                 // String attempt to reduce counter past zero.
      56: invokespecial #203                // Method java/lang/IllegalStateException."<init>":(Ljava/lang/String;)V
      59: athrow
      60: aload_0
      61: getfield      #199                // Field engineState:[I
      64: bipush        8
      66: iaload
      67: i2l
      68: ldc2_w        #124                // long 4294967295l
      71: land
      72: iload         4
      74: i2l
      75: ldc2_w        #124                // long 4294967295l
      78: land
      79: lcmp
      80: iflt          98
      83: aload_0
      84: getfield      #199                // Field engineState:[I
      87: bipush        8
      89: dup2
      90: iaload
      91: iload         4
      93: isub
      94: iastore
      95: goto          144
      98: aload_0
      99: getfield      #199                // Field engineState:[I
     102: bipush        9
     104: iaload
     105: ifeq          134
     108: aload_0
     109: getfield      #199                // Field engineState:[I
     112: bipush        9
     114: dup2
     115: iaload
     116: iconst_1
     117: isub
     118: iastore
     119: aload_0
     120: getfield      #199                // Field engineState:[I
     123: bipush        8
     125: dup2
     126: iaload
     127: iload         4
     129: isub
     130: iastore
     131: goto          144
     134: new           #127                // class java/lang/IllegalStateException
     137: dup
     138: ldc           #14                 // String attempt to reduce counter past zero.
     140: invokespecial #203                // Method java/lang/IllegalStateException."<init>":(Ljava/lang/String;)V
     143: athrow
     144: return

  protected void retreatCounter();
    Code:
       0: aload_0
       1: getfield      #199                // Field engineState:[I
       4: bipush        8
       6: iaload
       7: ifne          30
      10: aload_0
      11: getfield      #199                // Field engineState:[I
      14: bipush        9
      16: iaload
      17: ifne          30
      20: new           #127                // class java/lang/IllegalStateException
      23: dup
      24: ldc           #14                 // String attempt to reduce counter past zero.
      26: invokespecial #203                // Method java/lang/IllegalStateException."<init>":(Ljava/lang/String;)V
      29: athrow
      30: aload_0
      31: getfield      #199                // Field engineState:[I
      34: bipush        8
      36: dup2
      37: iaload
      38: iconst_1
      39: isub
      40: dup_x2
      41: iastore
      42: iconst_m1
      43: if_icmpne     57
      46: aload_0
      47: getfield      #199                // Field engineState:[I
      50: bipush        9
      52: dup2
      53: iaload
      54: iconst_1
      55: isub
      56: iastore
      57: return

  public int processBytes(byte[], int, int, byte[], int);
    Code:
       0: aload_0
       1: getfield      #194                // Field initialised:Z
       4: ifne          37
       7: new           #127                // class java/lang/IllegalStateException
      10: dup
      11: new           #129                // class java/lang/StringBuilder
      14: dup
      15: invokespecial #205                // Method java/lang/StringBuilder."<init>":()V
      18: aload_0
      19: invokevirtual #228                // Method getAlgorithmName:()Ljava/lang/String;
      22: invokevirtual #208                // Method java/lang/StringBuilder.append:(Ljava/lang/String;)Ljava/lang/StringBuilder;
      25: ldc           #5                  // String  not initialised
      27: invokevirtual #208                // Method java/lang/StringBuilder.append:(Ljava/lang/String;)Ljava/lang/StringBuilder;
      30: invokevirtual #206                // Method java/lang/StringBuilder.toString:()Ljava/lang/String;
      33: invokespecial #203                // Method java/lang/IllegalStateException."<init>":(Ljava/lang/String;)V
      36: athrow
      37: iload_2
      38: iload_3
      39: iadd
      40: aload_1
      41: arraylength
      42: if_icmple     55
      45: new           #130                // class org/bouncycastle/crypto/DataLengthException
      48: dup
      49: ldc           #18                 // String input buffer too short
      51: invokespecial #209                // Method org/bouncycastle/crypto/DataLengthException."<init>":(Ljava/lang/String;)V
      54: athrow
      55: iload         5
      57: iload_3
      58: iadd
      59: aload         4
      61: arraylength
      62: if_icmple     75
      65: new           #132                // class org/bouncycastle/crypto/OutputLengthException
      68: dup
      69: ldc           #19                 // String output buffer too short
      71: invokespecial #211                // Method org/bouncycastle/crypto/OutputLengthException."<init>":(Ljava/lang/String;)V
      74: athrow
      75: aload_0
      76: iload_3
      77: invokespecial #221                // Method limitExceeded:(I)Z
      80: ifeq          93
      83: new           #131                // class org/bouncycastle/crypto/MaxBytesExceededException
      86: dup
      87: ldc           #10                 // String 2^70 byte limit per IV would be exceeded; Change IV
      89: invokespecial #210                // Method org/bouncycastle/crypto/MaxBytesExceededException."<init>":(Ljava/lang/String;)V
      92: athrow
      93: iconst_0
      94: istore        6
      96: iload         6
      98: iload_3
      99: if_icmpge     165
     102: aload         4
     104: iload         6
     106: iload         5
     108: iadd
     109: aload_0
     110: getfield      #195                // Field keyStream:[B
     113: aload_0
     114: getfield      #192                // Field index:I
     117: baload
     118: aload_1
     119: iload         6
     121: iload_2
     122: iadd
     123: baload
     124: ixor
     125: i2b
     126: bastore
     127: aload_0
     128: aload_0
     129: getfield      #192                // Field index:I
     132: iconst_1
     133: iadd
     134: bipush        63
     136: iand
     137: putfield      #192                // Field index:I
     140: aload_0
     141: getfield      #192                // Field index:I
     144: ifne          159
     147: aload_0
     148: invokevirtual #214                // Method advanceCounter:()V
     151: aload_0
     152: aload_0
     153: getfield      #195                // Field keyStream:[B
     156: invokevirtual #226                // Method generateKeyStream:([B)V
     159: iinc          6, 1
     162: goto          96
     165: iload_3
     166: ireturn

  public long skip(long);
    Code:
       0: lload_1
       1: lconst_0
       2: lcmp
       3: iflt          74
       6: lload_1
       7: lstore_3
       8: lload_3
       9: ldc2_w        #122                // long 64l
      12: lcmp
      13: iflt          38
      16: lload_3
      17: ldc2_w        #122                // long 64l
      20: ldiv
      21: lstore        5
      23: aload_0
      24: lload         5
      26: invokevirtual #224                // Method advanceCounter:(J)V
      29: lload_3
      30: lload         5
      32: ldc2_w        #122                // long 64l
      35: lmul
      36: lsub
      37: lstore_3
      38: aload_0
      39: getfield      #192                // Field index:I
      42: istore        5
      44: aload_0
      45: aload_0
      46: getfield      #192                // Field index:I
      49: lload_3
      50: l2i
      51: iadd
      52: bipush        63
      54: iand
      55: putfield      #192                // Field index:I
      58: aload_0
      59: getfield      #192                // Field index:I
      62: iload         5
      64: if_icmpge     71
      67: aload_0
      68: invokevirtual #214                // Method advanceCounter:()V
      71: goto          150
      74: lload_1
      75: lneg
      76: lstore_3
      77: lload_3
      78: ldc2_w        #122                // long 64l
      81: lcmp
      82: iflt          107
      85: lload_3
      86: ldc2_w        #122                // long 64l
      89: ldiv
      90: lstore        5
      92: aload_0
      93: lload         5
      95: invokevirtual #225                // Method retreatCounter:(J)V
      98: lload_3
      99: lload         5
     101: ldc2_w        #122                // long 64l
     104: lmul
     105: lsub
     106: lstore_3
     107: lconst_0
     108: lstore        5
     110: lload         5
     112: lload_3
     113: lcmp
     114: ifge          150
     117: aload_0
     118: getfield      #192                // Field index:I
     121: ifne          128
     124: aload_0
     125: invokevirtual #218                // Method retreatCounter:()V
     128: aload_0
     129: aload_0
     130: getfield      #192                // Field index:I
     133: iconst_1
     134: isub
     135: bipush        63
     137: iand
     138: putfield      #192                // Field index:I
     141: lload         5
     143: lconst_1
     144: ladd
     145: lstore        5
     147: goto          110
     150: aload_0
     151: aload_0
     152: getfield      #195                // Field keyStream:[B
     155: invokevirtual #226                // Method generateKeyStream:([B)V
     158: lload_1
     159: lreturn

  public long seekTo(long);
    Code:
       0: aload_0
       1: invokevirtual #215                // Method reset:()V
       4: aload_0
       5: lload_1
       6: invokevirtual #223                // Method skip:(J)J
       9: lreturn

  public long getPosition();
    Code:
       0: aload_0
       1: invokevirtual #213                // Method getCounter:()J
       4: ldc2_w        #122                // long 64l
       7: lmul
       8: aload_0
       9: getfield      #192                // Field index:I
      12: i2l
      13: ladd
      14: lreturn

  public void reset();
    Code:
       0: aload_0
       1: iconst_0
       2: putfield      #192                // Field index:I
       5: aload_0
       6: invokespecial #217                // Method resetLimitCounter:()V
       9: aload_0
      10: invokevirtual #216                // Method resetCounter:()V
      13: aload_0
      14: aload_0
      15: getfield      #195                // Field keyStream:[B
      18: invokevirtual #226                // Method generateKeyStream:([B)V
      21: return

  protected long getCounter();
    Code:
       0: aload_0
       1: getfield      #199                // Field engineState:[I
       4: bipush        9
       6: iaload
       7: i2l
       8: bipush        32
      10: lshl
      11: aload_0
      12: getfield      #199                // Field engineState:[I
      15: bipush        8
      17: iaload
      18: i2l
      19: ldc2_w        #124                // long 4294967295l
      22: land
      23: lor
      24: lreturn

  protected void resetCounter();
    Code:
       0: aload_0
       1: getfield      #199                // Field engineState:[I
       4: bipush        8
       6: aload_0
       7: getfield      #199                // Field engineState:[I
      10: bipush        9
      12: iconst_0
      13: dup_x2
      14: iastore
      15: iastore
      16: return

  protected void setKey(byte[], byte[]);
    Code:
       0: aload_1
       1: ifnull        135
       4: aload_1
       5: arraylength
       6: bipush        16
       8: if_icmpeq     48
      11: aload_1
      12: arraylength
      13: bipush        32
      15: if_icmpeq     48
      18: new           #126                // class java/lang/IllegalArgumentException
      21: dup
      22: new           #129                // class java/lang/StringBuilder
      25: dup
      26: invokespecial #205                // Method java/lang/StringBuilder."<init>":()V
      29: aload_0
      30: invokevirtual #228                // Method getAlgorithmName:()Ljava/lang/String;
      33: invokevirtual #208                // Method java/lang/StringBuilder.append:(Ljava/lang/String;)Ljava/lang/StringBuilder;
      36: ldc           #6                  // String  requires 128 bit or 256 bit key
      38: invokevirtual #208                // Method java/lang/StringBuilder.append:(Ljava/lang/String;)Ljava/lang/StringBuilder;
      41: invokevirtual #206                // Method java/lang/StringBuilder.toString:()Ljava/lang/String;
      44: invokespecial #202                // Method java/lang/IllegalArgumentException."<init>":(Ljava/lang/String;)V
      47: athrow
      48: aload_1
      49: arraylength
      50: bipush        16
      52: isub
      53: iconst_4
      54: idiv
      55: istore_3
      56: aload_0
      57: getfield      #199                // Field engineState:[I
      60: iconst_0
      61: getstatic     #198                // Field TAU_SIGMA:[I
      64: iload_3
      65: iaload
      66: iastore
      67: aload_0
      68: getfield      #199                // Field engineState:[I
      71: iconst_5
      72: getstatic     #198                // Field TAU_SIGMA:[I
      75: iload_3
      76: iconst_1
      77: iadd
      78: iaload
      79: iastore
      80: aload_0
      81: getfield      #199                // Field engineState:[I
      84: bipush        10
      86: getstatic     #198                // Field TAU_SIGMA:[I
      89: iload_3
      90: iconst_2
      91: iadd
      92: iaload
      93: iastore
      94: aload_0
      95: getfield      #199                // Field engineState:[I
      98: bipush        15
     100: getstatic     #198                // Field TAU_SIGMA:[I
     103: iload_3
     104: iconst_3
     105: iadd
     106: iaload
     107: iastore
     108: aload_1
     109: iconst_0
     110: aload_0
     111: getfield      #199                // Field engineState:[I
     114: iconst_1
     115: iconst_4
     116: invokestatic  #234                // Method org/bouncycastle/util/Pack.littleEndianToInt:([BI[III)V
     119: aload_1
     120: aload_1
     121: arraylength
     122: bipush        16
     124: isub
     125: aload_0
     126: getfield      #199                // Field engineState:[I
     129: bipush        11
     131: iconst_4
     132: invokestatic  #234                // Method org/bouncycastle/util/Pack.littleEndianToInt:([BI[III)V
     135: aload_2
     136: iconst_0
     137: aload_0
     138: getfield      #199                // Field engineState:[I
     141: bipush        6
     143: iconst_2
     144: invokestatic  #234                // Method org/bouncycastle/util/Pack.littleEndianToInt:([BI[III)V
     147: return

  protected void generateKeyStream(byte[]);
    Code:
       0: aload_0
       1: getfield      #193                // Field rounds:I
       4: aload_0
       5: getfield      #199                // Field engineState:[I
       8: aload_0
       9: getfield      #200                // Field x:[I
      12: invokestatic  #222                // Method salsaCore:(I[I[I)V
      15: aload_0
      16: getfield      #200                // Field x:[I
      19: aload_1
      20: iconst_0
      21: invokestatic  #235                // Method org/bouncycastle/util/Pack.intToLittleEndian:([I[BI)V
      24: return

  public static void salsaCore(int, int[], int[]);
    Code:
       0: aload_1
       1: arraylength
       2: bipush        16
       4: if_icmpeq     15
       7: new           #126                // class java/lang/IllegalArgumentException
      10: dup
      11: invokespecial #201                // Method java/lang/IllegalArgumentException."<init>":()V
      14: athrow
      15: aload_2
      16: arraylength
      17: bipush        16
      19: if_icmpeq     30
      22: new           #126                // class java/lang/IllegalArgumentException
      25: dup
      26: invokespecial #201                // Method java/lang/IllegalArgumentException."<init>":()V
      29: athrow
      30: iload_0
      31: iconst_2
      32: irem
      33: ifeq          46
      36: new           #126                // class java/lang/IllegalArgumentException
      39: dup
      40: ldc           #12                 // String Number of rounds must be even
      42: invokespecial #202                // Method java/lang/IllegalArgumentException."<init>":(Ljava/lang/String;)V
      45: athrow
      46: aload_1
      47: iconst_0
      48: iaload
      49: istore_3
      50: aload_1
      51: iconst_1
      52: iaload
      53: istore        4
      55: aload_1
      56: iconst_2
      57: iaload
      58: istore        5
      60: aload_1
      61: iconst_3
      62: iaload
      63: istore        6
      65: aload_1
      66: iconst_4
      67: iaload
      68: istore        7
      70: aload_1
      71: iconst_5
      72: iaload
      73: istore        8
      75: aload_1
      76: bipush        6
      78: iaload
      79: istore        9
      81: aload_1
      82: bipush        7
      84: iaload
      85: istore        10
      87: aload_1
      88: bipush        8
      90: iaload
      91: istore        11
      93: aload_1
      94: bipush        9
      96: iaload
      97: istore        12
      99: aload_1
     100: bipush        10
     102: iaload
     103: istore        13
     105: aload_1
     106: bipush        11
     108: iaload
     109: istore        14
     111: aload_1
     112: bipush        12
     114: iaload
     115: istore        15
     117: aload_1
     118: bipush        13
     120: iaload
     121: istore        16
     123: aload_1
     124: bipush        14
     126: iaload
     127: istore        17
     129: aload_1
     130: bipush        15
     132: iaload
     133: istore        18
     135: iload_0
     136: istore        19
     138: iload         19
     140: ifle          621
     143: iload         7
     145: iload_3
     146: iload         15
     148: iadd
     149: bipush        7
     151: invokestatic  #232                // Method org/bouncycastle/util/Integers.rotateLeft:(II)I
     154: ixor
     155: istore        7
     157: iload         11
     159: iload         7
     161: iload_3
     162: iadd
     163: bipush        9
     165: invokestatic  #232                // Method org/bouncycastle/util/Integers.rotateLeft:(II)I
     168: ixor
     169: istore        11
     171: iload         15
     173: iload         11
     175: iload         7
     177: iadd
     178: bipush        13
     180: invokestatic  #232                // Method org/bouncycastle/util/Integers.rotateLeft:(II)I
     183: ixor
     184: istore        15
     186: iload_3
     187: iload         15
     189: iload         11
     191: iadd
     192: bipush        18
     194: invokestatic  #232                // Method org/bouncycastle/util/Integers.rotateLeft:(II)I
     197: ixor
     198: istore_3
     199: iload         12
     201: iload         8
     203: iload         4
     205: iadd
     206: bipush        7
     208: invokestatic  #232                // Method org/bouncycastle/util/Integers.rotateLeft:(II)I
     211: ixor
     212: istore        12
     214: iload         16
     216: iload         12
     218: iload         8
     220: iadd
     221: bipush        9
     223: invokestatic  #232                // Method org/bouncycastle/util/Integers.rotateLeft:(II)I
     226: ixor
     227: istore        16
     229: iload         4
     231: iload         16
     233: iload         12
     235: iadd
     236: bipush        13
     238: invokestatic  #232                // Method org/bouncycastle/util/Integers.rotateLeft:(II)I
     241: ixor
     242: istore        4
     244: iload         8
     246: iload         4
     248: iload         16
     250: iadd
     251: bipush        18
     253: invokestatic  #232                // Method org/bouncycastle/util/Integers.rotateLeft:(II)I
     256: ixor
     257: istore        8
     259: iload         17
     261: iload         13
     263: iload         9
     265: iadd
     266: bipush        7
     268: invokestatic  #232                // Method org/bouncycastle/util/Integers.rotateLeft:(II)I
     271: ixor
     272: istore        17
     274: iload         5
     276: iload         17
     278: iload         13
     280: iadd
     281: bipush        9
     283: invokestatic  #232                // Method org/bouncycastle/util/Integers.rotateLeft:(II)I
     286: ixor
     287: istore        5
     289: iload         9
     291: iload         5
     293: iload         17
     295: iadd
     296: bipush        13
     298: invokestatic  #232                // Method org/bouncycastle/util/Integers.rotateLeft:(II)I
     301: ixor
     302: istore        9
     304: iload         13
     306: iload         9
     308: iload         5
     310: iadd
     311: bipush        18
     313: invokestatic  #232                // Method org/bouncycastle/util/Integers.rotateLeft:(II)I
     316: ixor
     317: istore        13
     319: iload         6
     321: iload         18
     323: iload         14
     325: iadd
     326: bipush        7
     328: invokestatic  #232                // Method org/bouncycastle/util/Integers.rotateLeft:(II)I
     331: ixor
     332: istore        6
     334: iload         10
     336: iload         6
     338: iload         18
     340: iadd
     341: bipush        9
     343: invokestatic  #232                // Method org/bouncycastle/util/Integers.rotateLeft:(II)I
     346: ixor
     347: istore        10
     349: iload         14
     351: iload         10
     353: iload         6
     355: iadd
     356: bipush        13
     358: invokestatic  #232                // Method org/bouncycastle/util/Integers.rotateLeft:(II)I
     361: ixor
     362: istore        14
     364: iload         18
     366: iload         14
     368: iload         10
     370: iadd
     371: bipush        18
     373: invokestatic  #232                // Method org/bouncycastle/util/Integers.rotateLeft:(II)I
     376: ixor
     377: istore        18
     379: iload         4
     381: iload_3
     382: iload         6
     384: iadd
     385: bipush        7
     387: invokestatic  #232                // Method org/bouncycastle/util/Integers.rotateLeft:(II)I
     390: ixor
     391: istore        4
     393: iload         5
     395: iload         4
     397: iload_3
     398: iadd
     399: bipush        9
     401: invokestatic  #232                // Method org/bouncycastle/util/Integers.rotateLeft:(II)I
     404: ixor
     405: istore        5
     407: iload         6
     409: iload         5
     411: iload         4
     413: iadd
     414: bipush        13
     416: invokestatic  #232                // Method org/bouncycastle/util/Integers.rotateLeft:(II)I
     419: ixor
     420: istore        6
     422: iload_3
     423: iload         6
     425: iload         5
     427: iadd
     428: bipush        18
     430: invokestatic  #232                // Method org/bouncycastle/util/Integers.rotateLeft:(II)I
     433: ixor
     434: istore_3
     435: iload         9
     437: iload         8
     439: iload         7
     441: iadd
     442: bipush        7
     444: invokestatic  #232                // Method org/bouncycastle/util/Integers.rotateLeft:(II)I
     447: ixor
     448: istore        9
     450: iload         10
     452: iload         9
     454: iload         8
     456: iadd
     457: bipush        9
     459: invokestatic  #232                // Method org/bouncycastle/util/Integers.rotateLeft:(II)I
     462: ixor
     463: istore        10
     465: iload         7
     467: iload         10
     469: iload         9
     471: iadd
     472: bipush        13
     474: invokestatic  #232                // Method org/bouncycastle/util/Integers.rotateLeft:(II)I
     477: ixor
     478: istore        7
     480: iload         8
     482: iload         7
     484: iload         10
     486: iadd
     487: bipush        18
     489: invokestatic  #232                // Method org/bouncycastle/util/Integers.rotateLeft:(II)I
     492: ixor
     493: istore        8
     495: iload         14
     497: iload         13
     499: iload         12
     501: iadd
     502: bipush        7
     504: invokestatic  #232                // Method org/bouncycastle/util/Integers.rotateLeft:(II)I
     507: ixor
     508: istore        14
     510: iload         11
     512: iload         14
     514: iload         13
     516: iadd
     517: bipush        9
     519: invokestatic  #232                // Method org/bouncycastle/util/Integers.rotateLeft:(II)I
     522: ixor
     523: istore        11
     525: iload         12
     527: iload         11
     529: iload         14
     531: iadd
     532: bipush        13
     534: invokestatic  #232                // Method org/bouncycastle/util/Integers.rotateLeft:(II)I
     537: ixor
     538: istore        12
     540: iload         13
     542: iload         12
     544: iload         11
     546: iadd
     547: bipush        18
     549: invokestatic  #232                // Method org/bouncycastle/util/Integers.rotateLeft:(II)I
     552: ixor
     553: istore        13
     555: iload         15
     557: iload         18
     559: iload         17
     561: iadd
     562: bipush        7
     564: invokestatic  #232                // Method org/bouncycastle/util/Integers.rotateLeft:(II)I
     567: ixor
     568: istore        15
     570: iload         16
     572: iload         15
     574: iload         18
     576: iadd
     577: bipush        9
     579: invokestatic  #232                // Method org/bouncycastle/util/Integers.rotateLeft:(II)I
     582: ixor
     583: istore        16
     585: iload         17
     587: iload         16
     589: iload         15
     591: iadd
     592: bipush        13
     594: invokestatic  #232                // Method org/bouncycastle/util/Integers.rotateLeft:(II)I
     597: ixor
     598: istore        17
     600: iload         18
     602: iload         17
     604: iload         16
     606: iadd
     607: bipush        18
     609: invokestatic  #232                // Method org/bouncycastle/util/Integers.rotateLeft:(II)I
     612: ixor
     613: istore        18
     615: iinc          19, -2
     618: goto          138
     621: aload_2
     622: iconst_0
     623: iload_3
     624: aload_1
     625: iconst_0
     626: iaload
     627: iadd
     628: iastore
     629: aload_2
     630: iconst_1
     631: iload         4
     633: aload_1
     634: iconst_1
     635: iaload
     636: iadd
     637: iastore
     638: aload_2
     639: iconst_2
     640: iload         5
     642: aload_1
     643: iconst_2
     644: iaload
     645: iadd
     646: iastore
     647: aload_2
     648: iconst_3
     649: iload         6
     651: aload_1
     652: iconst_3
     653: iaload
     654: iadd
     655: iastore
     656: aload_2
     657: iconst_4
     658: iload         7
     660: aload_1
     661: iconst_4
     662: iaload
     663: iadd
     664: iastore
     665: aload_2
     666: iconst_5
     667: iload         8
     669: aload_1
     670: iconst_5
     671: iaload
     672: iadd
     673: iastore
     674: aload_2
     675: bipush        6
     677: iload         9
     679: aload_1
     680: bipush        6
     682: iaload
     683: iadd
     684: iastore
     685: aload_2
     686: bipush        7
     688: iload         10
     690: aload_1
     691: bipush        7
     693: iaload
     694: iadd
     695: iastore
     696: aload_2
     697: bipush        8
     699: iload         11
     701: aload_1
     702: bipush        8
     704: iaload
     705: iadd
     706: iastore
     707: aload_2
     708: bipush        9
     710: iload         12
     712: aload_1
     713: bipush        9
     715: iaload
     716: iadd
     717: iastore
     718: aload_2
     719: bipush        10
     721: iload         13
     723: aload_1
     724: bipush        10
     726: iaload
     727: iadd
     728: iastore
     729: aload_2
     730: bipush        11
     732: iload         14
     734: aload_1
     735: bipush        11
     737: iaload
     738: iadd
     739: iastore
     740: aload_2
     741: bipush        12
     743: iload         15
     745: aload_1
     746: bipush        12
     748: iaload
     749: iadd
     750: iastore
     751: aload_2
     752: bipush        13
     754: iload         16
     756: aload_1
     757: bipush        13
     759: iaload
     760: iadd
     761: iastore
     762: aload_2
     763: bipush        14
     765: iload         17
     767: aload_1
     768: bipush        14
     770: iaload
     771: iadd
     772: iastore
     773: aload_2
     774: bipush        15
     776: iload         18
     778: aload_1
     779: bipush        15
     781: iaload
     782: iadd
     783: iastore
     784: return

  private void resetLimitCounter();
    Code:
       0: aload_0
       1: iconst_0
       2: putfield      #189                // Field cW0:I
       5: aload_0
       6: iconst_0
       7: putfield      #190                // Field cW1:I
      10: aload_0
      11: iconst_0
      12: putfield      #191                // Field cW2:I
      15: return

  private boolean limitExceeded();
    Code:
       0: aload_0
       1: dup
       2: getfield      #189                // Field cW0:I
       5: iconst_1
       6: iadd
       7: dup_x1
       8: putfield      #189                // Field cW0:I
      11: ifne          51
      14: aload_0
      15: dup
      16: getfield      #190                // Field cW1:I
      19: iconst_1
      20: iadd
      21: dup_x1
      22: putfield      #190                // Field cW1:I
      25: ifne          51
      28: aload_0
      29: dup
      30: getfield      #191                // Field cW2:I
      33: iconst_1
      34: iadd
      35: dup_x1
      36: putfield      #191                // Field cW2:I
      39: bipush        32
      41: iand
      42: ifeq          49
      45: iconst_1
      46: goto          50
      49: iconst_0
      50: ireturn
      51: iconst_0
      52: ireturn

  private boolean limitExceeded(int);
    Code:
       0: aload_0
       1: dup
       2: getfield      #189                // Field cW0:I
       5: iload_1
       6: iadd
       7: putfield      #189                // Field cW0:I
      10: aload_0
      11: getfield      #189                // Field cW0:I
      14: iload_1
      15: if_icmpge     62
      18: aload_0
      19: getfield      #189                // Field cW0:I
      22: iflt          62
      25: aload_0
      26: dup
      27: getfield      #190                // Field cW1:I
      30: iconst_1
      31: iadd
      32: dup_x1
      33: putfield      #190                // Field cW1:I
      36: ifne          62
      39: aload_0
      40: dup
      41: getfield      #191                // Field cW2:I
      44: iconst_1
      45: iadd
      46: dup_x1
      47: putfield      #191                // Field cW2:I
      50: bipush        32
      52: iand
      53: ifeq          60
      56: iconst_1
      57: goto          61
      60: iconst_0
      61: ireturn
      62: iconst_0
      63: ireturn

  static {};
    Code:
       0: ldc           #16                 // String expand 16-byte kexpand 32-byte k
       2: invokestatic  #236                // Method org/bouncycastle/util/Strings.toByteArray:(Ljava/lang/String;)[B
       5: iconst_0
       6: bipush        8
       8: invokestatic  #233                // Method org/bouncycastle/util/Pack.littleEndianToInt:([BII)[I
      11: putstatic     #198                // Field TAU_SIGMA:[I
      14: ldc           #17                 // String expand 32-byte k
      16: invokestatic  #236                // Method org/bouncycastle/util/Strings.toByteArray:(Ljava/lang/String;)[B
      19: putstatic     #196                // Field sigma:[B
      22: ldc           #15                 // String expand 16-byte k
      24: invokestatic  #236                // Method org/bouncycastle/util/Strings.toByteArray:(Ljava/lang/String;)[B
      27: putstatic     #197                // Field tau:[B
      30: return
}
