Compiled from "PluginConfiguration.java"
public class org.apache.maven.model.PluginConfiguration extends org.apache.maven.model.PluginContainer implements java.io.Serializable,java.lang.Cloneable {
  private org.apache.maven.model.PluginManagement pluginManagement;

  public org.apache.maven.model.PluginConfiguration();
    Code:
       0: aload_0
       1: invokespecial #1                  // Method org/apache/maven/model/PluginContainer."<init>":()V
       4: return

  public org.apache.maven.model.PluginConfiguration clone();
    Code:
       0: aload_0
       1: invokespecial #2                  // Method org/apache/maven/model/PluginContainer.clone:()Lorg/apache/maven/model/PluginContainer;
       4: checkcast     #3                  // class org/apache/maven/model/PluginConfiguration
       7: astore_1
       8: aload_0
       9: getfield      #4                  // Field pluginManagement:Lorg/apache/maven/model/PluginManagement;
      12: ifnull        26
      15: aload_1
      16: aload_0
      17: getfield      #4                  // Field pluginManagement:Lorg/apache/maven/model/PluginManagement;
      20: invokevirtual #5                  // Method org/apache/maven/model/PluginManagement.clone:()Lorg/apache/maven/model/PluginManagement;
      23: putfield      #4                  // Field pluginManagement:Lorg/apache/maven/model/PluginManagement;
      26: aload_1
      27: areturn
      28: astore_1
      29: new           #7                  // class java/lang/UnsupportedOperationException
      32: dup
      33: new           #8                  // class java/lang/StringBuilder
      36: dup
      37: invokespecial #9                  // Method java/lang/StringBuilder."<init>":()V
      40: aload_0
      41: invokevirtual #10                 // Method java/lang/Object.getClass:()Ljava/lang/Class;
      44: invokevirtual #11                 // Method java/lang/Class.getName:()Ljava/lang/String;
      47: invokevirtual #12                 // Method java/lang/StringBuilder.append:(Ljava/lang/String;)Ljava/lang/StringBuilder;
      50: ldc           #13                 // String  does not support clone()
      52: invokevirtual #12                 // Method java/lang/StringBuilder.append:(Ljava/lang/String;)Ljava/lang/StringBuilder;
      55: invokevirtual #14                 // Method java/lang/StringBuilder.toString:()Ljava/lang/String;
      58: invokespecial #15                 // Method java/lang/UnsupportedOperationException."<init>":(Ljava/lang/String;)V
      61: aload_1
      62: invokevirtual #16                 // Method java/lang/UnsupportedOperationException.initCause:(Ljava/lang/Throwable;)Ljava/lang/Throwable;
      65: checkcast     #17                 // class java/lang/RuntimeException
      68: athrow
    Exception table:
       from    to  target type
           0    27    28   Class java/lang/Exception

  public org.apache.maven.model.PluginManagement getPluginManagement();
    Code:
       0: aload_0
       1: getfield      #4                  // Field pluginManagement:Lorg/apache/maven/model/PluginManagement;
       4: areturn

  public void setPluginManagement(org.apache.maven.model.PluginManagement);
    Code:
       0: aload_0
       1: aload_1
       2: putfield      #4                  // Field pluginManagement:Lorg/apache/maven/model/PluginManagement;
       5: return

  public org.apache.maven.model.PluginContainer clone();
    Code:
       0: aload_0
       1: invokevirtual #18                 // Method clone:()Lorg/apache/maven/model/PluginConfiguration;
       4: areturn

  public java.lang.Object clone() throws java.lang.CloneNotSupportedException;
    Code:
       0: aload_0
       1: invokevirtual #18                 // Method clone:()Lorg/apache/maven/model/PluginConfiguration;
       4: areturn
}
