Compiled from "KillApplicationResponse.java"
public abstract class org.apache.hadoop.yarn.api.protocolrecords.KillApplicationResponse {
  public org.apache.hadoop.yarn.api.protocolrecords.KillApplicationResponse();
    Code:
       0: aload_0
       1: invokespecial #1                  // Method java/lang/Object."<init>":()V
       4: return

  public static org.apache.hadoop.yarn.api.protocolrecords.KillApplicationResponse newInstance(boolean);
    Code:
       0: ldc           #2                  // class org/apache/hadoop/yarn/api/protocolrecords/KillApplicationResponse
       2: invokestatic  #3                  // Method org/apache/hadoop/yarn/util/Records.newRecord:(Ljava/lang/Class;)Ljava/lang/Object;
       5: checkcast     #2                  // class org/apache/hadoop/yarn/api/protocolrecords/KillApplicationResponse
       8: astore_1
       9: aload_1
      10: iload_0
      11: invokevirtual #4                  // Method setIsKillCompleted:(Z)V
      14: aload_1
      15: areturn

  public abstract boolean getIsKillCompleted();

  public abstract void setIsKillCompleted(boolean);
}
