Compiled from "MoveApplicationAcrossQueuesRequest.java"
public abstract class org.apache.hadoop.yarn.api.protocolrecords.MoveApplicationAcrossQueuesRequest {
  public org.apache.hadoop.yarn.api.protocolrecords.MoveApplicationAcrossQueuesRequest();
    Code:
       0: aload_0
       1: invokespecial #1                  // Method java/lang/Object."<init>":()V
       4: return

  public static org.apache.hadoop.yarn.api.protocolrecords.MoveApplicationAcrossQueuesRequest newInstance(org.apache.hadoop.yarn.api.records.ApplicationId, java.lang.String);
    Code:
       0: ldc           #2                  // class org/apache/hadoop/yarn/api/protocolrecords/MoveApplicationAcrossQueuesRequest
       2: invokestatic  #3                  // Method org/apache/hadoop/yarn/util/Records.newRecord:(Ljava/lang/Class;)Ljava/lang/Object;
       5: checkcast     #2                  // class org/apache/hadoop/yarn/api/protocolrecords/MoveApplicationAcrossQueuesRequest
       8: astore_2
       9: aload_2
      10: aload_0
      11: invokevirtual #4                  // Method setApplicationId:(Lorg/apache/hadoop/yarn/api/records/ApplicationId;)V
      14: aload_2
      15: aload_1
      16: invokevirtual #5                  // Method setTargetQueue:(Ljava/lang/String;)V
      19: aload_2
      20: areturn

  public abstract org.apache.hadoop.yarn.api.records.ApplicationId getApplicationId();

  public abstract void setApplicationId(org.apache.hadoop.yarn.api.records.ApplicationId);

  public abstract java.lang.String getTargetQueue();

  public abstract void setTargetQueue(java.lang.String);
}
