Compiled from "UpdateApplicationPriorityRequest.java"
public abstract class org.apache.hadoop.yarn.api.protocolrecords.UpdateApplicationPriorityRequest {
  public org.apache.hadoop.yarn.api.protocolrecords.UpdateApplicationPriorityRequest();
    Code:
       0: aload_0
       1: invokespecial #1                  // Method java/lang/Object."<init>":()V
       4: return

  public static org.apache.hadoop.yarn.api.protocolrecords.UpdateApplicationPriorityRequest newInstance(org.apache.hadoop.yarn.api.records.ApplicationId, org.apache.hadoop.yarn.api.records.Priority);
    Code:
       0: ldc           #2                  // class org/apache/hadoop/yarn/api/protocolrecords/UpdateApplicationPriorityRequest
       2: invokestatic  #3                  // Method org/apache/hadoop/yarn/util/Records.newRecord:(Ljava/lang/Class;)Ljava/lang/Object;
       5: checkcast     #2                  // class org/apache/hadoop/yarn/api/protocolrecords/UpdateApplicationPriorityRequest
       8: astore_2
       9: aload_2
      10: aload_0
      11: invokevirtual #4                  // Method setApplicationId:(Lorg/apache/hadoop/yarn/api/records/ApplicationId;)V
      14: aload_2
      15: aload_1
      16: invokevirtual #5                  // Method setApplicationPriority:(Lorg/apache/hadoop/yarn/api/records/Priority;)V
      19: aload_2
      20: areturn

  public abstract org.apache.hadoop.yarn.api.records.ApplicationId getApplicationId();

  public abstract void setApplicationId(org.apache.hadoop.yarn.api.records.ApplicationId);

  public abstract org.apache.hadoop.yarn.api.records.Priority getApplicationPriority();

  public abstract void setApplicationPriority(org.apache.hadoop.yarn.api.records.Priority);
}
