Compiled from "BooleanTextWriterFactory.java"
public class org.eclipse.rdf4j.query.resultio.text.BooleanTextWriterFactory implements org.eclipse.rdf4j.query.resultio.BooleanQueryResultWriterFactory {
  public org.eclipse.rdf4j.query.resultio.text.BooleanTextWriterFactory();
    Code:
       0: aload_0
       1: invokespecial #1                  // Method java/lang/Object."<init>":()V
       4: return

  public org.eclipse.rdf4j.query.resultio.BooleanQueryResultFormat getBooleanQueryResultFormat();
    Code:
       0: getstatic     #2                  // Field org/eclipse/rdf4j/query/resultio/BooleanQueryResultFormat.TEXT:Lorg/eclipse/rdf4j/query/resultio/BooleanQueryResultFormat;
       3: areturn

  public org.eclipse.rdf4j.query.resultio.BooleanQueryResultWriter getWriter(java.io.OutputStream);
    Code:
       0: new           #3                  // class org/eclipse/rdf4j/query/resultio/text/BooleanTextWriter
       3: dup
       4: aload_1
       5: invokespecial #4                  // Method org/eclipse/rdf4j/query/resultio/text/BooleanTextWriter."<init>":(Ljava/io/OutputStream;)V
       8: areturn
}
