Compiled from "UriEscape.java"
public final class org.unbescape.uri.UriEscape {
  public static final java.lang.String DEFAULT_ENCODING;

  public static java.lang.String escapeUriPath(java.lang.String);
    Code:
       0: aload_0
       1: ldc           #2                  // String UTF-8
       3: invokestatic  #3                  // Method escapeUriPath:(Ljava/lang/String;Ljava/lang/String;)Ljava/lang/String;
       6: areturn

  public static java.lang.String escapeUriPath(java.lang.String, java.lang.String);
    Code:
       0: aload_1
       1: ifnonnull     14
       4: new           #4                  // class java/lang/IllegalArgumentException
       7: dup
       8: ldc           #5                  // String Argument \'encoding\' cannot be null
      10: invokespecial #6                  // Method java/lang/IllegalArgumentException."<init>":(Ljava/lang/String;)V
      13: athrow
      14: aload_0
      15: getstatic     #7                  // Field org/unbescape/uri/UriEscapeUtil$UriEscapeType.PATH:Lorg/unbescape/uri/UriEscapeUtil$UriEscapeType;
      18: aload_1
      19: invokestatic  #8                  // Method org/unbescape/uri/UriEscapeUtil.escape:(Ljava/lang/String;Lorg/unbescape/uri/UriEscapeUtil$UriEscapeType;Ljava/lang/String;)Ljava/lang/String;
      22: areturn

  public static java.lang.String escapeUriPathSegment(java.lang.String);
    Code:
       0: aload_0
       1: ldc           #2                  // String UTF-8
       3: invokestatic  #9                  // Method escapeUriPathSegment:(Ljava/lang/String;Ljava/lang/String;)Ljava/lang/String;
       6: areturn

  public static java.lang.String escapeUriPathSegment(java.lang.String, java.lang.String);
    Code:
       0: aload_1
       1: ifnonnull     14
       4: new           #4                  // class java/lang/IllegalArgumentException
       7: dup
       8: ldc           #5                  // String Argument \'encoding\' cannot be null
      10: invokespecial #6                  // Method java/lang/IllegalArgumentException."<init>":(Ljava/lang/String;)V
      13: athrow
      14: aload_0
      15: getstatic     #10                 // Field org/unbescape/uri/UriEscapeUtil$UriEscapeType.PATH_SEGMENT:Lorg/unbescape/uri/UriEscapeUtil$UriEscapeType;
      18: aload_1
      19: invokestatic  #8                  // Method org/unbescape/uri/UriEscapeUtil.escape:(Ljava/lang/String;Lorg/unbescape/uri/UriEscapeUtil$UriEscapeType;Ljava/lang/String;)Ljava/lang/String;
      22: areturn

  public static java.lang.String escapeUriQueryParam(java.lang.String);
    Code:
       0: aload_0
       1: ldc           #2                  // String UTF-8
       3: invokestatic  #11                 // Method escapeUriQueryParam:(Ljava/lang/String;Ljava/lang/String;)Ljava/lang/String;
       6: areturn

  public static java.lang.String escapeUriQueryParam(java.lang.String, java.lang.String);
    Code:
       0: aload_1
       1: ifnonnull     14
       4: new           #4                  // class java/lang/IllegalArgumentException
       7: dup
       8: ldc           #5                  // String Argument \'encoding\' cannot be null
      10: invokespecial #6                  // Method java/lang/IllegalArgumentException."<init>":(Ljava/lang/String;)V
      13: athrow
      14: aload_0
      15: getstatic     #12                 // Field org/unbescape/uri/UriEscapeUtil$UriEscapeType.QUERY_PARAM:Lorg/unbescape/uri/UriEscapeUtil$UriEscapeType;
      18: aload_1
      19: invokestatic  #8                  // Method org/unbescape/uri/UriEscapeUtil.escape:(Ljava/lang/String;Lorg/unbescape/uri/UriEscapeUtil$UriEscapeType;Ljava/lang/String;)Ljava/lang/String;
      22: areturn

  public static java.lang.String escapeUriFragmentId(java.lang.String);
    Code:
       0: aload_0
       1: ldc           #2                  // String UTF-8
       3: invokestatic  #13                 // Method escapeUriFragmentId:(Ljava/lang/String;Ljava/lang/String;)Ljava/lang/String;
       6: areturn

  public static java.lang.String escapeUriFragmentId(java.lang.String, java.lang.String);
    Code:
       0: aload_1
       1: ifnonnull     14
       4: new           #4                  // class java/lang/IllegalArgumentException
       7: dup
       8: ldc           #5                  // String Argument \'encoding\' cannot be null
      10: invokespecial #6                  // Method java/lang/IllegalArgumentException."<init>":(Ljava/lang/String;)V
      13: athrow
      14: aload_0
      15: getstatic     #14                 // Field org/unbescape/uri/UriEscapeUtil$UriEscapeType.FRAGMENT_ID:Lorg/unbescape/uri/UriEscapeUtil$UriEscapeType;
      18: aload_1
      19: invokestatic  #8                  // Method org/unbescape/uri/UriEscapeUtil.escape:(Ljava/lang/String;Lorg/unbescape/uri/UriEscapeUtil$UriEscapeType;Ljava/lang/String;)Ljava/lang/String;
      22: areturn

  public static void escapeUriPath(java.lang.String, java.io.Writer) throws java.io.IOException;
    Code:
       0: aload_0
       1: aload_1
       2: ldc           #2                  // String UTF-8
       4: invokestatic  #15                 // Method escapeUriPath:(Ljava/lang/String;Ljava/io/Writer;Ljava/lang/String;)V
       7: return

  public static void escapeUriPath(java.lang.String, java.io.Writer, java.lang.String) throws java.io.IOException;
    Code:
       0: aload_1
       1: ifnonnull     14
       4: new           #4                  // class java/lang/IllegalArgumentException
       7: dup
       8: ldc           #16                 // String Argument \'writer\' cannot be null
      10: invokespecial #6                  // Method java/lang/IllegalArgumentException."<init>":(Ljava/lang/String;)V
      13: athrow
      14: aload_2
      15: ifnonnull     28
      18: new           #4                  // class java/lang/IllegalArgumentException
      21: dup
      22: ldc           #5                  // String Argument \'encoding\' cannot be null
      24: invokespecial #6                  // Method java/lang/IllegalArgumentException."<init>":(Ljava/lang/String;)V
      27: athrow
      28: new           #17                 // class org/unbescape/uri/UriEscape$InternalStringReader
      31: dup
      32: aload_0
      33: invokespecial #18                 // Method org/unbescape/uri/UriEscape$InternalStringReader."<init>":(Ljava/lang/String;)V
      36: aload_1
      37: getstatic     #7                  // Field org/unbescape/uri/UriEscapeUtil$UriEscapeType.PATH:Lorg/unbescape/uri/UriEscapeUtil$UriEscapeType;
      40: aload_2
      41: invokestatic  #19                 // Method org/unbescape/uri/UriEscapeUtil.escape:(Ljava/io/Reader;Ljava/io/Writer;Lorg/unbescape/uri/UriEscapeUtil$UriEscapeType;Ljava/lang/String;)V
      44: return

  public static void escapeUriPathSegment(java.lang.String, java.io.Writer) throws java.io.IOException;
    Code:
       0: aload_0
       1: aload_1
       2: ldc           #2                  // String UTF-8
       4: invokestatic  #20                 // Method escapeUriPathSegment:(Ljava/lang/String;Ljava/io/Writer;Ljava/lang/String;)V
       7: return

  public static void escapeUriPathSegment(java.lang.String, java.io.Writer, java.lang.String) throws java.io.IOException;
    Code:
       0: aload_1
       1: ifnonnull     14
       4: new           #4                  // class java/lang/IllegalArgumentException
       7: dup
       8: ldc           #16                 // String Argument \'writer\' cannot be null
      10: invokespecial #6                  // Method java/lang/IllegalArgumentException."<init>":(Ljava/lang/String;)V
      13: athrow
      14: aload_2
      15: ifnonnull     28
      18: new           #4                  // class java/lang/IllegalArgumentException
      21: dup
      22: ldc           #5                  // String Argument \'encoding\' cannot be null
      24: invokespecial #6                  // Method java/lang/IllegalArgumentException."<init>":(Ljava/lang/String;)V
      27: athrow
      28: new           #17                 // class org/unbescape/uri/UriEscape$InternalStringReader
      31: dup
      32: aload_0
      33: invokespecial #18                 // Method org/unbescape/uri/UriEscape$InternalStringReader."<init>":(Ljava/lang/String;)V
      36: aload_1
      37: getstatic     #10                 // Field org/unbescape/uri/UriEscapeUtil$UriEscapeType.PATH_SEGMENT:Lorg/unbescape/uri/UriEscapeUtil$UriEscapeType;
      40: aload_2
      41: invokestatic  #19                 // Method org/unbescape/uri/UriEscapeUtil.escape:(Ljava/io/Reader;Ljava/io/Writer;Lorg/unbescape/uri/UriEscapeUtil$UriEscapeType;Ljava/lang/String;)V
      44: return

  public static void escapeUriQueryParam(java.lang.String, java.io.Writer) throws java.io.IOException;
    Code:
       0: aload_0
       1: aload_1
       2: ldc           #2                  // String UTF-8
       4: invokestatic  #21                 // Method escapeUriQueryParam:(Ljava/lang/String;Ljava/io/Writer;Ljava/lang/String;)V
       7: return

  public static void escapeUriQueryParam(java.lang.String, java.io.Writer, java.lang.String) throws java.io.IOException;
    Code:
       0: aload_1
       1: ifnonnull     14
       4: new           #4                  // class java/lang/IllegalArgumentException
       7: dup
       8: ldc           #16                 // String Argument \'writer\' cannot be null
      10: invokespecial #6                  // Method java/lang/IllegalArgumentException."<init>":(Ljava/lang/String;)V
      13: athrow
      14: aload_2
      15: ifnonnull     28
      18: new           #4                  // class java/lang/IllegalArgumentException
      21: dup
      22: ldc           #5                  // String Argument \'encoding\' cannot be null
      24: invokespecial #6                  // Method java/lang/IllegalArgumentException."<init>":(Ljava/lang/String;)V
      27: athrow
      28: new           #17                 // class org/unbescape/uri/UriEscape$InternalStringReader
      31: dup
      32: aload_0
      33: invokespecial #18                 // Method org/unbescape/uri/UriEscape$InternalStringReader."<init>":(Ljava/lang/String;)V
      36: aload_1
      37: getstatic     #12                 // Field org/unbescape/uri/UriEscapeUtil$UriEscapeType.QUERY_PARAM:Lorg/unbescape/uri/UriEscapeUtil$UriEscapeType;
      40: aload_2
      41: invokestatic  #19                 // Method org/unbescape/uri/UriEscapeUtil.escape:(Ljava/io/Reader;Ljava/io/Writer;Lorg/unbescape/uri/UriEscapeUtil$UriEscapeType;Ljava/lang/String;)V
      44: return

  public static void escapeUriFragmentId(java.lang.String, java.io.Writer) throws java.io.IOException;
    Code:
       0: aload_0
       1: aload_1
       2: ldc           #2                  // String UTF-8
       4: invokestatic  #22                 // Method escapeUriFragmentId:(Ljava/lang/String;Ljava/io/Writer;Ljava/lang/String;)V
       7: return

  public static void escapeUriFragmentId(java.lang.String, java.io.Writer, java.lang.String) throws java.io.IOException;
    Code:
       0: aload_1
       1: ifnonnull     14
       4: new           #4                  // class java/lang/IllegalArgumentException
       7: dup
       8: ldc           #16                 // String Argument \'writer\' cannot be null
      10: invokespecial #6                  // Method java/lang/IllegalArgumentException."<init>":(Ljava/lang/String;)V
      13: athrow
      14: aload_2
      15: ifnonnull     28
      18: new           #4                  // class java/lang/IllegalArgumentException
      21: dup
      22: ldc           #5                  // String Argument \'encoding\' cannot be null
      24: invokespecial #6                  // Method java/lang/IllegalArgumentException."<init>":(Ljava/lang/String;)V
      27: athrow
      28: new           #17                 // class org/unbescape/uri/UriEscape$InternalStringReader
      31: dup
      32: aload_0
      33: invokespecial #18                 // Method org/unbescape/uri/UriEscape$InternalStringReader."<init>":(Ljava/lang/String;)V
      36: aload_1
      37: getstatic     #14                 // Field org/unbescape/uri/UriEscapeUtil$UriEscapeType.FRAGMENT_ID:Lorg/unbescape/uri/UriEscapeUtil$UriEscapeType;
      40: aload_2
      41: invokestatic  #19                 // Method org/unbescape/uri/UriEscapeUtil.escape:(Ljava/io/Reader;Ljava/io/Writer;Lorg/unbescape/uri/UriEscapeUtil$UriEscapeType;Ljava/lang/String;)V
      44: return

  public static void escapeUriPath(java.io.Reader, java.io.Writer) throws java.io.IOException;
    Code:
       0: aload_0
       1: aload_1
       2: ldc           #2                  // String UTF-8
       4: invokestatic  #23                 // Method escapeUriPath:(Ljava/io/Reader;Ljava/io/Writer;Ljava/lang/String;)V
       7: return

  public static void escapeUriPath(java.io.Reader, java.io.Writer, java.lang.String) throws java.io.IOException;
    Code:
       0: aload_1
       1: ifnonnull     14
       4: new           #4                  // class java/lang/IllegalArgumentException
       7: dup
       8: ldc           #16                 // String Argument \'writer\' cannot be null
      10: invokespecial #6                  // Method java/lang/IllegalArgumentException."<init>":(Ljava/lang/String;)V
      13: athrow
      14: aload_2
      15: ifnonnull     28
      18: new           #4                  // class java/lang/IllegalArgumentException
      21: dup
      22: ldc           #5                  // String Argument \'encoding\' cannot be null
      24: invokespecial #6                  // Method java/lang/IllegalArgumentException."<init>":(Ljava/lang/String;)V
      27: athrow
      28: aload_0
      29: aload_1
      30: getstatic     #7                  // Field org/unbescape/uri/UriEscapeUtil$UriEscapeType.PATH:Lorg/unbescape/uri/UriEscapeUtil$UriEscapeType;
      33: aload_2
      34: invokestatic  #19                 // Method org/unbescape/uri/UriEscapeUtil.escape:(Ljava/io/Reader;Ljava/io/Writer;Lorg/unbescape/uri/UriEscapeUtil$UriEscapeType;Ljava/lang/String;)V
      37: return

  public static void escapeUriPathSegment(java.io.Reader, java.io.Writer) throws java.io.IOException;
    Code:
       0: aload_0
       1: aload_1
       2: ldc           #2                  // String UTF-8
       4: invokestatic  #24                 // Method escapeUriPathSegment:(Ljava/io/Reader;Ljava/io/Writer;Ljava/lang/String;)V
       7: return

  public static void escapeUriPathSegment(java.io.Reader, java.io.Writer, java.lang.String) throws java.io.IOException;
    Code:
       0: aload_1
       1: ifnonnull     14
       4: new           #4                  // class java/lang/IllegalArgumentException
       7: dup
       8: ldc           #16                 // String Argument \'writer\' cannot be null
      10: invokespecial #6                  // Method java/lang/IllegalArgumentException."<init>":(Ljava/lang/String;)V
      13: athrow
      14: aload_2
      15: ifnonnull     28
      18: new           #4                  // class java/lang/IllegalArgumentException
      21: dup
      22: ldc           #5                  // String Argument \'encoding\' cannot be null
      24: invokespecial #6                  // Method java/lang/IllegalArgumentException."<init>":(Ljava/lang/String;)V
      27: athrow
      28: aload_0
      29: aload_1
      30: getstatic     #10                 // Field org/unbescape/uri/UriEscapeUtil$UriEscapeType.PATH_SEGMENT:Lorg/unbescape/uri/UriEscapeUtil$UriEscapeType;
      33: aload_2
      34: invokestatic  #19                 // Method org/unbescape/uri/UriEscapeUtil.escape:(Ljava/io/Reader;Ljava/io/Writer;Lorg/unbescape/uri/UriEscapeUtil$UriEscapeType;Ljava/lang/String;)V
      37: return

  public static void escapeUriQueryParam(java.io.Reader, java.io.Writer) throws java.io.IOException;
    Code:
       0: aload_0
       1: aload_1
       2: ldc           #2                  // String UTF-8
       4: invokestatic  #25                 // Method escapeUriQueryParam:(Ljava/io/Reader;Ljava/io/Writer;Ljava/lang/String;)V
       7: return

  public static void escapeUriQueryParam(java.io.Reader, java.io.Writer, java.lang.String) throws java.io.IOException;
    Code:
       0: aload_1
       1: ifnonnull     14
       4: new           #4                  // class java/lang/IllegalArgumentException
       7: dup
       8: ldc           #16                 // String Argument \'writer\' cannot be null
      10: invokespecial #6                  // Method java/lang/IllegalArgumentException."<init>":(Ljava/lang/String;)V
      13: athrow
      14: aload_2
      15: ifnonnull     28
      18: new           #4                  // class java/lang/IllegalArgumentException
      21: dup
      22: ldc           #5                  // String Argument \'encoding\' cannot be null
      24: invokespecial #6                  // Method java/lang/IllegalArgumentException."<init>":(Ljava/lang/String;)V
      27: athrow
      28: aload_0
      29: aload_1
      30: getstatic     #12                 // Field org/unbescape/uri/UriEscapeUtil$UriEscapeType.QUERY_PARAM:Lorg/unbescape/uri/UriEscapeUtil$UriEscapeType;
      33: aload_2
      34: invokestatic  #19                 // Method org/unbescape/uri/UriEscapeUtil.escape:(Ljava/io/Reader;Ljava/io/Writer;Lorg/unbescape/uri/UriEscapeUtil$UriEscapeType;Ljava/lang/String;)V
      37: return

  public static void escapeUriFragmentId(java.io.Reader, java.io.Writer) throws java.io.IOException;
    Code:
       0: aload_0
       1: aload_1
       2: ldc           #2                  // String UTF-8
       4: invokestatic  #26                 // Method escapeUriFragmentId:(Ljava/io/Reader;Ljava/io/Writer;Ljava/lang/String;)V
       7: return

  public static void escapeUriFragmentId(java.io.Reader, java.io.Writer, java.lang.String) throws java.io.IOException;
    Code:
       0: aload_1
       1: ifnonnull     14
       4: new           #4                  // class java/lang/IllegalArgumentException
       7: dup
       8: ldc           #16                 // String Argument \'writer\' cannot be null
      10: invokespecial #6                  // Method java/lang/IllegalArgumentException."<init>":(Ljava/lang/String;)V
      13: athrow
      14: aload_2
      15: ifnonnull     28
      18: new           #4                  // class java/lang/IllegalArgumentException
      21: dup
      22: ldc           #5                  // String Argument \'encoding\' cannot be null
      24: invokespecial #6                  // Method java/lang/IllegalArgumentException."<init>":(Ljava/lang/String;)V
      27: athrow
      28: aload_0
      29: aload_1
      30: getstatic     #14                 // Field org/unbescape/uri/UriEscapeUtil$UriEscapeType.FRAGMENT_ID:Lorg/unbescape/uri/UriEscapeUtil$UriEscapeType;
      33: aload_2
      34: invokestatic  #19                 // Method org/unbescape/uri/UriEscapeUtil.escape:(Ljava/io/Reader;Ljava/io/Writer;Lorg/unbescape/uri/UriEscapeUtil$UriEscapeType;Ljava/lang/String;)V
      37: return

  public static void escapeUriPath(char[], int, int, java.io.Writer) throws java.io.IOException;
    Code:
       0: aload_0
       1: iload_1
       2: iload_2
       3: aload_3
       4: ldc           #2                  // String UTF-8
       6: invokestatic  #27                 // Method escapeUriPath:([CIILjava/io/Writer;Ljava/lang/String;)V
       9: return

  public static void escapeUriPath(char[], int, int, java.io.Writer, java.lang.String) throws java.io.IOException;
    Code:
       0: aload_3
       1: ifnonnull     14
       4: new           #4                  // class java/lang/IllegalArgumentException
       7: dup
       8: ldc           #16                 // String Argument \'writer\' cannot be null
      10: invokespecial #6                  // Method java/lang/IllegalArgumentException."<init>":(Ljava/lang/String;)V
      13: athrow
      14: aload         4
      16: ifnonnull     29
      19: new           #4                  // class java/lang/IllegalArgumentException
      22: dup
      23: ldc           #5                  // String Argument \'encoding\' cannot be null
      25: invokespecial #6                  // Method java/lang/IllegalArgumentException."<init>":(Ljava/lang/String;)V
      28: athrow
      29: aload_0
      30: ifnonnull     37
      33: iconst_0
      34: goto          39
      37: aload_0
      38: arraylength
      39: istore        5
      41: iload_1
      42: iflt          51
      45: iload_1
      46: iload         5
      48: if_icmple     97
      51: new           #4                  // class java/lang/IllegalArgumentException
      54: dup
      55: new           #28                 // class java/lang/StringBuilder
      58: dup
      59: invokespecial #29                 // Method java/lang/StringBuilder."<init>":()V
      62: ldc           #30                 // String Invalid (offset, len). offset=
      64: invokevirtual #31                 // Method java/lang/StringBuilder.append:(Ljava/lang/String;)Ljava/lang/StringBuilder;
      67: iload_1
      68: invokevirtual #32                 // Method java/lang/StringBuilder.append:(I)Ljava/lang/StringBuilder;
      71: ldc           #33                 // String , len=
      73: invokevirtual #31                 // Method java/lang/StringBuilder.append:(Ljava/lang/String;)Ljava/lang/StringBuilder;
      76: iload_2
      77: invokevirtual #32                 // Method java/lang/StringBuilder.append:(I)Ljava/lang/StringBuilder;
      80: ldc           #34                 // String , text.length=
      82: invokevirtual #31                 // Method java/lang/StringBuilder.append:(Ljava/lang/String;)Ljava/lang/StringBuilder;
      85: iload         5
      87: invokevirtual #32                 // Method java/lang/StringBuilder.append:(I)Ljava/lang/StringBuilder;
      90: invokevirtual #35                 // Method java/lang/StringBuilder.toString:()Ljava/lang/String;
      93: invokespecial #6                  // Method java/lang/IllegalArgumentException."<init>":(Ljava/lang/String;)V
      96: athrow
      97: iload_2
      98: iflt          109
     101: iload_1
     102: iload_2
     103: iadd
     104: iload         5
     106: if_icmple     155
     109: new           #4                  // class java/lang/IllegalArgumentException
     112: dup
     113: new           #28                 // class java/lang/StringBuilder
     116: dup
     117: invokespecial #29                 // Method java/lang/StringBuilder."<init>":()V
     120: ldc           #30                 // String Invalid (offset, len). offset=
     122: invokevirtual #31                 // Method java/lang/StringBuilder.append:(Ljava/lang/String;)Ljava/lang/StringBuilder;
     125: iload_1
     126: invokevirtual #32                 // Method java/lang/StringBuilder.append:(I)Ljava/lang/StringBuilder;
     129: ldc           #33                 // String , len=
     131: invokevirtual #31                 // Method java/lang/StringBuilder.append:(Ljava/lang/String;)Ljava/lang/StringBuilder;
     134: iload_2
     135: invokevirtual #32                 // Method java/lang/StringBuilder.append:(I)Ljava/lang/StringBuilder;
     138: ldc           #34                 // String , text.length=
     140: invokevirtual #31                 // Method java/lang/StringBuilder.append:(Ljava/lang/String;)Ljava/lang/StringBuilder;
     143: iload         5
     145: invokevirtual #32                 // Method java/lang/StringBuilder.append:(I)Ljava/lang/StringBuilder;
     148: invokevirtual #35                 // Method java/lang/StringBuilder.toString:()Ljava/lang/String;
     151: invokespecial #6                  // Method java/lang/IllegalArgumentException."<init>":(Ljava/lang/String;)V
     154: athrow
     155: aload_0
     156: iload_1
     157: iload_2
     158: aload_3
     159: getstatic     #7                  // Field org/unbescape/uri/UriEscapeUtil$UriEscapeType.PATH:Lorg/unbescape/uri/UriEscapeUtil$UriEscapeType;
     162: aload         4
     164: invokestatic  #36                 // Method org/unbescape/uri/UriEscapeUtil.escape:([CIILjava/io/Writer;Lorg/unbescape/uri/UriEscapeUtil$UriEscapeType;Ljava/lang/String;)V
     167: return

  public static void escapeUriPathSegment(char[], int, int, java.io.Writer) throws java.io.IOException;
    Code:
       0: aload_0
       1: iload_1
       2: iload_2
       3: aload_3
       4: ldc           #2                  // String UTF-8
       6: invokestatic  #37                 // Method escapeUriPathSegment:([CIILjava/io/Writer;Ljava/lang/String;)V
       9: return

  public static void escapeUriPathSegment(char[], int, int, java.io.Writer, java.lang.String) throws java.io.IOException;
    Code:
       0: aload_3
       1: ifnonnull     14
       4: new           #4                  // class java/lang/IllegalArgumentException
       7: dup
       8: ldc           #16                 // String Argument \'writer\' cannot be null
      10: invokespecial #6                  // Method java/lang/IllegalArgumentException."<init>":(Ljava/lang/String;)V
      13: athrow
      14: aload         4
      16: ifnonnull     29
      19: new           #4                  // class java/lang/IllegalArgumentException
      22: dup
      23: ldc           #5                  // String Argument \'encoding\' cannot be null
      25: invokespecial #6                  // Method java/lang/IllegalArgumentException."<init>":(Ljava/lang/String;)V
      28: athrow
      29: aload_0
      30: ifnonnull     37
      33: iconst_0
      34: goto          39
      37: aload_0
      38: arraylength
      39: istore        5
      41: iload_1
      42: iflt          51
      45: iload_1
      46: iload         5
      48: if_icmple     97
      51: new           #4                  // class java/lang/IllegalArgumentException
      54: dup
      55: new           #28                 // class java/lang/StringBuilder
      58: dup
      59: invokespecial #29                 // Method java/lang/StringBuilder."<init>":()V
      62: ldc           #30                 // String Invalid (offset, len). offset=
      64: invokevirtual #31                 // Method java/lang/StringBuilder.append:(Ljava/lang/String;)Ljava/lang/StringBuilder;
      67: iload_1
      68: invokevirtual #32                 // Method java/lang/StringBuilder.append:(I)Ljava/lang/StringBuilder;
      71: ldc           #33                 // String , len=
      73: invokevirtual #31                 // Method java/lang/StringBuilder.append:(Ljava/lang/String;)Ljava/lang/StringBuilder;
      76: iload_2
      77: invokevirtual #32                 // Method java/lang/StringBuilder.append:(I)Ljava/lang/StringBuilder;
      80: ldc           #34                 // String , text.length=
      82: invokevirtual #31                 // Method java/lang/StringBuilder.append:(Ljava/lang/String;)Ljava/lang/StringBuilder;
      85: iload         5
      87: invokevirtual #32                 // Method java/lang/StringBuilder.append:(I)Ljava/lang/StringBuilder;
      90: invokevirtual #35                 // Method java/lang/StringBuilder.toString:()Ljava/lang/String;
      93: invokespecial #6                  // Method java/lang/IllegalArgumentException."<init>":(Ljava/lang/String;)V
      96: athrow
      97: iload_2
      98: iflt          109
     101: iload_1
     102: iload_2
     103: iadd
     104: iload         5
     106: if_icmple     155
     109: new           #4                  // class java/lang/IllegalArgumentException
     112: dup
     113: new           #28                 // class java/lang/StringBuilder
     116: dup
     117: invokespecial #29                 // Method java/lang/StringBuilder."<init>":()V
     120: ldc           #30                 // String Invalid (offset, len). offset=
     122: invokevirtual #31                 // Method java/lang/StringBuilder.append:(Ljava/lang/String;)Ljava/lang/StringBuilder;
     125: iload_1
     126: invokevirtual #32                 // Method java/lang/StringBuilder.append:(I)Ljava/lang/StringBuilder;
     129: ldc           #33                 // String , len=
     131: invokevirtual #31                 // Method java/lang/StringBuilder.append:(Ljava/lang/String;)Ljava/lang/StringBuilder;
     134: iload_2
     135: invokevirtual #32                 // Method java/lang/StringBuilder.append:(I)Ljava/lang/StringBuilder;
     138: ldc           #34                 // String , text.length=
     140: invokevirtual #31                 // Method java/lang/StringBuilder.append:(Ljava/lang/String;)Ljava/lang/StringBuilder;
     143: iload         5
     145: invokevirtual #32                 // Method java/lang/StringBuilder.append:(I)Ljava/lang/StringBuilder;
     148: invokevirtual #35                 // Method java/lang/StringBuilder.toString:()Ljava/lang/String;
     151: invokespecial #6                  // Method java/lang/IllegalArgumentException."<init>":(Ljava/lang/String;)V
     154: athrow
     155: aload_0
     156: iload_1
     157: iload_2
     158: aload_3
     159: getstatic     #10                 // Field org/unbescape/uri/UriEscapeUtil$UriEscapeType.PATH_SEGMENT:Lorg/unbescape/uri/UriEscapeUtil$UriEscapeType;
     162: aload         4
     164: invokestatic  #36                 // Method org/unbescape/uri/UriEscapeUtil.escape:([CIILjava/io/Writer;Lorg/unbescape/uri/UriEscapeUtil$UriEscapeType;Ljava/lang/String;)V
     167: return

  public static void escapeUriQueryParam(char[], int, int, java.io.Writer) throws java.io.IOException;
    Code:
       0: aload_0
       1: iload_1
       2: iload_2
       3: aload_3
       4: ldc           #2                  // String UTF-8
       6: invokestatic  #38                 // Method escapeUriQueryParam:([CIILjava/io/Writer;Ljava/lang/String;)V
       9: return

  public static void escapeUriQueryParam(char[], int, int, java.io.Writer, java.lang.String) throws java.io.IOException;
    Code:
       0: aload_3
       1: ifnonnull     14
       4: new           #4                  // class java/lang/IllegalArgumentException
       7: dup
       8: ldc           #16                 // String Argument \'writer\' cannot be null
      10: invokespecial #6                  // Method java/lang/IllegalArgumentException."<init>":(Ljava/lang/String;)V
      13: athrow
      14: aload         4
      16: ifnonnull     29
      19: new           #4                  // class java/lang/IllegalArgumentException
      22: dup
      23: ldc           #5                  // String Argument \'encoding\' cannot be null
      25: invokespecial #6                  // Method java/lang/IllegalArgumentException."<init>":(Ljava/lang/String;)V
      28: athrow
      29: aload_0
      30: ifnonnull     37
      33: iconst_0
      34: goto          39
      37: aload_0
      38: arraylength
      39: istore        5
      41: iload_1
      42: iflt          51
      45: iload_1
      46: iload         5
      48: if_icmple     97
      51: new           #4                  // class java/lang/IllegalArgumentException
      54: dup
      55: new           #28                 // class java/lang/StringBuilder
      58: dup
      59: invokespecial #29                 // Method java/lang/StringBuilder."<init>":()V
      62: ldc           #30                 // String Invalid (offset, len). offset=
      64: invokevirtual #31                 // Method java/lang/StringBuilder.append:(Ljava/lang/String;)Ljava/lang/StringBuilder;
      67: iload_1
      68: invokevirtual #32                 // Method java/lang/StringBuilder.append:(I)Ljava/lang/StringBuilder;
      71: ldc           #33                 // String , len=
      73: invokevirtual #31                 // Method java/lang/StringBuilder.append:(Ljava/lang/String;)Ljava/lang/StringBuilder;
      76: iload_2
      77: invokevirtual #32                 // Method java/lang/StringBuilder.append:(I)Ljava/lang/StringBuilder;
      80: ldc           #34                 // String , text.length=
      82: invokevirtual #31                 // Method java/lang/StringBuilder.append:(Ljava/lang/String;)Ljava/lang/StringBuilder;
      85: iload         5
      87: invokevirtual #32                 // Method java/lang/StringBuilder.append:(I)Ljava/lang/StringBuilder;
      90: invokevirtual #35                 // Method java/lang/StringBuilder.toString:()Ljava/lang/String;
      93: invokespecial #6                  // Method java/lang/IllegalArgumentException."<init>":(Ljava/lang/String;)V
      96: athrow
      97: iload_2
      98: iflt          109
     101: iload_1
     102: iload_2
     103: iadd
     104: iload         5
     106: if_icmple     155
     109: new           #4                  // class java/lang/IllegalArgumentException
     112: dup
     113: new           #28                 // class java/lang/StringBuilder
     116: dup
     117: invokespecial #29                 // Method java/lang/StringBuilder."<init>":()V
     120: ldc           #30                 // String Invalid (offset, len). offset=
     122: invokevirtual #31                 // Method java/lang/StringBuilder.append:(Ljava/lang/String;)Ljava/lang/StringBuilder;
     125: iload_1
     126: invokevirtual #32                 // Method java/lang/StringBuilder.append:(I)Ljava/lang/StringBuilder;
     129: ldc           #33                 // String , len=
     131: invokevirtual #31                 // Method java/lang/StringBuilder.append:(Ljava/lang/String;)Ljava/lang/StringBuilder;
     134: iload_2
     135: invokevirtual #32                 // Method java/lang/StringBuilder.append:(I)Ljava/lang/StringBuilder;
     138: ldc           #34                 // String , text.length=
     140: invokevirtual #31                 // Method java/lang/StringBuilder.append:(Ljava/lang/String;)Ljava/lang/StringBuilder;
     143: iload         5
     145: invokevirtual #32                 // Method java/lang/StringBuilder.append:(I)Ljava/lang/StringBuilder;
     148: invokevirtual #35                 // Method java/lang/StringBuilder.toString:()Ljava/lang/String;
     151: invokespecial #6                  // Method java/lang/IllegalArgumentException."<init>":(Ljava/lang/String;)V
     154: athrow
     155: aload_0
     156: iload_1
     157: iload_2
     158: aload_3
     159: getstatic     #12                 // Field org/unbescape/uri/UriEscapeUtil$UriEscapeType.QUERY_PARAM:Lorg/unbescape/uri/UriEscapeUtil$UriEscapeType;
     162: aload         4
     164: invokestatic  #36                 // Method org/unbescape/uri/UriEscapeUtil.escape:([CIILjava/io/Writer;Lorg/unbescape/uri/UriEscapeUtil$UriEscapeType;Ljava/lang/String;)V
     167: return

  public static void escapeUriFragmentId(char[], int, int, java.io.Writer) throws java.io.IOException;
    Code:
       0: aload_0
       1: iload_1
       2: iload_2
       3: aload_3
       4: ldc           #2                  // String UTF-8
       6: invokestatic  #39                 // Method escapeUriFragmentId:([CIILjava/io/Writer;Ljava/lang/String;)V
       9: return

  public static void escapeUriFragmentId(char[], int, int, java.io.Writer, java.lang.String) throws java.io.IOException;
    Code:
       0: aload_3
       1: ifnonnull     14
       4: new           #4                  // class java/lang/IllegalArgumentException
       7: dup
       8: ldc           #16                 // String Argument \'writer\' cannot be null
      10: invokespecial #6                  // Method java/lang/IllegalArgumentException."<init>":(Ljava/lang/String;)V
      13: athrow
      14: aload         4
      16: ifnonnull     29
      19: new           #4                  // class java/lang/IllegalArgumentException
      22: dup
      23: ldc           #5                  // String Argument \'encoding\' cannot be null
      25: invokespecial #6                  // Method java/lang/IllegalArgumentException."<init>":(Ljava/lang/String;)V
      28: athrow
      29: aload_0
      30: ifnonnull     37
      33: iconst_0
      34: goto          39
      37: aload_0
      38: arraylength
      39: istore        5
      41: iload_1
      42: iflt          51
      45: iload_1
      46: iload         5
      48: if_icmple     97
      51: new           #4                  // class java/lang/IllegalArgumentException
      54: dup
      55: new           #28                 // class java/lang/StringBuilder
      58: dup
      59: invokespecial #29                 // Method java/lang/StringBuilder."<init>":()V
      62: ldc           #30                 // String Invalid (offset, len). offset=
      64: invokevirtual #31                 // Method java/lang/StringBuilder.append:(Ljava/lang/String;)Ljava/lang/StringBuilder;
      67: iload_1
      68: invokevirtual #32                 // Method java/lang/StringBuilder.append:(I)Ljava/lang/StringBuilder;
      71: ldc           #33                 // String , len=
      73: invokevirtual #31                 // Method java/lang/StringBuilder.append:(Ljava/lang/String;)Ljava/lang/StringBuilder;
      76: iload_2
      77: invokevirtual #32                 // Method java/lang/StringBuilder.append:(I)Ljava/lang/StringBuilder;
      80: ldc           #34                 // String , text.length=
      82: invokevirtual #31                 // Method java/lang/StringBuilder.append:(Ljava/lang/String;)Ljava/lang/StringBuilder;
      85: iload         5
      87: invokevirtual #32                 // Method java/lang/StringBuilder.append:(I)Ljava/lang/StringBuilder;
      90: invokevirtual #35                 // Method java/lang/StringBuilder.toString:()Ljava/lang/String;
      93: invokespecial #6                  // Method java/lang/IllegalArgumentException."<init>":(Ljava/lang/String;)V
      96: athrow
      97: iload_2
      98: iflt          109
     101: iload_1
     102: iload_2
     103: iadd
     104: iload         5
     106: if_icmple     155
     109: new           #4                  // class java/lang/IllegalArgumentException
     112: dup
     113: new           #28                 // class java/lang/StringBuilder
     116: dup
     117: invokespecial #29                 // Method java/lang/StringBuilder."<init>":()V
     120: ldc           #30                 // String Invalid (offset, len). offset=
     122: invokevirtual #31                 // Method java/lang/StringBuilder.append:(Ljava/lang/String;)Ljava/lang/StringBuilder;
     125: iload_1
     126: invokevirtual #32                 // Method java/lang/StringBuilder.append:(I)Ljava/lang/StringBuilder;
     129: ldc           #33                 // String , len=
     131: invokevirtual #31                 // Method java/lang/StringBuilder.append:(Ljava/lang/String;)Ljava/lang/StringBuilder;
     134: iload_2
     135: invokevirtual #32                 // Method java/lang/StringBuilder.append:(I)Ljava/lang/StringBuilder;
     138: ldc           #34                 // String , text.length=
     140: invokevirtual #31                 // Method java/lang/StringBuilder.append:(Ljava/lang/String;)Ljava/lang/StringBuilder;
     143: iload         5
     145: invokevirtual #32                 // Method java/lang/StringBuilder.append:(I)Ljava/lang/StringBuilder;
     148: invokevirtual #35                 // Method java/lang/StringBuilder.toString:()Ljava/lang/String;
     151: invokespecial #6                  // Method java/lang/IllegalArgumentException."<init>":(Ljava/lang/String;)V
     154: athrow
     155: aload_0
     156: iload_1
     157: iload_2
     158: aload_3
     159: getstatic     #14                 // Field org/unbescape/uri/UriEscapeUtil$UriEscapeType.FRAGMENT_ID:Lorg/unbescape/uri/UriEscapeUtil$UriEscapeType;
     162: aload         4
     164: invokestatic  #36                 // Method org/unbescape/uri/UriEscapeUtil.escape:([CIILjava/io/Writer;Lorg/unbescape/uri/UriEscapeUtil$UriEscapeType;Ljava/lang/String;)V
     167: return

  public static java.lang.String unescapeUriPath(java.lang.String);
    Code:
       0: aload_0
       1: ldc           #2                  // String UTF-8
       3: invokestatic  #40                 // Method unescapeUriPath:(Ljava/lang/String;Ljava/lang/String;)Ljava/lang/String;
       6: areturn

  public static java.lang.String unescapeUriPath(java.lang.String, java.lang.String);
    Code:
       0: aload_1
       1: ifnonnull     14
       4: new           #4                  // class java/lang/IllegalArgumentException
       7: dup
       8: ldc           #5                  // String Argument \'encoding\' cannot be null
      10: invokespecial #6                  // Method java/lang/IllegalArgumentException."<init>":(Ljava/lang/String;)V
      13: athrow
      14: aload_0
      15: getstatic     #7                  // Field org/unbescape/uri/UriEscapeUtil$UriEscapeType.PATH:Lorg/unbescape/uri/UriEscapeUtil$UriEscapeType;
      18: aload_1
      19: invokestatic  #41                 // Method org/unbescape/uri/UriEscapeUtil.unescape:(Ljava/lang/String;Lorg/unbescape/uri/UriEscapeUtil$UriEscapeType;Ljava/lang/String;)Ljava/lang/String;
      22: areturn

  public static java.lang.String unescapeUriPathSegment(java.lang.String);
    Code:
       0: aload_0
       1: ldc           #2                  // String UTF-8
       3: invokestatic  #42                 // Method unescapeUriPathSegment:(Ljava/lang/String;Ljava/lang/String;)Ljava/lang/String;
       6: areturn

  public static java.lang.String unescapeUriPathSegment(java.lang.String, java.lang.String);
    Code:
       0: aload_1
       1: ifnonnull     14
       4: new           #4                  // class java/lang/IllegalArgumentException
       7: dup
       8: ldc           #5                  // String Argument \'encoding\' cannot be null
      10: invokespecial #6                  // Method java/lang/IllegalArgumentException."<init>":(Ljava/lang/String;)V
      13: athrow
      14: aload_0
      15: getstatic     #10                 // Field org/unbescape/uri/UriEscapeUtil$UriEscapeType.PATH_SEGMENT:Lorg/unbescape/uri/UriEscapeUtil$UriEscapeType;
      18: aload_1
      19: invokestatic  #41                 // Method org/unbescape/uri/UriEscapeUtil.unescape:(Ljava/lang/String;Lorg/unbescape/uri/UriEscapeUtil$UriEscapeType;Ljava/lang/String;)Ljava/lang/String;
      22: areturn

  public static java.lang.String unescapeUriQueryParam(java.lang.String);
    Code:
       0: aload_0
       1: ldc           #2                  // String UTF-8
       3: invokestatic  #43                 // Method unescapeUriQueryParam:(Ljava/lang/String;Ljava/lang/String;)Ljava/lang/String;
       6: areturn

  public static java.lang.String unescapeUriQueryParam(java.lang.String, java.lang.String);
    Code:
       0: aload_1
       1: ifnonnull     14
       4: new           #4                  // class java/lang/IllegalArgumentException
       7: dup
       8: ldc           #5                  // String Argument \'encoding\' cannot be null
      10: invokespecial #6                  // Method java/lang/IllegalArgumentException."<init>":(Ljava/lang/String;)V
      13: athrow
      14: aload_0
      15: getstatic     #12                 // Field org/unbescape/uri/UriEscapeUtil$UriEscapeType.QUERY_PARAM:Lorg/unbescape/uri/UriEscapeUtil$UriEscapeType;
      18: aload_1
      19: invokestatic  #41                 // Method org/unbescape/uri/UriEscapeUtil.unescape:(Ljava/lang/String;Lorg/unbescape/uri/UriEscapeUtil$UriEscapeType;Ljava/lang/String;)Ljava/lang/String;
      22: areturn

  public static java.lang.String unescapeUriFragmentId(java.lang.String);
    Code:
       0: aload_0
       1: ldc           #2                  // String UTF-8
       3: invokestatic  #44                 // Method unescapeUriFragmentId:(Ljava/lang/String;Ljava/lang/String;)Ljava/lang/String;
       6: areturn

  public static java.lang.String unescapeUriFragmentId(java.lang.String, java.lang.String);
    Code:
       0: aload_1
       1: ifnonnull     14
       4: new           #4                  // class java/lang/IllegalArgumentException
       7: dup
       8: ldc           #5                  // String Argument \'encoding\' cannot be null
      10: invokespecial #6                  // Method java/lang/IllegalArgumentException."<init>":(Ljava/lang/String;)V
      13: athrow
      14: aload_0
      15: getstatic     #14                 // Field org/unbescape/uri/UriEscapeUtil$UriEscapeType.FRAGMENT_ID:Lorg/unbescape/uri/UriEscapeUtil$UriEscapeType;
      18: aload_1
      19: invokestatic  #41                 // Method org/unbescape/uri/UriEscapeUtil.unescape:(Ljava/lang/String;Lorg/unbescape/uri/UriEscapeUtil$UriEscapeType;Ljava/lang/String;)Ljava/lang/String;
      22: areturn

  public static void unescapeUriPath(java.lang.String, java.io.Writer) throws java.io.IOException;
    Code:
       0: aload_0
       1: aload_1
       2: ldc           #2                  // String UTF-8
       4: invokestatic  #45                 // Method unescapeUriPath:(Ljava/lang/String;Ljava/io/Writer;Ljava/lang/String;)V
       7: return

  public static void unescapeUriPath(java.lang.String, java.io.Writer, java.lang.String) throws java.io.IOException;
    Code:
       0: aload_1
       1: ifnonnull     14
       4: new           #4                  // class java/lang/IllegalArgumentException
       7: dup
       8: ldc           #16                 // String Argument \'writer\' cannot be null
      10: invokespecial #6                  // Method java/lang/IllegalArgumentException."<init>":(Ljava/lang/String;)V
      13: athrow
      14: aload_2
      15: ifnonnull     28
      18: new           #4                  // class java/lang/IllegalArgumentException
      21: dup
      22: ldc           #5                  // String Argument \'encoding\' cannot be null
      24: invokespecial #6                  // Method java/lang/IllegalArgumentException."<init>":(Ljava/lang/String;)V
      27: athrow
      28: new           #17                 // class org/unbescape/uri/UriEscape$InternalStringReader
      31: dup
      32: aload_0
      33: invokespecial #18                 // Method org/unbescape/uri/UriEscape$InternalStringReader."<init>":(Ljava/lang/String;)V
      36: aload_1
      37: getstatic     #7                  // Field org/unbescape/uri/UriEscapeUtil$UriEscapeType.PATH:Lorg/unbescape/uri/UriEscapeUtil$UriEscapeType;
      40: aload_2
      41: invokestatic  #46                 // Method org/unbescape/uri/UriEscapeUtil.unescape:(Ljava/io/Reader;Ljava/io/Writer;Lorg/unbescape/uri/UriEscapeUtil$UriEscapeType;Ljava/lang/String;)V
      44: return

  public static void unescapeUriPathSegment(java.lang.String, java.io.Writer) throws java.io.IOException;
    Code:
       0: aload_0
       1: aload_1
       2: ldc           #2                  // String UTF-8
       4: invokestatic  #47                 // Method unescapeUriPathSegment:(Ljava/lang/String;Ljava/io/Writer;Ljava/lang/String;)V
       7: return

  public static void unescapeUriPathSegment(java.lang.String, java.io.Writer, java.lang.String) throws java.io.IOException;
    Code:
       0: aload_1
       1: ifnonnull     14
       4: new           #4                  // class java/lang/IllegalArgumentException
       7: dup
       8: ldc           #16                 // String Argument \'writer\' cannot be null
      10: invokespecial #6                  // Method java/lang/IllegalArgumentException."<init>":(Ljava/lang/String;)V
      13: athrow
      14: aload_2
      15: ifnonnull     28
      18: new           #4                  // class java/lang/IllegalArgumentException
      21: dup
      22: ldc           #5                  // String Argument \'encoding\' cannot be null
      24: invokespecial #6                  // Method java/lang/IllegalArgumentException."<init>":(Ljava/lang/String;)V
      27: athrow
      28: new           #17                 // class org/unbescape/uri/UriEscape$InternalStringReader
      31: dup
      32: aload_0
      33: invokespecial #18                 // Method org/unbescape/uri/UriEscape$InternalStringReader."<init>":(Ljava/lang/String;)V
      36: aload_1
      37: getstatic     #10                 // Field org/unbescape/uri/UriEscapeUtil$UriEscapeType.PATH_SEGMENT:Lorg/unbescape/uri/UriEscapeUtil$UriEscapeType;
      40: aload_2
      41: invokestatic  #46                 // Method org/unbescape/uri/UriEscapeUtil.unescape:(Ljava/io/Reader;Ljava/io/Writer;Lorg/unbescape/uri/UriEscapeUtil$UriEscapeType;Ljava/lang/String;)V
      44: return

  public static void unescapeUriQueryParam(java.lang.String, java.io.Writer) throws java.io.IOException;
    Code:
       0: aload_0
       1: aload_1
       2: ldc           #2                  // String UTF-8
       4: invokestatic  #48                 // Method unescapeUriQueryParam:(Ljava/lang/String;Ljava/io/Writer;Ljava/lang/String;)V
       7: return

  public static void unescapeUriQueryParam(java.lang.String, java.io.Writer, java.lang.String) throws java.io.IOException;
    Code:
       0: aload_1
       1: ifnonnull     14
       4: new           #4                  // class java/lang/IllegalArgumentException
       7: dup
       8: ldc           #16                 // String Argument \'writer\' cannot be null
      10: invokespecial #6                  // Method java/lang/IllegalArgumentException."<init>":(Ljava/lang/String;)V
      13: athrow
      14: aload_2
      15: ifnonnull     28
      18: new           #4                  // class java/lang/IllegalArgumentException
      21: dup
      22: ldc           #5                  // String Argument \'encoding\' cannot be null
      24: invokespecial #6                  // Method java/lang/IllegalArgumentException."<init>":(Ljava/lang/String;)V
      27: athrow
      28: new           #17                 // class org/unbescape/uri/UriEscape$InternalStringReader
      31: dup
      32: aload_0
      33: invokespecial #18                 // Method org/unbescape/uri/UriEscape$InternalStringReader."<init>":(Ljava/lang/String;)V
      36: aload_1
      37: getstatic     #12                 // Field org/unbescape/uri/UriEscapeUtil$UriEscapeType.QUERY_PARAM:Lorg/unbescape/uri/UriEscapeUtil$UriEscapeType;
      40: aload_2
      41: invokestatic  #46                 // Method org/unbescape/uri/UriEscapeUtil.unescape:(Ljava/io/Reader;Ljava/io/Writer;Lorg/unbescape/uri/UriEscapeUtil$UriEscapeType;Ljava/lang/String;)V
      44: return

  public static void unescapeUriFragmentId(java.lang.String, java.io.Writer) throws java.io.IOException;
    Code:
       0: aload_0
       1: aload_1
       2: ldc           #2                  // String UTF-8
       4: invokestatic  #49                 // Method unescapeUriFragmentId:(Ljava/lang/String;Ljava/io/Writer;Ljava/lang/String;)V
       7: return

  public static void unescapeUriFragmentId(java.lang.String, java.io.Writer, java.lang.String) throws java.io.IOException;
    Code:
       0: aload_1
       1: ifnonnull     14
       4: new           #4                  // class java/lang/IllegalArgumentException
       7: dup
       8: ldc           #16                 // String Argument \'writer\' cannot be null
      10: invokespecial #6                  // Method java/lang/IllegalArgumentException."<init>":(Ljava/lang/String;)V
      13: athrow
      14: aload_2
      15: ifnonnull     28
      18: new           #4                  // class java/lang/IllegalArgumentException
      21: dup
      22: ldc           #5                  // String Argument \'encoding\' cannot be null
      24: invokespecial #6                  // Method java/lang/IllegalArgumentException."<init>":(Ljava/lang/String;)V
      27: athrow
      28: new           #17                 // class org/unbescape/uri/UriEscape$InternalStringReader
      31: dup
      32: aload_0
      33: invokespecial #18                 // Method org/unbescape/uri/UriEscape$InternalStringReader."<init>":(Ljava/lang/String;)V
      36: aload_1
      37: getstatic     #14                 // Field org/unbescape/uri/UriEscapeUtil$UriEscapeType.FRAGMENT_ID:Lorg/unbescape/uri/UriEscapeUtil$UriEscapeType;
      40: aload_2
      41: invokestatic  #46                 // Method org/unbescape/uri/UriEscapeUtil.unescape:(Ljava/io/Reader;Ljava/io/Writer;Lorg/unbescape/uri/UriEscapeUtil$UriEscapeType;Ljava/lang/String;)V
      44: return

  public static void unescapeUriPath(java.io.Reader, java.io.Writer) throws java.io.IOException;
    Code:
       0: aload_0
       1: aload_1
       2: ldc           #2                  // String UTF-8
       4: invokestatic  #50                 // Method unescapeUriPath:(Ljava/io/Reader;Ljava/io/Writer;Ljava/lang/String;)V
       7: return

  public static void unescapeUriPath(java.io.Reader, java.io.Writer, java.lang.String) throws java.io.IOException;
    Code:
       0: aload_1
       1: ifnonnull     14
       4: new           #4                  // class java/lang/IllegalArgumentException
       7: dup
       8: ldc           #16                 // String Argument \'writer\' cannot be null
      10: invokespecial #6                  // Method java/lang/IllegalArgumentException."<init>":(Ljava/lang/String;)V
      13: athrow
      14: aload_2
      15: ifnonnull     28
      18: new           #4                  // class java/lang/IllegalArgumentException
      21: dup
      22: ldc           #5                  // String Argument \'encoding\' cannot be null
      24: invokespecial #6                  // Method java/lang/IllegalArgumentException."<init>":(Ljava/lang/String;)V
      27: athrow
      28: aload_0
      29: aload_1
      30: getstatic     #7                  // Field org/unbescape/uri/UriEscapeUtil$UriEscapeType.PATH:Lorg/unbescape/uri/UriEscapeUtil$UriEscapeType;
      33: aload_2
      34: invokestatic  #46                 // Method org/unbescape/uri/UriEscapeUtil.unescape:(Ljava/io/Reader;Ljava/io/Writer;Lorg/unbescape/uri/UriEscapeUtil$UriEscapeType;Ljava/lang/String;)V
      37: return

  public static void unescapeUriPathSegment(java.io.Reader, java.io.Writer) throws java.io.IOException;
    Code:
       0: aload_0
       1: aload_1
       2: ldc           #2                  // String UTF-8
       4: invokestatic  #51                 // Method unescapeUriPathSegment:(Ljava/io/Reader;Ljava/io/Writer;Ljava/lang/String;)V
       7: return

  public static void unescapeUriPathSegment(java.io.Reader, java.io.Writer, java.lang.String) throws java.io.IOException;
    Code:
       0: aload_1
       1: ifnonnull     14
       4: new           #4                  // class java/lang/IllegalArgumentException
       7: dup
       8: ldc           #16                 // String Argument \'writer\' cannot be null
      10: invokespecial #6                  // Method java/lang/IllegalArgumentException."<init>":(Ljava/lang/String;)V
      13: athrow
      14: aload_2
      15: ifnonnull     28
      18: new           #4                  // class java/lang/IllegalArgumentException
      21: dup
      22: ldc           #5                  // String Argument \'encoding\' cannot be null
      24: invokespecial #6                  // Method java/lang/IllegalArgumentException."<init>":(Ljava/lang/String;)V
      27: athrow
      28: aload_0
      29: aload_1
      30: getstatic     #10                 // Field org/unbescape/uri/UriEscapeUtil$UriEscapeType.PATH_SEGMENT:Lorg/unbescape/uri/UriEscapeUtil$UriEscapeType;
      33: aload_2
      34: invokestatic  #46                 // Method org/unbescape/uri/UriEscapeUtil.unescape:(Ljava/io/Reader;Ljava/io/Writer;Lorg/unbescape/uri/UriEscapeUtil$UriEscapeType;Ljava/lang/String;)V
      37: return

  public static void unescapeUriQueryParam(java.io.Reader, java.io.Writer) throws java.io.IOException;
    Code:
       0: aload_0
       1: aload_1
       2: ldc           #2                  // String UTF-8
       4: invokestatic  #52                 // Method unescapeUriQueryParam:(Ljava/io/Reader;Ljava/io/Writer;Ljava/lang/String;)V
       7: return

  public static void unescapeUriQueryParam(java.io.Reader, java.io.Writer, java.lang.String) throws java.io.IOException;
    Code:
       0: aload_1
       1: ifnonnull     14
       4: new           #4                  // class java/lang/IllegalArgumentException
       7: dup
       8: ldc           #16                 // String Argument \'writer\' cannot be null
      10: invokespecial #6                  // Method java/lang/IllegalArgumentException."<init>":(Ljava/lang/String;)V
      13: athrow
      14: aload_2
      15: ifnonnull     28
      18: new           #4                  // class java/lang/IllegalArgumentException
      21: dup
      22: ldc           #5                  // String Argument \'encoding\' cannot be null
      24: invokespecial #6                  // Method java/lang/IllegalArgumentException."<init>":(Ljava/lang/String;)V
      27: athrow
      28: aload_0
      29: aload_1
      30: getstatic     #12                 // Field org/unbescape/uri/UriEscapeUtil$UriEscapeType.QUERY_PARAM:Lorg/unbescape/uri/UriEscapeUtil$UriEscapeType;
      33: aload_2
      34: invokestatic  #46                 // Method org/unbescape/uri/UriEscapeUtil.unescape:(Ljava/io/Reader;Ljava/io/Writer;Lorg/unbescape/uri/UriEscapeUtil$UriEscapeType;Ljava/lang/String;)V
      37: return

  public static void unescapeUriFragmentId(java.io.Reader, java.io.Writer) throws java.io.IOException;
    Code:
       0: aload_0
       1: aload_1
       2: ldc           #2                  // String UTF-8
       4: invokestatic  #53                 // Method unescapeUriFragmentId:(Ljava/io/Reader;Ljava/io/Writer;Ljava/lang/String;)V
       7: return

  public static void unescapeUriFragmentId(java.io.Reader, java.io.Writer, java.lang.String) throws java.io.IOException;
    Code:
       0: aload_1
       1: ifnonnull     14
       4: new           #4                  // class java/lang/IllegalArgumentException
       7: dup
       8: ldc           #16                 // String Argument \'writer\' cannot be null
      10: invokespecial #6                  // Method java/lang/IllegalArgumentException."<init>":(Ljava/lang/String;)V
      13: athrow
      14: aload_2
      15: ifnonnull     28
      18: new           #4                  // class java/lang/IllegalArgumentException
      21: dup
      22: ldc           #5                  // String Argument \'encoding\' cannot be null
      24: invokespecial #6                  // Method java/lang/IllegalArgumentException."<init>":(Ljava/lang/String;)V
      27: athrow
      28: aload_0
      29: aload_1
      30: getstatic     #14                 // Field org/unbescape/uri/UriEscapeUtil$UriEscapeType.FRAGMENT_ID:Lorg/unbescape/uri/UriEscapeUtil$UriEscapeType;
      33: aload_2
      34: invokestatic  #46                 // Method org/unbescape/uri/UriEscapeUtil.unescape:(Ljava/io/Reader;Ljava/io/Writer;Lorg/unbescape/uri/UriEscapeUtil$UriEscapeType;Ljava/lang/String;)V
      37: return

  public static void unescapeUriPath(char[], int, int, java.io.Writer) throws java.io.IOException;
    Code:
       0: aload_0
       1: iload_1
       2: iload_2
       3: aload_3
       4: ldc           #2                  // String UTF-8
       6: invokestatic  #54                 // Method unescapeUriPath:([CIILjava/io/Writer;Ljava/lang/String;)V
       9: return

  public static void unescapeUriPath(char[], int, int, java.io.Writer, java.lang.String) throws java.io.IOException;
    Code:
       0: aload_3
       1: ifnonnull     14
       4: new           #4                  // class java/lang/IllegalArgumentException
       7: dup
       8: ldc           #16                 // String Argument \'writer\' cannot be null
      10: invokespecial #6                  // Method java/lang/IllegalArgumentException."<init>":(Ljava/lang/String;)V
      13: athrow
      14: aload         4
      16: ifnonnull     29
      19: new           #4                  // class java/lang/IllegalArgumentException
      22: dup
      23: ldc           #5                  // String Argument \'encoding\' cannot be null
      25: invokespecial #6                  // Method java/lang/IllegalArgumentException."<init>":(Ljava/lang/String;)V
      28: athrow
      29: aload_0
      30: ifnonnull     37
      33: iconst_0
      34: goto          39
      37: aload_0
      38: arraylength
      39: istore        5
      41: iload_1
      42: iflt          51
      45: iload_1
      46: iload         5
      48: if_icmple     97
      51: new           #4                  // class java/lang/IllegalArgumentException
      54: dup
      55: new           #28                 // class java/lang/StringBuilder
      58: dup
      59: invokespecial #29                 // Method java/lang/StringBuilder."<init>":()V
      62: ldc           #30                 // String Invalid (offset, len). offset=
      64: invokevirtual #31                 // Method java/lang/StringBuilder.append:(Ljava/lang/String;)Ljava/lang/StringBuilder;
      67: iload_1
      68: invokevirtual #32                 // Method java/lang/StringBuilder.append:(I)Ljava/lang/StringBuilder;
      71: ldc           #33                 // String , len=
      73: invokevirtual #31                 // Method java/lang/StringBuilder.append:(Ljava/lang/String;)Ljava/lang/StringBuilder;
      76: iload_2
      77: invokevirtual #32                 // Method java/lang/StringBuilder.append:(I)Ljava/lang/StringBuilder;
      80: ldc           #34                 // String , text.length=
      82: invokevirtual #31                 // Method java/lang/StringBuilder.append:(Ljava/lang/String;)Ljava/lang/StringBuilder;
      85: iload         5
      87: invokevirtual #32                 // Method java/lang/StringBuilder.append:(I)Ljava/lang/StringBuilder;
      90: invokevirtual #35                 // Method java/lang/StringBuilder.toString:()Ljava/lang/String;
      93: invokespecial #6                  // Method java/lang/IllegalArgumentException."<init>":(Ljava/lang/String;)V
      96: athrow
      97: iload_2
      98: iflt          109
     101: iload_1
     102: iload_2
     103: iadd
     104: iload         5
     106: if_icmple     155
     109: new           #4                  // class java/lang/IllegalArgumentException
     112: dup
     113: new           #28                 // class java/lang/StringBuilder
     116: dup
     117: invokespecial #29                 // Method java/lang/StringBuilder."<init>":()V
     120: ldc           #30                 // String Invalid (offset, len). offset=
     122: invokevirtual #31                 // Method java/lang/StringBuilder.append:(Ljava/lang/String;)Ljava/lang/StringBuilder;
     125: iload_1
     126: invokevirtual #32                 // Method java/lang/StringBuilder.append:(I)Ljava/lang/StringBuilder;
     129: ldc           #33                 // String , len=
     131: invokevirtual #31                 // Method java/lang/StringBuilder.append:(Ljava/lang/String;)Ljava/lang/StringBuilder;
     134: iload_2
     135: invokevirtual #32                 // Method java/lang/StringBuilder.append:(I)Ljava/lang/StringBuilder;
     138: ldc           #34                 // String , text.length=
     140: invokevirtual #31                 // Method java/lang/StringBuilder.append:(Ljava/lang/String;)Ljava/lang/StringBuilder;
     143: iload         5
     145: invokevirtual #32                 // Method java/lang/StringBuilder.append:(I)Ljava/lang/StringBuilder;
     148: invokevirtual #35                 // Method java/lang/StringBuilder.toString:()Ljava/lang/String;
     151: invokespecial #6                  // Method java/lang/IllegalArgumentException."<init>":(Ljava/lang/String;)V
     154: athrow
     155: aload_0
     156: iload_1
     157: iload_2
     158: aload_3
     159: getstatic     #7                  // Field org/unbescape/uri/UriEscapeUtil$UriEscapeType.PATH:Lorg/unbescape/uri/UriEscapeUtil$UriEscapeType;
     162: aload         4
     164: invokestatic  #55                 // Method org/unbescape/uri/UriEscapeUtil.unescape:([CIILjava/io/Writer;Lorg/unbescape/uri/UriEscapeUtil$UriEscapeType;Ljava/lang/String;)V
     167: return

  public static void unescapeUriPathSegment(char[], int, int, java.io.Writer) throws java.io.IOException;
    Code:
       0: aload_0
       1: iload_1
       2: iload_2
       3: aload_3
       4: ldc           #2                  // String UTF-8
       6: invokestatic  #56                 // Method unescapeUriPathSegment:([CIILjava/io/Writer;Ljava/lang/String;)V
       9: return

  public static void unescapeUriPathSegment(char[], int, int, java.io.Writer, java.lang.String) throws java.io.IOException;
    Code:
       0: aload_3
       1: ifnonnull     14
       4: new           #4                  // class java/lang/IllegalArgumentException
       7: dup
       8: ldc           #16                 // String Argument \'writer\' cannot be null
      10: invokespecial #6                  // Method java/lang/IllegalArgumentException."<init>":(Ljava/lang/String;)V
      13: athrow
      14: aload         4
      16: ifnonnull     29
      19: new           #4                  // class java/lang/IllegalArgumentException
      22: dup
      23: ldc           #5                  // String Argument \'encoding\' cannot be null
      25: invokespecial #6                  // Method java/lang/IllegalArgumentException."<init>":(Ljava/lang/String;)V
      28: athrow
      29: aload_0
      30: ifnonnull     37
      33: iconst_0
      34: goto          39
      37: aload_0
      38: arraylength
      39: istore        5
      41: iload_1
      42: iflt          51
      45: iload_1
      46: iload         5
      48: if_icmple     97
      51: new           #4                  // class java/lang/IllegalArgumentException
      54: dup
      55: new           #28                 // class java/lang/StringBuilder
      58: dup
      59: invokespecial #29                 // Method java/lang/StringBuilder."<init>":()V
      62: ldc           #30                 // String Invalid (offset, len). offset=
      64: invokevirtual #31                 // Method java/lang/StringBuilder.append:(Ljava/lang/String;)Ljava/lang/StringBuilder;
      67: iload_1
      68: invokevirtual #32                 // Method java/lang/StringBuilder.append:(I)Ljava/lang/StringBuilder;
      71: ldc           #33                 // String , len=
      73: invokevirtual #31                 // Method java/lang/StringBuilder.append:(Ljava/lang/String;)Ljava/lang/StringBuilder;
      76: iload_2
      77: invokevirtual #32                 // Method java/lang/StringBuilder.append:(I)Ljava/lang/StringBuilder;
      80: ldc           #34                 // String , text.length=
      82: invokevirtual #31                 // Method java/lang/StringBuilder.append:(Ljava/lang/String;)Ljava/lang/StringBuilder;
      85: iload         5
      87: invokevirtual #32                 // Method java/lang/StringBuilder.append:(I)Ljava/lang/StringBuilder;
      90: invokevirtual #35                 // Method java/lang/StringBuilder.toString:()Ljava/lang/String;
      93: invokespecial #6                  // Method java/lang/IllegalArgumentException."<init>":(Ljava/lang/String;)V
      96: athrow
      97: iload_2
      98: iflt          109
     101: iload_1
     102: iload_2
     103: iadd
     104: iload         5
     106: if_icmple     155
     109: new           #4                  // class java/lang/IllegalArgumentException
     112: dup
     113: new           #28                 // class java/lang/StringBuilder
     116: dup
     117: invokespecial #29                 // Method java/lang/StringBuilder."<init>":()V
     120: ldc           #30                 // String Invalid (offset, len). offset=
     122: invokevirtual #31                 // Method java/lang/StringBuilder.append:(Ljava/lang/String;)Ljava/lang/StringBuilder;
     125: iload_1
     126: invokevirtual #32                 // Method java/lang/StringBuilder.append:(I)Ljava/lang/StringBuilder;
     129: ldc           #33                 // String , len=
     131: invokevirtual #31                 // Method java/lang/StringBuilder.append:(Ljava/lang/String;)Ljava/lang/StringBuilder;
     134: iload_2
     135: invokevirtual #32                 // Method java/lang/StringBuilder.append:(I)Ljava/lang/StringBuilder;
     138: ldc           #34                 // String , text.length=
     140: invokevirtual #31                 // Method java/lang/StringBuilder.append:(Ljava/lang/String;)Ljava/lang/StringBuilder;
     143: iload         5
     145: invokevirtual #32                 // Method java/lang/StringBuilder.append:(I)Ljava/lang/StringBuilder;
     148: invokevirtual #35                 // Method java/lang/StringBuilder.toString:()Ljava/lang/String;
     151: invokespecial #6                  // Method java/lang/IllegalArgumentException."<init>":(Ljava/lang/String;)V
     154: athrow
     155: aload_0
     156: iload_1
     157: iload_2
     158: aload_3
     159: getstatic     #10                 // Field org/unbescape/uri/UriEscapeUtil$UriEscapeType.PATH_SEGMENT:Lorg/unbescape/uri/UriEscapeUtil$UriEscapeType;
     162: aload         4
     164: invokestatic  #55                 // Method org/unbescape/uri/UriEscapeUtil.unescape:([CIILjava/io/Writer;Lorg/unbescape/uri/UriEscapeUtil$UriEscapeType;Ljava/lang/String;)V
     167: return

  public static void unescapeUriQueryParam(char[], int, int, java.io.Writer) throws java.io.IOException;
    Code:
       0: aload_0
       1: iload_1
       2: iload_2
       3: aload_3
       4: ldc           #2                  // String UTF-8
       6: invokestatic  #57                 // Method unescapeUriQueryParam:([CIILjava/io/Writer;Ljava/lang/String;)V
       9: return

  public static void unescapeUriQueryParam(char[], int, int, java.io.Writer, java.lang.String) throws java.io.IOException;
    Code:
       0: aload_3
       1: ifnonnull     14
       4: new           #4                  // class java/lang/IllegalArgumentException
       7: dup
       8: ldc           #16                 // String Argument \'writer\' cannot be null
      10: invokespecial #6                  // Method java/lang/IllegalArgumentException."<init>":(Ljava/lang/String;)V
      13: athrow
      14: aload         4
      16: ifnonnull     29
      19: new           #4                  // class java/lang/IllegalArgumentException
      22: dup
      23: ldc           #5                  // String Argument \'encoding\' cannot be null
      25: invokespecial #6                  // Method java/lang/IllegalArgumentException."<init>":(Ljava/lang/String;)V
      28: athrow
      29: aload_0
      30: ifnonnull     37
      33: iconst_0
      34: goto          39
      37: aload_0
      38: arraylength
      39: istore        5
      41: iload_1
      42: iflt          51
      45: iload_1
      46: iload         5
      48: if_icmple     97
      51: new           #4                  // class java/lang/IllegalArgumentException
      54: dup
      55: new           #28                 // class java/lang/StringBuilder
      58: dup
      59: invokespecial #29                 // Method java/lang/StringBuilder."<init>":()V
      62: ldc           #30                 // String Invalid (offset, len). offset=
      64: invokevirtual #31                 // Method java/lang/StringBuilder.append:(Ljava/lang/String;)Ljava/lang/StringBuilder;
      67: iload_1
      68: invokevirtual #32                 // Method java/lang/StringBuilder.append:(I)Ljava/lang/StringBuilder;
      71: ldc           #33                 // String , len=
      73: invokevirtual #31                 // Method java/lang/StringBuilder.append:(Ljava/lang/String;)Ljava/lang/StringBuilder;
      76: iload_2
      77: invokevirtual #32                 // Method java/lang/StringBuilder.append:(I)Ljava/lang/StringBuilder;
      80: ldc           #34                 // String , text.length=
      82: invokevirtual #31                 // Method java/lang/StringBuilder.append:(Ljava/lang/String;)Ljava/lang/StringBuilder;
      85: iload         5
      87: invokevirtual #32                 // Method java/lang/StringBuilder.append:(I)Ljava/lang/StringBuilder;
      90: invokevirtual #35                 // Method java/lang/StringBuilder.toString:()Ljava/lang/String;
      93: invokespecial #6                  // Method java/lang/IllegalArgumentException."<init>":(Ljava/lang/String;)V
      96: athrow
      97: iload_2
      98: iflt          109
     101: iload_1
     102: iload_2
     103: iadd
     104: iload         5
     106: if_icmple     155
     109: new           #4                  // class java/lang/IllegalArgumentException
     112: dup
     113: new           #28                 // class java/lang/StringBuilder
     116: dup
     117: invokespecial #29                 // Method java/lang/StringBuilder."<init>":()V
     120: ldc           #30                 // String Invalid (offset, len). offset=
     122: invokevirtual #31                 // Method java/lang/StringBuilder.append:(Ljava/lang/String;)Ljava/lang/StringBuilder;
     125: iload_1
     126: invokevirtual #32                 // Method java/lang/StringBuilder.append:(I)Ljava/lang/StringBuilder;
     129: ldc           #33                 // String , len=
     131: invokevirtual #31                 // Method java/lang/StringBuilder.append:(Ljava/lang/String;)Ljava/lang/StringBuilder;
     134: iload_2
     135: invokevirtual #32                 // Method java/lang/StringBuilder.append:(I)Ljava/lang/StringBuilder;
     138: ldc           #34                 // String , text.length=
     140: invokevirtual #31                 // Method java/lang/StringBuilder.append:(Ljava/lang/String;)Ljava/lang/StringBuilder;
     143: iload         5
     145: invokevirtual #32                 // Method java/lang/StringBuilder.append:(I)Ljava/lang/StringBuilder;
     148: invokevirtual #35                 // Method java/lang/StringBuilder.toString:()Ljava/lang/String;
     151: invokespecial #6                  // Method java/lang/IllegalArgumentException."<init>":(Ljava/lang/String;)V
     154: athrow
     155: aload_0
     156: iload_1
     157: iload_2
     158: aload_3
     159: getstatic     #12                 // Field org/unbescape/uri/UriEscapeUtil$UriEscapeType.QUERY_PARAM:Lorg/unbescape/uri/UriEscapeUtil$UriEscapeType;
     162: aload         4
     164: invokestatic  #55                 // Method org/unbescape/uri/UriEscapeUtil.unescape:([CIILjava/io/Writer;Lorg/unbescape/uri/UriEscapeUtil$UriEscapeType;Ljava/lang/String;)V
     167: return

  public static void unescapeUriFragmentId(char[], int, int, java.io.Writer) throws java.io.IOException;
    Code:
       0: aload_0
       1: iload_1
       2: iload_2
       3: aload_3
       4: ldc           #2                  // String UTF-8
       6: invokestatic  #58                 // Method unescapeUriFragmentId:([CIILjava/io/Writer;Ljava/lang/String;)V
       9: return

  public static void unescapeUriFragmentId(char[], int, int, java.io.Writer, java.lang.String) throws java.io.IOException;
    Code:
       0: aload_3
       1: ifnonnull     14
       4: new           #4                  // class java/lang/IllegalArgumentException
       7: dup
       8: ldc           #16                 // String Argument \'writer\' cannot be null
      10: invokespecial #6                  // Method java/lang/IllegalArgumentException."<init>":(Ljava/lang/String;)V
      13: athrow
      14: aload         4
      16: ifnonnull     29
      19: new           #4                  // class java/lang/IllegalArgumentException
      22: dup
      23: ldc           #5                  // String Argument \'encoding\' cannot be null
      25: invokespecial #6                  // Method java/lang/IllegalArgumentException."<init>":(Ljava/lang/String;)V
      28: athrow
      29: aload_0
      30: ifnonnull     37
      33: iconst_0
      34: goto          39
      37: aload_0
      38: arraylength
      39: istore        5
      41: iload_1
      42: iflt          51
      45: iload_1
      46: iload         5
      48: if_icmple     97
      51: new           #4                  // class java/lang/IllegalArgumentException
      54: dup
      55: new           #28                 // class java/lang/StringBuilder
      58: dup
      59: invokespecial #29                 // Method java/lang/StringBuilder."<init>":()V
      62: ldc           #30                 // String Invalid (offset, len). offset=
      64: invokevirtual #31                 // Method java/lang/StringBuilder.append:(Ljava/lang/String;)Ljava/lang/StringBuilder;
      67: iload_1
      68: invokevirtual #32                 // Method java/lang/StringBuilder.append:(I)Ljava/lang/StringBuilder;
      71: ldc           #33                 // String , len=
      73: invokevirtual #31                 // Method java/lang/StringBuilder.append:(Ljava/lang/String;)Ljava/lang/StringBuilder;
      76: iload_2
      77: invokevirtual #32                 // Method java/lang/StringBuilder.append:(I)Ljava/lang/StringBuilder;
      80: ldc           #34                 // String , text.length=
      82: invokevirtual #31                 // Method java/lang/StringBuilder.append:(Ljava/lang/String;)Ljava/lang/StringBuilder;
      85: iload         5
      87: invokevirtual #32                 // Method java/lang/StringBuilder.append:(I)Ljava/lang/StringBuilder;
      90: invokevirtual #35                 // Method java/lang/StringBuilder.toString:()Ljava/lang/String;
      93: invokespecial #6                  // Method java/lang/IllegalArgumentException."<init>":(Ljava/lang/String;)V
      96: athrow
      97: iload_2
      98: iflt          109
     101: iload_1
     102: iload_2
     103: iadd
     104: iload         5
     106: if_icmple     155
     109: new           #4                  // class java/lang/IllegalArgumentException
     112: dup
     113: new           #28                 // class java/lang/StringBuilder
     116: dup
     117: invokespecial #29                 // Method java/lang/StringBuilder."<init>":()V
     120: ldc           #30                 // String Invalid (offset, len). offset=
     122: invokevirtual #31                 // Method java/lang/StringBuilder.append:(Ljava/lang/String;)Ljava/lang/StringBuilder;
     125: iload_1
     126: invokevirtual #32                 // Method java/lang/StringBuilder.append:(I)Ljava/lang/StringBuilder;
     129: ldc           #33                 // String , len=
     131: invokevirtual #31                 // Method java/lang/StringBuilder.append:(Ljava/lang/String;)Ljava/lang/StringBuilder;
     134: iload_2
     135: invokevirtual #32                 // Method java/lang/StringBuilder.append:(I)Ljava/lang/StringBuilder;
     138: ldc           #34                 // String , text.length=
     140: invokevirtual #31                 // Method java/lang/StringBuilder.append:(Ljava/lang/String;)Ljava/lang/StringBuilder;
     143: iload         5
     145: invokevirtual #32                 // Method java/lang/StringBuilder.append:(I)Ljava/lang/StringBuilder;
     148: invokevirtual #35                 // Method java/lang/StringBuilder.toString:()Ljava/lang/String;
     151: invokespecial #6                  // Method java/lang/IllegalArgumentException."<init>":(Ljava/lang/String;)V
     154: athrow
     155: aload_0
     156: iload_1
     157: iload_2
     158: aload_3
     159: getstatic     #14                 // Field org/unbescape/uri/UriEscapeUtil$UriEscapeType.FRAGMENT_ID:Lorg/unbescape/uri/UriEscapeUtil$UriEscapeType;
     162: aload         4
     164: invokestatic  #55                 // Method org/unbescape/uri/UriEscapeUtil.unescape:([CIILjava/io/Writer;Lorg/unbescape/uri/UriEscapeUtil$UriEscapeType;Ljava/lang/String;)V
     167: return

  private org.unbescape.uri.UriEscape();
    Code:
       0: aload_0
       1: invokespecial #59                 // Method java/lang/Object."<init>":()V
       4: return
}
