Compiled from "Bindings.java"
public final class javafx.beans.binding.Bindings {
  static final boolean $assertionsDisabled;

  private javafx.beans.binding.Bindings();
    Code:
       0: aload_0
       1: invokespecial #2                  // Method java/lang/Object."<init>":()V
       4: return

  public static javafx.beans.binding.BooleanBinding createBooleanBinding(java.util.concurrent.Callable<java.lang.Boolean>, javafx.beans.Observable...);
    Code:
       0: new           #3                  // class javafx/beans/binding/Bindings$1
       3: dup
       4: aload_1
       5: aload_0
       6: invokespecial #4                  // Method javafx/beans/binding/Bindings$1."<init>":([Ljavafx/beans/Observable;Ljava/util/concurrent/Callable;)V
       9: areturn

  public static javafx.beans.binding.DoubleBinding createDoubleBinding(java.util.concurrent.Callable<java.lang.Double>, javafx.beans.Observable...);
    Code:
       0: new           #5                  // class javafx/beans/binding/Bindings$2
       3: dup
       4: aload_1
       5: aload_0
       6: invokespecial #6                  // Method javafx/beans/binding/Bindings$2."<init>":([Ljavafx/beans/Observable;Ljava/util/concurrent/Callable;)V
       9: areturn

  public static javafx.beans.binding.FloatBinding createFloatBinding(java.util.concurrent.Callable<java.lang.Float>, javafx.beans.Observable...);
    Code:
       0: new           #7                  // class javafx/beans/binding/Bindings$3
       3: dup
       4: aload_1
       5: aload_0
       6: invokespecial #8                  // Method javafx/beans/binding/Bindings$3."<init>":([Ljavafx/beans/Observable;Ljava/util/concurrent/Callable;)V
       9: areturn

  public static javafx.beans.binding.IntegerBinding createIntegerBinding(java.util.concurrent.Callable<java.lang.Integer>, javafx.beans.Observable...);
    Code:
       0: new           #9                  // class javafx/beans/binding/Bindings$4
       3: dup
       4: aload_1
       5: aload_0
       6: invokespecial #10                 // Method javafx/beans/binding/Bindings$4."<init>":([Ljavafx/beans/Observable;Ljava/util/concurrent/Callable;)V
       9: areturn

  public static javafx.beans.binding.LongBinding createLongBinding(java.util.concurrent.Callable<java.lang.Long>, javafx.beans.Observable...);
    Code:
       0: new           #11                 // class javafx/beans/binding/Bindings$5
       3: dup
       4: aload_1
       5: aload_0
       6: invokespecial #12                 // Method javafx/beans/binding/Bindings$5."<init>":([Ljavafx/beans/Observable;Ljava/util/concurrent/Callable;)V
       9: areturn

  public static <T> javafx.beans.binding.ObjectBinding<T> createObjectBinding(java.util.concurrent.Callable<T>, javafx.beans.Observable...);
    Code:
       0: new           #13                 // class javafx/beans/binding/Bindings$6
       3: dup
       4: aload_1
       5: aload_0
       6: invokespecial #14                 // Method javafx/beans/binding/Bindings$6."<init>":([Ljavafx/beans/Observable;Ljava/util/concurrent/Callable;)V
       9: areturn

  public static javafx.beans.binding.StringBinding createStringBinding(java.util.concurrent.Callable<java.lang.String>, javafx.beans.Observable...);
    Code:
       0: new           #15                 // class javafx/beans/binding/Bindings$7
       3: dup
       4: aload_1
       5: aload_0
       6: invokespecial #16                 // Method javafx/beans/binding/Bindings$7."<init>":([Ljavafx/beans/Observable;Ljava/util/concurrent/Callable;)V
       9: areturn

  public static <T> javafx.beans.binding.ObjectBinding<T> select(javafx.beans.value.ObservableValue<?>, java.lang.String...);
    Code:
       0: new           #17                 // class com/sun/javafx/binding/SelectBinding$AsObject
       3: dup
       4: aload_0
       5: aload_1
       6: invokespecial #18                 // Method com/sun/javafx/binding/SelectBinding$AsObject."<init>":(Ljavafx/beans/value/ObservableValue;[Ljava/lang/String;)V
       9: areturn

  public static javafx.beans.binding.DoubleBinding selectDouble(javafx.beans.value.ObservableValue<?>, java.lang.String...);
    Code:
       0: new           #19                 // class com/sun/javafx/binding/SelectBinding$AsDouble
       3: dup
       4: aload_0
       5: aload_1
       6: invokespecial #20                 // Method com/sun/javafx/binding/SelectBinding$AsDouble."<init>":(Ljavafx/beans/value/ObservableValue;[Ljava/lang/String;)V
       9: areturn

  public static javafx.beans.binding.FloatBinding selectFloat(javafx.beans.value.ObservableValue<?>, java.lang.String...);
    Code:
       0: new           #21                 // class com/sun/javafx/binding/SelectBinding$AsFloat
       3: dup
       4: aload_0
       5: aload_1
       6: invokespecial #22                 // Method com/sun/javafx/binding/SelectBinding$AsFloat."<init>":(Ljavafx/beans/value/ObservableValue;[Ljava/lang/String;)V
       9: areturn

  public static javafx.beans.binding.IntegerBinding selectInteger(javafx.beans.value.ObservableValue<?>, java.lang.String...);
    Code:
       0: new           #23                 // class com/sun/javafx/binding/SelectBinding$AsInteger
       3: dup
       4: aload_0
       5: aload_1
       6: invokespecial #24                 // Method com/sun/javafx/binding/SelectBinding$AsInteger."<init>":(Ljavafx/beans/value/ObservableValue;[Ljava/lang/String;)V
       9: areturn

  public static javafx.beans.binding.LongBinding selectLong(javafx.beans.value.ObservableValue<?>, java.lang.String...);
    Code:
       0: new           #25                 // class com/sun/javafx/binding/SelectBinding$AsLong
       3: dup
       4: aload_0
       5: aload_1
       6: invokespecial #26                 // Method com/sun/javafx/binding/SelectBinding$AsLong."<init>":(Ljavafx/beans/value/ObservableValue;[Ljava/lang/String;)V
       9: areturn

  public static javafx.beans.binding.BooleanBinding selectBoolean(javafx.beans.value.ObservableValue<?>, java.lang.String...);
    Code:
       0: new           #27                 // class com/sun/javafx/binding/SelectBinding$AsBoolean
       3: dup
       4: aload_0
       5: aload_1
       6: invokespecial #28                 // Method com/sun/javafx/binding/SelectBinding$AsBoolean."<init>":(Ljavafx/beans/value/ObservableValue;[Ljava/lang/String;)V
       9: areturn

  public static javafx.beans.binding.StringBinding selectString(javafx.beans.value.ObservableValue<?>, java.lang.String...);
    Code:
       0: new           #29                 // class com/sun/javafx/binding/SelectBinding$AsString
       3: dup
       4: aload_0
       5: aload_1
       6: invokespecial #30                 // Method com/sun/javafx/binding/SelectBinding$AsString."<init>":(Ljavafx/beans/value/ObservableValue;[Ljava/lang/String;)V
       9: areturn

  public static <T> javafx.beans.binding.ObjectBinding<T> select(java.lang.Object, java.lang.String...);
    Code:
       0: new           #17                 // class com/sun/javafx/binding/SelectBinding$AsObject
       3: dup
       4: aload_0
       5: aload_1
       6: invokespecial #31                 // Method com/sun/javafx/binding/SelectBinding$AsObject."<init>":(Ljava/lang/Object;[Ljava/lang/String;)V
       9: areturn

  public static javafx.beans.binding.DoubleBinding selectDouble(java.lang.Object, java.lang.String...);
    Code:
       0: new           #19                 // class com/sun/javafx/binding/SelectBinding$AsDouble
       3: dup
       4: aload_0
       5: aload_1
       6: invokespecial #32                 // Method com/sun/javafx/binding/SelectBinding$AsDouble."<init>":(Ljava/lang/Object;[Ljava/lang/String;)V
       9: areturn

  public static javafx.beans.binding.FloatBinding selectFloat(java.lang.Object, java.lang.String...);
    Code:
       0: new           #21                 // class com/sun/javafx/binding/SelectBinding$AsFloat
       3: dup
       4: aload_0
       5: aload_1
       6: invokespecial #33                 // Method com/sun/javafx/binding/SelectBinding$AsFloat."<init>":(Ljava/lang/Object;[Ljava/lang/String;)V
       9: areturn

  public static javafx.beans.binding.IntegerBinding selectInteger(java.lang.Object, java.lang.String...);
    Code:
       0: new           #23                 // class com/sun/javafx/binding/SelectBinding$AsInteger
       3: dup
       4: aload_0
       5: aload_1
       6: invokespecial #34                 // Method com/sun/javafx/binding/SelectBinding$AsInteger."<init>":(Ljava/lang/Object;[Ljava/lang/String;)V
       9: areturn

  public static javafx.beans.binding.LongBinding selectLong(java.lang.Object, java.lang.String...);
    Code:
       0: new           #25                 // class com/sun/javafx/binding/SelectBinding$AsLong
       3: dup
       4: aload_0
       5: aload_1
       6: invokespecial #35                 // Method com/sun/javafx/binding/SelectBinding$AsLong."<init>":(Ljava/lang/Object;[Ljava/lang/String;)V
       9: areturn

  public static javafx.beans.binding.BooleanBinding selectBoolean(java.lang.Object, java.lang.String...);
    Code:
       0: new           #27                 // class com/sun/javafx/binding/SelectBinding$AsBoolean
       3: dup
       4: aload_0
       5: aload_1
       6: invokespecial #36                 // Method com/sun/javafx/binding/SelectBinding$AsBoolean."<init>":(Ljava/lang/Object;[Ljava/lang/String;)V
       9: areturn

  public static javafx.beans.binding.StringBinding selectString(java.lang.Object, java.lang.String...);
    Code:
       0: new           #29                 // class com/sun/javafx/binding/SelectBinding$AsString
       3: dup
       4: aload_0
       5: aload_1
       6: invokespecial #37                 // Method com/sun/javafx/binding/SelectBinding$AsString."<init>":(Ljava/lang/Object;[Ljava/lang/String;)V
       9: areturn

  public static javafx.beans.binding.When when(javafx.beans.value.ObservableBooleanValue);
    Code:
       0: new           #38                 // class javafx/beans/binding/When
       3: dup
       4: aload_0
       5: invokespecial #39                 // Method javafx/beans/binding/When."<init>":(Ljavafx/beans/value/ObservableBooleanValue;)V
       8: areturn

  public static <T> void bindBidirectional(javafx.beans.property.Property<T>, javafx.beans.property.Property<T>);
    Code:
       0: aload_0
       1: aload_1
       2: invokestatic  #40                 // Method com/sun/javafx/binding/BidirectionalBinding.bind:(Ljavafx/beans/property/Property;Ljavafx/beans/property/Property;)Lcom/sun/javafx/binding/BidirectionalBinding;
       5: pop
       6: return

  public static <T> void unbindBidirectional(javafx.beans.property.Property<T>, javafx.beans.property.Property<T>);
    Code:
       0: aload_0
       1: aload_1
       2: invokestatic  #41                 // Method com/sun/javafx/binding/BidirectionalBinding.unbind:(Ljavafx/beans/property/Property;Ljavafx/beans/property/Property;)V
       5: return

  public static void unbindBidirectional(java.lang.Object, java.lang.Object);
    Code:
       0: aload_0
       1: aload_1
       2: invokestatic  #42                 // Method com/sun/javafx/binding/BidirectionalBinding.unbind:(Ljava/lang/Object;Ljava/lang/Object;)V
       5: return

  public static void bindBidirectional(javafx.beans.property.Property<java.lang.String>, javafx.beans.property.Property<?>, java.text.Format);
    Code:
       0: aload_0
       1: aload_1
       2: aload_2
       3: invokestatic  #43                 // Method com/sun/javafx/binding/BidirectionalBinding.bind:(Ljavafx/beans/property/Property;Ljavafx/beans/property/Property;Ljava/text/Format;)Ljava/lang/Object;
       6: pop
       7: return

  public static <T> void bindBidirectional(javafx.beans.property.Property<java.lang.String>, javafx.beans.property.Property<T>, javafx.util.StringConverter<T>);
    Code:
       0: aload_0
       1: aload_1
       2: aload_2
       3: invokestatic  #44                 // Method com/sun/javafx/binding/BidirectionalBinding.bind:(Ljavafx/beans/property/Property;Ljavafx/beans/property/Property;Ljavafx/util/StringConverter;)Ljava/lang/Object;
       6: pop
       7: return

  public static <E> void bindContentBidirectional(javafx.collections.ObservableList<E>, javafx.collections.ObservableList<E>);
    Code:
       0: aload_0
       1: aload_1
       2: invokestatic  #45                 // Method com/sun/javafx/binding/BidirectionalContentBinding.bind:(Ljavafx/collections/ObservableList;Ljavafx/collections/ObservableList;)Ljava/lang/Object;
       5: pop
       6: return

  public static <E> void bindContentBidirectional(javafx.collections.ObservableSet<E>, javafx.collections.ObservableSet<E>);
    Code:
       0: aload_0
       1: aload_1
       2: invokestatic  #46                 // Method com/sun/javafx/binding/BidirectionalContentBinding.bind:(Ljavafx/collections/ObservableSet;Ljavafx/collections/ObservableSet;)Ljava/lang/Object;
       5: pop
       6: return

  public static <K, V> void bindContentBidirectional(javafx.collections.ObservableMap<K, V>, javafx.collections.ObservableMap<K, V>);
    Code:
       0: aload_0
       1: aload_1
       2: invokestatic  #47                 // Method com/sun/javafx/binding/BidirectionalContentBinding.bind:(Ljavafx/collections/ObservableMap;Ljavafx/collections/ObservableMap;)Ljava/lang/Object;
       5: pop
       6: return

  public static void unbindContentBidirectional(java.lang.Object, java.lang.Object);
    Code:
       0: aload_0
       1: aload_1
       2: invokestatic  #48                 // Method com/sun/javafx/binding/BidirectionalContentBinding.unbind:(Ljava/lang/Object;Ljava/lang/Object;)V
       5: return

  public static <E> void bindContent(java.util.List<E>, javafx.collections.ObservableList<? extends E>);
    Code:
       0: aload_0
       1: aload_1
       2: invokestatic  #49                 // Method com/sun/javafx/binding/ContentBinding.bind:(Ljava/util/List;Ljavafx/collections/ObservableList;)Ljava/lang/Object;
       5: pop
       6: return

  public static <E> void bindContent(java.util.Set<E>, javafx.collections.ObservableSet<? extends E>);
    Code:
       0: aload_0
       1: aload_1
       2: invokestatic  #50                 // Method com/sun/javafx/binding/ContentBinding.bind:(Ljava/util/Set;Ljavafx/collections/ObservableSet;)Ljava/lang/Object;
       5: pop
       6: return

  public static <K, V> void bindContent(java.util.Map<K, V>, javafx.collections.ObservableMap<? extends K, ? extends V>);
    Code:
       0: aload_0
       1: aload_1
       2: invokestatic  #51                 // Method com/sun/javafx/binding/ContentBinding.bind:(Ljava/util/Map;Ljavafx/collections/ObservableMap;)Ljava/lang/Object;
       5: pop
       6: return

  public static void unbindContent(java.lang.Object, java.lang.Object);
    Code:
       0: aload_0
       1: aload_1
       2: invokestatic  #52                 // Method com/sun/javafx/binding/ContentBinding.unbind:(Ljava/lang/Object;Ljava/lang/Object;)V
       5: return

  public static javafx.beans.binding.NumberBinding negate(javafx.beans.value.ObservableNumberValue);
    Code:
       0: aload_0
       1: ifnonnull     14
       4: new           #53                 // class java/lang/NullPointerException
       7: dup
       8: ldc           #54                 // String Operand cannot be null.
      10: invokespecial #55                 // Method java/lang/NullPointerException."<init>":(Ljava/lang/String;)V
      13: athrow
      14: aload_0
      15: instanceof    #56                 // class javafx/beans/value/ObservableDoubleValue
      18: ifeq          30
      21: new           #57                 // class javafx/beans/binding/Bindings$8
      24: dup
      25: aload_0
      26: invokespecial #58                 // Method javafx/beans/binding/Bindings$8."<init>":(Ljavafx/beans/value/ObservableNumberValue;)V
      29: areturn
      30: aload_0
      31: instanceof    #59                 // class javafx/beans/value/ObservableFloatValue
      34: ifeq          46
      37: new           #60                 // class javafx/beans/binding/Bindings$9
      40: dup
      41: aload_0
      42: invokespecial #61                 // Method javafx/beans/binding/Bindings$9."<init>":(Ljavafx/beans/value/ObservableNumberValue;)V
      45: areturn
      46: aload_0
      47: instanceof    #62                 // class javafx/beans/value/ObservableLongValue
      50: ifeq          62
      53: new           #63                 // class javafx/beans/binding/Bindings$10
      56: dup
      57: aload_0
      58: invokespecial #64                 // Method javafx/beans/binding/Bindings$10."<init>":(Ljavafx/beans/value/ObservableNumberValue;)V
      61: areturn
      62: new           #65                 // class javafx/beans/binding/Bindings$11
      65: dup
      66: aload_0
      67: invokespecial #66                 // Method javafx/beans/binding/Bindings$11."<init>":(Ljavafx/beans/value/ObservableNumberValue;)V
      70: areturn

  private static javafx.beans.binding.NumberBinding add(javafx.beans.value.ObservableNumberValue, javafx.beans.value.ObservableNumberValue, javafx.beans.Observable...);
    Code:
       0: aload_0
       1: ifnull        8
       4: aload_1
       5: ifnonnull     18
       8: new           #53                 // class java/lang/NullPointerException
      11: dup
      12: ldc           #67                 // String Operands cannot be null.
      14: invokespecial #55                 // Method java/lang/NullPointerException."<init>":(Ljava/lang/String;)V
      17: athrow
      18: getstatic     #68                 // Field $assertionsDisabled:Z
      21: ifne          41
      24: aload_2
      25: ifnull        33
      28: aload_2
      29: arraylength
      30: ifgt          41
      33: new           #69                 // class java/lang/AssertionError
      36: dup
      37: invokespecial #70                 // Method java/lang/AssertionError."<init>":()V
      40: athrow
      41: aload_0
      42: instanceof    #56                 // class javafx/beans/value/ObservableDoubleValue
      45: ifne          55
      48: aload_1
      49: instanceof    #56                 // class javafx/beans/value/ObservableDoubleValue
      52: ifeq          66
      55: new           #71                 // class javafx/beans/binding/Bindings$12
      58: dup
      59: aload_2
      60: aload_0
      61: aload_1
      62: invokespecial #72                 // Method javafx/beans/binding/Bindings$12."<init>":([Ljavafx/beans/Observable;Ljavafx/beans/value/ObservableNumberValue;Ljavafx/beans/value/ObservableNumberValue;)V
      65: areturn
      66: aload_0
      67: instanceof    #59                 // class javafx/beans/value/ObservableFloatValue
      70: ifne          80
      73: aload_1
      74: instanceof    #59                 // class javafx/beans/value/ObservableFloatValue
      77: ifeq          91
      80: new           #73                 // class javafx/beans/binding/Bindings$13
      83: dup
      84: aload_2
      85: aload_0
      86: aload_1
      87: invokespecial #74                 // Method javafx/beans/binding/Bindings$13."<init>":([Ljavafx/beans/Observable;Ljavafx/beans/value/ObservableNumberValue;Ljavafx/beans/value/ObservableNumberValue;)V
      90: areturn
      91: aload_0
      92: instanceof    #62                 // class javafx/beans/value/ObservableLongValue
      95: ifne          105
      98: aload_1
      99: instanceof    #62                 // class javafx/beans/value/ObservableLongValue
     102: ifeq          116
     105: new           #75                 // class javafx/beans/binding/Bindings$14
     108: dup
     109: aload_2
     110: aload_0
     111: aload_1
     112: invokespecial #76                 // Method javafx/beans/binding/Bindings$14."<init>":([Ljavafx/beans/Observable;Ljavafx/beans/value/ObservableNumberValue;Ljavafx/beans/value/ObservableNumberValue;)V
     115: areturn
     116: new           #77                 // class javafx/beans/binding/Bindings$15
     119: dup
     120: aload_2
     121: aload_0
     122: aload_1
     123: invokespecial #78                 // Method javafx/beans/binding/Bindings$15."<init>":([Ljavafx/beans/Observable;Ljavafx/beans/value/ObservableNumberValue;Ljavafx/beans/value/ObservableNumberValue;)V
     126: areturn

  public static javafx.beans.binding.NumberBinding add(javafx.beans.value.ObservableNumberValue, javafx.beans.value.ObservableNumberValue);
    Code:
       0: aload_0
       1: aload_1
       2: iconst_2
       3: anewarray     #79                 // class javafx/beans/Observable
       6: dup
       7: iconst_0
       8: aload_0
       9: aastore
      10: dup
      11: iconst_1
      12: aload_1
      13: aastore
      14: invokestatic  #80                 // Method add:(Ljavafx/beans/value/ObservableNumberValue;Ljavafx/beans/value/ObservableNumberValue;[Ljavafx/beans/Observable;)Ljavafx/beans/binding/NumberBinding;
      17: areturn

  public static javafx.beans.binding.DoubleBinding add(javafx.beans.value.ObservableNumberValue, double);
    Code:
       0: aload_0
       1: dload_1
       2: invokestatic  #81                 // Method com/sun/javafx/binding/DoubleConstant.valueOf:(D)Lcom/sun/javafx/binding/DoubleConstant;
       5: iconst_1
       6: anewarray     #79                 // class javafx/beans/Observable
       9: dup
      10: iconst_0
      11: aload_0
      12: aastore
      13: invokestatic  #80                 // Method add:(Ljavafx/beans/value/ObservableNumberValue;Ljavafx/beans/value/ObservableNumberValue;[Ljavafx/beans/Observable;)Ljavafx/beans/binding/NumberBinding;
      16: checkcast     #82                 // class javafx/beans/binding/DoubleBinding
      19: areturn

  public static javafx.beans.binding.DoubleBinding add(double, javafx.beans.value.ObservableNumberValue);
    Code:
       0: dload_0
       1: invokestatic  #81                 // Method com/sun/javafx/binding/DoubleConstant.valueOf:(D)Lcom/sun/javafx/binding/DoubleConstant;
       4: aload_2
       5: iconst_1
       6: anewarray     #79                 // class javafx/beans/Observable
       9: dup
      10: iconst_0
      11: aload_2
      12: aastore
      13: invokestatic  #80                 // Method add:(Ljavafx/beans/value/ObservableNumberValue;Ljavafx/beans/value/ObservableNumberValue;[Ljavafx/beans/Observable;)Ljavafx/beans/binding/NumberBinding;
      16: checkcast     #82                 // class javafx/beans/binding/DoubleBinding
      19: areturn

  public static javafx.beans.binding.NumberBinding add(javafx.beans.value.ObservableNumberValue, float);
    Code:
       0: aload_0
       1: fload_1
       2: invokestatic  #83                 // Method com/sun/javafx/binding/FloatConstant.valueOf:(F)Lcom/sun/javafx/binding/FloatConstant;
       5: iconst_1
       6: anewarray     #79                 // class javafx/beans/Observable
       9: dup
      10: iconst_0
      11: aload_0
      12: aastore
      13: invokestatic  #80                 // Method add:(Ljavafx/beans/value/ObservableNumberValue;Ljavafx/beans/value/ObservableNumberValue;[Ljavafx/beans/Observable;)Ljavafx/beans/binding/NumberBinding;
      16: areturn

  public static javafx.beans.binding.NumberBinding add(float, javafx.beans.value.ObservableNumberValue);
    Code:
       0: fload_0
       1: invokestatic  #83                 // Method com/sun/javafx/binding/FloatConstant.valueOf:(F)Lcom/sun/javafx/binding/FloatConstant;
       4: aload_1
       5: iconst_1
       6: anewarray     #79                 // class javafx/beans/Observable
       9: dup
      10: iconst_0
      11: aload_1
      12: aastore
      13: invokestatic  #80                 // Method add:(Ljavafx/beans/value/ObservableNumberValue;Ljavafx/beans/value/ObservableNumberValue;[Ljavafx/beans/Observable;)Ljavafx/beans/binding/NumberBinding;
      16: areturn

  public static javafx.beans.binding.NumberBinding add(javafx.beans.value.ObservableNumberValue, long);
    Code:
       0: aload_0
       1: lload_1
       2: invokestatic  #84                 // Method com/sun/javafx/binding/LongConstant.valueOf:(J)Lcom/sun/javafx/binding/LongConstant;
       5: iconst_1
       6: anewarray     #79                 // class javafx/beans/Observable
       9: dup
      10: iconst_0
      11: aload_0
      12: aastore
      13: invokestatic  #80                 // Method add:(Ljavafx/beans/value/ObservableNumberValue;Ljavafx/beans/value/ObservableNumberValue;[Ljavafx/beans/Observable;)Ljavafx/beans/binding/NumberBinding;
      16: areturn

  public static javafx.beans.binding.NumberBinding add(long, javafx.beans.value.ObservableNumberValue);
    Code:
       0: lload_0
       1: invokestatic  #84                 // Method com/sun/javafx/binding/LongConstant.valueOf:(J)Lcom/sun/javafx/binding/LongConstant;
       4: aload_2
       5: iconst_1
       6: anewarray     #79                 // class javafx/beans/Observable
       9: dup
      10: iconst_0
      11: aload_2
      12: aastore
      13: invokestatic  #80                 // Method add:(Ljavafx/beans/value/ObservableNumberValue;Ljavafx/beans/value/ObservableNumberValue;[Ljavafx/beans/Observable;)Ljavafx/beans/binding/NumberBinding;
      16: areturn

  public static javafx.beans.binding.NumberBinding add(javafx.beans.value.ObservableNumberValue, int);
    Code:
       0: aload_0
       1: iload_1
       2: invokestatic  #85                 // Method com/sun/javafx/binding/IntegerConstant.valueOf:(I)Lcom/sun/javafx/binding/IntegerConstant;
       5: iconst_1
       6: anewarray     #79                 // class javafx/beans/Observable
       9: dup
      10: iconst_0
      11: aload_0
      12: aastore
      13: invokestatic  #80                 // Method add:(Ljavafx/beans/value/ObservableNumberValue;Ljavafx/beans/value/ObservableNumberValue;[Ljavafx/beans/Observable;)Ljavafx/beans/binding/NumberBinding;
      16: areturn

  public static javafx.beans.binding.NumberBinding add(int, javafx.beans.value.ObservableNumberValue);
    Code:
       0: iload_0
       1: invokestatic  #85                 // Method com/sun/javafx/binding/IntegerConstant.valueOf:(I)Lcom/sun/javafx/binding/IntegerConstant;
       4: aload_1
       5: iconst_1
       6: anewarray     #79                 // class javafx/beans/Observable
       9: dup
      10: iconst_0
      11: aload_1
      12: aastore
      13: invokestatic  #80                 // Method add:(Ljavafx/beans/value/ObservableNumberValue;Ljavafx/beans/value/ObservableNumberValue;[Ljavafx/beans/Observable;)Ljavafx/beans/binding/NumberBinding;
      16: areturn

  private static javafx.beans.binding.NumberBinding subtract(javafx.beans.value.ObservableNumberValue, javafx.beans.value.ObservableNumberValue, javafx.beans.Observable...);
    Code:
       0: aload_0
       1: ifnull        8
       4: aload_1
       5: ifnonnull     18
       8: new           #53                 // class java/lang/NullPointerException
      11: dup
      12: ldc           #67                 // String Operands cannot be null.
      14: invokespecial #55                 // Method java/lang/NullPointerException."<init>":(Ljava/lang/String;)V
      17: athrow
      18: getstatic     #68                 // Field $assertionsDisabled:Z
      21: ifne          41
      24: aload_2
      25: ifnull        33
      28: aload_2
      29: arraylength
      30: ifgt          41
      33: new           #69                 // class java/lang/AssertionError
      36: dup
      37: invokespecial #70                 // Method java/lang/AssertionError."<init>":()V
      40: athrow
      41: aload_0
      42: instanceof    #56                 // class javafx/beans/value/ObservableDoubleValue
      45: ifne          55
      48: aload_1
      49: instanceof    #56                 // class javafx/beans/value/ObservableDoubleValue
      52: ifeq          66
      55: new           #86                 // class javafx/beans/binding/Bindings$16
      58: dup
      59: aload_2
      60: aload_0
      61: aload_1
      62: invokespecial #87                 // Method javafx/beans/binding/Bindings$16."<init>":([Ljavafx/beans/Observable;Ljavafx/beans/value/ObservableNumberValue;Ljavafx/beans/value/ObservableNumberValue;)V
      65: areturn
      66: aload_0
      67: instanceof    #59                 // class javafx/beans/value/ObservableFloatValue
      70: ifne          80
      73: aload_1
      74: instanceof    #59                 // class javafx/beans/value/ObservableFloatValue
      77: ifeq          91
      80: new           #88                 // class javafx/beans/binding/Bindings$17
      83: dup
      84: aload_2
      85: aload_0
      86: aload_1
      87: invokespecial #89                 // Method javafx/beans/binding/Bindings$17."<init>":([Ljavafx/beans/Observable;Ljavafx/beans/value/ObservableNumberValue;Ljavafx/beans/value/ObservableNumberValue;)V
      90: areturn
      91: aload_0
      92: instanceof    #62                 // class javafx/beans/value/ObservableLongValue
      95: ifne          105
      98: aload_1
      99: instanceof    #62                 // class javafx/beans/value/ObservableLongValue
     102: ifeq          116
     105: new           #90                 // class javafx/beans/binding/Bindings$18
     108: dup
     109: aload_2
     110: aload_0
     111: aload_1
     112: invokespecial #91                 // Method javafx/beans/binding/Bindings$18."<init>":([Ljavafx/beans/Observable;Ljavafx/beans/value/ObservableNumberValue;Ljavafx/beans/value/ObservableNumberValue;)V
     115: areturn
     116: new           #92                 // class javafx/beans/binding/Bindings$19
     119: dup
     120: aload_2
     121: aload_0
     122: aload_1
     123: invokespecial #93                 // Method javafx/beans/binding/Bindings$19."<init>":([Ljavafx/beans/Observable;Ljavafx/beans/value/ObservableNumberValue;Ljavafx/beans/value/ObservableNumberValue;)V
     126: areturn

  public static javafx.beans.binding.NumberBinding subtract(javafx.beans.value.ObservableNumberValue, javafx.beans.value.ObservableNumberValue);
    Code:
       0: aload_0
       1: aload_1
       2: iconst_2
       3: anewarray     #79                 // class javafx/beans/Observable
       6: dup
       7: iconst_0
       8: aload_0
       9: aastore
      10: dup
      11: iconst_1
      12: aload_1
      13: aastore
      14: invokestatic  #94                 // Method subtract:(Ljavafx/beans/value/ObservableNumberValue;Ljavafx/beans/value/ObservableNumberValue;[Ljavafx/beans/Observable;)Ljavafx/beans/binding/NumberBinding;
      17: areturn

  public static javafx.beans.binding.DoubleBinding subtract(javafx.beans.value.ObservableNumberValue, double);
    Code:
       0: aload_0
       1: dload_1
       2: invokestatic  #81                 // Method com/sun/javafx/binding/DoubleConstant.valueOf:(D)Lcom/sun/javafx/binding/DoubleConstant;
       5: iconst_1
       6: anewarray     #79                 // class javafx/beans/Observable
       9: dup
      10: iconst_0
      11: aload_0
      12: aastore
      13: invokestatic  #94                 // Method subtract:(Ljavafx/beans/value/ObservableNumberValue;Ljavafx/beans/value/ObservableNumberValue;[Ljavafx/beans/Observable;)Ljavafx/beans/binding/NumberBinding;
      16: checkcast     #82                 // class javafx/beans/binding/DoubleBinding
      19: areturn

  public static javafx.beans.binding.DoubleBinding subtract(double, javafx.beans.value.ObservableNumberValue);
    Code:
       0: dload_0
       1: invokestatic  #81                 // Method com/sun/javafx/binding/DoubleConstant.valueOf:(D)Lcom/sun/javafx/binding/DoubleConstant;
       4: aload_2
       5: iconst_1
       6: anewarray     #79                 // class javafx/beans/Observable
       9: dup
      10: iconst_0
      11: aload_2
      12: aastore
      13: invokestatic  #94                 // Method subtract:(Ljavafx/beans/value/ObservableNumberValue;Ljavafx/beans/value/ObservableNumberValue;[Ljavafx/beans/Observable;)Ljavafx/beans/binding/NumberBinding;
      16: checkcast     #82                 // class javafx/beans/binding/DoubleBinding
      19: areturn

  public static javafx.beans.binding.NumberBinding subtract(javafx.beans.value.ObservableNumberValue, float);
    Code:
       0: aload_0
       1: fload_1
       2: invokestatic  #83                 // Method com/sun/javafx/binding/FloatConstant.valueOf:(F)Lcom/sun/javafx/binding/FloatConstant;
       5: iconst_1
       6: anewarray     #79                 // class javafx/beans/Observable
       9: dup
      10: iconst_0
      11: aload_0
      12: aastore
      13: invokestatic  #94                 // Method subtract:(Ljavafx/beans/value/ObservableNumberValue;Ljavafx/beans/value/ObservableNumberValue;[Ljavafx/beans/Observable;)Ljavafx/beans/binding/NumberBinding;
      16: areturn

  public static javafx.beans.binding.NumberBinding subtract(float, javafx.beans.value.ObservableNumberValue);
    Code:
       0: fload_0
       1: invokestatic  #83                 // Method com/sun/javafx/binding/FloatConstant.valueOf:(F)Lcom/sun/javafx/binding/FloatConstant;
       4: aload_1
       5: iconst_1
       6: anewarray     #79                 // class javafx/beans/Observable
       9: dup
      10: iconst_0
      11: aload_1
      12: aastore
      13: invokestatic  #94                 // Method subtract:(Ljavafx/beans/value/ObservableNumberValue;Ljavafx/beans/value/ObservableNumberValue;[Ljavafx/beans/Observable;)Ljavafx/beans/binding/NumberBinding;
      16: areturn

  public static javafx.beans.binding.NumberBinding subtract(javafx.beans.value.ObservableNumberValue, long);
    Code:
       0: aload_0
       1: lload_1
       2: invokestatic  #84                 // Method com/sun/javafx/binding/LongConstant.valueOf:(J)Lcom/sun/javafx/binding/LongConstant;
       5: iconst_1
       6: anewarray     #79                 // class javafx/beans/Observable
       9: dup
      10: iconst_0
      11: aload_0
      12: aastore
      13: invokestatic  #94                 // Method subtract:(Ljavafx/beans/value/ObservableNumberValue;Ljavafx/beans/value/ObservableNumberValue;[Ljavafx/beans/Observable;)Ljavafx/beans/binding/NumberBinding;
      16: areturn

  public static javafx.beans.binding.NumberBinding subtract(long, javafx.beans.value.ObservableNumberValue);
    Code:
       0: lload_0
       1: invokestatic  #84                 // Method com/sun/javafx/binding/LongConstant.valueOf:(J)Lcom/sun/javafx/binding/LongConstant;
       4: aload_2
       5: iconst_1
       6: anewarray     #79                 // class javafx/beans/Observable
       9: dup
      10: iconst_0
      11: aload_2
      12: aastore
      13: invokestatic  #94                 // Method subtract:(Ljavafx/beans/value/ObservableNumberValue;Ljavafx/beans/value/ObservableNumberValue;[Ljavafx/beans/Observable;)Ljavafx/beans/binding/NumberBinding;
      16: areturn

  public static javafx.beans.binding.NumberBinding subtract(javafx.beans.value.ObservableNumberValue, int);
    Code:
       0: aload_0
       1: iload_1
       2: invokestatic  #85                 // Method com/sun/javafx/binding/IntegerConstant.valueOf:(I)Lcom/sun/javafx/binding/IntegerConstant;
       5: iconst_1
       6: anewarray     #79                 // class javafx/beans/Observable
       9: dup
      10: iconst_0
      11: aload_0
      12: aastore
      13: invokestatic  #94                 // Method subtract:(Ljavafx/beans/value/ObservableNumberValue;Ljavafx/beans/value/ObservableNumberValue;[Ljavafx/beans/Observable;)Ljavafx/beans/binding/NumberBinding;
      16: areturn

  public static javafx.beans.binding.NumberBinding subtract(int, javafx.beans.value.ObservableNumberValue);
    Code:
       0: iload_0
       1: invokestatic  #85                 // Method com/sun/javafx/binding/IntegerConstant.valueOf:(I)Lcom/sun/javafx/binding/IntegerConstant;
       4: aload_1
       5: iconst_1
       6: anewarray     #79                 // class javafx/beans/Observable
       9: dup
      10: iconst_0
      11: aload_1
      12: aastore
      13: invokestatic  #94                 // Method subtract:(Ljavafx/beans/value/ObservableNumberValue;Ljavafx/beans/value/ObservableNumberValue;[Ljavafx/beans/Observable;)Ljavafx/beans/binding/NumberBinding;
      16: areturn

  private static javafx.beans.binding.NumberBinding multiply(javafx.beans.value.ObservableNumberValue, javafx.beans.value.ObservableNumberValue, javafx.beans.Observable...);
    Code:
       0: aload_0
       1: ifnull        8
       4: aload_1
       5: ifnonnull     18
       8: new           #53                 // class java/lang/NullPointerException
      11: dup
      12: ldc           #67                 // String Operands cannot be null.
      14: invokespecial #55                 // Method java/lang/NullPointerException."<init>":(Ljava/lang/String;)V
      17: athrow
      18: getstatic     #68                 // Field $assertionsDisabled:Z
      21: ifne          41
      24: aload_2
      25: ifnull        33
      28: aload_2
      29: arraylength
      30: ifgt          41
      33: new           #69                 // class java/lang/AssertionError
      36: dup
      37: invokespecial #70                 // Method java/lang/AssertionError."<init>":()V
      40: athrow
      41: aload_0
      42: instanceof    #56                 // class javafx/beans/value/ObservableDoubleValue
      45: ifne          55
      48: aload_1
      49: instanceof    #56                 // class javafx/beans/value/ObservableDoubleValue
      52: ifeq          66
      55: new           #95                 // class javafx/beans/binding/Bindings$20
      58: dup
      59: aload_2
      60: aload_0
      61: aload_1
      62: invokespecial #96                 // Method javafx/beans/binding/Bindings$20."<init>":([Ljavafx/beans/Observable;Ljavafx/beans/value/ObservableNumberValue;Ljavafx/beans/value/ObservableNumberValue;)V
      65: areturn
      66: aload_0
      67: instanceof    #59                 // class javafx/beans/value/ObservableFloatValue
      70: ifne          80
      73: aload_1
      74: instanceof    #59                 // class javafx/beans/value/ObservableFloatValue
      77: ifeq          91
      80: new           #97                 // class javafx/beans/binding/Bindings$21
      83: dup
      84: aload_2
      85: aload_0
      86: aload_1
      87: invokespecial #98                 // Method javafx/beans/binding/Bindings$21."<init>":([Ljavafx/beans/Observable;Ljavafx/beans/value/ObservableNumberValue;Ljavafx/beans/value/ObservableNumberValue;)V
      90: areturn
      91: aload_0
      92: instanceof    #62                 // class javafx/beans/value/ObservableLongValue
      95: ifne          105
      98: aload_1
      99: instanceof    #62                 // class javafx/beans/value/ObservableLongValue
     102: ifeq          116
     105: new           #99                 // class javafx/beans/binding/Bindings$22
     108: dup
     109: aload_2
     110: aload_0
     111: aload_1
     112: invokespecial #100                // Method javafx/beans/binding/Bindings$22."<init>":([Ljavafx/beans/Observable;Ljavafx/beans/value/ObservableNumberValue;Ljavafx/beans/value/ObservableNumberValue;)V
     115: areturn
     116: new           #101                // class javafx/beans/binding/Bindings$23
     119: dup
     120: aload_2
     121: aload_0
     122: aload_1
     123: invokespecial #102                // Method javafx/beans/binding/Bindings$23."<init>":([Ljavafx/beans/Observable;Ljavafx/beans/value/ObservableNumberValue;Ljavafx/beans/value/ObservableNumberValue;)V
     126: areturn

  public static javafx.beans.binding.NumberBinding multiply(javafx.beans.value.ObservableNumberValue, javafx.beans.value.ObservableNumberValue);
    Code:
       0: aload_0
       1: aload_1
       2: iconst_2
       3: anewarray     #79                 // class javafx/beans/Observable
       6: dup
       7: iconst_0
       8: aload_0
       9: aastore
      10: dup
      11: iconst_1
      12: aload_1
      13: aastore
      14: invokestatic  #103                // Method multiply:(Ljavafx/beans/value/ObservableNumberValue;Ljavafx/beans/value/ObservableNumberValue;[Ljavafx/beans/Observable;)Ljavafx/beans/binding/NumberBinding;
      17: areturn

  public static javafx.beans.binding.DoubleBinding multiply(javafx.beans.value.ObservableNumberValue, double);
    Code:
       0: aload_0
       1: dload_1
       2: invokestatic  #81                 // Method com/sun/javafx/binding/DoubleConstant.valueOf:(D)Lcom/sun/javafx/binding/DoubleConstant;
       5: iconst_1
       6: anewarray     #79                 // class javafx/beans/Observable
       9: dup
      10: iconst_0
      11: aload_0
      12: aastore
      13: invokestatic  #103                // Method multiply:(Ljavafx/beans/value/ObservableNumberValue;Ljavafx/beans/value/ObservableNumberValue;[Ljavafx/beans/Observable;)Ljavafx/beans/binding/NumberBinding;
      16: checkcast     #82                 // class javafx/beans/binding/DoubleBinding
      19: areturn

  public static javafx.beans.binding.DoubleBinding multiply(double, javafx.beans.value.ObservableNumberValue);
    Code:
       0: dload_0
       1: invokestatic  #81                 // Method com/sun/javafx/binding/DoubleConstant.valueOf:(D)Lcom/sun/javafx/binding/DoubleConstant;
       4: aload_2
       5: iconst_1
       6: anewarray     #79                 // class javafx/beans/Observable
       9: dup
      10: iconst_0
      11: aload_2
      12: aastore
      13: invokestatic  #103                // Method multiply:(Ljavafx/beans/value/ObservableNumberValue;Ljavafx/beans/value/ObservableNumberValue;[Ljavafx/beans/Observable;)Ljavafx/beans/binding/NumberBinding;
      16: checkcast     #82                 // class javafx/beans/binding/DoubleBinding
      19: areturn

  public static javafx.beans.binding.NumberBinding multiply(javafx.beans.value.ObservableNumberValue, float);
    Code:
       0: aload_0
       1: fload_1
       2: invokestatic  #83                 // Method com/sun/javafx/binding/FloatConstant.valueOf:(F)Lcom/sun/javafx/binding/FloatConstant;
       5: iconst_1
       6: anewarray     #79                 // class javafx/beans/Observable
       9: dup
      10: iconst_0
      11: aload_0
      12: aastore
      13: invokestatic  #103                // Method multiply:(Ljavafx/beans/value/ObservableNumberValue;Ljavafx/beans/value/ObservableNumberValue;[Ljavafx/beans/Observable;)Ljavafx/beans/binding/NumberBinding;
      16: areturn

  public static javafx.beans.binding.NumberBinding multiply(float, javafx.beans.value.ObservableNumberValue);
    Code:
       0: fload_0
       1: invokestatic  #83                 // Method com/sun/javafx/binding/FloatConstant.valueOf:(F)Lcom/sun/javafx/binding/FloatConstant;
       4: aload_1
       5: iconst_1
       6: anewarray     #79                 // class javafx/beans/Observable
       9: dup
      10: iconst_0
      11: aload_1
      12: aastore
      13: invokestatic  #103                // Method multiply:(Ljavafx/beans/value/ObservableNumberValue;Ljavafx/beans/value/ObservableNumberValue;[Ljavafx/beans/Observable;)Ljavafx/beans/binding/NumberBinding;
      16: areturn

  public static javafx.beans.binding.NumberBinding multiply(javafx.beans.value.ObservableNumberValue, long);
    Code:
       0: aload_0
       1: lload_1
       2: invokestatic  #84                 // Method com/sun/javafx/binding/LongConstant.valueOf:(J)Lcom/sun/javafx/binding/LongConstant;
       5: iconst_1
       6: anewarray     #79                 // class javafx/beans/Observable
       9: dup
      10: iconst_0
      11: aload_0
      12: aastore
      13: invokestatic  #103                // Method multiply:(Ljavafx/beans/value/ObservableNumberValue;Ljavafx/beans/value/ObservableNumberValue;[Ljavafx/beans/Observable;)Ljavafx/beans/binding/NumberBinding;
      16: areturn

  public static javafx.beans.binding.NumberBinding multiply(long, javafx.beans.value.ObservableNumberValue);
    Code:
       0: lload_0
       1: invokestatic  #84                 // Method com/sun/javafx/binding/LongConstant.valueOf:(J)Lcom/sun/javafx/binding/LongConstant;
       4: aload_2
       5: iconst_1
       6: anewarray     #79                 // class javafx/beans/Observable
       9: dup
      10: iconst_0
      11: aload_2
      12: aastore
      13: invokestatic  #103                // Method multiply:(Ljavafx/beans/value/ObservableNumberValue;Ljavafx/beans/value/ObservableNumberValue;[Ljavafx/beans/Observable;)Ljavafx/beans/binding/NumberBinding;
      16: areturn

  public static javafx.beans.binding.NumberBinding multiply(javafx.beans.value.ObservableNumberValue, int);
    Code:
       0: aload_0
       1: iload_1
       2: invokestatic  #85                 // Method com/sun/javafx/binding/IntegerConstant.valueOf:(I)Lcom/sun/javafx/binding/IntegerConstant;
       5: iconst_1
       6: anewarray     #79                 // class javafx/beans/Observable
       9: dup
      10: iconst_0
      11: aload_0
      12: aastore
      13: invokestatic  #103                // Method multiply:(Ljavafx/beans/value/ObservableNumberValue;Ljavafx/beans/value/ObservableNumberValue;[Ljavafx/beans/Observable;)Ljavafx/beans/binding/NumberBinding;
      16: areturn

  public static javafx.beans.binding.NumberBinding multiply(int, javafx.beans.value.ObservableNumberValue);
    Code:
       0: iload_0
       1: invokestatic  #85                 // Method com/sun/javafx/binding/IntegerConstant.valueOf:(I)Lcom/sun/javafx/binding/IntegerConstant;
       4: aload_1
       5: iconst_1
       6: anewarray     #79                 // class javafx/beans/Observable
       9: dup
      10: iconst_0
      11: aload_1
      12: aastore
      13: invokestatic  #103                // Method multiply:(Ljavafx/beans/value/ObservableNumberValue;Ljavafx/beans/value/ObservableNumberValue;[Ljavafx/beans/Observable;)Ljavafx/beans/binding/NumberBinding;
      16: areturn

  private static javafx.beans.binding.NumberBinding divide(javafx.beans.value.ObservableNumberValue, javafx.beans.value.ObservableNumberValue, javafx.beans.Observable...);
    Code:
       0: aload_0
       1: ifnull        8
       4: aload_1
       5: ifnonnull     18
       8: new           #53                 // class java/lang/NullPointerException
      11: dup
      12: ldc           #67                 // String Operands cannot be null.
      14: invokespecial #55                 // Method java/lang/NullPointerException."<init>":(Ljava/lang/String;)V
      17: athrow
      18: getstatic     #68                 // Field $assertionsDisabled:Z
      21: ifne          41
      24: aload_2
      25: ifnull        33
      28: aload_2
      29: arraylength
      30: ifgt          41
      33: new           #69                 // class java/lang/AssertionError
      36: dup
      37: invokespecial #70                 // Method java/lang/AssertionError."<init>":()V
      40: athrow
      41: aload_0
      42: instanceof    #56                 // class javafx/beans/value/ObservableDoubleValue
      45: ifne          55
      48: aload_1
      49: instanceof    #56                 // class javafx/beans/value/ObservableDoubleValue
      52: ifeq          66
      55: new           #104                // class javafx/beans/binding/Bindings$24
      58: dup
      59: aload_2
      60: aload_0
      61: aload_1
      62: invokespecial #105                // Method javafx/beans/binding/Bindings$24."<init>":([Ljavafx/beans/Observable;Ljavafx/beans/value/ObservableNumberValue;Ljavafx/beans/value/ObservableNumberValue;)V
      65: areturn
      66: aload_0
      67: instanceof    #59                 // class javafx/beans/value/ObservableFloatValue
      70: ifne          80
      73: aload_1
      74: instanceof    #59                 // class javafx/beans/value/ObservableFloatValue
      77: ifeq          91
      80: new           #106                // class javafx/beans/binding/Bindings$25
      83: dup
      84: aload_2
      85: aload_0
      86: aload_1
      87: invokespecial #107                // Method javafx/beans/binding/Bindings$25."<init>":([Ljavafx/beans/Observable;Ljavafx/beans/value/ObservableNumberValue;Ljavafx/beans/value/ObservableNumberValue;)V
      90: areturn
      91: aload_0
      92: instanceof    #62                 // class javafx/beans/value/ObservableLongValue
      95: ifne          105
      98: aload_1
      99: instanceof    #62                 // class javafx/beans/value/ObservableLongValue
     102: ifeq          116
     105: new           #108                // class javafx/beans/binding/Bindings$26
     108: dup
     109: aload_2
     110: aload_0
     111: aload_1
     112: invokespecial #109                // Method javafx/beans/binding/Bindings$26."<init>":([Ljavafx/beans/Observable;Ljavafx/beans/value/ObservableNumberValue;Ljavafx/beans/value/ObservableNumberValue;)V
     115: areturn
     116: new           #110                // class javafx/beans/binding/Bindings$27
     119: dup
     120: aload_2
     121: aload_0
     122: aload_1
     123: invokespecial #111                // Method javafx/beans/binding/Bindings$27."<init>":([Ljavafx/beans/Observable;Ljavafx/beans/value/ObservableNumberValue;Ljavafx/beans/value/ObservableNumberValue;)V
     126: areturn

  public static javafx.beans.binding.NumberBinding divide(javafx.beans.value.ObservableNumberValue, javafx.beans.value.ObservableNumberValue);
    Code:
       0: aload_0
       1: aload_1
       2: iconst_2
       3: anewarray     #79                 // class javafx/beans/Observable
       6: dup
       7: iconst_0
       8: aload_0
       9: aastore
      10: dup
      11: iconst_1
      12: aload_1
      13: aastore
      14: invokestatic  #112                // Method divide:(Ljavafx/beans/value/ObservableNumberValue;Ljavafx/beans/value/ObservableNumberValue;[Ljavafx/beans/Observable;)Ljavafx/beans/binding/NumberBinding;
      17: areturn

  public static javafx.beans.binding.DoubleBinding divide(javafx.beans.value.ObservableNumberValue, double);
    Code:
       0: aload_0
       1: dload_1
       2: invokestatic  #81                 // Method com/sun/javafx/binding/DoubleConstant.valueOf:(D)Lcom/sun/javafx/binding/DoubleConstant;
       5: iconst_1
       6: anewarray     #79                 // class javafx/beans/Observable
       9: dup
      10: iconst_0
      11: aload_0
      12: aastore
      13: invokestatic  #112                // Method divide:(Ljavafx/beans/value/ObservableNumberValue;Ljavafx/beans/value/ObservableNumberValue;[Ljavafx/beans/Observable;)Ljavafx/beans/binding/NumberBinding;
      16: checkcast     #82                 // class javafx/beans/binding/DoubleBinding
      19: areturn

  public static javafx.beans.binding.DoubleBinding divide(double, javafx.beans.value.ObservableNumberValue);
    Code:
       0: dload_0
       1: invokestatic  #81                 // Method com/sun/javafx/binding/DoubleConstant.valueOf:(D)Lcom/sun/javafx/binding/DoubleConstant;
       4: aload_2
       5: iconst_1
       6: anewarray     #79                 // class javafx/beans/Observable
       9: dup
      10: iconst_0
      11: aload_2
      12: aastore
      13: invokestatic  #112                // Method divide:(Ljavafx/beans/value/ObservableNumberValue;Ljavafx/beans/value/ObservableNumberValue;[Ljavafx/beans/Observable;)Ljavafx/beans/binding/NumberBinding;
      16: checkcast     #82                 // class javafx/beans/binding/DoubleBinding
      19: areturn

  public static javafx.beans.binding.NumberBinding divide(javafx.beans.value.ObservableNumberValue, float);
    Code:
       0: aload_0
       1: fload_1
       2: invokestatic  #83                 // Method com/sun/javafx/binding/FloatConstant.valueOf:(F)Lcom/sun/javafx/binding/FloatConstant;
       5: iconst_1
       6: anewarray     #79                 // class javafx/beans/Observable
       9: dup
      10: iconst_0
      11: aload_0
      12: aastore
      13: invokestatic  #112                // Method divide:(Ljavafx/beans/value/ObservableNumberValue;Ljavafx/beans/value/ObservableNumberValue;[Ljavafx/beans/Observable;)Ljavafx/beans/binding/NumberBinding;
      16: areturn

  public static javafx.beans.binding.NumberBinding divide(float, javafx.beans.value.ObservableNumberValue);
    Code:
       0: fload_0
       1: invokestatic  #83                 // Method com/sun/javafx/binding/FloatConstant.valueOf:(F)Lcom/sun/javafx/binding/FloatConstant;
       4: aload_1
       5: iconst_1
       6: anewarray     #79                 // class javafx/beans/Observable
       9: dup
      10: iconst_0
      11: aload_1
      12: aastore
      13: invokestatic  #112                // Method divide:(Ljavafx/beans/value/ObservableNumberValue;Ljavafx/beans/value/ObservableNumberValue;[Ljavafx/beans/Observable;)Ljavafx/beans/binding/NumberBinding;
      16: areturn

  public static javafx.beans.binding.NumberBinding divide(javafx.beans.value.ObservableNumberValue, long);
    Code:
       0: aload_0
       1: lload_1
       2: invokestatic  #84                 // Method com/sun/javafx/binding/LongConstant.valueOf:(J)Lcom/sun/javafx/binding/LongConstant;
       5: iconst_1
       6: anewarray     #79                 // class javafx/beans/Observable
       9: dup
      10: iconst_0
      11: aload_0
      12: aastore
      13: invokestatic  #112                // Method divide:(Ljavafx/beans/value/ObservableNumberValue;Ljavafx/beans/value/ObservableNumberValue;[Ljavafx/beans/Observable;)Ljavafx/beans/binding/NumberBinding;
      16: areturn

  public static javafx.beans.binding.NumberBinding divide(long, javafx.beans.value.ObservableNumberValue);
    Code:
       0: lload_0
       1: invokestatic  #84                 // Method com/sun/javafx/binding/LongConstant.valueOf:(J)Lcom/sun/javafx/binding/LongConstant;
       4: aload_2
       5: iconst_1
       6: anewarray     #79                 // class javafx/beans/Observable
       9: dup
      10: iconst_0
      11: aload_2
      12: aastore
      13: invokestatic  #112                // Method divide:(Ljavafx/beans/value/ObservableNumberValue;Ljavafx/beans/value/ObservableNumberValue;[Ljavafx/beans/Observable;)Ljavafx/beans/binding/NumberBinding;
      16: areturn

  public static javafx.beans.binding.NumberBinding divide(javafx.beans.value.ObservableNumberValue, int);
    Code:
       0: aload_0
       1: iload_1
       2: invokestatic  #85                 // Method com/sun/javafx/binding/IntegerConstant.valueOf:(I)Lcom/sun/javafx/binding/IntegerConstant;
       5: iconst_1
       6: anewarray     #79                 // class javafx/beans/Observable
       9: dup
      10: iconst_0
      11: aload_0
      12: aastore
      13: invokestatic  #112                // Method divide:(Ljavafx/beans/value/ObservableNumberValue;Ljavafx/beans/value/ObservableNumberValue;[Ljavafx/beans/Observable;)Ljavafx/beans/binding/NumberBinding;
      16: areturn

  public static javafx.beans.binding.NumberBinding divide(int, javafx.beans.value.ObservableNumberValue);
    Code:
       0: iload_0
       1: invokestatic  #85                 // Method com/sun/javafx/binding/IntegerConstant.valueOf:(I)Lcom/sun/javafx/binding/IntegerConstant;
       4: aload_1
       5: iconst_1
       6: anewarray     #79                 // class javafx/beans/Observable
       9: dup
      10: iconst_0
      11: aload_1
      12: aastore
      13: invokestatic  #112                // Method divide:(Ljavafx/beans/value/ObservableNumberValue;Ljavafx/beans/value/ObservableNumberValue;[Ljavafx/beans/Observable;)Ljavafx/beans/binding/NumberBinding;
      16: areturn

  private static javafx.beans.binding.BooleanBinding equal(javafx.beans.value.ObservableNumberValue, javafx.beans.value.ObservableNumberValue, double, javafx.beans.Observable...);
    Code:
       0: aload_0
       1: ifnull        8
       4: aload_1
       5: ifnonnull     18
       8: new           #53                 // class java/lang/NullPointerException
      11: dup
      12: ldc           #67                 // String Operands cannot be null.
      14: invokespecial #55                 // Method java/lang/NullPointerException."<init>":(Ljava/lang/String;)V
      17: athrow
      18: getstatic     #68                 // Field $assertionsDisabled:Z
      21: ifne          43
      24: aload         4
      26: ifnull        35
      29: aload         4
      31: arraylength
      32: ifgt          43
      35: new           #69                 // class java/lang/AssertionError
      38: dup
      39: invokespecial #70                 // Method java/lang/AssertionError."<init>":()V
      42: athrow
      43: aload_0
      44: instanceof    #56                 // class javafx/beans/value/ObservableDoubleValue
      47: ifne          57
      50: aload_1
      51: instanceof    #56                 // class javafx/beans/value/ObservableDoubleValue
      54: ifeq          70
      57: new           #113                // class javafx/beans/binding/Bindings$28
      60: dup
      61: aload         4
      63: aload_0
      64: aload_1
      65: dload_2
      66: invokespecial #114                // Method javafx/beans/binding/Bindings$28."<init>":([Ljavafx/beans/Observable;Ljavafx/beans/value/ObservableNumberValue;Ljavafx/beans/value/ObservableNumberValue;D)V
      69: areturn
      70: aload_0
      71: instanceof    #59                 // class javafx/beans/value/ObservableFloatValue
      74: ifne          84
      77: aload_1
      78: instanceof    #59                 // class javafx/beans/value/ObservableFloatValue
      81: ifeq          97
      84: new           #115                // class javafx/beans/binding/Bindings$29
      87: dup
      88: aload         4
      90: aload_0
      91: aload_1
      92: dload_2
      93: invokespecial #116                // Method javafx/beans/binding/Bindings$29."<init>":([Ljavafx/beans/Observable;Ljavafx/beans/value/ObservableNumberValue;Ljavafx/beans/value/ObservableNumberValue;D)V
      96: areturn
      97: aload_0
      98: instanceof    #62                 // class javafx/beans/value/ObservableLongValue
     101: ifne          111
     104: aload_1
     105: instanceof    #62                 // class javafx/beans/value/ObservableLongValue
     108: ifeq          124
     111: new           #117                // class javafx/beans/binding/Bindings$30
     114: dup
     115: aload         4
     117: aload_0
     118: aload_1
     119: dload_2
     120: invokespecial #118                // Method javafx/beans/binding/Bindings$30."<init>":([Ljavafx/beans/Observable;Ljavafx/beans/value/ObservableNumberValue;Ljavafx/beans/value/ObservableNumberValue;D)V
     123: areturn
     124: new           #119                // class javafx/beans/binding/Bindings$31
     127: dup
     128: aload         4
     130: aload_0
     131: aload_1
     132: dload_2
     133: invokespecial #120                // Method javafx/beans/binding/Bindings$31."<init>":([Ljavafx/beans/Observable;Ljavafx/beans/value/ObservableNumberValue;Ljavafx/beans/value/ObservableNumberValue;D)V
     136: areturn

  public static javafx.beans.binding.BooleanBinding equal(javafx.beans.value.ObservableNumberValue, javafx.beans.value.ObservableNumberValue, double);
    Code:
       0: aload_0
       1: aload_1
       2: dload_2
       3: iconst_2
       4: anewarray     #79                 // class javafx/beans/Observable
       7: dup
       8: iconst_0
       9: aload_0
      10: aastore
      11: dup
      12: iconst_1
      13: aload_1
      14: aastore
      15: invokestatic  #121                // Method equal:(Ljavafx/beans/value/ObservableNumberValue;Ljavafx/beans/value/ObservableNumberValue;D[Ljavafx/beans/Observable;)Ljavafx/beans/binding/BooleanBinding;
      18: areturn

  public static javafx.beans.binding.BooleanBinding equal(javafx.beans.value.ObservableNumberValue, javafx.beans.value.ObservableNumberValue);
    Code:
       0: aload_0
       1: aload_1
       2: dconst_0
       3: iconst_2
       4: anewarray     #79                 // class javafx/beans/Observable
       7: dup
       8: iconst_0
       9: aload_0
      10: aastore
      11: dup
      12: iconst_1
      13: aload_1
      14: aastore
      15: invokestatic  #121                // Method equal:(Ljavafx/beans/value/ObservableNumberValue;Ljavafx/beans/value/ObservableNumberValue;D[Ljavafx/beans/Observable;)Ljavafx/beans/binding/BooleanBinding;
      18: areturn

  public static javafx.beans.binding.BooleanBinding equal(javafx.beans.value.ObservableNumberValue, double, double);
    Code:
       0: aload_0
       1: dload_1
       2: invokestatic  #81                 // Method com/sun/javafx/binding/DoubleConstant.valueOf:(D)Lcom/sun/javafx/binding/DoubleConstant;
       5: dload_3
       6: iconst_1
       7: anewarray     #79                 // class javafx/beans/Observable
      10: dup
      11: iconst_0
      12: aload_0
      13: aastore
      14: invokestatic  #121                // Method equal:(Ljavafx/beans/value/ObservableNumberValue;Ljavafx/beans/value/ObservableNumberValue;D[Ljavafx/beans/Observable;)Ljavafx/beans/binding/BooleanBinding;
      17: areturn

  public static javafx.beans.binding.BooleanBinding equal(double, javafx.beans.value.ObservableNumberValue, double);
    Code:
       0: dload_0
       1: invokestatic  #81                 // Method com/sun/javafx/binding/DoubleConstant.valueOf:(D)Lcom/sun/javafx/binding/DoubleConstant;
       4: aload_2
       5: dload_3
       6: iconst_1
       7: anewarray     #79                 // class javafx/beans/Observable
      10: dup
      11: iconst_0
      12: aload_2
      13: aastore
      14: invokestatic  #121                // Method equal:(Ljavafx/beans/value/ObservableNumberValue;Ljavafx/beans/value/ObservableNumberValue;D[Ljavafx/beans/Observable;)Ljavafx/beans/binding/BooleanBinding;
      17: areturn

  public static javafx.beans.binding.BooleanBinding equal(javafx.beans.value.ObservableNumberValue, float, double);
    Code:
       0: aload_0
       1: fload_1
       2: invokestatic  #83                 // Method com/sun/javafx/binding/FloatConstant.valueOf:(F)Lcom/sun/javafx/binding/FloatConstant;
       5: dload_2
       6: iconst_1
       7: anewarray     #79                 // class javafx/beans/Observable
      10: dup
      11: iconst_0
      12: aload_0
      13: aastore
      14: invokestatic  #121                // Method equal:(Ljavafx/beans/value/ObservableNumberValue;Ljavafx/beans/value/ObservableNumberValue;D[Ljavafx/beans/Observable;)Ljavafx/beans/binding/BooleanBinding;
      17: areturn

  public static javafx.beans.binding.BooleanBinding equal(float, javafx.beans.value.ObservableNumberValue, double);
    Code:
       0: fload_0
       1: invokestatic  #83                 // Method com/sun/javafx/binding/FloatConstant.valueOf:(F)Lcom/sun/javafx/binding/FloatConstant;
       4: aload_1
       5: dload_2
       6: iconst_1
       7: anewarray     #79                 // class javafx/beans/Observable
      10: dup
      11: iconst_0
      12: aload_1
      13: aastore
      14: invokestatic  #121                // Method equal:(Ljavafx/beans/value/ObservableNumberValue;Ljavafx/beans/value/ObservableNumberValue;D[Ljavafx/beans/Observable;)Ljavafx/beans/binding/BooleanBinding;
      17: areturn

  public static javafx.beans.binding.BooleanBinding equal(javafx.beans.value.ObservableNumberValue, long, double);
    Code:
       0: aload_0
       1: lload_1
       2: invokestatic  #84                 // Method com/sun/javafx/binding/LongConstant.valueOf:(J)Lcom/sun/javafx/binding/LongConstant;
       5: dload_3
       6: iconst_1
       7: anewarray     #79                 // class javafx/beans/Observable
      10: dup
      11: iconst_0
      12: aload_0
      13: aastore
      14: invokestatic  #121                // Method equal:(Ljavafx/beans/value/ObservableNumberValue;Ljavafx/beans/value/ObservableNumberValue;D[Ljavafx/beans/Observable;)Ljavafx/beans/binding/BooleanBinding;
      17: areturn

  public static javafx.beans.binding.BooleanBinding equal(javafx.beans.value.ObservableNumberValue, long);
    Code:
       0: aload_0
       1: lload_1
       2: invokestatic  #84                 // Method com/sun/javafx/binding/LongConstant.valueOf:(J)Lcom/sun/javafx/binding/LongConstant;
       5: dconst_0
       6: iconst_1
       7: anewarray     #79                 // class javafx/beans/Observable
      10: dup
      11: iconst_0
      12: aload_0
      13: aastore
      14: invokestatic  #121                // Method equal:(Ljavafx/beans/value/ObservableNumberValue;Ljavafx/beans/value/ObservableNumberValue;D[Ljavafx/beans/Observable;)Ljavafx/beans/binding/BooleanBinding;
      17: areturn

  public static javafx.beans.binding.BooleanBinding equal(long, javafx.beans.value.ObservableNumberValue, double);
    Code:
       0: lload_0
       1: invokestatic  #84                 // Method com/sun/javafx/binding/LongConstant.valueOf:(J)Lcom/sun/javafx/binding/LongConstant;
       4: aload_2
       5: dload_3
       6: iconst_1
       7: anewarray     #79                 // class javafx/beans/Observable
      10: dup
      11: iconst_0
      12: aload_2
      13: aastore
      14: invokestatic  #121                // Method equal:(Ljavafx/beans/value/ObservableNumberValue;Ljavafx/beans/value/ObservableNumberValue;D[Ljavafx/beans/Observable;)Ljavafx/beans/binding/BooleanBinding;
      17: areturn

  public static javafx.beans.binding.BooleanBinding equal(long, javafx.beans.value.ObservableNumberValue);
    Code:
       0: lload_0
       1: invokestatic  #84                 // Method com/sun/javafx/binding/LongConstant.valueOf:(J)Lcom/sun/javafx/binding/LongConstant;
       4: aload_2
       5: dconst_0
       6: iconst_1
       7: anewarray     #79                 // class javafx/beans/Observable
      10: dup
      11: iconst_0
      12: aload_2
      13: aastore
      14: invokestatic  #121                // Method equal:(Ljavafx/beans/value/ObservableNumberValue;Ljavafx/beans/value/ObservableNumberValue;D[Ljavafx/beans/Observable;)Ljavafx/beans/binding/BooleanBinding;
      17: areturn

  public static javafx.beans.binding.BooleanBinding equal(javafx.beans.value.ObservableNumberValue, int, double);
    Code:
       0: aload_0
       1: iload_1
       2: invokestatic  #85                 // Method com/sun/javafx/binding/IntegerConstant.valueOf:(I)Lcom/sun/javafx/binding/IntegerConstant;
       5: dload_2
       6: iconst_1
       7: anewarray     #79                 // class javafx/beans/Observable
      10: dup
      11: iconst_0
      12: aload_0
      13: aastore
      14: invokestatic  #121                // Method equal:(Ljavafx/beans/value/ObservableNumberValue;Ljavafx/beans/value/ObservableNumberValue;D[Ljavafx/beans/Observable;)Ljavafx/beans/binding/BooleanBinding;
      17: areturn

  public static javafx.beans.binding.BooleanBinding equal(javafx.beans.value.ObservableNumberValue, int);
    Code:
       0: aload_0
       1: iload_1
       2: invokestatic  #85                 // Method com/sun/javafx/binding/IntegerConstant.valueOf:(I)Lcom/sun/javafx/binding/IntegerConstant;
       5: dconst_0
       6: iconst_1
       7: anewarray     #79                 // class javafx/beans/Observable
      10: dup
      11: iconst_0
      12: aload_0
      13: aastore
      14: invokestatic  #121                // Method equal:(Ljavafx/beans/value/ObservableNumberValue;Ljavafx/beans/value/ObservableNumberValue;D[Ljavafx/beans/Observable;)Ljavafx/beans/binding/BooleanBinding;
      17: areturn

  public static javafx.beans.binding.BooleanBinding equal(int, javafx.beans.value.ObservableNumberValue, double);
    Code:
       0: iload_0
       1: invokestatic  #85                 // Method com/sun/javafx/binding/IntegerConstant.valueOf:(I)Lcom/sun/javafx/binding/IntegerConstant;
       4: aload_1
       5: dload_2
       6: iconst_1
       7: anewarray     #79                 // class javafx/beans/Observable
      10: dup
      11: iconst_0
      12: aload_1
      13: aastore
      14: invokestatic  #121                // Method equal:(Ljavafx/beans/value/ObservableNumberValue;Ljavafx/beans/value/ObservableNumberValue;D[Ljavafx/beans/Observable;)Ljavafx/beans/binding/BooleanBinding;
      17: areturn

  public static javafx.beans.binding.BooleanBinding equal(int, javafx.beans.value.ObservableNumberValue);
    Code:
       0: iload_0
       1: invokestatic  #85                 // Method com/sun/javafx/binding/IntegerConstant.valueOf:(I)Lcom/sun/javafx/binding/IntegerConstant;
       4: aload_1
       5: dconst_0
       6: iconst_1
       7: anewarray     #79                 // class javafx/beans/Observable
      10: dup
      11: iconst_0
      12: aload_1
      13: aastore
      14: invokestatic  #121                // Method equal:(Ljavafx/beans/value/ObservableNumberValue;Ljavafx/beans/value/ObservableNumberValue;D[Ljavafx/beans/Observable;)Ljavafx/beans/binding/BooleanBinding;
      17: areturn

  private static javafx.beans.binding.BooleanBinding notEqual(javafx.beans.value.ObservableNumberValue, javafx.beans.value.ObservableNumberValue, double, javafx.beans.Observable...);
    Code:
       0: aload_0
       1: ifnull        8
       4: aload_1
       5: ifnonnull     18
       8: new           #53                 // class java/lang/NullPointerException
      11: dup
      12: ldc           #67                 // String Operands cannot be null.
      14: invokespecial #55                 // Method java/lang/NullPointerException."<init>":(Ljava/lang/String;)V
      17: athrow
      18: getstatic     #68                 // Field $assertionsDisabled:Z
      21: ifne          43
      24: aload         4
      26: ifnull        35
      29: aload         4
      31: arraylength
      32: ifgt          43
      35: new           #69                 // class java/lang/AssertionError
      38: dup
      39: invokespecial #70                 // Method java/lang/AssertionError."<init>":()V
      42: athrow
      43: aload_0
      44: instanceof    #56                 // class javafx/beans/value/ObservableDoubleValue
      47: ifne          57
      50: aload_1
      51: instanceof    #56                 // class javafx/beans/value/ObservableDoubleValue
      54: ifeq          70
      57: new           #122                // class javafx/beans/binding/Bindings$32
      60: dup
      61: aload         4
      63: aload_0
      64: aload_1
      65: dload_2
      66: invokespecial #123                // Method javafx/beans/binding/Bindings$32."<init>":([Ljavafx/beans/Observable;Ljavafx/beans/value/ObservableNumberValue;Ljavafx/beans/value/ObservableNumberValue;D)V
      69: areturn
      70: aload_0
      71: instanceof    #59                 // class javafx/beans/value/ObservableFloatValue
      74: ifne          84
      77: aload_1
      78: instanceof    #59                 // class javafx/beans/value/ObservableFloatValue
      81: ifeq          97
      84: new           #124                // class javafx/beans/binding/Bindings$33
      87: dup
      88: aload         4
      90: aload_0
      91: aload_1
      92: dload_2
      93: invokespecial #125                // Method javafx/beans/binding/Bindings$33."<init>":([Ljavafx/beans/Observable;Ljavafx/beans/value/ObservableNumberValue;Ljavafx/beans/value/ObservableNumberValue;D)V
      96: areturn
      97: aload_0
      98: instanceof    #62                 // class javafx/beans/value/ObservableLongValue
     101: ifne          111
     104: aload_1
     105: instanceof    #62                 // class javafx/beans/value/ObservableLongValue
     108: ifeq          124
     111: new           #126                // class javafx/beans/binding/Bindings$34
     114: dup
     115: aload         4
     117: aload_0
     118: aload_1
     119: dload_2
     120: invokespecial #127                // Method javafx/beans/binding/Bindings$34."<init>":([Ljavafx/beans/Observable;Ljavafx/beans/value/ObservableNumberValue;Ljavafx/beans/value/ObservableNumberValue;D)V
     123: areturn
     124: new           #128                // class javafx/beans/binding/Bindings$35
     127: dup
     128: aload         4
     130: aload_0
     131: aload_1
     132: dload_2
     133: invokespecial #129                // Method javafx/beans/binding/Bindings$35."<init>":([Ljavafx/beans/Observable;Ljavafx/beans/value/ObservableNumberValue;Ljavafx/beans/value/ObservableNumberValue;D)V
     136: areturn

  public static javafx.beans.binding.BooleanBinding notEqual(javafx.beans.value.ObservableNumberValue, javafx.beans.value.ObservableNumberValue, double);
    Code:
       0: aload_0
       1: aload_1
       2: dload_2
       3: iconst_2
       4: anewarray     #79                 // class javafx/beans/Observable
       7: dup
       8: iconst_0
       9: aload_0
      10: aastore
      11: dup
      12: iconst_1
      13: aload_1
      14: aastore
      15: invokestatic  #130                // Method notEqual:(Ljavafx/beans/value/ObservableNumberValue;Ljavafx/beans/value/ObservableNumberValue;D[Ljavafx/beans/Observable;)Ljavafx/beans/binding/BooleanBinding;
      18: areturn

  public static javafx.beans.binding.BooleanBinding notEqual(javafx.beans.value.ObservableNumberValue, javafx.beans.value.ObservableNumberValue);
    Code:
       0: aload_0
       1: aload_1
       2: dconst_0
       3: iconst_2
       4: anewarray     #79                 // class javafx/beans/Observable
       7: dup
       8: iconst_0
       9: aload_0
      10: aastore
      11: dup
      12: iconst_1
      13: aload_1
      14: aastore
      15: invokestatic  #130                // Method notEqual:(Ljavafx/beans/value/ObservableNumberValue;Ljavafx/beans/value/ObservableNumberValue;D[Ljavafx/beans/Observable;)Ljavafx/beans/binding/BooleanBinding;
      18: areturn

  public static javafx.beans.binding.BooleanBinding notEqual(javafx.beans.value.ObservableNumberValue, double, double);
    Code:
       0: aload_0
       1: dload_1
       2: invokestatic  #81                 // Method com/sun/javafx/binding/DoubleConstant.valueOf:(D)Lcom/sun/javafx/binding/DoubleConstant;
       5: dload_3
       6: iconst_1
       7: anewarray     #79                 // class javafx/beans/Observable
      10: dup
      11: iconst_0
      12: aload_0
      13: aastore
      14: invokestatic  #130                // Method notEqual:(Ljavafx/beans/value/ObservableNumberValue;Ljavafx/beans/value/ObservableNumberValue;D[Ljavafx/beans/Observable;)Ljavafx/beans/binding/BooleanBinding;
      17: areturn

  public static javafx.beans.binding.BooleanBinding notEqual(double, javafx.beans.value.ObservableNumberValue, double);
    Code:
       0: dload_0
       1: invokestatic  #81                 // Method com/sun/javafx/binding/DoubleConstant.valueOf:(D)Lcom/sun/javafx/binding/DoubleConstant;
       4: aload_2
       5: dload_3
       6: iconst_1
       7: anewarray     #79                 // class javafx/beans/Observable
      10: dup
      11: iconst_0
      12: aload_2
      13: aastore
      14: invokestatic  #130                // Method notEqual:(Ljavafx/beans/value/ObservableNumberValue;Ljavafx/beans/value/ObservableNumberValue;D[Ljavafx/beans/Observable;)Ljavafx/beans/binding/BooleanBinding;
      17: areturn

  public static javafx.beans.binding.BooleanBinding notEqual(javafx.beans.value.ObservableNumberValue, float, double);
    Code:
       0: aload_0
       1: fload_1
       2: invokestatic  #83                 // Method com/sun/javafx/binding/FloatConstant.valueOf:(F)Lcom/sun/javafx/binding/FloatConstant;
       5: dload_2
       6: iconst_1
       7: anewarray     #79                 // class javafx/beans/Observable
      10: dup
      11: iconst_0
      12: aload_0
      13: aastore
      14: invokestatic  #130                // Method notEqual:(Ljavafx/beans/value/ObservableNumberValue;Ljavafx/beans/value/ObservableNumberValue;D[Ljavafx/beans/Observable;)Ljavafx/beans/binding/BooleanBinding;
      17: areturn

  public static javafx.beans.binding.BooleanBinding notEqual(float, javafx.beans.value.ObservableNumberValue, double);
    Code:
       0: fload_0
       1: invokestatic  #83                 // Method com/sun/javafx/binding/FloatConstant.valueOf:(F)Lcom/sun/javafx/binding/FloatConstant;
       4: aload_1
       5: dload_2
       6: iconst_1
       7: anewarray     #79                 // class javafx/beans/Observable
      10: dup
      11: iconst_0
      12: aload_1
      13: aastore
      14: invokestatic  #130                // Method notEqual:(Ljavafx/beans/value/ObservableNumberValue;Ljavafx/beans/value/ObservableNumberValue;D[Ljavafx/beans/Observable;)Ljavafx/beans/binding/BooleanBinding;
      17: areturn

  public static javafx.beans.binding.BooleanBinding notEqual(javafx.beans.value.ObservableNumberValue, long, double);
    Code:
       0: aload_0
       1: lload_1
       2: invokestatic  #84                 // Method com/sun/javafx/binding/LongConstant.valueOf:(J)Lcom/sun/javafx/binding/LongConstant;
       5: dload_3
       6: iconst_1
       7: anewarray     #79                 // class javafx/beans/Observable
      10: dup
      11: iconst_0
      12: aload_0
      13: aastore
      14: invokestatic  #130                // Method notEqual:(Ljavafx/beans/value/ObservableNumberValue;Ljavafx/beans/value/ObservableNumberValue;D[Ljavafx/beans/Observable;)Ljavafx/beans/binding/BooleanBinding;
      17: areturn

  public static javafx.beans.binding.BooleanBinding notEqual(javafx.beans.value.ObservableNumberValue, long);
    Code:
       0: aload_0
       1: lload_1
       2: invokestatic  #84                 // Method com/sun/javafx/binding/LongConstant.valueOf:(J)Lcom/sun/javafx/binding/LongConstant;
       5: dconst_0
       6: iconst_1
       7: anewarray     #79                 // class javafx/beans/Observable
      10: dup
      11: iconst_0
      12: aload_0
      13: aastore
      14: invokestatic  #130                // Method notEqual:(Ljavafx/beans/value/ObservableNumberValue;Ljavafx/beans/value/ObservableNumberValue;D[Ljavafx/beans/Observable;)Ljavafx/beans/binding/BooleanBinding;
      17: areturn

  public static javafx.beans.binding.BooleanBinding notEqual(long, javafx.beans.value.ObservableNumberValue, double);
    Code:
       0: lload_0
       1: invokestatic  #84                 // Method com/sun/javafx/binding/LongConstant.valueOf:(J)Lcom/sun/javafx/binding/LongConstant;
       4: aload_2
       5: dload_3
       6: iconst_1
       7: anewarray     #79                 // class javafx/beans/Observable
      10: dup
      11: iconst_0
      12: aload_2
      13: aastore
      14: invokestatic  #130                // Method notEqual:(Ljavafx/beans/value/ObservableNumberValue;Ljavafx/beans/value/ObservableNumberValue;D[Ljavafx/beans/Observable;)Ljavafx/beans/binding/BooleanBinding;
      17: areturn

  public static javafx.beans.binding.BooleanBinding notEqual(long, javafx.beans.value.ObservableNumberValue);
    Code:
       0: lload_0
       1: invokestatic  #84                 // Method com/sun/javafx/binding/LongConstant.valueOf:(J)Lcom/sun/javafx/binding/LongConstant;
       4: aload_2
       5: dconst_0
       6: iconst_1
       7: anewarray     #79                 // class javafx/beans/Observable
      10: dup
      11: iconst_0
      12: aload_2
      13: aastore
      14: invokestatic  #130                // Method notEqual:(Ljavafx/beans/value/ObservableNumberValue;Ljavafx/beans/value/ObservableNumberValue;D[Ljavafx/beans/Observable;)Ljavafx/beans/binding/BooleanBinding;
      17: areturn

  public static javafx.beans.binding.BooleanBinding notEqual(javafx.beans.value.ObservableNumberValue, int, double);
    Code:
       0: aload_0
       1: iload_1
       2: invokestatic  #85                 // Method com/sun/javafx/binding/IntegerConstant.valueOf:(I)Lcom/sun/javafx/binding/IntegerConstant;
       5: dload_2
       6: iconst_1
       7: anewarray     #79                 // class javafx/beans/Observable
      10: dup
      11: iconst_0
      12: aload_0
      13: aastore
      14: invokestatic  #130                // Method notEqual:(Ljavafx/beans/value/ObservableNumberValue;Ljavafx/beans/value/ObservableNumberValue;D[Ljavafx/beans/Observable;)Ljavafx/beans/binding/BooleanBinding;
      17: areturn

  public static javafx.beans.binding.BooleanBinding notEqual(javafx.beans.value.ObservableNumberValue, int);
    Code:
       0: aload_0
       1: iload_1
       2: invokestatic  #85                 // Method com/sun/javafx/binding/IntegerConstant.valueOf:(I)Lcom/sun/javafx/binding/IntegerConstant;
       5: dconst_0
       6: iconst_1
       7: anewarray     #79                 // class javafx/beans/Observable
      10: dup
      11: iconst_0
      12: aload_0
      13: aastore
      14: invokestatic  #130                // Method notEqual:(Ljavafx/beans/value/ObservableNumberValue;Ljavafx/beans/value/ObservableNumberValue;D[Ljavafx/beans/Observable;)Ljavafx/beans/binding/BooleanBinding;
      17: areturn

  public static javafx.beans.binding.BooleanBinding notEqual(int, javafx.beans.value.ObservableNumberValue, double);
    Code:
       0: iload_0
       1: invokestatic  #85                 // Method com/sun/javafx/binding/IntegerConstant.valueOf:(I)Lcom/sun/javafx/binding/IntegerConstant;
       4: aload_1
       5: dload_2
       6: iconst_1
       7: anewarray     #79                 // class javafx/beans/Observable
      10: dup
      11: iconst_0
      12: aload_1
      13: aastore
      14: invokestatic  #130                // Method notEqual:(Ljavafx/beans/value/ObservableNumberValue;Ljavafx/beans/value/ObservableNumberValue;D[Ljavafx/beans/Observable;)Ljavafx/beans/binding/BooleanBinding;
      17: areturn

  public static javafx.beans.binding.BooleanBinding notEqual(int, javafx.beans.value.ObservableNumberValue);
    Code:
       0: iload_0
       1: invokestatic  #85                 // Method com/sun/javafx/binding/IntegerConstant.valueOf:(I)Lcom/sun/javafx/binding/IntegerConstant;
       4: aload_1
       5: dconst_0
       6: iconst_1
       7: anewarray     #79                 // class javafx/beans/Observable
      10: dup
      11: iconst_0
      12: aload_1
      13: aastore
      14: invokestatic  #130                // Method notEqual:(Ljavafx/beans/value/ObservableNumberValue;Ljavafx/beans/value/ObservableNumberValue;D[Ljavafx/beans/Observable;)Ljavafx/beans/binding/BooleanBinding;
      17: areturn

  private static javafx.beans.binding.BooleanBinding greaterThan(javafx.beans.value.ObservableNumberValue, javafx.beans.value.ObservableNumberValue, javafx.beans.Observable...);
    Code:
       0: aload_0
       1: ifnull        8
       4: aload_1
       5: ifnonnull     18
       8: new           #53                 // class java/lang/NullPointerException
      11: dup
      12: ldc           #67                 // String Operands cannot be null.
      14: invokespecial #55                 // Method java/lang/NullPointerException."<init>":(Ljava/lang/String;)V
      17: athrow
      18: getstatic     #68                 // Field $assertionsDisabled:Z
      21: ifne          41
      24: aload_2
      25: ifnull        33
      28: aload_2
      29: arraylength
      30: ifgt          41
      33: new           #69                 // class java/lang/AssertionError
      36: dup
      37: invokespecial #70                 // Method java/lang/AssertionError."<init>":()V
      40: athrow
      41: aload_0
      42: instanceof    #56                 // class javafx/beans/value/ObservableDoubleValue
      45: ifne          55
      48: aload_1
      49: instanceof    #56                 // class javafx/beans/value/ObservableDoubleValue
      52: ifeq          66
      55: new           #131                // class javafx/beans/binding/Bindings$36
      58: dup
      59: aload_2
      60: aload_0
      61: aload_1
      62: invokespecial #132                // Method javafx/beans/binding/Bindings$36."<init>":([Ljavafx/beans/Observable;Ljavafx/beans/value/ObservableNumberValue;Ljavafx/beans/value/ObservableNumberValue;)V
      65: areturn
      66: aload_0
      67: instanceof    #59                 // class javafx/beans/value/ObservableFloatValue
      70: ifne          80
      73: aload_1
      74: instanceof    #59                 // class javafx/beans/value/ObservableFloatValue
      77: ifeq          91
      80: new           #133                // class javafx/beans/binding/Bindings$37
      83: dup
      84: aload_2
      85: aload_0
      86: aload_1
      87: invokespecial #134                // Method javafx/beans/binding/Bindings$37."<init>":([Ljavafx/beans/Observable;Ljavafx/beans/value/ObservableNumberValue;Ljavafx/beans/value/ObservableNumberValue;)V
      90: areturn
      91: aload_0
      92: instanceof    #62                 // class javafx/beans/value/ObservableLongValue
      95: ifne          105
      98: aload_1
      99: instanceof    #62                 // class javafx/beans/value/ObservableLongValue
     102: ifeq          116
     105: new           #135                // class javafx/beans/binding/Bindings$38
     108: dup
     109: aload_2
     110: aload_0
     111: aload_1
     112: invokespecial #136                // Method javafx/beans/binding/Bindings$38."<init>":([Ljavafx/beans/Observable;Ljavafx/beans/value/ObservableNumberValue;Ljavafx/beans/value/ObservableNumberValue;)V
     115: areturn
     116: new           #137                // class javafx/beans/binding/Bindings$39
     119: dup
     120: aload_2
     121: aload_0
     122: aload_1
     123: invokespecial #138                // Method javafx/beans/binding/Bindings$39."<init>":([Ljavafx/beans/Observable;Ljavafx/beans/value/ObservableNumberValue;Ljavafx/beans/value/ObservableNumberValue;)V
     126: areturn

  public static javafx.beans.binding.BooleanBinding greaterThan(javafx.beans.value.ObservableNumberValue, javafx.beans.value.ObservableNumberValue);
    Code:
       0: aload_0
       1: aload_1
       2: iconst_2
       3: anewarray     #79                 // class javafx/beans/Observable
       6: dup
       7: iconst_0
       8: aload_0
       9: aastore
      10: dup
      11: iconst_1
      12: aload_1
      13: aastore
      14: invokestatic  #139                // Method greaterThan:(Ljavafx/beans/value/ObservableNumberValue;Ljavafx/beans/value/ObservableNumberValue;[Ljavafx/beans/Observable;)Ljavafx/beans/binding/BooleanBinding;
      17: areturn

  public static javafx.beans.binding.BooleanBinding greaterThan(javafx.beans.value.ObservableNumberValue, double);
    Code:
       0: aload_0
       1: dload_1
       2: invokestatic  #81                 // Method com/sun/javafx/binding/DoubleConstant.valueOf:(D)Lcom/sun/javafx/binding/DoubleConstant;
       5: iconst_1
       6: anewarray     #79                 // class javafx/beans/Observable
       9: dup
      10: iconst_0
      11: aload_0
      12: aastore
      13: invokestatic  #139                // Method greaterThan:(Ljavafx/beans/value/ObservableNumberValue;Ljavafx/beans/value/ObservableNumberValue;[Ljavafx/beans/Observable;)Ljavafx/beans/binding/BooleanBinding;
      16: areturn

  public static javafx.beans.binding.BooleanBinding greaterThan(double, javafx.beans.value.ObservableNumberValue);
    Code:
       0: dload_0
       1: invokestatic  #81                 // Method com/sun/javafx/binding/DoubleConstant.valueOf:(D)Lcom/sun/javafx/binding/DoubleConstant;
       4: aload_2
       5: iconst_1
       6: anewarray     #79                 // class javafx/beans/Observable
       9: dup
      10: iconst_0
      11: aload_2
      12: aastore
      13: invokestatic  #139                // Method greaterThan:(Ljavafx/beans/value/ObservableNumberValue;Ljavafx/beans/value/ObservableNumberValue;[Ljavafx/beans/Observable;)Ljavafx/beans/binding/BooleanBinding;
      16: areturn

  public static javafx.beans.binding.BooleanBinding greaterThan(javafx.beans.value.ObservableNumberValue, float);
    Code:
       0: aload_0
       1: fload_1
       2: invokestatic  #83                 // Method com/sun/javafx/binding/FloatConstant.valueOf:(F)Lcom/sun/javafx/binding/FloatConstant;
       5: iconst_1
       6: anewarray     #79                 // class javafx/beans/Observable
       9: dup
      10: iconst_0
      11: aload_0
      12: aastore
      13: invokestatic  #139                // Method greaterThan:(Ljavafx/beans/value/ObservableNumberValue;Ljavafx/beans/value/ObservableNumberValue;[Ljavafx/beans/Observable;)Ljavafx/beans/binding/BooleanBinding;
      16: areturn

  public static javafx.beans.binding.BooleanBinding greaterThan(float, javafx.beans.value.ObservableNumberValue);
    Code:
       0: fload_0
       1: invokestatic  #83                 // Method com/sun/javafx/binding/FloatConstant.valueOf:(F)Lcom/sun/javafx/binding/FloatConstant;
       4: aload_1
       5: iconst_1
       6: anewarray     #79                 // class javafx/beans/Observable
       9: dup
      10: iconst_0
      11: aload_1
      12: aastore
      13: invokestatic  #139                // Method greaterThan:(Ljavafx/beans/value/ObservableNumberValue;Ljavafx/beans/value/ObservableNumberValue;[Ljavafx/beans/Observable;)Ljavafx/beans/binding/BooleanBinding;
      16: areturn

  public static javafx.beans.binding.BooleanBinding greaterThan(javafx.beans.value.ObservableNumberValue, long);
    Code:
       0: aload_0
       1: lload_1
       2: invokestatic  #84                 // Method com/sun/javafx/binding/LongConstant.valueOf:(J)Lcom/sun/javafx/binding/LongConstant;
       5: iconst_1
       6: anewarray     #79                 // class javafx/beans/Observable
       9: dup
      10: iconst_0
      11: aload_0
      12: aastore
      13: invokestatic  #139                // Method greaterThan:(Ljavafx/beans/value/ObservableNumberValue;Ljavafx/beans/value/ObservableNumberValue;[Ljavafx/beans/Observable;)Ljavafx/beans/binding/BooleanBinding;
      16: areturn

  public static javafx.beans.binding.BooleanBinding greaterThan(long, javafx.beans.value.ObservableNumberValue);
    Code:
       0: lload_0
       1: invokestatic  #84                 // Method com/sun/javafx/binding/LongConstant.valueOf:(J)Lcom/sun/javafx/binding/LongConstant;
       4: aload_2
       5: iconst_1
       6: anewarray     #79                 // class javafx/beans/Observable
       9: dup
      10: iconst_0
      11: aload_2
      12: aastore
      13: invokestatic  #139                // Method greaterThan:(Ljavafx/beans/value/ObservableNumberValue;Ljavafx/beans/value/ObservableNumberValue;[Ljavafx/beans/Observable;)Ljavafx/beans/binding/BooleanBinding;
      16: areturn

  public static javafx.beans.binding.BooleanBinding greaterThan(javafx.beans.value.ObservableNumberValue, int);
    Code:
       0: aload_0
       1: iload_1
       2: invokestatic  #85                 // Method com/sun/javafx/binding/IntegerConstant.valueOf:(I)Lcom/sun/javafx/binding/IntegerConstant;
       5: iconst_1
       6: anewarray     #79                 // class javafx/beans/Observable
       9: dup
      10: iconst_0
      11: aload_0
      12: aastore
      13: invokestatic  #139                // Method greaterThan:(Ljavafx/beans/value/ObservableNumberValue;Ljavafx/beans/value/ObservableNumberValue;[Ljavafx/beans/Observable;)Ljavafx/beans/binding/BooleanBinding;
      16: areturn

  public static javafx.beans.binding.BooleanBinding greaterThan(int, javafx.beans.value.ObservableNumberValue);
    Code:
       0: iload_0
       1: invokestatic  #85                 // Method com/sun/javafx/binding/IntegerConstant.valueOf:(I)Lcom/sun/javafx/binding/IntegerConstant;
       4: aload_1
       5: iconst_1
       6: anewarray     #79                 // class javafx/beans/Observable
       9: dup
      10: iconst_0
      11: aload_1
      12: aastore
      13: invokestatic  #139                // Method greaterThan:(Ljavafx/beans/value/ObservableNumberValue;Ljavafx/beans/value/ObservableNumberValue;[Ljavafx/beans/Observable;)Ljavafx/beans/binding/BooleanBinding;
      16: areturn

  private static javafx.beans.binding.BooleanBinding lessThan(javafx.beans.value.ObservableNumberValue, javafx.beans.value.ObservableNumberValue, javafx.beans.Observable...);
    Code:
       0: aload_1
       1: aload_0
       2: aload_2
       3: invokestatic  #139                // Method greaterThan:(Ljavafx/beans/value/ObservableNumberValue;Ljavafx/beans/value/ObservableNumberValue;[Ljavafx/beans/Observable;)Ljavafx/beans/binding/BooleanBinding;
       6: areturn

  public static javafx.beans.binding.BooleanBinding lessThan(javafx.beans.value.ObservableNumberValue, javafx.beans.value.ObservableNumberValue);
    Code:
       0: aload_0
       1: aload_1
       2: iconst_2
       3: anewarray     #79                 // class javafx/beans/Observable
       6: dup
       7: iconst_0
       8: aload_0
       9: aastore
      10: dup
      11: iconst_1
      12: aload_1
      13: aastore
      14: invokestatic  #140                // Method lessThan:(Ljavafx/beans/value/ObservableNumberValue;Ljavafx/beans/value/ObservableNumberValue;[Ljavafx/beans/Observable;)Ljavafx/beans/binding/BooleanBinding;
      17: areturn

  public static javafx.beans.binding.BooleanBinding lessThan(javafx.beans.value.ObservableNumberValue, double);
    Code:
       0: aload_0
       1: dload_1
       2: invokestatic  #81                 // Method com/sun/javafx/binding/DoubleConstant.valueOf:(D)Lcom/sun/javafx/binding/DoubleConstant;
       5: iconst_1
       6: anewarray     #79                 // class javafx/beans/Observable
       9: dup
      10: iconst_0
      11: aload_0
      12: aastore
      13: invokestatic  #140                // Method lessThan:(Ljavafx/beans/value/ObservableNumberValue;Ljavafx/beans/value/ObservableNumberValue;[Ljavafx/beans/Observable;)Ljavafx/beans/binding/BooleanBinding;
      16: areturn

  public static javafx.beans.binding.BooleanBinding lessThan(double, javafx.beans.value.ObservableNumberValue);
    Code:
       0: dload_0
       1: invokestatic  #81                 // Method com/sun/javafx/binding/DoubleConstant.valueOf:(D)Lcom/sun/javafx/binding/DoubleConstant;
       4: aload_2
       5: iconst_1
       6: anewarray     #79                 // class javafx/beans/Observable
       9: dup
      10: iconst_0
      11: aload_2
      12: aastore
      13: invokestatic  #140                // Method lessThan:(Ljavafx/beans/value/ObservableNumberValue;Ljavafx/beans/value/ObservableNumberValue;[Ljavafx/beans/Observable;)Ljavafx/beans/binding/BooleanBinding;
      16: areturn

  public static javafx.beans.binding.BooleanBinding lessThan(javafx.beans.value.ObservableNumberValue, float);
    Code:
       0: aload_0
       1: fload_1
       2: invokestatic  #83                 // Method com/sun/javafx/binding/FloatConstant.valueOf:(F)Lcom/sun/javafx/binding/FloatConstant;
       5: iconst_1
       6: anewarray     #79                 // class javafx/beans/Observable
       9: dup
      10: iconst_0
      11: aload_0
      12: aastore
      13: invokestatic  #140                // Method lessThan:(Ljavafx/beans/value/ObservableNumberValue;Ljavafx/beans/value/ObservableNumberValue;[Ljavafx/beans/Observable;)Ljavafx/beans/binding/BooleanBinding;
      16: areturn

  public static javafx.beans.binding.BooleanBinding lessThan(float, javafx.beans.value.ObservableNumberValue);
    Code:
       0: fload_0
       1: invokestatic  #83                 // Method com/sun/javafx/binding/FloatConstant.valueOf:(F)Lcom/sun/javafx/binding/FloatConstant;
       4: aload_1
       5: iconst_1
       6: anewarray     #79                 // class javafx/beans/Observable
       9: dup
      10: iconst_0
      11: aload_1
      12: aastore
      13: invokestatic  #140                // Method lessThan:(Ljavafx/beans/value/ObservableNumberValue;Ljavafx/beans/value/ObservableNumberValue;[Ljavafx/beans/Observable;)Ljavafx/beans/binding/BooleanBinding;
      16: areturn

  public static javafx.beans.binding.BooleanBinding lessThan(javafx.beans.value.ObservableNumberValue, long);
    Code:
       0: aload_0
       1: lload_1
       2: invokestatic  #84                 // Method com/sun/javafx/binding/LongConstant.valueOf:(J)Lcom/sun/javafx/binding/LongConstant;
       5: iconst_1
       6: anewarray     #79                 // class javafx/beans/Observable
       9: dup
      10: iconst_0
      11: aload_0
      12: aastore
      13: invokestatic  #140                // Method lessThan:(Ljavafx/beans/value/ObservableNumberValue;Ljavafx/beans/value/ObservableNumberValue;[Ljavafx/beans/Observable;)Ljavafx/beans/binding/BooleanBinding;
      16: areturn

  public static javafx.beans.binding.BooleanBinding lessThan(long, javafx.beans.value.ObservableNumberValue);
    Code:
       0: lload_0
       1: invokestatic  #84                 // Method com/sun/javafx/binding/LongConstant.valueOf:(J)Lcom/sun/javafx/binding/LongConstant;
       4: aload_2
       5: iconst_1
       6: anewarray     #79                 // class javafx/beans/Observable
       9: dup
      10: iconst_0
      11: aload_2
      12: aastore
      13: invokestatic  #140                // Method lessThan:(Ljavafx/beans/value/ObservableNumberValue;Ljavafx/beans/value/ObservableNumberValue;[Ljavafx/beans/Observable;)Ljavafx/beans/binding/BooleanBinding;
      16: areturn

  public static javafx.beans.binding.BooleanBinding lessThan(javafx.beans.value.ObservableNumberValue, int);
    Code:
       0: aload_0
       1: iload_1
       2: invokestatic  #85                 // Method com/sun/javafx/binding/IntegerConstant.valueOf:(I)Lcom/sun/javafx/binding/IntegerConstant;
       5: iconst_1
       6: anewarray     #79                 // class javafx/beans/Observable
       9: dup
      10: iconst_0
      11: aload_0
      12: aastore
      13: invokestatic  #140                // Method lessThan:(Ljavafx/beans/value/ObservableNumberValue;Ljavafx/beans/value/ObservableNumberValue;[Ljavafx/beans/Observable;)Ljavafx/beans/binding/BooleanBinding;
      16: areturn

  public static javafx.beans.binding.BooleanBinding lessThan(int, javafx.beans.value.ObservableNumberValue);
    Code:
       0: iload_0
       1: invokestatic  #85                 // Method com/sun/javafx/binding/IntegerConstant.valueOf:(I)Lcom/sun/javafx/binding/IntegerConstant;
       4: aload_1
       5: iconst_1
       6: anewarray     #79                 // class javafx/beans/Observable
       9: dup
      10: iconst_0
      11: aload_1
      12: aastore
      13: invokestatic  #140                // Method lessThan:(Ljavafx/beans/value/ObservableNumberValue;Ljavafx/beans/value/ObservableNumberValue;[Ljavafx/beans/Observable;)Ljavafx/beans/binding/BooleanBinding;
      16: areturn

  private static javafx.beans.binding.BooleanBinding greaterThanOrEqual(javafx.beans.value.ObservableNumberValue, javafx.beans.value.ObservableNumberValue, javafx.beans.Observable...);
    Code:
       0: aload_0
       1: ifnull        8
       4: aload_1
       5: ifnonnull     18
       8: new           #53                 // class java/lang/NullPointerException
      11: dup
      12: ldc           #67                 // String Operands cannot be null.
      14: invokespecial #55                 // Method java/lang/NullPointerException."<init>":(Ljava/lang/String;)V
      17: athrow
      18: getstatic     #68                 // Field $assertionsDisabled:Z
      21: ifne          41
      24: aload_2
      25: ifnull        33
      28: aload_2
      29: arraylength
      30: ifgt          41
      33: new           #69                 // class java/lang/AssertionError
      36: dup
      37: invokespecial #70                 // Method java/lang/AssertionError."<init>":()V
      40: athrow
      41: aload_0
      42: instanceof    #56                 // class javafx/beans/value/ObservableDoubleValue
      45: ifne          55
      48: aload_1
      49: instanceof    #56                 // class javafx/beans/value/ObservableDoubleValue
      52: ifeq          66
      55: new           #141                // class javafx/beans/binding/Bindings$40
      58: dup
      59: aload_2
      60: aload_0
      61: aload_1
      62: invokespecial #142                // Method javafx/beans/binding/Bindings$40."<init>":([Ljavafx/beans/Observable;Ljavafx/beans/value/ObservableNumberValue;Ljavafx/beans/value/ObservableNumberValue;)V
      65: areturn
      66: aload_0
      67: instanceof    #59                 // class javafx/beans/value/ObservableFloatValue
      70: ifne          80
      73: aload_1
      74: instanceof    #59                 // class javafx/beans/value/ObservableFloatValue
      77: ifeq          91
      80: new           #143                // class javafx/beans/binding/Bindings$41
      83: dup
      84: aload_2
      85: aload_0
      86: aload_1
      87: invokespecial #144                // Method javafx/beans/binding/Bindings$41."<init>":([Ljavafx/beans/Observable;Ljavafx/beans/value/ObservableNumberValue;Ljavafx/beans/value/ObservableNumberValue;)V
      90: areturn
      91: aload_0
      92: instanceof    #62                 // class javafx/beans/value/ObservableLongValue
      95: ifne          105
      98: aload_1
      99: instanceof    #62                 // class javafx/beans/value/ObservableLongValue
     102: ifeq          116
     105: new           #145                // class javafx/beans/binding/Bindings$42
     108: dup
     109: aload_2
     110: aload_0
     111: aload_1
     112: invokespecial #146                // Method javafx/beans/binding/Bindings$42."<init>":([Ljavafx/beans/Observable;Ljavafx/beans/value/ObservableNumberValue;Ljavafx/beans/value/ObservableNumberValue;)V
     115: areturn
     116: new           #147                // class javafx/beans/binding/Bindings$43
     119: dup
     120: aload_2
     121: aload_0
     122: aload_1
     123: invokespecial #148                // Method javafx/beans/binding/Bindings$43."<init>":([Ljavafx/beans/Observable;Ljavafx/beans/value/ObservableNumberValue;Ljavafx/beans/value/ObservableNumberValue;)V
     126: areturn

  public static javafx.beans.binding.BooleanBinding greaterThanOrEqual(javafx.beans.value.ObservableNumberValue, javafx.beans.value.ObservableNumberValue);
    Code:
       0: aload_0
       1: aload_1
       2: iconst_2
       3: anewarray     #79                 // class javafx/beans/Observable
       6: dup
       7: iconst_0
       8: aload_0
       9: aastore
      10: dup
      11: iconst_1
      12: aload_1
      13: aastore
      14: invokestatic  #149                // Method greaterThanOrEqual:(Ljavafx/beans/value/ObservableNumberValue;Ljavafx/beans/value/ObservableNumberValue;[Ljavafx/beans/Observable;)Ljavafx/beans/binding/BooleanBinding;
      17: areturn

  public static javafx.beans.binding.BooleanBinding greaterThanOrEqual(javafx.beans.value.ObservableNumberValue, double);
    Code:
       0: aload_0
       1: dload_1
       2: invokestatic  #81                 // Method com/sun/javafx/binding/DoubleConstant.valueOf:(D)Lcom/sun/javafx/binding/DoubleConstant;
       5: iconst_1
       6: anewarray     #79                 // class javafx/beans/Observable
       9: dup
      10: iconst_0
      11: aload_0
      12: aastore
      13: invokestatic  #149                // Method greaterThanOrEqual:(Ljavafx/beans/value/ObservableNumberValue;Ljavafx/beans/value/ObservableNumberValue;[Ljavafx/beans/Observable;)Ljavafx/beans/binding/BooleanBinding;
      16: areturn

  public static javafx.beans.binding.BooleanBinding greaterThanOrEqual(double, javafx.beans.value.ObservableNumberValue);
    Code:
       0: dload_0
       1: invokestatic  #81                 // Method com/sun/javafx/binding/DoubleConstant.valueOf:(D)Lcom/sun/javafx/binding/DoubleConstant;
       4: aload_2
       5: iconst_1
       6: anewarray     #79                 // class javafx/beans/Observable
       9: dup
      10: iconst_0
      11: aload_2
      12: aastore
      13: invokestatic  #149                // Method greaterThanOrEqual:(Ljavafx/beans/value/ObservableNumberValue;Ljavafx/beans/value/ObservableNumberValue;[Ljavafx/beans/Observable;)Ljavafx/beans/binding/BooleanBinding;
      16: areturn

  public static javafx.beans.binding.BooleanBinding greaterThanOrEqual(javafx.beans.value.ObservableNumberValue, float);
    Code:
       0: aload_0
       1: fload_1
       2: invokestatic  #83                 // Method com/sun/javafx/binding/FloatConstant.valueOf:(F)Lcom/sun/javafx/binding/FloatConstant;
       5: iconst_1
       6: anewarray     #79                 // class javafx/beans/Observable
       9: dup
      10: iconst_0
      11: aload_0
      12: aastore
      13: invokestatic  #149                // Method greaterThanOrEqual:(Ljavafx/beans/value/ObservableNumberValue;Ljavafx/beans/value/ObservableNumberValue;[Ljavafx/beans/Observable;)Ljavafx/beans/binding/BooleanBinding;
      16: areturn

  public static javafx.beans.binding.BooleanBinding greaterThanOrEqual(float, javafx.beans.value.ObservableNumberValue);
    Code:
       0: fload_0
       1: invokestatic  #83                 // Method com/sun/javafx/binding/FloatConstant.valueOf:(F)Lcom/sun/javafx/binding/FloatConstant;
       4: aload_1
       5: iconst_1
       6: anewarray     #79                 // class javafx/beans/Observable
       9: dup
      10: iconst_0
      11: aload_1
      12: aastore
      13: invokestatic  #149                // Method greaterThanOrEqual:(Ljavafx/beans/value/ObservableNumberValue;Ljavafx/beans/value/ObservableNumberValue;[Ljavafx/beans/Observable;)Ljavafx/beans/binding/BooleanBinding;
      16: areturn

  public static javafx.beans.binding.BooleanBinding greaterThanOrEqual(javafx.beans.value.ObservableNumberValue, long);
    Code:
       0: aload_0
       1: lload_1
       2: invokestatic  #84                 // Method com/sun/javafx/binding/LongConstant.valueOf:(J)Lcom/sun/javafx/binding/LongConstant;
       5: iconst_1
       6: anewarray     #79                 // class javafx/beans/Observable
       9: dup
      10: iconst_0
      11: aload_0
      12: aastore
      13: invokestatic  #149                // Method greaterThanOrEqual:(Ljavafx/beans/value/ObservableNumberValue;Ljavafx/beans/value/ObservableNumberValue;[Ljavafx/beans/Observable;)Ljavafx/beans/binding/BooleanBinding;
      16: areturn

  public static javafx.beans.binding.BooleanBinding greaterThanOrEqual(long, javafx.beans.value.ObservableNumberValue);
    Code:
       0: lload_0
       1: invokestatic  #84                 // Method com/sun/javafx/binding/LongConstant.valueOf:(J)Lcom/sun/javafx/binding/LongConstant;
       4: aload_2
       5: iconst_1
       6: anewarray     #79                 // class javafx/beans/Observable
       9: dup
      10: iconst_0
      11: aload_2
      12: aastore
      13: invokestatic  #149                // Method greaterThanOrEqual:(Ljavafx/beans/value/ObservableNumberValue;Ljavafx/beans/value/ObservableNumberValue;[Ljavafx/beans/Observable;)Ljavafx/beans/binding/BooleanBinding;
      16: areturn

  public static javafx.beans.binding.BooleanBinding greaterThanOrEqual(javafx.beans.value.ObservableNumberValue, int);
    Code:
       0: aload_0
       1: iload_1
       2: invokestatic  #85                 // Method com/sun/javafx/binding/IntegerConstant.valueOf:(I)Lcom/sun/javafx/binding/IntegerConstant;
       5: iconst_1
       6: anewarray     #79                 // class javafx/beans/Observable
       9: dup
      10: iconst_0
      11: aload_0
      12: aastore
      13: invokestatic  #149                // Method greaterThanOrEqual:(Ljavafx/beans/value/ObservableNumberValue;Ljavafx/beans/value/ObservableNumberValue;[Ljavafx/beans/Observable;)Ljavafx/beans/binding/BooleanBinding;
      16: areturn

  public static javafx.beans.binding.BooleanBinding greaterThanOrEqual(int, javafx.beans.value.ObservableNumberValue);
    Code:
       0: iload_0
       1: invokestatic  #85                 // Method com/sun/javafx/binding/IntegerConstant.valueOf:(I)Lcom/sun/javafx/binding/IntegerConstant;
       4: aload_1
       5: iconst_1
       6: anewarray     #79                 // class javafx/beans/Observable
       9: dup
      10: iconst_0
      11: aload_1
      12: aastore
      13: invokestatic  #149                // Method greaterThanOrEqual:(Ljavafx/beans/value/ObservableNumberValue;Ljavafx/beans/value/ObservableNumberValue;[Ljavafx/beans/Observable;)Ljavafx/beans/binding/BooleanBinding;
      16: areturn

  private static javafx.beans.binding.BooleanBinding lessThanOrEqual(javafx.beans.value.ObservableNumberValue, javafx.beans.value.ObservableNumberValue, javafx.beans.Observable...);
    Code:
       0: aload_1
       1: aload_0
       2: aload_2
       3: invokestatic  #149                // Method greaterThanOrEqual:(Ljavafx/beans/value/ObservableNumberValue;Ljavafx/beans/value/ObservableNumberValue;[Ljavafx/beans/Observable;)Ljavafx/beans/binding/BooleanBinding;
       6: areturn

  public static javafx.beans.binding.BooleanBinding lessThanOrEqual(javafx.beans.value.ObservableNumberValue, javafx.beans.value.ObservableNumberValue);
    Code:
       0: aload_0
       1: aload_1
       2: iconst_2
       3: anewarray     #79                 // class javafx/beans/Observable
       6: dup
       7: iconst_0
       8: aload_0
       9: aastore
      10: dup
      11: iconst_1
      12: aload_1
      13: aastore
      14: invokestatic  #150                // Method lessThanOrEqual:(Ljavafx/beans/value/ObservableNumberValue;Ljavafx/beans/value/ObservableNumberValue;[Ljavafx/beans/Observable;)Ljavafx/beans/binding/BooleanBinding;
      17: areturn

  public static javafx.beans.binding.BooleanBinding lessThanOrEqual(javafx.beans.value.ObservableNumberValue, double);
    Code:
       0: aload_0
       1: dload_1
       2: invokestatic  #81                 // Method com/sun/javafx/binding/DoubleConstant.valueOf:(D)Lcom/sun/javafx/binding/DoubleConstant;
       5: iconst_1
       6: anewarray     #79                 // class javafx/beans/Observable
       9: dup
      10: iconst_0
      11: aload_0
      12: aastore
      13: invokestatic  #150                // Method lessThanOrEqual:(Ljavafx/beans/value/ObservableNumberValue;Ljavafx/beans/value/ObservableNumberValue;[Ljavafx/beans/Observable;)Ljavafx/beans/binding/BooleanBinding;
      16: areturn

  public static javafx.beans.binding.BooleanBinding lessThanOrEqual(double, javafx.beans.value.ObservableNumberValue);
    Code:
       0: dload_0
       1: invokestatic  #81                 // Method com/sun/javafx/binding/DoubleConstant.valueOf:(D)Lcom/sun/javafx/binding/DoubleConstant;
       4: aload_2
       5: iconst_1
       6: anewarray     #79                 // class javafx/beans/Observable
       9: dup
      10: iconst_0
      11: aload_2
      12: aastore
      13: invokestatic  #150                // Method lessThanOrEqual:(Ljavafx/beans/value/ObservableNumberValue;Ljavafx/beans/value/ObservableNumberValue;[Ljavafx/beans/Observable;)Ljavafx/beans/binding/BooleanBinding;
      16: areturn

  public static javafx.beans.binding.BooleanBinding lessThanOrEqual(javafx.beans.value.ObservableNumberValue, float);
    Code:
       0: aload_0
       1: fload_1
       2: invokestatic  #83                 // Method com/sun/javafx/binding/FloatConstant.valueOf:(F)Lcom/sun/javafx/binding/FloatConstant;
       5: iconst_1
       6: anewarray     #79                 // class javafx/beans/Observable
       9: dup
      10: iconst_0
      11: aload_0
      12: aastore
      13: invokestatic  #150                // Method lessThanOrEqual:(Ljavafx/beans/value/ObservableNumberValue;Ljavafx/beans/value/ObservableNumberValue;[Ljavafx/beans/Observable;)Ljavafx/beans/binding/BooleanBinding;
      16: areturn

  public static javafx.beans.binding.BooleanBinding lessThanOrEqual(float, javafx.beans.value.ObservableNumberValue);
    Code:
       0: fload_0
       1: invokestatic  #83                 // Method com/sun/javafx/binding/FloatConstant.valueOf:(F)Lcom/sun/javafx/binding/FloatConstant;
       4: aload_1
       5: iconst_1
       6: anewarray     #79                 // class javafx/beans/Observable
       9: dup
      10: iconst_0
      11: aload_1
      12: aastore
      13: invokestatic  #150                // Method lessThanOrEqual:(Ljavafx/beans/value/ObservableNumberValue;Ljavafx/beans/value/ObservableNumberValue;[Ljavafx/beans/Observable;)Ljavafx/beans/binding/BooleanBinding;
      16: areturn

  public static javafx.beans.binding.BooleanBinding lessThanOrEqual(javafx.beans.value.ObservableNumberValue, long);
    Code:
       0: aload_0
       1: lload_1
       2: invokestatic  #84                 // Method com/sun/javafx/binding/LongConstant.valueOf:(J)Lcom/sun/javafx/binding/LongConstant;
       5: iconst_1
       6: anewarray     #79                 // class javafx/beans/Observable
       9: dup
      10: iconst_0
      11: aload_0
      12: aastore
      13: invokestatic  #150                // Method lessThanOrEqual:(Ljavafx/beans/value/ObservableNumberValue;Ljavafx/beans/value/ObservableNumberValue;[Ljavafx/beans/Observable;)Ljavafx/beans/binding/BooleanBinding;
      16: areturn

  public static javafx.beans.binding.BooleanBinding lessThanOrEqual(long, javafx.beans.value.ObservableNumberValue);
    Code:
       0: lload_0
       1: invokestatic  #84                 // Method com/sun/javafx/binding/LongConstant.valueOf:(J)Lcom/sun/javafx/binding/LongConstant;
       4: aload_2
       5: iconst_1
       6: anewarray     #79                 // class javafx/beans/Observable
       9: dup
      10: iconst_0
      11: aload_2
      12: aastore
      13: invokestatic  #150                // Method lessThanOrEqual:(Ljavafx/beans/value/ObservableNumberValue;Ljavafx/beans/value/ObservableNumberValue;[Ljavafx/beans/Observable;)Ljavafx/beans/binding/BooleanBinding;
      16: areturn

  public static javafx.beans.binding.BooleanBinding lessThanOrEqual(javafx.beans.value.ObservableNumberValue, int);
    Code:
       0: aload_0
       1: iload_1
       2: invokestatic  #85                 // Method com/sun/javafx/binding/IntegerConstant.valueOf:(I)Lcom/sun/javafx/binding/IntegerConstant;
       5: iconst_1
       6: anewarray     #79                 // class javafx/beans/Observable
       9: dup
      10: iconst_0
      11: aload_0
      12: aastore
      13: invokestatic  #150                // Method lessThanOrEqual:(Ljavafx/beans/value/ObservableNumberValue;Ljavafx/beans/value/ObservableNumberValue;[Ljavafx/beans/Observable;)Ljavafx/beans/binding/BooleanBinding;
      16: areturn

  public static javafx.beans.binding.BooleanBinding lessThanOrEqual(int, javafx.beans.value.ObservableNumberValue);
    Code:
       0: iload_0
       1: invokestatic  #85                 // Method com/sun/javafx/binding/IntegerConstant.valueOf:(I)Lcom/sun/javafx/binding/IntegerConstant;
       4: aload_1
       5: iconst_1
       6: anewarray     #79                 // class javafx/beans/Observable
       9: dup
      10: iconst_0
      11: aload_1
      12: aastore
      13: invokestatic  #150                // Method lessThanOrEqual:(Ljavafx/beans/value/ObservableNumberValue;Ljavafx/beans/value/ObservableNumberValue;[Ljavafx/beans/Observable;)Ljavafx/beans/binding/BooleanBinding;
      16: areturn

  private static javafx.beans.binding.NumberBinding min(javafx.beans.value.ObservableNumberValue, javafx.beans.value.ObservableNumberValue, javafx.beans.Observable...);
    Code:
       0: aload_0
       1: ifnull        8
       4: aload_1
       5: ifnonnull     18
       8: new           #53                 // class java/lang/NullPointerException
      11: dup
      12: ldc           #67                 // String Operands cannot be null.
      14: invokespecial #55                 // Method java/lang/NullPointerException."<init>":(Ljava/lang/String;)V
      17: athrow
      18: getstatic     #68                 // Field $assertionsDisabled:Z
      21: ifne          41
      24: aload_2
      25: ifnull        33
      28: aload_2
      29: arraylength
      30: ifgt          41
      33: new           #69                 // class java/lang/AssertionError
      36: dup
      37: invokespecial #70                 // Method java/lang/AssertionError."<init>":()V
      40: athrow
      41: aload_0
      42: instanceof    #56                 // class javafx/beans/value/ObservableDoubleValue
      45: ifne          55
      48: aload_1
      49: instanceof    #56                 // class javafx/beans/value/ObservableDoubleValue
      52: ifeq          66
      55: new           #151                // class javafx/beans/binding/Bindings$44
      58: dup
      59: aload_2
      60: aload_0
      61: aload_1
      62: invokespecial #152                // Method javafx/beans/binding/Bindings$44."<init>":([Ljavafx/beans/Observable;Ljavafx/beans/value/ObservableNumberValue;Ljavafx/beans/value/ObservableNumberValue;)V
      65: areturn
      66: aload_0
      67: instanceof    #59                 // class javafx/beans/value/ObservableFloatValue
      70: ifne          80
      73: aload_1
      74: instanceof    #59                 // class javafx/beans/value/ObservableFloatValue
      77: ifeq          91
      80: new           #153                // class javafx/beans/binding/Bindings$45
      83: dup
      84: aload_2
      85: aload_0
      86: aload_1
      87: invokespecial #154                // Method javafx/beans/binding/Bindings$45."<init>":([Ljavafx/beans/Observable;Ljavafx/beans/value/ObservableNumberValue;Ljavafx/beans/value/ObservableNumberValue;)V
      90: areturn
      91: aload_0
      92: instanceof    #62                 // class javafx/beans/value/ObservableLongValue
      95: ifne          105
      98: aload_1
      99: instanceof    #62                 // class javafx/beans/value/ObservableLongValue
     102: ifeq          116
     105: new           #155                // class javafx/beans/binding/Bindings$46
     108: dup
     109: aload_2
     110: aload_0
     111: aload_1
     112: invokespecial #156                // Method javafx/beans/binding/Bindings$46."<init>":([Ljavafx/beans/Observable;Ljavafx/beans/value/ObservableNumberValue;Ljavafx/beans/value/ObservableNumberValue;)V
     115: areturn
     116: new           #157                // class javafx/beans/binding/Bindings$47
     119: dup
     120: aload_2
     121: aload_0
     122: aload_1
     123: invokespecial #158                // Method javafx/beans/binding/Bindings$47."<init>":([Ljavafx/beans/Observable;Ljavafx/beans/value/ObservableNumberValue;Ljavafx/beans/value/ObservableNumberValue;)V
     126: areturn

  public static javafx.beans.binding.NumberBinding min(javafx.beans.value.ObservableNumberValue, javafx.beans.value.ObservableNumberValue);
    Code:
       0: aload_0
       1: aload_1
       2: iconst_2
       3: anewarray     #79                 // class javafx/beans/Observable
       6: dup
       7: iconst_0
       8: aload_0
       9: aastore
      10: dup
      11: iconst_1
      12: aload_1
      13: aastore
      14: invokestatic  #159                // Method min:(Ljavafx/beans/value/ObservableNumberValue;Ljavafx/beans/value/ObservableNumberValue;[Ljavafx/beans/Observable;)Ljavafx/beans/binding/NumberBinding;
      17: areturn

  public static javafx.beans.binding.DoubleBinding min(javafx.beans.value.ObservableNumberValue, double);
    Code:
       0: aload_0
       1: dload_1
       2: invokestatic  #81                 // Method com/sun/javafx/binding/DoubleConstant.valueOf:(D)Lcom/sun/javafx/binding/DoubleConstant;
       5: iconst_1
       6: anewarray     #79                 // class javafx/beans/Observable
       9: dup
      10: iconst_0
      11: aload_0
      12: aastore
      13: invokestatic  #159                // Method min:(Ljavafx/beans/value/ObservableNumberValue;Ljavafx/beans/value/ObservableNumberValue;[Ljavafx/beans/Observable;)Ljavafx/beans/binding/NumberBinding;
      16: checkcast     #82                 // class javafx/beans/binding/DoubleBinding
      19: areturn

  public static javafx.beans.binding.DoubleBinding min(double, javafx.beans.value.ObservableNumberValue);
    Code:
       0: dload_0
       1: invokestatic  #81                 // Method com/sun/javafx/binding/DoubleConstant.valueOf:(D)Lcom/sun/javafx/binding/DoubleConstant;
       4: aload_2
       5: iconst_1
       6: anewarray     #79                 // class javafx/beans/Observable
       9: dup
      10: iconst_0
      11: aload_2
      12: aastore
      13: invokestatic  #159                // Method min:(Ljavafx/beans/value/ObservableNumberValue;Ljavafx/beans/value/ObservableNumberValue;[Ljavafx/beans/Observable;)Ljavafx/beans/binding/NumberBinding;
      16: checkcast     #82                 // class javafx/beans/binding/DoubleBinding
      19: areturn

  public static javafx.beans.binding.NumberBinding min(javafx.beans.value.ObservableNumberValue, float);
    Code:
       0: aload_0
       1: fload_1
       2: invokestatic  #83                 // Method com/sun/javafx/binding/FloatConstant.valueOf:(F)Lcom/sun/javafx/binding/FloatConstant;
       5: iconst_1
       6: anewarray     #79                 // class javafx/beans/Observable
       9: dup
      10: iconst_0
      11: aload_0
      12: aastore
      13: invokestatic  #159                // Method min:(Ljavafx/beans/value/ObservableNumberValue;Ljavafx/beans/value/ObservableNumberValue;[Ljavafx/beans/Observable;)Ljavafx/beans/binding/NumberBinding;
      16: areturn

  public static javafx.beans.binding.NumberBinding min(float, javafx.beans.value.ObservableNumberValue);
    Code:
       0: fload_0
       1: invokestatic  #83                 // Method com/sun/javafx/binding/FloatConstant.valueOf:(F)Lcom/sun/javafx/binding/FloatConstant;
       4: aload_1
       5: iconst_1
       6: anewarray     #79                 // class javafx/beans/Observable
       9: dup
      10: iconst_0
      11: aload_1
      12: aastore
      13: invokestatic  #159                // Method min:(Ljavafx/beans/value/ObservableNumberValue;Ljavafx/beans/value/ObservableNumberValue;[Ljavafx/beans/Observable;)Ljavafx/beans/binding/NumberBinding;
      16: areturn

  public static javafx.beans.binding.NumberBinding min(javafx.beans.value.ObservableNumberValue, long);
    Code:
       0: aload_0
       1: lload_1
       2: invokestatic  #84                 // Method com/sun/javafx/binding/LongConstant.valueOf:(J)Lcom/sun/javafx/binding/LongConstant;
       5: iconst_1
       6: anewarray     #79                 // class javafx/beans/Observable
       9: dup
      10: iconst_0
      11: aload_0
      12: aastore
      13: invokestatic  #159                // Method min:(Ljavafx/beans/value/ObservableNumberValue;Ljavafx/beans/value/ObservableNumberValue;[Ljavafx/beans/Observable;)Ljavafx/beans/binding/NumberBinding;
      16: areturn

  public static javafx.beans.binding.NumberBinding min(long, javafx.beans.value.ObservableNumberValue);
    Code:
       0: lload_0
       1: invokestatic  #84                 // Method com/sun/javafx/binding/LongConstant.valueOf:(J)Lcom/sun/javafx/binding/LongConstant;
       4: aload_2
       5: iconst_1
       6: anewarray     #79                 // class javafx/beans/Observable
       9: dup
      10: iconst_0
      11: aload_2
      12: aastore
      13: invokestatic  #159                // Method min:(Ljavafx/beans/value/ObservableNumberValue;Ljavafx/beans/value/ObservableNumberValue;[Ljavafx/beans/Observable;)Ljavafx/beans/binding/NumberBinding;
      16: areturn

  public static javafx.beans.binding.NumberBinding min(javafx.beans.value.ObservableNumberValue, int);
    Code:
       0: aload_0
       1: iload_1
       2: invokestatic  #85                 // Method com/sun/javafx/binding/IntegerConstant.valueOf:(I)Lcom/sun/javafx/binding/IntegerConstant;
       5: iconst_1
       6: anewarray     #79                 // class javafx/beans/Observable
       9: dup
      10: iconst_0
      11: aload_0
      12: aastore
      13: invokestatic  #159                // Method min:(Ljavafx/beans/value/ObservableNumberValue;Ljavafx/beans/value/ObservableNumberValue;[Ljavafx/beans/Observable;)Ljavafx/beans/binding/NumberBinding;
      16: areturn

  public static javafx.beans.binding.NumberBinding min(int, javafx.beans.value.ObservableNumberValue);
    Code:
       0: iload_0
       1: invokestatic  #85                 // Method com/sun/javafx/binding/IntegerConstant.valueOf:(I)Lcom/sun/javafx/binding/IntegerConstant;
       4: aload_1
       5: iconst_1
       6: anewarray     #79                 // class javafx/beans/Observable
       9: dup
      10: iconst_0
      11: aload_1
      12: aastore
      13: invokestatic  #159                // Method min:(Ljavafx/beans/value/ObservableNumberValue;Ljavafx/beans/value/ObservableNumberValue;[Ljavafx/beans/Observable;)Ljavafx/beans/binding/NumberBinding;
      16: areturn

  private static javafx.beans.binding.NumberBinding max(javafx.beans.value.ObservableNumberValue, javafx.beans.value.ObservableNumberValue, javafx.beans.Observable...);
    Code:
       0: aload_0
       1: ifnull        8
       4: aload_1
       5: ifnonnull     18
       8: new           #53                 // class java/lang/NullPointerException
      11: dup
      12: ldc           #67                 // String Operands cannot be null.
      14: invokespecial #55                 // Method java/lang/NullPointerException."<init>":(Ljava/lang/String;)V
      17: athrow
      18: getstatic     #68                 // Field $assertionsDisabled:Z
      21: ifne          41
      24: aload_2
      25: ifnull        33
      28: aload_2
      29: arraylength
      30: ifgt          41
      33: new           #69                 // class java/lang/AssertionError
      36: dup
      37: invokespecial #70                 // Method java/lang/AssertionError."<init>":()V
      40: athrow
      41: aload_0
      42: instanceof    #56                 // class javafx/beans/value/ObservableDoubleValue
      45: ifne          55
      48: aload_1
      49: instanceof    #56                 // class javafx/beans/value/ObservableDoubleValue
      52: ifeq          66
      55: new           #160                // class javafx/beans/binding/Bindings$48
      58: dup
      59: aload_2
      60: aload_0
      61: aload_1
      62: invokespecial #161                // Method javafx/beans/binding/Bindings$48."<init>":([Ljavafx/beans/Observable;Ljavafx/beans/value/ObservableNumberValue;Ljavafx/beans/value/ObservableNumberValue;)V
      65: areturn
      66: aload_0
      67: instanceof    #59                 // class javafx/beans/value/ObservableFloatValue
      70: ifne          80
      73: aload_1
      74: instanceof    #59                 // class javafx/beans/value/ObservableFloatValue
      77: ifeq          91
      80: new           #162                // class javafx/beans/binding/Bindings$49
      83: dup
      84: aload_2
      85: aload_0
      86: aload_1
      87: invokespecial #163                // Method javafx/beans/binding/Bindings$49."<init>":([Ljavafx/beans/Observable;Ljavafx/beans/value/ObservableNumberValue;Ljavafx/beans/value/ObservableNumberValue;)V
      90: areturn
      91: aload_0
      92: instanceof    #62                 // class javafx/beans/value/ObservableLongValue
      95: ifne          105
      98: aload_1
      99: instanceof    #62                 // class javafx/beans/value/ObservableLongValue
     102: ifeq          116
     105: new           #164                // class javafx/beans/binding/Bindings$50
     108: dup
     109: aload_2
     110: aload_0
     111: aload_1
     112: invokespecial #165                // Method javafx/beans/binding/Bindings$50."<init>":([Ljavafx/beans/Observable;Ljavafx/beans/value/ObservableNumberValue;Ljavafx/beans/value/ObservableNumberValue;)V
     115: areturn
     116: new           #166                // class javafx/beans/binding/Bindings$51
     119: dup
     120: aload_2
     121: aload_0
     122: aload_1
     123: invokespecial #167                // Method javafx/beans/binding/Bindings$51."<init>":([Ljavafx/beans/Observable;Ljavafx/beans/value/ObservableNumberValue;Ljavafx/beans/value/ObservableNumberValue;)V
     126: areturn

  public static javafx.beans.binding.NumberBinding max(javafx.beans.value.ObservableNumberValue, javafx.beans.value.ObservableNumberValue);
    Code:
       0: aload_0
       1: aload_1
       2: iconst_2
       3: anewarray     #79                 // class javafx/beans/Observable
       6: dup
       7: iconst_0
       8: aload_0
       9: aastore
      10: dup
      11: iconst_1
      12: aload_1
      13: aastore
      14: invokestatic  #168                // Method max:(Ljavafx/beans/value/ObservableNumberValue;Ljavafx/beans/value/ObservableNumberValue;[Ljavafx/beans/Observable;)Ljavafx/beans/binding/NumberBinding;
      17: areturn

  public static javafx.beans.binding.DoubleBinding max(javafx.beans.value.ObservableNumberValue, double);
    Code:
       0: aload_0
       1: dload_1
       2: invokestatic  #81                 // Method com/sun/javafx/binding/DoubleConstant.valueOf:(D)Lcom/sun/javafx/binding/DoubleConstant;
       5: iconst_1
       6: anewarray     #79                 // class javafx/beans/Observable
       9: dup
      10: iconst_0
      11: aload_0
      12: aastore
      13: invokestatic  #168                // Method max:(Ljavafx/beans/value/ObservableNumberValue;Ljavafx/beans/value/ObservableNumberValue;[Ljavafx/beans/Observable;)Ljavafx/beans/binding/NumberBinding;
      16: checkcast     #82                 // class javafx/beans/binding/DoubleBinding
      19: areturn

  public static javafx.beans.binding.DoubleBinding max(double, javafx.beans.value.ObservableNumberValue);
    Code:
       0: dload_0
       1: invokestatic  #81                 // Method com/sun/javafx/binding/DoubleConstant.valueOf:(D)Lcom/sun/javafx/binding/DoubleConstant;
       4: aload_2
       5: iconst_1
       6: anewarray     #79                 // class javafx/beans/Observable
       9: dup
      10: iconst_0
      11: aload_2
      12: aastore
      13: invokestatic  #168                // Method max:(Ljavafx/beans/value/ObservableNumberValue;Ljavafx/beans/value/ObservableNumberValue;[Ljavafx/beans/Observable;)Ljavafx/beans/binding/NumberBinding;
      16: checkcast     #82                 // class javafx/beans/binding/DoubleBinding
      19: areturn

  public static javafx.beans.binding.NumberBinding max(javafx.beans.value.ObservableNumberValue, float);
    Code:
       0: aload_0
       1: fload_1
       2: invokestatic  #83                 // Method com/sun/javafx/binding/FloatConstant.valueOf:(F)Lcom/sun/javafx/binding/FloatConstant;
       5: iconst_1
       6: anewarray     #79                 // class javafx/beans/Observable
       9: dup
      10: iconst_0
      11: aload_0
      12: aastore
      13: invokestatic  #168                // Method max:(Ljavafx/beans/value/ObservableNumberValue;Ljavafx/beans/value/ObservableNumberValue;[Ljavafx/beans/Observable;)Ljavafx/beans/binding/NumberBinding;
      16: areturn

  public static javafx.beans.binding.NumberBinding max(float, javafx.beans.value.ObservableNumberValue);
    Code:
       0: fload_0
       1: invokestatic  #83                 // Method com/sun/javafx/binding/FloatConstant.valueOf:(F)Lcom/sun/javafx/binding/FloatConstant;
       4: aload_1
       5: iconst_1
       6: anewarray     #79                 // class javafx/beans/Observable
       9: dup
      10: iconst_0
      11: aload_1
      12: aastore
      13: invokestatic  #168                // Method max:(Ljavafx/beans/value/ObservableNumberValue;Ljavafx/beans/value/ObservableNumberValue;[Ljavafx/beans/Observable;)Ljavafx/beans/binding/NumberBinding;
      16: areturn

  public static javafx.beans.binding.NumberBinding max(javafx.beans.value.ObservableNumberValue, long);
    Code:
       0: aload_0
       1: lload_1
       2: invokestatic  #84                 // Method com/sun/javafx/binding/LongConstant.valueOf:(J)Lcom/sun/javafx/binding/LongConstant;
       5: iconst_1
       6: anewarray     #79                 // class javafx/beans/Observable
       9: dup
      10: iconst_0
      11: aload_0
      12: aastore
      13: invokestatic  #168                // Method max:(Ljavafx/beans/value/ObservableNumberValue;Ljavafx/beans/value/ObservableNumberValue;[Ljavafx/beans/Observable;)Ljavafx/beans/binding/NumberBinding;
      16: areturn

  public static javafx.beans.binding.NumberBinding max(long, javafx.beans.value.ObservableNumberValue);
    Code:
       0: lload_0
       1: invokestatic  #84                 // Method com/sun/javafx/binding/LongConstant.valueOf:(J)Lcom/sun/javafx/binding/LongConstant;
       4: aload_2
       5: iconst_1
       6: anewarray     #79                 // class javafx/beans/Observable
       9: dup
      10: iconst_0
      11: aload_2
      12: aastore
      13: invokestatic  #168                // Method max:(Ljavafx/beans/value/ObservableNumberValue;Ljavafx/beans/value/ObservableNumberValue;[Ljavafx/beans/Observable;)Ljavafx/beans/binding/NumberBinding;
      16: areturn

  public static javafx.beans.binding.NumberBinding max(javafx.beans.value.ObservableNumberValue, int);
    Code:
       0: aload_0
       1: iload_1
       2: invokestatic  #85                 // Method com/sun/javafx/binding/IntegerConstant.valueOf:(I)Lcom/sun/javafx/binding/IntegerConstant;
       5: iconst_1
       6: anewarray     #79                 // class javafx/beans/Observable
       9: dup
      10: iconst_0
      11: aload_0
      12: aastore
      13: invokestatic  #168                // Method max:(Ljavafx/beans/value/ObservableNumberValue;Ljavafx/beans/value/ObservableNumberValue;[Ljavafx/beans/Observable;)Ljavafx/beans/binding/NumberBinding;
      16: areturn

  public static javafx.beans.binding.NumberBinding max(int, javafx.beans.value.ObservableNumberValue);
    Code:
       0: iload_0
       1: invokestatic  #85                 // Method com/sun/javafx/binding/IntegerConstant.valueOf:(I)Lcom/sun/javafx/binding/IntegerConstant;
       4: aload_1
       5: iconst_1
       6: anewarray     #79                 // class javafx/beans/Observable
       9: dup
      10: iconst_0
      11: aload_1
      12: aastore
      13: invokestatic  #168                // Method max:(Ljavafx/beans/value/ObservableNumberValue;Ljavafx/beans/value/ObservableNumberValue;[Ljavafx/beans/Observable;)Ljavafx/beans/binding/NumberBinding;
      16: areturn

  public static javafx.beans.binding.BooleanBinding and(javafx.beans.value.ObservableBooleanValue, javafx.beans.value.ObservableBooleanValue);
    Code:
       0: aload_0
       1: ifnull        8
       4: aload_1
       5: ifnonnull     18
       8: new           #53                 // class java/lang/NullPointerException
      11: dup
      12: ldc           #67                 // String Operands cannot be null.
      14: invokespecial #55                 // Method java/lang/NullPointerException."<init>":(Ljava/lang/String;)V
      17: athrow
      18: new           #169                // class javafx/beans/binding/Bindings$BooleanAndBinding
      21: dup
      22: aload_0
      23: aload_1
      24: invokespecial #170                // Method javafx/beans/binding/Bindings$BooleanAndBinding."<init>":(Ljavafx/beans/value/ObservableBooleanValue;Ljavafx/beans/value/ObservableBooleanValue;)V
      27: areturn

  public static javafx.beans.binding.BooleanBinding or(javafx.beans.value.ObservableBooleanValue, javafx.beans.value.ObservableBooleanValue);
    Code:
       0: aload_0
       1: ifnull        8
       4: aload_1
       5: ifnonnull     18
       8: new           #53                 // class java/lang/NullPointerException
      11: dup
      12: ldc           #67                 // String Operands cannot be null.
      14: invokespecial #55                 // Method java/lang/NullPointerException."<init>":(Ljava/lang/String;)V
      17: athrow
      18: new           #171                // class javafx/beans/binding/Bindings$BooleanOrBinding
      21: dup
      22: aload_0
      23: aload_1
      24: invokespecial #172                // Method javafx/beans/binding/Bindings$BooleanOrBinding."<init>":(Ljavafx/beans/value/ObservableBooleanValue;Ljavafx/beans/value/ObservableBooleanValue;)V
      27: areturn

  public static javafx.beans.binding.BooleanBinding not(javafx.beans.value.ObservableBooleanValue);
    Code:
       0: aload_0
       1: ifnonnull     14
       4: new           #53                 // class java/lang/NullPointerException
       7: dup
       8: ldc           #54                 // String Operand cannot be null.
      10: invokespecial #55                 // Method java/lang/NullPointerException."<init>":(Ljava/lang/String;)V
      13: athrow
      14: new           #173                // class javafx/beans/binding/Bindings$52
      17: dup
      18: aload_0
      19: invokespecial #174                // Method javafx/beans/binding/Bindings$52."<init>":(Ljavafx/beans/value/ObservableBooleanValue;)V
      22: areturn

  public static javafx.beans.binding.BooleanBinding equal(javafx.beans.value.ObservableBooleanValue, javafx.beans.value.ObservableBooleanValue);
    Code:
       0: aload_0
       1: ifnull        8
       4: aload_1
       5: ifnonnull     18
       8: new           #53                 // class java/lang/NullPointerException
      11: dup
      12: ldc           #67                 // String Operands cannot be null.
      14: invokespecial #55                 // Method java/lang/NullPointerException."<init>":(Ljava/lang/String;)V
      17: athrow
      18: new           #175                // class javafx/beans/binding/Bindings$53
      21: dup
      22: aload_0
      23: aload_1
      24: invokespecial #176                // Method javafx/beans/binding/Bindings$53."<init>":(Ljavafx/beans/value/ObservableBooleanValue;Ljavafx/beans/value/ObservableBooleanValue;)V
      27: areturn

  public static javafx.beans.binding.BooleanBinding notEqual(javafx.beans.value.ObservableBooleanValue, javafx.beans.value.ObservableBooleanValue);
    Code:
       0: aload_0
       1: ifnull        8
       4: aload_1
       5: ifnonnull     18
       8: new           #53                 // class java/lang/NullPointerException
      11: dup
      12: ldc           #67                 // String Operands cannot be null.
      14: invokespecial #55                 // Method java/lang/NullPointerException."<init>":(Ljava/lang/String;)V
      17: athrow
      18: new           #177                // class javafx/beans/binding/Bindings$54
      21: dup
      22: aload_0
      23: aload_1
      24: invokespecial #178                // Method javafx/beans/binding/Bindings$54."<init>":(Ljavafx/beans/value/ObservableBooleanValue;Ljavafx/beans/value/ObservableBooleanValue;)V
      27: areturn

  public static javafx.beans.binding.StringExpression convert(javafx.beans.value.ObservableValue<?>);
    Code:
       0: aload_0
       1: invokestatic  #179                // Method com/sun/javafx/binding/StringFormatter.convert:(Ljavafx/beans/value/ObservableValue;)Ljavafx/beans/binding/StringExpression;
       4: areturn

  public static javafx.beans.binding.StringExpression concat(java.lang.Object...);
    Code:
       0: aload_0
       1: invokestatic  #180                // Method com/sun/javafx/binding/StringFormatter.concat:([Ljava/lang/Object;)Ljavafx/beans/binding/StringExpression;
       4: areturn

  public static javafx.beans.binding.StringExpression format(java.lang.String, java.lang.Object...);
    Code:
       0: aload_0
       1: aload_1
       2: invokestatic  #181                // Method com/sun/javafx/binding/StringFormatter.format:(Ljava/lang/String;[Ljava/lang/Object;)Ljavafx/beans/binding/StringExpression;
       5: areturn

  public static javafx.beans.binding.StringExpression format(java.util.Locale, java.lang.String, java.lang.Object...);
    Code:
       0: aload_0
       1: aload_1
       2: aload_2
       3: invokestatic  #182                // Method com/sun/javafx/binding/StringFormatter.format:(Ljava/util/Locale;Ljava/lang/String;[Ljava/lang/Object;)Ljavafx/beans/binding/StringExpression;
       6: areturn

  private static java.lang.String getStringSafe(java.lang.String);
    Code:
       0: aload_0
       1: ifnonnull     9
       4: ldc           #183                // String
       6: goto          10
       9: aload_0
      10: areturn

  private static javafx.beans.binding.BooleanBinding equal(javafx.beans.value.ObservableStringValue, javafx.beans.value.ObservableStringValue, javafx.beans.Observable...);
    Code:
       0: aload_0
       1: ifnull        8
       4: aload_1
       5: ifnonnull     18
       8: new           #53                 // class java/lang/NullPointerException
      11: dup
      12: ldc           #67                 // String Operands cannot be null.
      14: invokespecial #55                 // Method java/lang/NullPointerException."<init>":(Ljava/lang/String;)V
      17: athrow
      18: getstatic     #68                 // Field $assertionsDisabled:Z
      21: ifne          41
      24: aload_2
      25: ifnull        33
      28: aload_2
      29: arraylength
      30: ifgt          41
      33: new           #69                 // class java/lang/AssertionError
      36: dup
      37: invokespecial #70                 // Method java/lang/AssertionError."<init>":()V
      40: athrow
      41: new           #184                // class javafx/beans/binding/Bindings$55
      44: dup
      45: aload_2
      46: aload_0
      47: aload_1
      48: invokespecial #185                // Method javafx/beans/binding/Bindings$55."<init>":([Ljavafx/beans/Observable;Ljavafx/beans/value/ObservableStringValue;Ljavafx/beans/value/ObservableStringValue;)V
      51: areturn

  public static javafx.beans.binding.BooleanBinding equal(javafx.beans.value.ObservableStringValue, javafx.beans.value.ObservableStringValue);
    Code:
       0: aload_0
       1: aload_1
       2: iconst_2
       3: anewarray     #79                 // class javafx/beans/Observable
       6: dup
       7: iconst_0
       8: aload_0
       9: aastore
      10: dup
      11: iconst_1
      12: aload_1
      13: aastore
      14: invokestatic  #186                // Method equal:(Ljavafx/beans/value/ObservableStringValue;Ljavafx/beans/value/ObservableStringValue;[Ljavafx/beans/Observable;)Ljavafx/beans/binding/BooleanBinding;
      17: areturn

  public static javafx.beans.binding.BooleanBinding equal(javafx.beans.value.ObservableStringValue, java.lang.String);
    Code:
       0: aload_0
       1: aload_1
       2: invokestatic  #187                // Method com/sun/javafx/binding/StringConstant.valueOf:(Ljava/lang/String;)Lcom/sun/javafx/binding/StringConstant;
       5: iconst_1
       6: anewarray     #79                 // class javafx/beans/Observable
       9: dup
      10: iconst_0
      11: aload_0
      12: aastore
      13: invokestatic  #186                // Method equal:(Ljavafx/beans/value/ObservableStringValue;Ljavafx/beans/value/ObservableStringValue;[Ljavafx/beans/Observable;)Ljavafx/beans/binding/BooleanBinding;
      16: areturn

  public static javafx.beans.binding.BooleanBinding equal(java.lang.String, javafx.beans.value.ObservableStringValue);
    Code:
       0: aload_0
       1: invokestatic  #187                // Method com/sun/javafx/binding/StringConstant.valueOf:(Ljava/lang/String;)Lcom/sun/javafx/binding/StringConstant;
       4: aload_1
       5: iconst_1
       6: anewarray     #79                 // class javafx/beans/Observable
       9: dup
      10: iconst_0
      11: aload_1
      12: aastore
      13: invokestatic  #186                // Method equal:(Ljavafx/beans/value/ObservableStringValue;Ljavafx/beans/value/ObservableStringValue;[Ljavafx/beans/Observable;)Ljavafx/beans/binding/BooleanBinding;
      16: areturn

  private static javafx.beans.binding.BooleanBinding notEqual(javafx.beans.value.ObservableStringValue, javafx.beans.value.ObservableStringValue, javafx.beans.Observable...);
    Code:
       0: aload_0
       1: ifnull        8
       4: aload_1
       5: ifnonnull     18
       8: new           #53                 // class java/lang/NullPointerException
      11: dup
      12: ldc           #67                 // String Operands cannot be null.
      14: invokespecial #55                 // Method java/lang/NullPointerException."<init>":(Ljava/lang/String;)V
      17: athrow
      18: getstatic     #68                 // Field $assertionsDisabled:Z
      21: ifne          41
      24: aload_2
      25: ifnull        33
      28: aload_2
      29: arraylength
      30: ifgt          41
      33: new           #69                 // class java/lang/AssertionError
      36: dup
      37: invokespecial #70                 // Method java/lang/AssertionError."<init>":()V
      40: athrow
      41: new           #188                // class javafx/beans/binding/Bindings$56
      44: dup
      45: aload_2
      46: aload_0
      47: aload_1
      48: invokespecial #189                // Method javafx/beans/binding/Bindings$56."<init>":([Ljavafx/beans/Observable;Ljavafx/beans/value/ObservableStringValue;Ljavafx/beans/value/ObservableStringValue;)V
      51: areturn

  public static javafx.beans.binding.BooleanBinding notEqual(javafx.beans.value.ObservableStringValue, javafx.beans.value.ObservableStringValue);
    Code:
       0: aload_0
       1: aload_1
       2: iconst_2
       3: anewarray     #79                 // class javafx/beans/Observable
       6: dup
       7: iconst_0
       8: aload_0
       9: aastore
      10: dup
      11: iconst_1
      12: aload_1
      13: aastore
      14: invokestatic  #190                // Method notEqual:(Ljavafx/beans/value/ObservableStringValue;Ljavafx/beans/value/ObservableStringValue;[Ljavafx/beans/Observable;)Ljavafx/beans/binding/BooleanBinding;
      17: areturn

  public static javafx.beans.binding.BooleanBinding notEqual(javafx.beans.value.ObservableStringValue, java.lang.String);
    Code:
       0: aload_0
       1: aload_1
       2: invokestatic  #187                // Method com/sun/javafx/binding/StringConstant.valueOf:(Ljava/lang/String;)Lcom/sun/javafx/binding/StringConstant;
       5: iconst_1
       6: anewarray     #79                 // class javafx/beans/Observable
       9: dup
      10: iconst_0
      11: aload_0
      12: aastore
      13: invokestatic  #190                // Method notEqual:(Ljavafx/beans/value/ObservableStringValue;Ljavafx/beans/value/ObservableStringValue;[Ljavafx/beans/Observable;)Ljavafx/beans/binding/BooleanBinding;
      16: areturn

  public static javafx.beans.binding.BooleanBinding notEqual(java.lang.String, javafx.beans.value.ObservableStringValue);
    Code:
       0: aload_0
       1: invokestatic  #187                // Method com/sun/javafx/binding/StringConstant.valueOf:(Ljava/lang/String;)Lcom/sun/javafx/binding/StringConstant;
       4: aload_1
       5: iconst_1
       6: anewarray     #79                 // class javafx/beans/Observable
       9: dup
      10: iconst_0
      11: aload_1
      12: aastore
      13: invokestatic  #190                // Method notEqual:(Ljavafx/beans/value/ObservableStringValue;Ljavafx/beans/value/ObservableStringValue;[Ljavafx/beans/Observable;)Ljavafx/beans/binding/BooleanBinding;
      16: areturn

  private static javafx.beans.binding.BooleanBinding equalIgnoreCase(javafx.beans.value.ObservableStringValue, javafx.beans.value.ObservableStringValue, javafx.beans.Observable...);
    Code:
       0: aload_0
       1: ifnull        8
       4: aload_1
       5: ifnonnull     18
       8: new           #53                 // class java/lang/NullPointerException
      11: dup
      12: ldc           #67                 // String Operands cannot be null.
      14: invokespecial #55                 // Method java/lang/NullPointerException."<init>":(Ljava/lang/String;)V
      17: athrow
      18: getstatic     #68                 // Field $assertionsDisabled:Z
      21: ifne          41
      24: aload_2
      25: ifnull        33
      28: aload_2
      29: arraylength
      30: ifgt          41
      33: new           #69                 // class java/lang/AssertionError
      36: dup
      37: invokespecial #70                 // Method java/lang/AssertionError."<init>":()V
      40: athrow
      41: new           #191                // class javafx/beans/binding/Bindings$57
      44: dup
      45: aload_2
      46: aload_0
      47: aload_1
      48: invokespecial #192                // Method javafx/beans/binding/Bindings$57."<init>":([Ljavafx/beans/Observable;Ljavafx/beans/value/ObservableStringValue;Ljavafx/beans/value/ObservableStringValue;)V
      51: areturn

  public static javafx.beans.binding.BooleanBinding equalIgnoreCase(javafx.beans.value.ObservableStringValue, javafx.beans.value.ObservableStringValue);
    Code:
       0: aload_0
       1: aload_1
       2: iconst_2
       3: anewarray     #79                 // class javafx/beans/Observable
       6: dup
       7: iconst_0
       8: aload_0
       9: aastore
      10: dup
      11: iconst_1
      12: aload_1
      13: aastore
      14: invokestatic  #193                // Method equalIgnoreCase:(Ljavafx/beans/value/ObservableStringValue;Ljavafx/beans/value/ObservableStringValue;[Ljavafx/beans/Observable;)Ljavafx/beans/binding/BooleanBinding;
      17: areturn

  public static javafx.beans.binding.BooleanBinding equalIgnoreCase(javafx.beans.value.ObservableStringValue, java.lang.String);
    Code:
       0: aload_0
       1: aload_1
       2: invokestatic  #187                // Method com/sun/javafx/binding/StringConstant.valueOf:(Ljava/lang/String;)Lcom/sun/javafx/binding/StringConstant;
       5: iconst_1
       6: anewarray     #79                 // class javafx/beans/Observable
       9: dup
      10: iconst_0
      11: aload_0
      12: aastore
      13: invokestatic  #193                // Method equalIgnoreCase:(Ljavafx/beans/value/ObservableStringValue;Ljavafx/beans/value/ObservableStringValue;[Ljavafx/beans/Observable;)Ljavafx/beans/binding/BooleanBinding;
      16: areturn

  public static javafx.beans.binding.BooleanBinding equalIgnoreCase(java.lang.String, javafx.beans.value.ObservableStringValue);
    Code:
       0: aload_0
       1: invokestatic  #187                // Method com/sun/javafx/binding/StringConstant.valueOf:(Ljava/lang/String;)Lcom/sun/javafx/binding/StringConstant;
       4: aload_1
       5: iconst_1
       6: anewarray     #79                 // class javafx/beans/Observable
       9: dup
      10: iconst_0
      11: aload_1
      12: aastore
      13: invokestatic  #193                // Method equalIgnoreCase:(Ljavafx/beans/value/ObservableStringValue;Ljavafx/beans/value/ObservableStringValue;[Ljavafx/beans/Observable;)Ljavafx/beans/binding/BooleanBinding;
      16: areturn

  private static javafx.beans.binding.BooleanBinding notEqualIgnoreCase(javafx.beans.value.ObservableStringValue, javafx.beans.value.ObservableStringValue, javafx.beans.Observable...);
    Code:
       0: aload_0
       1: ifnull        8
       4: aload_1
       5: ifnonnull     18
       8: new           #53                 // class java/lang/NullPointerException
      11: dup
      12: ldc           #67                 // String Operands cannot be null.
      14: invokespecial #55                 // Method java/lang/NullPointerException."<init>":(Ljava/lang/String;)V
      17: athrow
      18: getstatic     #68                 // Field $assertionsDisabled:Z
      21: ifne          41
      24: aload_2
      25: ifnull        33
      28: aload_2
      29: arraylength
      30: ifgt          41
      33: new           #69                 // class java/lang/AssertionError
      36: dup
      37: invokespecial #70                 // Method java/lang/AssertionError."<init>":()V
      40: athrow
      41: new           #194                // class javafx/beans/binding/Bindings$58
      44: dup
      45: aload_2
      46: aload_0
      47: aload_1
      48: invokespecial #195                // Method javafx/beans/binding/Bindings$58."<init>":([Ljavafx/beans/Observable;Ljavafx/beans/value/ObservableStringValue;Ljavafx/beans/value/ObservableStringValue;)V
      51: areturn

  public static javafx.beans.binding.BooleanBinding notEqualIgnoreCase(javafx.beans.value.ObservableStringValue, javafx.beans.value.ObservableStringValue);
    Code:
       0: aload_0
       1: aload_1
       2: iconst_2
       3: anewarray     #79                 // class javafx/beans/Observable
       6: dup
       7: iconst_0
       8: aload_0
       9: aastore
      10: dup
      11: iconst_1
      12: aload_1
      13: aastore
      14: invokestatic  #196                // Method notEqualIgnoreCase:(Ljavafx/beans/value/ObservableStringValue;Ljavafx/beans/value/ObservableStringValue;[Ljavafx/beans/Observable;)Ljavafx/beans/binding/BooleanBinding;
      17: areturn

  public static javafx.beans.binding.BooleanBinding notEqualIgnoreCase(javafx.beans.value.ObservableStringValue, java.lang.String);
    Code:
       0: aload_0
       1: aload_1
       2: invokestatic  #187                // Method com/sun/javafx/binding/StringConstant.valueOf:(Ljava/lang/String;)Lcom/sun/javafx/binding/StringConstant;
       5: iconst_1
       6: anewarray     #79                 // class javafx/beans/Observable
       9: dup
      10: iconst_0
      11: aload_0
      12: aastore
      13: invokestatic  #196                // Method notEqualIgnoreCase:(Ljavafx/beans/value/ObservableStringValue;Ljavafx/beans/value/ObservableStringValue;[Ljavafx/beans/Observable;)Ljavafx/beans/binding/BooleanBinding;
      16: areturn

  public static javafx.beans.binding.BooleanBinding notEqualIgnoreCase(java.lang.String, javafx.beans.value.ObservableStringValue);
    Code:
       0: aload_0
       1: invokestatic  #187                // Method com/sun/javafx/binding/StringConstant.valueOf:(Ljava/lang/String;)Lcom/sun/javafx/binding/StringConstant;
       4: aload_1
       5: iconst_1
       6: anewarray     #79                 // class javafx/beans/Observable
       9: dup
      10: iconst_0
      11: aload_1
      12: aastore
      13: invokestatic  #196                // Method notEqualIgnoreCase:(Ljavafx/beans/value/ObservableStringValue;Ljavafx/beans/value/ObservableStringValue;[Ljavafx/beans/Observable;)Ljavafx/beans/binding/BooleanBinding;
      16: areturn

  private static javafx.beans.binding.BooleanBinding greaterThan(javafx.beans.value.ObservableStringValue, javafx.beans.value.ObservableStringValue, javafx.beans.Observable...);
    Code:
       0: aload_0
       1: ifnull        8
       4: aload_1
       5: ifnonnull     18
       8: new           #53                 // class java/lang/NullPointerException
      11: dup
      12: ldc           #67                 // String Operands cannot be null.
      14: invokespecial #55                 // Method java/lang/NullPointerException."<init>":(Ljava/lang/String;)V
      17: athrow
      18: getstatic     #68                 // Field $assertionsDisabled:Z
      21: ifne          41
      24: aload_2
      25: ifnull        33
      28: aload_2
      29: arraylength
      30: ifgt          41
      33: new           #69                 // class java/lang/AssertionError
      36: dup
      37: invokespecial #70                 // Method java/lang/AssertionError."<init>":()V
      40: athrow
      41: new           #197                // class javafx/beans/binding/Bindings$59
      44: dup
      45: aload_2
      46: aload_0
      47: aload_1
      48: invokespecial #198                // Method javafx/beans/binding/Bindings$59."<init>":([Ljavafx/beans/Observable;Ljavafx/beans/value/ObservableStringValue;Ljavafx/beans/value/ObservableStringValue;)V
      51: areturn

  public static javafx.beans.binding.BooleanBinding greaterThan(javafx.beans.value.ObservableStringValue, javafx.beans.value.ObservableStringValue);
    Code:
       0: aload_0
       1: aload_1
       2: iconst_2
       3: anewarray     #79                 // class javafx/beans/Observable
       6: dup
       7: iconst_0
       8: aload_0
       9: aastore
      10: dup
      11: iconst_1
      12: aload_1
      13: aastore
      14: invokestatic  #199                // Method greaterThan:(Ljavafx/beans/value/ObservableStringValue;Ljavafx/beans/value/ObservableStringValue;[Ljavafx/beans/Observable;)Ljavafx/beans/binding/BooleanBinding;
      17: areturn

  public static javafx.beans.binding.BooleanBinding greaterThan(javafx.beans.value.ObservableStringValue, java.lang.String);
    Code:
       0: aload_0
       1: aload_1
       2: invokestatic  #187                // Method com/sun/javafx/binding/StringConstant.valueOf:(Ljava/lang/String;)Lcom/sun/javafx/binding/StringConstant;
       5: iconst_1
       6: anewarray     #79                 // class javafx/beans/Observable
       9: dup
      10: iconst_0
      11: aload_0
      12: aastore
      13: invokestatic  #199                // Method greaterThan:(Ljavafx/beans/value/ObservableStringValue;Ljavafx/beans/value/ObservableStringValue;[Ljavafx/beans/Observable;)Ljavafx/beans/binding/BooleanBinding;
      16: areturn

  public static javafx.beans.binding.BooleanBinding greaterThan(java.lang.String, javafx.beans.value.ObservableStringValue);
    Code:
       0: aload_0
       1: invokestatic  #187                // Method com/sun/javafx/binding/StringConstant.valueOf:(Ljava/lang/String;)Lcom/sun/javafx/binding/StringConstant;
       4: aload_1
       5: iconst_1
       6: anewarray     #79                 // class javafx/beans/Observable
       9: dup
      10: iconst_0
      11: aload_1
      12: aastore
      13: invokestatic  #199                // Method greaterThan:(Ljavafx/beans/value/ObservableStringValue;Ljavafx/beans/value/ObservableStringValue;[Ljavafx/beans/Observable;)Ljavafx/beans/binding/BooleanBinding;
      16: areturn

  private static javafx.beans.binding.BooleanBinding lessThan(javafx.beans.value.ObservableStringValue, javafx.beans.value.ObservableStringValue, javafx.beans.Observable...);
    Code:
       0: aload_1
       1: aload_0
       2: aload_2
       3: invokestatic  #199                // Method greaterThan:(Ljavafx/beans/value/ObservableStringValue;Ljavafx/beans/value/ObservableStringValue;[Ljavafx/beans/Observable;)Ljavafx/beans/binding/BooleanBinding;
       6: areturn

  public static javafx.beans.binding.BooleanBinding lessThan(javafx.beans.value.ObservableStringValue, javafx.beans.value.ObservableStringValue);
    Code:
       0: aload_0
       1: aload_1
       2: iconst_2
       3: anewarray     #79                 // class javafx/beans/Observable
       6: dup
       7: iconst_0
       8: aload_0
       9: aastore
      10: dup
      11: iconst_1
      12: aload_1
      13: aastore
      14: invokestatic  #200                // Method lessThan:(Ljavafx/beans/value/ObservableStringValue;Ljavafx/beans/value/ObservableStringValue;[Ljavafx/beans/Observable;)Ljavafx/beans/binding/BooleanBinding;
      17: areturn

  public static javafx.beans.binding.BooleanBinding lessThan(javafx.beans.value.ObservableStringValue, java.lang.String);
    Code:
       0: aload_0
       1: aload_1
       2: invokestatic  #187                // Method com/sun/javafx/binding/StringConstant.valueOf:(Ljava/lang/String;)Lcom/sun/javafx/binding/StringConstant;
       5: iconst_1
       6: anewarray     #79                 // class javafx/beans/Observable
       9: dup
      10: iconst_0
      11: aload_0
      12: aastore
      13: invokestatic  #200                // Method lessThan:(Ljavafx/beans/value/ObservableStringValue;Ljavafx/beans/value/ObservableStringValue;[Ljavafx/beans/Observable;)Ljavafx/beans/binding/BooleanBinding;
      16: areturn

  public static javafx.beans.binding.BooleanBinding lessThan(java.lang.String, javafx.beans.value.ObservableStringValue);
    Code:
       0: aload_0
       1: invokestatic  #187                // Method com/sun/javafx/binding/StringConstant.valueOf:(Ljava/lang/String;)Lcom/sun/javafx/binding/StringConstant;
       4: aload_1
       5: iconst_1
       6: anewarray     #79                 // class javafx/beans/Observable
       9: dup
      10: iconst_0
      11: aload_1
      12: aastore
      13: invokestatic  #200                // Method lessThan:(Ljavafx/beans/value/ObservableStringValue;Ljavafx/beans/value/ObservableStringValue;[Ljavafx/beans/Observable;)Ljavafx/beans/binding/BooleanBinding;
      16: areturn

  private static javafx.beans.binding.BooleanBinding greaterThanOrEqual(javafx.beans.value.ObservableStringValue, javafx.beans.value.ObservableStringValue, javafx.beans.Observable...);
    Code:
       0: aload_0
       1: ifnull        8
       4: aload_1
       5: ifnonnull     18
       8: new           #53                 // class java/lang/NullPointerException
      11: dup
      12: ldc           #67                 // String Operands cannot be null.
      14: invokespecial #55                 // Method java/lang/NullPointerException."<init>":(Ljava/lang/String;)V
      17: athrow
      18: getstatic     #68                 // Field $assertionsDisabled:Z
      21: ifne          41
      24: aload_2
      25: ifnull        33
      28: aload_2
      29: arraylength
      30: ifgt          41
      33: new           #69                 // class java/lang/AssertionError
      36: dup
      37: invokespecial #70                 // Method java/lang/AssertionError."<init>":()V
      40: athrow
      41: new           #201                // class javafx/beans/binding/Bindings$60
      44: dup
      45: aload_2
      46: aload_0
      47: aload_1
      48: invokespecial #202                // Method javafx/beans/binding/Bindings$60."<init>":([Ljavafx/beans/Observable;Ljavafx/beans/value/ObservableStringValue;Ljavafx/beans/value/ObservableStringValue;)V
      51: areturn

  public static javafx.beans.binding.BooleanBinding greaterThanOrEqual(javafx.beans.value.ObservableStringValue, javafx.beans.value.ObservableStringValue);
    Code:
       0: aload_0
       1: aload_1
       2: iconst_2
       3: anewarray     #79                 // class javafx/beans/Observable
       6: dup
       7: iconst_0
       8: aload_0
       9: aastore
      10: dup
      11: iconst_1
      12: aload_1
      13: aastore
      14: invokestatic  #203                // Method greaterThanOrEqual:(Ljavafx/beans/value/ObservableStringValue;Ljavafx/beans/value/ObservableStringValue;[Ljavafx/beans/Observable;)Ljavafx/beans/binding/BooleanBinding;
      17: areturn

  public static javafx.beans.binding.BooleanBinding greaterThanOrEqual(javafx.beans.value.ObservableStringValue, java.lang.String);
    Code:
       0: aload_0
       1: aload_1
       2: invokestatic  #187                // Method com/sun/javafx/binding/StringConstant.valueOf:(Ljava/lang/String;)Lcom/sun/javafx/binding/StringConstant;
       5: iconst_1
       6: anewarray     #79                 // class javafx/beans/Observable
       9: dup
      10: iconst_0
      11: aload_0
      12: aastore
      13: invokestatic  #203                // Method greaterThanOrEqual:(Ljavafx/beans/value/ObservableStringValue;Ljavafx/beans/value/ObservableStringValue;[Ljavafx/beans/Observable;)Ljavafx/beans/binding/BooleanBinding;
      16: areturn

  public static javafx.beans.binding.BooleanBinding greaterThanOrEqual(java.lang.String, javafx.beans.value.ObservableStringValue);
    Code:
       0: aload_0
       1: invokestatic  #187                // Method com/sun/javafx/binding/StringConstant.valueOf:(Ljava/lang/String;)Lcom/sun/javafx/binding/StringConstant;
       4: aload_1
       5: iconst_1
       6: anewarray     #79                 // class javafx/beans/Observable
       9: dup
      10: iconst_0
      11: aload_1
      12: aastore
      13: invokestatic  #203                // Method greaterThanOrEqual:(Ljavafx/beans/value/ObservableStringValue;Ljavafx/beans/value/ObservableStringValue;[Ljavafx/beans/Observable;)Ljavafx/beans/binding/BooleanBinding;
      16: areturn

  private static javafx.beans.binding.BooleanBinding lessThanOrEqual(javafx.beans.value.ObservableStringValue, javafx.beans.value.ObservableStringValue, javafx.beans.Observable...);
    Code:
       0: aload_1
       1: aload_0
       2: aload_2
       3: invokestatic  #203                // Method greaterThanOrEqual:(Ljavafx/beans/value/ObservableStringValue;Ljavafx/beans/value/ObservableStringValue;[Ljavafx/beans/Observable;)Ljavafx/beans/binding/BooleanBinding;
       6: areturn

  public static javafx.beans.binding.BooleanBinding lessThanOrEqual(javafx.beans.value.ObservableStringValue, javafx.beans.value.ObservableStringValue);
    Code:
       0: aload_0
       1: aload_1
       2: iconst_2
       3: anewarray     #79                 // class javafx/beans/Observable
       6: dup
       7: iconst_0
       8: aload_0
       9: aastore
      10: dup
      11: iconst_1
      12: aload_1
      13: aastore
      14: invokestatic  #204                // Method lessThanOrEqual:(Ljavafx/beans/value/ObservableStringValue;Ljavafx/beans/value/ObservableStringValue;[Ljavafx/beans/Observable;)Ljavafx/beans/binding/BooleanBinding;
      17: areturn

  public static javafx.beans.binding.BooleanBinding lessThanOrEqual(javafx.beans.value.ObservableStringValue, java.lang.String);
    Code:
       0: aload_0
       1: aload_1
       2: invokestatic  #187                // Method com/sun/javafx/binding/StringConstant.valueOf:(Ljava/lang/String;)Lcom/sun/javafx/binding/StringConstant;
       5: iconst_1
       6: anewarray     #79                 // class javafx/beans/Observable
       9: dup
      10: iconst_0
      11: aload_0
      12: aastore
      13: invokestatic  #204                // Method lessThanOrEqual:(Ljavafx/beans/value/ObservableStringValue;Ljavafx/beans/value/ObservableStringValue;[Ljavafx/beans/Observable;)Ljavafx/beans/binding/BooleanBinding;
      16: areturn

  public static javafx.beans.binding.BooleanBinding lessThanOrEqual(java.lang.String, javafx.beans.value.ObservableStringValue);
    Code:
       0: aload_0
       1: invokestatic  #187                // Method com/sun/javafx/binding/StringConstant.valueOf:(Ljava/lang/String;)Lcom/sun/javafx/binding/StringConstant;
       4: aload_1
       5: iconst_1
       6: anewarray     #79                 // class javafx/beans/Observable
       9: dup
      10: iconst_0
      11: aload_1
      12: aastore
      13: invokestatic  #204                // Method lessThanOrEqual:(Ljavafx/beans/value/ObservableStringValue;Ljavafx/beans/value/ObservableStringValue;[Ljavafx/beans/Observable;)Ljavafx/beans/binding/BooleanBinding;
      16: areturn

  public static javafx.beans.binding.IntegerBinding length(javafx.beans.value.ObservableStringValue);
    Code:
       0: aload_0
       1: ifnonnull     14
       4: new           #53                 // class java/lang/NullPointerException
       7: dup
       8: ldc           #205                // String Operand cannot be null
      10: invokespecial #55                 // Method java/lang/NullPointerException."<init>":(Ljava/lang/String;)V
      13: athrow
      14: new           #206                // class javafx/beans/binding/Bindings$61
      17: dup
      18: aload_0
      19: invokespecial #207                // Method javafx/beans/binding/Bindings$61."<init>":(Ljavafx/beans/value/ObservableStringValue;)V
      22: areturn

  public static javafx.beans.binding.BooleanBinding isEmpty(javafx.beans.value.ObservableStringValue);
    Code:
       0: aload_0
       1: ifnonnull     14
       4: new           #53                 // class java/lang/NullPointerException
       7: dup
       8: ldc           #205                // String Operand cannot be null
      10: invokespecial #55                 // Method java/lang/NullPointerException."<init>":(Ljava/lang/String;)V
      13: athrow
      14: new           #208                // class javafx/beans/binding/Bindings$62
      17: dup
      18: aload_0
      19: invokespecial #209                // Method javafx/beans/binding/Bindings$62."<init>":(Ljavafx/beans/value/ObservableStringValue;)V
      22: areturn

  public static javafx.beans.binding.BooleanBinding isNotEmpty(javafx.beans.value.ObservableStringValue);
    Code:
       0: aload_0
       1: ifnonnull     14
       4: new           #53                 // class java/lang/NullPointerException
       7: dup
       8: ldc           #205                // String Operand cannot be null
      10: invokespecial #55                 // Method java/lang/NullPointerException."<init>":(Ljava/lang/String;)V
      13: athrow
      14: new           #210                // class javafx/beans/binding/Bindings$63
      17: dup
      18: aload_0
      19: invokespecial #211                // Method javafx/beans/binding/Bindings$63."<init>":(Ljavafx/beans/value/ObservableStringValue;)V
      22: areturn

  private static javafx.beans.binding.BooleanBinding equal(javafx.beans.value.ObservableObjectValue<?>, javafx.beans.value.ObservableObjectValue<?>, javafx.beans.Observable...);
    Code:
       0: aload_0
       1: ifnull        8
       4: aload_1
       5: ifnonnull     18
       8: new           #53                 // class java/lang/NullPointerException
      11: dup
      12: ldc           #67                 // String Operands cannot be null.
      14: invokespecial #55                 // Method java/lang/NullPointerException."<init>":(Ljava/lang/String;)V
      17: athrow
      18: getstatic     #68                 // Field $assertionsDisabled:Z
      21: ifne          41
      24: aload_2
      25: ifnull        33
      28: aload_2
      29: arraylength
      30: ifgt          41
      33: new           #69                 // class java/lang/AssertionError
      36: dup
      37: invokespecial #70                 // Method java/lang/AssertionError."<init>":()V
      40: athrow
      41: new           #212                // class javafx/beans/binding/Bindings$64
      44: dup
      45: aload_2
      46: aload_0
      47: aload_1
      48: invokespecial #213                // Method javafx/beans/binding/Bindings$64."<init>":([Ljavafx/beans/Observable;Ljavafx/beans/value/ObservableObjectValue;Ljavafx/beans/value/ObservableObjectValue;)V
      51: areturn

  public static javafx.beans.binding.BooleanBinding equal(javafx.beans.value.ObservableObjectValue<?>, javafx.beans.value.ObservableObjectValue<?>);
    Code:
       0: aload_0
       1: aload_1
       2: iconst_2
       3: anewarray     #79                 // class javafx/beans/Observable
       6: dup
       7: iconst_0
       8: aload_0
       9: aastore
      10: dup
      11: iconst_1
      12: aload_1
      13: aastore
      14: invokestatic  #214                // Method equal:(Ljavafx/beans/value/ObservableObjectValue;Ljavafx/beans/value/ObservableObjectValue;[Ljavafx/beans/Observable;)Ljavafx/beans/binding/BooleanBinding;
      17: areturn

  public static javafx.beans.binding.BooleanBinding equal(javafx.beans.value.ObservableObjectValue<?>, java.lang.Object);
    Code:
       0: aload_0
       1: aload_1
       2: invokestatic  #215                // Method com/sun/javafx/binding/ObjectConstant.valueOf:(Ljava/lang/Object;)Lcom/sun/javafx/binding/ObjectConstant;
       5: iconst_1
       6: anewarray     #79                 // class javafx/beans/Observable
       9: dup
      10: iconst_0
      11: aload_0
      12: aastore
      13: invokestatic  #214                // Method equal:(Ljavafx/beans/value/ObservableObjectValue;Ljavafx/beans/value/ObservableObjectValue;[Ljavafx/beans/Observable;)Ljavafx/beans/binding/BooleanBinding;
      16: areturn

  public static javafx.beans.binding.BooleanBinding equal(java.lang.Object, javafx.beans.value.ObservableObjectValue<?>);
    Code:
       0: aload_0
       1: invokestatic  #215                // Method com/sun/javafx/binding/ObjectConstant.valueOf:(Ljava/lang/Object;)Lcom/sun/javafx/binding/ObjectConstant;
       4: aload_1
       5: iconst_1
       6: anewarray     #79                 // class javafx/beans/Observable
       9: dup
      10: iconst_0
      11: aload_1
      12: aastore
      13: invokestatic  #214                // Method equal:(Ljavafx/beans/value/ObservableObjectValue;Ljavafx/beans/value/ObservableObjectValue;[Ljavafx/beans/Observable;)Ljavafx/beans/binding/BooleanBinding;
      16: areturn

  private static javafx.beans.binding.BooleanBinding notEqual(javafx.beans.value.ObservableObjectValue<?>, javafx.beans.value.ObservableObjectValue<?>, javafx.beans.Observable...);
    Code:
       0: aload_0
       1: ifnull        8
       4: aload_1
       5: ifnonnull     18
       8: new           #53                 // class java/lang/NullPointerException
      11: dup
      12: ldc           #67                 // String Operands cannot be null.
      14: invokespecial #55                 // Method java/lang/NullPointerException."<init>":(Ljava/lang/String;)V
      17: athrow
      18: getstatic     #68                 // Field $assertionsDisabled:Z
      21: ifne          41
      24: aload_2
      25: ifnull        33
      28: aload_2
      29: arraylength
      30: ifgt          41
      33: new           #69                 // class java/lang/AssertionError
      36: dup
      37: invokespecial #70                 // Method java/lang/AssertionError."<init>":()V
      40: athrow
      41: new           #216                // class javafx/beans/binding/Bindings$65
      44: dup
      45: aload_2
      46: aload_0
      47: aload_1
      48: invokespecial #217                // Method javafx/beans/binding/Bindings$65."<init>":([Ljavafx/beans/Observable;Ljavafx/beans/value/ObservableObjectValue;Ljavafx/beans/value/ObservableObjectValue;)V
      51: areturn

  public static javafx.beans.binding.BooleanBinding notEqual(javafx.beans.value.ObservableObjectValue<?>, javafx.beans.value.ObservableObjectValue<?>);
    Code:
       0: aload_0
       1: aload_1
       2: iconst_2
       3: anewarray     #79                 // class javafx/beans/Observable
       6: dup
       7: iconst_0
       8: aload_0
       9: aastore
      10: dup
      11: iconst_1
      12: aload_1
      13: aastore
      14: invokestatic  #218                // Method notEqual:(Ljavafx/beans/value/ObservableObjectValue;Ljavafx/beans/value/ObservableObjectValue;[Ljavafx/beans/Observable;)Ljavafx/beans/binding/BooleanBinding;
      17: areturn

  public static javafx.beans.binding.BooleanBinding notEqual(javafx.beans.value.ObservableObjectValue<?>, java.lang.Object);
    Code:
       0: aload_0
       1: aload_1
       2: invokestatic  #215                // Method com/sun/javafx/binding/ObjectConstant.valueOf:(Ljava/lang/Object;)Lcom/sun/javafx/binding/ObjectConstant;
       5: iconst_1
       6: anewarray     #79                 // class javafx/beans/Observable
       9: dup
      10: iconst_0
      11: aload_0
      12: aastore
      13: invokestatic  #218                // Method notEqual:(Ljavafx/beans/value/ObservableObjectValue;Ljavafx/beans/value/ObservableObjectValue;[Ljavafx/beans/Observable;)Ljavafx/beans/binding/BooleanBinding;
      16: areturn

  public static javafx.beans.binding.BooleanBinding notEqual(java.lang.Object, javafx.beans.value.ObservableObjectValue<?>);
    Code:
       0: aload_0
       1: invokestatic  #215                // Method com/sun/javafx/binding/ObjectConstant.valueOf:(Ljava/lang/Object;)Lcom/sun/javafx/binding/ObjectConstant;
       4: aload_1
       5: iconst_1
       6: anewarray     #79                 // class javafx/beans/Observable
       9: dup
      10: iconst_0
      11: aload_1
      12: aastore
      13: invokestatic  #218                // Method notEqual:(Ljavafx/beans/value/ObservableObjectValue;Ljavafx/beans/value/ObservableObjectValue;[Ljavafx/beans/Observable;)Ljavafx/beans/binding/BooleanBinding;
      16: areturn

  public static javafx.beans.binding.BooleanBinding isNull(javafx.beans.value.ObservableObjectValue<?>);
    Code:
       0: aload_0
       1: ifnonnull     14
       4: new           #53                 // class java/lang/NullPointerException
       7: dup
       8: ldc           #54                 // String Operand cannot be null.
      10: invokespecial #55                 // Method java/lang/NullPointerException."<init>":(Ljava/lang/String;)V
      13: athrow
      14: new           #219                // class javafx/beans/binding/Bindings$66
      17: dup
      18: aload_0
      19: invokespecial #220                // Method javafx/beans/binding/Bindings$66."<init>":(Ljavafx/beans/value/ObservableObjectValue;)V
      22: areturn

  public static javafx.beans.binding.BooleanBinding isNotNull(javafx.beans.value.ObservableObjectValue<?>);
    Code:
       0: aload_0
       1: ifnonnull     14
       4: new           #53                 // class java/lang/NullPointerException
       7: dup
       8: ldc           #54                 // String Operand cannot be null.
      10: invokespecial #55                 // Method java/lang/NullPointerException."<init>":(Ljava/lang/String;)V
      13: athrow
      14: new           #221                // class javafx/beans/binding/Bindings$67
      17: dup
      18: aload_0
      19: invokespecial #222                // Method javafx/beans/binding/Bindings$67."<init>":(Ljavafx/beans/value/ObservableObjectValue;)V
      22: areturn

  public static <E> javafx.beans.binding.IntegerBinding size(javafx.collections.ObservableList<E>);
    Code:
       0: aload_0
       1: ifnonnull     14
       4: new           #53                 // class java/lang/NullPointerException
       7: dup
       8: ldc           #223                // String List cannot be null.
      10: invokespecial #55                 // Method java/lang/NullPointerException."<init>":(Ljava/lang/String;)V
      13: athrow
      14: new           #224                // class javafx/beans/binding/Bindings$68
      17: dup
      18: aload_0
      19: invokespecial #225                // Method javafx/beans/binding/Bindings$68."<init>":(Ljavafx/collections/ObservableList;)V
      22: areturn

  public static <E> javafx.beans.binding.BooleanBinding isEmpty(javafx.collections.ObservableList<E>);
    Code:
       0: aload_0
       1: ifnonnull     14
       4: new           #53                 // class java/lang/NullPointerException
       7: dup
       8: ldc           #223                // String List cannot be null.
      10: invokespecial #55                 // Method java/lang/NullPointerException."<init>":(Ljava/lang/String;)V
      13: athrow
      14: new           #226                // class javafx/beans/binding/Bindings$69
      17: dup
      18: aload_0
      19: invokespecial #227                // Method javafx/beans/binding/Bindings$69."<init>":(Ljavafx/collections/ObservableList;)V
      22: areturn

  public static <E> javafx.beans.binding.BooleanBinding isNotEmpty(javafx.collections.ObservableList<E>);
    Code:
       0: aload_0
       1: ifnonnull     14
       4: new           #53                 // class java/lang/NullPointerException
       7: dup
       8: ldc           #223                // String List cannot be null.
      10: invokespecial #55                 // Method java/lang/NullPointerException."<init>":(Ljava/lang/String;)V
      13: athrow
      14: new           #228                // class javafx/beans/binding/Bindings$70
      17: dup
      18: aload_0
      19: invokespecial #229                // Method javafx/beans/binding/Bindings$70."<init>":(Ljavafx/collections/ObservableList;)V
      22: areturn

  public static <E> javafx.beans.binding.ObjectBinding<E> valueAt(javafx.collections.ObservableList<E>, int);
    Code:
       0: aload_0
       1: ifnonnull     14
       4: new           #53                 // class java/lang/NullPointerException
       7: dup
       8: ldc           #223                // String List cannot be null.
      10: invokespecial #55                 // Method java/lang/NullPointerException."<init>":(Ljava/lang/String;)V
      13: athrow
      14: iload_1
      15: ifge          28
      18: new           #230                // class java/lang/IllegalArgumentException
      21: dup
      22: ldc           #231                // String Index cannot be negative
      24: invokespecial #232                // Method java/lang/IllegalArgumentException."<init>":(Ljava/lang/String;)V
      27: athrow
      28: new           #233                // class javafx/beans/binding/Bindings$71
      31: dup
      32: aload_0
      33: iload_1
      34: invokespecial #234                // Method javafx/beans/binding/Bindings$71."<init>":(Ljavafx/collections/ObservableList;I)V
      37: areturn

  public static <E> javafx.beans.binding.ObjectBinding<E> valueAt(javafx.collections.ObservableList<E>, javafx.beans.value.ObservableIntegerValue);
    Code:
       0: aload_0
       1: aload_1
       2: invokestatic  #235                // Method valueAt:(Ljavafx/collections/ObservableList;Ljavafx/beans/value/ObservableNumberValue;)Ljavafx/beans/binding/ObjectBinding;
       5: areturn

  public static <E> javafx.beans.binding.ObjectBinding<E> valueAt(javafx.collections.ObservableList<E>, javafx.beans.value.ObservableNumberValue);
    Code:
       0: aload_0
       1: ifnull        8
       4: aload_1
       5: ifnonnull     18
       8: new           #53                 // class java/lang/NullPointerException
      11: dup
      12: ldc           #67                 // String Operands cannot be null.
      14: invokespecial #55                 // Method java/lang/NullPointerException."<init>":(Ljava/lang/String;)V
      17: athrow
      18: new           #236                // class javafx/beans/binding/Bindings$72
      21: dup
      22: aload_0
      23: aload_1
      24: invokespecial #237                // Method javafx/beans/binding/Bindings$72."<init>":(Ljavafx/collections/ObservableList;Ljavafx/beans/value/ObservableNumberValue;)V
      27: areturn

  public static javafx.beans.binding.BooleanBinding booleanValueAt(javafx.collections.ObservableList<java.lang.Boolean>, int);
    Code:
       0: aload_0
       1: ifnonnull     14
       4: new           #53                 // class java/lang/NullPointerException
       7: dup
       8: ldc           #223                // String List cannot be null.
      10: invokespecial #55                 // Method java/lang/NullPointerException."<init>":(Ljava/lang/String;)V
      13: athrow
      14: iload_1
      15: ifge          28
      18: new           #230                // class java/lang/IllegalArgumentException
      21: dup
      22: ldc           #231                // String Index cannot be negative
      24: invokespecial #232                // Method java/lang/IllegalArgumentException."<init>":(Ljava/lang/String;)V
      27: athrow
      28: new           #238                // class javafx/beans/binding/Bindings$73
      31: dup
      32: aload_0
      33: iload_1
      34: invokespecial #239                // Method javafx/beans/binding/Bindings$73."<init>":(Ljavafx/collections/ObservableList;I)V
      37: areturn

  public static javafx.beans.binding.BooleanBinding booleanValueAt(javafx.collections.ObservableList<java.lang.Boolean>, javafx.beans.value.ObservableIntegerValue);
    Code:
       0: aload_0
       1: aload_1
       2: invokestatic  #240                // Method booleanValueAt:(Ljavafx/collections/ObservableList;Ljavafx/beans/value/ObservableNumberValue;)Ljavafx/beans/binding/BooleanBinding;
       5: areturn

  public static javafx.beans.binding.BooleanBinding booleanValueAt(javafx.collections.ObservableList<java.lang.Boolean>, javafx.beans.value.ObservableNumberValue);
    Code:
       0: aload_0
       1: ifnull        8
       4: aload_1
       5: ifnonnull     18
       8: new           #53                 // class java/lang/NullPointerException
      11: dup
      12: ldc           #67                 // String Operands cannot be null.
      14: invokespecial #55                 // Method java/lang/NullPointerException."<init>":(Ljava/lang/String;)V
      17: athrow
      18: new           #241                // class javafx/beans/binding/Bindings$74
      21: dup
      22: aload_0
      23: aload_1
      24: invokespecial #242                // Method javafx/beans/binding/Bindings$74."<init>":(Ljavafx/collections/ObservableList;Ljavafx/beans/value/ObservableNumberValue;)V
      27: areturn

  public static javafx.beans.binding.DoubleBinding doubleValueAt(javafx.collections.ObservableList<? extends java.lang.Number>, int);
    Code:
       0: aload_0
       1: ifnonnull     14
       4: new           #53                 // class java/lang/NullPointerException
       7: dup
       8: ldc           #223                // String List cannot be null.
      10: invokespecial #55                 // Method java/lang/NullPointerException."<init>":(Ljava/lang/String;)V
      13: athrow
      14: iload_1
      15: ifge          28
      18: new           #230                // class java/lang/IllegalArgumentException
      21: dup
      22: ldc           #231                // String Index cannot be negative
      24: invokespecial #232                // Method java/lang/IllegalArgumentException."<init>":(Ljava/lang/String;)V
      27: athrow
      28: new           #243                // class javafx/beans/binding/Bindings$75
      31: dup
      32: aload_0
      33: iload_1
      34: invokespecial #244                // Method javafx/beans/binding/Bindings$75."<init>":(Ljavafx/collections/ObservableList;I)V
      37: areturn

  public static javafx.beans.binding.DoubleBinding doubleValueAt(javafx.collections.ObservableList<? extends java.lang.Number>, javafx.beans.value.ObservableIntegerValue);
    Code:
       0: aload_0
       1: aload_1
       2: invokestatic  #245                // Method doubleValueAt:(Ljavafx/collections/ObservableList;Ljavafx/beans/value/ObservableNumberValue;)Ljavafx/beans/binding/DoubleBinding;
       5: areturn

  public static javafx.beans.binding.DoubleBinding doubleValueAt(javafx.collections.ObservableList<? extends java.lang.Number>, javafx.beans.value.ObservableNumberValue);
    Code:
       0: aload_0
       1: ifnull        8
       4: aload_1
       5: ifnonnull     18
       8: new           #53                 // class java/lang/NullPointerException
      11: dup
      12: ldc           #67                 // String Operands cannot be null.
      14: invokespecial #55                 // Method java/lang/NullPointerException."<init>":(Ljava/lang/String;)V
      17: athrow
      18: new           #246                // class javafx/beans/binding/Bindings$76
      21: dup
      22: aload_0
      23: aload_1
      24: invokespecial #247                // Method javafx/beans/binding/Bindings$76."<init>":(Ljavafx/collections/ObservableList;Ljavafx/beans/value/ObservableNumberValue;)V
      27: areturn

  public static javafx.beans.binding.FloatBinding floatValueAt(javafx.collections.ObservableList<? extends java.lang.Number>, int);
    Code:
       0: aload_0
       1: ifnonnull     14
       4: new           #53                 // class java/lang/NullPointerException
       7: dup
       8: ldc           #223                // String List cannot be null.
      10: invokespecial #55                 // Method java/lang/NullPointerException."<init>":(Ljava/lang/String;)V
      13: athrow
      14: iload_1
      15: ifge          28
      18: new           #230                // class java/lang/IllegalArgumentException
      21: dup
      22: ldc           #231                // String Index cannot be negative
      24: invokespecial #232                // Method java/lang/IllegalArgumentException."<init>":(Ljava/lang/String;)V
      27: athrow
      28: new           #248                // class javafx/beans/binding/Bindings$77
      31: dup
      32: aload_0
      33: iload_1
      34: invokespecial #249                // Method javafx/beans/binding/Bindings$77."<init>":(Ljavafx/collections/ObservableList;I)V
      37: areturn

  public static javafx.beans.binding.FloatBinding floatValueAt(javafx.collections.ObservableList<? extends java.lang.Number>, javafx.beans.value.ObservableIntegerValue);
    Code:
       0: aload_0
       1: aload_1
       2: invokestatic  #250                // Method floatValueAt:(Ljavafx/collections/ObservableList;Ljavafx/beans/value/ObservableNumberValue;)Ljavafx/beans/binding/FloatBinding;
       5: areturn

  public static javafx.beans.binding.FloatBinding floatValueAt(javafx.collections.ObservableList<? extends java.lang.Number>, javafx.beans.value.ObservableNumberValue);
    Code:
       0: aload_0
       1: ifnull        8
       4: aload_1
       5: ifnonnull     18
       8: new           #53                 // class java/lang/NullPointerException
      11: dup
      12: ldc           #67                 // String Operands cannot be null.
      14: invokespecial #55                 // Method java/lang/NullPointerException."<init>":(Ljava/lang/String;)V
      17: athrow
      18: new           #251                // class javafx/beans/binding/Bindings$78
      21: dup
      22: aload_0
      23: aload_1
      24: invokespecial #252                // Method javafx/beans/binding/Bindings$78."<init>":(Ljavafx/collections/ObservableList;Ljavafx/beans/value/ObservableNumberValue;)V
      27: areturn

  public static javafx.beans.binding.IntegerBinding integerValueAt(javafx.collections.ObservableList<? extends java.lang.Number>, int);
    Code:
       0: aload_0
       1: ifnonnull     14
       4: new           #53                 // class java/lang/NullPointerException
       7: dup
       8: ldc           #223                // String List cannot be null.
      10: invokespecial #55                 // Method java/lang/NullPointerException."<init>":(Ljava/lang/String;)V
      13: athrow
      14: iload_1
      15: ifge          28
      18: new           #230                // class java/lang/IllegalArgumentException
      21: dup
      22: ldc           #231                // String Index cannot be negative
      24: invokespecial #232                // Method java/lang/IllegalArgumentException."<init>":(Ljava/lang/String;)V
      27: athrow
      28: new           #253                // class javafx/beans/binding/Bindings$79
      31: dup
      32: aload_0
      33: iload_1
      34: invokespecial #254                // Method javafx/beans/binding/Bindings$79."<init>":(Ljavafx/collections/ObservableList;I)V
      37: areturn

  public static javafx.beans.binding.IntegerBinding integerValueAt(javafx.collections.ObservableList<? extends java.lang.Number>, javafx.beans.value.ObservableIntegerValue);
    Code:
       0: aload_0
       1: aload_1
       2: invokestatic  #255                // Method integerValueAt:(Ljavafx/collections/ObservableList;Ljavafx/beans/value/ObservableNumberValue;)Ljavafx/beans/binding/IntegerBinding;
       5: areturn

  public static javafx.beans.binding.IntegerBinding integerValueAt(javafx.collections.ObservableList<? extends java.lang.Number>, javafx.beans.value.ObservableNumberValue);
    Code:
       0: aload_0
       1: ifnull        8
       4: aload_1
       5: ifnonnull     18
       8: new           #53                 // class java/lang/NullPointerException
      11: dup
      12: ldc           #67                 // String Operands cannot be null.
      14: invokespecial #55                 // Method java/lang/NullPointerException."<init>":(Ljava/lang/String;)V
      17: athrow
      18: new           #256                // class javafx/beans/binding/Bindings$80
      21: dup
      22: aload_0
      23: aload_1
      24: invokespecial #257                // Method javafx/beans/binding/Bindings$80."<init>":(Ljavafx/collections/ObservableList;Ljavafx/beans/value/ObservableNumberValue;)V
      27: areturn

  public static javafx.beans.binding.LongBinding longValueAt(javafx.collections.ObservableList<? extends java.lang.Number>, int);
    Code:
       0: aload_0
       1: ifnonnull     14
       4: new           #53                 // class java/lang/NullPointerException
       7: dup
       8: ldc           #223                // String List cannot be null.
      10: invokespecial #55                 // Method java/lang/NullPointerException."<init>":(Ljava/lang/String;)V
      13: athrow
      14: iload_1
      15: ifge          28
      18: new           #230                // class java/lang/IllegalArgumentException
      21: dup
      22: ldc           #231                // String Index cannot be negative
      24: invokespecial #232                // Method java/lang/IllegalArgumentException."<init>":(Ljava/lang/String;)V
      27: athrow
      28: new           #258                // class javafx/beans/binding/Bindings$81
      31: dup
      32: aload_0
      33: iload_1
      34: invokespecial #259                // Method javafx/beans/binding/Bindings$81."<init>":(Ljavafx/collections/ObservableList;I)V
      37: areturn

  public static javafx.beans.binding.LongBinding longValueAt(javafx.collections.ObservableList<? extends java.lang.Number>, javafx.beans.value.ObservableIntegerValue);
    Code:
       0: aload_0
       1: aload_1
       2: invokestatic  #260                // Method longValueAt:(Ljavafx/collections/ObservableList;Ljavafx/beans/value/ObservableNumberValue;)Ljavafx/beans/binding/LongBinding;
       5: areturn

  public static javafx.beans.binding.LongBinding longValueAt(javafx.collections.ObservableList<? extends java.lang.Number>, javafx.beans.value.ObservableNumberValue);
    Code:
       0: aload_0
       1: ifnull        8
       4: aload_1
       5: ifnonnull     18
       8: new           #53                 // class java/lang/NullPointerException
      11: dup
      12: ldc           #67                 // String Operands cannot be null.
      14: invokespecial #55                 // Method java/lang/NullPointerException."<init>":(Ljava/lang/String;)V
      17: athrow
      18: new           #261                // class javafx/beans/binding/Bindings$82
      21: dup
      22: aload_0
      23: aload_1
      24: invokespecial #262                // Method javafx/beans/binding/Bindings$82."<init>":(Ljavafx/collections/ObservableList;Ljavafx/beans/value/ObservableNumberValue;)V
      27: areturn

  public static javafx.beans.binding.StringBinding stringValueAt(javafx.collections.ObservableList<java.lang.String>, int);
    Code:
       0: aload_0
       1: ifnonnull     14
       4: new           #53                 // class java/lang/NullPointerException
       7: dup
       8: ldc           #223                // String List cannot be null.
      10: invokespecial #55                 // Method java/lang/NullPointerException."<init>":(Ljava/lang/String;)V
      13: athrow
      14: iload_1
      15: ifge          28
      18: new           #230                // class java/lang/IllegalArgumentException
      21: dup
      22: ldc           #231                // String Index cannot be negative
      24: invokespecial #232                // Method java/lang/IllegalArgumentException."<init>":(Ljava/lang/String;)V
      27: athrow
      28: new           #263                // class javafx/beans/binding/Bindings$83
      31: dup
      32: aload_0
      33: iload_1
      34: invokespecial #264                // Method javafx/beans/binding/Bindings$83."<init>":(Ljavafx/collections/ObservableList;I)V
      37: areturn

  public static javafx.beans.binding.StringBinding stringValueAt(javafx.collections.ObservableList<java.lang.String>, javafx.beans.value.ObservableIntegerValue);
    Code:
       0: aload_0
       1: aload_1
       2: invokestatic  #265                // Method stringValueAt:(Ljavafx/collections/ObservableList;Ljavafx/beans/value/ObservableNumberValue;)Ljavafx/beans/binding/StringBinding;
       5: areturn

  public static javafx.beans.binding.StringBinding stringValueAt(javafx.collections.ObservableList<java.lang.String>, javafx.beans.value.ObservableNumberValue);
    Code:
       0: aload_0
       1: ifnull        8
       4: aload_1
       5: ifnonnull     18
       8: new           #53                 // class java/lang/NullPointerException
      11: dup
      12: ldc           #67                 // String Operands cannot be null.
      14: invokespecial #55                 // Method java/lang/NullPointerException."<init>":(Ljava/lang/String;)V
      17: athrow
      18: new           #266                // class javafx/beans/binding/Bindings$84
      21: dup
      22: aload_0
      23: aload_1
      24: invokespecial #267                // Method javafx/beans/binding/Bindings$84."<init>":(Ljavafx/collections/ObservableList;Ljavafx/beans/value/ObservableNumberValue;)V
      27: areturn

  public static <E> javafx.beans.binding.IntegerBinding size(javafx.collections.ObservableSet<E>);
    Code:
       0: aload_0
       1: ifnonnull     15
       4: new           #53                 // class java/lang/NullPointerException
       7: dup
       8: ldc_w         #268                // String Set cannot be null.
      11: invokespecial #55                 // Method java/lang/NullPointerException."<init>":(Ljava/lang/String;)V
      14: athrow
      15: new           #269                // class javafx/beans/binding/Bindings$85
      18: dup
      19: aload_0
      20: invokespecial #270                // Method javafx/beans/binding/Bindings$85."<init>":(Ljavafx/collections/ObservableSet;)V
      23: areturn

  public static <E> javafx.beans.binding.BooleanBinding isEmpty(javafx.collections.ObservableSet<E>);
    Code:
       0: aload_0
       1: ifnonnull     15
       4: new           #53                 // class java/lang/NullPointerException
       7: dup
       8: ldc_w         #268                // String Set cannot be null.
      11: invokespecial #55                 // Method java/lang/NullPointerException."<init>":(Ljava/lang/String;)V
      14: athrow
      15: new           #271                // class javafx/beans/binding/Bindings$86
      18: dup
      19: aload_0
      20: invokespecial #272                // Method javafx/beans/binding/Bindings$86."<init>":(Ljavafx/collections/ObservableSet;)V
      23: areturn

  public static <E> javafx.beans.binding.BooleanBinding isNotEmpty(javafx.collections.ObservableSet<E>);
    Code:
       0: aload_0
       1: ifnonnull     14
       4: new           #53                 // class java/lang/NullPointerException
       7: dup
       8: ldc           #223                // String List cannot be null.
      10: invokespecial #55                 // Method java/lang/NullPointerException."<init>":(Ljava/lang/String;)V
      13: athrow
      14: new           #273                // class javafx/beans/binding/Bindings$87
      17: dup
      18: aload_0
      19: invokespecial #274                // Method javafx/beans/binding/Bindings$87."<init>":(Ljavafx/collections/ObservableSet;)V
      22: areturn

  public static javafx.beans.binding.IntegerBinding size(javafx.collections.ObservableArray);
    Code:
       0: aload_0
       1: ifnonnull     15
       4: new           #53                 // class java/lang/NullPointerException
       7: dup
       8: ldc_w         #275                // String Array cannot be null.
      11: invokespecial #55                 // Method java/lang/NullPointerException."<init>":(Ljava/lang/String;)V
      14: athrow
      15: new           #276                // class javafx/beans/binding/Bindings$88
      18: dup
      19: aload_0
      20: invokespecial #277                // Method javafx/beans/binding/Bindings$88."<init>":(Ljavafx/collections/ObservableArray;)V
      23: areturn

  public static javafx.beans.binding.FloatBinding floatValueAt(javafx.collections.ObservableFloatArray, int);
    Code:
       0: aload_0
       1: ifnonnull     15
       4: new           #53                 // class java/lang/NullPointerException
       7: dup
       8: ldc_w         #275                // String Array cannot be null.
      11: invokespecial #55                 // Method java/lang/NullPointerException."<init>":(Ljava/lang/String;)V
      14: athrow
      15: iload_1
      16: ifge          29
      19: new           #230                // class java/lang/IllegalArgumentException
      22: dup
      23: ldc           #231                // String Index cannot be negative
      25: invokespecial #232                // Method java/lang/IllegalArgumentException."<init>":(Ljava/lang/String;)V
      28: athrow
      29: new           #278                // class javafx/beans/binding/Bindings$89
      32: dup
      33: aload_0
      34: iload_1
      35: invokespecial #279                // Method javafx/beans/binding/Bindings$89."<init>":(Ljavafx/collections/ObservableFloatArray;I)V
      38: areturn

  public static javafx.beans.binding.FloatBinding floatValueAt(javafx.collections.ObservableFloatArray, javafx.beans.value.ObservableIntegerValue);
    Code:
       0: aload_0
       1: aload_1
       2: invokestatic  #280                // Method floatValueAt:(Ljavafx/collections/ObservableFloatArray;Ljavafx/beans/value/ObservableNumberValue;)Ljavafx/beans/binding/FloatBinding;
       5: areturn

  public static javafx.beans.binding.FloatBinding floatValueAt(javafx.collections.ObservableFloatArray, javafx.beans.value.ObservableNumberValue);
    Code:
       0: aload_0
       1: ifnull        8
       4: aload_1
       5: ifnonnull     18
       8: new           #53                 // class java/lang/NullPointerException
      11: dup
      12: ldc           #67                 // String Operands cannot be null.
      14: invokespecial #55                 // Method java/lang/NullPointerException."<init>":(Ljava/lang/String;)V
      17: athrow
      18: new           #281                // class javafx/beans/binding/Bindings$90
      21: dup
      22: aload_0
      23: aload_1
      24: invokespecial #282                // Method javafx/beans/binding/Bindings$90."<init>":(Ljavafx/collections/ObservableFloatArray;Ljavafx/beans/value/ObservableNumberValue;)V
      27: areturn

  public static javafx.beans.binding.IntegerBinding integerValueAt(javafx.collections.ObservableIntegerArray, int);
    Code:
       0: aload_0
       1: ifnonnull     15
       4: new           #53                 // class java/lang/NullPointerException
       7: dup
       8: ldc_w         #275                // String Array cannot be null.
      11: invokespecial #55                 // Method java/lang/NullPointerException."<init>":(Ljava/lang/String;)V
      14: athrow
      15: iload_1
      16: ifge          29
      19: new           #230                // class java/lang/IllegalArgumentException
      22: dup
      23: ldc           #231                // String Index cannot be negative
      25: invokespecial #232                // Method java/lang/IllegalArgumentException."<init>":(Ljava/lang/String;)V
      28: athrow
      29: new           #283                // class javafx/beans/binding/Bindings$91
      32: dup
      33: aload_0
      34: iload_1
      35: invokespecial #284                // Method javafx/beans/binding/Bindings$91."<init>":(Ljavafx/collections/ObservableIntegerArray;I)V
      38: areturn

  public static javafx.beans.binding.IntegerBinding integerValueAt(javafx.collections.ObservableIntegerArray, javafx.beans.value.ObservableIntegerValue);
    Code:
       0: aload_0
       1: aload_1
       2: invokestatic  #285                // Method integerValueAt:(Ljavafx/collections/ObservableIntegerArray;Ljavafx/beans/value/ObservableNumberValue;)Ljavafx/beans/binding/IntegerBinding;
       5: areturn

  public static javafx.beans.binding.IntegerBinding integerValueAt(javafx.collections.ObservableIntegerArray, javafx.beans.value.ObservableNumberValue);
    Code:
       0: aload_0
       1: ifnull        8
       4: aload_1
       5: ifnonnull     18
       8: new           #53                 // class java/lang/NullPointerException
      11: dup
      12: ldc           #67                 // String Operands cannot be null.
      14: invokespecial #55                 // Method java/lang/NullPointerException."<init>":(Ljava/lang/String;)V
      17: athrow
      18: new           #286                // class javafx/beans/binding/Bindings$92
      21: dup
      22: aload_0
      23: aload_1
      24: invokespecial #287                // Method javafx/beans/binding/Bindings$92."<init>":(Ljavafx/collections/ObservableIntegerArray;Ljavafx/beans/value/ObservableNumberValue;)V
      27: areturn

  public static <K, V> javafx.beans.binding.IntegerBinding size(javafx.collections.ObservableMap<K, V>);
    Code:
       0: aload_0
       1: ifnonnull     15
       4: new           #53                 // class java/lang/NullPointerException
       7: dup
       8: ldc_w         #288                // String Map cannot be null.
      11: invokespecial #55                 // Method java/lang/NullPointerException."<init>":(Ljava/lang/String;)V
      14: athrow
      15: new           #289                // class javafx/beans/binding/Bindings$93
      18: dup
      19: aload_0
      20: invokespecial #290                // Method javafx/beans/binding/Bindings$93."<init>":(Ljavafx/collections/ObservableMap;)V
      23: areturn

  public static <K, V> javafx.beans.binding.BooleanBinding isEmpty(javafx.collections.ObservableMap<K, V>);
    Code:
       0: aload_0
       1: ifnonnull     15
       4: new           #53                 // class java/lang/NullPointerException
       7: dup
       8: ldc_w         #288                // String Map cannot be null.
      11: invokespecial #55                 // Method java/lang/NullPointerException."<init>":(Ljava/lang/String;)V
      14: athrow
      15: new           #291                // class javafx/beans/binding/Bindings$94
      18: dup
      19: aload_0
      20: invokespecial #292                // Method javafx/beans/binding/Bindings$94."<init>":(Ljavafx/collections/ObservableMap;)V
      23: areturn

  public static <K, V> javafx.beans.binding.BooleanBinding isNotEmpty(javafx.collections.ObservableMap<K, V>);
    Code:
       0: aload_0
       1: ifnonnull     14
       4: new           #53                 // class java/lang/NullPointerException
       7: dup
       8: ldc           #223                // String List cannot be null.
      10: invokespecial #55                 // Method java/lang/NullPointerException."<init>":(Ljava/lang/String;)V
      13: athrow
      14: new           #293                // class javafx/beans/binding/Bindings$95
      17: dup
      18: aload_0
      19: invokespecial #294                // Method javafx/beans/binding/Bindings$95."<init>":(Ljavafx/collections/ObservableMap;)V
      22: areturn

  public static <K, V> javafx.beans.binding.ObjectBinding<V> valueAt(javafx.collections.ObservableMap<K, V>, K);
    Code:
       0: aload_0
       1: ifnonnull     15
       4: new           #53                 // class java/lang/NullPointerException
       7: dup
       8: ldc_w         #288                // String Map cannot be null.
      11: invokespecial #55                 // Method java/lang/NullPointerException."<init>":(Ljava/lang/String;)V
      14: athrow
      15: new           #295                // class javafx/beans/binding/Bindings$96
      18: dup
      19: aload_0
      20: aload_1
      21: invokespecial #296                // Method javafx/beans/binding/Bindings$96."<init>":(Ljavafx/collections/ObservableMap;Ljava/lang/Object;)V
      24: areturn

  public static <K, V> javafx.beans.binding.ObjectBinding<V> valueAt(javafx.collections.ObservableMap<K, V>, javafx.beans.value.ObservableValue<? extends K>);
    Code:
       0: aload_0
       1: ifnull        8
       4: aload_1
       5: ifnonnull     18
       8: new           #53                 // class java/lang/NullPointerException
      11: dup
      12: ldc           #67                 // String Operands cannot be null.
      14: invokespecial #55                 // Method java/lang/NullPointerException."<init>":(Ljava/lang/String;)V
      17: athrow
      18: new           #297                // class javafx/beans/binding/Bindings$97
      21: dup
      22: aload_0
      23: aload_1
      24: invokespecial #298                // Method javafx/beans/binding/Bindings$97."<init>":(Ljavafx/collections/ObservableMap;Ljavafx/beans/value/ObservableValue;)V
      27: areturn

  public static <K> javafx.beans.binding.BooleanBinding booleanValueAt(javafx.collections.ObservableMap<K, java.lang.Boolean>, K);
    Code:
       0: aload_0
       1: ifnonnull     15
       4: new           #53                 // class java/lang/NullPointerException
       7: dup
       8: ldc_w         #288                // String Map cannot be null.
      11: invokespecial #55                 // Method java/lang/NullPointerException."<init>":(Ljava/lang/String;)V
      14: athrow
      15: new           #299                // class javafx/beans/binding/Bindings$98
      18: dup
      19: aload_0
      20: aload_1
      21: invokespecial #300                // Method javafx/beans/binding/Bindings$98."<init>":(Ljavafx/collections/ObservableMap;Ljava/lang/Object;)V
      24: areturn

  public static <K> javafx.beans.binding.BooleanBinding booleanValueAt(javafx.collections.ObservableMap<K, java.lang.Boolean>, javafx.beans.value.ObservableValue<? extends K>);
    Code:
       0: aload_0
       1: ifnull        8
       4: aload_1
       5: ifnonnull     18
       8: new           #53                 // class java/lang/NullPointerException
      11: dup
      12: ldc           #67                 // String Operands cannot be null.
      14: invokespecial #55                 // Method java/lang/NullPointerException."<init>":(Ljava/lang/String;)V
      17: athrow
      18: new           #301                // class javafx/beans/binding/Bindings$99
      21: dup
      22: aload_0
      23: aload_1
      24: invokespecial #302                // Method javafx/beans/binding/Bindings$99."<init>":(Ljavafx/collections/ObservableMap;Ljavafx/beans/value/ObservableValue;)V
      27: areturn

  public static <K> javafx.beans.binding.DoubleBinding doubleValueAt(javafx.collections.ObservableMap<K, ? extends java.lang.Number>, K);
    Code:
       0: aload_0
       1: ifnonnull     15
       4: new           #53                 // class java/lang/NullPointerException
       7: dup
       8: ldc_w         #288                // String Map cannot be null.
      11: invokespecial #55                 // Method java/lang/NullPointerException."<init>":(Ljava/lang/String;)V
      14: athrow
      15: new           #303                // class javafx/beans/binding/Bindings$100
      18: dup
      19: aload_0
      20: aload_1
      21: invokespecial #304                // Method javafx/beans/binding/Bindings$100."<init>":(Ljavafx/collections/ObservableMap;Ljava/lang/Object;)V
      24: areturn

  public static <K> javafx.beans.binding.DoubleBinding doubleValueAt(javafx.collections.ObservableMap<K, ? extends java.lang.Number>, javafx.beans.value.ObservableValue<? extends K>);
    Code:
       0: aload_0
       1: ifnull        8
       4: aload_1
       5: ifnonnull     18
       8: new           #53                 // class java/lang/NullPointerException
      11: dup
      12: ldc           #67                 // String Operands cannot be null.
      14: invokespecial #55                 // Method java/lang/NullPointerException."<init>":(Ljava/lang/String;)V
      17: athrow
      18: new           #305                // class javafx/beans/binding/Bindings$101
      21: dup
      22: aload_0
      23: aload_1
      24: invokespecial #306                // Method javafx/beans/binding/Bindings$101."<init>":(Ljavafx/collections/ObservableMap;Ljavafx/beans/value/ObservableValue;)V
      27: areturn

  public static <K> javafx.beans.binding.FloatBinding floatValueAt(javafx.collections.ObservableMap<K, ? extends java.lang.Number>, K);
    Code:
       0: aload_0
       1: ifnonnull     15
       4: new           #53                 // class java/lang/NullPointerException
       7: dup
       8: ldc_w         #288                // String Map cannot be null.
      11: invokespecial #55                 // Method java/lang/NullPointerException."<init>":(Ljava/lang/String;)V
      14: athrow
      15: new           #307                // class javafx/beans/binding/Bindings$102
      18: dup
      19: aload_0
      20: aload_1
      21: invokespecial #308                // Method javafx/beans/binding/Bindings$102."<init>":(Ljavafx/collections/ObservableMap;Ljava/lang/Object;)V
      24: areturn

  public static <K> javafx.beans.binding.FloatBinding floatValueAt(javafx.collections.ObservableMap<K, ? extends java.lang.Number>, javafx.beans.value.ObservableValue<? extends K>);
    Code:
       0: aload_0
       1: ifnull        8
       4: aload_1
       5: ifnonnull     18
       8: new           #53                 // class java/lang/NullPointerException
      11: dup
      12: ldc           #67                 // String Operands cannot be null.
      14: invokespecial #55                 // Method java/lang/NullPointerException."<init>":(Ljava/lang/String;)V
      17: athrow
      18: new           #309                // class javafx/beans/binding/Bindings$103
      21: dup
      22: aload_0
      23: aload_1
      24: invokespecial #310                // Method javafx/beans/binding/Bindings$103."<init>":(Ljavafx/collections/ObservableMap;Ljavafx/beans/value/ObservableValue;)V
      27: areturn

  public static <K> javafx.beans.binding.IntegerBinding integerValueAt(javafx.collections.ObservableMap<K, ? extends java.lang.Number>, K);
    Code:
       0: aload_0
       1: ifnonnull     15
       4: new           #53                 // class java/lang/NullPointerException
       7: dup
       8: ldc_w         #288                // String Map cannot be null.
      11: invokespecial #55                 // Method java/lang/NullPointerException."<init>":(Ljava/lang/String;)V
      14: athrow
      15: new           #311                // class javafx/beans/binding/Bindings$104
      18: dup
      19: aload_0
      20: aload_1
      21: invokespecial #312                // Method javafx/beans/binding/Bindings$104."<init>":(Ljavafx/collections/ObservableMap;Ljava/lang/Object;)V
      24: areturn

  public static <K> javafx.beans.binding.IntegerBinding integerValueAt(javafx.collections.ObservableMap<K, ? extends java.lang.Number>, javafx.beans.value.ObservableValue<? extends K>);
    Code:
       0: aload_0
       1: ifnull        8
       4: aload_1
       5: ifnonnull     18
       8: new           #53                 // class java/lang/NullPointerException
      11: dup
      12: ldc           #67                 // String Operands cannot be null.
      14: invokespecial #55                 // Method java/lang/NullPointerException."<init>":(Ljava/lang/String;)V
      17: athrow
      18: new           #313                // class javafx/beans/binding/Bindings$105
      21: dup
      22: aload_0
      23: aload_1
      24: invokespecial #314                // Method javafx/beans/binding/Bindings$105."<init>":(Ljavafx/collections/ObservableMap;Ljavafx/beans/value/ObservableValue;)V
      27: areturn

  public static <K> javafx.beans.binding.LongBinding longValueAt(javafx.collections.ObservableMap<K, ? extends java.lang.Number>, K);
    Code:
       0: aload_0
       1: ifnonnull     15
       4: new           #53                 // class java/lang/NullPointerException
       7: dup
       8: ldc_w         #288                // String Map cannot be null.
      11: invokespecial #55                 // Method java/lang/NullPointerException."<init>":(Ljava/lang/String;)V
      14: athrow
      15: new           #315                // class javafx/beans/binding/Bindings$106
      18: dup
      19: aload_0
      20: aload_1
      21: invokespecial #316                // Method javafx/beans/binding/Bindings$106."<init>":(Ljavafx/collections/ObservableMap;Ljava/lang/Object;)V
      24: areturn

  public static <K> javafx.beans.binding.LongBinding longValueAt(javafx.collections.ObservableMap<K, ? extends java.lang.Number>, javafx.beans.value.ObservableValue<? extends K>);
    Code:
       0: aload_0
       1: ifnull        8
       4: aload_1
       5: ifnonnull     18
       8: new           #53                 // class java/lang/NullPointerException
      11: dup
      12: ldc           #67                 // String Operands cannot be null.
      14: invokespecial #55                 // Method java/lang/NullPointerException."<init>":(Ljava/lang/String;)V
      17: athrow
      18: new           #317                // class javafx/beans/binding/Bindings$107
      21: dup
      22: aload_0
      23: aload_1
      24: invokespecial #318                // Method javafx/beans/binding/Bindings$107."<init>":(Ljavafx/collections/ObservableMap;Ljavafx/beans/value/ObservableValue;)V
      27: areturn

  public static <K> javafx.beans.binding.StringBinding stringValueAt(javafx.collections.ObservableMap<K, java.lang.String>, K);
    Code:
       0: aload_0
       1: ifnonnull     15
       4: new           #53                 // class java/lang/NullPointerException
       7: dup
       8: ldc_w         #288                // String Map cannot be null.
      11: invokespecial #55                 // Method java/lang/NullPointerException."<init>":(Ljava/lang/String;)V
      14: athrow
      15: new           #319                // class javafx/beans/binding/Bindings$108
      18: dup
      19: aload_0
      20: aload_1
      21: invokespecial #320                // Method javafx/beans/binding/Bindings$108."<init>":(Ljavafx/collections/ObservableMap;Ljava/lang/Object;)V
      24: areturn

  public static <K> javafx.beans.binding.StringBinding stringValueAt(javafx.collections.ObservableMap<K, java.lang.String>, javafx.beans.value.ObservableValue<? extends K>);
    Code:
       0: aload_0
       1: ifnull        8
       4: aload_1
       5: ifnonnull     18
       8: new           #53                 // class java/lang/NullPointerException
      11: dup
      12: ldc           #67                 // String Operands cannot be null.
      14: invokespecial #55                 // Method java/lang/NullPointerException."<init>":(Ljava/lang/String;)V
      17: athrow
      18: new           #321                // class javafx/beans/binding/Bindings$109
      21: dup
      22: aload_0
      23: aload_1
      24: invokespecial #322                // Method javafx/beans/binding/Bindings$109."<init>":(Ljavafx/collections/ObservableMap;Ljavafx/beans/value/ObservableValue;)V
      27: areturn

  static java.lang.String access$400(java.lang.String);
    Code:
       0: aload_0
       1: invokestatic  #1                  // Method getStringSafe:(Ljava/lang/String;)Ljava/lang/String;
       4: areturn

  static {};
    Code:
       0: ldc_w         #323                // class javafx/beans/binding/Bindings
       3: invokevirtual #324                // Method java/lang/Class.desiredAssertionStatus:()Z
       6: ifne          13
       9: iconst_1
      10: goto          14
      13: iconst_0
      14: putstatic     #68                 // Field $assertionsDisabled:Z
      17: return
}
