Compiled from "LongExpression.java"
class javafx.beans.binding.LongExpression$1 extends javafx.beans.binding.LongBinding {
  final javafx.beans.value.ObservableLongValue val$value;

  javafx.beans.binding.LongExpression$1(javafx.beans.value.ObservableLongValue);
    Code:
       0: aload_0
       1: aload_1
       2: putfield      #1                  // Field val$value:Ljavafx/beans/value/ObservableLongValue;
       5: aload_0
       6: invokespecial #2                  // Method javafx/beans/binding/LongBinding."<init>":()V
       9: aload_0
      10: iconst_1
      11: anewarray     #3                  // class javafx/beans/Observable
      14: dup
      15: iconst_0
      16: aload_0
      17: getfield      #1                  // Field val$value:Ljavafx/beans/value/ObservableLongValue;
      20: aastore
      21: invokespecial #4                  // Method javafx/beans/binding/LongBinding.bind:([Ljavafx/beans/Observable;)V
      24: return

  public void dispose();
    Code:
       0: aload_0
       1: iconst_1
       2: anewarray     #3                  // class javafx/beans/Observable
       5: dup
       6: iconst_0
       7: aload_0
       8: getfield      #1                  // Field val$value:Ljavafx/beans/value/ObservableLongValue;
      11: aastore
      12: invokespecial #5                  // Method javafx/beans/binding/LongBinding.unbind:([Ljavafx/beans/Observable;)V
      15: return

  protected long computeValue();
    Code:
       0: aload_0
       1: getfield      #1                  // Field val$value:Ljavafx/beans/value/ObservableLongValue;
       4: invokeinterface #6,  1            // InterfaceMethod javafx/beans/value/ObservableLongValue.get:()J
       9: lreturn

  public javafx.collections.ObservableList<javafx.beans.value.ObservableLongValue> getDependencies();
    Code:
       0: aload_0
       1: getfield      #1                  // Field val$value:Ljavafx/beans/value/ObservableLongValue;
       4: invokestatic  #7                  // Method javafx/collections/FXCollections.singletonObservableList:(Ljava/lang/Object;)Ljavafx/collections/ObservableList;
       7: areturn
}
