Compiled from "CustomizePerspectiveDialog.java"
class org.eclipse.ui.internal.dialogs.cpd.CustomizePerspectiveDialog$4 extends org.eclipse.swt.events.SelectionAdapter {
  final org.eclipse.ui.internal.dialogs.cpd.CustomizePerspectiveDialog this$0;

  private final org.eclipse.swt.widgets.Button val$showCommandGroupFilterButton;

  private final org.eclipse.jface.viewers.TableViewer val$actionSetViewer;

  private final org.eclipse.ui.part.PageBook val$book;

  private final org.eclipse.swt.custom.SashForm val$advancedComposite;

  private final org.eclipse.swt.widgets.Composite val$simpleComposite;

  org.eclipse.ui.internal.dialogs.cpd.CustomizePerspectiveDialog$4(org.eclipse.ui.internal.dialogs.cpd.CustomizePerspectiveDialog, org.eclipse.swt.widgets.Button, org.eclipse.jface.viewers.TableViewer, org.eclipse.ui.part.PageBook, org.eclipse.swt.custom.SashForm, org.eclipse.swt.widgets.Composite);
    Code:
       0: aload_0
       1: aload_1
       2: putfield      #95                 // Field this$0:Lorg/eclipse/ui/internal/dialogs/cpd/CustomizePerspectiveDialog;
       5: aload_0
       6: aload_2
       7: putfield      #93                 // Field val$showCommandGroupFilterButton:Lorg/eclipse/swt/widgets/Button;
      10: aload_0
      11: aload_3
      12: putfield      #91                 // Field val$actionSetViewer:Lorg/eclipse/jface/viewers/TableViewer;
      15: aload_0
      16: aload         4
      18: putfield      #96                 // Field val$book:Lorg/eclipse/ui/part/PageBook;
      21: aload_0
      22: aload         5
      24: putfield      #92                 // Field val$advancedComposite:Lorg/eclipse/swt/custom/SashForm;
      27: aload_0
      28: aload         6
      30: putfield      #94                 // Field val$simpleComposite:Lorg/eclipse/swt/widgets/Composite;
      33: aload_0
      34: invokespecial #102                // Method org/eclipse/swt/events/SelectionAdapter."<init>":()V
      37: return

  public void widgetSelected(org.eclipse.swt.events.SelectionEvent);
    Code:
       0: aload_0
       1: getfield      #93                 // Field val$showCommandGroupFilterButton:Lorg/eclipse/swt/widgets/Button;
       4: invokevirtual #103                // Method org/eclipse/swt/widgets/Button.getSelection:()Z
       7: ifeq          130
      10: aload_0
      11: getfield      #95                 // Field this$0:Lorg/eclipse/ui/internal/dialogs/cpd/CustomizePerspectiveDialog;
      14: getfield      #89                 // Field org/eclipse/ui/internal/dialogs/cpd/CustomizePerspectiveDialog.menuStructureViewer1:Lorg/eclipse/jface/viewers/CheckboxTreeViewer;
      17: invokevirtual #98                 // Method org/eclipse/jface/viewers/CheckboxTreeViewer.getSelection:()Lorg/eclipse/jface/viewers/ISelection;
      20: checkcast     #40                 // class org/eclipse/jface/viewers/StructuredSelection
      23: invokevirtual #99                 // Method org/eclipse/jface/viewers/StructuredSelection.getFirstElement:()Ljava/lang/Object;
      26: astore_2
      27: aconst_null
      28: astore_3
      29: aconst_null
      30: astore        4
      32: aload_2
      33: instanceof    #47                 // class org/eclipse/ui/internal/dialogs/cpd/CustomizePerspectiveDialog$DisplayItem
      36: ifeq          51
      39: aload_2
      40: checkcast     #47                 // class org/eclipse/ui/internal/dialogs/cpd/CustomizePerspectiveDialog$DisplayItem
      43: astore        4
      45: aload         4
      47: invokevirtual #105                // Method org/eclipse/ui/internal/dialogs/cpd/CustomizePerspectiveDialog$DisplayItem.getActionSet:()Lorg/eclipse/ui/internal/dialogs/cpd/CustomizePerspectiveDialog$ActionSet;
      50: astore_3
      51: aload_3
      52: ifnonnull     67
      55: aload_0
      56: getfield      #91                 // Field val$actionSetViewer:Lorg/eclipse/jface/viewers/TableViewer;
      59: iconst_0
      60: invokevirtual #100                // Method org/eclipse/jface/viewers/TableViewer.getElementAt:(I)Ljava/lang/Object;
      63: checkcast     #46                 // class org/eclipse/ui/internal/dialogs/cpd/CustomizePerspectiveDialog$ActionSet
      66: astore_3
      67: aload_3
      68: ifnull        87
      71: aload_0
      72: getfield      #91                 // Field val$actionSetViewer:Lorg/eclipse/jface/viewers/TableViewer;
      75: aload_3
      76: invokestatic  #104                // Method org/eclipse/ui/internal/dialogs/cpd/CustomizePerspectiveDialog.setSelectionOn:(Lorg/eclipse/jface/viewers/Viewer;Ljava/lang/Object;)V
      79: aload_0
      80: getfield      #91                 // Field val$actionSetViewer:Lorg/eclipse/jface/viewers/TableViewer;
      83: aload_3
      84: invokevirtual #101                // Method org/eclipse/jface/viewers/TableViewer.reveal:(Ljava/lang/Object;)V
      87: aload         4
      89: ifnull        116
      92: aload_0
      93: getfield      #95                 // Field this$0:Lorg/eclipse/ui/internal/dialogs/cpd/CustomizePerspectiveDialog;
      96: getfield      #90                 // Field org/eclipse/ui/internal/dialogs/cpd/CustomizePerspectiveDialog.menuStructureViewer2:Lorg/eclipse/jface/viewers/CheckboxTreeViewer;
      99: aload         4
     101: invokestatic  #104                // Method org/eclipse/ui/internal/dialogs/cpd/CustomizePerspectiveDialog.setSelectionOn:(Lorg/eclipse/jface/viewers/Viewer;Ljava/lang/Object;)V
     104: aload_0
     105: getfield      #95                 // Field this$0:Lorg/eclipse/ui/internal/dialogs/cpd/CustomizePerspectiveDialog;
     108: getfield      #90                 // Field org/eclipse/ui/internal/dialogs/cpd/CustomizePerspectiveDialog.menuStructureViewer2:Lorg/eclipse/jface/viewers/CheckboxTreeViewer;
     111: aload         4
     113: invokevirtual #97                 // Method org/eclipse/jface/viewers/CheckboxTreeViewer.reveal:(Ljava/lang/Object;)V
     116: aload_0
     117: getfield      #96                 // Field val$book:Lorg/eclipse/ui/part/PageBook;
     120: aload_0
     121: getfield      #92                 // Field val$advancedComposite:Lorg/eclipse/swt/custom/SashForm;
     124: invokevirtual #106                // Method org/eclipse/ui/part/PageBook.showPage:(Lorg/eclipse/swt/widgets/Control;)V
     127: goto          141
     130: aload_0
     131: getfield      #96                 // Field val$book:Lorg/eclipse/ui/part/PageBook;
     134: aload_0
     135: getfield      #94                 // Field val$simpleComposite:Lorg/eclipse/swt/widgets/Composite;
     138: invokevirtual #106                // Method org/eclipse/ui/part/PageBook.showPage:(Lorg/eclipse/swt/widgets/Control;)V
     141: return
}
