Compiled from "CustomizePerspectiveDialog.java"
class org.eclipse.ui.internal.dialogs.cpd.CustomizePerspectiveDialog$DynamicContributionItem extends org.eclipse.ui.internal.dialogs.cpd.CustomizePerspectiveDialog$DisplayItem {
  private java.util.List<org.eclipse.swt.widgets.MenuItem> preview;

  final org.eclipse.ui.internal.dialogs.cpd.CustomizePerspectiveDialog this$0;

  public org.eclipse.ui.internal.dialogs.cpd.CustomizePerspectiveDialog$DynamicContributionItem(org.eclipse.ui.internal.dialogs.cpd.CustomizePerspectiveDialog, java.lang.String, org.eclipse.jface.action.IContributionItem);
    Code:
       0: aload_0
       1: aload_1
       2: putfield      #63                 // Field this$0:Lorg/eclipse/ui/internal/dialogs/cpd/CustomizePerspectiveDialog;
       5: aload_0
       6: aload_1
       7: new           #27                 // class java/lang/StringBuilder
      10: dup
      11: getstatic     #61                 // Field org/eclipse/ui/internal/WorkbenchMessages.HideItems_dynamicItemName:Ljava/lang/String;
      14: invokestatic  #64                 // Method java/lang/String.valueOf:(Ljava/lang/Object;)Ljava/lang/String;
      17: invokespecial #66                 // Method java/lang/StringBuilder."<init>":(Ljava/lang/String;)V
      20: ldc           #1                  // String  -
      22: invokevirtual #67                 // Method java/lang/StringBuilder.append:(Ljava/lang/String;)Ljava/lang/StringBuilder;
      25: aload_2
      26: invokevirtual #67                 // Method java/lang/StringBuilder.append:(Ljava/lang/String;)Ljava/lang/StringBuilder;
      29: invokevirtual #65                 // Method java/lang/StringBuilder.toString:()Ljava/lang/String;
      32: aload_3
      33: invokespecial #69                 // Method org/eclipse/ui/internal/dialogs/cpd/CustomizePerspectiveDialog$DisplayItem."<init>":(Lorg/eclipse/ui/internal/dialogs/cpd/CustomizePerspectiveDialog;Ljava/lang/String;Lorg/eclipse/jface/action/IContributionItem;)V
      36: aload_0
      37: new           #28                 // class java/util/ArrayList
      40: dup
      41: invokespecial #68                 // Method java/util/ArrayList."<init>":()V
      44: putfield      #62                 // Field preview:Ljava/util/List;
      47: return

  public org.eclipse.ui.internal.dialogs.cpd.CustomizePerspectiveDialog$DynamicContributionItem(org.eclipse.ui.internal.dialogs.cpd.CustomizePerspectiveDialog, org.eclipse.jface.action.IContributionItem);
    Code:
       0: aload_0
       1: aload_1
       2: putfield      #63                 // Field this$0:Lorg/eclipse/ui/internal/dialogs/cpd/CustomizePerspectiveDialog;
       5: aload_0
       6: aload_1
       7: getstatic     #61                 // Field org/eclipse/ui/internal/WorkbenchMessages.HideItems_dynamicItemName:Ljava/lang/String;
      10: aload_2
      11: invokespecial #69                 // Method org/eclipse/ui/internal/dialogs/cpd/CustomizePerspectiveDialog$DisplayItem."<init>":(Lorg/eclipse/ui/internal/dialogs/cpd/CustomizePerspectiveDialog;Ljava/lang/String;Lorg/eclipse/jface/action/IContributionItem;)V
      14: aload_0
      15: new           #28                 // class java/util/ArrayList
      18: dup
      19: invokespecial #68                 // Method java/util/ArrayList."<init>":()V
      22: putfield      #62                 // Field preview:Ljava/util/List;
      25: return

  public void addCurrentItem(org.eclipse.swt.widgets.MenuItem);
    Code:
       0: aload_0
       1: getfield      #62                 // Field preview:Ljava/util/List;
       4: aload_1
       5: invokeinterface #70,  2           // InterfaceMethod java/util/List.add:(Ljava/lang/Object;)Z
      10: pop
      11: return

  public java.util.List<org.eclipse.swt.widgets.MenuItem> getCurrentItems();
    Code:
       0: aload_0
       1: getfield      #62                 // Field preview:Ljava/util/List;
       4: areturn
}
