Compiled from "CustomizeActionBars.java"
public class org.eclipse.ui.internal.dialogs.cpd.CustomizeActionBars implements org.eclipse.ui.internal.provisional.application.IActionBarConfigurer2,org.eclipse.ui.IActionBars2 {
  private final org.eclipse.ui.application.IWorkbenchWindowConfigurer configurer;

  private final org.eclipse.jface.action.StatusLineManager statusLineManager;

  private final org.eclipse.e4.ui.model.application.MApplication app;

  final org.eclipse.jface.action.MenuManager menuManager;

  final org.eclipse.ui.internal.CoolBarToTrimManager coolBarManager;

  final org.eclipse.e4.ui.model.application.ui.basic.MTrimmedWindow windowModel;

  final org.eclipse.e4.ui.model.application.ui.menu.MMenu mainMenu;

  final org.eclipse.e4.ui.workbench.renderers.swt.MenuManagerRenderer menuRenderer;

  public org.eclipse.ui.internal.dialogs.cpd.CustomizeActionBars(org.eclipse.ui.application.IWorkbenchWindowConfigurer, org.eclipse.e4.core.contexts.IEclipseContext);
    Code:
       0: aload_0
       1: invokespecial #195                // Method java/lang/Object."<init>":()V
       4: aload_0
       5: aload_1
       6: putfield      #193                // Field configurer:Lorg/eclipse/ui/application/IWorkbenchWindowConfigurer;
       9: aload_0
      10: new           #98                 // class org/eclipse/jface/action/StatusLineManager
      13: dup
      14: invokespecial #200                // Method org/eclipse/jface/action/StatusLineManager."<init>":()V
      17: putfield      #192                // Field statusLineManager:Lorg/eclipse/jface/action/StatusLineManager;
      20: aload_0
      21: new           #97                 // class org/eclipse/jface/action/MenuManager
      24: dup
      25: ldc           #1                  // String MenuBar
      27: ldc           #3                  // String org.eclipse.ui.main.menu
      29: invokespecial #199                // Method org/eclipse/jface/action/MenuManager."<init>":(Ljava/lang/String;Ljava/lang/String;)V
      32: putfield      #191                // Field menuManager:Lorg/eclipse/jface/action/MenuManager;
      35: aload_2
      36: ldc           #10                 // class org/eclipse/e4/ui/workbench/swt/factories/IRendererFactory
      38: invokeinterface #214,  2          // InterfaceMethod org/eclipse/e4/core/contexts/IEclipseContext.get:(Ljava/lang/Class;)Ljava/lang/Object;
      43: checkcast     #10                 // class org/eclipse/e4/ui/workbench/swt/factories/IRendererFactory
      46: astore_3
      47: aload_2
      48: ldc           #9                  // class org/eclipse/e4/ui/workbench/modeling/EModelService
      50: invokeinterface #214,  2          // InterfaceMethod org/eclipse/e4/core/contexts/IEclipseContext.get:(Ljava/lang/Class;)Ljava/lang/Object;
      55: checkcast     #9                  // class org/eclipse/e4/ui/workbench/modeling/EModelService
      58: astore        4
      60: aload_0
      61: aload         4
      63: ldc           #6                  // class org/eclipse/e4/ui/model/application/ui/basic/MTrimmedWindow
      65: invokeinterface #226,  2          // InterfaceMethod org/eclipse/e4/ui/workbench/modeling/EModelService.createModelElement:(Ljava/lang/Class;)Lorg/eclipse/e4/ui/model/application/MApplicationElement;
      70: checkcast     #6                  // class org/eclipse/e4/ui/model/application/ui/basic/MTrimmedWindow
      73: putfield      #188                // Field windowModel:Lorg/eclipse/e4/ui/model/application/ui/basic/MTrimmedWindow;
      76: aload_0
      77: aload_2
      78: ldc           #5                  // class org/eclipse/e4/ui/model/application/MApplication
      80: invokeinterface #214,  2          // InterfaceMethod org/eclipse/e4/core/contexts/IEclipseContext.get:(Ljava/lang/Class;)Ljava/lang/Object;
      85: checkcast     #5                  // class org/eclipse/e4/ui/model/application/MApplication
      88: putfield      #187                // Field app:Lorg/eclipse/e4/ui/model/application/MApplication;
      91: aload_0
      92: getfield      #187                // Field app:Lorg/eclipse/e4/ui/model/application/MApplication;
      95: invokeinterface #218,  1          // InterfaceMethod org/eclipse/e4/ui/model/application/MApplication.getContext:()Lorg/eclipse/e4/core/contexts/IEclipseContext;
     100: ldc           #4                  // String window - CustomizeActionBars
     102: invokeinterface #216,  2          // InterfaceMethod org/eclipse/e4/core/contexts/IEclipseContext.createChild:(Ljava/lang/String;)Lorg/eclipse/e4/core/contexts/IEclipseContext;
     107: astore        5
     109: aload_0
     110: getfield      #188                // Field windowModel:Lorg/eclipse/e4/ui/model/application/ui/basic/MTrimmedWindow;
     113: aload         5
     115: invokeinterface #223,  2          // InterfaceMethod org/eclipse/e4/ui/model/application/ui/basic/MTrimmedWindow.setContext:(Lorg/eclipse/e4/core/contexts/IEclipseContext;)V
     120: aload         5
     122: ldc           #7                  // class org/eclipse/e4/ui/model/application/ui/basic/MWindow
     124: aload_0
     125: getfield      #188                // Field windowModel:Lorg/eclipse/e4/ui/model/application/ui/basic/MTrimmedWindow;
     128: invokeinterface #215,  3          // InterfaceMethod org/eclipse/e4/core/contexts/IEclipseContext.set:(Ljava/lang/Class;Ljava/lang/Object;)V
     133: new           #101                // class org/eclipse/swt/widgets/Shell
     136: dup
     137: invokespecial #204                // Method org/eclipse/swt/widgets/Shell."<init>":()V
     140: astore        6
     142: aload_0
     143: getfield      #188                // Field windowModel:Lorg/eclipse/e4/ui/model/application/ui/basic/MTrimmedWindow;
     146: aload         6
     148: invokeinterface #221,  2          // InterfaceMethod org/eclipse/e4/ui/model/application/ui/basic/MTrimmedWindow.setWidget:(Ljava/lang/Object;)V
     153: aload_0
     154: getfield      #188                // Field windowModel:Lorg/eclipse/e4/ui/model/application/ui/basic/MTrimmedWindow;
     157: iconst_0
     158: invokeinterface #219,  2          // InterfaceMethod org/eclipse/e4/ui/model/application/ui/basic/MTrimmedWindow.setToBeRendered:(Z)V
     163: aload_0
     164: getfield      #187                // Field app:Lorg/eclipse/e4/ui/model/application/MApplication;
     167: invokeinterface #217,  1          // InterfaceMethod org/eclipse/e4/ui/model/application/MApplication.getChildren:()Ljava/util/List;
     172: aload_0
     173: getfield      #188                // Field windowModel:Lorg/eclipse/e4/ui/model/application/ui/basic/MTrimmedWindow;
     176: invokeinterface #210,  2          // InterfaceMethod java/util/List.add:(Ljava/lang/Object;)Z
     181: pop
     182: aload         6
     184: ldc           #2                  // String modelElement
     186: aload_0
     187: getfield      #188                // Field windowModel:Lorg/eclipse/e4/ui/model/application/ui/basic/MTrimmedWindow;
     190: invokevirtual #206                // Method org/eclipse/swt/widgets/Shell.setData:(Ljava/lang/String;Ljava/lang/Object;)V
     193: aload_0
     194: aload         4
     196: ldc           #8                  // class org/eclipse/e4/ui/model/application/ui/menu/MMenu
     198: invokeinterface #226,  2          // InterfaceMethod org/eclipse/e4/ui/workbench/modeling/EModelService.createModelElement:(Ljava/lang/Class;)Lorg/eclipse/e4/ui/model/application/MApplicationElement;
     203: checkcast     #8                  // class org/eclipse/e4/ui/model/application/ui/menu/MMenu
     206: putfield      #189                // Field mainMenu:Lorg/eclipse/e4/ui/model/application/ui/menu/MMenu;
     209: aload_0
     210: getfield      #189                // Field mainMenu:Lorg/eclipse/e4/ui/model/application/ui/menu/MMenu;
     213: ldc           #3                  // String org.eclipse.ui.main.menu
     215: invokeinterface #225,  2          // InterfaceMethod org/eclipse/e4/ui/model/application/ui/menu/MMenu.setElementId:(Ljava/lang/String;)V
     220: aload_0
     221: aload_3
     222: aload_0
     223: getfield      #189                // Field mainMenu:Lorg/eclipse/e4/ui/model/application/ui/menu/MMenu;
     226: aconst_null
     227: invokeinterface #227,  3          // InterfaceMethod org/eclipse/e4/ui/workbench/swt/factories/IRendererFactory.getRenderer:(Lorg/eclipse/e4/ui/model/application/ui/MUIElement;Ljava/lang/Object;)Lorg/eclipse/e4/ui/internal/workbench/swt/AbstractPartRenderer;
     232: checkcast     #96                 // class org/eclipse/e4/ui/workbench/renderers/swt/MenuManagerRenderer
     235: putfield      #190                // Field menuRenderer:Lorg/eclipse/e4/ui/workbench/renderers/swt/MenuManagerRenderer;
     238: aload_0
     239: getfield      #190                // Field menuRenderer:Lorg/eclipse/e4/ui/workbench/renderers/swt/MenuManagerRenderer;
     242: aload_0
     243: getfield      #189                // Field mainMenu:Lorg/eclipse/e4/ui/model/application/ui/menu/MMenu;
     246: aload_0
     247: getfield      #191                // Field menuManager:Lorg/eclipse/jface/action/MenuManager;
     250: invokevirtual #197                // Method org/eclipse/e4/ui/workbench/renderers/swt/MenuManagerRenderer.linkModelToManager:(Lorg/eclipse/e4/ui/model/application/ui/menu/MMenu;Lorg/eclipse/jface/action/MenuManager;)V
     253: aload_0
     254: getfield      #188                // Field windowModel:Lorg/eclipse/e4/ui/model/application/ui/basic/MTrimmedWindow;
     257: aload_0
     258: getfield      #189                // Field mainMenu:Lorg/eclipse/e4/ui/model/application/ui/menu/MMenu;
     261: invokeinterface #224,  2          // InterfaceMethod org/eclipse/e4/ui/model/application/ui/basic/MTrimmedWindow.setMainMenu:(Lorg/eclipse/e4/ui/model/application/ui/menu/MMenu;)V
     266: aload_0
     267: new           #104                // class org/eclipse/ui/internal/CoolBarToTrimManager
     270: dup
     271: aload_0
     272: getfield      #187                // Field app:Lorg/eclipse/e4/ui/model/application/MApplication;
     275: aload_0
     276: getfield      #188                // Field windowModel:Lorg/eclipse/e4/ui/model/application/ui/basic/MTrimmedWindow;
     279: new           #93                 // class java/util/ArrayList
     282: dup
     283: invokespecial #196                // Method java/util/ArrayList."<init>":()V
     286: aload_3
     287: invokespecial #208                // Method org/eclipse/ui/internal/CoolBarToTrimManager."<init>":(Lorg/eclipse/e4/ui/model/application/MApplication;Lorg/eclipse/e4/ui/model/application/ui/basic/MTrimmedWindow;Ljava/util/List;Lorg/eclipse/e4/ui/workbench/swt/factories/IRendererFactory;)V
     290: putfield      #194                // Field coolBarManager:Lorg/eclipse/ui/internal/CoolBarToTrimManager;
     293: return

  public org.eclipse.ui.application.IWorkbenchWindowConfigurer getWindowConfigurer();
    Code:
       0: aload_0
       1: getfield      #193                // Field configurer:Lorg/eclipse/ui/application/IWorkbenchWindowConfigurer;
       4: areturn

  public org.eclipse.jface.action.IMenuManager getMenuManager();
    Code:
       0: aload_0
       1: getfield      #191                // Field menuManager:Lorg/eclipse/jface/action/MenuManager;
       4: areturn

  public org.eclipse.jface.action.IStatusLineManager getStatusLineManager();
    Code:
       0: aload_0
       1: getfield      #192                // Field statusLineManager:Lorg/eclipse/jface/action/StatusLineManager;
       4: areturn

  public org.eclipse.ui.internal.CoolBarToTrimManager getCoolBarManager();
    Code:
       0: aload_0
       1: getfield      #194                // Field coolBarManager:Lorg/eclipse/ui/internal/CoolBarToTrimManager;
       4: areturn

  public org.eclipse.jface.action.IToolBarManager getToolBarManager();
    Code:
       0: aconst_null
       1: areturn

  public void setGlobalActionHandler(java.lang.String, org.eclipse.jface.action.IAction);
    Code:
       0: return

  public void updateActionBars();
    Code:
       0: return

  public void clearGlobalActionHandlers();
    Code:
       0: return

  public org.eclipse.jface.action.IAction getGlobalActionHandler(java.lang.String);
    Code:
       0: aconst_null
       1: areturn

  public void registerGlobalAction(org.eclipse.jface.action.IAction);
    Code:
       0: return

  public void dispose();
    Code:
       0: aload_0
       1: getfield      #194                // Field coolBarManager:Lorg/eclipse/ui/internal/CoolBarToTrimManager;
       4: invokevirtual #207                // Method org/eclipse/ui/internal/CoolBarToTrimManager.dispose:()V
       7: aload_0
       8: getfield      #191                // Field menuManager:Lorg/eclipse/jface/action/MenuManager;
      11: invokevirtual #198                // Method org/eclipse/jface/action/MenuManager.dispose:()V
      14: aload_0
      15: getfield      #192                // Field statusLineManager:Lorg/eclipse/jface/action/StatusLineManager;
      18: invokevirtual #201                // Method org/eclipse/jface/action/StatusLineManager.dispose:()V
      21: aload_0
      22: getfield      #188                // Field windowModel:Lorg/eclipse/e4/ui/model/application/ui/basic/MTrimmedWindow;
      25: invokeinterface #222,  1          // InterfaceMethod org/eclipse/e4/ui/model/application/ui/basic/MTrimmedWindow.getContext:()Lorg/eclipse/e4/core/contexts/IEclipseContext;
      30: invokeinterface #212,  1          // InterfaceMethod org/eclipse/e4/core/contexts/IEclipseContext.deactivate:()V
      35: aload_0
      36: getfield      #188                // Field windowModel:Lorg/eclipse/e4/ui/model/application/ui/basic/MTrimmedWindow;
      39: invokeinterface #222,  1          // InterfaceMethod org/eclipse/e4/ui/model/application/ui/basic/MTrimmedWindow.getContext:()Lorg/eclipse/e4/core/contexts/IEclipseContext;
      44: invokeinterface #213,  1          // InterfaceMethod org/eclipse/e4/core/contexts/IEclipseContext.dispose:()V
      49: aload_0
      50: getfield      #188                // Field windowModel:Lorg/eclipse/e4/ui/model/application/ui/basic/MTrimmedWindow;
      53: invokeinterface #220,  1          // InterfaceMethod org/eclipse/e4/ui/model/application/ui/basic/MTrimmedWindow.getWidget:()Ljava/lang/Object;
      58: checkcast     #101                // class org/eclipse/swt/widgets/Shell
      61: invokevirtual #205                // Method org/eclipse/swt/widgets/Shell.dispose:()V
      64: aload_0
      65: getfield      #187                // Field app:Lorg/eclipse/e4/ui/model/application/MApplication;
      68: invokeinterface #217,  1          // InterfaceMethod org/eclipse/e4/ui/model/application/MApplication.getChildren:()Ljava/util/List;
      73: aload_0
      74: getfield      #188                // Field windowModel:Lorg/eclipse/e4/ui/model/application/ui/basic/MTrimmedWindow;
      77: invokeinterface #211,  2          // InterfaceMethod java/util/List.remove:(Ljava/lang/Object;)Z
      82: pop
      83: return

  public final org.eclipse.ui.services.IServiceLocator getServiceLocator();
    Code:
       0: aload_0
       1: getfield      #193                // Field configurer:Lorg/eclipse/ui/application/IWorkbenchWindowConfigurer;
       4: invokeinterface #228,  1          // InterfaceMethod org/eclipse/ui/application/IWorkbenchWindowConfigurer.getWindow:()Lorg/eclipse/ui/IWorkbenchWindow;
       9: areturn

  public org.eclipse.jface.internal.provisional.action.IToolBarContributionItem createToolBarContributionItem(org.eclipse.jface.action.IToolBarManager, java.lang.String);
    Code:
       0: new           #100                // class org/eclipse/jface/internal/provisional/action/ToolBarContributionItem2
       3: dup
       4: aload_1
       5: aload_2
       6: invokespecial #203                // Method org/eclipse/jface/internal/provisional/action/ToolBarContributionItem2."<init>":(Lorg/eclipse/jface/action/IToolBarManager;Ljava/lang/String;)V
       9: areturn

  public org.eclipse.jface.action.IToolBarManager createToolBarManager();
    Code:
       0: new           #99                 // class org/eclipse/jface/action/ToolBarManager
       3: dup
       4: invokespecial #202                // Method org/eclipse/jface/action/ToolBarManager."<init>":()V
       7: areturn

  public org.eclipse.jface.action.ICoolBarManager getCoolBarManager();
    Code:
       0: aload_0
       1: invokevirtual #209                // Method getCoolBarManager:()Lorg/eclipse/ui/internal/CoolBarToTrimManager;
       4: areturn
}
