Compiled from "TreeManager.java"
public class org.eclipse.ui.internal.dialogs.cpd.TreeManager$ModelListenerForCheckboxTree implements org.eclipse.ui.internal.dialogs.cpd.TreeManager$CheckListener {
  private org.eclipse.jface.viewers.CheckboxTreeViewer treeViewer;

  public org.eclipse.ui.internal.dialogs.cpd.TreeManager$ModelListenerForCheckboxTree(org.eclipse.ui.internal.dialogs.cpd.TreeManager, org.eclipse.jface.viewers.CheckboxTreeViewer);
    Code:
       0: aload_0
       1: invokespecial #36                 // Method java/lang/Object."<init>":()V
       4: aload_0
       5: aload_2
       6: putfield      #35                 // Field treeViewer:Lorg/eclipse/jface/viewers/CheckboxTreeViewer;
       9: aload_1
      10: aload_0
      11: invokevirtual #38                 // Method org/eclipse/ui/internal/dialogs/cpd/TreeManager.addListener:(Lorg/eclipse/ui/internal/dialogs/cpd/TreeManager$CheckListener;)V
      14: return

  public void checkChanged(org.eclipse.ui.internal.dialogs.cpd.TreeManager$TreeItem);
    Code:
       0: aload_0
       1: getfield      #35                 // Field treeViewer:Lorg/eclipse/jface/viewers/CheckboxTreeViewer;
       4: aload_1
       5: aconst_null
       6: invokevirtual #37                 // Method org/eclipse/jface/viewers/CheckboxTreeViewer.update:(Ljava/lang/Object;[Ljava/lang/String;)V
       9: return
}
