public final class nu.xom.Elements {
  private java.util.List elements;

  nu.xom.Elements();
    Code:
       0: aload_0
       1: invokespecial #10                 // Method java/lang/Object."<init>":()V
       4: aload_0
       5: new           #12                 // class java/util/ArrayList
       8: dup
       9: iconst_1
      10: invokespecial #15                 // Method java/util/ArrayList."<init>":(I)V
      13: putfield      #17                 // Field elements:Ljava/util/List;
      16: return

  public int size();
    Code:
       0: aload_0
       1: getfield      #17                 // Field elements:Ljava/util/List;
       4: invokeinterface #23,  1           // InterfaceMethod java/util/List.size:()I
       9: ireturn

  public nu.xom.Element get(int);
    Code:
       0: aload_0
       1: getfield      #17                 // Field elements:Ljava/util/List;
       4: iload_1
       5: invokeinterface #28,  2           // InterfaceMethod java/util/List.get:(I)Ljava/lang/Object;
      10: checkcast     #30                 // class nu/xom/Element
      13: areturn

  void add(nu.xom.Element);
    Code:
       0: aload_0
       1: getfield      #17                 // Field elements:Ljava/util/List;
       4: aload_1
       5: invokeinterface #35,  2           // InterfaceMethod java/util/List.add:(Ljava/lang/Object;)Z
      10: pop
      11: return
}
