class nu.xom.JaxenConnector extends nu.xom.jaxen.BaseXPath {
  private static final long serialVersionUID;

  private static nu.xom.jaxen.FunctionContext functionContext;

  nu.xom.JaxenConnector(java.lang.String) throws nu.xom.jaxen.JaxenException;
    Code:
       0: aload_0
       1: aload_1
       2: new           #16                 // class nu/xom/JaxenNavigator
       5: dup
       6: invokespecial #19                 // Method nu/xom/JaxenNavigator."<init>":()V
       9: invokespecial #22                 // Method nu/xom/jaxen/BaseXPath."<init>":(Ljava/lang/String;Lnu/xom/jaxen/Navigator;)V
      12: aload_0
      13: getstatic     #24                 // Field functionContext:Lnu/xom/jaxen/FunctionContext;
      16: invokevirtual #28                 // Method setFunctionContext:(Lnu/xom/jaxen/FunctionContext;)V
      19: return

  public java.util.List selectNodes(java.lang.Object) throws nu.xom.jaxen.JaxenException;
    Code:
       0: aload_0
       1: aload_1
       2: invokespecial #34                 // Method nu/xom/jaxen/BaseXPath.selectNodes:(Ljava/lang/Object;)Ljava/util/List;
       5: astore_2
       6: aload_2
       7: invokeinterface #40,  1           // InterfaceMethod java/util/List.listIterator:()Ljava/util/ListIterator;
      12: astore_3
      13: aload_3
      14: invokeinterface #46,  1           // InterfaceMethod java/util/ListIterator.hasNext:()Z
      19: ifeq          176
      22: aload_3
      23: invokeinterface #50,  1           // InterfaceMethod java/util/ListIterator.next:()Ljava/lang/Object;
      28: astore        4
      30: aload         4
      32: instanceof    #36                 // class java/util/List
      35: ifeq          109
      38: aload         4
      40: checkcast     #36                 // class java/util/List
      43: astore        5
      45: aload_3
      46: aload         5
      48: iconst_0
      49: invokeinterface #54,  2           // InterfaceMethod java/util/List.get:(I)Ljava/lang/Object;
      54: invokeinterface #58,  2           // InterfaceMethod java/util/ListIterator.set:(Ljava/lang/Object;)V
      59: aload         5
      61: invokeinterface #62,  1           // InterfaceMethod java/util/List.size:()I
      66: iconst_1
      67: if_icmple     106
      70: aload         5
      72: iconst_1
      73: invokeinterface #65,  2           // InterfaceMethod java/util/List.listIterator:(I)Ljava/util/ListIterator;
      78: astore        6
      80: aload         6
      82: invokeinterface #68,  1           // InterfaceMethod java/util/Iterator.hasNext:()Z
      87: ifeq          106
      90: aload_3
      91: aload         6
      93: invokeinterface #69,  1           // InterfaceMethod java/util/Iterator.next:()Ljava/lang/Object;
      98: invokeinterface #72,  2           // InterfaceMethod java/util/ListIterator.add:(Ljava/lang/Object;)V
     103: goto          80
     106: goto          173
     109: aload         4
     111: checkcast     #74                 // class nu/xom/Node
     114: astore        5
     116: aload         5
     118: invokevirtual #77                 // Method nu/xom/Node.isDocumentFragment:()Z
     121: ifeq          149
     124: aload_3
     125: invokeinterface #80,  1           // InterfaceMethod java/util/ListIterator.remove:()V
     130: aload_2
     131: invokeinterface #83,  1           // InterfaceMethod java/util/List.isEmpty:()Z
     136: ifeq          149
     139: new           #85                 // class nu/xom/XPathException
     142: dup
     143: ldc           #87                 // String Tried to get document node of disconnected subtree
     145: invokespecial #89                 // Method nu/xom/XPathException."<init>":(Ljava/lang/String;)V
     148: athrow
     149: goto          173
     152: astore        5
     154: new           #91                 // class nu/xom/XPathTypeException
     157: dup
     158: aload_2
     159: iconst_0
     160: invokeinterface #54,  2           // InterfaceMethod java/util/List.get:(I)Ljava/lang/Object;
     165: invokespecial #93                 // Method nu/xom/XPathTypeException."<init>":(Ljava/lang/Object;)V
     168: astore        6
     170: aload         6
     172: athrow
     173: goto          13
     176: aload_2
     177: areturn
    Exception table:
       from    to  target type
         109   149   152   Class java/lang/ClassCastException

  static {};
    Code:
       0: new           #96                 // class nu/xom/jaxen/XPathFunctionContext
       3: dup
       4: iconst_0
       5: invokespecial #99                 // Method nu/xom/jaxen/XPathFunctionContext."<init>":(Z)V
       8: putstatic     #24                 // Field functionContext:Lnu/xom/jaxen/FunctionContext;
      11: return
}
