Compiled from "CachingDateFormatter.java"
class ch.qos.logback.core.util.CachingDateFormatter$CacheTuple {
  final long lastTimestamp;

  final java.lang.String cachedStr;

  public ch.qos.logback.core.util.CachingDateFormatter$CacheTuple(long, java.lang.String);
    Code:
       0: aload_0
       1: invokespecial #1                  // Method java/lang/Object."<init>":()V
       4: aload_0
       5: lload_1
       6: putfield      #7                  // Field lastTimestamp:J
       9: aload_0
      10: aload_3
      11: putfield      #13                 // Field cachedStr:Ljava/lang/String;
      14: return
}
