Compiled from "AutoValue_MapDataSearchResult.java"
final class org.graylog.plugins.map.search.AutoValue_MapDataSearchResult extends org.graylog.plugins.map.search.MapDataSearchResult {
  private final java.lang.String query;

  private final org.graylog2.plugin.indexer.searches.timeranges.TimeRange timerange;

  private final int limit;

  private final java.lang.String streamId;

  private final java.util.Map<java.lang.String, org.graylog2.rest.models.search.responses.TermsResult> fields;

  private org.graylog.plugins.map.search.AutoValue_MapDataSearchResult(java.lang.String, org.graylog2.plugin.indexer.searches.timeranges.TimeRange, int, java.lang.String, java.util.Map<java.lang.String, org.graylog2.rest.models.search.responses.TermsResult>);
    Code:
       0: aload_0
       1: invokespecial #2                  // Method org/graylog/plugins/map/search/MapDataSearchResult."<init>":()V
       4: aload_0
       5: aload_1
       6: putfield      #3                  // Field query:Ljava/lang/String;
       9: aload_0
      10: aload_2
      11: putfield      #4                  // Field timerange:Lorg/graylog2/plugin/indexer/searches/timeranges/TimeRange;
      14: aload_0
      15: iload_3
      16: putfield      #5                  // Field limit:I
      19: aload_0
      20: aload         4
      22: putfield      #6                  // Field streamId:Ljava/lang/String;
      25: aload_0
      26: aload         5
      28: putfield      #7                  // Field fields:Ljava/util/Map;
      31: return

  public java.lang.String query();
    Code:
       0: aload_0
       1: getfield      #3                  // Field query:Ljava/lang/String;
       4: areturn

  public org.graylog2.plugin.indexer.searches.timeranges.TimeRange timerange();
    Code:
       0: aload_0
       1: getfield      #4                  // Field timerange:Lorg/graylog2/plugin/indexer/searches/timeranges/TimeRange;
       4: areturn

  public int limit();
    Code:
       0: aload_0
       1: getfield      #5                  // Field limit:I
       4: ireturn

  public java.lang.String streamId();
    Code:
       0: aload_0
       1: getfield      #6                  // Field streamId:Ljava/lang/String;
       4: areturn

  public java.util.Map<java.lang.String, org.graylog2.rest.models.search.responses.TermsResult> fields();
    Code:
       0: aload_0
       1: getfield      #7                  // Field fields:Ljava/util/Map;
       4: areturn

  public java.lang.String toString();
    Code:
       0: new           #8                  // class java/lang/StringBuilder
       3: dup
       4: invokespecial #9                  // Method java/lang/StringBuilder."<init>":()V
       7: ldc           #10                 // String MapDataSearchResult{query=
       9: invokevirtual #11                 // Method java/lang/StringBuilder.append:(Ljava/lang/String;)Ljava/lang/StringBuilder;
      12: aload_0
      13: getfield      #3                  // Field query:Ljava/lang/String;
      16: invokevirtual #11                 // Method java/lang/StringBuilder.append:(Ljava/lang/String;)Ljava/lang/StringBuilder;
      19: ldc           #12                 // String , timerange=
      21: invokevirtual #11                 // Method java/lang/StringBuilder.append:(Ljava/lang/String;)Ljava/lang/StringBuilder;
      24: aload_0
      25: getfield      #4                  // Field timerange:Lorg/graylog2/plugin/indexer/searches/timeranges/TimeRange;
      28: invokevirtual #13                 // Method java/lang/StringBuilder.append:(Ljava/lang/Object;)Ljava/lang/StringBuilder;
      31: ldc           #14                 // String , limit=
      33: invokevirtual #11                 // Method java/lang/StringBuilder.append:(Ljava/lang/String;)Ljava/lang/StringBuilder;
      36: aload_0
      37: getfield      #5                  // Field limit:I
      40: invokevirtual #15                 // Method java/lang/StringBuilder.append:(I)Ljava/lang/StringBuilder;
      43: ldc           #16                 // String , streamId=
      45: invokevirtual #11                 // Method java/lang/StringBuilder.append:(Ljava/lang/String;)Ljava/lang/StringBuilder;
      48: aload_0
      49: getfield      #6                  // Field streamId:Ljava/lang/String;
      52: invokevirtual #11                 // Method java/lang/StringBuilder.append:(Ljava/lang/String;)Ljava/lang/StringBuilder;
      55: ldc           #17                 // String , fields=
      57: invokevirtual #11                 // Method java/lang/StringBuilder.append:(Ljava/lang/String;)Ljava/lang/StringBuilder;
      60: aload_0
      61: getfield      #7                  // Field fields:Ljava/util/Map;
      64: invokevirtual #13                 // Method java/lang/StringBuilder.append:(Ljava/lang/Object;)Ljava/lang/StringBuilder;
      67: ldc           #18                 // String }
      69: invokevirtual #11                 // Method java/lang/StringBuilder.append:(Ljava/lang/String;)Ljava/lang/StringBuilder;
      72: invokevirtual #19                 // Method java/lang/StringBuilder.toString:()Ljava/lang/String;
      75: areturn

  public boolean equals(java.lang.Object);
    Code:
       0: aload_1
       1: aload_0
       2: if_acmpne     7
       5: iconst_1
       6: ireturn
       7: aload_1
       8: instanceof    #20                 // class org/graylog/plugins/map/search/MapDataSearchResult
      11: ifeq          111
      14: aload_1
      15: checkcast     #20                 // class org/graylog/plugins/map/search/MapDataSearchResult
      18: astore_2
      19: aload_0
      20: getfield      #3                  // Field query:Ljava/lang/String;
      23: aload_2
      24: invokevirtual #21                 // Method org/graylog/plugins/map/search/MapDataSearchResult.query:()Ljava/lang/String;
      27: invokevirtual #22                 // Method java/lang/String.equals:(Ljava/lang/Object;)Z
      30: ifeq          109
      33: aload_0
      34: getfield      #4                  // Field timerange:Lorg/graylog2/plugin/indexer/searches/timeranges/TimeRange;
      37: aload_2
      38: invokevirtual #23                 // Method org/graylog/plugins/map/search/MapDataSearchResult.timerange:()Lorg/graylog2/plugin/indexer/searches/timeranges/TimeRange;
      41: invokevirtual #24                 // Method java/lang/Object.equals:(Ljava/lang/Object;)Z
      44: ifeq          109
      47: aload_0
      48: getfield      #5                  // Field limit:I
      51: aload_2
      52: invokevirtual #25                 // Method org/graylog/plugins/map/search/MapDataSearchResult.limit:()I
      55: if_icmpne     109
      58: aload_0
      59: getfield      #6                  // Field streamId:Ljava/lang/String;
      62: ifnonnull     75
      65: aload_2
      66: invokevirtual #26                 // Method org/graylog/plugins/map/search/MapDataSearchResult.streamId:()Ljava/lang/String;
      69: ifnonnull     109
      72: goto          89
      75: aload_0
      76: getfield      #6                  // Field streamId:Ljava/lang/String;
      79: aload_2
      80: invokevirtual #26                 // Method org/graylog/plugins/map/search/MapDataSearchResult.streamId:()Ljava/lang/String;
      83: invokevirtual #22                 // Method java/lang/String.equals:(Ljava/lang/Object;)Z
      86: ifeq          109
      89: aload_0
      90: getfield      #7                  // Field fields:Ljava/util/Map;
      93: aload_2
      94: invokevirtual #27                 // Method org/graylog/plugins/map/search/MapDataSearchResult.fields:()Ljava/util/Map;
      97: invokeinterface #28,  2           // InterfaceMethod java/util/Map.equals:(Ljava/lang/Object;)Z
     102: ifeq          109
     105: iconst_1
     106: goto          110
     109: iconst_0
     110: ireturn
     111: iconst_0
     112: ireturn

  public int hashCode();
    Code:
       0: iconst_1
       1: istore_1
       2: iload_1
       3: ldc           #29                 // int 1000003
       5: imul
       6: istore_1
       7: iload_1
       8: aload_0
       9: getfield      #3                  // Field query:Ljava/lang/String;
      12: invokevirtual #30                 // Method java/lang/String.hashCode:()I
      15: ixor
      16: istore_1
      17: iload_1
      18: ldc           #29                 // int 1000003
      20: imul
      21: istore_1
      22: iload_1
      23: aload_0
      24: getfield      #4                  // Field timerange:Lorg/graylog2/plugin/indexer/searches/timeranges/TimeRange;
      27: invokevirtual #31                 // Method java/lang/Object.hashCode:()I
      30: ixor
      31: istore_1
      32: iload_1
      33: ldc           #29                 // int 1000003
      35: imul
      36: istore_1
      37: iload_1
      38: aload_0
      39: getfield      #5                  // Field limit:I
      42: ixor
      43: istore_1
      44: iload_1
      45: ldc           #29                 // int 1000003
      47: imul
      48: istore_1
      49: iload_1
      50: aload_0
      51: getfield      #6                  // Field streamId:Ljava/lang/String;
      54: ifnonnull     61
      57: iconst_0
      58: goto          68
      61: aload_0
      62: getfield      #6                  // Field streamId:Ljava/lang/String;
      65: invokevirtual #30                 // Method java/lang/String.hashCode:()I
      68: ixor
      69: istore_1
      70: iload_1
      71: ldc           #29                 // int 1000003
      73: imul
      74: istore_1
      75: iload_1
      76: aload_0
      77: getfield      #7                  // Field fields:Ljava/util/Map;
      80: invokeinterface #32,  1           // InterfaceMethod java/util/Map.hashCode:()I
      85: ixor
      86: istore_1
      87: iload_1
      88: ireturn

  public org.graylog.plugins.map.search.MapDataSearchResult$Builder toBuilder();
    Code:
       0: new           #33                 // class org/graylog/plugins/map/search/AutoValue_MapDataSearchResult$Builder
       3: dup
       4: aload_0
       5: aconst_null
       6: invokespecial #34                 // Method org/graylog/plugins/map/search/AutoValue_MapDataSearchResult$Builder."<init>":(Lorg/graylog/plugins/map/search/MapDataSearchResult;Lorg/graylog/plugins/map/search/AutoValue_MapDataSearchResult$1;)V
       9: areturn

  org.graylog.plugins.map.search.AutoValue_MapDataSearchResult(java.lang.String, org.graylog2.plugin.indexer.searches.timeranges.TimeRange, int, java.lang.String, java.util.Map, org.graylog.plugins.map.search.AutoValue_MapDataSearchResult$1);
    Code:
       0: aload_0
       1: aload_1
       2: aload_2
       3: iload_3
       4: aload         4
       6: aload         5
       8: invokespecial #1                  // Method "<init>":(Ljava/lang/String;Lorg/graylog2/plugin/indexer/searches/timeranges/TimeRange;ILjava/lang/String;Ljava/util/Map;)V
      11: return
}
