Compiled from "MapDataSearch.java"
public class org.graylog.plugins.map.search.MapDataSearch {
  private static final java.util.regex.Pattern VALIDATION_PATTERN;

  private final org.graylog2.indexer.searches.Searches searches;

  public org.graylog.plugins.map.search.MapDataSearch(org.graylog2.indexer.searches.Searches);
    Code:
       0: aload_0
       1: invokespecial #1                  // Method java/lang/Object."<init>":()V
       4: aload_0
       5: aload_1
       6: putfield      #2                  // Field searches:Lorg/graylog2/indexer/searches/Searches;
       9: return

  public org.graylog.plugins.map.search.MapDataSearchResult searchMapData(org.graylog.plugins.map.search.MapDataSearchRequest) throws org.graylog.plugins.map.search.MapDataSearch$ValueTypeException;
    Code:
       0: invokestatic  #3                  // Method com/google/common/collect/ImmutableMap.builder:()Lcom/google/common/collect/ImmutableMap$Builder;
       3: astore_2
       4: aconst_null
       5: astore_3
       6: aload_1
       7: invokevirtual #4                  // Method org/graylog/plugins/map/search/MapDataSearchRequest.streamId:()Ljava/lang/String;
      10: invokestatic  #5                  // Method com/google/common/base/Strings.isNullOrEmpty:(Ljava/lang/String;)Z
      13: ifne          39
      16: new           #6                  // class java/lang/StringBuilder
      19: dup
      20: invokespecial #7                  // Method java/lang/StringBuilder."<init>":()V
      23: ldc           #8                  // String streams:
      25: invokevirtual #9                  // Method java/lang/StringBuilder.append:(Ljava/lang/String;)Ljava/lang/StringBuilder;
      28: aload_1
      29: invokevirtual #4                  // Method org/graylog/plugins/map/search/MapDataSearchRequest.streamId:()Ljava/lang/String;
      32: invokevirtual #9                  // Method java/lang/StringBuilder.append:(Ljava/lang/String;)Ljava/lang/StringBuilder;
      35: invokevirtual #10                 // Method java/lang/StringBuilder.toString:()Ljava/lang/String;
      38: astore_3
      39: aload_1
      40: invokevirtual #11                 // Method org/graylog/plugins/map/search/MapDataSearchRequest.fields:()Ljava/util/Set;
      43: invokeinterface #12,  1           // InterfaceMethod java/util/Set.iterator:()Ljava/util/Iterator;
      48: astore        4
      50: aload         4
      52: invokeinterface #13,  1           // InterfaceMethod java/util/Iterator.hasNext:()Z
      57: ifeq          153
      60: aload         4
      62: invokeinterface #14,  1           // InterfaceMethod java/util/Iterator.next:()Ljava/lang/Object;
      67: checkcast     #15                 // class java/lang/String
      70: astore        5
      72: aload_0
      73: getfield      #2                  // Field searches:Lorg/graylog2/indexer/searches/Searches;
      76: aload         5
      78: aload_1
      79: invokevirtual #16                 // Method org/graylog/plugins/map/search/MapDataSearchRequest.limit:()I
      82: aload_1
      83: invokevirtual #17                 // Method org/graylog/plugins/map/search/MapDataSearchRequest.query:()Ljava/lang/String;
      86: aload_3
      87: aload_1
      88: invokevirtual #18                 // Method org/graylog/plugins/map/search/MapDataSearchRequest.timerange:()Lorg/graylog2/plugin/indexer/searches/timeranges/TimeRange;
      91: invokevirtual #19                 // Method org/graylog2/indexer/searches/Searches.terms:(Ljava/lang/String;ILjava/lang/String;Ljava/lang/String;Lorg/graylog2/plugin/indexer/searches/timeranges/TimeRange;)Lorg/graylog2/indexer/results/TermsResult;
      94: astore        6
      96: aload_0
      97: aload         5
      99: aload         6
     101: invokevirtual #20                 // Method org/graylog2/indexer/results/TermsResult.getTerms:()Ljava/util/Map;
     104: invokespecial #21                 // Method validateTerms:(Ljava/lang/String;Ljava/util/Map;)Ljava/util/Map;
     107: astore        7
     109: aload         6
     111: invokevirtual #22                 // Method org/graylog2/indexer/results/TermsResult.tookMs:()J
     114: aload         7
     116: aload         6
     118: invokevirtual #23                 // Method org/graylog2/indexer/results/TermsResult.getMissing:()J
     121: aload         6
     123: invokevirtual #24                 // Method org/graylog2/indexer/results/TermsResult.getOther:()J
     126: aload         6
     128: invokevirtual #25                 // Method org/graylog2/indexer/results/TermsResult.getTotal:()J
     131: aload         6
     133: invokevirtual #26                 // Method org/graylog2/indexer/results/TermsResult.getBuiltQuery:()Ljava/lang/String;
     136: invokestatic  #27                 // Method org/graylog2/rest/models/search/responses/TermsResult.create:(JLjava/util/Map;JJJLjava/lang/String;)Lorg/graylog2/rest/models/search/responses/TermsResult;
     139: astore        8
     141: aload_2
     142: aload         5
     144: aload         8
     146: invokevirtual #28                 // Method com/google/common/collect/ImmutableMap$Builder.put:(Ljava/lang/Object;Ljava/lang/Object;)Lcom/google/common/collect/ImmutableMap$Builder;
     149: pop
     150: goto          50
     153: invokestatic  #29                 // Method org/graylog/plugins/map/search/MapDataSearchResult.builder:()Lorg/graylog/plugins/map/search/MapDataSearchResult$Builder;
     156: aload_1
     157: invokevirtual #17                 // Method org/graylog/plugins/map/search/MapDataSearchRequest.query:()Ljava/lang/String;
     160: invokevirtual #30                 // Method org/graylog/plugins/map/search/MapDataSearchResult$Builder.query:(Ljava/lang/String;)Lorg/graylog/plugins/map/search/MapDataSearchResult$Builder;
     163: aload_1
     164: invokevirtual #18                 // Method org/graylog/plugins/map/search/MapDataSearchRequest.timerange:()Lorg/graylog2/plugin/indexer/searches/timeranges/TimeRange;
     167: invokevirtual #31                 // Method org/graylog/plugins/map/search/MapDataSearchResult$Builder.timerange:(Lorg/graylog2/plugin/indexer/searches/timeranges/TimeRange;)Lorg/graylog/plugins/map/search/MapDataSearchResult$Builder;
     170: aload_1
     171: invokevirtual #16                 // Method org/graylog/plugins/map/search/MapDataSearchRequest.limit:()I
     174: invokevirtual #32                 // Method org/graylog/plugins/map/search/MapDataSearchResult$Builder.limit:(I)Lorg/graylog/plugins/map/search/MapDataSearchResult$Builder;
     177: aload_1
     178: invokevirtual #4                  // Method org/graylog/plugins/map/search/MapDataSearchRequest.streamId:()Ljava/lang/String;
     181: invokevirtual #33                 // Method org/graylog/plugins/map/search/MapDataSearchResult$Builder.streamId:(Ljava/lang/String;)Lorg/graylog/plugins/map/search/MapDataSearchResult$Builder;
     184: aload_2
     185: invokevirtual #34                 // Method com/google/common/collect/ImmutableMap$Builder.build:()Lcom/google/common/collect/ImmutableMap;
     188: invokevirtual #35                 // Method org/graylog/plugins/map/search/MapDataSearchResult$Builder.fields:(Ljava/util/Map;)Lorg/graylog/plugins/map/search/MapDataSearchResult$Builder;
     191: invokevirtual #36                 // Method org/graylog/plugins/map/search/MapDataSearchResult$Builder.build:()Lorg/graylog/plugins/map/search/MapDataSearchResult;
     194: areturn

  private java.util.Map<java.lang.String, java.lang.Long> validateTerms(java.lang.String, java.util.Map<java.lang.String, java.lang.Long>) throws org.graylog.plugins.map.search.MapDataSearch$ValueTypeException;
    Code:
       0: bipush        44
       2: invokestatic  #37                 // Method com/google/common/base/Splitter.on:(C)Lcom/google/common/base/Splitter;
       5: invokevirtual #38                 // Method com/google/common/base/Splitter.omitEmptyStrings:()Lcom/google/common/base/Splitter;
       8: invokevirtual #39                 // Method com/google/common/base/Splitter.trimResults:()Lcom/google/common/base/Splitter;
      11: astore_3
      12: aload_2
      13: invokeinterface #40,  1           // InterfaceMethod java/util/Map.keySet:()Ljava/util/Set;
      18: invokeinterface #12,  1           // InterfaceMethod java/util/Set.iterator:()Ljava/util/Iterator;
      23: astore        4
      25: aload         4
      27: invokeinterface #13,  1           // InterfaceMethod java/util/Iterator.hasNext:()Z
      32: ifeq          144
      35: aload         4
      37: invokeinterface #14,  1           // InterfaceMethod java/util/Iterator.next:()Ljava/lang/Object;
      42: checkcast     #15                 // class java/lang/String
      45: astore        5
      47: aload         5
      49: invokestatic  #5                  // Method com/google/common/base/Strings.isNullOrEmpty:(Ljava/lang/String;)Z
      52: ifeq          58
      55: goto          25
      58: aload_3
      59: aload         5
      61: invokevirtual #41                 // Method com/google/common/base/Splitter.splitToList:(Ljava/lang/CharSequence;)Ljava/util/List;
      64: astore        6
      66: aload         6
      68: invokeinterface #42,  1           // InterfaceMethod java/util/List.size:()I
      73: iconst_2
      74: if_icmpeq     85
      77: aload_0
      78: aload_1
      79: aload         5
      81: invokespecial #43                 // Method getValueTypeException:(Ljava/lang/String;Ljava/lang/String;)Lorg/graylog/plugins/map/search/MapDataSearch$ValueTypeException;
      84: athrow
      85: aload         6
      87: invokeinterface #44,  1           // InterfaceMethod java/util/List.iterator:()Ljava/util/Iterator;
      92: astore        7
      94: aload         7
      96: invokeinterface #13,  1           // InterfaceMethod java/util/Iterator.hasNext:()Z
     101: ifeq          141
     104: aload         7
     106: invokeinterface #14,  1           // InterfaceMethod java/util/Iterator.next:()Ljava/lang/Object;
     111: checkcast     #15                 // class java/lang/String
     114: astore        8
     116: getstatic     #45                 // Field VALIDATION_PATTERN:Ljava/util/regex/Pattern;
     119: aload         8
     121: invokevirtual #46                 // Method java/util/regex/Pattern.matcher:(Ljava/lang/CharSequence;)Ljava/util/regex/Matcher;
     124: invokevirtual #47                 // Method java/util/regex/Matcher.matches:()Z
     127: ifne          138
     130: aload_0
     131: aload_1
     132: aload         5
     134: invokespecial #43                 // Method getValueTypeException:(Ljava/lang/String;Ljava/lang/String;)Lorg/graylog/plugins/map/search/MapDataSearch$ValueTypeException;
     137: athrow
     138: goto          94
     141: goto          25
     144: aload_2
     145: areturn

  private org.graylog.plugins.map.search.MapDataSearch$ValueTypeException getValueTypeException(java.lang.String, java.lang.String);
    Code:
       0: new           #48                 // class org/graylog/plugins/map/search/MapDataSearch$ValueTypeException
       3: dup
       4: new           #6                  // class java/lang/StringBuilder
       7: dup
       8: invokespecial #7                  // Method java/lang/StringBuilder."<init>":()V
      11: ldc           #49                 // String Invalid geo data term for field \"
      13: invokevirtual #9                  // Method java/lang/StringBuilder.append:(Ljava/lang/String;)Ljava/lang/StringBuilder;
      16: aload_1
      17: invokevirtual #9                  // Method java/lang/StringBuilder.append:(Ljava/lang/String;)Ljava/lang/StringBuilder;
      20: ldc           #50                 // String \":
      22: invokevirtual #9                  // Method java/lang/StringBuilder.append:(Ljava/lang/String;)Ljava/lang/StringBuilder;
      25: aload_2
      26: invokevirtual #9                  // Method java/lang/StringBuilder.append:(Ljava/lang/String;)Ljava/lang/StringBuilder;
      29: ldc           #51                 // String  (required: <lat>,<lng> - example: 1.23,3.11)
      31: invokevirtual #9                  // Method java/lang/StringBuilder.append:(Ljava/lang/String;)Ljava/lang/StringBuilder;
      34: invokevirtual #10                 // Method java/lang/StringBuilder.toString:()Ljava/lang/String;
      37: invokespecial #52                 // Method org/graylog/plugins/map/search/MapDataSearch$ValueTypeException."<init>":(Ljava/lang/String;)V
      40: areturn

  static {};
    Code:
       0: ldc           #53                 // String ^-?\\d+\\.\\d+$
       2: invokestatic  #54                 // Method java/util/regex/Pattern.compile:(Ljava/lang/String;)Ljava/util/regex/Pattern;
       5: putstatic     #45                 // Field VALIDATION_PATTERN:Ljava/util/regex/Pattern;
       8: return
}
