Compiled from "StringParameterParser.java"
final class org.apache.logging.log4j.layout.template.json.util.StringParameterParser$Parser implements java.util.concurrent.Callable<java.util.Map<java.lang.String, org.apache.logging.log4j.layout.template.json.util.StringParameterParser$Value>> {
  private final java.lang.String input;

  private final java.util.Map<java.lang.String, org.apache.logging.log4j.layout.template.json.util.StringParameterParser$Value> map;

  private org.apache.logging.log4j.layout.template.json.util.StringParameterParser$State state;

  private int i;

  private java.lang.String key;

  private org.apache.logging.log4j.layout.template.json.util.StringParameterParser$Parser(java.lang.String);
    Code:
       0: aload_0
       1: invokespecial #2                  // Method java/lang/Object."<init>":()V
       4: aload_0
       5: aload_1
       6: ldc           #3                  // String input
       8: invokestatic  #4                  // Method java/util/Objects.requireNonNull:(Ljava/lang/Object;Ljava/lang/String;)Ljava/lang/Object;
      11: checkcast     #5                  // class java/lang/String
      14: putfield      #6                  // Field input:Ljava/lang/String;
      17: aload_0
      18: new           #7                  // class java/util/LinkedHashMap
      21: dup
      22: invokespecial #8                  // Method java/util/LinkedHashMap."<init>":()V
      25: putfield      #9                  // Field map:Ljava/util/Map;
      28: aload_0
      29: getstatic     #10                 // Field org/apache/logging/log4j/layout/template/json/util/StringParameterParser$State.READING_KEY:Lorg/apache/logging/log4j/layout/template/json/util/StringParameterParser$State;
      32: putfield      #11                 // Field state:Lorg/apache/logging/log4j/layout/template/json/util/StringParameterParser$State;
      35: aload_0
      36: iconst_0
      37: putfield      #12                 // Field i:I
      40: aload_0
      41: aconst_null
      42: putfield      #13                 // Field key:Ljava/lang/String;
      45: return

  public java.util.Map<java.lang.String, org.apache.logging.log4j.layout.template.json.util.StringParameterParser$Value> call();
    Code:
       0: aload_0
       1: invokespecial #14                 // Method skipWhitespace:()V
       4: aload_0
       5: getfield      #12                 // Field i:I
       8: aload_0
       9: getfield      #6                  // Field input:Ljava/lang/String;
      12: invokevirtual #15                 // Method java/lang/String.length:()I
      15: if_icmplt     21
      18: goto          104
      21: getstatic     #16                 // Field org/apache/logging/log4j/layout/template/json/util/StringParameterParser$1.$SwitchMap$org$apache$logging$log4j$layout$template$json$util$StringParameterParser$State:[I
      24: aload_0
      25: getfield      #11                 // Field state:Lorg/apache/logging/log4j/layout/template/json/util/StringParameterParser$State;
      28: invokevirtual #17                 // Method org/apache/logging/log4j/layout/template/json/util/StringParameterParser$State.ordinal:()I
      31: iaload
      32: lookupswitch  { // 2
                     1: 60
                     2: 67
               default: 74
          }
      60: aload_0
      61: invokespecial #18                 // Method readKey:()V
      64: goto          0
      67: aload_0
      68: invokespecial #19                 // Method readValue:()V
      71: goto          0
      74: new           #20                 // class java/lang/IllegalStateException
      77: dup
      78: new           #21                 // class java/lang/StringBuilder
      81: dup
      82: invokespecial #22                 // Method java/lang/StringBuilder."<init>":()V
      85: ldc           #23                 // String unknown state:
      87: invokevirtual #24                 // Method java/lang/StringBuilder.append:(Ljava/lang/String;)Ljava/lang/StringBuilder;
      90: aload_0
      91: getfield      #11                 // Field state:Lorg/apache/logging/log4j/layout/template/json/util/StringParameterParser$State;
      94: invokevirtual #25                 // Method java/lang/StringBuilder.append:(Ljava/lang/Object;)Ljava/lang/StringBuilder;
      97: invokevirtual #26                 // Method java/lang/StringBuilder.toString:()Ljava/lang/String;
     100: invokespecial #27                 // Method java/lang/IllegalStateException."<init>":(Ljava/lang/String;)V
     103: athrow
     104: aload_0
     105: getfield      #11                 // Field state:Lorg/apache/logging/log4j/layout/template/json/util/StringParameterParser$State;
     108: getstatic     #28                 // Field org/apache/logging/log4j/layout/template/json/util/StringParameterParser$State.READING_VALUE:Lorg/apache/logging/log4j/layout/template/json/util/StringParameterParser$State;
     111: if_acmpne     131
     114: aload_0
     115: getfield      #9                  // Field map:Ljava/util/Map;
     118: aload_0
     119: getfield      #13                 // Field key:Ljava/lang/String;
     122: invokestatic  #29                 // Method org/apache/logging/log4j/layout/template/json/util/StringParameterParser$Values.nullValue:()Lorg/apache/logging/log4j/layout/template/json/util/StringParameterParser$NullValue;
     125: invokeinterface #30,  3           // InterfaceMethod java/util/Map.put:(Ljava/lang/Object;Ljava/lang/Object;)Ljava/lang/Object;
     130: pop
     131: aload_0
     132: getfield      #9                  // Field map:Ljava/util/Map;
     135: areturn

  private void readKey();
    Code:
       0: aload_0
       1: getfield      #6                  // Field input:Ljava/lang/String;
       4: bipush        61
       6: aload_0
       7: getfield      #12                 // Field i:I
      10: invokevirtual #31                 // Method java/lang/String.indexOf:(II)I
      13: istore_1
      14: aload_0
      15: getfield      #6                  // Field input:Ljava/lang/String;
      18: bipush        44
      20: aload_0
      21: getfield      #12                 // Field i:I
      24: invokevirtual #31                 // Method java/lang/String.indexOf:(II)I
      27: istore_2
      28: iload_1
      29: ifge          50
      32: iload_2
      33: ifge          50
      36: aload_0
      37: getfield      #6                  // Field input:Ljava/lang/String;
      40: invokevirtual #15                 // Method java/lang/String.length:()I
      43: dup
      44: istore        4
      46: istore_3
      47: goto          96
      50: iload_1
      51: ifge          62
      54: iload_2
      55: dup
      56: istore        4
      58: istore_3
      59: goto          96
      62: iload_2
      63: ifge          76
      66: iload_1
      67: istore_3
      68: iload_1
      69: iconst_1
      70: iadd
      71: istore        4
      73: goto          96
      76: iload_1
      77: iload_2
      78: if_icmpge     91
      81: iload_1
      82: istore_3
      83: iload_1
      84: iconst_1
      85: iadd
      86: istore        4
      88: goto          96
      91: iload_2
      92: istore_3
      93: iload_2
      94: istore        4
      96: aload_0
      97: aload_0
      98: getfield      #6                  // Field input:Ljava/lang/String;
     101: aload_0
     102: getfield      #12                 // Field i:I
     105: iload_3
     106: invokevirtual #32                 // Method java/lang/String.substring:(II)Ljava/lang/String;
     109: invokevirtual #33                 // Method java/lang/String.trim:()Ljava/lang/String;
     112: putfield      #13                 // Field key:Ljava/lang/String;
     115: aload_0
     116: getfield      #13                 // Field key:Ljava/lang/String;
     119: invokestatic  #34                 // Method org/apache/logging/log4j/util/Strings.isEmpty:(Ljava/lang/CharSequence;)Z
     122: ifeq          163
     125: ldc           #35                 // String failed to locate key at index %d: %s
     127: iconst_2
     128: anewarray     #36                 // class java/lang/Object
     131: dup
     132: iconst_0
     133: aload_0
     134: getfield      #12                 // Field i:I
     137: invokestatic  #37                 // Method java/lang/Integer.valueOf:(I)Ljava/lang/Integer;
     140: aastore
     141: dup
     142: iconst_1
     143: aload_0
     144: getfield      #6                  // Field input:Ljava/lang/String;
     147: aastore
     148: invokestatic  #38                 // Method java/lang/String.format:(Ljava/lang/String;[Ljava/lang/Object;)Ljava/lang/String;
     151: astore        5
     153: new           #39                 // class java/lang/IllegalArgumentException
     156: dup
     157: aload         5
     159: invokespecial #40                 // Method java/lang/IllegalArgumentException."<init>":(Ljava/lang/String;)V
     162: athrow
     163: aload_0
     164: getfield      #9                  // Field map:Ljava/util/Map;
     167: aload_0
     168: getfield      #13                 // Field key:Ljava/lang/String;
     171: invokeinterface #41,  2           // InterfaceMethod java/util/Map.containsKey:(Ljava/lang/Object;)Z
     176: ifeq          217
     179: ldc           #42                 // String conflicting key at index %d: %s
     181: iconst_2
     182: anewarray     #36                 // class java/lang/Object
     185: dup
     186: iconst_0
     187: aload_0
     188: getfield      #12                 // Field i:I
     191: invokestatic  #37                 // Method java/lang/Integer.valueOf:(I)Ljava/lang/Integer;
     194: aastore
     195: dup
     196: iconst_1
     197: aload_0
     198: getfield      #6                  // Field input:Ljava/lang/String;
     201: aastore
     202: invokestatic  #38                 // Method java/lang/String.format:(Ljava/lang/String;[Ljava/lang/Object;)Ljava/lang/String;
     205: astore        5
     207: new           #39                 // class java/lang/IllegalArgumentException
     210: dup
     211: aload         5
     213: invokespecial #40                 // Method java/lang/IllegalArgumentException."<init>":(Ljava/lang/String;)V
     216: athrow
     217: aload_0
     218: getstatic     #28                 // Field org/apache/logging/log4j/layout/template/json/util/StringParameterParser$State.READING_VALUE:Lorg/apache/logging/log4j/layout/template/json/util/StringParameterParser$State;
     221: putfield      #11                 // Field state:Lorg/apache/logging/log4j/layout/template/json/util/StringParameterParser$State;
     224: aload_0
     225: iload         4
     227: putfield      #12                 // Field i:I
     230: return

  private void readValue();
    Code:
       0: aload_0
       1: getfield      #6                  // Field input:Ljava/lang/String;
       4: aload_0
       5: getfield      #12                 // Field i:I
       8: invokevirtual #43                 // Method java/lang/String.charAt:(I)C
      11: bipush        34
      13: if_icmpne     20
      16: iconst_1
      17: goto          21
      20: iconst_0
      21: istore_1
      22: iload_1
      23: ifeq          33
      26: aload_0
      27: invokespecial #44                 // Method readDoubleQuotedStringValue:()V
      30: goto          37
      33: aload_0
      34: invokespecial #45                 // Method readStringValue:()V
      37: aload_0
      38: aconst_null
      39: putfield      #13                 // Field key:Ljava/lang/String;
      42: aload_0
      43: getstatic     #10                 // Field org/apache/logging/log4j/layout/template/json/util/StringParameterParser$State.READING_KEY:Lorg/apache/logging/log4j/layout/template/json/util/StringParameterParser$State;
      46: putfield      #11                 // Field state:Lorg/apache/logging/log4j/layout/template/json/util/StringParameterParser$State;
      49: return

  private void readDoubleQuotedStringValue();
    Code:
       0: aload_0
       1: getfield      #12                 // Field i:I
       4: iconst_1
       5: iadd
       6: istore_1
       7: iload_1
       8: aload_0
       9: getfield      #6                  // Field input:Ljava/lang/String;
      12: invokevirtual #15                 // Method java/lang/String.length:()I
      15: if_icmpge     55
      18: aload_0
      19: getfield      #6                  // Field input:Ljava/lang/String;
      22: iload_1
      23: invokevirtual #43                 // Method java/lang/String.charAt:(I)C
      26: bipush        34
      28: if_icmpne     49
      31: aload_0
      32: getfield      #6                  // Field input:Ljava/lang/String;
      35: iload_1
      36: iconst_1
      37: isub
      38: invokevirtual #43                 // Method java/lang/String.charAt:(I)C
      41: bipush        92
      43: if_icmpeq     49
      46: goto          55
      49: iinc          1, 1
      52: goto          7
      55: iload_1
      56: aload_0
      57: getfield      #6                  // Field input:Ljava/lang/String;
      60: invokevirtual #15                 // Method java/lang/String.length:()I
      63: if_icmplt     102
      66: ldc           #46                 // String failed to locate the end of double-quoted content starting at index %d: %s
      68: iconst_2
      69: anewarray     #36                 // class java/lang/Object
      72: dup
      73: iconst_0
      74: aload_0
      75: getfield      #12                 // Field i:I
      78: invokestatic  #37                 // Method java/lang/Integer.valueOf:(I)Ljava/lang/Integer;
      81: aastore
      82: dup
      83: iconst_1
      84: aload_0
      85: getfield      #6                  // Field input:Ljava/lang/String;
      88: aastore
      89: invokestatic  #38                 // Method java/lang/String.format:(Ljava/lang/String;[Ljava/lang/Object;)Ljava/lang/String;
      92: astore_2
      93: new           #39                 // class java/lang/IllegalArgumentException
      96: dup
      97: aload_2
      98: invokespecial #40                 // Method java/lang/IllegalArgumentException."<init>":(Ljava/lang/String;)V
     101: athrow
     102: aload_0
     103: getfield      #6                  // Field input:Ljava/lang/String;
     106: aload_0
     107: getfield      #12                 // Field i:I
     110: iconst_1
     111: iadd
     112: iload_1
     113: invokevirtual #32                 // Method java/lang/String.substring:(II)Ljava/lang/String;
     116: ldc           #47                 // String \\\\\"
     118: ldc           #48                 // String \"
     120: invokevirtual #49                 // Method java/lang/String.replaceAll:(Ljava/lang/String;Ljava/lang/String;)Ljava/lang/String;
     123: astore_2
     124: aload_2
     125: invokestatic  #50                 // Method org/apache/logging/log4j/layout/template/json/util/StringParameterParser$Values.doubleQuotedStringValue:(Ljava/lang/String;)Lorg/apache/logging/log4j/layout/template/json/util/StringParameterParser$DoubleQuotedStringValue;
     128: astore_3
     129: aload_0
     130: getfield      #9                  // Field map:Ljava/util/Map;
     133: aload_0
     134: getfield      #13                 // Field key:Ljava/lang/String;
     137: aload_3
     138: invokeinterface #30,  3           // InterfaceMethod java/util/Map.put:(Ljava/lang/Object;Ljava/lang/Object;)Ljava/lang/Object;
     143: pop
     144: aload_0
     145: iload_1
     146: iconst_1
     147: iadd
     148: putfield      #12                 // Field i:I
     151: aload_0
     152: invokespecial #14                 // Method skipWhitespace:()V
     155: aload_0
     156: getfield      #12                 // Field i:I
     159: aload_0
     160: getfield      #6                  // Field input:Ljava/lang/String;
     163: invokevirtual #15                 // Method java/lang/String.length:()I
     166: if_icmpge     233
     169: aload_0
     170: getfield      #6                  // Field input:Ljava/lang/String;
     173: aload_0
     174: getfield      #12                 // Field i:I
     177: invokevirtual #43                 // Method java/lang/String.charAt:(I)C
     180: bipush        44
     182: if_icmpeq     223
     185: ldc           #51                 // String was expecting comma at index %d: %s
     187: iconst_2
     188: anewarray     #36                 // class java/lang/Object
     191: dup
     192: iconst_0
     193: aload_0
     194: getfield      #12                 // Field i:I
     197: invokestatic  #37                 // Method java/lang/Integer.valueOf:(I)Ljava/lang/Integer;
     200: aastore
     201: dup
     202: iconst_1
     203: aload_0
     204: getfield      #6                  // Field input:Ljava/lang/String;
     207: aastore
     208: invokestatic  #38                 // Method java/lang/String.format:(Ljava/lang/String;[Ljava/lang/Object;)Ljava/lang/String;
     211: astore        4
     213: new           #39                 // class java/lang/IllegalArgumentException
     216: dup
     217: aload         4
     219: invokespecial #40                 // Method java/lang/IllegalArgumentException."<init>":(Ljava/lang/String;)V
     222: athrow
     223: aload_0
     224: dup
     225: getfield      #12                 // Field i:I
     228: iconst_1
     229: iadd
     230: putfield      #12                 // Field i:I
     233: return

  private void skipWhitespace();
    Code:
       0: aload_0
       1: getfield      #12                 // Field i:I
       4: aload_0
       5: getfield      #6                  // Field input:Ljava/lang/String;
       8: invokevirtual #15                 // Method java/lang/String.length:()I
      11: if_icmpge     49
      14: aload_0
      15: getfield      #6                  // Field input:Ljava/lang/String;
      18: aload_0
      19: getfield      #12                 // Field i:I
      22: invokevirtual #43                 // Method java/lang/String.charAt:(I)C
      25: istore_1
      26: iload_1
      27: invokestatic  #52                 // Method java/lang/Character.isWhitespace:(C)Z
      30: ifne          36
      33: goto          49
      36: aload_0
      37: dup
      38: getfield      #12                 // Field i:I
      41: iconst_1
      42: iadd
      43: putfield      #12                 // Field i:I
      46: goto          0
      49: return

  private void readStringValue();
    Code:
       0: aload_0
       1: getfield      #6                  // Field input:Ljava/lang/String;
       4: bipush        44
       6: aload_0
       7: getfield      #12                 // Field i:I
      10: invokevirtual #31                 // Method java/lang/String.indexOf:(II)I
      13: istore_1
      14: iload_1
      15: ifge          26
      18: aload_0
      19: getfield      #6                  // Field input:Ljava/lang/String;
      22: invokevirtual #15                 // Method java/lang/String.length:()I
      25: istore_1
      26: aload_0
      27: getfield      #6                  // Field input:Ljava/lang/String;
      30: aload_0
      31: getfield      #12                 // Field i:I
      34: iload_1
      35: invokevirtual #32                 // Method java/lang/String.substring:(II)Ljava/lang/String;
      38: astore_2
      39: aload_2
      40: invokevirtual #33                 // Method java/lang/String.trim:()Ljava/lang/String;
      43: astore_3
      44: aload_3
      45: invokevirtual #53                 // Method java/lang/String.isEmpty:()Z
      48: ifeq          57
      51: invokestatic  #29                 // Method org/apache/logging/log4j/layout/template/json/util/StringParameterParser$Values.nullValue:()Lorg/apache/logging/log4j/layout/template/json/util/StringParameterParser$NullValue;
      54: goto          61
      57: aload_3
      58: invokestatic  #54                 // Method org/apache/logging/log4j/layout/template/json/util/StringParameterParser$Values.stringValue:(Ljava/lang/String;)Lorg/apache/logging/log4j/layout/template/json/util/StringParameterParser$StringValue;
      61: astore        4
      63: aload_0
      64: getfield      #9                  // Field map:Ljava/util/Map;
      67: aload_0
      68: getfield      #13                 // Field key:Ljava/lang/String;
      71: aload         4
      73: invokeinterface #30,  3           // InterfaceMethod java/util/Map.put:(Ljava/lang/Object;Ljava/lang/Object;)Ljava/lang/Object;
      78: pop
      79: aload_0
      80: dup
      81: getfield      #12                 // Field i:I
      84: aload_2
      85: invokevirtual #15                 // Method java/lang/String.length:()I
      88: iconst_1
      89: iadd
      90: iadd
      91: putfield      #12                 // Field i:I
      94: return

  public java.lang.Object call() throws java.lang.Exception;
    Code:
       0: aload_0
       1: invokevirtual #55                 // Method call:()Ljava/util/Map;
       4: areturn

  org.apache.logging.log4j.layout.template.json.util.StringParameterParser$Parser(java.lang.String, org.apache.logging.log4j.layout.template.json.util.StringParameterParser$1);
    Code:
       0: aload_0
       1: aload_1
       2: invokespecial #1                  // Method "<init>":(Ljava/lang/String;)V
       5: return
}
