Compiled from "BeanDeserializer.java"
public class io.dekorate.deps.jackson.databind.deser.BeanDeserializer extends io.dekorate.deps.jackson.databind.deser.BeanDeserializerBase implements java.io.Serializable {
  private static final long serialVersionUID;

  protected transient java.lang.Exception _nullFromCreator;

  private volatile transient io.dekorate.deps.jackson.databind.util.NameTransformer _currentlyTransforming;

  public io.dekorate.deps.jackson.databind.deser.BeanDeserializer(io.dekorate.deps.jackson.databind.deser.BeanDeserializerBuilder, io.dekorate.deps.jackson.databind.BeanDescription, io.dekorate.deps.jackson.databind.deser.impl.BeanPropertyMap, java.util.Map<java.lang.String, io.dekorate.deps.jackson.databind.deser.SettableBeanProperty>, java.util.HashSet<java.lang.String>, boolean, boolean);
    Code:
       0: aload_0
       1: aload_1
       2: aload_2
       3: aload_3
       4: aload         4
       6: aload         5
       8: iload         6
      10: iload         7
      12: invokespecial #31                 // Method io/dekorate/deps/jackson/databind/deser/BeanDeserializerBase."<init>":(Lio/dekorate/deps/jackson/databind/deser/BeanDeserializerBuilder;Lio/dekorate/deps/jackson/databind/BeanDescription;Lio/dekorate/deps/jackson/databind/deser/impl/BeanPropertyMap;Ljava/util/Map;Ljava/util/Set;ZZ)V
      15: return

  protected io.dekorate.deps.jackson.databind.deser.BeanDeserializer(io.dekorate.deps.jackson.databind.deser.BeanDeserializerBase);
    Code:
       0: aload_0
       1: aload_1
       2: aload_1
       3: getfield      #52                 // Field io/dekorate/deps/jackson/databind/deser/BeanDeserializerBase._ignoreAllUnknown:Z
       6: invokespecial #55                 // Method io/dekorate/deps/jackson/databind/deser/BeanDeserializerBase."<init>":(Lio/dekorate/deps/jackson/databind/deser/BeanDeserializerBase;Z)V
       9: return

  protected io.dekorate.deps.jackson.databind.deser.BeanDeserializer(io.dekorate.deps.jackson.databind.deser.BeanDeserializerBase, boolean);
    Code:
       0: aload_0
       1: aload_1
       2: iload_2
       3: invokespecial #55                 // Method io/dekorate/deps/jackson/databind/deser/BeanDeserializerBase."<init>":(Lio/dekorate/deps/jackson/databind/deser/BeanDeserializerBase;Z)V
       6: return

  protected io.dekorate.deps.jackson.databind.deser.BeanDeserializer(io.dekorate.deps.jackson.databind.deser.BeanDeserializerBase, io.dekorate.deps.jackson.databind.util.NameTransformer);
    Code:
       0: aload_0
       1: aload_1
       2: aload_2
       3: invokespecial #60                 // Method io/dekorate/deps/jackson/databind/deser/BeanDeserializerBase."<init>":(Lio/dekorate/deps/jackson/databind/deser/BeanDeserializerBase;Lio/dekorate/deps/jackson/databind/util/NameTransformer;)V
       6: return

  public io.dekorate.deps.jackson.databind.deser.BeanDeserializer(io.dekorate.deps.jackson.databind.deser.BeanDeserializerBase, io.dekorate.deps.jackson.databind.deser.impl.ObjectIdReader);
    Code:
       0: aload_0
       1: aload_1
       2: aload_2
       3: invokespecial #64                 // Method io/dekorate/deps/jackson/databind/deser/BeanDeserializerBase."<init>":(Lio/dekorate/deps/jackson/databind/deser/BeanDeserializerBase;Lio/dekorate/deps/jackson/databind/deser/impl/ObjectIdReader;)V
       6: return

  public io.dekorate.deps.jackson.databind.deser.BeanDeserializer(io.dekorate.deps.jackson.databind.deser.BeanDeserializerBase, java.util.Set<java.lang.String>);
    Code:
       0: aload_0
       1: aload_1
       2: aload_2
       3: invokespecial #70                 // Method io/dekorate/deps/jackson/databind/deser/BeanDeserializerBase."<init>":(Lio/dekorate/deps/jackson/databind/deser/BeanDeserializerBase;Ljava/util/Set;)V
       6: return

  public io.dekorate.deps.jackson.databind.deser.BeanDeserializer(io.dekorate.deps.jackson.databind.deser.BeanDeserializerBase, io.dekorate.deps.jackson.databind.deser.impl.BeanPropertyMap);
    Code:
       0: aload_0
       1: aload_1
       2: aload_2
       3: invokespecial #75                 // Method io/dekorate/deps/jackson/databind/deser/BeanDeserializerBase."<init>":(Lio/dekorate/deps/jackson/databind/deser/BeanDeserializerBase;Lio/dekorate/deps/jackson/databind/deser/impl/BeanPropertyMap;)V
       6: return

  public io.dekorate.deps.jackson.databind.JsonDeserializer<java.lang.Object> unwrappingDeserializer(io.dekorate.deps.jackson.databind.util.NameTransformer);
    Code:
       0: aload_0
       1: invokevirtual #85                 // Method java/lang/Object.getClass:()Ljava/lang/Class;
       4: ldc           #2                  // class io/dekorate/deps/jackson/databind/deser/BeanDeserializer
       6: if_acmpeq     11
       9: aload_0
      10: areturn
      11: aload_0
      12: getfield      #87                 // Field _currentlyTransforming:Lio/dekorate/deps/jackson/databind/util/NameTransformer;
      15: aload_1
      16: if_acmpne     21
      19: aload_0
      20: areturn
      21: aload_0
      22: aload_1
      23: putfield      #87                 // Field _currentlyTransforming:Lio/dekorate/deps/jackson/databind/util/NameTransformer;
      26: new           #2                  // class io/dekorate/deps/jackson/databind/deser/BeanDeserializer
      29: dup
      30: aload_0
      31: aload_1
      32: invokespecial #88                 // Method "<init>":(Lio/dekorate/deps/jackson/databind/deser/BeanDeserializerBase;Lio/dekorate/deps/jackson/databind/util/NameTransformer;)V
      35: astore_2
      36: aload_0
      37: aconst_null
      38: putfield      #87                 // Field _currentlyTransforming:Lio/dekorate/deps/jackson/databind/util/NameTransformer;
      41: aload_2
      42: areturn
      43: astore_3
      44: aload_0
      45: aconst_null
      46: putfield      #87                 // Field _currentlyTransforming:Lio/dekorate/deps/jackson/databind/util/NameTransformer;
      49: aload_3
      50: athrow
    Exception table:
       from    to  target type
          26    36    43   any

  public io.dekorate.deps.jackson.databind.deser.BeanDeserializer withObjectIdReader(io.dekorate.deps.jackson.databind.deser.impl.ObjectIdReader);
    Code:
       0: new           #2                  // class io/dekorate/deps/jackson/databind/deser/BeanDeserializer
       3: dup
       4: aload_0
       5: aload_1
       6: invokespecial #94                 // Method "<init>":(Lio/dekorate/deps/jackson/databind/deser/BeanDeserializerBase;Lio/dekorate/deps/jackson/databind/deser/impl/ObjectIdReader;)V
       9: areturn

  public io.dekorate.deps.jackson.databind.deser.BeanDeserializer withIgnorableProperties(java.util.Set<java.lang.String>);
    Code:
       0: new           #2                  // class io/dekorate/deps/jackson/databind/deser/BeanDeserializer
       3: dup
       4: aload_0
       5: aload_1
       6: invokespecial #98                 // Method "<init>":(Lio/dekorate/deps/jackson/databind/deser/BeanDeserializerBase;Ljava/util/Set;)V
       9: areturn

  public io.dekorate.deps.jackson.databind.deser.BeanDeserializerBase withBeanProperties(io.dekorate.deps.jackson.databind.deser.impl.BeanPropertyMap);
    Code:
       0: new           #2                  // class io/dekorate/deps/jackson/databind/deser/BeanDeserializer
       3: dup
       4: aload_0
       5: aload_1
       6: invokespecial #101                // Method "<init>":(Lio/dekorate/deps/jackson/databind/deser/BeanDeserializerBase;Lio/dekorate/deps/jackson/databind/deser/impl/BeanPropertyMap;)V
       9: areturn

  protected io.dekorate.deps.jackson.databind.deser.BeanDeserializerBase asArrayDeserializer();
    Code:
       0: aload_0
       1: getfield      #106                // Field _beanProperties:Lio/dekorate/deps/jackson/databind/deser/impl/BeanPropertyMap;
       4: invokevirtual #112                // Method io/dekorate/deps/jackson/databind/deser/impl/BeanPropertyMap.getPropertiesInInsertionOrder:()[Lio/dekorate/deps/jackson/databind/deser/SettableBeanProperty;
       7: astore_1
       8: new           #114                // class io/dekorate/deps/jackson/databind/deser/impl/BeanAsArrayDeserializer
      11: dup
      12: aload_0
      13: aload_1
      14: invokespecial #117                // Method io/dekorate/deps/jackson/databind/deser/impl/BeanAsArrayDeserializer."<init>":(Lio/dekorate/deps/jackson/databind/deser/BeanDeserializerBase;[Lio/dekorate/deps/jackson/databind/deser/SettableBeanProperty;)V
      17: areturn

  public java.lang.Object deserialize(io.dekorate.deps.jackson.core.JsonParser, io.dekorate.deps.jackson.databind.DeserializationContext) throws java.io.IOException;
    Code:
       0: aload_1
       1: invokevirtual #128                // Method io/dekorate/deps/jackson/core/JsonParser.isExpectedStartObjectToken:()Z
       4: ifeq          51
       7: aload_0
       8: getfield      #131                // Field _vanillaProcessing:Z
      11: ifeq          25
      14: aload_0
      15: aload_1
      16: aload_2
      17: aload_1
      18: invokevirtual #135                // Method io/dekorate/deps/jackson/core/JsonParser.nextToken:()Lio/dekorate/deps/jackson/core/JsonToken;
      21: invokespecial #139                // Method vanillaDeserialize:(Lio/dekorate/deps/jackson/core/JsonParser;Lio/dekorate/deps/jackson/databind/DeserializationContext;Lio/dekorate/deps/jackson/core/JsonToken;)Ljava/lang/Object;
      24: areturn
      25: aload_1
      26: invokevirtual #135                // Method io/dekorate/deps/jackson/core/JsonParser.nextToken:()Lio/dekorate/deps/jackson/core/JsonToken;
      29: pop
      30: aload_0
      31: getfield      #142                // Field _objectIdReader:Lio/dekorate/deps/jackson/databind/deser/impl/ObjectIdReader;
      34: ifnull        44
      37: aload_0
      38: aload_1
      39: aload_2
      40: invokevirtual #145                // Method deserializeWithObjectId:(Lio/dekorate/deps/jackson/core/JsonParser;Lio/dekorate/deps/jackson/databind/DeserializationContext;)Ljava/lang/Object;
      43: areturn
      44: aload_0
      45: aload_1
      46: aload_2
      47: invokevirtual #148                // Method deserializeFromObject:(Lio/dekorate/deps/jackson/core/JsonParser;Lio/dekorate/deps/jackson/databind/DeserializationContext;)Ljava/lang/Object;
      50: areturn
      51: aload_0
      52: aload_1
      53: aload_2
      54: aload_1
      55: invokevirtual #151                // Method io/dekorate/deps/jackson/core/JsonParser.getCurrentToken:()Lio/dekorate/deps/jackson/core/JsonToken;
      58: invokevirtual #154                // Method _deserializeOther:(Lio/dekorate/deps/jackson/core/JsonParser;Lio/dekorate/deps/jackson/databind/DeserializationContext;Lio/dekorate/deps/jackson/core/JsonToken;)Ljava/lang/Object;
      61: areturn

  protected final java.lang.Object _deserializeOther(io.dekorate.deps.jackson.core.JsonParser, io.dekorate.deps.jackson.databind.DeserializationContext, io.dekorate.deps.jackson.core.JsonToken) throws java.io.IOException;
    Code:
       0: aload_3
       1: ifnull        153
       4: getstatic     #162                // Field io/dekorate/deps/jackson/databind/deser/BeanDeserializer$1.$SwitchMap$com$fasterxml$jackson$core$JsonToken:[I
       7: aload_3
       8: invokevirtual #168                // Method io/dekorate/deps/jackson/core/JsonToken.ordinal:()I
      11: iaload
      12: tableswitch   { // 1 to 10
                     1: 68
                     2: 75
                     3: 82
                     4: 89
                     5: 96
                     6: 96
                     7: 103
                     8: 110
                     9: 117
                    10: 117
               default: 153
          }
      68: aload_0
      69: aload_1
      70: aload_2
      71: invokevirtual #171                // Method deserializeFromString:(Lio/dekorate/deps/jackson/core/JsonParser;Lio/dekorate/deps/jackson/databind/DeserializationContext;)Ljava/lang/Object;
      74: areturn
      75: aload_0
      76: aload_1
      77: aload_2
      78: invokevirtual #174                // Method deserializeFromNumber:(Lio/dekorate/deps/jackson/core/JsonParser;Lio/dekorate/deps/jackson/databind/DeserializationContext;)Ljava/lang/Object;
      81: areturn
      82: aload_0
      83: aload_1
      84: aload_2
      85: invokevirtual #177                // Method deserializeFromDouble:(Lio/dekorate/deps/jackson/core/JsonParser;Lio/dekorate/deps/jackson/databind/DeserializationContext;)Ljava/lang/Object;
      88: areturn
      89: aload_0
      90: aload_1
      91: aload_2
      92: invokevirtual #180                // Method deserializeFromEmbedded:(Lio/dekorate/deps/jackson/core/JsonParser;Lio/dekorate/deps/jackson/databind/DeserializationContext;)Ljava/lang/Object;
      95: areturn
      96: aload_0
      97: aload_1
      98: aload_2
      99: invokevirtual #183                // Method deserializeFromBoolean:(Lio/dekorate/deps/jackson/core/JsonParser;Lio/dekorate/deps/jackson/databind/DeserializationContext;)Ljava/lang/Object;
     102: areturn
     103: aload_0
     104: aload_1
     105: aload_2
     106: invokevirtual #186                // Method deserializeFromNull:(Lio/dekorate/deps/jackson/core/JsonParser;Lio/dekorate/deps/jackson/databind/DeserializationContext;)Ljava/lang/Object;
     109: areturn
     110: aload_0
     111: aload_1
     112: aload_2
     113: invokevirtual #189                // Method deserializeFromArray:(Lio/dekorate/deps/jackson/core/JsonParser;Lio/dekorate/deps/jackson/databind/DeserializationContext;)Ljava/lang/Object;
     116: areturn
     117: aload_0
     118: getfield      #131                // Field _vanillaProcessing:Z
     121: ifeq          132
     124: aload_0
     125: aload_1
     126: aload_2
     127: aload_3
     128: invokespecial #139                // Method vanillaDeserialize:(Lio/dekorate/deps/jackson/core/JsonParser;Lio/dekorate/deps/jackson/databind/DeserializationContext;Lio/dekorate/deps/jackson/core/JsonToken;)Ljava/lang/Object;
     131: areturn
     132: aload_0
     133: getfield      #142                // Field _objectIdReader:Lio/dekorate/deps/jackson/databind/deser/impl/ObjectIdReader;
     136: ifnull        146
     139: aload_0
     140: aload_1
     141: aload_2
     142: invokevirtual #145                // Method deserializeWithObjectId:(Lio/dekorate/deps/jackson/core/JsonParser;Lio/dekorate/deps/jackson/databind/DeserializationContext;)Ljava/lang/Object;
     145: areturn
     146: aload_0
     147: aload_1
     148: aload_2
     149: invokevirtual #148                // Method deserializeFromObject:(Lio/dekorate/deps/jackson/core/JsonParser;Lio/dekorate/deps/jackson/databind/DeserializationContext;)Ljava/lang/Object;
     152: areturn
     153: aload_2
     154: aload_0
     155: aload_2
     156: invokevirtual #193                // Method getValueType:(Lio/dekorate/deps/jackson/databind/DeserializationContext;)Lio/dekorate/deps/jackson/databind/JavaType;
     159: aload_1
     160: invokevirtual #199                // Method io/dekorate/deps/jackson/databind/DeserializationContext.handleUnexpectedToken:(Lio/dekorate/deps/jackson/databind/JavaType;Lio/dekorate/deps/jackson/core/JsonParser;)Ljava/lang/Object;
     163: areturn

  protected java.lang.Object _missingToken(io.dekorate.deps.jackson.core.JsonParser, io.dekorate.deps.jackson.databind.DeserializationContext) throws java.io.IOException;
    Code:
       0: aload_2
       1: aload_0
       2: invokevirtual #206                // Method handledType:()Ljava/lang/Class;
       5: invokevirtual #210                // Method io/dekorate/deps/jackson/databind/DeserializationContext.endOfInputException:(Ljava/lang/Class;)Lio/dekorate/deps/jackson/databind/JsonMappingException;
       8: athrow

  public java.lang.Object deserialize(io.dekorate.deps.jackson.core.JsonParser, io.dekorate.deps.jackson.databind.DeserializationContext, java.lang.Object) throws java.io.IOException;
    Code:
       0: aload_1
       1: aload_3
       2: invokevirtual #217                // Method io/dekorate/deps/jackson/core/JsonParser.setCurrentValue:(Ljava/lang/Object;)V
       5: aload_0
       6: getfield      #221                // Field _injectables:[Lio/dekorate/deps/jackson/databind/deser/impl/ValueInjector;
       9: ifnull        18
      12: aload_0
      13: aload_2
      14: aload_3
      15: invokevirtual #225                // Method injectValues:(Lio/dekorate/deps/jackson/databind/DeserializationContext;Ljava/lang/Object;)V
      18: aload_0
      19: getfield      #229                // Field _unwrappedPropertyHandler:Lio/dekorate/deps/jackson/databind/deser/impl/UnwrappedPropertyHandler;
      22: ifnull        33
      25: aload_0
      26: aload_1
      27: aload_2
      28: aload_3
      29: invokevirtual #232                // Method deserializeWithUnwrapped:(Lio/dekorate/deps/jackson/core/JsonParser;Lio/dekorate/deps/jackson/databind/DeserializationContext;Ljava/lang/Object;)Ljava/lang/Object;
      32: areturn
      33: aload_0
      34: getfield      #236                // Field _externalTypeIdHandler:Lio/dekorate/deps/jackson/databind/deser/impl/ExternalTypeHandler;
      37: ifnull        48
      40: aload_0
      41: aload_1
      42: aload_2
      43: aload_3
      44: invokevirtual #239                // Method deserializeWithExternalTypeId:(Lio/dekorate/deps/jackson/core/JsonParser;Lio/dekorate/deps/jackson/databind/DeserializationContext;Ljava/lang/Object;)Ljava/lang/Object;
      47: areturn
      48: aload_1
      49: invokevirtual #128                // Method io/dekorate/deps/jackson/core/JsonParser.isExpectedStartObjectToken:()Z
      52: ifeq          68
      55: aload_1
      56: invokevirtual #243                // Method io/dekorate/deps/jackson/core/JsonParser.nextFieldName:()Ljava/lang/String;
      59: astore        4
      61: aload         4
      63: ifnonnull     87
      66: aload_3
      67: areturn
      68: aload_1
      69: iconst_5
      70: invokevirtual #247                // Method io/dekorate/deps/jackson/core/JsonParser.hasTokenId:(I)Z
      73: ifeq          85
      76: aload_1
      77: invokevirtual #250                // Method io/dekorate/deps/jackson/core/JsonParser.getCurrentName:()Ljava/lang/String;
      80: astore        4
      82: goto          87
      85: aload_3
      86: areturn
      87: aload_0
      88: getfield      #255                // Field _needViewProcesing:Z
      91: ifeq          115
      94: aload_2
      95: invokevirtual #258                // Method io/dekorate/deps/jackson/databind/DeserializationContext.getActiveView:()Ljava/lang/Class;
      98: astore        5
     100: aload         5
     102: ifnull        115
     105: aload_0
     106: aload_1
     107: aload_2
     108: aload_3
     109: aload         5
     111: invokevirtual #262                // Method deserializeWithView:(Lio/dekorate/deps/jackson/core/JsonParser;Lio/dekorate/deps/jackson/databind/DeserializationContext;Ljava/lang/Object;Ljava/lang/Class;)Ljava/lang/Object;
     114: areturn
     115: aload_1
     116: invokevirtual #135                // Method io/dekorate/deps/jackson/core/JsonParser.nextToken:()Lio/dekorate/deps/jackson/core/JsonToken;
     119: pop
     120: aload_0
     121: getfield      #106                // Field _beanProperties:Lio/dekorate/deps/jackson/databind/deser/impl/BeanPropertyMap;
     124: aload         4
     126: invokevirtual #266                // Method io/dekorate/deps/jackson/databind/deser/impl/BeanPropertyMap.find:(Ljava/lang/String;)Lio/dekorate/deps/jackson/databind/deser/SettableBeanProperty;
     129: astore        5
     131: aload         5
     133: ifnull        162
     136: aload         5
     138: aload_1
     139: aload_2
     140: aload_3
     141: invokevirtual #272                // Method io/dekorate/deps/jackson/databind/deser/SettableBeanProperty.deserializeAndSet:(Lio/dekorate/deps/jackson/core/JsonParser;Lio/dekorate/deps/jackson/databind/DeserializationContext;Ljava/lang/Object;)V
     144: goto          171
     147: astore        6
     149: aload_0
     150: aload         6
     152: aload_3
     153: aload         4
     155: aload_2
     156: invokevirtual #276                // Method wrapAndThrow:(Ljava/lang/Throwable;Ljava/lang/Object;Ljava/lang/String;Lio/dekorate/deps/jackson/databind/DeserializationContext;)V
     159: goto          171
     162: aload_0
     163: aload_1
     164: aload_2
     165: aload_3
     166: aload         4
     168: invokevirtual #280                // Method handleUnknownVanilla:(Lio/dekorate/deps/jackson/core/JsonParser;Lio/dekorate/deps/jackson/databind/DeserializationContext;Ljava/lang/Object;Ljava/lang/String;)V
     171: aload_1
     172: invokevirtual #243                // Method io/dekorate/deps/jackson/core/JsonParser.nextFieldName:()Ljava/lang/String;
     175: dup
     176: astore        4
     178: ifnonnull     115
     181: aload_3
     182: areturn
    Exception table:
       from    to  target type
         136   144   147   Class java/lang/Exception

  private final java.lang.Object vanillaDeserialize(io.dekorate.deps.jackson.core.JsonParser, io.dekorate.deps.jackson.databind.DeserializationContext, io.dekorate.deps.jackson.core.JsonToken) throws java.io.IOException;
    Code:
       0: aload_0
       1: getfield      #294                // Field _valueInstantiator:Lio/dekorate/deps/jackson/databind/deser/ValueInstantiator;
       4: aload_2
       5: invokevirtual #300                // Method io/dekorate/deps/jackson/databind/deser/ValueInstantiator.createUsingDefault:(Lio/dekorate/deps/jackson/databind/DeserializationContext;)Ljava/lang/Object;
       8: astore        4
      10: aload_1
      11: aload         4
      13: invokevirtual #217                // Method io/dekorate/deps/jackson/core/JsonParser.setCurrentValue:(Ljava/lang/Object;)V
      16: aload_1
      17: iconst_5
      18: invokevirtual #247                // Method io/dekorate/deps/jackson/core/JsonParser.hasTokenId:(I)Z
      21: ifeq          99
      24: aload_1
      25: invokevirtual #250                // Method io/dekorate/deps/jackson/core/JsonParser.getCurrentName:()Ljava/lang/String;
      28: astore        5
      30: aload_1
      31: invokevirtual #135                // Method io/dekorate/deps/jackson/core/JsonParser.nextToken:()Lio/dekorate/deps/jackson/core/JsonToken;
      34: pop
      35: aload_0
      36: getfield      #106                // Field _beanProperties:Lio/dekorate/deps/jackson/databind/deser/impl/BeanPropertyMap;
      39: aload         5
      41: invokevirtual #266                // Method io/dekorate/deps/jackson/databind/deser/impl/BeanPropertyMap.find:(Ljava/lang/String;)Lio/dekorate/deps/jackson/databind/deser/SettableBeanProperty;
      44: astore        6
      46: aload         6
      48: ifnull        79
      51: aload         6
      53: aload_1
      54: aload_2
      55: aload         4
      57: invokevirtual #272                // Method io/dekorate/deps/jackson/databind/deser/SettableBeanProperty.deserializeAndSet:(Lio/dekorate/deps/jackson/core/JsonParser;Lio/dekorate/deps/jackson/databind/DeserializationContext;Ljava/lang/Object;)V
      60: goto          89
      63: astore        7
      65: aload_0
      66: aload         7
      68: aload         4
      70: aload         5
      72: aload_2
      73: invokevirtual #276                // Method wrapAndThrow:(Ljava/lang/Throwable;Ljava/lang/Object;Ljava/lang/String;Lio/dekorate/deps/jackson/databind/DeserializationContext;)V
      76: goto          89
      79: aload_0
      80: aload_1
      81: aload_2
      82: aload         4
      84: aload         5
      86: invokevirtual #280                // Method handleUnknownVanilla:(Lio/dekorate/deps/jackson/core/JsonParser;Lio/dekorate/deps/jackson/databind/DeserializationContext;Ljava/lang/Object;Ljava/lang/String;)V
      89: aload_1
      90: invokevirtual #243                // Method io/dekorate/deps/jackson/core/JsonParser.nextFieldName:()Ljava/lang/String;
      93: dup
      94: astore        5
      96: ifnonnull     30
      99: aload         4
     101: areturn
    Exception table:
       from    to  target type
          51    60    63   Class java/lang/Exception

  public java.lang.Object deserializeFromObject(io.dekorate.deps.jackson.core.JsonParser, io.dekorate.deps.jackson.databind.DeserializationContext) throws java.io.IOException;
    Code:
       0: aload_0
       1: getfield      #142                // Field _objectIdReader:Lio/dekorate/deps/jackson/databind/deser/impl/ObjectIdReader;
       4: ifnull        47
       7: aload_0
       8: getfield      #142                // Field _objectIdReader:Lio/dekorate/deps/jackson/databind/deser/impl/ObjectIdReader;
      11: invokevirtual #305                // Method io/dekorate/deps/jackson/databind/deser/impl/ObjectIdReader.maySerializeAsObject:()Z
      14: ifeq          47
      17: aload_1
      18: iconst_5
      19: invokevirtual #247                // Method io/dekorate/deps/jackson/core/JsonParser.hasTokenId:(I)Z
      22: ifeq          47
      25: aload_0
      26: getfield      #142                // Field _objectIdReader:Lio/dekorate/deps/jackson/databind/deser/impl/ObjectIdReader;
      29: aload_1
      30: invokevirtual #250                // Method io/dekorate/deps/jackson/core/JsonParser.getCurrentName:()Ljava/lang/String;
      33: aload_1
      34: invokevirtual #309                // Method io/dekorate/deps/jackson/databind/deser/impl/ObjectIdReader.isValidReferencePropertyName:(Ljava/lang/String;Lio/dekorate/deps/jackson/core/JsonParser;)Z
      37: ifeq          47
      40: aload_0
      41: aload_1
      42: aload_2
      43: invokevirtual #312                // Method deserializeFromObjectId:(Lio/dekorate/deps/jackson/core/JsonParser;Lio/dekorate/deps/jackson/databind/DeserializationContext;)Ljava/lang/Object;
      46: areturn
      47: aload_0
      48: getfield      #315                // Field _nonStandardCreation:Z
      51: ifeq          104
      54: aload_0
      55: getfield      #229                // Field _unwrappedPropertyHandler:Lio/dekorate/deps/jackson/databind/deser/impl/UnwrappedPropertyHandler;
      58: ifnull        68
      61: aload_0
      62: aload_1
      63: aload_2
      64: invokevirtual #317                // Method deserializeWithUnwrapped:(Lio/dekorate/deps/jackson/core/JsonParser;Lio/dekorate/deps/jackson/databind/DeserializationContext;)Ljava/lang/Object;
      67: areturn
      68: aload_0
      69: getfield      #236                // Field _externalTypeIdHandler:Lio/dekorate/deps/jackson/databind/deser/impl/ExternalTypeHandler;
      72: ifnull        82
      75: aload_0
      76: aload_1
      77: aload_2
      78: invokevirtual #319                // Method deserializeWithExternalTypeId:(Lio/dekorate/deps/jackson/core/JsonParser;Lio/dekorate/deps/jackson/databind/DeserializationContext;)Ljava/lang/Object;
      81: areturn
      82: aload_0
      83: aload_1
      84: aload_2
      85: invokevirtual #322                // Method deserializeFromObjectUsingNonDefault:(Lio/dekorate/deps/jackson/core/JsonParser;Lio/dekorate/deps/jackson/databind/DeserializationContext;)Ljava/lang/Object;
      88: astore_3
      89: aload_0
      90: getfield      #221                // Field _injectables:[Lio/dekorate/deps/jackson/databind/deser/impl/ValueInjector;
      93: ifnull        102
      96: aload_0
      97: aload_2
      98: aload_3
      99: invokevirtual #225                // Method injectValues:(Lio/dekorate/deps/jackson/databind/DeserializationContext;Ljava/lang/Object;)V
     102: aload_3
     103: areturn
     104: aload_0
     105: getfield      #294                // Field _valueInstantiator:Lio/dekorate/deps/jackson/databind/deser/ValueInstantiator;
     108: aload_2
     109: invokevirtual #300                // Method io/dekorate/deps/jackson/databind/deser/ValueInstantiator.createUsingDefault:(Lio/dekorate/deps/jackson/databind/DeserializationContext;)Ljava/lang/Object;
     112: astore_3
     113: aload_1
     114: aload_3
     115: invokevirtual #217                // Method io/dekorate/deps/jackson/core/JsonParser.setCurrentValue:(Ljava/lang/Object;)V
     118: aload_1
     119: invokevirtual #325                // Method io/dekorate/deps/jackson/core/JsonParser.canReadObjectId:()Z
     122: ifeq          146
     125: aload_1
     126: invokevirtual #329                // Method io/dekorate/deps/jackson/core/JsonParser.getObjectId:()Ljava/lang/Object;
     129: astore        4
     131: aload         4
     133: ifnull        146
     136: aload_0
     137: aload_1
     138: aload_2
     139: aload_3
     140: aload         4
     142: invokevirtual #333                // Method _handleTypedObjectId:(Lio/dekorate/deps/jackson/core/JsonParser;Lio/dekorate/deps/jackson/databind/DeserializationContext;Ljava/lang/Object;Ljava/lang/Object;)Ljava/lang/Object;
     145: pop
     146: aload_0
     147: getfield      #221                // Field _injectables:[Lio/dekorate/deps/jackson/databind/deser/impl/ValueInjector;
     150: ifnull        159
     153: aload_0
     154: aload_2
     155: aload_3
     156: invokevirtual #225                // Method injectValues:(Lio/dekorate/deps/jackson/databind/DeserializationContext;Ljava/lang/Object;)V
     159: aload_0
     160: getfield      #255                // Field _needViewProcesing:Z
     163: ifeq          187
     166: aload_2
     167: invokevirtual #258                // Method io/dekorate/deps/jackson/databind/DeserializationContext.getActiveView:()Ljava/lang/Class;
     170: astore        4
     172: aload         4
     174: ifnull        187
     177: aload_0
     178: aload_1
     179: aload_2
     180: aload_3
     181: aload         4
     183: invokevirtual #262                // Method deserializeWithView:(Lio/dekorate/deps/jackson/core/JsonParser;Lio/dekorate/deps/jackson/databind/DeserializationContext;Ljava/lang/Object;Ljava/lang/Class;)Ljava/lang/Object;
     186: areturn
     187: aload_1
     188: iconst_5
     189: invokevirtual #247                // Method io/dekorate/deps/jackson/core/JsonParser.hasTokenId:(I)Z
     192: ifeq          267
     195: aload_1
     196: invokevirtual #250                // Method io/dekorate/deps/jackson/core/JsonParser.getCurrentName:()Ljava/lang/String;
     199: astore        4
     201: aload_1
     202: invokevirtual #135                // Method io/dekorate/deps/jackson/core/JsonParser.nextToken:()Lio/dekorate/deps/jackson/core/JsonToken;
     205: pop
     206: aload_0
     207: getfield      #106                // Field _beanProperties:Lio/dekorate/deps/jackson/databind/deser/impl/BeanPropertyMap;
     210: aload         4
     212: invokevirtual #266                // Method io/dekorate/deps/jackson/databind/deser/impl/BeanPropertyMap.find:(Ljava/lang/String;)Lio/dekorate/deps/jackson/databind/deser/SettableBeanProperty;
     215: astore        5
     217: aload         5
     219: ifnull        248
     222: aload         5
     224: aload_1
     225: aload_2
     226: aload_3
     227: invokevirtual #272                // Method io/dekorate/deps/jackson/databind/deser/SettableBeanProperty.deserializeAndSet:(Lio/dekorate/deps/jackson/core/JsonParser;Lio/dekorate/deps/jackson/databind/DeserializationContext;Ljava/lang/Object;)V
     230: goto          257
     233: astore        6
     235: aload_0
     236: aload         6
     238: aload_3
     239: aload         4
     241: aload_2
     242: invokevirtual #276                // Method wrapAndThrow:(Ljava/lang/Throwable;Ljava/lang/Object;Ljava/lang/String;Lio/dekorate/deps/jackson/databind/DeserializationContext;)V
     245: goto          257
     248: aload_0
     249: aload_1
     250: aload_2
     251: aload_3
     252: aload         4
     254: invokevirtual #280                // Method handleUnknownVanilla:(Lio/dekorate/deps/jackson/core/JsonParser;Lio/dekorate/deps/jackson/databind/DeserializationContext;Ljava/lang/Object;Ljava/lang/String;)V
     257: aload_1
     258: invokevirtual #243                // Method io/dekorate/deps/jackson/core/JsonParser.nextFieldName:()Ljava/lang/String;
     261: dup
     262: astore        4
     264: ifnonnull     201
     267: aload_3
     268: areturn
    Exception table:
       from    to  target type
         222   230   233   Class java/lang/Exception

  protected java.lang.Object _deserializeUsingPropertyBased(io.dekorate.deps.jackson.core.JsonParser, io.dekorate.deps.jackson.databind.DeserializationContext) throws java.io.IOException;
    Code:
       0: aload_0
       1: getfield      #341                // Field _propertyBasedCreator:Lio/dekorate/deps/jackson/databind/deser/impl/PropertyBasedCreator;
       4: astore_3
       5: aload_3
       6: aload_1
       7: aload_2
       8: aload_0
       9: getfield      #142                // Field _objectIdReader:Lio/dekorate/deps/jackson/databind/deser/impl/ObjectIdReader;
      12: invokevirtual #347                // Method io/dekorate/deps/jackson/databind/deser/impl/PropertyBasedCreator.startBuilding:(Lio/dekorate/deps/jackson/core/JsonParser;Lio/dekorate/deps/jackson/databind/DeserializationContext;Lio/dekorate/deps/jackson/databind/deser/impl/ObjectIdReader;)Lio/dekorate/deps/jackson/databind/deser/impl/PropertyValueBuffer;
      15: astore        4
      17: aconst_null
      18: astore        5
      20: aload_0
      21: getfield      #255                // Field _needViewProcesing:Z
      24: ifeq          34
      27: aload_2
      28: invokevirtual #258                // Method io/dekorate/deps/jackson/databind/DeserializationContext.getActiveView:()Ljava/lang/Class;
      31: goto          35
      34: aconst_null
      35: astore        6
      37: aload_1
      38: invokevirtual #151                // Method io/dekorate/deps/jackson/core/JsonParser.getCurrentToken:()Lio/dekorate/deps/jackson/core/JsonToken;
      41: astore        7
      43: aconst_null
      44: astore        8
      46: aload         7
      48: getstatic     #358                // Field io/dekorate/deps/jackson/core/JsonToken.FIELD_NAME:Lio/dekorate/deps/jackson/core/JsonToken;
      51: if_acmpne     441
      54: aload_1
      55: invokevirtual #250                // Method io/dekorate/deps/jackson/core/JsonParser.getCurrentName:()Ljava/lang/String;
      58: astore        9
      60: aload_1
      61: invokevirtual #135                // Method io/dekorate/deps/jackson/core/JsonParser.nextToken:()Lio/dekorate/deps/jackson/core/JsonToken;
      64: pop
      65: aload         4
      67: aload         9
      69: invokevirtual #362                // Method io/dekorate/deps/jackson/databind/deser/impl/PropertyValueBuffer.readIdProperty:(Ljava/lang/String;)Z
      72: ifeq          78
      75: goto          432
      78: aload_3
      79: aload         9
      81: invokevirtual #365                // Method io/dekorate/deps/jackson/databind/deser/impl/PropertyBasedCreator.findCreatorProperty:(Ljava/lang/String;)Lio/dekorate/deps/jackson/databind/deser/SettableBeanProperty;
      84: astore        10
      86: aload         10
      88: ifnull        240
      91: aload         6
      93: ifnull        114
      96: aload         10
      98: aload         6
     100: invokevirtual #369                // Method io/dekorate/deps/jackson/databind/deser/SettableBeanProperty.visibleInView:(Ljava/lang/Class;)Z
     103: ifne          114
     106: aload_1
     107: invokevirtual #373                // Method io/dekorate/deps/jackson/core/JsonParser.skipChildren:()Lio/dekorate/deps/jackson/core/JsonParser;
     110: pop
     111: goto          432
     114: aload_0
     115: aload_1
     116: aload_2
     117: aload         10
     119: invokevirtual #377                // Method _deserializeWithErrorWrapping:(Lio/dekorate/deps/jackson/core/JsonParser;Lio/dekorate/deps/jackson/databind/DeserializationContext;Lio/dekorate/deps/jackson/databind/deser/SettableBeanProperty;)Ljava/lang/Object;
     122: astore        11
     124: aload         4
     126: aload         10
     128: aload         11
     130: invokevirtual #381                // Method io/dekorate/deps/jackson/databind/deser/impl/PropertyValueBuffer.assignParameter:(Lio/dekorate/deps/jackson/databind/deser/SettableBeanProperty;Ljava/lang/Object;)Z
     133: ifeq          432
     136: aload_1
     137: invokevirtual #135                // Method io/dekorate/deps/jackson/core/JsonParser.nextToken:()Lio/dekorate/deps/jackson/core/JsonToken;
     140: pop
     141: aload_3
     142: aload_2
     143: aload         4
     145: invokevirtual #385                // Method io/dekorate/deps/jackson/databind/deser/impl/PropertyBasedCreator.build:(Lio/dekorate/deps/jackson/databind/DeserializationContext;Lio/dekorate/deps/jackson/databind/deser/impl/PropertyValueBuffer;)Ljava/lang/Object;
     148: astore        12
     150: goto          164
     153: astore        13
     155: aload_0
     156: aload         13
     158: aload_2
     159: invokevirtual #389                // Method wrapInstantiationProblem:(Ljava/lang/Throwable;Lio/dekorate/deps/jackson/databind/DeserializationContext;)Ljava/lang/Object;
     162: astore        12
     164: aload         12
     166: ifnonnull     183
     169: aload_2
     170: aload_0
     171: invokevirtual #206                // Method handledType:()Ljava/lang/Class;
     174: aconst_null
     175: aload_0
     176: invokevirtual #393                // Method _creatorReturnedNullException:()Ljava/lang/Exception;
     179: invokevirtual #397                // Method io/dekorate/deps/jackson/databind/DeserializationContext.handleInstantiationProblem:(Ljava/lang/Class;Ljava/lang/Object;Ljava/lang/Throwable;)Ljava/lang/Object;
     182: areturn
     183: aload_1
     184: aload         12
     186: invokevirtual #217                // Method io/dekorate/deps/jackson/core/JsonParser.setCurrentValue:(Ljava/lang/Object;)V
     189: aload         12
     191: invokevirtual #85                 // Method java/lang/Object.getClass:()Ljava/lang/Class;
     194: aload_0
     195: getfield      #401                // Field _beanType:Lio/dekorate/deps/jackson/databind/JavaType;
     198: invokevirtual #406                // Method io/dekorate/deps/jackson/databind/JavaType.getRawClass:()Ljava/lang/Class;
     201: if_acmpeq     215
     204: aload_0
     205: aload_1
     206: aload_2
     207: aload         12
     209: aload         5
     211: invokevirtual #410                // Method handlePolymorphic:(Lio/dekorate/deps/jackson/core/JsonParser;Lio/dekorate/deps/jackson/databind/DeserializationContext;Ljava/lang/Object;Lio/dekorate/deps/jackson/databind/util/TokenBuffer;)Ljava/lang/Object;
     214: areturn
     215: aload         5
     217: ifnull        231
     220: aload_0
     221: aload_2
     222: aload         12
     224: aload         5
     226: invokevirtual #414                // Method handleUnknownProperties:(Lio/dekorate/deps/jackson/databind/DeserializationContext;Ljava/lang/Object;Lio/dekorate/deps/jackson/databind/util/TokenBuffer;)Ljava/lang/Object;
     229: astore        12
     231: aload_0
     232: aload_1
     233: aload_2
     234: aload         12
     236: invokevirtual #416                // Method deserialize:(Lio/dekorate/deps/jackson/core/JsonParser;Lio/dekorate/deps/jackson/databind/DeserializationContext;Ljava/lang/Object;)Ljava/lang/Object;
     239: areturn
     240: aload_0
     241: getfield      #106                // Field _beanProperties:Lio/dekorate/deps/jackson/databind/deser/impl/BeanPropertyMap;
     244: aload         9
     246: invokevirtual #266                // Method io/dekorate/deps/jackson/databind/deser/impl/BeanPropertyMap.find:(Ljava/lang/String;)Lio/dekorate/deps/jackson/databind/deser/SettableBeanProperty;
     249: astore        11
     251: aload         11
     253: ifnull        316
     256: aload         4
     258: aload         11
     260: aload_0
     261: aload_1
     262: aload_2
     263: aload         11
     265: invokevirtual #377                // Method _deserializeWithErrorWrapping:(Lio/dekorate/deps/jackson/core/JsonParser;Lio/dekorate/deps/jackson/databind/DeserializationContext;Lio/dekorate/deps/jackson/databind/deser/SettableBeanProperty;)Ljava/lang/Object;
     268: invokevirtual #420                // Method io/dekorate/deps/jackson/databind/deser/impl/PropertyValueBuffer.bufferProperty:(Lio/dekorate/deps/jackson/databind/deser/SettableBeanProperty;Ljava/lang/Object;)V
     271: goto          432
     274: astore        12
     276: aload_0
     277: aload_2
     278: aload         11
     280: aload         4
     282: aload         12
     284: invokespecial #424                // Method handleUnresolvedReference:(Lio/dekorate/deps/jackson/databind/DeserializationContext;Lio/dekorate/deps/jackson/databind/deser/SettableBeanProperty;Lio/dekorate/deps/jackson/databind/deser/impl/PropertyValueBuffer;Lio/dekorate/deps/jackson/databind/deser/UnresolvedForwardReference;)Lio/dekorate/deps/jackson/databind/deser/BeanDeserializer$BeanReferring;
     287: astore        13
     289: aload         8
     291: ifnonnull     303
     294: new           #426                // class java/util/ArrayList
     297: dup
     298: invokespecial #429                // Method java/util/ArrayList."<init>":()V
     301: astore        8
     303: aload         8
     305: aload         13
     307: invokeinterface #433,  2          // InterfaceMethod java/util/List.add:(Ljava/lang/Object;)Z
     312: pop
     313: goto          432
     316: aload_0
     317: getfield      #436                // Field _ignorableProps:Ljava/util/Set;
     320: ifnull        352
     323: aload_0
     324: getfield      #436                // Field _ignorableProps:Ljava/util/Set;
     327: aload         9
     329: invokeinterface #441,  2          // InterfaceMethod java/util/Set.contains:(Ljava/lang/Object;)Z
     334: ifeq          352
     337: aload_0
     338: aload_1
     339: aload_2
     340: aload_0
     341: invokevirtual #206                // Method handledType:()Ljava/lang/Class;
     344: aload         9
     346: invokevirtual #444                // Method handleIgnoredProperty:(Lio/dekorate/deps/jackson/core/JsonParser;Lio/dekorate/deps/jackson/databind/DeserializationContext;Ljava/lang/Object;Ljava/lang/String;)V
     349: goto          432
     352: aload_0
     353: getfield      #448                // Field _anySetter:Lio/dekorate/deps/jackson/databind/deser/SettableAnyProperty;
     356: ifnull        403
     359: aload         4
     361: aload_0
     362: getfield      #448                // Field _anySetter:Lio/dekorate/deps/jackson/databind/deser/SettableAnyProperty;
     365: aload         9
     367: aload_0
     368: getfield      #448                // Field _anySetter:Lio/dekorate/deps/jackson/databind/deser/SettableAnyProperty;
     371: aload_1
     372: aload_2
     373: invokevirtual #452                // Method io/dekorate/deps/jackson/databind/deser/SettableAnyProperty.deserialize:(Lio/dekorate/deps/jackson/core/JsonParser;Lio/dekorate/deps/jackson/databind/DeserializationContext;)Ljava/lang/Object;
     376: invokevirtual #456                // Method io/dekorate/deps/jackson/databind/deser/impl/PropertyValueBuffer.bufferAnyProperty:(Lio/dekorate/deps/jackson/databind/deser/SettableAnyProperty;Ljava/lang/String;Ljava/lang/Object;)V
     379: goto          432
     382: astore        12
     384: aload_0
     385: aload         12
     387: aload_0
     388: getfield      #401                // Field _beanType:Lio/dekorate/deps/jackson/databind/JavaType;
     391: invokevirtual #406                // Method io/dekorate/deps/jackson/databind/JavaType.getRawClass:()Ljava/lang/Class;
     394: aload         9
     396: aload_2
     397: invokevirtual #276                // Method wrapAndThrow:(Ljava/lang/Throwable;Ljava/lang/Object;Ljava/lang/String;Lio/dekorate/deps/jackson/databind/DeserializationContext;)V
     400: goto          432
     403: aload         5
     405: ifnonnull     419
     408: new           #351                // class io/dekorate/deps/jackson/databind/util/TokenBuffer
     411: dup
     412: aload_1
     413: aload_2
     414: invokespecial #459                // Method io/dekorate/deps/jackson/databind/util/TokenBuffer."<init>":(Lio/dekorate/deps/jackson/core/JsonParser;Lio/dekorate/deps/jackson/databind/DeserializationContext;)V
     417: astore        5
     419: aload         5
     421: aload         9
     423: invokevirtual #463                // Method io/dekorate/deps/jackson/databind/util/TokenBuffer.writeFieldName:(Ljava/lang/String;)V
     426: aload         5
     428: aload_1
     429: invokevirtual #467                // Method io/dekorate/deps/jackson/databind/util/TokenBuffer.copyCurrentStructure:(Lio/dekorate/deps/jackson/core/JsonParser;)V
     432: aload_1
     433: invokevirtual #135                // Method io/dekorate/deps/jackson/core/JsonParser.nextToken:()Lio/dekorate/deps/jackson/core/JsonToken;
     436: astore        7
     438: goto          46
     441: aload_3
     442: aload_2
     443: aload         4
     445: invokevirtual #385                // Method io/dekorate/deps/jackson/databind/deser/impl/PropertyBasedCreator.build:(Lio/dekorate/deps/jackson/databind/DeserializationContext;Lio/dekorate/deps/jackson/databind/deser/impl/PropertyValueBuffer;)Ljava/lang/Object;
     448: astore        9
     450: goto          466
     453: astore        10
     455: aload_0
     456: aload         10
     458: aload_2
     459: invokevirtual #389                // Method wrapInstantiationProblem:(Ljava/lang/Throwable;Lio/dekorate/deps/jackson/databind/DeserializationContext;)Ljava/lang/Object;
     462: pop
     463: aconst_null
     464: astore        9
     466: aload         8
     468: ifnull        512
     471: aload         8
     473: invokeinterface #471,  1          // InterfaceMethod java/util/List.iterator:()Ljava/util/Iterator;
     478: astore        10
     480: aload         10
     482: invokeinterface #476,  1          // InterfaceMethod java/util/Iterator.hasNext:()Z
     487: ifeq          512
     490: aload         10
     492: invokeinterface #479,  1          // InterfaceMethod java/util/Iterator.next:()Ljava/lang/Object;
     497: checkcast     #11                 // class io/dekorate/deps/jackson/databind/deser/BeanDeserializer$BeanReferring
     500: astore        11
     502: aload         11
     504: aload         9
     506: invokevirtual #482                // Method io/dekorate/deps/jackson/databind/deser/BeanDeserializer$BeanReferring.setBean:(Ljava/lang/Object;)V
     509: goto          480
     512: aload         5
     514: ifnull        553
     517: aload         9
     519: invokevirtual #85                 // Method java/lang/Object.getClass:()Ljava/lang/Class;
     522: aload_0
     523: getfield      #401                // Field _beanType:Lio/dekorate/deps/jackson/databind/JavaType;
     526: invokevirtual #406                // Method io/dekorate/deps/jackson/databind/JavaType.getRawClass:()Ljava/lang/Class;
     529: if_acmpeq     543
     532: aload_0
     533: aconst_null
     534: aload_2
     535: aload         9
     537: aload         5
     539: invokevirtual #410                // Method handlePolymorphic:(Lio/dekorate/deps/jackson/core/JsonParser;Lio/dekorate/deps/jackson/databind/DeserializationContext;Ljava/lang/Object;Lio/dekorate/deps/jackson/databind/util/TokenBuffer;)Ljava/lang/Object;
     542: areturn
     543: aload_0
     544: aload_2
     545: aload         9
     547: aload         5
     549: invokevirtual #414                // Method handleUnknownProperties:(Lio/dekorate/deps/jackson/databind/DeserializationContext;Ljava/lang/Object;Lio/dekorate/deps/jackson/databind/util/TokenBuffer;)Ljava/lang/Object;
     552: areturn
     553: aload         9
     555: areturn
    Exception table:
       from    to  target type
         141   150   153   Class java/lang/Exception
         256   271   274   Class io/dekorate/deps/jackson/databind/deser/UnresolvedForwardReference
         359   379   382   Class java/lang/Exception
         441   450   453   Class java/lang/Exception

  private io.dekorate.deps.jackson.databind.deser.BeanDeserializer$BeanReferring handleUnresolvedReference(io.dekorate.deps.jackson.databind.DeserializationContext, io.dekorate.deps.jackson.databind.deser.SettableBeanProperty, io.dekorate.deps.jackson.databind.deser.impl.PropertyValueBuffer, io.dekorate.deps.jackson.databind.deser.UnresolvedForwardReference) throws io.dekorate.deps.jackson.databind.JsonMappingException;
    Code:
       0: new           #11                 // class io/dekorate/deps/jackson/databind/deser/BeanDeserializer$BeanReferring
       3: dup
       4: aload_1
       5: aload         4
       7: aload_2
       8: invokevirtual #503                // Method io/dekorate/deps/jackson/databind/deser/SettableBeanProperty.getType:()Lio/dekorate/deps/jackson/databind/JavaType;
      11: aload_3
      12: aload_2
      13: invokespecial #506                // Method io/dekorate/deps/jackson/databind/deser/BeanDeserializer$BeanReferring."<init>":(Lio/dekorate/deps/jackson/databind/DeserializationContext;Lio/dekorate/deps/jackson/databind/deser/UnresolvedForwardReference;Lio/dekorate/deps/jackson/databind/JavaType;Lio/dekorate/deps/jackson/databind/deser/impl/PropertyValueBuffer;Lio/dekorate/deps/jackson/databind/deser/SettableBeanProperty;)V
      16: astore        5
      18: aload         4
      20: invokevirtual #510                // Method io/dekorate/deps/jackson/databind/deser/UnresolvedForwardReference.getRoid:()Lio/dekorate/deps/jackson/databind/deser/impl/ReadableObjectId;
      23: aload         5
      25: invokevirtual #514                // Method io/dekorate/deps/jackson/databind/deser/impl/ReadableObjectId.appendReferring:(Lio/dekorate/deps/jackson/databind/deser/impl/ReadableObjectId$Referring;)V
      28: aload         5
      30: areturn

  protected final java.lang.Object _deserializeWithErrorWrapping(io.dekorate.deps.jackson.core.JsonParser, io.dekorate.deps.jackson.databind.DeserializationContext, io.dekorate.deps.jackson.databind.deser.SettableBeanProperty) throws java.io.IOException;
    Code:
       0: aload_3
       1: aload_1
       2: aload_2
       3: invokevirtual #515                // Method io/dekorate/deps/jackson/databind/deser/SettableBeanProperty.deserialize:(Lio/dekorate/deps/jackson/core/JsonParser;Lio/dekorate/deps/jackson/databind/DeserializationContext;)Ljava/lang/Object;
       6: areturn
       7: astore        4
       9: aload_0
      10: aload         4
      12: aload_0
      13: getfield      #401                // Field _beanType:Lio/dekorate/deps/jackson/databind/JavaType;
      16: invokevirtual #406                // Method io/dekorate/deps/jackson/databind/JavaType.getRawClass:()Ljava/lang/Class;
      19: aload_3
      20: invokevirtual #518                // Method io/dekorate/deps/jackson/databind/deser/SettableBeanProperty.getName:()Ljava/lang/String;
      23: aload_2
      24: invokevirtual #276                // Method wrapAndThrow:(Ljava/lang/Throwable;Ljava/lang/Object;Ljava/lang/String;Lio/dekorate/deps/jackson/databind/DeserializationContext;)V
      27: aconst_null
      28: areturn
    Exception table:
       from    to  target type
           0     6     7   Class java/lang/Exception

  protected java.lang.Object deserializeFromNull(io.dekorate.deps.jackson.core.JsonParser, io.dekorate.deps.jackson.databind.DeserializationContext) throws java.io.IOException;
    Code:
       0: aload_1
       1: invokevirtual #521                // Method io/dekorate/deps/jackson/core/JsonParser.requiresCustomCodec:()Z
       4: ifeq          71
       7: new           #351                // class io/dekorate/deps/jackson/databind/util/TokenBuffer
      10: dup
      11: aload_1
      12: aload_2
      13: invokespecial #459                // Method io/dekorate/deps/jackson/databind/util/TokenBuffer."<init>":(Lio/dekorate/deps/jackson/core/JsonParser;Lio/dekorate/deps/jackson/databind/DeserializationContext;)V
      16: astore_3
      17: aload_3
      18: invokevirtual #524                // Method io/dekorate/deps/jackson/databind/util/TokenBuffer.writeEndObject:()V
      21: aload_3
      22: aload_1
      23: invokevirtual #528                // Method io/dekorate/deps/jackson/databind/util/TokenBuffer.asParser:(Lio/dekorate/deps/jackson/core/JsonParser;)Lio/dekorate/deps/jackson/core/JsonParser;
      26: astore        4
      28: aload         4
      30: invokevirtual #135                // Method io/dekorate/deps/jackson/core/JsonParser.nextToken:()Lio/dekorate/deps/jackson/core/JsonToken;
      33: pop
      34: aload_0
      35: getfield      #131                // Field _vanillaProcessing:Z
      38: ifeq          54
      41: aload_0
      42: aload         4
      44: aload_2
      45: getstatic     #531                // Field io/dekorate/deps/jackson/core/JsonToken.END_OBJECT:Lio/dekorate/deps/jackson/core/JsonToken;
      48: invokespecial #139                // Method vanillaDeserialize:(Lio/dekorate/deps/jackson/core/JsonParser;Lio/dekorate/deps/jackson/databind/DeserializationContext;Lio/dekorate/deps/jackson/core/JsonToken;)Ljava/lang/Object;
      51: goto          61
      54: aload_0
      55: aload         4
      57: aload_2
      58: invokevirtual #148                // Method deserializeFromObject:(Lio/dekorate/deps/jackson/core/JsonParser;Lio/dekorate/deps/jackson/databind/DeserializationContext;)Ljava/lang/Object;
      61: astore        5
      63: aload         4
      65: invokevirtual #534                // Method io/dekorate/deps/jackson/core/JsonParser.close:()V
      68: aload         5
      70: areturn
      71: aload_2
      72: aload_0
      73: aload_2
      74: invokevirtual #193                // Method getValueType:(Lio/dekorate/deps/jackson/databind/DeserializationContext;)Lio/dekorate/deps/jackson/databind/JavaType;
      77: aload_1
      78: invokevirtual #199                // Method io/dekorate/deps/jackson/databind/DeserializationContext.handleUnexpectedToken:(Lio/dekorate/deps/jackson/databind/JavaType;Lio/dekorate/deps/jackson/core/JsonParser;)Ljava/lang/Object;
      81: areturn

  protected final java.lang.Object deserializeWithView(io.dekorate.deps.jackson.core.JsonParser, io.dekorate.deps.jackson.databind.DeserializationContext, java.lang.Object, java.lang.Class<?>) throws java.io.IOException;
    Code:
       0: aload_1
       1: iconst_5
       2: invokevirtual #247                // Method io/dekorate/deps/jackson/core/JsonParser.hasTokenId:(I)Z
       5: ifeq          98
       8: aload_1
       9: invokevirtual #250                // Method io/dekorate/deps/jackson/core/JsonParser.getCurrentName:()Ljava/lang/String;
      12: astore        5
      14: aload_1
      15: invokevirtual #135                // Method io/dekorate/deps/jackson/core/JsonParser.nextToken:()Lio/dekorate/deps/jackson/core/JsonToken;
      18: pop
      19: aload_0
      20: getfield      #106                // Field _beanProperties:Lio/dekorate/deps/jackson/databind/deser/impl/BeanPropertyMap;
      23: aload         5
      25: invokevirtual #266                // Method io/dekorate/deps/jackson/databind/deser/impl/BeanPropertyMap.find:(Ljava/lang/String;)Lio/dekorate/deps/jackson/databind/deser/SettableBeanProperty;
      28: astore        6
      30: aload         6
      32: ifnull        79
      35: aload         6
      37: aload         4
      39: invokevirtual #369                // Method io/dekorate/deps/jackson/databind/deser/SettableBeanProperty.visibleInView:(Ljava/lang/Class;)Z
      42: ifne          53
      45: aload_1
      46: invokevirtual #373                // Method io/dekorate/deps/jackson/core/JsonParser.skipChildren:()Lio/dekorate/deps/jackson/core/JsonParser;
      49: pop
      50: goto          88
      53: aload         6
      55: aload_1
      56: aload_2
      57: aload_3
      58: invokevirtual #272                // Method io/dekorate/deps/jackson/databind/deser/SettableBeanProperty.deserializeAndSet:(Lio/dekorate/deps/jackson/core/JsonParser;Lio/dekorate/deps/jackson/databind/DeserializationContext;Ljava/lang/Object;)V
      61: goto          88
      64: astore        7
      66: aload_0
      67: aload         7
      69: aload_3
      70: aload         5
      72: aload_2
      73: invokevirtual #276                // Method wrapAndThrow:(Ljava/lang/Throwable;Ljava/lang/Object;Ljava/lang/String;Lio/dekorate/deps/jackson/databind/DeserializationContext;)V
      76: goto          88
      79: aload_0
      80: aload_1
      81: aload_2
      82: aload_3
      83: aload         5
      85: invokevirtual #280                // Method handleUnknownVanilla:(Lio/dekorate/deps/jackson/core/JsonParser;Lio/dekorate/deps/jackson/databind/DeserializationContext;Ljava/lang/Object;Ljava/lang/String;)V
      88: aload_1
      89: invokevirtual #243                // Method io/dekorate/deps/jackson/core/JsonParser.nextFieldName:()Ljava/lang/String;
      92: dup
      93: astore        5
      95: ifnonnull     14
      98: aload_3
      99: areturn
    Exception table:
       from    to  target type
          53    61    64   Class java/lang/Exception

  protected java.lang.Object deserializeWithUnwrapped(io.dekorate.deps.jackson.core.JsonParser, io.dekorate.deps.jackson.databind.DeserializationContext) throws java.io.IOException;
    Code:
       0: aload_0
       1: getfield      #542                // Field _delegateDeserializer:Lio/dekorate/deps/jackson/databind/JsonDeserializer;
       4: ifnull        25
       7: aload_0
       8: getfield      #294                // Field _valueInstantiator:Lio/dekorate/deps/jackson/databind/deser/ValueInstantiator;
      11: aload_2
      12: aload_0
      13: getfield      #542                // Field _delegateDeserializer:Lio/dekorate/deps/jackson/databind/JsonDeserializer;
      16: aload_1
      17: aload_2
      18: invokevirtual #545                // Method io/dekorate/deps/jackson/databind/JsonDeserializer.deserialize:(Lio/dekorate/deps/jackson/core/JsonParser;Lio/dekorate/deps/jackson/databind/DeserializationContext;)Ljava/lang/Object;
      21: invokevirtual #549                // Method io/dekorate/deps/jackson/databind/deser/ValueInstantiator.createUsingDelegate:(Lio/dekorate/deps/jackson/databind/DeserializationContext;Ljava/lang/Object;)Ljava/lang/Object;
      24: areturn
      25: aload_0
      26: getfield      #341                // Field _propertyBasedCreator:Lio/dekorate/deps/jackson/databind/deser/impl/PropertyBasedCreator;
      29: ifnull        39
      32: aload_0
      33: aload_1
      34: aload_2
      35: invokevirtual #552                // Method deserializeUsingPropertyBasedWithUnwrapped:(Lio/dekorate/deps/jackson/core/JsonParser;Lio/dekorate/deps/jackson/databind/DeserializationContext;)Ljava/lang/Object;
      38: areturn
      39: new           #351                // class io/dekorate/deps/jackson/databind/util/TokenBuffer
      42: dup
      43: aload_1
      44: aload_2
      45: invokespecial #459                // Method io/dekorate/deps/jackson/databind/util/TokenBuffer."<init>":(Lio/dekorate/deps/jackson/core/JsonParser;Lio/dekorate/deps/jackson/databind/DeserializationContext;)V
      48: astore_3
      49: aload_3
      50: invokevirtual #555                // Method io/dekorate/deps/jackson/databind/util/TokenBuffer.writeStartObject:()V
      53: aload_0
      54: getfield      #294                // Field _valueInstantiator:Lio/dekorate/deps/jackson/databind/deser/ValueInstantiator;
      57: aload_2
      58: invokevirtual #300                // Method io/dekorate/deps/jackson/databind/deser/ValueInstantiator.createUsingDefault:(Lio/dekorate/deps/jackson/databind/DeserializationContext;)Ljava/lang/Object;
      61: astore        4
      63: aload_1
      64: aload         4
      66: invokevirtual #217                // Method io/dekorate/deps/jackson/core/JsonParser.setCurrentValue:(Ljava/lang/Object;)V
      69: aload_0
      70: getfield      #221                // Field _injectables:[Lio/dekorate/deps/jackson/databind/deser/impl/ValueInjector;
      73: ifnull        83
      76: aload_0
      77: aload_2
      78: aload         4
      80: invokevirtual #225                // Method injectValues:(Lio/dekorate/deps/jackson/databind/DeserializationContext;Ljava/lang/Object;)V
      83: aload_0
      84: getfield      #255                // Field _needViewProcesing:Z
      87: ifeq          97
      90: aload_2
      91: invokevirtual #258                // Method io/dekorate/deps/jackson/databind/DeserializationContext.getActiveView:()Ljava/lang/Class;
      94: goto          98
      97: aconst_null
      98: astore        5
     100: aload_1
     101: iconst_5
     102: invokevirtual #247                // Method io/dekorate/deps/jackson/core/JsonParser.hasTokenId:(I)Z
     105: ifeq          115
     108: aload_1
     109: invokevirtual #250                // Method io/dekorate/deps/jackson/core/JsonParser.getCurrentName:()Ljava/lang/String;
     112: goto          116
     115: aconst_null
     116: astore        6
     118: aload         6
     120: ifnull        311
     123: aload_1
     124: invokevirtual #135                // Method io/dekorate/deps/jackson/core/JsonParser.nextToken:()Lio/dekorate/deps/jackson/core/JsonToken;
     127: pop
     128: aload_0
     129: getfield      #106                // Field _beanProperties:Lio/dekorate/deps/jackson/databind/deser/impl/BeanPropertyMap;
     132: aload         6
     134: invokevirtual #266                // Method io/dekorate/deps/jackson/databind/deser/impl/BeanPropertyMap.find:(Ljava/lang/String;)Lio/dekorate/deps/jackson/databind/deser/SettableBeanProperty;
     137: astore        7
     139: aload         7
     141: ifnull        195
     144: aload         5
     146: ifnull        167
     149: aload         7
     151: aload         5
     153: invokevirtual #369                // Method io/dekorate/deps/jackson/databind/deser/SettableBeanProperty.visibleInView:(Ljava/lang/Class;)Z
     156: ifne          167
     159: aload_1
     160: invokevirtual #373                // Method io/dekorate/deps/jackson/core/JsonParser.skipChildren:()Lio/dekorate/deps/jackson/core/JsonParser;
     163: pop
     164: goto          302
     167: aload         7
     169: aload_1
     170: aload_2
     171: aload         4
     173: invokevirtual #272                // Method io/dekorate/deps/jackson/databind/deser/SettableBeanProperty.deserializeAndSet:(Lio/dekorate/deps/jackson/core/JsonParser;Lio/dekorate/deps/jackson/databind/DeserializationContext;Ljava/lang/Object;)V
     176: goto          302
     179: astore        8
     181: aload_0
     182: aload         8
     184: aload         4
     186: aload         6
     188: aload_2
     189: invokevirtual #276                // Method wrapAndThrow:(Ljava/lang/Throwable;Ljava/lang/Object;Ljava/lang/String;Lio/dekorate/deps/jackson/databind/DeserializationContext;)V
     192: goto          302
     195: aload_0
     196: getfield      #436                // Field _ignorableProps:Ljava/util/Set;
     199: ifnull        229
     202: aload_0
     203: getfield      #436                // Field _ignorableProps:Ljava/util/Set;
     206: aload         6
     208: invokeinterface #441,  2          // InterfaceMethod java/util/Set.contains:(Ljava/lang/Object;)Z
     213: ifeq          229
     216: aload_0
     217: aload_1
     218: aload_2
     219: aload         4
     221: aload         6
     223: invokevirtual #444                // Method handleIgnoredProperty:(Lio/dekorate/deps/jackson/core/JsonParser;Lio/dekorate/deps/jackson/databind/DeserializationContext;Ljava/lang/Object;Ljava/lang/String;)V
     226: goto          302
     229: aload_0
     230: getfield      #448                // Field _anySetter:Lio/dekorate/deps/jackson/databind/deser/SettableAnyProperty;
     233: ifnonnull     250
     236: aload_3
     237: aload         6
     239: invokevirtual #463                // Method io/dekorate/deps/jackson/databind/util/TokenBuffer.writeFieldName:(Ljava/lang/String;)V
     242: aload_3
     243: aload_1
     244: invokevirtual #467                // Method io/dekorate/deps/jackson/databind/util/TokenBuffer.copyCurrentStructure:(Lio/dekorate/deps/jackson/core/JsonParser;)V
     247: goto          302
     250: aload_1
     251: invokestatic  #559                // Method io/dekorate/deps/jackson/databind/util/TokenBuffer.asCopyOfValue:(Lio/dekorate/deps/jackson/core/JsonParser;)Lio/dekorate/deps/jackson/databind/util/TokenBuffer;
     254: astore        8
     256: aload_3
     257: aload         6
     259: invokevirtual #463                // Method io/dekorate/deps/jackson/databind/util/TokenBuffer.writeFieldName:(Ljava/lang/String;)V
     262: aload_3
     263: aload         8
     265: invokevirtual #563                // Method io/dekorate/deps/jackson/databind/util/TokenBuffer.append:(Lio/dekorate/deps/jackson/databind/util/TokenBuffer;)Lio/dekorate/deps/jackson/databind/util/TokenBuffer;
     268: pop
     269: aload_0
     270: getfield      #448                // Field _anySetter:Lio/dekorate/deps/jackson/databind/deser/SettableAnyProperty;
     273: aload         8
     275: invokevirtual #566                // Method io/dekorate/deps/jackson/databind/util/TokenBuffer.asParserOnFirstToken:()Lio/dekorate/deps/jackson/core/JsonParser;
     278: aload_2
     279: aload         4
     281: aload         6
     283: invokevirtual #568                // Method io/dekorate/deps/jackson/databind/deser/SettableAnyProperty.deserializeAndSet:(Lio/dekorate/deps/jackson/core/JsonParser;Lio/dekorate/deps/jackson/databind/DeserializationContext;Ljava/lang/Object;Ljava/lang/String;)V
     286: goto          302
     289: astore        9
     291: aload_0
     292: aload         9
     294: aload         4
     296: aload         6
     298: aload_2
     299: invokevirtual #276                // Method wrapAndThrow:(Ljava/lang/Throwable;Ljava/lang/Object;Ljava/lang/String;Lio/dekorate/deps/jackson/databind/DeserializationContext;)V
     302: aload_1
     303: invokevirtual #243                // Method io/dekorate/deps/jackson/core/JsonParser.nextFieldName:()Ljava/lang/String;
     306: astore        6
     308: goto          118
     311: aload_3
     312: invokevirtual #524                // Method io/dekorate/deps/jackson/databind/util/TokenBuffer.writeEndObject:()V
     315: aload_0
     316: getfield      #229                // Field _unwrappedPropertyHandler:Lio/dekorate/deps/jackson/databind/deser/impl/UnwrappedPropertyHandler;
     319: aload_1
     320: aload_2
     321: aload         4
     323: aload_3
     324: invokevirtual #573                // Method io/dekorate/deps/jackson/databind/deser/impl/UnwrappedPropertyHandler.processUnwrapped:(Lio/dekorate/deps/jackson/core/JsonParser;Lio/dekorate/deps/jackson/databind/DeserializationContext;Ljava/lang/Object;Lio/dekorate/deps/jackson/databind/util/TokenBuffer;)Ljava/lang/Object;
     327: pop
     328: aload         4
     330: areturn
    Exception table:
       from    to  target type
         167   176   179   Class java/lang/Exception
         269   286   289   Class java/lang/Exception

  protected java.lang.Object deserializeWithUnwrapped(io.dekorate.deps.jackson.core.JsonParser, io.dekorate.deps.jackson.databind.DeserializationContext, java.lang.Object) throws java.io.IOException;
    Code:
       0: aload_1
       1: invokevirtual #151                // Method io/dekorate/deps/jackson/core/JsonParser.getCurrentToken:()Lio/dekorate/deps/jackson/core/JsonToken;
       4: astore        4
       6: aload         4
       8: getstatic     #578                // Field io/dekorate/deps/jackson/core/JsonToken.START_OBJECT:Lio/dekorate/deps/jackson/core/JsonToken;
      11: if_acmpne     20
      14: aload_1
      15: invokevirtual #135                // Method io/dekorate/deps/jackson/core/JsonParser.nextToken:()Lio/dekorate/deps/jackson/core/JsonToken;
      18: astore        4
      20: new           #351                // class io/dekorate/deps/jackson/databind/util/TokenBuffer
      23: dup
      24: aload_1
      25: aload_2
      26: invokespecial #459                // Method io/dekorate/deps/jackson/databind/util/TokenBuffer."<init>":(Lio/dekorate/deps/jackson/core/JsonParser;Lio/dekorate/deps/jackson/databind/DeserializationContext;)V
      29: astore        5
      31: aload         5
      33: invokevirtual #555                // Method io/dekorate/deps/jackson/databind/util/TokenBuffer.writeStartObject:()V
      36: aload_0
      37: getfield      #255                // Field _needViewProcesing:Z
      40: ifeq          50
      43: aload_2
      44: invokevirtual #258                // Method io/dekorate/deps/jackson/databind/DeserializationContext.getActiveView:()Ljava/lang/Class;
      47: goto          51
      50: aconst_null
      51: astore        6
      53: aload         4
      55: getstatic     #358                // Field io/dekorate/deps/jackson/core/JsonToken.FIELD_NAME:Lio/dekorate/deps/jackson/core/JsonToken;
      58: if_acmpne     257
      61: aload_1
      62: invokevirtual #250                // Method io/dekorate/deps/jackson/core/JsonParser.getCurrentName:()Ljava/lang/String;
      65: astore        7
      67: aload_0
      68: getfield      #106                // Field _beanProperties:Lio/dekorate/deps/jackson/databind/deser/impl/BeanPropertyMap;
      71: aload         7
      73: invokevirtual #266                // Method io/dekorate/deps/jackson/databind/deser/impl/BeanPropertyMap.find:(Ljava/lang/String;)Lio/dekorate/deps/jackson/databind/deser/SettableBeanProperty;
      76: astore        8
      78: aload_1
      79: invokevirtual #135                // Method io/dekorate/deps/jackson/core/JsonParser.nextToken:()Lio/dekorate/deps/jackson/core/JsonToken;
      82: pop
      83: aload         8
      85: ifnull        137
      88: aload         6
      90: ifnull        111
      93: aload         8
      95: aload         6
      97: invokevirtual #369                // Method io/dekorate/deps/jackson/databind/deser/SettableBeanProperty.visibleInView:(Ljava/lang/Class;)Z
     100: ifne          111
     103: aload_1
     104: invokevirtual #373                // Method io/dekorate/deps/jackson/core/JsonParser.skipChildren:()Lio/dekorate/deps/jackson/core/JsonParser;
     107: pop
     108: goto          248
     111: aload         8
     113: aload_1
     114: aload_2
     115: aload_3
     116: invokevirtual #272                // Method io/dekorate/deps/jackson/databind/deser/SettableBeanProperty.deserializeAndSet:(Lio/dekorate/deps/jackson/core/JsonParser;Lio/dekorate/deps/jackson/databind/DeserializationContext;Ljava/lang/Object;)V
     119: goto          248
     122: astore        9
     124: aload_0
     125: aload         9
     127: aload_3
     128: aload         7
     130: aload_2
     131: invokevirtual #276                // Method wrapAndThrow:(Ljava/lang/Throwable;Ljava/lang/Object;Ljava/lang/String;Lio/dekorate/deps/jackson/databind/DeserializationContext;)V
     134: goto          248
     137: aload_0
     138: getfield      #436                // Field _ignorableProps:Ljava/util/Set;
     141: ifnull        170
     144: aload_0
     145: getfield      #436                // Field _ignorableProps:Ljava/util/Set;
     148: aload         7
     150: invokeinterface #441,  2          // InterfaceMethod java/util/Set.contains:(Ljava/lang/Object;)Z
     155: ifeq          170
     158: aload_0
     159: aload_1
     160: aload_2
     161: aload_3
     162: aload         7
     164: invokevirtual #444                // Method handleIgnoredProperty:(Lio/dekorate/deps/jackson/core/JsonParser;Lio/dekorate/deps/jackson/databind/DeserializationContext;Ljava/lang/Object;Ljava/lang/String;)V
     167: goto          248
     170: aload_0
     171: getfield      #448                // Field _anySetter:Lio/dekorate/deps/jackson/databind/deser/SettableAnyProperty;
     174: ifnonnull     193
     177: aload         5
     179: aload         7
     181: invokevirtual #463                // Method io/dekorate/deps/jackson/databind/util/TokenBuffer.writeFieldName:(Ljava/lang/String;)V
     184: aload         5
     186: aload_1
     187: invokevirtual #467                // Method io/dekorate/deps/jackson/databind/util/TokenBuffer.copyCurrentStructure:(Lio/dekorate/deps/jackson/core/JsonParser;)V
     190: goto          248
     193: aload_1
     194: invokestatic  #559                // Method io/dekorate/deps/jackson/databind/util/TokenBuffer.asCopyOfValue:(Lio/dekorate/deps/jackson/core/JsonParser;)Lio/dekorate/deps/jackson/databind/util/TokenBuffer;
     197: astore        9
     199: aload         5
     201: aload         7
     203: invokevirtual #463                // Method io/dekorate/deps/jackson/databind/util/TokenBuffer.writeFieldName:(Ljava/lang/String;)V
     206: aload         5
     208: aload         9
     210: invokevirtual #563                // Method io/dekorate/deps/jackson/databind/util/TokenBuffer.append:(Lio/dekorate/deps/jackson/databind/util/TokenBuffer;)Lio/dekorate/deps/jackson/databind/util/TokenBuffer;
     213: pop
     214: aload_0
     215: getfield      #448                // Field _anySetter:Lio/dekorate/deps/jackson/databind/deser/SettableAnyProperty;
     218: aload         9
     220: invokevirtual #566                // Method io/dekorate/deps/jackson/databind/util/TokenBuffer.asParserOnFirstToken:()Lio/dekorate/deps/jackson/core/JsonParser;
     223: aload_2
     224: aload_3
     225: aload         7
     227: invokevirtual #568                // Method io/dekorate/deps/jackson/databind/deser/SettableAnyProperty.deserializeAndSet:(Lio/dekorate/deps/jackson/core/JsonParser;Lio/dekorate/deps/jackson/databind/DeserializationContext;Ljava/lang/Object;Ljava/lang/String;)V
     230: goto          248
     233: astore        10
     235: aload_0
     236: aload         10
     238: aload_3
     239: aload         7
     241: aload_2
     242: invokevirtual #276                // Method wrapAndThrow:(Ljava/lang/Throwable;Ljava/lang/Object;Ljava/lang/String;Lio/dekorate/deps/jackson/databind/DeserializationContext;)V
     245: goto          248
     248: aload_1
     249: invokevirtual #135                // Method io/dekorate/deps/jackson/core/JsonParser.nextToken:()Lio/dekorate/deps/jackson/core/JsonToken;
     252: astore        4
     254: goto          53
     257: aload         5
     259: invokevirtual #524                // Method io/dekorate/deps/jackson/databind/util/TokenBuffer.writeEndObject:()V
     262: aload_0
     263: getfield      #229                // Field _unwrappedPropertyHandler:Lio/dekorate/deps/jackson/databind/deser/impl/UnwrappedPropertyHandler;
     266: aload_1
     267: aload_2
     268: aload_3
     269: aload         5
     271: invokevirtual #573                // Method io/dekorate/deps/jackson/databind/deser/impl/UnwrappedPropertyHandler.processUnwrapped:(Lio/dekorate/deps/jackson/core/JsonParser;Lio/dekorate/deps/jackson/databind/DeserializationContext;Ljava/lang/Object;Lio/dekorate/deps/jackson/databind/util/TokenBuffer;)Ljava/lang/Object;
     274: pop
     275: aload_3
     276: areturn
    Exception table:
       from    to  target type
         111   119   122   Class java/lang/Exception
         214   230   233   Class java/lang/Exception

  protected java.lang.Object deserializeUsingPropertyBasedWithUnwrapped(io.dekorate.deps.jackson.core.JsonParser, io.dekorate.deps.jackson.databind.DeserializationContext) throws java.io.IOException;
    Code:
       0: aload_0
       1: getfield      #341                // Field _propertyBasedCreator:Lio/dekorate/deps/jackson/databind/deser/impl/PropertyBasedCreator;
       4: astore_3
       5: aload_3
       6: aload_1
       7: aload_2
       8: aload_0
       9: getfield      #142                // Field _objectIdReader:Lio/dekorate/deps/jackson/databind/deser/impl/ObjectIdReader;
      12: invokevirtual #347                // Method io/dekorate/deps/jackson/databind/deser/impl/PropertyBasedCreator.startBuilding:(Lio/dekorate/deps/jackson/core/JsonParser;Lio/dekorate/deps/jackson/databind/DeserializationContext;Lio/dekorate/deps/jackson/databind/deser/impl/ObjectIdReader;)Lio/dekorate/deps/jackson/databind/deser/impl/PropertyValueBuffer;
      15: astore        4
      17: new           #351                // class io/dekorate/deps/jackson/databind/util/TokenBuffer
      20: dup
      21: aload_1
      22: aload_2
      23: invokespecial #459                // Method io/dekorate/deps/jackson/databind/util/TokenBuffer."<init>":(Lio/dekorate/deps/jackson/core/JsonParser;Lio/dekorate/deps/jackson/databind/DeserializationContext;)V
      26: astore        5
      28: aload         5
      30: invokevirtual #555                // Method io/dekorate/deps/jackson/databind/util/TokenBuffer.writeStartObject:()V
      33: aload_1
      34: invokevirtual #151                // Method io/dekorate/deps/jackson/core/JsonParser.getCurrentToken:()Lio/dekorate/deps/jackson/core/JsonToken;
      37: astore        6
      39: aload         6
      41: getstatic     #358                // Field io/dekorate/deps/jackson/core/JsonToken.FIELD_NAME:Lio/dekorate/deps/jackson/core/JsonToken;
      44: if_acmpne     414
      47: aload_1
      48: invokevirtual #250                // Method io/dekorate/deps/jackson/core/JsonParser.getCurrentName:()Ljava/lang/String;
      51: astore        7
      53: aload_1
      54: invokevirtual #135                // Method io/dekorate/deps/jackson/core/JsonParser.nextToken:()Lio/dekorate/deps/jackson/core/JsonToken;
      57: pop
      58: aload_3
      59: aload         7
      61: invokevirtual #365                // Method io/dekorate/deps/jackson/databind/deser/impl/PropertyBasedCreator.findCreatorProperty:(Ljava/lang/String;)Lio/dekorate/deps/jackson/databind/deser/SettableBeanProperty;
      64: astore        8
      66: aload         8
      68: ifnull        230
      71: aload         4
      73: aload         8
      75: aload_0
      76: aload_1
      77: aload_2
      78: aload         8
      80: invokevirtual #377                // Method _deserializeWithErrorWrapping:(Lio/dekorate/deps/jackson/core/JsonParser;Lio/dekorate/deps/jackson/databind/DeserializationContext;Lio/dekorate/deps/jackson/databind/deser/SettableBeanProperty;)Ljava/lang/Object;
      83: invokevirtual #381                // Method io/dekorate/deps/jackson/databind/deser/impl/PropertyValueBuffer.assignParameter:(Lio/dekorate/deps/jackson/databind/deser/SettableBeanProperty;Ljava/lang/Object;)Z
      86: ifeq          405
      89: aload_1
      90: invokevirtual #135                // Method io/dekorate/deps/jackson/core/JsonParser.nextToken:()Lio/dekorate/deps/jackson/core/JsonToken;
      93: astore        6
      95: aload_3
      96: aload_2
      97: aload         4
      99: invokevirtual #385                // Method io/dekorate/deps/jackson/databind/deser/impl/PropertyBasedCreator.build:(Lio/dekorate/deps/jackson/databind/DeserializationContext;Lio/dekorate/deps/jackson/databind/deser/impl/PropertyValueBuffer;)Ljava/lang/Object;
     102: astore        9
     104: goto          118
     107: astore        10
     109: aload_0
     110: aload         10
     112: aload_2
     113: invokevirtual #389                // Method wrapInstantiationProblem:(Ljava/lang/Throwable;Lio/dekorate/deps/jackson/databind/DeserializationContext;)Ljava/lang/Object;
     116: astore        9
     118: aload_1
     119: aload         9
     121: invokevirtual #217                // Method io/dekorate/deps/jackson/core/JsonParser.setCurrentValue:(Ljava/lang/Object;)V
     124: aload         6
     126: getstatic     #358                // Field io/dekorate/deps/jackson/core/JsonToken.FIELD_NAME:Lio/dekorate/deps/jackson/core/JsonToken;
     129: if_acmpne     147
     132: aload         5
     134: aload_1
     135: invokevirtual #467                // Method io/dekorate/deps/jackson/databind/util/TokenBuffer.copyCurrentStructure:(Lio/dekorate/deps/jackson/core/JsonParser;)V
     138: aload_1
     139: invokevirtual #135                // Method io/dekorate/deps/jackson/core/JsonParser.nextToken:()Lio/dekorate/deps/jackson/core/JsonToken;
     142: astore        6
     144: goto          124
     147: aload         6
     149: getstatic     #531                // Field io/dekorate/deps/jackson/core/JsonToken.END_OBJECT:Lio/dekorate/deps/jackson/core/JsonToken;
     152: if_acmpeq     180
     155: aload_2
     156: aload_0
     157: getstatic     #531                // Field io/dekorate/deps/jackson/core/JsonToken.END_OBJECT:Lio/dekorate/deps/jackson/core/JsonToken;
     160: ldc_w         #580                // String Attempted to unwrap \'%s\' value
     163: iconst_1
     164: anewarray     #81                 // class java/lang/Object
     167: dup
     168: iconst_0
     169: aload_0
     170: invokevirtual #206                // Method handledType:()Ljava/lang/Class;
     173: invokevirtual #581                // Method java/lang/Class.getName:()Ljava/lang/String;
     176: aastore
     177: invokevirtual #585                // Method io/dekorate/deps/jackson/databind/DeserializationContext.reportWrongTokenException:(Lio/dekorate/deps/jackson/databind/JsonDeserializer;Lio/dekorate/deps/jackson/core/JsonToken;Ljava/lang/String;[Ljava/lang/Object;)V
     180: aload         5
     182: invokevirtual #524                // Method io/dekorate/deps/jackson/databind/util/TokenBuffer.writeEndObject:()V
     185: aload         9
     187: invokevirtual #85                 // Method java/lang/Object.getClass:()Ljava/lang/Class;
     190: aload_0
     191: getfield      #401                // Field _beanType:Lio/dekorate/deps/jackson/databind/JavaType;
     194: invokevirtual #406                // Method io/dekorate/deps/jackson/databind/JavaType.getRawClass:()Ljava/lang/Class;
     197: if_acmpeq     216
     200: aload_2
     201: aload         8
     203: ldc_w         #587                // String Cannot create polymorphic instances with unwrapped values
     206: iconst_0
     207: anewarray     #81                 // class java/lang/Object
     210: invokevirtual #591                // Method io/dekorate/deps/jackson/databind/DeserializationContext.reportInputMismatch:(Lio/dekorate/deps/jackson/databind/BeanProperty;Ljava/lang/String;[Ljava/lang/Object;)Ljava/lang/Object;
     213: pop
     214: aconst_null
     215: areturn
     216: aload_0
     217: getfield      #229                // Field _unwrappedPropertyHandler:Lio/dekorate/deps/jackson/databind/deser/impl/UnwrappedPropertyHandler;
     220: aload_1
     221: aload_2
     222: aload         9
     224: aload         5
     226: invokevirtual #573                // Method io/dekorate/deps/jackson/databind/deser/impl/UnwrappedPropertyHandler.processUnwrapped:(Lio/dekorate/deps/jackson/core/JsonParser;Lio/dekorate/deps/jackson/databind/DeserializationContext;Ljava/lang/Object;Lio/dekorate/deps/jackson/databind/util/TokenBuffer;)Ljava/lang/Object;
     229: areturn
     230: aload         4
     232: aload         7
     234: invokevirtual #362                // Method io/dekorate/deps/jackson/databind/deser/impl/PropertyValueBuffer.readIdProperty:(Ljava/lang/String;)Z
     237: ifeq          243
     240: goto          405
     243: aload_0
     244: getfield      #106                // Field _beanProperties:Lio/dekorate/deps/jackson/databind/deser/impl/BeanPropertyMap;
     247: aload         7
     249: invokevirtual #266                // Method io/dekorate/deps/jackson/databind/deser/impl/BeanPropertyMap.find:(Ljava/lang/String;)Lio/dekorate/deps/jackson/databind/deser/SettableBeanProperty;
     252: astore        9
     254: aload         9
     256: ifnull        277
     259: aload         4
     261: aload         9
     263: aload_0
     264: aload_1
     265: aload_2
     266: aload         9
     268: invokevirtual #377                // Method _deserializeWithErrorWrapping:(Lio/dekorate/deps/jackson/core/JsonParser;Lio/dekorate/deps/jackson/databind/DeserializationContext;Lio/dekorate/deps/jackson/databind/deser/SettableBeanProperty;)Ljava/lang/Object;
     271: invokevirtual #420                // Method io/dekorate/deps/jackson/databind/deser/impl/PropertyValueBuffer.bufferProperty:(Lio/dekorate/deps/jackson/databind/deser/SettableBeanProperty;Ljava/lang/Object;)V
     274: goto          405
     277: aload_0
     278: getfield      #436                // Field _ignorableProps:Ljava/util/Set;
     281: ifnull        313
     284: aload_0
     285: getfield      #436                // Field _ignorableProps:Ljava/util/Set;
     288: aload         7
     290: invokeinterface #441,  2          // InterfaceMethod java/util/Set.contains:(Ljava/lang/Object;)Z
     295: ifeq          313
     298: aload_0
     299: aload_1
     300: aload_2
     301: aload_0
     302: invokevirtual #206                // Method handledType:()Ljava/lang/Class;
     305: aload         7
     307: invokevirtual #444                // Method handleIgnoredProperty:(Lio/dekorate/deps/jackson/core/JsonParser;Lio/dekorate/deps/jackson/databind/DeserializationContext;Ljava/lang/Object;Ljava/lang/String;)V
     310: goto          405
     313: aload_0
     314: getfield      #448                // Field _anySetter:Lio/dekorate/deps/jackson/databind/deser/SettableAnyProperty;
     317: ifnonnull     336
     320: aload         5
     322: aload         7
     324: invokevirtual #463                // Method io/dekorate/deps/jackson/databind/util/TokenBuffer.writeFieldName:(Ljava/lang/String;)V
     327: aload         5
     329: aload_1
     330: invokevirtual #467                // Method io/dekorate/deps/jackson/databind/util/TokenBuffer.copyCurrentStructure:(Lio/dekorate/deps/jackson/core/JsonParser;)V
     333: goto          405
     336: aload_1
     337: invokestatic  #559                // Method io/dekorate/deps/jackson/databind/util/TokenBuffer.asCopyOfValue:(Lio/dekorate/deps/jackson/core/JsonParser;)Lio/dekorate/deps/jackson/databind/util/TokenBuffer;
     340: astore        10
     342: aload         5
     344: aload         7
     346: invokevirtual #463                // Method io/dekorate/deps/jackson/databind/util/TokenBuffer.writeFieldName:(Ljava/lang/String;)V
     349: aload         5
     351: aload         10
     353: invokevirtual #563                // Method io/dekorate/deps/jackson/databind/util/TokenBuffer.append:(Lio/dekorate/deps/jackson/databind/util/TokenBuffer;)Lio/dekorate/deps/jackson/databind/util/TokenBuffer;
     356: pop
     357: aload         4
     359: aload_0
     360: getfield      #448                // Field _anySetter:Lio/dekorate/deps/jackson/databind/deser/SettableAnyProperty;
     363: aload         7
     365: aload_0
     366: getfield      #448                // Field _anySetter:Lio/dekorate/deps/jackson/databind/deser/SettableAnyProperty;
     369: aload         10
     371: invokevirtual #566                // Method io/dekorate/deps/jackson/databind/util/TokenBuffer.asParserOnFirstToken:()Lio/dekorate/deps/jackson/core/JsonParser;
     374: aload_2
     375: invokevirtual #452                // Method io/dekorate/deps/jackson/databind/deser/SettableAnyProperty.deserialize:(Lio/dekorate/deps/jackson/core/JsonParser;Lio/dekorate/deps/jackson/databind/DeserializationContext;)Ljava/lang/Object;
     378: invokevirtual #456                // Method io/dekorate/deps/jackson/databind/deser/impl/PropertyValueBuffer.bufferAnyProperty:(Lio/dekorate/deps/jackson/databind/deser/SettableAnyProperty;Ljava/lang/String;Ljava/lang/Object;)V
     381: goto          405
     384: astore        11
     386: aload_0
     387: aload         11
     389: aload_0
     390: getfield      #401                // Field _beanType:Lio/dekorate/deps/jackson/databind/JavaType;
     393: invokevirtual #406                // Method io/dekorate/deps/jackson/databind/JavaType.getRawClass:()Ljava/lang/Class;
     396: aload         7
     398: aload_2
     399: invokevirtual #276                // Method wrapAndThrow:(Ljava/lang/Throwable;Ljava/lang/Object;Ljava/lang/String;Lio/dekorate/deps/jackson/databind/DeserializationContext;)V
     402: goto          405
     405: aload_1
     406: invokevirtual #135                // Method io/dekorate/deps/jackson/core/JsonParser.nextToken:()Lio/dekorate/deps/jackson/core/JsonToken;
     409: astore        6
     411: goto          39
     414: aload_3
     415: aload_2
     416: aload         4
     418: invokevirtual #385                // Method io/dekorate/deps/jackson/databind/deser/impl/PropertyBasedCreator.build:(Lio/dekorate/deps/jackson/databind/DeserializationContext;Lio/dekorate/deps/jackson/databind/deser/impl/PropertyValueBuffer;)Ljava/lang/Object;
     421: astore        7
     423: goto          438
     426: astore        8
     428: aload_0
     429: aload         8
     431: aload_2
     432: invokevirtual #389                // Method wrapInstantiationProblem:(Ljava/lang/Throwable;Lio/dekorate/deps/jackson/databind/DeserializationContext;)Ljava/lang/Object;
     435: pop
     436: aconst_null
     437: areturn
     438: aload_0
     439: getfield      #229                // Field _unwrappedPropertyHandler:Lio/dekorate/deps/jackson/databind/deser/impl/UnwrappedPropertyHandler;
     442: aload_1
     443: aload_2
     444: aload         7
     446: aload         5
     448: invokevirtual #573                // Method io/dekorate/deps/jackson/databind/deser/impl/UnwrappedPropertyHandler.processUnwrapped:(Lio/dekorate/deps/jackson/core/JsonParser;Lio/dekorate/deps/jackson/databind/DeserializationContext;Ljava/lang/Object;Lio/dekorate/deps/jackson/databind/util/TokenBuffer;)Ljava/lang/Object;
     451: areturn
    Exception table:
       from    to  target type
          95   104   107   Class java/lang/Exception
         357   381   384   Class java/lang/Exception
         414   423   426   Class java/lang/Exception

  protected java.lang.Object deserializeWithExternalTypeId(io.dekorate.deps.jackson.core.JsonParser, io.dekorate.deps.jackson.databind.DeserializationContext) throws java.io.IOException;
    Code:
       0: aload_0
       1: getfield      #341                // Field _propertyBasedCreator:Lio/dekorate/deps/jackson/databind/deser/impl/PropertyBasedCreator;
       4: ifnull        14
       7: aload_0
       8: aload_1
       9: aload_2
      10: invokevirtual #594                // Method deserializeUsingPropertyBasedWithExternalTypeId:(Lio/dekorate/deps/jackson/core/JsonParser;Lio/dekorate/deps/jackson/databind/DeserializationContext;)Ljava/lang/Object;
      13: areturn
      14: aload_0
      15: getfield      #542                // Field _delegateDeserializer:Lio/dekorate/deps/jackson/databind/JsonDeserializer;
      18: ifnull        39
      21: aload_0
      22: getfield      #294                // Field _valueInstantiator:Lio/dekorate/deps/jackson/databind/deser/ValueInstantiator;
      25: aload_2
      26: aload_0
      27: getfield      #542                // Field _delegateDeserializer:Lio/dekorate/deps/jackson/databind/JsonDeserializer;
      30: aload_1
      31: aload_2
      32: invokevirtual #545                // Method io/dekorate/deps/jackson/databind/JsonDeserializer.deserialize:(Lio/dekorate/deps/jackson/core/JsonParser;Lio/dekorate/deps/jackson/databind/DeserializationContext;)Ljava/lang/Object;
      35: invokevirtual #549                // Method io/dekorate/deps/jackson/databind/deser/ValueInstantiator.createUsingDelegate:(Lio/dekorate/deps/jackson/databind/DeserializationContext;Ljava/lang/Object;)Ljava/lang/Object;
      38: areturn
      39: aload_0
      40: aload_1
      41: aload_2
      42: aload_0
      43: getfield      #294                // Field _valueInstantiator:Lio/dekorate/deps/jackson/databind/deser/ValueInstantiator;
      46: aload_2
      47: invokevirtual #300                // Method io/dekorate/deps/jackson/databind/deser/ValueInstantiator.createUsingDefault:(Lio/dekorate/deps/jackson/databind/DeserializationContext;)Ljava/lang/Object;
      50: invokevirtual #239                // Method deserializeWithExternalTypeId:(Lio/dekorate/deps/jackson/core/JsonParser;Lio/dekorate/deps/jackson/databind/DeserializationContext;Ljava/lang/Object;)Ljava/lang/Object;
      53: areturn

  protected java.lang.Object deserializeWithExternalTypeId(io.dekorate.deps.jackson.core.JsonParser, io.dekorate.deps.jackson.databind.DeserializationContext, java.lang.Object) throws java.io.IOException;
    Code:
       0: aload_0
       1: getfield      #255                // Field _needViewProcesing:Z
       4: ifeq          14
       7: aload_2
       8: invokevirtual #258                // Method io/dekorate/deps/jackson/databind/DeserializationContext.getActiveView:()Ljava/lang/Class;
      11: goto          15
      14: aconst_null
      15: astore        4
      17: aload_0
      18: getfield      #236                // Field _externalTypeIdHandler:Lio/dekorate/deps/jackson/databind/deser/impl/ExternalTypeHandler;
      21: invokevirtual #600                // Method io/dekorate/deps/jackson/databind/deser/impl/ExternalTypeHandler.start:()Lio/dekorate/deps/jackson/databind/deser/impl/ExternalTypeHandler;
      24: astore        5
      26: aload_1
      27: invokevirtual #151                // Method io/dekorate/deps/jackson/core/JsonParser.getCurrentToken:()Lio/dekorate/deps/jackson/core/JsonToken;
      30: astore        6
      32: aload         6
      34: getstatic     #358                // Field io/dekorate/deps/jackson/core/JsonToken.FIELD_NAME:Lio/dekorate/deps/jackson/core/JsonToken;
      37: if_acmpne     240
      40: aload_1
      41: invokevirtual #250                // Method io/dekorate/deps/jackson/core/JsonParser.getCurrentName:()Ljava/lang/String;
      44: astore        7
      46: aload_1
      47: invokevirtual #135                // Method io/dekorate/deps/jackson/core/JsonParser.nextToken:()Lio/dekorate/deps/jackson/core/JsonToken;
      50: astore        6
      52: aload_0
      53: getfield      #106                // Field _beanProperties:Lio/dekorate/deps/jackson/databind/deser/impl/BeanPropertyMap;
      56: aload         7
      58: invokevirtual #266                // Method io/dekorate/deps/jackson/databind/deser/impl/BeanPropertyMap.find:(Ljava/lang/String;)Lio/dekorate/deps/jackson/databind/deser/SettableBeanProperty;
      61: astore        8
      63: aload         8
      65: ifnull        136
      68: aload         6
      70: invokevirtual #603                // Method io/dekorate/deps/jackson/core/JsonToken.isScalarValue:()Z
      73: ifeq          87
      76: aload         5
      78: aload_1
      79: aload_2
      80: aload         7
      82: aload_3
      83: invokevirtual #607                // Method io/dekorate/deps/jackson/databind/deser/impl/ExternalTypeHandler.handleTypePropertyValue:(Lio/dekorate/deps/jackson/core/JsonParser;Lio/dekorate/deps/jackson/databind/DeserializationContext;Ljava/lang/String;Ljava/lang/Object;)Z
      86: pop
      87: aload         4
      89: ifnull        110
      92: aload         8
      94: aload         4
      96: invokevirtual #369                // Method io/dekorate/deps/jackson/databind/deser/SettableBeanProperty.visibleInView:(Ljava/lang/Class;)Z
      99: ifne          110
     102: aload_1
     103: invokevirtual #373                // Method io/dekorate/deps/jackson/core/JsonParser.skipChildren:()Lio/dekorate/deps/jackson/core/JsonParser;
     106: pop
     107: goto          231
     110: aload         8
     112: aload_1
     113: aload_2
     114: aload_3
     115: invokevirtual #272                // Method io/dekorate/deps/jackson/databind/deser/SettableBeanProperty.deserializeAndSet:(Lio/dekorate/deps/jackson/core/JsonParser;Lio/dekorate/deps/jackson/databind/DeserializationContext;Ljava/lang/Object;)V
     118: goto          231
     121: astore        9
     123: aload_0
     124: aload         9
     126: aload_3
     127: aload         7
     129: aload_2
     130: invokevirtual #276                // Method wrapAndThrow:(Ljava/lang/Throwable;Ljava/lang/Object;Ljava/lang/String;Lio/dekorate/deps/jackson/databind/DeserializationContext;)V
     133: goto          231
     136: aload_0
     137: getfield      #436                // Field _ignorableProps:Ljava/util/Set;
     140: ifnull        169
     143: aload_0
     144: getfield      #436                // Field _ignorableProps:Ljava/util/Set;
     147: aload         7
     149: invokeinterface #441,  2          // InterfaceMethod java/util/Set.contains:(Ljava/lang/Object;)Z
     154: ifeq          169
     157: aload_0
     158: aload_1
     159: aload_2
     160: aload_3
     161: aload         7
     163: invokevirtual #444                // Method handleIgnoredProperty:(Lio/dekorate/deps/jackson/core/JsonParser;Lio/dekorate/deps/jackson/databind/DeserializationContext;Ljava/lang/Object;Ljava/lang/String;)V
     166: goto          231
     169: aload         5
     171: aload_1
     172: aload_2
     173: aload         7
     175: aload_3
     176: invokevirtual #610                // Method io/dekorate/deps/jackson/databind/deser/impl/ExternalTypeHandler.handlePropertyValue:(Lio/dekorate/deps/jackson/core/JsonParser;Lio/dekorate/deps/jackson/databind/DeserializationContext;Ljava/lang/String;Ljava/lang/Object;)Z
     179: ifeq          185
     182: goto          231
     185: aload_0
     186: getfield      #448                // Field _anySetter:Lio/dekorate/deps/jackson/databind/deser/SettableAnyProperty;
     189: ifnull        222
     192: aload_0
     193: getfield      #448                // Field _anySetter:Lio/dekorate/deps/jackson/databind/deser/SettableAnyProperty;
     196: aload_1
     197: aload_2
     198: aload_3
     199: aload         7
     201: invokevirtual #568                // Method io/dekorate/deps/jackson/databind/deser/SettableAnyProperty.deserializeAndSet:(Lio/dekorate/deps/jackson/core/JsonParser;Lio/dekorate/deps/jackson/databind/DeserializationContext;Ljava/lang/Object;Ljava/lang/String;)V
     204: goto          231
     207: astore        9
     209: aload_0
     210: aload         9
     212: aload_3
     213: aload         7
     215: aload_2
     216: invokevirtual #276                // Method wrapAndThrow:(Ljava/lang/Throwable;Ljava/lang/Object;Ljava/lang/String;Lio/dekorate/deps/jackson/databind/DeserializationContext;)V
     219: goto          231
     222: aload_0
     223: aload_1
     224: aload_2
     225: aload_3
     226: aload         7
     228: invokevirtual #613                // Method handleUnknownProperty:(Lio/dekorate/deps/jackson/core/JsonParser;Lio/dekorate/deps/jackson/databind/DeserializationContext;Ljava/lang/Object;Ljava/lang/String;)V
     231: aload_1
     232: invokevirtual #135                // Method io/dekorate/deps/jackson/core/JsonParser.nextToken:()Lio/dekorate/deps/jackson/core/JsonToken;
     235: astore        6
     237: goto          32
     240: aload         5
     242: aload_1
     243: aload_2
     244: aload_3
     245: invokevirtual #616                // Method io/dekorate/deps/jackson/databind/deser/impl/ExternalTypeHandler.complete:(Lio/dekorate/deps/jackson/core/JsonParser;Lio/dekorate/deps/jackson/databind/DeserializationContext;Ljava/lang/Object;)Ljava/lang/Object;
     248: areturn
    Exception table:
       from    to  target type
         110   118   121   Class java/lang/Exception
         192   204   207   Class java/lang/Exception

  protected java.lang.Object deserializeUsingPropertyBasedWithExternalTypeId(io.dekorate.deps.jackson.core.JsonParser, io.dekorate.deps.jackson.databind.DeserializationContext) throws java.io.IOException;
    Code:
       0: aload_0
       1: getfield      #236                // Field _externalTypeIdHandler:Lio/dekorate/deps/jackson/databind/deser/impl/ExternalTypeHandler;
       4: invokevirtual #600                // Method io/dekorate/deps/jackson/databind/deser/impl/ExternalTypeHandler.start:()Lio/dekorate/deps/jackson/databind/deser/impl/ExternalTypeHandler;
       7: astore_3
       8: aload_0
       9: getfield      #341                // Field _propertyBasedCreator:Lio/dekorate/deps/jackson/databind/deser/impl/PropertyBasedCreator;
      12: astore        4
      14: aload         4
      16: aload_1
      17: aload_2
      18: aload_0
      19: getfield      #142                // Field _objectIdReader:Lio/dekorate/deps/jackson/databind/deser/impl/ObjectIdReader;
      22: invokevirtual #347                // Method io/dekorate/deps/jackson/databind/deser/impl/PropertyBasedCreator.startBuilding:(Lio/dekorate/deps/jackson/core/JsonParser;Lio/dekorate/deps/jackson/databind/DeserializationContext;Lio/dekorate/deps/jackson/databind/deser/impl/ObjectIdReader;)Lio/dekorate/deps/jackson/databind/deser/impl/PropertyValueBuffer;
      25: astore        5
      27: new           #351                // class io/dekorate/deps/jackson/databind/util/TokenBuffer
      30: dup
      31: aload_1
      32: aload_2
      33: invokespecial #459                // Method io/dekorate/deps/jackson/databind/util/TokenBuffer."<init>":(Lio/dekorate/deps/jackson/core/JsonParser;Lio/dekorate/deps/jackson/databind/DeserializationContext;)V
      36: astore        6
      38: aload         6
      40: invokevirtual #555                // Method io/dekorate/deps/jackson/databind/util/TokenBuffer.writeStartObject:()V
      43: aload_1
      44: invokevirtual #151                // Method io/dekorate/deps/jackson/core/JsonParser.getCurrentToken:()Lio/dekorate/deps/jackson/core/JsonToken;
      47: astore        7
      49: aload         7
      51: getstatic     #358                // Field io/dekorate/deps/jackson/core/JsonToken.FIELD_NAME:Lio/dekorate/deps/jackson/core/JsonToken;
      54: if_acmpne     389
      57: aload_1
      58: invokevirtual #250                // Method io/dekorate/deps/jackson/core/JsonParser.getCurrentName:()Ljava/lang/String;
      61: astore        8
      63: aload_1
      64: invokevirtual #135                // Method io/dekorate/deps/jackson/core/JsonParser.nextToken:()Lio/dekorate/deps/jackson/core/JsonToken;
      67: pop
      68: aload         4
      70: aload         8
      72: invokevirtual #365                // Method io/dekorate/deps/jackson/databind/deser/impl/PropertyBasedCreator.findCreatorProperty:(Ljava/lang/String;)Lio/dekorate/deps/jackson/databind/deser/SettableBeanProperty;
      75: astore        9
      77: aload         9
      79: ifnull        241
      82: aload_3
      83: aload_1
      84: aload_2
      85: aload         8
      87: aconst_null
      88: invokevirtual #610                // Method io/dekorate/deps/jackson/databind/deser/impl/ExternalTypeHandler.handlePropertyValue:(Lio/dekorate/deps/jackson/core/JsonParser;Lio/dekorate/deps/jackson/databind/DeserializationContext;Ljava/lang/String;Ljava/lang/Object;)Z
      91: ifeq          97
      94: goto          380
      97: aload         5
      99: aload         9
     101: aload_0
     102: aload_1
     103: aload_2
     104: aload         9
     106: invokevirtual #377                // Method _deserializeWithErrorWrapping:(Lio/dekorate/deps/jackson/core/JsonParser;Lio/dekorate/deps/jackson/databind/DeserializationContext;Lio/dekorate/deps/jackson/databind/deser/SettableBeanProperty;)Ljava/lang/Object;
     109: invokevirtual #381                // Method io/dekorate/deps/jackson/databind/deser/impl/PropertyValueBuffer.assignParameter:(Lio/dekorate/deps/jackson/databind/deser/SettableBeanProperty;Ljava/lang/Object;)Z
     112: ifeq          380
     115: aload_1
     116: invokevirtual #135                // Method io/dekorate/deps/jackson/core/JsonParser.nextToken:()Lio/dekorate/deps/jackson/core/JsonToken;
     119: astore        7
     121: aload         4
     123: aload_2
     124: aload         5
     126: invokevirtual #385                // Method io/dekorate/deps/jackson/databind/deser/impl/PropertyBasedCreator.build:(Lio/dekorate/deps/jackson/databind/DeserializationContext;Lio/dekorate/deps/jackson/databind/deser/impl/PropertyValueBuffer;)Ljava/lang/Object;
     129: astore        10
     131: goto          155
     134: astore        11
     136: aload_0
     137: aload         11
     139: aload_0
     140: getfield      #401                // Field _beanType:Lio/dekorate/deps/jackson/databind/JavaType;
     143: invokevirtual #406                // Method io/dekorate/deps/jackson/databind/JavaType.getRawClass:()Ljava/lang/Class;
     146: aload         8
     148: aload_2
     149: invokevirtual #276                // Method wrapAndThrow:(Ljava/lang/Throwable;Ljava/lang/Object;Ljava/lang/String;Lio/dekorate/deps/jackson/databind/DeserializationContext;)V
     152: goto          380
     155: aload         7
     157: getstatic     #358                // Field io/dekorate/deps/jackson/core/JsonToken.FIELD_NAME:Lio/dekorate/deps/jackson/core/JsonToken;
     160: if_acmpne     183
     163: aload_1
     164: invokevirtual #135                // Method io/dekorate/deps/jackson/core/JsonParser.nextToken:()Lio/dekorate/deps/jackson/core/JsonToken;
     167: pop
     168: aload         6
     170: aload_1
     171: invokevirtual #467                // Method io/dekorate/deps/jackson/databind/util/TokenBuffer.copyCurrentStructure:(Lio/dekorate/deps/jackson/core/JsonParser;)V
     174: aload_1
     175: invokevirtual #135                // Method io/dekorate/deps/jackson/core/JsonParser.nextToken:()Lio/dekorate/deps/jackson/core/JsonToken;
     178: astore        7
     180: goto          155
     183: aload         10
     185: invokevirtual #85                 // Method java/lang/Object.getClass:()Ljava/lang/Class;
     188: aload_0
     189: getfield      #401                // Field _beanType:Lio/dekorate/deps/jackson/databind/JavaType;
     192: invokevirtual #406                // Method io/dekorate/deps/jackson/databind/JavaType.getRawClass:()Ljava/lang/Class;
     195: if_acmpeq     232
     198: aload_2
     199: aload_0
     200: getfield      #401                // Field _beanType:Lio/dekorate/deps/jackson/databind/JavaType;
     203: ldc_w         #619                // String Cannot create polymorphic instances with external type ids (%s -> %s)
     206: iconst_2
     207: anewarray     #81                 // class java/lang/Object
     210: dup
     211: iconst_0
     212: aload_0
     213: getfield      #401                // Field _beanType:Lio/dekorate/deps/jackson/databind/JavaType;
     216: aastore
     217: dup
     218: iconst_1
     219: aload         10
     221: invokevirtual #85                 // Method java/lang/Object.getClass:()Ljava/lang/Class;
     224: aastore
     225: invokestatic  #623                // Method java/lang/String.format:(Ljava/lang/String;[Ljava/lang/Object;)Ljava/lang/String;
     228: invokevirtual #627                // Method io/dekorate/deps/jackson/databind/DeserializationContext.reportBadDefinition:(Lio/dekorate/deps/jackson/databind/JavaType;Ljava/lang/String;)Ljava/lang/Object;
     231: areturn
     232: aload_3
     233: aload_1
     234: aload_2
     235: aload         10
     237: invokevirtual #616                // Method io/dekorate/deps/jackson/databind/deser/impl/ExternalTypeHandler.complete:(Lio/dekorate/deps/jackson/core/JsonParser;Lio/dekorate/deps/jackson/databind/DeserializationContext;Ljava/lang/Object;)Ljava/lang/Object;
     240: areturn
     241: aload         5
     243: aload         8
     245: invokevirtual #362                // Method io/dekorate/deps/jackson/databind/deser/impl/PropertyValueBuffer.readIdProperty:(Ljava/lang/String;)Z
     248: ifeq          254
     251: goto          380
     254: aload_0
     255: getfield      #106                // Field _beanProperties:Lio/dekorate/deps/jackson/databind/deser/impl/BeanPropertyMap;
     258: aload         8
     260: invokevirtual #266                // Method io/dekorate/deps/jackson/databind/deser/impl/BeanPropertyMap.find:(Ljava/lang/String;)Lio/dekorate/deps/jackson/databind/deser/SettableBeanProperty;
     263: astore        10
     265: aload         10
     267: ifnull        287
     270: aload         5
     272: aload         10
     274: aload         10
     276: aload_1
     277: aload_2
     278: invokevirtual #515                // Method io/dekorate/deps/jackson/databind/deser/SettableBeanProperty.deserialize:(Lio/dekorate/deps/jackson/core/JsonParser;Lio/dekorate/deps/jackson/databind/DeserializationContext;)Ljava/lang/Object;
     281: invokevirtual #420                // Method io/dekorate/deps/jackson/databind/deser/impl/PropertyValueBuffer.bufferProperty:(Lio/dekorate/deps/jackson/databind/deser/SettableBeanProperty;Ljava/lang/Object;)V
     284: goto          380
     287: aload_3
     288: aload_1
     289: aload_2
     290: aload         8
     292: aconst_null
     293: invokevirtual #610                // Method io/dekorate/deps/jackson/databind/deser/impl/ExternalTypeHandler.handlePropertyValue:(Lio/dekorate/deps/jackson/core/JsonParser;Lio/dekorate/deps/jackson/databind/DeserializationContext;Ljava/lang/String;Ljava/lang/Object;)Z
     296: ifeq          302
     299: goto          380
     302: aload_0
     303: getfield      #436                // Field _ignorableProps:Ljava/util/Set;
     306: ifnull        338
     309: aload_0
     310: getfield      #436                // Field _ignorableProps:Ljava/util/Set;
     313: aload         8
     315: invokeinterface #441,  2          // InterfaceMethod java/util/Set.contains:(Ljava/lang/Object;)Z
     320: ifeq          338
     323: aload_0
     324: aload_1
     325: aload_2
     326: aload_0
     327: invokevirtual #206                // Method handledType:()Ljava/lang/Class;
     330: aload         8
     332: invokevirtual #444                // Method handleIgnoredProperty:(Lio/dekorate/deps/jackson/core/JsonParser;Lio/dekorate/deps/jackson/databind/DeserializationContext;Ljava/lang/Object;Ljava/lang/String;)V
     335: goto          380
     338: aload_0
     339: getfield      #448                // Field _anySetter:Lio/dekorate/deps/jackson/databind/deser/SettableAnyProperty;
     342: ifnull        368
     345: aload         5
     347: aload_0
     348: getfield      #448                // Field _anySetter:Lio/dekorate/deps/jackson/databind/deser/SettableAnyProperty;
     351: aload         8
     353: aload_0
     354: getfield      #448                // Field _anySetter:Lio/dekorate/deps/jackson/databind/deser/SettableAnyProperty;
     357: aload_1
     358: aload_2
     359: invokevirtual #452                // Method io/dekorate/deps/jackson/databind/deser/SettableAnyProperty.deserialize:(Lio/dekorate/deps/jackson/core/JsonParser;Lio/dekorate/deps/jackson/databind/DeserializationContext;)Ljava/lang/Object;
     362: invokevirtual #456                // Method io/dekorate/deps/jackson/databind/deser/impl/PropertyValueBuffer.bufferAnyProperty:(Lio/dekorate/deps/jackson/databind/deser/SettableAnyProperty;Ljava/lang/String;Ljava/lang/Object;)V
     365: goto          380
     368: aload_0
     369: aload_1
     370: aload_2
     371: aload_0
     372: getfield      #630                // Field _valueClass:Ljava/lang/Class;
     375: aload         8
     377: invokevirtual #613                // Method handleUnknownProperty:(Lio/dekorate/deps/jackson/core/JsonParser;Lio/dekorate/deps/jackson/databind/DeserializationContext;Ljava/lang/Object;Ljava/lang/String;)V
     380: aload_1
     381: invokevirtual #135                // Method io/dekorate/deps/jackson/core/JsonParser.nextToken:()Lio/dekorate/deps/jackson/core/JsonToken;
     384: astore        7
     386: goto          49
     389: aload         6
     391: invokevirtual #524                // Method io/dekorate/deps/jackson/databind/util/TokenBuffer.writeEndObject:()V
     394: aload_3
     395: aload_1
     396: aload_2
     397: aload         5
     399: aload         4
     401: invokevirtual #633                // Method io/dekorate/deps/jackson/databind/deser/impl/ExternalTypeHandler.complete:(Lio/dekorate/deps/jackson/core/JsonParser;Lio/dekorate/deps/jackson/databind/DeserializationContext;Lio/dekorate/deps/jackson/databind/deser/impl/PropertyValueBuffer;Lio/dekorate/deps/jackson/databind/deser/impl/PropertyBasedCreator;)Ljava/lang/Object;
     404: areturn
     405: astore        8
     407: aload_0
     408: aload         8
     410: aload_2
     411: invokevirtual #389                // Method wrapInstantiationProblem:(Ljava/lang/Throwable;Lio/dekorate/deps/jackson/databind/DeserializationContext;)Ljava/lang/Object;
     414: areturn
    Exception table:
       from    to  target type
         121   131   134   Class java/lang/Exception
         394   404   405   Class java/lang/Exception

  protected java.lang.Exception _creatorReturnedNullException();
    Code:
       0: aload_0
       1: getfield      #635                // Field _nullFromCreator:Ljava/lang/Exception;
       4: ifnonnull     21
       7: aload_0
       8: new           #637                // class java/lang/NullPointerException
      11: dup
      12: ldc_w         #639                // String JSON Creator returned null
      15: invokespecial #641                // Method java/lang/NullPointerException."<init>":(Ljava/lang/String;)V
      18: putfield      #635                // Field _nullFromCreator:Ljava/lang/Exception;
      21: aload_0
      22: getfield      #635                // Field _nullFromCreator:Ljava/lang/Exception;
      25: areturn

  public io.dekorate.deps.jackson.databind.deser.BeanDeserializerBase withIgnorableProperties(java.util.Set);
    Code:
       0: aload_0
       1: aload_1
       2: invokevirtual #644                // Method withIgnorableProperties:(Ljava/util/Set;)Lio/dekorate/deps/jackson/databind/deser/BeanDeserializer;
       5: areturn

  public io.dekorate.deps.jackson.databind.deser.BeanDeserializerBase withObjectIdReader(io.dekorate.deps.jackson.databind.deser.impl.ObjectIdReader);
    Code:
       0: aload_0
       1: aload_1
       2: invokevirtual #647                // Method withObjectIdReader:(Lio/dekorate/deps/jackson/databind/deser/impl/ObjectIdReader;)Lio/dekorate/deps/jackson/databind/deser/BeanDeserializer;
       5: areturn
}
