Compiled from "RetainedMessageSummary.java"
final class software.amazon.awssdk.services.iotdataplane.model.RetainedMessageSummary$BuilderImpl implements software.amazon.awssdk.services.iotdataplane.model.RetainedMessageSummary$Builder {
  private java.lang.String topic;

  private java.lang.Long payloadSize;

  private java.lang.Integer qos;

  private java.lang.Long lastModifiedTime;

  private software.amazon.awssdk.services.iotdataplane.model.RetainedMessageSummary$BuilderImpl();
    Code:
       0: aload_0
       1: invokespecial #7                  // Method java/lang/Object."<init>":()V
       4: return

  private software.amazon.awssdk.services.iotdataplane.model.RetainedMessageSummary$BuilderImpl(software.amazon.awssdk.services.iotdataplane.model.RetainedMessageSummary);
    Code:
       0: aload_0
       1: invokespecial #7                  // Method java/lang/Object."<init>":()V
       4: aload_0
       5: aload_1
       6: invokestatic  #8                  // Method software/amazon/awssdk/services/iotdataplane/model/RetainedMessageSummary.access$600:(Lsoftware/amazon/awssdk/services/iotdataplane/model/RetainedMessageSummary;)Ljava/lang/String;
       9: invokevirtual #9                  // Method topic:(Ljava/lang/String;)Lsoftware/amazon/awssdk/services/iotdataplane/model/RetainedMessageSummary$Builder;
      12: pop
      13: aload_0
      14: aload_1
      15: invokestatic  #10                 // Method software/amazon/awssdk/services/iotdataplane/model/RetainedMessageSummary.access$700:(Lsoftware/amazon/awssdk/services/iotdataplane/model/RetainedMessageSummary;)Ljava/lang/Long;
      18: invokevirtual #11                 // Method payloadSize:(Ljava/lang/Long;)Lsoftware/amazon/awssdk/services/iotdataplane/model/RetainedMessageSummary$Builder;
      21: pop
      22: aload_0
      23: aload_1
      24: invokestatic  #12                 // Method software/amazon/awssdk/services/iotdataplane/model/RetainedMessageSummary.access$800:(Lsoftware/amazon/awssdk/services/iotdataplane/model/RetainedMessageSummary;)Ljava/lang/Integer;
      27: invokevirtual #13                 // Method qos:(Ljava/lang/Integer;)Lsoftware/amazon/awssdk/services/iotdataplane/model/RetainedMessageSummary$Builder;
      30: pop
      31: aload_0
      32: aload_1
      33: invokestatic  #14                 // Method software/amazon/awssdk/services/iotdataplane/model/RetainedMessageSummary.access$900:(Lsoftware/amazon/awssdk/services/iotdataplane/model/RetainedMessageSummary;)Ljava/lang/Long;
      36: invokevirtual #15                 // Method lastModifiedTime:(Ljava/lang/Long;)Lsoftware/amazon/awssdk/services/iotdataplane/model/RetainedMessageSummary$Builder;
      39: pop
      40: return

  public final java.lang.String getTopic();
    Code:
       0: aload_0
       1: getfield      #6                  // Field topic:Ljava/lang/String;
       4: areturn

  public final void setTopic(java.lang.String);
    Code:
       0: aload_0
       1: aload_1
       2: putfield      #6                  // Field topic:Ljava/lang/String;
       5: return

  public final software.amazon.awssdk.services.iotdataplane.model.RetainedMessageSummary$Builder topic(java.lang.String);
    Code:
       0: aload_0
       1: aload_1
       2: putfield      #6                  // Field topic:Ljava/lang/String;
       5: aload_0
       6: areturn

  public final java.lang.Long getPayloadSize();
    Code:
       0: aload_0
       1: getfield      #5                  // Field payloadSize:Ljava/lang/Long;
       4: areturn

  public final void setPayloadSize(java.lang.Long);
    Code:
       0: aload_0
       1: aload_1
       2: putfield      #5                  // Field payloadSize:Ljava/lang/Long;
       5: return

  public final software.amazon.awssdk.services.iotdataplane.model.RetainedMessageSummary$Builder payloadSize(java.lang.Long);
    Code:
       0: aload_0
       1: aload_1
       2: putfield      #5                  // Field payloadSize:Ljava/lang/Long;
       5: aload_0
       6: areturn

  public final java.lang.Integer getQos();
    Code:
       0: aload_0
       1: getfield      #4                  // Field qos:Ljava/lang/Integer;
       4: areturn

  public final void setQos(java.lang.Integer);
    Code:
       0: aload_0
       1: aload_1
       2: putfield      #4                  // Field qos:Ljava/lang/Integer;
       5: return

  public final software.amazon.awssdk.services.iotdataplane.model.RetainedMessageSummary$Builder qos(java.lang.Integer);
    Code:
       0: aload_0
       1: aload_1
       2: putfield      #4                  // Field qos:Ljava/lang/Integer;
       5: aload_0
       6: areturn

  public final java.lang.Long getLastModifiedTime();
    Code:
       0: aload_0
       1: getfield      #3                  // Field lastModifiedTime:Ljava/lang/Long;
       4: areturn

  public final void setLastModifiedTime(java.lang.Long);
    Code:
       0: aload_0
       1: aload_1
       2: putfield      #3                  // Field lastModifiedTime:Ljava/lang/Long;
       5: return

  public final software.amazon.awssdk.services.iotdataplane.model.RetainedMessageSummary$Builder lastModifiedTime(java.lang.Long);
    Code:
       0: aload_0
       1: aload_1
       2: putfield      #3                  // Field lastModifiedTime:Ljava/lang/Long;
       5: aload_0
       6: areturn

  public software.amazon.awssdk.services.iotdataplane.model.RetainedMessageSummary build();
    Code:
       0: new           #16                 // class software/amazon/awssdk/services/iotdataplane/model/RetainedMessageSummary
       3: dup
       4: aload_0
       5: aconst_null
       6: invokespecial #17                 // Method software/amazon/awssdk/services/iotdataplane/model/RetainedMessageSummary."<init>":(Lsoftware/amazon/awssdk/services/iotdataplane/model/RetainedMessageSummary$BuilderImpl;Lsoftware/amazon/awssdk/services/iotdataplane/model/RetainedMessageSummary$1;)V
       9: areturn

  public java.util.List<software.amazon.awssdk.core.SdkField<?>> sdkFields();
    Code:
       0: invokestatic  #18                 // Method software/amazon/awssdk/services/iotdataplane/model/RetainedMessageSummary.access$1100:()Ljava/util/List;
       3: areturn

  public java.lang.Object build();
    Code:
       0: aload_0
       1: invokevirtual #19                 // Method build:()Lsoftware/amazon/awssdk/services/iotdataplane/model/RetainedMessageSummary;
       4: areturn

  static java.lang.String access$000(software.amazon.awssdk.services.iotdataplane.model.RetainedMessageSummary$BuilderImpl);
    Code:
       0: aload_0
       1: getfield      #6                  // Field topic:Ljava/lang/String;
       4: areturn

  static java.lang.Long access$100(software.amazon.awssdk.services.iotdataplane.model.RetainedMessageSummary$BuilderImpl);
    Code:
       0: aload_0
       1: getfield      #5                  // Field payloadSize:Ljava/lang/Long;
       4: areturn

  static java.lang.Integer access$200(software.amazon.awssdk.services.iotdataplane.model.RetainedMessageSummary$BuilderImpl);
    Code:
       0: aload_0
       1: getfield      #4                  // Field qos:Ljava/lang/Integer;
       4: areturn

  static java.lang.Long access$300(software.amazon.awssdk.services.iotdataplane.model.RetainedMessageSummary$BuilderImpl);
    Code:
       0: aload_0
       1: getfield      #3                  // Field lastModifiedTime:Ljava/lang/Long;
       4: areturn

  software.amazon.awssdk.services.iotdataplane.model.RetainedMessageSummary$BuilderImpl(software.amazon.awssdk.services.iotdataplane.model.RetainedMessageSummary, software.amazon.awssdk.services.iotdataplane.model.RetainedMessageSummary$1);
    Code:
       0: aload_0
       1: aload_1
       2: invokespecial #2                  // Method "<init>":(Lsoftware/amazon/awssdk/services/iotdataplane/model/RetainedMessageSummary;)V
       5: return

  software.amazon.awssdk.services.iotdataplane.model.RetainedMessageSummary$BuilderImpl(software.amazon.awssdk.services.iotdataplane.model.RetainedMessageSummary$1);
    Code:
       0: aload_0
       1: invokespecial #1                  // Method "<init>":()V
       4: return
}
