Compiled from "StringUtils.java"
public final class io.sundr.codegen.utils.StringUtils$ToString<X> implements io.sundr.Function<X, java.lang.String> {
  public io.sundr.codegen.utils.StringUtils$ToString();
    Code:
       0: aload_0
       1: invokespecial #15                 // Method java/lang/Object."<init>":()V
       4: return

  public java.lang.String apply(X);
    Code:
       0: aload_1
       1: invokestatic  #25                 // Method java/lang/String.valueOf:(Ljava/lang/Object;)Ljava/lang/String;
       4: areturn

  public java.lang.Object apply(java.lang.Object);
    Code:
       0: aload_0
       1: aload_1
       2: invokevirtual #31                 // Method apply:(Ljava/lang/Object;)Ljava/lang/String;
       5: areturn
}
