Compiled from "BinaryProtocol.java"
class org.apache.hadoop.mapred.pipes.BinaryProtocol$UplinkReaderThread<K2 extends org.apache.hadoop.io.WritableComparable, V2 extends org.apache.hadoop.io.Writable> extends java.lang.Thread {
  private java.io.DataInputStream inStream;

  private org.apache.hadoop.mapred.pipes.UpwardProtocol<K2, V2> handler;

  private K2 key;

  private V2 value;

  private boolean authPending;

  public org.apache.hadoop.mapred.pipes.BinaryProtocol$UplinkReaderThread(java.io.InputStream, org.apache.hadoop.mapred.pipes.UpwardProtocol<K2, V2>, K2, V2) throws java.io.IOException;
    Code:
       0: aload_0
       1: invokespecial #2                  // Method java/lang/Thread."<init>":()V
       4: aload_0
       5: iconst_1
       6: putfield      #3                  // Field authPending:Z
       9: aload_0
      10: new           #4                  // class java/io/DataInputStream
      13: dup
      14: new           #5                  // class java/io/BufferedInputStream
      17: dup
      18: aload_1
      19: ldc           #6                  // int 131072
      21: invokespecial #7                  // Method java/io/BufferedInputStream."<init>":(Ljava/io/InputStream;I)V
      24: invokespecial #8                  // Method java/io/DataInputStream."<init>":(Ljava/io/InputStream;)V
      27: putfield      #9                  // Field inStream:Ljava/io/DataInputStream;
      30: aload_0
      31: aload_2
      32: putfield      #10                 // Field handler:Lorg/apache/hadoop/mapred/pipes/UpwardProtocol;
      35: aload_0
      36: aload_3
      37: putfield      #11                 // Field key:Lorg/apache/hadoop/io/WritableComparable;
      40: aload_0
      41: aload         4
      43: putfield      #12                 // Field value:Lorg/apache/hadoop/io/Writable;
      46: return

  public void closeConnection() throws java.io.IOException;
    Code:
       0: aload_0
       1: getfield      #9                  // Field inStream:Ljava/io/DataInputStream;
       4: invokevirtual #13                 // Method java/io/DataInputStream.close:()V
       7: return

  public void run();
    Code:
       0: invokestatic  #14                 // Method java/lang/Thread.currentThread:()Ljava/lang/Thread;
       3: invokevirtual #15                 // Method java/lang/Thread.isInterrupted:()Z
       6: ifeq          17
       9: new           #16                 // class java/lang/InterruptedException
      12: dup
      13: invokespecial #17                 // Method java/lang/InterruptedException."<init>":()V
      16: athrow
      17: aload_0
      18: getfield      #9                  // Field inStream:Ljava/io/DataInputStream;
      21: invokestatic  #18                 // Method org/apache/hadoop/io/WritableUtils.readVInt:(Ljava/io/DataInput;)I
      24: istore_1
      25: invokestatic  #19                 // Method org/apache/hadoop/mapred/pipes/BinaryProtocol.access$000:()Lorg/slf4j/Logger;
      28: new           #20                 // class java/lang/StringBuilder
      31: dup
      32: invokespecial #21                 // Method java/lang/StringBuilder."<init>":()V
      35: ldc           #22                 // String Handling uplink command
      37: invokevirtual #23                 // Method java/lang/StringBuilder.append:(Ljava/lang/String;)Ljava/lang/StringBuilder;
      40: iload_1
      41: invokevirtual #24                 // Method java/lang/StringBuilder.append:(I)Ljava/lang/StringBuilder;
      44: invokevirtual #25                 // Method java/lang/StringBuilder.toString:()Ljava/lang/String;
      47: invokeinterface #26,  2           // InterfaceMethod org/slf4j/Logger.debug:(Ljava/lang/String;)V
      52: iload_1
      53: getstatic     #27                 // Field org/apache/hadoop/mapred/pipes/BinaryProtocol$MessageType.AUTHENTICATION_RESP:Lorg/apache/hadoop/mapred/pipes/BinaryProtocol$MessageType;
      56: getfield      #28                 // Field org/apache/hadoop/mapred/pipes/BinaryProtocol$MessageType.code:I
      59: if_icmpne     95
      62: aload_0
      63: getfield      #9                  // Field inStream:Ljava/io/DataInputStream;
      66: invokestatic  #29                 // Method org/apache/hadoop/io/Text.readString:(Ljava/io/DataInput;)Ljava/lang/String;
      69: astore_2
      70: aload_0
      71: aload_0
      72: getfield      #10                 // Field handler:Lorg/apache/hadoop/mapred/pipes/UpwardProtocol;
      75: aload_2
      76: invokeinterface #30,  2           // InterfaceMethod org/apache/hadoop/mapred/pipes/UpwardProtocol.authenticate:(Ljava/lang/String;)Z
      81: ifne          88
      84: iconst_1
      85: goto          89
      88: iconst_0
      89: putfield      #3                  // Field authPending:Z
      92: goto          444
      95: aload_0
      96: getfield      #3                  // Field authPending:Z
      99: ifeq          137
     102: invokestatic  #19                 // Method org/apache/hadoop/mapred/pipes/BinaryProtocol.access$000:()Lorg/slf4j/Logger;
     105: new           #20                 // class java/lang/StringBuilder
     108: dup
     109: invokespecial #21                 // Method java/lang/StringBuilder."<init>":()V
     112: ldc           #31                 // String Message
     114: invokevirtual #23                 // Method java/lang/StringBuilder.append:(Ljava/lang/String;)Ljava/lang/StringBuilder;
     117: iload_1
     118: invokevirtual #24                 // Method java/lang/StringBuilder.append:(I)Ljava/lang/StringBuilder;
     121: ldc           #32                 // String  received before authentication is complete. Ignoring
     123: invokevirtual #23                 // Method java/lang/StringBuilder.append:(Ljava/lang/String;)Ljava/lang/StringBuilder;
     126: invokevirtual #25                 // Method java/lang/StringBuilder.toString:()Ljava/lang/String;
     129: invokeinterface #33,  2           // InterfaceMethod org/slf4j/Logger.warn:(Ljava/lang/String;)V
     134: goto          0
     137: iload_1
     138: getstatic     #34                 // Field org/apache/hadoop/mapred/pipes/BinaryProtocol$MessageType.OUTPUT:Lorg/apache/hadoop/mapred/pipes/BinaryProtocol$MessageType;
     141: getfield      #28                 // Field org/apache/hadoop/mapred/pipes/BinaryProtocol$MessageType.code:I
     144: if_icmpne     183
     147: aload_0
     148: aload_0
     149: getfield      #11                 // Field key:Lorg/apache/hadoop/io/WritableComparable;
     152: invokespecial #35                 // Method readObject:(Lorg/apache/hadoop/io/Writable;)V
     155: aload_0
     156: aload_0
     157: getfield      #12                 // Field value:Lorg/apache/hadoop/io/Writable;
     160: invokespecial #35                 // Method readObject:(Lorg/apache/hadoop/io/Writable;)V
     163: aload_0
     164: getfield      #10                 // Field handler:Lorg/apache/hadoop/mapred/pipes/UpwardProtocol;
     167: aload_0
     168: getfield      #11                 // Field key:Lorg/apache/hadoop/io/WritableComparable;
     171: aload_0
     172: getfield      #12                 // Field value:Lorg/apache/hadoop/io/Writable;
     175: invokeinterface #36,  3           // InterfaceMethod org/apache/hadoop/mapred/pipes/UpwardProtocol.output:(Lorg/apache/hadoop/io/WritableComparable;Lorg/apache/hadoop/io/Writable;)V
     180: goto          444
     183: iload_1
     184: getstatic     #37                 // Field org/apache/hadoop/mapred/pipes/BinaryProtocol$MessageType.PARTITIONED_OUTPUT:Lorg/apache/hadoop/mapred/pipes/BinaryProtocol$MessageType;
     187: getfield      #28                 // Field org/apache/hadoop/mapred/pipes/BinaryProtocol$MessageType.code:I
     190: if_icmpne     238
     193: aload_0
     194: getfield      #9                  // Field inStream:Ljava/io/DataInputStream;
     197: invokestatic  #18                 // Method org/apache/hadoop/io/WritableUtils.readVInt:(Ljava/io/DataInput;)I
     200: istore_2
     201: aload_0
     202: aload_0
     203: getfield      #11                 // Field key:Lorg/apache/hadoop/io/WritableComparable;
     206: invokespecial #35                 // Method readObject:(Lorg/apache/hadoop/io/Writable;)V
     209: aload_0
     210: aload_0
     211: getfield      #12                 // Field value:Lorg/apache/hadoop/io/Writable;
     214: invokespecial #35                 // Method readObject:(Lorg/apache/hadoop/io/Writable;)V
     217: aload_0
     218: getfield      #10                 // Field handler:Lorg/apache/hadoop/mapred/pipes/UpwardProtocol;
     221: iload_2
     222: aload_0
     223: getfield      #11                 // Field key:Lorg/apache/hadoop/io/WritableComparable;
     226: aload_0
     227: getfield      #12                 // Field value:Lorg/apache/hadoop/io/Writable;
     230: invokeinterface #38,  4           // InterfaceMethod org/apache/hadoop/mapred/pipes/UpwardProtocol.partitionedOutput:(ILorg/apache/hadoop/io/WritableComparable;Lorg/apache/hadoop/io/Writable;)V
     235: goto          444
     238: iload_1
     239: getstatic     #39                 // Field org/apache/hadoop/mapred/pipes/BinaryProtocol$MessageType.STATUS:Lorg/apache/hadoop/mapred/pipes/BinaryProtocol$MessageType;
     242: getfield      #28                 // Field org/apache/hadoop/mapred/pipes/BinaryProtocol$MessageType.code:I
     245: if_icmpne     267
     248: aload_0
     249: getfield      #10                 // Field handler:Lorg/apache/hadoop/mapred/pipes/UpwardProtocol;
     252: aload_0
     253: getfield      #9                  // Field inStream:Ljava/io/DataInputStream;
     256: invokestatic  #29                 // Method org/apache/hadoop/io/Text.readString:(Ljava/io/DataInput;)Ljava/lang/String;
     259: invokeinterface #40,  2           // InterfaceMethod org/apache/hadoop/mapred/pipes/UpwardProtocol.status:(Ljava/lang/String;)V
     264: goto          444
     267: iload_1
     268: getstatic     #41                 // Field org/apache/hadoop/mapred/pipes/BinaryProtocol$MessageType.PROGRESS:Lorg/apache/hadoop/mapred/pipes/BinaryProtocol$MessageType;
     271: getfield      #28                 // Field org/apache/hadoop/mapred/pipes/BinaryProtocol$MessageType.code:I
     274: if_icmpne     296
     277: aload_0
     278: getfield      #10                 // Field handler:Lorg/apache/hadoop/mapred/pipes/UpwardProtocol;
     281: aload_0
     282: getfield      #9                  // Field inStream:Ljava/io/DataInputStream;
     285: invokevirtual #42                 // Method java/io/DataInputStream.readFloat:()F
     288: invokeinterface #43,  2           // InterfaceMethod org/apache/hadoop/mapred/pipes/UpwardProtocol.progress:(F)V
     293: goto          444
     296: iload_1
     297: getstatic     #44                 // Field org/apache/hadoop/mapred/pipes/BinaryProtocol$MessageType.REGISTER_COUNTER:Lorg/apache/hadoop/mapred/pipes/BinaryProtocol$MessageType;
     300: getfield      #28                 // Field org/apache/hadoop/mapred/pipes/BinaryProtocol$MessageType.code:I
     303: if_icmpne     347
     306: aload_0
     307: getfield      #9                  // Field inStream:Ljava/io/DataInputStream;
     310: invokestatic  #18                 // Method org/apache/hadoop/io/WritableUtils.readVInt:(Ljava/io/DataInput;)I
     313: istore_2
     314: aload_0
     315: getfield      #9                  // Field inStream:Ljava/io/DataInputStream;
     318: invokestatic  #29                 // Method org/apache/hadoop/io/Text.readString:(Ljava/io/DataInput;)Ljava/lang/String;
     321: astore_3
     322: aload_0
     323: getfield      #9                  // Field inStream:Ljava/io/DataInputStream;
     326: invokestatic  #29                 // Method org/apache/hadoop/io/Text.readString:(Ljava/io/DataInput;)Ljava/lang/String;
     329: astore        4
     331: aload_0
     332: getfield      #10                 // Field handler:Lorg/apache/hadoop/mapred/pipes/UpwardProtocol;
     335: iload_2
     336: aload_3
     337: aload         4
     339: invokeinterface #45,  4           // InterfaceMethod org/apache/hadoop/mapred/pipes/UpwardProtocol.registerCounter:(ILjava/lang/String;Ljava/lang/String;)V
     344: goto          444
     347: iload_1
     348: getstatic     #46                 // Field org/apache/hadoop/mapred/pipes/BinaryProtocol$MessageType.INCREMENT_COUNTER:Lorg/apache/hadoop/mapred/pipes/BinaryProtocol$MessageType;
     351: getfield      #28                 // Field org/apache/hadoop/mapred/pipes/BinaryProtocol$MessageType.code:I
     354: if_icmpne     387
     357: aload_0
     358: getfield      #9                  // Field inStream:Ljava/io/DataInputStream;
     361: invokestatic  #18                 // Method org/apache/hadoop/io/WritableUtils.readVInt:(Ljava/io/DataInput;)I
     364: istore_2
     365: aload_0
     366: getfield      #9                  // Field inStream:Ljava/io/DataInputStream;
     369: invokestatic  #47                 // Method org/apache/hadoop/io/WritableUtils.readVLong:(Ljava/io/DataInput;)J
     372: lstore_3
     373: aload_0
     374: getfield      #10                 // Field handler:Lorg/apache/hadoop/mapred/pipes/UpwardProtocol;
     377: iload_2
     378: lload_3
     379: invokeinterface #48,  4           // InterfaceMethod org/apache/hadoop/mapred/pipes/UpwardProtocol.incrementCounter:(IJ)V
     384: goto          444
     387: iload_1
     388: getstatic     #49                 // Field org/apache/hadoop/mapred/pipes/BinaryProtocol$MessageType.DONE:Lorg/apache/hadoop/mapred/pipes/BinaryProtocol$MessageType;
     391: getfield      #28                 // Field org/apache/hadoop/mapred/pipes/BinaryProtocol$MessageType.code:I
     394: if_icmpne     417
     397: invokestatic  #19                 // Method org/apache/hadoop/mapred/pipes/BinaryProtocol.access$000:()Lorg/slf4j/Logger;
     400: ldc           #50                 // String Pipe child done
     402: invokeinterface #26,  2           // InterfaceMethod org/slf4j/Logger.debug:(Ljava/lang/String;)V
     407: aload_0
     408: getfield      #10                 // Field handler:Lorg/apache/hadoop/mapred/pipes/UpwardProtocol;
     411: invokeinterface #51,  1           // InterfaceMethod org/apache/hadoop/mapred/pipes/UpwardProtocol.done:()V
     416: return
     417: new           #52                 // class java/io/IOException
     420: dup
     421: new           #20                 // class java/lang/StringBuilder
     424: dup
     425: invokespecial #21                 // Method java/lang/StringBuilder."<init>":()V
     428: ldc           #53                 // String Bad command code:
     430: invokevirtual #23                 // Method java/lang/StringBuilder.append:(Ljava/lang/String;)Ljava/lang/StringBuilder;
     433: iload_1
     434: invokevirtual #24                 // Method java/lang/StringBuilder.append:(I)Ljava/lang/StringBuilder;
     437: invokevirtual #25                 // Method java/lang/StringBuilder.toString:()Ljava/lang/String;
     440: invokespecial #54                 // Method java/io/IOException."<init>":(Ljava/lang/String;)V
     443: athrow
     444: goto          0
     447: astore_1
     448: return
     449: astore_1
     450: invokestatic  #19                 // Method org/apache/hadoop/mapred/pipes/BinaryProtocol.access$000:()Lorg/slf4j/Logger;
     453: aload_1
     454: invokestatic  #56                 // Method org/apache/hadoop/util/StringUtils.stringifyException:(Ljava/lang/Throwable;)Ljava/lang/String;
     457: invokeinterface #57,  2           // InterfaceMethod org/slf4j/Logger.error:(Ljava/lang/String;)V
     462: aload_0
     463: getfield      #10                 // Field handler:Lorg/apache/hadoop/mapred/pipes/UpwardProtocol;
     466: aload_1
     467: invokeinterface #58,  2           // InterfaceMethod org/apache/hadoop/mapred/pipes/UpwardProtocol.failed:(Ljava/lang/Throwable;)V
     472: return
    Exception table:
       from    to  target type
           0   134   447   Class java/lang/InterruptedException
         137   416   447   Class java/lang/InterruptedException
         417   444   447   Class java/lang/InterruptedException
           0   134   449   Class java/lang/Throwable
         137   416   449   Class java/lang/Throwable
         417   444   449   Class java/lang/Throwable

  private void readObject(org.apache.hadoop.io.Writable) throws java.io.IOException;
    Code:
       0: aload_0
       1: getfield      #9                  // Field inStream:Ljava/io/DataInputStream;
       4: invokestatic  #18                 // Method org/apache/hadoop/io/WritableUtils.readVInt:(Ljava/io/DataInput;)I
       7: istore_2
       8: aload_1
       9: instanceof    #59                 // class org/apache/hadoop/io/BytesWritable
      12: ifeq          40
      15: iload_2
      16: newarray       byte
      18: astore_3
      19: aload_0
      20: getfield      #9                  // Field inStream:Ljava/io/DataInputStream;
      23: aload_3
      24: invokevirtual #60                 // Method java/io/DataInputStream.readFully:([B)V
      27: aload_1
      28: checkcast     #59                 // class org/apache/hadoop/io/BytesWritable
      31: aload_3
      32: iconst_0
      33: iload_2
      34: invokevirtual #61                 // Method org/apache/hadoop/io/BytesWritable.set:([BII)V
      37: goto          80
      40: aload_1
      41: instanceof    #62                 // class org/apache/hadoop/io/Text
      44: ifeq          70
      47: iload_2
      48: newarray       byte
      50: astore_3
      51: aload_0
      52: getfield      #9                  // Field inStream:Ljava/io/DataInputStream;
      55: aload_3
      56: invokevirtual #60                 // Method java/io/DataInputStream.readFully:([B)V
      59: aload_1
      60: checkcast     #62                 // class org/apache/hadoop/io/Text
      63: aload_3
      64: invokevirtual #63                 // Method org/apache/hadoop/io/Text.set:([B)V
      67: goto          80
      70: aload_1
      71: aload_0
      72: getfield      #9                  // Field inStream:Ljava/io/DataInputStream;
      75: invokeinterface #64,  2           // InterfaceMethod org/apache/hadoop/io/Writable.readFields:(Ljava/io/DataInput;)V
      80: return
}
