Compiled from "AdminProxyHandler.java"
public class org.apache.pulsar.proxy.server.AdminProxyHandler$ReplayableProxyContentProvider extends org.eclipse.jetty.proxy.ProxyServlet$ProxyInputStreamContentProvider {
  private java.lang.Boolean firstIteratorCalled;

  private final java.io.ByteArrayOutputStream bodyBuffer;

  final org.apache.pulsar.proxy.server.AdminProxyHandler this$0;

  protected org.apache.pulsar.proxy.server.AdminProxyHandler$ReplayableProxyContentProvider(org.apache.pulsar.proxy.server.AdminProxyHandler, javax.servlet.http.HttpServletRequest, javax.servlet.http.HttpServletResponse, org.eclipse.jetty.client.api.Request, java.io.InputStream);
    Code:
       0: aload_0
       1: aload_1
       2: putfield      #1                  // Field this$0:Lorg/apache/pulsar/proxy/server/AdminProxyHandler;
       5: aload_0
       6: aload_1
       7: aload_2
       8: aload_3
       9: aload         4
      11: aload         5
      13: invokespecial #2                  // Method org/eclipse/jetty/proxy/ProxyServlet$ProxyInputStreamContentProvider."<init>":(Lorg/eclipse/jetty/proxy/ProxyServlet;Ljavax/servlet/http/HttpServletRequest;Ljavax/servlet/http/HttpServletResponse;Lorg/eclipse/jetty/client/api/Request;Ljava/io/InputStream;)V
      16: aload_0
      17: iconst_0
      18: invokestatic  #3                  // Method java/lang/Boolean.valueOf:(Z)Ljava/lang/Boolean;
      21: putfield      #4                  // Field firstIteratorCalled:Ljava/lang/Boolean;
      24: aload_0
      25: new           #5                  // class java/io/ByteArrayOutputStream
      28: dup
      29: aload_2
      30: invokeinterface #6,  1            // InterfaceMethod javax/servlet/http/HttpServletRequest.getContentLength:()I
      35: iconst_0
      36: invokestatic  #7                  // Method java/lang/Math.max:(II)I
      39: invokespecial #8                  // Method java/io/ByteArrayOutputStream."<init>":(I)V
      42: putfield      #9                  // Field bodyBuffer:Ljava/io/ByteArrayOutputStream;
      45: return

  public java.util.Iterator<java.nio.ByteBuffer> iterator();
    Code:
       0: aload_0
       1: getfield      #4                  // Field firstIteratorCalled:Ljava/lang/Boolean;
       4: invokevirtual #10                 // Method java/lang/Boolean.booleanValue:()Z
       7: ifeq          29
      10: aload_0
      11: getfield      #9                  // Field bodyBuffer:Ljava/io/ByteArrayOutputStream;
      14: invokevirtual #11                 // Method java/io/ByteArrayOutputStream.toByteArray:()[B
      17: invokestatic  #12                 // Method java/nio/ByteBuffer.wrap:([B)Ljava/nio/ByteBuffer;
      20: invokestatic  #13                 // Method java/util/Collections.singleton:(Ljava/lang/Object;)Ljava/util/Set;
      23: invokeinterface #14,  1           // InterfaceMethod java/util/Set.iterator:()Ljava/util/Iterator;
      28: areturn
      29: aload_0
      30: iconst_1
      31: invokestatic  #3                  // Method java/lang/Boolean.valueOf:(Z)Ljava/lang/Boolean;
      34: putfield      #4                  // Field firstIteratorCalled:Ljava/lang/Boolean;
      37: aload_0
      38: invokespecial #15                 // Method org/eclipse/jetty/proxy/ProxyServlet$ProxyInputStreamContentProvider.iterator:()Ljava/util/Iterator;
      41: areturn

  protected java.nio.ByteBuffer onRead(byte[], int, int);
    Code:
       0: aload_0
       1: getfield      #9                  // Field bodyBuffer:Ljava/io/ByteArrayOutputStream;
       4: aload_1
       5: iload_2
       6: iload_3
       7: invokevirtual #16                 // Method java/io/ByteArrayOutputStream.write:([BII)V
      10: aload_0
      11: aload_1
      12: iload_2
      13: iload_3
      14: invokespecial #17                 // Method org/eclipse/jetty/proxy/ProxyServlet$ProxyInputStreamContentProvider.onRead:([BII)Ljava/nio/ByteBuffer;
      17: areturn
}
