Compiled from "PathLib.java"
public class org.apache.jena.sparql.path.PathLib {
  public org.apache.jena.sparql.path.PathLib();
    Code:
       0: aload_0
       1: invokespecial #1                  // Method java/lang/Object."<init>":()V
       4: return

  public static org.apache.jena.sparql.algebra.Op pathToTriples(org.apache.jena.sparql.core.PathBlock);
    Code:
       0: aconst_null
       1: astore_1
       2: aconst_null
       3: astore_2
       4: aload_0
       5: invokevirtual #2                  // Method org/apache/jena/sparql/core/PathBlock.iterator:()Ljava/util/ListIterator;
       8: astore_3
       9: aload_3
      10: invokeinterface #3,  1            // InterfaceMethod java/util/Iterator.hasNext:()Z
      15: ifeq          90
      18: aload_3
      19: invokeinterface #4,  1            // InterfaceMethod java/util/Iterator.next:()Ljava/lang/Object;
      24: checkcast     #5                  // class org/apache/jena/sparql/core/TriplePath
      27: astore        4
      29: aload         4
      31: invokevirtual #6                  // Method org/apache/jena/sparql/core/TriplePath.isTriple:()Z
      34: ifeq          61
      37: aload_1
      38: ifnonnull     49
      41: new           #7                  // class org/apache/jena/sparql/core/BasicPattern
      44: dup
      45: invokespecial #8                  // Method org/apache/jena/sparql/core/BasicPattern."<init>":()V
      48: astore_1
      49: aload_1
      50: aload         4
      52: invokevirtual #9                  // Method org/apache/jena/sparql/core/TriplePath.asTriple:()Lorg/apache/jena/graph/Triple;
      55: invokevirtual #10                 // Method org/apache/jena/sparql/core/BasicPattern.add:(Lorg/apache/jena/graph/Triple;)V
      58: goto          9
      61: aload_1
      62: aload_2
      63: invokestatic  #11                 // Method flush:(Lorg/apache/jena/sparql/core/BasicPattern;Lorg/apache/jena/sparql/algebra/Op;)Lorg/apache/jena/sparql/algebra/Op;
      66: astore_2
      67: aconst_null
      68: astore_1
      69: new           #12                 // class org/apache/jena/sparql/algebra/op/OpPath
      72: dup
      73: aload         4
      75: invokespecial #13                 // Method org/apache/jena/sparql/algebra/op/OpPath."<init>":(Lorg/apache/jena/sparql/core/TriplePath;)V
      78: astore        5
      80: aload_2
      81: aload         5
      83: invokestatic  #14                 // Method org/apache/jena/sparql/algebra/op/OpSequence.create:(Lorg/apache/jena/sparql/algebra/Op;Lorg/apache/jena/sparql/algebra/Op;)Lorg/apache/jena/sparql/algebra/Op;
      86: astore_2
      87: goto          9
      90: aload_1
      91: aload_2
      92: invokestatic  #11                 // Method flush:(Lorg/apache/jena/sparql/core/BasicPattern;Lorg/apache/jena/sparql/algebra/Op;)Lorg/apache/jena/sparql/algebra/Op;
      95: astore_2
      96: aload_2
      97: areturn

  private static org.apache.jena.sparql.algebra.Op flush(org.apache.jena.sparql.core.BasicPattern, org.apache.jena.sparql.algebra.Op);
    Code:
       0: aload_0
       1: ifnull        11
       4: aload_0
       5: invokevirtual #15                 // Method org/apache/jena/sparql/core/BasicPattern.isEmpty:()Z
       8: ifeq          13
      11: aload_1
      12: areturn
      13: new           #16                 // class org/apache/jena/sparql/algebra/op/OpBGP
      16: dup
      17: aload_0
      18: invokespecial #17                 // Method org/apache/jena/sparql/algebra/op/OpBGP."<init>":(Lorg/apache/jena/sparql/core/BasicPattern;)V
      21: astore_2
      22: aload_1
      23: aload_2
      24: invokestatic  #14                 // Method org/apache/jena/sparql/algebra/op/OpSequence.create:(Lorg/apache/jena/sparql/algebra/Op;Lorg/apache/jena/sparql/algebra/Op;)Lorg/apache/jena/sparql/algebra/Op;
      27: astore_1
      28: aload_1
      29: areturn

  public static void install(java.lang.String, org.apache.jena.sparql.path.Path);
    Code:
       0: aload_0
       1: aload_1
       2: invokestatic  #18                 // Method org/apache/jena/sparql/pfunction/PropertyFunctionRegistry.get:()Lorg/apache/jena/sparql/pfunction/PropertyFunctionRegistry;
       5: invokestatic  #19                 // Method install:(Ljava/lang/String;Lorg/apache/jena/sparql/path/Path;Lorg/apache/jena/sparql/pfunction/PropertyFunctionRegistry;)V
       8: return

  public static void install(java.lang.String, org.apache.jena.sparql.path.Path, org.apache.jena.sparql.pfunction.PropertyFunctionRegistry);
    Code:
       0: aload_1
       1: invokedynamic #20,  0             // InvokeDynamic #0:create:(Lorg/apache/jena/sparql/path/Path;)Lorg/apache/jena/sparql/pfunction/PropertyFunctionFactory;
       6: astore_3
       7: aload_2
       8: aload_0
       9: aload_3
      10: invokevirtual #21                 // Method org/apache/jena/sparql/pfunction/PropertyFunctionRegistry.put:(Ljava/lang/String;Lorg/apache/jena/sparql/pfunction/PropertyFunctionFactory;)V
      13: return

  public static org.apache.jena.sparql.engine.QueryIterator execTriplePath(org.apache.jena.sparql.engine.binding.Binding, org.apache.jena.sparql.core.TriplePath, org.apache.jena.sparql.engine.ExecutionContext);
    Code:
       0: aload_1
       1: invokevirtual #6                  // Method org/apache/jena/sparql/core/TriplePath.isTriple:()Z
       4: ifeq          36
       7: new           #22                 // class org/apache/jena/sparql/path/P_Link
      10: dup
      11: aload_1
      12: invokevirtual #23                 // Method org/apache/jena/sparql/core/TriplePath.getPredicate:()Lorg/apache/jena/graph/Node;
      15: invokespecial #24                 // Method org/apache/jena/sparql/path/P_Link."<init>":(Lorg/apache/jena/graph/Node;)V
      18: astore_3
      19: new           #5                  // class org/apache/jena/sparql/core/TriplePath
      22: dup
      23: aload_1
      24: invokevirtual #25                 // Method org/apache/jena/sparql/core/TriplePath.getSubject:()Lorg/apache/jena/graph/Node;
      27: aload_3
      28: aload_1
      29: invokevirtual #26                 // Method org/apache/jena/sparql/core/TriplePath.getObject:()Lorg/apache/jena/graph/Node;
      32: invokespecial #27                 // Method org/apache/jena/sparql/core/TriplePath."<init>":(Lorg/apache/jena/graph/Node;Lorg/apache/jena/sparql/path/Path;Lorg/apache/jena/graph/Node;)V
      35: astore_1
      36: aload_0
      37: aload_1
      38: invokevirtual #25                 // Method org/apache/jena/sparql/core/TriplePath.getSubject:()Lorg/apache/jena/graph/Node;
      41: aload_1
      42: invokevirtual #28                 // Method org/apache/jena/sparql/core/TriplePath.getPath:()Lorg/apache/jena/sparql/path/Path;
      45: aload_1
      46: invokevirtual #26                 // Method org/apache/jena/sparql/core/TriplePath.getObject:()Lorg/apache/jena/graph/Node;
      49: aload_2
      50: invokestatic  #29                 // Method execTriplePath:(Lorg/apache/jena/sparql/engine/binding/Binding;Lorg/apache/jena/graph/Node;Lorg/apache/jena/sparql/path/Path;Lorg/apache/jena/graph/Node;Lorg/apache/jena/sparql/engine/ExecutionContext;)Lorg/apache/jena/sparql/engine/QueryIterator;
      53: areturn

  public static org.apache.jena.sparql.engine.QueryIterator execTriplePath(org.apache.jena.sparql.engine.binding.Binding, org.apache.jena.graph.Node, org.apache.jena.sparql.path.Path, org.apache.jena.graph.Node, org.apache.jena.sparql.engine.ExecutionContext);
    Code:
       0: aload_1
       1: aload_2
       2: aload_3
       3: aload         4
       5: invokevirtual #30                 // Method org/apache/jena/sparql/engine/ExecutionContext.getContext:()Lorg/apache/jena/sparql/util/Context;
       8: invokestatic  #31                 // Method org/apache/jena/sparql/mgt/Explain.explain:(Lorg/apache/jena/graph/Node;Lorg/apache/jena/sparql/path/Path;Lorg/apache/jena/graph/Node;Lorg/apache/jena/sparql/util/Context;)V
      11: aload_0
      12: aload_1
      13: invokestatic  #32                 // Method org/apache/jena/sparql/core/Var.lookup:(Lorg/apache/jena/sparql/engine/binding/Binding;Lorg/apache/jena/graph/Node;)Lorg/apache/jena/graph/Node;
      16: astore_1
      17: aload_0
      18: aload_3
      19: invokestatic  #32                 // Method org/apache/jena/sparql/core/Var.lookup:(Lorg/apache/jena/sparql/engine/binding/Binding;Lorg/apache/jena/graph/Node;)Lorg/apache/jena/graph/Node;
      22: astore_3
      23: aconst_null
      24: astore        5
      26: aconst_null
      27: astore        6
      29: aload         4
      31: invokevirtual #33                 // Method org/apache/jena/sparql/engine/ExecutionContext.getActiveGraph:()Lorg/apache/jena/graph/Graph;
      34: astore        7
      36: aload_1
      37: invokestatic  #34                 // Method org/apache/jena/sparql/core/Var.isVar:(Lorg/apache/jena/graph/Node;)Z
      40: ifeq          90
      43: aload_3
      44: invokestatic  #34                 // Method org/apache/jena/sparql/core/Var.isVar:(Lorg/apache/jena/graph/Node;)Z
      47: ifeq          90
      50: aload_1
      51: aload_3
      52: invokevirtual #35                 // Method org/apache/jena/graph/Node.equals:(Ljava/lang/Object;)Z
      55: ifeq          72
      58: aload_0
      59: aload         7
      61: aload_1
      62: invokestatic  #36                 // Method org/apache/jena/sparql/core/Var.alloc:(Lorg/apache/jena/graph/Node;)Lorg/apache/jena/sparql/core/Var;
      65: aload_2
      66: aload         4
      68: invokestatic  #37                 // Method execUngroundedPathSameVar:(Lorg/apache/jena/sparql/engine/binding/Binding;Lorg/apache/jena/graph/Graph;Lorg/apache/jena/sparql/core/Var;Lorg/apache/jena/sparql/path/Path;Lorg/apache/jena/sparql/engine/ExecutionContext;)Lorg/apache/jena/sparql/engine/QueryIterator;
      71: areturn
      72: aload_0
      73: aload         7
      75: aload_1
      76: invokestatic  #36                 // Method org/apache/jena/sparql/core/Var.alloc:(Lorg/apache/jena/graph/Node;)Lorg/apache/jena/sparql/core/Var;
      79: aload_2
      80: aload_3
      81: invokestatic  #36                 // Method org/apache/jena/sparql/core/Var.alloc:(Lorg/apache/jena/graph/Node;)Lorg/apache/jena/sparql/core/Var;
      84: aload         4
      86: invokestatic  #38                 // Method execUngroundedPath:(Lorg/apache/jena/sparql/engine/binding/Binding;Lorg/apache/jena/graph/Graph;Lorg/apache/jena/sparql/core/Var;Lorg/apache/jena/sparql/path/Path;Lorg/apache/jena/sparql/core/Var;Lorg/apache/jena/sparql/engine/ExecutionContext;)Lorg/apache/jena/sparql/engine/QueryIterator;
      89: areturn
      90: aload_1
      91: invokestatic  #34                 // Method org/apache/jena/sparql/core/Var.isVar:(Lorg/apache/jena/graph/Node;)Z
      94: ifne          116
      97: aload_3
      98: invokestatic  #34                 // Method org/apache/jena/sparql/core/Var.isVar:(Lorg/apache/jena/graph/Node;)Z
     101: ifne          116
     104: aload_0
     105: aload         7
     107: aload_1
     108: aload_2
     109: aload_3
     110: aload         4
     112: invokestatic  #39                 // Method evalGroundedPath:(Lorg/apache/jena/sparql/engine/binding/Binding;Lorg/apache/jena/graph/Graph;Lorg/apache/jena/graph/Node;Lorg/apache/jena/sparql/path/Path;Lorg/apache/jena/graph/Node;Lorg/apache/jena/sparql/engine/ExecutionContext;)Lorg/apache/jena/sparql/engine/QueryIterator;
     115: areturn
     116: aload_1
     117: invokestatic  #34                 // Method org/apache/jena/sparql/core/Var.isVar:(Lorg/apache/jena/graph/Node;)Z
     120: ifeq          143
     123: aload         7
     125: aload_3
     126: aload_2
     127: aload         4
     129: invokevirtual #30                 // Method org/apache/jena/sparql/engine/ExecutionContext.getContext:()Lorg/apache/jena/sparql/util/Context;
     132: invokestatic  #40                 // Method org/apache/jena/sparql/path/eval/PathEval.evalReverse:(Lorg/apache/jena/graph/Graph;Lorg/apache/jena/graph/Node;Lorg/apache/jena/sparql/path/Path;Lorg/apache/jena/sparql/util/Context;)Ljava/util/Iterator;
     135: astore        5
     137: aload_1
     138: astore        6
     140: goto          160
     143: aload         7
     145: aload_1
     146: aload_2
     147: aload         4
     149: invokevirtual #30                 // Method org/apache/jena/sparql/engine/ExecutionContext.getContext:()Lorg/apache/jena/sparql/util/Context;
     152: invokestatic  #41                 // Method org/apache/jena/sparql/path/eval/PathEval.eval:(Lorg/apache/jena/graph/Graph;Lorg/apache/jena/graph/Node;Lorg/apache/jena/sparql/path/Path;Lorg/apache/jena/sparql/util/Context;)Ljava/util/Iterator;
     155: astore        5
     157: aload_3
     158: astore        6
     160: aload_0
     161: aload         5
     163: aload         6
     165: aload         4
     167: invokestatic  #42                 // Method evalGroundedOneEnd:(Lorg/apache/jena/sparql/engine/binding/Binding;Ljava/util/Iterator;Lorg/apache/jena/graph/Node;Lorg/apache/jena/sparql/engine/ExecutionContext;)Lorg/apache/jena/sparql/engine/QueryIterator;
     170: areturn

  private static org.apache.jena.sparql.engine.QueryIterator evalGroundedOneEnd(org.apache.jena.sparql.engine.binding.Binding, java.util.Iterator<org.apache.jena.graph.Node>, org.apache.jena.graph.Node, org.apache.jena.sparql.engine.ExecutionContext);
    Code:
       0: new           #43                 // class java/util/ArrayList
       3: dup
       4: invokespecial #44                 // Method java/util/ArrayList."<init>":()V
       7: astore        4
       9: aload_2
      10: invokestatic  #34                 // Method org/apache/jena/sparql/core/Var.isVar:(Lorg/apache/jena/graph/Node;)Z
      13: ifne          26
      16: new           #45                 // class org/apache/jena/sparql/ARQInternalErrorException
      19: dup
      20: ldc           #46                 // String Non-variable endnode in _execTriplePath
      22: invokespecial #47                 // Method org/apache/jena/sparql/ARQInternalErrorException."<init>":(Ljava/lang/String;)V
      25: athrow
      26: aload_2
      27: invokestatic  #36                 // Method org/apache/jena/sparql/core/Var.alloc:(Lorg/apache/jena/graph/Node;)Lorg/apache/jena/sparql/core/Var;
      30: astore        5
      32: aload_1
      33: invokeinterface #3,  1            // InterfaceMethod java/util/Iterator.hasNext:()Z
      38: ifeq          71
      41: aload_1
      42: invokeinterface #4,  1            // InterfaceMethod java/util/Iterator.next:()Ljava/lang/Object;
      47: checkcast     #48                 // class org/apache/jena/graph/Node
      50: astore        6
      52: aload         4
      54: aload_0
      55: aload         5
      57: aload         6
      59: invokestatic  #49                 // Method org/apache/jena/sparql/engine/binding/BindingFactory.binding:(Lorg/apache/jena/sparql/engine/binding/Binding;Lorg/apache/jena/sparql/core/Var;Lorg/apache/jena/graph/Node;)Lorg/apache/jena/sparql/engine/binding/Binding;
      62: invokeinterface #50,  2           // InterfaceMethod java/util/List.add:(Ljava/lang/Object;)Z
      67: pop
      68: goto          32
      71: new           #51                 // class org/apache/jena/sparql/engine/iterator/QueryIterPlainWrapper
      74: dup
      75: aload         4
      77: invokeinterface #52,  1           // InterfaceMethod java/util/List.iterator:()Ljava/util/Iterator;
      82: aload_3
      83: invokespecial #53                 // Method org/apache/jena/sparql/engine/iterator/QueryIterPlainWrapper."<init>":(Ljava/util/Iterator;Lorg/apache/jena/sparql/engine/ExecutionContext;)V
      86: areturn

  private static org.apache.jena.sparql.engine.QueryIterator evalGroundedPath(org.apache.jena.sparql.engine.binding.Binding, org.apache.jena.graph.Graph, org.apache.jena.graph.Node, org.apache.jena.sparql.path.Path, org.apache.jena.graph.Node, org.apache.jena.sparql.engine.ExecutionContext);
    Code:
       0: aload_1
       1: aload_2
       2: aload_3
       3: aload         5
       5: invokevirtual #30                 // Method org/apache/jena/sparql/engine/ExecutionContext.getContext:()Lorg/apache/jena/sparql/util/Context;
       8: invokestatic  #41                 // Method org/apache/jena/sparql/path/eval/PathEval.eval:(Lorg/apache/jena/graph/Graph;Lorg/apache/jena/graph/Node;Lorg/apache/jena/sparql/path/Path;Lorg/apache/jena/sparql/util/Context;)Ljava/util/Iterator;
      11: astore        6
      13: iconst_0
      14: istore        7
      16: aload         6
      18: invokeinterface #3,  1            // InterfaceMethod java/util/Iterator.hasNext:()Z
      23: ifeq          54
      26: aload         6
      28: invokeinterface #4,  1            // InterfaceMethod java/util/Iterator.next:()Ljava/lang/Object;
      33: checkcast     #48                 // class org/apache/jena/graph/Node
      36: astore        8
      38: aload         8
      40: aload         4
      42: invokevirtual #54                 // Method org/apache/jena/graph/Node.sameValueAs:(Ljava/lang/Object;)Z
      45: ifeq          51
      48: iinc          7, 1
      51: goto          16
      54: new           #55                 // class org/apache/jena/sparql/engine/iterator/QueryIterYieldN
      57: dup
      58: iload         7
      60: aload_0
      61: aload         5
      63: invokespecial #56                 // Method org/apache/jena/sparql/engine/iterator/QueryIterYieldN."<init>":(ILorg/apache/jena/sparql/engine/binding/Binding;Lorg/apache/jena/sparql/engine/ExecutionContext;)V
      66: areturn

  private static org.apache.jena.sparql.engine.QueryIterator execUngroundedPath(org.apache.jena.sparql.engine.binding.Binding, org.apache.jena.graph.Graph, org.apache.jena.sparql.core.Var, org.apache.jena.sparql.path.Path, org.apache.jena.sparql.core.Var, org.apache.jena.sparql.engine.ExecutionContext);
    Code:
       0: aload_1
       1: aload_3
       2: aload         5
       4: invokestatic  #57                 // Method determineUngroundedStartingSet:(Lorg/apache/jena/graph/Graph;Lorg/apache/jena/sparql/path/Path;Lorg/apache/jena/sparql/engine/ExecutionContext;)Ljava/util/Iterator;
       7: astore        6
       9: new           #58                 // class org/apache/jena/sparql/engine/iterator/QueryIterConcat
      12: dup
      13: aload         5
      15: invokespecial #59                 // Method org/apache/jena/sparql/engine/iterator/QueryIterConcat."<init>":(Lorg/apache/jena/sparql/engine/ExecutionContext;)V
      18: astore        7
      20: aload         6
      22: invokeinterface #3,  1            // InterfaceMethod java/util/Iterator.hasNext:()Z
      27: ifeq          88
      30: aload         6
      32: invokeinterface #4,  1            // InterfaceMethod java/util/Iterator.next:()Ljava/lang/Object;
      37: checkcast     #48                 // class org/apache/jena/graph/Node
      40: astore        8
      42: aload_0
      43: aload_2
      44: aload         8
      46: invokestatic  #49                 // Method org/apache/jena/sparql/engine/binding/BindingFactory.binding:(Lorg/apache/jena/sparql/engine/binding/Binding;Lorg/apache/jena/sparql/core/Var;Lorg/apache/jena/graph/Node;)Lorg/apache/jena/sparql/engine/binding/Binding;
      49: astore        9
      51: aload_1
      52: aload         8
      54: aload_3
      55: aload         5
      57: invokevirtual #30                 // Method org/apache/jena/sparql/engine/ExecutionContext.getContext:()Lorg/apache/jena/sparql/util/Context;
      60: invokestatic  #41                 // Method org/apache/jena/sparql/path/eval/PathEval.eval:(Lorg/apache/jena/graph/Graph;Lorg/apache/jena/graph/Node;Lorg/apache/jena/sparql/path/Path;Lorg/apache/jena/sparql/util/Context;)Ljava/util/Iterator;
      63: astore        10
      65: aload         9
      67: aload         10
      69: aload         4
      71: aload         5
      73: invokestatic  #42                 // Method evalGroundedOneEnd:(Lorg/apache/jena/sparql/engine/binding/Binding;Ljava/util/Iterator;Lorg/apache/jena/graph/Node;Lorg/apache/jena/sparql/engine/ExecutionContext;)Lorg/apache/jena/sparql/engine/QueryIterator;
      76: astore        11
      78: aload         7
      80: aload         11
      82: invokevirtual #60                 // Method org/apache/jena/sparql/engine/iterator/QueryIterConcat.add:(Lorg/apache/jena/sparql/engine/QueryIterator;)V
      85: goto          20
      88: aload         7
      90: areturn

  private static org.apache.jena.sparql.engine.QueryIterator execUngroundedPathSameVar(org.apache.jena.sparql.engine.binding.Binding, org.apache.jena.graph.Graph, org.apache.jena.sparql.core.Var, org.apache.jena.sparql.path.Path, org.apache.jena.sparql.engine.ExecutionContext);
    Code:
       0: aload_1
       1: aload_3
       2: aload         4
       4: invokestatic  #57                 // Method determineUngroundedStartingSet:(Lorg/apache/jena/graph/Graph;Lorg/apache/jena/sparql/path/Path;Lorg/apache/jena/sparql/engine/ExecutionContext;)Ljava/util/Iterator;
       7: astore        5
       9: new           #58                 // class org/apache/jena/sparql/engine/iterator/QueryIterConcat
      12: dup
      13: aload         4
      15: invokespecial #59                 // Method org/apache/jena/sparql/engine/iterator/QueryIterConcat."<init>":(Lorg/apache/jena/sparql/engine/ExecutionContext;)V
      18: astore        6
      20: aload         5
      22: invokeinterface #3,  1            // InterfaceMethod java/util/Iterator.hasNext:()Z
      27: ifeq          94
      30: aload         5
      32: invokeinterface #4,  1            // InterfaceMethod java/util/Iterator.next:()Ljava/lang/Object;
      37: checkcast     #48                 // class org/apache/jena/graph/Node
      40: astore        7
      42: aload_0
      43: aload_2
      44: aload         7
      46: invokestatic  #49                 // Method org/apache/jena/sparql/engine/binding/BindingFactory.binding:(Lorg/apache/jena/sparql/engine/binding/Binding;Lorg/apache/jena/sparql/core/Var;Lorg/apache/jena/graph/Node;)Lorg/apache/jena/sparql/engine/binding/Binding;
      49: astore        8
      51: aload_1
      52: aload         7
      54: aload_3
      55: aload         7
      57: aload         4
      59: invokestatic  #61                 // Method existsPath:(Lorg/apache/jena/graph/Graph;Lorg/apache/jena/graph/Node;Lorg/apache/jena/sparql/path/Path;Lorg/apache/jena/graph/Node;Lorg/apache/jena/sparql/engine/ExecutionContext;)I
      62: istore        9
      64: iload         9
      66: ifle          91
      69: new           #55                 // class org/apache/jena/sparql/engine/iterator/QueryIterYieldN
      72: dup
      73: iload         9
      75: aload         8
      77: aload         4
      79: invokespecial #56                 // Method org/apache/jena/sparql/engine/iterator/QueryIterYieldN."<init>":(ILorg/apache/jena/sparql/engine/binding/Binding;Lorg/apache/jena/sparql/engine/ExecutionContext;)V
      82: astore        10
      84: aload         6
      86: aload         10
      88: invokevirtual #60                 // Method org/apache/jena/sparql/engine/iterator/QueryIterConcat.add:(Lorg/apache/jena/sparql/engine/QueryIterator;)V
      91: goto          20
      94: aload         6
      96: areturn

  private static java.util.Iterator<org.apache.jena.graph.Node> determineUngroundedStartingSet(org.apache.jena.graph.Graph, org.apache.jena.sparql.path.Path, org.apache.jena.sparql.engine.ExecutionContext);
    Code:
       0: aload_1
       1: instanceof    #62                 // class org/apache/jena/sparql/path/P_OneOrMore1
       4: ifne          14
       7: aload_1
       8: instanceof    #63                 // class org/apache/jena/sparql/path/P_OneOrMoreN
      11: ifeq          175
      14: aload_1
      15: checkcast     #64                 // class org/apache/jena/sparql/path/P_Path1
      18: invokevirtual #65                 // Method org/apache/jena/sparql/path/P_Path1.getSubPath:()Lorg/apache/jena/sparql/path/Path;
      21: astore_3
      22: aload_3
      23: instanceof    #22                 // class org/apache/jena/sparql/path/P_Link
      26: ifeq          88
      29: aload_3
      30: checkcast     #22                 // class org/apache/jena/sparql/path/P_Link
      33: astore        4
      35: aload         4
      37: invokevirtual #66                 // Method org/apache/jena/sparql/path/P_Link.getNode:()Lorg/apache/jena/graph/Node;
      40: aload_2
      41: invokevirtual #30                 // Method org/apache/jena/sparql/engine/ExecutionContext.getContext:()Lorg/apache/jena/sparql/util/Context;
      44: invokestatic  #67                 // Method isPropertyFunction:(Lorg/apache/jena/graph/Node;Lorg/apache/jena/sparql/util/Context;)Z
      47: ifne          85
      50: aload_0
      51: aconst_null
      52: aload         4
      54: invokevirtual #66                 // Method org/apache/jena/sparql/path/P_Link.getNode:()Lorg/apache/jena/graph/Node;
      57: aconst_null
      58: invokeinterface #68,  4           // InterfaceMethod org/apache/jena/graph/Graph.find:(Lorg/apache/jena/graph/Node;Lorg/apache/jena/graph/Node;Lorg/apache/jena/graph/Node;)Lorg/apache/jena/util/iterator/ExtendedIterator;
      63: astore        5
      65: aload         5
      67: invokestatic  #69                 // Method org/apache/jena/atlas/iterator/Iter.iter:(Ljava/util/Iterator;)Lorg/apache/jena/atlas/iterator/Iter;
      70: invokevirtual #70                 // Method org/apache/jena/atlas/iterator/Iter.distinctAdjacent:()Lorg/apache/jena/atlas/iterator/Iter;
      73: invokedynamic #71,  0             // InvokeDynamic #1:apply:()Ljava/util/function/Function;
      78: invokevirtual #72                 // Method org/apache/jena/atlas/iterator/Iter.map:(Ljava/util/function/Function;)Lorg/apache/jena/atlas/iterator/Iter;
      81: invokevirtual #73                 // Method org/apache/jena/atlas/iterator/Iter.distinct:()Lorg/apache/jena/atlas/iterator/Iter;
      84: areturn
      85: goto          175
      88: aload_3
      89: instanceof    #74                 // class org/apache/jena/sparql/path/P_Inverse
      92: ifeq          175
      95: aload_3
      96: checkcast     #74                 // class org/apache/jena/sparql/path/P_Inverse
      99: astore        4
     101: aload         4
     103: invokevirtual #75                 // Method org/apache/jena/sparql/path/P_Inverse.getSubPath:()Lorg/apache/jena/sparql/path/Path;
     106: instanceof    #22                 // class org/apache/jena/sparql/path/P_Link
     109: ifeq          175
     112: aload         4
     114: invokevirtual #75                 // Method org/apache/jena/sparql/path/P_Inverse.getSubPath:()Lorg/apache/jena/sparql/path/Path;
     117: checkcast     #22                 // class org/apache/jena/sparql/path/P_Link
     120: checkcast     #22                 // class org/apache/jena/sparql/path/P_Link
     123: astore        5
     125: aload         5
     127: invokevirtual #66                 // Method org/apache/jena/sparql/path/P_Link.getNode:()Lorg/apache/jena/graph/Node;
     130: aload_2
     131: invokevirtual #30                 // Method org/apache/jena/sparql/engine/ExecutionContext.getContext:()Lorg/apache/jena/sparql/util/Context;
     134: invokestatic  #67                 // Method isPropertyFunction:(Lorg/apache/jena/graph/Node;Lorg/apache/jena/sparql/util/Context;)Z
     137: ifne          175
     140: aload_0
     141: aconst_null
     142: aload         5
     144: invokevirtual #66                 // Method org/apache/jena/sparql/path/P_Link.getNode:()Lorg/apache/jena/graph/Node;
     147: aconst_null
     148: invokeinterface #68,  4           // InterfaceMethod org/apache/jena/graph/Graph.find:(Lorg/apache/jena/graph/Node;Lorg/apache/jena/graph/Node;Lorg/apache/jena/graph/Node;)Lorg/apache/jena/util/iterator/ExtendedIterator;
     153: astore        6
     155: aload         6
     157: invokestatic  #69                 // Method org/apache/jena/atlas/iterator/Iter.iter:(Ljava/util/Iterator;)Lorg/apache/jena/atlas/iterator/Iter;
     160: invokevirtual #70                 // Method org/apache/jena/atlas/iterator/Iter.distinctAdjacent:()Lorg/apache/jena/atlas/iterator/Iter;
     163: invokedynamic #76,  0             // InvokeDynamic #2:apply:()Ljava/util/function/Function;
     168: invokevirtual #72                 // Method org/apache/jena/atlas/iterator/Iter.map:(Ljava/util/function/Function;)Lorg/apache/jena/atlas/iterator/Iter;
     171: invokevirtual #73                 // Method org/apache/jena/atlas/iterator/Iter.distinct:()Lorg/apache/jena/atlas/iterator/Iter;
     174: areturn
     175: aload_0
     176: invokestatic  #77                 // Method org/apache/jena/sparql/util/graph/GraphUtils.allNodes:(Lorg/apache/jena/graph/Graph;)Ljava/util/Iterator;
     179: areturn

  private static boolean isPropertyFunction(org.apache.jena.graph.Node, org.apache.jena.sparql.util.Context);
    Code:
       0: aload_0
       1: invokevirtual #78                 // Method org/apache/jena/graph/Node.isURI:()Z
       4: ifne          9
       7: iconst_0
       8: ireturn
       9: aload_1
      10: invokestatic  #79                 // Method org/apache/jena/sparql/pfunction/PropertyFunctionRegistry.chooseRegistry:(Lorg/apache/jena/sparql/util/Context;)Lorg/apache/jena/sparql/pfunction/PropertyFunctionRegistry;
      13: aload_0
      14: invokevirtual #80                 // Method org/apache/jena/graph/Node.getURI:()Ljava/lang/String;
      17: invokevirtual #81                 // Method org/apache/jena/sparql/pfunction/PropertyFunctionRegistry.isRegistered:(Ljava/lang/String;)Z
      20: ireturn

  private static int existsPath(org.apache.jena.graph.Graph, org.apache.jena.graph.Node, org.apache.jena.sparql.path.Path, org.apache.jena.graph.Node, org.apache.jena.sparql.engine.ExecutionContext);
    Code:
       0: aload_1
       1: invokevirtual #82                 // Method org/apache/jena/graph/Node.isConcrete:()Z
       4: ifeq          14
       7: aload_3
       8: invokevirtual #82                 // Method org/apache/jena/graph/Node.isConcrete:()Z
      11: ifne          24
      14: new           #45                 // class org/apache/jena/sparql/ARQInternalErrorException
      17: dup
      18: ldc           #83                 // String Non concrete node for existsPath evaluation
      20: invokespecial #47                 // Method org/apache/jena/sparql/ARQInternalErrorException."<init>":(Ljava/lang/String;)V
      23: athrow
      24: aload_0
      25: aload_1
      26: aload_2
      27: aload         4
      29: invokevirtual #30                 // Method org/apache/jena/sparql/engine/ExecutionContext.getContext:()Lorg/apache/jena/sparql/util/Context;
      32: invokestatic  #41                 // Method org/apache/jena/sparql/path/eval/PathEval.eval:(Lorg/apache/jena/graph/Graph;Lorg/apache/jena/graph/Node;Lorg/apache/jena/sparql/path/Path;Lorg/apache/jena/sparql/util/Context;)Ljava/util/Iterator;
      35: astore        5
      37: aload_3
      38: invokedynamic #84,  0             // InvokeDynamic #3:test:(Lorg/apache/jena/graph/Node;)Ljava/util/function/Predicate;
      43: astore        6
      45: aload         5
      47: aload         6
      49: invokestatic  #85                 // Method org/apache/jena/atlas/iterator/Iter.filter:(Ljava/util/Iterator;Ljava/util/function/Predicate;)Ljava/util/Iterator;
      52: astore        5
      54: aload         5
      56: invokestatic  #86                 // Method org/apache/jena/atlas/iterator/Iter.count:(Ljava/util/Iterator;)J
      59: lstore        7
      61: lload         7
      63: l2i
      64: ireturn

  private static boolean lambda$existsPath$1(org.apache.jena.graph.Node, org.apache.jena.graph.Node);
    Code:
       0: aload_1
       1: aload_0
       2: invokestatic  #87                 // Method java/util/Objects.equals:(Ljava/lang/Object;Ljava/lang/Object;)Z
       5: ireturn

  private static org.apache.jena.sparql.pfunction.PropertyFunction lambda$install$0(org.apache.jena.sparql.path.Path, java.lang.String);
    Code:
       0: new           #88                 // class org/apache/jena/sparql/path/PathPropertyFunction
       3: dup
       4: aload_0
       5: invokespecial #89                 // Method org/apache/jena/sparql/path/PathPropertyFunction."<init>":(Lorg/apache/jena/sparql/path/Path;)V
       8: areturn
}
