Compiled from "ForwardingServletListener.java"
public abstract class org.jboss.weld.servlet.api.helpers.ForwardingServletListener implements org.jboss.weld.servlet.api.ServletListener {
  public org.jboss.weld.servlet.api.helpers.ForwardingServletListener();
    Code:
       0: aload_0
       1: invokespecial #1                  // Method java/lang/Object."<init>":()V
       4: return

  protected abstract org.jboss.weld.servlet.api.ServletListener delegate();

  public void contextDestroyed(javax.servlet.ServletContextEvent);
    Code:
       0: aload_0
       1: invokevirtual #2                  // Method delegate:()Lorg/jboss/weld/servlet/api/ServletListener;
       4: aload_1
       5: invokeinterface #3,  2            // InterfaceMethod org/jboss/weld/servlet/api/ServletListener.contextDestroyed:(Ljavax/servlet/ServletContextEvent;)V
      10: return

  public void contextInitialized(javax.servlet.ServletContextEvent);
    Code:
       0: aload_0
       1: invokevirtual #2                  // Method delegate:()Lorg/jboss/weld/servlet/api/ServletListener;
       4: aload_1
       5: invokeinterface #4,  2            // InterfaceMethod org/jboss/weld/servlet/api/ServletListener.contextInitialized:(Ljavax/servlet/ServletContextEvent;)V
      10: return

  public void requestDestroyed(javax.servlet.ServletRequestEvent);
    Code:
       0: aload_0
       1: invokevirtual #2                  // Method delegate:()Lorg/jboss/weld/servlet/api/ServletListener;
       4: aload_1
       5: invokeinterface #5,  2            // InterfaceMethod org/jboss/weld/servlet/api/ServletListener.requestDestroyed:(Ljavax/servlet/ServletRequestEvent;)V
      10: return

  public void requestInitialized(javax.servlet.ServletRequestEvent);
    Code:
       0: aload_0
       1: invokevirtual #2                  // Method delegate:()Lorg/jboss/weld/servlet/api/ServletListener;
       4: aload_1
       5: invokeinterface #6,  2            // InterfaceMethod org/jboss/weld/servlet/api/ServletListener.requestInitialized:(Ljavax/servlet/ServletRequestEvent;)V
      10: return

  public void sessionCreated(javax.servlet.http.HttpSessionEvent);
    Code:
       0: aload_0
       1: invokevirtual #2                  // Method delegate:()Lorg/jboss/weld/servlet/api/ServletListener;
       4: aload_1
       5: invokeinterface #7,  2            // InterfaceMethod org/jboss/weld/servlet/api/ServletListener.sessionCreated:(Ljavax/servlet/http/HttpSessionEvent;)V
      10: return

  public void sessionDestroyed(javax.servlet.http.HttpSessionEvent);
    Code:
       0: aload_0
       1: invokevirtual #2                  // Method delegate:()Lorg/jboss/weld/servlet/api/ServletListener;
       4: aload_1
       5: invokeinterface #8,  2            // InterfaceMethod org/jboss/weld/servlet/api/ServletListener.sessionDestroyed:(Ljavax/servlet/http/HttpSessionEvent;)V
      10: return
}
