Compiled from "AbstractListeningExecutorService.java"
public abstract class org.sonar.api.internal.google.common.util.concurrent.AbstractListeningExecutorService extends java.util.concurrent.AbstractExecutorService implements org.sonar.api.internal.google.common.util.concurrent.ListeningExecutorService {
  public org.sonar.api.internal.google.common.util.concurrent.AbstractListeningExecutorService();
    Code:
       0: aload_0
       1: invokespecial #12                 // Method java/util/concurrent/AbstractExecutorService."<init>":()V
       4: return

  protected final <T> org.sonar.api.internal.google.common.util.concurrent.ListenableFutureTask<T> newTaskFor(java.lang.Runnable, T);
    Code:
       0: aload_1
       1: aload_2
       2: invokestatic  #21                 // Method org/sonar/api/internal/google/common/util/concurrent/ListenableFutureTask.create:(Ljava/lang/Runnable;Ljava/lang/Object;)Lorg/sonar/api/internal/google/common/util/concurrent/ListenableFutureTask;
       5: areturn

  protected final <T> org.sonar.api.internal.google.common.util.concurrent.ListenableFutureTask<T> newTaskFor(java.util.concurrent.Callable<T>);
    Code:
       0: aload_1
       1: invokestatic  #29                 // Method org/sonar/api/internal/google/common/util/concurrent/ListenableFutureTask.create:(Ljava/util/concurrent/Callable;)Lorg/sonar/api/internal/google/common/util/concurrent/ListenableFutureTask;
       4: areturn

  public org.sonar.api.internal.google.common.util.concurrent.ListenableFuture<?> submit(java.lang.Runnable);
    Code:
       0: aload_0
       1: aload_1
       2: invokespecial #37                 // Method java/util/concurrent/AbstractExecutorService.submit:(Ljava/lang/Runnable;)Ljava/util/concurrent/Future;
       5: checkcast     #39                 // class org/sonar/api/internal/google/common/util/concurrent/ListenableFuture
       8: areturn

  public <T> org.sonar.api.internal.google.common.util.concurrent.ListenableFuture<T> submit(java.lang.Runnable, T);
    Code:
       0: aload_0
       1: aload_1
       2: aload_2
       3: invokespecial #45                 // Method java/util/concurrent/AbstractExecutorService.submit:(Ljava/lang/Runnable;Ljava/lang/Object;)Ljava/util/concurrent/Future;
       6: checkcast     #39                 // class org/sonar/api/internal/google/common/util/concurrent/ListenableFuture
       9: areturn

  public <T> org.sonar.api.internal.google.common.util.concurrent.ListenableFuture<T> submit(java.util.concurrent.Callable<T>);
    Code:
       0: aload_0
       1: aload_1
       2: invokespecial #50                 // Method java/util/concurrent/AbstractExecutorService.submit:(Ljava/util/concurrent/Callable;)Ljava/util/concurrent/Future;
       5: checkcast     #39                 // class org/sonar/api/internal/google/common/util/concurrent/ListenableFuture
       8: areturn

  public java.util.concurrent.Future submit(java.util.concurrent.Callable);
    Code:
       0: aload_0
       1: aload_1
       2: invokevirtual #52                 // Method submit:(Ljava/util/concurrent/Callable;)Lorg/sonar/api/internal/google/common/util/concurrent/ListenableFuture;
       5: areturn

  public java.util.concurrent.Future submit(java.lang.Runnable, java.lang.Object);
    Code:
       0: aload_0
       1: aload_1
       2: aload_2
       3: invokevirtual #55                 // Method submit:(Ljava/lang/Runnable;Ljava/lang/Object;)Lorg/sonar/api/internal/google/common/util/concurrent/ListenableFuture;
       6: areturn

  public java.util.concurrent.Future submit(java.lang.Runnable);
    Code:
       0: aload_0
       1: aload_1
       2: invokevirtual #58                 // Method submit:(Ljava/lang/Runnable;)Lorg/sonar/api/internal/google/common/util/concurrent/ListenableFuture;
       5: areturn

  protected java.util.concurrent.RunnableFuture newTaskFor(java.util.concurrent.Callable);
    Code:
       0: aload_0
       1: aload_1
       2: invokevirtual #61                 // Method newTaskFor:(Ljava/util/concurrent/Callable;)Lorg/sonar/api/internal/google/common/util/concurrent/ListenableFutureTask;
       5: areturn

  protected java.util.concurrent.RunnableFuture newTaskFor(java.lang.Runnable, java.lang.Object);
    Code:
       0: aload_0
       1: aload_1
       2: aload_2
       3: invokevirtual #64                 // Method newTaskFor:(Ljava/lang/Runnable;Ljava/lang/Object;)Lorg/sonar/api/internal/google/common/util/concurrent/ListenableFutureTask;
       6: areturn
}
