Compiled from "AbstractExecutionThreadService.java"
class org.sonar.api.internal.google.common.util.concurrent.AbstractExecutionThreadService$1 extends org.sonar.api.internal.google.common.util.concurrent.AbstractService {
  final org.sonar.api.internal.google.common.util.concurrent.AbstractExecutionThreadService this$0;

  org.sonar.api.internal.google.common.util.concurrent.AbstractExecutionThreadService$1(org.sonar.api.internal.google.common.util.concurrent.AbstractExecutionThreadService);
    Code:
       0: aload_0
       1: aload_1
       2: putfield      #17                 // Field this$0:Lorg/sonar/api/internal/google/common/util/concurrent/AbstractExecutionThreadService;
       5: aload_0
       6: invokespecial #20                 // Method org/sonar/api/internal/google/common/util/concurrent/AbstractService."<init>":()V
       9: return

  protected final void doStart();
    Code:
       0: aload_0
       1: getfield      #17                 // Field this$0:Lorg/sonar/api/internal/google/common/util/concurrent/AbstractExecutionThreadService;
       4: invokevirtual #27                 // Method org/sonar/api/internal/google/common/util/concurrent/AbstractExecutionThreadService.executor:()Ljava/util/concurrent/Executor;
       7: new           #11                 // class org/sonar/api/internal/google/common/util/concurrent/AbstractExecutionThreadService$1$1
      10: dup
      11: aload_0
      12: invokespecial #30                 // Method org/sonar/api/internal/google/common/util/concurrent/AbstractExecutionThreadService$1$1."<init>":(Lorg/sonar/api/internal/google/common/util/concurrent/AbstractExecutionThreadService$1;)V
      15: invokestatic  #36                 // Method org/sonar/api/internal/google/common/util/concurrent/MoreExecutors.renamingDecorator:(Ljava/util/concurrent/Executor;Lorg/sonar/api/internal/google/common/base/Supplier;)Ljava/util/concurrent/Executor;
      18: astore_1
      19: aload_1
      20: new           #9                  // class org/sonar/api/internal/google/common/util/concurrent/AbstractExecutionThreadService$1$2
      23: dup
      24: aload_0
      25: invokespecial #37                 // Method org/sonar/api/internal/google/common/util/concurrent/AbstractExecutionThreadService$1$2."<init>":(Lorg/sonar/api/internal/google/common/util/concurrent/AbstractExecutionThreadService$1;)V
      28: invokeinterface #43,  2           // InterfaceMethod java/util/concurrent/Executor.execute:(Ljava/lang/Runnable;)V
      33: return

  protected void doStop();
    Code:
       0: aload_0
       1: getfield      #17                 // Field this$0:Lorg/sonar/api/internal/google/common/util/concurrent/AbstractExecutionThreadService;
       4: invokevirtual #48                 // Method org/sonar/api/internal/google/common/util/concurrent/AbstractExecutionThreadService.triggerShutdown:()V
       7: return
}
