Compiled from "Futures.java"
final class org.sonar.api.internal.google.common.util.concurrent.Futures$5 implements java.lang.Runnable {
  final java.util.concurrent.ConcurrentLinkedQueue val$delegates;

  final org.sonar.api.internal.google.common.util.concurrent.ListenableFuture val$future;

  org.sonar.api.internal.google.common.util.concurrent.Futures$5(java.util.concurrent.ConcurrentLinkedQueue, org.sonar.api.internal.google.common.util.concurrent.ListenableFuture);
    Code:
       0: aload_0
       1: aload_1
       2: putfield      #20                 // Field val$delegates:Ljava/util/concurrent/ConcurrentLinkedQueue;
       5: aload_0
       6: aload_2
       7: putfield      #22                 // Field val$future:Lorg/sonar/api/internal/google/common/util/concurrent/ListenableFuture;
      10: aload_0
      11: invokespecial #25                 // Method java/lang/Object."<init>":()V
      14: return

  public void run();
    Code:
       0: aload_0
       1: getfield      #20                 // Field val$delegates:Ljava/util/concurrent/ConcurrentLinkedQueue;
       4: invokevirtual #34                 // Method java/util/concurrent/ConcurrentLinkedQueue.remove:()Ljava/lang/Object;
       7: checkcast     #36                 // class org/sonar/api/internal/google/common/util/concurrent/AsyncSettableFuture
      10: aload_0
      11: getfield      #22                 // Field val$future:Lorg/sonar/api/internal/google/common/util/concurrent/ListenableFuture;
      14: invokevirtual #40                 // Method org/sonar/api/internal/google/common/util/concurrent/AsyncSettableFuture.setFuture:(Lorg/sonar/api/internal/google/common/util/concurrent/ListenableFuture;)Z
      17: pop
      18: return
}
