Compiled from "ServiceManager.java"
final class org.sonar.api.internal.google.common.util.concurrent.ServiceManager$2 extends org.sonar.api.internal.google.common.util.concurrent.ListenerCallQueue$Callback<org.sonar.api.internal.google.common.util.concurrent.ServiceManager$Listener> {
  org.sonar.api.internal.google.common.util.concurrent.ServiceManager$2(java.lang.String);
    Code:
       0: aload_0
       1: aload_1
       2: invokespecial #18                 // Method org/sonar/api/internal/google/common/util/concurrent/ListenerCallQueue$Callback."<init>":(Ljava/lang/String;)V
       5: return

  void call(org.sonar.api.internal.google.common.util.concurrent.ServiceManager$Listener);
    Code:
       0: aload_1
       1: invokevirtual #28                 // Method org/sonar/api/internal/google/common/util/concurrent/ServiceManager$Listener.stopped:()V
       4: return

  void call(java.lang.Object);
    Code:
       0: aload_0
       1: aload_1
       2: checkcast     #10                 // class org/sonar/api/internal/google/common/util/concurrent/ServiceManager$Listener
       5: invokevirtual #33                 // Method call:(Lorg/sonar/api/internal/google/common/util/concurrent/ServiceManager$Listener;)V
       8: return
}
