Compiled from "PersistenceContextInjectionSource.java"
public class org.jboss.as.jpa.injectors.PersistenceContextInjectionSource extends org.jboss.as.ee.component.InjectionSource {
  private final javax.persistence.PersistenceContextType type;

  private final org.jboss.as.jpa.injectors.PersistenceContextInjectionSource$PersistenceContextJndiInjectable injectable;

  private final org.jboss.msc.service.ServiceName puServiceName;

  public org.jboss.as.jpa.injectors.PersistenceContextInjectionSource(javax.persistence.PersistenceContextType, javax.persistence.SynchronizationType, java.util.Map, org.jboss.msc.service.ServiceName, org.jboss.msc.service.ServiceRegistry, java.lang.String, java.lang.String, org.jipijapa.plugin.spi.PersistenceUnitMetadata, org.jboss.as.jpa.config.JPADeploymentSettings);
    Code:
       0: aload_0
       1: invokespecial #1                  // Method org/jboss/as/ee/component/InjectionSource."<init>":()V
       4: aload_0
       5: aload_1
       6: putfield      #2                  // Field type:Ljavax/persistence/PersistenceContextType;
       9: aload_0
      10: new           #3                  // class org/jboss/as/jpa/injectors/PersistenceContextInjectionSource$PersistenceContextJndiInjectable
      13: dup
      14: aload         4
      16: aload         5
      18: aload_0
      19: getfield      #2                  // Field type:Ljavax/persistence/PersistenceContextType;
      22: aload_2
      23: aload_3
      24: aload         6
      26: aload         7
      28: aload         8
      30: aload         9
      32: invokespecial #4                  // Method org/jboss/as/jpa/injectors/PersistenceContextInjectionSource$PersistenceContextJndiInjectable."<init>":(Lorg/jboss/msc/service/ServiceName;Lorg/jboss/msc/service/ServiceRegistry;Ljavax/persistence/PersistenceContextType;Ljavax/persistence/SynchronizationType;Ljava/util/Map;Ljava/lang/String;Ljava/lang/String;Lorg/jipijapa/plugin/spi/PersistenceUnitMetadata;Lorg/jboss/as/jpa/config/JPADeploymentSettings;)V
      35: putfield      #5                  // Field injectable:Lorg/jboss/as/jpa/injectors/PersistenceContextInjectionSource$PersistenceContextJndiInjectable;
      38: aload_0
      39: aload         4
      41: putfield      #6                  // Field puServiceName:Lorg/jboss/msc/service/ServiceName;
      44: return

  public void getResourceValue(org.jboss.as.ee.component.InjectionSource$ResolutionContext, org.jboss.msc.service.ServiceBuilder<?>, org.jboss.as.server.deployment.DeploymentPhaseContext, org.jboss.msc.inject.Injector<org.jboss.as.naming.ManagedReferenceFactory>) throws org.jboss.as.server.deployment.DeploymentUnitProcessingException;
    Code:
       0: aload_2
       1: iconst_1
       2: anewarray     #7                  // class org/jboss/msc/service/ServiceName
       5: dup
       6: iconst_0
       7: aload_0
       8: getfield      #6                  // Field puServiceName:Lorg/jboss/msc/service/ServiceName;
      11: aastore
      12: invokeinterface #8,  2            // InterfaceMethod org/jboss/msc/service/ServiceBuilder.addDependencies:([Lorg/jboss/msc/service/ServiceName;)Lorg/jboss/msc/service/ServiceBuilder;
      17: pop
      18: aload         4
      20: aload_0
      21: getfield      #5                  // Field injectable:Lorg/jboss/as/jpa/injectors/PersistenceContextInjectionSource$PersistenceContextJndiInjectable;
      24: invokeinterface #9,  2            // InterfaceMethod org/jboss/msc/inject/Injector.inject:(Ljava/lang/Object;)V
      29: return

  public boolean equals(java.lang.Object);
    Code:
       0: aload_1
       1: instanceof    #10                 // class org/jboss/as/jpa/injectors/PersistenceContextInjectionSource
       4: ifeq          24
       7: aload_1
       8: checkcast     #10                 // class org/jboss/as/jpa/injectors/PersistenceContextInjectionSource
      11: astore_2
      12: aload_2
      13: getfield      #6                  // Field puServiceName:Lorg/jboss/msc/service/ServiceName;
      16: aload_0
      17: getfield      #6                  // Field puServiceName:Lorg/jboss/msc/service/ServiceName;
      20: invokevirtual #11                 // Method org/jboss/msc/service/ServiceName.equals:(Lorg/jboss/msc/service/ServiceName;)Z
      23: ireturn
      24: iconst_0
      25: ireturn

  public int hashCode();
    Code:
       0: aload_0
       1: getfield      #6                  // Field puServiceName:Lorg/jboss/msc/service/ServiceName;
       4: invokevirtual #12                 // Method org/jboss/msc/service/ServiceName.hashCode:()I
       7: ireturn
}
