Compiled from "ECDH.java"
public final class com.nimbusds.jose.crypto.ECDH$AlgorithmMode extends java.lang.Enum<com.nimbusds.jose.crypto.ECDH$AlgorithmMode> {
  public static final com.nimbusds.jose.crypto.ECDH$AlgorithmMode DIRECT;

  public static final com.nimbusds.jose.crypto.ECDH$AlgorithmMode KW;

  private static final com.nimbusds.jose.crypto.ECDH$AlgorithmMode[] ENUM$VALUES;

  static {};
    Code:
       0: new           #1                  // class com/nimbusds/jose/crypto/ECDH$AlgorithmMode
       3: dup
       4: ldc           #13                 // String DIRECT
       6: iconst_0
       7: invokespecial #14                 // Method "<init>":(Ljava/lang/String;I)V
      10: putstatic     #18                 // Field DIRECT:Lcom/nimbusds/jose/crypto/ECDH$AlgorithmMode;
      13: new           #1                  // class com/nimbusds/jose/crypto/ECDH$AlgorithmMode
      16: dup
      17: ldc           #20                 // String KW
      19: iconst_1
      20: invokespecial #14                 // Method "<init>":(Ljava/lang/String;I)V
      23: putstatic     #21                 // Field KW:Lcom/nimbusds/jose/crypto/ECDH$AlgorithmMode;
      26: iconst_2
      27: anewarray     #1                  // class com/nimbusds/jose/crypto/ECDH$AlgorithmMode
      30: dup
      31: iconst_0
      32: getstatic     #18                 // Field DIRECT:Lcom/nimbusds/jose/crypto/ECDH$AlgorithmMode;
      35: aastore
      36: dup
      37: iconst_1
      38: getstatic     #21                 // Field KW:Lcom/nimbusds/jose/crypto/ECDH$AlgorithmMode;
      41: aastore
      42: putstatic     #23                 // Field ENUM$VALUES:[Lcom/nimbusds/jose/crypto/ECDH$AlgorithmMode;
      45: return

  private com.nimbusds.jose.crypto.ECDH$AlgorithmMode(java.lang.String, int);
    Code:
       0: aload_0
       1: aload_1
       2: iload_2
       3: invokespecial #27                 // Method java/lang/Enum."<init>":(Ljava/lang/String;I)V
       6: return

  public static com.nimbusds.jose.crypto.ECDH$AlgorithmMode[] values();
    Code:
       0: getstatic     #23                 // Field ENUM$VALUES:[Lcom/nimbusds/jose/crypto/ECDH$AlgorithmMode;
       3: dup
       4: astore_0
       5: iconst_0
       6: aload_0
       7: arraylength
       8: dup
       9: istore_1
      10: anewarray     #1                  // class com/nimbusds/jose/crypto/ECDH$AlgorithmMode
      13: dup
      14: astore_2
      15: iconst_0
      16: iload_1
      17: invokestatic  #31                 // Method java/lang/System.arraycopy:(Ljava/lang/Object;ILjava/lang/Object;II)V
      20: aload_2
      21: areturn

  public static com.nimbusds.jose.crypto.ECDH$AlgorithmMode valueOf(java.lang.String);
    Code:
       0: ldc           #1                  // class com/nimbusds/jose/crypto/ECDH$AlgorithmMode
       2: aload_0
       3: invokestatic  #39                 // Method java/lang/Enum.valueOf:(Ljava/lang/Class;Ljava/lang/String;)Ljava/lang/Enum;
       6: checkcast     #1                  // class com/nimbusds/jose/crypto/ECDH$AlgorithmMode
       9: areturn
}
