Compiled from "ForwardingLogger.java"
public final class com.mchange.v2.log.jdk14logging.ForwardingLogger extends java.util.logging.Logger {
  com.mchange.v2.log.MLogger forwardTo;

  public com.mchange.v2.log.jdk14logging.ForwardingLogger(com.mchange.v2.log.MLogger, java.lang.String);
    Code:
       0: aload_0
       1: aload_1
       2: invokeinterface #1,  1            // InterfaceMethod com/mchange/v2/log/MLogger.getName:()Ljava/lang/String;
       7: aload_2
       8: invokespecial #2                  // Method java/util/logging/Logger."<init>":(Ljava/lang/String;Ljava/lang/String;)V
      11: aload_0
      12: aload_1
      13: putfield      #3                  // Field forwardTo:Lcom/mchange/v2/log/MLogger;
      16: return

  public void log(java.util.logging.LogRecord);
    Code:
       0: aload_1
       1: invokevirtual #4                  // Method java/util/logging/LogRecord.getLevel:()Ljava/util/logging/Level;
       4: astore_2
       5: aload_2
       6: invokestatic  #5                  // Method com/mchange/v2/log/jdk14logging/Jdk14LoggingUtils.mlevelFromLevel:(Ljava/util/logging/Level;)Lcom/mchange/v2/log/MLevel;
       9: astore_3
      10: aload_1
      11: invokevirtual #6                  // Method java/util/logging/LogRecord.getResourceBundleName:()Ljava/lang/String;
      14: astore        4
      16: aload_1
      17: invokevirtual #7                  // Method java/util/logging/LogRecord.getMessage:()Ljava/lang/String;
      20: astore        5
      22: aload_1
      23: invokevirtual #8                  // Method java/util/logging/LogRecord.getParameters:()[Ljava/lang/Object;
      26: astore        6
      28: aload         4
      30: aload         5
      32: aload         6
      34: invokestatic  #9                  // Method com/mchange/v2/log/LogUtils.formatMessage:(Ljava/lang/String;Ljava/lang/String;[Ljava/lang/Object;)Ljava/lang/String;
      37: astore        7
      39: aload_1
      40: invokevirtual #10                 // Method java/util/logging/LogRecord.getThrown:()Ljava/lang/Throwable;
      43: astore        8
      45: aload_1
      46: invokevirtual #11                 // Method java/util/logging/LogRecord.getSourceClassName:()Ljava/lang/String;
      49: astore        9
      51: aload_1
      52: invokevirtual #12                 // Method java/util/logging/LogRecord.getSourceMethodName:()Ljava/lang/String;
      55: astore        10
      57: aload         9
      59: ifnull        66
      62: iconst_1
      63: goto          67
      66: iconst_0
      67: aload         10
      69: ifnull        76
      72: iconst_1
      73: goto          77
      76: iconst_0
      77: iand
      78: istore        11
      80: iload         11
      82: ifne          102
      85: aload_0
      86: getfield      #3                  // Field forwardTo:Lcom/mchange/v2/log/MLogger;
      89: aload_3
      90: aload         7
      92: aload         8
      94: invokeinterface #13,  4           // InterfaceMethod com/mchange/v2/log/MLogger.log:(Lcom/mchange/v2/log/MLevel;Ljava/lang/String;Ljava/lang/Throwable;)V
      99: goto          120
     102: aload_0
     103: getfield      #3                  // Field forwardTo:Lcom/mchange/v2/log/MLogger;
     106: aload_3
     107: aload         9
     109: aload         10
     111: aload         7
     113: aload         8
     115: invokeinterface #14,  6           // InterfaceMethod com/mchange/v2/log/MLogger.logp:(Lcom/mchange/v2/log/MLevel;Ljava/lang/String;Ljava/lang/String;Ljava/lang/String;Ljava/lang/Throwable;)V
     120: return
}
