Compiled from "MqttClient.kt"
final class io.vertx.kotlin.mqtt.MqttClientKt$connectAwait$4 extends kotlin.jvm.internal.Lambda implements kotlin.jvm.functions.Function1<io.vertx.core.Handler<io.vertx.core.AsyncResult<io.vertx.mqtt.messages.MqttConnAckMessage>>, kotlin.Unit> {
  final io.vertx.mqtt.MqttClient $this_connectAwait;

  final int $port;

  final java.lang.String $host;

  final java.lang.String $serverName;

  public java.lang.Object invoke(java.lang.Object);
    Code:
       0: aload_0
       1: aload_1
       2: checkcast     #11                 // class io/vertx/core/Handler
       5: invokevirtual #14                 // Method invoke:(Lio/vertx/core/Handler;)V
       8: getstatic     #20                 // Field kotlin/Unit.INSTANCE:Lkotlin/Unit;
      11: areturn

  public final void invoke(io.vertx.core.Handler<io.vertx.core.AsyncResult<io.vertx.mqtt.messages.MqttConnAckMessage>>);
    Code:
       0: aload_1
       1: ldc           #24                 // String it
       3: invokestatic  #30                 // Method kotlin/jvm/internal/Intrinsics.checkParameterIsNotNull:(Ljava/lang/Object;Ljava/lang/String;)V
       6: aload_0
       7: getfield      #34                 // Field $this_connectAwait:Lio/vertx/mqtt/MqttClient;
      10: aload_0
      11: getfield      #38                 // Field $port:I
      14: aload_0
      15: getfield      #42                 // Field $host:Ljava/lang/String;
      18: aload_0
      19: getfield      #45                 // Field $serverName:Ljava/lang/String;
      22: aload_1
      23: invokeinterface #51,  5           // InterfaceMethod io/vertx/mqtt/MqttClient.connect:(ILjava/lang/String;Ljava/lang/String;Lio/vertx/core/Handler;)Lio/vertx/mqtt/MqttClient;
      28: pop
      29: return

  io.vertx.kotlin.mqtt.MqttClientKt$connectAwait$4(io.vertx.mqtt.MqttClient, int, java.lang.String, java.lang.String);
    Code:
       0: aload_0
       1: aload_1
       2: putfield      #34                 // Field $this_connectAwait:Lio/vertx/mqtt/MqttClient;
       5: aload_0
       6: iload_2
       7: putfield      #38                 // Field $port:I
      10: aload_0
      11: aload_3
      12: putfield      #42                 // Field $host:Ljava/lang/String;
      15: aload_0
      16: aload         4
      18: putfield      #45                 // Field $serverName:Ljava/lang/String;
      21: aload_0
      22: iconst_1
      23: invokespecial #59                 // Method kotlin/jvm/internal/Lambda."<init>":(I)V
      26: return
}
