Compiled from "SolrHttpRequestRetryHandler.java"
public class org.apache.solr.client.solrj.impl.SolrHttpRequestRetryHandler implements org.apache.http.client.HttpRequestRetryHandler {
  private static final java.lang.String GET;

  private static final org.slf4j.Logger log;

  public static final org.apache.solr.client.solrj.impl.SolrHttpRequestRetryHandler INSTANCE;

  private final int retryCount;

  private final java.util.Set<java.lang.Class<? extends java.io.IOException>> nonRetriableClasses;

  protected org.apache.solr.client.solrj.impl.SolrHttpRequestRetryHandler(int, java.util.Collection<java.lang.Class<? extends java.io.IOException>>);
    Code:
       0: aload_0
       1: invokespecial #1                  // Method java/lang/Object."<init>":()V
       4: aload_0
       5: iload_1
       6: putfield      #2                  // Field retryCount:I
       9: aload_0
      10: new           #3                  // class java/util/HashSet
      13: dup
      14: invokespecial #4                  // Method java/util/HashSet."<init>":()V
      17: putfield      #5                  // Field nonRetriableClasses:Ljava/util/Set;
      20: aload_2
      21: invokeinterface #6,  1            // InterfaceMethod java/util/Collection.iterator:()Ljava/util/Iterator;
      26: astore_3
      27: aload_3
      28: invokeinterface #7,  1            // InterfaceMethod java/util/Iterator.hasNext:()Z
      33: ifeq          62
      36: aload_3
      37: invokeinterface #8,  1            // InterfaceMethod java/util/Iterator.next:()Ljava/lang/Object;
      42: checkcast     #9                  // class java/lang/Class
      45: astore        4
      47: aload_0
      48: getfield      #5                  // Field nonRetriableClasses:Ljava/util/Set;
      51: aload         4
      53: invokeinterface #10,  2           // InterfaceMethod java/util/Set.add:(Ljava/lang/Object;)Z
      58: pop
      59: goto          27
      62: return

  public org.apache.solr.client.solrj.impl.SolrHttpRequestRetryHandler(int);
    Code:
       0: aload_0
       1: iload_1
       2: iconst_4
       3: anewarray     #9                  // class java/lang/Class
       6: dup
       7: iconst_0
       8: ldc           #11                 // class java/io/InterruptedIOException
      10: aastore
      11: dup
      12: iconst_1
      13: ldc           #12                 // class java/net/UnknownHostException
      15: aastore
      16: dup
      17: iconst_2
      18: ldc           #13                 // class java/net/ConnectException
      20: aastore
      21: dup
      22: iconst_3
      23: ldc           #14                 // class javax/net/ssl/SSLException
      25: aastore
      26: invokestatic  #15                 // Method java/util/Arrays.asList:([Ljava/lang/Object;)Ljava/util/List;
      29: invokespecial #16                 // Method "<init>":(ILjava/util/Collection;)V
      32: return

  public org.apache.solr.client.solrj.impl.SolrHttpRequestRetryHandler();
    Code:
       0: aload_0
       1: iconst_3
       2: invokespecial #17                 // Method "<init>":(I)V
       5: return

  public boolean retryRequest(java.io.IOException, int, org.apache.http.protocol.HttpContext);
    Code:
       0: getstatic     #18                 // Field log:Lorg/slf4j/Logger;
       3: ldc           #19                 // String Retry http request {} out of {}
       5: iload_2
       6: invokestatic  #20                 // Method java/lang/Integer.valueOf:(I)Ljava/lang/Integer;
       9: aload_0
      10: getfield      #2                  // Field retryCount:I
      13: invokestatic  #20                 // Method java/lang/Integer.valueOf:(I)Ljava/lang/Integer;
      16: invokeinterface #21,  4           // InterfaceMethod org/slf4j/Logger.debug:(Ljava/lang/String;Ljava/lang/Object;Ljava/lang/Object;)V
      21: iload_2
      22: aload_0
      23: getfield      #2                  // Field retryCount:I
      26: if_icmple     41
      29: getstatic     #18                 // Field log:Lorg/slf4j/Logger;
      32: ldc           #22                 // String Do not retry, over max retry count
      34: invokeinterface #23,  2           // InterfaceMethod org/slf4j/Logger.debug:(Ljava/lang/String;)V
      39: iconst_0
      40: ireturn
      41: aload_0
      42: getfield      #5                  // Field nonRetriableClasses:Ljava/util/Set;
      45: aload_1
      46: invokevirtual #24                 // Method java/lang/Object.getClass:()Ljava/lang/Class;
      49: invokeinterface #25,  2           // InterfaceMethod java/util/Set.contains:(Ljava/lang/Object;)Z
      54: ifeq          76
      57: getstatic     #18                 // Field log:Lorg/slf4j/Logger;
      60: ldc           #26                 // String Do not retry, non retriable class {}
      62: aload_1
      63: invokevirtual #24                 // Method java/lang/Object.getClass:()Ljava/lang/Class;
      66: invokevirtual #27                 // Method java/lang/Class.getName:()Ljava/lang/String;
      69: invokeinterface #28,  3           // InterfaceMethod org/slf4j/Logger.debug:(Ljava/lang/String;Ljava/lang/Object;)V
      74: iconst_0
      75: ireturn
      76: aload_0
      77: getfield      #5                  // Field nonRetriableClasses:Ljava/util/Set;
      80: invokeinterface #29,  1           // InterfaceMethod java/util/Set.iterator:()Ljava/util/Iterator;
      85: astore        4
      87: aload         4
      89: invokeinterface #7,  1            // InterfaceMethod java/util/Iterator.hasNext:()Z
      94: ifeq          140
      97: aload         4
      99: invokeinterface #8,  1            // InterfaceMethod java/util/Iterator.next:()Ljava/lang/Object;
     104: checkcast     #9                  // class java/lang/Class
     107: astore        5
     109: aload         5
     111: aload_1
     112: invokevirtual #30                 // Method java/lang/Class.isInstance:(Ljava/lang/Object;)Z
     115: ifeq          137
     118: getstatic     #18                 // Field log:Lorg/slf4j/Logger;
     121: ldc           #26                 // String Do not retry, non retriable class {}
     123: aload_1
     124: invokevirtual #24                 // Method java/lang/Object.getClass:()Ljava/lang/Class;
     127: invokevirtual #27                 // Method java/lang/Class.getName:()Ljava/lang/String;
     130: invokeinterface #28,  3           // InterfaceMethod org/slf4j/Logger.debug:(Ljava/lang/String;Ljava/lang/Object;)V
     135: iconst_0
     136: ireturn
     137: goto          87
     140: aload_3
     141: invokestatic  #31                 // Method org/apache/http/client/protocol/HttpClientContext.adapt:(Lorg/apache/http/protocol/HttpContext;)Lorg/apache/http/client/protocol/HttpClientContext;
     144: astore        4
     146: aload         4
     148: invokevirtual #32                 // Method org/apache/http/client/protocol/HttpClientContext.getRequest:()Lorg/apache/http/HttpRequest;
     151: astore        5
     153: aload_0
     154: aload         5
     156: invokevirtual #33                 // Method requestIsAborted:(Lorg/apache/http/HttpRequest;)Z
     159: ifeq          174
     162: getstatic     #18                 // Field log:Lorg/slf4j/Logger;
     165: ldc           #34                 // String Do not retry, request was aborted
     167: invokeinterface #23,  2           // InterfaceMethod org/slf4j/Logger.debug:(Ljava/lang/String;)V
     172: iconst_0
     173: ireturn
     174: aload_0
     175: aload         4
     177: invokevirtual #35                 // Method handleAsIdempotent:(Lorg/apache/http/client/protocol/HttpClientContext;)Z
     180: ifeq          195
     183: getstatic     #18                 // Field log:Lorg/slf4j/Logger;
     186: ldc           #36                 // String Retry, request should be idempotent
     188: invokeinterface #23,  2           // InterfaceMethod org/slf4j/Logger.debug:(Ljava/lang/String;)V
     193: iconst_1
     194: ireturn
     195: getstatic     #18                 // Field log:Lorg/slf4j/Logger;
     198: ldc           #37                 // String Do not retry, no allow rules matched
     200: invokeinterface #23,  2           // InterfaceMethod org/slf4j/Logger.debug:(Ljava/lang/String;)V
     205: iconst_0
     206: ireturn

  public int getRetryCount();
    Code:
       0: aload_0
       1: getfield      #2                  // Field retryCount:I
       4: ireturn

  protected boolean handleAsIdempotent(org.apache.http.client.protocol.HttpClientContext);
    Code:
       0: aload_1
       1: invokevirtual #32                 // Method org/apache/http/client/protocol/HttpClientContext.getRequest:()Lorg/apache/http/HttpRequest;
       4: invokeinterface #38,  1           // InterfaceMethod org/apache/http/HttpRequest.getRequestLine:()Lorg/apache/http/RequestLine;
       9: invokeinterface #39,  1           // InterfaceMethod org/apache/http/RequestLine.getMethod:()Ljava/lang/String;
      14: astore_2
      15: aload_1
      16: invokevirtual #32                 // Method org/apache/http/client/protocol/HttpClientContext.getRequest:()Lorg/apache/http/HttpRequest;
      19: invokeinterface #38,  1           // InterfaceMethod org/apache/http/HttpRequest.getRequestLine:()Lorg/apache/http/RequestLine;
      24: invokeinterface #40,  1           // InterfaceMethod org/apache/http/RequestLine.getUri:()Ljava/lang/String;
      29: ldc           #41                 // String /admin/
      31: invokevirtual #42                 // Method java/lang/String.startsWith:(Ljava/lang/String;)Z
      34: ifeq          49
      37: getstatic     #18                 // Field log:Lorg/slf4j/Logger;
      40: ldc           #43                 // String Do not retry, this is an admin request
      42: invokeinterface #23,  2           // InterfaceMethod org/slf4j/Logger.debug:(Ljava/lang/String;)V
      47: iconst_0
      48: ireturn
      49: aload_2
      50: ldc           #45                 // String GET
      52: invokevirtual #46                 // Method java/lang/String.equals:(Ljava/lang/Object;)Z
      55: ireturn

  protected boolean requestIsAborted(org.apache.http.HttpRequest);
    Code:
       0: aload_1
       1: astore_2
       2: aload_1
       3: instanceof    #47                 // class org/apache/http/impl/client/RequestWrapper
       6: ifeq          17
       9: aload_1
      10: checkcast     #47                 // class org/apache/http/impl/client/RequestWrapper
      13: invokevirtual #48                 // Method org/apache/http/impl/client/RequestWrapper.getOriginal:()Lorg/apache/http/HttpRequest;
      16: astore_2
      17: aload_2
      18: instanceof    #49                 // class org/apache/http/client/methods/HttpUriRequest
      21: ifeq          40
      24: aload_2
      25: checkcast     #49                 // class org/apache/http/client/methods/HttpUriRequest
      28: invokeinterface #50,  1           // InterfaceMethod org/apache/http/client/methods/HttpUriRequest.isAborted:()Z
      33: ifeq          40
      36: iconst_1
      37: goto          41
      40: iconst_0
      41: ireturn

  static {};
    Code:
       0: invokestatic  #51                 // Method java/lang/invoke/MethodHandles.lookup:()Ljava/lang/invoke/MethodHandles$Lookup;
       3: invokevirtual #52                 // Method java/lang/invoke/MethodHandles$Lookup.lookupClass:()Ljava/lang/Class;
       6: invokestatic  #53                 // Method org/slf4j/LoggerFactory.getLogger:(Ljava/lang/Class;)Lorg/slf4j/Logger;
       9: putstatic     #18                 // Field log:Lorg/slf4j/Logger;
      12: new           #44                 // class org/apache/solr/client/solrj/impl/SolrHttpRequestRetryHandler
      15: dup
      16: invokespecial #54                 // Method "<init>":()V
      19: putstatic     #55                 // Field INSTANCE:Lorg/apache/solr/client/solrj/impl/SolrHttpRequestRetryHandler;
      22: return
}
