Compiled from "XMLResponseParser.java"
class org.apache.solr.client.solrj.impl.XMLResponseParser$1 {
  static final int[] $SwitchMap$org$apache$solr$client$solrj$impl$XMLResponseParser$KnownType;

  static {};
    Code:
       0: invokestatic  #1                  // Method org/apache/solr/client/solrj/impl/XMLResponseParser$KnownType.values:()[Lorg/apache/solr/client/solrj/impl/XMLResponseParser$KnownType;
       3: arraylength
       4: newarray       int
       6: putstatic     #2                  // Field $SwitchMap$org$apache$solr$client$solrj$impl$XMLResponseParser$KnownType:[I
       9: getstatic     #2                  // Field $SwitchMap$org$apache$solr$client$solrj$impl$XMLResponseParser$KnownType:[I
      12: getstatic     #3                  // Field org/apache/solr/client/solrj/impl/XMLResponseParser$KnownType.LST:Lorg/apache/solr/client/solrj/impl/XMLResponseParser$KnownType;
      15: invokevirtual #4                  // Method org/apache/solr/client/solrj/impl/XMLResponseParser$KnownType.ordinal:()I
      18: iconst_1
      19: iastore
      20: goto          24
      23: astore_0
      24: getstatic     #2                  // Field $SwitchMap$org$apache$solr$client$solrj$impl$XMLResponseParser$KnownType:[I
      27: getstatic     #6                  // Field org/apache/solr/client/solrj/impl/XMLResponseParser$KnownType.ARR:Lorg/apache/solr/client/solrj/impl/XMLResponseParser$KnownType;
      30: invokevirtual #4                  // Method org/apache/solr/client/solrj/impl/XMLResponseParser$KnownType.ordinal:()I
      33: iconst_2
      34: iastore
      35: goto          39
      38: astore_0
      39: getstatic     #2                  // Field $SwitchMap$org$apache$solr$client$solrj$impl$XMLResponseParser$KnownType:[I
      42: getstatic     #7                  // Field org/apache/solr/client/solrj/impl/XMLResponseParser$KnownType.RESULT:Lorg/apache/solr/client/solrj/impl/XMLResponseParser$KnownType;
      45: invokevirtual #4                  // Method org/apache/solr/client/solrj/impl/XMLResponseParser$KnownType.ordinal:()I
      48: iconst_3
      49: iastore
      50: goto          54
      53: astore_0
      54: getstatic     #2                  // Field $SwitchMap$org$apache$solr$client$solrj$impl$XMLResponseParser$KnownType:[I
      57: getstatic     #8                  // Field org/apache/solr/client/solrj/impl/XMLResponseParser$KnownType.DOC:Lorg/apache/solr/client/solrj/impl/XMLResponseParser$KnownType;
      60: invokevirtual #4                  // Method org/apache/solr/client/solrj/impl/XMLResponseParser$KnownType.ordinal:()I
      63: iconst_4
      64: iastore
      65: goto          69
      68: astore_0
      69: return
    Exception table:
       from    to  target type
           9    20    23   Class java/lang/NoSuchFieldError
          24    35    38   Class java/lang/NoSuchFieldError
          39    50    53   Class java/lang/NoSuchFieldError
          54    65    68   Class java/lang/NoSuchFieldError
}
