Compiled from "AuthenticationFilter.java"
public class org.apache.hadoop.security.authentication.server.AuthenticationFilter implements javax.servlet.Filter {
  private static org.slf4j.Logger LOG;

  public static final java.lang.String CONFIG_PREFIX;

  public static final java.lang.String AUTH_TYPE;

  public static final java.lang.String SIGNATURE_SECRET;

  public static final java.lang.String SIGNATURE_SECRET_FILE;

  public static final java.lang.String AUTH_TOKEN_MAX_INACTIVE_INTERVAL;

  public static final java.lang.String AUTH_TOKEN_VALIDITY;

  public static final java.lang.String COOKIE_DOMAIN;

  public static final java.lang.String COOKIE_PATH;

  public static final java.lang.String COOKIE_PERSISTENT;

  public static final java.lang.String SIGNER_SECRET_PROVIDER;

  public static final java.lang.String SIGNER_SECRET_PROVIDER_ATTRIBUTE;

  private java.util.Properties config;

  private org.apache.hadoop.security.authentication.util.Signer signer;

  private org.apache.hadoop.security.authentication.util.SignerSecretProvider secretProvider;

  private org.apache.hadoop.security.authentication.server.AuthenticationHandler authHandler;

  private long maxInactiveInterval;

  private long validity;

  private java.lang.String cookieDomain;

  private java.lang.String cookiePath;

  private boolean isCookiePersistent;

  private boolean destroySecretProvider;

  public org.apache.hadoop.security.authentication.server.AuthenticationFilter();
    Code:
       0: aload_0
       1: invokespecial #2                  // Method java/lang/Object."<init>":()V
       4: return

  public void init(javax.servlet.FilterConfig) throws javax.servlet.ServletException;
    Code:
       0: aload_1
       1: ldc           #3                  // String config.prefix
       3: invokeinterface #4,  2            // InterfaceMethod javax/servlet/FilterConfig.getInitParameter:(Ljava/lang/String;)Ljava/lang/String;
       8: astore_2
       9: aload_2
      10: ifnull        35
      13: new           #5                  // class java/lang/StringBuilder
      16: dup
      17: invokespecial #6                  // Method java/lang/StringBuilder."<init>":()V
      20: aload_2
      21: invokevirtual #7                  // Method java/lang/StringBuilder.append:(Ljava/lang/String;)Ljava/lang/StringBuilder;
      24: ldc           #8                  // String .
      26: invokevirtual #7                  // Method java/lang/StringBuilder.append:(Ljava/lang/String;)Ljava/lang/StringBuilder;
      29: invokevirtual #9                  // Method java/lang/StringBuilder.toString:()Ljava/lang/String;
      32: goto          37
      35: ldc           #10                 // String
      37: astore_2
      38: aload_0
      39: aload_0
      40: aload_2
      41: aload_1
      42: invokevirtual #11                 // Method getConfiguration:(Ljava/lang/String;Ljavax/servlet/FilterConfig;)Ljava/util/Properties;
      45: putfield      #12                 // Field config:Ljava/util/Properties;
      48: aload_0
      49: getfield      #12                 // Field config:Ljava/util/Properties;
      52: ldc           #13                 // String type
      54: aconst_null
      55: invokevirtual #14                 // Method java/util/Properties.getProperty:(Ljava/lang/String;Ljava/lang/String;)Ljava/lang/String;
      58: astore_3
      59: aload_3
      60: ifnonnull     73
      63: new           #15                 // class javax/servlet/ServletException
      66: dup
      67: ldc           #18                 // String Authentication type must be specified: simple|kerberos|<class>
      69: invokespecial #19                 // Method javax/servlet/ServletException."<init>":(Ljava/lang/String;)V
      72: athrow
      73: aload_3
      74: invokestatic  #20                 // Method org/apache/hadoop/security/authentication/server/AuthenticationHandlerUtil.getAuthenticationHandlerClassName:(Ljava/lang/String;)Ljava/lang/String;
      77: astore        4
      79: aload_0
      80: aload_0
      81: getfield      #12                 // Field config:Ljava/util/Properties;
      84: ldc           #21                 // String token.max-inactive-interval
      86: ldc           #22                 // String -1
      88: invokevirtual #14                 // Method java/util/Properties.getProperty:(Ljava/lang/String;Ljava/lang/String;)Ljava/lang/String;
      91: invokestatic  #23                 // Method java/lang/Long.parseLong:(Ljava/lang/String;)J
      94: putfield      #24                 // Field maxInactiveInterval:J
      97: aload_0
      98: getfield      #24                 // Field maxInactiveInterval:J
     101: lconst_0
     102: lcmp
     103: ifle          118
     106: aload_0
     107: dup
     108: getfield      #24                 // Field maxInactiveInterval:J
     111: ldc2_w        #25                 // long 1000l
     114: lmul
     115: putfield      #24                 // Field maxInactiveInterval:J
     118: aload_0
     119: aload_0
     120: getfield      #12                 // Field config:Ljava/util/Properties;
     123: ldc           #27                 // String token.validity
     125: ldc           #28                 // String 36000
     127: invokevirtual #14                 // Method java/util/Properties.getProperty:(Ljava/lang/String;Ljava/lang/String;)Ljava/lang/String;
     130: invokestatic  #23                 // Method java/lang/Long.parseLong:(Ljava/lang/String;)J
     133: ldc2_w        #25                 // long 1000l
     136: lmul
     137: putfield      #29                 // Field validity:J
     140: aload_0
     141: aload_1
     142: invokevirtual #30                 // Method initializeSecretProvider:(Ljavax/servlet/FilterConfig;)V
     145: aload_0
     146: aload         4
     148: aload_1
     149: invokevirtual #31                 // Method initializeAuthHandler:(Ljava/lang/String;Ljavax/servlet/FilterConfig;)V
     152: aload_0
     153: aload_0
     154: getfield      #12                 // Field config:Ljava/util/Properties;
     157: ldc           #32                 // String cookie.domain
     159: aconst_null
     160: invokevirtual #14                 // Method java/util/Properties.getProperty:(Ljava/lang/String;Ljava/lang/String;)Ljava/lang/String;
     163: putfield      #33                 // Field cookieDomain:Ljava/lang/String;
     166: aload_0
     167: aload_0
     168: getfield      #12                 // Field config:Ljava/util/Properties;
     171: ldc           #34                 // String cookie.path
     173: aconst_null
     174: invokevirtual #14                 // Method java/util/Properties.getProperty:(Ljava/lang/String;Ljava/lang/String;)Ljava/lang/String;
     177: putfield      #35                 // Field cookiePath:Ljava/lang/String;
     180: aload_0
     181: aload_0
     182: getfield      #12                 // Field config:Ljava/util/Properties;
     185: ldc           #36                 // String cookie.persistent
     187: ldc           #37                 // String false
     189: invokevirtual #14                 // Method java/util/Properties.getProperty:(Ljava/lang/String;Ljava/lang/String;)Ljava/lang/String;
     192: invokestatic  #38                 // Method java/lang/Boolean.parseBoolean:(Ljava/lang/String;)Z
     195: putfield      #39                 // Field isCookiePersistent:Z
     198: return

  protected void initializeAuthHandler(java.lang.String, javax.servlet.FilterConfig) throws javax.servlet.ServletException;
    Code:
       0: invokestatic  #40                 // Method java/lang/Thread.currentThread:()Ljava/lang/Thread;
       3: invokevirtual #41                 // Method java/lang/Thread.getContextClassLoader:()Ljava/lang/ClassLoader;
       6: aload_1
       7: invokevirtual #42                 // Method java/lang/ClassLoader.loadClass:(Ljava/lang/String;)Ljava/lang/Class;
      10: astore_3
      11: aload_0
      12: aload_3
      13: invokevirtual #43                 // Method java/lang/Class.newInstance:()Ljava/lang/Object;
      16: checkcast     #44                 // class org/apache/hadoop/security/authentication/server/AuthenticationHandler
      19: putfield      #45                 // Field authHandler:Lorg/apache/hadoop/security/authentication/server/AuthenticationHandler;
      22: aload_0
      23: getfield      #45                 // Field authHandler:Lorg/apache/hadoop/security/authentication/server/AuthenticationHandler;
      26: aload_0
      27: getfield      #12                 // Field config:Ljava/util/Properties;
      30: invokeinterface #46,  2           // InterfaceMethod org/apache/hadoop/security/authentication/server/AuthenticationHandler.init:(Ljava/util/Properties;)V
      35: goto          48
      38: astore_3
      39: new           #15                 // class javax/servlet/ServletException
      42: dup
      43: aload_3
      44: invokespecial #50                 // Method javax/servlet/ServletException."<init>":(Ljava/lang/Throwable;)V
      47: athrow
      48: return
    Exception table:
       from    to  target type
           0    35    38   Class java/lang/ClassNotFoundException
           0    35    38   Class java/lang/InstantiationException
           0    35    38   Class java/lang/IllegalAccessException

  protected void initializeSecretProvider(javax.servlet.FilterConfig) throws javax.servlet.ServletException;
    Code:
       0: aload_0
       1: aload_1
       2: invokeinterface #51,  1           // InterfaceMethod javax/servlet/FilterConfig.getServletContext:()Ljavax/servlet/ServletContext;
       7: ldc           #52                 // String signer.secret.provider.object
       9: invokeinterface #53,  2           // InterfaceMethod javax/servlet/ServletContext.getAttribute:(Ljava/lang/String;)Ljava/lang/Object;
      14: checkcast     #54                 // class org/apache/hadoop/security/authentication/util/SignerSecretProvider
      17: putfield      #55                 // Field secretProvider:Lorg/apache/hadoop/security/authentication/util/SignerSecretProvider;
      20: aload_0
      21: getfield      #55                 // Field secretProvider:Lorg/apache/hadoop/security/authentication/util/SignerSecretProvider;
      24: ifnonnull     63
      27: aload_0
      28: aload_1
      29: invokeinterface #51,  1           // InterfaceMethod javax/servlet/FilterConfig.getServletContext:()Ljavax/servlet/ServletContext;
      34: aload_0
      35: getfield      #12                 // Field config:Ljava/util/Properties;
      38: iconst_0
      39: invokestatic  #56                 // Method constructSecretProvider:(Ljavax/servlet/ServletContext;Ljava/util/Properties;Z)Lorg/apache/hadoop/security/authentication/util/SignerSecretProvider;
      42: putfield      #55                 // Field secretProvider:Lorg/apache/hadoop/security/authentication/util/SignerSecretProvider;
      45: aload_0
      46: iconst_1
      47: putfield      #57                 // Field destroySecretProvider:Z
      50: goto          63
      53: astore_2
      54: new           #15                 // class javax/servlet/ServletException
      57: dup
      58: aload_2
      59: invokespecial #50                 // Method javax/servlet/ServletException."<init>":(Ljava/lang/Throwable;)V
      62: athrow
      63: aload_0
      64: new           #59                 // class org/apache/hadoop/security/authentication/util/Signer
      67: dup
      68: aload_0
      69: getfield      #55                 // Field secretProvider:Lorg/apache/hadoop/security/authentication/util/SignerSecretProvider;
      72: invokespecial #60                 // Method org/apache/hadoop/security/authentication/util/Signer."<init>":(Lorg/apache/hadoop/security/authentication/util/SignerSecretProvider;)V
      75: putfield      #61                 // Field signer:Lorg/apache/hadoop/security/authentication/util/Signer;
      78: return
    Exception table:
       from    to  target type
          27    50    53   Class java/lang/Exception

  public static org.apache.hadoop.security.authentication.util.SignerSecretProvider constructSecretProvider(javax.servlet.ServletContext, java.util.Properties, boolean) throws java.lang.Exception;
    Code:
       0: aload_1
       1: ldc           #62                 // String signer.secret.provider
       3: ldc           #63                 // String file
       5: invokevirtual #14                 // Method java/util/Properties.getProperty:(Ljava/lang/String;Ljava/lang/String;)Ljava/lang/String;
       8: astore_3
       9: aload_1
      10: ldc           #27                 // String token.validity
      12: ldc           #28                 // String 36000
      14: invokevirtual #14                 // Method java/util/Properties.getProperty:(Ljava/lang/String;Ljava/lang/String;)Ljava/lang/String;
      17: invokestatic  #23                 // Method java/lang/Long.parseLong:(Ljava/lang/String;)J
      20: ldc2_w        #25                 // long 1000l
      23: lmul
      24: lstore        4
      26: iload_2
      27: ifne          51
      30: ldc           #63                 // String file
      32: aload_3
      33: invokevirtual #64                 // Method java/lang/String.equals:(Ljava/lang/Object;)Z
      36: ifeq          51
      39: aload_1
      40: ldc           #65                 // String signature.secret.file
      42: invokevirtual #66                 // Method java/util/Properties.getProperty:(Ljava/lang/String;)Ljava/lang/String;
      45: ifnonnull     51
      48: ldc           #67                 // String random
      50: astore_3
      51: ldc           #63                 // String file
      53: aload_3
      54: invokevirtual #64                 // Method java/lang/String.equals:(Ljava/lang/Object;)Z
      57: ifeq          124
      60: new           #68                 // class org/apache/hadoop/security/authentication/util/FileSignerSecretProvider
      63: dup
      64: invokespecial #69                 // Method org/apache/hadoop/security/authentication/util/FileSignerSecretProvider."<init>":()V
      67: astore        6
      69: aload         6
      71: aload_1
      72: aload_0
      73: lload         4
      75: invokevirtual #70                 // Method org/apache/hadoop/security/authentication/util/SignerSecretProvider.init:(Ljava/util/Properties;Ljavax/servlet/ServletContext;J)V
      78: goto          211
      81: astore        7
      83: iload_2
      84: ifne          118
      87: getstatic     #71                 // Field LOG:Lorg/slf4j/Logger;
      90: ldc           #72                 // String Unable to initialize FileSignerSecretProvider, falling back to use random secrets.
      92: invokeinterface #73,  2           // InterfaceMethod org/slf4j/Logger.info:(Ljava/lang/String;)V
      97: new           #74                 // class org/apache/hadoop/security/authentication/util/RandomSignerSecretProvider
     100: dup
     101: invokespecial #75                 // Method org/apache/hadoop/security/authentication/util/RandomSignerSecretProvider."<init>":()V
     104: astore        6
     106: aload         6
     108: aload_1
     109: aload_0
     110: lload         4
     112: invokevirtual #70                 // Method org/apache/hadoop/security/authentication/util/SignerSecretProvider.init:(Ljava/util/Properties;Ljavax/servlet/ServletContext;J)V
     115: goto          121
     118: aload         7
     120: athrow
     121: goto          211
     124: ldc           #67                 // String random
     126: aload_3
     127: invokevirtual #64                 // Method java/lang/String.equals:(Ljava/lang/Object;)Z
     130: ifeq          154
     133: new           #74                 // class org/apache/hadoop/security/authentication/util/RandomSignerSecretProvider
     136: dup
     137: invokespecial #75                 // Method org/apache/hadoop/security/authentication/util/RandomSignerSecretProvider."<init>":()V
     140: astore        6
     142: aload         6
     144: aload_1
     145: aload_0
     146: lload         4
     148: invokevirtual #70                 // Method org/apache/hadoop/security/authentication/util/SignerSecretProvider.init:(Ljava/util/Properties;Ljavax/servlet/ServletContext;J)V
     151: goto          211
     154: ldc           #76                 // String zookeeper
     156: aload_3
     157: invokevirtual #64                 // Method java/lang/String.equals:(Ljava/lang/Object;)Z
     160: ifeq          184
     163: new           #77                 // class org/apache/hadoop/security/authentication/util/ZKSignerSecretProvider
     166: dup
     167: invokespecial #78                 // Method org/apache/hadoop/security/authentication/util/ZKSignerSecretProvider."<init>":()V
     170: astore        6
     172: aload         6
     174: aload_1
     175: aload_0
     176: lload         4
     178: invokevirtual #70                 // Method org/apache/hadoop/security/authentication/util/SignerSecretProvider.init:(Ljava/util/Properties;Ljavax/servlet/ServletContext;J)V
     181: goto          211
     184: invokestatic  #40                 // Method java/lang/Thread.currentThread:()Ljava/lang/Thread;
     187: invokevirtual #41                 // Method java/lang/Thread.getContextClassLoader:()Ljava/lang/ClassLoader;
     190: aload_3
     191: invokevirtual #42                 // Method java/lang/ClassLoader.loadClass:(Ljava/lang/String;)Ljava/lang/Class;
     194: invokevirtual #43                 // Method java/lang/Class.newInstance:()Ljava/lang/Object;
     197: checkcast     #54                 // class org/apache/hadoop/security/authentication/util/SignerSecretProvider
     200: astore        6
     202: aload         6
     204: aload_1
     205: aload_0
     206: lload         4
     208: invokevirtual #70                 // Method org/apache/hadoop/security/authentication/util/SignerSecretProvider.init:(Ljava/util/Properties;Ljavax/servlet/ServletContext;J)V
     211: aload         6
     213: areturn
    Exception table:
       from    to  target type
          69    78    81   Class java/lang/Exception

  protected java.util.Properties getConfiguration();
    Code:
       0: aload_0
       1: getfield      #12                 // Field config:Ljava/util/Properties;
       4: areturn

  protected org.apache.hadoop.security.authentication.server.AuthenticationHandler getAuthenticationHandler();
    Code:
       0: aload_0
       1: getfield      #45                 // Field authHandler:Lorg/apache/hadoop/security/authentication/server/AuthenticationHandler;
       4: areturn

  protected boolean isRandomSecret();
    Code:
       0: aload_0
       1: getfield      #55                 // Field secretProvider:Lorg/apache/hadoop/security/authentication/util/SignerSecretProvider;
       4: invokevirtual #79                 // Method java/lang/Object.getClass:()Ljava/lang/Class;
       7: ldc           #74                 // class org/apache/hadoop/security/authentication/util/RandomSignerSecretProvider
       9: if_acmpne     16
      12: iconst_1
      13: goto          17
      16: iconst_0
      17: ireturn

  protected boolean isCustomSignerSecretProvider();
    Code:
       0: aload_0
       1: getfield      #55                 // Field secretProvider:Lorg/apache/hadoop/security/authentication/util/SignerSecretProvider;
       4: invokevirtual #79                 // Method java/lang/Object.getClass:()Ljava/lang/Class;
       7: astore_1
       8: aload_1
       9: ldc           #68                 // class org/apache/hadoop/security/authentication/util/FileSignerSecretProvider
      11: if_acmpeq     30
      14: aload_1
      15: ldc           #74                 // class org/apache/hadoop/security/authentication/util/RandomSignerSecretProvider
      17: if_acmpeq     30
      20: aload_1
      21: ldc           #77                 // class org/apache/hadoop/security/authentication/util/ZKSignerSecretProvider
      23: if_acmpeq     30
      26: iconst_1
      27: goto          31
      30: iconst_0
      31: ireturn

  protected long getMaxInactiveInterval();
    Code:
       0: aload_0
       1: getfield      #24                 // Field maxInactiveInterval:J
       4: ldc2_w        #25                 // long 1000l
       7: ldiv
       8: lreturn

  protected long getValidity();
    Code:
       0: aload_0
       1: getfield      #29                 // Field validity:J
       4: ldc2_w        #25                 // long 1000l
       7: ldiv
       8: lreturn

  protected java.lang.String getCookieDomain();
    Code:
       0: aload_0
       1: getfield      #33                 // Field cookieDomain:Ljava/lang/String;
       4: areturn

  protected java.lang.String getCookiePath();
    Code:
       0: aload_0
       1: getfield      #35                 // Field cookiePath:Ljava/lang/String;
       4: areturn

  protected boolean isCookiePersistent();
    Code:
       0: aload_0
       1: getfield      #39                 // Field isCookiePersistent:Z
       4: ireturn

  public void destroy();
    Code:
       0: aload_0
       1: getfield      #45                 // Field authHandler:Lorg/apache/hadoop/security/authentication/server/AuthenticationHandler;
       4: ifnull        21
       7: aload_0
       8: getfield      #45                 // Field authHandler:Lorg/apache/hadoop/security/authentication/server/AuthenticationHandler;
      11: invokeinterface #80,  1           // InterfaceMethod org/apache/hadoop/security/authentication/server/AuthenticationHandler.destroy:()V
      16: aload_0
      17: aconst_null
      18: putfield      #45                 // Field authHandler:Lorg/apache/hadoop/security/authentication/server/AuthenticationHandler;
      21: aload_0
      22: getfield      #55                 // Field secretProvider:Lorg/apache/hadoop/security/authentication/util/SignerSecretProvider;
      25: ifnull        47
      28: aload_0
      29: getfield      #57                 // Field destroySecretProvider:Z
      32: ifeq          47
      35: aload_0
      36: getfield      #55                 // Field secretProvider:Lorg/apache/hadoop/security/authentication/util/SignerSecretProvider;
      39: invokevirtual #81                 // Method org/apache/hadoop/security/authentication/util/SignerSecretProvider.destroy:()V
      42: aload_0
      43: aconst_null
      44: putfield      #55                 // Field secretProvider:Lorg/apache/hadoop/security/authentication/util/SignerSecretProvider;
      47: return

  protected java.util.Properties getConfiguration(java.lang.String, javax.servlet.FilterConfig) throws javax.servlet.ServletException;
    Code:
       0: new           #82                 // class java/util/Properties
       3: dup
       4: invokespecial #83                 // Method java/util/Properties."<init>":()V
       7: astore_3
       8: aload_2
       9: invokeinterface #84,  1           // InterfaceMethod javax/servlet/FilterConfig.getInitParameterNames:()Ljava/util/Enumeration;
      14: astore        4
      16: aload         4
      18: invokeinterface #85,  1           // InterfaceMethod java/util/Enumeration.hasMoreElements:()Z
      23: ifeq          76
      26: aload         4
      28: invokeinterface #86,  1           // InterfaceMethod java/util/Enumeration.nextElement:()Ljava/lang/Object;
      33: checkcast     #87                 // class java/lang/String
      36: astore        5
      38: aload         5
      40: aload_1
      41: invokevirtual #88                 // Method java/lang/String.startsWith:(Ljava/lang/String;)Z
      44: ifeq          73
      47: aload_2
      48: aload         5
      50: invokeinterface #4,  2            // InterfaceMethod javax/servlet/FilterConfig.getInitParameter:(Ljava/lang/String;)Ljava/lang/String;
      55: astore        6
      57: aload_3
      58: aload         5
      60: aload_1
      61: invokevirtual #89                 // Method java/lang/String.length:()I
      64: invokevirtual #90                 // Method java/lang/String.substring:(I)Ljava/lang/String;
      67: aload         6
      69: invokevirtual #91                 // Method java/util/Properties.put:(Ljava/lang/Object;Ljava/lang/Object;)Ljava/lang/Object;
      72: pop
      73: goto          16
      76: aload_3
      77: areturn

  protected java.lang.String getRequestURL(javax.servlet.http.HttpServletRequest);
    Code:
       0: aload_1
       1: invokeinterface #92,  1           // InterfaceMethod javax/servlet/http/HttpServletRequest.getRequestURL:()Ljava/lang/StringBuffer;
       6: astore_2
       7: aload_1
       8: invokeinterface #93,  1           // InterfaceMethod javax/servlet/http/HttpServletRequest.getQueryString:()Ljava/lang/String;
      13: ifnull        32
      16: aload_2
      17: ldc           #94                 // String ?
      19: invokevirtual #95                 // Method java/lang/StringBuffer.append:(Ljava/lang/String;)Ljava/lang/StringBuffer;
      22: aload_1
      23: invokeinterface #93,  1           // InterfaceMethod javax/servlet/http/HttpServletRequest.getQueryString:()Ljava/lang/String;
      28: invokevirtual #95                 // Method java/lang/StringBuffer.append:(Ljava/lang/String;)Ljava/lang/StringBuffer;
      31: pop
      32: aload_2
      33: invokevirtual #96                 // Method java/lang/StringBuffer.toString:()Ljava/lang/String;
      36: areturn

  protected org.apache.hadoop.security.authentication.server.AuthenticationToken getToken(javax.servlet.http.HttpServletRequest) throws java.io.IOException, org.apache.hadoop.security.authentication.client.AuthenticationException;
    Code:
       0: aconst_null
       1: astore_2
       2: aconst_null
       3: astore_3
       4: aload_1
       5: invokeinterface #97,  1           // InterfaceMethod javax/servlet/http/HttpServletRequest.getCookies:()[Ljavax/servlet/http/Cookie;
      10: astore        4
      12: aload         4
      14: ifnull        109
      17: aload         4
      19: astore        5
      21: aload         5
      23: arraylength
      24: istore        6
      26: iconst_0
      27: istore        7
      29: iload         7
      31: iload         6
      33: if_icmpge     109
      36: aload         5
      38: iload         7
      40: aaload
      41: astore        8
      43: aload         8
      45: invokevirtual #98                 // Method javax/servlet/http/Cookie.getName:()Ljava/lang/String;
      48: ldc           #100                // String hadoop.auth
      50: invokevirtual #64                 // Method java/lang/String.equals:(Ljava/lang/Object;)Z
      53: ifeq          103
      56: aload         8
      58: invokevirtual #101                // Method javax/servlet/http/Cookie.getValue:()Ljava/lang/String;
      61: astore_3
      62: aload_3
      63: invokevirtual #102                // Method java/lang/String.isEmpty:()Z
      66: ifeq          79
      69: new           #103                // class org/apache/hadoop/security/authentication/client/AuthenticationException
      72: dup
      73: ldc           #104                // String Unauthorized access
      75: invokespecial #105                // Method org/apache/hadoop/security/authentication/client/AuthenticationException."<init>":(Ljava/lang/String;)V
      78: athrow
      79: aload_0
      80: getfield      #61                 // Field signer:Lorg/apache/hadoop/security/authentication/util/Signer;
      83: aload_3
      84: invokevirtual #106                // Method org/apache/hadoop/security/authentication/util/Signer.verifyAndExtract:(Ljava/lang/String;)Ljava/lang/String;
      87: astore_3
      88: goto          109
      91: astore        9
      93: new           #103                // class org/apache/hadoop/security/authentication/client/AuthenticationException
      96: dup
      97: aload         9
      99: invokespecial #108                // Method org/apache/hadoop/security/authentication/client/AuthenticationException."<init>":(Ljava/lang/Throwable;)V
     102: athrow
     103: iinc          7, 1
     106: goto          29
     109: aload_3
     110: ifnull        161
     113: aload_3
     114: invokestatic  #109                // Method org/apache/hadoop/security/authentication/server/AuthenticationToken.parse:(Ljava/lang/String;)Lorg/apache/hadoop/security/authentication/server/AuthenticationToken;
     117: astore_2
     118: aload_0
     119: aload_0
     120: invokevirtual #110                // Method getAuthenticationHandler:()Lorg/apache/hadoop/security/authentication/server/AuthenticationHandler;
     123: aload_2
     124: invokevirtual #111                // Method verifyTokenType:(Lorg/apache/hadoop/security/authentication/server/AuthenticationHandler;Lorg/apache/hadoop/security/authentication/server/AuthenticationToken;)Z
     127: istore        5
     129: iload         5
     131: ifne          144
     134: new           #103                // class org/apache/hadoop/security/authentication/client/AuthenticationException
     137: dup
     138: ldc           #112                // String Invalid AuthenticationToken type
     140: invokespecial #105                // Method org/apache/hadoop/security/authentication/client/AuthenticationException."<init>":(Ljava/lang/String;)V
     143: athrow
     144: aload_2
     145: invokevirtual #113                // Method org/apache/hadoop/security/authentication/server/AuthenticationToken.isExpired:()Z
     148: ifeq          161
     151: new           #103                // class org/apache/hadoop/security/authentication/client/AuthenticationException
     154: dup
     155: ldc           #114                // String AuthenticationToken expired
     157: invokespecial #105                // Method org/apache/hadoop/security/authentication/client/AuthenticationException."<init>":(Ljava/lang/String;)V
     160: athrow
     161: aload_2
     162: areturn
    Exception table:
       from    to  target type
          79    88    91   Class org/apache/hadoop/security/authentication/util/SignerException

  protected boolean verifyTokenType(org.apache.hadoop.security.authentication.server.AuthenticationHandler, org.apache.hadoop.security.authentication.server.AuthenticationToken);
    Code:
       0: aload_1
       1: instanceof    #115                // class org/apache/hadoop/security/authentication/server/CompositeAuthenticationHandler
       4: ifne          21
       7: aload_1
       8: invokeinterface #116,  1          // InterfaceMethod org/apache/hadoop/security/authentication/server/AuthenticationHandler.getType:()Ljava/lang/String;
      13: aload_2
      14: invokevirtual #117                // Method org/apache/hadoop/security/authentication/server/AuthenticationToken.getType:()Ljava/lang/String;
      17: invokevirtual #64                 // Method java/lang/String.equals:(Ljava/lang/Object;)Z
      20: ireturn
      21: iconst_0
      22: istore_3
      23: aload_1
      24: checkcast     #115                // class org/apache/hadoop/security/authentication/server/CompositeAuthenticationHandler
      27: invokeinterface #118,  1          // InterfaceMethod org/apache/hadoop/security/authentication/server/CompositeAuthenticationHandler.getTokenTypes:()Ljava/util/Collection;
      32: astore        4
      34: aload         4
      36: invokeinterface #119,  1          // InterfaceMethod java/util/Collection.iterator:()Ljava/util/Iterator;
      41: astore        5
      43: aload         5
      45: invokeinterface #120,  1          // InterfaceMethod java/util/Iterator.hasNext:()Z
      50: ifeq          85
      53: aload         5
      55: invokeinterface #121,  1          // InterfaceMethod java/util/Iterator.next:()Ljava/lang/Object;
      60: checkcast     #87                 // class java/lang/String
      63: astore        6
      65: aload         6
      67: aload_2
      68: invokevirtual #117                // Method org/apache/hadoop/security/authentication/server/AuthenticationToken.getType:()Ljava/lang/String;
      71: invokevirtual #64                 // Method java/lang/String.equals:(Ljava/lang/Object;)Z
      74: ifeq          82
      77: iconst_1
      78: istore_3
      79: goto          85
      82: goto          43
      85: iload_3
      86: ireturn

  public void doFilter(javax.servlet.ServletRequest, javax.servlet.ServletResponse, javax.servlet.FilterChain) throws java.io.IOException, javax.servlet.ServletException;
    Code:
       0: iconst_1
       1: istore        4
       3: sipush        401
       6: istore        5
       8: aconst_null
       9: astore        6
      11: aload_1
      12: checkcast     #123                // class javax/servlet/http/HttpServletRequest
      15: astore        7
      17: aload_2
      18: checkcast     #122                // class javax/servlet/http/HttpServletResponse
      21: astore        8
      23: ldc           #124                // String https
      25: aload         7
      27: invokeinterface #125,  1          // InterfaceMethod javax/servlet/http/HttpServletRequest.getScheme:()Ljava/lang/String;
      32: invokevirtual #64                 // Method java/lang/String.equals:(Ljava/lang/Object;)Z
      35: istore        9
      37: iconst_0
      38: istore        10
      40: aload_0
      41: aload         7
      43: invokevirtual #126                // Method getToken:(Ljavax/servlet/http/HttpServletRequest;)Lorg/apache/hadoop/security/authentication/server/AuthenticationToken;
      46: astore        11
      48: getstatic     #71                 // Field LOG:Lorg/slf4j/Logger;
      51: invokeinterface #127,  1          // InterfaceMethod org/slf4j/Logger.isDebugEnabled:()Z
      56: ifeq          77
      59: getstatic     #71                 // Field LOG:Lorg/slf4j/Logger;
      62: ldc           #128                // String Got token {} from httpRequest {}
      64: aload         11
      66: aload_0
      67: aload         7
      69: invokevirtual #129                // Method getRequestURL:(Ljavax/servlet/http/HttpServletRequest;)Ljava/lang/String;
      72: invokeinterface #130,  4          // InterfaceMethod org/slf4j/Logger.debug:(Ljava/lang/String;Ljava/lang/Object;Ljava/lang/Object;)V
      77: goto          120
      80: astore        12
      82: getstatic     #71                 // Field LOG:Lorg/slf4j/Logger;
      85: new           #5                  // class java/lang/StringBuilder
      88: dup
      89: invokespecial #6                  // Method java/lang/StringBuilder."<init>":()V
      92: ldc           #131                // String AuthenticationToken ignored:
      94: invokevirtual #7                  // Method java/lang/StringBuilder.append:(Ljava/lang/String;)Ljava/lang/StringBuilder;
      97: aload         12
      99: invokevirtual #132                // Method org/apache/hadoop/security/authentication/client/AuthenticationException.getMessage:()Ljava/lang/String;
     102: invokevirtual #7                  // Method java/lang/StringBuilder.append:(Ljava/lang/String;)Ljava/lang/StringBuilder;
     105: invokevirtual #9                  // Method java/lang/StringBuilder.toString:()Ljava/lang/String;
     108: invokeinterface #133,  2          // InterfaceMethod org/slf4j/Logger.warn:(Ljava/lang/String;)V
     113: aload         12
     115: astore        6
     117: aconst_null
     118: astore        11
     120: aload_0
     121: getfield      #45                 // Field authHandler:Lorg/apache/hadoop/security/authentication/server/AuthenticationHandler;
     124: aload         11
     126: aload         7
     128: aload         8
     130: invokeinterface #134,  4          // InterfaceMethod org/apache/hadoop/security/authentication/server/AuthenticationHandler.managementOperation:(Lorg/apache/hadoop/security/authentication/server/AuthenticationToken;Ljavax/servlet/http/HttpServletRequest;Ljavax/servlet/http/HttpServletResponse;)Z
     135: ifeq          444
     138: aload         11
     140: ifnonnull     262
     143: getstatic     #71                 // Field LOG:Lorg/slf4j/Logger;
     146: invokeinterface #127,  1          // InterfaceMethod org/slf4j/Logger.isDebugEnabled:()Z
     151: ifeq          177
     154: getstatic     #71                 // Field LOG:Lorg/slf4j/Logger;
     157: ldc           #135                // String Request [{}] triggering authentication. handler: {}
     159: aload_0
     160: aload         7
     162: invokevirtual #129                // Method getRequestURL:(Ljavax/servlet/http/HttpServletRequest;)Ljava/lang/String;
     165: aload_0
     166: getfield      #45                 // Field authHandler:Lorg/apache/hadoop/security/authentication/server/AuthenticationHandler;
     169: invokevirtual #79                 // Method java/lang/Object.getClass:()Ljava/lang/Class;
     172: invokeinterface #130,  4          // InterfaceMethod org/slf4j/Logger.debug:(Ljava/lang/String;Ljava/lang/Object;Ljava/lang/Object;)V
     177: aload_0
     178: getfield      #45                 // Field authHandler:Lorg/apache/hadoop/security/authentication/server/AuthenticationHandler;
     181: aload         7
     183: aload         8
     185: invokeinterface #136,  3          // InterfaceMethod org/apache/hadoop/security/authentication/server/AuthenticationHandler.authenticate:(Ljavax/servlet/http/HttpServletRequest;Ljavax/servlet/http/HttpServletResponse;)Lorg/apache/hadoop/security/authentication/server/AuthenticationToken;
     190: astore        11
     192: aload         11
     194: ifnull        259
     197: aload         11
     199: getstatic     #137                // Field org/apache/hadoop/security/authentication/server/AuthenticationToken.ANONYMOUS:Lorg/apache/hadoop/security/authentication/server/AuthenticationToken;
     202: if_acmpeq     259
     205: aload         11
     207: invokevirtual #138                // Method org/apache/hadoop/security/authentication/server/AuthenticationToken.getMaxInactives:()J
     210: lconst_0
     211: lcmp
     212: ifle          232
     215: aload         11
     217: invokestatic  #139                // Method java/lang/System.currentTimeMillis:()J
     220: aload_0
     221: invokevirtual #140                // Method getMaxInactiveInterval:()J
     224: ldc2_w        #25                 // long 1000l
     227: lmul
     228: ladd
     229: invokevirtual #141                // Method org/apache/hadoop/security/authentication/server/AuthenticationToken.setMaxInactives:(J)V
     232: aload         11
     234: invokevirtual #142                // Method org/apache/hadoop/security/authentication/server/AuthenticationToken.getExpires:()J
     237: lconst_0
     238: lcmp
     239: ifeq          259
     242: aload         11
     244: invokestatic  #139                // Method java/lang/System.currentTimeMillis:()J
     247: aload_0
     248: invokevirtual #143                // Method getValidity:()J
     251: ldc2_w        #25                 // long 1000l
     254: lmul
     255: ladd
     256: invokevirtual #144                // Method org/apache/hadoop/security/authentication/server/AuthenticationToken.setExpires:(J)V
     259: iconst_1
     260: istore        10
     262: aload         11
     264: ifnull        476
     267: iconst_0
     268: istore        4
     270: getstatic     #71                 // Field LOG:Lorg/slf4j/Logger;
     273: invokeinterface #127,  1          // InterfaceMethod org/slf4j/Logger.isDebugEnabled:()Z
     278: ifeq          302
     281: getstatic     #71                 // Field LOG:Lorg/slf4j/Logger;
     284: ldc           #145                // String Request [{}] user [{}] authenticated
     286: aload_0
     287: aload         7
     289: invokevirtual #129                // Method getRequestURL:(Ljavax/servlet/http/HttpServletRequest;)Ljava/lang/String;
     292: aload         11
     294: invokevirtual #146                // Method org/apache/hadoop/security/authentication/server/AuthenticationToken.getUserName:()Ljava/lang/String;
     297: invokeinterface #130,  4          // InterfaceMethod org/slf4j/Logger.debug:(Ljava/lang/String;Ljava/lang/Object;Ljava/lang/Object;)V
     302: aload         11
     304: astore        12
     306: new           #147                // class org/apache/hadoop/security/authentication/server/AuthenticationFilter$1
     309: dup
     310: aload_0
     311: aload         7
     313: aload         12
     315: invokespecial #148                // Method org/apache/hadoop/security/authentication/server/AuthenticationFilter$1."<init>":(Lorg/apache/hadoop/security/authentication/server/AuthenticationFilter;Ljavax/servlet/http/HttpServletRequest;Lorg/apache/hadoop/security/authentication/server/AuthenticationToken;)V
     318: astore        7
     320: iload         10
     322: ifne          371
     325: aload_0
     326: invokevirtual #149                // Method isCookiePersistent:()Z
     329: ifne          371
     332: aload_0
     333: invokevirtual #140                // Method getMaxInactiveInterval:()J
     336: lconst_0
     337: lcmp
     338: ifle          371
     341: aload         11
     343: invokestatic  #139                // Method java/lang/System.currentTimeMillis:()J
     346: aload_0
     347: invokevirtual #140                // Method getMaxInactiveInterval:()J
     350: ldc2_w        #25                 // long 1000l
     353: lmul
     354: ladd
     355: invokevirtual #141                // Method org/apache/hadoop/security/authentication/server/AuthenticationToken.setMaxInactives:(J)V
     358: aload         11
     360: aload         11
     362: invokevirtual #142                // Method org/apache/hadoop/security/authentication/server/AuthenticationToken.getExpires:()J
     365: invokevirtual #144                // Method org/apache/hadoop/security/authentication/server/AuthenticationToken.setExpires:(J)V
     368: iconst_1
     369: istore        10
     371: iload         10
     373: ifeq          432
     376: aload         11
     378: invokevirtual #113                // Method org/apache/hadoop/security/authentication/server/AuthenticationToken.isExpired:()Z
     381: ifne          432
     384: aload         11
     386: getstatic     #137                // Field org/apache/hadoop/security/authentication/server/AuthenticationToken.ANONYMOUS:Lorg/apache/hadoop/security/authentication/server/AuthenticationToken;
     389: if_acmpeq     432
     392: aload_0
     393: getfield      #61                 // Field signer:Lorg/apache/hadoop/security/authentication/util/Signer;
     396: aload         11
     398: invokevirtual #150                // Method org/apache/hadoop/security/authentication/server/AuthenticationToken.toString:()Ljava/lang/String;
     401: invokevirtual #151                // Method org/apache/hadoop/security/authentication/util/Signer.sign:(Ljava/lang/String;)Ljava/lang/String;
     404: astore        13
     406: aload         8
     408: aload         13
     410: aload_0
     411: invokevirtual #152                // Method getCookieDomain:()Ljava/lang/String;
     414: aload_0
     415: invokevirtual #153                // Method getCookiePath:()Ljava/lang/String;
     418: aload         11
     420: invokevirtual #142                // Method org/apache/hadoop/security/authentication/server/AuthenticationToken.getExpires:()J
     423: aload_0
     424: invokevirtual #149                // Method isCookiePersistent:()Z
     427: iload         9
     429: invokestatic  #154                // Method createAuthCookie:(Ljavax/servlet/http/HttpServletResponse;Ljava/lang/String;Ljava/lang/String;Ljava/lang/String;JZZ)V
     432: aload_0
     433: aload_3
     434: aload         7
     436: aload         8
     438: invokevirtual #155                // Method doFilter:(Ljavax/servlet/FilterChain;Ljavax/servlet/http/HttpServletRequest;Ljavax/servlet/http/HttpServletResponse;)V
     441: goto          476
     444: getstatic     #71                 // Field LOG:Lorg/slf4j/Logger;
     447: invokeinterface #127,  1          // InterfaceMethod org/slf4j/Logger.isDebugEnabled:()Z
     452: ifeq          473
     455: getstatic     #71                 // Field LOG:Lorg/slf4j/Logger;
     458: ldc           #156                // String managementOperation returned false for request {}. token: {}
     460: aload_0
     461: aload         7
     463: invokevirtual #129                // Method getRequestURL:(Ljavax/servlet/http/HttpServletRequest;)Ljava/lang/String;
     466: aload         11
     468: invokeinterface #130,  4          // InterfaceMethod org/slf4j/Logger.debug:(Ljava/lang/String;Ljava/lang/Object;Ljava/lang/Object;)V
     473: iconst_0
     474: istore        4
     476: goto          568
     479: astore        10
     481: sipush        403
     484: istore        5
     486: aload         10
     488: astore        6
     490: getstatic     #71                 // Field LOG:Lorg/slf4j/Logger;
     493: invokeinterface #127,  1          // InterfaceMethod org/slf4j/Logger.isDebugEnabled:()Z
     498: ifeq          537
     501: getstatic     #71                 // Field LOG:Lorg/slf4j/Logger;
     504: new           #5                  // class java/lang/StringBuilder
     507: dup
     508: invokespecial #6                  // Method java/lang/StringBuilder."<init>":()V
     511: ldc           #157                // String Authentication exception:
     513: invokevirtual #7                  // Method java/lang/StringBuilder.append:(Ljava/lang/String;)Ljava/lang/StringBuilder;
     516: aload         10
     518: invokevirtual #132                // Method org/apache/hadoop/security/authentication/client/AuthenticationException.getMessage:()Ljava/lang/String;
     521: invokevirtual #7                  // Method java/lang/StringBuilder.append:(Ljava/lang/String;)Ljava/lang/StringBuilder;
     524: invokevirtual #9                  // Method java/lang/StringBuilder.toString:()Ljava/lang/String;
     527: aload         10
     529: invokeinterface #158,  3          // InterfaceMethod org/slf4j/Logger.debug:(Ljava/lang/String;Ljava/lang/Throwable;)V
     534: goto          568
     537: getstatic     #71                 // Field LOG:Lorg/slf4j/Logger;
     540: new           #5                  // class java/lang/StringBuilder
     543: dup
     544: invokespecial #6                  // Method java/lang/StringBuilder."<init>":()V
     547: ldc           #157                // String Authentication exception:
     549: invokevirtual #7                  // Method java/lang/StringBuilder.append:(Ljava/lang/String;)Ljava/lang/StringBuilder;
     552: aload         10
     554: invokevirtual #132                // Method org/apache/hadoop/security/authentication/client/AuthenticationException.getMessage:()Ljava/lang/String;
     557: invokevirtual #7                  // Method java/lang/StringBuilder.append:(Ljava/lang/String;)Ljava/lang/StringBuilder;
     560: invokevirtual #9                  // Method java/lang/StringBuilder.toString:()Ljava/lang/String;
     563: invokeinterface #133,  2          // InterfaceMethod org/slf4j/Logger.warn:(Ljava/lang/String;)V
     568: iload         4
     570: ifeq          671
     573: aload         8
     575: invokeinterface #159,  1          // InterfaceMethod javax/servlet/http/HttpServletResponse.isCommitted:()Z
     580: ifne          671
     583: aload         8
     585: ldc           #10                 // String
     587: aload_0
     588: invokevirtual #152                // Method getCookieDomain:()Ljava/lang/String;
     591: aload_0
     592: invokevirtual #153                // Method getCookiePath:()Ljava/lang/String;
     595: lconst_0
     596: aload_0
     597: invokevirtual #149                // Method isCookiePersistent:()Z
     600: iload         9
     602: invokestatic  #154                // Method createAuthCookie:(Ljavax/servlet/http/HttpServletResponse;Ljava/lang/String;Ljava/lang/String;Ljava/lang/String;JZZ)V
     605: iload         5
     607: sipush        401
     610: if_icmpne     630
     613: aload         8
     615: ldc           #161                // String WWW-Authenticate
     617: invokeinterface #162,  2          // InterfaceMethod javax/servlet/http/HttpServletResponse.containsHeader:(Ljava/lang/String;)Z
     622: ifne          630
     625: sipush        403
     628: istore        5
     630: aload         6
     632: ifnonnull     642
     635: ldc           #163                // String Authentication required
     637: astore        10
     639: goto          649
     642: aload         6
     644: invokevirtual #132                // Method org/apache/hadoop/security/authentication/client/AuthenticationException.getMessage:()Ljava/lang/String;
     647: astore        10
     649: aload         8
     651: iload         5
     653: aload         10
     655: invokeinterface #164,  3          // InterfaceMethod javax/servlet/http/HttpServletResponse.setStatus:(ILjava/lang/String;)V
     660: aload         8
     662: iload         5
     664: aload         10
     666: invokeinterface #165,  3          // InterfaceMethod javax/servlet/http/HttpServletResponse.sendError:(ILjava/lang/String;)V
     671: return
    Exception table:
       from    to  target type
          40    77    80   Class org/apache/hadoop/security/authentication/client/AuthenticationException
          37   476   479   Class org/apache/hadoop/security/authentication/client/AuthenticationException

  protected void doFilter(javax.servlet.FilterChain, javax.servlet.http.HttpServletRequest, javax.servlet.http.HttpServletResponse) throws java.io.IOException, javax.servlet.ServletException;
    Code:
       0: aload_1
       1: aload_2
       2: aload_3
       3: invokeinterface #166,  3          // InterfaceMethod javax/servlet/FilterChain.doFilter:(Ljavax/servlet/ServletRequest;Ljavax/servlet/ServletResponse;)V
       8: return

  public static void createAuthCookie(javax.servlet.http.HttpServletResponse, java.lang.String, java.lang.String, java.lang.String, long, boolean, boolean);
    Code:
       0: new           #5                  // class java/lang/StringBuilder
       3: dup
       4: ldc           #100                // String hadoop.auth
       6: invokespecial #167                // Method java/lang/StringBuilder."<init>":(Ljava/lang/String;)V
       9: ldc           #168                // String =
      11: invokevirtual #7                  // Method java/lang/StringBuilder.append:(Ljava/lang/String;)Ljava/lang/StringBuilder;
      14: astore        8
      16: aload_1
      17: ifnull        44
      20: aload_1
      21: invokevirtual #89                 // Method java/lang/String.length:()I
      24: ifle          44
      27: aload         8
      29: ldc           #169                // String \"
      31: invokevirtual #7                  // Method java/lang/StringBuilder.append:(Ljava/lang/String;)Ljava/lang/StringBuilder;
      34: aload_1
      35: invokevirtual #7                  // Method java/lang/StringBuilder.append:(Ljava/lang/String;)Ljava/lang/StringBuilder;
      38: ldc           #169                // String \"
      40: invokevirtual #7                  // Method java/lang/StringBuilder.append:(Ljava/lang/String;)Ljava/lang/StringBuilder;
      43: pop
      44: aload_3
      45: ifnull        60
      48: aload         8
      50: ldc           #170                // String ; Path=
      52: invokevirtual #7                  // Method java/lang/StringBuilder.append:(Ljava/lang/String;)Ljava/lang/StringBuilder;
      55: aload_3
      56: invokevirtual #7                  // Method java/lang/StringBuilder.append:(Ljava/lang/String;)Ljava/lang/StringBuilder;
      59: pop
      60: aload_2
      61: ifnull        76
      64: aload         8
      66: ldc           #171                // String ; Domain=
      68: invokevirtual #7                  // Method java/lang/StringBuilder.append:(Ljava/lang/String;)Ljava/lang/StringBuilder;
      71: aload_2
      72: invokevirtual #7                  // Method java/lang/StringBuilder.append:(Ljava/lang/String;)Ljava/lang/StringBuilder;
      75: pop
      76: lload         4
      78: lconst_0
      79: lcmp
      80: iflt          141
      83: iload         6
      85: ifeq          141
      88: new           #172                // class java/util/Date
      91: dup
      92: lload         4
      94: invokespecial #173                // Method java/util/Date."<init>":(J)V
      97: astore        9
      99: new           #174                // class java/text/SimpleDateFormat
     102: dup
     103: ldc           #175                // String EEE, dd-MMM-yyyy HH:mm:ss zzz
     105: getstatic     #176                // Field java/util/Locale.US:Ljava/util/Locale;
     108: invokespecial #177                // Method java/text/SimpleDateFormat."<init>":(Ljava/lang/String;Ljava/util/Locale;)V
     111: astore        10
     113: aload         10
     115: ldc           #178                // String GMT
     117: invokestatic  #179                // Method java/util/TimeZone.getTimeZone:(Ljava/lang/String;)Ljava/util/TimeZone;
     120: invokevirtual #180                // Method java/text/SimpleDateFormat.setTimeZone:(Ljava/util/TimeZone;)V
     123: aload         8
     125: ldc           #181                // String ; Expires=
     127: invokevirtual #7                  // Method java/lang/StringBuilder.append:(Ljava/lang/String;)Ljava/lang/StringBuilder;
     130: aload         10
     132: aload         9
     134: invokevirtual #182                // Method java/text/SimpleDateFormat.format:(Ljava/util/Date;)Ljava/lang/String;
     137: invokevirtual #7                  // Method java/lang/StringBuilder.append:(Ljava/lang/String;)Ljava/lang/StringBuilder;
     140: pop
     141: iload         7
     143: ifeq          154
     146: aload         8
     148: ldc           #183                // String ; Secure
     150: invokevirtual #7                  // Method java/lang/StringBuilder.append:(Ljava/lang/String;)Ljava/lang/StringBuilder;
     153: pop
     154: aload         8
     156: ldc           #184                // String ; HttpOnly
     158: invokevirtual #7                  // Method java/lang/StringBuilder.append:(Ljava/lang/String;)Ljava/lang/StringBuilder;
     161: pop
     162: aload_0
     163: ldc           #185                // String Set-Cookie
     165: aload         8
     167: invokevirtual #9                  // Method java/lang/StringBuilder.toString:()Ljava/lang/String;
     170: invokeinterface #186,  3          // InterfaceMethod javax/servlet/http/HttpServletResponse.addHeader:(Ljava/lang/String;Ljava/lang/String;)V
     175: return

  static {};
    Code:
       0: ldc           #1                  // class org/apache/hadoop/security/authentication/server/AuthenticationFilter
       2: invokestatic  #187                // Method org/slf4j/LoggerFactory.getLogger:(Ljava/lang/Class;)Lorg/slf4j/Logger;
       5: putstatic     #71                 // Field LOG:Lorg/slf4j/Logger;
       8: return
}
