Compiled from "NoOpPasswordEncoder.java"
public final class org.springframework.security.crypto.password.NoOpPasswordEncoder implements org.springframework.security.crypto.password.PasswordEncoder {
  private static final org.springframework.security.crypto.password.PasswordEncoder INSTANCE;

  public java.lang.String encode(java.lang.CharSequence);
    Code:
       0: aload_1
       1: invokeinterface #1,  1            // InterfaceMethod java/lang/CharSequence.toString:()Ljava/lang/String;
       6: areturn

  public boolean matches(java.lang.CharSequence, java.lang.String);
    Code:
       0: aload_1
       1: invokeinterface #1,  1            // InterfaceMethod java/lang/CharSequence.toString:()Ljava/lang/String;
       6: aload_2
       7: invokevirtual #2                  // Method java/lang/String.equals:(Ljava/lang/Object;)Z
      10: ireturn

  public static org.springframework.security.crypto.password.PasswordEncoder getInstance();
    Code:
       0: getstatic     #3                  // Field INSTANCE:Lorg/springframework/security/crypto/password/PasswordEncoder;
       3: areturn

  private org.springframework.security.crypto.password.NoOpPasswordEncoder();
    Code:
       0: aload_0
       1: invokespecial #4                  // Method java/lang/Object."<init>":()V
       4: return

  static {};
    Code:
       0: new           #5                  // class org/springframework/security/crypto/password/NoOpPasswordEncoder
       3: dup
       4: invokespecial #6                  // Method "<init>":()V
       7: putstatic     #3                  // Field INSTANCE:Lorg/springframework/security/crypto/password/PasswordEncoder;
      10: return
}
