Compiled from "KeyComparatorLinkedHashMap.java"
class org.glassfish.jersey.internal.util.collection.KeyComparatorLinkedHashMap$Entry<K, V> extends org.glassfish.jersey.internal.util.collection.KeyComparatorHashMap$Entry<K, V> {
  org.glassfish.jersey.internal.util.collection.KeyComparatorLinkedHashMap$Entry<K, V> before;

  org.glassfish.jersey.internal.util.collection.KeyComparatorLinkedHashMap$Entry<K, V> after;

  org.glassfish.jersey.internal.util.collection.KeyComparatorLinkedHashMap$Entry(int, K, V, org.glassfish.jersey.internal.util.collection.KeyComparatorHashMap$Entry<K, V>);
    Code:
       0: aload_0
       1: iload_1
       2: aload_2
       3: aload_3
       4: aload         4
       6: invokespecial #2                  // Method org/glassfish/jersey/internal/util/collection/KeyComparatorHashMap$Entry."<init>":(ILjava/lang/Object;Ljava/lang/Object;Lorg/glassfish/jersey/internal/util/collection/KeyComparatorHashMap$Entry;)V
       9: return

  private void remove();
    Code:
       0: aload_0
       1: getfield      #3                  // Field before:Lorg/glassfish/jersey/internal/util/collection/KeyComparatorLinkedHashMap$Entry;
       4: aload_0
       5: getfield      #4                  // Field after:Lorg/glassfish/jersey/internal/util/collection/KeyComparatorLinkedHashMap$Entry;
       8: putfield      #4                  // Field after:Lorg/glassfish/jersey/internal/util/collection/KeyComparatorLinkedHashMap$Entry;
      11: aload_0
      12: getfield      #4                  // Field after:Lorg/glassfish/jersey/internal/util/collection/KeyComparatorLinkedHashMap$Entry;
      15: aload_0
      16: getfield      #3                  // Field before:Lorg/glassfish/jersey/internal/util/collection/KeyComparatorLinkedHashMap$Entry;
      19: putfield      #3                  // Field before:Lorg/glassfish/jersey/internal/util/collection/KeyComparatorLinkedHashMap$Entry;
      22: return

  private void addBefore(org.glassfish.jersey.internal.util.collection.KeyComparatorLinkedHashMap$Entry<K, V>);
    Code:
       0: aload_0
       1: aload_1
       2: putfield      #4                  // Field after:Lorg/glassfish/jersey/internal/util/collection/KeyComparatorLinkedHashMap$Entry;
       5: aload_0
       6: aload_1
       7: getfield      #3                  // Field before:Lorg/glassfish/jersey/internal/util/collection/KeyComparatorLinkedHashMap$Entry;
      10: putfield      #3                  // Field before:Lorg/glassfish/jersey/internal/util/collection/KeyComparatorLinkedHashMap$Entry;
      13: aload_0
      14: getfield      #3                  // Field before:Lorg/glassfish/jersey/internal/util/collection/KeyComparatorLinkedHashMap$Entry;
      17: aload_0
      18: putfield      #4                  // Field after:Lorg/glassfish/jersey/internal/util/collection/KeyComparatorLinkedHashMap$Entry;
      21: aload_0
      22: getfield      #4                  // Field after:Lorg/glassfish/jersey/internal/util/collection/KeyComparatorLinkedHashMap$Entry;
      25: aload_0
      26: putfield      #3                  // Field before:Lorg/glassfish/jersey/internal/util/collection/KeyComparatorLinkedHashMap$Entry;
      29: return

  void recordAccess(org.glassfish.jersey.internal.util.collection.KeyComparatorHashMap<K, V>);
    Code:
       0: aload_1
       1: checkcast     #5                  // class org/glassfish/jersey/internal/util/collection/KeyComparatorLinkedHashMap
       4: astore_2
       5: aload_2
       6: invokestatic  #6                  // Method org/glassfish/jersey/internal/util/collection/KeyComparatorLinkedHashMap.access$000:(Lorg/glassfish/jersey/internal/util/collection/KeyComparatorLinkedHashMap;)Z
       9: ifeq          34
      12: aload_2
      13: dup
      14: getfield      #7                  // Field org/glassfish/jersey/internal/util/collection/KeyComparatorLinkedHashMap.modCount:I
      17: iconst_1
      18: iadd
      19: putfield      #7                  // Field org/glassfish/jersey/internal/util/collection/KeyComparatorLinkedHashMap.modCount:I
      22: aload_0
      23: invokespecial #8                  // Method remove:()V
      26: aload_0
      27: aload_2
      28: invokestatic  #9                  // Method org/glassfish/jersey/internal/util/collection/KeyComparatorLinkedHashMap.access$100:(Lorg/glassfish/jersey/internal/util/collection/KeyComparatorLinkedHashMap;)Lorg/glassfish/jersey/internal/util/collection/KeyComparatorLinkedHashMap$Entry;
      31: invokespecial #1                  // Method addBefore:(Lorg/glassfish/jersey/internal/util/collection/KeyComparatorLinkedHashMap$Entry;)V
      34: return

  void recordRemoval(org.glassfish.jersey.internal.util.collection.KeyComparatorHashMap<K, V>);
    Code:
       0: aload_0
       1: invokespecial #8                  // Method remove:()V
       4: return

  public boolean equals(java.lang.Object);
    Code:
       0: aload_0
       1: aload_1
       2: invokespecial #10                 // Method org/glassfish/jersey/internal/util/collection/KeyComparatorHashMap$Entry.equals:(Ljava/lang/Object;)Z
       5: ireturn

  public int hashCode();
    Code:
       0: aload_0
       1: invokespecial #11                 // Method org/glassfish/jersey/internal/util/collection/KeyComparatorHashMap$Entry.hashCode:()I
       4: ireturn

  static void access$600(org.glassfish.jersey.internal.util.collection.KeyComparatorLinkedHashMap$Entry, org.glassfish.jersey.internal.util.collection.KeyComparatorLinkedHashMap$Entry);
    Code:
       0: aload_0
       1: aload_1
       2: invokespecial #1                  // Method addBefore:(Lorg/glassfish/jersey/internal/util/collection/KeyComparatorLinkedHashMap$Entry;)V
       5: return
}
