Compiled from "Values.java"
public final class org.glassfish.jersey.internal.util.collection.Values {
  private static final org.glassfish.jersey.internal.util.collection.LazyValue EMPTY;

  private static final org.glassfish.jersey.internal.util.collection.LazyUnsafeValue EMPTY_UNSAFE;

  private org.glassfish.jersey.internal.util.collection.Values();
    Code:
       0: aload_0
       1: invokespecial #1                  // Method java/lang/Object."<init>":()V
       4: return

  public static <T> org.glassfish.jersey.internal.util.collection.Value<T> empty();
    Code:
       0: getstatic     #2                  // Field EMPTY:Lorg/glassfish/jersey/internal/util/collection/LazyValue;
       3: areturn

  public static <T, E extends java.lang.Throwable> org.glassfish.jersey.internal.util.collection.UnsafeValue<T, E> emptyUnsafe();
    Code:
       0: getstatic     #3                  // Field EMPTY_UNSAFE:Lorg/glassfish/jersey/internal/util/collection/LazyUnsafeValue;
       3: areturn

  public static <T> org.glassfish.jersey.internal.util.collection.Value<T> of(T);
    Code:
       0: aload_0
       1: ifnonnull     10
       4: invokestatic  #4                  // Method empty:()Lorg/glassfish/jersey/internal/util/collection/Value;
       7: goto          18
      10: new           #5                  // class org/glassfish/jersey/internal/util/collection/Values$InstanceValue
      13: dup
      14: aload_0
      15: invokespecial #6                  // Method org/glassfish/jersey/internal/util/collection/Values$InstanceValue."<init>":(Ljava/lang/Object;)V
      18: areturn

  public static <T, E extends java.lang.Throwable> org.glassfish.jersey.internal.util.collection.UnsafeValue<T, E> unsafe(T);
    Code:
       0: aload_0
       1: ifnonnull     10
       4: invokestatic  #7                  // Method emptyUnsafe:()Lorg/glassfish/jersey/internal/util/collection/UnsafeValue;
       7: goto          18
      10: new           #8                  // class org/glassfish/jersey/internal/util/collection/Values$InstanceUnsafeValue
      13: dup
      14: aload_0
      15: invokespecial #9                  // Method org/glassfish/jersey/internal/util/collection/Values$InstanceUnsafeValue."<init>":(Ljava/lang/Object;)V
      18: areturn

  public static <T, E extends java.lang.Throwable> org.glassfish.jersey.internal.util.collection.UnsafeValue<T, E> throwing(E);
    Code:
       0: aload_0
       1: ifnonnull     14
       4: new           #10                 // class java/lang/NullPointerException
       7: dup
       8: ldc           #11                 // String Supplied throwable
      10: invokespecial #12                 // Method java/lang/NullPointerException."<init>":(Ljava/lang/String;)V
      13: athrow
      14: new           #13                 // class org/glassfish/jersey/internal/util/collection/Values$ExceptionValue
      17: dup
      18: aload_0
      19: invokespecial #14                 // Method org/glassfish/jersey/internal/util/collection/Values$ExceptionValue."<init>":(Ljava/lang/Throwable;)V
      22: areturn

  public static <T> org.glassfish.jersey.internal.util.collection.LazyValue<T> lazy(org.glassfish.jersey.internal.util.collection.Value<T>);
    Code:
       0: aload_0
       1: ifnonnull     10
       4: getstatic     #2                  // Field EMPTY:Lorg/glassfish/jersey/internal/util/collection/LazyValue;
       7: goto          18
      10: new           #15                 // class org/glassfish/jersey/internal/util/collection/Values$LazyValueImpl
      13: dup
      14: aload_0
      15: invokespecial #16                 // Method org/glassfish/jersey/internal/util/collection/Values$LazyValueImpl."<init>":(Lorg/glassfish/jersey/internal/util/collection/Value;)V
      18: areturn

  public static <T> org.glassfish.jersey.internal.util.collection.Value<T> eager(org.glassfish.jersey.internal.util.collection.Value<T>);
    Code:
       0: aload_0
       1: ifnonnull     10
       4: invokestatic  #4                  // Method empty:()Lorg/glassfish/jersey/internal/util/collection/Value;
       7: goto          19
      10: new           #17                 // class org/glassfish/jersey/internal/util/collection/Values$EagerValue
      13: dup
      14: aload_0
      15: aconst_null
      16: invokespecial #18                 // Method org/glassfish/jersey/internal/util/collection/Values$EagerValue."<init>":(Lorg/glassfish/jersey/internal/util/collection/Value;Lorg/glassfish/jersey/internal/util/collection/Values$1;)V
      19: areturn

  public static <T, E extends java.lang.Throwable> org.glassfish.jersey.internal.util.collection.LazyUnsafeValue<T, E> lazy(org.glassfish.jersey.internal.util.collection.UnsafeValue<T, E>);
    Code:
       0: aload_0
       1: ifnonnull     10
       4: getstatic     #3                  // Field EMPTY_UNSAFE:Lorg/glassfish/jersey/internal/util/collection/LazyUnsafeValue;
       7: goto          18
      10: new           #19                 // class org/glassfish/jersey/internal/util/collection/Values$LazyUnsafeValueImpl
      13: dup
      14: aload_0
      15: invokespecial #20                 // Method org/glassfish/jersey/internal/util/collection/Values$LazyUnsafeValueImpl."<init>":(Lorg/glassfish/jersey/internal/util/collection/UnsafeValue;)V
      18: areturn

  static {};
    Code:
       0: new           #21                 // class org/glassfish/jersey/internal/util/collection/Values$1
       3: dup
       4: invokespecial #22                 // Method org/glassfish/jersey/internal/util/collection/Values$1."<init>":()V
       7: putstatic     #2                  // Field EMPTY:Lorg/glassfish/jersey/internal/util/collection/LazyValue;
      10: new           #23                 // class org/glassfish/jersey/internal/util/collection/Values$2
      13: dup
      14: invokespecial #24                 // Method org/glassfish/jersey/internal/util/collection/Values$2."<init>":()V
      17: putstatic     #3                  // Field EMPTY_UNSAFE:Lorg/glassfish/jersey/internal/util/collection/LazyUnsafeValue;
      20: return
}
