Compiled from "CanaryStatus.scala"
public interface zio.aws.synthetics.model.CanaryStatus$ReadOnly {
  public static zio.aws.synthetics.model.CanaryStatus asEditable$(zio.aws.synthetics.model.CanaryStatus$ReadOnly);
    Code:
       0: aload_0
       1: invokespecial #20                 // InterfaceMethod asEditable:()Lzio/aws/synthetics/model/CanaryStatus;
       4: areturn

  public default zio.aws.synthetics.model.CanaryStatus asEditable();
    Code:
       0: new           #12                 // class zio/aws/synthetics/model/CanaryStatus
       3: dup
       4: aload_0
       5: invokeinterface #25,  1           // InterfaceMethod state:()Lscala/Option;
      10: invokedynamic #48,  0             // InvokeDynamic #0:apply:()Lscala/Function1;
      15: invokevirtual #54                 // Method scala/Option.map:(Lscala/Function1;)Lscala/Option;
      18: aload_0
      19: invokeinterface #57,  1           // InterfaceMethod stateReason:()Lscala/Option;
      24: invokedynamic #64,  0             // InvokeDynamic #1:apply:()Lscala/Function1;
      29: invokevirtual #54                 // Method scala/Option.map:(Lscala/Function1;)Lscala/Option;
      32: aload_0
      33: invokeinterface #67,  1           // InterfaceMethod stateReasonCode:()Lscala/Option;
      38: invokedynamic #74,  0             // InvokeDynamic #2:apply:()Lscala/Function1;
      43: invokevirtual #54                 // Method scala/Option.map:(Lscala/Function1;)Lscala/Option;
      46: invokespecial #78                 // Method zio/aws/synthetics/model/CanaryStatus."<init>":(Lscala/Option;Lscala/Option;Lscala/Option;)V
      49: areturn

  public abstract scala.Option<zio.aws.synthetics.model.CanaryState> state();

  public abstract scala.Option<java.lang.String> stateReason();

  public abstract scala.Option<zio.aws.synthetics.model.CanaryStateReasonCode> stateReasonCode();

  public static zio.ZIO getState$(zio.aws.synthetics.model.CanaryStatus$ReadOnly);
    Code:
       0: aload_0
       1: invokespecial #88                 // InterfaceMethod getState:()Lzio/ZIO;
       4: areturn

  public default zio.ZIO<java.lang.Object, zio.aws.core.AwsError, zio.aws.synthetics.model.CanaryState> getState();
    Code:
       0: getstatic     #95                 // Field zio/aws/core/AwsError$.MODULE$:Lzio/aws/core/AwsError$;
       3: ldc           #96                 // String state
       5: aload_0
       6: invokedynamic #107,  0            // InvokeDynamic #3:apply:(Lzio/aws/synthetics/model/CanaryStatus$ReadOnly;)Lscala/Function0;
      11: invokevirtual #111                // Method zio/aws/core/AwsError$.unwrapOptionField:(Ljava/lang/String;Lscala/Function0;)Lzio/ZIO;
      14: areturn

  public static zio.ZIO getStateReason$(zio.aws.synthetics.model.CanaryStatus$ReadOnly);
    Code:
       0: aload_0
       1: invokespecial #115                // InterfaceMethod getStateReason:()Lzio/ZIO;
       4: areturn

  public default zio.ZIO<java.lang.Object, zio.aws.core.AwsError, java.lang.String> getStateReason();
    Code:
       0: getstatic     #95                 // Field zio/aws/core/AwsError$.MODULE$:Lzio/aws/core/AwsError$;
       3: ldc           #117                // String stateReason
       5: aload_0
       6: invokedynamic #122,  0            // InvokeDynamic #4:apply:(Lzio/aws/synthetics/model/CanaryStatus$ReadOnly;)Lscala/Function0;
      11: invokevirtual #111                // Method zio/aws/core/AwsError$.unwrapOptionField:(Ljava/lang/String;Lscala/Function0;)Lzio/ZIO;
      14: areturn

  public static zio.ZIO getStateReasonCode$(zio.aws.synthetics.model.CanaryStatus$ReadOnly);
    Code:
       0: aload_0
       1: invokespecial #126                // InterfaceMethod getStateReasonCode:()Lzio/ZIO;
       4: areturn

  public default zio.ZIO<java.lang.Object, zio.aws.core.AwsError, zio.aws.synthetics.model.CanaryStateReasonCode> getStateReasonCode();
    Code:
       0: getstatic     #95                 // Field zio/aws/core/AwsError$.MODULE$:Lzio/aws/core/AwsError$;
       3: ldc           #128                // String stateReasonCode
       5: aload_0
       6: invokedynamic #133,  0            // InvokeDynamic #5:apply:(Lzio/aws/synthetics/model/CanaryStatus$ReadOnly;)Lscala/Function0;
      11: invokevirtual #111                // Method zio/aws/core/AwsError$.unwrapOptionField:(Ljava/lang/String;Lscala/Function0;)Lzio/ZIO;
      14: areturn

  public static zio.aws.synthetics.model.CanaryState $anonfun$asEditable$1(zio.aws.synthetics.model.CanaryState);
    Code:
       0: aload_0
       1: areturn

  public static java.lang.String $anonfun$asEditable$2(java.lang.String);
    Code:
       0: aload_0
       1: areturn

  public static zio.aws.synthetics.model.CanaryStateReasonCode $anonfun$asEditable$3(zio.aws.synthetics.model.CanaryStateReasonCode);
    Code:
       0: aload_0
       1: areturn

  public static scala.Option $anonfun$getState$1(zio.aws.synthetics.model.CanaryStatus$ReadOnly);
    Code:
       0: aload_0
       1: invokeinterface #25,  1           // InterfaceMethod state:()Lscala/Option;
       6: areturn

  public static scala.Option $anonfun$getStateReason$1(zio.aws.synthetics.model.CanaryStatus$ReadOnly);
    Code:
       0: aload_0
       1: invokeinterface #57,  1           // InterfaceMethod stateReason:()Lscala/Option;
       6: areturn

  public static scala.Option $anonfun$getStateReasonCode$1(zio.aws.synthetics.model.CanaryStatus$ReadOnly);
    Code:
       0: aload_0
       1: invokeinterface #67,  1           // InterfaceMethod stateReasonCode:()Lscala/Option;
       6: areturn

  public static void $init$(zio.aws.synthetics.model.CanaryStatus$ReadOnly);
    Code:
       0: return

  private static java.lang.Object $deserializeLambda$(java.lang.invoke.SerializedLambda);
    Code:
       0: aload_0
       1: invokedynamic #151,  0            // InvokeDynamic #6:lambdaDeserialize:(Ljava/lang/invoke/SerializedLambda;)Ljava/lang/Object;
       6: areturn
}
