Compiled from "Canary.scala"
public interface zio.aws.synthetics.model.Canary$ReadOnly {
  public static zio.aws.synthetics.model.Canary asEditable$(zio.aws.synthetics.model.Canary$ReadOnly);
    Code:
       0: aload_0
       1: invokespecial #52                 // InterfaceMethod asEditable:()Lzio/aws/synthetics/model/Canary;
       4: areturn

  public default zio.aws.synthetics.model.Canary asEditable();
    Code:
       0: new           #17                 // class zio/aws/synthetics/model/Canary
       3: dup
       4: aload_0
       5: invokeinterface #57,  1           // InterfaceMethod id:()Lscala/Option;
      10: invokedynamic #80,  0             // InvokeDynamic #0:apply:()Lscala/Function1;
      15: invokevirtual #86                 // Method scala/Option.map:(Lscala/Function1;)Lscala/Option;
      18: aload_0
      19: invokeinterface #89,  1           // InterfaceMethod name:()Lscala/Option;
      24: invokedynamic #94,  0             // InvokeDynamic #1:apply:()Lscala/Function1;
      29: invokevirtual #86                 // Method scala/Option.map:(Lscala/Function1;)Lscala/Option;
      32: aload_0
      33: invokeinterface #97,  1           // InterfaceMethod code:()Lscala/Option;
      38: invokedynamic #104,  0            // InvokeDynamic #2:apply:()Lscala/Function1;
      43: invokevirtual #86                 // Method scala/Option.map:(Lscala/Function1;)Lscala/Option;
      46: aload_0
      47: invokeinterface #107,  1          // InterfaceMethod executionRoleArn:()Lscala/Option;
      52: invokedynamic #112,  0            // InvokeDynamic #3:apply:()Lscala/Function1;
      57: invokevirtual #86                 // Method scala/Option.map:(Lscala/Function1;)Lscala/Option;
      60: aload_0
      61: invokeinterface #115,  1          // InterfaceMethod schedule:()Lscala/Option;
      66: invokedynamic #122,  0            // InvokeDynamic #4:apply:()Lscala/Function1;
      71: invokevirtual #86                 // Method scala/Option.map:(Lscala/Function1;)Lscala/Option;
      74: aload_0
      75: invokeinterface #125,  1          // InterfaceMethod runConfig:()Lscala/Option;
      80: invokedynamic #132,  0            // InvokeDynamic #5:apply:()Lscala/Function1;
      85: invokevirtual #86                 // Method scala/Option.map:(Lscala/Function1;)Lscala/Option;
      88: aload_0
      89: invokeinterface #135,  1          // InterfaceMethod successRetentionPeriodInDays:()Lscala/Option;
      94: invokedynamic #146,  0            // InvokeDynamic #6:apply$mcII$sp:()Lscala/runtime/java8/JFunction1$mcII$sp;
      99: invokevirtual #86                 // Method scala/Option.map:(Lscala/Function1;)Lscala/Option;
     102: aload_0
     103: invokeinterface #149,  1          // InterfaceMethod failureRetentionPeriodInDays:()Lscala/Option;
     108: invokedynamic #154,  0            // InvokeDynamic #7:apply$mcII$sp:()Lscala/runtime/java8/JFunction1$mcII$sp;
     113: invokevirtual #86                 // Method scala/Option.map:(Lscala/Function1;)Lscala/Option;
     116: aload_0
     117: invokeinterface #157,  1          // InterfaceMethod status:()Lscala/Option;
     122: invokedynamic #164,  0            // InvokeDynamic #8:apply:()Lscala/Function1;
     127: invokevirtual #86                 // Method scala/Option.map:(Lscala/Function1;)Lscala/Option;
     130: aload_0
     131: invokeinterface #167,  1          // InterfaceMethod timeline:()Lscala/Option;
     136: invokedynamic #174,  0            // InvokeDynamic #9:apply:()Lscala/Function1;
     141: invokevirtual #86                 // Method scala/Option.map:(Lscala/Function1;)Lscala/Option;
     144: aload_0
     145: invokeinterface #177,  1          // InterfaceMethod artifactS3Location:()Lscala/Option;
     150: invokedynamic #182,  0            // InvokeDynamic #10:apply:()Lscala/Function1;
     155: invokevirtual #86                 // Method scala/Option.map:(Lscala/Function1;)Lscala/Option;
     158: aload_0
     159: invokeinterface #185,  1          // InterfaceMethod engineArn:()Lscala/Option;
     164: invokedynamic #190,  0            // InvokeDynamic #11:apply:()Lscala/Function1;
     169: invokevirtual #86                 // Method scala/Option.map:(Lscala/Function1;)Lscala/Option;
     172: aload_0
     173: invokeinterface #193,  1          // InterfaceMethod runtimeVersion:()Lscala/Option;
     178: invokedynamic #198,  0            // InvokeDynamic #12:apply:()Lscala/Function1;
     183: invokevirtual #86                 // Method scala/Option.map:(Lscala/Function1;)Lscala/Option;
     186: aload_0
     187: invokeinterface #201,  1          // InterfaceMethod vpcConfig:()Lscala/Option;
     192: invokedynamic #208,  0            // InvokeDynamic #13:apply:()Lscala/Function1;
     197: invokevirtual #86                 // Method scala/Option.map:(Lscala/Function1;)Lscala/Option;
     200: aload_0
     201: invokeinterface #211,  1          // InterfaceMethod visualReference:()Lscala/Option;
     206: invokedynamic #218,  0            // InvokeDynamic #14:apply:()Lscala/Function1;
     211: invokevirtual #86                 // Method scala/Option.map:(Lscala/Function1;)Lscala/Option;
     214: aload_0
     215: invokeinterface #221,  1          // InterfaceMethod tags:()Lscala/Option;
     220: invokedynamic #228,  0            // InvokeDynamic #15:apply:()Lscala/Function1;
     225: invokevirtual #86                 // Method scala/Option.map:(Lscala/Function1;)Lscala/Option;
     228: aload_0
     229: invokeinterface #231,  1          // InterfaceMethod artifactConfig:()Lscala/Option;
     234: invokedynamic #238,  0            // InvokeDynamic #16:apply:()Lscala/Function1;
     239: invokevirtual #86                 // Method scala/Option.map:(Lscala/Function1;)Lscala/Option;
     242: invokespecial #242                // Method zio/aws/synthetics/model/Canary."<init>":(Lscala/Option;Lscala/Option;Lscala/Option;Lscala/Option;Lscala/Option;Lscala/Option;Lscala/Option;Lscala/Option;Lscala/Option;Lscala/Option;Lscala/Option;Lscala/Option;Lscala/Option;Lscala/Option;Lscala/Option;Lscala/Option;Lscala/Option;)V
     245: areturn

  public abstract scala.Option<java.lang.String> id();

  public abstract scala.Option<java.lang.String> name();

  public abstract scala.Option<zio.aws.synthetics.model.CanaryCodeOutput$ReadOnly> code();

  public abstract scala.Option<java.lang.String> executionRoleArn();

  public abstract scala.Option<zio.aws.synthetics.model.CanaryScheduleOutput$ReadOnly> schedule();

  public abstract scala.Option<zio.aws.synthetics.model.CanaryRunConfigOutput$ReadOnly> runConfig();

  public abstract scala.Option<java.lang.Object> successRetentionPeriodInDays();

  public abstract scala.Option<java.lang.Object> failureRetentionPeriodInDays();

  public abstract scala.Option<zio.aws.synthetics.model.CanaryStatus$ReadOnly> status();

  public abstract scala.Option<zio.aws.synthetics.model.CanaryTimeline$ReadOnly> timeline();

  public abstract scala.Option<java.lang.String> artifactS3Location();

  public abstract scala.Option<java.lang.String> engineArn();

  public abstract scala.Option<java.lang.String> runtimeVersion();

  public abstract scala.Option<zio.aws.synthetics.model.VpcConfigOutput$ReadOnly> vpcConfig();

  public abstract scala.Option<zio.aws.synthetics.model.VisualReferenceOutput$ReadOnly> visualReference();

  public abstract scala.Option<scala.collection.immutable.Map<java.lang.String, java.lang.String>> tags();

  public abstract scala.Option<zio.aws.synthetics.model.ArtifactConfigOutput$ReadOnly> artifactConfig();

  public static zio.ZIO getId$(zio.aws.synthetics.model.Canary$ReadOnly);
    Code:
       0: aload_0
       1: invokespecial #260                // InterfaceMethod getId:()Lzio/ZIO;
       4: areturn

  public default zio.ZIO<java.lang.Object, zio.aws.core.AwsError, java.lang.String> getId();
    Code:
       0: getstatic     #267                // Field zio/aws/core/AwsError$.MODULE$:Lzio/aws/core/AwsError$;
       3: ldc_w         #268                // String id
       6: aload_0
       7: invokedynamic #279,  0            // InvokeDynamic #17:apply:(Lzio/aws/synthetics/model/Canary$ReadOnly;)Lscala/Function0;
      12: invokevirtual #283                // Method zio/aws/core/AwsError$.unwrapOptionField:(Ljava/lang/String;Lscala/Function0;)Lzio/ZIO;
      15: areturn

  public static zio.ZIO getName$(zio.aws.synthetics.model.Canary$ReadOnly);
    Code:
       0: aload_0
       1: invokespecial #287                // InterfaceMethod getName:()Lzio/ZIO;
       4: areturn

  public default zio.ZIO<java.lang.Object, zio.aws.core.AwsError, java.lang.String> getName();
    Code:
       0: getstatic     #267                // Field zio/aws/core/AwsError$.MODULE$:Lzio/aws/core/AwsError$;
       3: ldc_w         #288                // String name
       6: aload_0
       7: invokedynamic #293,  0            // InvokeDynamic #18:apply:(Lzio/aws/synthetics/model/Canary$ReadOnly;)Lscala/Function0;
      12: invokevirtual #283                // Method zio/aws/core/AwsError$.unwrapOptionField:(Ljava/lang/String;Lscala/Function0;)Lzio/ZIO;
      15: areturn

  public static zio.ZIO getCode$(zio.aws.synthetics.model.Canary$ReadOnly);
    Code:
       0: aload_0
       1: invokespecial #297                // InterfaceMethod getCode:()Lzio/ZIO;
       4: areturn

  public default zio.ZIO<java.lang.Object, zio.aws.core.AwsError, zio.aws.synthetics.model.CanaryCodeOutput$ReadOnly> getCode();
    Code:
       0: getstatic     #267                // Field zio/aws/core/AwsError$.MODULE$:Lzio/aws/core/AwsError$;
       3: ldc_w         #299                // String code
       6: aload_0
       7: invokedynamic #304,  0            // InvokeDynamic #19:apply:(Lzio/aws/synthetics/model/Canary$ReadOnly;)Lscala/Function0;
      12: invokevirtual #283                // Method zio/aws/core/AwsError$.unwrapOptionField:(Ljava/lang/String;Lscala/Function0;)Lzio/ZIO;
      15: areturn

  public static zio.ZIO getExecutionRoleArn$(zio.aws.synthetics.model.Canary$ReadOnly);
    Code:
       0: aload_0
       1: invokespecial #308                // InterfaceMethod getExecutionRoleArn:()Lzio/ZIO;
       4: areturn

  public default zio.ZIO<java.lang.Object, zio.aws.core.AwsError, java.lang.String> getExecutionRoleArn();
    Code:
       0: getstatic     #267                // Field zio/aws/core/AwsError$.MODULE$:Lzio/aws/core/AwsError$;
       3: ldc_w         #309                // String executionRoleArn
       6: aload_0
       7: invokedynamic #314,  0            // InvokeDynamic #20:apply:(Lzio/aws/synthetics/model/Canary$ReadOnly;)Lscala/Function0;
      12: invokevirtual #283                // Method zio/aws/core/AwsError$.unwrapOptionField:(Ljava/lang/String;Lscala/Function0;)Lzio/ZIO;
      15: areturn

  public static zio.ZIO getSchedule$(zio.aws.synthetics.model.Canary$ReadOnly);
    Code:
       0: aload_0
       1: invokespecial #318                // InterfaceMethod getSchedule:()Lzio/ZIO;
       4: areturn

  public default zio.ZIO<java.lang.Object, zio.aws.core.AwsError, zio.aws.synthetics.model.CanaryScheduleOutput$ReadOnly> getSchedule();
    Code:
       0: getstatic     #267                // Field zio/aws/core/AwsError$.MODULE$:Lzio/aws/core/AwsError$;
       3: ldc_w         #320                // String schedule
       6: aload_0
       7: invokedynamic #325,  0            // InvokeDynamic #21:apply:(Lzio/aws/synthetics/model/Canary$ReadOnly;)Lscala/Function0;
      12: invokevirtual #283                // Method zio/aws/core/AwsError$.unwrapOptionField:(Ljava/lang/String;Lscala/Function0;)Lzio/ZIO;
      15: areturn

  public static zio.ZIO getRunConfig$(zio.aws.synthetics.model.Canary$ReadOnly);
    Code:
       0: aload_0
       1: invokespecial #329                // InterfaceMethod getRunConfig:()Lzio/ZIO;
       4: areturn

  public default zio.ZIO<java.lang.Object, zio.aws.core.AwsError, zio.aws.synthetics.model.CanaryRunConfigOutput$ReadOnly> getRunConfig();
    Code:
       0: getstatic     #267                // Field zio/aws/core/AwsError$.MODULE$:Lzio/aws/core/AwsError$;
       3: ldc_w         #331                // String runConfig
       6: aload_0
       7: invokedynamic #336,  0            // InvokeDynamic #22:apply:(Lzio/aws/synthetics/model/Canary$ReadOnly;)Lscala/Function0;
      12: invokevirtual #283                // Method zio/aws/core/AwsError$.unwrapOptionField:(Ljava/lang/String;Lscala/Function0;)Lzio/ZIO;
      15: areturn

  public static zio.ZIO getSuccessRetentionPeriodInDays$(zio.aws.synthetics.model.Canary$ReadOnly);
    Code:
       0: aload_0
       1: invokespecial #340                // InterfaceMethod getSuccessRetentionPeriodInDays:()Lzio/ZIO;
       4: areturn

  public default zio.ZIO<java.lang.Object, zio.aws.core.AwsError, java.lang.Object> getSuccessRetentionPeriodInDays();
    Code:
       0: getstatic     #267                // Field zio/aws/core/AwsError$.MODULE$:Lzio/aws/core/AwsError$;
       3: ldc_w         #342                // String successRetentionPeriodInDays
       6: aload_0
       7: invokedynamic #347,  0            // InvokeDynamic #23:apply:(Lzio/aws/synthetics/model/Canary$ReadOnly;)Lscala/Function0;
      12: invokevirtual #283                // Method zio/aws/core/AwsError$.unwrapOptionField:(Ljava/lang/String;Lscala/Function0;)Lzio/ZIO;
      15: areturn

  public static zio.ZIO getFailureRetentionPeriodInDays$(zio.aws.synthetics.model.Canary$ReadOnly);
    Code:
       0: aload_0
       1: invokespecial #351                // InterfaceMethod getFailureRetentionPeriodInDays:()Lzio/ZIO;
       4: areturn

  public default zio.ZIO<java.lang.Object, zio.aws.core.AwsError, java.lang.Object> getFailureRetentionPeriodInDays();
    Code:
       0: getstatic     #267                // Field zio/aws/core/AwsError$.MODULE$:Lzio/aws/core/AwsError$;
       3: ldc_w         #352                // String failureRetentionPeriodInDays
       6: aload_0
       7: invokedynamic #357,  0            // InvokeDynamic #24:apply:(Lzio/aws/synthetics/model/Canary$ReadOnly;)Lscala/Function0;
      12: invokevirtual #283                // Method zio/aws/core/AwsError$.unwrapOptionField:(Ljava/lang/String;Lscala/Function0;)Lzio/ZIO;
      15: areturn

  public static zio.ZIO getStatus$(zio.aws.synthetics.model.Canary$ReadOnly);
    Code:
       0: aload_0
       1: invokespecial #361                // InterfaceMethod getStatus:()Lzio/ZIO;
       4: areturn

  public default zio.ZIO<java.lang.Object, zio.aws.core.AwsError, zio.aws.synthetics.model.CanaryStatus$ReadOnly> getStatus();
    Code:
       0: getstatic     #267                // Field zio/aws/core/AwsError$.MODULE$:Lzio/aws/core/AwsError$;
       3: ldc_w         #363                // String status
       6: aload_0
       7: invokedynamic #368,  0            // InvokeDynamic #25:apply:(Lzio/aws/synthetics/model/Canary$ReadOnly;)Lscala/Function0;
      12: invokevirtual #283                // Method zio/aws/core/AwsError$.unwrapOptionField:(Ljava/lang/String;Lscala/Function0;)Lzio/ZIO;
      15: areturn

  public static zio.ZIO getTimeline$(zio.aws.synthetics.model.Canary$ReadOnly);
    Code:
       0: aload_0
       1: invokespecial #372                // InterfaceMethod getTimeline:()Lzio/ZIO;
       4: areturn

  public default zio.ZIO<java.lang.Object, zio.aws.core.AwsError, zio.aws.synthetics.model.CanaryTimeline$ReadOnly> getTimeline();
    Code:
       0: getstatic     #267                // Field zio/aws/core/AwsError$.MODULE$:Lzio/aws/core/AwsError$;
       3: ldc_w         #374                // String timeline
       6: aload_0
       7: invokedynamic #379,  0            // InvokeDynamic #26:apply:(Lzio/aws/synthetics/model/Canary$ReadOnly;)Lscala/Function0;
      12: invokevirtual #283                // Method zio/aws/core/AwsError$.unwrapOptionField:(Ljava/lang/String;Lscala/Function0;)Lzio/ZIO;
      15: areturn

  public static zio.ZIO getArtifactS3Location$(zio.aws.synthetics.model.Canary$ReadOnly);
    Code:
       0: aload_0
       1: invokespecial #383                // InterfaceMethod getArtifactS3Location:()Lzio/ZIO;
       4: areturn

  public default zio.ZIO<java.lang.Object, zio.aws.core.AwsError, java.lang.String> getArtifactS3Location();
    Code:
       0: getstatic     #267                // Field zio/aws/core/AwsError$.MODULE$:Lzio/aws/core/AwsError$;
       3: ldc_w         #384                // String artifactS3Location
       6: aload_0
       7: invokedynamic #389,  0            // InvokeDynamic #27:apply:(Lzio/aws/synthetics/model/Canary$ReadOnly;)Lscala/Function0;
      12: invokevirtual #283                // Method zio/aws/core/AwsError$.unwrapOptionField:(Ljava/lang/String;Lscala/Function0;)Lzio/ZIO;
      15: areturn

  public static zio.ZIO getEngineArn$(zio.aws.synthetics.model.Canary$ReadOnly);
    Code:
       0: aload_0
       1: invokespecial #393                // InterfaceMethod getEngineArn:()Lzio/ZIO;
       4: areturn

  public default zio.ZIO<java.lang.Object, zio.aws.core.AwsError, java.lang.String> getEngineArn();
    Code:
       0: getstatic     #267                // Field zio/aws/core/AwsError$.MODULE$:Lzio/aws/core/AwsError$;
       3: ldc_w         #394                // String engineArn
       6: aload_0
       7: invokedynamic #399,  0            // InvokeDynamic #28:apply:(Lzio/aws/synthetics/model/Canary$ReadOnly;)Lscala/Function0;
      12: invokevirtual #283                // Method zio/aws/core/AwsError$.unwrapOptionField:(Ljava/lang/String;Lscala/Function0;)Lzio/ZIO;
      15: areturn

  public static zio.ZIO getRuntimeVersion$(zio.aws.synthetics.model.Canary$ReadOnly);
    Code:
       0: aload_0
       1: invokespecial #403                // InterfaceMethod getRuntimeVersion:()Lzio/ZIO;
       4: areturn

  public default zio.ZIO<java.lang.Object, zio.aws.core.AwsError, java.lang.String> getRuntimeVersion();
    Code:
       0: getstatic     #267                // Field zio/aws/core/AwsError$.MODULE$:Lzio/aws/core/AwsError$;
       3: ldc_w         #404                // String runtimeVersion
       6: aload_0
       7: invokedynamic #409,  0            // InvokeDynamic #29:apply:(Lzio/aws/synthetics/model/Canary$ReadOnly;)Lscala/Function0;
      12: invokevirtual #283                // Method zio/aws/core/AwsError$.unwrapOptionField:(Ljava/lang/String;Lscala/Function0;)Lzio/ZIO;
      15: areturn

  public static zio.ZIO getVpcConfig$(zio.aws.synthetics.model.Canary$ReadOnly);
    Code:
       0: aload_0
       1: invokespecial #413                // InterfaceMethod getVpcConfig:()Lzio/ZIO;
       4: areturn

  public default zio.ZIO<java.lang.Object, zio.aws.core.AwsError, zio.aws.synthetics.model.VpcConfigOutput$ReadOnly> getVpcConfig();
    Code:
       0: getstatic     #267                // Field zio/aws/core/AwsError$.MODULE$:Lzio/aws/core/AwsError$;
       3: ldc_w         #415                // String vpcConfig
       6: aload_0
       7: invokedynamic #420,  0            // InvokeDynamic #30:apply:(Lzio/aws/synthetics/model/Canary$ReadOnly;)Lscala/Function0;
      12: invokevirtual #283                // Method zio/aws/core/AwsError$.unwrapOptionField:(Ljava/lang/String;Lscala/Function0;)Lzio/ZIO;
      15: areturn

  public static zio.ZIO getVisualReference$(zio.aws.synthetics.model.Canary$ReadOnly);
    Code:
       0: aload_0
       1: invokespecial #424                // InterfaceMethod getVisualReference:()Lzio/ZIO;
       4: areturn

  public default zio.ZIO<java.lang.Object, zio.aws.core.AwsError, zio.aws.synthetics.model.VisualReferenceOutput$ReadOnly> getVisualReference();
    Code:
       0: getstatic     #267                // Field zio/aws/core/AwsError$.MODULE$:Lzio/aws/core/AwsError$;
       3: ldc_w         #426                // String visualReference
       6: aload_0
       7: invokedynamic #431,  0            // InvokeDynamic #31:apply:(Lzio/aws/synthetics/model/Canary$ReadOnly;)Lscala/Function0;
      12: invokevirtual #283                // Method zio/aws/core/AwsError$.unwrapOptionField:(Ljava/lang/String;Lscala/Function0;)Lzio/ZIO;
      15: areturn

  public static zio.ZIO getTags$(zio.aws.synthetics.model.Canary$ReadOnly);
    Code:
       0: aload_0
       1: invokespecial #435                // InterfaceMethod getTags:()Lzio/ZIO;
       4: areturn

  public default zio.ZIO<java.lang.Object, zio.aws.core.AwsError, scala.collection.immutable.Map<java.lang.String, java.lang.String>> getTags();
    Code:
       0: getstatic     #267                // Field zio/aws/core/AwsError$.MODULE$:Lzio/aws/core/AwsError$;
       3: ldc_w         #437                // String tags
       6: aload_0
       7: invokedynamic #442,  0            // InvokeDynamic #32:apply:(Lzio/aws/synthetics/model/Canary$ReadOnly;)Lscala/Function0;
      12: invokevirtual #283                // Method zio/aws/core/AwsError$.unwrapOptionField:(Ljava/lang/String;Lscala/Function0;)Lzio/ZIO;
      15: areturn

  public static zio.ZIO getArtifactConfig$(zio.aws.synthetics.model.Canary$ReadOnly);
    Code:
       0: aload_0
       1: invokespecial #446                // InterfaceMethod getArtifactConfig:()Lzio/ZIO;
       4: areturn

  public default zio.ZIO<java.lang.Object, zio.aws.core.AwsError, zio.aws.synthetics.model.ArtifactConfigOutput$ReadOnly> getArtifactConfig();
    Code:
       0: getstatic     #267                // Field zio/aws/core/AwsError$.MODULE$:Lzio/aws/core/AwsError$;
       3: ldc_w         #448                // String artifactConfig
       6: aload_0
       7: invokedynamic #453,  0            // InvokeDynamic #33:apply:(Lzio/aws/synthetics/model/Canary$ReadOnly;)Lscala/Function0;
      12: invokevirtual #283                // Method zio/aws/core/AwsError$.unwrapOptionField:(Ljava/lang/String;Lscala/Function0;)Lzio/ZIO;
      15: areturn

  public static java.lang.String $anonfun$asEditable$1(java.lang.String);
    Code:
       0: aload_0
       1: areturn

  public static java.lang.String $anonfun$asEditable$2(java.lang.String);
    Code:
       0: aload_0
       1: areturn

  public static zio.aws.synthetics.model.CanaryCodeOutput $anonfun$asEditable$3(zio.aws.synthetics.model.CanaryCodeOutput$ReadOnly);
    Code:
       0: aload_0
       1: invokeinterface #458,  1          // InterfaceMethod zio/aws/synthetics/model/CanaryCodeOutput$ReadOnly.asEditable:()Lzio/aws/synthetics/model/CanaryCodeOutput;
       6: areturn

  public static java.lang.String $anonfun$asEditable$4(java.lang.String);
    Code:
       0: aload_0
       1: areturn

  public static zio.aws.synthetics.model.CanaryScheduleOutput $anonfun$asEditable$5(zio.aws.synthetics.model.CanaryScheduleOutput$ReadOnly);
    Code:
       0: aload_0
       1: invokeinterface #462,  1          // InterfaceMethod zio/aws/synthetics/model/CanaryScheduleOutput$ReadOnly.asEditable:()Lzio/aws/synthetics/model/CanaryScheduleOutput;
       6: areturn

  public static zio.aws.synthetics.model.CanaryRunConfigOutput $anonfun$asEditable$6(zio.aws.synthetics.model.CanaryRunConfigOutput$ReadOnly);
    Code:
       0: aload_0
       1: invokeinterface #466,  1          // InterfaceMethod zio/aws/synthetics/model/CanaryRunConfigOutput$ReadOnly.asEditable:()Lzio/aws/synthetics/model/CanaryRunConfigOutput;
       6: areturn

  public static int $anonfun$asEditable$7(int);
    Code:
       0: iload_0
       1: ireturn

  public static int $anonfun$asEditable$8(int);
    Code:
       0: iload_0
       1: ireturn

  public static zio.aws.synthetics.model.CanaryStatus $anonfun$asEditable$9(zio.aws.synthetics.model.CanaryStatus$ReadOnly);
    Code:
       0: aload_0
       1: invokeinterface #471,  1          // InterfaceMethod zio/aws/synthetics/model/CanaryStatus$ReadOnly.asEditable:()Lzio/aws/synthetics/model/CanaryStatus;
       6: areturn

  public static zio.aws.synthetics.model.CanaryTimeline $anonfun$asEditable$10(zio.aws.synthetics.model.CanaryTimeline$ReadOnly);
    Code:
       0: aload_0
       1: invokeinterface #475,  1          // InterfaceMethod zio/aws/synthetics/model/CanaryTimeline$ReadOnly.asEditable:()Lzio/aws/synthetics/model/CanaryTimeline;
       6: areturn

  public static java.lang.String $anonfun$asEditable$11(java.lang.String);
    Code:
       0: aload_0
       1: areturn

  public static java.lang.String $anonfun$asEditable$12(java.lang.String);
    Code:
       0: aload_0
       1: areturn

  public static java.lang.String $anonfun$asEditable$13(java.lang.String);
    Code:
       0: aload_0
       1: areturn

  public static zio.aws.synthetics.model.VpcConfigOutput $anonfun$asEditable$14(zio.aws.synthetics.model.VpcConfigOutput$ReadOnly);
    Code:
       0: aload_0
       1: invokeinterface #479,  1          // InterfaceMethod zio/aws/synthetics/model/VpcConfigOutput$ReadOnly.asEditable:()Lzio/aws/synthetics/model/VpcConfigOutput;
       6: areturn

  public static zio.aws.synthetics.model.VisualReferenceOutput $anonfun$asEditable$15(zio.aws.synthetics.model.VisualReferenceOutput$ReadOnly);
    Code:
       0: aload_0
       1: invokeinterface #483,  1          // InterfaceMethod zio/aws/synthetics/model/VisualReferenceOutput$ReadOnly.asEditable:()Lzio/aws/synthetics/model/VisualReferenceOutput;
       6: areturn

  public static scala.collection.immutable.Map $anonfun$asEditable$16(scala.collection.immutable.Map);
    Code:
       0: aload_0
       1: areturn

  public static zio.aws.synthetics.model.ArtifactConfigOutput $anonfun$asEditable$17(zio.aws.synthetics.model.ArtifactConfigOutput$ReadOnly);
    Code:
       0: aload_0
       1: invokeinterface #488,  1          // InterfaceMethod zio/aws/synthetics/model/ArtifactConfigOutput$ReadOnly.asEditable:()Lzio/aws/synthetics/model/ArtifactConfigOutput;
       6: areturn

  public static scala.Option $anonfun$getId$1(zio.aws.synthetics.model.Canary$ReadOnly);
    Code:
       0: aload_0
       1: invokeinterface #57,  1           // InterfaceMethod id:()Lscala/Option;
       6: areturn

  public static scala.Option $anonfun$getName$1(zio.aws.synthetics.model.Canary$ReadOnly);
    Code:
       0: aload_0
       1: invokeinterface #89,  1           // InterfaceMethod name:()Lscala/Option;
       6: areturn

  public static scala.Option $anonfun$getCode$1(zio.aws.synthetics.model.Canary$ReadOnly);
    Code:
       0: aload_0
       1: invokeinterface #97,  1           // InterfaceMethod code:()Lscala/Option;
       6: areturn

  public static scala.Option $anonfun$getExecutionRoleArn$1(zio.aws.synthetics.model.Canary$ReadOnly);
    Code:
       0: aload_0
       1: invokeinterface #107,  1          // InterfaceMethod executionRoleArn:()Lscala/Option;
       6: areturn

  public static scala.Option $anonfun$getSchedule$1(zio.aws.synthetics.model.Canary$ReadOnly);
    Code:
       0: aload_0
       1: invokeinterface #115,  1          // InterfaceMethod schedule:()Lscala/Option;
       6: areturn

  public static scala.Option $anonfun$getRunConfig$1(zio.aws.synthetics.model.Canary$ReadOnly);
    Code:
       0: aload_0
       1: invokeinterface #125,  1          // InterfaceMethod runConfig:()Lscala/Option;
       6: areturn

  public static scala.Option $anonfun$getSuccessRetentionPeriodInDays$1(zio.aws.synthetics.model.Canary$ReadOnly);
    Code:
       0: aload_0
       1: invokeinterface #135,  1          // InterfaceMethod successRetentionPeriodInDays:()Lscala/Option;
       6: areturn

  public static scala.Option $anonfun$getFailureRetentionPeriodInDays$1(zio.aws.synthetics.model.Canary$ReadOnly);
    Code:
       0: aload_0
       1: invokeinterface #149,  1          // InterfaceMethod failureRetentionPeriodInDays:()Lscala/Option;
       6: areturn

  public static scala.Option $anonfun$getStatus$1(zio.aws.synthetics.model.Canary$ReadOnly);
    Code:
       0: aload_0
       1: invokeinterface #157,  1          // InterfaceMethod status:()Lscala/Option;
       6: areturn

  public static scala.Option $anonfun$getTimeline$1(zio.aws.synthetics.model.Canary$ReadOnly);
    Code:
       0: aload_0
       1: invokeinterface #167,  1          // InterfaceMethod timeline:()Lscala/Option;
       6: areturn

  public static scala.Option $anonfun$getArtifactS3Location$1(zio.aws.synthetics.model.Canary$ReadOnly);
    Code:
       0: aload_0
       1: invokeinterface #177,  1          // InterfaceMethod artifactS3Location:()Lscala/Option;
       6: areturn

  public static scala.Option $anonfun$getEngineArn$1(zio.aws.synthetics.model.Canary$ReadOnly);
    Code:
       0: aload_0
       1: invokeinterface #185,  1          // InterfaceMethod engineArn:()Lscala/Option;
       6: areturn

  public static scala.Option $anonfun$getRuntimeVersion$1(zio.aws.synthetics.model.Canary$ReadOnly);
    Code:
       0: aload_0
       1: invokeinterface #193,  1          // InterfaceMethod runtimeVersion:()Lscala/Option;
       6: areturn

  public static scala.Option $anonfun$getVpcConfig$1(zio.aws.synthetics.model.Canary$ReadOnly);
    Code:
       0: aload_0
       1: invokeinterface #201,  1          // InterfaceMethod vpcConfig:()Lscala/Option;
       6: areturn

  public static scala.Option $anonfun$getVisualReference$1(zio.aws.synthetics.model.Canary$ReadOnly);
    Code:
       0: aload_0
       1: invokeinterface #211,  1          // InterfaceMethod visualReference:()Lscala/Option;
       6: areturn

  public static scala.Option $anonfun$getTags$1(zio.aws.synthetics.model.Canary$ReadOnly);
    Code:
       0: aload_0
       1: invokeinterface #221,  1          // InterfaceMethod tags:()Lscala/Option;
       6: areturn

  public static scala.Option $anonfun$getArtifactConfig$1(zio.aws.synthetics.model.Canary$ReadOnly);
    Code:
       0: aload_0
       1: invokeinterface #231,  1          // InterfaceMethod artifactConfig:()Lscala/Option;
       6: areturn

  public static void $init$(zio.aws.synthetics.model.Canary$ReadOnly);
    Code:
       0: return

  private static java.lang.Object $deserializeLambda$(java.lang.invoke.SerializedLambda);
    Code:
       0: aload_0
       1: invokedynamic #503,  0            // InvokeDynamic #34:lambdaDeserialize:(Ljava/lang/invoke/SerializedLambda;)Ljava/lang/Object;
       6: areturn
}
