Compiled from "StopCanaryResponse.scala"
public final class zio.aws.synthetics.model.StopCanaryResponse$Wrapper implements zio.aws.synthetics.model.StopCanaryResponse$ReadOnly {
  public zio.aws.synthetics.model.StopCanaryResponse asEditable();
    Code:
       0: aload_0
       1: invokestatic  #17                 // InterfaceMethod zio/aws/synthetics/model/StopCanaryResponse$ReadOnly.asEditable$:(Lzio/aws/synthetics/model/StopCanaryResponse$ReadOnly;)Lzio/aws/synthetics/model/StopCanaryResponse;
       4: areturn

  public zio.aws.synthetics.model.StopCanaryResponse$Wrapper(software.amazon.awssdk.services.synthetics.model.StopCanaryResponse);
    Code:
       0: aload_0
       1: invokespecial #25                 // Method java/lang/Object."<init>":()V
       4: aload_0
       5: invokestatic  #29                 // InterfaceMethod zio/aws/synthetics/model/StopCanaryResponse$ReadOnly.$init$:(Lzio/aws/synthetics/model/StopCanaryResponse$ReadOnly;)V
       8: return
}
