Compiled from "base.kt"
final class net.mamoe.mirai.api.http.adapter.ws.router.BaseKt$wsRouter$1 extends kotlin.jvm.internal.Lambda implements kotlin.jvm.functions.Function1<io.ktor.routing.Routing, kotlin.Unit> {
  final net.mamoe.mirai.api.http.adapter.ws.WebsocketAdapter $wsAdapter;

  net.mamoe.mirai.api.http.adapter.ws.router.BaseKt$wsRouter$1(net.mamoe.mirai.api.http.adapter.ws.WebsocketAdapter);
    Code:
       0: aload_0
       1: aload_1
       2: putfield      #13                 // Field $wsAdapter:Lnet/mamoe/mirai/api/http/adapter/ws/WebsocketAdapter;
       5: aload_0
       6: iconst_1
       7: invokespecial #16                 // Method kotlin/jvm/internal/Lambda."<init>":(I)V
      10: return

  public final void invoke(io.ktor.routing.Routing);
    Code:
       0: aload_1
       1: ldc           #23                 // String $this$routing
       3: invokestatic  #29                 // Method kotlin/jvm/internal/Intrinsics.checkNotNullParameter:(Ljava/lang/Object;Ljava/lang/String;)V
       6: aload_1
       7: checkcast     #31                 // class io/ktor/routing/Route
      10: astore_2
      11: ldc           #33                 // String /message
      13: astore_3
      14: aload_0
      15: getfield      #13                 // Field $wsAdapter:Lnet/mamoe/mirai/api/http/adapter/ws/WebsocketAdapter;
      18: astore        4
      20: iconst_0
      21: istore        5
      23: aload_2
      24: aload_3
      25: aconst_null
      26: new           #35                 // class net/mamoe/mirai/api/http/adapter/ws/router/BaseKt$wsRouter$1$invoke$$inlined$miraiWebsocket$1
      29: dup
      30: aconst_null
      31: aload         4
      33: invokespecial #38                 // Method net/mamoe/mirai/api/http/adapter/ws/router/BaseKt$wsRouter$1$invoke$$inlined$miraiWebsocket$1."<init>":(Lkotlin/coroutines/Continuation;Lnet/mamoe/mirai/api/http/adapter/ws/WebsocketAdapter;)V
      36: checkcast     #40                 // class kotlin/jvm/functions/Function2
      39: iconst_2
      40: aconst_null
      41: invokestatic  #46                 // Method io/ktor/websocket/RoutingKt.webSocket$default:(Lio/ktor/routing/Route;Ljava/lang/String;Ljava/lang/String;Lkotlin/jvm/functions/Function2;ILjava/lang/Object;)V
      44: nop
      45: aload_1
      46: checkcast     #31                 // class io/ktor/routing/Route
      49: astore_2
      50: ldc           #48                 // String /event
      52: astore_3
      53: aload_0
      54: getfield      #13                 // Field $wsAdapter:Lnet/mamoe/mirai/api/http/adapter/ws/WebsocketAdapter;
      57: astore        4
      59: iconst_0
      60: istore        5
      62: aload_2
      63: aload_3
      64: aconst_null
      65: new           #50                 // class net/mamoe/mirai/api/http/adapter/ws/router/BaseKt$wsRouter$1$invoke$$inlined$miraiWebsocket$2
      68: dup
      69: aconst_null
      70: aload         4
      72: invokespecial #51                 // Method net/mamoe/mirai/api/http/adapter/ws/router/BaseKt$wsRouter$1$invoke$$inlined$miraiWebsocket$2."<init>":(Lkotlin/coroutines/Continuation;Lnet/mamoe/mirai/api/http/adapter/ws/WebsocketAdapter;)V
      75: checkcast     #40                 // class kotlin/jvm/functions/Function2
      78: iconst_2
      79: aconst_null
      80: invokestatic  #46                 // Method io/ktor/websocket/RoutingKt.webSocket$default:(Lio/ktor/routing/Route;Ljava/lang/String;Ljava/lang/String;Lkotlin/jvm/functions/Function2;ILjava/lang/Object;)V
      83: nop
      84: aload_1
      85: checkcast     #31                 // class io/ktor/routing/Route
      88: astore_2
      89: ldc           #53                 // String /all
      91: astore_3
      92: aload_0
      93: getfield      #13                 // Field $wsAdapter:Lnet/mamoe/mirai/api/http/adapter/ws/WebsocketAdapter;
      96: astore        4
      98: iconst_0
      99: istore        5
     101: aload_2
     102: aload_3
     103: aconst_null
     104: new           #55                 // class net/mamoe/mirai/api/http/adapter/ws/router/BaseKt$wsRouter$1$invoke$$inlined$miraiWebsocket$3
     107: dup
     108: aconst_null
     109: aload         4
     111: invokespecial #56                 // Method net/mamoe/mirai/api/http/adapter/ws/router/BaseKt$wsRouter$1$invoke$$inlined$miraiWebsocket$3."<init>":(Lkotlin/coroutines/Continuation;Lnet/mamoe/mirai/api/http/adapter/ws/WebsocketAdapter;)V
     114: checkcast     #40                 // class kotlin/jvm/functions/Function2
     117: iconst_2
     118: aconst_null
     119: invokestatic  #46                 // Method io/ktor/websocket/RoutingKt.webSocket$default:(Lio/ktor/routing/Route;Ljava/lang/String;Ljava/lang/String;Lkotlin/jvm/functions/Function2;ILjava/lang/Object;)V
     122: nop
     123: return

  public java.lang.Object invoke(java.lang.Object);
    Code:
       0: aload_0
       1: aload_1
       2: checkcast     #66                 // class io/ktor/routing/Routing
       5: invokevirtual #68                 // Method invoke:(Lio/ktor/routing/Routing;)V
       8: getstatic     #74                 // Field kotlin/Unit.INSTANCE:Lkotlin/Unit;
      11: areturn
}
