Compiled from "ClosureMetaClass.java"
class org.codehaus.groovy.runtime.metaclass.ClosureMetaClass$NormalMethodChooser implements org.codehaus.groovy.runtime.metaclass.ClosureMetaClass$MethodChooser {
  private final org.codehaus.groovy.util.FastArray methods;

  final java.lang.Class theClass;

  org.codehaus.groovy.runtime.metaclass.ClosureMetaClass$NormalMethodChooser(java.lang.Class, org.codehaus.groovy.util.FastArray);
    Code:
       0: aload_0
       1: invokespecial #20                 // Method java/lang/Object."<init>":()V
       4: aload_0
       5: aload_1
       6: putfield      #22                 // Field theClass:Ljava/lang/Class;
       9: aload_0
      10: aload_2
      11: putfield      #24                 // Field methods:Lorg/codehaus/groovy/util/FastArray;
      14: return

  public java.lang.Object chooseMethod(java.lang.Class[], boolean);
    Code:
       0: aload_1
       1: arraylength
       2: ifne          13
       5: aload_0
       6: getfield      #24                 // Field methods:Lorg/codehaus/groovy/util/FastArray;
       9: invokestatic  #34                 // Method org/codehaus/groovy/runtime/MetaClassHelper.chooseEmptyMethodParams:(Lorg/codehaus/groovy/util/FastArray;)Ljava/lang/Object;
      12: areturn
      13: aload_1
      14: arraylength
      15: iconst_1
      16: if_icmpne     33
      19: aload_1
      20: iconst_0
      21: aaload
      22: ifnonnull     33
      25: aload_0
      26: getfield      #24                 // Field methods:Lorg/codehaus/groovy/util/FastArray;
      29: invokestatic  #37                 // Method org/codehaus/groovy/runtime/MetaClassHelper.chooseMostGeneralMethodWith1NullParam:(Lorg/codehaus/groovy/util/FastArray;)Ljava/lang/Object;
      32: areturn
      33: new           #39                 // class java/util/ArrayList
      36: dup
      37: invokespecial #40                 // Method java/util/ArrayList."<init>":()V
      40: astore_3
      41: aload_0
      42: getfield      #24                 // Field methods:Lorg/codehaus/groovy/util/FastArray;
      45: invokevirtual #46                 // Method org/codehaus/groovy/util/FastArray.getArray:()[Ljava/lang/Object;
      48: astore        4
      50: iconst_0
      51: istore        5
      53: aload_0
      54: getfield      #24                 // Field methods:Lorg/codehaus/groovy/util/FastArray;
      57: invokevirtual #50                 // Method org/codehaus/groovy/util/FastArray.size:()I
      60: istore        6
      62: iload         5
      64: iload         6
      66: if_icmpeq     103
      69: aload         4
      71: iload         5
      73: aaload
      74: astore        7
      76: aload         7
      78: checkcast     #58                 // class org/codehaus/groovy/reflection/ParameterTypes
      81: aload_1
      82: invokevirtual #62                 // Method org/codehaus/groovy/reflection/ParameterTypes.isValidMethod:([Ljava/lang/Class;)Z
      85: ifeq          97
      88: aload_3
      89: aload         7
      91: invokeinterface #66,  2           // InterfaceMethod java/util/List.add:(Ljava/lang/Object;)Z
      96: pop
      97: iinc          5, 1
     100: goto          62
     103: aload_3
     104: invokeinterface #67,  1           // InterfaceMethod java/util/List.size:()I
     109: istore        5
     111: iconst_0
     112: iload         5
     114: if_icmpne     119
     117: aconst_null
     118: areturn
     119: iconst_1
     120: iload         5
     122: if_icmpne     133
     125: aload_3
     126: iconst_0
     127: invokeinterface #71,  2           // InterfaceMethod java/util/List.get:(I)Ljava/lang/Object;
     132: areturn
     133: aload_0
     134: ldc           #73                 // String doCall
     136: aload_3
     137: aload_1
     138: invokespecial #77                 // Method chooseMostSpecificParams:(Ljava/lang/String;Ljava/util/List;[Ljava/lang/Class;)Ljava/lang/Object;
     141: areturn

  private java.lang.Object chooseMostSpecificParams(java.lang.String, java.util.List, java.lang.Class[]);
    Code:
       0: aload_0
       1: getfield      #22                 // Field theClass:Ljava/lang/Class;
       4: invokevirtual #94                 // Method java/lang/Class.getName:()Ljava/lang/String;
       7: aload_1
       8: aload_2
       9: aload_3
      10: iconst_1
      11: invokestatic  #98                 // Method org/codehaus/groovy/runtime/metaclass/ClosureMetaClass.access$000:(Ljava/lang/String;Ljava/lang/String;Ljava/util/List;[Ljava/lang/Class;Z)Ljava/lang/Object;
      14: areturn
}
