Compiled from "NewMetaMethod.java"
public class org.codehaus.groovy.runtime.metaclass.NewMetaMethod extends org.codehaus.groovy.runtime.metaclass.ReflectionMetaMethod {
  protected static final org.codehaus.groovy.reflection.CachedClass[] EMPTY_TYPE_ARRAY;

  protected org.codehaus.groovy.reflection.CachedClass[] bytecodeParameterTypes;

  public org.codehaus.groovy.runtime.metaclass.NewMetaMethod(org.codehaus.groovy.reflection.CachedMethod);
    Code:
       0: aload_0
       1: aload_1
       2: invokespecial #12                 // Method org/codehaus/groovy/runtime/metaclass/ReflectionMetaMethod."<init>":(Lorg/codehaus/groovy/reflection/CachedMethod;)V
       5: aload_0
       6: aload_1
       7: invokevirtual #18                 // Method org/codehaus/groovy/reflection/CachedMethod.getParameterTypes:()[Lorg/codehaus/groovy/reflection/CachedClass;
      10: putfield      #20                 // Field bytecodeParameterTypes:[Lorg/codehaus/groovy/reflection/CachedClass;
      13: aload_0
      14: getfield      #20                 // Field bytecodeParameterTypes:[Lorg/codehaus/groovy/reflection/CachedClass;
      17: arraylength
      18: istore_2
      19: iload_2
      20: iconst_1
      21: if_icmpgt     31
      24: getstatic     #22                 // Field EMPTY_TYPE_ARRAY:[Lorg/codehaus/groovy/reflection/CachedClass;
      27: astore_3
      28: goto          50
      31: iinc          2, -1
      34: iload_2
      35: anewarray     #24                 // class org/codehaus/groovy/reflection/CachedClass
      38: astore_3
      39: aload_0
      40: getfield      #20                 // Field bytecodeParameterTypes:[Lorg/codehaus/groovy/reflection/CachedClass;
      43: iconst_1
      44: aload_3
      45: iconst_0
      46: iload_2
      47: invokestatic  #30                 // Method java/lang/System.arraycopy:(Ljava/lang/Object;ILjava/lang/Object;II)V
      50: aload_0
      51: aload_3
      52: invokevirtual #35                 // Method setParametersTypes:([Lorg/codehaus/groovy/reflection/CachedClass;)V
      55: return

  public org.codehaus.groovy.reflection.CachedClass getDeclaringClass();
    Code:
       0: aload_0
       1: invokevirtual #47                 // Method getBytecodeParameterTypes:()[Lorg/codehaus/groovy/reflection/CachedClass;
       4: iconst_0
       5: aaload
       6: areturn

  public org.codehaus.groovy.reflection.CachedClass[] getBytecodeParameterTypes();
    Code:
       0: aload_0
       1: getfield      #20                 // Field bytecodeParameterTypes:[Lorg/codehaus/groovy/reflection/CachedClass;
       4: areturn

  public org.codehaus.groovy.reflection.CachedClass getOwnerClass();
    Code:
       0: aload_0
       1: invokevirtual #47                 // Method getBytecodeParameterTypes:()[Lorg/codehaus/groovy/reflection/CachedClass;
       4: iconst_0
       5: aaload
       6: areturn

  static {};
    Code:
       0: iconst_0
       1: anewarray     #24                 // class org/codehaus/groovy/reflection/CachedClass
       4: putstatic     #22                 // Field EMPTY_TYPE_ARRAY:[Lorg/codehaus/groovy/reflection/CachedClass;
       7: return
}
