Compiled from "ExecutableLauncher.java"
public class de.ntcomputer.executablepacker.runtime.ExecutableLauncher {
  public static final java.lang.String MANIFEST_APPLICATION_MAIN_CLASS;

  public static final java.lang.String MANIFEST_DEPENDENCY_LIBPATH;

  public static final java.lang.String MANIFEST_DEPENDENCY_JARS;

  public de.ntcomputer.executablepacker.runtime.ExecutableLauncher();
    Code:
       0: aload_0
       1: invokespecial #19                 // Method java/lang/Object."<init>":()V
       4: return

  public static void main(java.lang.String[]) throws java.io.IOException, java.lang.ClassNotFoundException, java.lang.NoSuchMethodException, java.lang.SecurityException, java.lang.IllegalAccessException, java.lang.IllegalArgumentException, java.lang.reflect.InvocationTargetException;
    Code:
       0: invokestatic  #42                 // Method java/lang/Thread.currentThread:()Ljava/lang/Thread;
       3: invokevirtual #48                 // Method java/lang/Thread.getContextClassLoader:()Ljava/lang/ClassLoader;
       6: astore_1
       7: aload_1
       8: astore_2
       9: aconst_null
      10: astore_3
      11: aconst_null
      12: astore        4
      14: aconst_null
      15: astore        5
      17: aload_1
      18: ldc           #52                 // String META-INF/MANIFEST.MF
      20: invokevirtual #54                 // Method java/lang/ClassLoader.getResources:(Ljava/lang/String;)Ljava/util/Enumeration;
      23: astore        6
      25: aload         6
      27: ifnull        40
      30: aload         6
      32: invokeinterface #60,  1           // InterfaceMethod java/util/Enumeration.hasMoreElements:()Z
      37: ifne          183
      40: new           #66                 // class java/util/MissingResourceException
      43: dup
      44: ldc           #68                 // String Manifest file (META-INF/MANIFEST.MF) is missing
      46: ldc           #1                  // class de/ntcomputer/executablepacker/runtime/ExecutableLauncher
      48: invokevirtual #70                 // Method java/lang/Class.getName:()Ljava/lang/String;
      51: ldc           #52                 // String META-INF/MANIFEST.MF
      53: invokespecial #76                 // Method java/util/MissingResourceException."<init>":(Ljava/lang/String;Ljava/lang/String;Ljava/lang/String;)V
      56: athrow
      57: aload         6
      59: invokeinterface #79,  1           // InterfaceMethod java/util/Enumeration.nextElement:()Ljava/lang/Object;
      64: checkcast     #83                 // class java/net/URL
      67: astore        7
      69: aload         7
      71: invokevirtual #85                 // Method java/net/URL.openStream:()Ljava/io/InputStream;
      74: astore        8
      76: new           #89                 // class java/util/jar/Manifest
      79: dup
      80: aload         8
      82: invokespecial #91                 // Method java/util/jar/Manifest."<init>":(Ljava/io/InputStream;)V
      85: astore        9
      87: aload         9
      89: invokevirtual #94                 // Method java/util/jar/Manifest.getMainAttributes:()Ljava/util/jar/Attributes;
      92: astore        10
      94: aload         10
      96: ldc           #8                  // String Application-Main-Class
      98: invokevirtual #98                 // Method java/util/jar/Attributes.getValue:(Ljava/lang/String;)Ljava/lang/String;
     101: astore        11
     103: aload         10
     105: ldc           #11                 // String Dependency-Libpath
     107: invokevirtual #98                 // Method java/util/jar/Attributes.getValue:(Ljava/lang/String;)Ljava/lang/String;
     110: astore        12
     112: aload         10
     114: ldc           #14                 // String Dependency-Jars
     116: invokevirtual #98                 // Method java/util/jar/Attributes.getValue:(Ljava/lang/String;)Ljava/lang/String;
     119: astore        13
     121: aload         11
     123: ifnull        173
     126: aload         11
     128: invokevirtual #104                // Method java/lang/String.trim:()Ljava/lang/String;
     131: astore        11
     133: aload         11
     135: invokevirtual #104                // Method java/lang/String.trim:()Ljava/lang/String;
     138: invokevirtual #109                // Method java/lang/String.isEmpty:()Z
     141: ifne          173
     144: aload         11
     146: astore_3
     147: aload         12
     149: astore        4
     151: aload         13
     153: astore        5
     155: aload         8
     157: invokevirtual #112                // Method java/io/InputStream.close:()V
     160: goto          193
     163: astore        14
     165: aload         8
     167: invokevirtual #112                // Method java/io/InputStream.close:()V
     170: aload         14
     172: athrow
     173: aload         8
     175: invokevirtual #112                // Method java/io/InputStream.close:()V
     178: goto          183
     181: astore        8
     183: aload         6
     185: invokeinterface #60,  1           // InterfaceMethod java/util/Enumeration.hasMoreElements:()Z
     190: ifne          57
     193: aload_3
     194: ifnonnull     207
     197: new           #28                 // class java/io/IOException
     200: dup
     201: ldc           #117                // String Manifest is missing entry Application-Main-Class
     203: invokespecial #119                // Method java/io/IOException."<init>":(Ljava/lang/String;)V
     206: athrow
     207: aload         4
     209: ifnonnull     219
     212: ldc           #122                // String
     214: astore        4
     216: goto          226
     219: aload         4
     221: invokevirtual #104                // Method java/lang/String.trim:()Ljava/lang/String;
     224: astore        4
     226: aload         5
     228: ifnull        436
     231: aload         5
     233: invokevirtual #109                // Method java/lang/String.isEmpty:()Z
     236: ifne          436
     239: new           #124                // class de/ntcomputer/executablepacker/runtime/JarInJarURLStreamHandlerFactory
     242: dup
     243: aload_1
     244: invokespecial #126                // Method de/ntcomputer/executablepacker/runtime/JarInJarURLStreamHandlerFactory."<init>":(Ljava/lang/ClassLoader;)V
     247: invokestatic  #129                // Method java/net/URL.setURLStreamHandlerFactory:(Ljava/net/URLStreamHandlerFactory;)V
     250: aload         5
     252: ldc           #133                // String /
     254: invokevirtual #135                // Method java/lang/String.split:(Ljava/lang/String;)[Ljava/lang/String;
     257: astore        7
     259: new           #139                // class java/util/ArrayList
     262: dup
     263: aload         7
     265: arraylength
     266: invokespecial #141                // Method java/util/ArrayList."<init>":(I)V
     269: astore        8
     271: aload         8
     273: new           #83                 // class java/net/URL
     276: dup
     277: ldc           #144                // String jij:./
     279: invokespecial #146                // Method java/net/URL."<init>":(Ljava/lang/String;)V
     282: invokeinterface #147,  2          // InterfaceMethod java/util/List.add:(Ljava/lang/Object;)Z
     287: pop
     288: aload         7
     290: dup
     291: astore        12
     293: arraylength
     294: istore        11
     296: iconst_0
     297: istore        10
     299: goto          373
     302: aload         12
     304: iload         10
     306: aaload
     307: astore        9
     309: aload         9
     311: invokevirtual #104                // Method java/lang/String.trim:()Ljava/lang/String;
     314: astore        9
     316: aload         9
     318: invokevirtual #109                // Method java/lang/String.isEmpty:()Z
     321: ifne          370
     324: new           #83                 // class java/net/URL
     327: dup
     328: new           #153                // class java/lang/StringBuilder
     331: dup
     332: ldc           #155                // String jar:jij:
     334: invokespecial #157                // Method java/lang/StringBuilder."<init>":(Ljava/lang/String;)V
     337: aload         4
     339: invokevirtual #158                // Method java/lang/StringBuilder.append:(Ljava/lang/String;)Ljava/lang/StringBuilder;
     342: aload         9
     344: invokevirtual #158                // Method java/lang/StringBuilder.append:(Ljava/lang/String;)Ljava/lang/StringBuilder;
     347: ldc           #162                // String !/
     349: invokevirtual #158                // Method java/lang/StringBuilder.append:(Ljava/lang/String;)Ljava/lang/StringBuilder;
     352: invokevirtual #164                // Method java/lang/StringBuilder.toString:()Ljava/lang/String;
     355: invokespecial #146                // Method java/net/URL."<init>":(Ljava/lang/String;)V
     358: astore        13
     360: aload         8
     362: aload         13
     364: invokeinterface #147,  2          // InterfaceMethod java/util/List.add:(Ljava/lang/Object;)Z
     369: pop
     370: iinc          10, 1
     373: iload         10
     375: iload         11
     377: if_icmplt     302
     380: aload         8
     382: invokeinterface #167,  1          // InterfaceMethod java/util/List.size:()I
     387: iconst_1
     388: if_icmple     436
     391: aload         8
     393: aload         8
     395: invokeinterface #167,  1          // InterfaceMethod java/util/List.size:()I
     400: anewarray     #83                 // class java/net/URL
     403: invokeinterface #171,  2          // InterfaceMethod java/util/List.toArray:([Ljava/lang/Object;)[Ljava/lang/Object;
     408: checkcast     #175                // class "[Ljava/net/URL;"
     411: astore        9
     413: new           #177                // class java/net/URLClassLoader
     416: dup
     417: aload         9
     419: aconst_null
     420: invokespecial #179                // Method java/net/URLClassLoader."<init>":([Ljava/net/URL;Ljava/lang/ClassLoader;)V
     423: astore        10
     425: aload         10
     427: astore_2
     428: invokestatic  #42                 // Method java/lang/Thread.currentThread:()Ljava/lang/Thread;
     431: aload         10
     433: invokevirtual #182                // Method java/lang/Thread.setContextClassLoader:(Ljava/lang/ClassLoader;)V
     436: aload_3
     437: iconst_1
     438: aload_2
     439: invokestatic  #185                // Method java/lang/Class.forName:(Ljava/lang/String;ZLjava/lang/ClassLoader;)Ljava/lang/Class;
     442: astore        7
     444: aload         7
     446: ldc           #189                // String main
     448: iconst_1
     449: anewarray     #71                 // class java/lang/Class
     452: dup
     453: iconst_0
     454: ldc           #190                // class "[Ljava/lang/String;"
     456: aastore
     457: invokevirtual #192                // Method java/lang/Class.getMethod:(Ljava/lang/String;[Ljava/lang/Class;)Ljava/lang/reflect/Method;
     460: astore        8
     462: aload         8
     464: aconst_null
     465: iconst_1
     466: anewarray     #3                  // class java/lang/Object
     469: dup
     470: iconst_0
     471: aload_0
     472: aastore
     473: invokevirtual #196                // Method java/lang/reflect/Method.invoke:(Ljava/lang/Object;[Ljava/lang/Object;)Ljava/lang/Object;
     476: pop
     477: return
    Exception table:
       from    to  target type
          76   155   163   any
          69   160   181   Class java/lang/Exception
         163   178   181   Class java/lang/Exception
}
