public class org.bouncycastle.crypto.params.GOST3410PublicKeyParameters extends org.bouncycastle.crypto.params.GOST3410KeyParameters {
  private java.math.BigInteger y;

  public org.bouncycastle.crypto.params.GOST3410PublicKeyParameters(java.math.BigInteger, org.bouncycastle.crypto.params.GOST3410Parameters);
    Code:
       0: aload_0
       1: iconst_0
       2: aload_2
       3: invokespecial #15                 // Method org/bouncycastle/crypto/params/GOST3410KeyParameters."<init>":(ZLorg/bouncycastle/crypto/params/GOST3410Parameters;)V
       6: aload_0
       7: aload_1
       8: putfield      #14                 // Field y:Ljava/math/BigInteger;
      11: return

  public java.math.BigInteger getY();
    Code:
       0: aload_0
       1: getfield      #14                 // Field y:Ljava/math/BigInteger;
       4: areturn
}
