Compiled from "AbstractConfigurationFilter.java"
public abstract class org.jasig.cas.client.util.AbstractConfigurationFilter implements javax.servlet.Filter {
  private static final java.lang.String CONFIGURATION_STRATEGY_KEY;

  protected final org.slf4j.Logger logger;

  private boolean ignoreInitConfiguration;

  private org.jasig.cas.client.configuration.ConfigurationStrategy configurationStrategy;

  public org.jasig.cas.client.util.AbstractConfigurationFilter();
    Code:
       0: aload_0
       1: invokespecial #1                  // Method java/lang/Object."<init>":()V
       4: aload_0
       5: aload_0
       6: invokevirtual #2                  // Method java/lang/Object.getClass:()Ljava/lang/Class;
       9: invokestatic  #3                  // Method org/slf4j/LoggerFactory.getLogger:(Ljava/lang/Class;)Lorg/slf4j/Logger;
      12: putfield      #4                  // Field logger:Lorg/slf4j/Logger;
      15: aload_0
      16: iconst_0
      17: putfield      #5                  // Field ignoreInitConfiguration:Z
      20: return

  public void init(javax.servlet.FilterConfig) throws javax.servlet.ServletException;
    Code:
       0: aload_1
       1: invokeinterface #6,  1            // InterfaceMethod javax/servlet/FilterConfig.getServletContext:()Ljavax/servlet/ServletContext;
       6: ldc           #8                  // String configurationStrategy
       8: invokeinterface #9,  2            // InterfaceMethod javax/servlet/ServletContext.getInitParameter:(Ljava/lang/String;)Ljava/lang/String;
      13: astore_2
      14: aload_0
      15: aload_2
      16: invokestatic  #10                 // Method org/jasig/cas/client/configuration/ConfigurationStrategyName.resolveToConfigurationStrategy:(Ljava/lang/String;)Ljava/lang/Class;
      19: iconst_0
      20: anewarray     #11                 // class java/lang/Object
      23: invokestatic  #12                 // Method org/jasig/cas/client/util/ReflectUtils.newInstance:(Ljava/lang/Class;[Ljava/lang/Object;)Ljava/lang/Object;
      26: checkcast     #13                 // class org/jasig/cas/client/configuration/ConfigurationStrategy
      29: putfield      #14                 // Field configurationStrategy:Lorg/jasig/cas/client/configuration/ConfigurationStrategy;
      32: aload_0
      33: getfield      #14                 // Field configurationStrategy:Lorg/jasig/cas/client/configuration/ConfigurationStrategy;
      36: aload_1
      37: aload_0
      38: invokevirtual #2                  // Method java/lang/Object.getClass:()Ljava/lang/Class;
      41: invokeinterface #15,  3           // InterfaceMethod org/jasig/cas/client/configuration/ConfigurationStrategy.init:(Ljavax/servlet/FilterConfig;Ljava/lang/Class;)V
      46: return

  protected final boolean getBoolean(org.jasig.cas.client.configuration.ConfigurationKey<java.lang.Boolean>);
    Code:
       0: aload_0
       1: getfield      #14                 // Field configurationStrategy:Lorg/jasig/cas/client/configuration/ConfigurationStrategy;
       4: aload_1
       5: invokeinterface #16,  2           // InterfaceMethod org/jasig/cas/client/configuration/ConfigurationStrategy.getBoolean:(Lorg/jasig/cas/client/configuration/ConfigurationKey;)Z
      10: ireturn

  protected final java.lang.String getString(org.jasig.cas.client.configuration.ConfigurationKey<java.lang.String>);
    Code:
       0: aload_0
       1: getfield      #14                 // Field configurationStrategy:Lorg/jasig/cas/client/configuration/ConfigurationStrategy;
       4: aload_1
       5: invokeinterface #17,  2           // InterfaceMethod org/jasig/cas/client/configuration/ConfigurationStrategy.getString:(Lorg/jasig/cas/client/configuration/ConfigurationKey;)Ljava/lang/String;
      10: areturn

  protected final long getLong(org.jasig.cas.client.configuration.ConfigurationKey<java.lang.Long>);
    Code:
       0: aload_0
       1: getfield      #14                 // Field configurationStrategy:Lorg/jasig/cas/client/configuration/ConfigurationStrategy;
       4: aload_1
       5: invokeinterface #18,  2           // InterfaceMethod org/jasig/cas/client/configuration/ConfigurationStrategy.getLong:(Lorg/jasig/cas/client/configuration/ConfigurationKey;)J
      10: lreturn

  protected final int getInt(org.jasig.cas.client.configuration.ConfigurationKey<java.lang.Integer>);
    Code:
       0: aload_0
       1: getfield      #14                 // Field configurationStrategy:Lorg/jasig/cas/client/configuration/ConfigurationStrategy;
       4: aload_1
       5: invokeinterface #19,  2           // InterfaceMethod org/jasig/cas/client/configuration/ConfigurationStrategy.getInt:(Lorg/jasig/cas/client/configuration/ConfigurationKey;)I
      10: ireturn

  protected final <T> java.lang.Class<? extends T> getClass(org.jasig.cas.client.configuration.ConfigurationKey<java.lang.Class<? extends T>>);
    Code:
       0: aload_0
       1: getfield      #14                 // Field configurationStrategy:Lorg/jasig/cas/client/configuration/ConfigurationStrategy;
       4: aload_1
       5: invokeinterface #20,  2           // InterfaceMethod org/jasig/cas/client/configuration/ConfigurationStrategy.getClass:(Lorg/jasig/cas/client/configuration/ConfigurationKey;)Ljava/lang/Class;
      10: areturn

  public final void setIgnoreInitConfiguration(boolean);
    Code:
       0: aload_0
       1: iload_1
       2: putfield      #5                  // Field ignoreInitConfiguration:Z
       5: return

  protected final boolean isIgnoreInitConfiguration();
    Code:
       0: aload_0
       1: getfield      #5                  // Field ignoreInitConfiguration:Z
       4: ireturn
}
