Compiled from "DohResolver.java"
public final class org.xbill.DNS.DohResolver implements org.xbill.DNS.Resolver {
  private static final org.slf4j.Logger log;

  private static final boolean USE_HTTP_CLIENT;

  private static final java.util.Map<java.util.concurrent.Executor, java.lang.Object> httpClients;

  private final javax.net.ssl.SSLSocketFactory sslSocketFactory;

  private static java.lang.Object defaultHttpRequestBuilder;

  private static java.lang.reflect.Method publisherOfByteArrayMethod;

  private static java.lang.reflect.Method requestBuilderTimeoutMethod;

  private static java.lang.reflect.Method requestBuilderCopyMethod;

  private static java.lang.reflect.Method requestBuilderUriMethod;

  private static java.lang.reflect.Method requestBuilderBuildMethod;

  private static java.lang.reflect.Method requestBuilderPostMethod;

  private static java.lang.reflect.Method httpClientNewBuilderMethod;

  private static java.lang.reflect.Method httpClientBuilderTimeoutMethod;

  private static java.lang.reflect.Method httpClientBuilderExecutorMethod;

  private static java.lang.reflect.Method httpClientBuilderBuildMethod;

  private static java.lang.reflect.Method httpClientSendAsyncMethod;

  private static java.lang.reflect.Method byteArrayBodyPublisherMethod;

  private static java.lang.reflect.Method httpResponseBodyMethod;

  private static java.lang.reflect.Method httpResponseStatusCodeMethod;

  private boolean usePost;

  private java.time.Duration timeout;

  private java.lang.String uriTemplate;

  private final java.time.Duration idleConnectionTimeout;

  private org.xbill.DNS.OPTRecord queryOPT;

  private org.xbill.DNS.TSIG tsig;

  private java.util.concurrent.Executor defaultExecutor;

  private final org.xbill.DNS.AsyncSemaphore maxConcurrentRequests;

  private final java.util.concurrent.atomic.AtomicLong lastRequest;

  private final org.xbill.DNS.AsyncSemaphore initialRequestLock;

  private static final java.lang.String APPLICATION_DNS_MESSAGE;

  public org.xbill.DNS.DohResolver(java.lang.String);
    Code:
       0: aload_0
       1: aload_1
       2: bipush        100
       4: ldc2_w        #1                  // long 2l
       7: invokestatic  #3                  // Method java/time/Duration.ofMinutes:(J)Ljava/time/Duration;
      10: invokespecial #4                  // Method org/xbill/DNS/DohResolver."<init>":(Ljava/lang/String;ILjava/time/Duration;)V
      13: return

  public org.xbill.DNS.DohResolver(java.lang.String, int, java.time.Duration);
    Code:
       0: aload_0
       1: invokespecial #5                  // Method java/lang/Object."<init>":()V
       4: aload_0
       5: iconst_0
       6: putfield      #6                  // Field org/xbill/DNS/DohResolver.usePost:Z
       9: aload_0
      10: ldc2_w        #7                  // long 5l
      13: invokestatic  #9                  // Method java/time/Duration.ofSeconds:(J)Ljava/time/Duration;
      16: putfield      #10                 // Field org/xbill/DNS/DohResolver.timeout:Ljava/time/Duration;
      19: aload_0
      20: new           #11                 // class org/xbill/DNS/OPTRecord
      23: dup
      24: iconst_0
      25: iconst_0
      26: iconst_0
      27: invokespecial #12                 // Method org/xbill/DNS/OPTRecord."<init>":(III)V
      30: putfield      #13                 // Field org/xbill/DNS/DohResolver.queryOPT:Lorg/xbill/DNS/OPTRecord;
      33: aload_0
      34: invokestatic  #14                 // Method java/util/concurrent/ForkJoinPool.commonPool:()Ljava/util/concurrent/ForkJoinPool;
      37: putfield      #15                 // Field org/xbill/DNS/DohResolver.defaultExecutor:Ljava/util/concurrent/Executor;
      40: aload_0
      41: new           #16                 // class java/util/concurrent/atomic/AtomicLong
      44: dup
      45: lconst_0
      46: invokespecial #17                 // Method java/util/concurrent/atomic/AtomicLong."<init>":(J)V
      49: putfield      #18                 // Field org/xbill/DNS/DohResolver.lastRequest:Ljava/util/concurrent/atomic/AtomicLong;
      52: aload_0
      53: new           #19                 // class org/xbill/DNS/AsyncSemaphore
      56: dup
      57: iconst_1
      58: invokespecial #20                 // Method org/xbill/DNS/AsyncSemaphore."<init>":(I)V
      61: putfield      #21                 // Field org/xbill/DNS/DohResolver.initialRequestLock:Lorg/xbill/DNS/AsyncSemaphore;
      64: aload_0
      65: aload_1
      66: putfield      #22                 // Field org/xbill/DNS/DohResolver.uriTemplate:Ljava/lang/String;
      69: aload_0
      70: aload_3
      71: putfield      #23                 // Field org/xbill/DNS/DohResolver.idleConnectionTimeout:Ljava/time/Duration;
      74: iload_2
      75: ifgt          88
      78: new           #24                 // class java/lang/IllegalArgumentException
      81: dup
      82: ldc           #25                 // String maxConcurrentRequests must be > 0
      84: invokespecial #26                 // Method java/lang/IllegalArgumentException."<init>":(Ljava/lang/String;)V
      87: athrow
      88: getstatic     #27                 // Field org/xbill/DNS/DohResolver.USE_HTTP_CLIENT:Z
      91: ifne          120
      94: ldc           #28                 // String http.maxConnections
      96: ldc           #29                 // String 5
      98: invokestatic  #30                 // Method java/lang/System.getProperty:(Ljava/lang/String;Ljava/lang/String;)Ljava/lang/String;
     101: invokestatic  #31                 // Method java/lang/Integer.parseInt:(Ljava/lang/String;)I
     104: istore        4
     106: iload_2
     107: iload         4
     109: if_icmple     115
     112: iload         4
     114: istore_2
     115: goto          120
     118: astore        4
     120: aload_0
     121: new           #19                 // class org/xbill/DNS/AsyncSemaphore
     124: dup
     125: iload_2
     126: invokespecial #20                 // Method org/xbill/DNS/AsyncSemaphore."<init>":(I)V
     129: putfield      #33                 // Field org/xbill/DNS/DohResolver.maxConcurrentRequests:Lorg/xbill/DNS/AsyncSemaphore;
     132: aload_0
     133: invokestatic  #34                 // Method javax/net/ssl/SSLContext.getDefault:()Ljavax/net/ssl/SSLContext;
     136: invokevirtual #35                 // Method javax/net/ssl/SSLContext.getSocketFactory:()Ljavax/net/ssl/SSLSocketFactory;
     139: putfield      #36                 // Field org/xbill/DNS/DohResolver.sslSocketFactory:Ljavax/net/ssl/SSLSocketFactory;
     142: goto          157
     145: astore        4
     147: new           #38                 // class java/lang/RuntimeException
     150: dup
     151: aload         4
     153: invokespecial #39                 // Method java/lang/RuntimeException."<init>":(Ljava/lang/Throwable;)V
     156: athrow
     157: return
    Exception table:
       from    to  target type
          94   115   118   Class java/lang/NumberFormatException
         132   142   145   Class java/security/NoSuchAlgorithmException

  private java.lang.Object getHttpClient(java.util.concurrent.Executor);
    Code:
       0: getstatic     #40                 // Field org/xbill/DNS/DohResolver.httpClients:Ljava/util/Map;
       3: aload_1
       4: aload_0
       5: invokedynamic #41,  0             // InvokeDynamic #0:apply:(Lorg/xbill/DNS/DohResolver;)Ljava/util/function/Function;
      10: invokeinterface #42,  3           // InterfaceMethod java/util/Map.computeIfAbsent:(Ljava/lang/Object;Ljava/util/function/Function;)Ljava/lang/Object;
      15: areturn
      16: astore_2
      17: aload_2
      18: athrow
    Exception table:
       from    to  target type
           0    15    16   Class java/lang/Throwable

  public void setPort(int);
    Code:
       0: return

  public void setTCP(boolean);
    Code:
       0: return

  public void setIgnoreTruncation(boolean);
    Code:
       0: return

  public void setEDNS(int, int, int, java.util.List<org.xbill.DNS.EDNSOption>);
    Code:
       0: iload_1
       1: lookupswitch  { // 2
                    -1: 28
                     0: 36
               default: 56
          }
      28: aload_0
      29: aconst_null
      30: putfield      #13                 // Field org/xbill/DNS/DohResolver.queryOPT:Lorg/xbill/DNS/OPTRecord;
      33: goto          66
      36: aload_0
      37: new           #11                 // class org/xbill/DNS/OPTRecord
      40: dup
      41: iconst_0
      42: iconst_0
      43: iload_1
      44: iload_3
      45: aload         4
      47: invokespecial #45                 // Method org/xbill/DNS/OPTRecord."<init>":(IIIILjava/util/List;)V
      50: putfield      #13                 // Field org/xbill/DNS/DohResolver.queryOPT:Lorg/xbill/DNS/OPTRecord;
      53: goto          66
      56: new           #24                 // class java/lang/IllegalArgumentException
      59: dup
      60: ldc           #46                 // String invalid EDNS version - must be 0 or -1 to disable
      62: invokespecial #26                 // Method java/lang/IllegalArgumentException."<init>":(Ljava/lang/String;)V
      65: athrow
      66: return

  public void setTSIGKey(org.xbill.DNS.TSIG);
    Code:
       0: aload_0
       1: aload_1
       2: putfield      #47                 // Field org/xbill/DNS/DohResolver.tsig:Lorg/xbill/DNS/TSIG;
       5: return

  public void setTimeout(java.time.Duration);
    Code:
       0: aload_0
       1: aload_1
       2: putfield      #10                 // Field org/xbill/DNS/DohResolver.timeout:Ljava/time/Duration;
       5: getstatic     #40                 // Field org/xbill/DNS/DohResolver.httpClients:Ljava/util/Map;
       8: invokeinterface #48,  1           // InterfaceMethod java/util/Map.clear:()V
      13: return

  public java.time.Duration getTimeout();
    Code:
       0: aload_0
       1: getfield      #10                 // Field org/xbill/DNS/DohResolver.timeout:Ljava/time/Duration;
       4: areturn

  public java.util.concurrent.CompletionStage<org.xbill.DNS.Message> sendAsync(org.xbill.DNS.Message);
    Code:
       0: aload_0
       1: aload_1
       2: aload_0
       3: getfield      #15                 // Field org/xbill/DNS/DohResolver.defaultExecutor:Ljava/util/concurrent/Executor;
       6: invokevirtual #49                 // Method org/xbill/DNS/DohResolver.sendAsync:(Lorg/xbill/DNS/Message;Ljava/util/concurrent/Executor;)Ljava/util/concurrent/CompletionStage;
       9: areturn

  public java.util.concurrent.CompletionStage<org.xbill.DNS.Message> sendAsync(org.xbill.DNS.Message, java.util.concurrent.Executor);
    Code:
       0: getstatic     #27                 // Field org/xbill/DNS/DohResolver.USE_HTTP_CLIENT:Z
       3: ifeq          13
       6: aload_0
       7: aload_1
       8: aload_2
       9: invokespecial #50                 // Method org/xbill/DNS/DohResolver.sendAsync11:(Lorg/xbill/DNS/Message;Ljava/util/concurrent/Executor;)Ljava/util/concurrent/CompletionStage;
      12: areturn
      13: aload_0
      14: aload_1
      15: aload_2
      16: invokespecial #51                 // Method org/xbill/DNS/DohResolver.sendAsync8:(Lorg/xbill/DNS/Message;Ljava/util/concurrent/Executor;)Ljava/util/concurrent/CompletionStage;
      19: areturn

  private java.util.concurrent.CompletionStage<org.xbill.DNS.Message> sendAsync8(org.xbill.DNS.Message, java.util.concurrent.Executor);
    Code:
       0: aload_0
       1: aload_1
       2: invokespecial #52                 // Method org/xbill/DNS/DohResolver.prepareQuery:(Lorg/xbill/DNS/Message;)Lorg/xbill/DNS/Message;
       5: invokevirtual #53                 // Method org/xbill/DNS/Message.toWire:()[B
       8: astore_3
       9: aload_0
      10: aload_3
      11: invokespecial #54                 // Method org/xbill/DNS/DohResolver.getUrl:([B)Ljava/lang/String;
      14: astore        4
      16: invokestatic  #55                 // Method java/lang/System.nanoTime:()J
      19: lstore        5
      21: aload_0
      22: getfield      #33                 // Field org/xbill/DNS/DohResolver.maxConcurrentRequests:Lorg/xbill/DNS/AsyncSemaphore;
      25: aload_0
      26: getfield      #10                 // Field org/xbill/DNS/DohResolver.timeout:Ljava/time/Duration;
      29: invokevirtual #56                 // Method org/xbill/DNS/AsyncSemaphore.acquire:(Ljava/time/Duration;)Ljava/util/concurrent/CompletionStage;
      32: aload_0
      33: aload_1
      34: aload         4
      36: aload_3
      37: lload         5
      39: invokedynamic #57,  0             // InvokeDynamic #1:apply:(Lorg/xbill/DNS/DohResolver;Lorg/xbill/DNS/Message;Ljava/lang/String;[BJ)Ljava/util/function/BiFunction;
      44: aload_2
      45: invokeinterface #58,  3           // InterfaceMethod java/util/concurrent/CompletionStage.handleAsync:(Ljava/util/function/BiFunction;Ljava/util/concurrent/Executor;)Ljava/util/concurrent/CompletionStage;
      50: invokestatic  #59                 // InterfaceMethod java/util/function/Function.identity:()Ljava/util/function/Function;
      53: invokeinterface #60,  2           // InterfaceMethod java/util/concurrent/CompletionStage.thenCompose:(Ljava/util/function/Function;)Ljava/util/concurrent/CompletionStage;
      58: areturn

  private org.xbill.DNS.DohResolver$SendAndGetMessageBytesResponse sendAndGetMessageBytes(java.lang.String, byte[], long) throws java.io.IOException;
    Code:
       0: new           #61                 // class java/net/URL
       3: dup
       4: aload_1
       5: invokespecial #62                 // Method java/net/URL."<init>":(Ljava/lang/String;)V
       8: invokevirtual #63                 // Method java/net/URL.openConnection:()Ljava/net/URLConnection;
      11: checkcast     #379                // class java/net/HttpURLConnection
      14: astore        5
      16: aload         5
      18: instanceof    #65                 // class javax/net/ssl/HttpsURLConnection
      21: ifeq          36
      24: aload         5
      26: checkcast     #65                 // class javax/net/ssl/HttpsURLConnection
      29: aload_0
      30: getfield      #36                 // Field org/xbill/DNS/DohResolver.sslSocketFactory:Ljavax/net/ssl/SSLSocketFactory;
      33: invokevirtual #66                 // Method javax/net/ssl/HttpsURLConnection.setSSLSocketFactory:(Ljavax/net/ssl/SSLSocketFactory;)V
      36: aload_0
      37: getfield      #10                 // Field org/xbill/DNS/DohResolver.timeout:Ljava/time/Duration;
      40: invokestatic  #55                 // Method java/lang/System.nanoTime:()J
      43: lload_3
      44: lsub
      45: getstatic     #67                 // Field java/time/temporal/ChronoUnit.NANOS:Ljava/time/temporal/ChronoUnit;
      48: invokevirtual #68                 // Method java/time/Duration.minus:(JLjava/time/temporal/TemporalUnit;)Ljava/time/Duration;
      51: astore        6
      53: aload         5
      55: aload         6
      57: invokevirtual #69                 // Method java/time/Duration.toMillis:()J
      60: l2i
      61: invokevirtual #70                 // Method java/net/HttpURLConnection.setConnectTimeout:(I)V
      64: aload         5
      66: aload         6
      68: invokevirtual #69                 // Method java/time/Duration.toMillis:()J
      71: l2i
      72: invokevirtual #71                 // Method java/net/HttpURLConnection.setReadTimeout:(I)V
      75: aload         5
      77: aload_0
      78: getfield      #6                  // Field org/xbill/DNS/DohResolver.usePost:Z
      81: ifeq          89
      84: ldc           #72                 // String POST
      86: goto          91
      89: ldc           #73                 // String GET
      91: invokevirtual #74                 // Method java/net/HttpURLConnection.setRequestMethod:(Ljava/lang/String;)V
      94: aload         5
      96: ldc           #75                 // String Content-Type
      98: ldc           #77                 // String application/dns-message
     100: invokevirtual #78                 // Method java/net/HttpURLConnection.setRequestProperty:(Ljava/lang/String;Ljava/lang/String;)V
     103: aload         5
     105: ldc           #79                 // String Accept
     107: ldc           #77                 // String application/dns-message
     109: invokevirtual #78                 // Method java/net/HttpURLConnection.setRequestProperty:(Ljava/lang/String;Ljava/lang/String;)V
     112: aload_0
     113: getfield      #6                  // Field org/xbill/DNS/DohResolver.usePost:Z
     116: ifeq          134
     119: aload         5
     121: iconst_1
     122: invokevirtual #80                 // Method java/net/HttpURLConnection.setDoOutput:(Z)V
     125: aload         5
     127: invokevirtual #81                 // Method java/net/HttpURLConnection.getOutputStream:()Ljava/io/OutputStream;
     130: aload_2
     131: invokevirtual #82                 // Method java/io/OutputStream.write:([B)V
     134: aload         5
     136: invokevirtual #83                 // Method java/net/HttpURLConnection.getResponseCode:()I
     139: istore        7
     141: iload         7
     143: sipush        200
     146: if_icmplt     157
     149: iload         7
     151: sipush        300
     154: if_icmplt     185
     157: aload_0
     158: aload         5
     160: invokevirtual #84                 // Method java/net/HttpURLConnection.getInputStream:()Ljava/io/InputStream;
     163: invokespecial #85                 // Method org/xbill/DNS/DohResolver.discardStream:(Ljava/io/InputStream;)V
     166: aload_0
     167: aload         5
     169: invokevirtual #86                 // Method java/net/HttpURLConnection.getErrorStream:()Ljava/io/InputStream;
     172: invokespecial #85                 // Method org/xbill/DNS/DohResolver.discardStream:(Ljava/io/InputStream;)V
     175: new           #381                // class org/xbill/DNS/DohResolver$SendAndGetMessageBytesResponse
     178: dup
     179: iconst_2
     180: aconst_null
     181: invokespecial #89                 // Method org/xbill/DNS/DohResolver$SendAndGetMessageBytesResponse."<init>":(I[B)V
     184: areturn
     185: aload         5
     187: invokevirtual #84                 // Method java/net/HttpURLConnection.getInputStream:()Ljava/io/InputStream;
     190: astore        8
     192: aconst_null
     193: astore        9
     195: aload         5
     197: invokevirtual #90                 // Method java/net/HttpURLConnection.getContentLength:()I
     200: istore        10
     202: iload         10
     204: iconst_m1
     205: if_icmple     349
     208: aload         5
     210: invokevirtual #90                 // Method java/net/HttpURLConnection.getContentLength:()I
     213: newarray       byte
     215: astore        11
     217: iconst_0
     218: istore        13
     220: aload         8
     222: aload         11
     224: iload         13
     226: aload         11
     228: arraylength
     229: iload         13
     231: isub
     232: invokevirtual #91                 // Method java/io/InputStream.read:([BII)I
     235: dup
     236: istore        12
     238: ifle          281
     241: iload         13
     243: iload         12
     245: iadd
     246: istore        13
     248: aload_0
     249: getfield      #10                 // Field org/xbill/DNS/DohResolver.timeout:Ljava/time/Duration;
     252: invokestatic  #55                 // Method java/lang/System.nanoTime:()J
     255: lload_3
     256: lsub
     257: getstatic     #67                 // Field java/time/temporal/ChronoUnit.NANOS:Ljava/time/temporal/ChronoUnit;
     260: invokevirtual #68                 // Method java/time/Duration.minus:(JLjava/time/temporal/TemporalUnit;)Ljava/time/Duration;
     263: astore        6
     265: aload         6
     267: invokevirtual #92                 // Method java/time/Duration.isNegative:()Z
     270: ifeq          220
     273: new           #470                // class java/net/SocketTimeoutException
     276: dup
     277: invokespecial #94                 // Method java/net/SocketTimeoutException."<init>":()V
     280: athrow
     281: iload         13
     283: aload         11
     285: arraylength
     286: if_icmpge     299
     289: new           #95                 // class java/io/EOFException
     292: dup
     293: ldc           #96                 // String Could not read expected content length
     295: invokespecial #97                 // Method java/io/EOFException."<init>":(Ljava/lang/String;)V
     298: athrow
     299: new           #381                // class org/xbill/DNS/DohResolver$SendAndGetMessageBytesResponse
     302: dup
     303: iconst_0
     304: aload         11
     306: invokespecial #89                 // Method org/xbill/DNS/DohResolver$SendAndGetMessageBytesResponse."<init>":(I[B)V
     309: astore        14
     311: aload         8
     313: ifnull        346
     316: aload         9
     318: ifnull        341
     321: aload         8
     323: invokevirtual #98                 // Method java/io/InputStream.close:()V
     326: goto          346
     329: astore        15
     331: aload         9
     333: aload         15
     335: invokevirtual #99                 // Method java/lang/Throwable.addSuppressed:(Ljava/lang/Throwable;)V
     338: goto          346
     341: aload         8
     343: invokevirtual #98                 // Method java/io/InputStream.close:()V
     346: aload         14
     348: areturn
     349: new           #382                // class java/io/ByteArrayOutputStream
     352: dup
     353: invokespecial #101                // Method java/io/ByteArrayOutputStream."<init>":()V
     356: astore        11
     358: aconst_null
     359: astore        12
     361: sipush        4096
     364: newarray       byte
     366: astore        13
     368: aload         8
     370: aload         13
     372: iconst_0
     373: aload         13
     375: arraylength
     376: invokevirtual #91                 // Method java/io/InputStream.read:([BII)I
     379: dup
     380: istore        14
     382: ifle          431
     385: aload_0
     386: getfield      #10                 // Field org/xbill/DNS/DohResolver.timeout:Ljava/time/Duration;
     389: invokestatic  #55                 // Method java/lang/System.nanoTime:()J
     392: lload_3
     393: lsub
     394: getstatic     #67                 // Field java/time/temporal/ChronoUnit.NANOS:Ljava/time/temporal/ChronoUnit;
     397: invokevirtual #68                 // Method java/time/Duration.minus:(JLjava/time/temporal/TemporalUnit;)Ljava/time/Duration;
     400: astore        6
     402: aload         6
     404: invokevirtual #92                 // Method java/time/Duration.isNegative:()Z
     407: ifeq          418
     410: new           #470                // class java/net/SocketTimeoutException
     413: dup
     414: invokespecial #94                 // Method java/net/SocketTimeoutException."<init>":()V
     417: athrow
     418: aload         11
     420: aload         13
     422: iconst_0
     423: iload         14
     425: invokevirtual #102                // Method java/io/ByteArrayOutputStream.write:([BII)V
     428: goto          368
     431: new           #381                // class org/xbill/DNS/DohResolver$SendAndGetMessageBytesResponse
     434: dup
     435: iconst_0
     436: aload         11
     438: invokevirtual #103                // Method java/io/ByteArrayOutputStream.toByteArray:()[B
     441: invokespecial #89                 // Method org/xbill/DNS/DohResolver$SendAndGetMessageBytesResponse."<init>":(I[B)V
     444: astore        15
     446: aload         11
     448: ifnull        481
     451: aload         12
     453: ifnull        476
     456: aload         11
     458: invokevirtual #104                // Method java/io/ByteArrayOutputStream.close:()V
     461: goto          481
     464: astore        16
     466: aload         12
     468: aload         16
     470: invokevirtual #99                 // Method java/lang/Throwable.addSuppressed:(Ljava/lang/Throwable;)V
     473: goto          481
     476: aload         11
     478: invokevirtual #104                // Method java/io/ByteArrayOutputStream.close:()V
     481: aload         8
     483: ifnull        516
     486: aload         9
     488: ifnull        511
     491: aload         8
     493: invokevirtual #98                 // Method java/io/InputStream.close:()V
     496: goto          516
     499: astore        16
     501: aload         9
     503: aload         16
     505: invokevirtual #99                 // Method java/lang/Throwable.addSuppressed:(Ljava/lang/Throwable;)V
     508: goto          516
     511: aload         8
     513: invokevirtual #98                 // Method java/io/InputStream.close:()V
     516: aload         15
     518: areturn
     519: astore        13
     521: aload         13
     523: astore        12
     525: aload         13
     527: athrow
     528: astore        17
     530: aload         11
     532: ifnull        565
     535: aload         12
     537: ifnull        560
     540: aload         11
     542: invokevirtual #104                // Method java/io/ByteArrayOutputStream.close:()V
     545: goto          565
     548: astore        18
     550: aload         12
     552: aload         18
     554: invokevirtual #99                 // Method java/lang/Throwable.addSuppressed:(Ljava/lang/Throwable;)V
     557: goto          565
     560: aload         11
     562: invokevirtual #104                // Method java/io/ByteArrayOutputStream.close:()V
     565: aload         17
     567: athrow
     568: astore        10
     570: aload         10
     572: astore        9
     574: aload         10
     576: athrow
     577: astore        19
     579: aload         8
     581: ifnull        614
     584: aload         9
     586: ifnull        609
     589: aload         8
     591: invokevirtual #98                 // Method java/io/InputStream.close:()V
     594: goto          614
     597: astore        20
     599: aload         9
     601: aload         20
     603: invokevirtual #99                 // Method java/lang/Throwable.addSuppressed:(Ljava/lang/Throwable;)V
     606: goto          614
     609: aload         8
     611: invokevirtual #98                 // Method java/io/InputStream.close:()V
     614: aload         19
     616: athrow
     617: astore        8
     619: aload_0
     620: aload         5
     622: invokevirtual #86                 // Method java/net/HttpURLConnection.getErrorStream:()Ljava/io/InputStream;
     625: invokespecial #85                 // Method org/xbill/DNS/DohResolver.discardStream:(Ljava/io/InputStream;)V
     628: aload         8
     630: athrow
    Exception table:
       from    to  target type
         321   326   329   Class java/lang/Throwable
         456   461   464   Class java/lang/Throwable
         491   496   499   Class java/lang/Throwable
         361   446   519   Class java/lang/Throwable
         361   446   528   any
         540   545   548   Class java/lang/Throwable
         519   530   528   any
         195   311   568   Class java/lang/Throwable
         349   481   568   Class java/lang/Throwable
         519   568   568   Class java/lang/Throwable
         195   311   577   any
         349   481   577   any
         589   594   597   Class java/lang/Throwable
         519   579   577   any
         185   346   617   Class java/io/IOException
         349   516   617   Class java/io/IOException
         519   617   617   Class java/io/IOException

  private void discardStream(java.io.InputStream) throws java.io.IOException;
    Code:
       0: aload_1
       1: ifnull        107
       4: aload_1
       5: astore_2
       6: aconst_null
       7: astore_3
       8: sipush        4096
      11: newarray       byte
      13: astore        4
      15: aload_2
      16: aload         4
      18: invokevirtual #106                // Method java/io/InputStream.read:([B)I
      21: ifle          27
      24: goto          15
      27: aload_2
      28: ifnull        103
      31: aload_3
      32: ifnull        53
      35: aload_2
      36: invokevirtual #98                 // Method java/io/InputStream.close:()V
      39: goto          103
      42: astore        4
      44: aload_3
      45: aload         4
      47: invokevirtual #99                 // Method java/lang/Throwable.addSuppressed:(Ljava/lang/Throwable;)V
      50: goto          103
      53: aload_2
      54: invokevirtual #98                 // Method java/io/InputStream.close:()V
      57: goto          103
      60: astore        4
      62: aload         4
      64: astore_3
      65: aload         4
      67: athrow
      68: astore        5
      70: aload_2
      71: ifnull        100
      74: aload_3
      75: ifnull        96
      78: aload_2
      79: invokevirtual #98                 // Method java/io/InputStream.close:()V
      82: goto          100
      85: astore        6
      87: aload_3
      88: aload         6
      90: invokevirtual #99                 // Method java/lang/Throwable.addSuppressed:(Ljava/lang/Throwable;)V
      93: goto          100
      96: aload_2
      97: invokevirtual #98                 // Method java/io/InputStream.close:()V
     100: aload         5
     102: athrow
     103: goto          107
     106: astore_2
     107: return
    Exception table:
       from    to  target type
          35    39    42   Class java/lang/Throwable
           8    27    60   Class java/lang/Throwable
           8    27    68   any
          78    82    85   Class java/lang/Throwable
          60    70    68   any
           4   103   106   Class java/io/IOException

  private java.util.concurrent.CompletionStage<org.xbill.DNS.Message> sendAsync11(org.xbill.DNS.Message, java.util.concurrent.Executor);
    Code:
       0: invokestatic  #55                 // Method java/lang/System.nanoTime:()J
       3: lstore_3
       4: aload_0
       5: aload_1
       6: invokespecial #52                 // Method org/xbill/DNS/DohResolver.prepareQuery:(Lorg/xbill/DNS/Message;)Lorg/xbill/DNS/Message;
       9: invokevirtual #53                 // Method org/xbill/DNS/Message.toWire:()[B
      12: astore        5
      14: aload_0
      15: aload         5
      17: invokespecial #54                 // Method org/xbill/DNS/DohResolver.getUrl:([B)Ljava/lang/String;
      20: astore        6
      22: getstatic     #107                // Field org/xbill/DNS/DohResolver.requestBuilderCopyMethod:Ljava/lang/reflect/Method;
      25: getstatic     #108                // Field org/xbill/DNS/DohResolver.defaultHttpRequestBuilder:Ljava/lang/Object;
      28: iconst_0
      29: anewarray     #395                // class java/lang/Object
      32: invokevirtual #110                // Method java/lang/reflect/Method.invoke:(Ljava/lang/Object;[Ljava/lang/Object;)Ljava/lang/Object;
      35: astore        7
      37: getstatic     #111                // Field org/xbill/DNS/DohResolver.requestBuilderUriMethod:Ljava/lang/reflect/Method;
      40: aload         7
      42: iconst_1
      43: anewarray     #395                // class java/lang/Object
      46: dup
      47: iconst_0
      48: aload         6
      50: invokestatic  #112                // Method java/net/URI.create:(Ljava/lang/String;)Ljava/net/URI;
      53: aastore
      54: invokevirtual #110                // Method java/lang/reflect/Method.invoke:(Ljava/lang/Object;[Ljava/lang/Object;)Ljava/lang/Object;
      57: pop
      58: aload_0
      59: getfield      #6                  // Field org/xbill/DNS/DohResolver.usePost:Z
      62: ifeq          97
      65: getstatic     #113                // Field org/xbill/DNS/DohResolver.requestBuilderPostMethod:Ljava/lang/reflect/Method;
      68: aload         7
      70: iconst_1
      71: anewarray     #395                // class java/lang/Object
      74: dup
      75: iconst_0
      76: getstatic     #114                // Field org/xbill/DNS/DohResolver.publisherOfByteArrayMethod:Ljava/lang/reflect/Method;
      79: aconst_null
      80: iconst_1
      81: anewarray     #395                // class java/lang/Object
      84: dup
      85: iconst_0
      86: aload         5
      88: aastore
      89: invokevirtual #110                // Method java/lang/reflect/Method.invoke:(Ljava/lang/Object;[Ljava/lang/Object;)Ljava/lang/Object;
      92: aastore
      93: invokevirtual #110                // Method java/lang/reflect/Method.invoke:(Ljava/lang/Object;[Ljava/lang/Object;)Ljava/lang/Object;
      96: pop
      97: goto          109
     100: astore        8
     102: aload_0
     103: aload         8
     105: invokespecial #117                // Method org/xbill/DNS/DohResolver.failedFuture:(Ljava/lang/Throwable;)Ljava/util/concurrent/CompletableFuture;
     108: areturn
     109: aload_0
     110: getfield      #10                 // Field org/xbill/DNS/DohResolver.timeout:Ljava/time/Duration;
     113: invokestatic  #55                 // Method java/lang/System.nanoTime:()J
     116: lload_3
     117: lsub
     118: getstatic     #67                 // Field java/time/temporal/ChronoUnit.NANOS:Ljava/time/temporal/ChronoUnit;
     121: invokevirtual #68                 // Method java/time/Duration.minus:(JLjava/time/temporal/TemporalUnit;)Ljava/time/Duration;
     124: astore        8
     126: aload_0
     127: getfield      #21                 // Field org/xbill/DNS/DohResolver.initialRequestLock:Lorg/xbill/DNS/AsyncSemaphore;
     130: aload         8
     132: invokevirtual #56                 // Method org/xbill/DNS/AsyncSemaphore.acquire:(Ljava/time/Duration;)Ljava/util/concurrent/CompletionStage;
     135: aload_0
     136: aload_1
     137: aload_2
     138: lload_3
     139: aload         7
     141: invokedynamic #118,  0            // InvokeDynamic #2:apply:(Lorg/xbill/DNS/DohResolver;Lorg/xbill/DNS/Message;Ljava/util/concurrent/Executor;JLjava/lang/Object;)Ljava/util/function/BiFunction;
     146: invokeinterface #119,  2          // InterfaceMethod java/util/concurrent/CompletionStage.handle:(Ljava/util/function/BiFunction;)Ljava/util/concurrent/CompletionStage;
     151: invokestatic  #59                 // InterfaceMethod java/util/function/Function.identity:()Ljava/util/function/Function;
     154: invokeinterface #60,  2           // InterfaceMethod java/util/concurrent/CompletionStage.thenCompose:(Ljava/util/function/Function;)Ljava/util/concurrent/CompletionStage;
     159: areturn
    Exception table:
       from    to  target type
          22    97   100   Class java/lang/IllegalAccessException
          22    97   100   Class java/lang/reflect/InvocationTargetException

  private java.util.concurrent.CompletionStage<org.xbill.DNS.Message> sendAsync11WithInitialRequestPermit(org.xbill.DNS.Message, java.util.concurrent.Executor, long, java.lang.Object, org.xbill.DNS.AsyncSemaphore$Permit);
    Code:
       0: aload_0
       1: getfield      #18                 // Field org/xbill/DNS/DohResolver.lastRequest:Ljava/util/concurrent/atomic/AtomicLong;
       4: invokevirtual #120                // Method java/util/concurrent/atomic/AtomicLong.get:()J
       7: lstore        7
       9: lload         7
      11: invokestatic  #55                 // Method java/lang/System.nanoTime:()J
      14: aload_0
      15: getfield      #23                 // Field org/xbill/DNS/DohResolver.idleConnectionTimeout:Ljava/time/Duration;
      18: invokevirtual #121                // Method java/time/Duration.toNanos:()J
      21: lsub
      22: lcmp
      23: ifge          30
      26: iconst_1
      27: goto          31
      30: iconst_0
      31: istore        9
      33: iload         9
      35: ifne          43
      38: aload         6
      40: invokevirtual #122                // Method org/xbill/DNS/AsyncSemaphore$Permit.release:()V
      43: aload_0
      44: getfield      #10                 // Field org/xbill/DNS/DohResolver.timeout:Ljava/time/Duration;
      47: invokestatic  #55                 // Method java/lang/System.nanoTime:()J
      50: lload_3
      51: lsub
      52: getstatic     #67                 // Field java/time/temporal/ChronoUnit.NANOS:Ljava/time/temporal/ChronoUnit;
      55: invokevirtual #68                 // Method java/time/Duration.minus:(JLjava/time/temporal/TemporalUnit;)Ljava/time/Duration;
      58: astore        10
      60: aload         10
      62: invokevirtual #92                 // Method java/time/Duration.isNegative:()Z
      65: ifeq          85
      68: iload         9
      70: ifeq          78
      73: aload         6
      75: invokevirtual #122                // Method org/xbill/DNS/AsyncSemaphore$Permit.release:()V
      78: aload_0
      79: aload_1
      80: aconst_null
      81: invokespecial #123                // Method org/xbill/DNS/DohResolver.timeoutFailedFuture:(Lorg/xbill/DNS/Message;Ljava/lang/Throwable;)Ljava/util/concurrent/CompletableFuture;
      84: areturn
      85: aload_0
      86: getfield      #33                 // Field org/xbill/DNS/DohResolver.maxConcurrentRequests:Lorg/xbill/DNS/AsyncSemaphore;
      89: aload         10
      91: invokevirtual #56                 // Method org/xbill/DNS/AsyncSemaphore.acquire:(Ljava/time/Duration;)Ljava/util/concurrent/CompletionStage;
      94: aload_0
      95: iload         9
      97: aload         6
      99: aload_1
     100: aload_2
     101: lload_3
     102: aload         5
     104: invokedynamic #124,  0            // InvokeDynamic #3:apply:(Lorg/xbill/DNS/DohResolver;ZLorg/xbill/DNS/AsyncSemaphore$Permit;Lorg/xbill/DNS/Message;Ljava/util/concurrent/Executor;JLjava/lang/Object;)Ljava/util/function/BiFunction;
     109: invokeinterface #119,  2          // InterfaceMethod java/util/concurrent/CompletionStage.handle:(Ljava/util/function/BiFunction;)Ljava/util/concurrent/CompletionStage;
     114: invokestatic  #59                 // InterfaceMethod java/util/function/Function.identity:()Ljava/util/function/Function;
     117: invokeinterface #60,  2           // InterfaceMethod java/util/concurrent/CompletionStage.thenCompose:(Ljava/util/function/Function;)Ljava/util/concurrent/CompletionStage;
     122: areturn

  private java.util.concurrent.CompletionStage<org.xbill.DNS.Message> sendAsync11WithConcurrentRequestPermit(org.xbill.DNS.Message, java.util.concurrent.Executor, long, java.lang.Object, org.xbill.DNS.AsyncSemaphore$Permit, boolean, org.xbill.DNS.AsyncSemaphore$Permit);
    Code:
       0: aload_0
       1: getfield      #10                 // Field org/xbill/DNS/DohResolver.timeout:Ljava/time/Duration;
       4: invokestatic  #55                 // Method java/lang/System.nanoTime:()J
       7: lload_3
       8: lsub
       9: getstatic     #67                 // Field java/time/temporal/ChronoUnit.NANOS:Ljava/time/temporal/ChronoUnit;
      12: invokevirtual #68                 // Method java/time/Duration.minus:(JLjava/time/temporal/TemporalUnit;)Ljava/time/Duration;
      15: astore        9
      17: aload         9
      19: invokevirtual #92                 // Method java/time/Duration.isNegative:()Z
      22: ifeq          47
      25: iload         7
      27: ifeq          35
      30: aload         6
      32: invokevirtual #122                // Method org/xbill/DNS/AsyncSemaphore$Permit.release:()V
      35: aload         8
      37: invokevirtual #122                // Method org/xbill/DNS/AsyncSemaphore$Permit.release:()V
      40: aload_0
      41: aload_1
      42: aconst_null
      43: invokespecial #123                // Method org/xbill/DNS/DohResolver.timeoutFailedFuture:(Lorg/xbill/DNS/Message;Ljava/lang/Throwable;)Ljava/util/concurrent/CompletableFuture;
      46: areturn
      47: aload_0
      48: aload_2
      49: invokespecial #125                // Method org/xbill/DNS/DohResolver.getHttpClient:(Ljava/util/concurrent/Executor;)Ljava/lang/Object;
      52: astore        10
      54: getstatic     #126                // Field org/xbill/DNS/DohResolver.requestBuilderTimeoutMethod:Ljava/lang/reflect/Method;
      57: aload         5
      59: iconst_1
      60: anewarray     #395                // class java/lang/Object
      63: dup
      64: iconst_0
      65: aload         9
      67: aastore
      68: invokevirtual #110                // Method java/lang/reflect/Method.invoke:(Ljava/lang/Object;[Ljava/lang/Object;)Ljava/lang/Object;
      71: pop
      72: getstatic     #127                // Field org/xbill/DNS/DohResolver.requestBuilderBuildMethod:Ljava/lang/reflect/Method;
      75: aload         5
      77: iconst_0
      78: anewarray     #395                // class java/lang/Object
      81: invokevirtual #110                // Method java/lang/reflect/Method.invoke:(Ljava/lang/Object;[Ljava/lang/Object;)Ljava/lang/Object;
      84: astore        11
      86: getstatic     #128                // Field org/xbill/DNS/DohResolver.byteArrayBodyPublisherMethod:Ljava/lang/reflect/Method;
      89: aconst_null
      90: iconst_0
      91: anewarray     #395                // class java/lang/Object
      94: invokevirtual #110                // Method java/lang/reflect/Method.invoke:(Ljava/lang/Object;[Ljava/lang/Object;)Ljava/lang/Object;
      97: astore        12
      99: getstatic     #129                // Field org/xbill/DNS/DohResolver.httpClientSendAsyncMethod:Ljava/lang/reflect/Method;
     102: aload         10
     104: iconst_2
     105: anewarray     #395                // class java/lang/Object
     108: dup
     109: iconst_0
     110: aload         11
     112: aastore
     113: dup
     114: iconst_1
     115: aload         12
     117: aastore
     118: invokevirtual #110                // Method java/lang/reflect/Method.invoke:(Ljava/lang/Object;[Ljava/lang/Object;)Ljava/lang/Object;
     121: checkcast     #130                // class java/util/concurrent/CompletableFuture
     124: aload_0
     125: lload_3
     126: aload         8
     128: iload         7
     130: aload         6
     132: invokedynamic #131,  0            // InvokeDynamic #4:accept:(Lorg/xbill/DNS/DohResolver;JLorg/xbill/DNS/AsyncSemaphore$Permit;ZLorg/xbill/DNS/AsyncSemaphore$Permit;)Ljava/util/function/BiConsumer;
     137: invokevirtual #132                // Method java/util/concurrent/CompletableFuture.whenComplete:(Ljava/util/function/BiConsumer;)Ljava/util/concurrent/CompletableFuture;
     140: aload_0
     141: aload_1
     142: invokedynamic #133,  0            // InvokeDynamic #5:apply:(Lorg/xbill/DNS/DohResolver;Lorg/xbill/DNS/Message;)Ljava/util/function/BiFunction;
     147: aload_2
     148: invokevirtual #134                // Method java/util/concurrent/CompletableFuture.handleAsync:(Ljava/util/function/BiFunction;Ljava/util/concurrent/Executor;)Ljava/util/concurrent/CompletableFuture;
     151: invokestatic  #59                 // InterfaceMethod java/util/function/Function.identity:()Ljava/util/function/Function;
     154: invokevirtual #135                // Method java/util/concurrent/CompletableFuture.thenCompose:(Ljava/util/function/Function;)Ljava/util/concurrent/CompletableFuture;
     157: astore        13
     159: aload         13
     161: aload         9
     163: invokevirtual #69                 // Method java/time/Duration.toMillis:()J
     166: getstatic     #136                // Field java/util/concurrent/TimeUnit.MILLISECONDS:Ljava/util/concurrent/TimeUnit;
     169: invokestatic  #137                // Method org/xbill/DNS/TimeoutCompletableFuture.compatTimeout:(Ljava/util/concurrent/CompletableFuture;JLjava/util/concurrent/TimeUnit;)Ljava/util/concurrent/CompletableFuture;
     172: areturn
     173: astore        10
     175: aload_0
     176: aload         10
     178: invokespecial #117                // Method org/xbill/DNS/DohResolver.failedFuture:(Ljava/lang/Throwable;)Ljava/util/concurrent/CompletableFuture;
     181: areturn
    Exception table:
       from    to  target type
          47   172   173   Class java/lang/IllegalAccessException
          47   172   173   Class java/lang/reflect/InvocationTargetException

  private <T> java.util.concurrent.CompletableFuture<T> failedFuture(java.lang.Throwable);
    Code:
       0: new           #130                // class java/util/concurrent/CompletableFuture
       3: dup
       4: invokespecial #138                // Method java/util/concurrent/CompletableFuture."<init>":()V
       7: astore_2
       8: aload_2
       9: aload_1
      10: invokevirtual #139                // Method java/util/concurrent/CompletableFuture.completeExceptionally:(Ljava/lang/Throwable;)Z
      13: pop
      14: aload_2
      15: areturn

  private <T> java.util.concurrent.CompletableFuture<T> timeoutFailedFuture(org.xbill.DNS.Message, java.lang.Throwable);
    Code:
       0: aload_0
       1: new           #383                // class java/io/IOException
       4: dup
       5: new           #448                // class java/lang/StringBuilder
       8: dup
       9: invokespecial #141                // Method java/lang/StringBuilder."<init>":()V
      12: ldc           #142                // String Query
      14: invokevirtual #143                // Method java/lang/StringBuilder.append:(Ljava/lang/String;)Ljava/lang/StringBuilder;
      17: aload_1
      18: invokevirtual #144                // Method org/xbill/DNS/Message.getHeader:()Lorg/xbill/DNS/Header;
      21: invokevirtual #145                // Method org/xbill/DNS/Header.getID:()I
      24: invokevirtual #146                // Method java/lang/StringBuilder.append:(I)Ljava/lang/StringBuilder;
      27: ldc           #147                // String  for
      29: invokevirtual #143                // Method java/lang/StringBuilder.append:(Ljava/lang/String;)Ljava/lang/StringBuilder;
      32: aload_1
      33: invokevirtual #148                // Method org/xbill/DNS/Message.getQuestion:()Lorg/xbill/DNS/Record;
      36: invokevirtual #149                // Method org/xbill/DNS/Record.getName:()Lorg/xbill/DNS/Name;
      39: invokevirtual #150                // Method java/lang/StringBuilder.append:(Ljava/lang/Object;)Ljava/lang/StringBuilder;
      42: ldc           #151                // String /
      44: invokevirtual #143                // Method java/lang/StringBuilder.append:(Ljava/lang/String;)Ljava/lang/StringBuilder;
      47: aload_1
      48: invokevirtual #148                // Method org/xbill/DNS/Message.getQuestion:()Lorg/xbill/DNS/Record;
      51: invokevirtual #152                // Method org/xbill/DNS/Record.getType:()I
      54: invokestatic  #153                // Method org/xbill/DNS/Type.string:(I)Ljava/lang/String;
      57: invokevirtual #143                // Method java/lang/StringBuilder.append:(Ljava/lang/String;)Ljava/lang/StringBuilder;
      60: ldc           #154                // String  timed out
      62: invokevirtual #143                // Method java/lang/StringBuilder.append:(Ljava/lang/String;)Ljava/lang/StringBuilder;
      65: invokevirtual #155                // Method java/lang/StringBuilder.toString:()Ljava/lang/String;
      68: aload_2
      69: invokespecial #156                // Method java/io/IOException."<init>":(Ljava/lang/String;Ljava/lang/Throwable;)V
      72: invokespecial #117                // Method org/xbill/DNS/DohResolver.failedFuture:(Ljava/lang/Throwable;)Ljava/util/concurrent/CompletableFuture;
      75: areturn

  private java.lang.String getUrl(byte[]);
    Code:
       0: aload_0
       1: getfield      #22                 // Field org/xbill/DNS/DohResolver.uriTemplate:Ljava/lang/String;
       4: astore_2
       5: aload_0
       6: getfield      #6                  // Field org/xbill/DNS/DohResolver.usePost:Z
       9: ifne          40
      12: new           #448                // class java/lang/StringBuilder
      15: dup
      16: invokespecial #141                // Method java/lang/StringBuilder."<init>":()V
      19: aload_2
      20: invokevirtual #143                // Method java/lang/StringBuilder.append:(Ljava/lang/String;)Ljava/lang/StringBuilder;
      23: ldc           #157                // String ?dns=
      25: invokevirtual #143                // Method java/lang/StringBuilder.append:(Ljava/lang/String;)Ljava/lang/StringBuilder;
      28: aload_1
      29: iconst_1
      30: invokestatic  #158                // Method org/xbill/DNS/utils/base64.toString:([BZ)Ljava/lang/String;
      33: invokevirtual #143                // Method java/lang/StringBuilder.append:(Ljava/lang/String;)Ljava/lang/StringBuilder;
      36: invokevirtual #155                // Method java/lang/StringBuilder.toString:()Ljava/lang/String;
      39: astore_2
      40: aload_2
      41: areturn

  private org.xbill.DNS.Message prepareQuery(org.xbill.DNS.Message);
    Code:
       0: aload_1
       1: invokevirtual #159                // Method org/xbill/DNS/Message.clone:()Lorg/xbill/DNS/Message;
       4: astore_2
       5: aload_2
       6: invokevirtual #144                // Method org/xbill/DNS/Message.getHeader:()Lorg/xbill/DNS/Header;
       9: iconst_0
      10: invokevirtual #160                // Method org/xbill/DNS/Header.setID:(I)V
      13: aload_0
      14: getfield      #13                 // Field org/xbill/DNS/DohResolver.queryOPT:Lorg/xbill/DNS/OPTRecord;
      17: ifnull        36
      20: aload_2
      21: invokevirtual #161                // Method org/xbill/DNS/Message.getOPT:()Lorg/xbill/DNS/OPTRecord;
      24: ifnonnull     36
      27: aload_2
      28: aload_0
      29: getfield      #13                 // Field org/xbill/DNS/DohResolver.queryOPT:Lorg/xbill/DNS/OPTRecord;
      32: iconst_3
      33: invokevirtual #163                // Method org/xbill/DNS/Message.addRecord:(Lorg/xbill/DNS/Record;I)V
      36: aload_0
      37: getfield      #47                 // Field org/xbill/DNS/DohResolver.tsig:Lorg/xbill/DNS/TSIG;
      40: ifnull        52
      43: aload_0
      44: getfield      #47                 // Field org/xbill/DNS/DohResolver.tsig:Lorg/xbill/DNS/TSIG;
      47: aload_2
      48: aconst_null
      49: invokevirtual #164                // Method org/xbill/DNS/TSIG.apply:(Lorg/xbill/DNS/Message;Lorg/xbill/DNS/TSIGRecord;)V
      52: aload_2
      53: areturn

  private void verifyTSIG(org.xbill.DNS.Message, org.xbill.DNS.Message, byte[], org.xbill.DNS.TSIG);
    Code:
       0: aload         4
       2: ifnonnull     6
       5: return
       6: aload         4
       8: aload_2
       9: aload_3
      10: aload_1
      11: invokevirtual #165                // Method org/xbill/DNS/Message.getGeneratedTSIG:()Lorg/xbill/DNS/TSIGRecord;
      14: invokevirtual #166                // Method org/xbill/DNS/TSIG.verify:(Lorg/xbill/DNS/Message;[BLorg/xbill/DNS/TSIGRecord;)I
      17: istore        5
      19: getstatic     #167                // Field org/xbill/DNS/DohResolver.log:Lorg/slf4j/Logger;
      22: ldc           #168                // String TSIG verify for query {}, {}/{}: {}
      24: iconst_4
      25: anewarray     #395                // class java/lang/Object
      28: dup
      29: iconst_0
      30: aload_1
      31: invokevirtual #144                // Method org/xbill/DNS/Message.getHeader:()Lorg/xbill/DNS/Header;
      34: invokevirtual #145                // Method org/xbill/DNS/Header.getID:()I
      37: invokestatic  #169                // Method java/lang/Integer.valueOf:(I)Ljava/lang/Integer;
      40: aastore
      41: dup
      42: iconst_1
      43: aload_1
      44: invokevirtual #148                // Method org/xbill/DNS/Message.getQuestion:()Lorg/xbill/DNS/Record;
      47: invokevirtual #149                // Method org/xbill/DNS/Record.getName:()Lorg/xbill/DNS/Name;
      50: aastore
      51: dup
      52: iconst_2
      53: aload_1
      54: invokevirtual #148                // Method org/xbill/DNS/Message.getQuestion:()Lorg/xbill/DNS/Record;
      57: invokevirtual #152                // Method org/xbill/DNS/Record.getType:()I
      60: invokestatic  #153                // Method org/xbill/DNS/Type.string:(I)Ljava/lang/String;
      63: aastore
      64: dup
      65: iconst_3
      66: iload         5
      68: invokestatic  #170                // Method org/xbill/DNS/Rcode.TSIGstring:(I)Ljava/lang/String;
      71: aastore
      72: invokeinterface #171,  3          // InterfaceMethod org/slf4j/Logger.debug:(Ljava/lang/String;[Ljava/lang/Object;)V
      77: return

  public boolean isUsePost();
    Code:
       0: aload_0
       1: getfield      #6                  // Field org/xbill/DNS/DohResolver.usePost:Z
       4: ireturn

  public void setUsePost(boolean);
    Code:
       0: aload_0
       1: iload_1
       2: putfield      #6                  // Field org/xbill/DNS/DohResolver.usePost:Z
       5: return

  public java.lang.String getUriTemplate();
    Code:
       0: aload_0
       1: getfield      #22                 // Field org/xbill/DNS/DohResolver.uriTemplate:Ljava/lang/String;
       4: areturn

  public void setUriTemplate(java.lang.String);
    Code:
       0: aload_0
       1: aload_1
       2: putfield      #22                 // Field org/xbill/DNS/DohResolver.uriTemplate:Ljava/lang/String;
       5: return

  public java.util.concurrent.Executor getExecutor();
    Code:
       0: aload_0
       1: getfield      #15                 // Field org/xbill/DNS/DohResolver.defaultExecutor:Ljava/util/concurrent/Executor;
       4: areturn

  public void setExecutor(java.util.concurrent.Executor);
    Code:
       0: aload_0
       1: aload_1
       2: ifnonnull     11
       5: invokestatic  #14                 // Method java/util/concurrent/ForkJoinPool.commonPool:()Ljava/util/concurrent/ForkJoinPool;
       8: goto          12
      11: aload_1
      12: putfield      #15                 // Field org/xbill/DNS/DohResolver.defaultExecutor:Ljava/util/concurrent/Executor;
      15: getstatic     #40                 // Field org/xbill/DNS/DohResolver.httpClients:Ljava/util/Map;
      18: invokeinterface #48,  1           // InterfaceMethod java/util/Map.clear:()V
      23: return

  public java.lang.String toString();
    Code:
       0: new           #448                // class java/lang/StringBuilder
       3: dup
       4: invokespecial #141                // Method java/lang/StringBuilder."<init>":()V
       7: ldc           #172                // String DohResolver {
       9: invokevirtual #143                // Method java/lang/StringBuilder.append:(Ljava/lang/String;)Ljava/lang/StringBuilder;
      12: aload_0
      13: getfield      #6                  // Field org/xbill/DNS/DohResolver.usePost:Z
      16: ifeq          24
      19: ldc           #173                // String POST
      21: goto          26
      24: ldc           #174                // String GET
      26: invokevirtual #143                // Method java/lang/StringBuilder.append:(Ljava/lang/String;)Ljava/lang/StringBuilder;
      29: aload_0
      30: getfield      #22                 // Field org/xbill/DNS/DohResolver.uriTemplate:Ljava/lang/String;
      33: invokevirtual #143                // Method java/lang/StringBuilder.append:(Ljava/lang/String;)Ljava/lang/StringBuilder;
      36: ldc           #175                // String }
      38: invokevirtual #143                // Method java/lang/StringBuilder.append:(Ljava/lang/String;)Ljava/lang/StringBuilder;
      41: invokevirtual #155                // Method java/lang/StringBuilder.toString:()Ljava/lang/String;
      44: areturn

  private java.util.concurrent.CompletableFuture lambda$sendAsync11WithConcurrentRequestPermit$5(org.xbill.DNS.Message, java.lang.Object, java.lang.Throwable);
    Code:
       0: aload_3
       1: ifnull        38
       4: aload_3
       5: invokevirtual #176                // Method java/lang/Throwable.getCause:()Ljava/lang/Throwable;
       8: invokevirtual #177                // Method java/lang/Object.getClass:()Ljava/lang/Class;
      11: invokevirtual #178                // Method java/lang/Class.getSimpleName:()Ljava/lang/String;
      14: ldc           #179                // String HttpTimeoutException
      16: invokevirtual #180                // Method java/lang/String.equals:(Ljava/lang/Object;)Z
      19: ifeq          32
      22: aload_0
      23: aload_1
      24: aload_3
      25: invokevirtual #176                // Method java/lang/Throwable.getCause:()Ljava/lang/Throwable;
      28: invokespecial #123                // Method org/xbill/DNS/DohResolver.timeoutFailedFuture:(Lorg/xbill/DNS/Message;Ljava/lang/Throwable;)Ljava/util/concurrent/CompletableFuture;
      31: areturn
      32: aload_0
      33: aload_3
      34: invokespecial #117                // Method org/xbill/DNS/DohResolver.failedFuture:(Ljava/lang/Throwable;)Ljava/util/concurrent/CompletableFuture;
      37: areturn
      38: getstatic     #181                // Field org/xbill/DNS/DohResolver.httpResponseStatusCodeMethod:Ljava/lang/reflect/Method;
      41: aload_2
      42: iconst_0
      43: anewarray     #395                // class java/lang/Object
      46: invokevirtual #110                // Method java/lang/reflect/Method.invoke:(Ljava/lang/Object;[Ljava/lang/Object;)Ljava/lang/Object;
      49: checkcast     #182                // class java/lang/Integer
      52: invokevirtual #183                // Method java/lang/Integer.intValue:()I
      55: istore        5
      57: iload         5
      59: sipush        200
      62: if_icmplt     119
      65: iload         5
      67: sipush        300
      70: if_icmpge     119
      73: getstatic     #184                // Field org/xbill/DNS/DohResolver.httpResponseBodyMethod:Ljava/lang/reflect/Method;
      76: aload_2
      77: iconst_0
      78: anewarray     #395                // class java/lang/Object
      81: invokevirtual #110                // Method java/lang/reflect/Method.invoke:(Ljava/lang/Object;[Ljava/lang/Object;)Ljava/lang/Object;
      84: checkcast     #185                // class "[B"
      87: checkcast     #185                // class "[B"
      90: astore        6
      92: new           #393                // class org/xbill/DNS/Message
      95: dup
      96: aload         6
      98: invokespecial #187                // Method org/xbill/DNS/Message."<init>":([B)V
     101: astore        4
     103: aload_0
     104: aload_1
     105: aload         4
     107: aload         6
     109: aload_0
     110: getfield      #47                 // Field org/xbill/DNS/DohResolver.tsig:Lorg/xbill/DNS/TSIG;
     113: invokespecial #188                // Method org/xbill/DNS/DohResolver.verifyTSIG:(Lorg/xbill/DNS/Message;Lorg/xbill/DNS/Message;[BLorg/xbill/DNS/TSIG;)V
     116: goto          137
     119: new           #393                // class org/xbill/DNS/Message
     122: dup
     123: invokespecial #189                // Method org/xbill/DNS/Message."<init>":()V
     126: astore        4
     128: aload         4
     130: invokevirtual #144                // Method org/xbill/DNS/Message.getHeader:()Lorg/xbill/DNS/Header;
     133: iconst_2
     134: invokevirtual #190                // Method org/xbill/DNS/Header.setRcode:(I)V
     137: aload         4
     139: aload_0
     140: invokevirtual #191                // Method org/xbill/DNS/Message.setResolver:(Lorg/xbill/DNS/Resolver;)V
     143: aload         4
     145: invokestatic  #192                // Method java/util/concurrent/CompletableFuture.completedFuture:(Ljava/lang/Object;)Ljava/util/concurrent/CompletableFuture;
     148: areturn
     149: astore        4
     151: aload_0
     152: aload         4
     154: invokespecial #117                // Method org/xbill/DNS/DohResolver.failedFuture:(Ljava/lang/Throwable;)Ljava/util/concurrent/CompletableFuture;
     157: areturn
    Exception table:
       from    to  target type
          38   148   149   Class java/io/IOException
          38   148   149   Class java/lang/IllegalAccessException
          38   148   149   Class java/lang/reflect/InvocationTargetException

  private void lambda$sendAsync11WithConcurrentRequestPermit$4(long, org.xbill.DNS.AsyncSemaphore$Permit, boolean, org.xbill.DNS.AsyncSemaphore$Permit, java.lang.Object, java.lang.Throwable);
    Code:
       0: aload         7
       2: ifnonnull     13
       5: aload_0
       6: getfield      #18                 // Field org/xbill/DNS/DohResolver.lastRequest:Ljava/util/concurrent/atomic/AtomicLong;
       9: lload_1
      10: invokevirtual #193                // Method java/util/concurrent/atomic/AtomicLong.set:(J)V
      13: aload_3
      14: invokevirtual #122                // Method org/xbill/DNS/AsyncSemaphore$Permit.release:()V
      17: iload         4
      19: ifeq          27
      22: aload         5
      24: invokevirtual #122                // Method org/xbill/DNS/AsyncSemaphore$Permit.release:()V
      27: return

  private java.util.concurrent.CompletionStage lambda$sendAsync11WithInitialRequestPermit$3(boolean, org.xbill.DNS.AsyncSemaphore$Permit, org.xbill.DNS.Message, java.util.concurrent.Executor, long, java.lang.Object, org.xbill.DNS.AsyncSemaphore$Permit, java.lang.Throwable);
    Code:
       0: aload         9
       2: ifnull        21
       5: iload_1
       6: ifeq          13
       9: aload_2
      10: invokevirtual #122                // Method org/xbill/DNS/AsyncSemaphore$Permit.release:()V
      13: aload_0
      14: aload_3
      15: aload         9
      17: invokespecial #123                // Method org/xbill/DNS/DohResolver.timeoutFailedFuture:(Lorg/xbill/DNS/Message;Ljava/lang/Throwable;)Ljava/util/concurrent/CompletableFuture;
      20: areturn
      21: aload_0
      22: aload_3
      23: aload         4
      25: lload         5
      27: aload         7
      29: aload_2
      30: iload_1
      31: aload         8
      33: invokespecial #194                // Method org/xbill/DNS/DohResolver.sendAsync11WithConcurrentRequestPermit:(Lorg/xbill/DNS/Message;Ljava/util/concurrent/Executor;JLjava/lang/Object;Lorg/xbill/DNS/AsyncSemaphore$Permit;ZLorg/xbill/DNS/AsyncSemaphore$Permit;)Ljava/util/concurrent/CompletionStage;
      36: areturn

  private java.util.concurrent.CompletionStage lambda$sendAsync11$2(org.xbill.DNS.Message, java.util.concurrent.Executor, long, java.lang.Object, org.xbill.DNS.AsyncSemaphore$Permit, java.lang.Throwable);
    Code:
       0: aload         7
       2: ifnull        13
       5: aload_0
       6: aload_1
       7: aload         7
       9: invokespecial #123                // Method org/xbill/DNS/DohResolver.timeoutFailedFuture:(Lorg/xbill/DNS/Message;Ljava/lang/Throwable;)Ljava/util/concurrent/CompletableFuture;
      12: areturn
      13: aload_0
      14: aload_1
      15: aload_2
      16: lload_3
      17: aload         5
      19: aload         6
      21: invokespecial #195                // Method org/xbill/DNS/DohResolver.sendAsync11WithInitialRequestPermit:(Lorg/xbill/DNS/Message;Ljava/util/concurrent/Executor;JLjava/lang/Object;Lorg/xbill/DNS/AsyncSemaphore$Permit;)Ljava/util/concurrent/CompletionStage;
      24: areturn

  private java.util.concurrent.CompletableFuture lambda$sendAsync8$1(org.xbill.DNS.Message, java.lang.String, byte[], long, org.xbill.DNS.AsyncSemaphore$Permit, java.lang.Throwable);
    Code:
       0: aload         7
       2: ifnull        13
       5: aload_0
       6: aload_1
       7: aload         7
       9: invokespecial #123                // Method org/xbill/DNS/DohResolver.timeoutFailedFuture:(Lorg/xbill/DNS/Message;Ljava/lang/Throwable;)Ljava/util/concurrent/CompletableFuture;
      12: areturn
      13: aload_0
      14: aload_2
      15: aload_3
      16: lload         4
      18: invokespecial #196                // Method org/xbill/DNS/DohResolver.sendAndGetMessageBytes:(Ljava/lang/String;[BJ)Lorg/xbill/DNS/DohResolver$SendAndGetMessageBytesResponse;
      21: astore        8
      23: aload         8
      25: invokestatic  #197                // Method org/xbill/DNS/DohResolver$SendAndGetMessageBytesResponse.access$000:(Lorg/xbill/DNS/DohResolver$SendAndGetMessageBytesResponse;)I
      28: ifne          64
      31: new           #393                // class org/xbill/DNS/Message
      34: dup
      35: aload         8
      37: invokestatic  #198                // Method org/xbill/DNS/DohResolver$SendAndGetMessageBytesResponse.access$100:(Lorg/xbill/DNS/DohResolver$SendAndGetMessageBytesResponse;)[B
      40: invokespecial #187                // Method org/xbill/DNS/Message."<init>":([B)V
      43: astore        9
      45: aload_0
      46: aload_1
      47: aload         9
      49: aload         8
      51: invokestatic  #198                // Method org/xbill/DNS/DohResolver$SendAndGetMessageBytesResponse.access$100:(Lorg/xbill/DNS/DohResolver$SendAndGetMessageBytesResponse;)[B
      54: aload_0
      55: getfield      #47                 // Field org/xbill/DNS/DohResolver.tsig:Lorg/xbill/DNS/TSIG;
      58: invokespecial #188                // Method org/xbill/DNS/DohResolver.verifyTSIG:(Lorg/xbill/DNS/Message;Lorg/xbill/DNS/Message;[BLorg/xbill/DNS/TSIG;)V
      61: goto          87
      64: new           #393                // class org/xbill/DNS/Message
      67: dup
      68: iconst_0
      69: invokespecial #199                // Method org/xbill/DNS/Message."<init>":(I)V
      72: astore        9
      74: aload         9
      76: invokevirtual #144                // Method org/xbill/DNS/Message.getHeader:()Lorg/xbill/DNS/Header;
      79: aload         8
      81: invokestatic  #197                // Method org/xbill/DNS/DohResolver$SendAndGetMessageBytesResponse.access$000:(Lorg/xbill/DNS/DohResolver$SendAndGetMessageBytesResponse;)I
      84: invokevirtual #190                // Method org/xbill/DNS/Header.setRcode:(I)V
      87: aload         9
      89: aload_0
      90: invokevirtual #191                // Method org/xbill/DNS/Message.setResolver:(Lorg/xbill/DNS/Resolver;)V
      93: aload         9
      95: invokestatic  #192                // Method java/util/concurrent/CompletableFuture.completedFuture:(Ljava/lang/Object;)Ljava/util/concurrent/CompletableFuture;
      98: astore        10
     100: aload         6
     102: invokevirtual #122                // Method org/xbill/DNS/AsyncSemaphore$Permit.release:()V
     105: aload         10
     107: areturn
     108: astore        8
     110: aload_0
     111: aload_1
     112: aload         8
     114: invokespecial #123                // Method org/xbill/DNS/DohResolver.timeoutFailedFuture:(Lorg/xbill/DNS/Message;Ljava/lang/Throwable;)Ljava/util/concurrent/CompletableFuture;
     117: astore        9
     119: aload         6
     121: invokevirtual #122                // Method org/xbill/DNS/AsyncSemaphore$Permit.release:()V
     124: aload         9
     126: areturn
     127: astore        8
     129: aload_0
     130: aload         8
     132: invokespecial #117                // Method org/xbill/DNS/DohResolver.failedFuture:(Ljava/lang/Throwable;)Ljava/util/concurrent/CompletableFuture;
     135: astore        9
     137: aload         6
     139: invokevirtual #122                // Method org/xbill/DNS/AsyncSemaphore$Permit.release:()V
     142: aload         9
     144: areturn
     145: astore        11
     147: aload         6
     149: invokevirtual #122                // Method org/xbill/DNS/AsyncSemaphore$Permit.release:()V
     152: aload         11
     154: athrow
    Exception table:
       from    to  target type
          13   100   108   Class java/net/SocketTimeoutException
          13   100   127   Class java/io/IOException
          13   100   145   any
         108   119   145   any
         127   137   145   any
         145   147   145   any

  private java.lang.Object lambda$getHttpClient$0(java.util.concurrent.Executor);
    Code:
       0: getstatic     #200                // Field org/xbill/DNS/DohResolver.httpClientNewBuilderMethod:Ljava/lang/reflect/Method;
       3: aconst_null
       4: iconst_0
       5: anewarray     #395                // class java/lang/Object
       8: invokevirtual #110                // Method java/lang/reflect/Method.invoke:(Ljava/lang/Object;[Ljava/lang/Object;)Ljava/lang/Object;
      11: astore_2
      12: getstatic     #201                // Field org/xbill/DNS/DohResolver.httpClientBuilderTimeoutMethod:Ljava/lang/reflect/Method;
      15: aload_2
      16: iconst_1
      17: anewarray     #395                // class java/lang/Object
      20: dup
      21: iconst_0
      22: aload_0
      23: getfield      #10                 // Field org/xbill/DNS/DohResolver.timeout:Ljava/time/Duration;
      26: aastore
      27: invokevirtual #110                // Method java/lang/reflect/Method.invoke:(Ljava/lang/Object;[Ljava/lang/Object;)Ljava/lang/Object;
      30: pop
      31: getstatic     #202                // Field org/xbill/DNS/DohResolver.httpClientBuilderExecutorMethod:Ljava/lang/reflect/Method;
      34: aload_2
      35: iconst_1
      36: anewarray     #395                // class java/lang/Object
      39: dup
      40: iconst_0
      41: aload_1
      42: aastore
      43: invokevirtual #110                // Method java/lang/reflect/Method.invoke:(Ljava/lang/Object;[Ljava/lang/Object;)Ljava/lang/Object;
      46: pop
      47: getstatic     #203                // Field org/xbill/DNS/DohResolver.httpClientBuilderBuildMethod:Ljava/lang/reflect/Method;
      50: aload_2
      51: iconst_0
      52: anewarray     #395                // class java/lang/Object
      55: invokevirtual #110                // Method java/lang/reflect/Method.invoke:(Ljava/lang/Object;[Ljava/lang/Object;)Ljava/lang/Object;
      58: areturn
      59: astore_2
      60: getstatic     #167                // Field org/xbill/DNS/DohResolver.log:Lorg/slf4j/Logger;
      63: ldc           #204                // String Could not create a HttpClient with for Executor {}
      65: aload_1
      66: aload_2
      67: invokeinterface #205,  4          // InterfaceMethod org/slf4j/Logger.warn:(Ljava/lang/String;Ljava/lang/Object;Ljava/lang/Object;)V
      72: aconst_null
      73: areturn
    Exception table:
       from    to  target type
           0    58    59   Class java/lang/IllegalAccessException
           0    58    59   Class java/lang/reflect/InvocationTargetException

  static {};
    Code:
       0: ldc_w         #314                // class org/xbill/DNS/DohResolver
       3: invokestatic  #206                // Method org/slf4j/LoggerFactory.getLogger:(Ljava/lang/Class;)Lorg/slf4j/Logger;
       6: putstatic     #167                // Field org/xbill/DNS/DohResolver.log:Lorg/slf4j/Logger;
       9: new           #207                // class java/util/WeakHashMap
      12: dup
      13: invokespecial #208                // Method java/util/WeakHashMap."<init>":()V
      16: invokestatic  #209                // Method java/util/Collections.synchronizedMap:(Ljava/util/Map;)Ljava/util/Map;
      19: putstatic     #40                 // Field org/xbill/DNS/DohResolver.httpClients:Ljava/util/Map;
      22: iconst_0
      23: istore_0
      24: ldc           #210                // String java.version
      26: invokestatic  #211                // Method java/lang/System.getProperty:(Ljava/lang/String;)Ljava/lang/String;
      29: ldc           #212                // String 1.
      31: invokevirtual #213                // Method java/lang/String.startsWith:(Ljava/lang/String;)Z
      34: ifne          494
      37: ldc           #214                // String java.net.http.HttpClient$Builder
      39: invokestatic  #215                // Method java/lang/Class.forName:(Ljava/lang/String;)Ljava/lang/Class;
      42: astore_1
      43: ldc           #216                // String java.net.http.HttpClient
      45: invokestatic  #215                // Method java/lang/Class.forName:(Ljava/lang/String;)Ljava/lang/Class;
      48: astore_2
      49: ldc           #217                // String java.net.http.HttpClient$Version
      51: invokestatic  #215                // Method java/lang/Class.forName:(Ljava/lang/String;)Ljava/lang/Class;
      54: astore_3
      55: ldc           #218                // String java.net.http.HttpRequest$Builder
      57: invokestatic  #215                // Method java/lang/Class.forName:(Ljava/lang/String;)Ljava/lang/Class;
      60: astore        4
      62: ldc           #219                // String java.net.http.HttpRequest
      64: invokestatic  #215                // Method java/lang/Class.forName:(Ljava/lang/String;)Ljava/lang/Class;
      67: astore        5
      69: ldc           #220                // String java.net.http.HttpRequest$BodyPublishers
      71: invokestatic  #215                // Method java/lang/Class.forName:(Ljava/lang/String;)Ljava/lang/Class;
      74: astore        6
      76: ldc           #221                // String java.net.http.HttpRequest$BodyPublisher
      78: invokestatic  #215                // Method java/lang/Class.forName:(Ljava/lang/String;)Ljava/lang/Class;
      81: astore        7
      83: ldc           #222                // String java.net.http.HttpResponse
      85: invokestatic  #215                // Method java/lang/Class.forName:(Ljava/lang/String;)Ljava/lang/Class;
      88: astore        8
      90: ldc           #223                // String java.net.http.HttpResponse$BodyHandlers
      92: invokestatic  #215                // Method java/lang/Class.forName:(Ljava/lang/String;)Ljava/lang/Class;
      95: astore        9
      97: ldc           #224                // String java.net.http.HttpResponse$BodyHandler
      99: invokestatic  #215                // Method java/lang/Class.forName:(Ljava/lang/String;)Ljava/lang/Class;
     102: astore        10
     104: aload_1
     105: ldc           #225                // String connectTimeout
     107: iconst_1
     108: anewarray     #226                // class java/lang/Class
     111: dup
     112: iconst_0
     113: ldc_w         #316                // class java/time/Duration
     116: aastore
     117: invokevirtual #228                // Method java/lang/Class.getDeclaredMethod:(Ljava/lang/String;[Ljava/lang/Class;)Ljava/lang/reflect/Method;
     120: putstatic     #201                // Field org/xbill/DNS/DohResolver.httpClientBuilderTimeoutMethod:Ljava/lang/reflect/Method;
     123: aload_1
     124: ldc           #229                // String executor
     126: iconst_1
     127: anewarray     #226                // class java/lang/Class
     130: dup
     131: iconst_0
     132: ldc_w         #394                // class java/util/concurrent/Executor
     135: aastore
     136: invokevirtual #228                // Method java/lang/Class.getDeclaredMethod:(Ljava/lang/String;[Ljava/lang/Class;)Ljava/lang/reflect/Method;
     139: putstatic     #202                // Field org/xbill/DNS/DohResolver.httpClientBuilderExecutorMethod:Ljava/lang/reflect/Method;
     142: aload_1
     143: ldc           #231                // String build
     145: iconst_0
     146: anewarray     #226                // class java/lang/Class
     149: invokevirtual #228                // Method java/lang/Class.getDeclaredMethod:(Ljava/lang/String;[Ljava/lang/Class;)Ljava/lang/reflect/Method;
     152: putstatic     #203                // Field org/xbill/DNS/DohResolver.httpClientBuilderBuildMethod:Ljava/lang/reflect/Method;
     155: aload_2
     156: ldc           #232                // String newBuilder
     158: iconst_0
     159: anewarray     #226                // class java/lang/Class
     162: invokevirtual #228                // Method java/lang/Class.getDeclaredMethod:(Ljava/lang/String;[Ljava/lang/Class;)Ljava/lang/reflect/Method;
     165: putstatic     #200                // Field org/xbill/DNS/DohResolver.httpClientNewBuilderMethod:Ljava/lang/reflect/Method;
     168: aload_2
     169: ldc           #233                // String sendAsync
     171: iconst_2
     172: anewarray     #226                // class java/lang/Class
     175: dup
     176: iconst_0
     177: aload         5
     179: aastore
     180: dup
     181: iconst_1
     182: aload         10
     184: aastore
     185: invokevirtual #228                // Method java/lang/Class.getDeclaredMethod:(Ljava/lang/String;[Ljava/lang/Class;)Ljava/lang/reflect/Method;
     188: putstatic     #129                // Field org/xbill/DNS/DohResolver.httpClientSendAsyncMethod:Ljava/lang/reflect/Method;
     191: aload         4
     193: ldc           #234                // String header
     195: iconst_2
     196: anewarray     #226                // class java/lang/Class
     199: dup
     200: iconst_0
     201: ldc_w         #315                // class java/lang/String
     204: aastore
     205: dup
     206: iconst_1
     207: ldc_w         #315                // class java/lang/String
     210: aastore
     211: invokevirtual #228                // Method java/lang/Class.getDeclaredMethod:(Ljava/lang/String;[Ljava/lang/Class;)Ljava/lang/reflect/Method;
     214: astore        11
     216: aload         4
     218: ldc           #236                // String version
     220: iconst_1
     221: anewarray     #226                // class java/lang/Class
     224: dup
     225: iconst_0
     226: aload_3
     227: aastore
     228: invokevirtual #228                // Method java/lang/Class.getDeclaredMethod:(Ljava/lang/String;[Ljava/lang/Class;)Ljava/lang/reflect/Method;
     231: astore        12
     233: aload         4
     235: ldc           #237                // String timeout
     237: iconst_1
     238: anewarray     #226                // class java/lang/Class
     241: dup
     242: iconst_0
     243: ldc_w         #316                // class java/time/Duration
     246: aastore
     247: invokevirtual #228                // Method java/lang/Class.getDeclaredMethod:(Ljava/lang/String;[Ljava/lang/Class;)Ljava/lang/reflect/Method;
     250: putstatic     #126                // Field org/xbill/DNS/DohResolver.requestBuilderTimeoutMethod:Ljava/lang/reflect/Method;
     253: aload         4
     255: ldc           #238                // String uri
     257: iconst_1
     258: anewarray     #226                // class java/lang/Class
     261: dup
     262: iconst_0
     263: ldc           #239                // class java/net/URI
     265: aastore
     266: invokevirtual #228                // Method java/lang/Class.getDeclaredMethod:(Ljava/lang/String;[Ljava/lang/Class;)Ljava/lang/reflect/Method;
     269: putstatic     #111                // Field org/xbill/DNS/DohResolver.requestBuilderUriMethod:Ljava/lang/reflect/Method;
     272: aload         4
     274: ldc           #240                // String copy
     276: iconst_0
     277: anewarray     #226                // class java/lang/Class
     280: invokevirtual #228                // Method java/lang/Class.getDeclaredMethod:(Ljava/lang/String;[Ljava/lang/Class;)Ljava/lang/reflect/Method;
     283: putstatic     #107                // Field org/xbill/DNS/DohResolver.requestBuilderCopyMethod:Ljava/lang/reflect/Method;
     286: aload         4
     288: ldc           #231                // String build
     290: iconst_0
     291: anewarray     #226                // class java/lang/Class
     294: invokevirtual #228                // Method java/lang/Class.getDeclaredMethod:(Ljava/lang/String;[Ljava/lang/Class;)Ljava/lang/reflect/Method;
     297: putstatic     #127                // Field org/xbill/DNS/DohResolver.requestBuilderBuildMethod:Ljava/lang/reflect/Method;
     300: aload         4
     302: ldc           #72                 // String POST
     304: iconst_1
     305: anewarray     #226                // class java/lang/Class
     308: dup
     309: iconst_0
     310: aload         7
     312: aastore
     313: invokevirtual #228                // Method java/lang/Class.getDeclaredMethod:(Ljava/lang/String;[Ljava/lang/Class;)Ljava/lang/reflect/Method;
     316: putstatic     #113                // Field org/xbill/DNS/DohResolver.requestBuilderPostMethod:Ljava/lang/reflect/Method;
     319: aload         5
     321: ldc           #232                // String newBuilder
     323: iconst_0
     324: anewarray     #226                // class java/lang/Class
     327: invokevirtual #228                // Method java/lang/Class.getDeclaredMethod:(Ljava/lang/String;[Ljava/lang/Class;)Ljava/lang/reflect/Method;
     330: astore        13
     332: aload         6
     334: ldc           #241                // String ofByteArray
     336: iconst_1
     337: anewarray     #226                // class java/lang/Class
     340: dup
     341: iconst_0
     342: ldc           #185                // class "[B"
     344: aastore
     345: invokevirtual #228                // Method java/lang/Class.getDeclaredMethod:(Ljava/lang/String;[Ljava/lang/Class;)Ljava/lang/reflect/Method;
     348: putstatic     #114                // Field org/xbill/DNS/DohResolver.publisherOfByteArrayMethod:Ljava/lang/reflect/Method;
     351: aload         9
     353: ldc           #241                // String ofByteArray
     355: iconst_0
     356: anewarray     #226                // class java/lang/Class
     359: invokevirtual #228                // Method java/lang/Class.getDeclaredMethod:(Ljava/lang/String;[Ljava/lang/Class;)Ljava/lang/reflect/Method;
     362: putstatic     #128                // Field org/xbill/DNS/DohResolver.byteArrayBodyPublisherMethod:Ljava/lang/reflect/Method;
     365: aload         8
     367: ldc           #242                // String body
     369: iconst_0
     370: anewarray     #226                // class java/lang/Class
     373: invokevirtual #228                // Method java/lang/Class.getDeclaredMethod:(Ljava/lang/String;[Ljava/lang/Class;)Ljava/lang/reflect/Method;
     376: putstatic     #184                // Field org/xbill/DNS/DohResolver.httpResponseBodyMethod:Ljava/lang/reflect/Method;
     379: aload         8
     381: ldc           #243                // String statusCode
     383: iconst_0
     384: anewarray     #226                // class java/lang/Class
     387: invokevirtual #228                // Method java/lang/Class.getDeclaredMethod:(Ljava/lang/String;[Ljava/lang/Class;)Ljava/lang/reflect/Method;
     390: putstatic     #181                // Field org/xbill/DNS/DohResolver.httpResponseStatusCodeMethod:Ljava/lang/reflect/Method;
     393: aload         13
     395: aconst_null
     396: iconst_0
     397: anewarray     #395                // class java/lang/Object
     400: invokevirtual #110                // Method java/lang/reflect/Method.invoke:(Ljava/lang/Object;[Ljava/lang/Object;)Ljava/lang/Object;
     403: putstatic     #108                // Field org/xbill/DNS/DohResolver.defaultHttpRequestBuilder:Ljava/lang/Object;
     406: aload_3
     407: ldc           #244                // String HTTP_2
     409: invokestatic  #245                // Method java/lang/Enum.valueOf:(Ljava/lang/Class;Ljava/lang/String;)Ljava/lang/Enum;
     412: astore        14
     414: aload         12
     416: getstatic     #108                // Field org/xbill/DNS/DohResolver.defaultHttpRequestBuilder:Ljava/lang/Object;
     419: iconst_1
     420: anewarray     #395                // class java/lang/Object
     423: dup
     424: iconst_0
     425: aload         14
     427: aastore
     428: invokevirtual #110                // Method java/lang/reflect/Method.invoke:(Ljava/lang/Object;[Ljava/lang/Object;)Ljava/lang/Object;
     431: pop
     432: aload         11
     434: getstatic     #108                // Field org/xbill/DNS/DohResolver.defaultHttpRequestBuilder:Ljava/lang/Object;
     437: iconst_2
     438: anewarray     #395                // class java/lang/Object
     441: dup
     442: iconst_0
     443: ldc           #75                 // String Content-Type
     445: aastore
     446: dup
     447: iconst_1
     448: ldc           #77                 // String application/dns-message
     450: aastore
     451: invokevirtual #110                // Method java/lang/reflect/Method.invoke:(Ljava/lang/Object;[Ljava/lang/Object;)Ljava/lang/Object;
     454: pop
     455: aload         11
     457: getstatic     #108                // Field org/xbill/DNS/DohResolver.defaultHttpRequestBuilder:Ljava/lang/Object;
     460: iconst_2
     461: anewarray     #395                // class java/lang/Object
     464: dup
     465: iconst_0
     466: ldc           #79                 // String Accept
     468: aastore
     469: dup
     470: iconst_1
     471: ldc           #77                 // String application/dns-message
     473: aastore
     474: invokevirtual #110                // Method java/lang/reflect/Method.invoke:(Ljava/lang/Object;[Ljava/lang/Object;)Ljava/lang/Object;
     477: pop
     478: iconst_1
     479: istore_0
     480: goto          494
     483: astore_1
     484: getstatic     #167                // Field org/xbill/DNS/DohResolver.log:Lorg/slf4j/Logger;
     487: ldc           #248                // String Java >= 11 detected, but HttpRequest not available
     489: invokeinterface #249,  2          // InterfaceMethod org/slf4j/Logger.warn:(Ljava/lang/String;)V
     494: iload_0
     495: putstatic     #27                 // Field org/xbill/DNS/DohResolver.USE_HTTP_CLIENT:Z
     498: return
    Exception table:
       from    to  target type
          37   480   483   Class java/lang/ClassNotFoundException
          37   480   483   Class java/lang/NoSuchMethodException
          37   480   483   Class java/lang/IllegalAccessException
          37   480   483   Class java/lang/reflect/InvocationTargetException
}
