Compiled from "TSIG.java"
public class org.xbill.DNS.TSIG {
  private static final org.slf4j.Logger log;

  public static final org.xbill.DNS.Name GSS_TSIG;

  public static final org.xbill.DNS.Name HMAC_MD5;

  public static final org.xbill.DNS.Name HMAC;

  public static final org.xbill.DNS.Name HMAC_SHA1;

  public static final org.xbill.DNS.Name HMAC_SHA224;

  public static final org.xbill.DNS.Name HMAC_SHA256;

  public static final org.xbill.DNS.Name HMAC_SHA384;

  public static final org.xbill.DNS.Name HMAC_SHA512;

  private static final java.util.Map<org.xbill.DNS.Name, java.lang.String> algMap;

  public static final java.time.Duration FUDGE;

  private final org.xbill.DNS.Name alg;

  private final java.time.Clock clock;

  private final org.xbill.DNS.Name name;

  private final javax.crypto.SecretKey macKey;

  private final java.lang.String macAlgorithm;

  private final javax.crypto.Mac sharedHmac;

  public static org.xbill.DNS.Name algorithmToName(java.lang.String);
    Code:
       0: aload_0
       1: ifnonnull     14
       4: new           #2                  // class java/lang/IllegalArgumentException
       7: dup
       8: ldc           #3                  // String Null algorithm
      10: invokespecial #4                  // Method java/lang/IllegalArgumentException."<init>":(Ljava/lang/String;)V
      13: athrow
      14: aload_0
      15: ldc           #5                  // String HMAC-MD5
      17: invokevirtual #6                  // Method java/lang/String.equalsIgnoreCase:(Ljava/lang/String;)Z
      20: ifne          32
      23: aload_0
      24: ldc           #7                  // String HMAC-MD5.
      26: invokevirtual #6                  // Method java/lang/String.equalsIgnoreCase:(Ljava/lang/String;)Z
      29: ifeq          36
      32: getstatic     #8                  // Field HMAC_MD5:Lorg/xbill/DNS/Name;
      35: areturn
      36: getstatic     #9                  // Field algMap:Ljava/util/Map;
      39: invokeinterface #10,  1           // InterfaceMethod java/util/Map.keySet:()Ljava/util/Set;
      44: invokeinterface #11,  1           // InterfaceMethod java/util/Set.stream:()Ljava/util/stream/Stream;
      49: aload_0
      50: invokedynamic #12,  0             // InvokeDynamic #0:test:(Ljava/lang/String;)Ljava/util/function/Predicate;
      55: invokeinterface #13,  2           // InterfaceMethod java/util/stream/Stream.filter:(Ljava/util/function/Predicate;)Ljava/util/stream/Stream;
      60: invokeinterface #14,  1           // InterfaceMethod java/util/stream/Stream.findAny:()Ljava/util/Optional;
      65: aload_0
      66: invokedynamic #15,  0             // InvokeDynamic #1:get:(Ljava/lang/String;)Ljava/util/function/Supplier;
      71: invokevirtual #16                 // Method java/util/Optional.orElseGet:(Ljava/util/function/Supplier;)Ljava/lang/Object;
      74: checkcast     #17                 // class org/xbill/DNS/Name
      77: areturn

  public static java.lang.String nameToAlgorithm(org.xbill.DNS.Name);
    Code:
       0: getstatic     #9                  // Field algMap:Ljava/util/Map;
       3: aload_0
       4: invokeinterface #18,  2           // InterfaceMethod java/util/Map.get:(Ljava/lang/Object;)Ljava/lang/Object;
       9: checkcast     #19                 // class java/lang/String
      12: astore_1
      13: aload_1
      14: ifnull        19
      17: aload_1
      18: areturn
      19: new           #2                  // class java/lang/IllegalArgumentException
      22: dup
      23: new           #20                 // class java/lang/StringBuilder
      26: dup
      27: invokespecial #21                 // Method java/lang/StringBuilder."<init>":()V
      30: ldc           #22                 // String Unknown algorithm:
      32: invokevirtual #23                 // Method java/lang/StringBuilder.append:(Ljava/lang/String;)Ljava/lang/StringBuilder;
      35: aload_0
      36: invokevirtual #24                 // Method java/lang/StringBuilder.append:(Ljava/lang/Object;)Ljava/lang/StringBuilder;
      39: invokevirtual #25                 // Method java/lang/StringBuilder.toString:()Ljava/lang/String;
      42: invokespecial #4                  // Method java/lang/IllegalArgumentException."<init>":(Ljava/lang/String;)V
      45: athrow

  private static boolean verify(byte[], byte[]);
    Code:
       0: aload_1
       1: arraylength
       2: aload_0
       3: arraylength
       4: if_icmpge     23
       7: aload_1
       8: arraylength
       9: newarray       byte
      11: astore_2
      12: aload_0
      13: iconst_0
      14: aload_2
      15: iconst_0
      16: aload_2
      17: arraylength
      18: invokestatic  #26                 // Method java/lang/System.arraycopy:(Ljava/lang/Object;ILjava/lang/Object;II)V
      21: aload_2
      22: astore_0
      23: aload_1
      24: aload_0
      25: invokestatic  #27                 // Method java/util/Arrays.equals:([B[B)Z
      28: ireturn

  private javax.crypto.Mac initHmac();
    Code:
       0: aload_0
       1: getfield      #28                 // Field sharedHmac:Ljavax/crypto/Mac;
       4: ifnull        31
       7: aload_0
       8: getfield      #28                 // Field sharedHmac:Ljavax/crypto/Mac;
      11: invokevirtual #29                 // Method javax/crypto/Mac.clone:()Ljava/lang/Object;
      14: checkcast     #30                 // class javax/crypto/Mac
      17: areturn
      18: astore_1
      19: aload_0
      20: getfield      #28                 // Field sharedHmac:Ljavax/crypto/Mac;
      23: invokevirtual #32                 // Method javax/crypto/Mac.reset:()V
      26: aload_0
      27: getfield      #28                 // Field sharedHmac:Ljavax/crypto/Mac;
      30: areturn
      31: aload_0
      32: getfield      #33                 // Field macAlgorithm:Ljava/lang/String;
      35: invokestatic  #34                 // Method javax/crypto/Mac.getInstance:(Ljava/lang/String;)Ljavax/crypto/Mac;
      38: astore_1
      39: aload_1
      40: aload_0
      41: getfield      #35                 // Field macKey:Ljavax/crypto/SecretKey;
      44: invokevirtual #36                 // Method javax/crypto/Mac.init:(Ljava/security/Key;)V
      47: aload_1
      48: areturn
      49: astore_1
      50: new           #2                  // class java/lang/IllegalArgumentException
      53: dup
      54: ldc           #38                 // String Caught security exception setting up HMAC.
      56: aload_1
      57: invokespecial #39                 // Method java/lang/IllegalArgumentException."<init>":(Ljava/lang/String;Ljava/lang/Throwable;)V
      60: athrow
    Exception table:
       from    to  target type
           7    17    18   Class java/lang/CloneNotSupportedException
          31    48    49   Class java/security/GeneralSecurityException

  public org.xbill.DNS.TSIG(org.xbill.DNS.Name, org.xbill.DNS.Name, java.lang.String);
    Code:
       0: aload_0
       1: aload_1
       2: aload_2
       3: aload_3
       4: invokestatic  #40                 // Method org/xbill/DNS/utils/base64.fromString:(Ljava/lang/String;)[B
       7: invokestatic  #41                 // Method java/util/Objects.requireNonNull:(Ljava/lang/Object;)Ljava/lang/Object;
      10: checkcast     #42                 // class "[B"
      13: invokespecial #43                 // Method "<init>":(Lorg/xbill/DNS/Name;Lorg/xbill/DNS/Name;[B)V
      16: return

  public org.xbill.DNS.TSIG(org.xbill.DNS.Name, org.xbill.DNS.Name, byte[]);
    Code:
       0: aload_0
       1: aload_1
       2: aload_2
       3: new           #44                 // class javax/crypto/spec/SecretKeySpec
       6: dup
       7: aload_3
       8: aload_1
       9: invokestatic  #45                 // Method nameToAlgorithm:(Lorg/xbill/DNS/Name;)Ljava/lang/String;
      12: invokespecial #46                 // Method javax/crypto/spec/SecretKeySpec."<init>":([BLjava/lang/String;)V
      15: invokespecial #47                 // Method "<init>":(Lorg/xbill/DNS/Name;Lorg/xbill/DNS/Name;Ljavax/crypto/SecretKey;)V
      18: return

  public org.xbill.DNS.TSIG(org.xbill.DNS.Name, org.xbill.DNS.Name, javax.crypto.SecretKey);
    Code:
       0: aload_0
       1: aload_1
       2: aload_2
       3: aload_3
       4: invokestatic  #48                 // Method java/time/Clock.systemUTC:()Ljava/time/Clock;
       7: invokespecial #49                 // Method "<init>":(Lorg/xbill/DNS/Name;Lorg/xbill/DNS/Name;Ljavax/crypto/SecretKey;Ljava/time/Clock;)V
      10: return

  public org.xbill.DNS.TSIG(org.xbill.DNS.Name, org.xbill.DNS.Name, javax.crypto.SecretKey, java.time.Clock);
    Code:
       0: aload_0
       1: invokespecial #50                 // Method java/lang/Object."<init>":()V
       4: aload_0
       5: aload_2
       6: putfield      #51                 // Field name:Lorg/xbill/DNS/Name;
       9: aload_0
      10: aload_1
      11: putfield      #52                 // Field alg:Lorg/xbill/DNS/Name;
      14: aload_0
      15: aload         4
      17: putfield      #53                 // Field clock:Ljava/time/Clock;
      20: aload_0
      21: aload_1
      22: invokestatic  #45                 // Method nameToAlgorithm:(Lorg/xbill/DNS/Name;)Ljava/lang/String;
      25: putfield      #33                 // Field macAlgorithm:Ljava/lang/String;
      28: aload_0
      29: aload_3
      30: putfield      #35                 // Field macKey:Ljavax/crypto/SecretKey;
      33: aload_0
      34: aconst_null
      35: putfield      #28                 // Field sharedHmac:Ljavax/crypto/Mac;
      38: return

  public org.xbill.DNS.TSIG(javax.crypto.Mac, org.xbill.DNS.Name);
    Code:
       0: aload_0
       1: invokespecial #50                 // Method java/lang/Object."<init>":()V
       4: aload_0
       5: aload_2
       6: putfield      #51                 // Field name:Lorg/xbill/DNS/Name;
       9: aload_0
      10: aload_1
      11: putfield      #28                 // Field sharedHmac:Ljavax/crypto/Mac;
      14: aload_0
      15: aconst_null
      16: putfield      #33                 // Field macAlgorithm:Ljava/lang/String;
      19: aload_0
      20: aconst_null
      21: putfield      #35                 // Field macKey:Ljavax/crypto/SecretKey;
      24: aload_0
      25: invokestatic  #48                 // Method java/time/Clock.systemUTC:()Ljava/time/Clock;
      28: putfield      #53                 // Field clock:Ljava/time/Clock;
      31: aload_0
      32: aload_1
      33: invokevirtual #54                 // Method javax/crypto/Mac.getAlgorithm:()Ljava/lang/String;
      36: invokestatic  #55                 // Method algorithmToName:(Ljava/lang/String;)Lorg/xbill/DNS/Name;
      39: putfield      #52                 // Field alg:Lorg/xbill/DNS/Name;
      42: return

  public org.xbill.DNS.TSIG(org.xbill.DNS.Name, byte[]);
    Code:
       0: aload_0
       1: getstatic     #8                  // Field HMAC_MD5:Lorg/xbill/DNS/Name;
       4: aload_1
       5: aload_2
       6: invokespecial #43                 // Method "<init>":(Lorg/xbill/DNS/Name;Lorg/xbill/DNS/Name;[B)V
       9: return

  public org.xbill.DNS.TSIG(org.xbill.DNS.Name, java.lang.String, java.lang.String);
    Code:
       0: aload_0
       1: invokespecial #50                 // Method java/lang/Object."<init>":()V
       4: aload_3
       5: invokestatic  #40                 // Method org/xbill/DNS/utils/base64.fromString:(Ljava/lang/String;)[B
       8: astore        4
      10: aload         4
      12: ifnonnull     25
      15: new           #2                  // class java/lang/IllegalArgumentException
      18: dup
      19: ldc           #56                 // String Invalid TSIG key string
      21: invokespecial #4                  // Method java/lang/IllegalArgumentException."<init>":(Ljava/lang/String;)V
      24: athrow
      25: aload_0
      26: aload_2
      27: getstatic     #57                 // Field org/xbill/DNS/Name.root:Lorg/xbill/DNS/Name;
      30: invokestatic  #58                 // Method org/xbill/DNS/Name.fromString:(Ljava/lang/String;Lorg/xbill/DNS/Name;)Lorg/xbill/DNS/Name;
      33: putfield      #51                 // Field name:Lorg/xbill/DNS/Name;
      36: goto          51
      39: astore        5
      41: new           #2                  // class java/lang/IllegalArgumentException
      44: dup
      45: ldc           #60                 // String Invalid TSIG key name
      47: invokespecial #4                  // Method java/lang/IllegalArgumentException."<init>":(Ljava/lang/String;)V
      50: athrow
      51: aload_0
      52: aload_1
      53: putfield      #52                 // Field alg:Lorg/xbill/DNS/Name;
      56: aload_0
      57: invokestatic  #48                 // Method java/time/Clock.systemUTC:()Ljava/time/Clock;
      60: putfield      #53                 // Field clock:Ljava/time/Clock;
      63: aload_0
      64: aload_1
      65: invokestatic  #45                 // Method nameToAlgorithm:(Lorg/xbill/DNS/Name;)Ljava/lang/String;
      68: putfield      #33                 // Field macAlgorithm:Ljava/lang/String;
      71: aload_0
      72: aconst_null
      73: putfield      #28                 // Field sharedHmac:Ljavax/crypto/Mac;
      76: aload_0
      77: new           #44                 // class javax/crypto/spec/SecretKeySpec
      80: dup
      81: aload         4
      83: aload_0
      84: getfield      #33                 // Field macAlgorithm:Ljava/lang/String;
      87: invokespecial #46                 // Method javax/crypto/spec/SecretKeySpec."<init>":([BLjava/lang/String;)V
      90: putfield      #35                 // Field macKey:Ljavax/crypto/SecretKey;
      93: return
    Exception table:
       from    to  target type
          25    36    39   Class org/xbill/DNS/TextParseException

  public org.xbill.DNS.TSIG(java.lang.String, java.lang.String, java.lang.String);
    Code:
       0: aload_0
       1: aload_1
       2: invokestatic  #55                 // Method algorithmToName:(Ljava/lang/String;)Lorg/xbill/DNS/Name;
       5: aload_2
       6: aload_3
       7: invokespecial #61                 // Method "<init>":(Lorg/xbill/DNS/Name;Ljava/lang/String;Ljava/lang/String;)V
      10: return

  public org.xbill.DNS.TSIG(java.lang.String, java.lang.String);
    Code:
       0: aload_0
       1: getstatic     #8                  // Field HMAC_MD5:Lorg/xbill/DNS/Name;
       4: aload_1
       5: aload_2
       6: invokespecial #61                 // Method "<init>":(Lorg/xbill/DNS/Name;Ljava/lang/String;Ljava/lang/String;)V
       9: return

  public static org.xbill.DNS.TSIG fromString(java.lang.String);
    Code:
       0: aload_0
       1: ldc           #62                 // String [:/]
       3: iconst_3
       4: invokevirtual #63                 // Method java/lang/String.split:(Ljava/lang/String;I)[Ljava/lang/String;
       7: astore_1
       8: aload_1
       9: arraylength
      10: lookupswitch  { // 2
                     2: 36
                     3: 53
               default: 70
          }
      36: new           #64                 // class org/xbill/DNS/TSIG
      39: dup
      40: getstatic     #8                  // Field HMAC_MD5:Lorg/xbill/DNS/Name;
      43: aload_1
      44: iconst_0
      45: aaload
      46: aload_1
      47: iconst_1
      48: aaload
      49: invokespecial #61                 // Method "<init>":(Lorg/xbill/DNS/Name;Ljava/lang/String;Ljava/lang/String;)V
      52: areturn
      53: new           #64                 // class org/xbill/DNS/TSIG
      56: dup
      57: aload_1
      58: iconst_0
      59: aaload
      60: aload_1
      61: iconst_1
      62: aaload
      63: aload_1
      64: iconst_2
      65: aaload
      66: invokespecial #65                 // Method "<init>":(Ljava/lang/String;Ljava/lang/String;Ljava/lang/String;)V
      69: areturn
      70: new           #2                  // class java/lang/IllegalArgumentException
      73: dup
      74: ldc           #66                 // String Invalid TSIG key specification
      76: invokespecial #4                  // Method java/lang/IllegalArgumentException."<init>":(Ljava/lang/String;)V
      79: athrow

  public org.xbill.DNS.TSIGRecord generate(org.xbill.DNS.Message, byte[], int, org.xbill.DNS.TSIGRecord);
    Code:
       0: aload_0
       1: aload_1
       2: aload_2
       3: iload_3
       4: aload         4
       6: iconst_1
       7: invokevirtual #67                 // Method generate:(Lorg/xbill/DNS/Message;[BILorg/xbill/DNS/TSIGRecord;Z)Lorg/xbill/DNS/TSIGRecord;
      10: areturn

  public org.xbill.DNS.TSIGRecord generate(org.xbill.DNS.Message, byte[], int, org.xbill.DNS.TSIGRecord, boolean);
    Code:
       0: iload_3
       1: bipush        18
       3: if_icmpne     16
       6: aload         4
       8: invokevirtual #69                 // Method org/xbill/DNS/TSIGRecord.getTimeSigned:()Ljava/time/Instant;
      11: astore        6
      13: goto          25
      16: aload_0
      17: getfield      #53                 // Field clock:Ljava/time/Clock;
      20: invokevirtual #70                 // Method java/time/Clock.instant:()Ljava/time/Instant;
      23: astore        6
      25: iconst_0
      26: istore        7
      28: aconst_null
      29: astore        8
      31: iload_3
      32: ifeq          47
      35: iload_3
      36: bipush        18
      38: if_icmpeq     47
      41: iload_3
      42: bipush        22
      44: if_icmpne     56
      47: iconst_1
      48: istore        7
      50: aload_0
      51: invokespecial #71                 // Method initHmac:()Ljavax/crypto/Mac;
      54: astore        8
      56: ldc           #72                 // String tsigfudge
      58: invokestatic  #73                 // Method org/xbill/DNS/Options.intValue:(Ljava/lang/String;)I
      61: istore        10
      63: iload         10
      65: iflt          76
      68: iload         10
      70: sipush        32767
      73: if_icmple     84
      76: getstatic     #74                 // Field FUDGE:Ljava/time/Duration;
      79: astore        9
      81: goto          92
      84: iload         10
      86: i2l
      87: invokestatic  #75                 // Method java/time/Duration.ofSeconds:(J)Ljava/time/Duration;
      90: astore        9
      92: aload         4
      94: ifnull        109
      97: iload         7
      99: ifeq          109
     102: aload         8
     104: aload         4
     106: invokestatic  #76                 // Method hmacAddSignature:(Ljavax/crypto/Mac;Lorg/xbill/DNS/TSIGRecord;)V
     109: iload         7
     111: ifeq          145
     114: getstatic     #1                  // Field log:Lorg/slf4j/Logger;
     117: invokeinterface #77,  1           // InterfaceMethod org/slf4j/Logger.isTraceEnabled:()Z
     122: ifeq          139
     125: getstatic     #1                  // Field log:Lorg/slf4j/Logger;
     128: ldc           #78                 // String TSIG-HMAC rendered message
     130: aload_2
     131: invokestatic  #79                 // Method org/xbill/DNS/utils/hexdump.dump:(Ljava/lang/String;[B)Ljava/lang/String;
     134: invokeinterface #80,  2           // InterfaceMethod org/slf4j/Logger.trace:(Ljava/lang/String;)V
     139: aload         8
     141: aload_2
     142: invokevirtual #81                 // Method javax/crypto/Mac.update:([B)V
     145: new           #82                 // class org/xbill/DNS/DNSOutput
     148: dup
     149: invokespecial #83                 // Method org/xbill/DNS/DNSOutput."<init>":()V
     152: astore        11
     154: iload         5
     156: ifeq          191
     159: aload_0
     160: getfield      #51                 // Field name:Lorg/xbill/DNS/Name;
     163: aload         11
     165: invokevirtual #84                 // Method org/xbill/DNS/Name.toWireCanonical:(Lorg/xbill/DNS/DNSOutput;)V
     168: aload         11
     170: sipush        255
     173: invokevirtual #86                 // Method org/xbill/DNS/DNSOutput.writeU16:(I)V
     176: aload         11
     178: lconst_0
     179: invokevirtual #87                 // Method org/xbill/DNS/DNSOutput.writeU32:(J)V
     182: aload_0
     183: getfield      #52                 // Field alg:Lorg/xbill/DNS/Name;
     186: aload         11
     188: invokevirtual #84                 // Method org/xbill/DNS/Name.toWireCanonical:(Lorg/xbill/DNS/DNSOutput;)V
     191: aload         6
     193: aload         9
     195: aload         11
     197: invokestatic  #88                 // Method writeTsigTimersVariables:(Ljava/time/Instant;Ljava/time/Duration;Lorg/xbill/DNS/DNSOutput;)V
     200: iload         5
     202: ifeq          217
     205: aload         11
     207: iload_3
     208: invokevirtual #86                 // Method org/xbill/DNS/DNSOutput.writeU16:(I)V
     211: aload         11
     213: iconst_0
     214: invokevirtual #86                 // Method org/xbill/DNS/DNSOutput.writeU16:(I)V
     217: iload         7
     219: ifeq          267
     222: aload         11
     224: invokevirtual #89                 // Method org/xbill/DNS/DNSOutput.toByteArray:()[B
     227: astore        13
     229: getstatic     #1                  // Field log:Lorg/slf4j/Logger;
     232: invokeinterface #77,  1           // InterfaceMethod org/slf4j/Logger.isTraceEnabled:()Z
     237: ifeq          255
     240: getstatic     #1                  // Field log:Lorg/slf4j/Logger;
     243: ldc           #90                 // String TSIG-HMAC variables
     245: aload         13
     247: invokestatic  #79                 // Method org/xbill/DNS/utils/hexdump.dump:(Ljava/lang/String;[B)Ljava/lang/String;
     250: invokeinterface #80,  2           // InterfaceMethod org/slf4j/Logger.trace:(Ljava/lang/String;)V
     255: aload         8
     257: aload         13
     259: invokevirtual #91                 // Method javax/crypto/Mac.doFinal:([B)[B
     262: astore        12
     264: goto          272
     267: iconst_0
     268: newarray       byte
     270: astore        12
     272: aconst_null
     273: astore        13
     275: iload_3
     276: bipush        18
     278: if_icmpne     311
     281: new           #82                 // class org/xbill/DNS/DNSOutput
     284: dup
     285: bipush        6
     287: invokespecial #92                 // Method org/xbill/DNS/DNSOutput."<init>":(I)V
     290: astore        11
     292: aload_0
     293: getfield      #53                 // Field clock:Ljava/time/Clock;
     296: invokevirtual #70                 // Method java/time/Clock.instant:()Ljava/time/Instant;
     299: aload         11
     301: invokestatic  #93                 // Method writeTsigTime:(Ljava/time/Instant;Lorg/xbill/DNS/DNSOutput;)V
     304: aload         11
     306: invokevirtual #89                 // Method org/xbill/DNS/DNSOutput.toByteArray:()[B
     309: astore        13
     311: new           #94                 // class org/xbill/DNS/TSIGRecord
     314: dup
     315: aload_0
     316: getfield      #51                 // Field name:Lorg/xbill/DNS/Name;
     319: sipush        255
     322: lconst_0
     323: aload_0
     324: getfield      #52                 // Field alg:Lorg/xbill/DNS/Name;
     327: aload         6
     329: aload         9
     331: aload         12
     333: aload_1
     334: invokevirtual #95                 // Method org/xbill/DNS/Message.getHeader:()Lorg/xbill/DNS/Header;
     337: invokevirtual #96                 // Method org/xbill/DNS/Header.getID:()I
     340: iload_3
     341: aload         13
     343: invokespecial #97                 // Method org/xbill/DNS/TSIGRecord."<init>":(Lorg/xbill/DNS/Name;IJLorg/xbill/DNS/Name;Ljava/time/Instant;Ljava/time/Duration;[BII[B)V
     346: areturn

  public void apply(org.xbill.DNS.Message, org.xbill.DNS.TSIGRecord);
    Code:
       0: aload_0
       1: aload_1
       2: iconst_0
       3: aload_2
       4: iconst_1
       5: invokevirtual #98                 // Method apply:(Lorg/xbill/DNS/Message;ILorg/xbill/DNS/TSIGRecord;Z)V
       8: return

  public void apply(org.xbill.DNS.Message, int, org.xbill.DNS.TSIGRecord);
    Code:
       0: aload_0
       1: aload_1
       2: iload_2
       3: aload_3
       4: iconst_1
       5: invokevirtual #98                 // Method apply:(Lorg/xbill/DNS/Message;ILorg/xbill/DNS/TSIGRecord;Z)V
       8: return

  public void apply(org.xbill.DNS.Message, org.xbill.DNS.TSIGRecord, boolean);
    Code:
       0: aload_0
       1: aload_1
       2: iconst_0
       3: aload_2
       4: iload_3
       5: invokevirtual #98                 // Method apply:(Lorg/xbill/DNS/Message;ILorg/xbill/DNS/TSIGRecord;Z)V
       8: return

  public void apply(org.xbill.DNS.Message, int, org.xbill.DNS.TSIGRecord, boolean);
    Code:
       0: aload_0
       1: aload_1
       2: aload_1
       3: invokevirtual #99                 // Method org/xbill/DNS/Message.toWire:()[B
       6: iload_2
       7: aload_3
       8: iload         4
      10: invokevirtual #67                 // Method generate:(Lorg/xbill/DNS/Message;[BILorg/xbill/DNS/TSIGRecord;Z)Lorg/xbill/DNS/TSIGRecord;
      13: astore        5
      15: aload_1
      16: aload         5
      18: iconst_3
      19: invokevirtual #101                // Method org/xbill/DNS/Message.addRecord:(Lorg/xbill/DNS/Record;I)V
      22: aload_1
      23: iconst_3
      24: putfield      #103                // Field org/xbill/DNS/Message.tsigState:I
      27: return

  public void applyStream(org.xbill.DNS.Message, org.xbill.DNS.TSIGRecord, boolean);
    Code:
       0: aload_0
       1: aload_1
       2: iconst_0
       3: aload_2
       4: iload_3
       5: invokevirtual #98                 // Method apply:(Lorg/xbill/DNS/Message;ILorg/xbill/DNS/TSIGRecord;Z)V
       8: return

  public byte verify(org.xbill.DNS.Message, byte[], int, org.xbill.DNS.TSIGRecord);
    Code:
       0: aload_0
       1: aload_1
       2: aload_2
       3: aload         4
       5: invokevirtual #104                // Method verify:(Lorg/xbill/DNS/Message;[BLorg/xbill/DNS/TSIGRecord;)I
       8: i2b
       9: ireturn

  public int verify(org.xbill.DNS.Message, byte[], org.xbill.DNS.TSIGRecord);
    Code:
       0: aload_0
       1: aload_1
       2: aload_2
       3: aload_3
       4: iconst_1
       5: invokevirtual #105                // Method verify:(Lorg/xbill/DNS/Message;[BLorg/xbill/DNS/TSIGRecord;Z)I
       8: ireturn

  public int verify(org.xbill.DNS.Message, byte[], org.xbill.DNS.TSIGRecord, boolean);
    Code:
       0: aload_1
       1: iconst_4
       2: putfield      #103                // Field org/xbill/DNS/Message.tsigState:I
       5: aload_1
       6: invokevirtual #106                // Method org/xbill/DNS/Message.getTSIG:()Lorg/xbill/DNS/TSIGRecord;
       9: astore        5
      11: aload         5
      13: ifnonnull     18
      16: iconst_1
      17: ireturn
      18: aload         5
      20: invokevirtual #107                // Method org/xbill/DNS/TSIGRecord.getName:()Lorg/xbill/DNS/Name;
      23: aload_0
      24: getfield      #51                 // Field name:Lorg/xbill/DNS/Name;
      27: invokevirtual #108                // Method org/xbill/DNS/Name.equals:(Ljava/lang/Object;)Z
      30: ifeq          48
      33: aload         5
      35: invokevirtual #109                // Method org/xbill/DNS/TSIGRecord.getAlgorithm:()Lorg/xbill/DNS/Name;
      38: aload_0
      39: getfield      #52                 // Field alg:Lorg/xbill/DNS/Name;
      42: invokevirtual #108                // Method org/xbill/DNS/Name.equals:(Ljava/lang/Object;)Z
      45: ifne          108
      48: getstatic     #1                  // Field log:Lorg/slf4j/Logger;
      51: ldc           #110                // String BADKEY failure on message id {}, expected: {}/{}, actual: {}/{}
      53: iconst_5
      54: anewarray     #111                // class java/lang/Object
      57: dup
      58: iconst_0
      59: aload_1
      60: invokevirtual #95                 // Method org/xbill/DNS/Message.getHeader:()Lorg/xbill/DNS/Header;
      63: invokevirtual #96                 // Method org/xbill/DNS/Header.getID:()I
      66: invokestatic  #112                // Method java/lang/Integer.valueOf:(I)Ljava/lang/Integer;
      69: aastore
      70: dup
      71: iconst_1
      72: aload_0
      73: getfield      #51                 // Field name:Lorg/xbill/DNS/Name;
      76: aastore
      77: dup
      78: iconst_2
      79: aload_0
      80: getfield      #52                 // Field alg:Lorg/xbill/DNS/Name;
      83: aastore
      84: dup
      85: iconst_3
      86: aload         5
      88: invokevirtual #107                // Method org/xbill/DNS/TSIGRecord.getName:()Lorg/xbill/DNS/Name;
      91: aastore
      92: dup
      93: iconst_4
      94: aload         5
      96: invokevirtual #109                // Method org/xbill/DNS/TSIGRecord.getAlgorithm:()Lorg/xbill/DNS/Name;
      99: aastore
     100: invokeinterface #113,  3          // InterfaceMethod org/slf4j/Logger.debug:(Ljava/lang/String;[Ljava/lang/Object;)V
     105: bipush        17
     107: ireturn
     108: aload_0
     109: invokespecial #71                 // Method initHmac:()Ljavax/crypto/Mac;
     112: astore        6
     114: aload_3
     115: ifnull        144
     118: aload         5
     120: invokevirtual #114                // Method org/xbill/DNS/TSIGRecord.getError:()I
     123: bipush        17
     125: if_icmpeq     144
     128: aload         5
     130: invokevirtual #114                // Method org/xbill/DNS/TSIGRecord.getError:()I
     133: bipush        16
     135: if_icmpeq     144
     138: aload         6
     140: aload_3
     141: invokestatic  #76                 // Method hmacAddSignature:(Ljavax/crypto/Mac;Lorg/xbill/DNS/TSIGRecord;)V
     144: aload_1
     145: invokevirtual #95                 // Method org/xbill/DNS/Message.getHeader:()Lorg/xbill/DNS/Header;
     148: iconst_3
     149: invokevirtual #115                // Method org/xbill/DNS/Header.decCount:(I)V
     152: aload_1
     153: invokevirtual #95                 // Method org/xbill/DNS/Message.getHeader:()Lorg/xbill/DNS/Header;
     156: invokevirtual #116                // Method org/xbill/DNS/Header.toWire:()[B
     159: astore        7
     161: aload_1
     162: invokevirtual #95                 // Method org/xbill/DNS/Message.getHeader:()Lorg/xbill/DNS/Header;
     165: iconst_3
     166: invokevirtual #117                // Method org/xbill/DNS/Header.incCount:(I)V
     169: getstatic     #1                  // Field log:Lorg/slf4j/Logger;
     172: invokeinterface #77,  1           // InterfaceMethod org/slf4j/Logger.isTraceEnabled:()Z
     177: ifeq          195
     180: getstatic     #1                  // Field log:Lorg/slf4j/Logger;
     183: ldc           #118                // String TSIG-HMAC header
     185: aload         7
     187: invokestatic  #79                 // Method org/xbill/DNS/utils/hexdump.dump:(Ljava/lang/String;[B)Ljava/lang/String;
     190: invokeinterface #80,  2           // InterfaceMethod org/slf4j/Logger.trace:(Ljava/lang/String;)V
     195: aload         6
     197: aload         7
     199: invokevirtual #81                 // Method javax/crypto/Mac.update:([B)V
     202: aload_1
     203: getfield      #119                // Field org/xbill/DNS/Message.tsigstart:I
     206: aload         7
     208: arraylength
     209: isub
     210: istore        8
     212: getstatic     #1                  // Field log:Lorg/slf4j/Logger;
     215: invokeinterface #77,  1           // InterfaceMethod org/slf4j/Logger.isTraceEnabled:()Z
     220: ifeq          242
     223: getstatic     #1                  // Field log:Lorg/slf4j/Logger;
     226: ldc           #120                // String TSIG-HMAC message after header
     228: aload_2
     229: aload         7
     231: arraylength
     232: iload         8
     234: invokestatic  #121                // Method org/xbill/DNS/utils/hexdump.dump:(Ljava/lang/String;[BII)Ljava/lang/String;
     237: invokeinterface #80,  2           // InterfaceMethod org/slf4j/Logger.trace:(Ljava/lang/String;)V
     242: aload         6
     244: aload_2
     245: aload         7
     247: arraylength
     248: iload         8
     250: invokevirtual #122                // Method javax/crypto/Mac.update:([BII)V
     253: new           #82                 // class org/xbill/DNS/DNSOutput
     256: dup
     257: invokespecial #83                 // Method org/xbill/DNS/DNSOutput."<init>":()V
     260: astore        9
     262: iload         4
     264: ifeq          307
     267: aload         5
     269: invokevirtual #107                // Method org/xbill/DNS/TSIGRecord.getName:()Lorg/xbill/DNS/Name;
     272: aload         9
     274: invokevirtual #84                 // Method org/xbill/DNS/Name.toWireCanonical:(Lorg/xbill/DNS/DNSOutput;)V
     277: aload         9
     279: aload         5
     281: getfield      #123                // Field org/xbill/DNS/TSIGRecord.dclass:I
     284: invokevirtual #86                 // Method org/xbill/DNS/DNSOutput.writeU16:(I)V
     287: aload         9
     289: aload         5
     291: getfield      #124                // Field org/xbill/DNS/TSIGRecord.ttl:J
     294: invokevirtual #87                 // Method org/xbill/DNS/DNSOutput.writeU32:(J)V
     297: aload         5
     299: invokevirtual #109                // Method org/xbill/DNS/TSIGRecord.getAlgorithm:()Lorg/xbill/DNS/Name;
     302: aload         9
     304: invokevirtual #84                 // Method org/xbill/DNS/Name.toWireCanonical:(Lorg/xbill/DNS/DNSOutput;)V
     307: aload         5
     309: invokevirtual #69                 // Method org/xbill/DNS/TSIGRecord.getTimeSigned:()Ljava/time/Instant;
     312: aload         5
     314: invokevirtual #125                // Method org/xbill/DNS/TSIGRecord.getFudge:()Ljava/time/Duration;
     317: aload         9
     319: invokestatic  #88                 // Method writeTsigTimersVariables:(Ljava/time/Instant;Ljava/time/Duration;Lorg/xbill/DNS/DNSOutput;)V
     322: iload         4
     324: ifeq          375
     327: aload         9
     329: aload         5
     331: invokevirtual #114                // Method org/xbill/DNS/TSIGRecord.getError:()I
     334: invokevirtual #86                 // Method org/xbill/DNS/DNSOutput.writeU16:(I)V
     337: aload         5
     339: invokevirtual #126                // Method org/xbill/DNS/TSIGRecord.getOther:()[B
     342: ifnull        369
     345: aload         9
     347: aload         5
     349: invokevirtual #126                // Method org/xbill/DNS/TSIGRecord.getOther:()[B
     352: arraylength
     353: invokevirtual #86                 // Method org/xbill/DNS/DNSOutput.writeU16:(I)V
     356: aload         9
     358: aload         5
     360: invokevirtual #126                // Method org/xbill/DNS/TSIGRecord.getOther:()[B
     363: invokevirtual #127                // Method org/xbill/DNS/DNSOutput.writeByteArray:([B)V
     366: goto          375
     369: aload         9
     371: iconst_0
     372: invokevirtual #86                 // Method org/xbill/DNS/DNSOutput.writeU16:(I)V
     375: aload         9
     377: invokevirtual #89                 // Method org/xbill/DNS/DNSOutput.toByteArray:()[B
     380: astore        10
     382: getstatic     #1                  // Field log:Lorg/slf4j/Logger;
     385: invokeinterface #77,  1           // InterfaceMethod org/slf4j/Logger.isTraceEnabled:()Z
     390: ifeq          408
     393: getstatic     #1                  // Field log:Lorg/slf4j/Logger;
     396: ldc           #90                 // String TSIG-HMAC variables
     398: aload         10
     400: invokestatic  #79                 // Method org/xbill/DNS/utils/hexdump.dump:(Ljava/lang/String;[B)Ljava/lang/String;
     403: invokeinterface #80,  2           // InterfaceMethod org/slf4j/Logger.trace:(Ljava/lang/String;)V
     408: aload         6
     410: aload         10
     412: invokevirtual #81                 // Method javax/crypto/Mac.update:([B)V
     415: aload         5
     417: invokevirtual #128                // Method org/xbill/DNS/TSIGRecord.getSignature:()[B
     420: astore        11
     422: aload         6
     424: invokevirtual #129                // Method javax/crypto/Mac.getMacLength:()I
     427: istore        12
     429: bipush        10
     431: iload         12
     433: iconst_2
     434: idiv
     435: invokestatic  #130                // Method java/lang/Math.max:(II)I
     438: istore        13
     440: aload         11
     442: arraylength
     443: iload         12
     445: if_icmple     472
     448: getstatic     #1                  // Field log:Lorg/slf4j/Logger;
     451: ldc           #131                // String BADSIG: signature too long, expected: {}, actual: {}
     453: iload         12
     455: invokestatic  #112                // Method java/lang/Integer.valueOf:(I)Ljava/lang/Integer;
     458: aload         11
     460: arraylength
     461: invokestatic  #112                // Method java/lang/Integer.valueOf:(I)Ljava/lang/Integer;
     464: invokeinterface #132,  4          // InterfaceMethod org/slf4j/Logger.debug:(Ljava/lang/String;Ljava/lang/Object;Ljava/lang/Object;)V
     469: bipush        16
     471: ireturn
     472: aload         11
     474: arraylength
     475: iload         13
     477: if_icmpge     522
     480: getstatic     #1                  // Field log:Lorg/slf4j/Logger;
     483: ldc           #133                // String BADSIG: signature too short, expected: {} of {}, actual: {}
     485: iconst_3
     486: anewarray     #111                // class java/lang/Object
     489: dup
     490: iconst_0
     491: iload         13
     493: invokestatic  #112                // Method java/lang/Integer.valueOf:(I)Ljava/lang/Integer;
     496: aastore
     497: dup
     498: iconst_1
     499: iload         12
     501: invokestatic  #112                // Method java/lang/Integer.valueOf:(I)Ljava/lang/Integer;
     504: aastore
     505: dup
     506: iconst_2
     507: aload         11
     509: arraylength
     510: invokestatic  #112                // Method java/lang/Integer.valueOf:(I)Ljava/lang/Integer;
     513: aastore
     514: invokeinterface #113,  3          // InterfaceMethod org/slf4j/Logger.debug:(Ljava/lang/String;[Ljava/lang/Object;)V
     519: bipush        16
     521: ireturn
     522: aload         6
     524: invokevirtual #134                // Method javax/crypto/Mac.doFinal:()[B
     527: astore        14
     529: aload         14
     531: aload         11
     533: invokestatic  #135                // Method verify:([B[B)Z
     536: ifne          573
     539: getstatic     #1                  // Field log:Lorg/slf4j/Logger;
     542: invokeinterface #136,  1          // InterfaceMethod org/slf4j/Logger.isDebugEnabled:()Z
     547: ifeq          570
     550: getstatic     #1                  // Field log:Lorg/slf4j/Logger;
     553: ldc           #137                // String BADSIG: signature verification failed, expected: {}, actual: {}
     555: aload         14
     557: invokestatic  #138                // Method org/xbill/DNS/utils/base64.toString:([B)Ljava/lang/String;
     560: aload         11
     562: invokestatic  #138                // Method org/xbill/DNS/utils/base64.toString:([B)Ljava/lang/String;
     565: invokeinterface #132,  4          // InterfaceMethod org/slf4j/Logger.debug:(Ljava/lang/String;Ljava/lang/Object;Ljava/lang/Object;)V
     570: bipush        16
     572: ireturn
     573: aload_0
     574: getfield      #53                 // Field clock:Ljava/time/Clock;
     577: invokevirtual #70                 // Method java/time/Clock.instant:()Ljava/time/Instant;
     580: astore        14
     582: aload         14
     584: aload         5
     586: invokevirtual #69                 // Method org/xbill/DNS/TSIGRecord.getTimeSigned:()Ljava/time/Instant;
     589: invokestatic  #139                // Method java/time/Duration.between:(Ljava/time/temporal/Temporal;Ljava/time/temporal/Temporal;)Ljava/time/Duration;
     592: invokevirtual #140                // Method java/time/Duration.abs:()Ljava/time/Duration;
     595: astore        15
     597: aload         15
     599: aload         5
     601: invokevirtual #125                // Method org/xbill/DNS/TSIGRecord.getFudge:()Ljava/time/Duration;
     604: invokevirtual #141                // Method java/time/Duration.compareTo:(Ljava/time/Duration;)I
     607: ifle          648
     610: getstatic     #1                  // Field log:Lorg/slf4j/Logger;
     613: ldc           #142                // String BADTIME failure, now {} +/- tsig {} > fudge {}
     615: iconst_3
     616: anewarray     #111                // class java/lang/Object
     619: dup
     620: iconst_0
     621: aload         14
     623: aastore
     624: dup
     625: iconst_1
     626: aload         5
     628: invokevirtual #69                 // Method org/xbill/DNS/TSIGRecord.getTimeSigned:()Ljava/time/Instant;
     631: aastore
     632: dup
     633: iconst_2
     634: aload         5
     636: invokevirtual #125                // Method org/xbill/DNS/TSIGRecord.getFudge:()Ljava/time/Duration;
     639: aastore
     640: invokeinterface #113,  3          // InterfaceMethod org/slf4j/Logger.debug:(Ljava/lang/String;[Ljava/lang/Object;)V
     645: bipush        18
     647: ireturn
     648: aload_1
     649: iconst_1
     650: putfield      #103                // Field org/xbill/DNS/Message.tsigState:I
     653: iconst_0
     654: ireturn

  public int recordLength();
    Code:
       0: aload_0
       1: getfield      #51                 // Field name:Lorg/xbill/DNS/Name;
       4: invokevirtual #143                // Method org/xbill/DNS/Name.length:()S
       7: bipush        10
       9: iadd
      10: aload_0
      11: getfield      #52                 // Field alg:Lorg/xbill/DNS/Name;
      14: invokevirtual #143                // Method org/xbill/DNS/Name.length:()S
      17: iadd
      18: bipush        8
      20: iadd
      21: bipush        18
      23: iadd
      24: iconst_4
      25: iadd
      26: bipush        8
      28: iadd
      29: ireturn

  private static void hmacAddSignature(javax.crypto.Mac, org.xbill.DNS.TSIGRecord);
    Code:
       0: aload_1
       1: invokevirtual #128                // Method org/xbill/DNS/TSIGRecord.getSignature:()[B
       4: arraylength
       5: invokestatic  #144                // Method org/xbill/DNS/DNSOutput.toU16:(I)[B
       8: astore_2
       9: getstatic     #1                  // Field log:Lorg/slf4j/Logger;
      12: invokeinterface #77,  1           // InterfaceMethod org/slf4j/Logger.isTraceEnabled:()Z
      17: ifeq          51
      20: getstatic     #1                  // Field log:Lorg/slf4j/Logger;
      23: ldc           #145                // String TSIG-HMAC signature size
      25: aload_2
      26: invokestatic  #79                 // Method org/xbill/DNS/utils/hexdump.dump:(Ljava/lang/String;[B)Ljava/lang/String;
      29: invokeinterface #80,  2           // InterfaceMethod org/slf4j/Logger.trace:(Ljava/lang/String;)V
      34: getstatic     #1                  // Field log:Lorg/slf4j/Logger;
      37: ldc           #146                // String TSIG-HMAC signature
      39: aload_1
      40: invokevirtual #128                // Method org/xbill/DNS/TSIGRecord.getSignature:()[B
      43: invokestatic  #79                 // Method org/xbill/DNS/utils/hexdump.dump:(Ljava/lang/String;[B)Ljava/lang/String;
      46: invokeinterface #80,  2           // InterfaceMethod org/slf4j/Logger.trace:(Ljava/lang/String;)V
      51: aload_0
      52: aload_2
      53: invokevirtual #81                 // Method javax/crypto/Mac.update:([B)V
      56: aload_0
      57: aload_1
      58: invokevirtual #128                // Method org/xbill/DNS/TSIGRecord.getSignature:()[B
      61: invokevirtual #81                 // Method javax/crypto/Mac.update:([B)V
      64: return

  private static void writeTsigTimersVariables(java.time.Instant, java.time.Duration, org.xbill.DNS.DNSOutput);
    Code:
       0: aload_0
       1: aload_2
       2: invokestatic  #93                 // Method writeTsigTime:(Ljava/time/Instant;Lorg/xbill/DNS/DNSOutput;)V
       5: aload_2
       6: aload_1
       7: invokevirtual #147                // Method java/time/Duration.getSeconds:()J
      10: l2i
      11: invokevirtual #86                 // Method org/xbill/DNS/DNSOutput.writeU16:(I)V
      14: return

  private static void writeTsigTime(java.time.Instant, org.xbill.DNS.DNSOutput);
    Code:
       0: aload_0
       1: invokevirtual #148                // Method java/time/Instant.getEpochSecond:()J
       4: lstore_2
       5: lload_2
       6: bipush        32
       8: lshr
       9: l2i
      10: istore        4
      12: lload_2
      13: ldc2_w        #149                // long 4294967295l
      16: land
      17: lstore        5
      19: aload_1
      20: iload         4
      22: invokevirtual #86                 // Method org/xbill/DNS/DNSOutput.writeU16:(I)V
      25: aload_1
      26: lload         5
      28: invokevirtual #87                 // Method org/xbill/DNS/DNSOutput.writeU32:(J)V
      31: return

  private static org.xbill.DNS.Name lambda$algorithmToName$3(java.lang.String);
    Code:
       0: getstatic     #9                  // Field algMap:Ljava/util/Map;
       3: invokeinterface #151,  1          // InterfaceMethod java/util/Map.entrySet:()Ljava/util/Set;
       8: invokeinterface #11,  1           // InterfaceMethod java/util/Set.stream:()Ljava/util/stream/Stream;
      13: aload_0
      14: invokedynamic #152,  0            // InvokeDynamic #2:test:(Ljava/lang/String;)Ljava/util/function/Predicate;
      19: invokeinterface #13,  2           // InterfaceMethod java/util/stream/Stream.filter:(Ljava/util/function/Predicate;)Ljava/util/stream/Stream;
      24: invokedynamic #153,  0            // InvokeDynamic #3:apply:()Ljava/util/function/Function;
      29: invokeinterface #154,  2          // InterfaceMethod java/util/stream/Stream.map:(Ljava/util/function/Function;)Ljava/util/stream/Stream;
      34: invokeinterface #14,  1           // InterfaceMethod java/util/stream/Stream.findAny:()Ljava/util/Optional;
      39: aload_0
      40: invokedynamic #155,  0            // InvokeDynamic #4:get:(Ljava/lang/String;)Ljava/util/function/Supplier;
      45: invokevirtual #156                // Method java/util/Optional.orElseThrow:(Ljava/util/function/Supplier;)Ljava/lang/Object;
      48: checkcast     #17                 // class org/xbill/DNS/Name
      51: areturn

  private static java.lang.IllegalArgumentException lambda$null$2(java.lang.String);
    Code:
       0: new           #2                  // class java/lang/IllegalArgumentException
       3: dup
       4: new           #20                 // class java/lang/StringBuilder
       7: dup
       8: invokespecial #21                 // Method java/lang/StringBuilder."<init>":()V
      11: ldc           #22                 // String Unknown algorithm:
      13: invokevirtual #23                 // Method java/lang/StringBuilder.append:(Ljava/lang/String;)Ljava/lang/StringBuilder;
      16: aload_0
      17: invokevirtual #23                 // Method java/lang/StringBuilder.append:(Ljava/lang/String;)Ljava/lang/StringBuilder;
      20: invokevirtual #25                 // Method java/lang/StringBuilder.toString:()Ljava/lang/String;
      23: invokespecial #4                  // Method java/lang/IllegalArgumentException."<init>":(Ljava/lang/String;)V
      26: areturn

  private static boolean lambda$null$1(java.lang.String, java.util.Map$Entry);
    Code:
       0: aload_1
       1: invokeinterface #157,  1          // InterfaceMethod java/util/Map$Entry.getValue:()Ljava/lang/Object;
       6: checkcast     #19                 // class java/lang/String
       9: aload_0
      10: invokevirtual #6                  // Method java/lang/String.equalsIgnoreCase:(Ljava/lang/String;)Z
      13: ireturn

  private static boolean lambda$algorithmToName$0(java.lang.String, org.xbill.DNS.Name);
    Code:
       0: aload_1
       1: invokevirtual #158                // Method org/xbill/DNS/Name.toString:()Ljava/lang/String;
       4: aload_0
       5: invokevirtual #6                  // Method java/lang/String.equalsIgnoreCase:(Ljava/lang/String;)Z
       8: ifne          23
      11: aload_1
      12: iconst_1
      13: invokevirtual #159                // Method org/xbill/DNS/Name.toString:(Z)Ljava/lang/String;
      16: aload_0
      17: invokevirtual #6                  // Method java/lang/String.equalsIgnoreCase:(Ljava/lang/String;)Z
      20: ifeq          27
      23: iconst_1
      24: goto          28
      27: iconst_0
      28: ireturn

  static org.slf4j.Logger access$000();
    Code:
       0: getstatic     #1                  // Field log:Lorg/slf4j/Logger;
       3: areturn

  static {};
    Code:
       0: ldc           #64                 // class org/xbill/DNS/TSIG
       2: invokestatic  #160                // Method org/slf4j/LoggerFactory.getLogger:(Ljava/lang/Class;)Lorg/slf4j/Logger;
       5: putstatic     #1                  // Field log:Lorg/slf4j/Logger;
       8: ldc           #161                // String gss-tsig.
      10: invokestatic  #162                // Method org/xbill/DNS/Name.fromConstantString:(Ljava/lang/String;)Lorg/xbill/DNS/Name;
      13: putstatic     #163                // Field GSS_TSIG:Lorg/xbill/DNS/Name;
      16: ldc           #164                // String HMAC-MD5.SIG-ALG.REG.INT.
      18: invokestatic  #162                // Method org/xbill/DNS/Name.fromConstantString:(Ljava/lang/String;)Lorg/xbill/DNS/Name;
      21: putstatic     #8                  // Field HMAC_MD5:Lorg/xbill/DNS/Name;
      24: getstatic     #8                  // Field HMAC_MD5:Lorg/xbill/DNS/Name;
      27: putstatic     #165                // Field HMAC:Lorg/xbill/DNS/Name;
      30: ldc           #166                // String hmac-sha1.
      32: invokestatic  #162                // Method org/xbill/DNS/Name.fromConstantString:(Ljava/lang/String;)Lorg/xbill/DNS/Name;
      35: putstatic     #167                // Field HMAC_SHA1:Lorg/xbill/DNS/Name;
      38: ldc           #168                // String hmac-sha224.
      40: invokestatic  #162                // Method org/xbill/DNS/Name.fromConstantString:(Ljava/lang/String;)Lorg/xbill/DNS/Name;
      43: putstatic     #169                // Field HMAC_SHA224:Lorg/xbill/DNS/Name;
      46: ldc           #170                // String hmac-sha256.
      48: invokestatic  #162                // Method org/xbill/DNS/Name.fromConstantString:(Ljava/lang/String;)Lorg/xbill/DNS/Name;
      51: putstatic     #171                // Field HMAC_SHA256:Lorg/xbill/DNS/Name;
      54: ldc           #172                // String hmac-sha384.
      56: invokestatic  #162                // Method org/xbill/DNS/Name.fromConstantString:(Ljava/lang/String;)Lorg/xbill/DNS/Name;
      59: putstatic     #173                // Field HMAC_SHA384:Lorg/xbill/DNS/Name;
      62: ldc           #174                // String hmac-sha512.
      64: invokestatic  #162                // Method org/xbill/DNS/Name.fromConstantString:(Ljava/lang/String;)Lorg/xbill/DNS/Name;
      67: putstatic     #175                // Field HMAC_SHA512:Lorg/xbill/DNS/Name;
      70: new           #176                // class java/util/HashMap
      73: dup
      74: invokespecial #177                // Method java/util/HashMap."<init>":()V
      77: astore_0
      78: aload_0
      79: getstatic     #8                  // Field HMAC_MD5:Lorg/xbill/DNS/Name;
      82: ldc           #178                // String HmacMD5
      84: invokeinterface #179,  3          // InterfaceMethod java/util/Map.put:(Ljava/lang/Object;Ljava/lang/Object;)Ljava/lang/Object;
      89: pop
      90: aload_0
      91: getstatic     #167                // Field HMAC_SHA1:Lorg/xbill/DNS/Name;
      94: ldc           #180                // String HmacSHA1
      96: invokeinterface #179,  3          // InterfaceMethod java/util/Map.put:(Ljava/lang/Object;Ljava/lang/Object;)Ljava/lang/Object;
     101: pop
     102: aload_0
     103: getstatic     #169                // Field HMAC_SHA224:Lorg/xbill/DNS/Name;
     106: ldc           #181                // String HmacSHA224
     108: invokeinterface #179,  3          // InterfaceMethod java/util/Map.put:(Ljava/lang/Object;Ljava/lang/Object;)Ljava/lang/Object;
     113: pop
     114: aload_0
     115: getstatic     #171                // Field HMAC_SHA256:Lorg/xbill/DNS/Name;
     118: ldc           #182                // String HmacSHA256
     120: invokeinterface #179,  3          // InterfaceMethod java/util/Map.put:(Ljava/lang/Object;Ljava/lang/Object;)Ljava/lang/Object;
     125: pop
     126: aload_0
     127: getstatic     #173                // Field HMAC_SHA384:Lorg/xbill/DNS/Name;
     130: ldc           #183                // String HmacSHA384
     132: invokeinterface #179,  3          // InterfaceMethod java/util/Map.put:(Ljava/lang/Object;Ljava/lang/Object;)Ljava/lang/Object;
     137: pop
     138: aload_0
     139: getstatic     #175                // Field HMAC_SHA512:Lorg/xbill/DNS/Name;
     142: ldc           #184                // String HmacSHA512
     144: invokeinterface #179,  3          // InterfaceMethod java/util/Map.put:(Ljava/lang/Object;Ljava/lang/Object;)Ljava/lang/Object;
     149: pop
     150: aload_0
     151: invokestatic  #185                // Method java/util/Collections.unmodifiableMap:(Ljava/util/Map;)Ljava/util/Map;
     154: putstatic     #9                  // Field algMap:Ljava/util/Map;
     157: ldc2_w        #186                // long 300l
     160: invokestatic  #75                 // Method java/time/Duration.ofSeconds:(J)Ljava/time/Duration;
     163: putstatic     #74                 // Field FUDGE:Ljava/time/Duration;
     166: return
}
