Compiled from "AbstractTypeSafeBeanResolver.java"
public class org.jboss.weld.resolution.AbstractTypeSafeBeanResolver$BeanDisambiguation extends com.google.common.cache.CacheLoader<java.util.Set<javax.enterprise.inject.spi.Bean<?>>, java.util.Set<javax.enterprise.inject.spi.Bean<?>>> {
  final org.jboss.weld.resolution.AbstractTypeSafeBeanResolver this$0;

  private org.jboss.weld.resolution.AbstractTypeSafeBeanResolver$BeanDisambiguation(org.jboss.weld.resolution.AbstractTypeSafeBeanResolver);
    Code:
       0: aload_0
       1: aload_1
       2: putfield      #2                  // Field this$0:Lorg/jboss/weld/resolution/AbstractTypeSafeBeanResolver;
       5: aload_0
       6: invokespecial #3                  // Method com/google/common/cache/CacheLoader."<init>":()V
       9: return

  public java.util.Set<javax.enterprise.inject.spi.Bean<?>> load(java.util.Set<javax.enterprise.inject.spi.Bean<?>>);
    Code:
       0: aload_1
       1: invokeinterface #4,  1            // InterfaceMethod java/util/Set.size:()I
       6: iconst_1
       7: if_icmple     170
      10: new           #5                  // class java/util/HashSet
      13: dup
      14: invokespecial #6                  // Method java/util/HashSet."<init>":()V
      17: astore_2
      18: new           #5                  // class java/util/HashSet
      21: dup
      22: invokespecial #6                  // Method java/util/HashSet."<init>":()V
      25: astore_3
      26: aload_1
      27: invokeinterface #7,  1            // InterfaceMethod java/util/Set.iterator:()Ljava/util/Iterator;
      32: astore        4
      34: aload         4
      36: invokeinterface #8,  1            // InterfaceMethod java/util/Iterator.hasNext:()Z
      41: ifeq          125
      44: aload         4
      46: invokeinterface #9,  1            // InterfaceMethod java/util/Iterator.next:()Ljava/lang/Object;
      51: checkcast     #10                 // class javax/enterprise/inject/spi/Bean
      54: astore        5
      56: aload         5
      58: invokeinterface #11,  1           // InterfaceMethod javax/enterprise/inject/spi/Bean.isAlternative:()Z
      63: ifeq          78
      66: aload_3
      67: aload         5
      69: invokeinterface #12,  2           // InterfaceMethod java/util/Set.add:(Ljava/lang/Object;)Z
      74: pop
      75: goto          113
      78: aload         5
      80: instanceof    #13                 // class org/jboss/weld/bean/AbstractProducerBean
      83: ifeq          113
      86: aload         5
      88: checkcast     #13                 // class org/jboss/weld/bean/AbstractProducerBean
      91: astore        6
      93: aload         6
      95: invokevirtual #14                 // Method org/jboss/weld/bean/AbstractProducerBean.getDeclaringBean:()Lorg/jboss/weld/bean/AbstractClassBean;
      98: invokevirtual #15                 // Method org/jboss/weld/bean/AbstractClassBean.isAlternative:()Z
     101: ifeq          113
     104: aload_3
     105: aload         5
     107: invokeinterface #12,  2           // InterfaceMethod java/util/Set.add:(Ljava/lang/Object;)Z
     112: pop
     113: aload_2
     114: aload         5
     116: invokeinterface #12,  2           // InterfaceMethod java/util/Set.add:(Ljava/lang/Object;)Z
     121: pop
     122: goto          34
     125: aload_3
     126: invokeinterface #16,  1           // InterfaceMethod java/util/Set.isEmpty:()Z
     131: ifeq          139
     134: aload_2
     135: invokestatic  #17                 // Method org/jboss/weld/util/collections/WeldCollections.immutableGuavaSet:(Ljava/util/Set;)Ljava/util/Set;
     138: areturn
     139: aload_3
     140: invokeinterface #4,  1            // InterfaceMethod java/util/Set.size:()I
     145: iconst_1
     146: if_icmpne     164
     149: aload_3
     150: invokeinterface #7,  1            // InterfaceMethod java/util/Set.iterator:()Ljava/util/Iterator;
     155: invokeinterface #9,  1            // InterfaceMethod java/util/Iterator.next:()Ljava/lang/Object;
     160: invokestatic  #18                 // Method java/util/Collections.singleton:(Ljava/lang/Object;)Ljava/util/Set;
     163: areturn
     164: aload_0
     165: aload_3
     166: invokevirtual #19                 // Method resolveAlternatives:(Ljava/util/Set;)Ljava/util/Set;
     169: areturn
     170: aload_1
     171: invokestatic  #20                 // Method com/google/common/collect/ImmutableSet.copyOf:(Ljava/util/Collection;)Lcom/google/common/collect/ImmutableSet;
     174: areturn

  public java.util.Set<javax.enterprise.inject.spi.Bean<?>> resolveAlternatives(java.util.Set<javax.enterprise.inject.spi.Bean<?>>);
    Code:
       0: ldc           #22                 // int -2147483648
       2: istore_2
       3: new           #5                  // class java/util/HashSet
       6: dup
       7: invokespecial #6                  // Method java/util/HashSet."<init>":()V
      10: astore_3
      11: aload_1
      12: invokeinterface #7,  1            // InterfaceMethod java/util/Set.iterator:()Ljava/util/Iterator;
      17: astore        4
      19: aload         4
      21: invokeinterface #8,  1            // InterfaceMethod java/util/Iterator.hasNext:()Z
      26: ifeq          115
      29: aload         4
      31: invokeinterface #9,  1            // InterfaceMethod java/util/Iterator.next:()Ljava/lang/Object;
      36: checkcast     #10                 // class javax/enterprise/inject/spi/Bean
      39: astore        5
      41: aload_0
      42: getfield      #2                  // Field this$0:Lorg/jboss/weld/resolution/AbstractTypeSafeBeanResolver;
      45: invokestatic  #23                 // Method org/jboss/weld/resolution/AbstractTypeSafeBeanResolver.access$000:(Lorg/jboss/weld/resolution/AbstractTypeSafeBeanResolver;)Lorg/jboss/weld/manager/BeanManagerImpl;
      48: invokevirtual #24                 // Method org/jboss/weld/manager/BeanManagerImpl.getEnabled:()Lorg/jboss/weld/bootstrap/enablement/ModuleEnablement;
      51: aload         5
      53: invokeinterface #25,  1           // InterfaceMethod javax/enterprise/inject/spi/Bean.getBeanClass:()Ljava/lang/Class;
      58: invokevirtual #26                 // Method org/jboss/weld/bootstrap/enablement/ModuleEnablement.getAlternativePriority:(Ljava/lang/Class;)Ljava/lang/Integer;
      61: astore        6
      63: aload         6
      65: ifnonnull     73
      68: aload_1
      69: invokestatic  #17                 // Method org/jboss/weld/util/collections/WeldCollections.immutableGuavaSet:(Ljava/util/Set;)Ljava/util/Set;
      72: areturn
      73: aload         6
      75: invokevirtual #27                 // Method java/lang/Integer.intValue:()I
      78: iload_2
      79: if_icmple     94
      82: aload         6
      84: invokevirtual #27                 // Method java/lang/Integer.intValue:()I
      87: istore_2
      88: aload_3
      89: invokeinterface #28,  1           // InterfaceMethod java/util/Set.clear:()V
      94: aload         6
      96: invokevirtual #27                 // Method java/lang/Integer.intValue:()I
      99: iload_2
     100: if_icmpne     112
     103: aload_3
     104: aload         5
     106: invokeinterface #12,  2           // InterfaceMethod java/util/Set.add:(Ljava/lang/Object;)Z
     111: pop
     112: goto          19
     115: aload_3
     116: invokestatic  #17                 // Method org/jboss/weld/util/collections/WeldCollections.immutableGuavaSet:(Ljava/util/Set;)Ljava/util/Set;
     119: areturn

  public java.lang.Object load(java.lang.Object) throws java.lang.Exception;
    Code:
       0: aload_0
       1: aload_1
       2: checkcast     #29                 // class java/util/Set
       5: invokevirtual #30                 // Method load:(Ljava/util/Set;)Ljava/util/Set;
       8: areturn

  org.jboss.weld.resolution.AbstractTypeSafeBeanResolver$BeanDisambiguation(org.jboss.weld.resolution.AbstractTypeSafeBeanResolver, org.jboss.weld.resolution.AbstractTypeSafeBeanResolver$1);
    Code:
       0: aload_0
       1: aload_1
       2: invokespecial #1                  // Method "<init>":(Lorg/jboss/weld/resolution/AbstractTypeSafeBeanResolver;)V
       5: return
}
