Compiled from "NameBasedResolver.java"
public class org.jboss.weld.resolution.NameBasedResolver {
  private com.google.common.cache.LoadingCache<java.lang.String, java.util.Set<javax.enterprise.inject.spi.Bean<?>>> resolvedNames;

  public org.jboss.weld.resolution.NameBasedResolver(org.jboss.weld.manager.BeanManagerImpl, java.lang.Iterable<? extends javax.enterprise.inject.spi.Bean<?>>);
    Code:
       0: aload_0
       1: invokespecial #1                  // Method java/lang/Object."<init>":()V
       4: aload_0
       5: invokestatic  #2                  // Method com/google/common/cache/CacheBuilder.newBuilder:()Lcom/google/common/cache/CacheBuilder;
       8: new           #3                  // class org/jboss/weld/resolution/NameBasedResolver$NameToBeanSet
      11: dup
      12: aload_1
      13: aload_2
      14: aconst_null
      15: invokespecial #4                  // Method org/jboss/weld/resolution/NameBasedResolver$NameToBeanSet."<init>":(Lorg/jboss/weld/manager/BeanManagerImpl;Ljava/lang/Iterable;Lorg/jboss/weld/resolution/NameBasedResolver$1;)V
      18: invokevirtual #5                  // Method com/google/common/cache/CacheBuilder.build:(Lcom/google/common/cache/CacheLoader;)Lcom/google/common/cache/LoadingCache;
      21: putfield      #6                  // Field resolvedNames:Lcom/google/common/cache/LoadingCache;
      24: return

  public void clear();
    Code:
       0: aload_0
       1: getfield      #6                  // Field resolvedNames:Lcom/google/common/cache/LoadingCache;
       4: invokeinterface #7,  1            // InterfaceMethod com/google/common/cache/LoadingCache.invalidateAll:()V
       9: return

  public java.util.Set<javax.enterprise.inject.spi.Bean<?>> resolve(java.lang.String);
    Code:
       0: aload_0
       1: getfield      #6                  // Field resolvedNames:Lcom/google/common/cache/LoadingCache;
       4: aload_1
       5: invokestatic  #8                  // Method org/jboss/weld/util/cache/LoadingCacheUtils.getCacheValue:(Lcom/google/common/cache/LoadingCache;Ljava/lang/Object;)Ljava/lang/Object;
       8: checkcast     #9                  // class java/util/Set
      11: areturn

  public java.lang.String toString();
    Code:
       0: new           #10                 // class java/lang/StringBuilder
       3: dup
       4: invokespecial #11                 // Method java/lang/StringBuilder."<init>":()V
       7: astore_1
       8: aload_1
       9: ldc           #12                 // String Resolver\n
      11: invokevirtual #13                 // Method java/lang/StringBuilder.append:(Ljava/lang/String;)Ljava/lang/StringBuilder;
      14: pop
      15: aload_1
      16: ldc           #14                 // String Resolved names points:
      18: invokevirtual #13                 // Method java/lang/StringBuilder.append:(Ljava/lang/String;)Ljava/lang/StringBuilder;
      21: aload_0
      22: getfield      #6                  // Field resolvedNames:Lcom/google/common/cache/LoadingCache;
      25: invokeinterface #15,  1           // InterfaceMethod com/google/common/cache/LoadingCache.size:()J
      30: invokevirtual #16                 // Method java/lang/StringBuilder.append:(J)Ljava/lang/StringBuilder;
      33: bipush        10
      35: invokevirtual #17                 // Method java/lang/StringBuilder.append:(C)Ljava/lang/StringBuilder;
      38: pop
      39: aload_1
      40: invokevirtual #18                 // Method java/lang/StringBuilder.toString:()Ljava/lang/String;
      43: areturn
}
