Compiled from "NodeFormatterNT.java"
public class org.apache.jena.riot.out.NodeFormatterNT extends org.apache.jena.riot.out.NodeFormatterBase {
  private final org.apache.jena.riot.out.quoted.QuotedStringOutput quotedStringProc;

  private final org.apache.jena.riot.out.quoted.QuotedURI quotedUriProc;

  public org.apache.jena.riot.out.NodeFormatterNT();
    Code:
       0: aload_0
       1: getstatic     #1                  // Field org/apache/jena/atlas/lib/CharSpace.UTF8:Lorg/apache/jena/atlas/lib/CharSpace;
       4: invokespecial #2                  // Method "<init>":(Lorg/apache/jena/atlas/lib/CharSpace;)V
       7: return

  public org.apache.jena.riot.out.NodeFormatterNT(org.apache.jena.atlas.lib.CharSpace);
    Code:
       0: aload_0
       1: invokespecial #3                  // Method org/apache/jena/riot/out/NodeFormatterBase."<init>":()V
       4: aload_0
       5: new           #4                  // class org/apache/jena/riot/out/quoted/QuotedStringOutputNT
       8: dup
       9: aload_1
      10: invokespecial #5                  // Method org/apache/jena/riot/out/quoted/QuotedStringOutputNT."<init>":(Lorg/apache/jena/atlas/lib/CharSpace;)V
      13: putfield      #6                  // Field quotedStringProc:Lorg/apache/jena/riot/out/quoted/QuotedStringOutput;
      16: aload_0
      17: new           #7                  // class org/apache/jena/riot/out/quoted/QuotedURI
      20: dup
      21: aload_1
      22: invokespecial #8                  // Method org/apache/jena/riot/out/quoted/QuotedURI."<init>":(Lorg/apache/jena/atlas/lib/CharSpace;)V
      25: putfield      #9                  // Field quotedUriProc:Lorg/apache/jena/riot/out/quoted/QuotedURI;
      28: return

  public void formatURI(org.apache.jena.atlas.io.AWriter, java.lang.String);
    Code:
       0: aload_0
       1: getfield      #9                  // Field quotedUriProc:Lorg/apache/jena/riot/out/quoted/QuotedURI;
       4: aload_1
       5: aload_2
       6: invokevirtual #10                 // Method org/apache/jena/riot/out/quoted/QuotedURI.writeURI:(Lorg/apache/jena/atlas/io/AWriter;Ljava/lang/String;)V
       9: return

  public void formatVar(org.apache.jena.atlas.io.AWriter, java.lang.String);
    Code:
       0: aload_1
       1: bipush        63
       3: invokeinterface #11,  2           // InterfaceMethod org/apache/jena/atlas/io/AWriter.print:(C)V
       8: aload_1
       9: aload_2
      10: iconst_0
      11: invokestatic  #12                 // Method org/apache/jena/atlas/lib/EscapeStr.stringEsc:(Lorg/apache/jena/atlas/io/AWriter;Ljava/lang/String;Z)V
      14: return

  public void formatBNode(org.apache.jena.atlas.io.AWriter, java.lang.String);
    Code:
       0: aload_1
       1: ldc           #13                 // String _:
       3: invokeinterface #14,  2           // InterfaceMethod org/apache/jena/atlas/io/AWriter.print:(Ljava/lang/String;)V
       8: aload_2
       9: invokestatic  #15                 // Method org/apache/jena/riot/out/NodeFmtLib.encodeBNodeLabel:(Ljava/lang/String;)Ljava/lang/String;
      12: astore_3
      13: aload_1
      14: aload_3
      15: invokeinterface #14,  2           // InterfaceMethod org/apache/jena/atlas/io/AWriter.print:(Ljava/lang/String;)V
      20: return

  public void formatLitString(org.apache.jena.atlas.io.AWriter, java.lang.String);
    Code:
       0: aload_0
       1: aload_1
       2: aload_2
       3: invokespecial #16                 // Method writeEscaped:(Lorg/apache/jena/atlas/io/AWriter;Ljava/lang/String;)V
       6: return

  private void writeEscaped(org.apache.jena.atlas.io.AWriter, java.lang.String);
    Code:
       0: aload_0
       1: getfield      #6                  // Field quotedStringProc:Lorg/apache/jena/riot/out/quoted/QuotedStringOutput;
       4: aload_1
       5: aload_2
       6: invokeinterface #17,  3           // InterfaceMethod org/apache/jena/riot/out/quoted/QuotedStringOutput.writeStr:(Lorg/apache/jena/atlas/io/AWriter;Ljava/lang/String;)V
      11: return

  public void formatLitLang(org.apache.jena.atlas.io.AWriter, java.lang.String, java.lang.String);
    Code:
       0: aload_0
       1: aload_1
       2: aload_2
       3: invokespecial #16                 // Method writeEscaped:(Lorg/apache/jena/atlas/io/AWriter;Ljava/lang/String;)V
       6: aload_1
       7: bipush        64
       9: invokeinterface #11,  2           // InterfaceMethod org/apache/jena/atlas/io/AWriter.print:(C)V
      14: aload_1
      15: aload_3
      16: invokeinterface #14,  2           // InterfaceMethod org/apache/jena/atlas/io/AWriter.print:(Ljava/lang/String;)V
      21: return

  public void formatLitDT(org.apache.jena.atlas.io.AWriter, java.lang.String, java.lang.String);
    Code:
       0: aload_0
       1: aload_1
       2: aload_2
       3: invokespecial #16                 // Method writeEscaped:(Lorg/apache/jena/atlas/io/AWriter;Ljava/lang/String;)V
       6: aload_1
       7: ldc           #18                 // String ^^
       9: invokeinterface #14,  2           // InterfaceMethod org/apache/jena/atlas/io/AWriter.print:(Ljava/lang/String;)V
      14: aload_0
      15: aload_1
      16: aload_3
      17: invokevirtual #19                 // Method formatURI:(Lorg/apache/jena/atlas/io/AWriter;Ljava/lang/String;)V
      20: return
}
