Compiled from "KCallablesJvm.kt"
public final class kotlin.reflect.jvm.KCallablesJvm {
  public static final boolean isAccessible(kotlin.reflect.KCallable<?>);
    Code:
       0: aload_0
       1: ldc           #7                  // String <this>
       3: invokestatic  #44                 // Method kotlin/jvm/internal/Intrinsics.checkNotNullParameter:(Ljava/lang/Object;Ljava/lang/String;)V
       6: aload_0
       7: astore_1
       8: aload_1
       9: instanceof    #20                 // class kotlin/reflect/KMutableProperty
      12: ifeq          89
      15: aload_0
      16: checkcast     #22                 // class kotlin/reflect/KProperty
      19: invokestatic  #46                 // Method kotlin/reflect/jvm/ReflectJvmMapping.getJavaField:(Lkotlin/reflect/KProperty;)Ljava/lang/reflect/Field;
      22: dup
      23: ifnull        32
      26: invokevirtual #40                 // Method java/lang/reflect/Field.isAccessible:()Z
      29: goto          34
      32: pop
      33: iconst_1
      34: ifeq          85
      37: aload_0
      38: checkcast     #22                 // class kotlin/reflect/KProperty
      41: invokestatic  #47                 // Method kotlin/reflect/jvm/ReflectJvmMapping.getJavaGetter:(Lkotlin/reflect/KProperty;)Ljava/lang/reflect/Method;
      44: dup
      45: ifnull        54
      48: invokevirtual #42                 // Method java/lang/reflect/Method.isAccessible:()Z
      51: goto          56
      54: pop
      55: iconst_1
      56: ifeq          85
      59: aload_0
      60: checkcast     #20                 // class kotlin/reflect/KMutableProperty
      63: invokestatic  #49                 // Method kotlin/reflect/jvm/ReflectJvmMapping.getJavaSetter:(Lkotlin/reflect/KMutableProperty;)Ljava/lang/reflect/Method;
      66: dup
      67: ifnull        76
      70: invokevirtual #42                 // Method java/lang/reflect/Method.isAccessible:()Z
      73: goto          78
      76: pop
      77: iconst_1
      78: ifeq          85
      81: iconst_1
      82: goto          435
      85: iconst_0
      86: goto          435
      89: aload_1
      90: instanceof    #22                 // class kotlin/reflect/KProperty
      93: ifeq          148
      96: aload_0
      97: checkcast     #22                 // class kotlin/reflect/KProperty
     100: invokestatic  #46                 // Method kotlin/reflect/jvm/ReflectJvmMapping.getJavaField:(Lkotlin/reflect/KProperty;)Ljava/lang/reflect/Field;
     103: dup
     104: ifnull        113
     107: invokevirtual #40                 // Method java/lang/reflect/Field.isAccessible:()Z
     110: goto          115
     113: pop
     114: iconst_1
     115: ifeq          144
     118: aload_0
     119: checkcast     #22                 // class kotlin/reflect/KProperty
     122: invokestatic  #47                 // Method kotlin/reflect/jvm/ReflectJvmMapping.getJavaGetter:(Lkotlin/reflect/KProperty;)Ljava/lang/reflect/Method;
     125: dup
     126: ifnull        135
     129: invokevirtual #42                 // Method java/lang/reflect/Method.isAccessible:()Z
     132: goto          137
     135: pop
     136: iconst_1
     137: ifeq          144
     140: iconst_1
     141: goto          435
     144: iconst_0
     145: goto          435
     148: aload_1
     149: instanceof    #23                 // class kotlin/reflect/KProperty$Getter
     152: ifeq          212
     155: aload_0
     156: checkcast     #23                 // class kotlin/reflect/KProperty$Getter
     159: invokeinterface #53,  1           // InterfaceMethod kotlin/reflect/KProperty$Getter.getProperty:()Lkotlin/reflect/KProperty;
     164: invokestatic  #46                 // Method kotlin/reflect/jvm/ReflectJvmMapping.getJavaField:(Lkotlin/reflect/KProperty;)Ljava/lang/reflect/Field;
     167: dup
     168: ifnull        177
     171: invokevirtual #40                 // Method java/lang/reflect/Field.isAccessible:()Z
     174: goto          179
     177: pop
     178: iconst_1
     179: ifeq          208
     182: aload_0
     183: checkcast     #19                 // class kotlin/reflect/KFunction
     186: invokestatic  #48                 // Method kotlin/reflect/jvm/ReflectJvmMapping.getJavaMethod:(Lkotlin/reflect/KFunction;)Ljava/lang/reflect/Method;
     189: dup
     190: ifnull        199
     193: invokevirtual #42                 // Method java/lang/reflect/Method.isAccessible:()Z
     196: goto          201
     199: pop
     200: iconst_1
     201: ifeq          208
     204: iconst_1
     205: goto          435
     208: iconst_0
     209: goto          435
     212: aload_1
     213: instanceof    #21                 // class kotlin/reflect/KMutableProperty$Setter
     216: ifeq          276
     219: aload_0
     220: checkcast     #21                 // class kotlin/reflect/KMutableProperty$Setter
     223: invokeinterface #52,  1           // InterfaceMethod kotlin/reflect/KMutableProperty$Setter.getProperty:()Lkotlin/reflect/KProperty;
     228: invokestatic  #46                 // Method kotlin/reflect/jvm/ReflectJvmMapping.getJavaField:(Lkotlin/reflect/KProperty;)Ljava/lang/reflect/Field;
     231: dup
     232: ifnull        241
     235: invokevirtual #40                 // Method java/lang/reflect/Field.isAccessible:()Z
     238: goto          243
     241: pop
     242: iconst_1
     243: ifeq          272
     246: aload_0
     247: checkcast     #19                 // class kotlin/reflect/KFunction
     250: invokestatic  #48                 // Method kotlin/reflect/jvm/ReflectJvmMapping.getJavaMethod:(Lkotlin/reflect/KFunction;)Ljava/lang/reflect/Method;
     253: dup
     254: ifnull        263
     257: invokevirtual #42                 // Method java/lang/reflect/Method.isAccessible:()Z
     260: goto          265
     263: pop
     264: iconst_1
     265: ifeq          272
     268: iconst_1
     269: goto          435
     272: iconst_0
     273: goto          435
     276: aload_1
     277: instanceof    #19                 // class kotlin/reflect/KFunction
     280: ifeq          391
     283: aload_0
     284: checkcast     #19                 // class kotlin/reflect/KFunction
     287: invokestatic  #48                 // Method kotlin/reflect/jvm/ReflectJvmMapping.getJavaMethod:(Lkotlin/reflect/KFunction;)Ljava/lang/reflect/Method;
     290: dup
     291: ifnull        300
     294: invokevirtual #42                 // Method java/lang/reflect/Method.isAccessible:()Z
     297: goto          302
     300: pop
     301: iconst_1
     302: ifeq          387
     305: aload_0
     306: invokestatic  #51                 // Method kotlin/reflect/jvm/internal/UtilKt.asKCallableImpl:(Ljava/lang/Object;)Lkotlin/reflect/jvm/internal/KCallableImpl;
     309: dup
     310: ifnull        328
     313: invokevirtual #50                 // Method kotlin/reflect/jvm/internal/KCallableImpl.getDefaultCaller:()Lkotlin/reflect/jvm/internal/calls/Caller;
     316: dup
     317: ifnull        328
     320: invokeinterface #54,  1           // InterfaceMethod kotlin/reflect/jvm/internal/calls/Caller.getMember:()Ljava/lang/reflect/Member;
     325: goto          330
     328: pop
     329: aconst_null
     330: astore_2
     331: aload_2
     332: instanceof    #12                 // class java/lang/reflect/AccessibleObject
     335: ifeq          345
     338: aload_2
     339: checkcast     #12                 // class java/lang/reflect/AccessibleObject
     342: goto          346
     345: aconst_null
     346: dup
     347: ifnull        356
     350: invokevirtual #36                 // Method java/lang/reflect/AccessibleObject.isAccessible:()Z
     353: goto          358
     356: pop
     357: iconst_1
     358: ifeq          387
     361: aload_0
     362: checkcast     #19                 // class kotlin/reflect/KFunction
     365: invokestatic  #45                 // Method kotlin/reflect/jvm/ReflectJvmMapping.getJavaConstructor:(Lkotlin/reflect/KFunction;)Ljava/lang/reflect/Constructor;
     368: dup
     369: ifnull        378
     372: invokevirtual #38                 // Method java/lang/reflect/Constructor.isAccessible:()Z
     375: goto          380
     378: pop
     379: iconst_1
     380: ifeq          387
     383: iconst_1
     384: goto          435
     387: iconst_0
     388: goto          435
     391: new           #11                 // class java/lang/UnsupportedOperationException
     394: dup
     395: new           #10                 // class java/lang/StringBuilder
     398: dup
     399: invokespecial #30                 // Method java/lang/StringBuilder."<init>":()V
     402: ldc           #8                  // String Unknown callable:
     404: invokevirtual #33                 // Method java/lang/StringBuilder.append:(Ljava/lang/String;)Ljava/lang/StringBuilder;
     407: aload_0
     408: invokevirtual #32                 // Method java/lang/StringBuilder.append:(Ljava/lang/Object;)Ljava/lang/StringBuilder;
     411: ldc           #6                  // String  (
     413: invokevirtual #33                 // Method java/lang/StringBuilder.append:(Ljava/lang/String;)Ljava/lang/StringBuilder;
     416: aload_0
     417: invokevirtual #29                 // Method java/lang/Object.getClass:()Ljava/lang/Class;
     420: invokevirtual #32                 // Method java/lang/StringBuilder.append:(Ljava/lang/Object;)Ljava/lang/StringBuilder;
     423: bipush        41
     425: invokevirtual #31                 // Method java/lang/StringBuilder.append:(C)Ljava/lang/StringBuilder;
     428: invokevirtual #34                 // Method java/lang/StringBuilder.toString:()Ljava/lang/String;
     431: invokespecial #35                 // Method java/lang/UnsupportedOperationException."<init>":(Ljava/lang/String;)V
     434: athrow
     435: ireturn

  public static final void setAccessible(kotlin.reflect.KCallable<?>, boolean);
    Code:
       0: aload_0
       1: ldc           #7                  // String <this>
       3: invokestatic  #44                 // Method kotlin/jvm/internal/Intrinsics.checkNotNullParameter:(Ljava/lang/Object;Ljava/lang/String;)V
       6: aload_0
       7: astore_2
       8: aload_2
       9: instanceof    #20                 // class kotlin/reflect/KMutableProperty
      12: ifeq          75
      15: aload_0
      16: checkcast     #22                 // class kotlin/reflect/KProperty
      19: invokestatic  #46                 // Method kotlin/reflect/jvm/ReflectJvmMapping.getJavaField:(Lkotlin/reflect/KProperty;)Ljava/lang/reflect/Field;
      22: dup
      23: ifnonnull     30
      26: pop
      27: goto          34
      30: iload_1
      31: invokevirtual #41                 // Method java/lang/reflect/Field.setAccessible:(Z)V
      34: aload_0
      35: checkcast     #22                 // class kotlin/reflect/KProperty
      38: invokestatic  #47                 // Method kotlin/reflect/jvm/ReflectJvmMapping.getJavaGetter:(Lkotlin/reflect/KProperty;)Ljava/lang/reflect/Method;
      41: dup
      42: ifnonnull     49
      45: pop
      46: goto          53
      49: iload_1
      50: invokevirtual #43                 // Method java/lang/reflect/Method.setAccessible:(Z)V
      53: aload_0
      54: checkcast     #20                 // class kotlin/reflect/KMutableProperty
      57: invokestatic  #49                 // Method kotlin/reflect/jvm/ReflectJvmMapping.getJavaSetter:(Lkotlin/reflect/KMutableProperty;)Ljava/lang/reflect/Method;
      60: dup
      61: ifnonnull     68
      64: pop
      65: goto          374
      68: iload_1
      69: invokevirtual #43                 // Method java/lang/reflect/Method.setAccessible:(Z)V
      72: goto          374
      75: aload_2
      76: instanceof    #22                 // class kotlin/reflect/KProperty
      79: ifeq          123
      82: aload_0
      83: checkcast     #22                 // class kotlin/reflect/KProperty
      86: invokestatic  #46                 // Method kotlin/reflect/jvm/ReflectJvmMapping.getJavaField:(Lkotlin/reflect/KProperty;)Ljava/lang/reflect/Field;
      89: dup
      90: ifnonnull     97
      93: pop
      94: goto          101
      97: iload_1
      98: invokevirtual #41                 // Method java/lang/reflect/Field.setAccessible:(Z)V
     101: aload_0
     102: checkcast     #22                 // class kotlin/reflect/KProperty
     105: invokestatic  #47                 // Method kotlin/reflect/jvm/ReflectJvmMapping.getJavaGetter:(Lkotlin/reflect/KProperty;)Ljava/lang/reflect/Method;
     108: dup
     109: ifnonnull     116
     112: pop
     113: goto          374
     116: iload_1
     117: invokevirtual #43                 // Method java/lang/reflect/Method.setAccessible:(Z)V
     120: goto          374
     123: aload_2
     124: instanceof    #23                 // class kotlin/reflect/KProperty$Getter
     127: ifeq          176
     130: aload_0
     131: checkcast     #23                 // class kotlin/reflect/KProperty$Getter
     134: invokeinterface #53,  1           // InterfaceMethod kotlin/reflect/KProperty$Getter.getProperty:()Lkotlin/reflect/KProperty;
     139: invokestatic  #46                 // Method kotlin/reflect/jvm/ReflectJvmMapping.getJavaField:(Lkotlin/reflect/KProperty;)Ljava/lang/reflect/Field;
     142: dup
     143: ifnonnull     150
     146: pop
     147: goto          154
     150: iload_1
     151: invokevirtual #41                 // Method java/lang/reflect/Field.setAccessible:(Z)V
     154: aload_0
     155: checkcast     #19                 // class kotlin/reflect/KFunction
     158: invokestatic  #48                 // Method kotlin/reflect/jvm/ReflectJvmMapping.getJavaMethod:(Lkotlin/reflect/KFunction;)Ljava/lang/reflect/Method;
     161: dup
     162: ifnonnull     169
     165: pop
     166: goto          374
     169: iload_1
     170: invokevirtual #43                 // Method java/lang/reflect/Method.setAccessible:(Z)V
     173: goto          374
     176: aload_2
     177: instanceof    #21                 // class kotlin/reflect/KMutableProperty$Setter
     180: ifeq          229
     183: aload_0
     184: checkcast     #21                 // class kotlin/reflect/KMutableProperty$Setter
     187: invokeinterface #52,  1           // InterfaceMethod kotlin/reflect/KMutableProperty$Setter.getProperty:()Lkotlin/reflect/KProperty;
     192: invokestatic  #46                 // Method kotlin/reflect/jvm/ReflectJvmMapping.getJavaField:(Lkotlin/reflect/KProperty;)Ljava/lang/reflect/Field;
     195: dup
     196: ifnonnull     203
     199: pop
     200: goto          207
     203: iload_1
     204: invokevirtual #41                 // Method java/lang/reflect/Field.setAccessible:(Z)V
     207: aload_0
     208: checkcast     #19                 // class kotlin/reflect/KFunction
     211: invokestatic  #48                 // Method kotlin/reflect/jvm/ReflectJvmMapping.getJavaMethod:(Lkotlin/reflect/KFunction;)Ljava/lang/reflect/Method;
     214: dup
     215: ifnonnull     222
     218: pop
     219: goto          374
     222: iload_1
     223: invokevirtual #43                 // Method java/lang/reflect/Method.setAccessible:(Z)V
     226: goto          374
     229: aload_2
     230: instanceof    #19                 // class kotlin/reflect/KFunction
     233: ifeq          330
     236: aload_0
     237: checkcast     #19                 // class kotlin/reflect/KFunction
     240: invokestatic  #48                 // Method kotlin/reflect/jvm/ReflectJvmMapping.getJavaMethod:(Lkotlin/reflect/KFunction;)Ljava/lang/reflect/Method;
     243: dup
     244: ifnonnull     251
     247: pop
     248: goto          255
     251: iload_1
     252: invokevirtual #43                 // Method java/lang/reflect/Method.setAccessible:(Z)V
     255: aload_0
     256: invokestatic  #51                 // Method kotlin/reflect/jvm/internal/UtilKt.asKCallableImpl:(Ljava/lang/Object;)Lkotlin/reflect/jvm/internal/KCallableImpl;
     259: dup
     260: ifnull        278
     263: invokevirtual #50                 // Method kotlin/reflect/jvm/internal/KCallableImpl.getDefaultCaller:()Lkotlin/reflect/jvm/internal/calls/Caller;
     266: dup
     267: ifnull        278
     270: invokeinterface #54,  1           // InterfaceMethod kotlin/reflect/jvm/internal/calls/Caller.getMember:()Ljava/lang/reflect/Member;
     275: goto          280
     278: pop
     279: aconst_null
     280: astore_3
     281: aload_3
     282: instanceof    #12                 // class java/lang/reflect/AccessibleObject
     285: ifeq          295
     288: aload_3
     289: checkcast     #12                 // class java/lang/reflect/AccessibleObject
     292: goto          296
     295: aconst_null
     296: dup
     297: ifnonnull     304
     300: pop
     301: goto          308
     304: iconst_1
     305: invokevirtual #37                 // Method java/lang/reflect/AccessibleObject.setAccessible:(Z)V
     308: aload_0
     309: checkcast     #19                 // class kotlin/reflect/KFunction
     312: invokestatic  #45                 // Method kotlin/reflect/jvm/ReflectJvmMapping.getJavaConstructor:(Lkotlin/reflect/KFunction;)Ljava/lang/reflect/Constructor;
     315: dup
     316: ifnonnull     323
     319: pop
     320: goto          374
     323: iload_1
     324: invokevirtual #39                 // Method java/lang/reflect/Constructor.setAccessible:(Z)V
     327: goto          374
     330: new           #11                 // class java/lang/UnsupportedOperationException
     333: dup
     334: new           #10                 // class java/lang/StringBuilder
     337: dup
     338: invokespecial #30                 // Method java/lang/StringBuilder."<init>":()V
     341: ldc           #8                  // String Unknown callable:
     343: invokevirtual #33                 // Method java/lang/StringBuilder.append:(Ljava/lang/String;)Ljava/lang/StringBuilder;
     346: aload_0
     347: invokevirtual #32                 // Method java/lang/StringBuilder.append:(Ljava/lang/Object;)Ljava/lang/StringBuilder;
     350: ldc           #6                  // String  (
     352: invokevirtual #33                 // Method java/lang/StringBuilder.append:(Ljava/lang/String;)Ljava/lang/StringBuilder;
     355: aload_0
     356: invokevirtual #29                 // Method java/lang/Object.getClass:()Ljava/lang/Class;
     359: invokevirtual #32                 // Method java/lang/StringBuilder.append:(Ljava/lang/Object;)Ljava/lang/StringBuilder;
     362: bipush        41
     364: invokevirtual #31                 // Method java/lang/StringBuilder.append:(C)Ljava/lang/StringBuilder;
     367: invokevirtual #34                 // Method java/lang/StringBuilder.toString:()Ljava/lang/String;
     370: invokespecial #35                 // Method java/lang/UnsupportedOperationException."<init>":(Ljava/lang/String;)V
     373: athrow
     374: return
}
