Compiled from "Flat3Map.java"
class org.apache.commons.collections4.map.Flat3Map$FlatMapEntry<K, V> implements java.util.Map$Entry<K, V> {
  private final org.apache.commons.collections4.map.Flat3Map<K, V> parent;

  private final int index;

  private volatile boolean removed;

  public org.apache.commons.collections4.map.Flat3Map$FlatMapEntry(org.apache.commons.collections4.map.Flat3Map<K, V>, int);
    Code:
       0: aload_0
       1: invokespecial #1                  // Method java/lang/Object."<init>":()V
       4: aload_0
       5: aload_1
       6: putfield      #2                  // Field parent:Lorg/apache/commons/collections4/map/Flat3Map;
       9: aload_0
      10: iload_2
      11: putfield      #3                  // Field index:I
      14: aload_0
      15: iconst_0
      16: putfield      #4                  // Field removed:Z
      19: return

  void setRemoved(boolean);
    Code:
       0: aload_0
       1: iload_1
       2: putfield      #4                  // Field removed:Z
       5: return

  public K getKey();
    Code:
       0: aload_0
       1: getfield      #4                  // Field removed:Z
       4: ifeq          17
       7: new           #5                  // class java/lang/IllegalStateException
      10: dup
      11: ldc           #7                  // String getKey() can only be called after next() and before remove()
      13: invokespecial #8                  // Method java/lang/IllegalStateException."<init>":(Ljava/lang/String;)V
      16: athrow
      17: aload_0
      18: getfield      #3                  // Field index:I
      21: tableswitch   { // 1 to 3
                     1: 64
                     2: 56
                     3: 48
               default: 72
          }
      48: aload_0
      49: getfield      #2                  // Field parent:Lorg/apache/commons/collections4/map/Flat3Map;
      52: invokestatic  #9                  // Method org/apache/commons/collections4/map/Flat3Map.access$100:(Lorg/apache/commons/collections4/map/Flat3Map;)Ljava/lang/Object;
      55: areturn
      56: aload_0
      57: getfield      #2                  // Field parent:Lorg/apache/commons/collections4/map/Flat3Map;
      60: invokestatic  #10                 // Method org/apache/commons/collections4/map/Flat3Map.access$200:(Lorg/apache/commons/collections4/map/Flat3Map;)Ljava/lang/Object;
      63: areturn
      64: aload_0
      65: getfield      #2                  // Field parent:Lorg/apache/commons/collections4/map/Flat3Map;
      68: invokestatic  #11                 // Method org/apache/commons/collections4/map/Flat3Map.access$300:(Lorg/apache/commons/collections4/map/Flat3Map;)Ljava/lang/Object;
      71: areturn
      72: new           #5                  // class java/lang/IllegalStateException
      75: dup
      76: new           #12                 // class java/lang/StringBuilder
      79: dup
      80: invokespecial #13                 // Method java/lang/StringBuilder."<init>":()V
      83: ldc           #14                 // String Invalid map index:
      85: invokevirtual #15                 // Method java/lang/StringBuilder.append:(Ljava/lang/String;)Ljava/lang/StringBuilder;
      88: aload_0
      89: getfield      #3                  // Field index:I
      92: invokevirtual #16                 // Method java/lang/StringBuilder.append:(I)Ljava/lang/StringBuilder;
      95: invokevirtual #17                 // Method java/lang/StringBuilder.toString:()Ljava/lang/String;
      98: invokespecial #8                  // Method java/lang/IllegalStateException."<init>":(Ljava/lang/String;)V
     101: athrow

  public V getValue();
    Code:
       0: aload_0
       1: getfield      #4                  // Field removed:Z
       4: ifeq          17
       7: new           #5                  // class java/lang/IllegalStateException
      10: dup
      11: ldc           #18                 // String getValue() can only be called after next() and before remove()
      13: invokespecial #8                  // Method java/lang/IllegalStateException."<init>":(Ljava/lang/String;)V
      16: athrow
      17: aload_0
      18: getfield      #3                  // Field index:I
      21: tableswitch   { // 1 to 3
                     1: 64
                     2: 56
                     3: 48
               default: 72
          }
      48: aload_0
      49: getfield      #2                  // Field parent:Lorg/apache/commons/collections4/map/Flat3Map;
      52: invokestatic  #19                 // Method org/apache/commons/collections4/map/Flat3Map.access$400:(Lorg/apache/commons/collections4/map/Flat3Map;)Ljava/lang/Object;
      55: areturn
      56: aload_0
      57: getfield      #2                  // Field parent:Lorg/apache/commons/collections4/map/Flat3Map;
      60: invokestatic  #20                 // Method org/apache/commons/collections4/map/Flat3Map.access$500:(Lorg/apache/commons/collections4/map/Flat3Map;)Ljava/lang/Object;
      63: areturn
      64: aload_0
      65: getfield      #2                  // Field parent:Lorg/apache/commons/collections4/map/Flat3Map;
      68: invokestatic  #21                 // Method org/apache/commons/collections4/map/Flat3Map.access$600:(Lorg/apache/commons/collections4/map/Flat3Map;)Ljava/lang/Object;
      71: areturn
      72: new           #5                  // class java/lang/IllegalStateException
      75: dup
      76: new           #12                 // class java/lang/StringBuilder
      79: dup
      80: invokespecial #13                 // Method java/lang/StringBuilder."<init>":()V
      83: ldc           #14                 // String Invalid map index:
      85: invokevirtual #15                 // Method java/lang/StringBuilder.append:(Ljava/lang/String;)Ljava/lang/StringBuilder;
      88: aload_0
      89: getfield      #3                  // Field index:I
      92: invokevirtual #16                 // Method java/lang/StringBuilder.append:(I)Ljava/lang/StringBuilder;
      95: invokevirtual #17                 // Method java/lang/StringBuilder.toString:()Ljava/lang/String;
      98: invokespecial #8                  // Method java/lang/IllegalStateException."<init>":(Ljava/lang/String;)V
     101: athrow

  public V setValue(V);
    Code:
       0: aload_0
       1: getfield      #4                  // Field removed:Z
       4: ifeq          17
       7: new           #5                  // class java/lang/IllegalStateException
      10: dup
      11: ldc           #22                 // String setValue() can only be called after next() and before remove()
      13: invokespecial #8                  // Method java/lang/IllegalStateException."<init>":(Ljava/lang/String;)V
      16: athrow
      17: aload_0
      18: invokevirtual #23                 // Method getValue:()Ljava/lang/Object;
      21: astore_2
      22: aload_0
      23: getfield      #3                  // Field index:I
      26: tableswitch   { // 1 to 3
                     1: 76
                     2: 64
                     3: 52
               default: 88
          }
      52: aload_0
      53: getfield      #2                  // Field parent:Lorg/apache/commons/collections4/map/Flat3Map;
      56: aload_1
      57: invokestatic  #24                 // Method org/apache/commons/collections4/map/Flat3Map.access$402:(Lorg/apache/commons/collections4/map/Flat3Map;Ljava/lang/Object;)Ljava/lang/Object;
      60: pop
      61: goto          118
      64: aload_0
      65: getfield      #2                  // Field parent:Lorg/apache/commons/collections4/map/Flat3Map;
      68: aload_1
      69: invokestatic  #25                 // Method org/apache/commons/collections4/map/Flat3Map.access$502:(Lorg/apache/commons/collections4/map/Flat3Map;Ljava/lang/Object;)Ljava/lang/Object;
      72: pop
      73: goto          118
      76: aload_0
      77: getfield      #2                  // Field parent:Lorg/apache/commons/collections4/map/Flat3Map;
      80: aload_1
      81: invokestatic  #26                 // Method org/apache/commons/collections4/map/Flat3Map.access$602:(Lorg/apache/commons/collections4/map/Flat3Map;Ljava/lang/Object;)Ljava/lang/Object;
      84: pop
      85: goto          118
      88: new           #5                  // class java/lang/IllegalStateException
      91: dup
      92: new           #12                 // class java/lang/StringBuilder
      95: dup
      96: invokespecial #13                 // Method java/lang/StringBuilder."<init>":()V
      99: ldc           #14                 // String Invalid map index:
     101: invokevirtual #15                 // Method java/lang/StringBuilder.append:(Ljava/lang/String;)Ljava/lang/StringBuilder;
     104: aload_0
     105: getfield      #3                  // Field index:I
     108: invokevirtual #16                 // Method java/lang/StringBuilder.append:(I)Ljava/lang/StringBuilder;
     111: invokevirtual #17                 // Method java/lang/StringBuilder.toString:()Ljava/lang/String;
     114: invokespecial #8                  // Method java/lang/IllegalStateException."<init>":(Ljava/lang/String;)V
     117: athrow
     118: aload_2
     119: areturn

  public boolean equals(java.lang.Object);
    Code:
       0: aload_0
       1: getfield      #4                  // Field removed:Z
       4: ifeq          9
       7: iconst_0
       8: ireturn
       9: aload_1
      10: instanceof    #27                 // class java/util/Map$Entry
      13: ifne          18
      16: iconst_0
      17: ireturn
      18: aload_1
      19: checkcast     #27                 // class java/util/Map$Entry
      22: astore_2
      23: aload_0
      24: invokevirtual #28                 // Method getKey:()Ljava/lang/Object;
      27: astore_3
      28: aload_0
      29: invokevirtual #23                 // Method getValue:()Ljava/lang/Object;
      32: astore        4
      34: aload_3
      35: ifnonnull     50
      38: aload_2
      39: invokeinterface #29,  1           // InterfaceMethod java/util/Map$Entry.getKey:()Ljava/lang/Object;
      44: ifnonnull     98
      47: goto          63
      50: aload_3
      51: aload_2
      52: invokeinterface #29,  1           // InterfaceMethod java/util/Map$Entry.getKey:()Ljava/lang/Object;
      57: invokevirtual #30                 // Method java/lang/Object.equals:(Ljava/lang/Object;)Z
      60: ifeq          98
      63: aload         4
      65: ifnonnull     80
      68: aload_2
      69: invokeinterface #31,  1           // InterfaceMethod java/util/Map$Entry.getValue:()Ljava/lang/Object;
      74: ifnonnull     98
      77: goto          94
      80: aload         4
      82: aload_2
      83: invokeinterface #31,  1           // InterfaceMethod java/util/Map$Entry.getValue:()Ljava/lang/Object;
      88: invokevirtual #30                 // Method java/lang/Object.equals:(Ljava/lang/Object;)Z
      91: ifeq          98
      94: iconst_1
      95: goto          99
      98: iconst_0
      99: ireturn

  public int hashCode();
    Code:
       0: aload_0
       1: getfield      #4                  // Field removed:Z
       4: ifeq          9
       7: iconst_0
       8: ireturn
       9: aload_0
      10: invokevirtual #28                 // Method getKey:()Ljava/lang/Object;
      13: astore_1
      14: aload_0
      15: invokevirtual #23                 // Method getValue:()Ljava/lang/Object;
      18: astore_2
      19: aload_1
      20: ifnonnull     27
      23: iconst_0
      24: goto          31
      27: aload_1
      28: invokevirtual #32                 // Method java/lang/Object.hashCode:()I
      31: aload_2
      32: ifnonnull     39
      35: iconst_0
      36: goto          43
      39: aload_2
      40: invokevirtual #32                 // Method java/lang/Object.hashCode:()I
      43: ixor
      44: ireturn

  public java.lang.String toString();
    Code:
       0: aload_0
       1: getfield      #4                  // Field removed:Z
       4: ifne          37
       7: new           #12                 // class java/lang/StringBuilder
      10: dup
      11: invokespecial #13                 // Method java/lang/StringBuilder."<init>":()V
      14: aload_0
      15: invokevirtual #28                 // Method getKey:()Ljava/lang/Object;
      18: invokevirtual #33                 // Method java/lang/StringBuilder.append:(Ljava/lang/Object;)Ljava/lang/StringBuilder;
      21: ldc           #34                 // String =
      23: invokevirtual #15                 // Method java/lang/StringBuilder.append:(Ljava/lang/String;)Ljava/lang/StringBuilder;
      26: aload_0
      27: invokevirtual #23                 // Method getValue:()Ljava/lang/Object;
      30: invokevirtual #33                 // Method java/lang/StringBuilder.append:(Ljava/lang/Object;)Ljava/lang/StringBuilder;
      33: invokevirtual #17                 // Method java/lang/StringBuilder.toString:()Ljava/lang/String;
      36: areturn
      37: ldc           #35                 // String
      39: areturn
}
