Compiled from "UIInfo.java"
public interface org.opensaml.samlext.saml2mdui.UIInfo extends org.opensaml.common.SAMLObject {
  public static final java.lang.String MDUI_NS;

  public static final java.lang.String MDUI_PREFIX;

  public static final java.lang.String DEFAULT_ELEMENT_LOCAL_NAME;

  public static final javax.xml.namespace.QName DEFAULT_ELEMENT_NAME;

  public static final java.lang.String TYPE_LOCAL_NAME;

  public static final javax.xml.namespace.QName TYPE_NAME;

  public static final java.lang.String LANG_ATTRIB_NAME;

  public abstract java.util.List<org.opensaml.samlext.saml2mdui.DisplayName> getDisplayNames();

  public abstract java.util.List<org.opensaml.samlext.saml2mdui.Keywords> getKeywords();

  public abstract java.util.List<org.opensaml.samlext.saml2mdui.Description> getDescriptions();

  public abstract java.util.List<org.opensaml.samlext.saml2mdui.Logo> getLogos();

  public abstract java.util.List<org.opensaml.samlext.saml2mdui.InformationURL> getInformationURLs();

  public abstract java.util.List<org.opensaml.samlext.saml2mdui.PrivacyStatementURL> getPrivacyStatementURLs();

  static {};
    Code:
       0: new           #1                  // class javax/xml/namespace/QName
       3: dup
       4: ldc           #2                  // String urn:oasis:names:tc:SAML:metadata:ui
       6: ldc           #3                  // String UIInfo
       8: ldc           #4                  // String mdui
      10: invokespecial #5                  // Method javax/xml/namespace/QName."<init>":(Ljava/lang/String;Ljava/lang/String;Ljava/lang/String;)V
      13: putstatic     #6                  // Field DEFAULT_ELEMENT_NAME:Ljavax/xml/namespace/QName;
      16: new           #1                  // class javax/xml/namespace/QName
      19: dup
      20: ldc           #2                  // String urn:oasis:names:tc:SAML:metadata:ui
      22: ldc           #7                  // String UIInfoType
      24: ldc           #4                  // String mdui
      26: invokespecial #5                  // Method javax/xml/namespace/QName."<init>":(Ljava/lang/String;Ljava/lang/String;Ljava/lang/String;)V
      29: putstatic     #8                  // Field TYPE_NAME:Ljavax/xml/namespace/QName;
      32: return
}
