Compiled from "AbstractDashboardWidget.java"
public abstract class org.sonar.api.web.AbstractDashboardWidget extends org.sonar.api.web.AbstractRubyTemplate implements org.sonar.api.web.RubyRailsWidget {
  public org.sonar.api.web.AbstractDashboardWidget();
    Code:
       0: aload_0
       1: invokespecial #12                 // Method org/sonar/api/web/AbstractRubyTemplate."<init>":()V
       4: return

  public java.lang.String getId();
    Code:
       0: aload_0
       1: invokevirtual #22                 // Method java/lang/Object.getClass:()Ljava/lang/Class;
       4: invokevirtual #27                 // Method java/lang/Class.getSimpleName:()Ljava/lang/String;
       7: areturn

  public java.lang.String getTitle();
    Code:
       0: aload_0
       1: invokevirtual #22                 // Method java/lang/Object.getClass:()Ljava/lang/Class;
       4: invokevirtual #27                 // Method java/lang/Class.getSimpleName:()Ljava/lang/String;
       7: areturn
}
