Compiled from "FaultTranslatingClientResponseFilter.java"
public class org.smallmind.web.jersey.json.FaultTranslatingClientResponseFilter implements javax.ws.rs.client.ClientResponseFilter {
  private int lowerBound;

  private int upperBound;

  public org.smallmind.web.jersey.json.FaultTranslatingClientResponseFilter();
    Code:
       0: aload_0
       1: sipush        400
       4: sipush        600
       7: invokespecial #14                 // Method "<init>":(II)V
      10: return

  public org.smallmind.web.jersey.json.FaultTranslatingClientResponseFilter(int, int);
    Code:
       0: aload_0
       1: invokespecial #21                 // Method java/lang/Object."<init>":()V
       4: aload_0
       5: iload_1
       6: putfield      #23                 // Field lowerBound:I
       9: aload_0
      10: iload_2
      11: putfield      #25                 // Field upperBound:I
      14: return

  public void filter(javax.ws.rs.client.ClientRequestContext, javax.ws.rs.client.ClientResponseContext) throws java.io.IOException;
    Code:
       0: aload_2
       1: invokeinterface #32,  1           // InterfaceMethod javax/ws/rs/client/ClientResponseContext.getStatus:()I
       6: aload_0
       7: getfield      #23                 // Field lowerBound:I
      10: if_icmplt     244
      13: aload_2
      14: invokeinterface #32,  1           // InterfaceMethod javax/ws/rs/client/ClientResponseContext.getStatus:()I
      19: aload_0
      20: getfield      #25                 // Field upperBound:I
      23: if_icmpge     244
      26: getstatic     #38                 // Field javax/ws/rs/core/MediaType.APPLICATION_JSON_TYPE:Ljavax/ws/rs/core/MediaType;
      29: aload_2
      30: invokeinterface #44,  1           // InterfaceMethod javax/ws/rs/client/ClientResponseContext.getMediaType:()Ljavax/ws/rs/core/MediaType;
      35: invokevirtual #48                 // Method javax/ws/rs/core/MediaType.equals:(Ljava/lang/Object;)Z
      38: ifeq          244
      41: aload_2
      42: invokeinterface #52,  1           // InterfaceMethod javax/ws/rs/client/ClientResponseContext.hasEntity:()Z
      47: ifeq          244
      50: aload_2
      51: invokeinterface #56,  1           // InterfaceMethod javax/ws/rs/client/ClientResponseContext.getEntityStream:()Ljava/io/InputStream;
      56: ldc           #60                 // class org/smallmind/web/json/scaffold/fault/Fault
      58: invokestatic  #62                 // Method org/smallmind/web/json/scaffold/util/JsonCodec.read:(Ljava/io/InputStream;Ljava/lang/Class;)Ljava/lang/Object;
      61: checkcast     #60                 // class org/smallmind/web/json/scaffold/fault/Fault
      64: dup
      65: astore_3
      66: invokevirtual #68                 // Method org/smallmind/web/json/scaffold/fault/Fault.getNativeObject:()Lorg/smallmind/web/json/scaffold/fault/NativeObject;
      69: dup
      70: astore        4
      72: ifnull        235
      75: aload         4
      77: invokevirtual #72                 // Method org/smallmind/web/json/scaffold/fault/NativeObject.getLanguage:()Lorg/smallmind/web/json/scaffold/fault/NativeLanguage;
      80: getstatic     #78                 // Field org/smallmind/web/json/scaffold/fault/NativeLanguage.JAVA:Lorg/smallmind/web/json/scaffold/fault/NativeLanguage;
      83: invokevirtual #84                 // Method org/smallmind/web/json/scaffold/fault/NativeLanguage.equals:(Ljava/lang/Object;)Z
      86: ifeq          235
      89: aconst_null
      90: astore        5
      92: aconst_null
      93: astore        6
      95: new           #85                 // class java/io/ByteArrayInputStream
      98: dup
      99: aload         4
     101: invokevirtual #87                 // Method org/smallmind/web/json/scaffold/fault/NativeObject.getBytes:()[B
     104: invokespecial #91                 // Method java/io/ByteArrayInputStream."<init>":([B)V
     107: astore        7
     109: new           #94                 // class java/io/ObjectInputStream
     112: dup
     113: aload         7
     115: invokespecial #96                 // Method java/io/ObjectInputStream."<init>":(Ljava/io/InputStream;)V
     118: astore        8
     120: new           #99                 // class org/smallmind/web/json/scaffold/fault/ResourceInvocationException
     123: dup
     124: aload         8
     126: invokevirtual #101                // Method java/io/ObjectInputStream.readObject:()Ljava/lang/Object;
     129: checkcast     #105                // class java/lang/Throwable
     132: invokespecial #107                // Method org/smallmind/web/json/scaffold/fault/ResourceInvocationException."<init>":(Ljava/lang/Throwable;)V
     135: athrow
     136: astore        9
     138: new           #110                // class org/smallmind/web/json/scaffold/fault/ObjectInstantiationException
     141: dup
     142: aload         9
     144: invokespecial #112                // Method org/smallmind/web/json/scaffold/fault/ObjectInstantiationException."<init>":(Ljava/lang/ClassNotFoundException;)V
     147: athrow
     148: astore        5
     150: aload         8
     152: ifnull        160
     155: aload         8
     157: invokevirtual #115                // Method java/io/ObjectInputStream.close:()V
     160: aload         5
     162: athrow
     163: astore        6
     165: aload         5
     167: ifnonnull     177
     170: aload         6
     172: astore        5
     174: goto          191
     177: aload         5
     179: aload         6
     181: if_acmpeq     191
     184: aload         5
     186: aload         6
     188: invokevirtual #118                // Method java/lang/Throwable.addSuppressed:(Ljava/lang/Throwable;)V
     191: aload         7
     193: ifnull        201
     196: aload         7
     198: invokevirtual #121                // Method java/io/ByteArrayInputStream.close:()V
     201: aload         5
     203: athrow
     204: astore        6
     206: aload         5
     208: ifnonnull     218
     211: aload         6
     213: astore        5
     215: goto          232
     218: aload         5
     220: aload         6
     222: if_acmpeq     232
     225: aload         5
     227: aload         6
     229: invokevirtual #118                // Method java/lang/Throwable.addSuppressed:(Ljava/lang/Throwable;)V
     232: aload         5
     234: athrow
     235: new           #122                // class org/smallmind/web/json/scaffold/fault/FaultWrappingException
     238: dup
     239: aload_3
     240: invokespecial #124                // Method org/smallmind/web/json/scaffold/fault/FaultWrappingException."<init>":(Lorg/smallmind/web/json/scaffold/fault/Fault;)V
     243: athrow
     244: return
    Exception table:
       from    to  target type
         120   136   136   Class java/lang/ClassNotFoundException
         120   148   148   any
         109   163   163   any
          95   204   204   any
}
