Compiled from "ChannelInboundHandlerAdapter.java"
public class io.netty.channel.ChannelInboundHandlerAdapter extends io.netty.channel.ChannelHandlerAdapter implements io.netty.channel.ChannelInboundHandler {
  public io.netty.channel.ChannelInboundHandlerAdapter();
    Code:
       0: aload_0
       1: invokespecial #1                  // Method io/netty/channel/ChannelHandlerAdapter."<init>":()V
       4: return

  public void channelRegistered(io.netty.channel.ChannelHandlerContext) throws java.lang.Exception;
    Code:
       0: aload_1
       1: invokeinterface #2,  1            // InterfaceMethod io/netty/channel/ChannelHandlerContext.fireChannelRegistered:()Lio/netty/channel/ChannelHandlerContext;
       6: pop
       7: return

  public void channelUnregistered(io.netty.channel.ChannelHandlerContext) throws java.lang.Exception;
    Code:
       0: aload_1
       1: invokeinterface #3,  1            // InterfaceMethod io/netty/channel/ChannelHandlerContext.fireChannelUnregistered:()Lio/netty/channel/ChannelHandlerContext;
       6: pop
       7: return

  public void channelActive(io.netty.channel.ChannelHandlerContext) throws java.lang.Exception;
    Code:
       0: aload_1
       1: invokeinterface #4,  1            // InterfaceMethod io/netty/channel/ChannelHandlerContext.fireChannelActive:()Lio/netty/channel/ChannelHandlerContext;
       6: pop
       7: return

  public void channelInactive(io.netty.channel.ChannelHandlerContext) throws java.lang.Exception;
    Code:
       0: aload_1
       1: invokeinterface #5,  1            // InterfaceMethod io/netty/channel/ChannelHandlerContext.fireChannelInactive:()Lio/netty/channel/ChannelHandlerContext;
       6: pop
       7: return

  public void channelRead(io.netty.channel.ChannelHandlerContext, java.lang.Object) throws java.lang.Exception;
    Code:
       0: aload_1
       1: aload_2
       2: invokeinterface #6,  2            // InterfaceMethod io/netty/channel/ChannelHandlerContext.fireChannelRead:(Ljava/lang/Object;)Lio/netty/channel/ChannelHandlerContext;
       7: pop
       8: return

  public void channelReadComplete(io.netty.channel.ChannelHandlerContext) throws java.lang.Exception;
    Code:
       0: aload_1
       1: invokeinterface #7,  1            // InterfaceMethod io/netty/channel/ChannelHandlerContext.fireChannelReadComplete:()Lio/netty/channel/ChannelHandlerContext;
       6: pop
       7: return

  public void userEventTriggered(io.netty.channel.ChannelHandlerContext, java.lang.Object) throws java.lang.Exception;
    Code:
       0: aload_1
       1: aload_2
       2: invokeinterface #8,  2            // InterfaceMethod io/netty/channel/ChannelHandlerContext.fireUserEventTriggered:(Ljava/lang/Object;)Lio/netty/channel/ChannelHandlerContext;
       7: pop
       8: return

  public void channelWritabilityChanged(io.netty.channel.ChannelHandlerContext) throws java.lang.Exception;
    Code:
       0: aload_1
       1: invokeinterface #9,  1            // InterfaceMethod io/netty/channel/ChannelHandlerContext.fireChannelWritabilityChanged:()Lio/netty/channel/ChannelHandlerContext;
       6: pop
       7: return

  public void exceptionCaught(io.netty.channel.ChannelHandlerContext, java.lang.Throwable) throws java.lang.Exception;
    Code:
       0: aload_1
       1: aload_2
       2: invokeinterface #10,  2           // InterfaceMethod io/netty/channel/ChannelHandlerContext.fireExceptionCaught:(Ljava/lang/Throwable;)Lio/netty/channel/ChannelHandlerContext;
       7: pop
       8: return
}
