Compiled from "InstanceGroupDetailJsonMarshaller.java"
public class com.amazonaws.services.elasticmapreduce.model.transform.InstanceGroupDetailJsonMarshaller {
  private static com.amazonaws.services.elasticmapreduce.model.transform.InstanceGroupDetailJsonMarshaller instance;

  public com.amazonaws.services.elasticmapreduce.model.transform.InstanceGroupDetailJsonMarshaller();
    Code:
       0: aload_0
       1: invokespecial #1                  // Method java/lang/Object."<init>":()V
       4: return

  public void marshall(com.amazonaws.services.elasticmapreduce.model.InstanceGroupDetail, com.amazonaws.protocol.json.StructuredJsonGenerator);
    Code:
       0: aload_1
       1: ifnonnull     14
       4: new           #2                  // class com/amazonaws/AmazonClientException
       7: dup
       8: ldc           #3                  // String Invalid argument passed to marshall(...)
      10: invokespecial #4                  // Method com/amazonaws/AmazonClientException."<init>":(Ljava/lang/String;)V
      13: athrow
      14: aload_2
      15: invokeinterface #5,  1            // InterfaceMethod com/amazonaws/protocol/json/StructuredJsonGenerator.writeStartObject:()Lcom/amazonaws/protocol/json/StructuredJsonGenerator;
      20: pop
      21: aload_1
      22: invokevirtual #6                  // Method com/amazonaws/services/elasticmapreduce/model/InstanceGroupDetail.getInstanceGroupId:()Ljava/lang/String;
      25: ifnull        46
      28: aload_2
      29: ldc           #7                  // String InstanceGroupId
      31: invokeinterface #8,  2            // InterfaceMethod com/amazonaws/protocol/json/StructuredJsonGenerator.writeFieldName:(Ljava/lang/String;)Lcom/amazonaws/protocol/json/StructuredJsonGenerator;
      36: aload_1
      37: invokevirtual #6                  // Method com/amazonaws/services/elasticmapreduce/model/InstanceGroupDetail.getInstanceGroupId:()Ljava/lang/String;
      40: invokeinterface #9,  2            // InterfaceMethod com/amazonaws/protocol/json/StructuredJsonGenerator.writeValue:(Ljava/lang/String;)Lcom/amazonaws/protocol/json/StructuredJsonGenerator;
      45: pop
      46: aload_1
      47: invokevirtual #10                 // Method com/amazonaws/services/elasticmapreduce/model/InstanceGroupDetail.getName:()Ljava/lang/String;
      50: ifnull        71
      53: aload_2
      54: ldc           #11                 // String Name
      56: invokeinterface #8,  2            // InterfaceMethod com/amazonaws/protocol/json/StructuredJsonGenerator.writeFieldName:(Ljava/lang/String;)Lcom/amazonaws/protocol/json/StructuredJsonGenerator;
      61: aload_1
      62: invokevirtual #10                 // Method com/amazonaws/services/elasticmapreduce/model/InstanceGroupDetail.getName:()Ljava/lang/String;
      65: invokeinterface #9,  2            // InterfaceMethod com/amazonaws/protocol/json/StructuredJsonGenerator.writeValue:(Ljava/lang/String;)Lcom/amazonaws/protocol/json/StructuredJsonGenerator;
      70: pop
      71: aload_1
      72: invokevirtual #12                 // Method com/amazonaws/services/elasticmapreduce/model/InstanceGroupDetail.getMarket:()Ljava/lang/String;
      75: ifnull        96
      78: aload_2
      79: ldc           #13                 // String Market
      81: invokeinterface #8,  2            // InterfaceMethod com/amazonaws/protocol/json/StructuredJsonGenerator.writeFieldName:(Ljava/lang/String;)Lcom/amazonaws/protocol/json/StructuredJsonGenerator;
      86: aload_1
      87: invokevirtual #12                 // Method com/amazonaws/services/elasticmapreduce/model/InstanceGroupDetail.getMarket:()Ljava/lang/String;
      90: invokeinterface #9,  2            // InterfaceMethod com/amazonaws/protocol/json/StructuredJsonGenerator.writeValue:(Ljava/lang/String;)Lcom/amazonaws/protocol/json/StructuredJsonGenerator;
      95: pop
      96: aload_1
      97: invokevirtual #14                 // Method com/amazonaws/services/elasticmapreduce/model/InstanceGroupDetail.getInstanceRole:()Ljava/lang/String;
     100: ifnull        121
     103: aload_2
     104: ldc           #15                 // String InstanceRole
     106: invokeinterface #8,  2            // InterfaceMethod com/amazonaws/protocol/json/StructuredJsonGenerator.writeFieldName:(Ljava/lang/String;)Lcom/amazonaws/protocol/json/StructuredJsonGenerator;
     111: aload_1
     112: invokevirtual #14                 // Method com/amazonaws/services/elasticmapreduce/model/InstanceGroupDetail.getInstanceRole:()Ljava/lang/String;
     115: invokeinterface #9,  2            // InterfaceMethod com/amazonaws/protocol/json/StructuredJsonGenerator.writeValue:(Ljava/lang/String;)Lcom/amazonaws/protocol/json/StructuredJsonGenerator;
     120: pop
     121: aload_1
     122: invokevirtual #16                 // Method com/amazonaws/services/elasticmapreduce/model/InstanceGroupDetail.getBidPrice:()Ljava/lang/String;
     125: ifnull        146
     128: aload_2
     129: ldc           #17                 // String BidPrice
     131: invokeinterface #8,  2            // InterfaceMethod com/amazonaws/protocol/json/StructuredJsonGenerator.writeFieldName:(Ljava/lang/String;)Lcom/amazonaws/protocol/json/StructuredJsonGenerator;
     136: aload_1
     137: invokevirtual #16                 // Method com/amazonaws/services/elasticmapreduce/model/InstanceGroupDetail.getBidPrice:()Ljava/lang/String;
     140: invokeinterface #9,  2            // InterfaceMethod com/amazonaws/protocol/json/StructuredJsonGenerator.writeValue:(Ljava/lang/String;)Lcom/amazonaws/protocol/json/StructuredJsonGenerator;
     145: pop
     146: aload_1
     147: invokevirtual #18                 // Method com/amazonaws/services/elasticmapreduce/model/InstanceGroupDetail.getInstanceType:()Ljava/lang/String;
     150: ifnull        171
     153: aload_2
     154: ldc           #19                 // String InstanceType
     156: invokeinterface #8,  2            // InterfaceMethod com/amazonaws/protocol/json/StructuredJsonGenerator.writeFieldName:(Ljava/lang/String;)Lcom/amazonaws/protocol/json/StructuredJsonGenerator;
     161: aload_1
     162: invokevirtual #18                 // Method com/amazonaws/services/elasticmapreduce/model/InstanceGroupDetail.getInstanceType:()Ljava/lang/String;
     165: invokeinterface #9,  2            // InterfaceMethod com/amazonaws/protocol/json/StructuredJsonGenerator.writeValue:(Ljava/lang/String;)Lcom/amazonaws/protocol/json/StructuredJsonGenerator;
     170: pop
     171: aload_1
     172: invokevirtual #20                 // Method com/amazonaws/services/elasticmapreduce/model/InstanceGroupDetail.getInstanceRequestCount:()Ljava/lang/Integer;
     175: ifnull        199
     178: aload_2
     179: ldc           #21                 // String InstanceRequestCount
     181: invokeinterface #8,  2            // InterfaceMethod com/amazonaws/protocol/json/StructuredJsonGenerator.writeFieldName:(Ljava/lang/String;)Lcom/amazonaws/protocol/json/StructuredJsonGenerator;
     186: aload_1
     187: invokevirtual #20                 // Method com/amazonaws/services/elasticmapreduce/model/InstanceGroupDetail.getInstanceRequestCount:()Ljava/lang/Integer;
     190: invokevirtual #22                 // Method java/lang/Integer.intValue:()I
     193: invokeinterface #23,  2           // InterfaceMethod com/amazonaws/protocol/json/StructuredJsonGenerator.writeValue:(I)Lcom/amazonaws/protocol/json/StructuredJsonGenerator;
     198: pop
     199: aload_1
     200: invokevirtual #24                 // Method com/amazonaws/services/elasticmapreduce/model/InstanceGroupDetail.getInstanceRunningCount:()Ljava/lang/Integer;
     203: ifnull        227
     206: aload_2
     207: ldc           #25                 // String InstanceRunningCount
     209: invokeinterface #8,  2            // InterfaceMethod com/amazonaws/protocol/json/StructuredJsonGenerator.writeFieldName:(Ljava/lang/String;)Lcom/amazonaws/protocol/json/StructuredJsonGenerator;
     214: aload_1
     215: invokevirtual #24                 // Method com/amazonaws/services/elasticmapreduce/model/InstanceGroupDetail.getInstanceRunningCount:()Ljava/lang/Integer;
     218: invokevirtual #22                 // Method java/lang/Integer.intValue:()I
     221: invokeinterface #23,  2           // InterfaceMethod com/amazonaws/protocol/json/StructuredJsonGenerator.writeValue:(I)Lcom/amazonaws/protocol/json/StructuredJsonGenerator;
     226: pop
     227: aload_1
     228: invokevirtual #26                 // Method com/amazonaws/services/elasticmapreduce/model/InstanceGroupDetail.getState:()Ljava/lang/String;
     231: ifnull        252
     234: aload_2
     235: ldc           #27                 // String State
     237: invokeinterface #8,  2            // InterfaceMethod com/amazonaws/protocol/json/StructuredJsonGenerator.writeFieldName:(Ljava/lang/String;)Lcom/amazonaws/protocol/json/StructuredJsonGenerator;
     242: aload_1
     243: invokevirtual #26                 // Method com/amazonaws/services/elasticmapreduce/model/InstanceGroupDetail.getState:()Ljava/lang/String;
     246: invokeinterface #9,  2            // InterfaceMethod com/amazonaws/protocol/json/StructuredJsonGenerator.writeValue:(Ljava/lang/String;)Lcom/amazonaws/protocol/json/StructuredJsonGenerator;
     251: pop
     252: aload_1
     253: invokevirtual #28                 // Method com/amazonaws/services/elasticmapreduce/model/InstanceGroupDetail.getLastStateChangeReason:()Ljava/lang/String;
     256: ifnull        277
     259: aload_2
     260: ldc           #29                 // String LastStateChangeReason
     262: invokeinterface #8,  2            // InterfaceMethod com/amazonaws/protocol/json/StructuredJsonGenerator.writeFieldName:(Ljava/lang/String;)Lcom/amazonaws/protocol/json/StructuredJsonGenerator;
     267: aload_1
     268: invokevirtual #28                 // Method com/amazonaws/services/elasticmapreduce/model/InstanceGroupDetail.getLastStateChangeReason:()Ljava/lang/String;
     271: invokeinterface #9,  2            // InterfaceMethod com/amazonaws/protocol/json/StructuredJsonGenerator.writeValue:(Ljava/lang/String;)Lcom/amazonaws/protocol/json/StructuredJsonGenerator;
     276: pop
     277: aload_1
     278: invokevirtual #30                 // Method com/amazonaws/services/elasticmapreduce/model/InstanceGroupDetail.getCreationDateTime:()Ljava/util/Date;
     281: ifnull        302
     284: aload_2
     285: ldc           #31                 // String CreationDateTime
     287: invokeinterface #8,  2            // InterfaceMethod com/amazonaws/protocol/json/StructuredJsonGenerator.writeFieldName:(Ljava/lang/String;)Lcom/amazonaws/protocol/json/StructuredJsonGenerator;
     292: aload_1
     293: invokevirtual #30                 // Method com/amazonaws/services/elasticmapreduce/model/InstanceGroupDetail.getCreationDateTime:()Ljava/util/Date;
     296: invokeinterface #32,  2           // InterfaceMethod com/amazonaws/protocol/json/StructuredJsonGenerator.writeValue:(Ljava/util/Date;)Lcom/amazonaws/protocol/json/StructuredJsonGenerator;
     301: pop
     302: aload_1
     303: invokevirtual #33                 // Method com/amazonaws/services/elasticmapreduce/model/InstanceGroupDetail.getStartDateTime:()Ljava/util/Date;
     306: ifnull        327
     309: aload_2
     310: ldc           #34                 // String StartDateTime
     312: invokeinterface #8,  2            // InterfaceMethod com/amazonaws/protocol/json/StructuredJsonGenerator.writeFieldName:(Ljava/lang/String;)Lcom/amazonaws/protocol/json/StructuredJsonGenerator;
     317: aload_1
     318: invokevirtual #33                 // Method com/amazonaws/services/elasticmapreduce/model/InstanceGroupDetail.getStartDateTime:()Ljava/util/Date;
     321: invokeinterface #32,  2           // InterfaceMethod com/amazonaws/protocol/json/StructuredJsonGenerator.writeValue:(Ljava/util/Date;)Lcom/amazonaws/protocol/json/StructuredJsonGenerator;
     326: pop
     327: aload_1
     328: invokevirtual #35                 // Method com/amazonaws/services/elasticmapreduce/model/InstanceGroupDetail.getReadyDateTime:()Ljava/util/Date;
     331: ifnull        352
     334: aload_2
     335: ldc           #36                 // String ReadyDateTime
     337: invokeinterface #8,  2            // InterfaceMethod com/amazonaws/protocol/json/StructuredJsonGenerator.writeFieldName:(Ljava/lang/String;)Lcom/amazonaws/protocol/json/StructuredJsonGenerator;
     342: aload_1
     343: invokevirtual #35                 // Method com/amazonaws/services/elasticmapreduce/model/InstanceGroupDetail.getReadyDateTime:()Ljava/util/Date;
     346: invokeinterface #32,  2           // InterfaceMethod com/amazonaws/protocol/json/StructuredJsonGenerator.writeValue:(Ljava/util/Date;)Lcom/amazonaws/protocol/json/StructuredJsonGenerator;
     351: pop
     352: aload_1
     353: invokevirtual #37                 // Method com/amazonaws/services/elasticmapreduce/model/InstanceGroupDetail.getEndDateTime:()Ljava/util/Date;
     356: ifnull        377
     359: aload_2
     360: ldc           #38                 // String EndDateTime
     362: invokeinterface #8,  2            // InterfaceMethod com/amazonaws/protocol/json/StructuredJsonGenerator.writeFieldName:(Ljava/lang/String;)Lcom/amazonaws/protocol/json/StructuredJsonGenerator;
     367: aload_1
     368: invokevirtual #37                 // Method com/amazonaws/services/elasticmapreduce/model/InstanceGroupDetail.getEndDateTime:()Ljava/util/Date;
     371: invokeinterface #32,  2           // InterfaceMethod com/amazonaws/protocol/json/StructuredJsonGenerator.writeValue:(Ljava/util/Date;)Lcom/amazonaws/protocol/json/StructuredJsonGenerator;
     376: pop
     377: aload_2
     378: invokeinterface #39,  1           // InterfaceMethod com/amazonaws/protocol/json/StructuredJsonGenerator.writeEndObject:()Lcom/amazonaws/protocol/json/StructuredJsonGenerator;
     383: pop
     384: goto          419
     387: astore_3
     388: new           #2                  // class com/amazonaws/AmazonClientException
     391: dup
     392: new           #41                 // class java/lang/StringBuilder
     395: dup
     396: invokespecial #42                 // Method java/lang/StringBuilder."<init>":()V
     399: ldc           #43                 // String Unable to marshall request to JSON:
     401: invokevirtual #44                 // Method java/lang/StringBuilder.append:(Ljava/lang/String;)Ljava/lang/StringBuilder;
     404: aload_3
     405: invokevirtual #45                 // Method java/lang/Throwable.getMessage:()Ljava/lang/String;
     408: invokevirtual #44                 // Method java/lang/StringBuilder.append:(Ljava/lang/String;)Ljava/lang/StringBuilder;
     411: invokevirtual #46                 // Method java/lang/StringBuilder.toString:()Ljava/lang/String;
     414: aload_3
     415: invokespecial #47                 // Method com/amazonaws/AmazonClientException."<init>":(Ljava/lang/String;Ljava/lang/Throwable;)V
     418: athrow
     419: return
    Exception table:
       from    to  target type
          14   384   387   Class java/lang/Throwable

  public static com.amazonaws.services.elasticmapreduce.model.transform.InstanceGroupDetailJsonMarshaller getInstance();
    Code:
       0: getstatic     #48                 // Field instance:Lcom/amazonaws/services/elasticmapreduce/model/transform/InstanceGroupDetailJsonMarshaller;
       3: ifnonnull     16
       6: new           #49                 // class com/amazonaws/services/elasticmapreduce/model/transform/InstanceGroupDetailJsonMarshaller
       9: dup
      10: invokespecial #50                 // Method "<init>":()V
      13: putstatic     #48                 // Field instance:Lcom/amazonaws/services/elasticmapreduce/model/transform/InstanceGroupDetailJsonMarshaller;
      16: getstatic     #48                 // Field instance:Lcom/amazonaws/services/elasticmapreduce/model/transform/InstanceGroupDetailJsonMarshaller;
      19: areturn
}
