Compiled from "ApReq.java"
public class org.apache.kerby.kerberos.kerb.type.ap.ApReq extends org.apache.kerby.kerberos.kerb.type.base.KrbMessage {
  static org.apache.kerby.asn1.Asn1FieldInfo[] fieldInfos;

  private org.apache.kerby.kerberos.kerb.type.ap.Authenticator authenticator;

  public org.apache.kerby.kerberos.kerb.type.ap.ApReq();
    Code:
       0: aload_0
       1: getstatic     #1                  // Field org/apache/kerby/kerberos/kerb/type/base/KrbMessageType.AP_REQ:Lorg/apache/kerby/kerberos/kerb/type/base/KrbMessageType;
       4: getstatic     #2                  // Field fieldInfos:[Lorg/apache/kerby/asn1/Asn1FieldInfo;
       7: invokespecial #3                  // Method org/apache/kerby/kerberos/kerb/type/base/KrbMessage."<init>":(Lorg/apache/kerby/kerberos/kerb/type/base/KrbMessageType;[Lorg/apache/kerby/asn1/Asn1FieldInfo;)V
      10: return

  public org.apache.kerby.kerberos.kerb.type.ap.ApOptions getApOptions();
    Code:
       0: aload_0
       1: getstatic     #4                  // Field org/apache/kerby/kerberos/kerb/type/ap/ApReq$ApReqField.AP_OPTIONS:Lorg/apache/kerby/kerberos/kerb/type/ap/ApReq$ApReqField;
       4: ldc_w         #5                  // class org/apache/kerby/kerberos/kerb/type/ap/ApOptions
       7: invokevirtual #6                  // Method getFieldAs:(Lorg/apache/kerby/asn1/EnumType;Ljava/lang/Class;)Lorg/apache/kerby/asn1/type/Asn1Type;
      10: checkcast     #5                  // class org/apache/kerby/kerberos/kerb/type/ap/ApOptions
      13: areturn

  public void setApOptions(org.apache.kerby.kerberos.kerb.type.ap.ApOptions);
    Code:
       0: aload_0
       1: getstatic     #4                  // Field org/apache/kerby/kerberos/kerb/type/ap/ApReq$ApReqField.AP_OPTIONS:Lorg/apache/kerby/kerberos/kerb/type/ap/ApReq$ApReqField;
       4: aload_1
       5: invokevirtual #7                  // Method setFieldAs:(Lorg/apache/kerby/asn1/EnumType;Lorg/apache/kerby/asn1/type/Asn1Type;)V
       8: return

  public org.apache.kerby.kerberos.kerb.type.ticket.Ticket getTicket();
    Code:
       0: aload_0
       1: getstatic     #8                  // Field org/apache/kerby/kerberos/kerb/type/ap/ApReq$ApReqField.TICKET:Lorg/apache/kerby/kerberos/kerb/type/ap/ApReq$ApReqField;
       4: ldc_w         #9                  // class org/apache/kerby/kerberos/kerb/type/ticket/Ticket
       7: invokevirtual #6                  // Method getFieldAs:(Lorg/apache/kerby/asn1/EnumType;Ljava/lang/Class;)Lorg/apache/kerby/asn1/type/Asn1Type;
      10: checkcast     #9                  // class org/apache/kerby/kerberos/kerb/type/ticket/Ticket
      13: areturn

  public void setTicket(org.apache.kerby.kerberos.kerb.type.ticket.Ticket);
    Code:
       0: aload_0
       1: getstatic     #8                  // Field org/apache/kerby/kerberos/kerb/type/ap/ApReq$ApReqField.TICKET:Lorg/apache/kerby/kerberos/kerb/type/ap/ApReq$ApReqField;
       4: aload_1
       5: invokevirtual #7                  // Method setFieldAs:(Lorg/apache/kerby/asn1/EnumType;Lorg/apache/kerby/asn1/type/Asn1Type;)V
       8: return

  public org.apache.kerby.kerberos.kerb.type.ap.Authenticator getAuthenticator();
    Code:
       0: aload_0
       1: getfield      #10                 // Field authenticator:Lorg/apache/kerby/kerberos/kerb/type/ap/Authenticator;
       4: areturn

  public void setAuthenticator(org.apache.kerby.kerberos.kerb.type.ap.Authenticator);
    Code:
       0: aload_0
       1: aload_1
       2: putfield      #10                 // Field authenticator:Lorg/apache/kerby/kerberos/kerb/type/ap/Authenticator;
       5: return

  public org.apache.kerby.kerberos.kerb.type.base.EncryptedData getEncryptedAuthenticator();
    Code:
       0: aload_0
       1: getstatic     #11                 // Field org/apache/kerby/kerberos/kerb/type/ap/ApReq$ApReqField.AUTHENTICATOR:Lorg/apache/kerby/kerberos/kerb/type/ap/ApReq$ApReqField;
       4: ldc_w         #12                 // class org/apache/kerby/kerberos/kerb/type/base/EncryptedData
       7: invokevirtual #6                  // Method getFieldAs:(Lorg/apache/kerby/asn1/EnumType;Ljava/lang/Class;)Lorg/apache/kerby/asn1/type/Asn1Type;
      10: checkcast     #12                 // class org/apache/kerby/kerberos/kerb/type/base/EncryptedData
      13: areturn

  public void setEncryptedAuthenticator(org.apache.kerby.kerberos.kerb.type.base.EncryptedData);
    Code:
       0: aload_0
       1: getstatic     #11                 // Field org/apache/kerby/kerberos/kerb/type/ap/ApReq$ApReqField.AUTHENTICATOR:Lorg/apache/kerby/kerberos/kerb/type/ap/ApReq$ApReqField;
       4: aload_1
       5: invokevirtual #7                  // Method setFieldAs:(Lorg/apache/kerby/asn1/EnumType;Lorg/apache/kerby/asn1/type/Asn1Type;)V
       8: return

  static {};
    Code:
       0: iconst_5
       1: anewarray     #13                 // class org/apache/kerby/asn1/Asn1FieldInfo
       4: dup
       5: iconst_0
       6: new           #14                 // class org/apache/kerby/asn1/ExplicitField
       9: dup
      10: getstatic     #15                 // Field org/apache/kerby/kerberos/kerb/type/ap/ApReq$ApReqField.PVNO:Lorg/apache/kerby/kerberos/kerb/type/ap/ApReq$ApReqField;
      13: ldc_w         #16                 // class org/apache/kerby/asn1/type/Asn1Integer
      16: invokespecial #17                 // Method org/apache/kerby/asn1/ExplicitField."<init>":(Lorg/apache/kerby/asn1/EnumType;Ljava/lang/Class;)V
      19: aastore
      20: dup
      21: iconst_1
      22: new           #14                 // class org/apache/kerby/asn1/ExplicitField
      25: dup
      26: getstatic     #18                 // Field org/apache/kerby/kerberos/kerb/type/ap/ApReq$ApReqField.MSG_TYPE:Lorg/apache/kerby/kerberos/kerb/type/ap/ApReq$ApReqField;
      29: ldc_w         #16                 // class org/apache/kerby/asn1/type/Asn1Integer
      32: invokespecial #17                 // Method org/apache/kerby/asn1/ExplicitField."<init>":(Lorg/apache/kerby/asn1/EnumType;Ljava/lang/Class;)V
      35: aastore
      36: dup
      37: iconst_2
      38: new           #14                 // class org/apache/kerby/asn1/ExplicitField
      41: dup
      42: getstatic     #4                  // Field org/apache/kerby/kerberos/kerb/type/ap/ApReq$ApReqField.AP_OPTIONS:Lorg/apache/kerby/kerberos/kerb/type/ap/ApReq$ApReqField;
      45: ldc_w         #5                  // class org/apache/kerby/kerberos/kerb/type/ap/ApOptions
      48: invokespecial #17                 // Method org/apache/kerby/asn1/ExplicitField."<init>":(Lorg/apache/kerby/asn1/EnumType;Ljava/lang/Class;)V
      51: aastore
      52: dup
      53: iconst_3
      54: new           #14                 // class org/apache/kerby/asn1/ExplicitField
      57: dup
      58: getstatic     #8                  // Field org/apache/kerby/kerberos/kerb/type/ap/ApReq$ApReqField.TICKET:Lorg/apache/kerby/kerberos/kerb/type/ap/ApReq$ApReqField;
      61: ldc_w         #9                  // class org/apache/kerby/kerberos/kerb/type/ticket/Ticket
      64: invokespecial #17                 // Method org/apache/kerby/asn1/ExplicitField."<init>":(Lorg/apache/kerby/asn1/EnumType;Ljava/lang/Class;)V
      67: aastore
      68: dup
      69: iconst_4
      70: new           #14                 // class org/apache/kerby/asn1/ExplicitField
      73: dup
      74: getstatic     #11                 // Field org/apache/kerby/kerberos/kerb/type/ap/ApReq$ApReqField.AUTHENTICATOR:Lorg/apache/kerby/kerberos/kerb/type/ap/ApReq$ApReqField;
      77: ldc_w         #12                 // class org/apache/kerby/kerberos/kerb/type/base/EncryptedData
      80: invokespecial #17                 // Method org/apache/kerby/asn1/ExplicitField."<init>":(Lorg/apache/kerby/asn1/EnumType;Ljava/lang/Class;)V
      83: aastore
      84: putstatic     #2                  // Field fieldInfos:[Lorg/apache/kerby/asn1/Asn1FieldInfo;
      87: return
}
