Compiled from "EncAPRepPart.java"
public final class org.apache.kerby.kerberos.kerb.type.ap.EncAPRepPart$EncAPRepPartField extends java.lang.Enum<org.apache.kerby.kerberos.kerb.type.ap.EncAPRepPart$EncAPRepPartField> implements org.apache.kerby.asn1.EnumType {
  public static final org.apache.kerby.kerberos.kerb.type.ap.EncAPRepPart$EncAPRepPartField CTIME;

  public static final org.apache.kerby.kerberos.kerb.type.ap.EncAPRepPart$EncAPRepPartField CUSEC;

  public static final org.apache.kerby.kerberos.kerb.type.ap.EncAPRepPart$EncAPRepPartField SUBKEY;

  public static final org.apache.kerby.kerberos.kerb.type.ap.EncAPRepPart$EncAPRepPartField SEQ_NUMBER;

  private static final org.apache.kerby.kerberos.kerb.type.ap.EncAPRepPart$EncAPRepPartField[] $VALUES;

  public static org.apache.kerby.kerberos.kerb.type.ap.EncAPRepPart$EncAPRepPartField[] values();
    Code:
       0: getstatic     #1                  // Field $VALUES:[Lorg/apache/kerby/kerberos/kerb/type/ap/EncAPRepPart$EncAPRepPartField;
       3: invokevirtual #2                  // Method "[Lorg/apache/kerby/kerberos/kerb/type/ap/EncAPRepPart$EncAPRepPartField;".clone:()Ljava/lang/Object;
       6: checkcast     #3                  // class "[Lorg/apache/kerby/kerberos/kerb/type/ap/EncAPRepPart$EncAPRepPartField;"
       9: areturn

  public static org.apache.kerby.kerberos.kerb.type.ap.EncAPRepPart$EncAPRepPartField valueOf(java.lang.String);
    Code:
       0: ldc_w         #4                  // class org/apache/kerby/kerberos/kerb/type/ap/EncAPRepPart$EncAPRepPartField
       3: aload_0
       4: invokestatic  #5                  // Method java/lang/Enum.valueOf:(Ljava/lang/Class;Ljava/lang/String;)Ljava/lang/Enum;
       7: checkcast     #4                  // class org/apache/kerby/kerberos/kerb/type/ap/EncAPRepPart$EncAPRepPartField
      10: areturn

  private org.apache.kerby.kerberos.kerb.type.ap.EncAPRepPart$EncAPRepPartField();
    Code:
       0: aload_0
       1: aload_1
       2: iload_2
       3: invokespecial #6                  // Method java/lang/Enum."<init>":(Ljava/lang/String;I)V
       6: return

  public int getValue();
    Code:
       0: aload_0
       1: invokevirtual #7                  // Method ordinal:()I
       4: ireturn

  public java.lang.String getName();
    Code:
       0: aload_0
       1: invokevirtual #8                  // Method name:()Ljava/lang/String;
       4: areturn

  static {};
    Code:
       0: new           #4                  // class org/apache/kerby/kerberos/kerb/type/ap/EncAPRepPart$EncAPRepPartField
       3: dup
       4: ldc           #9                  // String CTIME
       6: iconst_0
       7: invokespecial #10                 // Method "<init>":(Ljava/lang/String;I)V
      10: putstatic     #11                 // Field CTIME:Lorg/apache/kerby/kerberos/kerb/type/ap/EncAPRepPart$EncAPRepPartField;
      13: new           #4                  // class org/apache/kerby/kerberos/kerb/type/ap/EncAPRepPart$EncAPRepPartField
      16: dup
      17: ldc           #12                 // String CUSEC
      19: iconst_1
      20: invokespecial #10                 // Method "<init>":(Ljava/lang/String;I)V
      23: putstatic     #13                 // Field CUSEC:Lorg/apache/kerby/kerberos/kerb/type/ap/EncAPRepPart$EncAPRepPartField;
      26: new           #4                  // class org/apache/kerby/kerberos/kerb/type/ap/EncAPRepPart$EncAPRepPartField
      29: dup
      30: ldc           #14                 // String SUBKEY
      32: iconst_2
      33: invokespecial #10                 // Method "<init>":(Ljava/lang/String;I)V
      36: putstatic     #15                 // Field SUBKEY:Lorg/apache/kerby/kerberos/kerb/type/ap/EncAPRepPart$EncAPRepPartField;
      39: new           #4                  // class org/apache/kerby/kerberos/kerb/type/ap/EncAPRepPart$EncAPRepPartField
      42: dup
      43: ldc           #16                 // String SEQ_NUMBER
      45: iconst_3
      46: invokespecial #10                 // Method "<init>":(Ljava/lang/String;I)V
      49: putstatic     #17                 // Field SEQ_NUMBER:Lorg/apache/kerby/kerberos/kerb/type/ap/EncAPRepPart$EncAPRepPartField;
      52: iconst_4
      53: anewarray     #4                  // class org/apache/kerby/kerberos/kerb/type/ap/EncAPRepPart$EncAPRepPartField
      56: dup
      57: iconst_0
      58: getstatic     #11                 // Field CTIME:Lorg/apache/kerby/kerberos/kerb/type/ap/EncAPRepPart$EncAPRepPartField;
      61: aastore
      62: dup
      63: iconst_1
      64: getstatic     #13                 // Field CUSEC:Lorg/apache/kerby/kerberos/kerb/type/ap/EncAPRepPart$EncAPRepPartField;
      67: aastore
      68: dup
      69: iconst_2
      70: getstatic     #15                 // Field SUBKEY:Lorg/apache/kerby/kerberos/kerb/type/ap/EncAPRepPart$EncAPRepPartField;
      73: aastore
      74: dup
      75: iconst_3
      76: getstatic     #17                 // Field SEQ_NUMBER:Lorg/apache/kerby/kerberos/kerb/type/ap/EncAPRepPart$EncAPRepPartField;
      79: aastore
      80: putstatic     #1                  // Field $VALUES:[Lorg/apache/kerby/kerberos/kerb/type/ap/EncAPRepPart$EncAPRepPartField;
      83: return
}
