Compiled from "TcpSocketManager.java"
class org.apache.logging.log4j.core.net.TcpSocketManager$Reconnector extends org.apache.logging.log4j.core.util.Log4jThread {
  private final java.util.concurrent.CountDownLatch latch;

  private boolean shutdown;

  private final java.lang.Object owner;

  final org.apache.logging.log4j.core.net.TcpSocketManager this$0;

  public org.apache.logging.log4j.core.net.TcpSocketManager$Reconnector(org.apache.logging.log4j.core.net.TcpSocketManager, org.apache.logging.log4j.core.appender.OutputStreamManager);
    Code:
       0: aload_0
       1: aload_1
       2: putfield      #1                  // Field this$0:Lorg/apache/logging/log4j/core/net/TcpSocketManager;
       5: aload_0
       6: ldc           #2                  // String TcpSocketManager-Reconnector
       8: invokespecial #3                  // Method org/apache/logging/log4j/core/util/Log4jThread."<init>":(Ljava/lang/String;)V
      11: aload_0
      12: new           #4                  // class java/util/concurrent/CountDownLatch
      15: dup
      16: iconst_1
      17: invokespecial #5                  // Method java/util/concurrent/CountDownLatch."<init>":(I)V
      20: putfield      #6                  // Field latch:Ljava/util/concurrent/CountDownLatch;
      23: aload_0
      24: iconst_0
      25: putfield      #7                  // Field shutdown:Z
      28: aload_0
      29: aload_2
      30: putfield      #8                  // Field owner:Ljava/lang/Object;
      33: return

  public void latch();
    Code:
       0: aload_0
       1: getfield      #6                  // Field latch:Ljava/util/concurrent/CountDownLatch;
       4: invokevirtual #9                  // Method java/util/concurrent/CountDownLatch.await:()V
       7: goto          11
      10: astore_1
      11: return
    Exception table:
       from    to  target type
           0     7    10   Class java/lang/InterruptedException

  public void shutdown();
    Code:
       0: aload_0
       1: iconst_1
       2: putfield      #7                  // Field shutdown:Z
       5: return

  public void run();
    Code:
       0: aload_0
       1: getfield      #7                  // Field shutdown:Z
       4: ifne          142
       7: aload_0
       8: getfield      #1                  // Field this$0:Lorg/apache/logging/log4j/core/net/TcpSocketManager;
      11: invokestatic  #11                 // Method org/apache/logging/log4j/core/net/TcpSocketManager.access$000:(Lorg/apache/logging/log4j/core/net/TcpSocketManager;)I
      14: i2l
      15: invokestatic  #12                 // Method sleep:(J)V
      18: aload_0
      19: invokevirtual #13                 // Method reconnect:()V
      22: aload_0
      23: getfield      #6                  // Field latch:Ljava/util/concurrent/CountDownLatch;
      26: invokevirtual #14                 // Method java/util/concurrent/CountDownLatch.countDown:()V
      29: goto          139
      32: astore_1
      33: invokestatic  #15                 // Method org/apache/logging/log4j/core/net/TcpSocketManager.access$100:()Lorg/apache/logging/log4j/Logger;
      36: ldc           #16                 // String Reconnection interrupted.
      38: invokeinterface #17,  2           // InterfaceMethod org/apache/logging/log4j/Logger.debug:(Ljava/lang/String;)V
      43: aload_0
      44: getfield      #6                  // Field latch:Ljava/util/concurrent/CountDownLatch;
      47: invokevirtual #14                 // Method java/util/concurrent/CountDownLatch.countDown:()V
      50: goto          139
      53: astore_1
      54: invokestatic  #19                 // Method org/apache/logging/log4j/core/net/TcpSocketManager.access$200:()Lorg/apache/logging/log4j/Logger;
      57: ldc           #20                 // String {}:{} refused connection
      59: aload_0
      60: getfield      #1                  // Field this$0:Lorg/apache/logging/log4j/core/net/TcpSocketManager;
      63: getfield      #21                 // Field org/apache/logging/log4j/core/net/TcpSocketManager.host:Ljava/lang/String;
      66: aload_0
      67: getfield      #1                  // Field this$0:Lorg/apache/logging/log4j/core/net/TcpSocketManager;
      70: getfield      #22                 // Field org/apache/logging/log4j/core/net/TcpSocketManager.port:I
      73: invokestatic  #23                 // Method java/lang/Integer.valueOf:(I)Ljava/lang/Integer;
      76: invokeinterface #24,  4           // InterfaceMethod org/apache/logging/log4j/Logger.debug:(Ljava/lang/String;Ljava/lang/Object;Ljava/lang/Object;)V
      81: aload_0
      82: getfield      #6                  // Field latch:Ljava/util/concurrent/CountDownLatch;
      85: invokevirtual #14                 // Method java/util/concurrent/CountDownLatch.countDown:()V
      88: goto          139
      91: astore_1
      92: invokestatic  #26                 // Method org/apache/logging/log4j/core/net/TcpSocketManager.access$300:()Lorg/apache/logging/log4j/Logger;
      95: ldc           #27                 // String Unable to reconnect to {}:{}
      97: aload_0
      98: getfield      #1                  // Field this$0:Lorg/apache/logging/log4j/core/net/TcpSocketManager;
     101: getfield      #21                 // Field org/apache/logging/log4j/core/net/TcpSocketManager.host:Ljava/lang/String;
     104: aload_0
     105: getfield      #1                  // Field this$0:Lorg/apache/logging/log4j/core/net/TcpSocketManager;
     108: getfield      #22                 // Field org/apache/logging/log4j/core/net/TcpSocketManager.port:I
     111: invokestatic  #23                 // Method java/lang/Integer.valueOf:(I)Ljava/lang/Integer;
     114: invokeinterface #24,  4           // InterfaceMethod org/apache/logging/log4j/Logger.debug:(Ljava/lang/String;Ljava/lang/Object;Ljava/lang/Object;)V
     119: aload_0
     120: getfield      #6                  // Field latch:Ljava/util/concurrent/CountDownLatch;
     123: invokevirtual #14                 // Method java/util/concurrent/CountDownLatch.countDown:()V
     126: goto          139
     129: astore_2
     130: aload_0
     131: getfield      #6                  // Field latch:Ljava/util/concurrent/CountDownLatch;
     134: invokevirtual #14                 // Method java/util/concurrent/CountDownLatch.countDown:()V
     137: aload_2
     138: athrow
     139: goto          0
     142: return
    Exception table:
       from    to  target type
           7    22    32   Class java/lang/InterruptedException
           7    22    53   Class java/net/ConnectException
           7    22    91   Class java/io/IOException
           7    22   129   any
          32    43   129   any
          53    81   129   any
          91   119   129   any

  void reconnect() throws java.io.IOException;
    Code:
       0: getstatic     #28                 // Field org/apache/logging/log4j/core/net/TcpSocketManager$TcpSocketManagerFactory.RESOLVER:Lorg/apache/logging/log4j/core/net/TcpSocketManager$HostResolver;
       3: aload_0
       4: getfield      #1                  // Field this$0:Lorg/apache/logging/log4j/core/net/TcpSocketManager;
       7: getfield      #21                 // Field org/apache/logging/log4j/core/net/TcpSocketManager.host:Ljava/lang/String;
      10: aload_0
      11: getfield      #1                  // Field this$0:Lorg/apache/logging/log4j/core/net/TcpSocketManager;
      14: getfield      #22                 // Field org/apache/logging/log4j/core/net/TcpSocketManager.port:I
      17: invokevirtual #29                 // Method org/apache/logging/log4j/core/net/TcpSocketManager$HostResolver.resolveHost:(Ljava/lang/String;I)Ljava/util/List;
      20: astore_1
      21: aload_1
      22: invokeinterface #30,  1           // InterfaceMethod java/util/List.size:()I
      27: iconst_1
      28: if_icmpne     81
      31: invokestatic  #31                 // Method org/apache/logging/log4j/core/net/TcpSocketManager.access$400:()Lorg/apache/logging/log4j/Logger;
      34: new           #32                 // class java/lang/StringBuilder
      37: dup
      38: invokespecial #33                 // Method java/lang/StringBuilder."<init>":()V
      41: ldc           #34                 // String Reconnecting
      43: invokevirtual #35                 // Method java/lang/StringBuilder.append:(Ljava/lang/String;)Ljava/lang/StringBuilder;
      46: aload_1
      47: iconst_0
      48: invokeinterface #36,  2           // InterfaceMethod java/util/List.get:(I)Ljava/lang/Object;
      53: invokevirtual #37                 // Method java/lang/StringBuilder.append:(Ljava/lang/Object;)Ljava/lang/StringBuilder;
      56: invokevirtual #38                 // Method java/lang/StringBuilder.toString:()Ljava/lang/String;
      59: invokeinterface #17,  2           // InterfaceMethod org/apache/logging/log4j/Logger.debug:(Ljava/lang/String;)V
      64: aload_0
      65: aload_1
      66: iconst_0
      67: invokeinterface #36,  2           // InterfaceMethod java/util/List.get:(I)Ljava/lang/Object;
      72: checkcast     #39                 // class java/net/InetSocketAddress
      75: invokespecial #40                 // Method connect:(Ljava/net/InetSocketAddress;)V
      78: goto          155
      81: aconst_null
      82: astore_2
      83: aload_1
      84: invokeinterface #41,  1           // InterfaceMethod java/util/List.iterator:()Ljava/util/Iterator;
      89: astore_3
      90: aload_3
      91: invokeinterface #42,  1           // InterfaceMethod java/util/Iterator.hasNext:()Z
      96: ifeq          153
      99: aload_3
     100: invokeinterface #43,  1           // InterfaceMethod java/util/Iterator.next:()Ljava/lang/Object;
     105: checkcast     #39                 // class java/net/InetSocketAddress
     108: astore        4
     110: invokestatic  #44                 // Method org/apache/logging/log4j/core/net/TcpSocketManager.access$500:()Lorg/apache/logging/log4j/Logger;
     113: new           #32                 // class java/lang/StringBuilder
     116: dup
     117: invokespecial #33                 // Method java/lang/StringBuilder."<init>":()V
     120: ldc           #34                 // String Reconnecting
     122: invokevirtual #35                 // Method java/lang/StringBuilder.append:(Ljava/lang/String;)Ljava/lang/StringBuilder;
     125: aload         4
     127: invokevirtual #37                 // Method java/lang/StringBuilder.append:(Ljava/lang/Object;)Ljava/lang/StringBuilder;
     130: invokevirtual #38                 // Method java/lang/StringBuilder.toString:()Ljava/lang/String;
     133: invokeinterface #17,  2           // InterfaceMethod org/apache/logging/log4j/Logger.debug:(Ljava/lang/String;)V
     138: aload_0
     139: aload         4
     141: invokespecial #40                 // Method connect:(Ljava/net/InetSocketAddress;)V
     144: return
     145: astore        5
     147: aload         5
     149: astore_2
     150: goto          90
     153: aload_2
     154: athrow
     155: return
    Exception table:
       from    to  target type
         110   144   145   Class java/io/IOException

  private void connect(java.net.InetSocketAddress) throws java.io.IOException;
    Code:
       0: aload_0
       1: getfield      #1                  // Field this$0:Lorg/apache/logging/log4j/core/net/TcpSocketManager;
       4: aload_1
       5: invokevirtual #45                 // Method org/apache/logging/log4j/core/net/TcpSocketManager.createSocket:(Ljava/net/InetSocketAddress;)Ljava/net/Socket;
       8: astore_2
       9: aload_2
      10: invokevirtual #46                 // Method java/net/Socket.getOutputStream:()Ljava/io/OutputStream;
      13: astore_3
      14: aload_0
      15: getfield      #1                  // Field this$0:Lorg/apache/logging/log4j/core/net/TcpSocketManager;
      18: invokestatic  #47                 // Method org/apache/logging/log4j/core/net/TcpSocketManager.access$600:(Lorg/apache/logging/log4j/core/net/TcpSocketManager;)Ljava/net/Socket;
      21: ifnull        37
      24: aload_0
      25: getfield      #1                  // Field this$0:Lorg/apache/logging/log4j/core/net/TcpSocketManager;
      28: invokestatic  #47                 // Method org/apache/logging/log4j/core/net/TcpSocketManager.access$600:(Lorg/apache/logging/log4j/core/net/TcpSocketManager;)Ljava/net/Socket;
      31: invokevirtual #48                 // Method java/net/Socket.getInetAddress:()Ljava/net/InetAddress;
      34: goto          38
      37: aconst_null
      38: astore        4
      40: aload_0
      41: getfield      #8                  // Field owner:Ljava/lang/Object;
      44: dup
      45: astore        5
      47: monitorenter
      48: aload_0
      49: getfield      #1                  // Field this$0:Lorg/apache/logging/log4j/core/net/TcpSocketManager;
      52: invokestatic  #49                 // Method org/apache/logging/log4j/core/net/TcpSocketManager.access$700:(Lorg/apache/logging/log4j/core/net/TcpSocketManager;)Ljava/io/OutputStream;
      55: invokestatic  #50                 // Method org/apache/logging/log4j/core/util/Closer.closeSilently:(Ljava/lang/AutoCloseable;)Z
      58: pop
      59: aload_0
      60: getfield      #1                  // Field this$0:Lorg/apache/logging/log4j/core/net/TcpSocketManager;
      63: aload_3
      64: invokestatic  #51                 // Method org/apache/logging/log4j/core/net/TcpSocketManager.access$800:(Lorg/apache/logging/log4j/core/net/TcpSocketManager;Ljava/io/OutputStream;)V
      67: aload_0
      68: getfield      #1                  // Field this$0:Lorg/apache/logging/log4j/core/net/TcpSocketManager;
      71: aload_2
      72: invokestatic  #52                 // Method org/apache/logging/log4j/core/net/TcpSocketManager.access$602:(Lorg/apache/logging/log4j/core/net/TcpSocketManager;Ljava/net/Socket;)Ljava/net/Socket;
      75: pop
      76: aload_0
      77: getfield      #1                  // Field this$0:Lorg/apache/logging/log4j/core/net/TcpSocketManager;
      80: aconst_null
      81: invokestatic  #53                 // Method org/apache/logging/log4j/core/net/TcpSocketManager.access$902:(Lorg/apache/logging/log4j/core/net/TcpSocketManager;Lorg/apache/logging/log4j/core/net/TcpSocketManager$Reconnector;)Lorg/apache/logging/log4j/core/net/TcpSocketManager$Reconnector;
      84: pop
      85: aload_0
      86: iconst_1
      87: putfield      #7                  // Field shutdown:Z
      90: aload         5
      92: monitorexit
      93: goto          104
      96: astore        6
      98: aload         5
     100: monitorexit
     101: aload         6
     103: athrow
     104: aload         4
     106: ifnull        132
     109: aload         4
     111: invokevirtual #54                 // Method java/net/InetAddress.getHostAddress:()Ljava/lang/String;
     114: aload_1
     115: invokevirtual #55                 // Method java/net/InetSocketAddress.getAddress:()Ljava/net/InetAddress;
     118: invokevirtual #54                 // Method java/net/InetAddress.getHostAddress:()Ljava/lang/String;
     121: invokevirtual #56                 // Method java/lang/String.equals:(Ljava/lang/Object;)Z
     124: ifeq          132
     127: ldc           #57                 // String reestablished
     129: goto          134
     132: ldc           #58                 // String established
     134: astore        5
     136: invokestatic  #59                 // Method org/apache/logging/log4j/core/net/TcpSocketManager.access$1000:()Lorg/apache/logging/log4j/Logger;
     139: ldc           #60                 // String Connection to {}:{} {}: {}
     141: aload_0
     142: getfield      #1                  // Field this$0:Lorg/apache/logging/log4j/core/net/TcpSocketManager;
     145: getfield      #21                 // Field org/apache/logging/log4j/core/net/TcpSocketManager.host:Ljava/lang/String;
     148: aload_0
     149: getfield      #1                  // Field this$0:Lorg/apache/logging/log4j/core/net/TcpSocketManager;
     152: getfield      #22                 // Field org/apache/logging/log4j/core/net/TcpSocketManager.port:I
     155: invokestatic  #23                 // Method java/lang/Integer.valueOf:(I)Ljava/lang/Integer;
     158: aload         5
     160: aload_0
     161: getfield      #1                  // Field this$0:Lorg/apache/logging/log4j/core/net/TcpSocketManager;
     164: invokestatic  #47                 // Method org/apache/logging/log4j/core/net/TcpSocketManager.access$600:(Lorg/apache/logging/log4j/core/net/TcpSocketManager;)Ljava/net/Socket;
     167: invokeinterface #61,  6           // InterfaceMethod org/apache/logging/log4j/Logger.debug:(Ljava/lang/String;Ljava/lang/Object;Ljava/lang/Object;Ljava/lang/Object;Ljava/lang/Object;)V
     172: return
    Exception table:
       from    to  target type
          48    93    96   any
          96   101    96   any

  public java.lang.String toString();
    Code:
       0: new           #32                 // class java/lang/StringBuilder
       3: dup
       4: invokespecial #33                 // Method java/lang/StringBuilder."<init>":()V
       7: ldc           #62                 // String Reconnector [latch=
       9: invokevirtual #35                 // Method java/lang/StringBuilder.append:(Ljava/lang/String;)Ljava/lang/StringBuilder;
      12: aload_0
      13: getfield      #6                  // Field latch:Ljava/util/concurrent/CountDownLatch;
      16: invokevirtual #37                 // Method java/lang/StringBuilder.append:(Ljava/lang/Object;)Ljava/lang/StringBuilder;
      19: ldc           #63                 // String , shutdown=
      21: invokevirtual #35                 // Method java/lang/StringBuilder.append:(Ljava/lang/String;)Ljava/lang/StringBuilder;
      24: aload_0
      25: getfield      #7                  // Field shutdown:Z
      28: invokevirtual #64                 // Method java/lang/StringBuilder.append:(Z)Ljava/lang/StringBuilder;
      31: ldc           #65                 // String ]
      33: invokevirtual #35                 // Method java/lang/StringBuilder.append:(Ljava/lang/String;)Ljava/lang/StringBuilder;
      36: invokevirtual #38                 // Method java/lang/StringBuilder.toString:()Ljava/lang/String;
      39: areturn
}
