Compiled from "Roles.java"
class org.graylog2.shared.users.Roles$RoleToNameFunction implements com.google.common.base.Function<org.graylog2.shared.users.Role, java.lang.String> {
  private final boolean lowerCase;

  public org.graylog2.shared.users.Roles$RoleToNameFunction(boolean);
    Code:
       0: aload_0
       1: invokespecial #1                  // Method java/lang/Object."<init>":()V
       4: aload_0
       5: iload_1
       6: putfield      #2                  // Field lowerCase:Z
       9: return

  public java.lang.String apply(org.graylog2.shared.users.Role);
    Code:
       0: aload_1
       1: ifnull        30
       4: aload_1
       5: invokeinterface #3,  1            // InterfaceMethod org/graylog2/shared/users/Role.getName:()Ljava/lang/String;
      10: astore_2
      11: aload_0
      12: getfield      #2                  // Field lowerCase:Z
      15: ifeq          28
      18: aload_2
      19: getstatic     #4                  // Field java/util/Locale.ENGLISH:Ljava/util/Locale;
      22: invokevirtual #5                  // Method java/lang/String.toLowerCase:(Ljava/util/Locale;)Ljava/lang/String;
      25: goto          29
      28: aload_2
      29: areturn
      30: aconst_null
      31: areturn

  public java.lang.Object apply(java.lang.Object);
    Code:
       0: aload_0
       1: aload_1
       2: checkcast     #6                  // class org/graylog2/shared/users/Role
       5: invokevirtual #7                  // Method apply:(Lorg/graylog2/shared/users/Role;)Ljava/lang/String;
       8: areturn
}
