Compiled from "StreamObservers.java"
final class io.grpc.stub.StreamObservers$1FlowControllingOnReadyHandler implements java.lang.Runnable {
  private boolean completed;

  final io.grpc.stub.CallStreamObserver val$target;

  final java.util.Iterator val$source;

  io.grpc.stub.StreamObservers$1FlowControllingOnReadyHandler();
    Code:
       0: aload_0
       1: aload_1
       2: putfield      #1                  // Field val$target:Lio/grpc/stub/CallStreamObserver;
       5: aload_0
       6: aload_2
       7: putfield      #2                  // Field val$source:Ljava/util/Iterator;
      10: aload_0
      11: invokespecial #3                  // Method java/lang/Object."<init>":()V
      14: return

  public void run();
    Code:
       0: aload_0
       1: getfield      #4                  // Field completed:Z
       4: ifeq          8
       7: return
       8: aload_0
       9: getfield      #1                  // Field val$target:Lio/grpc/stub/CallStreamObserver;
      12: invokevirtual #5                  // Method io/grpc/stub/CallStreamObserver.isReady:()Z
      15: ifeq          49
      18: aload_0
      19: getfield      #2                  // Field val$source:Ljava/util/Iterator;
      22: invokeinterface #6,  1            // InterfaceMethod java/util/Iterator.hasNext:()Z
      27: ifeq          49
      30: aload_0
      31: getfield      #1                  // Field val$target:Lio/grpc/stub/CallStreamObserver;
      34: aload_0
      35: getfield      #2                  // Field val$source:Ljava/util/Iterator;
      38: invokeinterface #7,  1            // InterfaceMethod java/util/Iterator.next:()Ljava/lang/Object;
      43: invokevirtual #8                  // Method io/grpc/stub/CallStreamObserver.onNext:(Ljava/lang/Object;)V
      46: goto          8
      49: aload_0
      50: getfield      #2                  // Field val$source:Ljava/util/Iterator;
      53: invokeinterface #6,  1            // InterfaceMethod java/util/Iterator.hasNext:()Z
      58: ifne          73
      61: aload_0
      62: iconst_1
      63: putfield      #4                  // Field completed:Z
      66: aload_0
      67: getfield      #1                  // Field val$target:Lio/grpc/stub/CallStreamObserver;
      70: invokevirtual #9                  // Method io/grpc/stub/CallStreamObserver.onCompleted:()V
      73: return
}
