public class org.bouncycastle.asn1.x9.KeySpecificInfo extends org.bouncycastle.asn1.ASN1Object {
  private org.bouncycastle.asn1.ASN1ObjectIdentifier algorithm;

  private org.bouncycastle.asn1.ASN1OctetString counter;

  public org.bouncycastle.asn1.x9.KeySpecificInfo(org.bouncycastle.asn1.ASN1ObjectIdentifier, org.bouncycastle.asn1.ASN1OctetString);
    Code:
       0: aload_0
       1: invokespecial #56                 // Method org/bouncycastle/asn1/ASN1Object."<init>":()V
       4: aload_0
       5: aload_1
       6: putfield      #52                 // Field algorithm:Lorg/bouncycastle/asn1/ASN1ObjectIdentifier;
       9: aload_0
      10: aload_2
      11: putfield      #53                 // Field counter:Lorg/bouncycastle/asn1/ASN1OctetString;
      14: return

  public static org.bouncycastle.asn1.x9.KeySpecificInfo getInstance(java.lang.Object);
    Code:
       0: aload_0
       1: instanceof    #28                 // class org/bouncycastle/asn1/x9/KeySpecificInfo
       4: ifeq          12
       7: aload_0
       8: checkcast     #28                 // class org/bouncycastle/asn1/x9/KeySpecificInfo
      11: areturn
      12: aload_0
      13: ifnull        28
      16: new           #28                 // class org/bouncycastle/asn1/x9/KeySpecificInfo
      19: dup
      20: aload_0
      21: invokestatic  #58                 // Method org/bouncycastle/asn1/ASN1Sequence.getInstance:(Ljava/lang/Object;)Lorg/bouncycastle/asn1/ASN1Sequence;
      24: invokespecial #60                 // Method "<init>":(Lorg/bouncycastle/asn1/ASN1Sequence;)V
      27: areturn
      28: aconst_null
      29: areturn

  private org.bouncycastle.asn1.x9.KeySpecificInfo(org.bouncycastle.asn1.ASN1Sequence);
    Code:
       0: aload_0
       1: invokespecial #56                 // Method org/bouncycastle/asn1/ASN1Object."<init>":()V
       4: aload_1
       5: invokevirtual #57                 // Method org/bouncycastle/asn1/ASN1Sequence.getObjects:()Ljava/util/Enumeration;
       8: astore_2
       9: aload_0
      10: aload_2
      11: invokeinterface #61,  1           // InterfaceMethod java/util/Enumeration.nextElement:()Ljava/lang/Object;
      16: checkcast     #24                 // class org/bouncycastle/asn1/ASN1ObjectIdentifier
      19: putfield      #52                 // Field algorithm:Lorg/bouncycastle/asn1/ASN1ObjectIdentifier;
      22: aload_0
      23: aload_2
      24: invokeinterface #61,  1           // InterfaceMethod java/util/Enumeration.nextElement:()Ljava/lang/Object;
      29: checkcast     #25                 // class org/bouncycastle/asn1/ASN1OctetString
      32: putfield      #53                 // Field counter:Lorg/bouncycastle/asn1/ASN1OctetString;
      35: return

  public org.bouncycastle.asn1.ASN1ObjectIdentifier getAlgorithm();
    Code:
       0: aload_0
       1: getfield      #52                 // Field algorithm:Lorg/bouncycastle/asn1/ASN1ObjectIdentifier;
       4: areturn

  public org.bouncycastle.asn1.ASN1OctetString getCounter();
    Code:
       0: aload_0
       1: getfield      #53                 // Field counter:Lorg/bouncycastle/asn1/ASN1OctetString;
       4: areturn

  public org.bouncycastle.asn1.ASN1Primitive toASN1Primitive();
    Code:
       0: new           #22                 // class org/bouncycastle/asn1/ASN1EncodableVector
       3: dup
       4: iconst_2
       5: invokespecial #54                 // Method org/bouncycastle/asn1/ASN1EncodableVector."<init>":(I)V
       8: astore_1
       9: aload_1
      10: aload_0
      11: getfield      #52                 // Field algorithm:Lorg/bouncycastle/asn1/ASN1ObjectIdentifier;
      14: invokevirtual #55                 // Method org/bouncycastle/asn1/ASN1EncodableVector.add:(Lorg/bouncycastle/asn1/ASN1Encodable;)V
      17: aload_1
      18: aload_0
      19: getfield      #53                 // Field counter:Lorg/bouncycastle/asn1/ASN1OctetString;
      22: invokevirtual #55                 // Method org/bouncycastle/asn1/ASN1EncodableVector.add:(Lorg/bouncycastle/asn1/ASN1Encodable;)V
      25: new           #27                 // class org/bouncycastle/asn1/DERSequence
      28: dup
      29: aload_1
      30: invokespecial #59                 // Method org/bouncycastle/asn1/DERSequence."<init>":(Lorg/bouncycastle/asn1/ASN1EncodableVector;)V
      33: areturn
}
