Compiled from "ScalazProperties.scala"
public final class scalaz.scalacheck.ScalazProperties$bitraverse$ implements java.io.Serializable {
  public static final scalaz.scalacheck.ScalazProperties$bitraverse$ MODULE$;

  public scalaz.scalacheck.ScalazProperties$bitraverse$();
    Code:
       0: aload_0
       1: invokespecial #22                 // Method java/lang/Object."<init>":()V
       4: return

  public static {};
    Code:
       0: new           #2                  // class scalaz/scalacheck/ScalazProperties$bitraverse$
       3: dup
       4: invokespecial #25                 // Method "<init>":()V
       7: putstatic     #27                 // Field MODULE$:Lscalaz/scalacheck/ScalazProperties$bitraverse$;
      10: return

  private java.lang.Object writeReplace();
    Code:
       0: new           #31                 // class scala/runtime/ModuleSerializationProxy
       3: dup
       4: ldc           #2                  // class scalaz/scalacheck/ScalazProperties$bitraverse$
       6: invokespecial #34                 // Method scala/runtime/ModuleSerializationProxy."<init>":(Ljava/lang/Class;)V
       9: areturn

  public <F> org.scalacheck.Properties laws(org.scalacheck.Arbitrary<java.lang.Object>, scalaz.Bitraverse<F>, scalaz.Equal<java.lang.Object>);
    Code:
       0: getstatic     #45                 // Field scalaz/scalacheck/ScalazProperties$.MODULE$:Lscalaz/scalacheck/ScalazProperties$;
       3: ldc           #47                 // String bitraverse
       5: aload_0
       6: aload_1
       7: aload_2
       8: aload_3
       9: invokedynamic #69,  0             // InvokeDynamic #0:apply:(Lscalaz/scalacheck/ScalazProperties$bitraverse$;Lorg/scalacheck/Arbitrary;Lscalaz/Bitraverse;Lscalaz/Equal;)Lscala/Function1;
      14: invokevirtual #73                 // Method scalaz/scalacheck/ScalazProperties$.scalaz$scalacheck$ScalazProperties$$$newProperties:(Ljava/lang/String;Lscala/Function1;)Lorg/scalacheck/Properties;
      17: areturn

  private final void laws$$anonfun$1(org.scalacheck.Arbitrary, scalaz.Bitraverse, scalaz.Equal, org.scalacheck.Properties);
    Code:
       0: aload         4
       2: getstatic     #85                 // Field scalaz/scalacheck/ScalazProperties$bifoldable$.MODULE$:Lscalaz/scalacheck/ScalazProperties$bifoldable$;
       5: aload_1
       6: aload_2
       7: invokevirtual #88                 // Method scalaz/scalacheck/ScalazProperties$bifoldable$.laws:(Lorg/scalacheck/Arbitrary;Lscalaz/Bifoldable;)Lorg/scalacheck/Properties;
      10: invokevirtual #94                 // Method org/scalacheck/Properties.include:(Lorg/scalacheck/Properties;)V
      13: aload_2
      14: invokeinterface #100,  1          // InterfaceMethod scalaz/Bitraverse.leftTraverse:()Lscalaz/Traverse;
      19: astore        5
      21: aload_2
      22: invokeinterface #103,  1          // InterfaceMethod scalaz/Bitraverse.rightTraverse:()Lscalaz/Traverse;
      27: astore        6
      29: aload         4
      31: getstatic     #106                // Field scalaz/scalacheck/ScalazProperties$traverse$.MODULE$:Lscalaz/scalacheck/ScalazProperties$traverse$;
      34: aload_1
      35: aload         5
      37: aload_3
      38: invokevirtual #109                // Method scalaz/scalacheck/ScalazProperties$traverse$.laws:(Lorg/scalacheck/Arbitrary;Lscalaz/Traverse;Lscalaz/Equal;)Lorg/scalacheck/Properties;
      41: invokevirtual #94                 // Method org/scalacheck/Properties.include:(Lorg/scalacheck/Properties;)V
      44: aload         4
      46: getstatic     #106                // Field scalaz/scalacheck/ScalazProperties$traverse$.MODULE$:Lscalaz/scalacheck/ScalazProperties$traverse$;
      49: aload_1
      50: aload         6
      52: aload_3
      53: invokevirtual #109                // Method scalaz/scalacheck/ScalazProperties$traverse$.laws:(Lorg/scalacheck/Arbitrary;Lscalaz/Traverse;Lscalaz/Equal;)Lorg/scalacheck/Properties;
      56: invokevirtual #94                 // Method org/scalacheck/Properties.include:(Lorg/scalacheck/Properties;)V
      59: return

  private java.lang.Object laws$$anonfun$adapted$1(org.scalacheck.Arbitrary, scalaz.Bitraverse, scalaz.Equal, org.scalacheck.Properties);
    Code:
       0: aload_0
       1: aload_1
       2: aload_2
       3: aload_3
       4: aload         4
       6: invokespecial #118                // Method laws$$anonfun$1:(Lorg/scalacheck/Arbitrary;Lscalaz/Bitraverse;Lscalaz/Equal;Lorg/scalacheck/Properties;)V
       9: getstatic     #124                // Field scala/runtime/BoxedUnit.UNIT:Lscala/runtime/BoxedUnit;
      12: areturn

  private static java.lang.Object $deserializeLambda$(java.lang.invoke.SerializedLambda);
    Code:
       0: aload_0
       1: invokedynamic #136,  0            // InvokeDynamic #1:lambdaDeserialize:(Ljava/lang/invoke/SerializedLambda;)Ljava/lang/Object;
       6: areturn
}
