Compiled from "WebContextProvider.kt"
public final class dev.neeffect.nee.ctx.web.EffectsInstance$PlainInstances<R, G extends dev.neeffect.nee.effects.tx.TxProvider<R, G>> {
  private final dev.neeffect.nee.effects.tx.TxEffect<java.sql.Connection, dev.neeffect.nee.ctx.web.WebContext<R, G>> tx;

  public final dev.neeffect.nee.effects.tx.TxEffect<java.sql.Connection, dev.neeffect.nee.ctx.web.WebContext<R, G>> getTx();
    Code:
       0: aload_0
       1: getfield      #14                 // Field tx:Ldev/neeffect/nee/effects/tx/TxEffect;
       4: areturn

  public dev.neeffect.nee.ctx.web.EffectsInstance$PlainInstances();
    Code:
       0: aload_0
       1: invokespecial #20                 // Method java/lang/Object."<init>":()V
       4: aload_0
       5: new           #22                 // class dev/neeffect/nee/effects/tx/TxEffect
       8: dup
       9: iconst_0
      10: iconst_1
      11: aconst_null
      12: invokespecial #25                 // Method dev/neeffect/nee/effects/tx/TxEffect."<init>":(ZILkotlin/jvm/internal/DefaultConstructorMarker;)V
      15: putfield      #14                 // Field tx:Ldev/neeffect/nee/effects/tx/TxEffect;
      18: return
}
