Compiled from "DFUWorkunit.java"
public class org.hpccsystems.ws.client.gen.axis2.filespray.v1_20.DFUWorkunit implements org.apache.axis2.databinding.ADBBean {
  protected java.lang.String localID;

  protected boolean localIDTracker;

  protected java.lang.String localDFUServerName;

  protected boolean localDFUServerNameTracker;

  protected java.lang.String localClusterName;

  protected boolean localClusterNameTracker;

  protected java.lang.String localJobName;

  protected boolean localJobNameTracker;

  protected java.lang.String localQueue;

  protected boolean localQueueTracker;

  protected java.lang.String localUser;

  protected boolean localUserTracker;

  protected boolean localIsProtected;

  protected boolean localIsProtectedTracker;

  protected int localCommand;

  protected boolean localCommandTracker;

  protected java.lang.String localCommandMessage;

  protected boolean localCommandMessageTracker;

  protected int localPercentDone;

  protected boolean localPercentDoneTracker;

  protected int localSecsLeft;

  protected boolean localSecsLeftTracker;

  protected java.lang.String localProgressMessage;

  protected boolean localProgressMessageTracker;

  protected java.lang.String localSummaryMessage;

  protected boolean localSummaryMessageTracker;

  protected int localState;

  protected boolean localStateTracker;

  protected java.lang.String localSourceLogicalName;

  protected boolean localSourceLogicalNameTracker;

  protected java.lang.String localSourceIP;

  protected boolean localSourceIPTracker;

  protected java.lang.String localSourceFilePath;

  protected boolean localSourceFilePathTracker;

  protected java.lang.String localSourceDali;

  protected boolean localSourceDaliTracker;

  protected int localSourceRecordSize;

  protected boolean localSourceRecordSizeTracker;

  protected int localSourceFormat;

  protected boolean localSourceFormatTracker;

  protected java.lang.String localRowTag;

  protected boolean localRowTagTracker;

  protected int localSourceNumParts;

  protected boolean localSourceNumPartsTracker;

  protected java.lang.String localSourceDirectory;

  protected boolean localSourceDirectoryTracker;

  protected java.lang.String localDestLogicalName;

  protected boolean localDestLogicalNameTracker;

  protected java.lang.String localDestGroupName;

  protected boolean localDestGroupNameTracker;

  protected java.lang.String localDestDirectory;

  protected boolean localDestDirectoryTracker;

  protected java.lang.String localDestIP;

  protected boolean localDestIPTracker;

  protected java.lang.String localDestFilePath;

  protected boolean localDestFilePathTracker;

  protected int localDestFormat;

  protected boolean localDestFormatTracker;

  protected int localDestNumParts;

  protected boolean localDestNumPartsTracker;

  protected int localDestRecordSize;

  protected boolean localDestRecordSizeTracker;

  protected boolean localReplicate;

  protected boolean localReplicateTracker;

  protected boolean localOverwrite;

  protected boolean localOverwriteTracker;

  protected boolean localCompress;

  protected boolean localCompressTracker;

  protected java.lang.String localSourceCsvSeparate;

  protected boolean localSourceCsvSeparateTracker;

  protected java.lang.String localSourceCsvQuote;

  protected boolean localSourceCsvQuoteTracker;

  protected java.lang.String localSourceCsvTerminate;

  protected boolean localSourceCsvTerminateTracker;

  protected java.lang.String localSourceCsvEscape;

  protected boolean localSourceCsvEscapeTracker;

  protected java.lang.String localTimeStarted;

  protected boolean localTimeStartedTracker;

  protected java.lang.String localTimeStopped;

  protected boolean localTimeStoppedTracker;

  protected java.lang.String localStateMessage;

  protected boolean localStateMessageTracker;

  protected java.lang.String localMonitorEventName;

  protected boolean localMonitorEventNameTracker;

  protected boolean localMonitorSub;

  protected boolean localMonitorSubTracker;

  protected int localMonitorShotLimit;

  protected boolean localMonitorShotLimitTracker;

  protected java.lang.String localSourceDiffKeyName;

  protected boolean localSourceDiffKeyNameTracker;

  protected java.lang.String localDestDiffKeyName;

  protected boolean localDestDiffKeyNameTracker;

  protected boolean localArchived;

  protected boolean localArchivedTracker;

  protected java.lang.String localEncrypt;

  protected boolean localEncryptTracker;

  protected java.lang.String localDecrypt;

  protected boolean localDecryptTracker;

  protected boolean localFailIfNoSourceFile;

  protected boolean localFailIfNoSourceFileTracker;

  protected boolean localRecordStructurePresent;

  protected boolean localRecordStructurePresentTracker;

  protected boolean localQuotedTerminator;

  protected boolean localQuotedTerminatorTracker;

  protected boolean localPreserveCompression;

  protected boolean localPreserveCompressionTracker;

  protected int localExpireDays;

  protected boolean localExpireDaysTracker;

  public org.hpccsystems.ws.client.gen.axis2.filespray.v1_20.DFUWorkunit();
    Code:
       0: aload_0
       1: invokespecial #1                  // Method java/lang/Object."<init>":()V
       4: aload_0
       5: iconst_0
       6: putfield      #2                  // Field localIDTracker:Z
       9: aload_0
      10: iconst_0
      11: putfield      #3                  // Field localDFUServerNameTracker:Z
      14: aload_0
      15: iconst_0
      16: putfield      #4                  // Field localClusterNameTracker:Z
      19: aload_0
      20: iconst_0
      21: putfield      #5                  // Field localJobNameTracker:Z
      24: aload_0
      25: iconst_0
      26: putfield      #6                  // Field localQueueTracker:Z
      29: aload_0
      30: iconst_0
      31: putfield      #7                  // Field localUserTracker:Z
      34: aload_0
      35: iconst_0
      36: putfield      #8                  // Field localIsProtectedTracker:Z
      39: aload_0
      40: iconst_0
      41: putfield      #9                  // Field localCommandTracker:Z
      44: aload_0
      45: iconst_0
      46: putfield      #10                 // Field localCommandMessageTracker:Z
      49: aload_0
      50: iconst_0
      51: putfield      #11                 // Field localPercentDoneTracker:Z
      54: aload_0
      55: iconst_0
      56: putfield      #12                 // Field localSecsLeftTracker:Z
      59: aload_0
      60: iconst_0
      61: putfield      #13                 // Field localProgressMessageTracker:Z
      64: aload_0
      65: iconst_0
      66: putfield      #14                 // Field localSummaryMessageTracker:Z
      69: aload_0
      70: iconst_0
      71: putfield      #15                 // Field localStateTracker:Z
      74: aload_0
      75: iconst_0
      76: putfield      #16                 // Field localSourceLogicalNameTracker:Z
      79: aload_0
      80: iconst_0
      81: putfield      #17                 // Field localSourceIPTracker:Z
      84: aload_0
      85: iconst_0
      86: putfield      #18                 // Field localSourceFilePathTracker:Z
      89: aload_0
      90: iconst_0
      91: putfield      #19                 // Field localSourceDaliTracker:Z
      94: aload_0
      95: iconst_0
      96: putfield      #20                 // Field localSourceRecordSizeTracker:Z
      99: aload_0
     100: iconst_0
     101: putfield      #21                 // Field localSourceFormatTracker:Z
     104: aload_0
     105: iconst_0
     106: putfield      #22                 // Field localRowTagTracker:Z
     109: aload_0
     110: iconst_0
     111: putfield      #23                 // Field localSourceNumPartsTracker:Z
     114: aload_0
     115: iconst_0
     116: putfield      #24                 // Field localSourceDirectoryTracker:Z
     119: aload_0
     120: iconst_0
     121: putfield      #25                 // Field localDestLogicalNameTracker:Z
     124: aload_0
     125: iconst_0
     126: putfield      #26                 // Field localDestGroupNameTracker:Z
     129: aload_0
     130: iconst_0
     131: putfield      #27                 // Field localDestDirectoryTracker:Z
     134: aload_0
     135: iconst_0
     136: putfield      #28                 // Field localDestIPTracker:Z
     139: aload_0
     140: iconst_0
     141: putfield      #29                 // Field localDestFilePathTracker:Z
     144: aload_0
     145: iconst_0
     146: putfield      #30                 // Field localDestFormatTracker:Z
     149: aload_0
     150: iconst_0
     151: putfield      #31                 // Field localDestNumPartsTracker:Z
     154: aload_0
     155: iconst_0
     156: putfield      #32                 // Field localDestRecordSizeTracker:Z
     159: aload_0
     160: iconst_0
     161: putfield      #33                 // Field localReplicateTracker:Z
     164: aload_0
     165: iconst_0
     166: putfield      #34                 // Field localOverwriteTracker:Z
     169: aload_0
     170: iconst_0
     171: putfield      #35                 // Field localCompressTracker:Z
     174: aload_0
     175: iconst_0
     176: putfield      #36                 // Field localSourceCsvSeparateTracker:Z
     179: aload_0
     180: iconst_0
     181: putfield      #37                 // Field localSourceCsvQuoteTracker:Z
     184: aload_0
     185: iconst_0
     186: putfield      #38                 // Field localSourceCsvTerminateTracker:Z
     189: aload_0
     190: iconst_0
     191: putfield      #39                 // Field localSourceCsvEscapeTracker:Z
     194: aload_0
     195: iconst_0
     196: putfield      #40                 // Field localTimeStartedTracker:Z
     199: aload_0
     200: iconst_0
     201: putfield      #41                 // Field localTimeStoppedTracker:Z
     204: aload_0
     205: iconst_0
     206: putfield      #42                 // Field localStateMessageTracker:Z
     209: aload_0
     210: iconst_0
     211: putfield      #43                 // Field localMonitorEventNameTracker:Z
     214: aload_0
     215: iconst_0
     216: putfield      #44                 // Field localMonitorSubTracker:Z
     219: aload_0
     220: iconst_0
     221: putfield      #45                 // Field localMonitorShotLimitTracker:Z
     224: aload_0
     225: iconst_0
     226: putfield      #46                 // Field localSourceDiffKeyNameTracker:Z
     229: aload_0
     230: iconst_0
     231: putfield      #47                 // Field localDestDiffKeyNameTracker:Z
     234: aload_0
     235: ldc           #48                 // String false
     237: invokestatic  #49                 // Method org/apache/axis2/databinding/utils/ConverterUtil.convertToBoolean:(Ljava/lang/String;)Z
     240: putfield      #50                 // Field localArchived:Z
     243: aload_0
     244: iconst_0
     245: putfield      #51                 // Field localArchivedTracker:Z
     248: aload_0
     249: iconst_0
     250: putfield      #52                 // Field localEncryptTracker:Z
     253: aload_0
     254: iconst_0
     255: putfield      #53                 // Field localDecryptTracker:Z
     258: aload_0
     259: ldc           #48                 // String false
     261: invokestatic  #49                 // Method org/apache/axis2/databinding/utils/ConverterUtil.convertToBoolean:(Ljava/lang/String;)Z
     264: putfield      #54                 // Field localFailIfNoSourceFile:Z
     267: aload_0
     268: iconst_0
     269: putfield      #55                 // Field localFailIfNoSourceFileTracker:Z
     272: aload_0
     273: ldc           #48                 // String false
     275: invokestatic  #49                 // Method org/apache/axis2/databinding/utils/ConverterUtil.convertToBoolean:(Ljava/lang/String;)Z
     278: putfield      #56                 // Field localRecordStructurePresent:Z
     281: aload_0
     282: iconst_0
     283: putfield      #57                 // Field localRecordStructurePresentTracker:Z
     286: aload_0
     287: ldc           #58                 // String true
     289: invokestatic  #49                 // Method org/apache/axis2/databinding/utils/ConverterUtil.convertToBoolean:(Ljava/lang/String;)Z
     292: putfield      #59                 // Field localQuotedTerminator:Z
     295: aload_0
     296: iconst_0
     297: putfield      #60                 // Field localQuotedTerminatorTracker:Z
     300: aload_0
     301: ldc           #58                 // String true
     303: invokestatic  #49                 // Method org/apache/axis2/databinding/utils/ConverterUtil.convertToBoolean:(Ljava/lang/String;)Z
     306: putfield      #61                 // Field localPreserveCompression:Z
     309: aload_0
     310: iconst_0
     311: putfield      #62                 // Field localPreserveCompressionTracker:Z
     314: aload_0
     315: iconst_0
     316: putfield      #63                 // Field localExpireDaysTracker:Z
     319: return

  public boolean isIDSpecified();
    Code:
       0: aload_0
       1: getfield      #2                  // Field localIDTracker:Z
       4: ireturn

  public java.lang.String getID();
    Code:
       0: aload_0
       1: getfield      #64                 // Field localID:Ljava/lang/String;
       4: areturn

  public void setID(java.lang.String);
    Code:
       0: aload_0
       1: aload_1
       2: ifnull        9
       5: iconst_1
       6: goto          10
       9: iconst_0
      10: putfield      #2                  // Field localIDTracker:Z
      13: aload_0
      14: aload_1
      15: putfield      #64                 // Field localID:Ljava/lang/String;
      18: return

  public boolean isDFUServerNameSpecified();
    Code:
       0: aload_0
       1: getfield      #3                  // Field localDFUServerNameTracker:Z
       4: ireturn

  public java.lang.String getDFUServerName();
    Code:
       0: aload_0
       1: getfield      #65                 // Field localDFUServerName:Ljava/lang/String;
       4: areturn

  public void setDFUServerName(java.lang.String);
    Code:
       0: aload_0
       1: aload_1
       2: ifnull        9
       5: iconst_1
       6: goto          10
       9: iconst_0
      10: putfield      #3                  // Field localDFUServerNameTracker:Z
      13: aload_0
      14: aload_1
      15: putfield      #65                 // Field localDFUServerName:Ljava/lang/String;
      18: return

  public boolean isClusterNameSpecified();
    Code:
       0: aload_0
       1: getfield      #4                  // Field localClusterNameTracker:Z
       4: ireturn

  public java.lang.String getClusterName();
    Code:
       0: aload_0
       1: getfield      #66                 // Field localClusterName:Ljava/lang/String;
       4: areturn

  public void setClusterName(java.lang.String);
    Code:
       0: aload_0
       1: aload_1
       2: ifnull        9
       5: iconst_1
       6: goto          10
       9: iconst_0
      10: putfield      #4                  // Field localClusterNameTracker:Z
      13: aload_0
      14: aload_1
      15: putfield      #66                 // Field localClusterName:Ljava/lang/String;
      18: return

  public boolean isJobNameSpecified();
    Code:
       0: aload_0
       1: getfield      #5                  // Field localJobNameTracker:Z
       4: ireturn

  public java.lang.String getJobName();
    Code:
       0: aload_0
       1: getfield      #67                 // Field localJobName:Ljava/lang/String;
       4: areturn

  public void setJobName(java.lang.String);
    Code:
       0: aload_0
       1: aload_1
       2: ifnull        9
       5: iconst_1
       6: goto          10
       9: iconst_0
      10: putfield      #5                  // Field localJobNameTracker:Z
      13: aload_0
      14: aload_1
      15: putfield      #67                 // Field localJobName:Ljava/lang/String;
      18: return

  public boolean isQueueSpecified();
    Code:
       0: aload_0
       1: getfield      #6                  // Field localQueueTracker:Z
       4: ireturn

  public java.lang.String getQueue();
    Code:
       0: aload_0
       1: getfield      #68                 // Field localQueue:Ljava/lang/String;
       4: areturn

  public void setQueue(java.lang.String);
    Code:
       0: aload_0
       1: aload_1
       2: ifnull        9
       5: iconst_1
       6: goto          10
       9: iconst_0
      10: putfield      #6                  // Field localQueueTracker:Z
      13: aload_0
      14: aload_1
      15: putfield      #68                 // Field localQueue:Ljava/lang/String;
      18: return

  public boolean isUserSpecified();
    Code:
       0: aload_0
       1: getfield      #7                  // Field localUserTracker:Z
       4: ireturn

  public java.lang.String getUser();
    Code:
       0: aload_0
       1: getfield      #69                 // Field localUser:Ljava/lang/String;
       4: areturn

  public void setUser(java.lang.String);
    Code:
       0: aload_0
       1: aload_1
       2: ifnull        9
       5: iconst_1
       6: goto          10
       9: iconst_0
      10: putfield      #7                  // Field localUserTracker:Z
      13: aload_0
      14: aload_1
      15: putfield      #69                 // Field localUser:Ljava/lang/String;
      18: return

  public boolean isIsProtectedSpecified();
    Code:
       0: aload_0
       1: getfield      #8                  // Field localIsProtectedTracker:Z
       4: ireturn

  public boolean getIsProtected();
    Code:
       0: aload_0
       1: getfield      #70                 // Field localIsProtected:Z
       4: ireturn

  public void setIsProtected(boolean);
    Code:
       0: aload_0
       1: iconst_1
       2: putfield      #8                  // Field localIsProtectedTracker:Z
       5: aload_0
       6: iload_1
       7: putfield      #70                 // Field localIsProtected:Z
      10: return

  public boolean isCommandSpecified();
    Code:
       0: aload_0
       1: getfield      #9                  // Field localCommandTracker:Z
       4: ireturn

  public int getCommand();
    Code:
       0: aload_0
       1: getfield      #71                 // Field localCommand:I
       4: ireturn

  public void setCommand(int);
    Code:
       0: aload_0
       1: iload_1
       2: ldc           #73                 // int -2147483648
       4: if_icmpeq     11
       7: iconst_1
       8: goto          12
      11: iconst_0
      12: putfield      #9                  // Field localCommandTracker:Z
      15: aload_0
      16: iload_1
      17: putfield      #71                 // Field localCommand:I
      20: return

  public boolean isCommandMessageSpecified();
    Code:
       0: aload_0
       1: getfield      #10                 // Field localCommandMessageTracker:Z
       4: ireturn

  public java.lang.String getCommandMessage();
    Code:
       0: aload_0
       1: getfield      #74                 // Field localCommandMessage:Ljava/lang/String;
       4: areturn

  public void setCommandMessage(java.lang.String);
    Code:
       0: aload_0
       1: aload_1
       2: ifnull        9
       5: iconst_1
       6: goto          10
       9: iconst_0
      10: putfield      #10                 // Field localCommandMessageTracker:Z
      13: aload_0
      14: aload_1
      15: putfield      #74                 // Field localCommandMessage:Ljava/lang/String;
      18: return

  public boolean isPercentDoneSpecified();
    Code:
       0: aload_0
       1: getfield      #11                 // Field localPercentDoneTracker:Z
       4: ireturn

  public int getPercentDone();
    Code:
       0: aload_0
       1: getfield      #75                 // Field localPercentDone:I
       4: ireturn

  public void setPercentDone(int);
    Code:
       0: aload_0
       1: iload_1
       2: ldc           #73                 // int -2147483648
       4: if_icmpeq     11
       7: iconst_1
       8: goto          12
      11: iconst_0
      12: putfield      #11                 // Field localPercentDoneTracker:Z
      15: aload_0
      16: iload_1
      17: putfield      #75                 // Field localPercentDone:I
      20: return

  public boolean isSecsLeftSpecified();
    Code:
       0: aload_0
       1: getfield      #12                 // Field localSecsLeftTracker:Z
       4: ireturn

  public int getSecsLeft();
    Code:
       0: aload_0
       1: getfield      #76                 // Field localSecsLeft:I
       4: ireturn

  public void setSecsLeft(int);
    Code:
       0: aload_0
       1: iload_1
       2: ldc           #73                 // int -2147483648
       4: if_icmpeq     11
       7: iconst_1
       8: goto          12
      11: iconst_0
      12: putfield      #12                 // Field localSecsLeftTracker:Z
      15: aload_0
      16: iload_1
      17: putfield      #76                 // Field localSecsLeft:I
      20: return

  public boolean isProgressMessageSpecified();
    Code:
       0: aload_0
       1: getfield      #13                 // Field localProgressMessageTracker:Z
       4: ireturn

  public java.lang.String getProgressMessage();
    Code:
       0: aload_0
       1: getfield      #77                 // Field localProgressMessage:Ljava/lang/String;
       4: areturn

  public void setProgressMessage(java.lang.String);
    Code:
       0: aload_0
       1: aload_1
       2: ifnull        9
       5: iconst_1
       6: goto          10
       9: iconst_0
      10: putfield      #13                 // Field localProgressMessageTracker:Z
      13: aload_0
      14: aload_1
      15: putfield      #77                 // Field localProgressMessage:Ljava/lang/String;
      18: return

  public boolean isSummaryMessageSpecified();
    Code:
       0: aload_0
       1: getfield      #14                 // Field localSummaryMessageTracker:Z
       4: ireturn

  public java.lang.String getSummaryMessage();
    Code:
       0: aload_0
       1: getfield      #78                 // Field localSummaryMessage:Ljava/lang/String;
       4: areturn

  public void setSummaryMessage(java.lang.String);
    Code:
       0: aload_0
       1: aload_1
       2: ifnull        9
       5: iconst_1
       6: goto          10
       9: iconst_0
      10: putfield      #14                 // Field localSummaryMessageTracker:Z
      13: aload_0
      14: aload_1
      15: putfield      #78                 // Field localSummaryMessage:Ljava/lang/String;
      18: return

  public boolean isStateSpecified();
    Code:
       0: aload_0
       1: getfield      #15                 // Field localStateTracker:Z
       4: ireturn

  public int getState();
    Code:
       0: aload_0
       1: getfield      #79                 // Field localState:I
       4: ireturn

  public void setState(int);
    Code:
       0: aload_0
       1: iload_1
       2: ldc           #73                 // int -2147483648
       4: if_icmpeq     11
       7: iconst_1
       8: goto          12
      11: iconst_0
      12: putfield      #15                 // Field localStateTracker:Z
      15: aload_0
      16: iload_1
      17: putfield      #79                 // Field localState:I
      20: return

  public boolean isSourceLogicalNameSpecified();
    Code:
       0: aload_0
       1: getfield      #16                 // Field localSourceLogicalNameTracker:Z
       4: ireturn

  public java.lang.String getSourceLogicalName();
    Code:
       0: aload_0
       1: getfield      #80                 // Field localSourceLogicalName:Ljava/lang/String;
       4: areturn

  public void setSourceLogicalName(java.lang.String);
    Code:
       0: aload_0
       1: aload_1
       2: ifnull        9
       5: iconst_1
       6: goto          10
       9: iconst_0
      10: putfield      #16                 // Field localSourceLogicalNameTracker:Z
      13: aload_0
      14: aload_1
      15: putfield      #80                 // Field localSourceLogicalName:Ljava/lang/String;
      18: return

  public boolean isSourceIPSpecified();
    Code:
       0: aload_0
       1: getfield      #17                 // Field localSourceIPTracker:Z
       4: ireturn

  public java.lang.String getSourceIP();
    Code:
       0: aload_0
       1: getfield      #81                 // Field localSourceIP:Ljava/lang/String;
       4: areturn

  public void setSourceIP(java.lang.String);
    Code:
       0: aload_0
       1: aload_1
       2: ifnull        9
       5: iconst_1
       6: goto          10
       9: iconst_0
      10: putfield      #17                 // Field localSourceIPTracker:Z
      13: aload_0
      14: aload_1
      15: putfield      #81                 // Field localSourceIP:Ljava/lang/String;
      18: return

  public boolean isSourceFilePathSpecified();
    Code:
       0: aload_0
       1: getfield      #18                 // Field localSourceFilePathTracker:Z
       4: ireturn

  public java.lang.String getSourceFilePath();
    Code:
       0: aload_0
       1: getfield      #82                 // Field localSourceFilePath:Ljava/lang/String;
       4: areturn

  public void setSourceFilePath(java.lang.String);
    Code:
       0: aload_0
       1: aload_1
       2: ifnull        9
       5: iconst_1
       6: goto          10
       9: iconst_0
      10: putfield      #18                 // Field localSourceFilePathTracker:Z
      13: aload_0
      14: aload_1
      15: putfield      #82                 // Field localSourceFilePath:Ljava/lang/String;
      18: return

  public boolean isSourceDaliSpecified();
    Code:
       0: aload_0
       1: getfield      #19                 // Field localSourceDaliTracker:Z
       4: ireturn

  public java.lang.String getSourceDali();
    Code:
       0: aload_0
       1: getfield      #83                 // Field localSourceDali:Ljava/lang/String;
       4: areturn

  public void setSourceDali(java.lang.String);
    Code:
       0: aload_0
       1: aload_1
       2: ifnull        9
       5: iconst_1
       6: goto          10
       9: iconst_0
      10: putfield      #19                 // Field localSourceDaliTracker:Z
      13: aload_0
      14: aload_1
      15: putfield      #83                 // Field localSourceDali:Ljava/lang/String;
      18: return

  public boolean isSourceRecordSizeSpecified();
    Code:
       0: aload_0
       1: getfield      #20                 // Field localSourceRecordSizeTracker:Z
       4: ireturn

  public int getSourceRecordSize();
    Code:
       0: aload_0
       1: getfield      #84                 // Field localSourceRecordSize:I
       4: ireturn

  public void setSourceRecordSize(int);
    Code:
       0: aload_0
       1: iload_1
       2: ldc           #73                 // int -2147483648
       4: if_icmpeq     11
       7: iconst_1
       8: goto          12
      11: iconst_0
      12: putfield      #20                 // Field localSourceRecordSizeTracker:Z
      15: aload_0
      16: iload_1
      17: putfield      #84                 // Field localSourceRecordSize:I
      20: return

  public boolean isSourceFormatSpecified();
    Code:
       0: aload_0
       1: getfield      #21                 // Field localSourceFormatTracker:Z
       4: ireturn

  public int getSourceFormat();
    Code:
       0: aload_0
       1: getfield      #85                 // Field localSourceFormat:I
       4: ireturn

  public void setSourceFormat(int);
    Code:
       0: aload_0
       1: iload_1
       2: ldc           #73                 // int -2147483648
       4: if_icmpeq     11
       7: iconst_1
       8: goto          12
      11: iconst_0
      12: putfield      #21                 // Field localSourceFormatTracker:Z
      15: aload_0
      16: iload_1
      17: putfield      #85                 // Field localSourceFormat:I
      20: return

  public boolean isRowTagSpecified();
    Code:
       0: aload_0
       1: getfield      #22                 // Field localRowTagTracker:Z
       4: ireturn

  public java.lang.String getRowTag();
    Code:
       0: aload_0
       1: getfield      #86                 // Field localRowTag:Ljava/lang/String;
       4: areturn

  public void setRowTag(java.lang.String);
    Code:
       0: aload_0
       1: aload_1
       2: ifnull        9
       5: iconst_1
       6: goto          10
       9: iconst_0
      10: putfield      #22                 // Field localRowTagTracker:Z
      13: aload_0
      14: aload_1
      15: putfield      #86                 // Field localRowTag:Ljava/lang/String;
      18: return

  public boolean isSourceNumPartsSpecified();
    Code:
       0: aload_0
       1: getfield      #23                 // Field localSourceNumPartsTracker:Z
       4: ireturn

  public int getSourceNumParts();
    Code:
       0: aload_0
       1: getfield      #87                 // Field localSourceNumParts:I
       4: ireturn

  public void setSourceNumParts(int);
    Code:
       0: aload_0
       1: iload_1
       2: ldc           #73                 // int -2147483648
       4: if_icmpeq     11
       7: iconst_1
       8: goto          12
      11: iconst_0
      12: putfield      #23                 // Field localSourceNumPartsTracker:Z
      15: aload_0
      16: iload_1
      17: putfield      #87                 // Field localSourceNumParts:I
      20: return

  public boolean isSourceDirectorySpecified();
    Code:
       0: aload_0
       1: getfield      #24                 // Field localSourceDirectoryTracker:Z
       4: ireturn

  public java.lang.String getSourceDirectory();
    Code:
       0: aload_0
       1: getfield      #88                 // Field localSourceDirectory:Ljava/lang/String;
       4: areturn

  public void setSourceDirectory(java.lang.String);
    Code:
       0: aload_0
       1: aload_1
       2: ifnull        9
       5: iconst_1
       6: goto          10
       9: iconst_0
      10: putfield      #24                 // Field localSourceDirectoryTracker:Z
      13: aload_0
      14: aload_1
      15: putfield      #88                 // Field localSourceDirectory:Ljava/lang/String;
      18: return

  public boolean isDestLogicalNameSpecified();
    Code:
       0: aload_0
       1: getfield      #25                 // Field localDestLogicalNameTracker:Z
       4: ireturn

  public java.lang.String getDestLogicalName();
    Code:
       0: aload_0
       1: getfield      #89                 // Field localDestLogicalName:Ljava/lang/String;
       4: areturn

  public void setDestLogicalName(java.lang.String);
    Code:
       0: aload_0
       1: aload_1
       2: ifnull        9
       5: iconst_1
       6: goto          10
       9: iconst_0
      10: putfield      #25                 // Field localDestLogicalNameTracker:Z
      13: aload_0
      14: aload_1
      15: putfield      #89                 // Field localDestLogicalName:Ljava/lang/String;
      18: return

  public boolean isDestGroupNameSpecified();
    Code:
       0: aload_0
       1: getfield      #26                 // Field localDestGroupNameTracker:Z
       4: ireturn

  public java.lang.String getDestGroupName();
    Code:
       0: aload_0
       1: getfield      #90                 // Field localDestGroupName:Ljava/lang/String;
       4: areturn

  public void setDestGroupName(java.lang.String);
    Code:
       0: aload_0
       1: aload_1
       2: ifnull        9
       5: iconst_1
       6: goto          10
       9: iconst_0
      10: putfield      #26                 // Field localDestGroupNameTracker:Z
      13: aload_0
      14: aload_1
      15: putfield      #90                 // Field localDestGroupName:Ljava/lang/String;
      18: return

  public boolean isDestDirectorySpecified();
    Code:
       0: aload_0
       1: getfield      #27                 // Field localDestDirectoryTracker:Z
       4: ireturn

  public java.lang.String getDestDirectory();
    Code:
       0: aload_0
       1: getfield      #91                 // Field localDestDirectory:Ljava/lang/String;
       4: areturn

  public void setDestDirectory(java.lang.String);
    Code:
       0: aload_0
       1: aload_1
       2: ifnull        9
       5: iconst_1
       6: goto          10
       9: iconst_0
      10: putfield      #27                 // Field localDestDirectoryTracker:Z
      13: aload_0
      14: aload_1
      15: putfield      #91                 // Field localDestDirectory:Ljava/lang/String;
      18: return

  public boolean isDestIPSpecified();
    Code:
       0: aload_0
       1: getfield      #28                 // Field localDestIPTracker:Z
       4: ireturn

  public java.lang.String getDestIP();
    Code:
       0: aload_0
       1: getfield      #92                 // Field localDestIP:Ljava/lang/String;
       4: areturn

  public void setDestIP(java.lang.String);
    Code:
       0: aload_0
       1: aload_1
       2: ifnull        9
       5: iconst_1
       6: goto          10
       9: iconst_0
      10: putfield      #28                 // Field localDestIPTracker:Z
      13: aload_0
      14: aload_1
      15: putfield      #92                 // Field localDestIP:Ljava/lang/String;
      18: return

  public boolean isDestFilePathSpecified();
    Code:
       0: aload_0
       1: getfield      #29                 // Field localDestFilePathTracker:Z
       4: ireturn

  public java.lang.String getDestFilePath();
    Code:
       0: aload_0
       1: getfield      #93                 // Field localDestFilePath:Ljava/lang/String;
       4: areturn

  public void setDestFilePath(java.lang.String);
    Code:
       0: aload_0
       1: aload_1
       2: ifnull        9
       5: iconst_1
       6: goto          10
       9: iconst_0
      10: putfield      #29                 // Field localDestFilePathTracker:Z
      13: aload_0
      14: aload_1
      15: putfield      #93                 // Field localDestFilePath:Ljava/lang/String;
      18: return

  public boolean isDestFormatSpecified();
    Code:
       0: aload_0
       1: getfield      #30                 // Field localDestFormatTracker:Z
       4: ireturn

  public int getDestFormat();
    Code:
       0: aload_0
       1: getfield      #94                 // Field localDestFormat:I
       4: ireturn

  public void setDestFormat(int);
    Code:
       0: aload_0
       1: iload_1
       2: ldc           #73                 // int -2147483648
       4: if_icmpeq     11
       7: iconst_1
       8: goto          12
      11: iconst_0
      12: putfield      #30                 // Field localDestFormatTracker:Z
      15: aload_0
      16: iload_1
      17: putfield      #94                 // Field localDestFormat:I
      20: return

  public boolean isDestNumPartsSpecified();
    Code:
       0: aload_0
       1: getfield      #31                 // Field localDestNumPartsTracker:Z
       4: ireturn

  public int getDestNumParts();
    Code:
       0: aload_0
       1: getfield      #95                 // Field localDestNumParts:I
       4: ireturn

  public void setDestNumParts(int);
    Code:
       0: aload_0
       1: iload_1
       2: ldc           #73                 // int -2147483648
       4: if_icmpeq     11
       7: iconst_1
       8: goto          12
      11: iconst_0
      12: putfield      #31                 // Field localDestNumPartsTracker:Z
      15: aload_0
      16: iload_1
      17: putfield      #95                 // Field localDestNumParts:I
      20: return

  public boolean isDestRecordSizeSpecified();
    Code:
       0: aload_0
       1: getfield      #32                 // Field localDestRecordSizeTracker:Z
       4: ireturn

  public int getDestRecordSize();
    Code:
       0: aload_0
       1: getfield      #96                 // Field localDestRecordSize:I
       4: ireturn

  public void setDestRecordSize(int);
    Code:
       0: aload_0
       1: iload_1
       2: ldc           #73                 // int -2147483648
       4: if_icmpeq     11
       7: iconst_1
       8: goto          12
      11: iconst_0
      12: putfield      #32                 // Field localDestRecordSizeTracker:Z
      15: aload_0
      16: iload_1
      17: putfield      #96                 // Field localDestRecordSize:I
      20: return

  public boolean isReplicateSpecified();
    Code:
       0: aload_0
       1: getfield      #33                 // Field localReplicateTracker:Z
       4: ireturn

  public boolean getReplicate();
    Code:
       0: aload_0
       1: getfield      #97                 // Field localReplicate:Z
       4: ireturn

  public void setReplicate(boolean);
    Code:
       0: aload_0
       1: iconst_1
       2: putfield      #33                 // Field localReplicateTracker:Z
       5: aload_0
       6: iload_1
       7: putfield      #97                 // Field localReplicate:Z
      10: return

  public boolean isOverwriteSpecified();
    Code:
       0: aload_0
       1: getfield      #34                 // Field localOverwriteTracker:Z
       4: ireturn

  public boolean getOverwrite();
    Code:
       0: aload_0
       1: getfield      #98                 // Field localOverwrite:Z
       4: ireturn

  public void setOverwrite(boolean);
    Code:
       0: aload_0
       1: iconst_1
       2: putfield      #34                 // Field localOverwriteTracker:Z
       5: aload_0
       6: iload_1
       7: putfield      #98                 // Field localOverwrite:Z
      10: return

  public boolean isCompressSpecified();
    Code:
       0: aload_0
       1: getfield      #35                 // Field localCompressTracker:Z
       4: ireturn

  public boolean getCompress();
    Code:
       0: aload_0
       1: getfield      #99                 // Field localCompress:Z
       4: ireturn

  public void setCompress(boolean);
    Code:
       0: aload_0
       1: iconst_1
       2: putfield      #35                 // Field localCompressTracker:Z
       5: aload_0
       6: iload_1
       7: putfield      #99                 // Field localCompress:Z
      10: return

  public boolean isSourceCsvSeparateSpecified();
    Code:
       0: aload_0
       1: getfield      #36                 // Field localSourceCsvSeparateTracker:Z
       4: ireturn

  public java.lang.String getSourceCsvSeparate();
    Code:
       0: aload_0
       1: getfield      #100                // Field localSourceCsvSeparate:Ljava/lang/String;
       4: areturn

  public void setSourceCsvSeparate(java.lang.String);
    Code:
       0: aload_0
       1: aload_1
       2: ifnull        9
       5: iconst_1
       6: goto          10
       9: iconst_0
      10: putfield      #36                 // Field localSourceCsvSeparateTracker:Z
      13: aload_0
      14: aload_1
      15: putfield      #100                // Field localSourceCsvSeparate:Ljava/lang/String;
      18: return

  public boolean isSourceCsvQuoteSpecified();
    Code:
       0: aload_0
       1: getfield      #37                 // Field localSourceCsvQuoteTracker:Z
       4: ireturn

  public java.lang.String getSourceCsvQuote();
    Code:
       0: aload_0
       1: getfield      #101                // Field localSourceCsvQuote:Ljava/lang/String;
       4: areturn

  public void setSourceCsvQuote(java.lang.String);
    Code:
       0: aload_0
       1: aload_1
       2: ifnull        9
       5: iconst_1
       6: goto          10
       9: iconst_0
      10: putfield      #37                 // Field localSourceCsvQuoteTracker:Z
      13: aload_0
      14: aload_1
      15: putfield      #101                // Field localSourceCsvQuote:Ljava/lang/String;
      18: return

  public boolean isSourceCsvTerminateSpecified();
    Code:
       0: aload_0
       1: getfield      #38                 // Field localSourceCsvTerminateTracker:Z
       4: ireturn

  public java.lang.String getSourceCsvTerminate();
    Code:
       0: aload_0
       1: getfield      #102                // Field localSourceCsvTerminate:Ljava/lang/String;
       4: areturn

  public void setSourceCsvTerminate(java.lang.String);
    Code:
       0: aload_0
       1: aload_1
       2: ifnull        9
       5: iconst_1
       6: goto          10
       9: iconst_0
      10: putfield      #38                 // Field localSourceCsvTerminateTracker:Z
      13: aload_0
      14: aload_1
      15: putfield      #102                // Field localSourceCsvTerminate:Ljava/lang/String;
      18: return

  public boolean isSourceCsvEscapeSpecified();
    Code:
       0: aload_0
       1: getfield      #39                 // Field localSourceCsvEscapeTracker:Z
       4: ireturn

  public java.lang.String getSourceCsvEscape();
    Code:
       0: aload_0
       1: getfield      #103                // Field localSourceCsvEscape:Ljava/lang/String;
       4: areturn

  public void setSourceCsvEscape(java.lang.String);
    Code:
       0: aload_0
       1: aload_1
       2: ifnull        9
       5: iconst_1
       6: goto          10
       9: iconst_0
      10: putfield      #39                 // Field localSourceCsvEscapeTracker:Z
      13: aload_0
      14: aload_1
      15: putfield      #103                // Field localSourceCsvEscape:Ljava/lang/String;
      18: return

  public boolean isTimeStartedSpecified();
    Code:
       0: aload_0
       1: getfield      #40                 // Field localTimeStartedTracker:Z
       4: ireturn

  public java.lang.String getTimeStarted();
    Code:
       0: aload_0
       1: getfield      #104                // Field localTimeStarted:Ljava/lang/String;
       4: areturn

  public void setTimeStarted(java.lang.String);
    Code:
       0: aload_0
       1: aload_1
       2: ifnull        9
       5: iconst_1
       6: goto          10
       9: iconst_0
      10: putfield      #40                 // Field localTimeStartedTracker:Z
      13: aload_0
      14: aload_1
      15: putfield      #104                // Field localTimeStarted:Ljava/lang/String;
      18: return

  public boolean isTimeStoppedSpecified();
    Code:
       0: aload_0
       1: getfield      #41                 // Field localTimeStoppedTracker:Z
       4: ireturn

  public java.lang.String getTimeStopped();
    Code:
       0: aload_0
       1: getfield      #105                // Field localTimeStopped:Ljava/lang/String;
       4: areturn

  public void setTimeStopped(java.lang.String);
    Code:
       0: aload_0
       1: aload_1
       2: ifnull        9
       5: iconst_1
       6: goto          10
       9: iconst_0
      10: putfield      #41                 // Field localTimeStoppedTracker:Z
      13: aload_0
      14: aload_1
      15: putfield      #105                // Field localTimeStopped:Ljava/lang/String;
      18: return

  public boolean isStateMessageSpecified();
    Code:
       0: aload_0
       1: getfield      #42                 // Field localStateMessageTracker:Z
       4: ireturn

  public java.lang.String getStateMessage();
    Code:
       0: aload_0
       1: getfield      #106                // Field localStateMessage:Ljava/lang/String;
       4: areturn

  public void setStateMessage(java.lang.String);
    Code:
       0: aload_0
       1: aload_1
       2: ifnull        9
       5: iconst_1
       6: goto          10
       9: iconst_0
      10: putfield      #42                 // Field localStateMessageTracker:Z
      13: aload_0
      14: aload_1
      15: putfield      #106                // Field localStateMessage:Ljava/lang/String;
      18: return

  public boolean isMonitorEventNameSpecified();
    Code:
       0: aload_0
       1: getfield      #43                 // Field localMonitorEventNameTracker:Z
       4: ireturn

  public java.lang.String getMonitorEventName();
    Code:
       0: aload_0
       1: getfield      #107                // Field localMonitorEventName:Ljava/lang/String;
       4: areturn

  public void setMonitorEventName(java.lang.String);
    Code:
       0: aload_0
       1: aload_1
       2: ifnull        9
       5: iconst_1
       6: goto          10
       9: iconst_0
      10: putfield      #43                 // Field localMonitorEventNameTracker:Z
      13: aload_0
      14: aload_1
      15: putfield      #107                // Field localMonitorEventName:Ljava/lang/String;
      18: return

  public boolean isMonitorSubSpecified();
    Code:
       0: aload_0
       1: getfield      #44                 // Field localMonitorSubTracker:Z
       4: ireturn

  public boolean getMonitorSub();
    Code:
       0: aload_0
       1: getfield      #108                // Field localMonitorSub:Z
       4: ireturn

  public void setMonitorSub(boolean);
    Code:
       0: aload_0
       1: iconst_1
       2: putfield      #44                 // Field localMonitorSubTracker:Z
       5: aload_0
       6: iload_1
       7: putfield      #108                // Field localMonitorSub:Z
      10: return

  public boolean isMonitorShotLimitSpecified();
    Code:
       0: aload_0
       1: getfield      #45                 // Field localMonitorShotLimitTracker:Z
       4: ireturn

  public int getMonitorShotLimit();
    Code:
       0: aload_0
       1: getfield      #109                // Field localMonitorShotLimit:I
       4: ireturn

  public void setMonitorShotLimit(int);
    Code:
       0: aload_0
       1: iload_1
       2: ldc           #73                 // int -2147483648
       4: if_icmpeq     11
       7: iconst_1
       8: goto          12
      11: iconst_0
      12: putfield      #45                 // Field localMonitorShotLimitTracker:Z
      15: aload_0
      16: iload_1
      17: putfield      #109                // Field localMonitorShotLimit:I
      20: return

  public boolean isSourceDiffKeyNameSpecified();
    Code:
       0: aload_0
       1: getfield      #46                 // Field localSourceDiffKeyNameTracker:Z
       4: ireturn

  public java.lang.String getSourceDiffKeyName();
    Code:
       0: aload_0
       1: getfield      #110                // Field localSourceDiffKeyName:Ljava/lang/String;
       4: areturn

  public void setSourceDiffKeyName(java.lang.String);
    Code:
       0: aload_0
       1: aload_1
       2: ifnull        9
       5: iconst_1
       6: goto          10
       9: iconst_0
      10: putfield      #46                 // Field localSourceDiffKeyNameTracker:Z
      13: aload_0
      14: aload_1
      15: putfield      #110                // Field localSourceDiffKeyName:Ljava/lang/String;
      18: return

  public boolean isDestDiffKeyNameSpecified();
    Code:
       0: aload_0
       1: getfield      #47                 // Field localDestDiffKeyNameTracker:Z
       4: ireturn

  public java.lang.String getDestDiffKeyName();
    Code:
       0: aload_0
       1: getfield      #111                // Field localDestDiffKeyName:Ljava/lang/String;
       4: areturn

  public void setDestDiffKeyName(java.lang.String);
    Code:
       0: aload_0
       1: aload_1
       2: ifnull        9
       5: iconst_1
       6: goto          10
       9: iconst_0
      10: putfield      #47                 // Field localDestDiffKeyNameTracker:Z
      13: aload_0
      14: aload_1
      15: putfield      #111                // Field localDestDiffKeyName:Ljava/lang/String;
      18: return

  public boolean isArchivedSpecified();
    Code:
       0: aload_0
       1: getfield      #51                 // Field localArchivedTracker:Z
       4: ireturn

  public boolean getArchived();
    Code:
       0: aload_0
       1: getfield      #50                 // Field localArchived:Z
       4: ireturn

  public void setArchived(boolean);
    Code:
       0: aload_0
       1: iconst_1
       2: putfield      #51                 // Field localArchivedTracker:Z
       5: aload_0
       6: iload_1
       7: putfield      #50                 // Field localArchived:Z
      10: return

  public boolean isEncryptSpecified();
    Code:
       0: aload_0
       1: getfield      #52                 // Field localEncryptTracker:Z
       4: ireturn

  public java.lang.String getEncrypt();
    Code:
       0: aload_0
       1: getfield      #112                // Field localEncrypt:Ljava/lang/String;
       4: areturn

  public void setEncrypt(java.lang.String);
    Code:
       0: aload_0
       1: aload_1
       2: ifnull        9
       5: iconst_1
       6: goto          10
       9: iconst_0
      10: putfield      #52                 // Field localEncryptTracker:Z
      13: aload_0
      14: aload_1
      15: putfield      #112                // Field localEncrypt:Ljava/lang/String;
      18: return

  public boolean isDecryptSpecified();
    Code:
       0: aload_0
       1: getfield      #53                 // Field localDecryptTracker:Z
       4: ireturn

  public java.lang.String getDecrypt();
    Code:
       0: aload_0
       1: getfield      #113                // Field localDecrypt:Ljava/lang/String;
       4: areturn

  public void setDecrypt(java.lang.String);
    Code:
       0: aload_0
       1: aload_1
       2: ifnull        9
       5: iconst_1
       6: goto          10
       9: iconst_0
      10: putfield      #53                 // Field localDecryptTracker:Z
      13: aload_0
      14: aload_1
      15: putfield      #113                // Field localDecrypt:Ljava/lang/String;
      18: return

  public boolean isFailIfNoSourceFileSpecified();
    Code:
       0: aload_0
       1: getfield      #55                 // Field localFailIfNoSourceFileTracker:Z
       4: ireturn

  public boolean getFailIfNoSourceFile();
    Code:
       0: aload_0
       1: getfield      #54                 // Field localFailIfNoSourceFile:Z
       4: ireturn

  public void setFailIfNoSourceFile(boolean);
    Code:
       0: aload_0
       1: iconst_1
       2: putfield      #55                 // Field localFailIfNoSourceFileTracker:Z
       5: aload_0
       6: iload_1
       7: putfield      #54                 // Field localFailIfNoSourceFile:Z
      10: return

  public boolean isRecordStructurePresentSpecified();
    Code:
       0: aload_0
       1: getfield      #57                 // Field localRecordStructurePresentTracker:Z
       4: ireturn

  public boolean getRecordStructurePresent();
    Code:
       0: aload_0
       1: getfield      #56                 // Field localRecordStructurePresent:Z
       4: ireturn

  public void setRecordStructurePresent(boolean);
    Code:
       0: aload_0
       1: iconst_1
       2: putfield      #57                 // Field localRecordStructurePresentTracker:Z
       5: aload_0
       6: iload_1
       7: putfield      #56                 // Field localRecordStructurePresent:Z
      10: return

  public boolean isQuotedTerminatorSpecified();
    Code:
       0: aload_0
       1: getfield      #60                 // Field localQuotedTerminatorTracker:Z
       4: ireturn

  public boolean getQuotedTerminator();
    Code:
       0: aload_0
       1: getfield      #59                 // Field localQuotedTerminator:Z
       4: ireturn

  public void setQuotedTerminator(boolean);
    Code:
       0: aload_0
       1: iconst_1
       2: putfield      #60                 // Field localQuotedTerminatorTracker:Z
       5: aload_0
       6: iload_1
       7: putfield      #59                 // Field localQuotedTerminator:Z
      10: return

  public boolean isPreserveCompressionSpecified();
    Code:
       0: aload_0
       1: getfield      #62                 // Field localPreserveCompressionTracker:Z
       4: ireturn

  public boolean getPreserveCompression();
    Code:
       0: aload_0
       1: getfield      #61                 // Field localPreserveCompression:Z
       4: ireturn

  public void setPreserveCompression(boolean);
    Code:
       0: aload_0
       1: iconst_1
       2: putfield      #62                 // Field localPreserveCompressionTracker:Z
       5: aload_0
       6: iload_1
       7: putfield      #61                 // Field localPreserveCompression:Z
      10: return

  public boolean isExpireDaysSpecified();
    Code:
       0: aload_0
       1: getfield      #63                 // Field localExpireDaysTracker:Z
       4: ireturn

  public int getExpireDays();
    Code:
       0: aload_0
       1: getfield      #114                // Field localExpireDays:I
       4: ireturn

  public void setExpireDays(int);
    Code:
       0: aload_0
       1: iload_1
       2: ldc           #73                 // int -2147483648
       4: if_icmpeq     11
       7: iconst_1
       8: goto          12
      11: iconst_0
      12: putfield      #63                 // Field localExpireDaysTracker:Z
      15: aload_0
      16: iload_1
      17: putfield      #114                // Field localExpireDays:I
      20: return

  public org.apache.axiom.om.OMElement getOMElement(javax.xml.namespace.QName, org.apache.axiom.om.OMFactory) throws org.apache.axis2.databinding.ADBException;
    Code:
       0: aload_2
       1: new           #115                // class org/apache/axis2/databinding/ADBDataSource
       4: dup
       5: aload_0
       6: aload_1
       7: invokespecial #116                // Method org/apache/axis2/databinding/ADBDataSource."<init>":(Lorg/apache/axis2/databinding/ADBBean;Ljavax/xml/namespace/QName;)V
      10: invokeinterface #117,  2          // InterfaceMethod org/apache/axiom/om/OMFactory.createOMElement:(Lorg/apache/axiom/om/OMDataSource;)Lorg/apache/axiom/om/OMSourcedElement;
      15: areturn

  public void serialize(javax.xml.namespace.QName, javax.xml.stream.XMLStreamWriter) throws javax.xml.stream.XMLStreamException, org.apache.axis2.databinding.ADBException;
    Code:
       0: aload_0
       1: aload_1
       2: aload_2
       3: iconst_0
       4: invokevirtual #118                // Method serialize:(Ljavax/xml/namespace/QName;Ljavax/xml/stream/XMLStreamWriter;Z)V
       7: return

  public void serialize(javax.xml.namespace.QName, javax.xml.stream.XMLStreamWriter, boolean) throws javax.xml.stream.XMLStreamException, org.apache.axis2.databinding.ADBException;
    Code:
       0: aconst_null
       1: astore        4
       3: aconst_null
       4: astore        5
       6: aload_1
       7: invokevirtual #119                // Method javax/xml/namespace/QName.getPrefix:()Ljava/lang/String;
      10: astore        4
      12: aload_1
      13: invokevirtual #120                // Method javax/xml/namespace/QName.getNamespaceURI:()Ljava/lang/String;
      16: astore        5
      18: aload_0
      19: aload         4
      21: aload         5
      23: aload_1
      24: invokevirtual #121                // Method javax/xml/namespace/QName.getLocalPart:()Ljava/lang/String;
      27: aload_2
      28: invokespecial #122                // Method writeStartElement:(Ljava/lang/String;Ljava/lang/String;Ljava/lang/String;Ljavax/xml/stream/XMLStreamWriter;)V
      31: iload_3
      32: ifeq          107
      35: aload_0
      36: aload_2
      37: ldc           #123                // String urn:hpccsystems:ws:filespray
      39: invokespecial #124                // Method registerPrefix:(Ljavax/xml/stream/XMLStreamWriter;Ljava/lang/String;)Ljava/lang/String;
      42: astore        6
      44: aload         6
      46: ifnull        94
      49: aload         6
      51: invokevirtual #125                // Method java/lang/String.trim:()Ljava/lang/String;
      54: invokevirtual #126                // Method java/lang/String.length:()I
      57: ifle          94
      60: aload_0
      61: ldc           #127                // String xsi
      63: ldc           #128                // String http://www.w3.org/2001/XMLSchema-instance
      65: ldc           #129                // String type
      67: new           #130                // class java/lang/StringBuilder
      70: dup
      71: invokespecial #131                // Method java/lang/StringBuilder."<init>":()V
      74: aload         6
      76: invokevirtual #132                // Method java/lang/StringBuilder.append:(Ljava/lang/String;)Ljava/lang/StringBuilder;
      79: ldc           #133                // String :DFUWorkunit
      81: invokevirtual #132                // Method java/lang/StringBuilder.append:(Ljava/lang/String;)Ljava/lang/StringBuilder;
      84: invokevirtual #134                // Method java/lang/StringBuilder.toString:()Ljava/lang/String;
      87: aload_2
      88: invokespecial #135                // Method writeAttribute:(Ljava/lang/String;Ljava/lang/String;Ljava/lang/String;Ljava/lang/String;Ljavax/xml/stream/XMLStreamWriter;)V
      91: goto          107
      94: aload_0
      95: ldc           #127                // String xsi
      97: ldc           #128                // String http://www.w3.org/2001/XMLSchema-instance
      99: ldc           #129                // String type
     101: ldc           #136                // String DFUWorkunit
     103: aload_2
     104: invokespecial #135                // Method writeAttribute:(Ljava/lang/String;Ljava/lang/String;Ljava/lang/String;Ljava/lang/String;Ljavax/xml/stream/XMLStreamWriter;)V
     107: aload_0
     108: getfield      #2                  // Field localIDTracker:Z
     111: ifeq          161
     114: ldc           #123                // String urn:hpccsystems:ws:filespray
     116: astore        5
     118: aload_0
     119: aconst_null
     120: aload         5
     122: ldc           #137                // String ID
     124: aload_2
     125: invokespecial #122                // Method writeStartElement:(Ljava/lang/String;Ljava/lang/String;Ljava/lang/String;Ljavax/xml/stream/XMLStreamWriter;)V
     128: aload_0
     129: getfield      #64                 // Field localID:Ljava/lang/String;
     132: ifnonnull     145
     135: new           #138                // class org/apache/axis2/databinding/ADBException
     138: dup
     139: ldc           #139                // String ID cannot be null!!
     141: invokespecial #140                // Method org/apache/axis2/databinding/ADBException."<init>":(Ljava/lang/String;)V
     144: athrow
     145: aload_2
     146: aload_0
     147: getfield      #64                 // Field localID:Ljava/lang/String;
     150: invokeinterface #141,  2          // InterfaceMethod javax/xml/stream/XMLStreamWriter.writeCharacters:(Ljava/lang/String;)V
     155: aload_2
     156: invokeinterface #142,  1          // InterfaceMethod javax/xml/stream/XMLStreamWriter.writeEndElement:()V
     161: aload_0
     162: getfield      #3                  // Field localDFUServerNameTracker:Z
     165: ifeq          215
     168: ldc           #123                // String urn:hpccsystems:ws:filespray
     170: astore        5
     172: aload_0
     173: aconst_null
     174: aload         5
     176: ldc           #143                // String DFUServerName
     178: aload_2
     179: invokespecial #122                // Method writeStartElement:(Ljava/lang/String;Ljava/lang/String;Ljava/lang/String;Ljavax/xml/stream/XMLStreamWriter;)V
     182: aload_0
     183: getfield      #65                 // Field localDFUServerName:Ljava/lang/String;
     186: ifnonnull     199
     189: new           #138                // class org/apache/axis2/databinding/ADBException
     192: dup
     193: ldc           #144                // String DFUServerName cannot be null!!
     195: invokespecial #140                // Method org/apache/axis2/databinding/ADBException."<init>":(Ljava/lang/String;)V
     198: athrow
     199: aload_2
     200: aload_0
     201: getfield      #65                 // Field localDFUServerName:Ljava/lang/String;
     204: invokeinterface #141,  2          // InterfaceMethod javax/xml/stream/XMLStreamWriter.writeCharacters:(Ljava/lang/String;)V
     209: aload_2
     210: invokeinterface #142,  1          // InterfaceMethod javax/xml/stream/XMLStreamWriter.writeEndElement:()V
     215: aload_0
     216: getfield      #4                  // Field localClusterNameTracker:Z
     219: ifeq          269
     222: ldc           #123                // String urn:hpccsystems:ws:filespray
     224: astore        5
     226: aload_0
     227: aconst_null
     228: aload         5
     230: ldc           #145                // String ClusterName
     232: aload_2
     233: invokespecial #122                // Method writeStartElement:(Ljava/lang/String;Ljava/lang/String;Ljava/lang/String;Ljavax/xml/stream/XMLStreamWriter;)V
     236: aload_0
     237: getfield      #66                 // Field localClusterName:Ljava/lang/String;
     240: ifnonnull     253
     243: new           #138                // class org/apache/axis2/databinding/ADBException
     246: dup
     247: ldc           #146                // String ClusterName cannot be null!!
     249: invokespecial #140                // Method org/apache/axis2/databinding/ADBException."<init>":(Ljava/lang/String;)V
     252: athrow
     253: aload_2
     254: aload_0
     255: getfield      #66                 // Field localClusterName:Ljava/lang/String;
     258: invokeinterface #141,  2          // InterfaceMethod javax/xml/stream/XMLStreamWriter.writeCharacters:(Ljava/lang/String;)V
     263: aload_2
     264: invokeinterface #142,  1          // InterfaceMethod javax/xml/stream/XMLStreamWriter.writeEndElement:()V
     269: aload_0
     270: getfield      #5                  // Field localJobNameTracker:Z
     273: ifeq          323
     276: ldc           #123                // String urn:hpccsystems:ws:filespray
     278: astore        5
     280: aload_0
     281: aconst_null
     282: aload         5
     284: ldc           #147                // String JobName
     286: aload_2
     287: invokespecial #122                // Method writeStartElement:(Ljava/lang/String;Ljava/lang/String;Ljava/lang/String;Ljavax/xml/stream/XMLStreamWriter;)V
     290: aload_0
     291: getfield      #67                 // Field localJobName:Ljava/lang/String;
     294: ifnonnull     307
     297: new           #138                // class org/apache/axis2/databinding/ADBException
     300: dup
     301: ldc           #148                // String JobName cannot be null!!
     303: invokespecial #140                // Method org/apache/axis2/databinding/ADBException."<init>":(Ljava/lang/String;)V
     306: athrow
     307: aload_2
     308: aload_0
     309: getfield      #67                 // Field localJobName:Ljava/lang/String;
     312: invokeinterface #141,  2          // InterfaceMethod javax/xml/stream/XMLStreamWriter.writeCharacters:(Ljava/lang/String;)V
     317: aload_2
     318: invokeinterface #142,  1          // InterfaceMethod javax/xml/stream/XMLStreamWriter.writeEndElement:()V
     323: aload_0
     324: getfield      #6                  // Field localQueueTracker:Z
     327: ifeq          377
     330: ldc           #123                // String urn:hpccsystems:ws:filespray
     332: astore        5
     334: aload_0
     335: aconst_null
     336: aload         5
     338: ldc           #149                // String Queue
     340: aload_2
     341: invokespecial #122                // Method writeStartElement:(Ljava/lang/String;Ljava/lang/String;Ljava/lang/String;Ljavax/xml/stream/XMLStreamWriter;)V
     344: aload_0
     345: getfield      #68                 // Field localQueue:Ljava/lang/String;
     348: ifnonnull     361
     351: new           #138                // class org/apache/axis2/databinding/ADBException
     354: dup
     355: ldc           #150                // String Queue cannot be null!!
     357: invokespecial #140                // Method org/apache/axis2/databinding/ADBException."<init>":(Ljava/lang/String;)V
     360: athrow
     361: aload_2
     362: aload_0
     363: getfield      #68                 // Field localQueue:Ljava/lang/String;
     366: invokeinterface #141,  2          // InterfaceMethod javax/xml/stream/XMLStreamWriter.writeCharacters:(Ljava/lang/String;)V
     371: aload_2
     372: invokeinterface #142,  1          // InterfaceMethod javax/xml/stream/XMLStreamWriter.writeEndElement:()V
     377: aload_0
     378: getfield      #7                  // Field localUserTracker:Z
     381: ifeq          431
     384: ldc           #123                // String urn:hpccsystems:ws:filespray
     386: astore        5
     388: aload_0
     389: aconst_null
     390: aload         5
     392: ldc           #151                // String User
     394: aload_2
     395: invokespecial #122                // Method writeStartElement:(Ljava/lang/String;Ljava/lang/String;Ljava/lang/String;Ljavax/xml/stream/XMLStreamWriter;)V
     398: aload_0
     399: getfield      #69                 // Field localUser:Ljava/lang/String;
     402: ifnonnull     415
     405: new           #138                // class org/apache/axis2/databinding/ADBException
     408: dup
     409: ldc           #152                // String User cannot be null!!
     411: invokespecial #140                // Method org/apache/axis2/databinding/ADBException."<init>":(Ljava/lang/String;)V
     414: athrow
     415: aload_2
     416: aload_0
     417: getfield      #69                 // Field localUser:Ljava/lang/String;
     420: invokeinterface #141,  2          // InterfaceMethod javax/xml/stream/XMLStreamWriter.writeCharacters:(Ljava/lang/String;)V
     425: aload_2
     426: invokeinterface #142,  1          // InterfaceMethod javax/xml/stream/XMLStreamWriter.writeEndElement:()V
     431: aload_0
     432: getfield      #8                  // Field localIsProtectedTracker:Z
     435: ifeq          471
     438: ldc           #123                // String urn:hpccsystems:ws:filespray
     440: astore        5
     442: aload_0
     443: aconst_null
     444: aload         5
     446: ldc           #153                // String isProtected
     448: aload_2
     449: invokespecial #122                // Method writeStartElement:(Ljava/lang/String;Ljava/lang/String;Ljava/lang/String;Ljavax/xml/stream/XMLStreamWriter;)V
     452: aload_2
     453: aload_0
     454: getfield      #70                 // Field localIsProtected:Z
     457: invokestatic  #154                // Method org/apache/axis2/databinding/utils/ConverterUtil.convertToString:(Z)Ljava/lang/String;
     460: invokeinterface #141,  2          // InterfaceMethod javax/xml/stream/XMLStreamWriter.writeCharacters:(Ljava/lang/String;)V
     465: aload_2
     466: invokeinterface #142,  1          // InterfaceMethod javax/xml/stream/XMLStreamWriter.writeEndElement:()V
     471: aload_0
     472: getfield      #9                  // Field localCommandTracker:Z
     475: ifeq          530
     478: ldc           #123                // String urn:hpccsystems:ws:filespray
     480: astore        5
     482: aload_0
     483: aconst_null
     484: aload         5
     486: ldc           #155                // String Command
     488: aload_2
     489: invokespecial #122                // Method writeStartElement:(Ljava/lang/String;Ljava/lang/String;Ljava/lang/String;Ljavax/xml/stream/XMLStreamWriter;)V
     492: aload_0
     493: getfield      #71                 // Field localCommand:I
     496: ldc           #73                 // int -2147483648
     498: if_icmpne     511
     501: new           #138                // class org/apache/axis2/databinding/ADBException
     504: dup
     505: ldc           #156                // String Command cannot be null!!
     507: invokespecial #140                // Method org/apache/axis2/databinding/ADBException."<init>":(Ljava/lang/String;)V
     510: athrow
     511: aload_2
     512: aload_0
     513: getfield      #71                 // Field localCommand:I
     516: invokestatic  #157                // Method org/apache/axis2/databinding/utils/ConverterUtil.convertToString:(I)Ljava/lang/String;
     519: invokeinterface #141,  2          // InterfaceMethod javax/xml/stream/XMLStreamWriter.writeCharacters:(Ljava/lang/String;)V
     524: aload_2
     525: invokeinterface #142,  1          // InterfaceMethod javax/xml/stream/XMLStreamWriter.writeEndElement:()V
     530: aload_0
     531: getfield      #10                 // Field localCommandMessageTracker:Z
     534: ifeq          584
     537: ldc           #123                // String urn:hpccsystems:ws:filespray
     539: astore        5
     541: aload_0
     542: aconst_null
     543: aload         5
     545: ldc           #158                // String CommandMessage
     547: aload_2
     548: invokespecial #122                // Method writeStartElement:(Ljava/lang/String;Ljava/lang/String;Ljava/lang/String;Ljavax/xml/stream/XMLStreamWriter;)V
     551: aload_0
     552: getfield      #74                 // Field localCommandMessage:Ljava/lang/String;
     555: ifnonnull     568
     558: new           #138                // class org/apache/axis2/databinding/ADBException
     561: dup
     562: ldc           #159                // String CommandMessage cannot be null!!
     564: invokespecial #140                // Method org/apache/axis2/databinding/ADBException."<init>":(Ljava/lang/String;)V
     567: athrow
     568: aload_2
     569: aload_0
     570: getfield      #74                 // Field localCommandMessage:Ljava/lang/String;
     573: invokeinterface #141,  2          // InterfaceMethod javax/xml/stream/XMLStreamWriter.writeCharacters:(Ljava/lang/String;)V
     578: aload_2
     579: invokeinterface #142,  1          // InterfaceMethod javax/xml/stream/XMLStreamWriter.writeEndElement:()V
     584: aload_0
     585: getfield      #11                 // Field localPercentDoneTracker:Z
     588: ifeq          643
     591: ldc           #123                // String urn:hpccsystems:ws:filespray
     593: astore        5
     595: aload_0
     596: aconst_null
     597: aload         5
     599: ldc           #160                // String PercentDone
     601: aload_2
     602: invokespecial #122                // Method writeStartElement:(Ljava/lang/String;Ljava/lang/String;Ljava/lang/String;Ljavax/xml/stream/XMLStreamWriter;)V
     605: aload_0
     606: getfield      #75                 // Field localPercentDone:I
     609: ldc           #73                 // int -2147483648
     611: if_icmpne     624
     614: new           #138                // class org/apache/axis2/databinding/ADBException
     617: dup
     618: ldc           #161                // String PercentDone cannot be null!!
     620: invokespecial #140                // Method org/apache/axis2/databinding/ADBException."<init>":(Ljava/lang/String;)V
     623: athrow
     624: aload_2
     625: aload_0
     626: getfield      #75                 // Field localPercentDone:I
     629: invokestatic  #157                // Method org/apache/axis2/databinding/utils/ConverterUtil.convertToString:(I)Ljava/lang/String;
     632: invokeinterface #141,  2          // InterfaceMethod javax/xml/stream/XMLStreamWriter.writeCharacters:(Ljava/lang/String;)V
     637: aload_2
     638: invokeinterface #142,  1          // InterfaceMethod javax/xml/stream/XMLStreamWriter.writeEndElement:()V
     643: aload_0
     644: getfield      #12                 // Field localSecsLeftTracker:Z
     647: ifeq          702
     650: ldc           #123                // String urn:hpccsystems:ws:filespray
     652: astore        5
     654: aload_0
     655: aconst_null
     656: aload         5
     658: ldc           #162                // String SecsLeft
     660: aload_2
     661: invokespecial #122                // Method writeStartElement:(Ljava/lang/String;Ljava/lang/String;Ljava/lang/String;Ljavax/xml/stream/XMLStreamWriter;)V
     664: aload_0
     665: getfield      #76                 // Field localSecsLeft:I
     668: ldc           #73                 // int -2147483648
     670: if_icmpne     683
     673: new           #138                // class org/apache/axis2/databinding/ADBException
     676: dup
     677: ldc           #163                // String SecsLeft cannot be null!!
     679: invokespecial #140                // Method org/apache/axis2/databinding/ADBException."<init>":(Ljava/lang/String;)V
     682: athrow
     683: aload_2
     684: aload_0
     685: getfield      #76                 // Field localSecsLeft:I
     688: invokestatic  #157                // Method org/apache/axis2/databinding/utils/ConverterUtil.convertToString:(I)Ljava/lang/String;
     691: invokeinterface #141,  2          // InterfaceMethod javax/xml/stream/XMLStreamWriter.writeCharacters:(Ljava/lang/String;)V
     696: aload_2
     697: invokeinterface #142,  1          // InterfaceMethod javax/xml/stream/XMLStreamWriter.writeEndElement:()V
     702: aload_0
     703: getfield      #13                 // Field localProgressMessageTracker:Z
     706: ifeq          756
     709: ldc           #123                // String urn:hpccsystems:ws:filespray
     711: astore        5
     713: aload_0
     714: aconst_null
     715: aload         5
     717: ldc           #164                // String ProgressMessage
     719: aload_2
     720: invokespecial #122                // Method writeStartElement:(Ljava/lang/String;Ljava/lang/String;Ljava/lang/String;Ljavax/xml/stream/XMLStreamWriter;)V
     723: aload_0
     724: getfield      #77                 // Field localProgressMessage:Ljava/lang/String;
     727: ifnonnull     740
     730: new           #138                // class org/apache/axis2/databinding/ADBException
     733: dup
     734: ldc           #165                // String ProgressMessage cannot be null!!
     736: invokespecial #140                // Method org/apache/axis2/databinding/ADBException."<init>":(Ljava/lang/String;)V
     739: athrow
     740: aload_2
     741: aload_0
     742: getfield      #77                 // Field localProgressMessage:Ljava/lang/String;
     745: invokeinterface #141,  2          // InterfaceMethod javax/xml/stream/XMLStreamWriter.writeCharacters:(Ljava/lang/String;)V
     750: aload_2
     751: invokeinterface #142,  1          // InterfaceMethod javax/xml/stream/XMLStreamWriter.writeEndElement:()V
     756: aload_0
     757: getfield      #14                 // Field localSummaryMessageTracker:Z
     760: ifeq          810
     763: ldc           #123                // String urn:hpccsystems:ws:filespray
     765: astore        5
     767: aload_0
     768: aconst_null
     769: aload         5
     771: ldc           #166                // String SummaryMessage
     773: aload_2
     774: invokespecial #122                // Method writeStartElement:(Ljava/lang/String;Ljava/lang/String;Ljava/lang/String;Ljavax/xml/stream/XMLStreamWriter;)V
     777: aload_0
     778: getfield      #78                 // Field localSummaryMessage:Ljava/lang/String;
     781: ifnonnull     794
     784: new           #138                // class org/apache/axis2/databinding/ADBException
     787: dup
     788: ldc           #167                // String SummaryMessage cannot be null!!
     790: invokespecial #140                // Method org/apache/axis2/databinding/ADBException."<init>":(Ljava/lang/String;)V
     793: athrow
     794: aload_2
     795: aload_0
     796: getfield      #78                 // Field localSummaryMessage:Ljava/lang/String;
     799: invokeinterface #141,  2          // InterfaceMethod javax/xml/stream/XMLStreamWriter.writeCharacters:(Ljava/lang/String;)V
     804: aload_2
     805: invokeinterface #142,  1          // InterfaceMethod javax/xml/stream/XMLStreamWriter.writeEndElement:()V
     810: aload_0
     811: getfield      #15                 // Field localStateTracker:Z
     814: ifeq          869
     817: ldc           #123                // String urn:hpccsystems:ws:filespray
     819: astore        5
     821: aload_0
     822: aconst_null
     823: aload         5
     825: ldc           #168                // String State
     827: aload_2
     828: invokespecial #122                // Method writeStartElement:(Ljava/lang/String;Ljava/lang/String;Ljava/lang/String;Ljavax/xml/stream/XMLStreamWriter;)V
     831: aload_0
     832: getfield      #79                 // Field localState:I
     835: ldc           #73                 // int -2147483648
     837: if_icmpne     850
     840: new           #138                // class org/apache/axis2/databinding/ADBException
     843: dup
     844: ldc           #169                // String State cannot be null!!
     846: invokespecial #140                // Method org/apache/axis2/databinding/ADBException."<init>":(Ljava/lang/String;)V
     849: athrow
     850: aload_2
     851: aload_0
     852: getfield      #79                 // Field localState:I
     855: invokestatic  #157                // Method org/apache/axis2/databinding/utils/ConverterUtil.convertToString:(I)Ljava/lang/String;
     858: invokeinterface #141,  2          // InterfaceMethod javax/xml/stream/XMLStreamWriter.writeCharacters:(Ljava/lang/String;)V
     863: aload_2
     864: invokeinterface #142,  1          // InterfaceMethod javax/xml/stream/XMLStreamWriter.writeEndElement:()V
     869: aload_0
     870: getfield      #16                 // Field localSourceLogicalNameTracker:Z
     873: ifeq          923
     876: ldc           #123                // String urn:hpccsystems:ws:filespray
     878: astore        5
     880: aload_0
     881: aconst_null
     882: aload         5
     884: ldc           #170                // String SourceLogicalName
     886: aload_2
     887: invokespecial #122                // Method writeStartElement:(Ljava/lang/String;Ljava/lang/String;Ljava/lang/String;Ljavax/xml/stream/XMLStreamWriter;)V
     890: aload_0
     891: getfield      #80                 // Field localSourceLogicalName:Ljava/lang/String;
     894: ifnonnull     907
     897: new           #138                // class org/apache/axis2/databinding/ADBException
     900: dup
     901: ldc           #171                // String SourceLogicalName cannot be null!!
     903: invokespecial #140                // Method org/apache/axis2/databinding/ADBException."<init>":(Ljava/lang/String;)V
     906: athrow
     907: aload_2
     908: aload_0
     909: getfield      #80                 // Field localSourceLogicalName:Ljava/lang/String;
     912: invokeinterface #141,  2          // InterfaceMethod javax/xml/stream/XMLStreamWriter.writeCharacters:(Ljava/lang/String;)V
     917: aload_2
     918: invokeinterface #142,  1          // InterfaceMethod javax/xml/stream/XMLStreamWriter.writeEndElement:()V
     923: aload_0
     924: getfield      #17                 // Field localSourceIPTracker:Z
     927: ifeq          977
     930: ldc           #123                // String urn:hpccsystems:ws:filespray
     932: astore        5
     934: aload_0
     935: aconst_null
     936: aload         5
     938: ldc           #172                // String SourceIP
     940: aload_2
     941: invokespecial #122                // Method writeStartElement:(Ljava/lang/String;Ljava/lang/String;Ljava/lang/String;Ljavax/xml/stream/XMLStreamWriter;)V
     944: aload_0
     945: getfield      #81                 // Field localSourceIP:Ljava/lang/String;
     948: ifnonnull     961
     951: new           #138                // class org/apache/axis2/databinding/ADBException
     954: dup
     955: ldc           #173                // String SourceIP cannot be null!!
     957: invokespecial #140                // Method org/apache/axis2/databinding/ADBException."<init>":(Ljava/lang/String;)V
     960: athrow
     961: aload_2
     962: aload_0
     963: getfield      #81                 // Field localSourceIP:Ljava/lang/String;
     966: invokeinterface #141,  2          // InterfaceMethod javax/xml/stream/XMLStreamWriter.writeCharacters:(Ljava/lang/String;)V
     971: aload_2
     972: invokeinterface #142,  1          // InterfaceMethod javax/xml/stream/XMLStreamWriter.writeEndElement:()V
     977: aload_0
     978: getfield      #18                 // Field localSourceFilePathTracker:Z
     981: ifeq          1031
     984: ldc           #123                // String urn:hpccsystems:ws:filespray
     986: astore        5
     988: aload_0
     989: aconst_null
     990: aload         5
     992: ldc           #174                // String SourceFilePath
     994: aload_2
     995: invokespecial #122                // Method writeStartElement:(Ljava/lang/String;Ljava/lang/String;Ljava/lang/String;Ljavax/xml/stream/XMLStreamWriter;)V
     998: aload_0
     999: getfield      #82                 // Field localSourceFilePath:Ljava/lang/String;
    1002: ifnonnull     1015
    1005: new           #138                // class org/apache/axis2/databinding/ADBException
    1008: dup
    1009: ldc           #175                // String SourceFilePath cannot be null!!
    1011: invokespecial #140                // Method org/apache/axis2/databinding/ADBException."<init>":(Ljava/lang/String;)V
    1014: athrow
    1015: aload_2
    1016: aload_0
    1017: getfield      #82                 // Field localSourceFilePath:Ljava/lang/String;
    1020: invokeinterface #141,  2          // InterfaceMethod javax/xml/stream/XMLStreamWriter.writeCharacters:(Ljava/lang/String;)V
    1025: aload_2
    1026: invokeinterface #142,  1          // InterfaceMethod javax/xml/stream/XMLStreamWriter.writeEndElement:()V
    1031: aload_0
    1032: getfield      #19                 // Field localSourceDaliTracker:Z
    1035: ifeq          1085
    1038: ldc           #123                // String urn:hpccsystems:ws:filespray
    1040: astore        5
    1042: aload_0
    1043: aconst_null
    1044: aload         5
    1046: ldc           #176                // String SourceDali
    1048: aload_2
    1049: invokespecial #122                // Method writeStartElement:(Ljava/lang/String;Ljava/lang/String;Ljava/lang/String;Ljavax/xml/stream/XMLStreamWriter;)V
    1052: aload_0
    1053: getfield      #83                 // Field localSourceDali:Ljava/lang/String;
    1056: ifnonnull     1069
    1059: new           #138                // class org/apache/axis2/databinding/ADBException
    1062: dup
    1063: ldc           #177                // String SourceDali cannot be null!!
    1065: invokespecial #140                // Method org/apache/axis2/databinding/ADBException."<init>":(Ljava/lang/String;)V
    1068: athrow
    1069: aload_2
    1070: aload_0
    1071: getfield      #83                 // Field localSourceDali:Ljava/lang/String;
    1074: invokeinterface #141,  2          // InterfaceMethod javax/xml/stream/XMLStreamWriter.writeCharacters:(Ljava/lang/String;)V
    1079: aload_2
    1080: invokeinterface #142,  1          // InterfaceMethod javax/xml/stream/XMLStreamWriter.writeEndElement:()V
    1085: aload_0
    1086: getfield      #20                 // Field localSourceRecordSizeTracker:Z
    1089: ifeq          1144
    1092: ldc           #123                // String urn:hpccsystems:ws:filespray
    1094: astore        5
    1096: aload_0
    1097: aconst_null
    1098: aload         5
    1100: ldc           #178                // String SourceRecordSize
    1102: aload_2
    1103: invokespecial #122                // Method writeStartElement:(Ljava/lang/String;Ljava/lang/String;Ljava/lang/String;Ljavax/xml/stream/XMLStreamWriter;)V
    1106: aload_0
    1107: getfield      #84                 // Field localSourceRecordSize:I
    1110: ldc           #73                 // int -2147483648
    1112: if_icmpne     1125
    1115: new           #138                // class org/apache/axis2/databinding/ADBException
    1118: dup
    1119: ldc           #179                // String SourceRecordSize cannot be null!!
    1121: invokespecial #140                // Method org/apache/axis2/databinding/ADBException."<init>":(Ljava/lang/String;)V
    1124: athrow
    1125: aload_2
    1126: aload_0
    1127: getfield      #84                 // Field localSourceRecordSize:I
    1130: invokestatic  #157                // Method org/apache/axis2/databinding/utils/ConverterUtil.convertToString:(I)Ljava/lang/String;
    1133: invokeinterface #141,  2          // InterfaceMethod javax/xml/stream/XMLStreamWriter.writeCharacters:(Ljava/lang/String;)V
    1138: aload_2
    1139: invokeinterface #142,  1          // InterfaceMethod javax/xml/stream/XMLStreamWriter.writeEndElement:()V
    1144: aload_0
    1145: getfield      #21                 // Field localSourceFormatTracker:Z
    1148: ifeq          1203
    1151: ldc           #123                // String urn:hpccsystems:ws:filespray
    1153: astore        5
    1155: aload_0
    1156: aconst_null
    1157: aload         5
    1159: ldc           #180                // String SourceFormat
    1161: aload_2
    1162: invokespecial #122                // Method writeStartElement:(Ljava/lang/String;Ljava/lang/String;Ljava/lang/String;Ljavax/xml/stream/XMLStreamWriter;)V
    1165: aload_0
    1166: getfield      #85                 // Field localSourceFormat:I
    1169: ldc           #73                 // int -2147483648
    1171: if_icmpne     1184
    1174: new           #138                // class org/apache/axis2/databinding/ADBException
    1177: dup
    1178: ldc           #181                // String SourceFormat cannot be null!!
    1180: invokespecial #140                // Method org/apache/axis2/databinding/ADBException."<init>":(Ljava/lang/String;)V
    1183: athrow
    1184: aload_2
    1185: aload_0
    1186: getfield      #85                 // Field localSourceFormat:I
    1189: invokestatic  #157                // Method org/apache/axis2/databinding/utils/ConverterUtil.convertToString:(I)Ljava/lang/String;
    1192: invokeinterface #141,  2          // InterfaceMethod javax/xml/stream/XMLStreamWriter.writeCharacters:(Ljava/lang/String;)V
    1197: aload_2
    1198: invokeinterface #142,  1          // InterfaceMethod javax/xml/stream/XMLStreamWriter.writeEndElement:()V
    1203: aload_0
    1204: getfield      #22                 // Field localRowTagTracker:Z
    1207: ifeq          1257
    1210: ldc           #123                // String urn:hpccsystems:ws:filespray
    1212: astore        5
    1214: aload_0
    1215: aconst_null
    1216: aload         5
    1218: ldc           #182                // String RowTag
    1220: aload_2
    1221: invokespecial #122                // Method writeStartElement:(Ljava/lang/String;Ljava/lang/String;Ljava/lang/String;Ljavax/xml/stream/XMLStreamWriter;)V
    1224: aload_0
    1225: getfield      #86                 // Field localRowTag:Ljava/lang/String;
    1228: ifnonnull     1241
    1231: new           #138                // class org/apache/axis2/databinding/ADBException
    1234: dup
    1235: ldc           #183                // String RowTag cannot be null!!
    1237: invokespecial #140                // Method org/apache/axis2/databinding/ADBException."<init>":(Ljava/lang/String;)V
    1240: athrow
    1241: aload_2
    1242: aload_0
    1243: getfield      #86                 // Field localRowTag:Ljava/lang/String;
    1246: invokeinterface #141,  2          // InterfaceMethod javax/xml/stream/XMLStreamWriter.writeCharacters:(Ljava/lang/String;)V
    1251: aload_2
    1252: invokeinterface #142,  1          // InterfaceMethod javax/xml/stream/XMLStreamWriter.writeEndElement:()V
    1257: aload_0
    1258: getfield      #23                 // Field localSourceNumPartsTracker:Z
    1261: ifeq          1316
    1264: ldc           #123                // String urn:hpccsystems:ws:filespray
    1266: astore        5
    1268: aload_0
    1269: aconst_null
    1270: aload         5
    1272: ldc           #184                // String SourceNumParts
    1274: aload_2
    1275: invokespecial #122                // Method writeStartElement:(Ljava/lang/String;Ljava/lang/String;Ljava/lang/String;Ljavax/xml/stream/XMLStreamWriter;)V
    1278: aload_0
    1279: getfield      #87                 // Field localSourceNumParts:I
    1282: ldc           #73                 // int -2147483648
    1284: if_icmpne     1297
    1287: new           #138                // class org/apache/axis2/databinding/ADBException
    1290: dup
    1291: ldc           #185                // String SourceNumParts cannot be null!!
    1293: invokespecial #140                // Method org/apache/axis2/databinding/ADBException."<init>":(Ljava/lang/String;)V
    1296: athrow
    1297: aload_2
    1298: aload_0
    1299: getfield      #87                 // Field localSourceNumParts:I
    1302: invokestatic  #157                // Method org/apache/axis2/databinding/utils/ConverterUtil.convertToString:(I)Ljava/lang/String;
    1305: invokeinterface #141,  2          // InterfaceMethod javax/xml/stream/XMLStreamWriter.writeCharacters:(Ljava/lang/String;)V
    1310: aload_2
    1311: invokeinterface #142,  1          // InterfaceMethod javax/xml/stream/XMLStreamWriter.writeEndElement:()V
    1316: aload_0
    1317: getfield      #24                 // Field localSourceDirectoryTracker:Z
    1320: ifeq          1370
    1323: ldc           #123                // String urn:hpccsystems:ws:filespray
    1325: astore        5
    1327: aload_0
    1328: aconst_null
    1329: aload         5
    1331: ldc           #186                // String SourceDirectory
    1333: aload_2
    1334: invokespecial #122                // Method writeStartElement:(Ljava/lang/String;Ljava/lang/String;Ljava/lang/String;Ljavax/xml/stream/XMLStreamWriter;)V
    1337: aload_0
    1338: getfield      #88                 // Field localSourceDirectory:Ljava/lang/String;
    1341: ifnonnull     1354
    1344: new           #138                // class org/apache/axis2/databinding/ADBException
    1347: dup
    1348: ldc           #187                // String SourceDirectory cannot be null!!
    1350: invokespecial #140                // Method org/apache/axis2/databinding/ADBException."<init>":(Ljava/lang/String;)V
    1353: athrow
    1354: aload_2
    1355: aload_0
    1356: getfield      #88                 // Field localSourceDirectory:Ljava/lang/String;
    1359: invokeinterface #141,  2          // InterfaceMethod javax/xml/stream/XMLStreamWriter.writeCharacters:(Ljava/lang/String;)V
    1364: aload_2
    1365: invokeinterface #142,  1          // InterfaceMethod javax/xml/stream/XMLStreamWriter.writeEndElement:()V
    1370: aload_0
    1371: getfield      #25                 // Field localDestLogicalNameTracker:Z
    1374: ifeq          1424
    1377: ldc           #123                // String urn:hpccsystems:ws:filespray
    1379: astore        5
    1381: aload_0
    1382: aconst_null
    1383: aload         5
    1385: ldc           #188                // String DestLogicalName
    1387: aload_2
    1388: invokespecial #122                // Method writeStartElement:(Ljava/lang/String;Ljava/lang/String;Ljava/lang/String;Ljavax/xml/stream/XMLStreamWriter;)V
    1391: aload_0
    1392: getfield      #89                 // Field localDestLogicalName:Ljava/lang/String;
    1395: ifnonnull     1408
    1398: new           #138                // class org/apache/axis2/databinding/ADBException
    1401: dup
    1402: ldc           #189                // String DestLogicalName cannot be null!!
    1404: invokespecial #140                // Method org/apache/axis2/databinding/ADBException."<init>":(Ljava/lang/String;)V
    1407: athrow
    1408: aload_2
    1409: aload_0
    1410: getfield      #89                 // Field localDestLogicalName:Ljava/lang/String;
    1413: invokeinterface #141,  2          // InterfaceMethod javax/xml/stream/XMLStreamWriter.writeCharacters:(Ljava/lang/String;)V
    1418: aload_2
    1419: invokeinterface #142,  1          // InterfaceMethod javax/xml/stream/XMLStreamWriter.writeEndElement:()V
    1424: aload_0
    1425: getfield      #26                 // Field localDestGroupNameTracker:Z
    1428: ifeq          1478
    1431: ldc           #123                // String urn:hpccsystems:ws:filespray
    1433: astore        5
    1435: aload_0
    1436: aconst_null
    1437: aload         5
    1439: ldc           #190                // String DestGroupName
    1441: aload_2
    1442: invokespecial #122                // Method writeStartElement:(Ljava/lang/String;Ljava/lang/String;Ljava/lang/String;Ljavax/xml/stream/XMLStreamWriter;)V
    1445: aload_0
    1446: getfield      #90                 // Field localDestGroupName:Ljava/lang/String;
    1449: ifnonnull     1462
    1452: new           #138                // class org/apache/axis2/databinding/ADBException
    1455: dup
    1456: ldc           #191                // String DestGroupName cannot be null!!
    1458: invokespecial #140                // Method org/apache/axis2/databinding/ADBException."<init>":(Ljava/lang/String;)V
    1461: athrow
    1462: aload_2
    1463: aload_0
    1464: getfield      #90                 // Field localDestGroupName:Ljava/lang/String;
    1467: invokeinterface #141,  2          // InterfaceMethod javax/xml/stream/XMLStreamWriter.writeCharacters:(Ljava/lang/String;)V
    1472: aload_2
    1473: invokeinterface #142,  1          // InterfaceMethod javax/xml/stream/XMLStreamWriter.writeEndElement:()V
    1478: aload_0
    1479: getfield      #27                 // Field localDestDirectoryTracker:Z
    1482: ifeq          1532
    1485: ldc           #123                // String urn:hpccsystems:ws:filespray
    1487: astore        5
    1489: aload_0
    1490: aconst_null
    1491: aload         5
    1493: ldc           #192                // String DestDirectory
    1495: aload_2
    1496: invokespecial #122                // Method writeStartElement:(Ljava/lang/String;Ljava/lang/String;Ljava/lang/String;Ljavax/xml/stream/XMLStreamWriter;)V
    1499: aload_0
    1500: getfield      #91                 // Field localDestDirectory:Ljava/lang/String;
    1503: ifnonnull     1516
    1506: new           #138                // class org/apache/axis2/databinding/ADBException
    1509: dup
    1510: ldc           #193                // String DestDirectory cannot be null!!
    1512: invokespecial #140                // Method org/apache/axis2/databinding/ADBException."<init>":(Ljava/lang/String;)V
    1515: athrow
    1516: aload_2
    1517: aload_0
    1518: getfield      #91                 // Field localDestDirectory:Ljava/lang/String;
    1521: invokeinterface #141,  2          // InterfaceMethod javax/xml/stream/XMLStreamWriter.writeCharacters:(Ljava/lang/String;)V
    1526: aload_2
    1527: invokeinterface #142,  1          // InterfaceMethod javax/xml/stream/XMLStreamWriter.writeEndElement:()V
    1532: aload_0
    1533: getfield      #28                 // Field localDestIPTracker:Z
    1536: ifeq          1586
    1539: ldc           #123                // String urn:hpccsystems:ws:filespray
    1541: astore        5
    1543: aload_0
    1544: aconst_null
    1545: aload         5
    1547: ldc           #194                // String DestIP
    1549: aload_2
    1550: invokespecial #122                // Method writeStartElement:(Ljava/lang/String;Ljava/lang/String;Ljava/lang/String;Ljavax/xml/stream/XMLStreamWriter;)V
    1553: aload_0
    1554: getfield      #92                 // Field localDestIP:Ljava/lang/String;
    1557: ifnonnull     1570
    1560: new           #138                // class org/apache/axis2/databinding/ADBException
    1563: dup
    1564: ldc           #195                // String DestIP cannot be null!!
    1566: invokespecial #140                // Method org/apache/axis2/databinding/ADBException."<init>":(Ljava/lang/String;)V
    1569: athrow
    1570: aload_2
    1571: aload_0
    1572: getfield      #92                 // Field localDestIP:Ljava/lang/String;
    1575: invokeinterface #141,  2          // InterfaceMethod javax/xml/stream/XMLStreamWriter.writeCharacters:(Ljava/lang/String;)V
    1580: aload_2
    1581: invokeinterface #142,  1          // InterfaceMethod javax/xml/stream/XMLStreamWriter.writeEndElement:()V
    1586: aload_0
    1587: getfield      #29                 // Field localDestFilePathTracker:Z
    1590: ifeq          1640
    1593: ldc           #123                // String urn:hpccsystems:ws:filespray
    1595: astore        5
    1597: aload_0
    1598: aconst_null
    1599: aload         5
    1601: ldc           #196                // String DestFilePath
    1603: aload_2
    1604: invokespecial #122                // Method writeStartElement:(Ljava/lang/String;Ljava/lang/String;Ljava/lang/String;Ljavax/xml/stream/XMLStreamWriter;)V
    1607: aload_0
    1608: getfield      #93                 // Field localDestFilePath:Ljava/lang/String;
    1611: ifnonnull     1624
    1614: new           #138                // class org/apache/axis2/databinding/ADBException
    1617: dup
    1618: ldc           #197                // String DestFilePath cannot be null!!
    1620: invokespecial #140                // Method org/apache/axis2/databinding/ADBException."<init>":(Ljava/lang/String;)V
    1623: athrow
    1624: aload_2
    1625: aload_0
    1626: getfield      #93                 // Field localDestFilePath:Ljava/lang/String;
    1629: invokeinterface #141,  2          // InterfaceMethod javax/xml/stream/XMLStreamWriter.writeCharacters:(Ljava/lang/String;)V
    1634: aload_2
    1635: invokeinterface #142,  1          // InterfaceMethod javax/xml/stream/XMLStreamWriter.writeEndElement:()V
    1640: aload_0
    1641: getfield      #30                 // Field localDestFormatTracker:Z
    1644: ifeq          1699
    1647: ldc           #123                // String urn:hpccsystems:ws:filespray
    1649: astore        5
    1651: aload_0
    1652: aconst_null
    1653: aload         5
    1655: ldc           #198                // String DestFormat
    1657: aload_2
    1658: invokespecial #122                // Method writeStartElement:(Ljava/lang/String;Ljava/lang/String;Ljava/lang/String;Ljavax/xml/stream/XMLStreamWriter;)V
    1661: aload_0
    1662: getfield      #94                 // Field localDestFormat:I
    1665: ldc           #73                 // int -2147483648
    1667: if_icmpne     1680
    1670: new           #138                // class org/apache/axis2/databinding/ADBException
    1673: dup
    1674: ldc           #199                // String DestFormat cannot be null!!
    1676: invokespecial #140                // Method org/apache/axis2/databinding/ADBException."<init>":(Ljava/lang/String;)V
    1679: athrow
    1680: aload_2
    1681: aload_0
    1682: getfield      #94                 // Field localDestFormat:I
    1685: invokestatic  #157                // Method org/apache/axis2/databinding/utils/ConverterUtil.convertToString:(I)Ljava/lang/String;
    1688: invokeinterface #141,  2          // InterfaceMethod javax/xml/stream/XMLStreamWriter.writeCharacters:(Ljava/lang/String;)V
    1693: aload_2
    1694: invokeinterface #142,  1          // InterfaceMethod javax/xml/stream/XMLStreamWriter.writeEndElement:()V
    1699: aload_0
    1700: getfield      #31                 // Field localDestNumPartsTracker:Z
    1703: ifeq          1758
    1706: ldc           #123                // String urn:hpccsystems:ws:filespray
    1708: astore        5
    1710: aload_0
    1711: aconst_null
    1712: aload         5
    1714: ldc           #200                // String DestNumParts
    1716: aload_2
    1717: invokespecial #122                // Method writeStartElement:(Ljava/lang/String;Ljava/lang/String;Ljava/lang/String;Ljavax/xml/stream/XMLStreamWriter;)V
    1720: aload_0
    1721: getfield      #95                 // Field localDestNumParts:I
    1724: ldc           #73                 // int -2147483648
    1726: if_icmpne     1739
    1729: new           #138                // class org/apache/axis2/databinding/ADBException
    1732: dup
    1733: ldc           #201                // String DestNumParts cannot be null!!
    1735: invokespecial #140                // Method org/apache/axis2/databinding/ADBException."<init>":(Ljava/lang/String;)V
    1738: athrow
    1739: aload_2
    1740: aload_0
    1741: getfield      #95                 // Field localDestNumParts:I
    1744: invokestatic  #157                // Method org/apache/axis2/databinding/utils/ConverterUtil.convertToString:(I)Ljava/lang/String;
    1747: invokeinterface #141,  2          // InterfaceMethod javax/xml/stream/XMLStreamWriter.writeCharacters:(Ljava/lang/String;)V
    1752: aload_2
    1753: invokeinterface #142,  1          // InterfaceMethod javax/xml/stream/XMLStreamWriter.writeEndElement:()V
    1758: aload_0
    1759: getfield      #32                 // Field localDestRecordSizeTracker:Z
    1762: ifeq          1817
    1765: ldc           #123                // String urn:hpccsystems:ws:filespray
    1767: astore        5
    1769: aload_0
    1770: aconst_null
    1771: aload         5
    1773: ldc           #202                // String DestRecordSize
    1775: aload_2
    1776: invokespecial #122                // Method writeStartElement:(Ljava/lang/String;Ljava/lang/String;Ljava/lang/String;Ljavax/xml/stream/XMLStreamWriter;)V
    1779: aload_0
    1780: getfield      #96                 // Field localDestRecordSize:I
    1783: ldc           #73                 // int -2147483648
    1785: if_icmpne     1798
    1788: new           #138                // class org/apache/axis2/databinding/ADBException
    1791: dup
    1792: ldc           #203                // String DestRecordSize cannot be null!!
    1794: invokespecial #140                // Method org/apache/axis2/databinding/ADBException."<init>":(Ljava/lang/String;)V
    1797: athrow
    1798: aload_2
    1799: aload_0
    1800: getfield      #96                 // Field localDestRecordSize:I
    1803: invokestatic  #157                // Method org/apache/axis2/databinding/utils/ConverterUtil.convertToString:(I)Ljava/lang/String;
    1806: invokeinterface #141,  2          // InterfaceMethod javax/xml/stream/XMLStreamWriter.writeCharacters:(Ljava/lang/String;)V
    1811: aload_2
    1812: invokeinterface #142,  1          // InterfaceMethod javax/xml/stream/XMLStreamWriter.writeEndElement:()V
    1817: aload_0
    1818: getfield      #33                 // Field localReplicateTracker:Z
    1821: ifeq          1857
    1824: ldc           #123                // String urn:hpccsystems:ws:filespray
    1826: astore        5
    1828: aload_0
    1829: aconst_null
    1830: aload         5
    1832: ldc           #204                // String Replicate
    1834: aload_2
    1835: invokespecial #122                // Method writeStartElement:(Ljava/lang/String;Ljava/lang/String;Ljava/lang/String;Ljavax/xml/stream/XMLStreamWriter;)V
    1838: aload_2
    1839: aload_0
    1840: getfield      #97                 // Field localReplicate:Z
    1843: invokestatic  #154                // Method org/apache/axis2/databinding/utils/ConverterUtil.convertToString:(Z)Ljava/lang/String;
    1846: invokeinterface #141,  2          // InterfaceMethod javax/xml/stream/XMLStreamWriter.writeCharacters:(Ljava/lang/String;)V
    1851: aload_2
    1852: invokeinterface #142,  1          // InterfaceMethod javax/xml/stream/XMLStreamWriter.writeEndElement:()V
    1857: aload_0
    1858: getfield      #34                 // Field localOverwriteTracker:Z
    1861: ifeq          1897
    1864: ldc           #123                // String urn:hpccsystems:ws:filespray
    1866: astore        5
    1868: aload_0
    1869: aconst_null
    1870: aload         5
    1872: ldc           #205                // String Overwrite
    1874: aload_2
    1875: invokespecial #122                // Method writeStartElement:(Ljava/lang/String;Ljava/lang/String;Ljava/lang/String;Ljavax/xml/stream/XMLStreamWriter;)V
    1878: aload_2
    1879: aload_0
    1880: getfield      #98                 // Field localOverwrite:Z
    1883: invokestatic  #154                // Method org/apache/axis2/databinding/utils/ConverterUtil.convertToString:(Z)Ljava/lang/String;
    1886: invokeinterface #141,  2          // InterfaceMethod javax/xml/stream/XMLStreamWriter.writeCharacters:(Ljava/lang/String;)V
    1891: aload_2
    1892: invokeinterface #142,  1          // InterfaceMethod javax/xml/stream/XMLStreamWriter.writeEndElement:()V
    1897: aload_0
    1898: getfield      #35                 // Field localCompressTracker:Z
    1901: ifeq          1937
    1904: ldc           #123                // String urn:hpccsystems:ws:filespray
    1906: astore        5
    1908: aload_0
    1909: aconst_null
    1910: aload         5
    1912: ldc           #206                // String Compress
    1914: aload_2
    1915: invokespecial #122                // Method writeStartElement:(Ljava/lang/String;Ljava/lang/String;Ljava/lang/String;Ljavax/xml/stream/XMLStreamWriter;)V
    1918: aload_2
    1919: aload_0
    1920: getfield      #99                 // Field localCompress:Z
    1923: invokestatic  #154                // Method org/apache/axis2/databinding/utils/ConverterUtil.convertToString:(Z)Ljava/lang/String;
    1926: invokeinterface #141,  2          // InterfaceMethod javax/xml/stream/XMLStreamWriter.writeCharacters:(Ljava/lang/String;)V
    1931: aload_2
    1932: invokeinterface #142,  1          // InterfaceMethod javax/xml/stream/XMLStreamWriter.writeEndElement:()V
    1937: aload_0
    1938: getfield      #36                 // Field localSourceCsvSeparateTracker:Z
    1941: ifeq          1991
    1944: ldc           #123                // String urn:hpccsystems:ws:filespray
    1946: astore        5
    1948: aload_0
    1949: aconst_null
    1950: aload         5
    1952: ldc           #207                // String SourceCsvSeparate
    1954: aload_2
    1955: invokespecial #122                // Method writeStartElement:(Ljava/lang/String;Ljava/lang/String;Ljava/lang/String;Ljavax/xml/stream/XMLStreamWriter;)V
    1958: aload_0
    1959: getfield      #100                // Field localSourceCsvSeparate:Ljava/lang/String;
    1962: ifnonnull     1975
    1965: new           #138                // class org/apache/axis2/databinding/ADBException
    1968: dup
    1969: ldc           #208                // String SourceCsvSeparate cannot be null!!
    1971: invokespecial #140                // Method org/apache/axis2/databinding/ADBException."<init>":(Ljava/lang/String;)V
    1974: athrow
    1975: aload_2
    1976: aload_0
    1977: getfield      #100                // Field localSourceCsvSeparate:Ljava/lang/String;
    1980: invokeinterface #141,  2          // InterfaceMethod javax/xml/stream/XMLStreamWriter.writeCharacters:(Ljava/lang/String;)V
    1985: aload_2
    1986: invokeinterface #142,  1          // InterfaceMethod javax/xml/stream/XMLStreamWriter.writeEndElement:()V
    1991: aload_0
    1992: getfield      #37                 // Field localSourceCsvQuoteTracker:Z
    1995: ifeq          2045
    1998: ldc           #123                // String urn:hpccsystems:ws:filespray
    2000: astore        5
    2002: aload_0
    2003: aconst_null
    2004: aload         5
    2006: ldc           #209                // String SourceCsvQuote
    2008: aload_2
    2009: invokespecial #122                // Method writeStartElement:(Ljava/lang/String;Ljava/lang/String;Ljava/lang/String;Ljavax/xml/stream/XMLStreamWriter;)V
    2012: aload_0
    2013: getfield      #101                // Field localSourceCsvQuote:Ljava/lang/String;
    2016: ifnonnull     2029
    2019: new           #138                // class org/apache/axis2/databinding/ADBException
    2022: dup
    2023: ldc           #210                // String SourceCsvQuote cannot be null!!
    2025: invokespecial #140                // Method org/apache/axis2/databinding/ADBException."<init>":(Ljava/lang/String;)V
    2028: athrow
    2029: aload_2
    2030: aload_0
    2031: getfield      #101                // Field localSourceCsvQuote:Ljava/lang/String;
    2034: invokeinterface #141,  2          // InterfaceMethod javax/xml/stream/XMLStreamWriter.writeCharacters:(Ljava/lang/String;)V
    2039: aload_2
    2040: invokeinterface #142,  1          // InterfaceMethod javax/xml/stream/XMLStreamWriter.writeEndElement:()V
    2045: aload_0
    2046: getfield      #38                 // Field localSourceCsvTerminateTracker:Z
    2049: ifeq          2099
    2052: ldc           #123                // String urn:hpccsystems:ws:filespray
    2054: astore        5
    2056: aload_0
    2057: aconst_null
    2058: aload         5
    2060: ldc           #211                // String SourceCsvTerminate
    2062: aload_2
    2063: invokespecial #122                // Method writeStartElement:(Ljava/lang/String;Ljava/lang/String;Ljava/lang/String;Ljavax/xml/stream/XMLStreamWriter;)V
    2066: aload_0
    2067: getfield      #102                // Field localSourceCsvTerminate:Ljava/lang/String;
    2070: ifnonnull     2083
    2073: new           #138                // class org/apache/axis2/databinding/ADBException
    2076: dup
    2077: ldc           #212                // String SourceCsvTerminate cannot be null!!
    2079: invokespecial #140                // Method org/apache/axis2/databinding/ADBException."<init>":(Ljava/lang/String;)V
    2082: athrow
    2083: aload_2
    2084: aload_0
    2085: getfield      #102                // Field localSourceCsvTerminate:Ljava/lang/String;
    2088: invokeinterface #141,  2          // InterfaceMethod javax/xml/stream/XMLStreamWriter.writeCharacters:(Ljava/lang/String;)V
    2093: aload_2
    2094: invokeinterface #142,  1          // InterfaceMethod javax/xml/stream/XMLStreamWriter.writeEndElement:()V
    2099: aload_0
    2100: getfield      #39                 // Field localSourceCsvEscapeTracker:Z
    2103: ifeq          2153
    2106: ldc           #123                // String urn:hpccsystems:ws:filespray
    2108: astore        5
    2110: aload_0
    2111: aconst_null
    2112: aload         5
    2114: ldc           #213                // String SourceCsvEscape
    2116: aload_2
    2117: invokespecial #122                // Method writeStartElement:(Ljava/lang/String;Ljava/lang/String;Ljava/lang/String;Ljavax/xml/stream/XMLStreamWriter;)V
    2120: aload_0
    2121: getfield      #103                // Field localSourceCsvEscape:Ljava/lang/String;
    2124: ifnonnull     2137
    2127: new           #138                // class org/apache/axis2/databinding/ADBException
    2130: dup
    2131: ldc           #214                // String SourceCsvEscape cannot be null!!
    2133: invokespecial #140                // Method org/apache/axis2/databinding/ADBException."<init>":(Ljava/lang/String;)V
    2136: athrow
    2137: aload_2
    2138: aload_0
    2139: getfield      #103                // Field localSourceCsvEscape:Ljava/lang/String;
    2142: invokeinterface #141,  2          // InterfaceMethod javax/xml/stream/XMLStreamWriter.writeCharacters:(Ljava/lang/String;)V
    2147: aload_2
    2148: invokeinterface #142,  1          // InterfaceMethod javax/xml/stream/XMLStreamWriter.writeEndElement:()V
    2153: aload_0
    2154: getfield      #40                 // Field localTimeStartedTracker:Z
    2157: ifeq          2207
    2160: ldc           #123                // String urn:hpccsystems:ws:filespray
    2162: astore        5
    2164: aload_0
    2165: aconst_null
    2166: aload         5
    2168: ldc           #215                // String TimeStarted
    2170: aload_2
    2171: invokespecial #122                // Method writeStartElement:(Ljava/lang/String;Ljava/lang/String;Ljava/lang/String;Ljavax/xml/stream/XMLStreamWriter;)V
    2174: aload_0
    2175: getfield      #104                // Field localTimeStarted:Ljava/lang/String;
    2178: ifnonnull     2191
    2181: new           #138                // class org/apache/axis2/databinding/ADBException
    2184: dup
    2185: ldc           #216                // String TimeStarted cannot be null!!
    2187: invokespecial #140                // Method org/apache/axis2/databinding/ADBException."<init>":(Ljava/lang/String;)V
    2190: athrow
    2191: aload_2
    2192: aload_0
    2193: getfield      #104                // Field localTimeStarted:Ljava/lang/String;
    2196: invokeinterface #141,  2          // InterfaceMethod javax/xml/stream/XMLStreamWriter.writeCharacters:(Ljava/lang/String;)V
    2201: aload_2
    2202: invokeinterface #142,  1          // InterfaceMethod javax/xml/stream/XMLStreamWriter.writeEndElement:()V
    2207: aload_0
    2208: getfield      #41                 // Field localTimeStoppedTracker:Z
    2211: ifeq          2261
    2214: ldc           #123                // String urn:hpccsystems:ws:filespray
    2216: astore        5
    2218: aload_0
    2219: aconst_null
    2220: aload         5
    2222: ldc           #217                // String TimeStopped
    2224: aload_2
    2225: invokespecial #122                // Method writeStartElement:(Ljava/lang/String;Ljava/lang/String;Ljava/lang/String;Ljavax/xml/stream/XMLStreamWriter;)V
    2228: aload_0
    2229: getfield      #105                // Field localTimeStopped:Ljava/lang/String;
    2232: ifnonnull     2245
    2235: new           #138                // class org/apache/axis2/databinding/ADBException
    2238: dup
    2239: ldc           #218                // String TimeStopped cannot be null!!
    2241: invokespecial #140                // Method org/apache/axis2/databinding/ADBException."<init>":(Ljava/lang/String;)V
    2244: athrow
    2245: aload_2
    2246: aload_0
    2247: getfield      #105                // Field localTimeStopped:Ljava/lang/String;
    2250: invokeinterface #141,  2          // InterfaceMethod javax/xml/stream/XMLStreamWriter.writeCharacters:(Ljava/lang/String;)V
    2255: aload_2
    2256: invokeinterface #142,  1          // InterfaceMethod javax/xml/stream/XMLStreamWriter.writeEndElement:()V
    2261: aload_0
    2262: getfield      #42                 // Field localStateMessageTracker:Z
    2265: ifeq          2315
    2268: ldc           #123                // String urn:hpccsystems:ws:filespray
    2270: astore        5
    2272: aload_0
    2273: aconst_null
    2274: aload         5
    2276: ldc           #219                // String StateMessage
    2278: aload_2
    2279: invokespecial #122                // Method writeStartElement:(Ljava/lang/String;Ljava/lang/String;Ljava/lang/String;Ljavax/xml/stream/XMLStreamWriter;)V
    2282: aload_0
    2283: getfield      #106                // Field localStateMessage:Ljava/lang/String;
    2286: ifnonnull     2299
    2289: new           #138                // class org/apache/axis2/databinding/ADBException
    2292: dup
    2293: ldc           #220                // String StateMessage cannot be null!!
    2295: invokespecial #140                // Method org/apache/axis2/databinding/ADBException."<init>":(Ljava/lang/String;)V
    2298: athrow
    2299: aload_2
    2300: aload_0
    2301: getfield      #106                // Field localStateMessage:Ljava/lang/String;
    2304: invokeinterface #141,  2          // InterfaceMethod javax/xml/stream/XMLStreamWriter.writeCharacters:(Ljava/lang/String;)V
    2309: aload_2
    2310: invokeinterface #142,  1          // InterfaceMethod javax/xml/stream/XMLStreamWriter.writeEndElement:()V
    2315: aload_0
    2316: getfield      #43                 // Field localMonitorEventNameTracker:Z
    2319: ifeq          2369
    2322: ldc           #123                // String urn:hpccsystems:ws:filespray
    2324: astore        5
    2326: aload_0
    2327: aconst_null
    2328: aload         5
    2330: ldc           #221                // String MonitorEventName
    2332: aload_2
    2333: invokespecial #122                // Method writeStartElement:(Ljava/lang/String;Ljava/lang/String;Ljava/lang/String;Ljavax/xml/stream/XMLStreamWriter;)V
    2336: aload_0
    2337: getfield      #107                // Field localMonitorEventName:Ljava/lang/String;
    2340: ifnonnull     2353
    2343: new           #138                // class org/apache/axis2/databinding/ADBException
    2346: dup
    2347: ldc           #222                // String MonitorEventName cannot be null!!
    2349: invokespecial #140                // Method org/apache/axis2/databinding/ADBException."<init>":(Ljava/lang/String;)V
    2352: athrow
    2353: aload_2
    2354: aload_0
    2355: getfield      #107                // Field localMonitorEventName:Ljava/lang/String;
    2358: invokeinterface #141,  2          // InterfaceMethod javax/xml/stream/XMLStreamWriter.writeCharacters:(Ljava/lang/String;)V
    2363: aload_2
    2364: invokeinterface #142,  1          // InterfaceMethod javax/xml/stream/XMLStreamWriter.writeEndElement:()V
    2369: aload_0
    2370: getfield      #44                 // Field localMonitorSubTracker:Z
    2373: ifeq          2409
    2376: ldc           #123                // String urn:hpccsystems:ws:filespray
    2378: astore        5
    2380: aload_0
    2381: aconst_null
    2382: aload         5
    2384: ldc           #223                // String MonitorSub
    2386: aload_2
    2387: invokespecial #122                // Method writeStartElement:(Ljava/lang/String;Ljava/lang/String;Ljava/lang/String;Ljavax/xml/stream/XMLStreamWriter;)V
    2390: aload_2
    2391: aload_0
    2392: getfield      #108                // Field localMonitorSub:Z
    2395: invokestatic  #154                // Method org/apache/axis2/databinding/utils/ConverterUtil.convertToString:(Z)Ljava/lang/String;
    2398: invokeinterface #141,  2          // InterfaceMethod javax/xml/stream/XMLStreamWriter.writeCharacters:(Ljava/lang/String;)V
    2403: aload_2
    2404: invokeinterface #142,  1          // InterfaceMethod javax/xml/stream/XMLStreamWriter.writeEndElement:()V
    2409: aload_0
    2410: getfield      #45                 // Field localMonitorShotLimitTracker:Z
    2413: ifeq          2468
    2416: ldc           #123                // String urn:hpccsystems:ws:filespray
    2418: astore        5
    2420: aload_0
    2421: aconst_null
    2422: aload         5
    2424: ldc           #224                // String MonitorShotLimit
    2426: aload_2
    2427: invokespecial #122                // Method writeStartElement:(Ljava/lang/String;Ljava/lang/String;Ljava/lang/String;Ljavax/xml/stream/XMLStreamWriter;)V
    2430: aload_0
    2431: getfield      #109                // Field localMonitorShotLimit:I
    2434: ldc           #73                 // int -2147483648
    2436: if_icmpne     2449
    2439: new           #138                // class org/apache/axis2/databinding/ADBException
    2442: dup
    2443: ldc           #225                // String MonitorShotLimit cannot be null!!
    2445: invokespecial #140                // Method org/apache/axis2/databinding/ADBException."<init>":(Ljava/lang/String;)V
    2448: athrow
    2449: aload_2
    2450: aload_0
    2451: getfield      #109                // Field localMonitorShotLimit:I
    2454: invokestatic  #157                // Method org/apache/axis2/databinding/utils/ConverterUtil.convertToString:(I)Ljava/lang/String;
    2457: invokeinterface #141,  2          // InterfaceMethod javax/xml/stream/XMLStreamWriter.writeCharacters:(Ljava/lang/String;)V
    2462: aload_2
    2463: invokeinterface #142,  1          // InterfaceMethod javax/xml/stream/XMLStreamWriter.writeEndElement:()V
    2468: aload_0
    2469: getfield      #46                 // Field localSourceDiffKeyNameTracker:Z
    2472: ifeq          2522
    2475: ldc           #123                // String urn:hpccsystems:ws:filespray
    2477: astore        5
    2479: aload_0
    2480: aconst_null
    2481: aload         5
    2483: ldc           #226                // String SourceDiffKeyName
    2485: aload_2
    2486: invokespecial #122                // Method writeStartElement:(Ljava/lang/String;Ljava/lang/String;Ljava/lang/String;Ljavax/xml/stream/XMLStreamWriter;)V
    2489: aload_0
    2490: getfield      #110                // Field localSourceDiffKeyName:Ljava/lang/String;
    2493: ifnonnull     2506
    2496: new           #138                // class org/apache/axis2/databinding/ADBException
    2499: dup
    2500: ldc           #227                // String SourceDiffKeyName cannot be null!!
    2502: invokespecial #140                // Method org/apache/axis2/databinding/ADBException."<init>":(Ljava/lang/String;)V
    2505: athrow
    2506: aload_2
    2507: aload_0
    2508: getfield      #110                // Field localSourceDiffKeyName:Ljava/lang/String;
    2511: invokeinterface #141,  2          // InterfaceMethod javax/xml/stream/XMLStreamWriter.writeCharacters:(Ljava/lang/String;)V
    2516: aload_2
    2517: invokeinterface #142,  1          // InterfaceMethod javax/xml/stream/XMLStreamWriter.writeEndElement:()V
    2522: aload_0
    2523: getfield      #47                 // Field localDestDiffKeyNameTracker:Z
    2526: ifeq          2576
    2529: ldc           #123                // String urn:hpccsystems:ws:filespray
    2531: astore        5
    2533: aload_0
    2534: aconst_null
    2535: aload         5
    2537: ldc           #228                // String DestDiffKeyName
    2539: aload_2
    2540: invokespecial #122                // Method writeStartElement:(Ljava/lang/String;Ljava/lang/String;Ljava/lang/String;Ljavax/xml/stream/XMLStreamWriter;)V
    2543: aload_0
    2544: getfield      #111                // Field localDestDiffKeyName:Ljava/lang/String;
    2547: ifnonnull     2560
    2550: new           #138                // class org/apache/axis2/databinding/ADBException
    2553: dup
    2554: ldc           #229                // String DestDiffKeyName cannot be null!!
    2556: invokespecial #140                // Method org/apache/axis2/databinding/ADBException."<init>":(Ljava/lang/String;)V
    2559: athrow
    2560: aload_2
    2561: aload_0
    2562: getfield      #111                // Field localDestDiffKeyName:Ljava/lang/String;
    2565: invokeinterface #141,  2          // InterfaceMethod javax/xml/stream/XMLStreamWriter.writeCharacters:(Ljava/lang/String;)V
    2570: aload_2
    2571: invokeinterface #142,  1          // InterfaceMethod javax/xml/stream/XMLStreamWriter.writeEndElement:()V
    2576: aload_0
    2577: getfield      #51                 // Field localArchivedTracker:Z
    2580: ifeq          2616
    2583: ldc           #123                // String urn:hpccsystems:ws:filespray
    2585: astore        5
    2587: aload_0
    2588: aconst_null
    2589: aload         5
    2591: ldc           #230                // String Archived
    2593: aload_2
    2594: invokespecial #122                // Method writeStartElement:(Ljava/lang/String;Ljava/lang/String;Ljava/lang/String;Ljavax/xml/stream/XMLStreamWriter;)V
    2597: aload_2
    2598: aload_0
    2599: getfield      #50                 // Field localArchived:Z
    2602: invokestatic  #154                // Method org/apache/axis2/databinding/utils/ConverterUtil.convertToString:(Z)Ljava/lang/String;
    2605: invokeinterface #141,  2          // InterfaceMethod javax/xml/stream/XMLStreamWriter.writeCharacters:(Ljava/lang/String;)V
    2610: aload_2
    2611: invokeinterface #142,  1          // InterfaceMethod javax/xml/stream/XMLStreamWriter.writeEndElement:()V
    2616: aload_0
    2617: getfield      #52                 // Field localEncryptTracker:Z
    2620: ifeq          2670
    2623: ldc           #123                // String urn:hpccsystems:ws:filespray
    2625: astore        5
    2627: aload_0
    2628: aconst_null
    2629: aload         5
    2631: ldc           #231                // String encrypt
    2633: aload_2
    2634: invokespecial #122                // Method writeStartElement:(Ljava/lang/String;Ljava/lang/String;Ljava/lang/String;Ljavax/xml/stream/XMLStreamWriter;)V
    2637: aload_0
    2638: getfield      #112                // Field localEncrypt:Ljava/lang/String;
    2641: ifnonnull     2654
    2644: new           #138                // class org/apache/axis2/databinding/ADBException
    2647: dup
    2648: ldc           #232                // String encrypt cannot be null!!
    2650: invokespecial #140                // Method org/apache/axis2/databinding/ADBException."<init>":(Ljava/lang/String;)V
    2653: athrow
    2654: aload_2
    2655: aload_0
    2656: getfield      #112                // Field localEncrypt:Ljava/lang/String;
    2659: invokeinterface #141,  2          // InterfaceMethod javax/xml/stream/XMLStreamWriter.writeCharacters:(Ljava/lang/String;)V
    2664: aload_2
    2665: invokeinterface #142,  1          // InterfaceMethod javax/xml/stream/XMLStreamWriter.writeEndElement:()V
    2670: aload_0
    2671: getfield      #53                 // Field localDecryptTracker:Z
    2674: ifeq          2724
    2677: ldc           #123                // String urn:hpccsystems:ws:filespray
    2679: astore        5
    2681: aload_0
    2682: aconst_null
    2683: aload         5
    2685: ldc           #233                // String decrypt
    2687: aload_2
    2688: invokespecial #122                // Method writeStartElement:(Ljava/lang/String;Ljava/lang/String;Ljava/lang/String;Ljavax/xml/stream/XMLStreamWriter;)V
    2691: aload_0
    2692: getfield      #113                // Field localDecrypt:Ljava/lang/String;
    2695: ifnonnull     2708
    2698: new           #138                // class org/apache/axis2/databinding/ADBException
    2701: dup
    2702: ldc           #234                // String decrypt cannot be null!!
    2704: invokespecial #140                // Method org/apache/axis2/databinding/ADBException."<init>":(Ljava/lang/String;)V
    2707: athrow
    2708: aload_2
    2709: aload_0
    2710: getfield      #113                // Field localDecrypt:Ljava/lang/String;
    2713: invokeinterface #141,  2          // InterfaceMethod javax/xml/stream/XMLStreamWriter.writeCharacters:(Ljava/lang/String;)V
    2718: aload_2
    2719: invokeinterface #142,  1          // InterfaceMethod javax/xml/stream/XMLStreamWriter.writeEndElement:()V
    2724: aload_0
    2725: getfield      #55                 // Field localFailIfNoSourceFileTracker:Z
    2728: ifeq          2764
    2731: ldc           #123                // String urn:hpccsystems:ws:filespray
    2733: astore        5
    2735: aload_0
    2736: aconst_null
    2737: aload         5
    2739: ldc           #235                // String failIfNoSourceFile
    2741: aload_2
    2742: invokespecial #122                // Method writeStartElement:(Ljava/lang/String;Ljava/lang/String;Ljava/lang/String;Ljavax/xml/stream/XMLStreamWriter;)V
    2745: aload_2
    2746: aload_0
    2747: getfield      #54                 // Field localFailIfNoSourceFile:Z
    2750: invokestatic  #154                // Method org/apache/axis2/databinding/utils/ConverterUtil.convertToString:(Z)Ljava/lang/String;
    2753: invokeinterface #141,  2          // InterfaceMethod javax/xml/stream/XMLStreamWriter.writeCharacters:(Ljava/lang/String;)V
    2758: aload_2
    2759: invokeinterface #142,  1          // InterfaceMethod javax/xml/stream/XMLStreamWriter.writeEndElement:()V
    2764: aload_0
    2765: getfield      #57                 // Field localRecordStructurePresentTracker:Z
    2768: ifeq          2804
    2771: ldc           #123                // String urn:hpccsystems:ws:filespray
    2773: astore        5
    2775: aload_0
    2776: aconst_null
    2777: aload         5
    2779: ldc           #236                // String recordStructurePresent
    2781: aload_2
    2782: invokespecial #122                // Method writeStartElement:(Ljava/lang/String;Ljava/lang/String;Ljava/lang/String;Ljavax/xml/stream/XMLStreamWriter;)V
    2785: aload_2
    2786: aload_0
    2787: getfield      #56                 // Field localRecordStructurePresent:Z
    2790: invokestatic  #154                // Method org/apache/axis2/databinding/utils/ConverterUtil.convertToString:(Z)Ljava/lang/String;
    2793: invokeinterface #141,  2          // InterfaceMethod javax/xml/stream/XMLStreamWriter.writeCharacters:(Ljava/lang/String;)V
    2798: aload_2
    2799: invokeinterface #142,  1          // InterfaceMethod javax/xml/stream/XMLStreamWriter.writeEndElement:()V
    2804: aload_0
    2805: getfield      #60                 // Field localQuotedTerminatorTracker:Z
    2808: ifeq          2844
    2811: ldc           #123                // String urn:hpccsystems:ws:filespray
    2813: astore        5
    2815: aload_0
    2816: aconst_null
    2817: aload         5
    2819: ldc           #237                // String quotedTerminator
    2821: aload_2
    2822: invokespecial #122                // Method writeStartElement:(Ljava/lang/String;Ljava/lang/String;Ljava/lang/String;Ljavax/xml/stream/XMLStreamWriter;)V
    2825: aload_2
    2826: aload_0
    2827: getfield      #59                 // Field localQuotedTerminator:Z
    2830: invokestatic  #154                // Method org/apache/axis2/databinding/utils/ConverterUtil.convertToString:(Z)Ljava/lang/String;
    2833: invokeinterface #141,  2          // InterfaceMethod javax/xml/stream/XMLStreamWriter.writeCharacters:(Ljava/lang/String;)V
    2838: aload_2
    2839: invokeinterface #142,  1          // InterfaceMethod javax/xml/stream/XMLStreamWriter.writeEndElement:()V
    2844: aload_0
    2845: getfield      #62                 // Field localPreserveCompressionTracker:Z
    2848: ifeq          2884
    2851: ldc           #123                // String urn:hpccsystems:ws:filespray
    2853: astore        5
    2855: aload_0
    2856: aconst_null
    2857: aload         5
    2859: ldc           #238                // String preserveCompression
    2861: aload_2
    2862: invokespecial #122                // Method writeStartElement:(Ljava/lang/String;Ljava/lang/String;Ljava/lang/String;Ljavax/xml/stream/XMLStreamWriter;)V
    2865: aload_2
    2866: aload_0
    2867: getfield      #61                 // Field localPreserveCompression:Z
    2870: invokestatic  #154                // Method org/apache/axis2/databinding/utils/ConverterUtil.convertToString:(Z)Ljava/lang/String;
    2873: invokeinterface #141,  2          // InterfaceMethod javax/xml/stream/XMLStreamWriter.writeCharacters:(Ljava/lang/String;)V
    2878: aload_2
    2879: invokeinterface #142,  1          // InterfaceMethod javax/xml/stream/XMLStreamWriter.writeEndElement:()V
    2884: aload_0
    2885: getfield      #63                 // Field localExpireDaysTracker:Z
    2888: ifeq          2943
    2891: ldc           #123                // String urn:hpccsystems:ws:filespray
    2893: astore        5
    2895: aload_0
    2896: aconst_null
    2897: aload         5
    2899: ldc           #239                // String expireDays
    2901: aload_2
    2902: invokespecial #122                // Method writeStartElement:(Ljava/lang/String;Ljava/lang/String;Ljava/lang/String;Ljavax/xml/stream/XMLStreamWriter;)V
    2905: aload_0
    2906: getfield      #114                // Field localExpireDays:I
    2909: ldc           #73                 // int -2147483648
    2911: if_icmpne     2924
    2914: new           #138                // class org/apache/axis2/databinding/ADBException
    2917: dup
    2918: ldc           #240                // String expireDays cannot be null!!
    2920: invokespecial #140                // Method org/apache/axis2/databinding/ADBException."<init>":(Ljava/lang/String;)V
    2923: athrow
    2924: aload_2
    2925: aload_0
    2926: getfield      #114                // Field localExpireDays:I
    2929: invokestatic  #157                // Method org/apache/axis2/databinding/utils/ConverterUtil.convertToString:(I)Ljava/lang/String;
    2932: invokeinterface #141,  2          // InterfaceMethod javax/xml/stream/XMLStreamWriter.writeCharacters:(Ljava/lang/String;)V
    2937: aload_2
    2938: invokeinterface #142,  1          // InterfaceMethod javax/xml/stream/XMLStreamWriter.writeEndElement:()V
    2943: aload_2
    2944: invokeinterface #142,  1          // InterfaceMethod javax/xml/stream/XMLStreamWriter.writeEndElement:()V
    2949: return

  private static java.lang.String generatePrefix(java.lang.String);
    Code:
       0: aload_0
       1: ldc           #123                // String urn:hpccsystems:ws:filespray
       3: invokevirtual #241                // Method java/lang/String.equals:(Ljava/lang/Object;)Z
       6: ifeq          12
       9: ldc           #242                // String ns2
      11: areturn
      12: invokestatic  #243                // Method org/apache/axis2/databinding/utils/BeanUtil.getUniquePrefix:()Ljava/lang/String;
      15: areturn

  private void writeStartElement(java.lang.String, java.lang.String, java.lang.String, javax.xml.stream.XMLStreamWriter) throws javax.xml.stream.XMLStreamException;
    Code:
       0: aload         4
       2: aload_2
       3: invokeinterface #244,  2          // InterfaceMethod javax/xml/stream/XMLStreamWriter.getPrefix:(Ljava/lang/String;)Ljava/lang/String;
       8: astore        5
      10: aload         5
      12: ifnull        29
      15: aload         4
      17: aload         5
      19: aload_3
      20: aload_2
      21: invokeinterface #245,  4          // InterfaceMethod javax/xml/stream/XMLStreamWriter.writeStartElement:(Ljava/lang/String;Ljava/lang/String;Ljava/lang/String;)V
      26: goto          79
      29: aload_2
      30: invokevirtual #126                // Method java/lang/String.length:()I
      33: ifne          42
      36: ldc           #246                // String
      38: astore_1
      39: goto          51
      42: aload_1
      43: ifnonnull     51
      46: aload_2
      47: invokestatic  #247                // Method generatePrefix:(Ljava/lang/String;)Ljava/lang/String;
      50: astore_1
      51: aload         4
      53: aload_1
      54: aload_3
      55: aload_2
      56: invokeinterface #245,  4          // InterfaceMethod javax/xml/stream/XMLStreamWriter.writeStartElement:(Ljava/lang/String;Ljava/lang/String;Ljava/lang/String;)V
      61: aload         4
      63: aload_1
      64: aload_2
      65: invokeinterface #248,  3          // InterfaceMethod javax/xml/stream/XMLStreamWriter.writeNamespace:(Ljava/lang/String;Ljava/lang/String;)V
      70: aload         4
      72: aload_1
      73: aload_2
      74: invokeinterface #249,  3          // InterfaceMethod javax/xml/stream/XMLStreamWriter.setPrefix:(Ljava/lang/String;Ljava/lang/String;)V
      79: return

  private void writeAttribute(java.lang.String, java.lang.String, java.lang.String, java.lang.String, javax.xml.stream.XMLStreamWriter) throws javax.xml.stream.XMLStreamException;
    Code:
       0: aload         5
       2: aload_2
       3: invokeinterface #244,  2          // InterfaceMethod javax/xml/stream/XMLStreamWriter.getPrefix:(Ljava/lang/String;)Ljava/lang/String;
       8: astore        6
      10: aload         6
      12: ifnull        31
      15: aload         5
      17: aload         6
      19: aload_2
      20: aload_3
      21: aload         4
      23: invokeinterface #250,  5          // InterfaceMethod javax/xml/stream/XMLStreamWriter.writeAttribute:(Ljava/lang/String;Ljava/lang/String;Ljava/lang/String;Ljava/lang/String;)V
      28: goto          61
      31: aload         5
      33: aload_1
      34: aload_2
      35: invokeinterface #248,  3          // InterfaceMethod javax/xml/stream/XMLStreamWriter.writeNamespace:(Ljava/lang/String;Ljava/lang/String;)V
      40: aload         5
      42: aload_1
      43: aload_2
      44: invokeinterface #249,  3          // InterfaceMethod javax/xml/stream/XMLStreamWriter.setPrefix:(Ljava/lang/String;Ljava/lang/String;)V
      49: aload         5
      51: aload_1
      52: aload_2
      53: aload_3
      54: aload         4
      56: invokeinterface #250,  5          // InterfaceMethod javax/xml/stream/XMLStreamWriter.writeAttribute:(Ljava/lang/String;Ljava/lang/String;Ljava/lang/String;Ljava/lang/String;)V
      61: return

  private void writeAttribute(java.lang.String, java.lang.String, java.lang.String, javax.xml.stream.XMLStreamWriter) throws javax.xml.stream.XMLStreamException;
    Code:
       0: aload_1
       1: ldc           #246                // String
       3: invokevirtual #241                // Method java/lang/String.equals:(Ljava/lang/Object;)Z
       6: ifeq          21
       9: aload         4
      11: aload_2
      12: aload_3
      13: invokeinterface #251,  3          // InterfaceMethod javax/xml/stream/XMLStreamWriter.writeAttribute:(Ljava/lang/String;Ljava/lang/String;)V
      18: goto          38
      21: aload         4
      23: aload_0
      24: aload         4
      26: aload_1
      27: invokespecial #124                // Method registerPrefix:(Ljavax/xml/stream/XMLStreamWriter;Ljava/lang/String;)Ljava/lang/String;
      30: aload_1
      31: aload_2
      32: aload_3
      33: invokeinterface #250,  5          // InterfaceMethod javax/xml/stream/XMLStreamWriter.writeAttribute:(Ljava/lang/String;Ljava/lang/String;Ljava/lang/String;Ljava/lang/String;)V
      38: return

  private void writeQNameAttribute(java.lang.String, java.lang.String, javax.xml.namespace.QName, javax.xml.stream.XMLStreamWriter) throws javax.xml.stream.XMLStreamException;
    Code:
       0: aload_3
       1: invokevirtual #120                // Method javax/xml/namespace/QName.getNamespaceURI:()Ljava/lang/String;
       4: astore        5
       6: aload         4
       8: aload         5
      10: invokeinterface #244,  2          // InterfaceMethod javax/xml/stream/XMLStreamWriter.getPrefix:(Ljava/lang/String;)Ljava/lang/String;
      15: astore        6
      17: aload         6
      19: ifnonnull     32
      22: aload_0
      23: aload         4
      25: aload         5
      27: invokespecial #124                // Method registerPrefix:(Ljavax/xml/stream/XMLStreamWriter;Ljava/lang/String;)Ljava/lang/String;
      30: astore        6
      32: aload         6
      34: invokevirtual #125                // Method java/lang/String.trim:()Ljava/lang/String;
      37: invokevirtual #126                // Method java/lang/String.length:()I
      40: ifle          75
      43: new           #130                // class java/lang/StringBuilder
      46: dup
      47: invokespecial #131                // Method java/lang/StringBuilder."<init>":()V
      50: aload         6
      52: invokevirtual #132                // Method java/lang/StringBuilder.append:(Ljava/lang/String;)Ljava/lang/StringBuilder;
      55: ldc           #252                // String :
      57: invokevirtual #132                // Method java/lang/StringBuilder.append:(Ljava/lang/String;)Ljava/lang/StringBuilder;
      60: aload_3
      61: invokevirtual #121                // Method javax/xml/namespace/QName.getLocalPart:()Ljava/lang/String;
      64: invokevirtual #132                // Method java/lang/StringBuilder.append:(Ljava/lang/String;)Ljava/lang/StringBuilder;
      67: invokevirtual #134                // Method java/lang/StringBuilder.toString:()Ljava/lang/String;
      70: astore        7
      72: goto          81
      75: aload_3
      76: invokevirtual #121                // Method javax/xml/namespace/QName.getLocalPart:()Ljava/lang/String;
      79: astore        7
      81: aload_1
      82: ldc           #246                // String
      84: invokevirtual #241                // Method java/lang/String.equals:(Ljava/lang/Object;)Z
      87: ifeq          103
      90: aload         4
      92: aload_2
      93: aload         7
      95: invokeinterface #251,  3          // InterfaceMethod javax/xml/stream/XMLStreamWriter.writeAttribute:(Ljava/lang/String;Ljava/lang/String;)V
     100: goto          124
     103: aload_0
     104: aload         4
     106: aload_1
     107: invokespecial #124                // Method registerPrefix:(Ljavax/xml/stream/XMLStreamWriter;Ljava/lang/String;)Ljava/lang/String;
     110: pop
     111: aload         4
     113: aload         6
     115: aload_1
     116: aload_2
     117: aload         7
     119: invokeinterface #250,  5          // InterfaceMethod javax/xml/stream/XMLStreamWriter.writeAttribute:(Ljava/lang/String;Ljava/lang/String;Ljava/lang/String;Ljava/lang/String;)V
     124: return

  private void writeQName(javax.xml.namespace.QName, javax.xml.stream.XMLStreamWriter) throws javax.xml.stream.XMLStreamException;
    Code:
       0: aload_1
       1: invokevirtual #120                // Method javax/xml/namespace/QName.getNamespaceURI:()Ljava/lang/String;
       4: astore_3
       5: aload_3
       6: ifnull        107
       9: aload_2
      10: aload_3
      11: invokeinterface #244,  2          // InterfaceMethod javax/xml/stream/XMLStreamWriter.getPrefix:(Ljava/lang/String;)Ljava/lang/String;
      16: astore        4
      18: aload         4
      20: ifnonnull     47
      23: aload_3
      24: invokestatic  #247                // Method generatePrefix:(Ljava/lang/String;)Ljava/lang/String;
      27: astore        4
      29: aload_2
      30: aload         4
      32: aload_3
      33: invokeinterface #248,  3          // InterfaceMethod javax/xml/stream/XMLStreamWriter.writeNamespace:(Ljava/lang/String;Ljava/lang/String;)V
      38: aload_2
      39: aload         4
      41: aload_3
      42: invokeinterface #249,  3          // InterfaceMethod javax/xml/stream/XMLStreamWriter.setPrefix:(Ljava/lang/String;Ljava/lang/String;)V
      47: aload         4
      49: invokevirtual #125                // Method java/lang/String.trim:()Ljava/lang/String;
      52: invokevirtual #126                // Method java/lang/String.length:()I
      55: ifle          94
      58: aload_2
      59: new           #130                // class java/lang/StringBuilder
      62: dup
      63: invokespecial #131                // Method java/lang/StringBuilder."<init>":()V
      66: aload         4
      68: invokevirtual #132                // Method java/lang/StringBuilder.append:(Ljava/lang/String;)Ljava/lang/StringBuilder;
      71: ldc           #252                // String :
      73: invokevirtual #132                // Method java/lang/StringBuilder.append:(Ljava/lang/String;)Ljava/lang/StringBuilder;
      76: aload_1
      77: invokestatic  #253                // Method org/apache/axis2/databinding/utils/ConverterUtil.convertToString:(Ljavax/xml/namespace/QName;)Ljava/lang/String;
      80: invokevirtual #132                // Method java/lang/StringBuilder.append:(Ljava/lang/String;)Ljava/lang/StringBuilder;
      83: invokevirtual #134                // Method java/lang/StringBuilder.toString:()Ljava/lang/String;
      86: invokeinterface #141,  2          // InterfaceMethod javax/xml/stream/XMLStreamWriter.writeCharacters:(Ljava/lang/String;)V
      91: goto          104
      94: aload_2
      95: aload_1
      96: invokestatic  #253                // Method org/apache/axis2/databinding/utils/ConverterUtil.convertToString:(Ljavax/xml/namespace/QName;)Ljava/lang/String;
      99: invokeinterface #141,  2          // InterfaceMethod javax/xml/stream/XMLStreamWriter.writeCharacters:(Ljava/lang/String;)V
     104: goto          117
     107: aload_2
     108: aload_1
     109: invokestatic  #253                // Method org/apache/axis2/databinding/utils/ConverterUtil.convertToString:(Ljavax/xml/namespace/QName;)Ljava/lang/String;
     112: invokeinterface #141,  2          // InterfaceMethod javax/xml/stream/XMLStreamWriter.writeCharacters:(Ljava/lang/String;)V
     117: return

  private void writeQNames(javax.xml.namespace.QName[], javax.xml.stream.XMLStreamWriter) throws javax.xml.stream.XMLStreamException;
    Code:
       0: aload_1
       1: ifnull        184
       4: new           #254                // class java/lang/StringBuffer
       7: dup
       8: invokespecial #255                // Method java/lang/StringBuffer."<init>":()V
      11: astore_3
      12: aconst_null
      13: astore        4
      15: aconst_null
      16: astore        5
      18: iconst_0
      19: istore        6
      21: iload         6
      23: aload_1
      24: arraylength
      25: if_icmpge     174
      28: iload         6
      30: ifle          41
      33: aload_3
      34: ldc_w         #256                // String
      37: invokevirtual #257                // Method java/lang/StringBuffer.append:(Ljava/lang/String;)Ljava/lang/StringBuffer;
      40: pop
      41: aload_1
      42: iload         6
      44: aaload
      45: invokevirtual #120                // Method javax/xml/namespace/QName.getNamespaceURI:()Ljava/lang/String;
      48: astore        4
      50: aload         4
      52: ifnull        156
      55: aload_2
      56: aload         4
      58: invokeinterface #244,  2          // InterfaceMethod javax/xml/stream/XMLStreamWriter.getPrefix:(Ljava/lang/String;)Ljava/lang/String;
      63: astore        5
      65: aload         5
      67: ifnull        78
      70: aload         5
      72: invokevirtual #126                // Method java/lang/String.length:()I
      75: ifne          105
      78: aload         4
      80: invokestatic  #247                // Method generatePrefix:(Ljava/lang/String;)Ljava/lang/String;
      83: astore        5
      85: aload_2
      86: aload         5
      88: aload         4
      90: invokeinterface #248,  3          // InterfaceMethod javax/xml/stream/XMLStreamWriter.writeNamespace:(Ljava/lang/String;Ljava/lang/String;)V
      95: aload_2
      96: aload         5
      98: aload         4
     100: invokeinterface #249,  3          // InterfaceMethod javax/xml/stream/XMLStreamWriter.setPrefix:(Ljava/lang/String;Ljava/lang/String;)V
     105: aload         5
     107: invokevirtual #125                // Method java/lang/String.trim:()Ljava/lang/String;
     110: invokevirtual #126                // Method java/lang/String.length:()I
     113: ifle          141
     116: aload_3
     117: aload         5
     119: invokevirtual #257                // Method java/lang/StringBuffer.append:(Ljava/lang/String;)Ljava/lang/StringBuffer;
     122: ldc           #252                // String :
     124: invokevirtual #257                // Method java/lang/StringBuffer.append:(Ljava/lang/String;)Ljava/lang/StringBuffer;
     127: aload_1
     128: iload         6
     130: aaload
     131: invokestatic  #253                // Method org/apache/axis2/databinding/utils/ConverterUtil.convertToString:(Ljavax/xml/namespace/QName;)Ljava/lang/String;
     134: invokevirtual #257                // Method java/lang/StringBuffer.append:(Ljava/lang/String;)Ljava/lang/StringBuffer;
     137: pop
     138: goto          168
     141: aload_3
     142: aload_1
     143: iload         6
     145: aaload
     146: invokestatic  #253                // Method org/apache/axis2/databinding/utils/ConverterUtil.convertToString:(Ljavax/xml/namespace/QName;)Ljava/lang/String;
     149: invokevirtual #257                // Method java/lang/StringBuffer.append:(Ljava/lang/String;)Ljava/lang/StringBuffer;
     152: pop
     153: goto          168
     156: aload_3
     157: aload_1
     158: iload         6
     160: aaload
     161: invokestatic  #253                // Method org/apache/axis2/databinding/utils/ConverterUtil.convertToString:(Ljavax/xml/namespace/QName;)Ljava/lang/String;
     164: invokevirtual #257                // Method java/lang/StringBuffer.append:(Ljava/lang/String;)Ljava/lang/StringBuffer;
     167: pop
     168: iinc          6, 1
     171: goto          21
     174: aload_2
     175: aload_3
     176: invokevirtual #258                // Method java/lang/StringBuffer.toString:()Ljava/lang/String;
     179: invokeinterface #141,  2          // InterfaceMethod javax/xml/stream/XMLStreamWriter.writeCharacters:(Ljava/lang/String;)V
     184: return

  private java.lang.String registerPrefix(javax.xml.stream.XMLStreamWriter, java.lang.String) throws javax.xml.stream.XMLStreamException;
    Code:
       0: aload_1
       1: aload_2
       2: invokeinterface #244,  2          // InterfaceMethod javax/xml/stream/XMLStreamWriter.getPrefix:(Ljava/lang/String;)Ljava/lang/String;
       7: astore_3
       8: aload_3
       9: ifnonnull     74
      12: aload_2
      13: invokestatic  #247                // Method generatePrefix:(Ljava/lang/String;)Ljava/lang/String;
      16: astore_3
      17: aload_1
      18: invokeinterface #259,  1          // InterfaceMethod javax/xml/stream/XMLStreamWriter.getNamespaceContext:()Ljavax/xml/namespace/NamespaceContext;
      23: astore        4
      25: aload         4
      27: aload_3
      28: invokeinterface #260,  2          // InterfaceMethod javax/xml/namespace/NamespaceContext.getNamespaceURI:(Ljava/lang/String;)Ljava/lang/String;
      33: astore        5
      35: aload         5
      37: ifnull        58
      40: aload         5
      42: invokevirtual #126                // Method java/lang/String.length:()I
      45: ifne          51
      48: goto          58
      51: invokestatic  #243                // Method org/apache/axis2/databinding/utils/BeanUtil.getUniquePrefix:()Ljava/lang/String;
      54: astore_3
      55: goto          25
      58: aload_1
      59: aload_3
      60: aload_2
      61: invokeinterface #248,  3          // InterfaceMethod javax/xml/stream/XMLStreamWriter.writeNamespace:(Ljava/lang/String;Ljava/lang/String;)V
      66: aload_1
      67: aload_3
      68: aload_2
      69: invokeinterface #249,  3          // InterfaceMethod javax/xml/stream/XMLStreamWriter.setPrefix:(Ljava/lang/String;Ljava/lang/String;)V
      74: aload_3
      75: areturn
}
