Compiled from "SprayVariable.java"
public class org.hpccsystems.ws.client.gen.axis2.filespray.v1_20.SprayVariable implements org.apache.axis2.databinding.ADBBean {
  public static final javax.xml.namespace.QName MY_QNAME;

  protected java.lang.String localSourceIP;

  protected boolean localSourceIPTracker;

  protected java.lang.String localSourcePath;

  protected boolean localSourcePathTracker;

  protected javax.activation.DataHandler localSrcxml;

  protected boolean localSrcxmlTracker;

  protected int localSourceMaxRecordSize;

  protected boolean localSourceMaxRecordSizeTracker;

  protected int localSourceFormat;

  protected boolean localSourceFormatTracker;

  protected boolean localNoSourceCsvSeparator;

  protected boolean localNoSourceCsvSeparatorTracker;

  protected java.lang.String localSourceCsvSeparate;

  protected boolean localSourceCsvSeparateTracker;

  protected java.lang.String localSourceCsvTerminate;

  protected boolean localSourceCsvTerminateTracker;

  protected java.lang.String localSourceCsvQuote;

  protected boolean localSourceCsvQuoteTracker;

  protected java.lang.String localSourceCsvEscape;

  protected boolean localSourceCsvEscapeTracker;

  protected java.lang.String localSourceRowTag;

  protected boolean localSourceRowTagTracker;

  protected java.lang.String localDestGroup;

  protected boolean localDestGroupTracker;

  protected java.lang.String localDestLogicalName;

  protected boolean localDestLogicalNameTracker;

  protected boolean localOverwrite;

  protected boolean localOverwriteTracker;

  protected boolean localReplicate;

  protected boolean localReplicateTracker;

  protected int localReplicateOffset;

  protected boolean localReplicateOffsetTracker;

  protected int localMaxConnections;

  protected boolean localMaxConnectionsTracker;

  protected int localThrottle;

  protected boolean localThrottleTracker;

  protected int localTransferBufferSize;

  protected boolean localTransferBufferSizeTracker;

  protected java.lang.String localPrefix;

  protected boolean localPrefixTracker;

  protected boolean localNosplit;

  protected boolean localNosplitTracker;

  protected boolean localNorecover;

  protected boolean localNorecoverTracker;

  protected boolean localCompress;

  protected boolean localCompressTracker;

  protected boolean localPush;

  protected boolean localPushTracker;

  protected boolean localPull;

  protected boolean localPullTracker;

  protected boolean localNoCommon;

  protected boolean localNoCommonTracker;

  protected java.lang.String localEncrypt;

  protected boolean localEncryptTracker;

  protected java.lang.String localDecrypt;

  protected boolean localDecryptTracker;

  protected boolean localFailIfNoSourceFile;

  protected boolean localFailIfNoSourceFileTracker;

  protected boolean localRecordStructurePresent;

  protected boolean localRecordStructurePresentTracker;

  protected boolean localQuotedTerminator;

  protected boolean localQuotedTerminatorTracker;

  protected java.lang.String localSourceRowPath;

  protected boolean localSourceRowPathTracker;

  protected boolean localIsJSON;

  protected boolean localIsJSONTracker;

  protected int localExpireDays;

  protected boolean localExpireDaysTracker;

  protected java.lang.String localDFUServerQueue;

  protected boolean localDFUServerQueueTracker;

  protected java.lang.String localSrcUsername;

  protected boolean localSrcUsernameTracker;

  protected java.lang.String localSrcPassword;

  protected boolean localSrcPasswordTracker;

  public org.hpccsystems.ws.client.gen.axis2.filespray.v1_20.SprayVariable();
    Code:
       0: aload_0
       1: invokespecial #1                  // Method java/lang/Object."<init>":()V
       4: aload_0
       5: iconst_0
       6: putfield      #2                  // Field localSourceIPTracker:Z
       9: aload_0
      10: iconst_0
      11: putfield      #3                  // Field localSourcePathTracker:Z
      14: aload_0
      15: iconst_0
      16: putfield      #4                  // Field localSrcxmlTracker:Z
      19: aload_0
      20: iconst_0
      21: putfield      #5                  // Field localSourceMaxRecordSizeTracker:Z
      24: aload_0
      25: iconst_0
      26: putfield      #6                  // Field localSourceFormatTracker:Z
      29: aload_0
      30: ldc           #7                  // String false
      32: invokestatic  #8                  // Method org/apache/axis2/databinding/utils/ConverterUtil.convertToBoolean:(Ljava/lang/String;)Z
      35: putfield      #9                  // Field localNoSourceCsvSeparator:Z
      38: aload_0
      39: iconst_0
      40: putfield      #10                 // Field localNoSourceCsvSeparatorTracker:Z
      43: aload_0
      44: iconst_0
      45: putfield      #11                 // Field localSourceCsvSeparateTracker:Z
      48: aload_0
      49: iconst_0
      50: putfield      #12                 // Field localSourceCsvTerminateTracker:Z
      53: aload_0
      54: iconst_0
      55: putfield      #13                 // Field localSourceCsvQuoteTracker:Z
      58: aload_0
      59: iconst_0
      60: putfield      #14                 // Field localSourceCsvEscapeTracker:Z
      63: aload_0
      64: iconst_0
      65: putfield      #15                 // Field localSourceRowTagTracker:Z
      68: aload_0
      69: iconst_0
      70: putfield      #16                 // Field localDestGroupTracker:Z
      73: aload_0
      74: iconst_0
      75: putfield      #17                 // Field localDestLogicalNameTracker:Z
      78: aload_0
      79: iconst_0
      80: putfield      #18                 // Field localOverwriteTracker:Z
      83: aload_0
      84: iconst_0
      85: putfield      #19                 // Field localReplicateTracker:Z
      88: aload_0
      89: ldc           #20                 // String 1
      91: invokestatic  #21                 // Method org/apache/axis2/databinding/utils/ConverterUtil.convertToInt:(Ljava/lang/String;)I
      94: putfield      #22                 // Field localReplicateOffset:I
      97: aload_0
      98: iconst_0
      99: putfield      #23                 // Field localReplicateOffsetTracker:Z
     102: aload_0
     103: iconst_0
     104: putfield      #24                 // Field localMaxConnectionsTracker:Z
     107: aload_0
     108: iconst_0
     109: putfield      #25                 // Field localThrottleTracker:Z
     112: aload_0
     113: iconst_0
     114: putfield      #26                 // Field localTransferBufferSizeTracker:Z
     117: aload_0
     118: iconst_0
     119: putfield      #27                 // Field localPrefixTracker:Z
     122: aload_0
     123: ldc           #7                  // String false
     125: invokestatic  #8                  // Method org/apache/axis2/databinding/utils/ConverterUtil.convertToBoolean:(Ljava/lang/String;)Z
     128: putfield      #28                 // Field localNosplit:Z
     131: aload_0
     132: iconst_0
     133: putfield      #29                 // Field localNosplitTracker:Z
     136: aload_0
     137: ldc           #7                  // String false
     139: invokestatic  #8                  // Method org/apache/axis2/databinding/utils/ConverterUtil.convertToBoolean:(Ljava/lang/String;)Z
     142: putfield      #30                 // Field localNorecover:Z
     145: aload_0
     146: iconst_0
     147: putfield      #31                 // Field localNorecoverTracker:Z
     150: aload_0
     151: ldc           #7                  // String false
     153: invokestatic  #8                  // Method org/apache/axis2/databinding/utils/ConverterUtil.convertToBoolean:(Ljava/lang/String;)Z
     156: putfield      #32                 // Field localCompress:Z
     159: aload_0
     160: iconst_0
     161: putfield      #33                 // Field localCompressTracker:Z
     164: aload_0
     165: ldc           #7                  // String false
     167: invokestatic  #8                  // Method org/apache/axis2/databinding/utils/ConverterUtil.convertToBoolean:(Ljava/lang/String;)Z
     170: putfield      #34                 // Field localPush:Z
     173: aload_0
     174: iconst_0
     175: putfield      #35                 // Field localPushTracker:Z
     178: aload_0
     179: ldc           #7                  // String false
     181: invokestatic  #8                  // Method org/apache/axis2/databinding/utils/ConverterUtil.convertToBoolean:(Ljava/lang/String;)Z
     184: putfield      #36                 // Field localPull:Z
     187: aload_0
     188: iconst_0
     189: putfield      #37                 // Field localPullTracker:Z
     192: aload_0
     193: ldc           #38                 // String true
     195: invokestatic  #8                  // Method org/apache/axis2/databinding/utils/ConverterUtil.convertToBoolean:(Ljava/lang/String;)Z
     198: putfield      #39                 // Field localNoCommon:Z
     201: aload_0
     202: iconst_0
     203: putfield      #40                 // Field localNoCommonTracker:Z
     206: aload_0
     207: iconst_0
     208: putfield      #41                 // Field localEncryptTracker:Z
     211: aload_0
     212: iconst_0
     213: putfield      #42                 // Field localDecryptTracker:Z
     216: aload_0
     217: ldc           #7                  // String false
     219: invokestatic  #8                  // Method org/apache/axis2/databinding/utils/ConverterUtil.convertToBoolean:(Ljava/lang/String;)Z
     222: putfield      #43                 // Field localFailIfNoSourceFile:Z
     225: aload_0
     226: iconst_0
     227: putfield      #44                 // Field localFailIfNoSourceFileTracker:Z
     230: aload_0
     231: ldc           #7                  // String false
     233: invokestatic  #8                  // Method org/apache/axis2/databinding/utils/ConverterUtil.convertToBoolean:(Ljava/lang/String;)Z
     236: putfield      #45                 // Field localRecordStructurePresent:Z
     239: aload_0
     240: iconst_0
     241: putfield      #46                 // Field localRecordStructurePresentTracker:Z
     244: aload_0
     245: ldc           #38                 // String true
     247: invokestatic  #8                  // Method org/apache/axis2/databinding/utils/ConverterUtil.convertToBoolean:(Ljava/lang/String;)Z
     250: putfield      #47                 // Field localQuotedTerminator:Z
     253: aload_0
     254: iconst_0
     255: putfield      #48                 // Field localQuotedTerminatorTracker:Z
     258: aload_0
     259: iconst_0
     260: putfield      #49                 // Field localSourceRowPathTracker:Z
     263: aload_0
     264: ldc           #7                  // String false
     266: invokestatic  #8                  // Method org/apache/axis2/databinding/utils/ConverterUtil.convertToBoolean:(Ljava/lang/String;)Z
     269: putfield      #50                 // Field localIsJSON:Z
     272: aload_0
     273: iconst_0
     274: putfield      #51                 // Field localIsJSONTracker:Z
     277: aload_0
     278: iconst_0
     279: putfield      #52                 // Field localExpireDaysTracker:Z
     282: aload_0
     283: iconst_0
     284: putfield      #53                 // Field localDFUServerQueueTracker:Z
     287: aload_0
     288: iconst_0
     289: putfield      #54                 // Field localSrcUsernameTracker:Z
     292: aload_0
     293: iconst_0
     294: putfield      #55                 // Field localSrcPasswordTracker:Z
     297: return

  public boolean isSourceIPSpecified();
    Code:
       0: aload_0
       1: getfield      #2                  // Field localSourceIPTracker:Z
       4: ireturn

  public java.lang.String getSourceIP();
    Code:
       0: aload_0
       1: getfield      #56                 // Field localSourceIP:Ljava/lang/String;
       4: areturn

  public void setSourceIP(java.lang.String);
    Code:
       0: aload_0
       1: aload_1
       2: ifnull        9
       5: iconst_1
       6: goto          10
       9: iconst_0
      10: putfield      #2                  // Field localSourceIPTracker:Z
      13: aload_0
      14: aload_1
      15: putfield      #56                 // Field localSourceIP:Ljava/lang/String;
      18: return

  public boolean isSourcePathSpecified();
    Code:
       0: aload_0
       1: getfield      #3                  // Field localSourcePathTracker:Z
       4: ireturn

  public java.lang.String getSourcePath();
    Code:
       0: aload_0
       1: getfield      #57                 // Field localSourcePath:Ljava/lang/String;
       4: areturn

  public void setSourcePath(java.lang.String);
    Code:
       0: aload_0
       1: aload_1
       2: ifnull        9
       5: iconst_1
       6: goto          10
       9: iconst_0
      10: putfield      #3                  // Field localSourcePathTracker:Z
      13: aload_0
      14: aload_1
      15: putfield      #57                 // Field localSourcePath:Ljava/lang/String;
      18: return

  public boolean isSrcxmlSpecified();
    Code:
       0: aload_0
       1: getfield      #4                  // Field localSrcxmlTracker:Z
       4: ireturn

  public javax.activation.DataHandler getSrcxml();
    Code:
       0: aload_0
       1: getfield      #58                 // Field localSrcxml:Ljavax/activation/DataHandler;
       4: areturn

  public void setSrcxml(javax.activation.DataHandler);
    Code:
       0: aload_0
       1: aload_1
       2: ifnull        9
       5: iconst_1
       6: goto          10
       9: iconst_0
      10: putfield      #4                  // Field localSrcxmlTracker:Z
      13: aload_0
      14: aload_1
      15: putfield      #58                 // Field localSrcxml:Ljavax/activation/DataHandler;
      18: return

  public boolean isSourceMaxRecordSizeSpecified();
    Code:
       0: aload_0
       1: getfield      #5                  // Field localSourceMaxRecordSizeTracker:Z
       4: ireturn

  public int getSourceMaxRecordSize();
    Code:
       0: aload_0
       1: getfield      #59                 // Field localSourceMaxRecordSize:I
       4: ireturn

  public void setSourceMaxRecordSize(int);
    Code:
       0: aload_0
       1: iload_1
       2: ldc           #61                 // int -2147483648
       4: if_icmpeq     11
       7: iconst_1
       8: goto          12
      11: iconst_0
      12: putfield      #5                  // Field localSourceMaxRecordSizeTracker:Z
      15: aload_0
      16: iload_1
      17: putfield      #59                 // Field localSourceMaxRecordSize:I
      20: return

  public boolean isSourceFormatSpecified();
    Code:
       0: aload_0
       1: getfield      #6                  // Field localSourceFormatTracker:Z
       4: ireturn

  public int getSourceFormat();
    Code:
       0: aload_0
       1: getfield      #62                 // Field localSourceFormat:I
       4: ireturn

  public void setSourceFormat(int);
    Code:
       0: aload_0
       1: iload_1
       2: ldc           #61                 // int -2147483648
       4: if_icmpeq     11
       7: iconst_1
       8: goto          12
      11: iconst_0
      12: putfield      #6                  // Field localSourceFormatTracker:Z
      15: aload_0
      16: iload_1
      17: putfield      #62                 // Field localSourceFormat:I
      20: return

  public boolean isNoSourceCsvSeparatorSpecified();
    Code:
       0: aload_0
       1: getfield      #10                 // Field localNoSourceCsvSeparatorTracker:Z
       4: ireturn

  public boolean getNoSourceCsvSeparator();
    Code:
       0: aload_0
       1: getfield      #9                  // Field localNoSourceCsvSeparator:Z
       4: ireturn

  public void setNoSourceCsvSeparator(boolean);
    Code:
       0: aload_0
       1: iconst_1
       2: putfield      #10                 // Field localNoSourceCsvSeparatorTracker:Z
       5: aload_0
       6: iload_1
       7: putfield      #9                  // Field localNoSourceCsvSeparator:Z
      10: return

  public boolean isSourceCsvSeparateSpecified();
    Code:
       0: aload_0
       1: getfield      #11                 // Field localSourceCsvSeparateTracker:Z
       4: ireturn

  public java.lang.String getSourceCsvSeparate();
    Code:
       0: aload_0
       1: getfield      #63                 // Field localSourceCsvSeparate:Ljava/lang/String;
       4: areturn

  public void setSourceCsvSeparate(java.lang.String);
    Code:
       0: aload_0
       1: aload_1
       2: ifnull        9
       5: iconst_1
       6: goto          10
       9: iconst_0
      10: putfield      #11                 // Field localSourceCsvSeparateTracker:Z
      13: aload_0
      14: aload_1
      15: putfield      #63                 // Field localSourceCsvSeparate:Ljava/lang/String;
      18: return

  public boolean isSourceCsvTerminateSpecified();
    Code:
       0: aload_0
       1: getfield      #12                 // Field localSourceCsvTerminateTracker:Z
       4: ireturn

  public java.lang.String getSourceCsvTerminate();
    Code:
       0: aload_0
       1: getfield      #64                 // Field localSourceCsvTerminate:Ljava/lang/String;
       4: areturn

  public void setSourceCsvTerminate(java.lang.String);
    Code:
       0: aload_0
       1: aload_1
       2: ifnull        9
       5: iconst_1
       6: goto          10
       9: iconst_0
      10: putfield      #12                 // Field localSourceCsvTerminateTracker:Z
      13: aload_0
      14: aload_1
      15: putfield      #64                 // Field localSourceCsvTerminate:Ljava/lang/String;
      18: return

  public boolean isSourceCsvQuoteSpecified();
    Code:
       0: aload_0
       1: getfield      #13                 // Field localSourceCsvQuoteTracker:Z
       4: ireturn

  public java.lang.String getSourceCsvQuote();
    Code:
       0: aload_0
       1: getfield      #65                 // Field localSourceCsvQuote:Ljava/lang/String;
       4: areturn

  public void setSourceCsvQuote(java.lang.String);
    Code:
       0: aload_0
       1: aload_1
       2: ifnull        9
       5: iconst_1
       6: goto          10
       9: iconst_0
      10: putfield      #13                 // Field localSourceCsvQuoteTracker:Z
      13: aload_0
      14: aload_1
      15: putfield      #65                 // Field localSourceCsvQuote:Ljava/lang/String;
      18: return

  public boolean isSourceCsvEscapeSpecified();
    Code:
       0: aload_0
       1: getfield      #14                 // Field localSourceCsvEscapeTracker:Z
       4: ireturn

  public java.lang.String getSourceCsvEscape();
    Code:
       0: aload_0
       1: getfield      #66                 // Field localSourceCsvEscape:Ljava/lang/String;
       4: areturn

  public void setSourceCsvEscape(java.lang.String);
    Code:
       0: aload_0
       1: aload_1
       2: ifnull        9
       5: iconst_1
       6: goto          10
       9: iconst_0
      10: putfield      #14                 // Field localSourceCsvEscapeTracker:Z
      13: aload_0
      14: aload_1
      15: putfield      #66                 // Field localSourceCsvEscape:Ljava/lang/String;
      18: return

  public boolean isSourceRowTagSpecified();
    Code:
       0: aload_0
       1: getfield      #15                 // Field localSourceRowTagTracker:Z
       4: ireturn

  public java.lang.String getSourceRowTag();
    Code:
       0: aload_0
       1: getfield      #67                 // Field localSourceRowTag:Ljava/lang/String;
       4: areturn

  public void setSourceRowTag(java.lang.String);
    Code:
       0: aload_0
       1: aload_1
       2: ifnull        9
       5: iconst_1
       6: goto          10
       9: iconst_0
      10: putfield      #15                 // Field localSourceRowTagTracker:Z
      13: aload_0
      14: aload_1
      15: putfield      #67                 // Field localSourceRowTag:Ljava/lang/String;
      18: return

  public boolean isDestGroupSpecified();
    Code:
       0: aload_0
       1: getfield      #16                 // Field localDestGroupTracker:Z
       4: ireturn

  public java.lang.String getDestGroup();
    Code:
       0: aload_0
       1: getfield      #68                 // Field localDestGroup:Ljava/lang/String;
       4: areturn

  public void setDestGroup(java.lang.String);
    Code:
       0: aload_0
       1: aload_1
       2: ifnull        9
       5: iconst_1
       6: goto          10
       9: iconst_0
      10: putfield      #16                 // Field localDestGroupTracker:Z
      13: aload_0
      14: aload_1
      15: putfield      #68                 // Field localDestGroup:Ljava/lang/String;
      18: return

  public boolean isDestLogicalNameSpecified();
    Code:
       0: aload_0
       1: getfield      #17                 // Field localDestLogicalNameTracker:Z
       4: ireturn

  public java.lang.String getDestLogicalName();
    Code:
       0: aload_0
       1: getfield      #69                 // Field localDestLogicalName:Ljava/lang/String;
       4: areturn

  public void setDestLogicalName(java.lang.String);
    Code:
       0: aload_0
       1: aload_1
       2: ifnull        9
       5: iconst_1
       6: goto          10
       9: iconst_0
      10: putfield      #17                 // Field localDestLogicalNameTracker:Z
      13: aload_0
      14: aload_1
      15: putfield      #69                 // Field localDestLogicalName:Ljava/lang/String;
      18: return

  public boolean isOverwriteSpecified();
    Code:
       0: aload_0
       1: getfield      #18                 // Field localOverwriteTracker:Z
       4: ireturn

  public boolean getOverwrite();
    Code:
       0: aload_0
       1: getfield      #70                 // Field localOverwrite:Z
       4: ireturn

  public void setOverwrite(boolean);
    Code:
       0: aload_0
       1: iconst_1
       2: putfield      #18                 // Field localOverwriteTracker:Z
       5: aload_0
       6: iload_1
       7: putfield      #70                 // Field localOverwrite:Z
      10: return

  public boolean isReplicateSpecified();
    Code:
       0: aload_0
       1: getfield      #19                 // Field localReplicateTracker:Z
       4: ireturn

  public boolean getReplicate();
    Code:
       0: aload_0
       1: getfield      #71                 // Field localReplicate:Z
       4: ireturn

  public void setReplicate(boolean);
    Code:
       0: aload_0
       1: iconst_1
       2: putfield      #19                 // Field localReplicateTracker:Z
       5: aload_0
       6: iload_1
       7: putfield      #71                 // Field localReplicate:Z
      10: return

  public boolean isReplicateOffsetSpecified();
    Code:
       0: aload_0
       1: getfield      #23                 // Field localReplicateOffsetTracker:Z
       4: ireturn

  public int getReplicateOffset();
    Code:
       0: aload_0
       1: getfield      #22                 // Field localReplicateOffset:I
       4: ireturn

  public void setReplicateOffset(int);
    Code:
       0: aload_0
       1: iload_1
       2: ldc           #61                 // int -2147483648
       4: if_icmpeq     11
       7: iconst_1
       8: goto          12
      11: iconst_0
      12: putfield      #23                 // Field localReplicateOffsetTracker:Z
      15: aload_0
      16: iload_1
      17: putfield      #22                 // Field localReplicateOffset:I
      20: return

  public boolean isMaxConnectionsSpecified();
    Code:
       0: aload_0
       1: getfield      #24                 // Field localMaxConnectionsTracker:Z
       4: ireturn

  public int getMaxConnections();
    Code:
       0: aload_0
       1: getfield      #72                 // Field localMaxConnections:I
       4: ireturn

  public void setMaxConnections(int);
    Code:
       0: aload_0
       1: iload_1
       2: ldc           #61                 // int -2147483648
       4: if_icmpeq     11
       7: iconst_1
       8: goto          12
      11: iconst_0
      12: putfield      #24                 // Field localMaxConnectionsTracker:Z
      15: aload_0
      16: iload_1
      17: putfield      #72                 // Field localMaxConnections:I
      20: return

  public boolean isThrottleSpecified();
    Code:
       0: aload_0
       1: getfield      #25                 // Field localThrottleTracker:Z
       4: ireturn

  public int getThrottle();
    Code:
       0: aload_0
       1: getfield      #73                 // Field localThrottle:I
       4: ireturn

  public void setThrottle(int);
    Code:
       0: aload_0
       1: iload_1
       2: ldc           #61                 // int -2147483648
       4: if_icmpeq     11
       7: iconst_1
       8: goto          12
      11: iconst_0
      12: putfield      #25                 // Field localThrottleTracker:Z
      15: aload_0
      16: iload_1
      17: putfield      #73                 // Field localThrottle:I
      20: return

  public boolean isTransferBufferSizeSpecified();
    Code:
       0: aload_0
       1: getfield      #26                 // Field localTransferBufferSizeTracker:Z
       4: ireturn

  public int getTransferBufferSize();
    Code:
       0: aload_0
       1: getfield      #74                 // Field localTransferBufferSize:I
       4: ireturn

  public void setTransferBufferSize(int);
    Code:
       0: aload_0
       1: iload_1
       2: ldc           #61                 // int -2147483648
       4: if_icmpeq     11
       7: iconst_1
       8: goto          12
      11: iconst_0
      12: putfield      #26                 // Field localTransferBufferSizeTracker:Z
      15: aload_0
      16: iload_1
      17: putfield      #74                 // Field localTransferBufferSize:I
      20: return

  public boolean isPrefixSpecified();
    Code:
       0: aload_0
       1: getfield      #27                 // Field localPrefixTracker:Z
       4: ireturn

  public java.lang.String getPrefix();
    Code:
       0: aload_0
       1: getfield      #75                 // Field localPrefix:Ljava/lang/String;
       4: areturn

  public void setPrefix(java.lang.String);
    Code:
       0: aload_0
       1: aload_1
       2: ifnull        9
       5: iconst_1
       6: goto          10
       9: iconst_0
      10: putfield      #27                 // Field localPrefixTracker:Z
      13: aload_0
      14: aload_1
      15: putfield      #75                 // Field localPrefix:Ljava/lang/String;
      18: return

  public boolean isNosplitSpecified();
    Code:
       0: aload_0
       1: getfield      #29                 // Field localNosplitTracker:Z
       4: ireturn

  public boolean getNosplit();
    Code:
       0: aload_0
       1: getfield      #28                 // Field localNosplit:Z
       4: ireturn

  public void setNosplit(boolean);
    Code:
       0: aload_0
       1: iconst_1
       2: putfield      #29                 // Field localNosplitTracker:Z
       5: aload_0
       6: iload_1
       7: putfield      #28                 // Field localNosplit:Z
      10: return

  public boolean isNorecoverSpecified();
    Code:
       0: aload_0
       1: getfield      #31                 // Field localNorecoverTracker:Z
       4: ireturn

  public boolean getNorecover();
    Code:
       0: aload_0
       1: getfield      #30                 // Field localNorecover:Z
       4: ireturn

  public void setNorecover(boolean);
    Code:
       0: aload_0
       1: iconst_1
       2: putfield      #31                 // Field localNorecoverTracker:Z
       5: aload_0
       6: iload_1
       7: putfield      #30                 // Field localNorecover:Z
      10: return

  public boolean isCompressSpecified();
    Code:
       0: aload_0
       1: getfield      #33                 // Field localCompressTracker:Z
       4: ireturn

  public boolean getCompress();
    Code:
       0: aload_0
       1: getfield      #32                 // Field localCompress:Z
       4: ireturn

  public void setCompress(boolean);
    Code:
       0: aload_0
       1: iconst_1
       2: putfield      #33                 // Field localCompressTracker:Z
       5: aload_0
       6: iload_1
       7: putfield      #32                 // Field localCompress:Z
      10: return

  public boolean isPushSpecified();
    Code:
       0: aload_0
       1: getfield      #35                 // Field localPushTracker:Z
       4: ireturn

  public boolean getPush();
    Code:
       0: aload_0
       1: getfield      #34                 // Field localPush:Z
       4: ireturn

  public void setPush(boolean);
    Code:
       0: aload_0
       1: iconst_1
       2: putfield      #35                 // Field localPushTracker:Z
       5: aload_0
       6: iload_1
       7: putfield      #34                 // Field localPush:Z
      10: return

  public boolean isPullSpecified();
    Code:
       0: aload_0
       1: getfield      #37                 // Field localPullTracker:Z
       4: ireturn

  public boolean getPull();
    Code:
       0: aload_0
       1: getfield      #36                 // Field localPull:Z
       4: ireturn

  public void setPull(boolean);
    Code:
       0: aload_0
       1: iconst_1
       2: putfield      #37                 // Field localPullTracker:Z
       5: aload_0
       6: iload_1
       7: putfield      #36                 // Field localPull:Z
      10: return

  public boolean isNoCommonSpecified();
    Code:
       0: aload_0
       1: getfield      #40                 // Field localNoCommonTracker:Z
       4: ireturn

  public boolean getNoCommon();
    Code:
       0: aload_0
       1: getfield      #39                 // Field localNoCommon:Z
       4: ireturn

  public void setNoCommon(boolean);
    Code:
       0: aload_0
       1: iconst_1
       2: putfield      #40                 // Field localNoCommonTracker:Z
       5: aload_0
       6: iload_1
       7: putfield      #39                 // Field localNoCommon:Z
      10: return

  public boolean isEncryptSpecified();
    Code:
       0: aload_0
       1: getfield      #41                 // Field localEncryptTracker:Z
       4: ireturn

  public java.lang.String getEncrypt();
    Code:
       0: aload_0
       1: getfield      #76                 // Field localEncrypt:Ljava/lang/String;
       4: areturn

  public void setEncrypt(java.lang.String);
    Code:
       0: aload_0
       1: aload_1
       2: ifnull        9
       5: iconst_1
       6: goto          10
       9: iconst_0
      10: putfield      #41                 // Field localEncryptTracker:Z
      13: aload_0
      14: aload_1
      15: putfield      #76                 // Field localEncrypt:Ljava/lang/String;
      18: return

  public boolean isDecryptSpecified();
    Code:
       0: aload_0
       1: getfield      #42                 // Field localDecryptTracker:Z
       4: ireturn

  public java.lang.String getDecrypt();
    Code:
       0: aload_0
       1: getfield      #77                 // Field localDecrypt:Ljava/lang/String;
       4: areturn

  public void setDecrypt(java.lang.String);
    Code:
       0: aload_0
       1: aload_1
       2: ifnull        9
       5: iconst_1
       6: goto          10
       9: iconst_0
      10: putfield      #42                 // Field localDecryptTracker:Z
      13: aload_0
      14: aload_1
      15: putfield      #77                 // Field localDecrypt:Ljava/lang/String;
      18: return

  public boolean isFailIfNoSourceFileSpecified();
    Code:
       0: aload_0
       1: getfield      #44                 // Field localFailIfNoSourceFileTracker:Z
       4: ireturn

  public boolean getFailIfNoSourceFile();
    Code:
       0: aload_0
       1: getfield      #43                 // Field localFailIfNoSourceFile:Z
       4: ireturn

  public void setFailIfNoSourceFile(boolean);
    Code:
       0: aload_0
       1: iconst_1
       2: putfield      #44                 // Field localFailIfNoSourceFileTracker:Z
       5: aload_0
       6: iload_1
       7: putfield      #43                 // Field localFailIfNoSourceFile:Z
      10: return

  public boolean isRecordStructurePresentSpecified();
    Code:
       0: aload_0
       1: getfield      #46                 // Field localRecordStructurePresentTracker:Z
       4: ireturn

  public boolean getRecordStructurePresent();
    Code:
       0: aload_0
       1: getfield      #45                 // Field localRecordStructurePresent:Z
       4: ireturn

  public void setRecordStructurePresent(boolean);
    Code:
       0: aload_0
       1: iconst_1
       2: putfield      #46                 // Field localRecordStructurePresentTracker:Z
       5: aload_0
       6: iload_1
       7: putfield      #45                 // Field localRecordStructurePresent:Z
      10: return

  public boolean isQuotedTerminatorSpecified();
    Code:
       0: aload_0
       1: getfield      #48                 // Field localQuotedTerminatorTracker:Z
       4: ireturn

  public boolean getQuotedTerminator();
    Code:
       0: aload_0
       1: getfield      #47                 // Field localQuotedTerminator:Z
       4: ireturn

  public void setQuotedTerminator(boolean);
    Code:
       0: aload_0
       1: iconst_1
       2: putfield      #48                 // Field localQuotedTerminatorTracker:Z
       5: aload_0
       6: iload_1
       7: putfield      #47                 // Field localQuotedTerminator:Z
      10: return

  public boolean isSourceRowPathSpecified();
    Code:
       0: aload_0
       1: getfield      #49                 // Field localSourceRowPathTracker:Z
       4: ireturn

  public java.lang.String getSourceRowPath();
    Code:
       0: aload_0
       1: getfield      #78                 // Field localSourceRowPath:Ljava/lang/String;
       4: areturn

  public void setSourceRowPath(java.lang.String);
    Code:
       0: aload_0
       1: aload_1
       2: ifnull        9
       5: iconst_1
       6: goto          10
       9: iconst_0
      10: putfield      #49                 // Field localSourceRowPathTracker:Z
      13: aload_0
      14: aload_1
      15: putfield      #78                 // Field localSourceRowPath:Ljava/lang/String;
      18: return

  public boolean isIsJSONSpecified();
    Code:
       0: aload_0
       1: getfield      #51                 // Field localIsJSONTracker:Z
       4: ireturn

  public boolean getIsJSON();
    Code:
       0: aload_0
       1: getfield      #50                 // Field localIsJSON:Z
       4: ireturn

  public void setIsJSON(boolean);
    Code:
       0: aload_0
       1: iconst_1
       2: putfield      #51                 // Field localIsJSONTracker:Z
       5: aload_0
       6: iload_1
       7: putfield      #50                 // Field localIsJSON:Z
      10: return

  public boolean isExpireDaysSpecified();
    Code:
       0: aload_0
       1: getfield      #52                 // Field localExpireDaysTracker:Z
       4: ireturn

  public int getExpireDays();
    Code:
       0: aload_0
       1: getfield      #79                 // Field localExpireDays:I
       4: ireturn

  public void setExpireDays(int);
    Code:
       0: aload_0
       1: iload_1
       2: ldc           #61                 // int -2147483648
       4: if_icmpeq     11
       7: iconst_1
       8: goto          12
      11: iconst_0
      12: putfield      #52                 // Field localExpireDaysTracker:Z
      15: aload_0
      16: iload_1
      17: putfield      #79                 // Field localExpireDays:I
      20: return

  public boolean isDFUServerQueueSpecified();
    Code:
       0: aload_0
       1: getfield      #53                 // Field localDFUServerQueueTracker:Z
       4: ireturn

  public java.lang.String getDFUServerQueue();
    Code:
       0: aload_0
       1: getfield      #80                 // Field localDFUServerQueue:Ljava/lang/String;
       4: areturn

  public void setDFUServerQueue(java.lang.String);
    Code:
       0: aload_0
       1: aload_1
       2: ifnull        9
       5: iconst_1
       6: goto          10
       9: iconst_0
      10: putfield      #53                 // Field localDFUServerQueueTracker:Z
      13: aload_0
      14: aload_1
      15: putfield      #80                 // Field localDFUServerQueue:Ljava/lang/String;
      18: return

  public boolean isSrcUsernameSpecified();
    Code:
       0: aload_0
       1: getfield      #54                 // Field localSrcUsernameTracker:Z
       4: ireturn

  public java.lang.String getSrcUsername();
    Code:
       0: aload_0
       1: getfield      #81                 // Field localSrcUsername:Ljava/lang/String;
       4: areturn

  public void setSrcUsername(java.lang.String);
    Code:
       0: aload_0
       1: aload_1
       2: ifnull        9
       5: iconst_1
       6: goto          10
       9: iconst_0
      10: putfield      #54                 // Field localSrcUsernameTracker:Z
      13: aload_0
      14: aload_1
      15: putfield      #81                 // Field localSrcUsername:Ljava/lang/String;
      18: return

  public boolean isSrcPasswordSpecified();
    Code:
       0: aload_0
       1: getfield      #55                 // Field localSrcPasswordTracker:Z
       4: ireturn

  public java.lang.String getSrcPassword();
    Code:
       0: aload_0
       1: getfield      #82                 // Field localSrcPassword:Ljava/lang/String;
       4: areturn

  public void setSrcPassword(java.lang.String);
    Code:
       0: aload_0
       1: aload_1
       2: ifnull        9
       5: iconst_1
       6: goto          10
       9: iconst_0
      10: putfield      #55                 // Field localSrcPasswordTracker:Z
      13: aload_0
      14: aload_1
      15: putfield      #82                 // Field localSrcPassword:Ljava/lang/String;
      18: return

  public org.apache.axiom.om.OMElement getOMElement(javax.xml.namespace.QName, org.apache.axiom.om.OMFactory) throws org.apache.axis2.databinding.ADBException;
    Code:
       0: aload_2
       1: new           #83                 // class org/apache/axis2/databinding/ADBDataSource
       4: dup
       5: aload_0
       6: getstatic     #84                 // Field MY_QNAME:Ljavax/xml/namespace/QName;
       9: invokespecial #85                 // Method org/apache/axis2/databinding/ADBDataSource."<init>":(Lorg/apache/axis2/databinding/ADBBean;Ljavax/xml/namespace/QName;)V
      12: invokeinterface #86,  2           // InterfaceMethod org/apache/axiom/om/OMFactory.createOMElement:(Lorg/apache/axiom/om/OMDataSource;)Lorg/apache/axiom/om/OMSourcedElement;
      17: areturn

  public void serialize(javax.xml.namespace.QName, javax.xml.stream.XMLStreamWriter) throws javax.xml.stream.XMLStreamException, org.apache.axis2.databinding.ADBException;
    Code:
       0: aload_0
       1: aload_1
       2: aload_2
       3: iconst_0
       4: invokevirtual #87                 // Method serialize:(Ljavax/xml/namespace/QName;Ljavax/xml/stream/XMLStreamWriter;Z)V
       7: return

  public void serialize(javax.xml.namespace.QName, javax.xml.stream.XMLStreamWriter, boolean) throws javax.xml.stream.XMLStreamException, org.apache.axis2.databinding.ADBException;
    Code:
       0: aconst_null
       1: astore        4
       3: aconst_null
       4: astore        5
       6: aload_1
       7: invokevirtual #88                 // Method javax/xml/namespace/QName.getPrefix:()Ljava/lang/String;
      10: astore        4
      12: aload_1
      13: invokevirtual #89                 // Method javax/xml/namespace/QName.getNamespaceURI:()Ljava/lang/String;
      16: astore        5
      18: aload_0
      19: aload         4
      21: aload         5
      23: aload_1
      24: invokevirtual #90                 // Method javax/xml/namespace/QName.getLocalPart:()Ljava/lang/String;
      27: aload_2
      28: invokespecial #91                 // Method writeStartElement:(Ljava/lang/String;Ljava/lang/String;Ljava/lang/String;Ljavax/xml/stream/XMLStreamWriter;)V
      31: iload_3
      32: ifeq          107
      35: aload_0
      36: aload_2
      37: ldc           #92                 // String urn:hpccsystems:ws:filespray
      39: invokespecial #93                 // Method registerPrefix:(Ljavax/xml/stream/XMLStreamWriter;Ljava/lang/String;)Ljava/lang/String;
      42: astore        6
      44: aload         6
      46: ifnull        94
      49: aload         6
      51: invokevirtual #94                 // Method java/lang/String.trim:()Ljava/lang/String;
      54: invokevirtual #95                 // Method java/lang/String.length:()I
      57: ifle          94
      60: aload_0
      61: ldc           #96                 // String xsi
      63: ldc           #97                 // String http://www.w3.org/2001/XMLSchema-instance
      65: ldc           #98                 // String type
      67: new           #99                 // class java/lang/StringBuilder
      70: dup
      71: invokespecial #100                // Method java/lang/StringBuilder."<init>":()V
      74: aload         6
      76: invokevirtual #101                // Method java/lang/StringBuilder.append:(Ljava/lang/String;)Ljava/lang/StringBuilder;
      79: ldc           #102                // String :SprayVariable
      81: invokevirtual #101                // Method java/lang/StringBuilder.append:(Ljava/lang/String;)Ljava/lang/StringBuilder;
      84: invokevirtual #103                // Method java/lang/StringBuilder.toString:()Ljava/lang/String;
      87: aload_2
      88: invokespecial #104                // Method writeAttribute:(Ljava/lang/String;Ljava/lang/String;Ljava/lang/String;Ljava/lang/String;Ljavax/xml/stream/XMLStreamWriter;)V
      91: goto          107
      94: aload_0
      95: ldc           #96                 // String xsi
      97: ldc           #97                 // String http://www.w3.org/2001/XMLSchema-instance
      99: ldc           #98                 // String type
     101: ldc           #105                // String SprayVariable
     103: aload_2
     104: invokespecial #104                // Method writeAttribute:(Ljava/lang/String;Ljava/lang/String;Ljava/lang/String;Ljava/lang/String;Ljavax/xml/stream/XMLStreamWriter;)V
     107: aload_0
     108: getfield      #2                  // Field localSourceIPTracker:Z
     111: ifeq          161
     114: ldc           #92                 // String urn:hpccsystems:ws:filespray
     116: astore        5
     118: aload_0
     119: aconst_null
     120: aload         5
     122: ldc           #106                // String sourceIP
     124: aload_2
     125: invokespecial #91                 // Method writeStartElement:(Ljava/lang/String;Ljava/lang/String;Ljava/lang/String;Ljavax/xml/stream/XMLStreamWriter;)V
     128: aload_0
     129: getfield      #56                 // Field localSourceIP:Ljava/lang/String;
     132: ifnonnull     145
     135: new           #107                // class org/apache/axis2/databinding/ADBException
     138: dup
     139: ldc           #108                // String sourceIP cannot be null!!
     141: invokespecial #109                // Method org/apache/axis2/databinding/ADBException."<init>":(Ljava/lang/String;)V
     144: athrow
     145: aload_2
     146: aload_0
     147: getfield      #56                 // Field localSourceIP:Ljava/lang/String;
     150: invokeinterface #110,  2          // InterfaceMethod javax/xml/stream/XMLStreamWriter.writeCharacters:(Ljava/lang/String;)V
     155: aload_2
     156: invokeinterface #111,  1          // InterfaceMethod javax/xml/stream/XMLStreamWriter.writeEndElement:()V
     161: aload_0
     162: getfield      #3                  // Field localSourcePathTracker:Z
     165: ifeq          215
     168: ldc           #92                 // String urn:hpccsystems:ws:filespray
     170: astore        5
     172: aload_0
     173: aconst_null
     174: aload         5
     176: ldc           #112                // String sourcePath
     178: aload_2
     179: invokespecial #91                 // Method writeStartElement:(Ljava/lang/String;Ljava/lang/String;Ljava/lang/String;Ljavax/xml/stream/XMLStreamWriter;)V
     182: aload_0
     183: getfield      #57                 // Field localSourcePath:Ljava/lang/String;
     186: ifnonnull     199
     189: new           #107                // class org/apache/axis2/databinding/ADBException
     192: dup
     193: ldc           #113                // String sourcePath cannot be null!!
     195: invokespecial #109                // Method org/apache/axis2/databinding/ADBException."<init>":(Ljava/lang/String;)V
     198: athrow
     199: aload_2
     200: aload_0
     201: getfield      #57                 // Field localSourcePath:Ljava/lang/String;
     204: invokeinterface #110,  2          // InterfaceMethod javax/xml/stream/XMLStreamWriter.writeCharacters:(Ljava/lang/String;)V
     209: aload_2
     210: invokeinterface #111,  1          // InterfaceMethod javax/xml/stream/XMLStreamWriter.writeEndElement:()V
     215: aload_0
     216: getfield      #4                  // Field localSrcxmlTracker:Z
     219: ifeq          276
     222: ldc           #92                 // String urn:hpccsystems:ws:filespray
     224: astore        5
     226: aload_0
     227: aconst_null
     228: aload         5
     230: ldc           #114                // String srcxml
     232: aload_2
     233: invokespecial #91                 // Method writeStartElement:(Ljava/lang/String;Ljava/lang/String;Ljava/lang/String;Ljavax/xml/stream/XMLStreamWriter;)V
     236: aload_0
     237: getfield      #58                 // Field localSrcxml:Ljavax/activation/DataHandler;
     240: ifnull        270
     243: aload_2
     244: aload_0
     245: getfield      #58                 // Field localSrcxml:Ljavax/activation/DataHandler;
     248: aconst_null
     249: iconst_1
     250: invokestatic  #115                // Method org/apache/axiom/util/stax/XMLStreamWriterUtils.writeDataHandler:(Ljavax/xml/stream/XMLStreamWriter;Ljavax/activation/DataHandler;Ljava/lang/String;Z)V
     253: goto          270
     256: astore        6
     258: new           #117                // class javax/xml/stream/XMLStreamException
     261: dup
     262: ldc           #118                // String Unable to read data handler for srcxml
     264: aload         6
     266: invokespecial #119                // Method javax/xml/stream/XMLStreamException."<init>":(Ljava/lang/String;Ljava/lang/Throwable;)V
     269: athrow
     270: aload_2
     271: invokeinterface #111,  1          // InterfaceMethod javax/xml/stream/XMLStreamWriter.writeEndElement:()V
     276: aload_0
     277: getfield      #5                  // Field localSourceMaxRecordSizeTracker:Z
     280: ifeq          335
     283: ldc           #92                 // String urn:hpccsystems:ws:filespray
     285: astore        5
     287: aload_0
     288: aconst_null
     289: aload         5
     291: ldc           #120                // String sourceMaxRecordSize
     293: aload_2
     294: invokespecial #91                 // Method writeStartElement:(Ljava/lang/String;Ljava/lang/String;Ljava/lang/String;Ljavax/xml/stream/XMLStreamWriter;)V
     297: aload_0
     298: getfield      #59                 // Field localSourceMaxRecordSize:I
     301: ldc           #61                 // int -2147483648
     303: if_icmpne     316
     306: new           #107                // class org/apache/axis2/databinding/ADBException
     309: dup
     310: ldc           #121                // String sourceMaxRecordSize cannot be null!!
     312: invokespecial #109                // Method org/apache/axis2/databinding/ADBException."<init>":(Ljava/lang/String;)V
     315: athrow
     316: aload_2
     317: aload_0
     318: getfield      #59                 // Field localSourceMaxRecordSize:I
     321: invokestatic  #122                // Method org/apache/axis2/databinding/utils/ConverterUtil.convertToString:(I)Ljava/lang/String;
     324: invokeinterface #110,  2          // InterfaceMethod javax/xml/stream/XMLStreamWriter.writeCharacters:(Ljava/lang/String;)V
     329: aload_2
     330: invokeinterface #111,  1          // InterfaceMethod javax/xml/stream/XMLStreamWriter.writeEndElement:()V
     335: aload_0
     336: getfield      #6                  // Field localSourceFormatTracker:Z
     339: ifeq          394
     342: ldc           #92                 // String urn:hpccsystems:ws:filespray
     344: astore        5
     346: aload_0
     347: aconst_null
     348: aload         5
     350: ldc           #123                // String sourceFormat
     352: aload_2
     353: invokespecial #91                 // Method writeStartElement:(Ljava/lang/String;Ljava/lang/String;Ljava/lang/String;Ljavax/xml/stream/XMLStreamWriter;)V
     356: aload_0
     357: getfield      #62                 // Field localSourceFormat:I
     360: ldc           #61                 // int -2147483648
     362: if_icmpne     375
     365: new           #107                // class org/apache/axis2/databinding/ADBException
     368: dup
     369: ldc           #124                // String sourceFormat cannot be null!!
     371: invokespecial #109                // Method org/apache/axis2/databinding/ADBException."<init>":(Ljava/lang/String;)V
     374: athrow
     375: aload_2
     376: aload_0
     377: getfield      #62                 // Field localSourceFormat:I
     380: invokestatic  #122                // Method org/apache/axis2/databinding/utils/ConverterUtil.convertToString:(I)Ljava/lang/String;
     383: invokeinterface #110,  2          // InterfaceMethod javax/xml/stream/XMLStreamWriter.writeCharacters:(Ljava/lang/String;)V
     388: aload_2
     389: invokeinterface #111,  1          // InterfaceMethod javax/xml/stream/XMLStreamWriter.writeEndElement:()V
     394: aload_0
     395: getfield      #10                 // Field localNoSourceCsvSeparatorTracker:Z
     398: ifeq          434
     401: ldc           #92                 // String urn:hpccsystems:ws:filespray
     403: astore        5
     405: aload_0
     406: aconst_null
     407: aload         5
     409: ldc           #125                // String NoSourceCsvSeparator
     411: aload_2
     412: invokespecial #91                 // Method writeStartElement:(Ljava/lang/String;Ljava/lang/String;Ljava/lang/String;Ljavax/xml/stream/XMLStreamWriter;)V
     415: aload_2
     416: aload_0
     417: getfield      #9                  // Field localNoSourceCsvSeparator:Z
     420: invokestatic  #126                // Method org/apache/axis2/databinding/utils/ConverterUtil.convertToString:(Z)Ljava/lang/String;
     423: invokeinterface #110,  2          // InterfaceMethod javax/xml/stream/XMLStreamWriter.writeCharacters:(Ljava/lang/String;)V
     428: aload_2
     429: invokeinterface #111,  1          // InterfaceMethod javax/xml/stream/XMLStreamWriter.writeEndElement:()V
     434: aload_0
     435: getfield      #11                 // Field localSourceCsvSeparateTracker:Z
     438: ifeq          488
     441: ldc           #92                 // String urn:hpccsystems:ws:filespray
     443: astore        5
     445: aload_0
     446: aconst_null
     447: aload         5
     449: ldc           #127                // String sourceCsvSeparate
     451: aload_2
     452: invokespecial #91                 // Method writeStartElement:(Ljava/lang/String;Ljava/lang/String;Ljava/lang/String;Ljavax/xml/stream/XMLStreamWriter;)V
     455: aload_0
     456: getfield      #63                 // Field localSourceCsvSeparate:Ljava/lang/String;
     459: ifnonnull     472
     462: new           #107                // class org/apache/axis2/databinding/ADBException
     465: dup
     466: ldc           #128                // String sourceCsvSeparate cannot be null!!
     468: invokespecial #109                // Method org/apache/axis2/databinding/ADBException."<init>":(Ljava/lang/String;)V
     471: athrow
     472: aload_2
     473: aload_0
     474: getfield      #63                 // Field localSourceCsvSeparate:Ljava/lang/String;
     477: invokeinterface #110,  2          // InterfaceMethod javax/xml/stream/XMLStreamWriter.writeCharacters:(Ljava/lang/String;)V
     482: aload_2
     483: invokeinterface #111,  1          // InterfaceMethod javax/xml/stream/XMLStreamWriter.writeEndElement:()V
     488: aload_0
     489: getfield      #12                 // Field localSourceCsvTerminateTracker:Z
     492: ifeq          542
     495: ldc           #92                 // String urn:hpccsystems:ws:filespray
     497: astore        5
     499: aload_0
     500: aconst_null
     501: aload         5
     503: ldc           #129                // String sourceCsvTerminate
     505: aload_2
     506: invokespecial #91                 // Method writeStartElement:(Ljava/lang/String;Ljava/lang/String;Ljava/lang/String;Ljavax/xml/stream/XMLStreamWriter;)V
     509: aload_0
     510: getfield      #64                 // Field localSourceCsvTerminate:Ljava/lang/String;
     513: ifnonnull     526
     516: new           #107                // class org/apache/axis2/databinding/ADBException
     519: dup
     520: ldc           #130                // String sourceCsvTerminate cannot be null!!
     522: invokespecial #109                // Method org/apache/axis2/databinding/ADBException."<init>":(Ljava/lang/String;)V
     525: athrow
     526: aload_2
     527: aload_0
     528: getfield      #64                 // Field localSourceCsvTerminate:Ljava/lang/String;
     531: invokeinterface #110,  2          // InterfaceMethod javax/xml/stream/XMLStreamWriter.writeCharacters:(Ljava/lang/String;)V
     536: aload_2
     537: invokeinterface #111,  1          // InterfaceMethod javax/xml/stream/XMLStreamWriter.writeEndElement:()V
     542: aload_0
     543: getfield      #13                 // Field localSourceCsvQuoteTracker:Z
     546: ifeq          596
     549: ldc           #92                 // String urn:hpccsystems:ws:filespray
     551: astore        5
     553: aload_0
     554: aconst_null
     555: aload         5
     557: ldc           #131                // String sourceCsvQuote
     559: aload_2
     560: invokespecial #91                 // Method writeStartElement:(Ljava/lang/String;Ljava/lang/String;Ljava/lang/String;Ljavax/xml/stream/XMLStreamWriter;)V
     563: aload_0
     564: getfield      #65                 // Field localSourceCsvQuote:Ljava/lang/String;
     567: ifnonnull     580
     570: new           #107                // class org/apache/axis2/databinding/ADBException
     573: dup
     574: ldc           #132                // String sourceCsvQuote cannot be null!!
     576: invokespecial #109                // Method org/apache/axis2/databinding/ADBException."<init>":(Ljava/lang/String;)V
     579: athrow
     580: aload_2
     581: aload_0
     582: getfield      #65                 // Field localSourceCsvQuote:Ljava/lang/String;
     585: invokeinterface #110,  2          // InterfaceMethod javax/xml/stream/XMLStreamWriter.writeCharacters:(Ljava/lang/String;)V
     590: aload_2
     591: invokeinterface #111,  1          // InterfaceMethod javax/xml/stream/XMLStreamWriter.writeEndElement:()V
     596: aload_0
     597: getfield      #14                 // Field localSourceCsvEscapeTracker:Z
     600: ifeq          650
     603: ldc           #92                 // String urn:hpccsystems:ws:filespray
     605: astore        5
     607: aload_0
     608: aconst_null
     609: aload         5
     611: ldc           #133                // String sourceCsvEscape
     613: aload_2
     614: invokespecial #91                 // Method writeStartElement:(Ljava/lang/String;Ljava/lang/String;Ljava/lang/String;Ljavax/xml/stream/XMLStreamWriter;)V
     617: aload_0
     618: getfield      #66                 // Field localSourceCsvEscape:Ljava/lang/String;
     621: ifnonnull     634
     624: new           #107                // class org/apache/axis2/databinding/ADBException
     627: dup
     628: ldc           #134                // String sourceCsvEscape cannot be null!!
     630: invokespecial #109                // Method org/apache/axis2/databinding/ADBException."<init>":(Ljava/lang/String;)V
     633: athrow
     634: aload_2
     635: aload_0
     636: getfield      #66                 // Field localSourceCsvEscape:Ljava/lang/String;
     639: invokeinterface #110,  2          // InterfaceMethod javax/xml/stream/XMLStreamWriter.writeCharacters:(Ljava/lang/String;)V
     644: aload_2
     645: invokeinterface #111,  1          // InterfaceMethod javax/xml/stream/XMLStreamWriter.writeEndElement:()V
     650: aload_0
     651: getfield      #15                 // Field localSourceRowTagTracker:Z
     654: ifeq          704
     657: ldc           #92                 // String urn:hpccsystems:ws:filespray
     659: astore        5
     661: aload_0
     662: aconst_null
     663: aload         5
     665: ldc           #135                // String sourceRowTag
     667: aload_2
     668: invokespecial #91                 // Method writeStartElement:(Ljava/lang/String;Ljava/lang/String;Ljava/lang/String;Ljavax/xml/stream/XMLStreamWriter;)V
     671: aload_0
     672: getfield      #67                 // Field localSourceRowTag:Ljava/lang/String;
     675: ifnonnull     688
     678: new           #107                // class org/apache/axis2/databinding/ADBException
     681: dup
     682: ldc           #136                // String sourceRowTag cannot be null!!
     684: invokespecial #109                // Method org/apache/axis2/databinding/ADBException."<init>":(Ljava/lang/String;)V
     687: athrow
     688: aload_2
     689: aload_0
     690: getfield      #67                 // Field localSourceRowTag:Ljava/lang/String;
     693: invokeinterface #110,  2          // InterfaceMethod javax/xml/stream/XMLStreamWriter.writeCharacters:(Ljava/lang/String;)V
     698: aload_2
     699: invokeinterface #111,  1          // InterfaceMethod javax/xml/stream/XMLStreamWriter.writeEndElement:()V
     704: aload_0
     705: getfield      #16                 // Field localDestGroupTracker:Z
     708: ifeq          758
     711: ldc           #92                 // String urn:hpccsystems:ws:filespray
     713: astore        5
     715: aload_0
     716: aconst_null
     717: aload         5
     719: ldc           #137                // String destGroup
     721: aload_2
     722: invokespecial #91                 // Method writeStartElement:(Ljava/lang/String;Ljava/lang/String;Ljava/lang/String;Ljavax/xml/stream/XMLStreamWriter;)V
     725: aload_0
     726: getfield      #68                 // Field localDestGroup:Ljava/lang/String;
     729: ifnonnull     742
     732: new           #107                // class org/apache/axis2/databinding/ADBException
     735: dup
     736: ldc           #138                // String destGroup cannot be null!!
     738: invokespecial #109                // Method org/apache/axis2/databinding/ADBException."<init>":(Ljava/lang/String;)V
     741: athrow
     742: aload_2
     743: aload_0
     744: getfield      #68                 // Field localDestGroup:Ljava/lang/String;
     747: invokeinterface #110,  2          // InterfaceMethod javax/xml/stream/XMLStreamWriter.writeCharacters:(Ljava/lang/String;)V
     752: aload_2
     753: invokeinterface #111,  1          // InterfaceMethod javax/xml/stream/XMLStreamWriter.writeEndElement:()V
     758: aload_0
     759: getfield      #17                 // Field localDestLogicalNameTracker:Z
     762: ifeq          812
     765: ldc           #92                 // String urn:hpccsystems:ws:filespray
     767: astore        5
     769: aload_0
     770: aconst_null
     771: aload         5
     773: ldc           #139                // String destLogicalName
     775: aload_2
     776: invokespecial #91                 // Method writeStartElement:(Ljava/lang/String;Ljava/lang/String;Ljava/lang/String;Ljavax/xml/stream/XMLStreamWriter;)V
     779: aload_0
     780: getfield      #69                 // Field localDestLogicalName:Ljava/lang/String;
     783: ifnonnull     796
     786: new           #107                // class org/apache/axis2/databinding/ADBException
     789: dup
     790: ldc           #140                // String destLogicalName cannot be null!!
     792: invokespecial #109                // Method org/apache/axis2/databinding/ADBException."<init>":(Ljava/lang/String;)V
     795: athrow
     796: aload_2
     797: aload_0
     798: getfield      #69                 // Field localDestLogicalName:Ljava/lang/String;
     801: invokeinterface #110,  2          // InterfaceMethod javax/xml/stream/XMLStreamWriter.writeCharacters:(Ljava/lang/String;)V
     806: aload_2
     807: invokeinterface #111,  1          // InterfaceMethod javax/xml/stream/XMLStreamWriter.writeEndElement:()V
     812: aload_0
     813: getfield      #18                 // Field localOverwriteTracker:Z
     816: ifeq          852
     819: ldc           #92                 // String urn:hpccsystems:ws:filespray
     821: astore        5
     823: aload_0
     824: aconst_null
     825: aload         5
     827: ldc           #141                // String overwrite
     829: aload_2
     830: invokespecial #91                 // Method writeStartElement:(Ljava/lang/String;Ljava/lang/String;Ljava/lang/String;Ljavax/xml/stream/XMLStreamWriter;)V
     833: aload_2
     834: aload_0
     835: getfield      #70                 // Field localOverwrite:Z
     838: invokestatic  #126                // Method org/apache/axis2/databinding/utils/ConverterUtil.convertToString:(Z)Ljava/lang/String;
     841: invokeinterface #110,  2          // InterfaceMethod javax/xml/stream/XMLStreamWriter.writeCharacters:(Ljava/lang/String;)V
     846: aload_2
     847: invokeinterface #111,  1          // InterfaceMethod javax/xml/stream/XMLStreamWriter.writeEndElement:()V
     852: aload_0
     853: getfield      #19                 // Field localReplicateTracker:Z
     856: ifeq          892
     859: ldc           #92                 // String urn:hpccsystems:ws:filespray
     861: astore        5
     863: aload_0
     864: aconst_null
     865: aload         5
     867: ldc           #142                // String replicate
     869: aload_2
     870: invokespecial #91                 // Method writeStartElement:(Ljava/lang/String;Ljava/lang/String;Ljava/lang/String;Ljavax/xml/stream/XMLStreamWriter;)V
     873: aload_2
     874: aload_0
     875: getfield      #71                 // Field localReplicate:Z
     878: invokestatic  #126                // Method org/apache/axis2/databinding/utils/ConverterUtil.convertToString:(Z)Ljava/lang/String;
     881: invokeinterface #110,  2          // InterfaceMethod javax/xml/stream/XMLStreamWriter.writeCharacters:(Ljava/lang/String;)V
     886: aload_2
     887: invokeinterface #111,  1          // InterfaceMethod javax/xml/stream/XMLStreamWriter.writeEndElement:()V
     892: aload_0
     893: getfield      #23                 // Field localReplicateOffsetTracker:Z
     896: ifeq          951
     899: ldc           #92                 // String urn:hpccsystems:ws:filespray
     901: astore        5
     903: aload_0
     904: aconst_null
     905: aload         5
     907: ldc           #143                // String ReplicateOffset
     909: aload_2
     910: invokespecial #91                 // Method writeStartElement:(Ljava/lang/String;Ljava/lang/String;Ljava/lang/String;Ljavax/xml/stream/XMLStreamWriter;)V
     913: aload_0
     914: getfield      #22                 // Field localReplicateOffset:I
     917: ldc           #61                 // int -2147483648
     919: if_icmpne     932
     922: new           #107                // class org/apache/axis2/databinding/ADBException
     925: dup
     926: ldc           #144                // String ReplicateOffset cannot be null!!
     928: invokespecial #109                // Method org/apache/axis2/databinding/ADBException."<init>":(Ljava/lang/String;)V
     931: athrow
     932: aload_2
     933: aload_0
     934: getfield      #22                 // Field localReplicateOffset:I
     937: invokestatic  #122                // Method org/apache/axis2/databinding/utils/ConverterUtil.convertToString:(I)Ljava/lang/String;
     940: invokeinterface #110,  2          // InterfaceMethod javax/xml/stream/XMLStreamWriter.writeCharacters:(Ljava/lang/String;)V
     945: aload_2
     946: invokeinterface #111,  1          // InterfaceMethod javax/xml/stream/XMLStreamWriter.writeEndElement:()V
     951: aload_0
     952: getfield      #24                 // Field localMaxConnectionsTracker:Z
     955: ifeq          1010
     958: ldc           #92                 // String urn:hpccsystems:ws:filespray
     960: astore        5
     962: aload_0
     963: aconst_null
     964: aload         5
     966: ldc           #145                // String maxConnections
     968: aload_2
     969: invokespecial #91                 // Method writeStartElement:(Ljava/lang/String;Ljava/lang/String;Ljava/lang/String;Ljavax/xml/stream/XMLStreamWriter;)V
     972: aload_0
     973: getfield      #72                 // Field localMaxConnections:I
     976: ldc           #61                 // int -2147483648
     978: if_icmpne     991
     981: new           #107                // class org/apache/axis2/databinding/ADBException
     984: dup
     985: ldc           #146                // String maxConnections cannot be null!!
     987: invokespecial #109                // Method org/apache/axis2/databinding/ADBException."<init>":(Ljava/lang/String;)V
     990: athrow
     991: aload_2
     992: aload_0
     993: getfield      #72                 // Field localMaxConnections:I
     996: invokestatic  #122                // Method org/apache/axis2/databinding/utils/ConverterUtil.convertToString:(I)Ljava/lang/String;
     999: invokeinterface #110,  2          // InterfaceMethod javax/xml/stream/XMLStreamWriter.writeCharacters:(Ljava/lang/String;)V
    1004: aload_2
    1005: invokeinterface #111,  1          // InterfaceMethod javax/xml/stream/XMLStreamWriter.writeEndElement:()V
    1010: aload_0
    1011: getfield      #25                 // Field localThrottleTracker:Z
    1014: ifeq          1069
    1017: ldc           #92                 // String urn:hpccsystems:ws:filespray
    1019: astore        5
    1021: aload_0
    1022: aconst_null
    1023: aload         5
    1025: ldc           #147                // String throttle
    1027: aload_2
    1028: invokespecial #91                 // Method writeStartElement:(Ljava/lang/String;Ljava/lang/String;Ljava/lang/String;Ljavax/xml/stream/XMLStreamWriter;)V
    1031: aload_0
    1032: getfield      #73                 // Field localThrottle:I
    1035: ldc           #61                 // int -2147483648
    1037: if_icmpne     1050
    1040: new           #107                // class org/apache/axis2/databinding/ADBException
    1043: dup
    1044: ldc           #148                // String throttle cannot be null!!
    1046: invokespecial #109                // Method org/apache/axis2/databinding/ADBException."<init>":(Ljava/lang/String;)V
    1049: athrow
    1050: aload_2
    1051: aload_0
    1052: getfield      #73                 // Field localThrottle:I
    1055: invokestatic  #122                // Method org/apache/axis2/databinding/utils/ConverterUtil.convertToString:(I)Ljava/lang/String;
    1058: invokeinterface #110,  2          // InterfaceMethod javax/xml/stream/XMLStreamWriter.writeCharacters:(Ljava/lang/String;)V
    1063: aload_2
    1064: invokeinterface #111,  1          // InterfaceMethod javax/xml/stream/XMLStreamWriter.writeEndElement:()V
    1069: aload_0
    1070: getfield      #26                 // Field localTransferBufferSizeTracker:Z
    1073: ifeq          1128
    1076: ldc           #92                 // String urn:hpccsystems:ws:filespray
    1078: astore        5
    1080: aload_0
    1081: aconst_null
    1082: aload         5
    1084: ldc           #149                // String transferBufferSize
    1086: aload_2
    1087: invokespecial #91                 // Method writeStartElement:(Ljava/lang/String;Ljava/lang/String;Ljava/lang/String;Ljavax/xml/stream/XMLStreamWriter;)V
    1090: aload_0
    1091: getfield      #74                 // Field localTransferBufferSize:I
    1094: ldc           #61                 // int -2147483648
    1096: if_icmpne     1109
    1099: new           #107                // class org/apache/axis2/databinding/ADBException
    1102: dup
    1103: ldc           #150                // String transferBufferSize cannot be null!!
    1105: invokespecial #109                // Method org/apache/axis2/databinding/ADBException."<init>":(Ljava/lang/String;)V
    1108: athrow
    1109: aload_2
    1110: aload_0
    1111: getfield      #74                 // Field localTransferBufferSize:I
    1114: invokestatic  #122                // Method org/apache/axis2/databinding/utils/ConverterUtil.convertToString:(I)Ljava/lang/String;
    1117: invokeinterface #110,  2          // InterfaceMethod javax/xml/stream/XMLStreamWriter.writeCharacters:(Ljava/lang/String;)V
    1122: aload_2
    1123: invokeinterface #111,  1          // InterfaceMethod javax/xml/stream/XMLStreamWriter.writeEndElement:()V
    1128: aload_0
    1129: getfield      #27                 // Field localPrefixTracker:Z
    1132: ifeq          1182
    1135: ldc           #92                 // String urn:hpccsystems:ws:filespray
    1137: astore        5
    1139: aload_0
    1140: aconst_null
    1141: aload         5
    1143: ldc           #151                // String prefix
    1145: aload_2
    1146: invokespecial #91                 // Method writeStartElement:(Ljava/lang/String;Ljava/lang/String;Ljava/lang/String;Ljavax/xml/stream/XMLStreamWriter;)V
    1149: aload_0
    1150: getfield      #75                 // Field localPrefix:Ljava/lang/String;
    1153: ifnonnull     1166
    1156: new           #107                // class org/apache/axis2/databinding/ADBException
    1159: dup
    1160: ldc           #152                // String prefix cannot be null!!
    1162: invokespecial #109                // Method org/apache/axis2/databinding/ADBException."<init>":(Ljava/lang/String;)V
    1165: athrow
    1166: aload_2
    1167: aload_0
    1168: getfield      #75                 // Field localPrefix:Ljava/lang/String;
    1171: invokeinterface #110,  2          // InterfaceMethod javax/xml/stream/XMLStreamWriter.writeCharacters:(Ljava/lang/String;)V
    1176: aload_2
    1177: invokeinterface #111,  1          // InterfaceMethod javax/xml/stream/XMLStreamWriter.writeEndElement:()V
    1182: aload_0
    1183: getfield      #29                 // Field localNosplitTracker:Z
    1186: ifeq          1222
    1189: ldc           #92                 // String urn:hpccsystems:ws:filespray
    1191: astore        5
    1193: aload_0
    1194: aconst_null
    1195: aload         5
    1197: ldc           #153                // String nosplit
    1199: aload_2
    1200: invokespecial #91                 // Method writeStartElement:(Ljava/lang/String;Ljava/lang/String;Ljava/lang/String;Ljavax/xml/stream/XMLStreamWriter;)V
    1203: aload_2
    1204: aload_0
    1205: getfield      #28                 // Field localNosplit:Z
    1208: invokestatic  #126                // Method org/apache/axis2/databinding/utils/ConverterUtil.convertToString:(Z)Ljava/lang/String;
    1211: invokeinterface #110,  2          // InterfaceMethod javax/xml/stream/XMLStreamWriter.writeCharacters:(Ljava/lang/String;)V
    1216: aload_2
    1217: invokeinterface #111,  1          // InterfaceMethod javax/xml/stream/XMLStreamWriter.writeEndElement:()V
    1222: aload_0
    1223: getfield      #31                 // Field localNorecoverTracker:Z
    1226: ifeq          1262
    1229: ldc           #92                 // String urn:hpccsystems:ws:filespray
    1231: astore        5
    1233: aload_0
    1234: aconst_null
    1235: aload         5
    1237: ldc           #154                // String norecover
    1239: aload_2
    1240: invokespecial #91                 // Method writeStartElement:(Ljava/lang/String;Ljava/lang/String;Ljava/lang/String;Ljavax/xml/stream/XMLStreamWriter;)V
    1243: aload_2
    1244: aload_0
    1245: getfield      #30                 // Field localNorecover:Z
    1248: invokestatic  #126                // Method org/apache/axis2/databinding/utils/ConverterUtil.convertToString:(Z)Ljava/lang/String;
    1251: invokeinterface #110,  2          // InterfaceMethod javax/xml/stream/XMLStreamWriter.writeCharacters:(Ljava/lang/String;)V
    1256: aload_2
    1257: invokeinterface #111,  1          // InterfaceMethod javax/xml/stream/XMLStreamWriter.writeEndElement:()V
    1262: aload_0
    1263: getfield      #33                 // Field localCompressTracker:Z
    1266: ifeq          1302
    1269: ldc           #92                 // String urn:hpccsystems:ws:filespray
    1271: astore        5
    1273: aload_0
    1274: aconst_null
    1275: aload         5
    1277: ldc           #155                // String compress
    1279: aload_2
    1280: invokespecial #91                 // Method writeStartElement:(Ljava/lang/String;Ljava/lang/String;Ljava/lang/String;Ljavax/xml/stream/XMLStreamWriter;)V
    1283: aload_2
    1284: aload_0
    1285: getfield      #32                 // Field localCompress:Z
    1288: invokestatic  #126                // Method org/apache/axis2/databinding/utils/ConverterUtil.convertToString:(Z)Ljava/lang/String;
    1291: invokeinterface #110,  2          // InterfaceMethod javax/xml/stream/XMLStreamWriter.writeCharacters:(Ljava/lang/String;)V
    1296: aload_2
    1297: invokeinterface #111,  1          // InterfaceMethod javax/xml/stream/XMLStreamWriter.writeEndElement:()V
    1302: aload_0
    1303: getfield      #35                 // Field localPushTracker:Z
    1306: ifeq          1342
    1309: ldc           #92                 // String urn:hpccsystems:ws:filespray
    1311: astore        5
    1313: aload_0
    1314: aconst_null
    1315: aload         5
    1317: ldc           #156                // String push
    1319: aload_2
    1320: invokespecial #91                 // Method writeStartElement:(Ljava/lang/String;Ljava/lang/String;Ljava/lang/String;Ljavax/xml/stream/XMLStreamWriter;)V
    1323: aload_2
    1324: aload_0
    1325: getfield      #34                 // Field localPush:Z
    1328: invokestatic  #126                // Method org/apache/axis2/databinding/utils/ConverterUtil.convertToString:(Z)Ljava/lang/String;
    1331: invokeinterface #110,  2          // InterfaceMethod javax/xml/stream/XMLStreamWriter.writeCharacters:(Ljava/lang/String;)V
    1336: aload_2
    1337: invokeinterface #111,  1          // InterfaceMethod javax/xml/stream/XMLStreamWriter.writeEndElement:()V
    1342: aload_0
    1343: getfield      #37                 // Field localPullTracker:Z
    1346: ifeq          1382
    1349: ldc           #92                 // String urn:hpccsystems:ws:filespray
    1351: astore        5
    1353: aload_0
    1354: aconst_null
    1355: aload         5
    1357: ldc           #157                // String pull
    1359: aload_2
    1360: invokespecial #91                 // Method writeStartElement:(Ljava/lang/String;Ljava/lang/String;Ljava/lang/String;Ljavax/xml/stream/XMLStreamWriter;)V
    1363: aload_2
    1364: aload_0
    1365: getfield      #36                 // Field localPull:Z
    1368: invokestatic  #126                // Method org/apache/axis2/databinding/utils/ConverterUtil.convertToString:(Z)Ljava/lang/String;
    1371: invokeinterface #110,  2          // InterfaceMethod javax/xml/stream/XMLStreamWriter.writeCharacters:(Ljava/lang/String;)V
    1376: aload_2
    1377: invokeinterface #111,  1          // InterfaceMethod javax/xml/stream/XMLStreamWriter.writeEndElement:()V
    1382: aload_0
    1383: getfield      #40                 // Field localNoCommonTracker:Z
    1386: ifeq          1422
    1389: ldc           #92                 // String urn:hpccsystems:ws:filespray
    1391: astore        5
    1393: aload_0
    1394: aconst_null
    1395: aload         5
    1397: ldc           #158                // String noCommon
    1399: aload_2
    1400: invokespecial #91                 // Method writeStartElement:(Ljava/lang/String;Ljava/lang/String;Ljava/lang/String;Ljavax/xml/stream/XMLStreamWriter;)V
    1403: aload_2
    1404: aload_0
    1405: getfield      #39                 // Field localNoCommon:Z
    1408: invokestatic  #126                // Method org/apache/axis2/databinding/utils/ConverterUtil.convertToString:(Z)Ljava/lang/String;
    1411: invokeinterface #110,  2          // InterfaceMethod javax/xml/stream/XMLStreamWriter.writeCharacters:(Ljava/lang/String;)V
    1416: aload_2
    1417: invokeinterface #111,  1          // InterfaceMethod javax/xml/stream/XMLStreamWriter.writeEndElement:()V
    1422: aload_0
    1423: getfield      #41                 // Field localEncryptTracker:Z
    1426: ifeq          1476
    1429: ldc           #92                 // String urn:hpccsystems:ws:filespray
    1431: astore        5
    1433: aload_0
    1434: aconst_null
    1435: aload         5
    1437: ldc           #159                // String encrypt
    1439: aload_2
    1440: invokespecial #91                 // Method writeStartElement:(Ljava/lang/String;Ljava/lang/String;Ljava/lang/String;Ljavax/xml/stream/XMLStreamWriter;)V
    1443: aload_0
    1444: getfield      #76                 // Field localEncrypt:Ljava/lang/String;
    1447: ifnonnull     1460
    1450: new           #107                // class org/apache/axis2/databinding/ADBException
    1453: dup
    1454: ldc           #160                // String encrypt cannot be null!!
    1456: invokespecial #109                // Method org/apache/axis2/databinding/ADBException."<init>":(Ljava/lang/String;)V
    1459: athrow
    1460: aload_2
    1461: aload_0
    1462: getfield      #76                 // Field localEncrypt:Ljava/lang/String;
    1465: invokeinterface #110,  2          // InterfaceMethod javax/xml/stream/XMLStreamWriter.writeCharacters:(Ljava/lang/String;)V
    1470: aload_2
    1471: invokeinterface #111,  1          // InterfaceMethod javax/xml/stream/XMLStreamWriter.writeEndElement:()V
    1476: aload_0
    1477: getfield      #42                 // Field localDecryptTracker:Z
    1480: ifeq          1530
    1483: ldc           #92                 // String urn:hpccsystems:ws:filespray
    1485: astore        5
    1487: aload_0
    1488: aconst_null
    1489: aload         5
    1491: ldc           #161                // String decrypt
    1493: aload_2
    1494: invokespecial #91                 // Method writeStartElement:(Ljava/lang/String;Ljava/lang/String;Ljava/lang/String;Ljavax/xml/stream/XMLStreamWriter;)V
    1497: aload_0
    1498: getfield      #77                 // Field localDecrypt:Ljava/lang/String;
    1501: ifnonnull     1514
    1504: new           #107                // class org/apache/axis2/databinding/ADBException
    1507: dup
    1508: ldc           #162                // String decrypt cannot be null!!
    1510: invokespecial #109                // Method org/apache/axis2/databinding/ADBException."<init>":(Ljava/lang/String;)V
    1513: athrow
    1514: aload_2
    1515: aload_0
    1516: getfield      #77                 // Field localDecrypt:Ljava/lang/String;
    1519: invokeinterface #110,  2          // InterfaceMethod javax/xml/stream/XMLStreamWriter.writeCharacters:(Ljava/lang/String;)V
    1524: aload_2
    1525: invokeinterface #111,  1          // InterfaceMethod javax/xml/stream/XMLStreamWriter.writeEndElement:()V
    1530: aload_0
    1531: getfield      #44                 // Field localFailIfNoSourceFileTracker:Z
    1534: ifeq          1570
    1537: ldc           #92                 // String urn:hpccsystems:ws:filespray
    1539: astore        5
    1541: aload_0
    1542: aconst_null
    1543: aload         5
    1545: ldc           #163                // String failIfNoSourceFile
    1547: aload_2
    1548: invokespecial #91                 // Method writeStartElement:(Ljava/lang/String;Ljava/lang/String;Ljava/lang/String;Ljavax/xml/stream/XMLStreamWriter;)V
    1551: aload_2
    1552: aload_0
    1553: getfield      #43                 // Field localFailIfNoSourceFile:Z
    1556: invokestatic  #126                // Method org/apache/axis2/databinding/utils/ConverterUtil.convertToString:(Z)Ljava/lang/String;
    1559: invokeinterface #110,  2          // InterfaceMethod javax/xml/stream/XMLStreamWriter.writeCharacters:(Ljava/lang/String;)V
    1564: aload_2
    1565: invokeinterface #111,  1          // InterfaceMethod javax/xml/stream/XMLStreamWriter.writeEndElement:()V
    1570: aload_0
    1571: getfield      #46                 // Field localRecordStructurePresentTracker:Z
    1574: ifeq          1610
    1577: ldc           #92                 // String urn:hpccsystems:ws:filespray
    1579: astore        5
    1581: aload_0
    1582: aconst_null
    1583: aload         5
    1585: ldc           #164                // String recordStructurePresent
    1587: aload_2
    1588: invokespecial #91                 // Method writeStartElement:(Ljava/lang/String;Ljava/lang/String;Ljava/lang/String;Ljavax/xml/stream/XMLStreamWriter;)V
    1591: aload_2
    1592: aload_0
    1593: getfield      #45                 // Field localRecordStructurePresent:Z
    1596: invokestatic  #126                // Method org/apache/axis2/databinding/utils/ConverterUtil.convertToString:(Z)Ljava/lang/String;
    1599: invokeinterface #110,  2          // InterfaceMethod javax/xml/stream/XMLStreamWriter.writeCharacters:(Ljava/lang/String;)V
    1604: aload_2
    1605: invokeinterface #111,  1          // InterfaceMethod javax/xml/stream/XMLStreamWriter.writeEndElement:()V
    1610: aload_0
    1611: getfield      #48                 // Field localQuotedTerminatorTracker:Z
    1614: ifeq          1650
    1617: ldc           #92                 // String urn:hpccsystems:ws:filespray
    1619: astore        5
    1621: aload_0
    1622: aconst_null
    1623: aload         5
    1625: ldc           #165                // String quotedTerminator
    1627: aload_2
    1628: invokespecial #91                 // Method writeStartElement:(Ljava/lang/String;Ljava/lang/String;Ljava/lang/String;Ljavax/xml/stream/XMLStreamWriter;)V
    1631: aload_2
    1632: aload_0
    1633: getfield      #47                 // Field localQuotedTerminator:Z
    1636: invokestatic  #126                // Method org/apache/axis2/databinding/utils/ConverterUtil.convertToString:(Z)Ljava/lang/String;
    1639: invokeinterface #110,  2          // InterfaceMethod javax/xml/stream/XMLStreamWriter.writeCharacters:(Ljava/lang/String;)V
    1644: aload_2
    1645: invokeinterface #111,  1          // InterfaceMethod javax/xml/stream/XMLStreamWriter.writeEndElement:()V
    1650: aload_0
    1651: getfield      #49                 // Field localSourceRowPathTracker:Z
    1654: ifeq          1704
    1657: ldc           #92                 // String urn:hpccsystems:ws:filespray
    1659: astore        5
    1661: aload_0
    1662: aconst_null
    1663: aload         5
    1665: ldc           #166                // String sourceRowPath
    1667: aload_2
    1668: invokespecial #91                 // Method writeStartElement:(Ljava/lang/String;Ljava/lang/String;Ljava/lang/String;Ljavax/xml/stream/XMLStreamWriter;)V
    1671: aload_0
    1672: getfield      #78                 // Field localSourceRowPath:Ljava/lang/String;
    1675: ifnonnull     1688
    1678: new           #107                // class org/apache/axis2/databinding/ADBException
    1681: dup
    1682: ldc           #167                // String sourceRowPath cannot be null!!
    1684: invokespecial #109                // Method org/apache/axis2/databinding/ADBException."<init>":(Ljava/lang/String;)V
    1687: athrow
    1688: aload_2
    1689: aload_0
    1690: getfield      #78                 // Field localSourceRowPath:Ljava/lang/String;
    1693: invokeinterface #110,  2          // InterfaceMethod javax/xml/stream/XMLStreamWriter.writeCharacters:(Ljava/lang/String;)V
    1698: aload_2
    1699: invokeinterface #111,  1          // InterfaceMethod javax/xml/stream/XMLStreamWriter.writeEndElement:()V
    1704: aload_0
    1705: getfield      #51                 // Field localIsJSONTracker:Z
    1708: ifeq          1744
    1711: ldc           #92                 // String urn:hpccsystems:ws:filespray
    1713: astore        5
    1715: aload_0
    1716: aconst_null
    1717: aload         5
    1719: ldc           #168                // String isJSON
    1721: aload_2
    1722: invokespecial #91                 // Method writeStartElement:(Ljava/lang/String;Ljava/lang/String;Ljava/lang/String;Ljavax/xml/stream/XMLStreamWriter;)V
    1725: aload_2
    1726: aload_0
    1727: getfield      #50                 // Field localIsJSON:Z
    1730: invokestatic  #126                // Method org/apache/axis2/databinding/utils/ConverterUtil.convertToString:(Z)Ljava/lang/String;
    1733: invokeinterface #110,  2          // InterfaceMethod javax/xml/stream/XMLStreamWriter.writeCharacters:(Ljava/lang/String;)V
    1738: aload_2
    1739: invokeinterface #111,  1          // InterfaceMethod javax/xml/stream/XMLStreamWriter.writeEndElement:()V
    1744: aload_0
    1745: getfield      #52                 // Field localExpireDaysTracker:Z
    1748: ifeq          1803
    1751: ldc           #92                 // String urn:hpccsystems:ws:filespray
    1753: astore        5
    1755: aload_0
    1756: aconst_null
    1757: aload         5
    1759: ldc           #169                // String expireDays
    1761: aload_2
    1762: invokespecial #91                 // Method writeStartElement:(Ljava/lang/String;Ljava/lang/String;Ljava/lang/String;Ljavax/xml/stream/XMLStreamWriter;)V
    1765: aload_0
    1766: getfield      #79                 // Field localExpireDays:I
    1769: ldc           #61                 // int -2147483648
    1771: if_icmpne     1784
    1774: new           #107                // class org/apache/axis2/databinding/ADBException
    1777: dup
    1778: ldc           #170                // String expireDays cannot be null!!
    1780: invokespecial #109                // Method org/apache/axis2/databinding/ADBException."<init>":(Ljava/lang/String;)V
    1783: athrow
    1784: aload_2
    1785: aload_0
    1786: getfield      #79                 // Field localExpireDays:I
    1789: invokestatic  #122                // Method org/apache/axis2/databinding/utils/ConverterUtil.convertToString:(I)Ljava/lang/String;
    1792: invokeinterface #110,  2          // InterfaceMethod javax/xml/stream/XMLStreamWriter.writeCharacters:(Ljava/lang/String;)V
    1797: aload_2
    1798: invokeinterface #111,  1          // InterfaceMethod javax/xml/stream/XMLStreamWriter.writeEndElement:()V
    1803: aload_0
    1804: getfield      #53                 // Field localDFUServerQueueTracker:Z
    1807: ifeq          1857
    1810: ldc           #92                 // String urn:hpccsystems:ws:filespray
    1812: astore        5
    1814: aload_0
    1815: aconst_null
    1816: aload         5
    1818: ldc           #171                // String DFUServerQueue
    1820: aload_2
    1821: invokespecial #91                 // Method writeStartElement:(Ljava/lang/String;Ljava/lang/String;Ljava/lang/String;Ljavax/xml/stream/XMLStreamWriter;)V
    1824: aload_0
    1825: getfield      #80                 // Field localDFUServerQueue:Ljava/lang/String;
    1828: ifnonnull     1841
    1831: new           #107                // class org/apache/axis2/databinding/ADBException
    1834: dup
    1835: ldc           #172                // String DFUServerQueue cannot be null!!
    1837: invokespecial #109                // Method org/apache/axis2/databinding/ADBException."<init>":(Ljava/lang/String;)V
    1840: athrow
    1841: aload_2
    1842: aload_0
    1843: getfield      #80                 // Field localDFUServerQueue:Ljava/lang/String;
    1846: invokeinterface #110,  2          // InterfaceMethod javax/xml/stream/XMLStreamWriter.writeCharacters:(Ljava/lang/String;)V
    1851: aload_2
    1852: invokeinterface #111,  1          // InterfaceMethod javax/xml/stream/XMLStreamWriter.writeEndElement:()V
    1857: aload_0
    1858: getfield      #54                 // Field localSrcUsernameTracker:Z
    1861: ifeq          1911
    1864: ldc           #92                 // String urn:hpccsystems:ws:filespray
    1866: astore        5
    1868: aload_0
    1869: aconst_null
    1870: aload         5
    1872: ldc           #173                // String srcUsername
    1874: aload_2
    1875: invokespecial #91                 // Method writeStartElement:(Ljava/lang/String;Ljava/lang/String;Ljava/lang/String;Ljavax/xml/stream/XMLStreamWriter;)V
    1878: aload_0
    1879: getfield      #81                 // Field localSrcUsername:Ljava/lang/String;
    1882: ifnonnull     1895
    1885: new           #107                // class org/apache/axis2/databinding/ADBException
    1888: dup
    1889: ldc           #174                // String srcUsername cannot be null!!
    1891: invokespecial #109                // Method org/apache/axis2/databinding/ADBException."<init>":(Ljava/lang/String;)V
    1894: athrow
    1895: aload_2
    1896: aload_0
    1897: getfield      #81                 // Field localSrcUsername:Ljava/lang/String;
    1900: invokeinterface #110,  2          // InterfaceMethod javax/xml/stream/XMLStreamWriter.writeCharacters:(Ljava/lang/String;)V
    1905: aload_2
    1906: invokeinterface #111,  1          // InterfaceMethod javax/xml/stream/XMLStreamWriter.writeEndElement:()V
    1911: aload_0
    1912: getfield      #55                 // Field localSrcPasswordTracker:Z
    1915: ifeq          1965
    1918: ldc           #92                 // String urn:hpccsystems:ws:filespray
    1920: astore        5
    1922: aload_0
    1923: aconst_null
    1924: aload         5
    1926: ldc           #175                // String srcPassword
    1928: aload_2
    1929: invokespecial #91                 // Method writeStartElement:(Ljava/lang/String;Ljava/lang/String;Ljava/lang/String;Ljavax/xml/stream/XMLStreamWriter;)V
    1932: aload_0
    1933: getfield      #82                 // Field localSrcPassword:Ljava/lang/String;
    1936: ifnonnull     1949
    1939: new           #107                // class org/apache/axis2/databinding/ADBException
    1942: dup
    1943: ldc           #176                // String srcPassword cannot be null!!
    1945: invokespecial #109                // Method org/apache/axis2/databinding/ADBException."<init>":(Ljava/lang/String;)V
    1948: athrow
    1949: aload_2
    1950: aload_0
    1951: getfield      #82                 // Field localSrcPassword:Ljava/lang/String;
    1954: invokeinterface #110,  2          // InterfaceMethod javax/xml/stream/XMLStreamWriter.writeCharacters:(Ljava/lang/String;)V
    1959: aload_2
    1960: invokeinterface #111,  1          // InterfaceMethod javax/xml/stream/XMLStreamWriter.writeEndElement:()V
    1965: aload_2
    1966: invokeinterface #111,  1          // InterfaceMethod javax/xml/stream/XMLStreamWriter.writeEndElement:()V
    1971: return
    Exception table:
       from    to  target type
         243   253   256   Class java/io/IOException

  private static java.lang.String generatePrefix(java.lang.String);
    Code:
       0: aload_0
       1: ldc           #92                 // String urn:hpccsystems:ws:filespray
       3: invokevirtual #177                // Method java/lang/String.equals:(Ljava/lang/Object;)Z
       6: ifeq          12
       9: ldc           #178                // String ns2
      11: areturn
      12: invokestatic  #179                // Method org/apache/axis2/databinding/utils/BeanUtil.getUniquePrefix:()Ljava/lang/String;
      15: areturn

  private void writeStartElement(java.lang.String, java.lang.String, java.lang.String, javax.xml.stream.XMLStreamWriter) throws javax.xml.stream.XMLStreamException;
    Code:
       0: aload         4
       2: aload_2
       3: invokeinterface #180,  2          // InterfaceMethod javax/xml/stream/XMLStreamWriter.getPrefix:(Ljava/lang/String;)Ljava/lang/String;
       8: astore        5
      10: aload         5
      12: ifnull        29
      15: aload         4
      17: aload         5
      19: aload_3
      20: aload_2
      21: invokeinterface #181,  4          // InterfaceMethod javax/xml/stream/XMLStreamWriter.writeStartElement:(Ljava/lang/String;Ljava/lang/String;Ljava/lang/String;)V
      26: goto          79
      29: aload_2
      30: invokevirtual #95                 // Method java/lang/String.length:()I
      33: ifne          42
      36: ldc           #182                // String
      38: astore_1
      39: goto          51
      42: aload_1
      43: ifnonnull     51
      46: aload_2
      47: invokestatic  #183                // Method generatePrefix:(Ljava/lang/String;)Ljava/lang/String;
      50: astore_1
      51: aload         4
      53: aload_1
      54: aload_3
      55: aload_2
      56: invokeinterface #181,  4          // InterfaceMethod javax/xml/stream/XMLStreamWriter.writeStartElement:(Ljava/lang/String;Ljava/lang/String;Ljava/lang/String;)V
      61: aload         4
      63: aload_1
      64: aload_2
      65: invokeinterface #184,  3          // InterfaceMethod javax/xml/stream/XMLStreamWriter.writeNamespace:(Ljava/lang/String;Ljava/lang/String;)V
      70: aload         4
      72: aload_1
      73: aload_2
      74: invokeinterface #185,  3          // InterfaceMethod javax/xml/stream/XMLStreamWriter.setPrefix:(Ljava/lang/String;Ljava/lang/String;)V
      79: return

  private void writeAttribute(java.lang.String, java.lang.String, java.lang.String, java.lang.String, javax.xml.stream.XMLStreamWriter) throws javax.xml.stream.XMLStreamException;
    Code:
       0: aload         5
       2: aload_2
       3: invokeinterface #180,  2          // InterfaceMethod javax/xml/stream/XMLStreamWriter.getPrefix:(Ljava/lang/String;)Ljava/lang/String;
       8: astore        6
      10: aload         6
      12: ifnull        31
      15: aload         5
      17: aload         6
      19: aload_2
      20: aload_3
      21: aload         4
      23: invokeinterface #186,  5          // InterfaceMethod javax/xml/stream/XMLStreamWriter.writeAttribute:(Ljava/lang/String;Ljava/lang/String;Ljava/lang/String;Ljava/lang/String;)V
      28: goto          61
      31: aload         5
      33: aload_1
      34: aload_2
      35: invokeinterface #184,  3          // InterfaceMethod javax/xml/stream/XMLStreamWriter.writeNamespace:(Ljava/lang/String;Ljava/lang/String;)V
      40: aload         5
      42: aload_1
      43: aload_2
      44: invokeinterface #185,  3          // InterfaceMethod javax/xml/stream/XMLStreamWriter.setPrefix:(Ljava/lang/String;Ljava/lang/String;)V
      49: aload         5
      51: aload_1
      52: aload_2
      53: aload_3
      54: aload         4
      56: invokeinterface #186,  5          // InterfaceMethod javax/xml/stream/XMLStreamWriter.writeAttribute:(Ljava/lang/String;Ljava/lang/String;Ljava/lang/String;Ljava/lang/String;)V
      61: return

  private void writeAttribute(java.lang.String, java.lang.String, java.lang.String, javax.xml.stream.XMLStreamWriter) throws javax.xml.stream.XMLStreamException;
    Code:
       0: aload_1
       1: ldc           #182                // String
       3: invokevirtual #177                // Method java/lang/String.equals:(Ljava/lang/Object;)Z
       6: ifeq          21
       9: aload         4
      11: aload_2
      12: aload_3
      13: invokeinterface #187,  3          // InterfaceMethod javax/xml/stream/XMLStreamWriter.writeAttribute:(Ljava/lang/String;Ljava/lang/String;)V
      18: goto          38
      21: aload         4
      23: aload_0
      24: aload         4
      26: aload_1
      27: invokespecial #93                 // Method registerPrefix:(Ljavax/xml/stream/XMLStreamWriter;Ljava/lang/String;)Ljava/lang/String;
      30: aload_1
      31: aload_2
      32: aload_3
      33: invokeinterface #186,  5          // InterfaceMethod javax/xml/stream/XMLStreamWriter.writeAttribute:(Ljava/lang/String;Ljava/lang/String;Ljava/lang/String;Ljava/lang/String;)V
      38: return

  private void writeQNameAttribute(java.lang.String, java.lang.String, javax.xml.namespace.QName, javax.xml.stream.XMLStreamWriter) throws javax.xml.stream.XMLStreamException;
    Code:
       0: aload_3
       1: invokevirtual #89                 // Method javax/xml/namespace/QName.getNamespaceURI:()Ljava/lang/String;
       4: astore        5
       6: aload         4
       8: aload         5
      10: invokeinterface #180,  2          // InterfaceMethod javax/xml/stream/XMLStreamWriter.getPrefix:(Ljava/lang/String;)Ljava/lang/String;
      15: astore        6
      17: aload         6
      19: ifnonnull     32
      22: aload_0
      23: aload         4
      25: aload         5
      27: invokespecial #93                 // Method registerPrefix:(Ljavax/xml/stream/XMLStreamWriter;Ljava/lang/String;)Ljava/lang/String;
      30: astore        6
      32: aload         6
      34: invokevirtual #94                 // Method java/lang/String.trim:()Ljava/lang/String;
      37: invokevirtual #95                 // Method java/lang/String.length:()I
      40: ifle          75
      43: new           #99                 // class java/lang/StringBuilder
      46: dup
      47: invokespecial #100                // Method java/lang/StringBuilder."<init>":()V
      50: aload         6
      52: invokevirtual #101                // Method java/lang/StringBuilder.append:(Ljava/lang/String;)Ljava/lang/StringBuilder;
      55: ldc           #188                // String :
      57: invokevirtual #101                // Method java/lang/StringBuilder.append:(Ljava/lang/String;)Ljava/lang/StringBuilder;
      60: aload_3
      61: invokevirtual #90                 // Method javax/xml/namespace/QName.getLocalPart:()Ljava/lang/String;
      64: invokevirtual #101                // Method java/lang/StringBuilder.append:(Ljava/lang/String;)Ljava/lang/StringBuilder;
      67: invokevirtual #103                // Method java/lang/StringBuilder.toString:()Ljava/lang/String;
      70: astore        7
      72: goto          81
      75: aload_3
      76: invokevirtual #90                 // Method javax/xml/namespace/QName.getLocalPart:()Ljava/lang/String;
      79: astore        7
      81: aload_1
      82: ldc           #182                // String
      84: invokevirtual #177                // Method java/lang/String.equals:(Ljava/lang/Object;)Z
      87: ifeq          103
      90: aload         4
      92: aload_2
      93: aload         7
      95: invokeinterface #187,  3          // InterfaceMethod javax/xml/stream/XMLStreamWriter.writeAttribute:(Ljava/lang/String;Ljava/lang/String;)V
     100: goto          124
     103: aload_0
     104: aload         4
     106: aload_1
     107: invokespecial #93                 // Method registerPrefix:(Ljavax/xml/stream/XMLStreamWriter;Ljava/lang/String;)Ljava/lang/String;
     110: pop
     111: aload         4
     113: aload         6
     115: aload_1
     116: aload_2
     117: aload         7
     119: invokeinterface #186,  5          // InterfaceMethod javax/xml/stream/XMLStreamWriter.writeAttribute:(Ljava/lang/String;Ljava/lang/String;Ljava/lang/String;Ljava/lang/String;)V
     124: return

  private void writeQName(javax.xml.namespace.QName, javax.xml.stream.XMLStreamWriter) throws javax.xml.stream.XMLStreamException;
    Code:
       0: aload_1
       1: invokevirtual #89                 // Method javax/xml/namespace/QName.getNamespaceURI:()Ljava/lang/String;
       4: astore_3
       5: aload_3
       6: ifnull        107
       9: aload_2
      10: aload_3
      11: invokeinterface #180,  2          // InterfaceMethod javax/xml/stream/XMLStreamWriter.getPrefix:(Ljava/lang/String;)Ljava/lang/String;
      16: astore        4
      18: aload         4
      20: ifnonnull     47
      23: aload_3
      24: invokestatic  #183                // Method generatePrefix:(Ljava/lang/String;)Ljava/lang/String;
      27: astore        4
      29: aload_2
      30: aload         4
      32: aload_3
      33: invokeinterface #184,  3          // InterfaceMethod javax/xml/stream/XMLStreamWriter.writeNamespace:(Ljava/lang/String;Ljava/lang/String;)V
      38: aload_2
      39: aload         4
      41: aload_3
      42: invokeinterface #185,  3          // InterfaceMethod javax/xml/stream/XMLStreamWriter.setPrefix:(Ljava/lang/String;Ljava/lang/String;)V
      47: aload         4
      49: invokevirtual #94                 // Method java/lang/String.trim:()Ljava/lang/String;
      52: invokevirtual #95                 // Method java/lang/String.length:()I
      55: ifle          94
      58: aload_2
      59: new           #99                 // class java/lang/StringBuilder
      62: dup
      63: invokespecial #100                // Method java/lang/StringBuilder."<init>":()V
      66: aload         4
      68: invokevirtual #101                // Method java/lang/StringBuilder.append:(Ljava/lang/String;)Ljava/lang/StringBuilder;
      71: ldc           #188                // String :
      73: invokevirtual #101                // Method java/lang/StringBuilder.append:(Ljava/lang/String;)Ljava/lang/StringBuilder;
      76: aload_1
      77: invokestatic  #189                // Method org/apache/axis2/databinding/utils/ConverterUtil.convertToString:(Ljavax/xml/namespace/QName;)Ljava/lang/String;
      80: invokevirtual #101                // Method java/lang/StringBuilder.append:(Ljava/lang/String;)Ljava/lang/StringBuilder;
      83: invokevirtual #103                // Method java/lang/StringBuilder.toString:()Ljava/lang/String;
      86: invokeinterface #110,  2          // InterfaceMethod javax/xml/stream/XMLStreamWriter.writeCharacters:(Ljava/lang/String;)V
      91: goto          104
      94: aload_2
      95: aload_1
      96: invokestatic  #189                // Method org/apache/axis2/databinding/utils/ConverterUtil.convertToString:(Ljavax/xml/namespace/QName;)Ljava/lang/String;
      99: invokeinterface #110,  2          // InterfaceMethod javax/xml/stream/XMLStreamWriter.writeCharacters:(Ljava/lang/String;)V
     104: goto          117
     107: aload_2
     108: aload_1
     109: invokestatic  #189                // Method org/apache/axis2/databinding/utils/ConverterUtil.convertToString:(Ljavax/xml/namespace/QName;)Ljava/lang/String;
     112: invokeinterface #110,  2          // InterfaceMethod javax/xml/stream/XMLStreamWriter.writeCharacters:(Ljava/lang/String;)V
     117: return

  private void writeQNames(javax.xml.namespace.QName[], javax.xml.stream.XMLStreamWriter) throws javax.xml.stream.XMLStreamException;
    Code:
       0: aload_1
       1: ifnull        183
       4: new           #190                // class java/lang/StringBuffer
       7: dup
       8: invokespecial #191                // Method java/lang/StringBuffer."<init>":()V
      11: astore_3
      12: aconst_null
      13: astore        4
      15: aconst_null
      16: astore        5
      18: iconst_0
      19: istore        6
      21: iload         6
      23: aload_1
      24: arraylength
      25: if_icmpge     173
      28: iload         6
      30: ifle          40
      33: aload_3
      34: ldc           #192                // String
      36: invokevirtual #193                // Method java/lang/StringBuffer.append:(Ljava/lang/String;)Ljava/lang/StringBuffer;
      39: pop
      40: aload_1
      41: iload         6
      43: aaload
      44: invokevirtual #89                 // Method javax/xml/namespace/QName.getNamespaceURI:()Ljava/lang/String;
      47: astore        4
      49: aload         4
      51: ifnull        155
      54: aload_2
      55: aload         4
      57: invokeinterface #180,  2          // InterfaceMethod javax/xml/stream/XMLStreamWriter.getPrefix:(Ljava/lang/String;)Ljava/lang/String;
      62: astore        5
      64: aload         5
      66: ifnull        77
      69: aload         5
      71: invokevirtual #95                 // Method java/lang/String.length:()I
      74: ifne          104
      77: aload         4
      79: invokestatic  #183                // Method generatePrefix:(Ljava/lang/String;)Ljava/lang/String;
      82: astore        5
      84: aload_2
      85: aload         5
      87: aload         4
      89: invokeinterface #184,  3          // InterfaceMethod javax/xml/stream/XMLStreamWriter.writeNamespace:(Ljava/lang/String;Ljava/lang/String;)V
      94: aload_2
      95: aload         5
      97: aload         4
      99: invokeinterface #185,  3          // InterfaceMethod javax/xml/stream/XMLStreamWriter.setPrefix:(Ljava/lang/String;Ljava/lang/String;)V
     104: aload         5
     106: invokevirtual #94                 // Method java/lang/String.trim:()Ljava/lang/String;
     109: invokevirtual #95                 // Method java/lang/String.length:()I
     112: ifle          140
     115: aload_3
     116: aload         5
     118: invokevirtual #193                // Method java/lang/StringBuffer.append:(Ljava/lang/String;)Ljava/lang/StringBuffer;
     121: ldc           #188                // String :
     123: invokevirtual #193                // Method java/lang/StringBuffer.append:(Ljava/lang/String;)Ljava/lang/StringBuffer;
     126: aload_1
     127: iload         6
     129: aaload
     130: invokestatic  #189                // Method org/apache/axis2/databinding/utils/ConverterUtil.convertToString:(Ljavax/xml/namespace/QName;)Ljava/lang/String;
     133: invokevirtual #193                // Method java/lang/StringBuffer.append:(Ljava/lang/String;)Ljava/lang/StringBuffer;
     136: pop
     137: goto          167
     140: aload_3
     141: aload_1
     142: iload         6
     144: aaload
     145: invokestatic  #189                // Method org/apache/axis2/databinding/utils/ConverterUtil.convertToString:(Ljavax/xml/namespace/QName;)Ljava/lang/String;
     148: invokevirtual #193                // Method java/lang/StringBuffer.append:(Ljava/lang/String;)Ljava/lang/StringBuffer;
     151: pop
     152: goto          167
     155: aload_3
     156: aload_1
     157: iload         6
     159: aaload
     160: invokestatic  #189                // Method org/apache/axis2/databinding/utils/ConverterUtil.convertToString:(Ljavax/xml/namespace/QName;)Ljava/lang/String;
     163: invokevirtual #193                // Method java/lang/StringBuffer.append:(Ljava/lang/String;)Ljava/lang/StringBuffer;
     166: pop
     167: iinc          6, 1
     170: goto          21
     173: aload_2
     174: aload_3
     175: invokevirtual #194                // Method java/lang/StringBuffer.toString:()Ljava/lang/String;
     178: invokeinterface #110,  2          // InterfaceMethod javax/xml/stream/XMLStreamWriter.writeCharacters:(Ljava/lang/String;)V
     183: return

  private java.lang.String registerPrefix(javax.xml.stream.XMLStreamWriter, java.lang.String) throws javax.xml.stream.XMLStreamException;
    Code:
       0: aload_1
       1: aload_2
       2: invokeinterface #180,  2          // InterfaceMethod javax/xml/stream/XMLStreamWriter.getPrefix:(Ljava/lang/String;)Ljava/lang/String;
       7: astore_3
       8: aload_3
       9: ifnonnull     74
      12: aload_2
      13: invokestatic  #183                // Method generatePrefix:(Ljava/lang/String;)Ljava/lang/String;
      16: astore_3
      17: aload_1
      18: invokeinterface #195,  1          // InterfaceMethod javax/xml/stream/XMLStreamWriter.getNamespaceContext:()Ljavax/xml/namespace/NamespaceContext;
      23: astore        4
      25: aload         4
      27: aload_3
      28: invokeinterface #196,  2          // InterfaceMethod javax/xml/namespace/NamespaceContext.getNamespaceURI:(Ljava/lang/String;)Ljava/lang/String;
      33: astore        5
      35: aload         5
      37: ifnull        58
      40: aload         5
      42: invokevirtual #95                 // Method java/lang/String.length:()I
      45: ifne          51
      48: goto          58
      51: invokestatic  #179                // Method org/apache/axis2/databinding/utils/BeanUtil.getUniquePrefix:()Ljava/lang/String;
      54: astore_3
      55: goto          25
      58: aload_1
      59: aload_3
      60: aload_2
      61: invokeinterface #184,  3          // InterfaceMethod javax/xml/stream/XMLStreamWriter.writeNamespace:(Ljava/lang/String;Ljava/lang/String;)V
      66: aload_1
      67: aload_3
      68: aload_2
      69: invokeinterface #185,  3          // InterfaceMethod javax/xml/stream/XMLStreamWriter.setPrefix:(Ljava/lang/String;Ljava/lang/String;)V
      74: aload_3
      75: areturn

  static {};
    Code:
       0: new           #197                // class javax/xml/namespace/QName
       3: dup
       4: ldc           #92                 // String urn:hpccsystems:ws:filespray
       6: ldc           #105                // String SprayVariable
       8: ldc           #178                // String ns2
      10: invokespecial #198                // Method javax/xml/namespace/QName."<init>":(Ljava/lang/String;Ljava/lang/String;Ljava/lang/String;)V
      13: putstatic     #84                 // Field MY_QNAME:Ljavax/xml/namespace/QName;
      16: return
}
