Compiled from "BinderProperties.java"
public class org.springframework.cloud.stream.config.BinderProperties {
  private java.lang.String type;

  private java.util.Map<java.lang.String, java.lang.Object> environment;

  private boolean inheritEnvironment;

  private boolean defaultCandidate;

  public org.springframework.cloud.stream.config.BinderProperties();
    Code:
       0: aload_0
       1: invokespecial #1                  // Method java/lang/Object."<init>":()V
       4: aload_0
       5: new           #2                  // class java/util/HashMap
       8: dup
       9: invokespecial #3                  // Method java/util/HashMap."<init>":()V
      12: putfield      #4                  // Field environment:Ljava/util/Map;
      15: aload_0
      16: iconst_1
      17: putfield      #5                  // Field inheritEnvironment:Z
      20: aload_0
      21: iconst_1
      22: putfield      #6                  // Field defaultCandidate:Z
      25: return

  public java.lang.String getType();
    Code:
       0: aload_0
       1: getfield      #7                  // Field type:Ljava/lang/String;
       4: areturn

  public void setType(java.lang.String);
    Code:
       0: aload_0
       1: aload_1
       2: putfield      #7                  // Field type:Ljava/lang/String;
       5: return

  public java.util.Map<java.lang.String, java.lang.Object> getEnvironment();
    Code:
       0: aload_0
       1: getfield      #4                  // Field environment:Ljava/util/Map;
       4: areturn

  public void setEnvironment(java.util.Properties);
    Code:
       0: aload_0
       1: getfield      #4                  // Field environment:Ljava/util/Map;
       4: invokeinterface #8,  1            // InterfaceMethod java/util/Map.clear:()V
       9: aload_0
      10: getfield      #4                  // Field environment:Ljava/util/Map;
      13: aload_1
      14: invokevirtual #9                  // Method java/util/Properties.entrySet:()Ljava/util/Set;
      17: invokeinterface #10,  1           // InterfaceMethod java/util/Set.stream:()Ljava/util/stream/Stream;
      22: invokedynamic #11,  0             // InvokeDynamic #0:apply:()Ljava/util/function/Function;
      27: invokedynamic #12,  0             // InvokeDynamic #1:apply:()Ljava/util/function/Function;
      32: invokestatic  #13                 // Method java/util/stream/Collectors.toMap:(Ljava/util/function/Function;Ljava/util/function/Function;)Ljava/util/stream/Collector;
      35: invokeinterface #14,  2           // InterfaceMethod java/util/stream/Stream.collect:(Ljava/util/stream/Collector;)Ljava/lang/Object;
      40: checkcast     #15                 // class java/util/Map
      43: invokeinterface #16,  2           // InterfaceMethod java/util/Map.putAll:(Ljava/util/Map;)V
      48: return

  public void setEnvironment(java.util.Map<java.lang.String, java.lang.Object>);
    Code:
       0: aload_0
       1: aload_1
       2: putfield      #4                  // Field environment:Ljava/util/Map;
       5: return

  public boolean isInheritEnvironment();
    Code:
       0: aload_0
       1: getfield      #5                  // Field inheritEnvironment:Z
       4: ireturn

  public void setInheritEnvironment(boolean);
    Code:
       0: aload_0
       1: iload_1
       2: putfield      #5                  // Field inheritEnvironment:Z
       5: return

  public boolean isDefaultCandidate();
    Code:
       0: aload_0
       1: getfield      #6                  // Field defaultCandidate:Z
       4: ireturn

  public void setDefaultCandidate(boolean);
    Code:
       0: aload_0
       1: iload_1
       2: putfield      #6                  // Field defaultCandidate:Z
       5: return

  private static java.lang.Object lambda$setEnvironment$1(java.util.Map$Entry);
    Code:
       0: aload_0
       1: invokeinterface #17,  1           // InterfaceMethod java/util/Map$Entry.getValue:()Ljava/lang/Object;
       6: areturn

  private static java.lang.String lambda$setEnvironment$0(java.util.Map$Entry);
    Code:
       0: aload_0
       1: invokeinterface #18,  1           // InterfaceMethod java/util/Map$Entry.getKey:()Ljava/lang/Object;
       6: invokevirtual #19                 // Method java/lang/Object.toString:()Ljava/lang/String;
       9: areturn
}
