Compiled from "BindersHealthIndicatorAutoConfiguration.java"
public class org.springframework.cloud.stream.config.BindersHealthIndicatorAutoConfiguration {
  public org.springframework.cloud.stream.config.BindersHealthIndicatorAutoConfiguration();
    Code:
       0: aload_0
       1: invokespecial #1                  // Method java/lang/Object."<init>":()V
       4: return

  public org.springframework.boot.actuate.health.CompositeHealthIndicator bindersHealthIndicator();
    Code:
       0: new           #2                  // class org/springframework/boot/actuate/health/CompositeHealthIndicator
       3: dup
       4: new           #3                  // class org/springframework/boot/actuate/health/OrderedHealthAggregator
       7: dup
       8: invokespecial #4                  // Method org/springframework/boot/actuate/health/OrderedHealthAggregator."<init>":()V
      11: new           #5                  // class org/springframework/boot/actuate/health/DefaultHealthIndicatorRegistry
      14: dup
      15: invokespecial #6                  // Method org/springframework/boot/actuate/health/DefaultHealthIndicatorRegistry."<init>":()V
      18: invokespecial #7                  // Method org/springframework/boot/actuate/health/CompositeHealthIndicator."<init>":(Lorg/springframework/boot/actuate/health/HealthAggregator;Lorg/springframework/boot/actuate/health/HealthIndicatorRegistry;)V
      21: areturn

  public org.springframework.cloud.stream.binder.DefaultBinderFactory$Listener bindersHealthIndicatorListener(org.springframework.boot.actuate.health.CompositeHealthIndicator);
    Code:
       0: new           #8                  // class org/springframework/cloud/stream/config/BindersHealthIndicatorAutoConfiguration$BindersHealthIndicatorListener
       3: dup
       4: aload_1
       5: invokespecial #9                  // Method org/springframework/cloud/stream/config/BindersHealthIndicatorAutoConfiguration$BindersHealthIndicatorListener."<init>":(Lorg/springframework/boot/actuate/health/CompositeHealthIndicator;)V
       8: areturn
}
