Compiled from "ProtobufRpcEngine.java"
class org.apache.hadoop.ipc.ProtobufRpcEngine$Server$CallInfo {
  private final org.apache.hadoop.ipc.RPC$Server server;

  private final java.lang.String methodName;

  public org.apache.hadoop.ipc.ProtobufRpcEngine$Server$CallInfo(org.apache.hadoop.ipc.RPC$Server, java.lang.String);
    Code:
       0: aload_0
       1: invokespecial #3                  // Method java/lang/Object."<init>":()V
       4: aload_0
       5: aload_1
       6: putfield      #2                  // Field server:Lorg/apache/hadoop/ipc/RPC$Server;
       9: aload_0
      10: aload_2
      11: putfield      #1                  // Field methodName:Ljava/lang/String;
      14: return

  static org.apache.hadoop.ipc.RPC$Server access$300(org.apache.hadoop.ipc.ProtobufRpcEngine$Server$CallInfo);
    Code:
       0: aload_0
       1: getfield      #2                  // Field server:Lorg/apache/hadoop/ipc/RPC$Server;
       4: areturn

  static java.lang.String access$400(org.apache.hadoop.ipc.ProtobufRpcEngine$Server$CallInfo);
    Code:
       0: aload_0
       1: getfield      #1                  // Field methodName:Ljava/lang/String;
       4: areturn
}
