Compiled from "Server.java"
class org.apache.hadoop.ipc.Server$ExceptionsHandler {
  private volatile java.util.Set<java.lang.String> terseExceptions;

  private volatile java.util.Set<java.lang.String> suppressedExceptions;

  org.apache.hadoop.ipc.Server$ExceptionsHandler();
    Code:
       0: aload_0
       1: invokespecial #1                  // Method java/lang/Object."<init>":()V
       4: aload_0
       5: new           #2                  // class java/util/HashSet
       8: dup
       9: invokespecial #3                  // Method java/util/HashSet."<init>":()V
      12: putfield      #4                  // Field terseExceptions:Ljava/util/Set;
      15: aload_0
      16: new           #2                  // class java/util/HashSet
      19: dup
      20: invokespecial #3                  // Method java/util/HashSet."<init>":()V
      23: putfield      #5                  // Field suppressedExceptions:Ljava/util/Set;
      26: return

  void addTerseLoggingExceptions(java.lang.Class<?>...);
    Code:
       0: aload_0
       1: aload_0
       2: getfield      #4                  // Field terseExceptions:Ljava/util/Set;
       5: aload_1
       6: invokestatic  #6                  // Method addExceptions:(Ljava/util/Set;[Ljava/lang/Class;)Ljava/util/Set;
       9: putfield      #4                  // Field terseExceptions:Ljava/util/Set;
      12: return

  void addSuppressedLoggingExceptions(java.lang.Class<?>...);
    Code:
       0: aload_0
       1: aload_0
       2: getfield      #5                  // Field suppressedExceptions:Ljava/util/Set;
       5: aload_1
       6: invokestatic  #6                  // Method addExceptions:(Ljava/util/Set;[Ljava/lang/Class;)Ljava/util/Set;
       9: putfield      #5                  // Field suppressedExceptions:Ljava/util/Set;
      12: return

  boolean isTerseLog(java.lang.Class<?>);
    Code:
       0: aload_0
       1: getfield      #4                  // Field terseExceptions:Ljava/util/Set;
       4: aload_1
       5: invokevirtual #7                  // Method java/lang/Class.toString:()Ljava/lang/String;
       8: invokeinterface #8,  2            // InterfaceMethod java/util/Set.contains:(Ljava/lang/Object;)Z
      13: ireturn

  boolean isSuppressedLog(java.lang.Class<?>);
    Code:
       0: aload_0
       1: getfield      #5                  // Field suppressedExceptions:Ljava/util/Set;
       4: aload_1
       5: invokevirtual #7                  // Method java/lang/Class.toString:()Ljava/lang/String;
       8: invokeinterface #8,  2            // InterfaceMethod java/util/Set.contains:(Ljava/lang/Object;)Z
      13: ireturn

  private static java.util.Set<java.lang.String> addExceptions(java.util.Set<java.lang.String>, java.lang.Class<?>[]);
    Code:
       0: new           #2                  // class java/util/HashSet
       3: dup
       4: aload_0
       5: invokespecial #9                  // Method java/util/HashSet."<init>":(Ljava/util/Collection;)V
       8: astore_2
       9: aload_1
      10: astore_3
      11: aload_3
      12: arraylength
      13: istore        4
      15: iconst_0
      16: istore        5
      18: iload         5
      20: iload         4
      22: if_icmpge     47
      25: aload_3
      26: iload         5
      28: aaload
      29: astore        6
      31: aload_2
      32: aload         6
      34: invokevirtual #7                  // Method java/lang/Class.toString:()Ljava/lang/String;
      37: invokevirtual #10                 // Method java/util/HashSet.add:(Ljava/lang/Object;)Z
      40: pop
      41: iinc          5, 1
      44: goto          18
      47: aload_2
      48: invokestatic  #11                 // Method java/util/Collections.unmodifiableSet:(Ljava/util/Set;)Ljava/util/Set;
      51: areturn
}
