Compiled from "ExecsTest.java"
class io.druid.concurrent.ExecsTest$1$1 implements java.lang.Runnable {
  final int val$taskID;

  final io.druid.concurrent.ExecsTest$1 this$0;

  io.druid.concurrent.ExecsTest$1$1(io.druid.concurrent.ExecsTest$1, int);
    Code:
       0: aload_0
       1: aload_1
       2: putfield      #1                  // Field this$0:Lio/druid/concurrent/ExecsTest$1;
       5: aload_0
       6: iload_2
       7: putfield      #2                  // Field val$taskID:I
      10: aload_0
      11: invokespecial #3                  // Method java/lang/Object."<init>":()V
      14: return

  public void run();
    Code:
       0: invokestatic  #4                  // Method io/druid/concurrent/ExecsTest.access$000:()Lcom/metamx/common/logger/Logger;
       3: ldc           #5                  // String Starting task: %s
       5: iconst_1
       6: anewarray     #6                  // class java/lang/Object
       9: dup
      10: iconst_0
      11: aload_0
      12: getfield      #2                  // Field val$taskID:I
      15: invokestatic  #7                  // Method java/lang/Integer.valueOf:(I)Ljava/lang/Integer;
      18: aastore
      19: invokevirtual #8                  // Method com/metamx/common/logger/Logger.info:(Ljava/lang/String;[Ljava/lang/Object;)V
      22: aload_0
      23: getfield      #1                  // Field this$0:Lio/druid/concurrent/ExecsTest$1;
      26: getfield      #9                  // Field io/druid/concurrent/ExecsTest$1.val$taskStartSignal:Ljava/util/concurrent/CountDownLatch;
      29: invokevirtual #10                 // Method java/util/concurrent/CountDownLatch.await:()V
      32: aload_0
      33: getfield      #1                  // Field this$0:Lio/druid/concurrent/ExecsTest$1;
      36: getfield      #11                 // Field io/druid/concurrent/ExecsTest$1.val$consumedCount:Ljava/util/concurrent/atomic/AtomicInteger;
      39: invokevirtual #12                 // Method java/util/concurrent/atomic/AtomicInteger.incrementAndGet:()I
      42: pop
      43: aload_0
      44: getfield      #1                  // Field this$0:Lio/druid/concurrent/ExecsTest$1;
      47: getfield      #13                 // Field io/druid/concurrent/ExecsTest$1.val$taskCompletedSignal:Ljava/util/concurrent/CountDownLatch;
      50: invokevirtual #14                 // Method java/util/concurrent/CountDownLatch.countDown:()V
      53: goto          62
      56: astore_1
      57: aload_1
      58: invokestatic  #16                 // Method com/google/common/base/Throwables.propagate:(Ljava/lang/Throwable;)Ljava/lang/RuntimeException;
      61: athrow
      62: invokestatic  #4                  // Method io/druid/concurrent/ExecsTest.access$000:()Lcom/metamx/common/logger/Logger;
      65: ldc           #17                 // String Completed task: %s
      67: iconst_1
      68: anewarray     #6                  // class java/lang/Object
      71: dup
      72: iconst_0
      73: aload_0
      74: getfield      #2                  // Field val$taskID:I
      77: invokestatic  #7                  // Method java/lang/Integer.valueOf:(I)Ljava/lang/Integer;
      80: aastore
      81: invokevirtual #8                  // Method com/metamx/common/logger/Logger.info:(Ljava/lang/String;[Ljava/lang/Object;)V
      84: return
    Exception table:
       from    to  target type
          22    53    56   Class java/lang/Exception
}
