Compiled from "DedicatedTenancySupportResultEnum.scala"
public final class zio.aws.workspaces.model.DedicatedTenancySupportResultEnum$ {
  public static final zio.aws.workspaces.model.DedicatedTenancySupportResultEnum$ MODULE$;

  public static {};
    Code:
       0: new           #2                  // class zio/aws/workspaces/model/DedicatedTenancySupportResultEnum$
       3: dup
       4: invokespecial #23                 // Method "<init>":()V
       7: putstatic     #25                 // Field MODULE$:Lzio/aws/workspaces/model/DedicatedTenancySupportResultEnum$;
      10: return

  public zio.aws.workspaces.model.DedicatedTenancySupportResultEnum wrap(software.amazon.awssdk.services.workspaces.model.DedicatedTenancySupportResultEnum);
    Code:
       0: aload_1
       1: astore_3
       2: getstatic     #34                 // Field software/amazon/awssdk/services/workspaces/model/DedicatedTenancySupportResultEnum.UNKNOWN_TO_SDK_VERSION:Lsoftware/amazon/awssdk/services/workspaces/model/DedicatedTenancySupportResultEnum;
       5: aload_3
       6: invokevirtual #38                 // Method java/lang/Object.equals:(Ljava/lang/Object;)Z
       9: ifeq          23
      12: getstatic     #41                 // Field zio/aws/workspaces/model/DedicatedTenancySupportResultEnum$unknownToSdkVersion$.MODULE$:Lzio/aws/workspaces/model/DedicatedTenancySupportResultEnum$unknownToSdkVersion$;
      15: astore        4
      17: aload         4
      19: astore_2
      20: goto          83
      23: goto          26
      26: getstatic     #44                 // Field software/amazon/awssdk/services/workspaces/model/DedicatedTenancySupportResultEnum.ENABLED:Lsoftware/amazon/awssdk/services/workspaces/model/DedicatedTenancySupportResultEnum;
      29: aload_3
      30: invokevirtual #38                 // Method java/lang/Object.equals:(Ljava/lang/Object;)Z
      33: ifeq          47
      36: getstatic     #47                 // Field zio/aws/workspaces/model/DedicatedTenancySupportResultEnum$ENABLED$.MODULE$:Lzio/aws/workspaces/model/DedicatedTenancySupportResultEnum$ENABLED$;
      39: astore        5
      41: aload         5
      43: astore_2
      44: goto          83
      47: goto          50
      50: getstatic     #50                 // Field software/amazon/awssdk/services/workspaces/model/DedicatedTenancySupportResultEnum.DISABLED:Lsoftware/amazon/awssdk/services/workspaces/model/DedicatedTenancySupportResultEnum;
      53: aload_3
      54: invokevirtual #38                 // Method java/lang/Object.equals:(Ljava/lang/Object;)Z
      57: ifeq          71
      60: getstatic     #53                 // Field zio/aws/workspaces/model/DedicatedTenancySupportResultEnum$DISABLED$.MODULE$:Lzio/aws/workspaces/model/DedicatedTenancySupportResultEnum$DISABLED$;
      63: astore        6
      65: aload         6
      67: astore_2
      68: goto          83
      71: goto          74
      74: new           #55                 // class scala/MatchError
      77: dup
      78: aload_3
      79: invokespecial #58                 // Method scala/MatchError."<init>":(Ljava/lang/Object;)V
      82: athrow
      83: aload_2
      84: areturn

  private zio.aws.workspaces.model.DedicatedTenancySupportResultEnum$();
    Code:
       0: aload_0
       1: invokespecial #61                 // Method java/lang/Object."<init>":()V
       4: return
}
