Compiled from "ImportWorkspaceImageRequest.scala"
public final class zio.aws.workspaces.model.ImportWorkspaceImageRequest implements scala.Product,java.io.Serializable {
  private final java.lang.String ec2ImageId;

  private final zio.aws.workspaces.model.WorkspaceImageIngestionProcess ingestionProcess;

  private final java.lang.String imageName;

  private final java.lang.String imageDescription;

  private final zio.prelude.data.Optional<scala.collection.Iterable<zio.aws.workspaces.model.Tag>> tags;

  private final zio.prelude.data.Optional<scala.collection.Iterable<zio.aws.workspaces.model.Application>> applications;

  public static zio.prelude.data.Optional<scala.collection.Iterable<zio.aws.workspaces.model.Application>> $lessinit$greater$default$6();
    Code:
       0: getstatic     #72                 // Field zio/aws/workspaces/model/ImportWorkspaceImageRequest$.MODULE$:Lzio/aws/workspaces/model/ImportWorkspaceImageRequest$;
       3: invokevirtual #74                 // Method zio/aws/workspaces/model/ImportWorkspaceImageRequest$.$lessinit$greater$default$6:()Lzio/prelude/data/Optional;
       6: areturn

  public static zio.prelude.data.Optional<scala.collection.Iterable<zio.aws.workspaces.model.Tag>> $lessinit$greater$default$5();
    Code:
       0: getstatic     #72                 // Field zio/aws/workspaces/model/ImportWorkspaceImageRequest$.MODULE$:Lzio/aws/workspaces/model/ImportWorkspaceImageRequest$;
       3: invokevirtual #78                 // Method zio/aws/workspaces/model/ImportWorkspaceImageRequest$.$lessinit$greater$default$5:()Lzio/prelude/data/Optional;
       6: areturn

  public static scala.Option<scala.Tuple6<java.lang.String, zio.aws.workspaces.model.WorkspaceImageIngestionProcess, java.lang.String, java.lang.String, zio.prelude.data.Optional<scala.collection.Iterable<zio.aws.workspaces.model.Tag>>, zio.prelude.data.Optional<scala.collection.Iterable<zio.aws.workspaces.model.Application>>>> unapply(zio.aws.workspaces.model.ImportWorkspaceImageRequest);
    Code:
       0: getstatic     #72                 // Field zio/aws/workspaces/model/ImportWorkspaceImageRequest$.MODULE$:Lzio/aws/workspaces/model/ImportWorkspaceImageRequest$;
       3: aload_0
       4: invokevirtual #84                 // Method zio/aws/workspaces/model/ImportWorkspaceImageRequest$.unapply:(Lzio/aws/workspaces/model/ImportWorkspaceImageRequest;)Lscala/Option;
       7: areturn

  public static zio.prelude.data.Optional<scala.collection.Iterable<zio.aws.workspaces.model.Application>> apply$default$6();
    Code:
       0: getstatic     #72                 // Field zio/aws/workspaces/model/ImportWorkspaceImageRequest$.MODULE$:Lzio/aws/workspaces/model/ImportWorkspaceImageRequest$;
       3: invokevirtual #88                 // Method zio/aws/workspaces/model/ImportWorkspaceImageRequest$.apply$default$6:()Lzio/prelude/data/Optional;
       6: areturn

  public static zio.prelude.data.Optional<scala.collection.Iterable<zio.aws.workspaces.model.Tag>> apply$default$5();
    Code:
       0: getstatic     #72                 // Field zio/aws/workspaces/model/ImportWorkspaceImageRequest$.MODULE$:Lzio/aws/workspaces/model/ImportWorkspaceImageRequest$;
       3: invokevirtual #91                 // Method zio/aws/workspaces/model/ImportWorkspaceImageRequest$.apply$default$5:()Lzio/prelude/data/Optional;
       6: areturn

  public static zio.aws.workspaces.model.ImportWorkspaceImageRequest apply(java.lang.String, zio.aws.workspaces.model.WorkspaceImageIngestionProcess, java.lang.String, java.lang.String, zio.prelude.data.Optional<scala.collection.Iterable<zio.aws.workspaces.model.Tag>>, zio.prelude.data.Optional<scala.collection.Iterable<zio.aws.workspaces.model.Application>>);
    Code:
       0: getstatic     #72                 // Field zio/aws/workspaces/model/ImportWorkspaceImageRequest$.MODULE$:Lzio/aws/workspaces/model/ImportWorkspaceImageRequest$;
       3: aload_0
       4: aload_1
       5: aload_2
       6: aload_3
       7: aload         4
       9: aload         5
      11: invokevirtual #96                 // Method zio/aws/workspaces/model/ImportWorkspaceImageRequest$.apply:(Ljava/lang/String;Lzio/aws/workspaces/model/WorkspaceImageIngestionProcess;Ljava/lang/String;Ljava/lang/String;Lzio/prelude/data/Optional;Lzio/prelude/data/Optional;)Lzio/aws/workspaces/model/ImportWorkspaceImageRequest;
      14: areturn

  public static zio.aws.workspaces.model.ImportWorkspaceImageRequest$ReadOnly wrap(software.amazon.awssdk.services.workspaces.model.ImportWorkspaceImageRequest);
    Code:
       0: getstatic     #72                 // Field zio/aws/workspaces/model/ImportWorkspaceImageRequest$.MODULE$:Lzio/aws/workspaces/model/ImportWorkspaceImageRequest$;
       3: aload_0
       4: invokevirtual #101                // Method zio/aws/workspaces/model/ImportWorkspaceImageRequest$.wrap:(Lsoftware/amazon/awssdk/services/workspaces/model/ImportWorkspaceImageRequest;)Lzio/aws/workspaces/model/ImportWorkspaceImageRequest$ReadOnly;
       7: areturn

  public scala.collection.Iterator<java.lang.String> productElementNames();
    Code:
       0: aload_0
       1: invokestatic  #109                // InterfaceMethod scala/Product.productElementNames$:(Lscala/Product;)Lscala/collection/Iterator;
       4: areturn

  public java.lang.String ec2ImageId();
    Code:
       0: aload_0
       1: getfield      #113                // Field ec2ImageId:Ljava/lang/String;
       4: areturn

  public zio.aws.workspaces.model.WorkspaceImageIngestionProcess ingestionProcess();
    Code:
       0: aload_0
       1: getfield      #116                // Field ingestionProcess:Lzio/aws/workspaces/model/WorkspaceImageIngestionProcess;
       4: areturn

  public java.lang.String imageName();
    Code:
       0: aload_0
       1: getfield      #118                // Field imageName:Ljava/lang/String;
       4: areturn

  public java.lang.String imageDescription();
    Code:
       0: aload_0
       1: getfield      #120                // Field imageDescription:Ljava/lang/String;
       4: areturn

  public zio.prelude.data.Optional<scala.collection.Iterable<zio.aws.workspaces.model.Tag>> tags();
    Code:
       0: aload_0
       1: getfield      #122                // Field tags:Lzio/prelude/data/Optional;
       4: areturn

  public zio.prelude.data.Optional<scala.collection.Iterable<zio.aws.workspaces.model.Application>> applications();
    Code:
       0: aload_0
       1: getfield      #124                // Field applications:Lzio/prelude/data/Optional;
       4: areturn

  public software.amazon.awssdk.services.workspaces.model.ImportWorkspaceImageRequest buildAwsValue();
    Code:
       0: getstatic     #72                 // Field zio/aws/workspaces/model/ImportWorkspaceImageRequest$.MODULE$:Lzio/aws/workspaces/model/ImportWorkspaceImageRequest$;
       3: invokevirtual #130                // Method zio/aws/workspaces/model/ImportWorkspaceImageRequest$.zio$aws$workspaces$model$ImportWorkspaceImageRequest$$zioAwsBuilderHelper:()Lzio/aws/core/BuilderHelper;
       6: getstatic     #72                 // Field zio/aws/workspaces/model/ImportWorkspaceImageRequest$.MODULE$:Lzio/aws/workspaces/model/ImportWorkspaceImageRequest$;
       9: invokevirtual #130                // Method zio/aws/workspaces/model/ImportWorkspaceImageRequest$.zio$aws$workspaces$model$ImportWorkspaceImageRequest$$zioAwsBuilderHelper:()Lzio/aws/core/BuilderHelper;
      12: invokestatic  #134                // Method software/amazon/awssdk/services/workspaces/model/ImportWorkspaceImageRequest.builder:()Lsoftware/amazon/awssdk/services/workspaces/model/ImportWorkspaceImageRequest$Builder;
      15: getstatic     #137                // Field zio/aws/workspaces/model/package$primitives$Ec2ImageId$.MODULE$:Lzio/aws/workspaces/model/package$primitives$Ec2ImageId$;
      18: aload_0
      19: invokevirtual #139                // Method ec2ImageId:()Ljava/lang/String;
      22: invokevirtual #143                // Method zio/aws/workspaces/model/package$primitives$Ec2ImageId$.unwrap:(Ljava/lang/Object;)Ljava/lang/Object;
      25: checkcast     #145                // class java/lang/String
      28: invokeinterface #148,  2          // InterfaceMethod software/amazon/awssdk/services/workspaces/model/ImportWorkspaceImageRequest$Builder.ec2ImageId:(Ljava/lang/String;)Lsoftware/amazon/awssdk/services/workspaces/model/ImportWorkspaceImageRequest$Builder;
      33: aload_0
      34: invokevirtual #150                // Method ingestionProcess:()Lzio/aws/workspaces/model/WorkspaceImageIngestionProcess;
      37: invokeinterface #155,  1          // InterfaceMethod zio/aws/workspaces/model/WorkspaceImageIngestionProcess.unwrap:()Lsoftware/amazon/awssdk/services/workspaces/model/WorkspaceImageIngestionProcess;
      42: invokeinterface #158,  2          // InterfaceMethod software/amazon/awssdk/services/workspaces/model/ImportWorkspaceImageRequest$Builder.ingestionProcess:(Lsoftware/amazon/awssdk/services/workspaces/model/WorkspaceImageIngestionProcess;)Lsoftware/amazon/awssdk/services/workspaces/model/ImportWorkspaceImageRequest$Builder;
      47: getstatic     #161                // Field zio/aws/workspaces/model/package$primitives$WorkspaceImageName$.MODULE$:Lzio/aws/workspaces/model/package$primitives$WorkspaceImageName$;
      50: aload_0
      51: invokevirtual #163                // Method imageName:()Ljava/lang/String;
      54: invokevirtual #164                // Method zio/aws/workspaces/model/package$primitives$WorkspaceImageName$.unwrap:(Ljava/lang/Object;)Ljava/lang/Object;
      57: checkcast     #145                // class java/lang/String
      60: invokeinterface #166,  2          // InterfaceMethod software/amazon/awssdk/services/workspaces/model/ImportWorkspaceImageRequest$Builder.imageName:(Ljava/lang/String;)Lsoftware/amazon/awssdk/services/workspaces/model/ImportWorkspaceImageRequest$Builder;
      65: getstatic     #169                // Field zio/aws/workspaces/model/package$primitives$WorkspaceImageDescription$.MODULE$:Lzio/aws/workspaces/model/package$primitives$WorkspaceImageDescription$;
      68: aload_0
      69: invokevirtual #171                // Method imageDescription:()Ljava/lang/String;
      72: invokevirtual #172                // Method zio/aws/workspaces/model/package$primitives$WorkspaceImageDescription$.unwrap:(Ljava/lang/Object;)Ljava/lang/Object;
      75: checkcast     #145                // class java/lang/String
      78: invokeinterface #174,  2          // InterfaceMethod software/amazon/awssdk/services/workspaces/model/ImportWorkspaceImageRequest$Builder.imageDescription:(Ljava/lang/String;)Lsoftware/amazon/awssdk/services/workspaces/model/ImportWorkspaceImageRequest$Builder;
      83: invokeinterface #177,  2          // InterfaceMethod zio/aws/core/BuilderHelper.BuilderOps:(Lsoftware/amazon/awssdk/utils/builder/SdkBuilder;)Lzio/aws/core/BuilderHelper$BuilderOps;
      88: aload_0
      89: invokevirtual #179                // Method tags:()Lzio/prelude/data/Optional;
      92: invokedynamic #198,  0            // InvokeDynamic #0:apply:()Lscala/Function1;
      97: invokeinterface #204,  2          // InterfaceMethod zio/prelude/data/Optional.map:(Lscala/Function1;)Lzio/prelude/data/Optional;
     102: invokedynamic #211,  0            // InvokeDynamic #1:apply:()Lscala/Function1;
     107: invokevirtual #215                // Method zio/aws/core/BuilderHelper$BuilderOps.optionallyWith:(Lzio/prelude/data/Optional;Lscala/Function1;)Lsoftware/amazon/awssdk/utils/builder/SdkBuilder;
     110: invokeinterface #177,  2          // InterfaceMethod zio/aws/core/BuilderHelper.BuilderOps:(Lsoftware/amazon/awssdk/utils/builder/SdkBuilder;)Lzio/aws/core/BuilderHelper$BuilderOps;
     115: aload_0
     116: invokevirtual #217                // Method applications:()Lzio/prelude/data/Optional;
     119: invokedynamic #222,  0            // InvokeDynamic #2:apply:()Lscala/Function1;
     124: invokeinterface #204,  2          // InterfaceMethod zio/prelude/data/Optional.map:(Lscala/Function1;)Lzio/prelude/data/Optional;
     129: invokedynamic #227,  0            // InvokeDynamic #3:apply:()Lscala/Function1;
     134: invokevirtual #215                // Method zio/aws/core/BuilderHelper$BuilderOps.optionallyWith:(Lzio/prelude/data/Optional;Lscala/Function1;)Lsoftware/amazon/awssdk/utils/builder/SdkBuilder;
     137: invokeinterface #233,  1          // InterfaceMethod software/amazon/awssdk/utils/builder/SdkBuilder.build:()Ljava/lang/Object;
     142: checkcast     #26                 // class software/amazon/awssdk/services/workspaces/model/ImportWorkspaceImageRequest
     145: areturn

  public zio.aws.workspaces.model.ImportWorkspaceImageRequest$ReadOnly asReadOnly();
    Code:
       0: getstatic     #72                 // Field zio/aws/workspaces/model/ImportWorkspaceImageRequest$.MODULE$:Lzio/aws/workspaces/model/ImportWorkspaceImageRequest$;
       3: aload_0
       4: invokevirtual #237                // Method buildAwsValue:()Lsoftware/amazon/awssdk/services/workspaces/model/ImportWorkspaceImageRequest;
       7: invokevirtual #101                // Method zio/aws/workspaces/model/ImportWorkspaceImageRequest$.wrap:(Lsoftware/amazon/awssdk/services/workspaces/model/ImportWorkspaceImageRequest;)Lzio/aws/workspaces/model/ImportWorkspaceImageRequest$ReadOnly;
      10: areturn

  public zio.aws.workspaces.model.ImportWorkspaceImageRequest copy(java.lang.String, zio.aws.workspaces.model.WorkspaceImageIngestionProcess, java.lang.String, java.lang.String, zio.prelude.data.Optional<scala.collection.Iterable<zio.aws.workspaces.model.Tag>>, zio.prelude.data.Optional<scala.collection.Iterable<zio.aws.workspaces.model.Application>>);
    Code:
       0: new           #2                  // class zio/aws/workspaces/model/ImportWorkspaceImageRequest
       3: dup
       4: aload_1
       5: aload_2
       6: aload_3
       7: aload         4
       9: aload         5
      11: aload         6
      13: invokespecial #242                // Method "<init>":(Ljava/lang/String;Lzio/aws/workspaces/model/WorkspaceImageIngestionProcess;Ljava/lang/String;Ljava/lang/String;Lzio/prelude/data/Optional;Lzio/prelude/data/Optional;)V
      16: areturn

  public java.lang.String copy$default$1();
    Code:
       0: aload_0
       1: invokevirtual #139                // Method ec2ImageId:()Ljava/lang/String;
       4: areturn

  public zio.aws.workspaces.model.WorkspaceImageIngestionProcess copy$default$2();
    Code:
       0: aload_0
       1: invokevirtual #150                // Method ingestionProcess:()Lzio/aws/workspaces/model/WorkspaceImageIngestionProcess;
       4: areturn

  public java.lang.String copy$default$3();
    Code:
       0: aload_0
       1: invokevirtual #163                // Method imageName:()Ljava/lang/String;
       4: areturn

  public java.lang.String copy$default$4();
    Code:
       0: aload_0
       1: invokevirtual #171                // Method imageDescription:()Ljava/lang/String;
       4: areturn

  public zio.prelude.data.Optional<scala.collection.Iterable<zio.aws.workspaces.model.Tag>> copy$default$5();
    Code:
       0: aload_0
       1: invokevirtual #179                // Method tags:()Lzio/prelude/data/Optional;
       4: areturn

  public zio.prelude.data.Optional<scala.collection.Iterable<zio.aws.workspaces.model.Application>> copy$default$6();
    Code:
       0: aload_0
       1: invokevirtual #217                // Method applications:()Lzio/prelude/data/Optional;
       4: areturn

  public java.lang.String productPrefix();
    Code:
       0: ldc           #251                // String ImportWorkspaceImageRequest
       2: areturn

  public int productArity();
    Code:
       0: bipush        6
       2: ireturn

  public java.lang.Object productElement(int);
    Code:
       0: iload_1
       1: istore_2
       2: iload_2
       3: tableswitch   { // 0 to 5
                     0: 40
                     1: 47
                     2: 54
                     3: 61
                     4: 68
                     5: 75
               default: 82
          }
      40: aload_0
      41: invokevirtual #139                // Method ec2ImageId:()Ljava/lang/String;
      44: goto          89
      47: aload_0
      48: invokevirtual #150                // Method ingestionProcess:()Lzio/aws/workspaces/model/WorkspaceImageIngestionProcess;
      51: goto          89
      54: aload_0
      55: invokevirtual #163                // Method imageName:()Ljava/lang/String;
      58: goto          89
      61: aload_0
      62: invokevirtual #171                // Method imageDescription:()Ljava/lang/String;
      65: goto          89
      68: aload_0
      69: invokevirtual #179                // Method tags:()Lzio/prelude/data/Optional;
      72: goto          89
      75: aload_0
      76: invokevirtual #217                // Method applications:()Lzio/prelude/data/Optional;
      79: goto          89
      82: iload_1
      83: invokestatic  #261                // Method scala/runtime/Statics.ioobe:(I)Ljava/lang/Object;
      86: goto          89
      89: areturn

  public scala.collection.Iterator<java.lang.Object> productIterator();
    Code:
       0: getstatic     #269                // Field scala/runtime/ScalaRunTime$.MODULE$:Lscala/runtime/ScalaRunTime$;
       3: aload_0
       4: invokevirtual #272                // Method scala/runtime/ScalaRunTime$.typedProductIterator:(Lscala/Product;)Lscala/collection/Iterator;
       7: areturn

  public boolean canEqual(java.lang.Object);
    Code:
       0: aload_1
       1: instanceof    #2                  // class zio/aws/workspaces/model/ImportWorkspaceImageRequest
       4: ireturn

  public java.lang.String productElementName(int);
    Code:
       0: iload_1
       1: istore_2
       2: iload_2
       3: tableswitch   { // 0 to 5
                     0: 40
                     1: 46
                     2: 52
                     3: 58
                     4: 64
                     5: 70
               default: 76
          }
      40: ldc_w         #278                // String ec2ImageId
      43: goto          86
      46: ldc_w         #279                // String ingestionProcess
      49: goto          86
      52: ldc_w         #280                // String imageName
      55: goto          86
      58: ldc_w         #281                // String imageDescription
      61: goto          86
      64: ldc_w         #282                // String tags
      67: goto          86
      70: ldc_w         #283                // String applications
      73: goto          86
      76: iload_1
      77: invokestatic  #261                // Method scala/runtime/Statics.ioobe:(I)Ljava/lang/Object;
      80: checkcast     #145                // class java/lang/String
      83: goto          86
      86: areturn

  public int hashCode();
    Code:
       0: getstatic     #269                // Field scala/runtime/ScalaRunTime$.MODULE$:Lscala/runtime/ScalaRunTime$;
       3: aload_0
       4: invokevirtual #288                // Method scala/runtime/ScalaRunTime$._hashCode:(Lscala/Product;)I
       7: ireturn

  public java.lang.String toString();
    Code:
       0: getstatic     #269                // Field scala/runtime/ScalaRunTime$.MODULE$:Lscala/runtime/ScalaRunTime$;
       3: aload_0
       4: invokevirtual #293                // Method scala/runtime/ScalaRunTime$._toString:(Lscala/Product;)Ljava/lang/String;
       7: areturn

  public boolean equals(java.lang.Object);
    Code:
       0: aload_0
       1: aload_1
       2: if_acmpeq     237
       5: aload_1
       6: astore_3
       7: aload_3
       8: instanceof    #2                  // class zio/aws/workspaces/model/ImportWorkspaceImageRequest
      11: ifeq          19
      14: iconst_1
      15: istore_2
      16: goto          27
      19: goto          22
      22: iconst_0
      23: istore_2
      24: goto          27
      27: iload_2
      28: ifeq          241
      31: aload_1
      32: checkcast     #2                  // class zio/aws/workspaces/model/ImportWorkspaceImageRequest
      35: astore        4
      37: aload_0
      38: invokevirtual #139                // Method ec2ImageId:()Ljava/lang/String;
      41: aload         4
      43: invokevirtual #139                // Method ec2ImageId:()Ljava/lang/String;
      46: astore        5
      48: dup
      49: ifnonnull     61
      52: pop
      53: aload         5
      55: ifnull        69
      58: goto          233
      61: aload         5
      63: invokevirtual #296                // Method java/lang/Object.equals:(Ljava/lang/Object;)Z
      66: ifeq          233
      69: aload_0
      70: invokevirtual #150                // Method ingestionProcess:()Lzio/aws/workspaces/model/WorkspaceImageIngestionProcess;
      73: aload         4
      75: invokevirtual #150                // Method ingestionProcess:()Lzio/aws/workspaces/model/WorkspaceImageIngestionProcess;
      78: astore        6
      80: dup
      81: ifnonnull     93
      84: pop
      85: aload         6
      87: ifnull        101
      90: goto          233
      93: aload         6
      95: invokevirtual #296                // Method java/lang/Object.equals:(Ljava/lang/Object;)Z
      98: ifeq          233
     101: aload_0
     102: invokevirtual #163                // Method imageName:()Ljava/lang/String;
     105: aload         4
     107: invokevirtual #163                // Method imageName:()Ljava/lang/String;
     110: astore        7
     112: dup
     113: ifnonnull     125
     116: pop
     117: aload         7
     119: ifnull        133
     122: goto          233
     125: aload         7
     127: invokevirtual #296                // Method java/lang/Object.equals:(Ljava/lang/Object;)Z
     130: ifeq          233
     133: aload_0
     134: invokevirtual #171                // Method imageDescription:()Ljava/lang/String;
     137: aload         4
     139: invokevirtual #171                // Method imageDescription:()Ljava/lang/String;
     142: astore        8
     144: dup
     145: ifnonnull     157
     148: pop
     149: aload         8
     151: ifnull        165
     154: goto          233
     157: aload         8
     159: invokevirtual #296                // Method java/lang/Object.equals:(Ljava/lang/Object;)Z
     162: ifeq          233
     165: aload_0
     166: invokevirtual #179                // Method tags:()Lzio/prelude/data/Optional;
     169: aload         4
     171: invokevirtual #179                // Method tags:()Lzio/prelude/data/Optional;
     174: astore        9
     176: dup
     177: ifnonnull     189
     180: pop
     181: aload         9
     183: ifnull        197
     186: goto          233
     189: aload         9
     191: invokevirtual #296                // Method java/lang/Object.equals:(Ljava/lang/Object;)Z
     194: ifeq          233
     197: aload_0
     198: invokevirtual #217                // Method applications:()Lzio/prelude/data/Optional;
     201: aload         4
     203: invokevirtual #217                // Method applications:()Lzio/prelude/data/Optional;
     206: astore        10
     208: dup
     209: ifnonnull     221
     212: pop
     213: aload         10
     215: ifnull        229
     218: goto          233
     221: aload         10
     223: invokevirtual #296                // Method java/lang/Object.equals:(Ljava/lang/Object;)Z
     226: ifeq          233
     229: iconst_1
     230: goto          234
     233: iconst_0
     234: ifeq          241
     237: iconst_1
     238: goto          242
     241: iconst_0
     242: ireturn

  public static final software.amazon.awssdk.services.workspaces.model.Tag $anonfun$buildAwsValue$2(zio.aws.workspaces.model.Tag);
    Code:
       0: aload_0
       1: invokevirtual #304                // Method zio/aws/workspaces/model/Tag.buildAwsValue:()Lsoftware/amazon/awssdk/services/workspaces/model/Tag;
       4: areturn

  public static final java.util.Collection $anonfun$buildAwsValue$1(scala.collection.Iterable);
    Code:
       0: getstatic     #311                // Field scala/jdk/CollectionConverters$.MODULE$:Lscala/jdk/CollectionConverters$;
       3: aload_0
       4: invokedynamic #316,  0            // InvokeDynamic #4:apply:()Lscala/Function1;
       9: invokeinterface #321,  2          // InterfaceMethod scala/collection/Iterable.map:(Lscala/Function1;)Ljava/lang/Object;
      14: checkcast     #318                // class scala/collection/Iterable
      17: invokevirtual #324                // Method scala/jdk/CollectionConverters$.IterableHasAsJava:(Lscala/collection/Iterable;)Lscala/collection/convert/AsJavaExtensions$IterableHasAsJava;
      20: invokevirtual #328                // Method scala/collection/convert/AsJavaExtensions$IterableHasAsJava.asJavaCollection:()Ljava/util/Collection;
      23: areturn

  public static final software.amazon.awssdk.services.workspaces.model.ImportWorkspaceImageRequest$Builder $anonfun$buildAwsValue$4(software.amazon.awssdk.services.workspaces.model.ImportWorkspaceImageRequest$Builder, java.util.Collection);
    Code:
       0: aload_0
       1: aload_1
       2: invokeinterface #335,  2          // InterfaceMethod software/amazon/awssdk/services/workspaces/model/ImportWorkspaceImageRequest$Builder.tags:(Ljava/util/Collection;)Lsoftware/amazon/awssdk/services/workspaces/model/ImportWorkspaceImageRequest$Builder;
       7: areturn

  public static final scala.Function1 $anonfun$buildAwsValue$3(software.amazon.awssdk.services.workspaces.model.ImportWorkspaceImageRequest$Builder);
    Code:
       0: aload_0
       1: invokedynamic #343,  0            // InvokeDynamic #5:apply:(Lsoftware/amazon/awssdk/services/workspaces/model/ImportWorkspaceImageRequest$Builder;)Lscala/Function1;
       6: areturn

  public static final java.lang.String $anonfun$buildAwsValue$6(zio.aws.workspaces.model.Application);
    Code:
       0: aload_0
       1: invokeinterface #350,  1          // InterfaceMethod zio/aws/workspaces/model/Application.unwrap:()Lsoftware/amazon/awssdk/services/workspaces/model/Application;
       6: invokevirtual #354                // Method software/amazon/awssdk/services/workspaces/model/Application.toString:()Ljava/lang/String;
       9: areturn

  public static final java.util.Collection $anonfun$buildAwsValue$5(scala.collection.Iterable);
    Code:
       0: getstatic     #311                // Field scala/jdk/CollectionConverters$.MODULE$:Lscala/jdk/CollectionConverters$;
       3: aload_0
       4: invokedynamic #360,  0            // InvokeDynamic #6:apply:()Lscala/Function1;
       9: invokeinterface #321,  2          // InterfaceMethod scala/collection/Iterable.map:(Lscala/Function1;)Ljava/lang/Object;
      14: checkcast     #318                // class scala/collection/Iterable
      17: invokevirtual #324                // Method scala/jdk/CollectionConverters$.IterableHasAsJava:(Lscala/collection/Iterable;)Lscala/collection/convert/AsJavaExtensions$IterableHasAsJava;
      20: invokevirtual #328                // Method scala/collection/convert/AsJavaExtensions$IterableHasAsJava.asJavaCollection:()Ljava/util/Collection;
      23: areturn

  public static final software.amazon.awssdk.services.workspaces.model.ImportWorkspaceImageRequest$Builder $anonfun$buildAwsValue$8(software.amazon.awssdk.services.workspaces.model.ImportWorkspaceImageRequest$Builder, java.util.Collection);
    Code:
       0: aload_0
       1: aload_1
       2: invokeinterface #365,  2          // InterfaceMethod software/amazon/awssdk/services/workspaces/model/ImportWorkspaceImageRequest$Builder.applicationsWithStrings:(Ljava/util/Collection;)Lsoftware/amazon/awssdk/services/workspaces/model/ImportWorkspaceImageRequest$Builder;
       7: areturn

  public static final scala.Function1 $anonfun$buildAwsValue$7(software.amazon.awssdk.services.workspaces.model.ImportWorkspaceImageRequest$Builder);
    Code:
       0: aload_0
       1: invokedynamic #370,  0            // InvokeDynamic #7:apply:(Lsoftware/amazon/awssdk/services/workspaces/model/ImportWorkspaceImageRequest$Builder;)Lscala/Function1;
       6: areturn

  public zio.aws.workspaces.model.ImportWorkspaceImageRequest(java.lang.String, zio.aws.workspaces.model.WorkspaceImageIngestionProcess, java.lang.String, java.lang.String, zio.prelude.data.Optional<scala.collection.Iterable<zio.aws.workspaces.model.Tag>>, zio.prelude.data.Optional<scala.collection.Iterable<zio.aws.workspaces.model.Application>>);
    Code:
       0: aload_0
       1: aload_1
       2: putfield      #113                // Field ec2ImageId:Ljava/lang/String;
       5: aload_0
       6: aload_2
       7: putfield      #116                // Field ingestionProcess:Lzio/aws/workspaces/model/WorkspaceImageIngestionProcess;
      10: aload_0
      11: aload_3
      12: putfield      #118                // Field imageName:Ljava/lang/String;
      15: aload_0
      16: aload         4
      18: putfield      #120                // Field imageDescription:Ljava/lang/String;
      21: aload_0
      22: aload         5
      24: putfield      #122                // Field tags:Lzio/prelude/data/Optional;
      27: aload_0
      28: aload         6
      30: putfield      #124                // Field applications:Lzio/prelude/data/Optional;
      33: aload_0
      34: invokespecial #374                // Method java/lang/Object."<init>":()V
      37: aload_0
      38: invokestatic  #378                // InterfaceMethod scala/Product.$init$:(Lscala/Product;)V
      41: return

  private static java.lang.Object $deserializeLambda$(java.lang.invoke.SerializedLambda);
    Code:
       0: aload_0
       1: invokedynamic #390,  0            // InvokeDynamic #8:lambdaDeserialize:(Ljava/lang/invoke/SerializedLambda;)Ljava/lang/Object;
       6: areturn
}
