Compiled from "ModifyWorkspaceStateRequest.scala"
public interface zio.aws.workspaces.model.ModifyWorkspaceStateRequest$ReadOnly {
  public static zio.aws.workspaces.model.ModifyWorkspaceStateRequest asEditable$(zio.aws.workspaces.model.ModifyWorkspaceStateRequest$ReadOnly);
    Code:
       0: aload_0
       1: invokespecial #20                 // InterfaceMethod asEditable:()Lzio/aws/workspaces/model/ModifyWorkspaceStateRequest;
       4: areturn

  public default zio.aws.workspaces.model.ModifyWorkspaceStateRequest asEditable();
    Code:
       0: new           #12                 // class zio/aws/workspaces/model/ModifyWorkspaceStateRequest
       3: dup
       4: aload_0
       5: invokeinterface #25,  1           // InterfaceMethod workspaceId:()Ljava/lang/String;
      10: aload_0
      11: invokeinterface #29,  1           // InterfaceMethod workspaceState:()Lzio/aws/workspaces/model/TargetWorkspaceState;
      16: invokespecial #33                 // Method zio/aws/workspaces/model/ModifyWorkspaceStateRequest."<init>":(Ljava/lang/String;Lzio/aws/workspaces/model/TargetWorkspaceState;)V
      19: areturn

  public abstract java.lang.String workspaceId();

  public abstract zio.aws.workspaces.model.TargetWorkspaceState workspaceState();

  public static zio.ZIO getWorkspaceId$(zio.aws.workspaces.model.ModifyWorkspaceStateRequest$ReadOnly);
    Code:
       0: aload_0
       1: invokespecial #40                 // InterfaceMethod getWorkspaceId:()Lzio/ZIO;
       4: areturn

  public default zio.ZIO<java.lang.Object, scala.runtime.Nothing$, java.lang.String> getWorkspaceId();
    Code:
       0: getstatic     #47                 // Field zio/ZIO$.MODULE$:Lzio/ZIO$;
       3: aload_0
       4: invokedynamic #68,  0             // InvokeDynamic #0:apply:(Lzio/aws/workspaces/model/ModifyWorkspaceStateRequest$ReadOnly;)Lscala/Function0;
       9: ldc           #70                 // String zio.aws.workspaces.model.ModifyWorkspaceStateRequest.ReadOnly.getWorkspaceId(ModifyWorkspaceStateRequest.scala:34)
      11: invokevirtual #74                 // Method zio/ZIO$.succeed:(Lscala/Function0;Ljava/lang/Object;)Lzio/ZIO;
      14: areturn

  public static zio.ZIO getWorkspaceState$(zio.aws.workspaces.model.ModifyWorkspaceStateRequest$ReadOnly);
    Code:
       0: aload_0
       1: invokespecial #78                 // InterfaceMethod getWorkspaceState:()Lzio/ZIO;
       4: areturn

  public default zio.ZIO<java.lang.Object, scala.runtime.Nothing$, zio.aws.workspaces.model.TargetWorkspaceState> getWorkspaceState();
    Code:
       0: getstatic     #47                 // Field zio/ZIO$.MODULE$:Lzio/ZIO$;
       3: aload_0
       4: invokedynamic #86,  0             // InvokeDynamic #1:apply:(Lzio/aws/workspaces/model/ModifyWorkspaceStateRequest$ReadOnly;)Lscala/Function0;
       9: ldc           #88                 // String zio.aws.workspaces.model.ModifyWorkspaceStateRequest.ReadOnly.getWorkspaceState(ModifyWorkspaceStateRequest.scala:37)
      11: invokevirtual #74                 // Method zio/ZIO$.succeed:(Lscala/Function0;Ljava/lang/Object;)Lzio/ZIO;
      14: areturn

  public static java.lang.String $anonfun$getWorkspaceId$1(zio.aws.workspaces.model.ModifyWorkspaceStateRequest$ReadOnly);
    Code:
       0: aload_0
       1: invokeinterface #25,  1           // InterfaceMethod workspaceId:()Ljava/lang/String;
       6: areturn

  public static zio.aws.workspaces.model.TargetWorkspaceState $anonfun$getWorkspaceState$1(zio.aws.workspaces.model.ModifyWorkspaceStateRequest$ReadOnly);
    Code:
       0: aload_0
       1: invokeinterface #29,  1           // InterfaceMethod workspaceState:()Lzio/aws/workspaces/model/TargetWorkspaceState;
       6: areturn

  public static void $init$(zio.aws.workspaces.model.ModifyWorkspaceStateRequest$ReadOnly);
    Code:
       0: return

  private static java.lang.Object $deserializeLambda$(java.lang.invoke.SerializedLambda);
    Code:
       0: aload_0
       1: invokedynamic #102,  0            // InvokeDynamic #2:lambdaDeserialize:(Ljava/lang/invoke/SerializedLambda;)Ljava/lang/Object;
       6: areturn
}
