Compiled from "AutoValue_GrokPatternEntity.java"
final class org.graylog2.contentpacks.model.entities.AutoValue_GrokPatternEntity extends org.graylog2.contentpacks.model.entities.$AutoValue_GrokPatternEntity {
  org.graylog2.contentpacks.model.entities.AutoValue_GrokPatternEntity(java.lang.String, java.lang.String);
    Code:
       0: aload_0
       1: aload_1
       2: aload_2
       3: invokespecial #1                  // Method org/graylog2/contentpacks/model/entities/$AutoValue_GrokPatternEntity."<init>":(Ljava/lang/String;Ljava/lang/String;)V
       6: return

  public final java.lang.String getName();
    Code:
       0: aload_0
       1: invokevirtual #2                  // Method name:()Ljava/lang/String;
       4: areturn

  public final java.lang.String getPattern();
    Code:
       0: aload_0
       1: invokevirtual #3                  // Method pattern:()Ljava/lang/String;
       4: areturn
}
