Compiled from "AutoValue_PipelineEntity.java"
final class org.graylog2.contentpacks.model.entities.AutoValue_PipelineEntity extends org.graylog2.contentpacks.model.entities.$AutoValue_PipelineEntity {
  org.graylog2.contentpacks.model.entities.AutoValue_PipelineEntity(org.graylog2.contentpacks.model.entities.references.ValueReference, org.graylog2.contentpacks.model.entities.references.ValueReference, org.graylog2.contentpacks.model.entities.references.ValueReference, java.util.Set<org.graylog2.contentpacks.model.entities.references.ValueReference>);
    Code:
       0: aload_0
       1: aload_1
       2: aload_2
       3: aload_3
       4: aload         4
       6: invokespecial #1                  // Method org/graylog2/contentpacks/model/entities/$AutoValue_PipelineEntity."<init>":(Lorg/graylog2/contentpacks/model/entities/references/ValueReference;Lorg/graylog2/contentpacks/model/entities/references/ValueReference;Lorg/graylog2/contentpacks/model/entities/references/ValueReference;Ljava/util/Set;)V
       9: return

  public final org.graylog2.contentpacks.model.entities.references.ValueReference getTitle();
    Code:
       0: aload_0
       1: invokevirtual #2                  // Method title:()Lorg/graylog2/contentpacks/model/entities/references/ValueReference;
       4: areturn

  public final org.graylog2.contentpacks.model.entities.references.ValueReference getDescription();
    Code:
       0: aload_0
       1: invokevirtual #3                  // Method description:()Lorg/graylog2/contentpacks/model/entities/references/ValueReference;
       4: areturn

  public final org.graylog2.contentpacks.model.entities.references.ValueReference getSource();
    Code:
       0: aload_0
       1: invokevirtual #4                  // Method source:()Lorg/graylog2/contentpacks/model/entities/references/ValueReference;
       4: areturn

  public final java.util.Set<org.graylog2.contentpacks.model.entities.references.ValueReference> getConnectedStreams();
    Code:
       0: aload_0
       1: invokevirtual #5                  // Method connectedStreams:()Ljava/util/Set;
       4: areturn
}
