Compiled from "LookupTableEntity.java"
public abstract class org.graylog2.contentpacks.model.entities.LookupTableEntity {
  public org.graylog2.contentpacks.model.entities.LookupTableEntity();
    Code:
       0: aload_0
       1: invokespecial #1                  // Method java/lang/Object."<init>":()V
       4: return

  public abstract org.graylog2.contentpacks.model.entities.references.ValueReference name();

  public abstract org.graylog2.contentpacks.model.entities.references.ValueReference title();

  public abstract org.graylog2.contentpacks.model.entities.references.ValueReference description();

  public abstract org.graylog2.contentpacks.model.entities.references.ValueReference cacheName();

  public abstract org.graylog2.contentpacks.model.entities.references.ValueReference dataAdapterName();

  public abstract org.graylog2.contentpacks.model.entities.references.ValueReference defaultSingleValue();

  public abstract org.graylog2.contentpacks.model.entities.references.ValueReference defaultSingleValueType();

  public abstract org.graylog2.contentpacks.model.entities.references.ValueReference defaultMultiValue();

  public abstract org.graylog2.contentpacks.model.entities.references.ValueReference defaultMultiValueType();

  public static org.graylog2.contentpacks.model.entities.LookupTableEntity create(org.graylog2.contentpacks.model.entities.references.ValueReference, org.graylog2.contentpacks.model.entities.references.ValueReference, org.graylog2.contentpacks.model.entities.references.ValueReference, org.graylog2.contentpacks.model.entities.references.ValueReference, org.graylog2.contentpacks.model.entities.references.ValueReference, org.graylog2.contentpacks.model.entities.references.ValueReference, org.graylog2.contentpacks.model.entities.references.ValueReference, org.graylog2.contentpacks.model.entities.references.ValueReference, org.graylog2.contentpacks.model.entities.references.ValueReference);
    Code:
       0: new           #2                  // class org/graylog2/contentpacks/model/entities/AutoValue_LookupTableEntity
       3: dup
       4: aload_0
       5: aload_1
       6: aload_2
       7: aload_3
       8: aload         4
      10: aload         5
      12: aload         6
      14: aload         7
      16: aload         8
      18: invokespecial #3                  // Method org/graylog2/contentpacks/model/entities/AutoValue_LookupTableEntity."<init>":(Lorg/graylog2/contentpacks/model/entities/references/ValueReference;Lorg/graylog2/contentpacks/model/entities/references/ValueReference;Lorg/graylog2/contentpacks/model/entities/references/ValueReference;Lorg/graylog2/contentpacks/model/entities/references/ValueReference;Lorg/graylog2/contentpacks/model/entities/references/ValueReference;Lorg/graylog2/contentpacks/model/entities/references/ValueReference;Lorg/graylog2/contentpacks/model/entities/references/ValueReference;Lorg/graylog2/contentpacks/model/entities/references/ValueReference;Lorg/graylog2/contentpacks/model/entities/references/ValueReference;)V
      21: areturn
}
