Compiled from "LookupDataAdapterEntity.java"
public abstract class org.graylog2.contentpacks.model.entities.LookupDataAdapterEntity {
  public org.graylog2.contentpacks.model.entities.LookupDataAdapterEntity();
    Code:
       0: aload_0
       1: invokespecial #1                  // Method java/lang/Object."<init>":()V
       4: return

  public abstract org.graylog2.contentpacks.model.entities.references.ValueReference name();

  public abstract org.graylog2.contentpacks.model.entities.references.ValueReference title();

  public abstract org.graylog2.contentpacks.model.entities.references.ValueReference description();

  public abstract org.graylog2.contentpacks.model.entities.references.ReferenceMap configuration();

  public static org.graylog2.contentpacks.model.entities.LookupDataAdapterEntity create(org.graylog2.contentpacks.model.entities.references.ValueReference, org.graylog2.contentpacks.model.entities.references.ValueReference, org.graylog2.contentpacks.model.entities.references.ValueReference, org.graylog2.contentpacks.model.entities.references.ReferenceMap);
    Code:
       0: new           #2                  // class org/graylog2/contentpacks/model/entities/AutoValue_LookupDataAdapterEntity
       3: dup
       4: aload_0
       5: aload_1
       6: aload_2
       7: aload_3
       8: invokespecial #3                  // Method org/graylog2/contentpacks/model/entities/AutoValue_LookupDataAdapterEntity."<init>":(Lorg/graylog2/contentpacks/model/entities/references/ValueReference;Lorg/graylog2/contentpacks/model/entities/references/ValueReference;Lorg/graylog2/contentpacks/model/entities/references/ValueReference;Lorg/graylog2/contentpacks/model/entities/references/ReferenceMap;)V
      11: areturn
}
