Compiled from "NativeEntityDescriptor.java"
public abstract class org.graylog2.contentpacks.model.entities.NativeEntityDescriptor implements org.graylog2.contentpacks.model.Identified,org.graylog2.contentpacks.model.Typed {
  public static final java.lang.String FIELD_ENTITY_ID;

  public static final java.lang.String FIELD_ENTITY_TITLE;

  public org.graylog2.contentpacks.model.entities.NativeEntityDescriptor();
    Code:
       0: aload_0
       1: invokespecial #1                  // Method java/lang/Object."<init>":()V
       4: return

  public abstract org.graylog2.contentpacks.model.ModelId contentPackEntityId();

  public abstract java.lang.String title();

  public static org.graylog2.contentpacks.model.entities.NativeEntityDescriptor create(org.graylog2.contentpacks.model.ModelId, org.graylog2.contentpacks.model.ModelId, org.graylog2.contentpacks.model.ModelType, java.lang.String);
    Code:
       0: invokestatic  #2                  // Method builder:()Lorg/graylog2/contentpacks/model/entities/NativeEntityDescriptor$Builder;
       3: aload_0
       4: invokevirtual #3                  // Method org/graylog2/contentpacks/model/entities/NativeEntityDescriptor$Builder.contentPackEntityId:(Lorg/graylog2/contentpacks/model/ModelId;)Lorg/graylog2/contentpacks/model/entities/NativeEntityDescriptor$Builder;
       7: aload_1
       8: invokevirtual #4                  // Method org/graylog2/contentpacks/model/entities/NativeEntityDescriptor$Builder.id:(Lorg/graylog2/contentpacks/model/ModelId;)Ljava/lang/Object;
      11: checkcast     #5                  // class org/graylog2/contentpacks/model/entities/NativeEntityDescriptor$Builder
      14: aload_3
      15: invokevirtual #6                  // Method org/graylog2/contentpacks/model/entities/NativeEntityDescriptor$Builder.title:(Ljava/lang/String;)Lorg/graylog2/contentpacks/model/entities/NativeEntityDescriptor$Builder;
      18: aload_2
      19: invokevirtual #7                  // Method org/graylog2/contentpacks/model/entities/NativeEntityDescriptor$Builder.type:(Lorg/graylog2/contentpacks/model/ModelType;)Ljava/lang/Object;
      22: checkcast     #5                  // class org/graylog2/contentpacks/model/entities/NativeEntityDescriptor$Builder
      25: invokevirtual #8                  // Method org/graylog2/contentpacks/model/entities/NativeEntityDescriptor$Builder.build:()Lorg/graylog2/contentpacks/model/entities/NativeEntityDescriptor;
      28: areturn

  public static org.graylog2.contentpacks.model.entities.NativeEntityDescriptor create(java.lang.String, java.lang.String, org.graylog2.contentpacks.model.ModelType, java.lang.String);
    Code:
       0: aload_0
       1: invokestatic  #9                  // Method org/graylog2/contentpacks/model/ModelId.of:(Ljava/lang/String;)Lorg/graylog2/contentpacks/model/ModelId;
       4: aload_1
       5: invokestatic  #9                  // Method org/graylog2/contentpacks/model/ModelId.of:(Ljava/lang/String;)Lorg/graylog2/contentpacks/model/ModelId;
       8: aload_2
       9: aload_3
      10: invokestatic  #10                 // Method create:(Lorg/graylog2/contentpacks/model/ModelId;Lorg/graylog2/contentpacks/model/ModelId;Lorg/graylog2/contentpacks/model/ModelType;Ljava/lang/String;)Lorg/graylog2/contentpacks/model/entities/NativeEntityDescriptor;
      13: areturn

  public static org.graylog2.contentpacks.model.entities.NativeEntityDescriptor create(org.graylog2.contentpacks.model.ModelId, java.lang.String, org.graylog2.contentpacks.model.ModelType, java.lang.String);
    Code:
       0: aload_0
       1: aload_1
       2: invokestatic  #9                  // Method org/graylog2/contentpacks/model/ModelId.of:(Ljava/lang/String;)Lorg/graylog2/contentpacks/model/ModelId;
       5: aload_2
       6: aload_3
       7: invokestatic  #10                 // Method create:(Lorg/graylog2/contentpacks/model/ModelId;Lorg/graylog2/contentpacks/model/ModelId;Lorg/graylog2/contentpacks/model/ModelType;Ljava/lang/String;)Lorg/graylog2/contentpacks/model/entities/NativeEntityDescriptor;
      10: areturn

  public static org.graylog2.contentpacks.model.entities.NativeEntityDescriptor$Builder builder();
    Code:
       0: new           #11                 // class org/graylog2/contentpacks/model/entities/AutoValue_NativeEntityDescriptor$Builder
       3: dup
       4: invokespecial #12                 // Method org/graylog2/contentpacks/model/entities/AutoValue_NativeEntityDescriptor$Builder."<init>":()V
       7: areturn
}
