Compiled from "DeliveryOptions.java"
final class software.amazon.awssdk.services.sesv2.model.DeliveryOptions$BuilderImpl implements software.amazon.awssdk.services.sesv2.model.DeliveryOptions$Builder {
  private java.lang.String tlsPolicy;

  private java.lang.String sendingPoolName;

  private software.amazon.awssdk.services.sesv2.model.DeliveryOptions$BuilderImpl();
    Code:
       0: aload_0
       1: invokespecial #5                  // Method java/lang/Object."<init>":()V
       4: return

  private software.amazon.awssdk.services.sesv2.model.DeliveryOptions$BuilderImpl(software.amazon.awssdk.services.sesv2.model.DeliveryOptions);
    Code:
       0: aload_0
       1: invokespecial #5                  // Method java/lang/Object."<init>":()V
       4: aload_0
       5: aload_1
       6: invokestatic  #6                  // Method software/amazon/awssdk/services/sesv2/model/DeliveryOptions.access$400:(Lsoftware/amazon/awssdk/services/sesv2/model/DeliveryOptions;)Ljava/lang/String;
       9: invokevirtual #7                  // Method tlsPolicy:(Ljava/lang/String;)Lsoftware/amazon/awssdk/services/sesv2/model/DeliveryOptions$Builder;
      12: pop
      13: aload_0
      14: aload_1
      15: invokestatic  #8                  // Method software/amazon/awssdk/services/sesv2/model/DeliveryOptions.access$500:(Lsoftware/amazon/awssdk/services/sesv2/model/DeliveryOptions;)Ljava/lang/String;
      18: invokevirtual #9                  // Method sendingPoolName:(Ljava/lang/String;)Lsoftware/amazon/awssdk/services/sesv2/model/DeliveryOptions$Builder;
      21: pop
      22: return

  public final java.lang.String getTlsPolicy();
    Code:
       0: aload_0
       1: getfield      #4                  // Field tlsPolicy:Ljava/lang/String;
       4: areturn

  public final void setTlsPolicy(java.lang.String);
    Code:
       0: aload_0
       1: aload_1
       2: putfield      #4                  // Field tlsPolicy:Ljava/lang/String;
       5: return

  public final software.amazon.awssdk.services.sesv2.model.DeliveryOptions$Builder tlsPolicy(java.lang.String);
    Code:
       0: aload_0
       1: aload_1
       2: putfield      #4                  // Field tlsPolicy:Ljava/lang/String;
       5: aload_0
       6: areturn

  public final software.amazon.awssdk.services.sesv2.model.DeliveryOptions$Builder tlsPolicy(software.amazon.awssdk.services.sesv2.model.TlsPolicy);
    Code:
       0: aload_0
       1: aload_1
       2: ifnonnull     9
       5: aconst_null
       6: goto          13
       9: aload_1
      10: invokevirtual #10                 // Method software/amazon/awssdk/services/sesv2/model/TlsPolicy.toString:()Ljava/lang/String;
      13: invokevirtual #7                  // Method tlsPolicy:(Ljava/lang/String;)Lsoftware/amazon/awssdk/services/sesv2/model/DeliveryOptions$Builder;
      16: pop
      17: aload_0
      18: areturn

  public final java.lang.String getSendingPoolName();
    Code:
       0: aload_0
       1: getfield      #3                  // Field sendingPoolName:Ljava/lang/String;
       4: areturn

  public final void setSendingPoolName(java.lang.String);
    Code:
       0: aload_0
       1: aload_1
       2: putfield      #3                  // Field sendingPoolName:Ljava/lang/String;
       5: return

  public final software.amazon.awssdk.services.sesv2.model.DeliveryOptions$Builder sendingPoolName(java.lang.String);
    Code:
       0: aload_0
       1: aload_1
       2: putfield      #3                  // Field sendingPoolName:Ljava/lang/String;
       5: aload_0
       6: areturn

  public software.amazon.awssdk.services.sesv2.model.DeliveryOptions build();
    Code:
       0: new           #11                 // class software/amazon/awssdk/services/sesv2/model/DeliveryOptions
       3: dup
       4: aload_0
       5: aconst_null
       6: invokespecial #12                 // Method software/amazon/awssdk/services/sesv2/model/DeliveryOptions."<init>":(Lsoftware/amazon/awssdk/services/sesv2/model/DeliveryOptions$BuilderImpl;Lsoftware/amazon/awssdk/services/sesv2/model/DeliveryOptions$1;)V
       9: areturn

  public java.util.List<software.amazon.awssdk.core.SdkField<?>> sdkFields();
    Code:
       0: invokestatic  #13                 // Method software/amazon/awssdk/services/sesv2/model/DeliveryOptions.access$700:()Ljava/util/List;
       3: areturn

  public java.lang.Object build();
    Code:
       0: aload_0
       1: invokevirtual #14                 // Method build:()Lsoftware/amazon/awssdk/services/sesv2/model/DeliveryOptions;
       4: areturn

  static java.lang.String access$000(software.amazon.awssdk.services.sesv2.model.DeliveryOptions$BuilderImpl);
    Code:
       0: aload_0
       1: getfield      #4                  // Field tlsPolicy:Ljava/lang/String;
       4: areturn

  static java.lang.String access$100(software.amazon.awssdk.services.sesv2.model.DeliveryOptions$BuilderImpl);
    Code:
       0: aload_0
       1: getfield      #3                  // Field sendingPoolName:Ljava/lang/String;
       4: areturn

  software.amazon.awssdk.services.sesv2.model.DeliveryOptions$BuilderImpl(software.amazon.awssdk.services.sesv2.model.DeliveryOptions, software.amazon.awssdk.services.sesv2.model.DeliveryOptions$1);
    Code:
       0: aload_0
       1: aload_1
       2: invokespecial #2                  // Method "<init>":(Lsoftware/amazon/awssdk/services/sesv2/model/DeliveryOptions;)V
       5: return

  software.amazon.awssdk.services.sesv2.model.DeliveryOptions$BuilderImpl(software.amazon.awssdk.services.sesv2.model.DeliveryOptions$1);
    Code:
       0: aload_0
       1: invokespecial #1                  // Method "<init>":()V
       4: return
}
