Compiled from "DomainDeliverabilityCampaign.java"
final class software.amazon.awssdk.services.sesv2.model.DomainDeliverabilityCampaign$BuilderImpl implements software.amazon.awssdk.services.sesv2.model.DomainDeliverabilityCampaign$Builder {
  private java.lang.String campaignId;

  private java.lang.String imageUrl;

  private java.lang.String subject;

  private java.lang.String fromAddress;

  private java.util.List<java.lang.String> sendingIps;

  private java.time.Instant firstSeenDateTime;

  private java.time.Instant lastSeenDateTime;

  private java.lang.Long inboxCount;

  private java.lang.Long spamCount;

  private java.lang.Double readRate;

  private java.lang.Double deleteRate;

  private java.lang.Double readDeleteRate;

  private java.lang.Long projectedVolume;

  private java.util.List<java.lang.String> esps;

  private software.amazon.awssdk.services.sesv2.model.DomainDeliverabilityCampaign$BuilderImpl();
    Code:
       0: aload_0
       1: invokespecial #17                 // Method java/lang/Object."<init>":()V
       4: aload_0
       5: invokestatic  #18                 // Method software/amazon/awssdk/core/util/DefaultSdkAutoConstructList.getInstance:()Lsoftware/amazon/awssdk/core/util/DefaultSdkAutoConstructList;
       8: putfield      #12                 // Field sendingIps:Ljava/util/List;
      11: aload_0
      12: invokestatic  #18                 // Method software/amazon/awssdk/core/util/DefaultSdkAutoConstructList.getInstance:()Lsoftware/amazon/awssdk/core/util/DefaultSdkAutoConstructList;
      15: putfield      #3                  // Field esps:Ljava/util/List;
      18: return

  private software.amazon.awssdk.services.sesv2.model.DomainDeliverabilityCampaign$BuilderImpl(software.amazon.awssdk.services.sesv2.model.DomainDeliverabilityCampaign);
    Code:
       0: aload_0
       1: invokespecial #17                 // Method java/lang/Object."<init>":()V
       4: aload_0
       5: invokestatic  #18                 // Method software/amazon/awssdk/core/util/DefaultSdkAutoConstructList.getInstance:()Lsoftware/amazon/awssdk/core/util/DefaultSdkAutoConstructList;
       8: putfield      #12                 // Field sendingIps:Ljava/util/List;
      11: aload_0
      12: invokestatic  #18                 // Method software/amazon/awssdk/core/util/DefaultSdkAutoConstructList.getInstance:()Lsoftware/amazon/awssdk/core/util/DefaultSdkAutoConstructList;
      15: putfield      #3                  // Field esps:Ljava/util/List;
      18: aload_0
      19: aload_1
      20: invokestatic  #19                 // Method software/amazon/awssdk/services/sesv2/model/DomainDeliverabilityCampaign.access$1600:(Lsoftware/amazon/awssdk/services/sesv2/model/DomainDeliverabilityCampaign;)Ljava/lang/String;
      23: invokevirtual #20                 // Method campaignId:(Ljava/lang/String;)Lsoftware/amazon/awssdk/services/sesv2/model/DomainDeliverabilityCampaign$Builder;
      26: pop
      27: aload_0
      28: aload_1
      29: invokestatic  #21                 // Method software/amazon/awssdk/services/sesv2/model/DomainDeliverabilityCampaign.access$1700:(Lsoftware/amazon/awssdk/services/sesv2/model/DomainDeliverabilityCampaign;)Ljava/lang/String;
      32: invokevirtual #22                 // Method imageUrl:(Ljava/lang/String;)Lsoftware/amazon/awssdk/services/sesv2/model/DomainDeliverabilityCampaign$Builder;
      35: pop
      36: aload_0
      37: aload_1
      38: invokestatic  #23                 // Method software/amazon/awssdk/services/sesv2/model/DomainDeliverabilityCampaign.access$1800:(Lsoftware/amazon/awssdk/services/sesv2/model/DomainDeliverabilityCampaign;)Ljava/lang/String;
      41: invokevirtual #24                 // Method subject:(Ljava/lang/String;)Lsoftware/amazon/awssdk/services/sesv2/model/DomainDeliverabilityCampaign$Builder;
      44: pop
      45: aload_0
      46: aload_1
      47: invokestatic  #25                 // Method software/amazon/awssdk/services/sesv2/model/DomainDeliverabilityCampaign.access$1900:(Lsoftware/amazon/awssdk/services/sesv2/model/DomainDeliverabilityCampaign;)Ljava/lang/String;
      50: invokevirtual #26                 // Method fromAddress:(Ljava/lang/String;)Lsoftware/amazon/awssdk/services/sesv2/model/DomainDeliverabilityCampaign$Builder;
      53: pop
      54: aload_0
      55: aload_1
      56: invokestatic  #27                 // Method software/amazon/awssdk/services/sesv2/model/DomainDeliverabilityCampaign.access$2000:(Lsoftware/amazon/awssdk/services/sesv2/model/DomainDeliverabilityCampaign;)Ljava/util/List;
      59: invokevirtual #28                 // Method sendingIps:(Ljava/util/Collection;)Lsoftware/amazon/awssdk/services/sesv2/model/DomainDeliverabilityCampaign$Builder;
      62: pop
      63: aload_0
      64: aload_1
      65: invokestatic  #29                 // Method software/amazon/awssdk/services/sesv2/model/DomainDeliverabilityCampaign.access$2100:(Lsoftware/amazon/awssdk/services/sesv2/model/DomainDeliverabilityCampaign;)Ljava/time/Instant;
      68: invokevirtual #30                 // Method firstSeenDateTime:(Ljava/time/Instant;)Lsoftware/amazon/awssdk/services/sesv2/model/DomainDeliverabilityCampaign$Builder;
      71: pop
      72: aload_0
      73: aload_1
      74: invokestatic  #31                 // Method software/amazon/awssdk/services/sesv2/model/DomainDeliverabilityCampaign.access$2200:(Lsoftware/amazon/awssdk/services/sesv2/model/DomainDeliverabilityCampaign;)Ljava/time/Instant;
      77: invokevirtual #32                 // Method lastSeenDateTime:(Ljava/time/Instant;)Lsoftware/amazon/awssdk/services/sesv2/model/DomainDeliverabilityCampaign$Builder;
      80: pop
      81: aload_0
      82: aload_1
      83: invokestatic  #33                 // Method software/amazon/awssdk/services/sesv2/model/DomainDeliverabilityCampaign.access$2300:(Lsoftware/amazon/awssdk/services/sesv2/model/DomainDeliverabilityCampaign;)Ljava/lang/Long;
      86: invokevirtual #34                 // Method inboxCount:(Ljava/lang/Long;)Lsoftware/amazon/awssdk/services/sesv2/model/DomainDeliverabilityCampaign$Builder;
      89: pop
      90: aload_0
      91: aload_1
      92: invokestatic  #35                 // Method software/amazon/awssdk/services/sesv2/model/DomainDeliverabilityCampaign.access$2400:(Lsoftware/amazon/awssdk/services/sesv2/model/DomainDeliverabilityCampaign;)Ljava/lang/Long;
      95: invokevirtual #36                 // Method spamCount:(Ljava/lang/Long;)Lsoftware/amazon/awssdk/services/sesv2/model/DomainDeliverabilityCampaign$Builder;
      98: pop
      99: aload_0
     100: aload_1
     101: invokestatic  #37                 // Method software/amazon/awssdk/services/sesv2/model/DomainDeliverabilityCampaign.access$2500:(Lsoftware/amazon/awssdk/services/sesv2/model/DomainDeliverabilityCampaign;)Ljava/lang/Double;
     104: invokevirtual #38                 // Method readRate:(Ljava/lang/Double;)Lsoftware/amazon/awssdk/services/sesv2/model/DomainDeliverabilityCampaign$Builder;
     107: pop
     108: aload_0
     109: aload_1
     110: invokestatic  #39                 // Method software/amazon/awssdk/services/sesv2/model/DomainDeliverabilityCampaign.access$2600:(Lsoftware/amazon/awssdk/services/sesv2/model/DomainDeliverabilityCampaign;)Ljava/lang/Double;
     113: invokevirtual #40                 // Method deleteRate:(Ljava/lang/Double;)Lsoftware/amazon/awssdk/services/sesv2/model/DomainDeliverabilityCampaign$Builder;
     116: pop
     117: aload_0
     118: aload_1
     119: invokestatic  #41                 // Method software/amazon/awssdk/services/sesv2/model/DomainDeliverabilityCampaign.access$2700:(Lsoftware/amazon/awssdk/services/sesv2/model/DomainDeliverabilityCampaign;)Ljava/lang/Double;
     122: invokevirtual #42                 // Method readDeleteRate:(Ljava/lang/Double;)Lsoftware/amazon/awssdk/services/sesv2/model/DomainDeliverabilityCampaign$Builder;
     125: pop
     126: aload_0
     127: aload_1
     128: invokestatic  #43                 // Method software/amazon/awssdk/services/sesv2/model/DomainDeliverabilityCampaign.access$2800:(Lsoftware/amazon/awssdk/services/sesv2/model/DomainDeliverabilityCampaign;)Ljava/lang/Long;
     131: invokevirtual #44                 // Method projectedVolume:(Ljava/lang/Long;)Lsoftware/amazon/awssdk/services/sesv2/model/DomainDeliverabilityCampaign$Builder;
     134: pop
     135: aload_0
     136: aload_1
     137: invokestatic  #45                 // Method software/amazon/awssdk/services/sesv2/model/DomainDeliverabilityCampaign.access$2900:(Lsoftware/amazon/awssdk/services/sesv2/model/DomainDeliverabilityCampaign;)Ljava/util/List;
     140: invokevirtual #46                 // Method esps:(Ljava/util/Collection;)Lsoftware/amazon/awssdk/services/sesv2/model/DomainDeliverabilityCampaign$Builder;
     143: pop
     144: return

  public final java.lang.String getCampaignId();
    Code:
       0: aload_0
       1: getfield      #16                 // Field campaignId:Ljava/lang/String;
       4: areturn

  public final void setCampaignId(java.lang.String);
    Code:
       0: aload_0
       1: aload_1
       2: putfield      #16                 // Field campaignId:Ljava/lang/String;
       5: return

  public final software.amazon.awssdk.services.sesv2.model.DomainDeliverabilityCampaign$Builder campaignId(java.lang.String);
    Code:
       0: aload_0
       1: aload_1
       2: putfield      #16                 // Field campaignId:Ljava/lang/String;
       5: aload_0
       6: areturn

  public final java.lang.String getImageUrl();
    Code:
       0: aload_0
       1: getfield      #15                 // Field imageUrl:Ljava/lang/String;
       4: areturn

  public final void setImageUrl(java.lang.String);
    Code:
       0: aload_0
       1: aload_1
       2: putfield      #15                 // Field imageUrl:Ljava/lang/String;
       5: return

  public final software.amazon.awssdk.services.sesv2.model.DomainDeliverabilityCampaign$Builder imageUrl(java.lang.String);
    Code:
       0: aload_0
       1: aload_1
       2: putfield      #15                 // Field imageUrl:Ljava/lang/String;
       5: aload_0
       6: areturn

  public final java.lang.String getSubject();
    Code:
       0: aload_0
       1: getfield      #14                 // Field subject:Ljava/lang/String;
       4: areturn

  public final void setSubject(java.lang.String);
    Code:
       0: aload_0
       1: aload_1
       2: putfield      #14                 // Field subject:Ljava/lang/String;
       5: return

  public final software.amazon.awssdk.services.sesv2.model.DomainDeliverabilityCampaign$Builder subject(java.lang.String);
    Code:
       0: aload_0
       1: aload_1
       2: putfield      #14                 // Field subject:Ljava/lang/String;
       5: aload_0
       6: areturn

  public final java.lang.String getFromAddress();
    Code:
       0: aload_0
       1: getfield      #13                 // Field fromAddress:Ljava/lang/String;
       4: areturn

  public final void setFromAddress(java.lang.String);
    Code:
       0: aload_0
       1: aload_1
       2: putfield      #13                 // Field fromAddress:Ljava/lang/String;
       5: return

  public final software.amazon.awssdk.services.sesv2.model.DomainDeliverabilityCampaign$Builder fromAddress(java.lang.String);
    Code:
       0: aload_0
       1: aload_1
       2: putfield      #13                 // Field fromAddress:Ljava/lang/String;
       5: aload_0
       6: areturn

  public final java.util.Collection<java.lang.String> getSendingIps();
    Code:
       0: aload_0
       1: getfield      #12                 // Field sendingIps:Ljava/util/List;
       4: instanceof    #47                 // class software/amazon/awssdk/core/util/SdkAutoConstructList
       7: ifeq          12
      10: aconst_null
      11: areturn
      12: aload_0
      13: getfield      #12                 // Field sendingIps:Ljava/util/List;
      16: areturn

  public final void setSendingIps(java.util.Collection<java.lang.String>);
    Code:
       0: aload_0
       1: aload_1
       2: invokestatic  #48                 // Method software/amazon/awssdk/services/sesv2/model/IpListCopier.copy:(Ljava/util/Collection;)Ljava/util/List;
       5: putfield      #12                 // Field sendingIps:Ljava/util/List;
       8: return

  public final software.amazon.awssdk.services.sesv2.model.DomainDeliverabilityCampaign$Builder sendingIps(java.util.Collection<java.lang.String>);
    Code:
       0: aload_0
       1: aload_1
       2: invokestatic  #48                 // Method software/amazon/awssdk/services/sesv2/model/IpListCopier.copy:(Ljava/util/Collection;)Ljava/util/List;
       5: putfield      #12                 // Field sendingIps:Ljava/util/List;
       8: aload_0
       9: areturn

  public final software.amazon.awssdk.services.sesv2.model.DomainDeliverabilityCampaign$Builder sendingIps(java.lang.String...);
    Code:
       0: aload_0
       1: aload_1
       2: invokestatic  #49                 // Method java/util/Arrays.asList:([Ljava/lang/Object;)Ljava/util/List;
       5: invokevirtual #28                 // Method sendingIps:(Ljava/util/Collection;)Lsoftware/amazon/awssdk/services/sesv2/model/DomainDeliverabilityCampaign$Builder;
       8: pop
       9: aload_0
      10: areturn

  public final java.time.Instant getFirstSeenDateTime();
    Code:
       0: aload_0
       1: getfield      #11                 // Field firstSeenDateTime:Ljava/time/Instant;
       4: areturn

  public final void setFirstSeenDateTime(java.time.Instant);
    Code:
       0: aload_0
       1: aload_1
       2: putfield      #11                 // Field firstSeenDateTime:Ljava/time/Instant;
       5: return

  public final software.amazon.awssdk.services.sesv2.model.DomainDeliverabilityCampaign$Builder firstSeenDateTime(java.time.Instant);
    Code:
       0: aload_0
       1: aload_1
       2: putfield      #11                 // Field firstSeenDateTime:Ljava/time/Instant;
       5: aload_0
       6: areturn

  public final java.time.Instant getLastSeenDateTime();
    Code:
       0: aload_0
       1: getfield      #10                 // Field lastSeenDateTime:Ljava/time/Instant;
       4: areturn

  public final void setLastSeenDateTime(java.time.Instant);
    Code:
       0: aload_0
       1: aload_1
       2: putfield      #10                 // Field lastSeenDateTime:Ljava/time/Instant;
       5: return

  public final software.amazon.awssdk.services.sesv2.model.DomainDeliverabilityCampaign$Builder lastSeenDateTime(java.time.Instant);
    Code:
       0: aload_0
       1: aload_1
       2: putfield      #10                 // Field lastSeenDateTime:Ljava/time/Instant;
       5: aload_0
       6: areturn

  public final java.lang.Long getInboxCount();
    Code:
       0: aload_0
       1: getfield      #9                  // Field inboxCount:Ljava/lang/Long;
       4: areturn

  public final void setInboxCount(java.lang.Long);
    Code:
       0: aload_0
       1: aload_1
       2: putfield      #9                  // Field inboxCount:Ljava/lang/Long;
       5: return

  public final software.amazon.awssdk.services.sesv2.model.DomainDeliverabilityCampaign$Builder inboxCount(java.lang.Long);
    Code:
       0: aload_0
       1: aload_1
       2: putfield      #9                  // Field inboxCount:Ljava/lang/Long;
       5: aload_0
       6: areturn

  public final java.lang.Long getSpamCount();
    Code:
       0: aload_0
       1: getfield      #8                  // Field spamCount:Ljava/lang/Long;
       4: areturn

  public final void setSpamCount(java.lang.Long);
    Code:
       0: aload_0
       1: aload_1
       2: putfield      #8                  // Field spamCount:Ljava/lang/Long;
       5: return

  public final software.amazon.awssdk.services.sesv2.model.DomainDeliverabilityCampaign$Builder spamCount(java.lang.Long);
    Code:
       0: aload_0
       1: aload_1
       2: putfield      #8                  // Field spamCount:Ljava/lang/Long;
       5: aload_0
       6: areturn

  public final java.lang.Double getReadRate();
    Code:
       0: aload_0
       1: getfield      #7                  // Field readRate:Ljava/lang/Double;
       4: areturn

  public final void setReadRate(java.lang.Double);
    Code:
       0: aload_0
       1: aload_1
       2: putfield      #7                  // Field readRate:Ljava/lang/Double;
       5: return

  public final software.amazon.awssdk.services.sesv2.model.DomainDeliverabilityCampaign$Builder readRate(java.lang.Double);
    Code:
       0: aload_0
       1: aload_1
       2: putfield      #7                  // Field readRate:Ljava/lang/Double;
       5: aload_0
       6: areturn

  public final java.lang.Double getDeleteRate();
    Code:
       0: aload_0
       1: getfield      #6                  // Field deleteRate:Ljava/lang/Double;
       4: areturn

  public final void setDeleteRate(java.lang.Double);
    Code:
       0: aload_0
       1: aload_1
       2: putfield      #6                  // Field deleteRate:Ljava/lang/Double;
       5: return

  public final software.amazon.awssdk.services.sesv2.model.DomainDeliverabilityCampaign$Builder deleteRate(java.lang.Double);
    Code:
       0: aload_0
       1: aload_1
       2: putfield      #6                  // Field deleteRate:Ljava/lang/Double;
       5: aload_0
       6: areturn

  public final java.lang.Double getReadDeleteRate();
    Code:
       0: aload_0
       1: getfield      #5                  // Field readDeleteRate:Ljava/lang/Double;
       4: areturn

  public final void setReadDeleteRate(java.lang.Double);
    Code:
       0: aload_0
       1: aload_1
       2: putfield      #5                  // Field readDeleteRate:Ljava/lang/Double;
       5: return

  public final software.amazon.awssdk.services.sesv2.model.DomainDeliverabilityCampaign$Builder readDeleteRate(java.lang.Double);
    Code:
       0: aload_0
       1: aload_1
       2: putfield      #5                  // Field readDeleteRate:Ljava/lang/Double;
       5: aload_0
       6: areturn

  public final java.lang.Long getProjectedVolume();
    Code:
       0: aload_0
       1: getfield      #4                  // Field projectedVolume:Ljava/lang/Long;
       4: areturn

  public final void setProjectedVolume(java.lang.Long);
    Code:
       0: aload_0
       1: aload_1
       2: putfield      #4                  // Field projectedVolume:Ljava/lang/Long;
       5: return

  public final software.amazon.awssdk.services.sesv2.model.DomainDeliverabilityCampaign$Builder projectedVolume(java.lang.Long);
    Code:
       0: aload_0
       1: aload_1
       2: putfield      #4                  // Field projectedVolume:Ljava/lang/Long;
       5: aload_0
       6: areturn

  public final java.util.Collection<java.lang.String> getEsps();
    Code:
       0: aload_0
       1: getfield      #3                  // Field esps:Ljava/util/List;
       4: instanceof    #47                 // class software/amazon/awssdk/core/util/SdkAutoConstructList
       7: ifeq          12
      10: aconst_null
      11: areturn
      12: aload_0
      13: getfield      #3                  // Field esps:Ljava/util/List;
      16: areturn

  public final void setEsps(java.util.Collection<java.lang.String>);
    Code:
       0: aload_0
       1: aload_1
       2: invokestatic  #50                 // Method software/amazon/awssdk/services/sesv2/model/EspsCopier.copy:(Ljava/util/Collection;)Ljava/util/List;
       5: putfield      #3                  // Field esps:Ljava/util/List;
       8: return

  public final software.amazon.awssdk.services.sesv2.model.DomainDeliverabilityCampaign$Builder esps(java.util.Collection<java.lang.String>);
    Code:
       0: aload_0
       1: aload_1
       2: invokestatic  #50                 // Method software/amazon/awssdk/services/sesv2/model/EspsCopier.copy:(Ljava/util/Collection;)Ljava/util/List;
       5: putfield      #3                  // Field esps:Ljava/util/List;
       8: aload_0
       9: areturn

  public final software.amazon.awssdk.services.sesv2.model.DomainDeliverabilityCampaign$Builder esps(java.lang.String...);
    Code:
       0: aload_0
       1: aload_1
       2: invokestatic  #49                 // Method java/util/Arrays.asList:([Ljava/lang/Object;)Ljava/util/List;
       5: invokevirtual #46                 // Method esps:(Ljava/util/Collection;)Lsoftware/amazon/awssdk/services/sesv2/model/DomainDeliverabilityCampaign$Builder;
       8: pop
       9: aload_0
      10: areturn

  public software.amazon.awssdk.services.sesv2.model.DomainDeliverabilityCampaign build();
    Code:
       0: new           #51                 // class software/amazon/awssdk/services/sesv2/model/DomainDeliverabilityCampaign
       3: dup
       4: aload_0
       5: aconst_null
       6: invokespecial #52                 // Method software/amazon/awssdk/services/sesv2/model/DomainDeliverabilityCampaign."<init>":(Lsoftware/amazon/awssdk/services/sesv2/model/DomainDeliverabilityCampaign$BuilderImpl;Lsoftware/amazon/awssdk/services/sesv2/model/DomainDeliverabilityCampaign$1;)V
       9: areturn

  public java.util.List<software.amazon.awssdk.core.SdkField<?>> sdkFields();
    Code:
       0: invokestatic  #53                 // Method software/amazon/awssdk/services/sesv2/model/DomainDeliverabilityCampaign.access$3100:()Ljava/util/List;
       3: areturn

  public java.lang.Object build();
    Code:
       0: aload_0
       1: invokevirtual #54                 // Method build:()Lsoftware/amazon/awssdk/services/sesv2/model/DomainDeliverabilityCampaign;
       4: areturn

  static java.lang.String access$000(software.amazon.awssdk.services.sesv2.model.DomainDeliverabilityCampaign$BuilderImpl);
    Code:
       0: aload_0
       1: getfield      #16                 // Field campaignId:Ljava/lang/String;
       4: areturn

  static java.lang.String access$100(software.amazon.awssdk.services.sesv2.model.DomainDeliverabilityCampaign$BuilderImpl);
    Code:
       0: aload_0
       1: getfield      #15                 // Field imageUrl:Ljava/lang/String;
       4: areturn

  static java.lang.String access$200(software.amazon.awssdk.services.sesv2.model.DomainDeliverabilityCampaign$BuilderImpl);
    Code:
       0: aload_0
       1: getfield      #14                 // Field subject:Ljava/lang/String;
       4: areturn

  static java.lang.String access$300(software.amazon.awssdk.services.sesv2.model.DomainDeliverabilityCampaign$BuilderImpl);
    Code:
       0: aload_0
       1: getfield      #13                 // Field fromAddress:Ljava/lang/String;
       4: areturn

  static java.util.List access$400(software.amazon.awssdk.services.sesv2.model.DomainDeliverabilityCampaign$BuilderImpl);
    Code:
       0: aload_0
       1: getfield      #12                 // Field sendingIps:Ljava/util/List;
       4: areturn

  static java.time.Instant access$500(software.amazon.awssdk.services.sesv2.model.DomainDeliverabilityCampaign$BuilderImpl);
    Code:
       0: aload_0
       1: getfield      #11                 // Field firstSeenDateTime:Ljava/time/Instant;
       4: areturn

  static java.time.Instant access$600(software.amazon.awssdk.services.sesv2.model.DomainDeliverabilityCampaign$BuilderImpl);
    Code:
       0: aload_0
       1: getfield      #10                 // Field lastSeenDateTime:Ljava/time/Instant;
       4: areturn

  static java.lang.Long access$700(software.amazon.awssdk.services.sesv2.model.DomainDeliverabilityCampaign$BuilderImpl);
    Code:
       0: aload_0
       1: getfield      #9                  // Field inboxCount:Ljava/lang/Long;
       4: areturn

  static java.lang.Long access$800(software.amazon.awssdk.services.sesv2.model.DomainDeliverabilityCampaign$BuilderImpl);
    Code:
       0: aload_0
       1: getfield      #8                  // Field spamCount:Ljava/lang/Long;
       4: areturn

  static java.lang.Double access$900(software.amazon.awssdk.services.sesv2.model.DomainDeliverabilityCampaign$BuilderImpl);
    Code:
       0: aload_0
       1: getfield      #7                  // Field readRate:Ljava/lang/Double;
       4: areturn

  static java.lang.Double access$1000(software.amazon.awssdk.services.sesv2.model.DomainDeliverabilityCampaign$BuilderImpl);
    Code:
       0: aload_0
       1: getfield      #6                  // Field deleteRate:Ljava/lang/Double;
       4: areturn

  static java.lang.Double access$1100(software.amazon.awssdk.services.sesv2.model.DomainDeliverabilityCampaign$BuilderImpl);
    Code:
       0: aload_0
       1: getfield      #5                  // Field readDeleteRate:Ljava/lang/Double;
       4: areturn

  static java.lang.Long access$1200(software.amazon.awssdk.services.sesv2.model.DomainDeliverabilityCampaign$BuilderImpl);
    Code:
       0: aload_0
       1: getfield      #4                  // Field projectedVolume:Ljava/lang/Long;
       4: areturn

  static java.util.List access$1300(software.amazon.awssdk.services.sesv2.model.DomainDeliverabilityCampaign$BuilderImpl);
    Code:
       0: aload_0
       1: getfield      #3                  // Field esps:Ljava/util/List;
       4: areturn

  software.amazon.awssdk.services.sesv2.model.DomainDeliverabilityCampaign$BuilderImpl(software.amazon.awssdk.services.sesv2.model.DomainDeliverabilityCampaign, software.amazon.awssdk.services.sesv2.model.DomainDeliverabilityCampaign$1);
    Code:
       0: aload_0
       1: aload_1
       2: invokespecial #2                  // Method "<init>":(Lsoftware/amazon/awssdk/services/sesv2/model/DomainDeliverabilityCampaign;)V
       5: return

  software.amazon.awssdk.services.sesv2.model.DomainDeliverabilityCampaign$BuilderImpl(software.amazon.awssdk.services.sesv2.model.DomainDeliverabilityCampaign$1);
    Code:
       0: aload_0
       1: invokespecial #1                  // Method "<init>":()V
       4: return
}
