Compiled from "ImportDestination.java"
public interface software.amazon.awssdk.services.sesv2.model.ImportDestination$Builder extends software.amazon.awssdk.core.SdkPojo, software.amazon.awssdk.utils.builder.CopyableBuilder<software.amazon.awssdk.services.sesv2.model.ImportDestination$Builder, software.amazon.awssdk.services.sesv2.model.ImportDestination> {
  public abstract software.amazon.awssdk.services.sesv2.model.ImportDestination$Builder suppressionListDestination(software.amazon.awssdk.services.sesv2.model.SuppressionListDestination);

  public default software.amazon.awssdk.services.sesv2.model.ImportDestination$Builder suppressionListDestination(java.util.function.Consumer<software.amazon.awssdk.services.sesv2.model.SuppressionListDestination$Builder>);
    Code:
       0: aload_0
       1: invokestatic  #1                  // Method software/amazon/awssdk/services/sesv2/model/SuppressionListDestination.builder:()Lsoftware/amazon/awssdk/services/sesv2/model/SuppressionListDestination$Builder;
       4: aload_1
       5: invokeinterface #2,  2            // InterfaceMethod software/amazon/awssdk/services/sesv2/model/SuppressionListDestination$Builder.applyMutation:(Ljava/util/function/Consumer;)Lsoftware/amazon/awssdk/utils/builder/SdkBuilder;
      10: checkcast     #3                  // class software/amazon/awssdk/services/sesv2/model/SuppressionListDestination$Builder
      13: invokeinterface #4,  1            // InterfaceMethod software/amazon/awssdk/services/sesv2/model/SuppressionListDestination$Builder.build:()Ljava/lang/Object;
      18: checkcast     #5                  // class software/amazon/awssdk/services/sesv2/model/SuppressionListDestination
      21: invokeinterface #6,  2            // InterfaceMethod suppressionListDestination:(Lsoftware/amazon/awssdk/services/sesv2/model/SuppressionListDestination;)Lsoftware/amazon/awssdk/services/sesv2/model/ImportDestination$Builder;
      26: areturn

  public abstract software.amazon.awssdk.services.sesv2.model.ImportDestination$Builder contactListDestination(software.amazon.awssdk.services.sesv2.model.ContactListDestination);

  public default software.amazon.awssdk.services.sesv2.model.ImportDestination$Builder contactListDestination(java.util.function.Consumer<software.amazon.awssdk.services.sesv2.model.ContactListDestination$Builder>);
    Code:
       0: aload_0
       1: invokestatic  #7                  // Method software/amazon/awssdk/services/sesv2/model/ContactListDestination.builder:()Lsoftware/amazon/awssdk/services/sesv2/model/ContactListDestination$Builder;
       4: aload_1
       5: invokeinterface #8,  2            // InterfaceMethod software/amazon/awssdk/services/sesv2/model/ContactListDestination$Builder.applyMutation:(Ljava/util/function/Consumer;)Lsoftware/amazon/awssdk/utils/builder/SdkBuilder;
      10: checkcast     #9                  // class software/amazon/awssdk/services/sesv2/model/ContactListDestination$Builder
      13: invokeinterface #10,  1           // InterfaceMethod software/amazon/awssdk/services/sesv2/model/ContactListDestination$Builder.build:()Ljava/lang/Object;
      18: checkcast     #11                 // class software/amazon/awssdk/services/sesv2/model/ContactListDestination
      21: invokeinterface #12,  2           // InterfaceMethod contactListDestination:(Lsoftware/amazon/awssdk/services/sesv2/model/ContactListDestination;)Lsoftware/amazon/awssdk/services/sesv2/model/ImportDestination$Builder;
      26: areturn
}
