Compiled from "CreatorProperty.java"
public class org.codehaus.jackson.map.deser.impl.CreatorProperty extends org.codehaus.jackson.map.deser.SettableBeanProperty {
  protected final org.codehaus.jackson.map.introspect.AnnotatedParameter _annotated;

  protected final java.lang.Object _injectableValueId;

  public org.codehaus.jackson.map.deser.impl.CreatorProperty(java.lang.String, org.codehaus.jackson.type.JavaType, org.codehaus.jackson.map.TypeDeserializer, org.codehaus.jackson.map.util.Annotations, org.codehaus.jackson.map.introspect.AnnotatedParameter, int, java.lang.Object);
    Code:
       0: aload_0
       1: aload_1
       2: aload_2
       3: aload_3
       4: aload         4
       6: invokespecial #1                  // Method org/codehaus/jackson/map/deser/SettableBeanProperty."<init>":(Ljava/lang/String;Lorg/codehaus/jackson/type/JavaType;Lorg/codehaus/jackson/map/TypeDeserializer;Lorg/codehaus/jackson/map/util/Annotations;)V
       9: aload_0
      10: aload         5
      12: putfield      #2                  // Field _annotated:Lorg/codehaus/jackson/map/introspect/AnnotatedParameter;
      15: aload_0
      16: iload         6
      18: putfield      #3                  // Field _propertyIndex:I
      21: aload_0
      22: aload         7
      24: putfield      #4                  // Field _injectableValueId:Ljava/lang/Object;
      27: return

  protected org.codehaus.jackson.map.deser.impl.CreatorProperty(org.codehaus.jackson.map.deser.impl.CreatorProperty, org.codehaus.jackson.map.JsonDeserializer<java.lang.Object>);
    Code:
       0: aload_0
       1: aload_1
       2: aload_2
       3: invokespecial #5                  // Method org/codehaus/jackson/map/deser/SettableBeanProperty."<init>":(Lorg/codehaus/jackson/map/deser/SettableBeanProperty;Lorg/codehaus/jackson/map/JsonDeserializer;)V
       6: aload_0
       7: aload_1
       8: getfield      #2                  // Field _annotated:Lorg/codehaus/jackson/map/introspect/AnnotatedParameter;
      11: putfield      #2                  // Field _annotated:Lorg/codehaus/jackson/map/introspect/AnnotatedParameter;
      14: aload_0
      15: aload_1
      16: getfield      #4                  // Field _injectableValueId:Ljava/lang/Object;
      19: putfield      #4                  // Field _injectableValueId:Ljava/lang/Object;
      22: return

  public org.codehaus.jackson.map.deser.impl.CreatorProperty withValueDeserializer(org.codehaus.jackson.map.JsonDeserializer<java.lang.Object>);
    Code:
       0: new           #6                  // class org/codehaus/jackson/map/deser/impl/CreatorProperty
       3: dup
       4: aload_0
       5: aload_1
       6: invokespecial #7                  // Method "<init>":(Lorg/codehaus/jackson/map/deser/impl/CreatorProperty;Lorg/codehaus/jackson/map/JsonDeserializer;)V
       9: areturn

  public java.lang.Object findInjectableValue(org.codehaus.jackson.map.DeserializationContext, java.lang.Object);
    Code:
       0: aload_0
       1: getfield      #4                  // Field _injectableValueId:Ljava/lang/Object;
       4: ifnonnull     57
       7: new           #8                  // class java/lang/IllegalStateException
      10: dup
      11: new           #9                  // class java/lang/StringBuilder
      14: dup
      15: invokespecial #10                 // Method java/lang/StringBuilder."<init>":()V
      18: ldc           #11                 // String Property \'
      20: invokevirtual #12                 // Method java/lang/StringBuilder.append:(Ljava/lang/String;)Ljava/lang/StringBuilder;
      23: aload_0
      24: invokevirtual #13                 // Method getName:()Ljava/lang/String;
      27: invokevirtual #12                 // Method java/lang/StringBuilder.append:(Ljava/lang/String;)Ljava/lang/StringBuilder;
      30: ldc           #14                 // String \' (type
      32: invokevirtual #12                 // Method java/lang/StringBuilder.append:(Ljava/lang/String;)Ljava/lang/StringBuilder;
      35: aload_0
      36: invokevirtual #15                 // Method java/lang/Object.getClass:()Ljava/lang/Class;
      39: invokevirtual #16                 // Method java/lang/Class.getName:()Ljava/lang/String;
      42: invokevirtual #12                 // Method java/lang/StringBuilder.append:(Ljava/lang/String;)Ljava/lang/StringBuilder;
      45: ldc           #17                 // String ) has no injectable value id configured
      47: invokevirtual #12                 // Method java/lang/StringBuilder.append:(Ljava/lang/String;)Ljava/lang/StringBuilder;
      50: invokevirtual #18                 // Method java/lang/StringBuilder.toString:()Ljava/lang/String;
      53: invokespecial #19                 // Method java/lang/IllegalStateException."<init>":(Ljava/lang/String;)V
      56: athrow
      57: aload_1
      58: aload_0
      59: getfield      #4                  // Field _injectableValueId:Ljava/lang/Object;
      62: aload_0
      63: aload_2
      64: invokevirtual #20                 // Method org/codehaus/jackson/map/DeserializationContext.findInjectableValue:(Ljava/lang/Object;Lorg/codehaus/jackson/map/BeanProperty;Ljava/lang/Object;)Ljava/lang/Object;
      67: areturn

  public void inject(org.codehaus.jackson.map.DeserializationContext, java.lang.Object) throws java.io.IOException;
    Code:
       0: aload_0
       1: aload_2
       2: aload_0
       3: aload_1
       4: aload_2
       5: invokevirtual #21                 // Method findInjectableValue:(Lorg/codehaus/jackson/map/DeserializationContext;Ljava/lang/Object;)Ljava/lang/Object;
       8: invokevirtual #22                 // Method set:(Ljava/lang/Object;Ljava/lang/Object;)V
      11: return

  public <A extends java.lang.annotation.Annotation> A getAnnotation(java.lang.Class<A>);
    Code:
       0: aload_0
       1: getfield      #2                  // Field _annotated:Lorg/codehaus/jackson/map/introspect/AnnotatedParameter;
       4: ifnonnull     9
       7: aconst_null
       8: areturn
       9: aload_0
      10: getfield      #2                  // Field _annotated:Lorg/codehaus/jackson/map/introspect/AnnotatedParameter;
      13: aload_1
      14: invokevirtual #23                 // Method org/codehaus/jackson/map/introspect/AnnotatedParameter.getAnnotation:(Ljava/lang/Class;)Ljava/lang/annotation/Annotation;
      17: areturn

  public org.codehaus.jackson.map.introspect.AnnotatedMember getMember();
    Code:
       0: aload_0
       1: getfield      #2                  // Field _annotated:Lorg/codehaus/jackson/map/introspect/AnnotatedParameter;
       4: areturn

  public void deserializeAndSet(org.codehaus.jackson.JsonParser, org.codehaus.jackson.map.DeserializationContext, java.lang.Object) throws java.io.IOException, org.codehaus.jackson.JsonProcessingException;
    Code:
       0: aload_0
       1: aload_3
       2: aload_0
       3: aload_1
       4: aload_2
       5: invokevirtual #24                 // Method deserialize:(Lorg/codehaus/jackson/JsonParser;Lorg/codehaus/jackson/map/DeserializationContext;)Ljava/lang/Object;
       8: invokevirtual #22                 // Method set:(Ljava/lang/Object;Ljava/lang/Object;)V
      11: return

  public void set(java.lang.Object, java.lang.Object) throws java.io.IOException;
    Code:
       0: return

  public java.lang.Object getInjectableValueId();
    Code:
       0: aload_0
       1: getfield      #4                  // Field _injectableValueId:Ljava/lang/Object;
       4: areturn

  public org.codehaus.jackson.map.deser.SettableBeanProperty withValueDeserializer(org.codehaus.jackson.map.JsonDeserializer);
    Code:
       0: aload_0
       1: aload_1
       2: invokevirtual #25                 // Method withValueDeserializer:(Lorg/codehaus/jackson/map/JsonDeserializer;)Lorg/codehaus/jackson/map/deser/impl/CreatorProperty;
       5: areturn
}
