Compiled from "InodeTree.java"
class org.apache.hadoop.fs.viewfs.InodeTree$ResolveResult<T> {
  final org.apache.hadoop.fs.viewfs.InodeTree$ResultKind kind;

  final T targetFileSystem;

  final java.lang.String resolvedPath;

  final org.apache.hadoop.fs.Path remainingPath;

  org.apache.hadoop.fs.viewfs.InodeTree$ResolveResult(org.apache.hadoop.fs.viewfs.InodeTree$ResultKind, T, java.lang.String, org.apache.hadoop.fs.Path);
    Code:
       0: aload_0
       1: invokespecial #1                  // Method java/lang/Object."<init>":()V
       4: aload_0
       5: aload_1
       6: putfield      #2                  // Field kind:Lorg/apache/hadoop/fs/viewfs/InodeTree$ResultKind;
       9: aload_0
      10: aload_2
      11: putfield      #3                  // Field targetFileSystem:Ljava/lang/Object;
      14: aload_0
      15: aload_3
      16: putfield      #4                  // Field resolvedPath:Ljava/lang/String;
      19: aload_0
      20: aload         4
      22: putfield      #5                  // Field remainingPath:Lorg/apache/hadoop/fs/Path;
      25: return

  boolean isInternalDir();
    Code:
       0: aload_0
       1: getfield      #2                  // Field kind:Lorg/apache/hadoop/fs/viewfs/InodeTree$ResultKind;
       4: getstatic     #6                  // Field org/apache/hadoop/fs/viewfs/InodeTree$ResultKind.INTERNAL_DIR:Lorg/apache/hadoop/fs/viewfs/InodeTree$ResultKind;
       7: if_acmpne     14
      10: iconst_1
      11: goto          15
      14: iconst_0
      15: ireturn
}
