Compiled from "ViewFileSystem.java"
class org.apache.hadoop.fs.viewfs.ViewFileSystem$InnerCache {
  private java.util.Map<org.apache.hadoop.fs.viewfs.ViewFileSystem$InnerCache$Key, org.apache.hadoop.fs.FileSystem> map;

  private org.apache.hadoop.fs.viewfs.FsGetter fsCreator;

  org.apache.hadoop.fs.viewfs.ViewFileSystem$InnerCache(org.apache.hadoop.fs.viewfs.FsGetter);
    Code:
       0: aload_0
       1: invokespecial #1                  // Method java/lang/Object."<init>":()V
       4: aload_0
       5: new           #2                  // class java/util/HashMap
       8: dup
       9: invokespecial #3                  // Method java/util/HashMap."<init>":()V
      12: putfield      #4                  // Field map:Ljava/util/Map;
      15: aload_0
      16: aload_1
      17: putfield      #5                  // Field fsCreator:Lorg/apache/hadoop/fs/viewfs/FsGetter;
      20: return

  org.apache.hadoop.fs.FileSystem get(java.net.URI, org.apache.hadoop.conf.Configuration) throws java.io.IOException;
    Code:
       0: new           #6                  // class org/apache/hadoop/fs/viewfs/ViewFileSystem$InnerCache$Key
       3: dup
       4: aload_1
       5: invokespecial #7                  // Method org/apache/hadoop/fs/viewfs/ViewFileSystem$InnerCache$Key."<init>":(Ljava/net/URI;)V
       8: astore_3
       9: aload_0
      10: getfield      #4                  // Field map:Ljava/util/Map;
      13: aload_3
      14: invokeinterface #8,  2            // InterfaceMethod java/util/Map.get:(Ljava/lang/Object;)Ljava/lang/Object;
      19: ifnonnull     49
      22: aload_0
      23: getfield      #5                  // Field fsCreator:Lorg/apache/hadoop/fs/viewfs/FsGetter;
      26: aload_1
      27: aload_2
      28: invokevirtual #9                  // Method org/apache/hadoop/fs/viewfs/FsGetter.getNewInstance:(Ljava/net/URI;Lorg/apache/hadoop/conf/Configuration;)Lorg/apache/hadoop/fs/FileSystem;
      31: astore        4
      33: aload_0
      34: getfield      #4                  // Field map:Ljava/util/Map;
      37: aload_3
      38: aload         4
      40: invokeinterface #10,  3           // InterfaceMethod java/util/Map.put:(Ljava/lang/Object;Ljava/lang/Object;)Ljava/lang/Object;
      45: pop
      46: aload         4
      48: areturn
      49: aload_0
      50: getfield      #4                  // Field map:Ljava/util/Map;
      53: aload_3
      54: invokeinterface #8,  2            // InterfaceMethod java/util/Map.get:(Ljava/lang/Object;)Ljava/lang/Object;
      59: checkcast     #11                 // class org/apache/hadoop/fs/FileSystem
      62: areturn

  void closeAll();
    Code:
       0: aload_0
       1: getfield      #4                  // Field map:Ljava/util/Map;
       4: invokeinterface #12,  1           // InterfaceMethod java/util/Map.values:()Ljava/util/Collection;
       9: invokeinterface #13,  1           // InterfaceMethod java/util/Collection.iterator:()Ljava/util/Iterator;
      14: astore_1
      15: aload_1
      16: invokeinterface #14,  1           // InterfaceMethod java/util/Iterator.hasNext:()Z
      21: ifeq          73
      24: aload_1
      25: invokeinterface #15,  1           // InterfaceMethod java/util/Iterator.next:()Ljava/lang/Object;
      30: checkcast     #11                 // class org/apache/hadoop/fs/FileSystem
      33: astore_2
      34: aload_2
      35: invokevirtual #16                 // Method org/apache/hadoop/fs/FileSystem.close:()V
      38: goto          70
      41: astore_3
      42: getstatic     #18                 // Field org/apache/hadoop/fs/FileSystem.LOG:Lorg/apache/commons/logging/Log;
      45: new           #19                 // class java/lang/StringBuilder
      48: dup
      49: invokespecial #20                 // Method java/lang/StringBuilder."<init>":()V
      52: ldc           #21                 // String Fail closing ViewFileSystem\'s child filesystem
      54: invokevirtual #22                 // Method java/lang/StringBuilder.append:(Ljava/lang/String;)Ljava/lang/StringBuilder;
      57: aload_2
      58: invokevirtual #23                 // Method java/lang/StringBuilder.append:(Ljava/lang/Object;)Ljava/lang/StringBuilder;
      61: invokevirtual #24                 // Method java/lang/StringBuilder.toString:()Ljava/lang/String;
      64: aload_3
      65: invokeinterface #25,  3           // InterfaceMethod org/apache/commons/logging/Log.info:(Ljava/lang/Object;Ljava/lang/Throwable;)V
      70: goto          15
      73: return
    Exception table:
       from    to  target type
          34    38    41   Class java/io/IOException

  org.apache.hadoop.fs.viewfs.ViewFileSystem$InnerCache unmodifiableCache();
    Code:
       0: aload_0
       1: aload_0
       2: getfield      #4                  // Field map:Ljava/util/Map;
       5: invokestatic  #26                 // Method java/util/Collections.unmodifiableMap:(Ljava/util/Map;)Ljava/util/Map;
       8: putfield      #4                  // Field map:Ljava/util/Map;
      11: aload_0
      12: areturn
}
