Compiled from "SubscriptionIdType.java"
public final class net.java.slee.resource.diameter.cca.events.avp.SubscriptionIdType extends java.lang.Enum<net.java.slee.resource.diameter.cca.events.avp.SubscriptionIdType> implements net.java.slee.resource.diameter.base.events.avp.Enumerated {
  public static final net.java.slee.resource.diameter.cca.events.avp.SubscriptionIdType END_USER_E164;

  public static final net.java.slee.resource.diameter.cca.events.avp.SubscriptionIdType END_USER_IMSI;

  public static final net.java.slee.resource.diameter.cca.events.avp.SubscriptionIdType END_USER_SIP_URI;

  public static final net.java.slee.resource.diameter.cca.events.avp.SubscriptionIdType END_USER_NAI;

  public static final net.java.slee.resource.diameter.cca.events.avp.SubscriptionIdType END_USER_PRIVATE;

  private int value;

  private static final net.java.slee.resource.diameter.cca.events.avp.SubscriptionIdType[] $VALUES;

  public static net.java.slee.resource.diameter.cca.events.avp.SubscriptionIdType[] values();
    Code:
       0: getstatic     #1                  // Field $VALUES:[Lnet/java/slee/resource/diameter/cca/events/avp/SubscriptionIdType;
       3: invokevirtual #2                  // Method "[Lnet/java/slee/resource/diameter/cca/events/avp/SubscriptionIdType;".clone:()Ljava/lang/Object;
       6: checkcast     #3                  // class "[Lnet/java/slee/resource/diameter/cca/events/avp/SubscriptionIdType;"
       9: areturn

  public static net.java.slee.resource.diameter.cca.events.avp.SubscriptionIdType valueOf(java.lang.String);
    Code:
       0: ldc_w         #4                  // class net/java/slee/resource/diameter/cca/events/avp/SubscriptionIdType
       3: aload_0
       4: invokestatic  #5                  // Method java/lang/Enum.valueOf:(Ljava/lang/Class;Ljava/lang/String;)Ljava/lang/Enum;
       7: checkcast     #4                  // class net/java/slee/resource/diameter/cca/events/avp/SubscriptionIdType
      10: areturn

  private net.java.slee.resource.diameter.cca.events.avp.SubscriptionIdType(int);
    Code:
       0: aload_0
       1: aload_1
       2: iload_2
       3: invokespecial #6                  // Method java/lang/Enum."<init>":(Ljava/lang/String;I)V
       6: aload_0
       7: iconst_m1
       8: putfield      #7                  // Field value:I
      11: aload_0
      12: iload_3
      13: putfield      #7                  // Field value:I
      16: return

  private java.lang.Object readResolve() throws java.io.StreamCorruptedException;
    Code:
       0: aload_0
       1: getfield      #7                  // Field value:I
       4: invokestatic  #8                  // Method fromInt:(I)Lnet/java/slee/resource/diameter/cca/events/avp/SubscriptionIdType;
       7: areturn
       8: astore_1
       9: new           #10                 // class java/io/StreamCorruptedException
      12: dup
      13: new           #11                 // class java/lang/StringBuilder
      16: dup
      17: invokespecial #12                 // Method java/lang/StringBuilder."<init>":()V
      20: ldc           #13                 // String Invalid internal state found:
      22: invokevirtual #14                 // Method java/lang/StringBuilder.append:(Ljava/lang/String;)Ljava/lang/StringBuilder;
      25: aload_0
      26: getfield      #7                  // Field value:I
      29: invokevirtual #15                 // Method java/lang/StringBuilder.append:(I)Ljava/lang/StringBuilder;
      32: invokevirtual #16                 // Method java/lang/StringBuilder.toString:()Ljava/lang/String;
      35: invokespecial #17                 // Method java/io/StreamCorruptedException."<init>":(Ljava/lang/String;)V
      38: athrow
    Exception table:
       from    to  target type
           0     7     8   Class java/lang/IllegalArgumentException

  public static net.java.slee.resource.diameter.cca.events.avp.SubscriptionIdType fromInt(int) throws java.lang.IllegalArgumentException;
    Code:
       0: iload_0
       1: tableswitch   { // 0 to 4
                     0: 36
                     1: 40
                     2: 44
                     3: 48
                     4: 52
               default: 56
          }
      36: getstatic     #18                 // Field END_USER_E164:Lnet/java/slee/resource/diameter/cca/events/avp/SubscriptionIdType;
      39: areturn
      40: getstatic     #19                 // Field END_USER_IMSI:Lnet/java/slee/resource/diameter/cca/events/avp/SubscriptionIdType;
      43: areturn
      44: getstatic     #20                 // Field END_USER_SIP_URI:Lnet/java/slee/resource/diameter/cca/events/avp/SubscriptionIdType;
      47: areturn
      48: getstatic     #21                 // Field END_USER_NAI:Lnet/java/slee/resource/diameter/cca/events/avp/SubscriptionIdType;
      51: areturn
      52: getstatic     #22                 // Field END_USER_PRIVATE:Lnet/java/slee/resource/diameter/cca/events/avp/SubscriptionIdType;
      55: areturn
      56: new           #9                  // class java/lang/IllegalArgumentException
      59: dup
      60: invokespecial #23                 // Method java/lang/IllegalArgumentException."<init>":()V
      63: athrow

  public int getValue();
    Code:
       0: aload_0
       1: getfield      #7                  // Field value:I
       4: ireturn

  static {};
    Code:
       0: new           #4                  // class net/java/slee/resource/diameter/cca/events/avp/SubscriptionIdType
       3: dup
       4: ldc           #24                 // String END_USER_E164
       6: iconst_0
       7: iconst_0
       8: invokespecial #25                 // Method "<init>":(Ljava/lang/String;II)V
      11: putstatic     #18                 // Field END_USER_E164:Lnet/java/slee/resource/diameter/cca/events/avp/SubscriptionIdType;
      14: new           #4                  // class net/java/slee/resource/diameter/cca/events/avp/SubscriptionIdType
      17: dup
      18: ldc           #26                 // String END_USER_IMSI
      20: iconst_1
      21: iconst_1
      22: invokespecial #25                 // Method "<init>":(Ljava/lang/String;II)V
      25: putstatic     #19                 // Field END_USER_IMSI:Lnet/java/slee/resource/diameter/cca/events/avp/SubscriptionIdType;
      28: new           #4                  // class net/java/slee/resource/diameter/cca/events/avp/SubscriptionIdType
      31: dup
      32: ldc           #27                 // String END_USER_SIP_URI
      34: iconst_2
      35: iconst_2
      36: invokespecial #25                 // Method "<init>":(Ljava/lang/String;II)V
      39: putstatic     #20                 // Field END_USER_SIP_URI:Lnet/java/slee/resource/diameter/cca/events/avp/SubscriptionIdType;
      42: new           #4                  // class net/java/slee/resource/diameter/cca/events/avp/SubscriptionIdType
      45: dup
      46: ldc           #28                 // String END_USER_NAI
      48: iconst_3
      49: iconst_3
      50: invokespecial #25                 // Method "<init>":(Ljava/lang/String;II)V
      53: putstatic     #21                 // Field END_USER_NAI:Lnet/java/slee/resource/diameter/cca/events/avp/SubscriptionIdType;
      56: new           #4                  // class net/java/slee/resource/diameter/cca/events/avp/SubscriptionIdType
      59: dup
      60: ldc           #29                 // String END_USER_PRIVATE
      62: iconst_4
      63: iconst_4
      64: invokespecial #25                 // Method "<init>":(Ljava/lang/String;II)V
      67: putstatic     #22                 // Field END_USER_PRIVATE:Lnet/java/slee/resource/diameter/cca/events/avp/SubscriptionIdType;
      70: iconst_5
      71: anewarray     #4                  // class net/java/slee/resource/diameter/cca/events/avp/SubscriptionIdType
      74: dup
      75: iconst_0
      76: getstatic     #18                 // Field END_USER_E164:Lnet/java/slee/resource/diameter/cca/events/avp/SubscriptionIdType;
      79: aastore
      80: dup
      81: iconst_1
      82: getstatic     #19                 // Field END_USER_IMSI:Lnet/java/slee/resource/diameter/cca/events/avp/SubscriptionIdType;
      85: aastore
      86: dup
      87: iconst_2
      88: getstatic     #20                 // Field END_USER_SIP_URI:Lnet/java/slee/resource/diameter/cca/events/avp/SubscriptionIdType;
      91: aastore
      92: dup
      93: iconst_3
      94: getstatic     #21                 // Field END_USER_NAI:Lnet/java/slee/resource/diameter/cca/events/avp/SubscriptionIdType;
      97: aastore
      98: dup
      99: iconst_4
     100: getstatic     #22                 // Field END_USER_PRIVATE:Lnet/java/slee/resource/diameter/cca/events/avp/SubscriptionIdType;
     103: aastore
     104: putstatic     #1                  // Field $VALUES:[Lnet/java/slee/resource/diameter/cca/events/avp/SubscriptionIdType;
     107: return
}
