Compiled from "PKIXValidationOptions.java"
public class org.opensaml.xml.security.x509.PKIXValidationOptions {
  private boolean processEmptyCRLs;

  private boolean processExpiredCRLs;

  private boolean processCredentialCRLs;

  private java.lang.Integer defaultVerificationDepth;

  public org.opensaml.xml.security.x509.PKIXValidationOptions();
    Code:
       0: aload_0
       1: invokespecial #1                  // Method java/lang/Object."<init>":()V
       4: aload_0
       5: iconst_1
       6: putfield      #2                  // Field processEmptyCRLs:Z
       9: aload_0
      10: iconst_1
      11: putfield      #3                  // Field processExpiredCRLs:Z
      14: aload_0
      15: iconst_1
      16: putfield      #4                  // Field processCredentialCRLs:Z
      19: aload_0
      20: new           #5                  // class java/lang/Integer
      23: dup
      24: iconst_1
      25: invokespecial #6                  // Method java/lang/Integer."<init>":(I)V
      28: putfield      #7                  // Field defaultVerificationDepth:Ljava/lang/Integer;
      31: return

  public boolean isProcessEmptyCRLs();
    Code:
       0: aload_0
       1: getfield      #2                  // Field processEmptyCRLs:Z
       4: ireturn

  public void setProcessEmptyCRLs(boolean);
    Code:
       0: aload_0
       1: iload_1
       2: putfield      #2                  // Field processEmptyCRLs:Z
       5: return

  public boolean isProcessExpiredCRLs();
    Code:
       0: aload_0
       1: getfield      #3                  // Field processExpiredCRLs:Z
       4: ireturn

  public void setProcessExpiredCRLs(boolean);
    Code:
       0: aload_0
       1: iload_1
       2: putfield      #3                  // Field processExpiredCRLs:Z
       5: return

  public boolean isProcessCredentialCRLs();
    Code:
       0: aload_0
       1: getfield      #4                  // Field processCredentialCRLs:Z
       4: ireturn

  public void setProcessCredentialCRLs(boolean);
    Code:
       0: aload_0
       1: iload_1
       2: putfield      #4                  // Field processCredentialCRLs:Z
       5: return

  public java.lang.Integer getDefaultVerificationDepth();
    Code:
       0: aload_0
       1: getfield      #7                  // Field defaultVerificationDepth:Ljava/lang/Integer;
       4: areturn

  public void setDefaultVerificationDepth(java.lang.Integer);
    Code:
       0: aload_1
       1: ifnonnull     14
       4: new           #8                  // class java/lang/IllegalArgumentException
       7: dup
       8: ldc           #9                  // String Default verification depth may not be null
      10: invokespecial #10                 // Method java/lang/IllegalArgumentException."<init>":(Ljava/lang/String;)V
      13: athrow
      14: aload_0
      15: aload_1
      16: putfield      #7                  // Field defaultVerificationDepth:Ljava/lang/Integer;
      19: return
}
