Compiled from "AbstractEntityGraphVisitationStrategy.java"
final class org.hibernate.loader.plan.build.internal.AbstractEntityGraphVisitationStrategy$1 implements org.hibernate.graph.spi.AttributeNodeImplementor {
  org.hibernate.loader.plan.build.internal.AbstractEntityGraphVisitationStrategy$1();
    Code:
       0: aload_0
       1: invokespecial #1                  // Method java/lang/Object."<init>":()V
       4: return

  public javax.persistence.metamodel.Attribute getAttribute();
    Code:
       0: aconst_null
       1: areturn

  public org.hibernate.graph.spi.AttributeNodeImplementor makeImmutableCopy();
    Code:
       0: aload_0
       1: areturn

  public java.lang.String getAttributeName();
    Code:
       0: aconst_null
       1: areturn

  public java.util.Map<java.lang.Class, javax.persistence.Subgraph> getSubgraphs();
    Code:
       0: invokestatic  #2                  // Method java/util/Collections.emptyMap:()Ljava/util/Map;
       3: areturn

  public java.util.Map<java.lang.Class, javax.persistence.Subgraph> getKeySubgraphs();
    Code:
       0: invokestatic  #2                  // Method java/util/Collections.emptyMap:()Ljava/util/Map;
       3: areturn

  public java.lang.String toString();
    Code:
       0: ldc           #3                  // String Mocked NON-EXIST attribute node
       2: areturn
}
