Compiled from "NodePingUtil.java"
class io.undertow.server.handlers.proxy.mod_cluster.NodePingUtil$ConnectionPoolPingTask$1$1 implements org.xnio.ChannelExceptionHandler<org.xnio.channels.StreamSinkChannel> {
  final io.undertow.server.handlers.proxy.mod_cluster.NodePingUtil$ConnectionPoolPingTask$1 this$1;

  io.undertow.server.handlers.proxy.mod_cluster.NodePingUtil$ConnectionPoolPingTask$1$1(io.undertow.server.handlers.proxy.mod_cluster.NodePingUtil$ConnectionPoolPingTask$1);
    Code:
       0: aload_0
       1: aload_1
       2: putfield      #1                  // Field this$1:Lio/undertow/server/handlers/proxy/mod_cluster/NodePingUtil$ConnectionPoolPingTask$1;
       5: aload_0
       6: invokespecial #2                  // Method java/lang/Object."<init>":()V
       9: return

  public void handleException(org.xnio.channels.StreamSinkChannel, java.io.IOException);
    Code:
       0: aload_0
       1: getfield      #1                  // Field this$1:Lio/undertow/server/handlers/proxy/mod_cluster/NodePingUtil$ConnectionPoolPingTask$1;
       4: getfield      #3                  // Field io/undertow/server/handlers/proxy/mod_cluster/NodePingUtil$ConnectionPoolPingTask$1.this$0:Lio/undertow/server/handlers/proxy/mod_cluster/NodePingUtil$ConnectionPoolPingTask;
       7: invokestatic  #4                  // Method io/undertow/server/handlers/proxy/mod_cluster/NodePingUtil$ConnectionPoolPingTask.access$200:(Lio/undertow/server/handlers/proxy/mod_cluster/NodePingUtil$ConnectionPoolPingTask;)Lio/undertow/server/handlers/proxy/ProxyConnection;
      10: invokevirtual #5                  // Method io/undertow/server/handlers/proxy/ProxyConnection.getConnection:()Lio/undertow/client/ClientConnection;
      13: invokestatic  #6                  // Method org/xnio/IoUtils.safeClose:(Ljava/io/Closeable;)V
      16: aload_0
      17: getfield      #1                  // Field this$1:Lio/undertow/server/handlers/proxy/mod_cluster/NodePingUtil$ConnectionPoolPingTask$1;
      20: getfield      #3                  // Field io/undertow/server/handlers/proxy/mod_cluster/NodePingUtil$ConnectionPoolPingTask$1.this$0:Lio/undertow/server/handlers/proxy/mod_cluster/NodePingUtil$ConnectionPoolPingTask;
      23: invokestatic  #7                  // Method io/undertow/server/handlers/proxy/mod_cluster/NodePingUtil$ConnectionPoolPingTask.access$100:(Lio/undertow/server/handlers/proxy/mod_cluster/NodePingUtil$ConnectionPoolPingTask;)Lio/undertow/server/handlers/proxy/mod_cluster/NodePingUtil$RequestExchangeListener;
      26: invokevirtual #8                  // Method io/undertow/server/handlers/proxy/mod_cluster/NodePingUtil$RequestExchangeListener.taskFailed:()V
      29: return

  public void handleException(java.nio.channels.Channel, java.io.IOException);
    Code:
       0: aload_0
       1: aload_1
       2: checkcast     #9                  // class org/xnio/channels/StreamSinkChannel
       5: aload_2
       6: invokevirtual #10                 // Method handleException:(Lorg/xnio/channels/StreamSinkChannel;Ljava/io/IOException;)V
       9: return
}
