Compiled from "VirtualHost.java"
public class io.undertow.server.handlers.proxy.mod_cluster.VirtualHost {
  private static final java.lang.String STRING_PATH_SEPARATOR;

  private final io.undertow.server.handlers.proxy.mod_cluster.VirtualHost$HostEntry defaultHandler;

  private final java.util.concurrent.ConcurrentMap<java.lang.String, io.undertow.server.handlers.proxy.mod_cluster.VirtualHost$HostEntry> contexts;

  private volatile int[] lengths;

  static final boolean $assertionsDisabled;

  protected io.undertow.server.handlers.proxy.mod_cluster.VirtualHost();
    Code:
       0: aload_0
       1: invokespecial #1                  // Method java/lang/Object."<init>":()V
       4: aload_0
       5: new           #2                  // class io/undertow/server/handlers/proxy/mod_cluster/VirtualHost$HostEntry
       8: dup
       9: ldc           #4                  // String /
      11: invokespecial #5                  // Method io/undertow/server/handlers/proxy/mod_cluster/VirtualHost$HostEntry."<init>":(Ljava/lang/String;)V
      14: putfield      #6                  // Field defaultHandler:Lio/undertow/server/handlers/proxy/mod_cluster/VirtualHost$HostEntry;
      17: aload_0
      18: new           #7                  // class io/undertow/util/CopyOnWriteMap
      21: dup
      22: invokespecial #8                  // Method io/undertow/util/CopyOnWriteMap."<init>":()V
      25: putfield      #9                  // Field contexts:Ljava/util/concurrent/ConcurrentMap;
      28: aload_0
      29: iconst_0
      30: newarray       int
      32: putfield      #10                 // Field lengths:[I
      35: return

  io.undertow.util.PathMatcher$PathMatch<io.undertow.server.handlers.proxy.mod_cluster.VirtualHost$HostEntry> match(java.lang.String);
    Code:
       0: aload_1
       1: invokevirtual #11                 // Method java/lang/String.length:()I
       4: istore_2
       5: aload_0
       6: getfield      #10                 // Field lengths:[I
       9: astore_3
      10: iconst_0
      11: istore        4
      13: iload         4
      15: aload_3
      16: arraylength
      17: if_icmpge     143
      20: aload_3
      21: iload         4
      23: iaload
      24: istore        5
      26: iload         5
      28: iload_2
      29: if_icmpne     68
      32: aload_0
      33: getfield      #9                  // Field contexts:Ljava/util/concurrent/ConcurrentMap;
      36: aload_1
      37: invokeinterface #12,  2           // InterfaceMethod java/util/concurrent/ConcurrentMap.get:(Ljava/lang/Object;)Ljava/lang/Object;
      42: checkcast     #2                  // class io/undertow/server/handlers/proxy/mod_cluster/VirtualHost$HostEntry
      45: astore        6
      47: aload         6
      49: ifnull        65
      52: new           #13                 // class io/undertow/util/PathMatcher$PathMatch
      55: dup
      56: aload_1
      57: ldc           #14                 // String
      59: aload         6
      61: invokespecial #15                 // Method io/undertow/util/PathMatcher$PathMatch."<init>":(Ljava/lang/String;Ljava/lang/String;Ljava/lang/Object;)V
      64: areturn
      65: goto          137
      68: iload         5
      70: iload_2
      71: if_icmpge     137
      74: aload_1
      75: iload         5
      77: invokevirtual #16                 // Method java/lang/String.charAt:(I)C
      80: istore        6
      82: iload         6
      84: bipush        47
      86: if_icmpne     137
      89: aload_1
      90: iconst_0
      91: iload         5
      93: invokevirtual #17                 // Method java/lang/String.substring:(II)Ljava/lang/String;
      96: astore        7
      98: aload_0
      99: getfield      #9                  // Field contexts:Ljava/util/concurrent/ConcurrentMap;
     102: aload         7
     104: invokeinterface #12,  2           // InterfaceMethod java/util/concurrent/ConcurrentMap.get:(Ljava/lang/Object;)Ljava/lang/Object;
     109: checkcast     #2                  // class io/undertow/server/handlers/proxy/mod_cluster/VirtualHost$HostEntry
     112: astore        8
     114: aload         8
     116: ifnull        137
     119: new           #13                 // class io/undertow/util/PathMatcher$PathMatch
     122: dup
     123: aload         7
     125: aload_1
     126: iload         5
     128: invokevirtual #18                 // Method java/lang/String.substring:(I)Ljava/lang/String;
     131: aload         8
     133: invokespecial #15                 // Method io/undertow/util/PathMatcher$PathMatch."<init>":(Ljava/lang/String;Ljava/lang/String;Ljava/lang/Object;)V
     136: areturn
     137: iinc          4, 1
     140: goto          13
     143: aload_0
     144: getfield      #6                  // Field defaultHandler:Lio/undertow/server/handlers/proxy/mod_cluster/VirtualHost$HostEntry;
     147: invokestatic  #19                 // Method io/undertow/server/handlers/proxy/mod_cluster/VirtualHost$HostEntry.access$000:(Lio/undertow/server/handlers/proxy/mod_cluster/VirtualHost$HostEntry;)Ljava/util/concurrent/ConcurrentMap;
     150: invokeinterface #20,  1           // InterfaceMethod java/util/concurrent/ConcurrentMap.isEmpty:()Z
     155: ifeq          170
     158: new           #13                 // class io/undertow/util/PathMatcher$PathMatch
     161: dup
     162: ldc           #14                 // String
     164: aload_1
     165: aconst_null
     166: invokespecial #15                 // Method io/undertow/util/PathMatcher$PathMatch."<init>":(Ljava/lang/String;Ljava/lang/String;Ljava/lang/Object;)V
     169: areturn
     170: new           #13                 // class io/undertow/util/PathMatcher$PathMatch
     173: dup
     174: ldc           #14                 // String
     176: aload_1
     177: aload_0
     178: getfield      #6                  // Field defaultHandler:Lio/undertow/server/handlers/proxy/mod_cluster/VirtualHost$HostEntry;
     181: invokespecial #15                 // Method io/undertow/util/PathMatcher$PathMatch."<init>":(Ljava/lang/String;Ljava/lang/String;Ljava/lang/Object;)V
     184: areturn

  public synchronized void registerContext(java.lang.String, java.lang.String, io.undertow.server.handlers.proxy.mod_cluster.Context);
    Code:
       0: aload_1
       1: invokevirtual #21                 // Method java/lang/String.isEmpty:()Z
       4: ifeq          16
       7: getstatic     #22                 // Field io/undertow/UndertowMessages.MESSAGES:Lio/undertow/UndertowMessages;
      10: invokeinterface #23,  1           // InterfaceMethod io/undertow/UndertowMessages.pathMustBeSpecified:()Ljava/lang/IllegalArgumentException;
      15: athrow
      16: aload_1
      17: invokestatic  #24                 // Method io/undertow/util/URLUtils.normalizeSlashes:(Ljava/lang/String;)Ljava/lang/String;
      20: astore        4
      22: ldc           #4                  // String /
      24: aload         4
      26: invokevirtual #25                 // Method java/lang/String.equals:(Ljava/lang/Object;)Z
      29: ifeq          48
      32: aload_0
      33: getfield      #6                  // Field defaultHandler:Lio/undertow/server/handlers/proxy/mod_cluster/VirtualHost$HostEntry;
      36: invokestatic  #19                 // Method io/undertow/server/handlers/proxy/mod_cluster/VirtualHost$HostEntry.access$000:(Lio/undertow/server/handlers/proxy/mod_cluster/VirtualHost$HostEntry;)Ljava/util/concurrent/ConcurrentMap;
      39: aload_2
      40: aload_3
      41: invokeinterface #26,  3           // InterfaceMethod java/util/concurrent/ConcurrentMap.put:(Ljava/lang/Object;Ljava/lang/Object;)Ljava/lang/Object;
      46: pop
      47: return
      48: iconst_0
      49: istore        5
      51: aload_0
      52: getfield      #9                  // Field contexts:Ljava/util/concurrent/ConcurrentMap;
      55: aload         4
      57: invokeinterface #12,  2           // InterfaceMethod java/util/concurrent/ConcurrentMap.get:(Ljava/lang/Object;)Ljava/lang/Object;
      62: checkcast     #2                  // class io/undertow/server/handlers/proxy/mod_cluster/VirtualHost$HostEntry
      65: astore        6
      67: aload         6
      69: ifnonnull     100
      72: iconst_1
      73: istore        5
      75: new           #2                  // class io/undertow/server/handlers/proxy/mod_cluster/VirtualHost$HostEntry
      78: dup
      79: aload         4
      81: invokespecial #5                  // Method io/undertow/server/handlers/proxy/mod_cluster/VirtualHost$HostEntry."<init>":(Ljava/lang/String;)V
      84: astore        6
      86: aload_0
      87: getfield      #9                  // Field contexts:Ljava/util/concurrent/ConcurrentMap;
      90: aload         4
      92: aload         6
      94: invokeinterface #26,  3           // InterfaceMethod java/util/concurrent/ConcurrentMap.put:(Ljava/lang/Object;Ljava/lang/Object;)Ljava/lang/Object;
      99: pop
     100: getstatic     #27                 // Field $assertionsDisabled:Z
     103: ifne          128
     106: aload         6
     108: invokestatic  #19                 // Method io/undertow/server/handlers/proxy/mod_cluster/VirtualHost$HostEntry.access$000:(Lio/undertow/server/handlers/proxy/mod_cluster/VirtualHost$HostEntry;)Ljava/util/concurrent/ConcurrentMap;
     111: aload_2
     112: invokeinterface #28,  2           // InterfaceMethod java/util/concurrent/ConcurrentMap.containsKey:(Ljava/lang/Object;)Z
     117: ifeq          128
     120: new           #29                 // class java/lang/AssertionError
     123: dup
     124: invokespecial #30                 // Method java/lang/AssertionError."<init>":()V
     127: athrow
     128: aload         6
     130: invokestatic  #19                 // Method io/undertow/server/handlers/proxy/mod_cluster/VirtualHost$HostEntry.access$000:(Lio/undertow/server/handlers/proxy/mod_cluster/VirtualHost$HostEntry;)Ljava/util/concurrent/ConcurrentMap;
     133: aload_2
     134: aload_3
     135: invokeinterface #26,  3           // InterfaceMethod java/util/concurrent/ConcurrentMap.put:(Ljava/lang/Object;Ljava/lang/Object;)Ljava/lang/Object;
     140: pop
     141: iload         5
     143: ifeq          150
     146: aload_0
     147: invokespecial #31                 // Method buildLengths:()V
     150: return

  public synchronized void removeContext(java.lang.String, java.lang.String, io.undertow.server.handlers.proxy.mod_cluster.Context);
    Code:
       0: aload_1
       1: ifnull        11
       4: aload_1
       5: invokevirtual #21                 // Method java/lang/String.isEmpty:()Z
       8: ifeq          20
      11: getstatic     #22                 // Field io/undertow/UndertowMessages.MESSAGES:Lio/undertow/UndertowMessages;
      14: invokeinterface #23,  1           // InterfaceMethod io/undertow/UndertowMessages.pathMustBeSpecified:()Ljava/lang/IllegalArgumentException;
      19: athrow
      20: aload_1
      21: invokestatic  #24                 // Method io/undertow/util/URLUtils.normalizeSlashes:(Ljava/lang/String;)Ljava/lang/String;
      24: astore        4
      26: ldc           #4                  // String /
      28: aload         4
      30: invokevirtual #25                 // Method java/lang/String.equals:(Ljava/lang/Object;)Z
      33: ifeq          51
      36: aload_0
      37: getfield      #6                  // Field defaultHandler:Lio/undertow/server/handlers/proxy/mod_cluster/VirtualHost$HostEntry;
      40: invokestatic  #19                 // Method io/undertow/server/handlers/proxy/mod_cluster/VirtualHost$HostEntry.access$000:(Lio/undertow/server/handlers/proxy/mod_cluster/VirtualHost$HostEntry;)Ljava/util/concurrent/ConcurrentMap;
      43: aload_2
      44: aload_3
      45: invokeinterface #32,  3           // InterfaceMethod java/util/concurrent/ConcurrentMap.remove:(Ljava/lang/Object;Ljava/lang/Object;)Z
      50: pop
      51: aload_0
      52: getfield      #9                  // Field contexts:Ljava/util/concurrent/ConcurrentMap;
      55: aload         4
      57: invokeinterface #12,  2           // InterfaceMethod java/util/concurrent/ConcurrentMap.get:(Ljava/lang/Object;)Ljava/lang/Object;
      62: checkcast     #2                  // class io/undertow/server/handlers/proxy/mod_cluster/VirtualHost$HostEntry
      65: astore        5
      67: aload         5
      69: ifnull        116
      72: aload         5
      74: invokestatic  #19                 // Method io/undertow/server/handlers/proxy/mod_cluster/VirtualHost$HostEntry.access$000:(Lio/undertow/server/handlers/proxy/mod_cluster/VirtualHost$HostEntry;)Ljava/util/concurrent/ConcurrentMap;
      77: aload_2
      78: aload_3
      79: invokeinterface #32,  3           // InterfaceMethod java/util/concurrent/ConcurrentMap.remove:(Ljava/lang/Object;Ljava/lang/Object;)Z
      84: ifeq          116
      87: aload         5
      89: invokestatic  #19                 // Method io/undertow/server/handlers/proxy/mod_cluster/VirtualHost$HostEntry.access$000:(Lio/undertow/server/handlers/proxy/mod_cluster/VirtualHost$HostEntry;)Ljava/util/concurrent/ConcurrentMap;
      92: invokeinterface #20,  1           // InterfaceMethod java/util/concurrent/ConcurrentMap.isEmpty:()Z
      97: ifeq          116
     100: aload_0
     101: getfield      #9                  // Field contexts:Ljava/util/concurrent/ConcurrentMap;
     104: aload         4
     106: invokeinterface #33,  2           // InterfaceMethod java/util/concurrent/ConcurrentMap.remove:(Ljava/lang/Object;)Ljava/lang/Object;
     111: pop
     112: aload_0
     113: invokespecial #31                 // Method buildLengths:()V
     116: return

  boolean isEmpty();
    Code:
       0: aload_0
       1: getfield      #9                  // Field contexts:Ljava/util/concurrent/ConcurrentMap;
       4: invokeinterface #20,  1           // InterfaceMethod java/util/concurrent/ConcurrentMap.isEmpty:()Z
       9: ifeq          31
      12: aload_0
      13: getfield      #6                  // Field defaultHandler:Lio/undertow/server/handlers/proxy/mod_cluster/VirtualHost$HostEntry;
      16: invokestatic  #19                 // Method io/undertow/server/handlers/proxy/mod_cluster/VirtualHost$HostEntry.access$000:(Lio/undertow/server/handlers/proxy/mod_cluster/VirtualHost$HostEntry;)Ljava/util/concurrent/ConcurrentMap;
      19: invokeinterface #20,  1           // InterfaceMethod java/util/concurrent/ConcurrentMap.isEmpty:()Z
      24: ifeq          31
      27: iconst_1
      28: goto          32
      31: iconst_0
      32: ireturn

  private void buildLengths();
    Code:
       0: new           #34                 // class java/util/TreeSet
       3: dup
       4: new           #35                 // class io/undertow/server/handlers/proxy/mod_cluster/VirtualHost$1
       7: dup
       8: aload_0
       9: invokespecial #36                 // Method io/undertow/server/handlers/proxy/mod_cluster/VirtualHost$1."<init>":(Lio/undertow/server/handlers/proxy/mod_cluster/VirtualHost;)V
      12: invokespecial #37                 // Method java/util/TreeSet."<init>":(Ljava/util/Comparator;)V
      15: astore_1
      16: aload_0
      17: getfield      #9                  // Field contexts:Ljava/util/concurrent/ConcurrentMap;
      20: invokeinterface #38,  1           // InterfaceMethod java/util/concurrent/ConcurrentMap.keySet:()Ljava/util/Set;
      25: invokeinterface #39,  1           // InterfaceMethod java/util/Set.iterator:()Ljava/util/Iterator;
      30: astore_2
      31: aload_2
      32: invokeinterface #40,  1           // InterfaceMethod java/util/Iterator.hasNext:()Z
      37: ifeq          67
      40: aload_2
      41: invokeinterface #41,  1           // InterfaceMethod java/util/Iterator.next:()Ljava/lang/Object;
      46: checkcast     #42                 // class java/lang/String
      49: astore_3
      50: aload_1
      51: aload_3
      52: invokevirtual #11                 // Method java/lang/String.length:()I
      55: invokestatic  #43                 // Method java/lang/Integer.valueOf:(I)Ljava/lang/Integer;
      58: invokeinterface #44,  2           // InterfaceMethod java/util/Set.add:(Ljava/lang/Object;)Z
      63: pop
      64: goto          31
      67: aload_1
      68: invokeinterface #45,  1           // InterfaceMethod java/util/Set.size:()I
      73: newarray       int
      75: astore_2
      76: iconst_0
      77: istore_3
      78: aload_1
      79: invokeinterface #39,  1           // InterfaceMethod java/util/Set.iterator:()Ljava/util/Iterator;
      84: astore        4
      86: aload         4
      88: invokeinterface #40,  1           // InterfaceMethod java/util/Iterator.hasNext:()Z
      93: ifeq          122
      96: aload         4
      98: invokeinterface #41,  1           // InterfaceMethod java/util/Iterator.next:()Ljava/lang/Object;
     103: checkcast     #46                 // class java/lang/Integer
     106: invokevirtual #47                 // Method java/lang/Integer.intValue:()I
     109: istore        5
     111: aload_2
     112: iload_3
     113: iinc          3, 1
     116: iload         5
     118: iastore
     119: goto          86
     122: aload_0
     123: aload_2
     124: putfield      #10                 // Field lengths:[I
     127: return

  static {};
    Code:
       0: ldc           #3                  // class io/undertow/server/handlers/proxy/mod_cluster/VirtualHost
       2: invokevirtual #48                 // Method java/lang/Class.desiredAssertionStatus:()Z
       5: ifne          12
       8: iconst_1
       9: goto          13
      12: iconst_0
      13: putstatic     #27                 // Field $assertionsDisabled:Z
      16: return
}
