Compiled from "AudioCodecSettings.java"
public interface software.amazon.awssdk.services.medialive.model.AudioCodecSettings$Builder extends software.amazon.awssdk.core.SdkPojo, software.amazon.awssdk.utils.builder.CopyableBuilder<software.amazon.awssdk.services.medialive.model.AudioCodecSettings$Builder, software.amazon.awssdk.services.medialive.model.AudioCodecSettings> {
  public abstract software.amazon.awssdk.services.medialive.model.AudioCodecSettings$Builder aacSettings(software.amazon.awssdk.services.medialive.model.AacSettings);

  public default software.amazon.awssdk.services.medialive.model.AudioCodecSettings$Builder aacSettings(java.util.function.Consumer<software.amazon.awssdk.services.medialive.model.AacSettings$Builder>);
    Code:
       0: aload_0
       1: invokestatic  #1                  // Method software/amazon/awssdk/services/medialive/model/AacSettings.builder:()Lsoftware/amazon/awssdk/services/medialive/model/AacSettings$Builder;
       4: aload_1
       5: invokeinterface #2,  2            // InterfaceMethod software/amazon/awssdk/services/medialive/model/AacSettings$Builder.applyMutation:(Ljava/util/function/Consumer;)Lsoftware/amazon/awssdk/utils/builder/SdkBuilder;
      10: checkcast     #3                  // class software/amazon/awssdk/services/medialive/model/AacSettings$Builder
      13: invokeinterface #4,  1            // InterfaceMethod software/amazon/awssdk/services/medialive/model/AacSettings$Builder.build:()Ljava/lang/Object;
      18: checkcast     #5                  // class software/amazon/awssdk/services/medialive/model/AacSettings
      21: invokeinterface #6,  2            // InterfaceMethod aacSettings:(Lsoftware/amazon/awssdk/services/medialive/model/AacSettings;)Lsoftware/amazon/awssdk/services/medialive/model/AudioCodecSettings$Builder;
      26: areturn

  public abstract software.amazon.awssdk.services.medialive.model.AudioCodecSettings$Builder ac3Settings(software.amazon.awssdk.services.medialive.model.Ac3Settings);

  public default software.amazon.awssdk.services.medialive.model.AudioCodecSettings$Builder ac3Settings(java.util.function.Consumer<software.amazon.awssdk.services.medialive.model.Ac3Settings$Builder>);
    Code:
       0: aload_0
       1: invokestatic  #7                  // Method software/amazon/awssdk/services/medialive/model/Ac3Settings.builder:()Lsoftware/amazon/awssdk/services/medialive/model/Ac3Settings$Builder;
       4: aload_1
       5: invokeinterface #8,  2            // InterfaceMethod software/amazon/awssdk/services/medialive/model/Ac3Settings$Builder.applyMutation:(Ljava/util/function/Consumer;)Lsoftware/amazon/awssdk/utils/builder/SdkBuilder;
      10: checkcast     #9                  // class software/amazon/awssdk/services/medialive/model/Ac3Settings$Builder
      13: invokeinterface #10,  1           // InterfaceMethod software/amazon/awssdk/services/medialive/model/Ac3Settings$Builder.build:()Ljava/lang/Object;
      18: checkcast     #11                 // class software/amazon/awssdk/services/medialive/model/Ac3Settings
      21: invokeinterface #12,  2           // InterfaceMethod ac3Settings:(Lsoftware/amazon/awssdk/services/medialive/model/Ac3Settings;)Lsoftware/amazon/awssdk/services/medialive/model/AudioCodecSettings$Builder;
      26: areturn

  public abstract software.amazon.awssdk.services.medialive.model.AudioCodecSettings$Builder eac3Settings(software.amazon.awssdk.services.medialive.model.Eac3Settings);

  public default software.amazon.awssdk.services.medialive.model.AudioCodecSettings$Builder eac3Settings(java.util.function.Consumer<software.amazon.awssdk.services.medialive.model.Eac3Settings$Builder>);
    Code:
       0: aload_0
       1: invokestatic  #13                 // Method software/amazon/awssdk/services/medialive/model/Eac3Settings.builder:()Lsoftware/amazon/awssdk/services/medialive/model/Eac3Settings$Builder;
       4: aload_1
       5: invokeinterface #14,  2           // InterfaceMethod software/amazon/awssdk/services/medialive/model/Eac3Settings$Builder.applyMutation:(Ljava/util/function/Consumer;)Lsoftware/amazon/awssdk/utils/builder/SdkBuilder;
      10: checkcast     #15                 // class software/amazon/awssdk/services/medialive/model/Eac3Settings$Builder
      13: invokeinterface #16,  1           // InterfaceMethod software/amazon/awssdk/services/medialive/model/Eac3Settings$Builder.build:()Ljava/lang/Object;
      18: checkcast     #17                 // class software/amazon/awssdk/services/medialive/model/Eac3Settings
      21: invokeinterface #18,  2           // InterfaceMethod eac3Settings:(Lsoftware/amazon/awssdk/services/medialive/model/Eac3Settings;)Lsoftware/amazon/awssdk/services/medialive/model/AudioCodecSettings$Builder;
      26: areturn

  public abstract software.amazon.awssdk.services.medialive.model.AudioCodecSettings$Builder mp2Settings(software.amazon.awssdk.services.medialive.model.Mp2Settings);

  public default software.amazon.awssdk.services.medialive.model.AudioCodecSettings$Builder mp2Settings(java.util.function.Consumer<software.amazon.awssdk.services.medialive.model.Mp2Settings$Builder>);
    Code:
       0: aload_0
       1: invokestatic  #19                 // Method software/amazon/awssdk/services/medialive/model/Mp2Settings.builder:()Lsoftware/amazon/awssdk/services/medialive/model/Mp2Settings$Builder;
       4: aload_1
       5: invokeinterface #20,  2           // InterfaceMethod software/amazon/awssdk/services/medialive/model/Mp2Settings$Builder.applyMutation:(Ljava/util/function/Consumer;)Lsoftware/amazon/awssdk/utils/builder/SdkBuilder;
      10: checkcast     #21                 // class software/amazon/awssdk/services/medialive/model/Mp2Settings$Builder
      13: invokeinterface #22,  1           // InterfaceMethod software/amazon/awssdk/services/medialive/model/Mp2Settings$Builder.build:()Ljava/lang/Object;
      18: checkcast     #23                 // class software/amazon/awssdk/services/medialive/model/Mp2Settings
      21: invokeinterface #24,  2           // InterfaceMethod mp2Settings:(Lsoftware/amazon/awssdk/services/medialive/model/Mp2Settings;)Lsoftware/amazon/awssdk/services/medialive/model/AudioCodecSettings$Builder;
      26: areturn

  public abstract software.amazon.awssdk.services.medialive.model.AudioCodecSettings$Builder passThroughSettings(software.amazon.awssdk.services.medialive.model.PassThroughSettings);

  public default software.amazon.awssdk.services.medialive.model.AudioCodecSettings$Builder passThroughSettings(java.util.function.Consumer<software.amazon.awssdk.services.medialive.model.PassThroughSettings$Builder>);
    Code:
       0: aload_0
       1: invokestatic  #25                 // Method software/amazon/awssdk/services/medialive/model/PassThroughSettings.builder:()Lsoftware/amazon/awssdk/services/medialive/model/PassThroughSettings$Builder;
       4: aload_1
       5: invokeinterface #26,  2           // InterfaceMethod software/amazon/awssdk/services/medialive/model/PassThroughSettings$Builder.applyMutation:(Ljava/util/function/Consumer;)Lsoftware/amazon/awssdk/utils/builder/SdkBuilder;
      10: checkcast     #27                 // class software/amazon/awssdk/services/medialive/model/PassThroughSettings$Builder
      13: invokeinterface #28,  1           // InterfaceMethod software/amazon/awssdk/services/medialive/model/PassThroughSettings$Builder.build:()Ljava/lang/Object;
      18: checkcast     #29                 // class software/amazon/awssdk/services/medialive/model/PassThroughSettings
      21: invokeinterface #30,  2           // InterfaceMethod passThroughSettings:(Lsoftware/amazon/awssdk/services/medialive/model/PassThroughSettings;)Lsoftware/amazon/awssdk/services/medialive/model/AudioCodecSettings$Builder;
      26: areturn
}
