Compiled from "AudioLanguageSelection.java"
final class software.amazon.awssdk.services.medialive.model.AudioLanguageSelection$BuilderImpl implements software.amazon.awssdk.services.medialive.model.AudioLanguageSelection$Builder {
  private java.lang.String languageCode;

  private java.lang.String languageSelectionPolicy;

  private software.amazon.awssdk.services.medialive.model.AudioLanguageSelection$BuilderImpl();
    Code:
       0: aload_0
       1: invokespecial #5                  // Method java/lang/Object."<init>":()V
       4: return

  private software.amazon.awssdk.services.medialive.model.AudioLanguageSelection$BuilderImpl(software.amazon.awssdk.services.medialive.model.AudioLanguageSelection);
    Code:
       0: aload_0
       1: invokespecial #5                  // Method java/lang/Object."<init>":()V
       4: aload_0
       5: aload_1
       6: invokestatic  #6                  // Method software/amazon/awssdk/services/medialive/model/AudioLanguageSelection.access$400:(Lsoftware/amazon/awssdk/services/medialive/model/AudioLanguageSelection;)Ljava/lang/String;
       9: invokevirtual #7                  // Method languageCode:(Ljava/lang/String;)Lsoftware/amazon/awssdk/services/medialive/model/AudioLanguageSelection$Builder;
      12: pop
      13: aload_0
      14: aload_1
      15: invokestatic  #8                  // Method software/amazon/awssdk/services/medialive/model/AudioLanguageSelection.access$500:(Lsoftware/amazon/awssdk/services/medialive/model/AudioLanguageSelection;)Ljava/lang/String;
      18: invokevirtual #9                  // Method languageSelectionPolicy:(Ljava/lang/String;)Lsoftware/amazon/awssdk/services/medialive/model/AudioLanguageSelection$Builder;
      21: pop
      22: return

  public final java.lang.String getLanguageCode();
    Code:
       0: aload_0
       1: getfield      #4                  // Field languageCode:Ljava/lang/String;
       4: areturn

  public final software.amazon.awssdk.services.medialive.model.AudioLanguageSelection$Builder languageCode(java.lang.String);
    Code:
       0: aload_0
       1: aload_1
       2: putfield      #4                  // Field languageCode:Ljava/lang/String;
       5: aload_0
       6: areturn

  public final void setLanguageCode(java.lang.String);
    Code:
       0: aload_0
       1: aload_1
       2: putfield      #4                  // Field languageCode:Ljava/lang/String;
       5: return

  public final java.lang.String getLanguageSelectionPolicy();
    Code:
       0: aload_0
       1: getfield      #3                  // Field languageSelectionPolicy:Ljava/lang/String;
       4: areturn

  public final software.amazon.awssdk.services.medialive.model.AudioLanguageSelection$Builder languageSelectionPolicy(java.lang.String);
    Code:
       0: aload_0
       1: aload_1
       2: putfield      #3                  // Field languageSelectionPolicy:Ljava/lang/String;
       5: aload_0
       6: areturn

  public final software.amazon.awssdk.services.medialive.model.AudioLanguageSelection$Builder languageSelectionPolicy(software.amazon.awssdk.services.medialive.model.AudioLanguageSelectionPolicy);
    Code:
       0: aload_0
       1: aload_1
       2: ifnonnull     9
       5: aconst_null
       6: goto          13
       9: aload_1
      10: invokevirtual #10                 // Method software/amazon/awssdk/services/medialive/model/AudioLanguageSelectionPolicy.toString:()Ljava/lang/String;
      13: invokevirtual #9                  // Method languageSelectionPolicy:(Ljava/lang/String;)Lsoftware/amazon/awssdk/services/medialive/model/AudioLanguageSelection$Builder;
      16: pop
      17: aload_0
      18: areturn

  public final void setLanguageSelectionPolicy(java.lang.String);
    Code:
       0: aload_0
       1: aload_1
       2: putfield      #3                  // Field languageSelectionPolicy:Ljava/lang/String;
       5: return

  public software.amazon.awssdk.services.medialive.model.AudioLanguageSelection build();
    Code:
       0: new           #11                 // class software/amazon/awssdk/services/medialive/model/AudioLanguageSelection
       3: dup
       4: aload_0
       5: aconst_null
       6: invokespecial #12                 // Method software/amazon/awssdk/services/medialive/model/AudioLanguageSelection."<init>":(Lsoftware/amazon/awssdk/services/medialive/model/AudioLanguageSelection$BuilderImpl;Lsoftware/amazon/awssdk/services/medialive/model/AudioLanguageSelection$1;)V
       9: areturn

  public java.util.List<software.amazon.awssdk.core.SdkField<?>> sdkFields();
    Code:
       0: invokestatic  #13                 // Method software/amazon/awssdk/services/medialive/model/AudioLanguageSelection.access$700:()Ljava/util/List;
       3: areturn

  public java.lang.Object build();
    Code:
       0: aload_0
       1: invokevirtual #14                 // Method build:()Lsoftware/amazon/awssdk/services/medialive/model/AudioLanguageSelection;
       4: areturn

  static java.lang.String access$000(software.amazon.awssdk.services.medialive.model.AudioLanguageSelection$BuilderImpl);
    Code:
       0: aload_0
       1: getfield      #4                  // Field languageCode:Ljava/lang/String;
       4: areturn

  static java.lang.String access$100(software.amazon.awssdk.services.medialive.model.AudioLanguageSelection$BuilderImpl);
    Code:
       0: aload_0
       1: getfield      #3                  // Field languageSelectionPolicy:Ljava/lang/String;
       4: areturn

  software.amazon.awssdk.services.medialive.model.AudioLanguageSelection$BuilderImpl(software.amazon.awssdk.services.medialive.model.AudioLanguageSelection, software.amazon.awssdk.services.medialive.model.AudioLanguageSelection$1);
    Code:
       0: aload_0
       1: aload_1
       2: invokespecial #2                  // Method "<init>":(Lsoftware/amazon/awssdk/services/medialive/model/AudioLanguageSelection;)V
       5: return

  software.amazon.awssdk.services.medialive.model.AudioLanguageSelection$BuilderImpl(software.amazon.awssdk.services.medialive.model.AudioLanguageSelection$1);
    Code:
       0: aload_0
       1: invokespecial #1                  // Method "<init>":()V
       4: return
}
