Compiled from "FecOutputSettings.java"
final class software.amazon.awssdk.services.medialive.model.FecOutputSettings$BuilderImpl implements software.amazon.awssdk.services.medialive.model.FecOutputSettings$Builder {
  private java.lang.Integer columnDepth;

  private java.lang.String includeFec;

  private java.lang.Integer rowLength;

  private software.amazon.awssdk.services.medialive.model.FecOutputSettings$BuilderImpl();
    Code:
       0: aload_0
       1: invokespecial #6                  // Method java/lang/Object."<init>":()V
       4: return

  private software.amazon.awssdk.services.medialive.model.FecOutputSettings$BuilderImpl(software.amazon.awssdk.services.medialive.model.FecOutputSettings);
    Code:
       0: aload_0
       1: invokespecial #6                  // Method java/lang/Object."<init>":()V
       4: aload_0
       5: aload_1
       6: invokestatic  #7                  // Method software/amazon/awssdk/services/medialive/model/FecOutputSettings.access$500:(Lsoftware/amazon/awssdk/services/medialive/model/FecOutputSettings;)Ljava/lang/Integer;
       9: invokevirtual #8                  // Method columnDepth:(Ljava/lang/Integer;)Lsoftware/amazon/awssdk/services/medialive/model/FecOutputSettings$Builder;
      12: pop
      13: aload_0
      14: aload_1
      15: invokestatic  #9                  // Method software/amazon/awssdk/services/medialive/model/FecOutputSettings.access$600:(Lsoftware/amazon/awssdk/services/medialive/model/FecOutputSettings;)Ljava/lang/String;
      18: invokevirtual #10                 // Method includeFec:(Ljava/lang/String;)Lsoftware/amazon/awssdk/services/medialive/model/FecOutputSettings$Builder;
      21: pop
      22: aload_0
      23: aload_1
      24: invokestatic  #11                 // Method software/amazon/awssdk/services/medialive/model/FecOutputSettings.access$700:(Lsoftware/amazon/awssdk/services/medialive/model/FecOutputSettings;)Ljava/lang/Integer;
      27: invokevirtual #12                 // Method rowLength:(Ljava/lang/Integer;)Lsoftware/amazon/awssdk/services/medialive/model/FecOutputSettings$Builder;
      30: pop
      31: return

  public final java.lang.Integer getColumnDepth();
    Code:
       0: aload_0
       1: getfield      #5                  // Field columnDepth:Ljava/lang/Integer;
       4: areturn

  public final software.amazon.awssdk.services.medialive.model.FecOutputSettings$Builder columnDepth(java.lang.Integer);
    Code:
       0: aload_0
       1: aload_1
       2: putfield      #5                  // Field columnDepth:Ljava/lang/Integer;
       5: aload_0
       6: areturn

  public final void setColumnDepth(java.lang.Integer);
    Code:
       0: aload_0
       1: aload_1
       2: putfield      #5                  // Field columnDepth:Ljava/lang/Integer;
       5: return

  public final java.lang.String getIncludeFec();
    Code:
       0: aload_0
       1: getfield      #4                  // Field includeFec:Ljava/lang/String;
       4: areturn

  public final software.amazon.awssdk.services.medialive.model.FecOutputSettings$Builder includeFec(java.lang.String);
    Code:
       0: aload_0
       1: aload_1
       2: putfield      #4                  // Field includeFec:Ljava/lang/String;
       5: aload_0
       6: areturn

  public final software.amazon.awssdk.services.medialive.model.FecOutputSettings$Builder includeFec(software.amazon.awssdk.services.medialive.model.FecOutputIncludeFec);
    Code:
       0: aload_0
       1: aload_1
       2: ifnonnull     9
       5: aconst_null
       6: goto          13
       9: aload_1
      10: invokevirtual #13                 // Method software/amazon/awssdk/services/medialive/model/FecOutputIncludeFec.toString:()Ljava/lang/String;
      13: invokevirtual #10                 // Method includeFec:(Ljava/lang/String;)Lsoftware/amazon/awssdk/services/medialive/model/FecOutputSettings$Builder;
      16: pop
      17: aload_0
      18: areturn

  public final void setIncludeFec(java.lang.String);
    Code:
       0: aload_0
       1: aload_1
       2: putfield      #4                  // Field includeFec:Ljava/lang/String;
       5: return

  public final java.lang.Integer getRowLength();
    Code:
       0: aload_0
       1: getfield      #3                  // Field rowLength:Ljava/lang/Integer;
       4: areturn

  public final software.amazon.awssdk.services.medialive.model.FecOutputSettings$Builder rowLength(java.lang.Integer);
    Code:
       0: aload_0
       1: aload_1
       2: putfield      #3                  // Field rowLength:Ljava/lang/Integer;
       5: aload_0
       6: areturn

  public final void setRowLength(java.lang.Integer);
    Code:
       0: aload_0
       1: aload_1
       2: putfield      #3                  // Field rowLength:Ljava/lang/Integer;
       5: return

  public software.amazon.awssdk.services.medialive.model.FecOutputSettings build();
    Code:
       0: new           #14                 // class software/amazon/awssdk/services/medialive/model/FecOutputSettings
       3: dup
       4: aload_0
       5: aconst_null
       6: invokespecial #15                 // Method software/amazon/awssdk/services/medialive/model/FecOutputSettings."<init>":(Lsoftware/amazon/awssdk/services/medialive/model/FecOutputSettings$BuilderImpl;Lsoftware/amazon/awssdk/services/medialive/model/FecOutputSettings$1;)V
       9: areturn

  public java.util.List<software.amazon.awssdk.core.SdkField<?>> sdkFields();
    Code:
       0: invokestatic  #16                 // Method software/amazon/awssdk/services/medialive/model/FecOutputSettings.access$900:()Ljava/util/List;
       3: areturn

  public java.lang.Object build();
    Code:
       0: aload_0
       1: invokevirtual #17                 // Method build:()Lsoftware/amazon/awssdk/services/medialive/model/FecOutputSettings;
       4: areturn

  static java.lang.Integer access$000(software.amazon.awssdk.services.medialive.model.FecOutputSettings$BuilderImpl);
    Code:
       0: aload_0
       1: getfield      #5                  // Field columnDepth:Ljava/lang/Integer;
       4: areturn

  static java.lang.String access$100(software.amazon.awssdk.services.medialive.model.FecOutputSettings$BuilderImpl);
    Code:
       0: aload_0
       1: getfield      #4                  // Field includeFec:Ljava/lang/String;
       4: areturn

  static java.lang.Integer access$200(software.amazon.awssdk.services.medialive.model.FecOutputSettings$BuilderImpl);
    Code:
       0: aload_0
       1: getfield      #3                  // Field rowLength:Ljava/lang/Integer;
       4: areturn

  software.amazon.awssdk.services.medialive.model.FecOutputSettings$BuilderImpl(software.amazon.awssdk.services.medialive.model.FecOutputSettings, software.amazon.awssdk.services.medialive.model.FecOutputSettings$1);
    Code:
       0: aload_0
       1: aload_1
       2: invokespecial #2                  // Method "<init>":(Lsoftware/amazon/awssdk/services/medialive/model/FecOutputSettings;)V
       5: return

  software.amazon.awssdk.services.medialive.model.FecOutputSettings$BuilderImpl(software.amazon.awssdk.services.medialive.model.FecOutputSettings$1);
    Code:
       0: aload_0
       1: invokespecial #1                  // Method "<init>":()V
       4: return
}
