Compiled from "FrameCaptureOutputSettings.java"
final class software.amazon.awssdk.services.medialive.model.FrameCaptureOutputSettings$BuilderImpl implements software.amazon.awssdk.services.medialive.model.FrameCaptureOutputSettings$Builder {
  private java.lang.String nameModifier;

  private software.amazon.awssdk.services.medialive.model.FrameCaptureOutputSettings$BuilderImpl();
    Code:
       0: aload_0
       1: invokespecial #4                  // Method java/lang/Object."<init>":()V
       4: return

  private software.amazon.awssdk.services.medialive.model.FrameCaptureOutputSettings$BuilderImpl(software.amazon.awssdk.services.medialive.model.FrameCaptureOutputSettings);
    Code:
       0: aload_0
       1: invokespecial #4                  // Method java/lang/Object."<init>":()V
       4: aload_0
       5: aload_1
       6: invokestatic  #5                  // Method software/amazon/awssdk/services/medialive/model/FrameCaptureOutputSettings.access$300:(Lsoftware/amazon/awssdk/services/medialive/model/FrameCaptureOutputSettings;)Ljava/lang/String;
       9: invokevirtual #6                  // Method nameModifier:(Ljava/lang/String;)Lsoftware/amazon/awssdk/services/medialive/model/FrameCaptureOutputSettings$Builder;
      12: pop
      13: return

  public final java.lang.String getNameModifier();
    Code:
       0: aload_0
       1: getfield      #3                  // Field nameModifier:Ljava/lang/String;
       4: areturn

  public final software.amazon.awssdk.services.medialive.model.FrameCaptureOutputSettings$Builder nameModifier(java.lang.String);
    Code:
       0: aload_0
       1: aload_1
       2: putfield      #3                  // Field nameModifier:Ljava/lang/String;
       5: aload_0
       6: areturn

  public final void setNameModifier(java.lang.String);
    Code:
       0: aload_0
       1: aload_1
       2: putfield      #3                  // Field nameModifier:Ljava/lang/String;
       5: return

  public software.amazon.awssdk.services.medialive.model.FrameCaptureOutputSettings build();
    Code:
       0: new           #7                  // class software/amazon/awssdk/services/medialive/model/FrameCaptureOutputSettings
       3: dup
       4: aload_0
       5: aconst_null
       6: invokespecial #8                  // Method software/amazon/awssdk/services/medialive/model/FrameCaptureOutputSettings."<init>":(Lsoftware/amazon/awssdk/services/medialive/model/FrameCaptureOutputSettings$BuilderImpl;Lsoftware/amazon/awssdk/services/medialive/model/FrameCaptureOutputSettings$1;)V
       9: areturn

  public java.util.List<software.amazon.awssdk.core.SdkField<?>> sdkFields();
    Code:
       0: invokestatic  #9                  // Method software/amazon/awssdk/services/medialive/model/FrameCaptureOutputSettings.access$500:()Ljava/util/List;
       3: areturn

  public java.lang.Object build();
    Code:
       0: aload_0
       1: invokevirtual #10                 // Method build:()Lsoftware/amazon/awssdk/services/medialive/model/FrameCaptureOutputSettings;
       4: areturn

  static java.lang.String access$000(software.amazon.awssdk.services.medialive.model.FrameCaptureOutputSettings$BuilderImpl);
    Code:
       0: aload_0
       1: getfield      #3                  // Field nameModifier:Ljava/lang/String;
       4: areturn

  software.amazon.awssdk.services.medialive.model.FrameCaptureOutputSettings$BuilderImpl(software.amazon.awssdk.services.medialive.model.FrameCaptureOutputSettings, software.amazon.awssdk.services.medialive.model.FrameCaptureOutputSettings$1);
    Code:
       0: aload_0
       1: aload_1
       2: invokespecial #2                  // Method "<init>":(Lsoftware/amazon/awssdk/services/medialive/model/FrameCaptureOutputSettings;)V
       5: return

  software.amazon.awssdk.services.medialive.model.FrameCaptureOutputSettings$BuilderImpl(software.amazon.awssdk.services.medialive.model.FrameCaptureOutputSettings$1);
    Code:
       0: aload_0
       1: invokespecial #1                  // Method "<init>":()V
       4: return
}
