Compiled from "HlsCdnSettings.java"
public interface software.amazon.awssdk.services.medialive.model.HlsCdnSettings$Builder extends software.amazon.awssdk.core.SdkPojo, software.amazon.awssdk.utils.builder.CopyableBuilder<software.amazon.awssdk.services.medialive.model.HlsCdnSettings$Builder, software.amazon.awssdk.services.medialive.model.HlsCdnSettings> {
  public abstract software.amazon.awssdk.services.medialive.model.HlsCdnSettings$Builder hlsAkamaiSettings(software.amazon.awssdk.services.medialive.model.HlsAkamaiSettings);

  public default software.amazon.awssdk.services.medialive.model.HlsCdnSettings$Builder hlsAkamaiSettings(java.util.function.Consumer<software.amazon.awssdk.services.medialive.model.HlsAkamaiSettings$Builder>);
    Code:
       0: aload_0
       1: invokestatic  #1                  // Method software/amazon/awssdk/services/medialive/model/HlsAkamaiSettings.builder:()Lsoftware/amazon/awssdk/services/medialive/model/HlsAkamaiSettings$Builder;
       4: aload_1
       5: invokeinterface #2,  2            // InterfaceMethod software/amazon/awssdk/services/medialive/model/HlsAkamaiSettings$Builder.applyMutation:(Ljava/util/function/Consumer;)Lsoftware/amazon/awssdk/utils/builder/SdkBuilder;
      10: checkcast     #3                  // class software/amazon/awssdk/services/medialive/model/HlsAkamaiSettings$Builder
      13: invokeinterface #4,  1            // InterfaceMethod software/amazon/awssdk/services/medialive/model/HlsAkamaiSettings$Builder.build:()Ljava/lang/Object;
      18: checkcast     #5                  // class software/amazon/awssdk/services/medialive/model/HlsAkamaiSettings
      21: invokeinterface #6,  2            // InterfaceMethod hlsAkamaiSettings:(Lsoftware/amazon/awssdk/services/medialive/model/HlsAkamaiSettings;)Lsoftware/amazon/awssdk/services/medialive/model/HlsCdnSettings$Builder;
      26: areturn

  public abstract software.amazon.awssdk.services.medialive.model.HlsCdnSettings$Builder hlsBasicPutSettings(software.amazon.awssdk.services.medialive.model.HlsBasicPutSettings);

  public default software.amazon.awssdk.services.medialive.model.HlsCdnSettings$Builder hlsBasicPutSettings(java.util.function.Consumer<software.amazon.awssdk.services.medialive.model.HlsBasicPutSettings$Builder>);
    Code:
       0: aload_0
       1: invokestatic  #7                  // Method software/amazon/awssdk/services/medialive/model/HlsBasicPutSettings.builder:()Lsoftware/amazon/awssdk/services/medialive/model/HlsBasicPutSettings$Builder;
       4: aload_1
       5: invokeinterface #8,  2            // InterfaceMethod software/amazon/awssdk/services/medialive/model/HlsBasicPutSettings$Builder.applyMutation:(Ljava/util/function/Consumer;)Lsoftware/amazon/awssdk/utils/builder/SdkBuilder;
      10: checkcast     #9                  // class software/amazon/awssdk/services/medialive/model/HlsBasicPutSettings$Builder
      13: invokeinterface #10,  1           // InterfaceMethod software/amazon/awssdk/services/medialive/model/HlsBasicPutSettings$Builder.build:()Ljava/lang/Object;
      18: checkcast     #11                 // class software/amazon/awssdk/services/medialive/model/HlsBasicPutSettings
      21: invokeinterface #12,  2           // InterfaceMethod hlsBasicPutSettings:(Lsoftware/amazon/awssdk/services/medialive/model/HlsBasicPutSettings;)Lsoftware/amazon/awssdk/services/medialive/model/HlsCdnSettings$Builder;
      26: areturn

  public abstract software.amazon.awssdk.services.medialive.model.HlsCdnSettings$Builder hlsMediaStoreSettings(software.amazon.awssdk.services.medialive.model.HlsMediaStoreSettings);

  public default software.amazon.awssdk.services.medialive.model.HlsCdnSettings$Builder hlsMediaStoreSettings(java.util.function.Consumer<software.amazon.awssdk.services.medialive.model.HlsMediaStoreSettings$Builder>);
    Code:
       0: aload_0
       1: invokestatic  #13                 // Method software/amazon/awssdk/services/medialive/model/HlsMediaStoreSettings.builder:()Lsoftware/amazon/awssdk/services/medialive/model/HlsMediaStoreSettings$Builder;
       4: aload_1
       5: invokeinterface #14,  2           // InterfaceMethod software/amazon/awssdk/services/medialive/model/HlsMediaStoreSettings$Builder.applyMutation:(Ljava/util/function/Consumer;)Lsoftware/amazon/awssdk/utils/builder/SdkBuilder;
      10: checkcast     #15                 // class software/amazon/awssdk/services/medialive/model/HlsMediaStoreSettings$Builder
      13: invokeinterface #16,  1           // InterfaceMethod software/amazon/awssdk/services/medialive/model/HlsMediaStoreSettings$Builder.build:()Ljava/lang/Object;
      18: checkcast     #17                 // class software/amazon/awssdk/services/medialive/model/HlsMediaStoreSettings
      21: invokeinterface #18,  2           // InterfaceMethod hlsMediaStoreSettings:(Lsoftware/amazon/awssdk/services/medialive/model/HlsMediaStoreSettings;)Lsoftware/amazon/awssdk/services/medialive/model/HlsCdnSettings$Builder;
      26: areturn

  public abstract software.amazon.awssdk.services.medialive.model.HlsCdnSettings$Builder hlsWebdavSettings(software.amazon.awssdk.services.medialive.model.HlsWebdavSettings);

  public default software.amazon.awssdk.services.medialive.model.HlsCdnSettings$Builder hlsWebdavSettings(java.util.function.Consumer<software.amazon.awssdk.services.medialive.model.HlsWebdavSettings$Builder>);
    Code:
       0: aload_0
       1: invokestatic  #19                 // Method software/amazon/awssdk/services/medialive/model/HlsWebdavSettings.builder:()Lsoftware/amazon/awssdk/services/medialive/model/HlsWebdavSettings$Builder;
       4: aload_1
       5: invokeinterface #20,  2           // InterfaceMethod software/amazon/awssdk/services/medialive/model/HlsWebdavSettings$Builder.applyMutation:(Ljava/util/function/Consumer;)Lsoftware/amazon/awssdk/utils/builder/SdkBuilder;
      10: checkcast     #21                 // class software/amazon/awssdk/services/medialive/model/HlsWebdavSettings$Builder
      13: invokeinterface #22,  1           // InterfaceMethod software/amazon/awssdk/services/medialive/model/HlsWebdavSettings$Builder.build:()Ljava/lang/Object;
      18: checkcast     #23                 // class software/amazon/awssdk/services/medialive/model/HlsWebdavSettings
      21: invokeinterface #24,  2           // InterfaceMethod hlsWebdavSettings:(Lsoftware/amazon/awssdk/services/medialive/model/HlsWebdavSettings;)Lsoftware/amazon/awssdk/services/medialive/model/HlsCdnSettings$Builder;
      26: areturn
}
