Compiled from "InputSwitchScheduleActionSettings.java"
final class software.amazon.awssdk.services.medialive.model.InputSwitchScheduleActionSettings$BuilderImpl implements software.amazon.awssdk.services.medialive.model.InputSwitchScheduleActionSettings$Builder {
  private java.lang.String inputAttachmentNameReference;

  private software.amazon.awssdk.services.medialive.model.InputClippingSettings inputClippingSettings;

  private java.util.List<java.lang.String> urlPath;

  private software.amazon.awssdk.services.medialive.model.InputSwitchScheduleActionSettings$BuilderImpl();
    Code:
       0: aload_0
       1: invokespecial #6                  // Method java/lang/Object."<init>":()V
       4: aload_0
       5: invokestatic  #7                  // Method software/amazon/awssdk/core/util/DefaultSdkAutoConstructList.getInstance:()Lsoftware/amazon/awssdk/core/util/DefaultSdkAutoConstructList;
       8: putfield      #3                  // Field urlPath:Ljava/util/List;
      11: return

  private software.amazon.awssdk.services.medialive.model.InputSwitchScheduleActionSettings$BuilderImpl(software.amazon.awssdk.services.medialive.model.InputSwitchScheduleActionSettings);
    Code:
       0: aload_0
       1: invokespecial #6                  // Method java/lang/Object."<init>":()V
       4: aload_0
       5: invokestatic  #7                  // Method software/amazon/awssdk/core/util/DefaultSdkAutoConstructList.getInstance:()Lsoftware/amazon/awssdk/core/util/DefaultSdkAutoConstructList;
       8: putfield      #3                  // Field urlPath:Ljava/util/List;
      11: aload_0
      12: aload_1
      13: invokestatic  #8                  // Method software/amazon/awssdk/services/medialive/model/InputSwitchScheduleActionSettings.access$500:(Lsoftware/amazon/awssdk/services/medialive/model/InputSwitchScheduleActionSettings;)Ljava/lang/String;
      16: invokevirtual #9                  // Method inputAttachmentNameReference:(Ljava/lang/String;)Lsoftware/amazon/awssdk/services/medialive/model/InputSwitchScheduleActionSettings$Builder;
      19: pop
      20: aload_0
      21: aload_1
      22: invokestatic  #10                 // Method software/amazon/awssdk/services/medialive/model/InputSwitchScheduleActionSettings.access$600:(Lsoftware/amazon/awssdk/services/medialive/model/InputSwitchScheduleActionSettings;)Lsoftware/amazon/awssdk/services/medialive/model/InputClippingSettings;
      25: invokevirtual #11                 // Method inputClippingSettings:(Lsoftware/amazon/awssdk/services/medialive/model/InputClippingSettings;)Lsoftware/amazon/awssdk/services/medialive/model/InputSwitchScheduleActionSettings$Builder;
      28: pop
      29: aload_0
      30: aload_1
      31: invokestatic  #12                 // Method software/amazon/awssdk/services/medialive/model/InputSwitchScheduleActionSettings.access$700:(Lsoftware/amazon/awssdk/services/medialive/model/InputSwitchScheduleActionSettings;)Ljava/util/List;
      34: invokevirtual #13                 // Method urlPath:(Ljava/util/Collection;)Lsoftware/amazon/awssdk/services/medialive/model/InputSwitchScheduleActionSettings$Builder;
      37: pop
      38: return

  public final java.lang.String getInputAttachmentNameReference();
    Code:
       0: aload_0
       1: getfield      #5                  // Field inputAttachmentNameReference:Ljava/lang/String;
       4: areturn

  public final software.amazon.awssdk.services.medialive.model.InputSwitchScheduleActionSettings$Builder inputAttachmentNameReference(java.lang.String);
    Code:
       0: aload_0
       1: aload_1
       2: putfield      #5                  // Field inputAttachmentNameReference:Ljava/lang/String;
       5: aload_0
       6: areturn

  public final void setInputAttachmentNameReference(java.lang.String);
    Code:
       0: aload_0
       1: aload_1
       2: putfield      #5                  // Field inputAttachmentNameReference:Ljava/lang/String;
       5: return

  public final software.amazon.awssdk.services.medialive.model.InputClippingSettings$Builder getInputClippingSettings();
    Code:
       0: aload_0
       1: getfield      #4                  // Field inputClippingSettings:Lsoftware/amazon/awssdk/services/medialive/model/InputClippingSettings;
       4: ifnull        17
       7: aload_0
       8: getfield      #4                  // Field inputClippingSettings:Lsoftware/amazon/awssdk/services/medialive/model/InputClippingSettings;
      11: invokevirtual #14                 // Method software/amazon/awssdk/services/medialive/model/InputClippingSettings.toBuilder:()Lsoftware/amazon/awssdk/services/medialive/model/InputClippingSettings$Builder;
      14: goto          18
      17: aconst_null
      18: areturn

  public final software.amazon.awssdk.services.medialive.model.InputSwitchScheduleActionSettings$Builder inputClippingSettings(software.amazon.awssdk.services.medialive.model.InputClippingSettings);
    Code:
       0: aload_0
       1: aload_1
       2: putfield      #4                  // Field inputClippingSettings:Lsoftware/amazon/awssdk/services/medialive/model/InputClippingSettings;
       5: aload_0
       6: areturn

  public final void setInputClippingSettings(software.amazon.awssdk.services.medialive.model.InputClippingSettings$BuilderImpl);
    Code:
       0: aload_0
       1: aload_1
       2: ifnull        12
       5: aload_1
       6: invokevirtual #15                 // Method software/amazon/awssdk/services/medialive/model/InputClippingSettings$BuilderImpl.build:()Lsoftware/amazon/awssdk/services/medialive/model/InputClippingSettings;
       9: goto          13
      12: aconst_null
      13: putfield      #4                  // Field inputClippingSettings:Lsoftware/amazon/awssdk/services/medialive/model/InputClippingSettings;
      16: return

  public final java.util.Collection<java.lang.String> getUrlPath();
    Code:
       0: aload_0
       1: getfield      #3                  // Field urlPath:Ljava/util/List;
       4: areturn

  public final software.amazon.awssdk.services.medialive.model.InputSwitchScheduleActionSettings$Builder urlPath(java.util.Collection<java.lang.String>);
    Code:
       0: aload_0
       1: aload_1
       2: invokestatic  #16                 // Method software/amazon/awssdk/services/medialive/model/___listOf__stringCopier.copy:(Ljava/util/Collection;)Ljava/util/List;
       5: putfield      #3                  // Field urlPath:Ljava/util/List;
       8: aload_0
       9: areturn

  public final software.amazon.awssdk.services.medialive.model.InputSwitchScheduleActionSettings$Builder urlPath(java.lang.String...);
    Code:
       0: aload_0
       1: aload_1
       2: invokestatic  #17                 // Method java/util/Arrays.asList:([Ljava/lang/Object;)Ljava/util/List;
       5: invokevirtual #13                 // Method urlPath:(Ljava/util/Collection;)Lsoftware/amazon/awssdk/services/medialive/model/InputSwitchScheduleActionSettings$Builder;
       8: pop
       9: aload_0
      10: areturn

  public final void setUrlPath(java.util.Collection<java.lang.String>);
    Code:
       0: aload_0
       1: aload_1
       2: invokestatic  #16                 // Method software/amazon/awssdk/services/medialive/model/___listOf__stringCopier.copy:(Ljava/util/Collection;)Ljava/util/List;
       5: putfield      #3                  // Field urlPath:Ljava/util/List;
       8: return

  public software.amazon.awssdk.services.medialive.model.InputSwitchScheduleActionSettings build();
    Code:
       0: new           #18                 // class software/amazon/awssdk/services/medialive/model/InputSwitchScheduleActionSettings
       3: dup
       4: aload_0
       5: aconst_null
       6: invokespecial #19                 // Method software/amazon/awssdk/services/medialive/model/InputSwitchScheduleActionSettings."<init>":(Lsoftware/amazon/awssdk/services/medialive/model/InputSwitchScheduleActionSettings$BuilderImpl;Lsoftware/amazon/awssdk/services/medialive/model/InputSwitchScheduleActionSettings$1;)V
       9: areturn

  public java.util.List<software.amazon.awssdk.core.SdkField<?>> sdkFields();
    Code:
       0: invokestatic  #20                 // Method software/amazon/awssdk/services/medialive/model/InputSwitchScheduleActionSettings.access$900:()Ljava/util/List;
       3: areturn

  public java.lang.Object build();
    Code:
       0: aload_0
       1: invokevirtual #21                 // Method build:()Lsoftware/amazon/awssdk/services/medialive/model/InputSwitchScheduleActionSettings;
       4: areturn

  static java.lang.String access$000(software.amazon.awssdk.services.medialive.model.InputSwitchScheduleActionSettings$BuilderImpl);
    Code:
       0: aload_0
       1: getfield      #5                  // Field inputAttachmentNameReference:Ljava/lang/String;
       4: areturn

  static software.amazon.awssdk.services.medialive.model.InputClippingSettings access$100(software.amazon.awssdk.services.medialive.model.InputSwitchScheduleActionSettings$BuilderImpl);
    Code:
       0: aload_0
       1: getfield      #4                  // Field inputClippingSettings:Lsoftware/amazon/awssdk/services/medialive/model/InputClippingSettings;
       4: areturn

  static java.util.List access$200(software.amazon.awssdk.services.medialive.model.InputSwitchScheduleActionSettings$BuilderImpl);
    Code:
       0: aload_0
       1: getfield      #3                  // Field urlPath:Ljava/util/List;
       4: areturn

  software.amazon.awssdk.services.medialive.model.InputSwitchScheduleActionSettings$BuilderImpl(software.amazon.awssdk.services.medialive.model.InputSwitchScheduleActionSettings, software.amazon.awssdk.services.medialive.model.InputSwitchScheduleActionSettings$1);
    Code:
       0: aload_0
       1: aload_1
       2: invokespecial #2                  // Method "<init>":(Lsoftware/amazon/awssdk/services/medialive/model/InputSwitchScheduleActionSettings;)V
       5: return

  software.amazon.awssdk.services.medialive.model.InputSwitchScheduleActionSettings$BuilderImpl(software.amazon.awssdk.services.medialive.model.InputSwitchScheduleActionSettings$1);
    Code:
       0: aload_0
       1: invokespecial #1                  // Method "<init>":()V
       4: return
}
