Compiled from "OutputDestinationSettings.java"
final class software.amazon.awssdk.services.medialive.model.OutputDestinationSettings$BuilderImpl implements software.amazon.awssdk.services.medialive.model.OutputDestinationSettings$Builder {
  private java.lang.String passwordParam;

  private java.lang.String streamName;

  private java.lang.String url;

  private java.lang.String username;

  private software.amazon.awssdk.services.medialive.model.OutputDestinationSettings$BuilderImpl();
    Code:
       0: aload_0
       1: invokespecial #7                  // Method java/lang/Object."<init>":()V
       4: return

  private software.amazon.awssdk.services.medialive.model.OutputDestinationSettings$BuilderImpl(software.amazon.awssdk.services.medialive.model.OutputDestinationSettings);
    Code:
       0: aload_0
       1: invokespecial #7                  // Method java/lang/Object."<init>":()V
       4: aload_0
       5: aload_1
       6: invokestatic  #8                  // Method software/amazon/awssdk/services/medialive/model/OutputDestinationSettings.access$600:(Lsoftware/amazon/awssdk/services/medialive/model/OutputDestinationSettings;)Ljava/lang/String;
       9: invokevirtual #9                  // Method passwordParam:(Ljava/lang/String;)Lsoftware/amazon/awssdk/services/medialive/model/OutputDestinationSettings$Builder;
      12: pop
      13: aload_0
      14: aload_1
      15: invokestatic  #10                 // Method software/amazon/awssdk/services/medialive/model/OutputDestinationSettings.access$700:(Lsoftware/amazon/awssdk/services/medialive/model/OutputDestinationSettings;)Ljava/lang/String;
      18: invokevirtual #11                 // Method streamName:(Ljava/lang/String;)Lsoftware/amazon/awssdk/services/medialive/model/OutputDestinationSettings$Builder;
      21: pop
      22: aload_0
      23: aload_1
      24: invokestatic  #12                 // Method software/amazon/awssdk/services/medialive/model/OutputDestinationSettings.access$800:(Lsoftware/amazon/awssdk/services/medialive/model/OutputDestinationSettings;)Ljava/lang/String;
      27: invokevirtual #13                 // Method url:(Ljava/lang/String;)Lsoftware/amazon/awssdk/services/medialive/model/OutputDestinationSettings$Builder;
      30: pop
      31: aload_0
      32: aload_1
      33: invokestatic  #14                 // Method software/amazon/awssdk/services/medialive/model/OutputDestinationSettings.access$900:(Lsoftware/amazon/awssdk/services/medialive/model/OutputDestinationSettings;)Ljava/lang/String;
      36: invokevirtual #15                 // Method username:(Ljava/lang/String;)Lsoftware/amazon/awssdk/services/medialive/model/OutputDestinationSettings$Builder;
      39: pop
      40: return

  public final java.lang.String getPasswordParam();
    Code:
       0: aload_0
       1: getfield      #6                  // Field passwordParam:Ljava/lang/String;
       4: areturn

  public final software.amazon.awssdk.services.medialive.model.OutputDestinationSettings$Builder passwordParam(java.lang.String);
    Code:
       0: aload_0
       1: aload_1
       2: putfield      #6                  // Field passwordParam:Ljava/lang/String;
       5: aload_0
       6: areturn

  public final void setPasswordParam(java.lang.String);
    Code:
       0: aload_0
       1: aload_1
       2: putfield      #6                  // Field passwordParam:Ljava/lang/String;
       5: return

  public final java.lang.String getStreamName();
    Code:
       0: aload_0
       1: getfield      #5                  // Field streamName:Ljava/lang/String;
       4: areturn

  public final software.amazon.awssdk.services.medialive.model.OutputDestinationSettings$Builder streamName(java.lang.String);
    Code:
       0: aload_0
       1: aload_1
       2: putfield      #5                  // Field streamName:Ljava/lang/String;
       5: aload_0
       6: areturn

  public final void setStreamName(java.lang.String);
    Code:
       0: aload_0
       1: aload_1
       2: putfield      #5                  // Field streamName:Ljava/lang/String;
       5: return

  public final java.lang.String getUrl();
    Code:
       0: aload_0
       1: getfield      #4                  // Field url:Ljava/lang/String;
       4: areturn

  public final software.amazon.awssdk.services.medialive.model.OutputDestinationSettings$Builder url(java.lang.String);
    Code:
       0: aload_0
       1: aload_1
       2: putfield      #4                  // Field url:Ljava/lang/String;
       5: aload_0
       6: areturn

  public final void setUrl(java.lang.String);
    Code:
       0: aload_0
       1: aload_1
       2: putfield      #4                  // Field url:Ljava/lang/String;
       5: return

  public final java.lang.String getUsername();
    Code:
       0: aload_0
       1: getfield      #3                  // Field username:Ljava/lang/String;
       4: areturn

  public final software.amazon.awssdk.services.medialive.model.OutputDestinationSettings$Builder username(java.lang.String);
    Code:
       0: aload_0
       1: aload_1
       2: putfield      #3                  // Field username:Ljava/lang/String;
       5: aload_0
       6: areturn

  public final void setUsername(java.lang.String);
    Code:
       0: aload_0
       1: aload_1
       2: putfield      #3                  // Field username:Ljava/lang/String;
       5: return

  public software.amazon.awssdk.services.medialive.model.OutputDestinationSettings build();
    Code:
       0: new           #16                 // class software/amazon/awssdk/services/medialive/model/OutputDestinationSettings
       3: dup
       4: aload_0
       5: aconst_null
       6: invokespecial #17                 // Method software/amazon/awssdk/services/medialive/model/OutputDestinationSettings."<init>":(Lsoftware/amazon/awssdk/services/medialive/model/OutputDestinationSettings$BuilderImpl;Lsoftware/amazon/awssdk/services/medialive/model/OutputDestinationSettings$1;)V
       9: areturn

  public java.util.List<software.amazon.awssdk.core.SdkField<?>> sdkFields();
    Code:
       0: invokestatic  #18                 // Method software/amazon/awssdk/services/medialive/model/OutputDestinationSettings.access$1100:()Ljava/util/List;
       3: areturn

  public java.lang.Object build();
    Code:
       0: aload_0
       1: invokevirtual #19                 // Method build:()Lsoftware/amazon/awssdk/services/medialive/model/OutputDestinationSettings;
       4: areturn

  static java.lang.String access$000(software.amazon.awssdk.services.medialive.model.OutputDestinationSettings$BuilderImpl);
    Code:
       0: aload_0
       1: getfield      #6                  // Field passwordParam:Ljava/lang/String;
       4: areturn

  static java.lang.String access$100(software.amazon.awssdk.services.medialive.model.OutputDestinationSettings$BuilderImpl);
    Code:
       0: aload_0
       1: getfield      #5                  // Field streamName:Ljava/lang/String;
       4: areturn

  static java.lang.String access$200(software.amazon.awssdk.services.medialive.model.OutputDestinationSettings$BuilderImpl);
    Code:
       0: aload_0
       1: getfield      #4                  // Field url:Ljava/lang/String;
       4: areturn

  static java.lang.String access$300(software.amazon.awssdk.services.medialive.model.OutputDestinationSettings$BuilderImpl);
    Code:
       0: aload_0
       1: getfield      #3                  // Field username:Ljava/lang/String;
       4: areturn

  software.amazon.awssdk.services.medialive.model.OutputDestinationSettings$BuilderImpl(software.amazon.awssdk.services.medialive.model.OutputDestinationSettings, software.amazon.awssdk.services.medialive.model.OutputDestinationSettings$1);
    Code:
       0: aload_0
       1: aload_1
       2: invokespecial #2                  // Method "<init>":(Lsoftware/amazon/awssdk/services/medialive/model/OutputDestinationSettings;)V
       5: return

  software.amazon.awssdk.services.medialive.model.OutputDestinationSettings$BuilderImpl(software.amazon.awssdk.services.medialive.model.OutputDestinationSettings$1);
    Code:
       0: aload_0
       1: invokespecial #1                  // Method "<init>":()V
       4: return
}
