Compiled from "StaticImageDeactivateScheduleActionSettings.java"
final class software.amazon.awssdk.services.medialive.model.StaticImageDeactivateScheduleActionSettings$BuilderImpl implements software.amazon.awssdk.services.medialive.model.StaticImageDeactivateScheduleActionSettings$Builder {
  private java.lang.Integer fadeOut;

  private java.lang.Integer layer;

  private software.amazon.awssdk.services.medialive.model.StaticImageDeactivateScheduleActionSettings$BuilderImpl();
    Code:
       0: aload_0
       1: invokespecial #5                  // Method java/lang/Object."<init>":()V
       4: return

  private software.amazon.awssdk.services.medialive.model.StaticImageDeactivateScheduleActionSettings$BuilderImpl(software.amazon.awssdk.services.medialive.model.StaticImageDeactivateScheduleActionSettings);
    Code:
       0: aload_0
       1: invokespecial #5                  // Method java/lang/Object."<init>":()V
       4: aload_0
       5: aload_1
       6: invokestatic  #6                  // Method software/amazon/awssdk/services/medialive/model/StaticImageDeactivateScheduleActionSettings.access$400:(Lsoftware/amazon/awssdk/services/medialive/model/StaticImageDeactivateScheduleActionSettings;)Ljava/lang/Integer;
       9: invokevirtual #7                  // Method fadeOut:(Ljava/lang/Integer;)Lsoftware/amazon/awssdk/services/medialive/model/StaticImageDeactivateScheduleActionSettings$Builder;
      12: pop
      13: aload_0
      14: aload_1
      15: invokestatic  #8                  // Method software/amazon/awssdk/services/medialive/model/StaticImageDeactivateScheduleActionSettings.access$500:(Lsoftware/amazon/awssdk/services/medialive/model/StaticImageDeactivateScheduleActionSettings;)Ljava/lang/Integer;
      18: invokevirtual #9                  // Method layer:(Ljava/lang/Integer;)Lsoftware/amazon/awssdk/services/medialive/model/StaticImageDeactivateScheduleActionSettings$Builder;
      21: pop
      22: return

  public final java.lang.Integer getFadeOut();
    Code:
       0: aload_0
       1: getfield      #4                  // Field fadeOut:Ljava/lang/Integer;
       4: areturn

  public final software.amazon.awssdk.services.medialive.model.StaticImageDeactivateScheduleActionSettings$Builder fadeOut(java.lang.Integer);
    Code:
       0: aload_0
       1: aload_1
       2: putfield      #4                  // Field fadeOut:Ljava/lang/Integer;
       5: aload_0
       6: areturn

  public final void setFadeOut(java.lang.Integer);
    Code:
       0: aload_0
       1: aload_1
       2: putfield      #4                  // Field fadeOut:Ljava/lang/Integer;
       5: return

  public final java.lang.Integer getLayer();
    Code:
       0: aload_0
       1: getfield      #3                  // Field layer:Ljava/lang/Integer;
       4: areturn

  public final software.amazon.awssdk.services.medialive.model.StaticImageDeactivateScheduleActionSettings$Builder layer(java.lang.Integer);
    Code:
       0: aload_0
       1: aload_1
       2: putfield      #3                  // Field layer:Ljava/lang/Integer;
       5: aload_0
       6: areturn

  public final void setLayer(java.lang.Integer);
    Code:
       0: aload_0
       1: aload_1
       2: putfield      #3                  // Field layer:Ljava/lang/Integer;
       5: return

  public software.amazon.awssdk.services.medialive.model.StaticImageDeactivateScheduleActionSettings build();
    Code:
       0: new           #10                 // class software/amazon/awssdk/services/medialive/model/StaticImageDeactivateScheduleActionSettings
       3: dup
       4: aload_0
       5: aconst_null
       6: invokespecial #11                 // Method software/amazon/awssdk/services/medialive/model/StaticImageDeactivateScheduleActionSettings."<init>":(Lsoftware/amazon/awssdk/services/medialive/model/StaticImageDeactivateScheduleActionSettings$BuilderImpl;Lsoftware/amazon/awssdk/services/medialive/model/StaticImageDeactivateScheduleActionSettings$1;)V
       9: areturn

  public java.util.List<software.amazon.awssdk.core.SdkField<?>> sdkFields();
    Code:
       0: invokestatic  #12                 // Method software/amazon/awssdk/services/medialive/model/StaticImageDeactivateScheduleActionSettings.access$700:()Ljava/util/List;
       3: areturn

  public java.lang.Object build();
    Code:
       0: aload_0
       1: invokevirtual #13                 // Method build:()Lsoftware/amazon/awssdk/services/medialive/model/StaticImageDeactivateScheduleActionSettings;
       4: areturn

  static java.lang.Integer access$000(software.amazon.awssdk.services.medialive.model.StaticImageDeactivateScheduleActionSettings$BuilderImpl);
    Code:
       0: aload_0
       1: getfield      #4                  // Field fadeOut:Ljava/lang/Integer;
       4: areturn

  static java.lang.Integer access$100(software.amazon.awssdk.services.medialive.model.StaticImageDeactivateScheduleActionSettings$BuilderImpl);
    Code:
       0: aload_0
       1: getfield      #3                  // Field layer:Ljava/lang/Integer;
       4: areturn

  software.amazon.awssdk.services.medialive.model.StaticImageDeactivateScheduleActionSettings$BuilderImpl(software.amazon.awssdk.services.medialive.model.StaticImageDeactivateScheduleActionSettings, software.amazon.awssdk.services.medialive.model.StaticImageDeactivateScheduleActionSettings$1);
    Code:
       0: aload_0
       1: aload_1
       2: invokespecial #2                  // Method "<init>":(Lsoftware/amazon/awssdk/services/medialive/model/StaticImageDeactivateScheduleActionSettings;)V
       5: return

  software.amazon.awssdk.services.medialive.model.StaticImageDeactivateScheduleActionSettings$BuilderImpl(software.amazon.awssdk.services.medialive.model.StaticImageDeactivateScheduleActionSettings$1);
    Code:
       0: aload_0
       1: invokespecial #1                  // Method "<init>":()V
       4: return
}
