Compiled from "UdpContainerSettings.java"
public interface software.amazon.awssdk.services.medialive.model.UdpContainerSettings$Builder extends software.amazon.awssdk.core.SdkPojo, software.amazon.awssdk.utils.builder.CopyableBuilder<software.amazon.awssdk.services.medialive.model.UdpContainerSettings$Builder, software.amazon.awssdk.services.medialive.model.UdpContainerSettings> {
  public abstract software.amazon.awssdk.services.medialive.model.UdpContainerSettings$Builder m2tsSettings(software.amazon.awssdk.services.medialive.model.M2tsSettings);

  public default software.amazon.awssdk.services.medialive.model.UdpContainerSettings$Builder m2tsSettings(java.util.function.Consumer<software.amazon.awssdk.services.medialive.model.M2tsSettings$Builder>);
    Code:
       0: aload_0
       1: invokestatic  #1                  // Method software/amazon/awssdk/services/medialive/model/M2tsSettings.builder:()Lsoftware/amazon/awssdk/services/medialive/model/M2tsSettings$Builder;
       4: aload_1
       5: invokeinterface #2,  2            // InterfaceMethod software/amazon/awssdk/services/medialive/model/M2tsSettings$Builder.applyMutation:(Ljava/util/function/Consumer;)Lsoftware/amazon/awssdk/utils/builder/SdkBuilder;
      10: checkcast     #3                  // class software/amazon/awssdk/services/medialive/model/M2tsSettings$Builder
      13: invokeinterface #4,  1            // InterfaceMethod software/amazon/awssdk/services/medialive/model/M2tsSettings$Builder.build:()Ljava/lang/Object;
      18: checkcast     #5                  // class software/amazon/awssdk/services/medialive/model/M2tsSettings
      21: invokeinterface #6,  2            // InterfaceMethod m2tsSettings:(Lsoftware/amazon/awssdk/services/medialive/model/M2tsSettings;)Lsoftware/amazon/awssdk/services/medialive/model/UdpContainerSettings$Builder;
      26: areturn
}
