Compiled from "UpdateChannelResponse.java"
final class software.amazon.awssdk.services.medialive.model.UpdateChannelResponse$BuilderImpl extends software.amazon.awssdk.services.medialive.model.MediaLiveResponse$BuilderImpl implements software.amazon.awssdk.services.medialive.model.UpdateChannelResponse$Builder {
  private software.amazon.awssdk.services.medialive.model.Channel channel;

  private software.amazon.awssdk.services.medialive.model.UpdateChannelResponse$BuilderImpl();
    Code:
       0: aload_0
       1: invokespecial #4                  // Method software/amazon/awssdk/services/medialive/model/MediaLiveResponse$BuilderImpl."<init>":()V
       4: return

  private software.amazon.awssdk.services.medialive.model.UpdateChannelResponse$BuilderImpl(software.amazon.awssdk.services.medialive.model.UpdateChannelResponse);
    Code:
       0: aload_0
       1: aload_1
       2: invokespecial #5                  // Method software/amazon/awssdk/services/medialive/model/MediaLiveResponse$BuilderImpl."<init>":(Lsoftware/amazon/awssdk/services/medialive/model/MediaLiveResponse;)V
       5: aload_0
       6: aload_1
       7: invokestatic  #6                  // Method software/amazon/awssdk/services/medialive/model/UpdateChannelResponse.access$300:(Lsoftware/amazon/awssdk/services/medialive/model/UpdateChannelResponse;)Lsoftware/amazon/awssdk/services/medialive/model/Channel;
      10: invokevirtual #7                  // Method channel:(Lsoftware/amazon/awssdk/services/medialive/model/Channel;)Lsoftware/amazon/awssdk/services/medialive/model/UpdateChannelResponse$Builder;
      13: pop
      14: return

  public final software.amazon.awssdk.services.medialive.model.Channel$Builder getChannel();
    Code:
       0: aload_0
       1: getfield      #3                  // Field channel:Lsoftware/amazon/awssdk/services/medialive/model/Channel;
       4: ifnull        17
       7: aload_0
       8: getfield      #3                  // Field channel:Lsoftware/amazon/awssdk/services/medialive/model/Channel;
      11: invokevirtual #8                  // Method software/amazon/awssdk/services/medialive/model/Channel.toBuilder:()Lsoftware/amazon/awssdk/services/medialive/model/Channel$Builder;
      14: goto          18
      17: aconst_null
      18: areturn

  public final software.amazon.awssdk.services.medialive.model.UpdateChannelResponse$Builder channel(software.amazon.awssdk.services.medialive.model.Channel);
    Code:
       0: aload_0
       1: aload_1
       2: putfield      #3                  // Field channel:Lsoftware/amazon/awssdk/services/medialive/model/Channel;
       5: aload_0
       6: areturn

  public final void setChannel(software.amazon.awssdk.services.medialive.model.Channel$BuilderImpl);
    Code:
       0: aload_0
       1: aload_1
       2: ifnull        12
       5: aload_1
       6: invokevirtual #9                  // Method software/amazon/awssdk/services/medialive/model/Channel$BuilderImpl.build:()Lsoftware/amazon/awssdk/services/medialive/model/Channel;
       9: goto          13
      12: aconst_null
      13: putfield      #3                  // Field channel:Lsoftware/amazon/awssdk/services/medialive/model/Channel;
      16: return

  public software.amazon.awssdk.services.medialive.model.UpdateChannelResponse build();
    Code:
       0: new           #10                 // class software/amazon/awssdk/services/medialive/model/UpdateChannelResponse
       3: dup
       4: aload_0
       5: aconst_null
       6: invokespecial #11                 // Method software/amazon/awssdk/services/medialive/model/UpdateChannelResponse."<init>":(Lsoftware/amazon/awssdk/services/medialive/model/UpdateChannelResponse$BuilderImpl;Lsoftware/amazon/awssdk/services/medialive/model/UpdateChannelResponse$1;)V
       9: areturn

  public java.util.List<software.amazon.awssdk.core.SdkField<?>> sdkFields();
    Code:
       0: invokestatic  #12                 // Method software/amazon/awssdk/services/medialive/model/UpdateChannelResponse.access$500:()Ljava/util/List;
       3: areturn

  public software.amazon.awssdk.services.medialive.model.MediaLiveResponse build();
    Code:
       0: aload_0
       1: invokevirtual #13                 // Method build:()Lsoftware/amazon/awssdk/services/medialive/model/UpdateChannelResponse;
       4: areturn

  public software.amazon.awssdk.awscore.AwsResponse build();
    Code:
       0: aload_0
       1: invokevirtual #13                 // Method build:()Lsoftware/amazon/awssdk/services/medialive/model/UpdateChannelResponse;
       4: areturn

  public software.amazon.awssdk.core.SdkResponse build();
    Code:
       0: aload_0
       1: invokevirtual #13                 // Method build:()Lsoftware/amazon/awssdk/services/medialive/model/UpdateChannelResponse;
       4: areturn

  public java.lang.Object build();
    Code:
       0: aload_0
       1: invokevirtual #13                 // Method build:()Lsoftware/amazon/awssdk/services/medialive/model/UpdateChannelResponse;
       4: areturn

  static software.amazon.awssdk.services.medialive.model.Channel access$000(software.amazon.awssdk.services.medialive.model.UpdateChannelResponse$BuilderImpl);
    Code:
       0: aload_0
       1: getfield      #3                  // Field channel:Lsoftware/amazon/awssdk/services/medialive/model/Channel;
       4: areturn

  software.amazon.awssdk.services.medialive.model.UpdateChannelResponse$BuilderImpl(software.amazon.awssdk.services.medialive.model.UpdateChannelResponse, software.amazon.awssdk.services.medialive.model.UpdateChannelResponse$1);
    Code:
       0: aload_0
       1: aload_1
       2: invokespecial #2                  // Method "<init>":(Lsoftware/amazon/awssdk/services/medialive/model/UpdateChannelResponse;)V
       5: return

  software.amazon.awssdk.services.medialive.model.UpdateChannelResponse$BuilderImpl(software.amazon.awssdk.services.medialive.model.UpdateChannelResponse$1);
    Code:
       0: aload_0
       1: invokespecial #1                  // Method "<init>":()V
       4: return
}
