Compiled from "VideoSelectorSettings.java"
public interface software.amazon.awssdk.services.medialive.model.VideoSelectorSettings$Builder extends software.amazon.awssdk.core.SdkPojo, software.amazon.awssdk.utils.builder.CopyableBuilder<software.amazon.awssdk.services.medialive.model.VideoSelectorSettings$Builder, software.amazon.awssdk.services.medialive.model.VideoSelectorSettings> {
  public abstract software.amazon.awssdk.services.medialive.model.VideoSelectorSettings$Builder videoSelectorPid(software.amazon.awssdk.services.medialive.model.VideoSelectorPid);

  public default software.amazon.awssdk.services.medialive.model.VideoSelectorSettings$Builder videoSelectorPid(java.util.function.Consumer<software.amazon.awssdk.services.medialive.model.VideoSelectorPid$Builder>);
    Code:
       0: aload_0
       1: invokestatic  #1                  // Method software/amazon/awssdk/services/medialive/model/VideoSelectorPid.builder:()Lsoftware/amazon/awssdk/services/medialive/model/VideoSelectorPid$Builder;
       4: aload_1
       5: invokeinterface #2,  2            // InterfaceMethod software/amazon/awssdk/services/medialive/model/VideoSelectorPid$Builder.applyMutation:(Ljava/util/function/Consumer;)Lsoftware/amazon/awssdk/utils/builder/SdkBuilder;
      10: checkcast     #3                  // class software/amazon/awssdk/services/medialive/model/VideoSelectorPid$Builder
      13: invokeinterface #4,  1            // InterfaceMethod software/amazon/awssdk/services/medialive/model/VideoSelectorPid$Builder.build:()Ljava/lang/Object;
      18: checkcast     #5                  // class software/amazon/awssdk/services/medialive/model/VideoSelectorPid
      21: invokeinterface #6,  2            // InterfaceMethod videoSelectorPid:(Lsoftware/amazon/awssdk/services/medialive/model/VideoSelectorPid;)Lsoftware/amazon/awssdk/services/medialive/model/VideoSelectorSettings$Builder;
      26: areturn

  public abstract software.amazon.awssdk.services.medialive.model.VideoSelectorSettings$Builder videoSelectorProgramId(software.amazon.awssdk.services.medialive.model.VideoSelectorProgramId);

  public default software.amazon.awssdk.services.medialive.model.VideoSelectorSettings$Builder videoSelectorProgramId(java.util.function.Consumer<software.amazon.awssdk.services.medialive.model.VideoSelectorProgramId$Builder>);
    Code:
       0: aload_0
       1: invokestatic  #7                  // Method software/amazon/awssdk/services/medialive/model/VideoSelectorProgramId.builder:()Lsoftware/amazon/awssdk/services/medialive/model/VideoSelectorProgramId$Builder;
       4: aload_1
       5: invokeinterface #8,  2            // InterfaceMethod software/amazon/awssdk/services/medialive/model/VideoSelectorProgramId$Builder.applyMutation:(Ljava/util/function/Consumer;)Lsoftware/amazon/awssdk/utils/builder/SdkBuilder;
      10: checkcast     #9                  // class software/amazon/awssdk/services/medialive/model/VideoSelectorProgramId$Builder
      13: invokeinterface #10,  1           // InterfaceMethod software/amazon/awssdk/services/medialive/model/VideoSelectorProgramId$Builder.build:()Ljava/lang/Object;
      18: checkcast     #11                 // class software/amazon/awssdk/services/medialive/model/VideoSelectorProgramId
      21: invokeinterface #12,  2           // InterfaceMethod videoSelectorProgramId:(Lsoftware/amazon/awssdk/services/medialive/model/VideoSelectorProgramId;)Lsoftware/amazon/awssdk/services/medialive/model/VideoSelectorSettings$Builder;
      26: areturn
}
