Compiled from "_Sequences.kt"
final class kotlin.sequences.SequencesKt___SequencesKt$zip$1 extends kotlin.jvm.internal.Lambda implements kotlin.jvm.functions.Function2<T, R, kotlin.Pair<? extends T, ? extends R>> {
  public static final kotlin.sequences.SequencesKt___SequencesKt$zip$1 INSTANCE;

  kotlin.sequences.SequencesKt___SequencesKt$zip$1();
    Code:
       0: aload_0
       1: iconst_2
       2: invokespecial #12                 // Method kotlin/jvm/internal/Lambda."<init>":(I)V
       5: return

  public final kotlin.Pair<T, R> invoke(T, R);
    Code:
       0: aload_1
       1: aload_2
       2: invokestatic  #23                 // Method kotlin/TuplesKt.to:(Ljava/lang/Object;Ljava/lang/Object;)Lkotlin/Pair;
       5: areturn

  public java.lang.Object invoke(java.lang.Object, java.lang.Object);
    Code:
       0: aload_0
       1: aload_1
       2: aload_2
       3: invokevirtual #29                 // Method invoke:(Ljava/lang/Object;Ljava/lang/Object;)Lkotlin/Pair;
       6: areturn

  static {};
    Code:
       0: new           #2                  // class kotlin/sequences/SequencesKt___SequencesKt$zip$1
       3: dup
       4: invokespecial #34                 // Method "<init>":()V
       7: putstatic     #37                 // Field INSTANCE:Lkotlin/sequences/SequencesKt___SequencesKt$zip$1;
      10: return
}
