Compiled from "AbstractCamelProducerTemplateFactoryBean.java"
public abstract class org.apache.camel.core.xml.AbstractCamelProducerTemplateFactoryBean extends org.apache.camel.core.xml.AbstractCamelFactoryBean<org.apache.camel.ProducerTemplate> {
  private org.apache.camel.ProducerTemplate template;

  private java.lang.String defaultEndpoint;

  private java.lang.Integer maximumCacheSize;

  public org.apache.camel.core.xml.AbstractCamelProducerTemplateFactoryBean();
    Code:
       0: aload_0
       1: invokespecial #1                  // Method org/apache/camel/core/xml/AbstractCamelFactoryBean."<init>":()V
       4: return

  public org.apache.camel.ProducerTemplate getObject() throws java.lang.Exception;
    Code:
       0: aload_0
       1: invokevirtual #2                  // Method getCamelContext:()Lorg/apache/camel/CamelContext;
       4: astore_1
       5: aload_0
       6: getfield      #3                  // Field defaultEndpoint:Ljava/lang/String;
       9: ifnull        73
      12: aload_1
      13: aload_0
      14: getfield      #3                  // Field defaultEndpoint:Ljava/lang/String;
      17: invokeinterface #4,  2            // InterfaceMethod org/apache/camel/CamelContext.getEndpoint:(Ljava/lang/String;)Lorg/apache/camel/Endpoint;
      22: astore_2
      23: aload_2
      24: ifnonnull     57
      27: new           #5                  // class java/lang/IllegalArgumentException
      30: dup
      31: new           #6                  // class java/lang/StringBuilder
      34: dup
      35: invokespecial #7                  // Method java/lang/StringBuilder."<init>":()V
      38: ldc           #8                  // String No endpoint found for URI:
      40: invokevirtual #9                  // Method java/lang/StringBuilder.append:(Ljava/lang/String;)Ljava/lang/StringBuilder;
      43: aload_0
      44: getfield      #3                  // Field defaultEndpoint:Ljava/lang/String;
      47: invokevirtual #9                  // Method java/lang/StringBuilder.append:(Ljava/lang/String;)Ljava/lang/StringBuilder;
      50: invokevirtual #10                 // Method java/lang/StringBuilder.toString:()Ljava/lang/String;
      53: invokespecial #11                 // Method java/lang/IllegalArgumentException."<init>":(Ljava/lang/String;)V
      56: athrow
      57: aload_0
      58: new           #12                 // class org/apache/camel/impl/DefaultProducerTemplate
      61: dup
      62: aload_1
      63: aload_2
      64: invokespecial #13                 // Method org/apache/camel/impl/DefaultProducerTemplate."<init>":(Lorg/apache/camel/CamelContext;Lorg/apache/camel/Endpoint;)V
      67: putfield      #14                 // Field template:Lorg/apache/camel/ProducerTemplate;
      70: goto          85
      73: aload_0
      74: new           #12                 // class org/apache/camel/impl/DefaultProducerTemplate
      77: dup
      78: aload_1
      79: invokespecial #15                 // Method org/apache/camel/impl/DefaultProducerTemplate."<init>":(Lorg/apache/camel/CamelContext;)V
      82: putfield      #14                 // Field template:Lorg/apache/camel/ProducerTemplate;
      85: aload_0
      86: getfield      #16                 // Field maximumCacheSize:Ljava/lang/Integer;
      89: ifnull        108
      92: aload_0
      93: getfield      #14                 // Field template:Lorg/apache/camel/ProducerTemplate;
      96: aload_0
      97: getfield      #16                 // Field maximumCacheSize:Ljava/lang/Integer;
     100: invokevirtual #17                 // Method java/lang/Integer.intValue:()I
     103: invokeinterface #18,  2           // InterfaceMethod org/apache/camel/ProducerTemplate.setMaximumCacheSize:(I)V
     108: aload_0
     109: getfield      #14                 // Field template:Lorg/apache/camel/ProducerTemplate;
     112: invokestatic  #19                 // Method org/apache/camel/util/ServiceHelper.startService:(Lorg/apache/camel/Service;)V
     115: aload_0
     116: getfield      #14                 // Field template:Lorg/apache/camel/ProducerTemplate;
     119: areturn

  public java.lang.Class<org.apache.camel.impl.DefaultProducerTemplate> getObjectType();
    Code:
       0: ldc           #12                 // class org/apache/camel/impl/DefaultProducerTemplate
       2: areturn

  public void destroy() throws java.lang.Exception;
    Code:
       0: aload_0
       1: getfield      #14                 // Field template:Lorg/apache/camel/ProducerTemplate;
       4: invokestatic  #20                 // Method org/apache/camel/util/ServiceHelper.stopService:(Ljava/lang/Object;)V
       7: return

  public java.lang.String getDefaultEndpoint();
    Code:
       0: aload_0
       1: getfield      #3                  // Field defaultEndpoint:Ljava/lang/String;
       4: areturn

  public void setDefaultEndpoint(java.lang.String);
    Code:
       0: aload_0
       1: aload_1
       2: putfield      #3                  // Field defaultEndpoint:Ljava/lang/String;
       5: return

  public java.lang.Integer getMaximumCacheSize();
    Code:
       0: aload_0
       1: getfield      #16                 // Field maximumCacheSize:Ljava/lang/Integer;
       4: areturn

  public void setMaximumCacheSize(java.lang.Integer);
    Code:
       0: aload_0
       1: aload_1
       2: putfield      #16                 // Field maximumCacheSize:Ljava/lang/Integer;
       5: return

  public java.lang.Object getObject() throws java.lang.Exception;
    Code:
       0: aload_0
       1: invokevirtual #21                 // Method getObject:()Lorg/apache/camel/ProducerTemplate;
       4: areturn
}
