Compiled from "TDB.java"
public class org.apache.jena.tdb.TDB {
  private static final java.lang.Object initLock;

  private static volatile boolean initialized;

  public static final java.lang.String tdbIRI;

  public static final java.lang.String tdbParamNS;

  public static final java.lang.String tdbSymbolPrefix;

  private static final org.slf4j.Logger log;

  public static final java.lang.String logLoaderName;

  public static final org.slf4j.Logger logLoader;

  public static final java.lang.String logInfoName;

  public static final org.slf4j.Logger logInfo;

  public static final java.lang.String namespace;

  public static final org.apache.jena.sparql.util.Symbol symUnionDefaultGraph;

  public static final org.apache.jena.sparql.util.Symbol transactionJournalWriteBlockMode;

  private static java.lang.String metadataLocation;

  private static org.apache.jena.sparql.lib.Metadata metadata;

  public static final java.lang.String PATH;

  public static final java.lang.String NAME;

  public static final java.lang.String VERSION;

  public static final java.lang.String BUILD_DATE;

  public org.apache.jena.tdb.TDB();
    Code:
       0: aload_0
       1: invokespecial #1                  // Method java/lang/Object."<init>":()V
       4: return

  public static org.apache.jena.sparql.util.Context getContext();
    Code:
       0: invokestatic  #2                  // Method org/apache/jena/query/ARQ.getContext:()Lorg/apache/jena/sparql/util/Context;
       3: areturn

  public static void closedown();
    Code:
       0: invokestatic  #3                  // Method org/apache/jena/tdb/StoreConnection.reset:()V
       3: return

  public static void setOptimizerWarningFlag(boolean);
    Code:
       0: iload_0
       1: invokestatic  #4                  // Method org/apache/jena/tdb/setup/DatasetBuilderStd.setOptimizerWarningFlag:(Z)V
       4: return

  public static void sync(org.apache.jena.rdf.model.Model);
    Code:
       0: aload_0
       1: instanceof    #5                  // class org/apache/jena/ontology/impl/OntModelImpl
       4: ifeq          20
       7: aload_0
       8: checkcast     #5                  // class org/apache/jena/ontology/impl/OntModelImpl
      11: astore_1
      12: aload_1
      13: invokevirtual #6                  // Method org/apache/jena/ontology/impl/OntModelImpl.getBaseGraph:()Lorg/apache/jena/graph/Graph;
      16: invokestatic  #7                  // Method sync:(Lorg/apache/jena/graph/Graph;)V
      19: return
      20: aload_0
      21: instanceof    #8                  // class org/apache/jena/ontology/OntModel
      24: ifeq          42
      27: aload_0
      28: checkcast     #8                  // class org/apache/jena/ontology/OntModel
      31: astore_1
      32: aload_1
      33: invokeinterface #9,  1            // InterfaceMethod org/apache/jena/ontology/OntModel.getBaseModel:()Lorg/apache/jena/rdf/model/Model;
      38: invokestatic  #10                 // Method sync:(Lorg/apache/jena/rdf/model/Model;)V
      41: return
      42: aload_0
      43: invokeinterface #11,  1           // InterfaceMethod org/apache/jena/rdf/model/Model.getGraph:()Lorg/apache/jena/graph/Graph;
      48: invokestatic  #7                  // Method sync:(Lorg/apache/jena/graph/Graph;)V
      51: return

  public static void sync(org.apache.jena.graph.Graph);
    Code:
       0: aload_0
       1: ifnonnull     5
       4: return
       5: aload_0
       6: instanceof    #12                 // class org/apache/jena/reasoner/InfGraph
       9: ifeq          27
      12: aload_0
      13: checkcast     #12                 // class org/apache/jena/reasoner/InfGraph
      16: astore_1
      17: aload_1
      18: invokeinterface #13,  1           // InterfaceMethod org/apache/jena/reasoner/InfGraph.getRawGraph:()Lorg/apache/jena/graph/Graph;
      23: invokestatic  #7                  // Method sync:(Lorg/apache/jena/graph/Graph;)V
      26: return
      27: aload_0
      28: invokestatic  #14                 // Method syncObject:(Ljava/lang/Object;)V
      31: return

  public static void sync(org.apache.jena.query.Dataset);
    Code:
       0: aload_0
       1: ifnonnull     5
       4: return
       5: aload_0
       6: invokeinterface #15,  1           // InterfaceMethod org/apache/jena/query/Dataset.asDatasetGraph:()Lorg/apache/jena/sparql/core/DatasetGraph;
      11: astore_1
      12: aload_1
      13: invokestatic  #16                 // Method sync:(Lorg/apache/jena/sparql/core/DatasetGraph;)V
      16: return

  public static void sync(org.apache.jena.sparql.core.DatasetGraph);
    Code:
       0: aload_0
       1: ifnonnull     5
       4: return
       5: aload_0
       6: instanceof    #17                 // class org/apache/jena/tdb/store/DatasetGraphTDB
       9: ifeq          17
      12: aload_0
      13: invokestatic  #14                 // Method syncObject:(Ljava/lang/Object;)V
      16: return
      17: aload_0
      18: instanceof    #18                 // class org/apache/jena/tdb/transaction/DatasetGraphTransaction
      21: ifeq          34
      24: aload_0
      25: checkcast     #18                 // class org/apache/jena/tdb/transaction/DatasetGraphTransaction
      28: astore_1
      29: aload_1
      30: invokevirtual #19                 // Method org/apache/jena/tdb/transaction/DatasetGraphTransaction.syncIfNotTransactional:()V
      33: return
      34: aload_0
      35: invokeinterface #20,  1           // InterfaceMethod org/apache/jena/sparql/core/DatasetGraph.getDefaultGraph:()Lorg/apache/jena/graph/Graph;
      40: invokestatic  #7                  // Method sync:(Lorg/apache/jena/graph/Graph;)V
      43: aload_0
      44: invokeinterface #21,  1           // InterfaceMethod org/apache/jena/sparql/core/DatasetGraph.listGraphNodes:()Ljava/util/Iterator;
      49: astore_1
      50: aload_1
      51: invokestatic  #22                 // Method org/apache/jena/atlas/iterator/Iter.toList:(Ljava/util/Iterator;)Ljava/util/List;
      54: invokeinterface #23,  1           // InterfaceMethod java/util/List.iterator:()Ljava/util/Iterator;
      59: astore_1
      60: aload_1
      61: invokeinterface #24,  1           // InterfaceMethod java/util/Iterator.hasNext:()Z
      66: ifeq          94
      69: aload_1
      70: invokeinterface #25,  1           // InterfaceMethod java/util/Iterator.next:()Ljava/lang/Object;
      75: checkcast     #26                 // class org/apache/jena/graph/Node
      78: astore_2
      79: aload_0
      80: aload_2
      81: invokeinterface #27,  2           // InterfaceMethod org/apache/jena/sparql/core/DatasetGraph.getGraph:(Lorg/apache/jena/graph/Node;)Lorg/apache/jena/graph/Graph;
      86: astore_3
      87: aload_3
      88: invokestatic  #7                  // Method sync:(Lorg/apache/jena/graph/Graph;)V
      91: goto          60
      94: return

  private static void syncObject(java.lang.Object);
    Code:
       0: aload_0
       1: ifnonnull     5
       4: return
       5: aload_0
       6: instanceof    #28                 // class org/apache/jena/atlas/lib/Sync
       9: ifeq          21
      12: aload_0
      13: checkcast     #28                 // class org/apache/jena/atlas/lib/Sync
      16: invokeinterface #29,  1           // InterfaceMethod org/apache/jena/atlas/lib/Sync.sync:()V
      21: return

  public static void init();
    Code:
       0: getstatic     #30                 // Field initialized:Z
       3: ifeq          7
       6: return
       7: getstatic     #31                 // Field initLock:Ljava/lang/Object;
      10: dup
      11: astore_0
      12: monitorenter
      13: getstatic     #30                 // Field initialized:Z
      16: ifeq          31
      19: ldc           #32                 // String TDB.init - return
      21: iconst_0
      22: anewarray     #33                 // class java/lang/Object
      25: invokestatic  #34                 // Method org/apache/jena/system/JenaSystem.logLifecycle:(Ljava/lang/String;[Ljava/lang/Object;)V
      28: aload_0
      29: monitorexit
      30: return
      31: iconst_1
      32: putstatic     #30                 // Field initialized:Z
      35: ldc           #35                 // String TDB.init - start
      37: iconst_0
      38: anewarray     #33                 // class java/lang/Object
      41: invokestatic  #34                 // Method org/apache/jena/system/JenaSystem.logLifecycle:(Ljava/lang/String;[Ljava/lang/Object;)V
      44: iconst_1
      45: putstatic     #36                 // Field org/apache/jena/riot/lang/ReaderRIOTRDFXML.RiotUniformCompatibility:Z
      48: invokestatic  #37                 // Method org/apache/jena/tdb/sys/EnvTDB.processGlobalSystemProperties:()V
      51: ldc           #39                 // String tdb
      53: ldc           #40                 // String http://jena.hpl.hp.com/TDB#
      55: invokestatic  #41                 // Method org/apache/jena/sparql/util/MappingRegistry.addPrefixMapping:(Ljava/lang/String;Ljava/lang/String;)V
      58: invokestatic  #42                 // Method org/apache/jena/tdb/assembler/AssemblerTDB.init:()V
      61: invokestatic  #43                 // Method org/apache/jena/tdb/solver/QueryEngineTDB.register:()V
      64: invokestatic  #44                 // Method org/apache/jena/tdb/modify/UpdateEngineTDB.register:()V
      67: ldc           #39                 // String tdb
      69: ldc           #40                 // String http://jena.hpl.hp.com/TDB#
      71: invokestatic  #41                 // Method org/apache/jena/sparql/util/MappingRegistry.addPrefixMapping:(Ljava/lang/String;Ljava/lang/String;)V
      74: invokestatic  #46                 // Method wireIntoExecution:()V
      77: ldc           #47                 // String TDB.init - finish
      79: iconst_0
      80: anewarray     #33                 // class java/lang/Object
      83: invokestatic  #34                 // Method org/apache/jena/system/JenaSystem.logLifecycle:(Ljava/lang/String;[Ljava/lang/Object;)V
      86: aload_0
      87: monitorexit
      88: goto          96
      91: astore_1
      92: aload_0
      93: monitorexit
      94: aload_1
      95: athrow
      96: return
    Exception table:
       from    to  target type
          13    30    91   any
          31    88    91   any
          91    94    91   any

  private static void wireIntoExecution();
    Code:
       0: invokestatic  #2                  // Method org/apache/jena/query/ARQ.getContext:()Lorg/apache/jena/sparql/util/Context;
       3: astore_0
       4: aload_0
       5: invokestatic  #48                 // Method org/apache/jena/sparql/engine/main/StageBuilder.chooseStageGenerator:(Lorg/apache/jena/sparql/util/Context;)Lorg/apache/jena/sparql/engine/main/StageGenerator;
       8: astore_1
       9: new           #49                 // class org/apache/jena/tdb/solver/StageGeneratorDirectTDB
      12: dup
      13: aload_1
      14: invokespecial #50                 // Method org/apache/jena/tdb/solver/StageGeneratorDirectTDB."<init>":(Lorg/apache/jena/sparql/engine/main/StageGenerator;)V
      17: astore_2
      18: invokestatic  #2                  // Method org/apache/jena/query/ARQ.getContext:()Lorg/apache/jena/sparql/util/Context;
      21: aload_2
      22: invokestatic  #51                 // Method org/apache/jena/sparql/engine/main/StageBuilder.setGenerator:(Lorg/apache/jena/sparql/util/Context;Lorg/apache/jena/sparql/engine/main/StageGenerator;)V
      25: return

  private static void initialization2();
    Code:
       0: new           #52                 // class org/apache/jena/sparql/mgt/SystemInfo
       3: dup
       4: ldc           #53                 // String http://jena.hpl.hp.com/#tdb
       6: ldc           #54                 // String org.apache.jena.tdb
       8: getstatic     #55                 // Field VERSION:Ljava/lang/String;
      11: getstatic     #56                 // Field BUILD_DATE:Ljava/lang/String;
      14: invokespecial #57                 // Method org/apache/jena/sparql/mgt/SystemInfo."<init>":(Ljava/lang/String;Ljava/lang/String;Ljava/lang/String;Ljava/lang/String;)V
      17: astore_0
      18: aload_0
      19: invokestatic  #58                 // Method org/apache/jena/sparql/SystemARQ.registerSubSystem:(Lorg/apache/jena/sparql/mgt/SystemInfo;)V
      22: return

  static {};
    Code:
       0: new           #33                 // class java/lang/Object
       3: dup
       4: invokespecial #1                  // Method java/lang/Object."<init>":()V
       7: putstatic     #31                 // Field initLock:Ljava/lang/Object;
      10: iconst_0
      11: putstatic     #30                 // Field initialized:Z
      14: ldc           #45                 // class org/apache/jena/tdb/TDB
      16: invokestatic  #59                 // Method org/slf4j/LoggerFactory.getLogger:(Ljava/lang/Class;)Lorg/slf4j/Logger;
      19: putstatic     #60                 // Field log:Lorg/slf4j/Logger;
      22: ldc           #61                 // String org.apache.jena.tdb.loader
      24: invokestatic  #62                 // Method org/slf4j/LoggerFactory.getLogger:(Ljava/lang/String;)Lorg/slf4j/Logger;
      27: putstatic     #63                 // Field logLoader:Lorg/slf4j/Logger;
      30: ldc           #64                 // String org.apache.jena.info
      32: invokestatic  #62                 // Method org/slf4j/LoggerFactory.getLogger:(Ljava/lang/String;)Lorg/slf4j/Logger;
      35: putstatic     #65                 // Field logInfo:Lorg/slf4j/Logger;
      38: ldc           #66                 // String unionDefaultGraph
      40: invokestatic  #67                 // Method org/apache/jena/tdb/sys/SystemTDB.allocSymbol:(Ljava/lang/String;)Lorg/apache/jena/sparql/util/Symbol;
      43: putstatic     #68                 // Field symUnionDefaultGraph:Lorg/apache/jena/sparql/util/Symbol;
      46: ldc           #69                 // String transactionJournalWriteBlockMode
      48: invokestatic  #67                 // Method org/apache/jena/tdb/sys/SystemTDB.allocSymbol:(Ljava/lang/String;)Lorg/apache/jena/sparql/util/Symbol;
      51: putstatic     #70                 // Field transactionJournalWriteBlockMode:Lorg/apache/jena/sparql/util/Symbol;
      54: ldc           #71                 // String org/apache/jena/tdb/tdb-properties.xml
      56: putstatic     #72                 // Field metadataLocation:Ljava/lang/String;
      59: new           #73                 // class org/apache/jena/sparql/lib/Metadata
      62: dup
      63: getstatic     #72                 // Field metadataLocation:Ljava/lang/String;
      66: invokespecial #74                 // Method org/apache/jena/sparql/lib/Metadata."<init>":(Ljava/lang/String;)V
      69: putstatic     #75                 // Field metadata:Lorg/apache/jena/sparql/lib/Metadata;
      72: getstatic     #75                 // Field metadata:Lorg/apache/jena/sparql/lib/Metadata;
      75: ldc           #76                 // String org.apache.jena.tdb.version
      77: ldc           #77                 // String DEV
      79: invokevirtual #78                 // Method org/apache/jena/sparql/lib/Metadata.get:(Ljava/lang/String;Ljava/lang/String;)Ljava/lang/String;
      82: putstatic     #55                 // Field VERSION:Ljava/lang/String;
      85: getstatic     #75                 // Field metadata:Lorg/apache/jena/sparql/lib/Metadata;
      88: ldc           #79                 // String org.apache.jena.tdb.build.datetime
      90: ldc           #80                 // String unset
      92: invokevirtual #78                 // Method org/apache/jena/sparql/lib/Metadata.get:(Ljava/lang/String;Ljava/lang/String;)Ljava/lang/String;
      95: putstatic     #56                 // Field BUILD_DATE:Ljava/lang/String;
      98: invokestatic  #81                 // Method org/apache/jena/system/JenaSystem.init:()V
     101: invokestatic  #82                 // Method initialization2:()V
     104: return
}
