Compiled from "FileStructure.java"
public final class org.sonar.scanner.protocol.output.FileStructure$Domain extends java.lang.Enum<org.sonar.scanner.protocol.output.FileStructure$Domain> {
  public static final org.sonar.scanner.protocol.output.FileStructure$Domain ISSUES;

  public static final org.sonar.scanner.protocol.output.FileStructure$Domain COMPONENT;

  public static final org.sonar.scanner.protocol.output.FileStructure$Domain MEASURES;

  public static final org.sonar.scanner.protocol.output.FileStructure$Domain DUPLICATIONS;

  public static final org.sonar.scanner.protocol.output.FileStructure$Domain CPD_TEXT_BLOCKS;

  public static final org.sonar.scanner.protocol.output.FileStructure$Domain SYNTAX_HIGHLIGHTINGS;

  public static final org.sonar.scanner.protocol.output.FileStructure$Domain CHANGESETS;

  public static final org.sonar.scanner.protocol.output.FileStructure$Domain SYMBOLS;

  public static final org.sonar.scanner.protocol.output.FileStructure$Domain COVERAGES;

  public static final org.sonar.scanner.protocol.output.FileStructure$Domain TESTS;

  public static final org.sonar.scanner.protocol.output.FileStructure$Domain COVERAGE_DETAILS;

  public static final org.sonar.scanner.protocol.output.FileStructure$Domain SOURCE;

  private static final java.lang.String PB;

  private final java.lang.String filePrefix;

  private final java.lang.String fileSuffix;

  private static final org.sonar.scanner.protocol.output.FileStructure$Domain[] $VALUES;

  public static org.sonar.scanner.protocol.output.FileStructure$Domain[] values();
    Code:
       0: getstatic     #3                  // Field $VALUES:[Lorg/sonar/scanner/protocol/output/FileStructure$Domain;
       3: invokevirtual #4                  // Method "[Lorg/sonar/scanner/protocol/output/FileStructure$Domain;".clone:()Ljava/lang/Object;
       6: checkcast     #5                  // class "[Lorg/sonar/scanner/protocol/output/FileStructure$Domain;"
       9: areturn

  public static org.sonar.scanner.protocol.output.FileStructure$Domain valueOf(java.lang.String);
    Code:
       0: ldc           #6                  // class org/sonar/scanner/protocol/output/FileStructure$Domain
       2: aload_0
       3: invokestatic  #7                  // Method java/lang/Enum.valueOf:(Ljava/lang/Class;Ljava/lang/String;)Ljava/lang/Enum;
       6: checkcast     #6                  // class org/sonar/scanner/protocol/output/FileStructure$Domain
       9: areturn

  private org.sonar.scanner.protocol.output.FileStructure$Domain(java.lang.String, java.lang.String);
    Code:
       0: aload_0
       1: aload_1
       2: iload_2
       3: invokespecial #8                  // Method java/lang/Enum."<init>":(Ljava/lang/String;I)V
       6: aload_0
       7: aload_3
       8: putfield      #2                  // Field filePrefix:Ljava/lang/String;
      11: aload_0
      12: aload         4
      14: putfield      #1                  // Field fileSuffix:Ljava/lang/String;
      17: return

  static java.lang.String access$000(org.sonar.scanner.protocol.output.FileStructure$Domain);
    Code:
       0: aload_0
       1: getfield      #2                  // Field filePrefix:Ljava/lang/String;
       4: areturn

  static java.lang.String access$100(org.sonar.scanner.protocol.output.FileStructure$Domain);
    Code:
       0: aload_0
       1: getfield      #1                  // Field fileSuffix:Ljava/lang/String;
       4: areturn

  static {};
    Code:
       0: new           #6                  // class org/sonar/scanner/protocol/output/FileStructure$Domain
       3: dup
       4: ldc           #9                  // String ISSUES
       6: iconst_0
       7: ldc           #10                 // String issues-
       9: ldc           #11                 // String .pb
      11: invokespecial #12                 // Method "<init>":(Ljava/lang/String;ILjava/lang/String;Ljava/lang/String;)V
      14: putstatic     #13                 // Field ISSUES:Lorg/sonar/scanner/protocol/output/FileStructure$Domain;
      17: new           #6                  // class org/sonar/scanner/protocol/output/FileStructure$Domain
      20: dup
      21: ldc           #14                 // String COMPONENT
      23: iconst_1
      24: ldc           #15                 // String component-
      26: ldc           #11                 // String .pb
      28: invokespecial #12                 // Method "<init>":(Ljava/lang/String;ILjava/lang/String;Ljava/lang/String;)V
      31: putstatic     #16                 // Field COMPONENT:Lorg/sonar/scanner/protocol/output/FileStructure$Domain;
      34: new           #6                  // class org/sonar/scanner/protocol/output/FileStructure$Domain
      37: dup
      38: ldc           #17                 // String MEASURES
      40: iconst_2
      41: ldc           #18                 // String measures-
      43: ldc           #11                 // String .pb
      45: invokespecial #12                 // Method "<init>":(Ljava/lang/String;ILjava/lang/String;Ljava/lang/String;)V
      48: putstatic     #19                 // Field MEASURES:Lorg/sonar/scanner/protocol/output/FileStructure$Domain;
      51: new           #6                  // class org/sonar/scanner/protocol/output/FileStructure$Domain
      54: dup
      55: ldc           #20                 // String DUPLICATIONS
      57: iconst_3
      58: ldc           #21                 // String duplications-
      60: ldc           #11                 // String .pb
      62: invokespecial #12                 // Method "<init>":(Ljava/lang/String;ILjava/lang/String;Ljava/lang/String;)V
      65: putstatic     #22                 // Field DUPLICATIONS:Lorg/sonar/scanner/protocol/output/FileStructure$Domain;
      68: new           #6                  // class org/sonar/scanner/protocol/output/FileStructure$Domain
      71: dup
      72: ldc           #23                 // String CPD_TEXT_BLOCKS
      74: iconst_4
      75: ldc           #24                 // String cpd-text-block-
      77: ldc           #11                 // String .pb
      79: invokespecial #12                 // Method "<init>":(Ljava/lang/String;ILjava/lang/String;Ljava/lang/String;)V
      82: putstatic     #25                 // Field CPD_TEXT_BLOCKS:Lorg/sonar/scanner/protocol/output/FileStructure$Domain;
      85: new           #6                  // class org/sonar/scanner/protocol/output/FileStructure$Domain
      88: dup
      89: ldc           #26                 // String SYNTAX_HIGHLIGHTINGS
      91: iconst_5
      92: ldc           #27                 // String syntax-highlightings-
      94: ldc           #11                 // String .pb
      96: invokespecial #12                 // Method "<init>":(Ljava/lang/String;ILjava/lang/String;Ljava/lang/String;)V
      99: putstatic     #28                 // Field SYNTAX_HIGHLIGHTINGS:Lorg/sonar/scanner/protocol/output/FileStructure$Domain;
     102: new           #6                  // class org/sonar/scanner/protocol/output/FileStructure$Domain
     105: dup
     106: ldc           #29                 // String CHANGESETS
     108: bipush        6
     110: ldc           #30                 // String changesets-
     112: ldc           #11                 // String .pb
     114: invokespecial #12                 // Method "<init>":(Ljava/lang/String;ILjava/lang/String;Ljava/lang/String;)V
     117: putstatic     #31                 // Field CHANGESETS:Lorg/sonar/scanner/protocol/output/FileStructure$Domain;
     120: new           #6                  // class org/sonar/scanner/protocol/output/FileStructure$Domain
     123: dup
     124: ldc           #32                 // String SYMBOLS
     126: bipush        7
     128: ldc           #33                 // String symbols-
     130: ldc           #11                 // String .pb
     132: invokespecial #12                 // Method "<init>":(Ljava/lang/String;ILjava/lang/String;Ljava/lang/String;)V
     135: putstatic     #34                 // Field SYMBOLS:Lorg/sonar/scanner/protocol/output/FileStructure$Domain;
     138: new           #6                  // class org/sonar/scanner/protocol/output/FileStructure$Domain
     141: dup
     142: ldc           #35                 // String COVERAGES
     144: bipush        8
     146: ldc           #36                 // String coverages-
     148: ldc           #11                 // String .pb
     150: invokespecial #12                 // Method "<init>":(Ljava/lang/String;ILjava/lang/String;Ljava/lang/String;)V
     153: putstatic     #37                 // Field COVERAGES:Lorg/sonar/scanner/protocol/output/FileStructure$Domain;
     156: new           #6                  // class org/sonar/scanner/protocol/output/FileStructure$Domain
     159: dup
     160: ldc           #38                 // String TESTS
     162: bipush        9
     164: ldc           #39                 // String tests-
     166: ldc           #11                 // String .pb
     168: invokespecial #12                 // Method "<init>":(Ljava/lang/String;ILjava/lang/String;Ljava/lang/String;)V
     171: putstatic     #40                 // Field TESTS:Lorg/sonar/scanner/protocol/output/FileStructure$Domain;
     174: new           #6                  // class org/sonar/scanner/protocol/output/FileStructure$Domain
     177: dup
     178: ldc           #41                 // String COVERAGE_DETAILS
     180: bipush        10
     182: ldc           #42                 // String coverage-details-
     184: ldc           #11                 // String .pb
     186: invokespecial #12                 // Method "<init>":(Ljava/lang/String;ILjava/lang/String;Ljava/lang/String;)V
     189: putstatic     #43                 // Field COVERAGE_DETAILS:Lorg/sonar/scanner/protocol/output/FileStructure$Domain;
     192: new           #6                  // class org/sonar/scanner/protocol/output/FileStructure$Domain
     195: dup
     196: ldc           #44                 // String SOURCE
     198: bipush        11
     200: ldc           #45                 // String source-
     202: ldc           #46                 // String .txt
     204: invokespecial #12                 // Method "<init>":(Ljava/lang/String;ILjava/lang/String;Ljava/lang/String;)V
     207: putstatic     #47                 // Field SOURCE:Lorg/sonar/scanner/protocol/output/FileStructure$Domain;
     210: bipush        12
     212: anewarray     #6                  // class org/sonar/scanner/protocol/output/FileStructure$Domain
     215: dup
     216: iconst_0
     217: getstatic     #13                 // Field ISSUES:Lorg/sonar/scanner/protocol/output/FileStructure$Domain;
     220: aastore
     221: dup
     222: iconst_1
     223: getstatic     #16                 // Field COMPONENT:Lorg/sonar/scanner/protocol/output/FileStructure$Domain;
     226: aastore
     227: dup
     228: iconst_2
     229: getstatic     #19                 // Field MEASURES:Lorg/sonar/scanner/protocol/output/FileStructure$Domain;
     232: aastore
     233: dup
     234: iconst_3
     235: getstatic     #22                 // Field DUPLICATIONS:Lorg/sonar/scanner/protocol/output/FileStructure$Domain;
     238: aastore
     239: dup
     240: iconst_4
     241: getstatic     #25                 // Field CPD_TEXT_BLOCKS:Lorg/sonar/scanner/protocol/output/FileStructure$Domain;
     244: aastore
     245: dup
     246: iconst_5
     247: getstatic     #28                 // Field SYNTAX_HIGHLIGHTINGS:Lorg/sonar/scanner/protocol/output/FileStructure$Domain;
     250: aastore
     251: dup
     252: bipush        6
     254: getstatic     #31                 // Field CHANGESETS:Lorg/sonar/scanner/protocol/output/FileStructure$Domain;
     257: aastore
     258: dup
     259: bipush        7
     261: getstatic     #34                 // Field SYMBOLS:Lorg/sonar/scanner/protocol/output/FileStructure$Domain;
     264: aastore
     265: dup
     266: bipush        8
     268: getstatic     #37                 // Field COVERAGES:Lorg/sonar/scanner/protocol/output/FileStructure$Domain;
     271: aastore
     272: dup
     273: bipush        9
     275: getstatic     #40                 // Field TESTS:Lorg/sonar/scanner/protocol/output/FileStructure$Domain;
     278: aastore
     279: dup
     280: bipush        10
     282: getstatic     #43                 // Field COVERAGE_DETAILS:Lorg/sonar/scanner/protocol/output/FileStructure$Domain;
     285: aastore
     286: dup
     287: bipush        11
     289: getstatic     #47                 // Field SOURCE:Lorg/sonar/scanner/protocol/output/FileStructure$Domain;
     292: aastore
     293: putstatic     #3                  // Field $VALUES:[Lorg/sonar/scanner/protocol/output/FileStructure$Domain;
     296: return
}
