Compiled from "RestClients.java"
class net.yudichev.jiotty.common.rest.RestClients$1 implements okhttp3.Callback {
  final int val$retryCount;

  final java.util.concurrent.CompletableFuture val$future;

  final com.google.common.reflect.TypeToken val$responseType;

  net.yudichev.jiotty.common.rest.RestClients$1(int, java.util.concurrent.CompletableFuture, com.google.common.reflect.TypeToken);
    Code:
       0: aload_0
       1: iload_1
       2: putfield      #1                  // Field val$retryCount:I
       5: aload_0
       6: aload_2
       7: putfield      #2                  // Field val$future:Ljava/util/concurrent/CompletableFuture;
      10: aload_0
      11: aload_3
      12: putfield      #3                  // Field val$responseType:Lcom/google/common/reflect/TypeToken;
      15: aload_0
      16: invokespecial #4                  // Method java/lang/Object."<init>":()V
      19: return

  public void onFailure(okhttp3.Call, java.io.IOException);
    Code:
       0: getstatic     #5                  // Field net/yudichev/jiotty/common/rest/RestClients.logger:Lorg/slf4j/Logger;
       3: ldc           #6                  // String Call failed: {}, retries left: {}
       5: iconst_3
       6: anewarray     #7                  // class java/lang/Object
       9: dup
      10: iconst_0
      11: aload_1
      12: aastore
      13: dup
      14: iconst_1
      15: aload_0
      16: getfield      #1                  // Field val$retryCount:I
      19: invokestatic  #8                  // Method java/lang/Integer.valueOf:(I)Ljava/lang/Integer;
      22: aastore
      23: dup
      24: iconst_2
      25: aload_2
      26: aastore
      27: invokeinterface #9,  3            // InterfaceMethod org/slf4j/Logger.debug:(Ljava/lang/String;[Ljava/lang/Object;)V
      32: aload_0
      33: getfield      #1                  // Field val$retryCount:I
      36: ifne          69
      39: aload_0
      40: getfield      #2                  // Field val$future:Ljava/util/concurrent/CompletableFuture;
      43: new           #10                 // class java/lang/RuntimeException
      46: dup
      47: aload_1
      48: invokeinterface #11,  1           // InterfaceMethod okhttp3/Call.request:()Lokhttp3/Request;
      53: invokedynamic #12,  0             // InvokeDynamic #0:makeConcatWithConstants:(Lokhttp3/Request;)Ljava/lang/String;
      58: aload_2
      59: invokespecial #13                 // Method java/lang/RuntimeException."<init>":(Ljava/lang/String;Ljava/lang/Throwable;)V
      62: invokevirtual #14                 // Method java/util/concurrent/CompletableFuture.completeExceptionally:(Ljava/lang/Throwable;)Z
      65: pop
      66: goto          101
      69: aload_1
      70: invokeinterface #15,  1           // InterfaceMethod okhttp3/Call.clone:()Lokhttp3/Call;
      75: aload_0
      76: getfield      #3                  // Field val$responseType:Lcom/google/common/reflect/TypeToken;
      79: aload_0
      80: getfield      #1                  // Field val$retryCount:I
      83: iconst_1
      84: isub
      85: invokestatic  #16                 // Method net/yudichev/jiotty/common/rest/RestClients.call:(Lokhttp3/Call;Lcom/google/common/reflect/TypeToken;I)Ljava/util/concurrent/CompletableFuture;
      88: aload_0
      89: getfield      #2                  // Field val$future:Ljava/util/concurrent/CompletableFuture;
      92: invokedynamic #17,  0             // InvokeDynamic #1:accept:(Ljava/util/concurrent/CompletableFuture;)Ljava/util/function/BiConsumer;
      97: invokevirtual #18                 // Method java/util/concurrent/CompletableFuture.whenComplete:(Ljava/util/function/BiConsumer;)Ljava/util/concurrent/CompletableFuture;
     100: pop
     101: return

  public void onResponse(okhttp3.Call, okhttp3.Response);
    Code:
       0: aload_2
       1: invokevirtual #19                 // Method okhttp3/Response.body:()Lokhttp3/ResponseBody;
       4: invokestatic  #20                 // Method java/util/Objects.requireNonNull:(Ljava/lang/Object;)Ljava/lang/Object;
       7: checkcast     #21                 // class okhttp3/ResponseBody
      10: astore_3
      11: aload_3
      12: invokevirtual #22                 // Method okhttp3/ResponseBody.string:()Ljava/lang/String;
      15: astore        4
      17: aload_0
      18: getfield      #2                  // Field val$future:Ljava/util/concurrent/CompletableFuture;
      21: aload         4
      23: aload_0
      24: getfield      #3                  // Field val$responseType:Lcom/google/common/reflect/TypeToken;
      27: invokestatic  #23                 // Method net/yudichev/jiotty/common/lang/Json.parse:(Ljava/lang/String;Lcom/google/common/reflect/TypeToken;)Ljava/lang/Object;
      30: invokevirtual #24                 // Method java/util/concurrent/CompletableFuture.complete:(Ljava/lang/Object;)Z
      33: pop
      34: goto          62
      37: astore        4
      39: aload_0
      40: getfield      #2                  // Field val$future:Ljava/util/concurrent/CompletableFuture;
      43: new           #10                 // class java/lang/RuntimeException
      46: dup
      47: aload_3
      48: invokedynamic #26,  0             // InvokeDynamic #2:makeConcatWithConstants:(Lokhttp3/ResponseBody;)Ljava/lang/String;
      53: aload         4
      55: invokespecial #13                 // Method java/lang/RuntimeException."<init>":(Ljava/lang/String;Ljava/lang/Throwable;)V
      58: invokevirtual #14                 // Method java/util/concurrent/CompletableFuture.completeExceptionally:(Ljava/lang/Throwable;)Z
      61: pop
      62: return
    Exception table:
       from    to  target type
          11    34    37   Class java/lang/RuntimeException
          11    34    37   Class java/io/IOException

  private static void lambda$onFailure$0(java.util.concurrent.CompletableFuture, java.lang.Object, java.lang.Throwable);
    Code:
       0: aload_2
       1: ifnonnull     13
       4: aload_0
       5: aload_1
       6: invokevirtual #24                 // Method java/util/concurrent/CompletableFuture.complete:(Ljava/lang/Object;)Z
       9: pop
      10: goto          19
      13: aload_0
      14: aload_2
      15: invokevirtual #14                 // Method java/util/concurrent/CompletableFuture.completeExceptionally:(Ljava/lang/Throwable;)Z
      18: pop
      19: return
}
