Compiled from "AbstractAccessReferenceMap.java"
public abstract class org.owasp.esapi.reference.AbstractAccessReferenceMap<K> implements org.owasp.esapi.AccessReferenceMap<K> {
  private static final long serialVersionUID;

  protected java.util.Map<K, java.lang.Object> itod;

  protected java.util.Map<java.lang.Object, K> dtoi;

  public org.owasp.esapi.reference.AbstractAccessReferenceMap();
    Code:
       0: aload_0
       1: invokespecial #1                  // Method java/lang/Object."<init>":()V
       4: aload_0
       5: new           #2                  // class java/util/concurrent/ConcurrentHashMap
       8: dup
       9: invokespecial #3                  // Method java/util/concurrent/ConcurrentHashMap."<init>":()V
      12: putfield      #4                  // Field itod:Ljava/util/Map;
      15: aload_0
      16: new           #2                  // class java/util/concurrent/ConcurrentHashMap
      19: dup
      20: invokespecial #3                  // Method java/util/concurrent/ConcurrentHashMap."<init>":()V
      23: putfield      #5                  // Field dtoi:Ljava/util/Map;
      26: return

  public org.owasp.esapi.reference.AbstractAccessReferenceMap(int);
    Code:
       0: aload_0
       1: invokespecial #1                  // Method java/lang/Object."<init>":()V
       4: aload_0
       5: new           #2                  // class java/util/concurrent/ConcurrentHashMap
       8: dup
       9: iload_1
      10: invokespecial #6                  // Method java/util/concurrent/ConcurrentHashMap."<init>":(I)V
      13: putfield      #4                  // Field itod:Ljava/util/Map;
      16: aload_0
      17: new           #2                  // class java/util/concurrent/ConcurrentHashMap
      20: dup
      21: iload_1
      22: invokespecial #6                  // Method java/util/concurrent/ConcurrentHashMap."<init>":(I)V
      25: putfield      #5                  // Field dtoi:Ljava/util/Map;
      28: return

  public org.owasp.esapi.reference.AbstractAccessReferenceMap(java.util.Set<java.lang.Object>);
    Code:
       0: aload_0
       1: invokespecial #1                  // Method java/lang/Object."<init>":()V
       4: aload_0
       5: new           #2                  // class java/util/concurrent/ConcurrentHashMap
       8: dup
       9: aload_1
      10: invokeinterface #7,  1            // InterfaceMethod java/util/Set.size:()I
      15: invokespecial #6                  // Method java/util/concurrent/ConcurrentHashMap."<init>":(I)V
      18: putfield      #4                  // Field itod:Ljava/util/Map;
      21: aload_0
      22: new           #2                  // class java/util/concurrent/ConcurrentHashMap
      25: dup
      26: aload_1
      27: invokeinterface #7,  1            // InterfaceMethod java/util/Set.size:()I
      32: invokespecial #6                  // Method java/util/concurrent/ConcurrentHashMap."<init>":(I)V
      35: putfield      #5                  // Field dtoi:Ljava/util/Map;
      38: aload_0
      39: aload_1
      40: invokevirtual #8                  // Method update:(Ljava/util/Set;)V
      43: return

  public org.owasp.esapi.reference.AbstractAccessReferenceMap(java.util.Set<java.lang.Object>, int);
    Code:
       0: aload_0
       1: invokespecial #1                  // Method java/lang/Object."<init>":()V
       4: aload_0
       5: new           #2                  // class java/util/concurrent/ConcurrentHashMap
       8: dup
       9: iload_2
      10: invokespecial #6                  // Method java/util/concurrent/ConcurrentHashMap."<init>":(I)V
      13: putfield      #4                  // Field itod:Ljava/util/Map;
      16: aload_0
      17: new           #2                  // class java/util/concurrent/ConcurrentHashMap
      20: dup
      21: iload_2
      22: invokespecial #6                  // Method java/util/concurrent/ConcurrentHashMap."<init>":(I)V
      25: putfield      #5                  // Field dtoi:Ljava/util/Map;
      28: aload_0
      29: aload_1
      30: invokevirtual #8                  // Method update:(Ljava/util/Set;)V
      33: return

  protected abstract K getUniqueReference();

  public synchronized java.util.Iterator iterator();
    Code:
       0: new           #9                  // class java/util/TreeSet
       3: dup
       4: aload_0
       5: getfield      #5                  // Field dtoi:Ljava/util/Map;
       8: invokeinterface #10,  1           // InterfaceMethod java/util/Map.keySet:()Ljava/util/Set;
      13: invokespecial #11                 // Method java/util/TreeSet."<init>":(Ljava/util/Collection;)V
      16: astore_1
      17: aload_1
      18: invokevirtual #12                 // Method java/util/TreeSet.iterator:()Ljava/util/Iterator;
      21: areturn

  public <T> K addDirectReference(T);
    Code:
       0: aload_0
       1: getfield      #5                  // Field dtoi:Ljava/util/Map;
       4: invokeinterface #10,  1           // InterfaceMethod java/util/Map.keySet:()Ljava/util/Set;
       9: aload_1
      10: invokeinterface #13,  2           // InterfaceMethod java/util/Set.contains:(Ljava/lang/Object;)Z
      15: ifeq          29
      18: aload_0
      19: getfield      #5                  // Field dtoi:Ljava/util/Map;
      22: aload_1
      23: invokeinterface #14,  2           // InterfaceMethod java/util/Map.get:(Ljava/lang/Object;)Ljava/lang/Object;
      28: areturn
      29: aload_0
      30: invokevirtual #15                 // Method getUniqueReference:()Ljava/lang/Object;
      33: astore_2
      34: aload_0
      35: getfield      #4                  // Field itod:Ljava/util/Map;
      38: aload_2
      39: aload_1
      40: invokeinterface #16,  3           // InterfaceMethod java/util/Map.put:(Ljava/lang/Object;Ljava/lang/Object;)Ljava/lang/Object;
      45: pop
      46: aload_0
      47: getfield      #5                  // Field dtoi:Ljava/util/Map;
      50: aload_1
      51: aload_2
      52: invokeinterface #16,  3           // InterfaceMethod java/util/Map.put:(Ljava/lang/Object;Ljava/lang/Object;)Ljava/lang/Object;
      57: pop
      58: aload_2
      59: areturn

  public <T> K removeDirectReference(T) throws org.owasp.esapi.errors.AccessControlException;
    Code:
       0: aload_0
       1: getfield      #5                  // Field dtoi:Ljava/util/Map;
       4: aload_1
       5: invokeinterface #14,  2           // InterfaceMethod java/util/Map.get:(Ljava/lang/Object;)Ljava/lang/Object;
      10: astore_2
      11: aload_2
      12: ifnull        37
      15: aload_0
      16: getfield      #4                  // Field itod:Ljava/util/Map;
      19: aload_2
      20: invokeinterface #17,  2           // InterfaceMethod java/util/Map.remove:(Ljava/lang/Object;)Ljava/lang/Object;
      25: pop
      26: aload_0
      27: getfield      #5                  // Field dtoi:Ljava/util/Map;
      30: aload_1
      31: invokeinterface #17,  2           // InterfaceMethod java/util/Map.remove:(Ljava/lang/Object;)Ljava/lang/Object;
      36: pop
      37: aload_2
      38: areturn

  public final synchronized void update(java.util.Set);
    Code:
       0: new           #2                  // class java/util/concurrent/ConcurrentHashMap
       3: dup
       4: aload_1
       5: invokeinterface #7,  1            // InterfaceMethod java/util/Set.size:()I
      10: invokespecial #6                  // Method java/util/concurrent/ConcurrentHashMap."<init>":(I)V
      13: astore_2
      14: new           #2                  // class java/util/concurrent/ConcurrentHashMap
      17: dup
      18: aload_1
      19: invokeinterface #7,  1            // InterfaceMethod java/util/Set.size:()I
      24: invokespecial #6                  // Method java/util/concurrent/ConcurrentHashMap."<init>":(I)V
      27: astore_3
      28: aload_1
      29: invokeinterface #18,  1           // InterfaceMethod java/util/Set.iterator:()Ljava/util/Iterator;
      34: astore        4
      36: aload         4
      38: invokeinterface #19,  1           // InterfaceMethod java/util/Iterator.hasNext:()Z
      43: ifeq          104
      46: aload         4
      48: invokeinterface #20,  1           // InterfaceMethod java/util/Iterator.next:()Ljava/lang/Object;
      53: astore        5
      55: aload_0
      56: getfield      #5                  // Field dtoi:Ljava/util/Map;
      59: aload         5
      61: invokeinterface #14,  2           // InterfaceMethod java/util/Map.get:(Ljava/lang/Object;)Ljava/lang/Object;
      66: astore        6
      68: aload         6
      70: ifnonnull     79
      73: aload_0
      74: invokevirtual #15                 // Method getUniqueReference:()Ljava/lang/Object;
      77: astore        6
      79: aload_2
      80: aload         5
      82: aload         6
      84: invokeinterface #16,  3           // InterfaceMethod java/util/Map.put:(Ljava/lang/Object;Ljava/lang/Object;)Ljava/lang/Object;
      89: pop
      90: aload_3
      91: aload         6
      93: aload         5
      95: invokeinterface #16,  3           // InterfaceMethod java/util/Map.put:(Ljava/lang/Object;Ljava/lang/Object;)Ljava/lang/Object;
     100: pop
     101: goto          36
     104: aload_0
     105: aload_2
     106: putfield      #5                  // Field dtoi:Ljava/util/Map;
     109: aload_0
     110: aload_3
     111: putfield      #4                  // Field itod:Ljava/util/Map;
     114: return

  public <T> K getIndirectReference(T);
    Code:
       0: aload_0
       1: getfield      #5                  // Field dtoi:Ljava/util/Map;
       4: aload_1
       5: invokeinterface #14,  2           // InterfaceMethod java/util/Map.get:(Ljava/lang/Object;)Ljava/lang/Object;
      10: areturn

  public <T> T getDirectReference(K) throws org.owasp.esapi.errors.AccessControlException;
    Code:
       0: aload_0
       1: getfield      #4                  // Field itod:Ljava/util/Map;
       4: aload_1
       5: invokeinterface #21,  2           // InterfaceMethod java/util/Map.containsKey:(Ljava/lang/Object;)Z
      10: ifeq          54
      13: aload_0
      14: getfield      #4                  // Field itod:Ljava/util/Map;
      17: aload_1
      18: invokeinterface #14,  2           // InterfaceMethod java/util/Map.get:(Ljava/lang/Object;)Ljava/lang/Object;
      23: areturn
      24: astore_2
      25: new           #23                 // class org/owasp/esapi/errors/AccessControlException
      28: dup
      29: ldc           #24                 // String Access denied.
      31: new           #25                 // class java/lang/StringBuilder
      34: dup
      35: invokespecial #26                 // Method java/lang/StringBuilder."<init>":()V
      38: ldc           #27                 // String Request for incorrect type reference:
      40: invokevirtual #28                 // Method java/lang/StringBuilder.append:(Ljava/lang/String;)Ljava/lang/StringBuilder;
      43: aload_1
      44: invokevirtual #29                 // Method java/lang/StringBuilder.append:(Ljava/lang/Object;)Ljava/lang/StringBuilder;
      47: invokevirtual #30                 // Method java/lang/StringBuilder.toString:()Ljava/lang/String;
      50: invokespecial #31                 // Method org/owasp/esapi/errors/AccessControlException."<init>":(Ljava/lang/String;Ljava/lang/String;)V
      53: athrow
      54: new           #23                 // class org/owasp/esapi/errors/AccessControlException
      57: dup
      58: ldc           #32                 // String Access denied
      60: new           #25                 // class java/lang/StringBuilder
      63: dup
      64: invokespecial #26                 // Method java/lang/StringBuilder."<init>":()V
      67: ldc           #33                 // String Request for invalid indirect reference:
      69: invokevirtual #28                 // Method java/lang/StringBuilder.append:(Ljava/lang/String;)Ljava/lang/StringBuilder;
      72: aload_1
      73: invokevirtual #29                 // Method java/lang/StringBuilder.append:(Ljava/lang/Object;)Ljava/lang/StringBuilder;
      76: invokevirtual #30                 // Method java/lang/StringBuilder.toString:()Ljava/lang/String;
      79: invokespecial #31                 // Method org/owasp/esapi/errors/AccessControlException."<init>":(Ljava/lang/String;Ljava/lang/String;)V
      82: athrow
    Exception table:
       from    to  target type
          13    23    24   Class java/lang/ClassCastException
}
