Compiled from "DefaultHTTPUtilities.java"
public class org.owasp.esapi.reference.DefaultHTTPUtilities implements org.owasp.esapi.HTTPUtilities {
  private static volatile org.owasp.esapi.HTTPUtilities instance;

  private final org.owasp.esapi.Logger logger;

  static final int maxBytes;

  private org.owasp.esapi.reference.DefaultHTTPUtilities$ThreadLocalRequest currentRequest;

  private org.owasp.esapi.reference.DefaultHTTPUtilities$ThreadLocalResponse currentResponse;

  public static org.owasp.esapi.HTTPUtilities getInstance();
    Code:
       0: getstatic     #1                  // Field instance:Lorg/owasp/esapi/HTTPUtilities;
       3: ifnonnull     38
       6: ldc_w         #2                  // class org/owasp/esapi/reference/DefaultHTTPUtilities
       9: dup
      10: astore_0
      11: monitorenter
      12: getstatic     #1                  // Field instance:Lorg/owasp/esapi/HTTPUtilities;
      15: ifnonnull     28
      18: new           #2                  // class org/owasp/esapi/reference/DefaultHTTPUtilities
      21: dup
      22: invokespecial #3                  // Method "<init>":()V
      25: putstatic     #1                  // Field instance:Lorg/owasp/esapi/HTTPUtilities;
      28: aload_0
      29: monitorexit
      30: goto          38
      33: astore_1
      34: aload_0
      35: monitorexit
      36: aload_1
      37: athrow
      38: getstatic     #1                  // Field instance:Lorg/owasp/esapi/HTTPUtilities;
      41: areturn
    Exception table:
       from    to  target type
          12    30    33   any
          33    36    33   any

  public org.owasp.esapi.reference.DefaultHTTPUtilities();
    Code:
       0: aload_0
       1: invokespecial #4                  // Method java/lang/Object."<init>":()V
       4: aload_0
       5: ldc           #5                  // String HTTPUtilities
       7: invokestatic  #6                  // Method org/owasp/esapi/ESAPI.getLogger:(Ljava/lang/String;)Lorg/owasp/esapi/Logger;
      10: putfield      #7                  // Field logger:Lorg/owasp/esapi/Logger;
      13: aload_0
      14: new           #8                  // class org/owasp/esapi/reference/DefaultHTTPUtilities$ThreadLocalRequest
      17: dup
      18: aload_0
      19: aconst_null
      20: invokespecial #9                  // Method org/owasp/esapi/reference/DefaultHTTPUtilities$ThreadLocalRequest."<init>":(Lorg/owasp/esapi/reference/DefaultHTTPUtilities;Lorg/owasp/esapi/reference/DefaultHTTPUtilities$1;)V
      23: putfield      #10                 // Field currentRequest:Lorg/owasp/esapi/reference/DefaultHTTPUtilities$ThreadLocalRequest;
      26: aload_0
      27: new           #11                 // class org/owasp/esapi/reference/DefaultHTTPUtilities$ThreadLocalResponse
      30: dup
      31: aload_0
      32: aconst_null
      33: invokespecial #12                 // Method org/owasp/esapi/reference/DefaultHTTPUtilities$ThreadLocalResponse."<init>":(Lorg/owasp/esapi/reference/DefaultHTTPUtilities;Lorg/owasp/esapi/reference/DefaultHTTPUtilities$1;)V
      36: putfield      #13                 // Field currentResponse:Lorg/owasp/esapi/reference/DefaultHTTPUtilities$ThreadLocalResponse;
      39: return

  public void addCookie(javax.servlet.http.Cookie);
    Code:
       0: aload_0
       1: aload_0
       2: invokevirtual #14                 // Method getCurrentResponse:()Ljavax/servlet/http/HttpServletResponse;
       5: aload_1
       6: invokevirtual #15                 // Method addCookie:(Ljavax/servlet/http/HttpServletResponse;Ljavax/servlet/http/Cookie;)V
       9: return

  public void addCookie(javax.servlet.http.HttpServletResponse, javax.servlet.http.Cookie);
    Code:
       0: aload_2
       1: invokevirtual #16                 // Method javax/servlet/http/Cookie.getName:()Ljava/lang/String;
       4: astore_3
       5: aload_2
       6: invokevirtual #17                 // Method javax/servlet/http/Cookie.getValue:()Ljava/lang/String;
       9: astore        4
      11: aload_2
      12: invokevirtual #18                 // Method javax/servlet/http/Cookie.getMaxAge:()I
      15: istore        5
      17: aload_2
      18: invokevirtual #19                 // Method javax/servlet/http/Cookie.getDomain:()Ljava/lang/String;
      21: astore        6
      23: aload_2
      24: invokevirtual #20                 // Method javax/servlet/http/Cookie.getPath:()Ljava/lang/String;
      27: astore        7
      29: aload_2
      30: invokevirtual #21                 // Method javax/servlet/http/Cookie.getSecure:()Z
      33: istore        8
      35: new           #22                 // class org/owasp/esapi/ValidationErrorList
      38: dup
      39: invokespecial #23                 // Method org/owasp/esapi/ValidationErrorList."<init>":()V
      42: astore        9
      44: invokestatic  #24                 // Method org/owasp/esapi/ESAPI.validator:()Lorg/owasp/esapi/Validator;
      47: ldc           #25                 // String cookie name
      49: aload_3
      50: ldc           #26                 // String HTTPCookieName
      52: bipush        50
      54: iconst_0
      55: aload         9
      57: invokeinterface #27,  7           // InterfaceMethod org/owasp/esapi/Validator.getValidInput:(Ljava/lang/String;Ljava/lang/String;Ljava/lang/String;IZLorg/owasp/esapi/ValidationErrorList;)Ljava/lang/String;
      62: astore        10
      64: invokestatic  #24                 // Method org/owasp/esapi/ESAPI.validator:()Lorg/owasp/esapi/Validator;
      67: ldc           #28                 // String cookie value
      69: aload         4
      71: ldc           #29                 // String HTTPCookieValue
      73: sipush        5000
      76: iconst_0
      77: aload         9
      79: invokeinterface #27,  7           // InterfaceMethod org/owasp/esapi/Validator.getValidInput:(Ljava/lang/String;Ljava/lang/String;Ljava/lang/String;IZLorg/owasp/esapi/ValidationErrorList;)Ljava/lang/String;
      84: astore        11
      86: aload         9
      88: invokevirtual #30                 // Method org/owasp/esapi/ValidationErrorList.size:()I
      91: ifne          168
      94: invokestatic  #31                 // Method org/owasp/esapi/ESAPI.securityConfiguration:()Lorg/owasp/esapi/SecurityConfiguration;
      97: invokeinterface #32,  1           // InterfaceMethod org/owasp/esapi/SecurityConfiguration.getForceHttpOnlyCookies:()Z
     102: ifeq          135
     105: aload_0
     106: aload         10
     108: aload         11
     110: iload         5
     112: aload         6
     114: aload         7
     116: iload         8
     118: invokespecial #33                 // Method createCookieHeader:(Ljava/lang/String;Ljava/lang/String;ILjava/lang/String;Ljava/lang/String;Z)Ljava/lang/String;
     121: astore        12
     123: aload_0
     124: aload_1
     125: ldc           #34                 // String Set-Cookie
     127: aload         12
     129: invokevirtual #35                 // Method addHeader:(Ljavax/servlet/http/HttpServletResponse;Ljava/lang/String;Ljava/lang/String;)V
     132: goto          167
     135: aload_2
     136: iload         8
     138: ifne          152
     141: invokestatic  #31                 // Method org/owasp/esapi/ESAPI.securityConfiguration:()Lorg/owasp/esapi/SecurityConfiguration;
     144: invokeinterface #36,  1           // InterfaceMethod org/owasp/esapi/SecurityConfiguration.getForceSecureCookies:()Z
     149: ifeq          156
     152: iconst_1
     153: goto          157
     156: iconst_0
     157: invokevirtual #37                 // Method javax/servlet/http/Cookie.setSecure:(Z)V
     160: aload_1
     161: aload_2
     162: invokeinterface #38,  2           // InterfaceMethod javax/servlet/http/HttpServletResponse.addCookie:(Ljavax/servlet/http/Cookie;)V
     167: return
     168: aload_0
     169: getfield      #7                  // Field logger:Lorg/owasp/esapi/Logger;
     172: getstatic     #39                 // Field org/owasp/esapi/Logger.SECURITY_FAILURE:Lorg/owasp/esapi/Logger$EventType;
     175: ldc           #40                 // String Attempt to add unsafe data to cookie (skip mode). Skipping cookie and continuing.
     177: invokeinterface #41,  3           // InterfaceMethod org/owasp/esapi/Logger.warning:(Lorg/owasp/esapi/Logger$EventType;Ljava/lang/String;)V
     182: return

  public java.lang.String addCSRFToken(java.lang.String);
    Code:
       0: invokestatic  #42                 // Method org/owasp/esapi/ESAPI.authenticator:()Lorg/owasp/esapi/Authenticator;
       3: invokeinterface #43,  1           // InterfaceMethod org/owasp/esapi/Authenticator.getCurrentUser:()Lorg/owasp/esapi/User;
       8: astore_2
       9: aload_2
      10: invokeinterface #44,  1           // InterfaceMethod org/owasp/esapi/User.isAnonymous:()Z
      15: ifeq          20
      18: aload_1
      19: areturn
      20: new           #45                 // class java/lang/StringBuilder
      23: dup
      24: invokespecial #46                 // Method java/lang/StringBuilder."<init>":()V
      27: ldc           #47                 // String ctoken=
      29: invokevirtual #48                 // Method java/lang/StringBuilder.append:(Ljava/lang/String;)Ljava/lang/StringBuilder;
      32: aload_2
      33: invokeinterface #49,  1           // InterfaceMethod org/owasp/esapi/User.getCSRFToken:()Ljava/lang/String;
      38: invokevirtual #48                 // Method java/lang/StringBuilder.append:(Ljava/lang/String;)Ljava/lang/StringBuilder;
      41: invokevirtual #50                 // Method java/lang/StringBuilder.toString:()Ljava/lang/String;
      44: astore_3
      45: aload_1
      46: bipush        63
      48: invokevirtual #51                 // Method java/lang/String.indexOf:(I)I
      51: iconst_m1
      52: if_icmpeq     81
      55: new           #45                 // class java/lang/StringBuilder
      58: dup
      59: invokespecial #46                 // Method java/lang/StringBuilder."<init>":()V
      62: aload_1
      63: invokevirtual #48                 // Method java/lang/StringBuilder.append:(Ljava/lang/String;)Ljava/lang/StringBuilder;
      66: ldc           #52                 // String &
      68: invokevirtual #48                 // Method java/lang/StringBuilder.append:(Ljava/lang/String;)Ljava/lang/StringBuilder;
      71: aload_3
      72: invokevirtual #48                 // Method java/lang/StringBuilder.append:(Ljava/lang/String;)Ljava/lang/StringBuilder;
      75: invokevirtual #50                 // Method java/lang/StringBuilder.toString:()Ljava/lang/String;
      78: goto          104
      81: new           #45                 // class java/lang/StringBuilder
      84: dup
      85: invokespecial #46                 // Method java/lang/StringBuilder."<init>":()V
      88: aload_1
      89: invokevirtual #48                 // Method java/lang/StringBuilder.append:(Ljava/lang/String;)Ljava/lang/StringBuilder;
      92: ldc           #53                 // String ?
      94: invokevirtual #48                 // Method java/lang/StringBuilder.append:(Ljava/lang/String;)Ljava/lang/StringBuilder;
      97: aload_3
      98: invokevirtual #48                 // Method java/lang/StringBuilder.append:(Ljava/lang/String;)Ljava/lang/StringBuilder;
     101: invokevirtual #50                 // Method java/lang/StringBuilder.toString:()Ljava/lang/String;
     104: areturn

  public void addHeader(java.lang.String, java.lang.String);
    Code:
       0: aload_0
       1: aload_0
       2: invokevirtual #14                 // Method getCurrentResponse:()Ljavax/servlet/http/HttpServletResponse;
       5: aload_1
       6: aload_2
       7: invokevirtual #35                 // Method addHeader:(Ljavax/servlet/http/HttpServletResponse;Ljava/lang/String;Ljava/lang/String;)V
      10: return

  public void addHeader(javax.servlet.http.HttpServletResponse, java.lang.String, java.lang.String);
    Code:
       0: aload_2
       1: invokestatic  #54                 // Method org/owasp/esapi/StringUtilities.replaceLinearWhiteSpace:(Ljava/lang/String;)Ljava/lang/String;
       4: astore        4
       6: aload_3
       7: invokestatic  #54                 // Method org/owasp/esapi/StringUtilities.replaceLinearWhiteSpace:(Ljava/lang/String;)Ljava/lang/String;
      10: astore        5
      12: invokestatic  #24                 // Method org/owasp/esapi/ESAPI.validator:()Lorg/owasp/esapi/Validator;
      15: ldc           #55                 // String addHeader
      17: aload         4
      19: ldc           #56                 // String HTTPHeaderName
      21: bipush        20
      23: iconst_0
      24: invokeinterface #57,  6           // InterfaceMethod org/owasp/esapi/Validator.getValidInput:(Ljava/lang/String;Ljava/lang/String;Ljava/lang/String;IZ)Ljava/lang/String;
      29: astore        6
      31: invokestatic  #24                 // Method org/owasp/esapi/ESAPI.validator:()Lorg/owasp/esapi/Validator;
      34: ldc           #55                 // String addHeader
      36: aload         5
      38: ldc           #58                 // String HTTPHeaderValue
      40: sipush        500
      43: iconst_0
      44: invokeinterface #57,  6           // InterfaceMethod org/owasp/esapi/Validator.getValidInput:(Ljava/lang/String;Ljava/lang/String;Ljava/lang/String;IZ)Ljava/lang/String;
      49: astore        7
      51: aload_1
      52: aload         6
      54: aload         7
      56: invokeinterface #59,  3           // InterfaceMethod javax/servlet/http/HttpServletResponse.addHeader:(Ljava/lang/String;Ljava/lang/String;)V
      61: goto          82
      64: astore        4
      66: aload_0
      67: getfield      #7                  // Field logger:Lorg/owasp/esapi/Logger;
      70: getstatic     #39                 // Field org/owasp/esapi/Logger.SECURITY_FAILURE:Lorg/owasp/esapi/Logger$EventType;
      73: ldc           #61                 // String Attempt to add invalid header denied
      75: aload         4
      77: invokeinterface #62,  4           // InterfaceMethod org/owasp/esapi/Logger.warning:(Lorg/owasp/esapi/Logger$EventType;Ljava/lang/String;Ljava/lang/Throwable;)V
      82: return
    Exception table:
       from    to  target type
           0    61    64   Class org/owasp/esapi/errors/ValidationException

  public void assertSecureChannel() throws org.owasp.esapi.errors.AccessControlException;
    Code:
       0: aload_0
       1: aload_0
       2: invokevirtual #63                 // Method getCurrentRequest:()Ljavax/servlet/http/HttpServletRequest;
       5: invokevirtual #64                 // Method assertSecureChannel:(Ljavax/servlet/http/HttpServletRequest;)V
       8: return

  public void assertSecureChannel(javax.servlet.http.HttpServletRequest) throws org.owasp.esapi.errors.AccessControlException;
    Code:
       0: aload_1
       1: ifnonnull     16
       4: new           #65                 // class org/owasp/esapi/errors/AccessControlException
       7: dup
       8: ldc           #66                 // String Insecure request received
      10: ldc           #67                 // String HTTP request was null
      12: invokespecial #68                 // Method org/owasp/esapi/errors/AccessControlException."<init>":(Ljava/lang/String;Ljava/lang/String;)V
      15: athrow
      16: aload_1
      17: invokeinterface #69,  1           // InterfaceMethod javax/servlet/http/HttpServletRequest.getRequestURL:()Ljava/lang/StringBuffer;
      22: astore_2
      23: aload_2
      24: ifnonnull     39
      27: new           #65                 // class org/owasp/esapi/errors/AccessControlException
      30: dup
      31: ldc           #66                 // String Insecure request received
      33: ldc           #70                 // String HTTP request URL was null
      35: invokespecial #68                 // Method org/owasp/esapi/errors/AccessControlException."<init>":(Ljava/lang/String;Ljava/lang/String;)V
      38: athrow
      39: aload_2
      40: invokevirtual #71                 // Method java/lang/StringBuffer.toString:()Ljava/lang/String;
      43: astore_3
      44: aload_3
      45: ldc           #72                 // String https
      47: invokevirtual #73                 // Method java/lang/String.startsWith:(Ljava/lang/String;)Z
      50: ifne          65
      53: new           #65                 // class org/owasp/esapi/errors/AccessControlException
      56: dup
      57: ldc           #66                 // String Insecure request received
      59: ldc           #74                 // String HTTP request did not use SSL
      61: invokespecial #68                 // Method org/owasp/esapi/errors/AccessControlException."<init>":(Ljava/lang/String;Ljava/lang/String;)V
      64: athrow
      65: return

  public void assertSecureRequest() throws org.owasp.esapi.errors.AccessControlException;
    Code:
       0: aload_0
       1: aload_0
       2: invokevirtual #63                 // Method getCurrentRequest:()Ljavax/servlet/http/HttpServletRequest;
       5: invokevirtual #75                 // Method assertSecureRequest:(Ljavax/servlet/http/HttpServletRequest;)V
       8: return

  public void assertSecureRequest(javax.servlet.http.HttpServletRequest) throws org.owasp.esapi.errors.AccessControlException;
    Code:
       0: aload_0
       1: aload_1
       2: invokevirtual #64                 // Method assertSecureChannel:(Ljavax/servlet/http/HttpServletRequest;)V
       5: aload_1
       6: invokeinterface #76,  1           // InterfaceMethod javax/servlet/http/HttpServletRequest.getMethod:()Ljava/lang/String;
      11: astore_2
      12: ldc           #77                 // String POST
      14: astore_3
      15: aload_2
      16: aload_3
      17: invokevirtual #78                 // Method java/lang/String.equals:(Ljava/lang/Object;)Z
      20: ifne          66
      23: new           #65                 // class org/owasp/esapi/errors/AccessControlException
      26: dup
      27: ldc           #66                 // String Insecure request received
      29: new           #45                 // class java/lang/StringBuilder
      32: dup
      33: invokespecial #46                 // Method java/lang/StringBuilder."<init>":()V
      36: ldc           #79                 // String Received request using
      38: invokevirtual #48                 // Method java/lang/StringBuilder.append:(Ljava/lang/String;)Ljava/lang/StringBuilder;
      41: aload_2
      42: invokevirtual #48                 // Method java/lang/StringBuilder.append:(Ljava/lang/String;)Ljava/lang/StringBuilder;
      45: ldc           #80                 // String  when only
      47: invokevirtual #48                 // Method java/lang/StringBuilder.append:(Ljava/lang/String;)Ljava/lang/StringBuilder;
      50: aload_3
      51: invokevirtual #48                 // Method java/lang/StringBuilder.append:(Ljava/lang/String;)Ljava/lang/StringBuilder;
      54: ldc           #81                 // String  is allowed
      56: invokevirtual #48                 // Method java/lang/StringBuilder.append:(Ljava/lang/String;)Ljava/lang/StringBuilder;
      59: invokevirtual #50                 // Method java/lang/StringBuilder.toString:()Ljava/lang/String;
      62: invokespecial #68                 // Method org/owasp/esapi/errors/AccessControlException."<init>":(Ljava/lang/String;Ljava/lang/String;)V
      65: athrow
      66: return

  public javax.servlet.http.HttpSession changeSessionIdentifier() throws org.owasp.esapi.errors.AuthenticationException;
    Code:
       0: aload_0
       1: aload_0
       2: invokevirtual #63                 // Method getCurrentRequest:()Ljavax/servlet/http/HttpServletRequest;
       5: invokevirtual #82                 // Method changeSessionIdentifier:(Ljavax/servlet/http/HttpServletRequest;)Ljavax/servlet/http/HttpSession;
       8: areturn

  public javax.servlet.http.HttpSession changeSessionIdentifier(javax.servlet.http.HttpServletRequest) throws org.owasp.esapi.errors.AuthenticationException;
    Code:
       0: aload_1
       1: invokeinterface #83,  1           // InterfaceMethod javax/servlet/http/HttpServletRequest.getSession:()Ljavax/servlet/http/HttpSession;
       6: astore_2
       7: new           #84                 // class java/util/concurrent/ConcurrentHashMap
      10: dup
      11: invokespecial #85                 // Method java/util/concurrent/ConcurrentHashMap."<init>":()V
      14: astore_3
      15: aload_2
      16: invokeinterface #86,  1           // InterfaceMethod javax/servlet/http/HttpSession.getAttributeNames:()Ljava/util/Enumeration;
      21: astore        4
      23: aload         4
      25: ifnull        74
      28: aload         4
      30: invokeinterface #87,  1           // InterfaceMethod java/util/Enumeration.hasMoreElements:()Z
      35: ifeq          74
      38: aload         4
      40: invokeinterface #88,  1           // InterfaceMethod java/util/Enumeration.nextElement:()Ljava/lang/Object;
      45: checkcast     #89                 // class java/lang/String
      48: astore        5
      50: aload_2
      51: aload         5
      53: invokeinterface #90,  2           // InterfaceMethod javax/servlet/http/HttpSession.getAttribute:(Ljava/lang/String;)Ljava/lang/Object;
      58: astore        6
      60: aload_3
      61: aload         5
      63: aload         6
      65: invokeinterface #91,  3           // InterfaceMethod java/util/Map.put:(Ljava/lang/Object;Ljava/lang/Object;)Ljava/lang/Object;
      70: pop
      71: goto          23
      74: aload_2
      75: invokeinterface #92,  1           // InterfaceMethod javax/servlet/http/HttpSession.invalidate:()V
      80: aload_1
      81: invokeinterface #83,  1           // InterfaceMethod javax/servlet/http/HttpServletRequest.getSession:()Ljavax/servlet/http/HttpSession;
      86: astore        5
      88: invokestatic  #42                 // Method org/owasp/esapi/ESAPI.authenticator:()Lorg/owasp/esapi/Authenticator;
      91: invokeinterface #43,  1           // InterfaceMethod org/owasp/esapi/Authenticator.getCurrentUser:()Lorg/owasp/esapi/User;
      96: astore        6
      98: aload         6
     100: aload         5
     102: invokeinterface #93,  2           // InterfaceMethod org/owasp/esapi/User.addSession:(Ljavax/servlet/http/HttpSession;)V
     107: aload         6
     109: aload_2
     110: invokeinterface #94,  2           // InterfaceMethod org/owasp/esapi/User.removeSession:(Ljavax/servlet/http/HttpSession;)V
     115: aload_3
     116: invokeinterface #95,  1           // InterfaceMethod java/util/Map.entrySet:()Ljava/util/Set;
     121: invokeinterface #96,  1           // InterfaceMethod java/util/Set.iterator:()Ljava/util/Iterator;
     126: astore        7
     128: aload         7
     130: invokeinterface #97,  1           // InterfaceMethod java/util/Iterator.hasNext:()Z
     135: ifeq          177
     138: aload         7
     140: invokeinterface #98,  1           // InterfaceMethod java/util/Iterator.next:()Ljava/lang/Object;
     145: checkcast     #99                 // class java/util/Map$Entry
     148: astore        8
     150: aload         5
     152: aload         8
     154: invokeinterface #100,  1          // InterfaceMethod java/util/Map$Entry.getKey:()Ljava/lang/Object;
     159: checkcast     #89                 // class java/lang/String
     162: aload         8
     164: invokeinterface #101,  1          // InterfaceMethod java/util/Map$Entry.getValue:()Ljava/lang/Object;
     169: invokeinterface #102,  3          // InterfaceMethod javax/servlet/http/HttpSession.setAttribute:(Ljava/lang/String;Ljava/lang/Object;)V
     174: goto          128
     177: aload         5
     179: areturn

  public void clearCurrent();
    Code:
       0: aload_0
       1: getfield      #10                 // Field currentRequest:Lorg/owasp/esapi/reference/DefaultHTTPUtilities$ThreadLocalRequest;
       4: aconst_null
       5: invokevirtual #103                // Method org/owasp/esapi/reference/DefaultHTTPUtilities$ThreadLocalRequest.set:(Ljava/lang/Object;)V
       8: aload_0
       9: getfield      #13                 // Field currentResponse:Lorg/owasp/esapi/reference/DefaultHTTPUtilities$ThreadLocalResponse;
      12: aconst_null
      13: invokevirtual #104                // Method org/owasp/esapi/reference/DefaultHTTPUtilities$ThreadLocalResponse.set:(Ljava/lang/Object;)V
      16: return

  private java.lang.String createCookieHeader(java.lang.String, java.lang.String, int, java.lang.String, java.lang.String, boolean);
    Code:
       0: new           #45                 // class java/lang/StringBuilder
       3: dup
       4: invokespecial #46                 // Method java/lang/StringBuilder."<init>":()V
       7: aload_1
       8: invokevirtual #48                 // Method java/lang/StringBuilder.append:(Ljava/lang/String;)Ljava/lang/StringBuilder;
      11: ldc           #105                // String =
      13: invokevirtual #48                 // Method java/lang/StringBuilder.append:(Ljava/lang/String;)Ljava/lang/StringBuilder;
      16: aload_2
      17: invokevirtual #48                 // Method java/lang/StringBuilder.append:(Ljava/lang/String;)Ljava/lang/StringBuilder;
      20: invokevirtual #50                 // Method java/lang/StringBuilder.toString:()Ljava/lang/String;
      23: astore        7
      25: new           #45                 // class java/lang/StringBuilder
      28: dup
      29: invokespecial #46                 // Method java/lang/StringBuilder."<init>":()V
      32: aload         7
      34: invokevirtual #48                 // Method java/lang/StringBuilder.append:(Ljava/lang/String;)Ljava/lang/StringBuilder;
      37: ldc           #106                // String ; Max-Age=
      39: invokevirtual #48                 // Method java/lang/StringBuilder.append:(Ljava/lang/String;)Ljava/lang/StringBuilder;
      42: iload_3
      43: invokevirtual #107                // Method java/lang/StringBuilder.append:(I)Ljava/lang/StringBuilder;
      46: invokevirtual #50                 // Method java/lang/StringBuilder.toString:()Ljava/lang/String;
      49: astore        7
      51: aload         4
      53: ifnull        83
      56: new           #45                 // class java/lang/StringBuilder
      59: dup
      60: invokespecial #46                 // Method java/lang/StringBuilder."<init>":()V
      63: aload         7
      65: invokevirtual #48                 // Method java/lang/StringBuilder.append:(Ljava/lang/String;)Ljava/lang/StringBuilder;
      68: ldc           #108                // String ; Domain=
      70: invokevirtual #48                 // Method java/lang/StringBuilder.append:(Ljava/lang/String;)Ljava/lang/StringBuilder;
      73: aload         4
      75: invokevirtual #48                 // Method java/lang/StringBuilder.append:(Ljava/lang/String;)Ljava/lang/StringBuilder;
      78: invokevirtual #50                 // Method java/lang/StringBuilder.toString:()Ljava/lang/String;
      81: astore        7
      83: aload         5
      85: ifnull        115
      88: new           #45                 // class java/lang/StringBuilder
      91: dup
      92: invokespecial #46                 // Method java/lang/StringBuilder."<init>":()V
      95: aload         7
      97: invokevirtual #48                 // Method java/lang/StringBuilder.append:(Ljava/lang/String;)Ljava/lang/StringBuilder;
     100: ldc           #109                // String ; Path=
     102: invokevirtual #48                 // Method java/lang/StringBuilder.append:(Ljava/lang/String;)Ljava/lang/StringBuilder;
     105: aload         5
     107: invokevirtual #48                 // Method java/lang/StringBuilder.append:(Ljava/lang/String;)Ljava/lang/StringBuilder;
     110: invokevirtual #50                 // Method java/lang/StringBuilder.toString:()Ljava/lang/String;
     113: astore        7
     115: iload         6
     117: ifne          131
     120: invokestatic  #31                 // Method org/owasp/esapi/ESAPI.securityConfiguration:()Lorg/owasp/esapi/SecurityConfiguration;
     123: invokeinterface #36,  1           // InterfaceMethod org/owasp/esapi/SecurityConfiguration.getForceSecureCookies:()Z
     128: ifeq          153
     131: new           #45                 // class java/lang/StringBuilder
     134: dup
     135: invokespecial #46                 // Method java/lang/StringBuilder."<init>":()V
     138: aload         7
     140: invokevirtual #48                 // Method java/lang/StringBuilder.append:(Ljava/lang/String;)Ljava/lang/StringBuilder;
     143: ldc           #110                // String ; Secure
     145: invokevirtual #48                 // Method java/lang/StringBuilder.append:(Ljava/lang/String;)Ljava/lang/StringBuilder;
     148: invokevirtual #50                 // Method java/lang/StringBuilder.toString:()Ljava/lang/String;
     151: astore        7
     153: invokestatic  #31                 // Method org/owasp/esapi/ESAPI.securityConfiguration:()Lorg/owasp/esapi/SecurityConfiguration;
     156: invokeinterface #32,  1           // InterfaceMethod org/owasp/esapi/SecurityConfiguration.getForceHttpOnlyCookies:()Z
     161: ifeq          186
     164: new           #45                 // class java/lang/StringBuilder
     167: dup
     168: invokespecial #46                 // Method java/lang/StringBuilder."<init>":()V
     171: aload         7
     173: invokevirtual #48                 // Method java/lang/StringBuilder.append:(Ljava/lang/String;)Ljava/lang/StringBuilder;
     176: ldc           #111                // String ; HttpOnly
     178: invokevirtual #48                 // Method java/lang/StringBuilder.append:(Ljava/lang/String;)Ljava/lang/StringBuilder;
     181: invokevirtual #50                 // Method java/lang/StringBuilder.toString:()Ljava/lang/String;
     184: astore        7
     186: aload         7
     188: areturn

  public java.lang.String decryptHiddenField(java.lang.String);
    Code:
       0: aload_0
       1: aload_1
       2: invokespecial #112                // Method decryptString:(Ljava/lang/String;)Ljava/lang/String;
       5: areturn
       6: astore_2
       7: new           #114                // class org/owasp/esapi/errors/IntrusionException
      10: dup
      11: ldc           #115                // String Invalid request
      13: ldc           #116                // String Tampering detected. Hidden field data did not decrypt properly.
      15: aload_2
      16: invokespecial #117                // Method org/owasp/esapi/errors/IntrusionException."<init>":(Ljava/lang/String;Ljava/lang/String;Ljava/lang/Throwable;)V
      19: athrow
    Exception table:
       from    to  target type
           0     5     6   Class org/owasp/esapi/errors/EncryptionException

  public java.util.Map<java.lang.String, java.lang.String> decryptQueryString(java.lang.String) throws org.owasp.esapi.errors.EncryptionException;
    Code:
       0: aload_0
       1: aload_1
       2: invokespecial #112                // Method decryptString:(Ljava/lang/String;)Ljava/lang/String;
       5: astore_2
       6: aload_0
       7: aload_2
       8: invokespecial #118                // Method queryToMap:(Ljava/lang/String;)Ljava/util/Map;
      11: areturn

  public java.util.Map<java.lang.String, java.lang.String> decryptStateFromCookie() throws org.owasp.esapi.errors.EncryptionException;
    Code:
       0: aload_0
       1: aload_0
       2: invokevirtual #63                 // Method getCurrentRequest:()Ljavax/servlet/http/HttpServletRequest;
       5: invokevirtual #119                // Method decryptStateFromCookie:(Ljavax/servlet/http/HttpServletRequest;)Ljava/util/Map;
       8: areturn

  public java.util.Map<java.lang.String, java.lang.String> decryptStateFromCookie(javax.servlet.http.HttpServletRequest) throws org.owasp.esapi.errors.EncryptionException;
    Code:
       0: aload_0
       1: aload_1
       2: ldc           #120                // String estate
       4: invokevirtual #121                // Method getCookie:(Ljavax/servlet/http/HttpServletRequest;Ljava/lang/String;)Ljava/lang/String;
       7: astore_2
       8: aload_2
       9: ifnonnull     20
      12: new           #122                // class java/util/HashMap
      15: dup
      16: invokespecial #123                // Method java/util/HashMap."<init>":()V
      19: areturn
      20: aload_0
      21: aload_2
      22: invokespecial #112                // Method decryptString:(Ljava/lang/String;)Ljava/lang/String;
      25: astore_3
      26: aload_0
      27: aload_3
      28: invokespecial #118                // Method queryToMap:(Ljava/lang/String;)Ljava/util/Map;
      31: areturn
      32: astore_2
      33: aconst_null
      34: areturn
    Exception table:
       from    to  target type
           0    19    32   Class org/owasp/esapi/errors/ValidationException
          20    31    32   Class org/owasp/esapi/errors/ValidationException

  public java.lang.String encryptHiddenField(java.lang.String) throws org.owasp.esapi.errors.EncryptionException;
    Code:
       0: aload_0
       1: aload_1
       2: invokespecial #124                // Method encryptString:(Ljava/lang/String;)Ljava/lang/String;
       5: areturn

  public java.lang.String encryptQueryString(java.lang.String) throws org.owasp.esapi.errors.EncryptionException;
    Code:
       0: aload_0
       1: aload_1
       2: invokespecial #124                // Method encryptString:(Ljava/lang/String;)Ljava/lang/String;
       5: areturn

  public void encryptStateInCookie(javax.servlet.http.HttpServletResponse, java.util.Map<java.lang.String, java.lang.String>) throws org.owasp.esapi.errors.EncryptionException;
    Code:
       0: new           #45                 // class java/lang/StringBuilder
       3: dup
       4: invokespecial #46                 // Method java/lang/StringBuilder."<init>":()V
       7: astore_3
       8: aload_2
       9: invokeinterface #95,  1           // InterfaceMethod java/util/Map.entrySet:()Ljava/util/Set;
      14: invokeinterface #125,  1          // InterfaceMethod java/util/Set.iterator:()Ljava/util/Iterator;
      19: astore        4
      21: aload         4
      23: invokeinterface #97,  1           // InterfaceMethod java/util/Iterator.hasNext:()Z
      28: ifeq          141
      31: aload         4
      33: invokeinterface #98,  1           // InterfaceMethod java/util/Iterator.next:()Ljava/lang/Object;
      38: checkcast     #99                 // class java/util/Map$Entry
      41: astore        5
      43: invokestatic  #126                // Method org/owasp/esapi/ESAPI.encoder:()Lorg/owasp/esapi/Encoder;
      46: aload         5
      48: invokeinterface #100,  1          // InterfaceMethod java/util/Map$Entry.getKey:()Ljava/lang/Object;
      53: invokevirtual #127                // Method java/lang/Object.toString:()Ljava/lang/String;
      56: invokeinterface #128,  2          // InterfaceMethod org/owasp/esapi/Encoder.encodeForURL:(Ljava/lang/String;)Ljava/lang/String;
      61: astore        6
      63: invokestatic  #126                // Method org/owasp/esapi/ESAPI.encoder:()Lorg/owasp/esapi/Encoder;
      66: aload         5
      68: invokeinterface #101,  1          // InterfaceMethod java/util/Map$Entry.getValue:()Ljava/lang/Object;
      73: invokevirtual #127                // Method java/lang/Object.toString:()Ljava/lang/String;
      76: invokeinterface #128,  2          // InterfaceMethod org/owasp/esapi/Encoder.encodeForURL:(Ljava/lang/String;)Ljava/lang/String;
      81: astore        7
      83: aload_3
      84: aload         6
      86: invokevirtual #48                 // Method java/lang/StringBuilder.append:(Ljava/lang/String;)Ljava/lang/StringBuilder;
      89: ldc           #105                // String =
      91: invokevirtual #48                 // Method java/lang/StringBuilder.append:(Ljava/lang/String;)Ljava/lang/StringBuilder;
      94: aload         7
      96: invokevirtual #48                 // Method java/lang/StringBuilder.append:(Ljava/lang/String;)Ljava/lang/StringBuilder;
      99: pop
     100: aload         4
     102: invokeinterface #97,  1           // InterfaceMethod java/util/Iterator.hasNext:()Z
     107: ifeq          117
     110: aload_3
     111: ldc           #52                 // String &
     113: invokevirtual #48                 // Method java/lang/StringBuilder.append:(Ljava/lang/String;)Ljava/lang/StringBuilder;
     116: pop
     117: goto          21
     120: astore        5
     122: aload_0
     123: getfield      #7                  // Field logger:Lorg/owasp/esapi/Logger;
     126: getstatic     #39                 // Field org/owasp/esapi/Logger.SECURITY_FAILURE:Lorg/owasp/esapi/Logger$EventType;
     129: ldc           #130                // String Problem encrypting state in cookie - skipping entry
     131: aload         5
     133: invokeinterface #131,  4          // InterfaceMethod org/owasp/esapi/Logger.error:(Lorg/owasp/esapi/Logger$EventType;Ljava/lang/String;Ljava/lang/Throwable;)V
     138: goto          21
     141: aload_0
     142: aload_3
     143: invokevirtual #50                 // Method java/lang/StringBuilder.toString:()Ljava/lang/String;
     146: invokespecial #124                // Method encryptString:(Ljava/lang/String;)Ljava/lang/String;
     149: astore        5
     151: aload         5
     153: invokevirtual #132                // Method java/lang/String.length:()I
     156: sipush        4096
     159: if_icmple     220
     162: aload_0
     163: getfield      #7                  // Field logger:Lorg/owasp/esapi/Logger;
     166: getstatic     #39                 // Field org/owasp/esapi/Logger.SECURITY_FAILURE:Lorg/owasp/esapi/Logger$EventType;
     169: ldc           #130                // String Problem encrypting state in cookie - skipping entry
     171: invokeinterface #133,  3          // InterfaceMethod org/owasp/esapi/Logger.error:(Lorg/owasp/esapi/Logger$EventType;Ljava/lang/String;)V
     176: new           #113                // class org/owasp/esapi/errors/EncryptionException
     179: dup
     180: ldc           #134                // String Encryption failure
     182: new           #45                 // class java/lang/StringBuilder
     185: dup
     186: invokespecial #46                 // Method java/lang/StringBuilder."<init>":()V
     189: ldc           #135                // String Encrypted cookie state of
     191: invokevirtual #48                 // Method java/lang/StringBuilder.append:(Ljava/lang/String;)Ljava/lang/StringBuilder;
     194: aload         5
     196: invokevirtual #132                // Method java/lang/String.length:()I
     199: invokevirtual #107                // Method java/lang/StringBuilder.append:(I)Ljava/lang/StringBuilder;
     202: ldc           #136                // String  longer than allowed
     204: invokevirtual #48                 // Method java/lang/StringBuilder.append:(Ljava/lang/String;)Ljava/lang/StringBuilder;
     207: sipush        4096
     210: invokevirtual #107                // Method java/lang/StringBuilder.append:(I)Ljava/lang/StringBuilder;
     213: invokevirtual #50                 // Method java/lang/StringBuilder.toString:()Ljava/lang/String;
     216: invokespecial #137                // Method org/owasp/esapi/errors/EncryptionException."<init>":(Ljava/lang/String;Ljava/lang/String;)V
     219: athrow
     220: new           #138                // class javax/servlet/http/Cookie
     223: dup
     224: ldc           #120                // String estate
     226: aload         5
     228: invokespecial #139                // Method javax/servlet/http/Cookie."<init>":(Ljava/lang/String;Ljava/lang/String;)V
     231: astore        6
     233: aload_0
     234: aload_1
     235: aload         6
     237: invokevirtual #15                 // Method addCookie:(Ljavax/servlet/http/HttpServletResponse;Ljavax/servlet/http/Cookie;)V
     240: return
    Exception table:
       from    to  target type
          31   117   120   Class org/owasp/esapi/errors/EncodingException

  public void encryptStateInCookie(java.util.Map<java.lang.String, java.lang.String>) throws org.owasp.esapi.errors.EncryptionException;
    Code:
       0: aload_0
       1: aload_0
       2: invokevirtual #14                 // Method getCurrentResponse:()Ljavax/servlet/http/HttpServletResponse;
       5: aload_1
       6: invokevirtual #140                // Method encryptStateInCookie:(Ljavax/servlet/http/HttpServletResponse;Ljava/util/Map;)V
       9: return

  public java.lang.String getCookie(javax.servlet.http.HttpServletRequest, java.lang.String) throws org.owasp.esapi.errors.ValidationException;
    Code:
       0: aload_0
       1: aload_1
       2: aload_2
       3: invokespecial #141                // Method getFirstCookie:(Ljavax/servlet/http/HttpServletRequest;Ljava/lang/String;)Ljavax/servlet/http/Cookie;
       6: astore_3
       7: aload_3
       8: ifnonnull     13
      11: aconst_null
      12: areturn
      13: aload_3
      14: invokevirtual #17                 // Method javax/servlet/http/Cookie.getValue:()Ljava/lang/String;
      17: astore        4
      19: invokestatic  #24                 // Method org/owasp/esapi/ESAPI.validator:()Lorg/owasp/esapi/Validator;
      22: new           #45                 // class java/lang/StringBuilder
      25: dup
      26: invokespecial #46                 // Method java/lang/StringBuilder."<init>":()V
      29: ldc           #142                // String HTTP cookie value:
      31: invokevirtual #48                 // Method java/lang/StringBuilder.append:(Ljava/lang/String;)Ljava/lang/StringBuilder;
      34: aload         4
      36: invokevirtual #48                 // Method java/lang/StringBuilder.append:(Ljava/lang/String;)Ljava/lang/StringBuilder;
      39: invokevirtual #50                 // Method java/lang/StringBuilder.toString:()Ljava/lang/String;
      42: aload         4
      44: ldc           #29                 // String HTTPCookieValue
      46: sipush        1000
      49: iconst_0
      50: invokeinterface #57,  6           // InterfaceMethod org/owasp/esapi/Validator.getValidInput:(Ljava/lang/String;Ljava/lang/String;Ljava/lang/String;IZ)Ljava/lang/String;
      55: areturn

  public java.lang.String getCookie(java.lang.String) throws org.owasp.esapi.errors.ValidationException;
    Code:
       0: aload_0
       1: aload_0
       2: invokevirtual #63                 // Method getCurrentRequest:()Ljavax/servlet/http/HttpServletRequest;
       5: aload_1
       6: invokevirtual #121                // Method getCookie:(Ljavax/servlet/http/HttpServletRequest;Ljava/lang/String;)Ljava/lang/String;
       9: areturn

  public java.lang.String getCSRFToken();
    Code:
       0: invokestatic  #42                 // Method org/owasp/esapi/ESAPI.authenticator:()Lorg/owasp/esapi/Authenticator;
       3: invokeinterface #43,  1           // InterfaceMethod org/owasp/esapi/Authenticator.getCurrentUser:()Lorg/owasp/esapi/User;
       8: astore_1
       9: aload_1
      10: ifnonnull     15
      13: aconst_null
      14: areturn
      15: aload_1
      16: invokeinterface #49,  1           // InterfaceMethod org/owasp/esapi/User.getCSRFToken:()Ljava/lang/String;
      21: areturn

  public javax.servlet.http.HttpServletRequest getCurrentRequest();
    Code:
       0: aload_0
       1: getfield      #10                 // Field currentRequest:Lorg/owasp/esapi/reference/DefaultHTTPUtilities$ThreadLocalRequest;
       4: invokevirtual #143                // Method org/owasp/esapi/reference/DefaultHTTPUtilities$ThreadLocalRequest.getRequest:()Ljavax/servlet/http/HttpServletRequest;
       7: areturn

  public javax.servlet.http.HttpServletResponse getCurrentResponse();
    Code:
       0: aload_0
       1: getfield      #13                 // Field currentResponse:Lorg/owasp/esapi/reference/DefaultHTTPUtilities$ThreadLocalResponse;
       4: invokevirtual #144                // Method org/owasp/esapi/reference/DefaultHTTPUtilities$ThreadLocalResponse.getResponse:()Ljavax/servlet/http/HttpServletResponse;
       7: areturn

  public java.util.List<java.io.File> getFileUploads() throws org.owasp.esapi.errors.ValidationException;
    Code:
       0: aload_0
       1: aload_0
       2: invokevirtual #63                 // Method getCurrentRequest:()Ljavax/servlet/http/HttpServletRequest;
       5: invokestatic  #31                 // Method org/owasp/esapi/ESAPI.securityConfiguration:()Lorg/owasp/esapi/SecurityConfiguration;
       8: invokeinterface #145,  1          // InterfaceMethod org/owasp/esapi/SecurityConfiguration.getUploadDirectory:()Ljava/io/File;
      13: invokestatic  #31                 // Method org/owasp/esapi/ESAPI.securityConfiguration:()Lorg/owasp/esapi/SecurityConfiguration;
      16: invokeinterface #146,  1          // InterfaceMethod org/owasp/esapi/SecurityConfiguration.getAllowedFileExtensions:()Ljava/util/List;
      21: invokevirtual #147                // Method getFileUploads:(Ljavax/servlet/http/HttpServletRequest;Ljava/io/File;Ljava/util/List;)Ljava/util/List;
      24: areturn

  public java.util.List<java.io.File> getFileUploads(javax.servlet.http.HttpServletRequest) throws org.owasp.esapi.errors.ValidationException;
    Code:
       0: aload_0
       1: aload_1
       2: invokestatic  #31                 // Method org/owasp/esapi/ESAPI.securityConfiguration:()Lorg/owasp/esapi/SecurityConfiguration;
       5: invokeinterface #145,  1          // InterfaceMethod org/owasp/esapi/SecurityConfiguration.getUploadDirectory:()Ljava/io/File;
      10: invokestatic  #31                 // Method org/owasp/esapi/ESAPI.securityConfiguration:()Lorg/owasp/esapi/SecurityConfiguration;
      13: invokeinterface #146,  1          // InterfaceMethod org/owasp/esapi/SecurityConfiguration.getAllowedFileExtensions:()Ljava/util/List;
      18: invokevirtual #147                // Method getFileUploads:(Ljavax/servlet/http/HttpServletRequest;Ljava/io/File;Ljava/util/List;)Ljava/util/List;
      21: areturn

  public java.util.List<java.io.File> getFileUploads(javax.servlet.http.HttpServletRequest, java.io.File) throws org.owasp.esapi.errors.ValidationException;
    Code:
       0: aload_0
       1: aload_1
       2: aload_2
       3: invokestatic  #31                 // Method org/owasp/esapi/ESAPI.securityConfiguration:()Lorg/owasp/esapi/SecurityConfiguration;
       6: invokeinterface #146,  1          // InterfaceMethod org/owasp/esapi/SecurityConfiguration.getAllowedFileExtensions:()Ljava/util/List;
      11: invokevirtual #147                // Method getFileUploads:(Ljavax/servlet/http/HttpServletRequest;Ljava/io/File;Ljava/util/List;)Ljava/util/List;
      14: areturn

  public java.util.List<java.io.File> getFileUploads(javax.servlet.http.HttpServletRequest, java.io.File, java.util.List) throws org.owasp.esapi.errors.ValidationException;
    Code:
       0: invokestatic  #31                 // Method org/owasp/esapi/ESAPI.securityConfiguration:()Lorg/owasp/esapi/SecurityConfiguration;
       3: invokeinterface #148,  1          // InterfaceMethod org/owasp/esapi/SecurityConfiguration.getUploadTempDirectory:()Ljava/io/File;
       8: astore        4
      10: aload         4
      12: invokevirtual #149                // Method java/io/File.exists:()Z
      15: ifne          59
      18: aload         4
      20: invokevirtual #150                // Method java/io/File.mkdirs:()Z
      23: ifne          59
      26: new           #151                // class org/owasp/esapi/errors/ValidationUploadException
      29: dup
      30: ldc           #152                // String Upload failed
      32: new           #45                 // class java/lang/StringBuilder
      35: dup
      36: invokespecial #46                 // Method java/lang/StringBuilder."<init>":()V
      39: ldc           #153                // String Could not create temp directory:
      41: invokevirtual #48                 // Method java/lang/StringBuilder.append:(Ljava/lang/String;)Ljava/lang/StringBuilder;
      44: aload         4
      46: invokevirtual #154                // Method java/io/File.getAbsolutePath:()Ljava/lang/String;
      49: invokevirtual #48                 // Method java/lang/StringBuilder.append:(Ljava/lang/String;)Ljava/lang/StringBuilder;
      52: invokevirtual #50                 // Method java/lang/StringBuilder.toString:()Ljava/lang/String;
      55: invokespecial #155                // Method org/owasp/esapi/errors/ValidationUploadException."<init>":(Ljava/lang/String;Ljava/lang/String;)V
      58: athrow
      59: aload_2
      60: ifnull        109
      63: aload_2
      64: invokevirtual #149                // Method java/io/File.exists:()Z
      67: ifne          185
      70: aload_2
      71: invokevirtual #150                // Method java/io/File.mkdirs:()Z
      74: ifne          185
      77: new           #151                // class org/owasp/esapi/errors/ValidationUploadException
      80: dup
      81: ldc           #152                // String Upload failed
      83: new           #45                 // class java/lang/StringBuilder
      86: dup
      87: invokespecial #46                 // Method java/lang/StringBuilder."<init>":()V
      90: ldc           #156                // String Could not create final upload directory:
      92: invokevirtual #48                 // Method java/lang/StringBuilder.append:(Ljava/lang/String;)Ljava/lang/StringBuilder;
      95: aload_2
      96: invokevirtual #154                // Method java/io/File.getAbsolutePath:()Ljava/lang/String;
      99: invokevirtual #48                 // Method java/lang/StringBuilder.append:(Ljava/lang/String;)Ljava/lang/StringBuilder;
     102: invokevirtual #50                 // Method java/lang/StringBuilder.toString:()Ljava/lang/String;
     105: invokespecial #155                // Method org/owasp/esapi/errors/ValidationUploadException."<init>":(Ljava/lang/String;Ljava/lang/String;)V
     108: athrow
     109: invokestatic  #31                 // Method org/owasp/esapi/ESAPI.securityConfiguration:()Lorg/owasp/esapi/SecurityConfiguration;
     112: invokeinterface #145,  1          // InterfaceMethod org/owasp/esapi/SecurityConfiguration.getUploadDirectory:()Ljava/io/File;
     117: invokevirtual #149                // Method java/io/File.exists:()Z
     120: ifne          176
     123: invokestatic  #31                 // Method org/owasp/esapi/ESAPI.securityConfiguration:()Lorg/owasp/esapi/SecurityConfiguration;
     126: invokeinterface #145,  1          // InterfaceMethod org/owasp/esapi/SecurityConfiguration.getUploadDirectory:()Ljava/io/File;
     131: invokevirtual #150                // Method java/io/File.mkdirs:()Z
     134: ifne          176
     137: new           #151                // class org/owasp/esapi/errors/ValidationUploadException
     140: dup
     141: ldc           #152                // String Upload failed
     143: new           #45                 // class java/lang/StringBuilder
     146: dup
     147: invokespecial #46                 // Method java/lang/StringBuilder."<init>":()V
     150: ldc           #156                // String Could not create final upload directory:
     152: invokevirtual #48                 // Method java/lang/StringBuilder.append:(Ljava/lang/String;)Ljava/lang/StringBuilder;
     155: invokestatic  #31                 // Method org/owasp/esapi/ESAPI.securityConfiguration:()Lorg/owasp/esapi/SecurityConfiguration;
     158: invokeinterface #145,  1          // InterfaceMethod org/owasp/esapi/SecurityConfiguration.getUploadDirectory:()Ljava/io/File;
     163: invokevirtual #154                // Method java/io/File.getAbsolutePath:()Ljava/lang/String;
     166: invokevirtual #48                 // Method java/lang/StringBuilder.append:(Ljava/lang/String;)Ljava/lang/StringBuilder;
     169: invokevirtual #50                 // Method java/lang/StringBuilder.toString:()Ljava/lang/String;
     172: invokespecial #155                // Method org/owasp/esapi/errors/ValidationUploadException."<init>":(Ljava/lang/String;Ljava/lang/String;)V
     175: athrow
     176: invokestatic  #31                 // Method org/owasp/esapi/ESAPI.securityConfiguration:()Lorg/owasp/esapi/SecurityConfiguration;
     179: invokeinterface #145,  1          // InterfaceMethod org/owasp/esapi/SecurityConfiguration.getUploadDirectory:()Ljava/io/File;
     184: astore_2
     185: new           #157                // class java/util/ArrayList
     188: dup
     189: invokespecial #158                // Method java/util/ArrayList."<init>":()V
     192: astore        5
     194: aload_1
     195: iconst_0
     196: invokeinterface #159,  2          // InterfaceMethod javax/servlet/http/HttpServletRequest.getSession:(Z)Ljavax/servlet/http/HttpSession;
     201: astore        6
     203: aload_1
     204: invokestatic  #160                // Method org/apache/commons/fileupload/servlet/ServletFileUpload.isMultipartContent:(Ljavax/servlet/http/HttpServletRequest;)Z
     207: ifne          222
     210: new           #151                // class org/owasp/esapi/errors/ValidationUploadException
     213: dup
     214: ldc           #152                // String Upload failed
     216: ldc           #161                // String Not a multipart request
     218: invokespecial #155                // Method org/owasp/esapi/errors/ValidationUploadException."<init>":(Ljava/lang/String;Ljava/lang/String;)V
     221: athrow
     222: new           #162                // class org/apache/commons/fileupload/disk/DiskFileItemFactory
     225: dup
     226: iconst_0
     227: aload         4
     229: invokespecial #163                // Method org/apache/commons/fileupload/disk/DiskFileItemFactory."<init>":(ILjava/io/File;)V
     232: astore        7
     234: new           #164                // class org/apache/commons/fileupload/servlet/ServletFileUpload
     237: dup
     238: aload         7
     240: invokespecial #165                // Method org/apache/commons/fileupload/servlet/ServletFileUpload."<init>":(Lorg/apache/commons/fileupload/FileItemFactory;)V
     243: astore        8
     245: aload         8
     247: getstatic     #166                // Field maxBytes:I
     250: i2l
     251: invokevirtual #167                // Method org/apache/commons/fileupload/servlet/ServletFileUpload.setSizeMax:(J)V
     254: new           #168                // class org/owasp/esapi/reference/DefaultHTTPUtilities$1
     257: dup
     258: aload_0
     259: aload         6
     261: invokespecial #169                // Method org/owasp/esapi/reference/DefaultHTTPUtilities$1."<init>":(Lorg/owasp/esapi/reference/DefaultHTTPUtilities;Ljavax/servlet/http/HttpSession;)V
     264: astore        9
     266: aload         8
     268: aload         9
     270: invokevirtual #170                // Method org/apache/commons/fileupload/servlet/ServletFileUpload.setProgressListener:(Lorg/apache/commons/fileupload/ProgressListener;)V
     273: aload         8
     275: aload_1
     276: invokevirtual #171                // Method org/apache/commons/fileupload/servlet/ServletFileUpload.parseRequest:(Ljavax/servlet/http/HttpServletRequest;)Ljava/util/List;
     279: astore        10
     281: aload         10
     283: invokeinterface #172,  1          // InterfaceMethod java/util/List.iterator:()Ljava/util/Iterator;
     288: astore        11
     290: aload         11
     292: invokeinterface #97,  1           // InterfaceMethod java/util/Iterator.hasNext:()Z
     297: ifeq          625
     300: aload         11
     302: invokeinterface #98,  1           // InterfaceMethod java/util/Iterator.next:()Ljava/lang/Object;
     307: checkcast     #173                // class org/apache/commons/fileupload/FileItem
     310: astore        12
     312: aload         12
     314: invokeinterface #174,  1          // InterfaceMethod org/apache/commons/fileupload/FileItem.isFormField:()Z
     319: ifne          622
     322: aload         12
     324: invokeinterface #175,  1          // InterfaceMethod org/apache/commons/fileupload/FileItem.getName:()Ljava/lang/String;
     329: ifnull        622
     332: aload         12
     334: invokeinterface #175,  1          // InterfaceMethod org/apache/commons/fileupload/FileItem.getName:()Ljava/lang/String;
     339: ldc           #176                // String
     341: invokevirtual #78                 // Method java/lang/String.equals:(Ljava/lang/Object;)Z
     344: ifne          622
     347: aload         12
     349: invokeinterface #175,  1          // InterfaceMethod org/apache/commons/fileupload/FileItem.getName:()Ljava/lang/String;
     354: ldc           #177                // String [\\/\\\\]
     356: invokevirtual #178                // Method java/lang/String.split:(Ljava/lang/String;)[Ljava/lang/String;
     359: astore        13
     361: aload         13
     363: aload         13
     365: arraylength
     366: iconst_1
     367: isub
     368: aaload
     369: astore        14
     371: invokestatic  #24                 // Method org/owasp/esapi/ESAPI.validator:()Lorg/owasp/esapi/Validator;
     374: ldc           #179                // String upload
     376: aload         14
     378: aload_3
     379: iconst_0
     380: invokeinterface #180,  5          // InterfaceMethod org/owasp/esapi/Validator.isValidFileName:(Ljava/lang/String;Ljava/lang/String;Ljava/util/List;Z)Z
     385: ifne          417
     388: new           #151                // class org/owasp/esapi/errors/ValidationUploadException
     391: dup
     392: new           #45                 // class java/lang/StringBuilder
     395: dup
     396: invokespecial #46                 // Method java/lang/StringBuilder."<init>":()V
     399: ldc           #181                // String Upload only simple filenames with the following extensions
     401: invokevirtual #48                 // Method java/lang/StringBuilder.append:(Ljava/lang/String;)Ljava/lang/StringBuilder;
     404: aload_3
     405: invokevirtual #182                // Method java/lang/StringBuilder.append:(Ljava/lang/Object;)Ljava/lang/StringBuilder;
     408: invokevirtual #50                 // Method java/lang/StringBuilder.toString:()Ljava/lang/String;
     411: ldc           #183                // String Upload failed isValidFileName check
     413: invokespecial #155                // Method org/owasp/esapi/errors/ValidationUploadException."<init>":(Ljava/lang/String;Ljava/lang/String;)V
     416: athrow
     417: aload_0
     418: getfield      #7                  // Field logger:Lorg/owasp/esapi/Logger;
     421: getstatic     #184                // Field org/owasp/esapi/Logger.SECURITY_SUCCESS:Lorg/owasp/esapi/Logger$EventType;
     424: new           #45                 // class java/lang/StringBuilder
     427: dup
     428: invokespecial #46                 // Method java/lang/StringBuilder."<init>":()V
     431: ldc           #185                // String File upload requested:
     433: invokevirtual #48                 // Method java/lang/StringBuilder.append:(Ljava/lang/String;)Ljava/lang/StringBuilder;
     436: aload         14
     438: invokevirtual #48                 // Method java/lang/StringBuilder.append:(Ljava/lang/String;)Ljava/lang/StringBuilder;
     441: invokevirtual #50                 // Method java/lang/StringBuilder.toString:()Ljava/lang/String;
     444: invokeinterface #186,  3          // InterfaceMethod org/owasp/esapi/Logger.info:(Lorg/owasp/esapi/Logger$EventType;Ljava/lang/String;)V
     449: new           #187                // class java/io/File
     452: dup
     453: aload_2
     454: aload         14
     456: invokespecial #188                // Method java/io/File."<init>":(Ljava/io/File;Ljava/lang/String;)V
     459: astore        15
     461: aload         15
     463: invokevirtual #149                // Method java/io/File.exists:()Z
     466: ifeq          546
     469: aload         14
     471: ldc           #189                // String \\/.
     473: invokevirtual #178                // Method java/lang/String.split:(Ljava/lang/String;)[Ljava/lang/String;
     476: astore        16
     478: ldc           #176                // String
     480: astore        17
     482: aload         16
     484: arraylength
     485: iconst_1
     486: if_icmple     499
     489: aload         16
     491: aload         16
     493: arraylength
     494: iconst_1
     495: isub
     496: aaload
     497: astore        17
     499: aload         14
     501: iconst_0
     502: aload         14
     504: invokevirtual #132                // Method java/lang/String.length:()I
     507: aload         17
     509: invokevirtual #132                // Method java/lang/String.length:()I
     512: isub
     513: invokevirtual #190                // Method java/lang/String.substring:(II)Ljava/lang/String;
     516: astore        18
     518: aload         18
     520: new           #45                 // class java/lang/StringBuilder
     523: dup
     524: invokespecial #46                 // Method java/lang/StringBuilder."<init>":()V
     527: ldc           #191                // String .
     529: invokevirtual #48                 // Method java/lang/StringBuilder.append:(Ljava/lang/String;)Ljava/lang/StringBuilder;
     532: aload         17
     534: invokevirtual #48                 // Method java/lang/StringBuilder.append:(Ljava/lang/String;)Ljava/lang/StringBuilder;
     537: invokevirtual #50                 // Method java/lang/StringBuilder.toString:()Ljava/lang/String;
     540: aload_2
     541: invokestatic  #192                // Method java/io/File.createTempFile:(Ljava/lang/String;Ljava/lang/String;Ljava/io/File;)Ljava/io/File;
     544: astore        15
     546: aload         12
     548: aload         15
     550: invokeinterface #193,  2          // InterfaceMethod org/apache/commons/fileupload/FileItem.write:(Ljava/io/File;)V
     555: aload         5
     557: aload         15
     559: invokeinterface #194,  2          // InterfaceMethod java/util/List.add:(Ljava/lang/Object;)Z
     564: pop
     565: aload         12
     567: invokeinterface #195,  1          // InterfaceMethod org/apache/commons/fileupload/FileItem.delete:()V
     572: aload_0
     573: getfield      #7                  // Field logger:Lorg/owasp/esapi/Logger;
     576: getstatic     #184                // Field org/owasp/esapi/Logger.SECURITY_SUCCESS:Lorg/owasp/esapi/Logger$EventType;
     579: new           #45                 // class java/lang/StringBuilder
     582: dup
     583: invokespecial #46                 // Method java/lang/StringBuilder."<init>":()V
     586: ldc           #196                // String File successfully uploaded:
     588: invokevirtual #48                 // Method java/lang/StringBuilder.append:(Ljava/lang/String;)Ljava/lang/StringBuilder;
     591: aload         15
     593: invokevirtual #182                // Method java/lang/StringBuilder.append:(Ljava/lang/Object;)Ljava/lang/StringBuilder;
     596: invokevirtual #50                 // Method java/lang/StringBuilder.toString:()Ljava/lang/String;
     599: invokeinterface #197,  3          // InterfaceMethod org/owasp/esapi/Logger.fatal:(Lorg/owasp/esapi/Logger$EventType;Ljava/lang/String;)V
     604: aload         6
     606: ifnull        622
     609: aload         6
     611: ldc           #198                // String progress
     613: lconst_0
     614: invokestatic  #199                // Method java/lang/Long.toString:(J)Ljava/lang/String;
     617: invokeinterface #102,  3          // InterfaceMethod javax/servlet/http/HttpSession.setAttribute:(Ljava/lang/String;Ljava/lang/Object;)V
     622: goto          290
     625: goto          679
     628: astore        6
     630: aload         6
     632: instanceof    #151                // class org/owasp/esapi/errors/ValidationUploadException
     635: ifeq          644
     638: aload         6
     640: checkcast     #60                 // class org/owasp/esapi/errors/ValidationException
     643: athrow
     644: new           #151                // class org/owasp/esapi/errors/ValidationUploadException
     647: dup
     648: ldc           #201                // String Upload failure
     650: new           #45                 // class java/lang/StringBuilder
     653: dup
     654: invokespecial #46                 // Method java/lang/StringBuilder."<init>":()V
     657: ldc           #202                // String Problem during upload:
     659: invokevirtual #48                 // Method java/lang/StringBuilder.append:(Ljava/lang/String;)Ljava/lang/StringBuilder;
     662: aload         6
     664: invokevirtual #203                // Method java/lang/Exception.getMessage:()Ljava/lang/String;
     667: invokevirtual #48                 // Method java/lang/StringBuilder.append:(Ljava/lang/String;)Ljava/lang/StringBuilder;
     670: invokevirtual #50                 // Method java/lang/StringBuilder.toString:()Ljava/lang/String;
     673: aload         6
     675: invokespecial #204                // Method org/owasp/esapi/errors/ValidationUploadException."<init>":(Ljava/lang/String;Ljava/lang/String;Ljava/lang/Throwable;)V
     678: athrow
     679: aload         5
     681: invokestatic  #205                // Method java/util/Collections.synchronizedList:(Ljava/util/List;)Ljava/util/List;
     684: areturn
    Exception table:
       from    to  target type
         194   625   628   Class java/lang/Exception

  private javax.servlet.http.Cookie getFirstCookie(javax.servlet.http.HttpServletRequest, java.lang.String);
    Code:
       0: aload_1
       1: invokeinterface #206,  1          // InterfaceMethod javax/servlet/http/HttpServletRequest.getCookies:()[Ljavax/servlet/http/Cookie;
       6: astore_3
       7: aload_3
       8: ifnull        57
      11: aload_3
      12: astore        4
      14: aload         4
      16: arraylength
      17: istore        5
      19: iconst_0
      20: istore        6
      22: iload         6
      24: iload         5
      26: if_icmpge     57
      29: aload         4
      31: iload         6
      33: aaload
      34: astore        7
      36: aload         7
      38: invokevirtual #16                 // Method javax/servlet/http/Cookie.getName:()Ljava/lang/String;
      41: aload_2
      42: invokevirtual #78                 // Method java/lang/String.equals:(Ljava/lang/Object;)Z
      45: ifeq          51
      48: aload         7
      50: areturn
      51: iinc          6, 1
      54: goto          22
      57: aconst_null
      58: areturn

  public java.lang.String getHeader(javax.servlet.http.HttpServletRequest, java.lang.String) throws org.owasp.esapi.errors.ValidationException;
    Code:
       0: aload_1
       1: aload_2
       2: invokeinterface #207,  2          // InterfaceMethod javax/servlet/http/HttpServletRequest.getHeader:(Ljava/lang/String;)Ljava/lang/String;
       7: astore_3
       8: invokestatic  #24                 // Method org/owasp/esapi/ESAPI.validator:()Lorg/owasp/esapi/Validator;
      11: new           #45                 // class java/lang/StringBuilder
      14: dup
      15: invokespecial #46                 // Method java/lang/StringBuilder."<init>":()V
      18: ldc           #208                // String HTTP header value:
      20: invokevirtual #48                 // Method java/lang/StringBuilder.append:(Ljava/lang/String;)Ljava/lang/StringBuilder;
      23: aload_3
      24: invokevirtual #48                 // Method java/lang/StringBuilder.append:(Ljava/lang/String;)Ljava/lang/StringBuilder;
      27: invokevirtual #50                 // Method java/lang/StringBuilder.toString:()Ljava/lang/String;
      30: aload_3
      31: ldc           #58                 // String HTTPHeaderValue
      33: sipush        150
      36: iconst_0
      37: invokeinterface #57,  6           // InterfaceMethod org/owasp/esapi/Validator.getValidInput:(Ljava/lang/String;Ljava/lang/String;Ljava/lang/String;IZ)Ljava/lang/String;
      42: areturn

  public java.lang.String getHeader(java.lang.String) throws org.owasp.esapi.errors.ValidationException;
    Code:
       0: aload_0
       1: aload_0
       2: invokevirtual #63                 // Method getCurrentRequest:()Ljavax/servlet/http/HttpServletRequest;
       5: aload_1
       6: invokevirtual #209                // Method getHeader:(Ljavax/servlet/http/HttpServletRequest;Ljava/lang/String;)Ljava/lang/String;
       9: areturn

  public java.lang.String getParameter(javax.servlet.http.HttpServletRequest, java.lang.String) throws org.owasp.esapi.errors.ValidationException;
    Code:
       0: aload_1
       1: aload_2
       2: invokeinterface #210,  2          // InterfaceMethod javax/servlet/http/HttpServletRequest.getParameter:(Ljava/lang/String;)Ljava/lang/String;
       7: astore_3
       8: invokestatic  #24                 // Method org/owasp/esapi/ESAPI.validator:()Lorg/owasp/esapi/Validator;
      11: new           #45                 // class java/lang/StringBuilder
      14: dup
      15: invokespecial #46                 // Method java/lang/StringBuilder."<init>":()V
      18: ldc           #211                // String HTTP parameter value:
      20: invokevirtual #48                 // Method java/lang/StringBuilder.append:(Ljava/lang/String;)Ljava/lang/StringBuilder;
      23: aload_3
      24: invokevirtual #48                 // Method java/lang/StringBuilder.append:(Ljava/lang/String;)Ljava/lang/StringBuilder;
      27: invokevirtual #50                 // Method java/lang/StringBuilder.toString:()Ljava/lang/String;
      30: aload_3
      31: ldc           #212                // String HTTPParameterValue
      33: sipush        2000
      36: iconst_1
      37: invokeinterface #57,  6           // InterfaceMethod org/owasp/esapi/Validator.getValidInput:(Ljava/lang/String;Ljava/lang/String;Ljava/lang/String;IZ)Ljava/lang/String;
      42: areturn

  public java.lang.String getParameter(java.lang.String) throws org.owasp.esapi.errors.ValidationException;
    Code:
       0: aload_0
       1: aload_0
       2: invokevirtual #63                 // Method getCurrentRequest:()Ljavax/servlet/http/HttpServletRequest;
       5: aload_1
       6: invokevirtual #213                // Method getParameter:(Ljavax/servlet/http/HttpServletRequest;Ljava/lang/String;)Ljava/lang/String;
       9: areturn

  public void killAllCookies();
    Code:
       0: aload_0
       1: aload_0
       2: invokevirtual #63                 // Method getCurrentRequest:()Ljavax/servlet/http/HttpServletRequest;
       5: aload_0
       6: invokevirtual #14                 // Method getCurrentResponse:()Ljavax/servlet/http/HttpServletResponse;
       9: invokevirtual #214                // Method killAllCookies:(Ljavax/servlet/http/HttpServletRequest;Ljavax/servlet/http/HttpServletResponse;)V
      12: return

  public void killAllCookies(javax.servlet.http.HttpServletRequest, javax.servlet.http.HttpServletResponse);
    Code:
       0: aload_1
       1: invokeinterface #206,  1          // InterfaceMethod javax/servlet/http/HttpServletRequest.getCookies:()[Ljavax/servlet/http/Cookie;
       6: astore_3
       7: aload_3
       8: ifnull        53
      11: aload_3
      12: astore        4
      14: aload         4
      16: arraylength
      17: istore        5
      19: iconst_0
      20: istore        6
      22: iload         6
      24: iload         5
      26: if_icmpge     53
      29: aload         4
      31: iload         6
      33: aaload
      34: astore        7
      36: aload_0
      37: aload_1
      38: aload_2
      39: aload         7
      41: invokevirtual #16                 // Method javax/servlet/http/Cookie.getName:()Ljava/lang/String;
      44: invokevirtual #215                // Method killCookie:(Ljavax/servlet/http/HttpServletRequest;Ljavax/servlet/http/HttpServletResponse;Ljava/lang/String;)V
      47: iinc          6, 1
      50: goto          22
      53: return

  public void killCookie(javax.servlet.http.HttpServletRequest, javax.servlet.http.HttpServletResponse, java.lang.String);
    Code:
       0: ldc           #216                // String //
       2: astore        4
       4: ldc           #176                // String
       6: astore        5
       8: aload_0
       9: aload_1
      10: aload_3
      11: invokespecial #141                // Method getFirstCookie:(Ljavax/servlet/http/HttpServletRequest;Ljava/lang/String;)Ljavax/servlet/http/Cookie;
      14: astore        6
      16: aload         6
      18: ifnull        35
      21: aload         6
      23: invokevirtual #20                 // Method javax/servlet/http/Cookie.getPath:()Ljava/lang/String;
      26: astore        4
      28: aload         6
      30: invokevirtual #19                 // Method javax/servlet/http/Cookie.getDomain:()Ljava/lang/String;
      33: astore        5
      35: new           #138                // class javax/servlet/http/Cookie
      38: dup
      39: aload_3
      40: ldc           #217                // String deleted
      42: invokespecial #139                // Method javax/servlet/http/Cookie."<init>":(Ljava/lang/String;Ljava/lang/String;)V
      45: astore        7
      47: aload         7
      49: iconst_0
      50: invokevirtual #218                // Method javax/servlet/http/Cookie.setMaxAge:(I)V
      53: aload         5
      55: ifnull        65
      58: aload         7
      60: aload         5
      62: invokevirtual #219                // Method javax/servlet/http/Cookie.setDomain:(Ljava/lang/String;)V
      65: aload         4
      67: ifnull        77
      70: aload         7
      72: aload         4
      74: invokevirtual #220                // Method javax/servlet/http/Cookie.setPath:(Ljava/lang/String;)V
      77: aload_2
      78: aload         7
      80: invokeinterface #38,  2           // InterfaceMethod javax/servlet/http/HttpServletResponse.addCookie:(Ljavax/servlet/http/Cookie;)V
      85: return

  public void killCookie(java.lang.String);
    Code:
       0: aload_0
       1: aload_0
       2: invokevirtual #63                 // Method getCurrentRequest:()Ljavax/servlet/http/HttpServletRequest;
       5: aload_0
       6: invokevirtual #14                 // Method getCurrentResponse:()Ljavax/servlet/http/HttpServletResponse;
       9: aload_1
      10: invokevirtual #215                // Method killCookie:(Ljavax/servlet/http/HttpServletRequest;Ljavax/servlet/http/HttpServletResponse;Ljava/lang/String;)V
      13: return

  public void logHTTPRequest();
    Code:
       0: aload_0
       1: aload_0
       2: invokevirtual #63                 // Method getCurrentRequest:()Ljavax/servlet/http/HttpServletRequest;
       5: aload_0
       6: getfield      #7                  // Field logger:Lorg/owasp/esapi/Logger;
       9: aconst_null
      10: invokevirtual #221                // Method logHTTPRequest:(Ljavax/servlet/http/HttpServletRequest;Lorg/owasp/esapi/Logger;Ljava/util/List;)V
      13: return

  public void logHTTPRequest(javax.servlet.http.HttpServletRequest, org.owasp.esapi.Logger);
    Code:
       0: aload_0
       1: aload_1
       2: aload_2
       3: aconst_null
       4: invokevirtual #221                // Method logHTTPRequest:(Ljavax/servlet/http/HttpServletRequest;Lorg/owasp/esapi/Logger;Ljava/util/List;)V
       7: return

  public void logHTTPRequest(javax.servlet.http.HttpServletRequest, org.owasp.esapi.Logger, java.util.List);
    Code:
       0: new           #45                 // class java/lang/StringBuilder
       3: dup
       4: invokespecial #46                 // Method java/lang/StringBuilder."<init>":()V
       7: astore        4
       9: aload_1
      10: invokeinterface #222,  1          // InterfaceMethod javax/servlet/http/HttpServletRequest.getParameterMap:()Ljava/util/Map;
      15: invokeinterface #223,  1          // InterfaceMethod java/util/Map.keySet:()Ljava/util/Set;
      20: invokeinterface #125,  1          // InterfaceMethod java/util/Set.iterator:()Ljava/util/Iterator;
      25: astore        5
      27: aload         5
      29: invokeinterface #97,  1           // InterfaceMethod java/util/Iterator.hasNext:()Z
      34: ifeq          176
      37: aload         5
      39: invokeinterface #98,  1           // InterfaceMethod java/util/Iterator.next:()Ljava/lang/Object;
      44: checkcast     #89                 // class java/lang/String
      47: astore        6
      49: aload_1
      50: invokeinterface #222,  1          // InterfaceMethod javax/servlet/http/HttpServletRequest.getParameterMap:()Ljava/util/Map;
      55: aload         6
      57: invokeinterface #224,  2          // InterfaceMethod java/util/Map.get:(Ljava/lang/Object;)Ljava/lang/Object;
      62: checkcast     #225                // class "[Ljava/lang/String;"
      65: checkcast     #225                // class "[Ljava/lang/String;"
      68: astore        7
      70: iconst_0
      71: istore        8
      73: iload         8
      75: aload         7
      77: arraylength
      78: if_icmpge     155
      81: aload         4
      83: aload         6
      85: invokevirtual #48                 // Method java/lang/StringBuilder.append:(Ljava/lang/String;)Ljava/lang/StringBuilder;
      88: ldc           #105                // String =
      90: invokevirtual #48                 // Method java/lang/StringBuilder.append:(Ljava/lang/String;)Ljava/lang/StringBuilder;
      93: pop
      94: aload_3
      95: ifnull        120
      98: aload_3
      99: aload         6
     101: invokeinterface #226,  2          // InterfaceMethod java/util/List.contains:(Ljava/lang/Object;)Z
     106: ifeq          120
     109: aload         4
     111: ldc           #227                // String ********
     113: invokevirtual #48                 // Method java/lang/StringBuilder.append:(Ljava/lang/String;)Ljava/lang/StringBuilder;
     116: pop
     117: goto          131
     120: aload         4
     122: aload         7
     124: iload         8
     126: aaload
     127: invokevirtual #48                 // Method java/lang/StringBuilder.append:(Ljava/lang/String;)Ljava/lang/StringBuilder;
     130: pop
     131: iload         8
     133: aload         7
     135: arraylength
     136: iconst_1
     137: isub
     138: if_icmpge     149
     141: aload         4
     143: ldc           #52                 // String &
     145: invokevirtual #48                 // Method java/lang/StringBuilder.append:(Ljava/lang/String;)Ljava/lang/StringBuilder;
     148: pop
     149: iinc          8, 1
     152: goto          73
     155: aload         5
     157: invokeinterface #97,  1           // InterfaceMethod java/util/Iterator.hasNext:()Z
     162: ifeq          173
     165: aload         4
     167: ldc           #52                 // String &
     169: invokevirtual #48                 // Method java/lang/StringBuilder.append:(Ljava/lang/String;)Ljava/lang/StringBuilder;
     172: pop
     173: goto          27
     176: aload_1
     177: invokeinterface #206,  1          // InterfaceMethod javax/servlet/http/HttpServletRequest.getCookies:()[Ljavax/servlet/http/Cookie;
     182: astore        6
     184: aload         6
     186: ifnull        269
     189: aload         6
     191: astore        7
     193: aload         7
     195: arraylength
     196: istore        8
     198: iconst_0
     199: istore        9
     201: iload         9
     203: iload         8
     205: if_icmpge     269
     208: aload         7
     210: iload         9
     212: aaload
     213: astore        10
     215: aload         10
     217: invokevirtual #16                 // Method javax/servlet/http/Cookie.getName:()Ljava/lang/String;
     220: invokestatic  #31                 // Method org/owasp/esapi/ESAPI.securityConfiguration:()Lorg/owasp/esapi/SecurityConfiguration;
     223: invokeinterface #228,  1          // InterfaceMethod org/owasp/esapi/SecurityConfiguration.getHttpSessionIdName:()Ljava/lang/String;
     228: invokevirtual #78                 // Method java/lang/String.equals:(Ljava/lang/Object;)Z
     231: ifne          263
     234: aload         4
     236: ldc           #229                // String +
     238: invokevirtual #48                 // Method java/lang/StringBuilder.append:(Ljava/lang/String;)Ljava/lang/StringBuilder;
     241: aload         10
     243: invokevirtual #16                 // Method javax/servlet/http/Cookie.getName:()Ljava/lang/String;
     246: invokevirtual #48                 // Method java/lang/StringBuilder.append:(Ljava/lang/String;)Ljava/lang/StringBuilder;
     249: ldc           #105                // String =
     251: invokevirtual #48                 // Method java/lang/StringBuilder.append:(Ljava/lang/String;)Ljava/lang/StringBuilder;
     254: aload         10
     256: invokevirtual #17                 // Method javax/servlet/http/Cookie.getValue:()Ljava/lang/String;
     259: invokevirtual #48                 // Method java/lang/StringBuilder.append:(Ljava/lang/String;)Ljava/lang/StringBuilder;
     262: pop
     263: iinc          9, 1
     266: goto          201
     269: new           #45                 // class java/lang/StringBuilder
     272: dup
     273: invokespecial #46                 // Method java/lang/StringBuilder."<init>":()V
     276: aload_1
     277: invokeinterface #76,  1           // InterfaceMethod javax/servlet/http/HttpServletRequest.getMethod:()Ljava/lang/String;
     282: invokevirtual #48                 // Method java/lang/StringBuilder.append:(Ljava/lang/String;)Ljava/lang/StringBuilder;
     285: ldc           #230                // String
     287: invokevirtual #48                 // Method java/lang/StringBuilder.append:(Ljava/lang/String;)Ljava/lang/StringBuilder;
     290: aload_1
     291: invokeinterface #69,  1           // InterfaceMethod javax/servlet/http/HttpServletRequest.getRequestURL:()Ljava/lang/StringBuffer;
     296: invokevirtual #182                // Method java/lang/StringBuilder.append:(Ljava/lang/Object;)Ljava/lang/StringBuilder;
     299: aload         4
     301: invokevirtual #231                // Method java/lang/StringBuilder.length:()I
     304: ifle          330
     307: new           #45                 // class java/lang/StringBuilder
     310: dup
     311: invokespecial #46                 // Method java/lang/StringBuilder."<init>":()V
     314: ldc           #53                 // String ?
     316: invokevirtual #48                 // Method java/lang/StringBuilder.append:(Ljava/lang/String;)Ljava/lang/StringBuilder;
     319: aload         4
     321: invokevirtual #182                // Method java/lang/StringBuilder.append:(Ljava/lang/Object;)Ljava/lang/StringBuilder;
     324: invokevirtual #50                 // Method java/lang/StringBuilder.toString:()Ljava/lang/String;
     327: goto          332
     330: ldc           #176                // String
     332: invokevirtual #48                 // Method java/lang/StringBuilder.append:(Ljava/lang/String;)Ljava/lang/StringBuilder;
     335: invokevirtual #50                 // Method java/lang/StringBuilder.toString:()Ljava/lang/String;
     338: astore        7
     340: aload_2
     341: getstatic     #184                // Field org/owasp/esapi/Logger.SECURITY_SUCCESS:Lorg/owasp/esapi/Logger$EventType;
     344: aload         7
     346: invokeinterface #186,  3          // InterfaceMethod org/owasp/esapi/Logger.info:(Lorg/owasp/esapi/Logger$EventType;Ljava/lang/String;)V
     351: return

  private java.util.Map<java.lang.String, java.lang.String> queryToMap(java.lang.String);
    Code:
       0: new           #232                // class java/util/TreeMap
       3: dup
       4: invokespecial #233                // Method java/util/TreeMap."<init>":()V
       7: astore_2
       8: aload_1
       9: ldc           #52                 // String &
      11: invokevirtual #178                // Method java/lang/String.split:(Ljava/lang/String;)[Ljava/lang/String;
      14: astore_3
      15: aload_3
      16: astore        4
      18: aload         4
      20: arraylength
      21: istore        5
      23: iconst_0
      24: istore        6
      26: iload         6
      28: iload         5
      30: if_icmpge     97
      33: aload         4
      35: iload         6
      37: aaload
      38: astore        7
      40: aload         7
      42: ldc           #105                // String =
      44: invokevirtual #178                // Method java/lang/String.split:(Ljava/lang/String;)[Ljava/lang/String;
      47: astore        8
      49: invokestatic  #126                // Method org/owasp/esapi/ESAPI.encoder:()Lorg/owasp/esapi/Encoder;
      52: aload         8
      54: iconst_0
      55: aaload
      56: invokeinterface #234,  2          // InterfaceMethod org/owasp/esapi/Encoder.decodeFromURL:(Ljava/lang/String;)Ljava/lang/String;
      61: astore        9
      63: invokestatic  #126                // Method org/owasp/esapi/ESAPI.encoder:()Lorg/owasp/esapi/Encoder;
      66: aload         8
      68: iconst_1
      69: aaload
      70: invokeinterface #234,  2          // InterfaceMethod org/owasp/esapi/Encoder.decodeFromURL:(Ljava/lang/String;)Ljava/lang/String;
      75: astore        10
      77: aload_2
      78: aload         9
      80: aload         10
      82: invokevirtual #235                // Method java/util/TreeMap.put:(Ljava/lang/Object;Ljava/lang/Object;)Ljava/lang/Object;
      85: pop
      86: goto          91
      89: astore        8
      91: iinc          6, 1
      94: goto          26
      97: aload_2
      98: areturn
    Exception table:
       from    to  target type
          40    86    89   Class org/owasp/esapi/errors/EncodingException

  public void sendForward(javax.servlet.http.HttpServletRequest, javax.servlet.http.HttpServletResponse, java.lang.String) throws org.owasp.esapi.errors.AccessControlException, javax.servlet.ServletException, java.io.IOException;
    Code:
       0: aload_3
       1: ldc           #236                // String WEB-INF
       3: invokevirtual #73                 // Method java/lang/String.startsWith:(Ljava/lang/String;)Z
       6: ifne          38
       9: new           #65                 // class org/owasp/esapi/errors/AccessControlException
      12: dup
      13: ldc           #237                // String Forward failed
      15: new           #45                 // class java/lang/StringBuilder
      18: dup
      19: invokespecial #46                 // Method java/lang/StringBuilder."<init>":()V
      22: ldc           #238                // String Bad forward location:
      24: invokevirtual #48                 // Method java/lang/StringBuilder.append:(Ljava/lang/String;)Ljava/lang/StringBuilder;
      27: aload_3
      28: invokevirtual #48                 // Method java/lang/StringBuilder.append:(Ljava/lang/String;)Ljava/lang/StringBuilder;
      31: invokevirtual #50                 // Method java/lang/StringBuilder.toString:()Ljava/lang/String;
      34: invokespecial #68                 // Method org/owasp/esapi/errors/AccessControlException."<init>":(Ljava/lang/String;Ljava/lang/String;)V
      37: athrow
      38: aload_1
      39: aload_3
      40: invokeinterface #239,  2          // InterfaceMethod javax/servlet/http/HttpServletRequest.getRequestDispatcher:(Ljava/lang/String;)Ljavax/servlet/RequestDispatcher;
      45: astore        4
      47: aload         4
      49: aload_1
      50: aload_2
      51: invokeinterface #240,  3          // InterfaceMethod javax/servlet/RequestDispatcher.forward:(Ljavax/servlet/ServletRequest;Ljavax/servlet/ServletResponse;)V
      56: return

  public void sendForward(java.lang.String) throws org.owasp.esapi.errors.AccessControlException, javax.servlet.ServletException, java.io.IOException;
    Code:
       0: aload_0
       1: aload_0
       2: invokevirtual #63                 // Method getCurrentRequest:()Ljavax/servlet/http/HttpServletRequest;
       5: aload_0
       6: invokevirtual #14                 // Method getCurrentResponse:()Ljavax/servlet/http/HttpServletResponse;
       9: aload_1
      10: invokevirtual #241                // Method sendForward:(Ljavax/servlet/http/HttpServletRequest;Ljavax/servlet/http/HttpServletResponse;Ljava/lang/String;)V
      13: return

  public void sendRedirect(javax.servlet.http.HttpServletResponse, java.lang.String) throws org.owasp.esapi.errors.AccessControlException, java.io.IOException;
    Code:
       0: invokestatic  #24                 // Method org/owasp/esapi/ESAPI.validator:()Lorg/owasp/esapi/Validator;
       3: ldc           #242                // String Redirect
       5: aload_2
       6: iconst_0
       7: invokeinterface #243,  4          // InterfaceMethod org/owasp/esapi/Validator.isValidRedirectLocation:(Ljava/lang/String;Ljava/lang/String;Z)Z
      12: ifne          56
      15: aload_0
      16: getfield      #7                  // Field logger:Lorg/owasp/esapi/Logger;
      19: getstatic     #39                 // Field org/owasp/esapi/Logger.SECURITY_FAILURE:Lorg/owasp/esapi/Logger$EventType;
      22: new           #45                 // class java/lang/StringBuilder
      25: dup
      26: invokespecial #46                 // Method java/lang/StringBuilder."<init>":()V
      29: ldc           #244                // String Bad redirect location:
      31: invokevirtual #48                 // Method java/lang/StringBuilder.append:(Ljava/lang/String;)Ljava/lang/StringBuilder;
      34: aload_2
      35: invokevirtual #48                 // Method java/lang/StringBuilder.append:(Ljava/lang/String;)Ljava/lang/StringBuilder;
      38: invokevirtual #50                 // Method java/lang/StringBuilder.toString:()Ljava/lang/String;
      41: invokeinterface #197,  3          // InterfaceMethod org/owasp/esapi/Logger.fatal:(Lorg/owasp/esapi/Logger$EventType;Ljava/lang/String;)V
      46: new           #245                // class java/io/IOException
      49: dup
      50: ldc           #246                // String Redirect failed
      52: invokespecial #247                // Method java/io/IOException."<init>":(Ljava/lang/String;)V
      55: athrow
      56: aload_1
      57: aload_2
      58: invokeinterface #248,  2          // InterfaceMethod javax/servlet/http/HttpServletResponse.sendRedirect:(Ljava/lang/String;)V
      63: return

  public void sendRedirect(java.lang.String) throws org.owasp.esapi.errors.AccessControlException, java.io.IOException;
    Code:
       0: aload_0
       1: aload_0
       2: invokevirtual #14                 // Method getCurrentResponse:()Ljavax/servlet/http/HttpServletResponse;
       5: aload_1
       6: invokevirtual #249                // Method sendRedirect:(Ljavax/servlet/http/HttpServletResponse;Ljava/lang/String;)V
       9: return

  public void setContentType();
    Code:
       0: aload_0
       1: aload_0
       2: invokevirtual #14                 // Method getCurrentResponse:()Ljavax/servlet/http/HttpServletResponse;
       5: invokevirtual #250                // Method setContentType:(Ljavax/servlet/http/HttpServletResponse;)V
       8: return

  public void setContentType(javax.servlet.http.HttpServletResponse);
    Code:
       0: aload_1
       1: invokestatic  #31                 // Method org/owasp/esapi/ESAPI.securityConfiguration:()Lorg/owasp/esapi/SecurityConfiguration;
       4: invokeinterface #251,  1          // InterfaceMethod org/owasp/esapi/SecurityConfiguration.getResponseContentType:()Ljava/lang/String;
       9: invokeinterface #252,  2          // InterfaceMethod javax/servlet/http/HttpServletResponse.setContentType:(Ljava/lang/String;)V
      14: return

  public void setCurrentHTTP(javax.servlet.http.HttpServletRequest, javax.servlet.http.HttpServletResponse);
    Code:
       0: aload_0
       1: getfield      #10                 // Field currentRequest:Lorg/owasp/esapi/reference/DefaultHTTPUtilities$ThreadLocalRequest;
       4: aload_1
       5: invokevirtual #253                // Method org/owasp/esapi/reference/DefaultHTTPUtilities$ThreadLocalRequest.setRequest:(Ljavax/servlet/http/HttpServletRequest;)V
       8: aload_0
       9: getfield      #13                 // Field currentResponse:Lorg/owasp/esapi/reference/DefaultHTTPUtilities$ThreadLocalResponse;
      12: aload_2
      13: invokevirtual #254                // Method org/owasp/esapi/reference/DefaultHTTPUtilities$ThreadLocalResponse.setResponse:(Ljavax/servlet/http/HttpServletResponse;)V
      16: return

  public void setHeader(javax.servlet.http.HttpServletResponse, java.lang.String, java.lang.String);
    Code:
       0: aload_2
       1: invokestatic  #54                 // Method org/owasp/esapi/StringUtilities.replaceLinearWhiteSpace:(Ljava/lang/String;)Ljava/lang/String;
       4: astore        4
       6: aload_3
       7: invokestatic  #54                 // Method org/owasp/esapi/StringUtilities.replaceLinearWhiteSpace:(Ljava/lang/String;)Ljava/lang/String;
      10: astore        5
      12: invokestatic  #24                 // Method org/owasp/esapi/ESAPI.validator:()Lorg/owasp/esapi/Validator;
      15: ldc           #255                // String setHeader
      17: aload         4
      19: ldc           #56                 // String HTTPHeaderName
      21: bipush        20
      23: iconst_0
      24: invokeinterface #57,  6           // InterfaceMethod org/owasp/esapi/Validator.getValidInput:(Ljava/lang/String;Ljava/lang/String;Ljava/lang/String;IZ)Ljava/lang/String;
      29: astore        6
      31: invokestatic  #24                 // Method org/owasp/esapi/ESAPI.validator:()Lorg/owasp/esapi/Validator;
      34: ldc           #255                // String setHeader
      36: aload         5
      38: ldc           #58                 // String HTTPHeaderValue
      40: sipush        500
      43: iconst_0
      44: invokeinterface #57,  6           // InterfaceMethod org/owasp/esapi/Validator.getValidInput:(Ljava/lang/String;Ljava/lang/String;Ljava/lang/String;IZ)Ljava/lang/String;
      49: astore        7
      51: aload_1
      52: aload         6
      54: aload         7
      56: invokeinterface #256,  3          // InterfaceMethod javax/servlet/http/HttpServletResponse.setHeader:(Ljava/lang/String;Ljava/lang/String;)V
      61: goto          83
      64: astore        4
      66: aload_0
      67: getfield      #7                  // Field logger:Lorg/owasp/esapi/Logger;
      70: getstatic     #39                 // Field org/owasp/esapi/Logger.SECURITY_FAILURE:Lorg/owasp/esapi/Logger$EventType;
      73: ldc_w         #257                // String Attempt to set invalid header denied
      76: aload         4
      78: invokeinterface #62,  4           // InterfaceMethod org/owasp/esapi/Logger.warning:(Lorg/owasp/esapi/Logger$EventType;Ljava/lang/String;Ljava/lang/Throwable;)V
      83: return
    Exception table:
       from    to  target type
           0    61    64   Class org/owasp/esapi/errors/ValidationException

  public void setHeader(java.lang.String, java.lang.String);
    Code:
       0: aload_0
       1: aload_0
       2: invokevirtual #14                 // Method getCurrentResponse:()Ljavax/servlet/http/HttpServletResponse;
       5: aload_1
       6: aload_2
       7: invokevirtual #258                // Method setHeader:(Ljavax/servlet/http/HttpServletResponse;Ljava/lang/String;Ljava/lang/String;)V
      10: return

  public void setNoCacheHeaders();
    Code:
       0: aload_0
       1: aload_0
       2: invokevirtual #14                 // Method getCurrentResponse:()Ljavax/servlet/http/HttpServletResponse;
       5: invokevirtual #259                // Method setNoCacheHeaders:(Ljavax/servlet/http/HttpServletResponse;)V
       8: return

  public void setNoCacheHeaders(javax.servlet.http.HttpServletResponse);
    Code:
       0: aload_1
       1: ldc_w         #260                // String Cache-Control
       4: ldc_w         #261                // String no-store, no-cache, must-revalidate
       7: invokeinterface #256,  3          // InterfaceMethod javax/servlet/http/HttpServletResponse.setHeader:(Ljava/lang/String;Ljava/lang/String;)V
      12: aload_1
      13: ldc_w         #262                // String Pragma
      16: ldc_w         #263                // String no-cache
      19: invokeinterface #256,  3          // InterfaceMethod javax/servlet/http/HttpServletResponse.setHeader:(Ljava/lang/String;Ljava/lang/String;)V
      24: aload_1
      25: ldc_w         #264                // String Expires
      28: ldc2_w        #265                // long -1l
      31: invokeinterface #267,  4          // InterfaceMethod javax/servlet/http/HttpServletResponse.setDateHeader:(Ljava/lang/String;J)V
      36: return

  public java.lang.String setRememberToken(javax.servlet.http.HttpServletRequest, javax.servlet.http.HttpServletResponse, java.lang.String, int, java.lang.String, java.lang.String);
    Code:
       0: invokestatic  #42                 // Method org/owasp/esapi/ESAPI.authenticator:()Lorg/owasp/esapi/Authenticator;
       3: invokeinterface #43,  1           // InterfaceMethod org/owasp/esapi/Authenticator.getCurrentUser:()Lorg/owasp/esapi/User;
       8: astore        7
      10: aload_0
      11: aload_1
      12: aload_2
      13: ldc_w         #268                // String rtoken
      16: invokevirtual #215                // Method killCookie:(Ljavax/servlet/http/HttpServletRequest;Ljavax/servlet/http/HttpServletResponse;Ljava/lang/String;)V
      19: new           #45                 // class java/lang/StringBuilder
      22: dup
      23: invokespecial #46                 // Method java/lang/StringBuilder."<init>":()V
      26: aload         7
      28: invokeinterface #269,  1          // InterfaceMethod org/owasp/esapi/User.getAccountName:()Ljava/lang/String;
      33: invokevirtual #48                 // Method java/lang/StringBuilder.append:(Ljava/lang/String;)Ljava/lang/StringBuilder;
      36: ldc_w         #270                // String |
      39: invokevirtual #48                 // Method java/lang/StringBuilder.append:(Ljava/lang/String;)Ljava/lang/StringBuilder;
      42: aload_3
      43: invokevirtual #48                 // Method java/lang/StringBuilder.append:(Ljava/lang/String;)Ljava/lang/StringBuilder;
      46: invokevirtual #50                 // Method java/lang/StringBuilder.toString:()Ljava/lang/String;
      49: astore        8
      51: invokestatic  #271                // Method org/owasp/esapi/ESAPI.encryptor:()Lorg/owasp/esapi/Encryptor;
      54: iload         4
      56: sipush        1000
      59: imul
      60: i2l
      61: invokeinterface #272,  3          // InterfaceMethod org/owasp/esapi/Encryptor.getRelativeTimeStamp:(J)J
      66: lstore        9
      68: invokestatic  #271                // Method org/owasp/esapi/ESAPI.encryptor:()Lorg/owasp/esapi/Encryptor;
      71: aload         8
      73: lload         9
      75: invokeinterface #273,  4          // InterfaceMethod org/owasp/esapi/Encryptor.seal:(Ljava/lang/String;J)Ljava/lang/String;
      80: astore        11
      82: new           #138                // class javax/servlet/http/Cookie
      85: dup
      86: ldc_w         #268                // String rtoken
      89: aload         11
      91: invokespecial #139                // Method javax/servlet/http/Cookie."<init>":(Ljava/lang/String;Ljava/lang/String;)V
      94: astore        12
      96: aload         12
      98: iload         4
     100: invokevirtual #218                // Method javax/servlet/http/Cookie.setMaxAge:(I)V
     103: aload         12
     105: aload         5
     107: invokevirtual #219                // Method javax/servlet/http/Cookie.setDomain:(Ljava/lang/String;)V
     110: aload         12
     112: aload         6
     114: invokevirtual #220                // Method javax/servlet/http/Cookie.setPath:(Ljava/lang/String;)V
     117: aload_2
     118: aload         12
     120: invokeinterface #38,  2           // InterfaceMethod javax/servlet/http/HttpServletResponse.addCookie:(Ljavax/servlet/http/Cookie;)V
     125: aload_0
     126: getfield      #7                  // Field logger:Lorg/owasp/esapi/Logger;
     129: getstatic     #184                // Field org/owasp/esapi/Logger.SECURITY_SUCCESS:Lorg/owasp/esapi/Logger$EventType;
     132: new           #45                 // class java/lang/StringBuilder
     135: dup
     136: invokespecial #46                 // Method java/lang/StringBuilder."<init>":()V
     139: ldc_w         #274                // String Enabled remember me token for
     142: invokevirtual #48                 // Method java/lang/StringBuilder.append:(Ljava/lang/String;)Ljava/lang/StringBuilder;
     145: aload         7
     147: invokeinterface #269,  1          // InterfaceMethod org/owasp/esapi/User.getAccountName:()Ljava/lang/String;
     152: invokevirtual #48                 // Method java/lang/StringBuilder.append:(Ljava/lang/String;)Ljava/lang/StringBuilder;
     155: invokevirtual #50                 // Method java/lang/StringBuilder.toString:()Ljava/lang/String;
     158: invokeinterface #186,  3          // InterfaceMethod org/owasp/esapi/Logger.info:(Lorg/owasp/esapi/Logger$EventType;Ljava/lang/String;)V
     163: aload         11
     165: areturn
     166: astore        8
     168: aload_0
     169: getfield      #7                  // Field logger:Lorg/owasp/esapi/Logger;
     172: getstatic     #39                 // Field org/owasp/esapi/Logger.SECURITY_FAILURE:Lorg/owasp/esapi/Logger$EventType;
     175: new           #45                 // class java/lang/StringBuilder
     178: dup
     179: invokespecial #46                 // Method java/lang/StringBuilder."<init>":()V
     182: ldc_w         #276                // String Attempt to set remember me token failed for
     185: invokevirtual #48                 // Method java/lang/StringBuilder.append:(Ljava/lang/String;)Ljava/lang/StringBuilder;
     188: aload         7
     190: invokeinterface #269,  1          // InterfaceMethod org/owasp/esapi/User.getAccountName:()Ljava/lang/String;
     195: invokevirtual #48                 // Method java/lang/StringBuilder.append:(Ljava/lang/String;)Ljava/lang/StringBuilder;
     198: invokevirtual #50                 // Method java/lang/StringBuilder.toString:()Ljava/lang/String;
     201: aload         8
     203: invokeinterface #62,  4           // InterfaceMethod org/owasp/esapi/Logger.warning:(Lorg/owasp/esapi/Logger$EventType;Ljava/lang/String;Ljava/lang/Throwable;)V
     208: aconst_null
     209: areturn
    Exception table:
       from    to  target type
          10   165   166   Class org/owasp/esapi/errors/IntegrityException

  public java.lang.String setRememberToken(java.lang.String, int, java.lang.String, java.lang.String);
    Code:
       0: aload_0
       1: aload_0
       2: invokevirtual #63                 // Method getCurrentRequest:()Ljavax/servlet/http/HttpServletRequest;
       5: aload_0
       6: invokevirtual #14                 // Method getCurrentResponse:()Ljavax/servlet/http/HttpServletResponse;
       9: aload_1
      10: iload_2
      11: aload_3
      12: aload         4
      14: invokevirtual #277                // Method setRememberToken:(Ljavax/servlet/http/HttpServletRequest;Ljavax/servlet/http/HttpServletResponse;Ljava/lang/String;ILjava/lang/String;Ljava/lang/String;)Ljava/lang/String;
      17: areturn

  public void verifyCSRFToken() throws org.owasp.esapi.errors.IntrusionException;
    Code:
       0: aload_0
       1: aload_0
       2: invokevirtual #63                 // Method getCurrentRequest:()Ljavax/servlet/http/HttpServletRequest;
       5: invokevirtual #278                // Method verifyCSRFToken:(Ljavax/servlet/http/HttpServletRequest;)V
       8: return

  public void verifyCSRFToken(javax.servlet.http.HttpServletRequest) throws org.owasp.esapi.errors.IntrusionException;
    Code:
       0: invokestatic  #42                 // Method org/owasp/esapi/ESAPI.authenticator:()Lorg/owasp/esapi/Authenticator;
       3: invokeinterface #43,  1           // InterfaceMethod org/owasp/esapi/Authenticator.getCurrentUser:()Lorg/owasp/esapi/User;
       8: astore_2
       9: aload_1
      10: aload_2
      11: invokeinterface #49,  1           // InterfaceMethod org/owasp/esapi/User.getCSRFToken:()Ljava/lang/String;
      16: invokeinterface #279,  2          // InterfaceMethod javax/servlet/http/HttpServletRequest.getAttribute:(Ljava/lang/String;)Ljava/lang/Object;
      21: ifnull        25
      24: return
      25: aload_1
      26: ldc_w         #280                // String ctoken
      29: invokeinterface #210,  2          // InterfaceMethod javax/servlet/http/HttpServletRequest.getParameter:(Ljava/lang/String;)Ljava/lang/String;
      34: astore_3
      35: aload_2
      36: invokeinterface #49,  1           // InterfaceMethod org/owasp/esapi/User.getCSRFToken:()Ljava/lang/String;
      41: aload_3
      42: invokevirtual #78                 // Method java/lang/String.equals:(Ljava/lang/Object;)Z
      45: ifne          62
      48: new           #114                // class org/owasp/esapi/errors/IntrusionException
      51: dup
      52: ldc_w         #281                // String Authentication failed
      55: ldc_w         #282                // String Possibly forged HTTP request without proper CSRF token detected
      58: invokespecial #283                // Method org/owasp/esapi/errors/IntrusionException."<init>":(Ljava/lang/String;Ljava/lang/String;)V
      61: athrow
      62: return

  public <T> T getSessionAttribute(java.lang.String);
    Code:
       0: invokestatic  #284                // Method org/owasp/esapi/ESAPI.currentRequest:()Ljavax/servlet/http/HttpServletRequest;
       3: iconst_0
       4: invokeinterface #159,  2          // InterfaceMethod javax/servlet/http/HttpServletRequest.getSession:(Z)Ljavax/servlet/http/HttpSession;
       9: astore_2
      10: aload_2
      11: ifnull        22
      14: aload_2
      15: aload_1
      16: invokeinterface #90,  2           // InterfaceMethod javax/servlet/http/HttpSession.getAttribute:(Ljava/lang/String;)Ljava/lang/Object;
      21: areturn
      22: aconst_null
      23: areturn

  public <T> T getSessionAttribute(javax.servlet.http.HttpSession, java.lang.String);
    Code:
       0: aload_1
       1: aload_2
       2: invokeinterface #90,  2           // InterfaceMethod javax/servlet/http/HttpSession.getAttribute:(Ljava/lang/String;)Ljava/lang/Object;
       7: areturn

  public <T> T getRequestAttribute(java.lang.String);
    Code:
       0: invokestatic  #284                // Method org/owasp/esapi/ESAPI.currentRequest:()Ljavax/servlet/http/HttpServletRequest;
       3: aload_1
       4: invokeinterface #279,  2          // InterfaceMethod javax/servlet/http/HttpServletRequest.getAttribute:(Ljava/lang/String;)Ljava/lang/Object;
       9: areturn

  public <T> T getRequestAttribute(javax.servlet.http.HttpServletRequest, java.lang.String);
    Code:
       0: aload_1
       1: aload_2
       2: invokeinterface #279,  2          // InterfaceMethod javax/servlet/http/HttpServletRequest.getAttribute:(Ljava/lang/String;)Ljava/lang/Object;
       7: areturn

  private java.lang.String encryptString(java.lang.String) throws org.owasp.esapi.errors.EncryptionException;
    Code:
       0: new           #285                // class org/owasp/esapi/crypto/PlainText
       3: dup
       4: aload_1
       5: invokespecial #286                // Method org/owasp/esapi/crypto/PlainText."<init>":(Ljava/lang/String;)V
       8: astore_2
       9: invokestatic  #271                // Method org/owasp/esapi/ESAPI.encryptor:()Lorg/owasp/esapi/Encryptor;
      12: aload_2
      13: invokeinterface #287,  2          // InterfaceMethod org/owasp/esapi/Encryptor.encrypt:(Lorg/owasp/esapi/crypto/PlainText;)Lorg/owasp/esapi/crypto/CipherText;
      18: astore_3
      19: aload_3
      20: invokevirtual #288                // Method org/owasp/esapi/crypto/CipherText.asPortableSerializedByteArray:()[B
      23: astore        4
      25: aload         4
      27: iconst_0
      28: invokestatic  #289                // Method org/owasp/esapi/codecs/Hex.encode:([BZ)Ljava/lang/String;
      31: areturn

  private java.lang.String decryptString(java.lang.String) throws org.owasp.esapi.errors.EncryptionException;
    Code:
       0: aload_1
       1: invokestatic  #290                // Method org/owasp/esapi/codecs/Hex.decode:(Ljava/lang/String;)[B
       4: astore_2
       5: aload_2
       6: invokestatic  #291                // Method org/owasp/esapi/crypto/CipherText.fromPortableSerializedBytes:([B)Lorg/owasp/esapi/crypto/CipherText;
       9: astore_3
      10: invokestatic  #271                // Method org/owasp/esapi/ESAPI.encryptor:()Lorg/owasp/esapi/Encryptor;
      13: aload_3
      14: invokeinterface #292,  2          // InterfaceMethod org/owasp/esapi/Encryptor.decrypt:(Lorg/owasp/esapi/crypto/CipherText;)Lorg/owasp/esapi/crypto/PlainText;
      19: astore        4
      21: aload         4
      23: invokevirtual #293                // Method org/owasp/esapi/crypto/PlainText.toString:()Ljava/lang/String;
      26: areturn

  static {};
    Code:
       0: aconst_null
       1: putstatic     #1                  // Field instance:Lorg/owasp/esapi/HTTPUtilities;
       4: invokestatic  #31                 // Method org/owasp/esapi/ESAPI.securityConfiguration:()Lorg/owasp/esapi/SecurityConfiguration;
       7: invokeinterface #294,  1          // InterfaceMethod org/owasp/esapi/SecurityConfiguration.getAllowedFileUploadSize:()I
      12: putstatic     #166                // Field maxBytes:I
      15: return
}
