Compiled from "AutoValue_FieldStatsResult.java"
final class org.graylog2.rest.models.search.responses.AutoValue_FieldStatsResult extends org.graylog2.rest.models.search.responses.$AutoValue_FieldStatsResult {
  org.graylog2.rest.models.search.responses.AutoValue_FieldStatsResult(long, long, double, double, double, double, double, double, double, java.lang.String, long);
    Code:
       0: aload_0
       1: lload_1
       2: lload_3
       3: dload         5
       5: dload         7
       7: dload         9
       9: dload         11
      11: dload         13
      13: dload         15
      15: dload         17
      17: aload         19
      19: lload         20
      21: invokespecial #1                  // Method org/graylog2/rest/models/search/responses/$AutoValue_FieldStatsResult."<init>":(JJDDDDDDDLjava/lang/String;J)V
      24: return

  public final long getTime();
    Code:
       0: aload_0
       1: invokevirtual #2                  // Method time:()J
       4: lreturn

  public final long getCount();
    Code:
       0: aload_0
       1: invokevirtual #3                  // Method count:()J
       4: lreturn

  public final double getSum();
    Code:
       0: aload_0
       1: invokevirtual #4                  // Method sum:()D
       4: dreturn

  public final double getSumOfSquares();
    Code:
       0: aload_0
       1: invokevirtual #5                  // Method sumOfSquares:()D
       4: dreturn

  public final double getMean();
    Code:
       0: aload_0
       1: invokevirtual #6                  // Method mean:()D
       4: dreturn

  public final double getMin();
    Code:
       0: aload_0
       1: invokevirtual #7                  // Method min:()D
       4: dreturn

  public final double getMax();
    Code:
       0: aload_0
       1: invokevirtual #8                  // Method max:()D
       4: dreturn

  public final double getVariance();
    Code:
       0: aload_0
       1: invokevirtual #9                  // Method variance:()D
       4: dreturn

  public final double getStdDeviation();
    Code:
       0: aload_0
       1: invokevirtual #10                 // Method stdDeviation:()D
       4: dreturn

  public final java.lang.String getBuiltQuery();
    Code:
       0: aload_0
       1: invokevirtual #11                 // Method builtQuery:()Ljava/lang/String;
       4: areturn

  public final long getCardinality();
    Code:
       0: aload_0
       1: invokevirtual #12                 // Method cardinality:()J
       4: lreturn
}
