Compiled from "AutoValue_HistogramResult.java"
final class org.graylog2.rest.models.search.responses.AutoValue_HistogramResult extends org.graylog2.rest.models.search.responses.$AutoValue_HistogramResult {
  org.graylog2.rest.models.search.responses.AutoValue_HistogramResult(java.lang.String, java.util.Map, long, java.lang.String, org.graylog2.rest.models.search.responses.TimeRange);
    Code:
       0: aload_0
       1: aload_1
       2: aload_2
       3: lload_3
       4: aload         5
       6: aload         6
       8: invokespecial #1                  // Method org/graylog2/rest/models/search/responses/$AutoValue_HistogramResult."<init>":(Ljava/lang/String;Ljava/util/Map;JLjava/lang/String;Lorg/graylog2/rest/models/search/responses/TimeRange;)V
      11: return

  public final java.lang.String getInterval();
    Code:
       0: aload_0
       1: invokevirtual #2                  // Method interval:()Ljava/lang/String;
       4: areturn

  public final java.util.Map getResults();
    Code:
       0: aload_0
       1: invokevirtual #3                  // Method results:()Ljava/util/Map;
       4: areturn

  public final long getTime();
    Code:
       0: aload_0
       1: invokevirtual #4                  // Method time:()J
       4: lreturn

  public final java.lang.String getBuiltQuery();
    Code:
       0: aload_0
       1: invokevirtual #5                  // Method builtQuery:()Ljava/lang/String;
       4: areturn

  public final org.graylog2.rest.models.search.responses.TimeRange getQueriedTimerange();
    Code:
       0: aload_0
       1: invokevirtual #6                  // Method queriedTimerange:()Lorg/graylog2/rest/models/search/responses/TimeRange;
       4: areturn
}
