Compiled from "StreamWrapper.java"
public class org.postgresql.util.StreamWrapper {
  private static final int MAX_MEMORY_BUFFER_BYTES;

  private static final java.lang.String TEMP_FILE_PREFIX;

  private final java.io.InputStream stream;

  private final byte[] rawData;

  private final int offset;

  private final int length;

  public org.postgresql.util.StreamWrapper(byte[], int, int);
    Code:
       0: aload_0
       1: invokespecial #2                  // Method java/lang/Object."<init>":()V
       4: aload_0
       5: aconst_null
       6: putfield      #3                  // Field stream:Ljava/io/InputStream;
       9: aload_0
      10: aload_1
      11: putfield      #4                  // Field rawData:[B
      14: aload_0
      15: iload_2
      16: putfield      #5                  // Field offset:I
      19: aload_0
      20: iload_3
      21: putfield      #1                  // Field length:I
      24: return

  public org.postgresql.util.StreamWrapper(java.io.InputStream, int);
    Code:
       0: aload_0
       1: invokespecial #2                  // Method java/lang/Object."<init>":()V
       4: aload_0
       5: aload_1
       6: putfield      #3                  // Field stream:Ljava/io/InputStream;
       9: aload_0
      10: aconst_null
      11: putfield      #4                  // Field rawData:[B
      14: aload_0
      15: iconst_0
      16: putfield      #5                  // Field offset:I
      19: aload_0
      20: iload_2
      21: putfield      #1                  // Field length:I
      24: return

  public org.postgresql.util.StreamWrapper(java.io.InputStream) throws org.postgresql.util.PSQLException;
    Code:
       0: aload_0
       1: invokespecial #2                  // Method java/lang/Object."<init>":()V
       4: new           #6                  // class java/io/ByteArrayOutputStream
       7: dup
       8: invokespecial #7                  // Method java/io/ByteArrayOutputStream."<init>":()V
      11: astore_2
      12: aload_1
      13: aload_2
      14: ldc           #9                  // int 51200
      16: invokestatic  #10                 // Method copyStream:(Ljava/io/InputStream;Ljava/io/OutputStream;I)I
      19: istore_3
      20: aload_2
      21: invokevirtual #11                 // Method java/io/ByteArrayOutputStream.toByteArray:()[B
      24: astore        4
      26: iload_3
      27: iconst_m1
      28: if_icmpne     159
      31: ldc           #12                 // String postgres-pgjdbc-stream
      33: aconst_null
      34: invokestatic  #13                 // Method java/io/File.createTempFile:(Ljava/lang/String;Ljava/lang/String;)Ljava/io/File;
      37: astore        6
      39: new           #14                 // class java/io/FileOutputStream
      42: dup
      43: aload         6
      45: invokespecial #15                 // Method java/io/FileOutputStream."<init>":(Ljava/io/File;)V
      48: astore        7
      50: aload         7
      52: aload         4
      54: invokevirtual #16                 // Method java/io/FileOutputStream.write:([B)V
      57: aload_1
      58: aload         7
      60: ldc           #18                 // int 2147483647
      62: aload         4
      64: arraylength
      65: isub
      66: invokestatic  #10                 // Method copyStream:(Ljava/io/InputStream;Ljava/io/OutputStream;I)I
      69: istore        5
      71: iload         5
      73: iconst_m1
      74: if_icmpne     97
      77: new           #19                 // class org/postgresql/util/PSQLException
      80: dup
      81: ldc           #20                 // String Object is too large to send over the protocol.
      83: iconst_0
      84: anewarray     #21                 // class java/lang/Object
      87: invokestatic  #22                 // Method org/postgresql/util/GT.tr:(Ljava/lang/String;[Ljava/lang/Object;)Ljava/lang/String;
      90: getstatic     #23                 // Field org/postgresql/util/PSQLState.NUMERIC_CONSTANT_OUT_OF_RANGE:Lorg/postgresql/util/PSQLState;
      93: invokespecial #24                 // Method org/postgresql/util/PSQLException."<init>":(Ljava/lang/String;Lorg/postgresql/util/PSQLState;)V
      96: athrow
      97: aload         7
      99: invokevirtual #25                 // Method java/io/FileOutputStream.flush:()V
     102: aload         7
     104: invokevirtual #26                 // Method java/io/FileOutputStream.close:()V
     107: goto          120
     110: astore        8
     112: aload         7
     114: invokevirtual #26                 // Method java/io/FileOutputStream.close:()V
     117: aload         8
     119: athrow
     120: aload_0
     121: iconst_0
     122: putfield      #5                  // Field offset:I
     125: aload_0
     126: aload         4
     128: arraylength
     129: iload         5
     131: iadd
     132: putfield      #1                  // Field length:I
     135: aload_0
     136: aconst_null
     137: putfield      #4                  // Field rawData:[B
     140: aload_0
     141: new           #27                 // class org/postgresql/util/StreamWrapper$1
     144: dup
     145: aload_0
     146: aload         6
     148: aload         6
     150: invokespecial #28                 // Method org/postgresql/util/StreamWrapper$1."<init>":(Lorg/postgresql/util/StreamWrapper;Ljava/io/File;Ljava/io/File;)V
     153: putfield      #3                  // Field stream:Ljava/io/InputStream;
     156: goto          182
     159: aload_0
     160: aload         4
     162: putfield      #4                  // Field rawData:[B
     165: aload_0
     166: aconst_null
     167: putfield      #3                  // Field stream:Ljava/io/InputStream;
     170: aload_0
     171: iconst_0
     172: putfield      #5                  // Field offset:I
     175: aload_0
     176: aload         4
     178: arraylength
     179: putfield      #1                  // Field length:I
     182: goto          207
     185: astore_2
     186: new           #19                 // class org/postgresql/util/PSQLException
     189: dup
     190: ldc           #30                 // String An I/O error occurred while sending to the backend.
     192: iconst_0
     193: anewarray     #21                 // class java/lang/Object
     196: invokestatic  #22                 // Method org/postgresql/util/GT.tr:(Ljava/lang/String;[Ljava/lang/Object;)Ljava/lang/String;
     199: getstatic     #31                 // Field org/postgresql/util/PSQLState.IO_ERROR:Lorg/postgresql/util/PSQLState;
     202: aload_2
     203: invokespecial #32                 // Method org/postgresql/util/PSQLException."<init>":(Ljava/lang/String;Lorg/postgresql/util/PSQLState;Ljava/lang/Throwable;)V
     206: athrow
     207: return
    Exception table:
       from    to  target type
          57   102   110   any
         110   112   110   any
           4   182   185   Class java/io/IOException

  public java.io.InputStream getStream();
    Code:
       0: aload_0
       1: getfield      #3                  // Field stream:Ljava/io/InputStream;
       4: ifnull        12
       7: aload_0
       8: getfield      #3                  // Field stream:Ljava/io/InputStream;
      11: areturn
      12: new           #33                 // class java/io/ByteArrayInputStream
      15: dup
      16: aload_0
      17: getfield      #4                  // Field rawData:[B
      20: aload_0
      21: getfield      #5                  // Field offset:I
      24: aload_0
      25: getfield      #1                  // Field length:I
      28: invokespecial #34                 // Method java/io/ByteArrayInputStream."<init>":([BII)V
      31: areturn

  public int getLength();
    Code:
       0: aload_0
       1: getfield      #1                  // Field length:I
       4: ireturn

  public int getOffset();
    Code:
       0: aload_0
       1: getfield      #5                  // Field offset:I
       4: ireturn

  public byte[] getBytes();
    Code:
       0: aload_0
       1: getfield      #4                  // Field rawData:[B
       4: areturn

  public java.lang.String toString();
    Code:
       0: new           #35                 // class java/lang/StringBuilder
       3: dup
       4: invokespecial #36                 // Method java/lang/StringBuilder."<init>":()V
       7: ldc           #37                 // String <stream of
       9: invokevirtual #38                 // Method java/lang/StringBuilder.append:(Ljava/lang/String;)Ljava/lang/StringBuilder;
      12: aload_0
      13: getfield      #1                  // Field length:I
      16: invokevirtual #39                 // Method java/lang/StringBuilder.append:(I)Ljava/lang/StringBuilder;
      19: ldc           #40                 // String  bytes>
      21: invokevirtual #38                 // Method java/lang/StringBuilder.append:(Ljava/lang/String;)Ljava/lang/StringBuilder;
      24: invokevirtual #41                 // Method java/lang/StringBuilder.toString:()Ljava/lang/String;
      27: areturn

  private static int copyStream(java.io.InputStream, java.io.OutputStream, int) throws java.io.IOException;
    Code:
       0: iconst_0
       1: istore_3
       2: sipush        2048
       5: newarray       byte
       7: astore        4
       9: aload_0
      10: aload         4
      12: invokevirtual #42                 // Method java/io/InputStream.read:([B)I
      15: istore        5
      17: iload         5
      19: ifle          54
      22: iload_3
      23: iload         5
      25: iadd
      26: istore_3
      27: aload_1
      28: aload         4
      30: iconst_0
      31: iload         5
      33: invokevirtual #43                 // Method java/io/OutputStream.write:([BII)V
      36: iload_3
      37: iload_2
      38: if_icmplt     43
      41: iconst_m1
      42: ireturn
      43: aload_0
      44: aload         4
      46: invokevirtual #42                 // Method java/io/InputStream.read:([B)I
      49: istore        5
      51: goto          17
      54: iload_3
      55: ireturn

  static int access$000(org.postgresql.util.StreamWrapper);
    Code:
       0: aload_0
       1: getfield      #1                  // Field length:I
       4: ireturn
}
