Compiled from "$AutoValue_JournalSummaryResponse.java"
abstract class org.graylog2.rest.resources.system.responses.$AutoValue_JournalSummaryResponse extends org.graylog2.rest.resources.system.responses.JournalSummaryResponse {
  private final boolean enabled;

  private final long appendEventsPerSecond;

  private final long readEventsPerSecond;

  private final long uncommittedJournalEntries;

  private final com.github.joschi.jadconfig.util.Size journalSize;

  private final com.github.joschi.jadconfig.util.Size journalSizeLimit;

  private final int numberOfSegments;

  private final org.joda.time.DateTime oldestSegment;

  private final org.graylog2.plugin.KafkaJournalConfiguration journalConfig;

  org.graylog2.rest.resources.system.responses.$AutoValue_JournalSummaryResponse(boolean, long, long, long, com.github.joschi.jadconfig.util.Size, com.github.joschi.jadconfig.util.Size, int, org.joda.time.DateTime, org.graylog2.plugin.KafkaJournalConfiguration);
    Code:
       0: aload_0
       1: invokespecial #1                  // Method org/graylog2/rest/resources/system/responses/JournalSummaryResponse."<init>":()V
       4: aload_0
       5: iload_1
       6: putfield      #2                  // Field enabled:Z
       9: aload_0
      10: lload_2
      11: putfield      #3                  // Field appendEventsPerSecond:J
      14: aload_0
      15: lload         4
      17: putfield      #4                  // Field readEventsPerSecond:J
      20: aload_0
      21: lload         6
      23: putfield      #5                  // Field uncommittedJournalEntries:J
      26: aload         8
      28: ifnonnull     41
      31: new           #6                  // class java/lang/NullPointerException
      34: dup
      35: ldc           #7                  // String Null journalSize
      37: invokespecial #8                  // Method java/lang/NullPointerException."<init>":(Ljava/lang/String;)V
      40: athrow
      41: aload_0
      42: aload         8
      44: putfield      #9                  // Field journalSize:Lcom/github/joschi/jadconfig/util/Size;
      47: aload         9
      49: ifnonnull     62
      52: new           #6                  // class java/lang/NullPointerException
      55: dup
      56: ldc           #10                 // String Null journalSizeLimit
      58: invokespecial #8                  // Method java/lang/NullPointerException."<init>":(Ljava/lang/String;)V
      61: athrow
      62: aload_0
      63: aload         9
      65: putfield      #11                 // Field journalSizeLimit:Lcom/github/joschi/jadconfig/util/Size;
      68: aload_0
      69: iload         10
      71: putfield      #12                 // Field numberOfSegments:I
      74: aload_0
      75: aload         11
      77: putfield      #13                 // Field oldestSegment:Lorg/joda/time/DateTime;
      80: aload_0
      81: aload         12
      83: putfield      #14                 // Field journalConfig:Lorg/graylog2/plugin/KafkaJournalConfiguration;
      86: return

  public boolean enabled();
    Code:
       0: aload_0
       1: getfield      #2                  // Field enabled:Z
       4: ireturn

  public long appendEventsPerSecond();
    Code:
       0: aload_0
       1: getfield      #3                  // Field appendEventsPerSecond:J
       4: lreturn

  public long readEventsPerSecond();
    Code:
       0: aload_0
       1: getfield      #4                  // Field readEventsPerSecond:J
       4: lreturn

  public long uncommittedJournalEntries();
    Code:
       0: aload_0
       1: getfield      #5                  // Field uncommittedJournalEntries:J
       4: lreturn

  public com.github.joschi.jadconfig.util.Size journalSize();
    Code:
       0: aload_0
       1: getfield      #9                  // Field journalSize:Lcom/github/joschi/jadconfig/util/Size;
       4: areturn

  public com.github.joschi.jadconfig.util.Size journalSizeLimit();
    Code:
       0: aload_0
       1: getfield      #11                 // Field journalSizeLimit:Lcom/github/joschi/jadconfig/util/Size;
       4: areturn

  public int numberOfSegments();
    Code:
       0: aload_0
       1: getfield      #12                 // Field numberOfSegments:I
       4: ireturn

  public org.joda.time.DateTime oldestSegment();
    Code:
       0: aload_0
       1: getfield      #13                 // Field oldestSegment:Lorg/joda/time/DateTime;
       4: areturn

  public org.graylog2.plugin.KafkaJournalConfiguration journalConfig();
    Code:
       0: aload_0
       1: getfield      #14                 // Field journalConfig:Lorg/graylog2/plugin/KafkaJournalConfiguration;
       4: areturn

  public java.lang.String toString();
    Code:
       0: new           #15                 // class java/lang/StringBuilder
       3: dup
       4: invokespecial #16                 // Method java/lang/StringBuilder."<init>":()V
       7: ldc           #17                 // String JournalSummaryResponse{enabled=
       9: invokevirtual #18                 // Method java/lang/StringBuilder.append:(Ljava/lang/String;)Ljava/lang/StringBuilder;
      12: aload_0
      13: getfield      #2                  // Field enabled:Z
      16: invokevirtual #19                 // Method java/lang/StringBuilder.append:(Z)Ljava/lang/StringBuilder;
      19: ldc           #20                 // String , appendEventsPerSecond=
      21: invokevirtual #18                 // Method java/lang/StringBuilder.append:(Ljava/lang/String;)Ljava/lang/StringBuilder;
      24: aload_0
      25: getfield      #3                  // Field appendEventsPerSecond:J
      28: invokevirtual #21                 // Method java/lang/StringBuilder.append:(J)Ljava/lang/StringBuilder;
      31: ldc           #22                 // String , readEventsPerSecond=
      33: invokevirtual #18                 // Method java/lang/StringBuilder.append:(Ljava/lang/String;)Ljava/lang/StringBuilder;
      36: aload_0
      37: getfield      #4                  // Field readEventsPerSecond:J
      40: invokevirtual #21                 // Method java/lang/StringBuilder.append:(J)Ljava/lang/StringBuilder;
      43: ldc           #23                 // String , uncommittedJournalEntries=
      45: invokevirtual #18                 // Method java/lang/StringBuilder.append:(Ljava/lang/String;)Ljava/lang/StringBuilder;
      48: aload_0
      49: getfield      #5                  // Field uncommittedJournalEntries:J
      52: invokevirtual #21                 // Method java/lang/StringBuilder.append:(J)Ljava/lang/StringBuilder;
      55: ldc           #24                 // String , journalSize=
      57: invokevirtual #18                 // Method java/lang/StringBuilder.append:(Ljava/lang/String;)Ljava/lang/StringBuilder;
      60: aload_0
      61: getfield      #9                  // Field journalSize:Lcom/github/joschi/jadconfig/util/Size;
      64: invokevirtual #25                 // Method java/lang/StringBuilder.append:(Ljava/lang/Object;)Ljava/lang/StringBuilder;
      67: ldc           #26                 // String , journalSizeLimit=
      69: invokevirtual #18                 // Method java/lang/StringBuilder.append:(Ljava/lang/String;)Ljava/lang/StringBuilder;
      72: aload_0
      73: getfield      #11                 // Field journalSizeLimit:Lcom/github/joschi/jadconfig/util/Size;
      76: invokevirtual #25                 // Method java/lang/StringBuilder.append:(Ljava/lang/Object;)Ljava/lang/StringBuilder;
      79: ldc           #27                 // String , numberOfSegments=
      81: invokevirtual #18                 // Method java/lang/StringBuilder.append:(Ljava/lang/String;)Ljava/lang/StringBuilder;
      84: aload_0
      85: getfield      #12                 // Field numberOfSegments:I
      88: invokevirtual #28                 // Method java/lang/StringBuilder.append:(I)Ljava/lang/StringBuilder;
      91: ldc           #29                 // String , oldestSegment=
      93: invokevirtual #18                 // Method java/lang/StringBuilder.append:(Ljava/lang/String;)Ljava/lang/StringBuilder;
      96: aload_0
      97: getfield      #13                 // Field oldestSegment:Lorg/joda/time/DateTime;
     100: invokevirtual #25                 // Method java/lang/StringBuilder.append:(Ljava/lang/Object;)Ljava/lang/StringBuilder;
     103: ldc           #30                 // String , journalConfig=
     105: invokevirtual #18                 // Method java/lang/StringBuilder.append:(Ljava/lang/String;)Ljava/lang/StringBuilder;
     108: aload_0
     109: getfield      #14                 // Field journalConfig:Lorg/graylog2/plugin/KafkaJournalConfiguration;
     112: invokevirtual #25                 // Method java/lang/StringBuilder.append:(Ljava/lang/Object;)Ljava/lang/StringBuilder;
     115: ldc           #31                 // String }
     117: invokevirtual #18                 // Method java/lang/StringBuilder.append:(Ljava/lang/String;)Ljava/lang/StringBuilder;
     120: invokevirtual #32                 // Method java/lang/StringBuilder.toString:()Ljava/lang/String;
     123: areturn

  public boolean equals(java.lang.Object);
    Code:
       0: aload_1
       1: aload_0
       2: if_acmpne     7
       5: iconst_1
       6: ireturn
       7: aload_1
       8: instanceof    #33                 // class org/graylog2/rest/resources/system/responses/JournalSummaryResponse
      11: ifeq          173
      14: aload_1
      15: checkcast     #33                 // class org/graylog2/rest/resources/system/responses/JournalSummaryResponse
      18: astore_2
      19: aload_0
      20: getfield      #2                  // Field enabled:Z
      23: aload_2
      24: invokevirtual #34                 // Method org/graylog2/rest/resources/system/responses/JournalSummaryResponse.enabled:()Z
      27: if_icmpne     171
      30: aload_0
      31: getfield      #3                  // Field appendEventsPerSecond:J
      34: aload_2
      35: invokevirtual #35                 // Method org/graylog2/rest/resources/system/responses/JournalSummaryResponse.appendEventsPerSecond:()J
      38: lcmp
      39: ifne          171
      42: aload_0
      43: getfield      #4                  // Field readEventsPerSecond:J
      46: aload_2
      47: invokevirtual #36                 // Method org/graylog2/rest/resources/system/responses/JournalSummaryResponse.readEventsPerSecond:()J
      50: lcmp
      51: ifne          171
      54: aload_0
      55: getfield      #5                  // Field uncommittedJournalEntries:J
      58: aload_2
      59: invokevirtual #37                 // Method org/graylog2/rest/resources/system/responses/JournalSummaryResponse.uncommittedJournalEntries:()J
      62: lcmp
      63: ifne          171
      66: aload_0
      67: getfield      #9                  // Field journalSize:Lcom/github/joschi/jadconfig/util/Size;
      70: aload_2
      71: invokevirtual #38                 // Method org/graylog2/rest/resources/system/responses/JournalSummaryResponse.journalSize:()Lcom/github/joschi/jadconfig/util/Size;
      74: invokevirtual #39                 // Method com/github/joschi/jadconfig/util/Size.equals:(Ljava/lang/Object;)Z
      77: ifeq          171
      80: aload_0
      81: getfield      #11                 // Field journalSizeLimit:Lcom/github/joschi/jadconfig/util/Size;
      84: aload_2
      85: invokevirtual #40                 // Method org/graylog2/rest/resources/system/responses/JournalSummaryResponse.journalSizeLimit:()Lcom/github/joschi/jadconfig/util/Size;
      88: invokevirtual #39                 // Method com/github/joschi/jadconfig/util/Size.equals:(Ljava/lang/Object;)Z
      91: ifeq          171
      94: aload_0
      95: getfield      #12                 // Field numberOfSegments:I
      98: aload_2
      99: invokevirtual #41                 // Method org/graylog2/rest/resources/system/responses/JournalSummaryResponse.numberOfSegments:()I
     102: if_icmpne     171
     105: aload_0
     106: getfield      #13                 // Field oldestSegment:Lorg/joda/time/DateTime;
     109: ifnonnull     122
     112: aload_2
     113: invokevirtual #42                 // Method org/graylog2/rest/resources/system/responses/JournalSummaryResponse.oldestSegment:()Lorg/joda/time/DateTime;
     116: ifnonnull     171
     119: goto          136
     122: aload_0
     123: getfield      #13                 // Field oldestSegment:Lorg/joda/time/DateTime;
     126: aload_2
     127: invokevirtual #42                 // Method org/graylog2/rest/resources/system/responses/JournalSummaryResponse.oldestSegment:()Lorg/joda/time/DateTime;
     130: invokevirtual #43                 // Method org/joda/time/DateTime.equals:(Ljava/lang/Object;)Z
     133: ifeq          171
     136: aload_0
     137: getfield      #14                 // Field journalConfig:Lorg/graylog2/plugin/KafkaJournalConfiguration;
     140: ifnonnull     153
     143: aload_2
     144: invokevirtual #44                 // Method org/graylog2/rest/resources/system/responses/JournalSummaryResponse.journalConfig:()Lorg/graylog2/plugin/KafkaJournalConfiguration;
     147: ifnonnull     171
     150: goto          167
     153: aload_0
     154: getfield      #14                 // Field journalConfig:Lorg/graylog2/plugin/KafkaJournalConfiguration;
     157: aload_2
     158: invokevirtual #44                 // Method org/graylog2/rest/resources/system/responses/JournalSummaryResponse.journalConfig:()Lorg/graylog2/plugin/KafkaJournalConfiguration;
     161: invokevirtual #45                 // Method java/lang/Object.equals:(Ljava/lang/Object;)Z
     164: ifeq          171
     167: iconst_1
     168: goto          172
     171: iconst_0
     172: ireturn
     173: iconst_0
     174: ireturn

  public int hashCode();
    Code:
       0: iconst_1
       1: istore_1
       2: iload_1
       3: ldc           #46                 // int 1000003
       5: imul
       6: istore_1
       7: iload_1
       8: aload_0
       9: getfield      #2                  // Field enabled:Z
      12: ifeq          21
      15: sipush        1231
      18: goto          24
      21: sipush        1237
      24: ixor
      25: istore_1
      26: iload_1
      27: ldc           #46                 // int 1000003
      29: imul
      30: istore_1
      31: iload_1
      32: aload_0
      33: getfield      #3                  // Field appendEventsPerSecond:J
      36: bipush        32
      38: lushr
      39: aload_0
      40: getfield      #3                  // Field appendEventsPerSecond:J
      43: lxor
      44: l2i
      45: ixor
      46: istore_1
      47: iload_1
      48: ldc           #46                 // int 1000003
      50: imul
      51: istore_1
      52: iload_1
      53: aload_0
      54: getfield      #4                  // Field readEventsPerSecond:J
      57: bipush        32
      59: lushr
      60: aload_0
      61: getfield      #4                  // Field readEventsPerSecond:J
      64: lxor
      65: l2i
      66: ixor
      67: istore_1
      68: iload_1
      69: ldc           #46                 // int 1000003
      71: imul
      72: istore_1
      73: iload_1
      74: aload_0
      75: getfield      #5                  // Field uncommittedJournalEntries:J
      78: bipush        32
      80: lushr
      81: aload_0
      82: getfield      #5                  // Field uncommittedJournalEntries:J
      85: lxor
      86: l2i
      87: ixor
      88: istore_1
      89: iload_1
      90: ldc           #46                 // int 1000003
      92: imul
      93: istore_1
      94: iload_1
      95: aload_0
      96: getfield      #9                  // Field journalSize:Lcom/github/joschi/jadconfig/util/Size;
      99: invokevirtual #47                 // Method com/github/joschi/jadconfig/util/Size.hashCode:()I
     102: ixor
     103: istore_1
     104: iload_1
     105: ldc           #46                 // int 1000003
     107: imul
     108: istore_1
     109: iload_1
     110: aload_0
     111: getfield      #11                 // Field journalSizeLimit:Lcom/github/joschi/jadconfig/util/Size;
     114: invokevirtual #47                 // Method com/github/joschi/jadconfig/util/Size.hashCode:()I
     117: ixor
     118: istore_1
     119: iload_1
     120: ldc           #46                 // int 1000003
     122: imul
     123: istore_1
     124: iload_1
     125: aload_0
     126: getfield      #12                 // Field numberOfSegments:I
     129: ixor
     130: istore_1
     131: iload_1
     132: ldc           #46                 // int 1000003
     134: imul
     135: istore_1
     136: iload_1
     137: aload_0
     138: getfield      #13                 // Field oldestSegment:Lorg/joda/time/DateTime;
     141: ifnonnull     148
     144: iconst_0
     145: goto          155
     148: aload_0
     149: getfield      #13                 // Field oldestSegment:Lorg/joda/time/DateTime;
     152: invokevirtual #48                 // Method org/joda/time/DateTime.hashCode:()I
     155: ixor
     156: istore_1
     157: iload_1
     158: ldc           #46                 // int 1000003
     160: imul
     161: istore_1
     162: iload_1
     163: aload_0
     164: getfield      #14                 // Field journalConfig:Lorg/graylog2/plugin/KafkaJournalConfiguration;
     167: ifnonnull     174
     170: iconst_0
     171: goto          181
     174: aload_0
     175: getfield      #14                 // Field journalConfig:Lorg/graylog2/plugin/KafkaJournalConfiguration;
     178: invokevirtual #49                 // Method java/lang/Object.hashCode:()I
     181: ixor
     182: istore_1
     183: iload_1
     184: ireturn
}
