Compiled from "JerseyEndpointResourceFactory.java"
public class org.springframework.boot.actuate.endpoint.web.jersey.JerseyEndpointResourceFactory {
  public org.springframework.boot.actuate.endpoint.web.jersey.JerseyEndpointResourceFactory();
    Code:
       0: aload_0
       1: invokespecial #1                  // Method java/lang/Object."<init>":()V
       4: return

  public java.util.Collection<org.glassfish.jersey.server.model.Resource> createEndpointResources(org.springframework.boot.actuate.endpoint.web.EndpointMapping, java.util.Collection<org.springframework.boot.actuate.endpoint.web.ExposableWebEndpoint>, org.springframework.boot.actuate.endpoint.web.EndpointMediaTypes, org.springframework.boot.actuate.endpoint.web.EndpointLinksResolver);
    Code:
       0: new           #2                  // class java/util/ArrayList
       3: dup
       4: invokespecial #3                  // Method java/util/ArrayList."<init>":()V
       7: astore        5
       9: aload_2
      10: invokeinterface #4,  1            // InterfaceMethod java/util/Collection.stream:()Ljava/util/stream/Stream;
      15: invokedynamic #5,  0              // InvokeDynamic #0:apply:()Ljava/util/function/Function;
      20: invokeinterface #6,  2            // InterfaceMethod java/util/stream/Stream.flatMap:(Ljava/util/function/Function;)Ljava/util/stream/Stream;
      25: aload_0
      26: aload_1
      27: invokedynamic #7,  0              // InvokeDynamic #1:apply:(Lorg/springframework/boot/actuate/endpoint/web/jersey/JerseyEndpointResourceFactory;Lorg/springframework/boot/actuate/endpoint/web/EndpointMapping;)Ljava/util/function/Function;
      32: invokeinterface #8,  2            // InterfaceMethod java/util/stream/Stream.map:(Ljava/util/function/Function;)Ljava/util/stream/Stream;
      37: aload         5
      39: dup
      40: invokevirtual #9                  // Method java/lang/Object.getClass:()Ljava/lang/Class;
      43: pop
      44: invokedynamic #10,  0             // InvokeDynamic #2:accept:(Ljava/util/List;)Ljava/util/function/Consumer;
      49: invokeinterface #11,  2           // InterfaceMethod java/util/stream/Stream.forEach:(Ljava/util/function/Consumer;)V
      54: aload_1
      55: invokevirtual #12                 // Method org/springframework/boot/actuate/endpoint/web/EndpointMapping.getPath:()Ljava/lang/String;
      58: invokestatic  #13                 // Method org/springframework/util/StringUtils.hasText:(Ljava/lang/String;)Z
      61: ifeq          87
      64: aload_0
      65: aload_1
      66: invokevirtual #12                 // Method org/springframework/boot/actuate/endpoint/web/EndpointMapping.getPath:()Ljava/lang/String;
      69: aload_3
      70: aload         4
      72: invokespecial #14                 // Method createEndpointLinksResource:(Ljava/lang/String;Lorg/springframework/boot/actuate/endpoint/web/EndpointMediaTypes;Lorg/springframework/boot/actuate/endpoint/web/EndpointLinksResolver;)Lorg/glassfish/jersey/server/model/Resource;
      75: astore        6
      77: aload         5
      79: aload         6
      81: invokeinterface #15,  2           // InterfaceMethod java/util/List.add:(Ljava/lang/Object;)Z
      86: pop
      87: aload         5
      89: areturn

  private org.glassfish.jersey.server.model.Resource createResource(org.springframework.boot.actuate.endpoint.web.EndpointMapping, org.springframework.boot.actuate.endpoint.web.WebOperation);
    Code:
       0: aload_2
       1: invokeinterface #16,  1           // InterfaceMethod org/springframework/boot/actuate/endpoint/web/WebOperation.getRequestPredicate:()Lorg/springframework/boot/actuate/endpoint/web/WebOperationRequestPredicate;
       6: astore_3
       7: invokestatic  #17                 // Method org/glassfish/jersey/server/model/Resource.builder:()Lorg/glassfish/jersey/server/model/Resource$Builder;
      10: aload_1
      11: aload_3
      12: invokevirtual #18                 // Method org/springframework/boot/actuate/endpoint/web/WebOperationRequestPredicate.getPath:()Ljava/lang/String;
      15: invokevirtual #19                 // Method org/springframework/boot/actuate/endpoint/web/EndpointMapping.createSubPath:(Ljava/lang/String;)Ljava/lang/String;
      18: invokevirtual #20                 // Method org/glassfish/jersey/server/model/Resource$Builder.path:(Ljava/lang/String;)Lorg/glassfish/jersey/server/model/Resource$Builder;
      21: astore        4
      23: aload         4
      25: aload_3
      26: invokevirtual #21                 // Method org/springframework/boot/actuate/endpoint/web/WebOperationRequestPredicate.getHttpMethod:()Lorg/springframework/boot/actuate/endpoint/web/WebEndpointHttpMethod;
      29: invokevirtual #22                 // Method org/springframework/boot/actuate/endpoint/web/WebEndpointHttpMethod.name:()Ljava/lang/String;
      32: invokevirtual #23                 // Method org/glassfish/jersey/server/model/Resource$Builder.addMethod:(Ljava/lang/String;)Lorg/glassfish/jersey/server/model/ResourceMethod$Builder;
      35: aload_3
      36: invokevirtual #24                 // Method org/springframework/boot/actuate/endpoint/web/WebOperationRequestPredicate.getConsumes:()Ljava/util/Collection;
      39: invokestatic  #25                 // Method org/springframework/util/StringUtils.toStringArray:(Ljava/util/Collection;)[Ljava/lang/String;
      42: invokevirtual #26                 // Method org/glassfish/jersey/server/model/ResourceMethod$Builder.consumes:([Ljava/lang/String;)Lorg/glassfish/jersey/server/model/ResourceMethod$Builder;
      45: aload_3
      46: invokevirtual #27                 // Method org/springframework/boot/actuate/endpoint/web/WebOperationRequestPredicate.getProduces:()Ljava/util/Collection;
      49: invokestatic  #25                 // Method org/springframework/util/StringUtils.toStringArray:(Ljava/util/Collection;)[Ljava/lang/String;
      52: invokevirtual #28                 // Method org/glassfish/jersey/server/model/ResourceMethod$Builder.produces:([Ljava/lang/String;)Lorg/glassfish/jersey/server/model/ResourceMethod$Builder;
      55: new           #29                 // class org/springframework/boot/actuate/endpoint/web/jersey/JerseyEndpointResourceFactory$OperationInflector
      58: dup
      59: aload_2
      60: aload_3
      61: invokevirtual #24                 // Method org/springframework/boot/actuate/endpoint/web/WebOperationRequestPredicate.getConsumes:()Ljava/util/Collection;
      64: invokeinterface #30,  1           // InterfaceMethod java/util/Collection.isEmpty:()Z
      69: ifne          76
      72: iconst_1
      73: goto          77
      76: iconst_0
      77: aconst_null
      78: invokespecial #31                 // Method org/springframework/boot/actuate/endpoint/web/jersey/JerseyEndpointResourceFactory$OperationInflector."<init>":(Lorg/springframework/boot/actuate/endpoint/web/WebOperation;ZLorg/springframework/boot/actuate/endpoint/web/jersey/JerseyEndpointResourceFactory$1;)V
      81: invokevirtual #32                 // Method org/glassfish/jersey/server/model/ResourceMethod$Builder.handledBy:(Lorg/glassfish/jersey/process/Inflector;)Lorg/glassfish/jersey/server/model/ResourceMethod$Builder;
      84: pop
      85: aload         4
      87: invokevirtual #33                 // Method org/glassfish/jersey/server/model/Resource$Builder.build:()Lorg/glassfish/jersey/server/model/Resource;
      90: areturn

  private org.glassfish.jersey.server.model.Resource createEndpointLinksResource(java.lang.String, org.springframework.boot.actuate.endpoint.web.EndpointMediaTypes, org.springframework.boot.actuate.endpoint.web.EndpointLinksResolver);
    Code:
       0: invokestatic  #17                 // Method org/glassfish/jersey/server/model/Resource.builder:()Lorg/glassfish/jersey/server/model/Resource$Builder;
       3: aload_1
       4: invokevirtual #20                 // Method org/glassfish/jersey/server/model/Resource$Builder.path:(Ljava/lang/String;)Lorg/glassfish/jersey/server/model/Resource$Builder;
       7: astore        4
       9: aload         4
      11: ldc           #34                 // String GET
      13: invokevirtual #23                 // Method org/glassfish/jersey/server/model/Resource$Builder.addMethod:(Ljava/lang/String;)Lorg/glassfish/jersey/server/model/ResourceMethod$Builder;
      16: aload_2
      17: invokevirtual #35                 // Method org/springframework/boot/actuate/endpoint/web/EndpointMediaTypes.getProduced:()Ljava/util/List;
      20: invokestatic  #25                 // Method org/springframework/util/StringUtils.toStringArray:(Ljava/util/Collection;)[Ljava/lang/String;
      23: invokevirtual #28                 // Method org/glassfish/jersey/server/model/ResourceMethod$Builder.produces:([Ljava/lang/String;)Lorg/glassfish/jersey/server/model/ResourceMethod$Builder;
      26: new           #36                 // class org/springframework/boot/actuate/endpoint/web/jersey/JerseyEndpointResourceFactory$EndpointLinksInflector
      29: dup
      30: aload_3
      31: aconst_null
      32: invokespecial #37                 // Method org/springframework/boot/actuate/endpoint/web/jersey/JerseyEndpointResourceFactory$EndpointLinksInflector."<init>":(Lorg/springframework/boot/actuate/endpoint/web/EndpointLinksResolver;Lorg/springframework/boot/actuate/endpoint/web/jersey/JerseyEndpointResourceFactory$1;)V
      35: invokevirtual #32                 // Method org/glassfish/jersey/server/model/ResourceMethod$Builder.handledBy:(Lorg/glassfish/jersey/process/Inflector;)Lorg/glassfish/jersey/server/model/ResourceMethod$Builder;
      38: pop
      39: aload         4
      41: invokevirtual #33                 // Method org/glassfish/jersey/server/model/Resource$Builder.build:()Lorg/glassfish/jersey/server/model/Resource;
      44: areturn

  private org.glassfish.jersey.server.model.Resource lambda$createEndpointResources$1(org.springframework.boot.actuate.endpoint.web.EndpointMapping, org.springframework.boot.actuate.endpoint.web.WebOperation);
    Code:
       0: aload_0
       1: aload_1
       2: aload_2
       3: invokespecial #38                 // Method createResource:(Lorg/springframework/boot/actuate/endpoint/web/EndpointMapping;Lorg/springframework/boot/actuate/endpoint/web/WebOperation;)Lorg/glassfish/jersey/server/model/Resource;
       6: areturn

  private static java.util.stream.Stream lambda$createEndpointResources$0(org.springframework.boot.actuate.endpoint.web.ExposableWebEndpoint);
    Code:
       0: aload_0
       1: invokeinterface #39,  1           // InterfaceMethod org/springframework/boot/actuate/endpoint/web/ExposableWebEndpoint.getOperations:()Ljava/util/Collection;
       6: invokeinterface #4,  1            // InterfaceMethod java/util/Collection.stream:()Ljava/util/stream/Stream;
      11: areturn
}
