Compiled from "SpringInnerTransactionRollbackTest.java"
public class org.camunda.bpm.engine.spring.test.transaction.inner.rollback.SpringInnerTransactionRollbackTest {
  public org.camunda.bpm.engine.test.ProcessEngineRule rule;

  public org.camunda.bpm.engine.ProcessEngine processEngine;

  org.camunda.bpm.engine.RuntimeService runtimeService;

  org.camunda.bpm.engine.HistoryService historyService;

  public org.camunda.bpm.engine.spring.test.transaction.inner.rollback.SpringInnerTransactionRollbackTest();
    Code:
       0: aload_0
       1: invokespecial #1                  // Method java/lang/Object."<init>":()V
       4: return

  public void shouldRollbackProcessData();
    Code:
       0: aload_0
       1: getfield      #2                  // Field runtimeService:Lorg/camunda/bpm/engine/RuntimeService;
       4: ldc           #3                  // String OuterTxNestedTransactionTest
       6: invokeinterface #4,  2            // InterfaceMethod org/camunda/bpm/engine/RuntimeService.startProcessInstanceByKey:(Ljava/lang/String;)Lorg/camunda/bpm/engine/runtime/ProcessInstance;
      11: astore_1
      12: aload_0
      13: getfield      #2                  // Field runtimeService:Lorg/camunda/bpm/engine/RuntimeService;
      16: invokeinterface #5,  1            // InterfaceMethod org/camunda/bpm/engine/RuntimeService.createProcessInstanceQuery:()Lorg/camunda/bpm/engine/runtime/ProcessInstanceQuery;
      21: aload_1
      22: invokeinterface #6,  1            // InterfaceMethod org/camunda/bpm/engine/runtime/ProcessInstance.getId:()Ljava/lang/String;
      27: invokeinterface #7,  2            // InterfaceMethod org/camunda/bpm/engine/runtime/ProcessInstanceQuery.processInstanceId:(Ljava/lang/String;)Lorg/camunda/bpm/engine/runtime/ProcessInstanceQuery;
      32: invokeinterface #8,  1            // InterfaceMethod org/camunda/bpm/engine/runtime/ProcessInstanceQuery.singleResult:()Ljava/lang/Object;
      37: checkcast     #9                  // class org/camunda/bpm/engine/runtime/ProcessInstance
      40: astore_2
      41: aload_2
      42: invokestatic  #10                 // Method org/assertj/core/api/Assertions.assertThat:(Ljava/lang/Object;)Lorg/assertj/core/api/AbstractObjectAssert;
      45: invokevirtual #11                 // Method org/assertj/core/api/AbstractObjectAssert.isNull:()V
      48: aload_0
      49: getfield      #2                  // Field runtimeService:Lorg/camunda/bpm/engine/RuntimeService;
      52: invokeinterface #5,  1            // InterfaceMethod org/camunda/bpm/engine/RuntimeService.createProcessInstanceQuery:()Lorg/camunda/bpm/engine/runtime/ProcessInstanceQuery;
      57: ldc           #12                 // String InnerTxNestedTransactionTest
      59: invokeinterface #13,  2           // InterfaceMethod org/camunda/bpm/engine/runtime/ProcessInstanceQuery.processDefinitionKey:(Ljava/lang/String;)Lorg/camunda/bpm/engine/runtime/ProcessInstanceQuery;
      64: invokeinterface #14,  1           // InterfaceMethod org/camunda/bpm/engine/runtime/ProcessInstanceQuery.list:()Ljava/util/List;
      69: astore_3
      70: aload_3
      71: invokestatic  #15                 // Method org/assertj/core/api/Assertions.assertThat:(Ljava/util/List;)Lorg/assertj/core/api/ListAssert;
      74: invokevirtual #16                 // Method org/assertj/core/api/ListAssert.isEmpty:()V
      77: aload_0
      78: getfield      #17                 // Field historyService:Lorg/camunda/bpm/engine/HistoryService;
      81: invokeinterface #18,  1           // InterfaceMethod org/camunda/bpm/engine/HistoryService.createHistoricProcessInstanceQuery:()Lorg/camunda/bpm/engine/history/HistoricProcessInstanceQuery;
      86: ldc           #12                 // String InnerTxNestedTransactionTest
      88: invokeinterface #19,  2           // InterfaceMethod org/camunda/bpm/engine/history/HistoricProcessInstanceQuery.processDefinitionKey:(Ljava/lang/String;)Lorg/camunda/bpm/engine/history/HistoricProcessInstanceQuery;
      93: invokeinterface #20,  1           // InterfaceMethod org/camunda/bpm/engine/history/HistoricProcessInstanceQuery.list:()Ljava/util/List;
      98: astore        4
     100: aload         4
     102: invokestatic  #15                 // Method org/assertj/core/api/Assertions.assertThat:(Ljava/util/List;)Lorg/assertj/core/api/ListAssert;
     105: invokevirtual #16                 // Method org/assertj/core/api/ListAssert.isEmpty:()V
     108: return
}
