final class org.bouncycastle.jcajce.provider.symmetric.util.GcmSpecUtil$1 implements java.security.PrivilegedExceptionAction {
  final java.lang.String val$name;

  org.bouncycastle.jcajce.provider.symmetric.util.GcmSpecUtil$1(java.lang.String);
    Code:
       0: aload_0
       1: aload_1
       2: putfield      #32                 // Field val$name:Ljava/lang/String;
       5: aload_0
       6: invokespecial #34                 // Method java/lang/Object."<init>":()V
       9: return

  public java.lang.Object run() throws java.lang.Exception;
    Code:
       0: getstatic     #31                 // Field org/bouncycastle/jcajce/provider/symmetric/util/GcmSpecUtil.gcmSpecClass:Ljava/lang/Class;
       3: aload_0
       4: getfield      #32                 // Field val$name:Ljava/lang/String;
       7: iconst_0
       8: anewarray     #14                 // class java/lang/Class
      11: invokevirtual #33                 // Method java/lang/Class.getDeclaredMethod:(Ljava/lang/String;[Ljava/lang/Class;)Ljava/lang/reflect/Method;
      14: areturn
}
