Compiled from "SerializationUtils.java"
public class io.fabric8.kubernetes.client.internal.SerializationUtils {
  private static com.fasterxml.jackson.databind.ObjectMapper mapper;

  private static com.fasterxml.jackson.databind.ObjectMapper statelessMapper;

  public io.fabric8.kubernetes.client.internal.SerializationUtils();
    Code:
       0: aload_0
       1: invokespecial #1                  // Method java/lang/Object."<init>":()V
       4: return

  public static com.fasterxml.jackson.databind.ObjectMapper getStatelessMapper();
    Code:
       0: getstatic     #2                  // Field statelessMapper:Lcom/fasterxml/jackson/databind/ObjectMapper;
       3: ifnonnull     43
       6: new           #3                  // class com/fasterxml/jackson/databind/ObjectMapper
       9: dup
      10: new           #4                  // class com/fasterxml/jackson/dataformat/yaml/YAMLFactory
      13: dup
      14: invokespecial #5                  // Method com/fasterxml/jackson/dataformat/yaml/YAMLFactory."<init>":()V
      17: invokespecial #6                  // Method com/fasterxml/jackson/databind/ObjectMapper."<init>":(Lcom/fasterxml/jackson/core/JsonFactory;)V
      20: putstatic     #2                  // Field statelessMapper:Lcom/fasterxml/jackson/databind/ObjectMapper;
      23: getstatic     #2                  // Field statelessMapper:Lcom/fasterxml/jackson/databind/ObjectMapper;
      26: ldc           #7                  // class io/fabric8/kubernetes/api/model/ObjectMeta
      28: ldc           #8                  // class io/fabric8/kubernetes/client/internal/serializationmixins/ObjectMetaMixIn
      30: invokevirtual #9                  // Method com/fasterxml/jackson/databind/ObjectMapper.addMixInAnnotations:(Ljava/lang/Class;Ljava/lang/Class;)V
      33: getstatic     #2                  // Field statelessMapper:Lcom/fasterxml/jackson/databind/ObjectMapper;
      36: ldc           #10                 // class io/fabric8/kubernetes/api/model/ReplicationController
      38: ldc           #11                 // class io/fabric8/kubernetes/client/internal/serializationmixins/ReplicationControllerMixIn
      40: invokevirtual #9                  // Method com/fasterxml/jackson/databind/ObjectMapper.addMixInAnnotations:(Ljava/lang/Class;Ljava/lang/Class;)V
      43: getstatic     #2                  // Field statelessMapper:Lcom/fasterxml/jackson/databind/ObjectMapper;
      46: areturn

  public static com.fasterxml.jackson.databind.ObjectMapper getMapper();
    Code:
       0: getstatic     #12                 // Field mapper:Lcom/fasterxml/jackson/databind/ObjectMapper;
       3: ifnonnull     23
       6: new           #3                  // class com/fasterxml/jackson/databind/ObjectMapper
       9: dup
      10: new           #4                  // class com/fasterxml/jackson/dataformat/yaml/YAMLFactory
      13: dup
      14: invokespecial #5                  // Method com/fasterxml/jackson/dataformat/yaml/YAMLFactory."<init>":()V
      17: invokespecial #6                  // Method com/fasterxml/jackson/databind/ObjectMapper."<init>":(Lcom/fasterxml/jackson/core/JsonFactory;)V
      20: putstatic     #12                 // Field mapper:Lcom/fasterxml/jackson/databind/ObjectMapper;
      23: getstatic     #12                 // Field mapper:Lcom/fasterxml/jackson/databind/ObjectMapper;
      26: areturn

  public static java.lang.String dumpAsYaml(io.fabric8.kubernetes.api.model.HasMetadata) throws com.fasterxml.jackson.core.JsonProcessingException;
    Code:
       0: invokestatic  #13                 // Method getMapper:()Lcom/fasterxml/jackson/databind/ObjectMapper;
       3: aload_0
       4: invokevirtual #14                 // Method com/fasterxml/jackson/databind/ObjectMapper.writeValueAsString:(Ljava/lang/Object;)Ljava/lang/String;
       7: areturn

  public static java.lang.String dumpWithoutRuntimeStateAsYaml(io.fabric8.kubernetes.api.model.HasMetadata) throws com.fasterxml.jackson.core.JsonProcessingException;
    Code:
       0: invokestatic  #15                 // Method getStatelessMapper:()Lcom/fasterxml/jackson/databind/ObjectMapper;
       3: aload_0
       4: invokevirtual #14                 // Method com/fasterxml/jackson/databind/ObjectMapper.writeValueAsString:(Ljava/lang/Object;)Ljava/lang/String;
       7: areturn
}
