Compiled from "SpdySettingsParser.java"
class io.undertow.protocols.spdy.SpdySettingsParser extends io.undertow.protocols.spdy.SpdyPushBackParser {
  private int length;

  private int count;

  private final java.util.List<io.undertow.protocols.spdy.SpdySetting> settings;

  io.undertow.protocols.spdy.SpdySettingsParser(int);
    Code:
       0: aload_0
       1: iload_1
       2: invokespecial #1                  // Method io/undertow/protocols/spdy/SpdyPushBackParser."<init>":(I)V
       5: aload_0
       6: iconst_m1
       7: putfield      #2                  // Field length:I
      10: aload_0
      11: iconst_0
      12: putfield      #3                  // Field count:I
      15: aload_0
      16: new           #4                  // class java/util/ArrayList
      19: dup
      20: invokespecial #5                  // Method java/util/ArrayList."<init>":()V
      23: putfield      #6                  // Field settings:Ljava/util/List;
      26: return

  protected void handleData(java.nio.ByteBuffer);
    Code:
       0: aload_0
       1: getfield      #2                  // Field length:I
       4: iconst_m1
       5: if_icmpne     89
       8: aload_1
       9: invokevirtual #7                  // Method java/nio/ByteBuffer.remaining:()I
      12: iconst_4
      13: if_icmpge     17
      16: return
      17: aload_0
      18: aload_1
      19: invokevirtual #8                  // Method java/nio/ByteBuffer.get:()B
      22: sipush        255
      25: iand
      26: bipush        24
      28: ishl
      29: putfield      #2                  // Field length:I
      32: aload_0
      33: dup
      34: getfield      #2                  // Field length:I
      37: aload_1
      38: invokevirtual #8                  // Method java/nio/ByteBuffer.get:()B
      41: sipush        255
      44: iand
      45: bipush        16
      47: ishl
      48: iadd
      49: putfield      #2                  // Field length:I
      52: aload_0
      53: dup
      54: getfield      #2                  // Field length:I
      57: aload_1
      58: invokevirtual #8                  // Method java/nio/ByteBuffer.get:()B
      61: sipush        255
      64: iand
      65: bipush        8
      67: ishl
      68: iadd
      69: putfield      #2                  // Field length:I
      72: aload_0
      73: dup
      74: getfield      #2                  // Field length:I
      77: aload_1
      78: invokevirtual #8                  // Method java/nio/ByteBuffer.get:()B
      81: sipush        255
      84: iand
      85: iadd
      86: putfield      #2                  // Field length:I
      89: aload_0
      90: getfield      #3                  // Field count:I
      93: aload_0
      94: getfield      #2                  // Field length:I
      97: if_icmpge     307
     100: aload_1
     101: invokevirtual #7                  // Method java/nio/ByteBuffer.remaining:()I
     104: bipush        8
     106: if_icmpge     110
     109: return
     110: aload_1
     111: invokevirtual #8                  // Method java/nio/ByteBuffer.get:()B
     114: sipush        255
     117: iand
     118: istore_2
     119: aload_1
     120: invokevirtual #8                  // Method java/nio/ByteBuffer.get:()B
     123: sipush        255
     126: iand
     127: bipush        16
     129: ishl
     130: istore_3
     131: iload_3
     132: aload_1
     133: invokevirtual #8                  // Method java/nio/ByteBuffer.get:()B
     136: sipush        255
     139: iand
     140: bipush        8
     142: ishl
     143: iadd
     144: istore_3
     145: iload_3
     146: aload_1
     147: invokevirtual #8                  // Method java/nio/ByteBuffer.get:()B
     150: sipush        255
     153: iand
     154: iadd
     155: istore_3
     156: aload_1
     157: invokevirtual #8                  // Method java/nio/ByteBuffer.get:()B
     160: sipush        255
     163: iand
     164: bipush        24
     166: ishl
     167: istore        4
     169: iload         4
     171: aload_1
     172: invokevirtual #8                  // Method java/nio/ByteBuffer.get:()B
     175: sipush        255
     178: iand
     179: bipush        16
     181: ishl
     182: iadd
     183: istore        4
     185: iload         4
     187: aload_1
     188: invokevirtual #8                  // Method java/nio/ByteBuffer.get:()B
     191: sipush        255
     194: iand
     195: bipush        8
     197: ishl
     198: iadd
     199: istore        4
     201: iload         4
     203: aload_1
     204: invokevirtual #8                  // Method java/nio/ByteBuffer.get:()B
     207: sipush        255
     210: iand
     211: iadd
     212: istore        4
     214: iconst_0
     215: istore        5
     217: aload_0
     218: getfield      #6                  // Field settings:Ljava/util/List;
     221: invokeinterface #9,  1            // InterfaceMethod java/util/List.iterator:()Ljava/util/Iterator;
     226: astore        6
     228: aload         6
     230: invokeinterface #10,  1           // InterfaceMethod java/util/Iterator.hasNext:()Z
     235: ifeq          268
     238: aload         6
     240: invokeinterface #11,  1           // InterfaceMethod java/util/Iterator.next:()Ljava/lang/Object;
     245: checkcast     #12                 // class io/undertow/protocols/spdy/SpdySetting
     248: astore        7
     250: aload         7
     252: invokevirtual #13                 // Method io/undertow/protocols/spdy/SpdySetting.getId:()I
     255: iload_3
     256: if_icmpne     265
     259: iconst_1
     260: istore        5
     262: goto          268
     265: goto          228
     268: iload         5
     270: ifne          294
     273: aload_0
     274: getfield      #6                  // Field settings:Ljava/util/List;
     277: new           #12                 // class io/undertow/protocols/spdy/SpdySetting
     280: dup
     281: iload_2
     282: iload_3
     283: iload         4
     285: invokespecial #14                 // Method io/undertow/protocols/spdy/SpdySetting."<init>":(III)V
     288: invokeinterface #15,  2           // InterfaceMethod java/util/List.add:(Ljava/lang/Object;)Z
     293: pop
     294: aload_0
     295: dup
     296: getfield      #3                  // Field count:I
     299: iconst_1
     300: iadd
     301: putfield      #3                  // Field count:I
     304: goto          89
     307: return

  public java.util.List<io.undertow.protocols.spdy.SpdySetting> getSettings();
    Code:
       0: aload_0
       1: getfield      #6                  // Field settings:Ljava/util/List;
       4: areturn
}
