Compiled from "JdbcObserverImpl.java"
public class org.hibernate.internal.JdbcObserverImpl implements org.hibernate.resource.jdbc.spi.JdbcObserver {
  private final org.hibernate.engine.spi.SharedSessionContractImplementor session;

  private final transient java.util.List<org.hibernate.engine.jdbc.spi.ConnectionObserver> observers;

  public org.hibernate.internal.JdbcObserverImpl(org.hibernate.engine.spi.SharedSessionContractImplementor);
    Code:
       0: aload_0
       1: invokespecial #1                  // Method java/lang/Object."<init>":()V
       4: aload_0
       5: aload_1
       6: putfield      #2                  // Field session:Lorg/hibernate/engine/spi/SharedSessionContractImplementor;
       9: aload_0
      10: new           #3                  // class java/util/ArrayList
      13: dup
      14: invokespecial #4                  // Method java/util/ArrayList."<init>":()V
      17: putfield      #5                  // Field observers:Ljava/util/List;
      20: aload_0
      21: getfield      #5                  // Field observers:Ljava/util/List;
      24: new           #6                  // class org/hibernate/internal/ConnectionObserverStatsBridge
      27: dup
      28: aload_1
      29: invokeinterface #7,  1            // InterfaceMethod org/hibernate/engine/spi/SharedSessionContractImplementor.getFactory:()Lorg/hibernate/engine/spi/SessionFactoryImplementor;
      34: invokespecial #8                  // Method org/hibernate/internal/ConnectionObserverStatsBridge."<init>":(Lorg/hibernate/engine/spi/SessionFactoryImplementor;)V
      37: invokeinterface #9,  2            // InterfaceMethod java/util/List.add:(Ljava/lang/Object;)Z
      42: pop
      43: return

  public void jdbcConnectionAcquisitionStart();
    Code:
       0: return

  public void jdbcConnectionAcquisitionEnd(java.sql.Connection);
    Code:
       0: aload_0
       1: getfield      #5                  // Field observers:Ljava/util/List;
       4: invokeinterface #10,  1           // InterfaceMethod java/util/List.iterator:()Ljava/util/Iterator;
       9: astore_2
      10: aload_2
      11: invokeinterface #11,  1           // InterfaceMethod java/util/Iterator.hasNext:()Z
      16: ifeq          39
      19: aload_2
      20: invokeinterface #12,  1           // InterfaceMethod java/util/Iterator.next:()Ljava/lang/Object;
      25: checkcast     #13                 // class org/hibernate/engine/jdbc/spi/ConnectionObserver
      28: astore_3
      29: aload_3
      30: aload_1
      31: invokeinterface #14,  2           // InterfaceMethod org/hibernate/engine/jdbc/spi/ConnectionObserver.physicalConnectionObtained:(Ljava/sql/Connection;)V
      36: goto          10
      39: return

  public void jdbcConnectionReleaseStart();
    Code:
       0: return

  public void jdbcConnectionReleaseEnd();
    Code:
       0: aload_0
       1: getfield      #5                  // Field observers:Ljava/util/List;
       4: invokeinterface #10,  1           // InterfaceMethod java/util/List.iterator:()Ljava/util/Iterator;
       9: astore_1
      10: aload_1
      11: invokeinterface #11,  1           // InterfaceMethod java/util/Iterator.hasNext:()Z
      16: ifeq          38
      19: aload_1
      20: invokeinterface #12,  1           // InterfaceMethod java/util/Iterator.next:()Ljava/lang/Object;
      25: checkcast     #13                 // class org/hibernate/engine/jdbc/spi/ConnectionObserver
      28: astore_2
      29: aload_2
      30: invokeinterface #15,  1           // InterfaceMethod org/hibernate/engine/jdbc/spi/ConnectionObserver.physicalConnectionReleased:()V
      35: goto          10
      38: return

  public void jdbcPrepareStatementStart();
    Code:
       0: aload_0
       1: getfield      #2                  // Field session:Lorg/hibernate/engine/spi/SharedSessionContractImplementor;
       4: invokeinterface #16,  1           // InterfaceMethod org/hibernate/engine/spi/SharedSessionContractImplementor.getEventListenerManager:()Lorg/hibernate/engine/spi/SessionEventListenerManager;
       9: invokeinterface #17,  1           // InterfaceMethod org/hibernate/engine/spi/SessionEventListenerManager.jdbcPrepareStatementStart:()V
      14: return

  public void jdbcPrepareStatementEnd();
    Code:
       0: aload_0
       1: getfield      #5                  // Field observers:Ljava/util/List;
       4: invokeinterface #10,  1           // InterfaceMethod java/util/List.iterator:()Ljava/util/Iterator;
       9: astore_1
      10: aload_1
      11: invokeinterface #11,  1           // InterfaceMethod java/util/Iterator.hasNext:()Z
      16: ifeq          38
      19: aload_1
      20: invokeinterface #12,  1           // InterfaceMethod java/util/Iterator.next:()Ljava/lang/Object;
      25: checkcast     #13                 // class org/hibernate/engine/jdbc/spi/ConnectionObserver
      28: astore_2
      29: aload_2
      30: invokeinterface #18,  1           // InterfaceMethod org/hibernate/engine/jdbc/spi/ConnectionObserver.statementPrepared:()V
      35: goto          10
      38: aload_0
      39: getfield      #2                  // Field session:Lorg/hibernate/engine/spi/SharedSessionContractImplementor;
      42: invokeinterface #16,  1           // InterfaceMethod org/hibernate/engine/spi/SharedSessionContractImplementor.getEventListenerManager:()Lorg/hibernate/engine/spi/SessionEventListenerManager;
      47: invokeinterface #19,  1           // InterfaceMethod org/hibernate/engine/spi/SessionEventListenerManager.jdbcPrepareStatementEnd:()V
      52: return

  public void jdbcExecuteStatementStart();
    Code:
       0: aload_0
       1: getfield      #2                  // Field session:Lorg/hibernate/engine/spi/SharedSessionContractImplementor;
       4: invokeinterface #16,  1           // InterfaceMethod org/hibernate/engine/spi/SharedSessionContractImplementor.getEventListenerManager:()Lorg/hibernate/engine/spi/SessionEventListenerManager;
       9: invokeinterface #20,  1           // InterfaceMethod org/hibernate/engine/spi/SessionEventListenerManager.jdbcExecuteStatementStart:()V
      14: return

  public void jdbcExecuteStatementEnd();
    Code:
       0: aload_0
       1: getfield      #2                  // Field session:Lorg/hibernate/engine/spi/SharedSessionContractImplementor;
       4: invokeinterface #16,  1           // InterfaceMethod org/hibernate/engine/spi/SharedSessionContractImplementor.getEventListenerManager:()Lorg/hibernate/engine/spi/SessionEventListenerManager;
       9: invokeinterface #21,  1           // InterfaceMethod org/hibernate/engine/spi/SessionEventListenerManager.jdbcExecuteStatementEnd:()V
      14: return

  public void jdbcExecuteBatchStart();
    Code:
       0: aload_0
       1: getfield      #2                  // Field session:Lorg/hibernate/engine/spi/SharedSessionContractImplementor;
       4: invokeinterface #16,  1           // InterfaceMethod org/hibernate/engine/spi/SharedSessionContractImplementor.getEventListenerManager:()Lorg/hibernate/engine/spi/SessionEventListenerManager;
       9: invokeinterface #22,  1           // InterfaceMethod org/hibernate/engine/spi/SessionEventListenerManager.jdbcExecuteBatchStart:()V
      14: return

  public void jdbcExecuteBatchEnd();
    Code:
       0: aload_0
       1: getfield      #2                  // Field session:Lorg/hibernate/engine/spi/SharedSessionContractImplementor;
       4: invokeinterface #16,  1           // InterfaceMethod org/hibernate/engine/spi/SharedSessionContractImplementor.getEventListenerManager:()Lorg/hibernate/engine/spi/SessionEventListenerManager;
       9: invokeinterface #23,  1           // InterfaceMethod org/hibernate/engine/spi/SessionEventListenerManager.jdbcExecuteBatchEnd:()V
      14: return

  public void jdbcReleaseRegistryResourcesStart();
    Code:
       0: aload_0
       1: getfield      #2                  // Field session:Lorg/hibernate/engine/spi/SharedSessionContractImplementor;
       4: invokeinterface #24,  1           // InterfaceMethod org/hibernate/engine/spi/SharedSessionContractImplementor.getJdbcCoordinator:()Lorg/hibernate/engine/jdbc/spi/JdbcCoordinator;
       9: invokeinterface #25,  1           // InterfaceMethod org/hibernate/engine/jdbc/spi/JdbcCoordinator.abortBatch:()V
      14: return

  public void jdbcReleaseRegistryResourcesEnd();
    Code:
       0: return
}
