Compiled from "SessionImpl.java"
class org.hibernate.internal.SessionImpl$SharedSessionBuilderImpl<T extends org.hibernate.SharedSessionBuilder> extends org.hibernate.internal.SessionFactoryImpl$SessionBuilderImpl<T> implements org.hibernate.SharedSessionBuilder<T>, org.hibernate.internal.SharedSessionCreationOptions {
  private final org.hibernate.internal.SessionImpl session;

  private boolean shareTransactionContext;

  private org.hibernate.internal.SessionImpl$SharedSessionBuilderImpl(org.hibernate.internal.SessionImpl);
    Code:
       0: aload_0
       1: aload_1
       2: invokevirtual #2                  // Method org/hibernate/internal/SessionImpl.getFactory:()Lorg/hibernate/engine/spi/SessionFactoryImplementor;
       5: checkcast     #3                  // class org/hibernate/internal/SessionFactoryImpl
       8: invokespecial #4                  // Method org/hibernate/internal/SessionFactoryImpl$SessionBuilderImpl."<init>":(Lorg/hibernate/internal/SessionFactoryImpl;)V
      11: aload_0
      12: aload_1
      13: putfield      #5                  // Field session:Lorg/hibernate/internal/SessionImpl;
      16: aload_0
      17: aload_1
      18: invokestatic  #6                  // Method org/hibernate/internal/SessionImpl.access$900:(Lorg/hibernate/internal/SessionImpl;)Lorg/hibernate/engine/spi/SessionOwner;
      21: invokespecial #7                  // Method org/hibernate/internal/SessionFactoryImpl$SessionBuilderImpl.owner:(Lorg/hibernate/engine/spi/SessionOwner;)Lorg/hibernate/SessionBuilder;
      24: pop
      25: aload_0
      26: aload_1
      27: invokevirtual #8                  // Method org/hibernate/internal/SessionImpl.getTenantIdentifier:()Ljava/lang/String;
      30: invokespecial #9                  // Method org/hibernate/internal/SessionFactoryImpl$SessionBuilderImpl.tenantIdentifier:(Ljava/lang/String;)Lorg/hibernate/SessionBuilder;
      33: pop
      34: return

  public T tenantIdentifier(java.lang.String);
    Code:
       0: new           #10                 // class org/hibernate/SessionException
       3: dup
       4: ldc           #11                 // String Cannot redefine tenant identifier on child session
       6: invokespecial #12                 // Method org/hibernate/SessionException."<init>":(Ljava/lang/String;)V
       9: athrow

  public T interceptor();
    Code:
       0: aload_0
       1: aload_0
       2: getfield      #5                  // Field session:Lorg/hibernate/internal/SessionImpl;
       5: invokevirtual #13                 // Method org/hibernate/internal/SessionImpl.getInterceptor:()Lorg/hibernate/Interceptor;
       8: invokevirtual #14                 // Method interceptor:(Lorg/hibernate/Interceptor;)Lorg/hibernate/SessionBuilder;
      11: checkcast     #15                 // class org/hibernate/SharedSessionBuilder
      14: areturn

  public T connection();
    Code:
       0: aload_0
       1: iconst_1
       2: putfield      #16                 // Field shareTransactionContext:Z
       5: aload_0
       6: areturn

  public T connectionReleaseMode();
    Code:
       0: aload_0
       1: aload_0
       2: getfield      #5                  // Field session:Lorg/hibernate/internal/SessionImpl;
       5: invokevirtual #17                 // Method org/hibernate/internal/SessionImpl.getJdbcCoordinator:()Lorg/hibernate/engine/jdbc/spi/JdbcCoordinator;
       8: invokeinterface #18,  1           // InterfaceMethod org/hibernate/engine/jdbc/spi/JdbcCoordinator.getLogicalConnection:()Lorg/hibernate/resource/jdbc/spi/LogicalConnectionImplementor;
      13: invokeinterface #19,  1           // InterfaceMethod org/hibernate/resource/jdbc/spi/LogicalConnectionImplementor.getConnectionHandlingMode:()Lorg/hibernate/resource/jdbc/spi/PhysicalConnectionHandlingMode;
      18: invokevirtual #20                 // Method org/hibernate/resource/jdbc/spi/PhysicalConnectionHandlingMode.getReleaseMode:()Lorg/hibernate/ConnectionReleaseMode;
      21: invokevirtual #21                 // Method connectionReleaseMode:(Lorg/hibernate/ConnectionReleaseMode;)Lorg/hibernate/SessionBuilder;
      24: checkcast     #15                 // class org/hibernate/SharedSessionBuilder
      27: areturn

  public T connectionHandlingMode();
    Code:
       0: aload_0
       1: aload_0
       2: getfield      #5                  // Field session:Lorg/hibernate/internal/SessionImpl;
       5: invokevirtual #17                 // Method org/hibernate/internal/SessionImpl.getJdbcCoordinator:()Lorg/hibernate/engine/jdbc/spi/JdbcCoordinator;
       8: invokeinterface #18,  1           // InterfaceMethod org/hibernate/engine/jdbc/spi/JdbcCoordinator.getLogicalConnection:()Lorg/hibernate/resource/jdbc/spi/LogicalConnectionImplementor;
      13: invokeinterface #19,  1           // InterfaceMethod org/hibernate/resource/jdbc/spi/LogicalConnectionImplementor.getConnectionHandlingMode:()Lorg/hibernate/resource/jdbc/spi/PhysicalConnectionHandlingMode;
      18: invokevirtual #22                 // Method connectionHandlingMode:(Lorg/hibernate/resource/jdbc/spi/PhysicalConnectionHandlingMode;)Lorg/hibernate/SessionBuilder;
      21: checkcast     #15                 // class org/hibernate/SharedSessionBuilder
      24: areturn

  public T autoJoinTransactions();
    Code:
       0: aload_0
       1: aload_0
       2: getfield      #5                  // Field session:Lorg/hibernate/internal/SessionImpl;
       5: invokevirtual #23                 // Method org/hibernate/internal/SessionImpl.isAutoCloseSessionEnabled:()Z
       8: invokevirtual #24                 // Method autoJoinTransactions:(Z)Lorg/hibernate/SessionBuilder;
      11: checkcast     #15                 // class org/hibernate/SharedSessionBuilder
      14: areturn

  public T flushMode();
    Code:
       0: aload_0
       1: aload_0
       2: getfield      #5                  // Field session:Lorg/hibernate/internal/SessionImpl;
       5: invokevirtual #25                 // Method org/hibernate/internal/SessionImpl.getHibernateFlushMode:()Lorg/hibernate/FlushMode;
       8: invokevirtual #26                 // Method flushMode:(Lorg/hibernate/FlushMode;)Lorg/hibernate/SessionBuilder;
      11: checkcast     #15                 // class org/hibernate/SharedSessionBuilder
      14: areturn

  public T autoClose();
    Code:
       0: aload_0
       1: aload_0
       2: getfield      #5                  // Field session:Lorg/hibernate/internal/SessionImpl;
       5: invokestatic  #27                 // Method org/hibernate/internal/SessionImpl.access$1000:(Lorg/hibernate/internal/SessionImpl;)Z
       8: invokevirtual #28                 // Method autoClose:(Z)Lorg/hibernate/SessionBuilder;
      11: checkcast     #15                 // class org/hibernate/SharedSessionBuilder
      14: areturn

  public boolean isTransactionCoordinatorShared();
    Code:
       0: aload_0
       1: getfield      #16                 // Field shareTransactionContext:Z
       4: ireturn

  public org.hibernate.resource.transaction.spi.TransactionCoordinator getTransactionCoordinator();
    Code:
       0: aload_0
       1: getfield      #16                 // Field shareTransactionContext:Z
       4: ifeq          17
       7: aload_0
       8: getfield      #5                  // Field session:Lorg/hibernate/internal/SessionImpl;
      11: invokevirtual #29                 // Method org/hibernate/internal/SessionImpl.getTransactionCoordinator:()Lorg/hibernate/resource/transaction/spi/TransactionCoordinator;
      14: goto          18
      17: aconst_null
      18: areturn

  public org.hibernate.engine.jdbc.spi.JdbcCoordinator getJdbcCoordinator();
    Code:
       0: aload_0
       1: getfield      #16                 // Field shareTransactionContext:Z
       4: ifeq          17
       7: aload_0
       8: getfield      #5                  // Field session:Lorg/hibernate/internal/SessionImpl;
      11: invokevirtual #17                 // Method org/hibernate/internal/SessionImpl.getJdbcCoordinator:()Lorg/hibernate/engine/jdbc/spi/JdbcCoordinator;
      14: goto          18
      17: aconst_null
      18: areturn

  public org.hibernate.engine.transaction.spi.TransactionImplementor getTransaction();
    Code:
       0: aload_0
       1: getfield      #16                 // Field shareTransactionContext:Z
       4: ifeq          17
       7: aload_0
       8: getfield      #5                  // Field session:Lorg/hibernate/internal/SessionImpl;
      11: invokevirtual #30                 // Method org/hibernate/internal/SessionImpl.getCurrentTransaction:()Lorg/hibernate/engine/transaction/spi/TransactionImplementor;
      14: goto          18
      17: aconst_null
      18: areturn

  public org.hibernate.engine.spi.ActionQueue$TransactionCompletionProcesses getTransactionCompletionProcesses();
    Code:
       0: aload_0
       1: getfield      #16                 // Field shareTransactionContext:Z
       4: ifeq          20
       7: aload_0
       8: getfield      #5                  // Field session:Lorg/hibernate/internal/SessionImpl;
      11: invokevirtual #31                 // Method org/hibernate/internal/SessionImpl.getActionQueue:()Lorg/hibernate/engine/spi/ActionQueue;
      14: invokevirtual #32                 // Method org/hibernate/engine/spi/ActionQueue.getTransactionCompletionProcesses:()Lorg/hibernate/engine/spi/ActionQueue$TransactionCompletionProcesses;
      17: goto          21
      20: aconst_null
      21: areturn

  public boolean isQueryParametersValidationEnabled();
    Code:
       0: aload_0
       1: getfield      #5                  // Field session:Lorg/hibernate/internal/SessionImpl;
       4: invokevirtual #33                 // Method org/hibernate/internal/SessionImpl.isQueryParametersValidationEnabled:()Z
       7: ireturn

  public org.hibernate.SessionBuilder tenantIdentifier(java.lang.String);
    Code:
       0: aload_0
       1: aload_1
       2: invokevirtual #34                 // Method tenantIdentifier:(Ljava/lang/String;)Lorg/hibernate/SharedSessionBuilder;
       5: areturn

  public org.hibernate.SharedSessionBuilder autoClose(boolean);
    Code:
       0: aload_0
       1: iload_1
       2: invokespecial #35                 // Method org/hibernate/internal/SessionFactoryImpl$SessionBuilderImpl.autoClose:(Z)Lorg/hibernate/SessionBuilder;
       5: checkcast     #15                 // class org/hibernate/SharedSessionBuilder
       8: areturn

  public org.hibernate.SharedSessionBuilder autoJoinTransactions(boolean);
    Code:
       0: aload_0
       1: iload_1
       2: invokespecial #36                 // Method org/hibernate/internal/SessionFactoryImpl$SessionBuilderImpl.autoJoinTransactions:(Z)Lorg/hibernate/SessionBuilder;
       5: checkcast     #15                 // class org/hibernate/SharedSessionBuilder
       8: areturn

  public org.hibernate.SharedSessionBuilder connectionReleaseMode(org.hibernate.ConnectionReleaseMode);
    Code:
       0: aload_0
       1: aload_1
       2: invokespecial #37                 // Method org/hibernate/internal/SessionFactoryImpl$SessionBuilderImpl.connectionReleaseMode:(Lorg/hibernate/ConnectionReleaseMode;)Lorg/hibernate/SessionBuilder;
       5: checkcast     #15                 // class org/hibernate/SharedSessionBuilder
       8: areturn

  public org.hibernate.SharedSessionBuilder connection(java.sql.Connection);
    Code:
       0: aload_0
       1: aload_1
       2: invokespecial #38                 // Method org/hibernate/internal/SessionFactoryImpl$SessionBuilderImpl.connection:(Ljava/sql/Connection;)Lorg/hibernate/SessionBuilder;
       5: checkcast     #15                 // class org/hibernate/SharedSessionBuilder
       8: areturn

  public org.hibernate.SharedSessionBuilder noInterceptor();
    Code:
       0: aload_0
       1: invokespecial #39                 // Method org/hibernate/internal/SessionFactoryImpl$SessionBuilderImpl.noInterceptor:()Lorg/hibernate/SessionBuilder;
       4: checkcast     #15                 // class org/hibernate/SharedSessionBuilder
       7: areturn

  public org.hibernate.SharedSessionBuilder interceptor(org.hibernate.Interceptor);
    Code:
       0: aload_0
       1: aload_1
       2: invokespecial #40                 // Method org/hibernate/internal/SessionFactoryImpl$SessionBuilderImpl.interceptor:(Lorg/hibernate/Interceptor;)Lorg/hibernate/SessionBuilder;
       5: checkcast     #15                 // class org/hibernate/SharedSessionBuilder
       8: areturn

  org.hibernate.internal.SessionImpl$SharedSessionBuilderImpl(org.hibernate.internal.SessionImpl, org.hibernate.internal.SessionImpl$1);
    Code:
       0: aload_0
       1: aload_1
       2: invokespecial #1                  // Method "<init>":(Lorg/hibernate/internal/SessionImpl;)V
       5: return
}
