Compiled from "QueryIterYieldN.java"
public class org.apache.jena.sparql.engine.iterator.QueryIterYieldN extends org.apache.jena.sparql.engine.iterator.QueryIter {
  protected int limitYielded;

  protected int countYielded;

  protected org.apache.jena.sparql.engine.binding.Binding binding;

  public org.apache.jena.sparql.engine.iterator.QueryIterYieldN(int, org.apache.jena.sparql.engine.binding.Binding);
    Code:
       0: aload_0
       1: iload_1
       2: aload_2
       3: aconst_null
       4: invokespecial #1                  // Method "<init>":(ILorg/apache/jena/sparql/engine/binding/Binding;Lorg/apache/jena/sparql/engine/ExecutionContext;)V
       7: return

  public org.apache.jena.sparql.engine.iterator.QueryIterYieldN(int, org.apache.jena.sparql.engine.binding.Binding, org.apache.jena.sparql.engine.ExecutionContext);
    Code:
       0: aload_0
       1: aload_3
       2: invokespecial #2                  // Method org/apache/jena/sparql/engine/iterator/QueryIter."<init>":(Lorg/apache/jena/sparql/engine/ExecutionContext;)V
       5: aload_0
       6: iconst_0
       7: putfield      #3                  // Field countYielded:I
      10: aload_0
      11: aload_2
      12: putfield      #4                  // Field binding:Lorg/apache/jena/sparql/engine/binding/Binding;
      15: aload_0
      16: iload_1
      17: putfield      #5                  // Field limitYielded:I
      20: return

  public org.apache.jena.sparql.engine.binding.Binding getBinding();
    Code:
       0: aload_0
       1: getfield      #4                  // Field binding:Lorg/apache/jena/sparql/engine/binding/Binding;
       4: areturn

  protected boolean hasNextBinding();
    Code:
       0: aload_0
       1: getfield      #3                  // Field countYielded:I
       4: aload_0
       5: getfield      #5                  // Field limitYielded:I
       8: if_icmpge     15
      11: iconst_1
      12: goto          16
      15: iconst_0
      16: ireturn

  protected org.apache.jena.sparql.engine.binding.Binding moveToNextBinding();
    Code:
       0: aload_0
       1: invokevirtual #6                  // Method hasNextBinding:()Z
       4: ifne          19
       7: new           #7                  // class java/util/NoSuchElementException
      10: dup
      11: aload_0
      12: invokestatic  #8                  // Method org/apache/jena/atlas/lib/Lib.className:(Ljava/lang/Object;)Ljava/lang/String;
      15: invokespecial #9                  // Method java/util/NoSuchElementException."<init>":(Ljava/lang/String;)V
      18: athrow
      19: aload_0
      20: dup
      21: getfield      #3                  // Field countYielded:I
      24: iconst_1
      25: iadd
      26: putfield      #3                  // Field countYielded:I
      29: aload_0
      30: getfield      #4                  // Field binding:Lorg/apache/jena/sparql/engine/binding/Binding;
      33: areturn

  protected void closeIterator();
    Code:
       0: return

  protected void requestCancel();
    Code:
       0: return

  public void output(org.apache.jena.atlas.io.IndentedWriter, org.apache.jena.sparql.serializer.SerializationContext);
    Code:
       0: aload_1
       1: new           #10                 // class java/lang/StringBuilder
       4: dup
       5: invokespecial #11                 // Method java/lang/StringBuilder."<init>":()V
       8: ldc           #12                 // String QueryIterYieldN:
      10: invokevirtual #13                 // Method java/lang/StringBuilder.append:(Ljava/lang/String;)Ljava/lang/StringBuilder;
      13: aload_0
      14: getfield      #5                  // Field limitYielded:I
      17: invokevirtual #14                 // Method java/lang/StringBuilder.append:(I)Ljava/lang/StringBuilder;
      20: ldc           #15                 // String  of
      22: invokevirtual #13                 // Method java/lang/StringBuilder.append:(Ljava/lang/String;)Ljava/lang/StringBuilder;
      25: aload_0
      26: getfield      #4                  // Field binding:Lorg/apache/jena/sparql/engine/binding/Binding;
      29: invokevirtual #16                 // Method java/lang/StringBuilder.append:(Ljava/lang/Object;)Ljava/lang/StringBuilder;
      32: invokevirtual #17                 // Method java/lang/StringBuilder.toString:()Ljava/lang/String;
      35: invokevirtual #18                 // Method org/apache/jena/atlas/io/IndentedWriter.print:(Ljava/lang/String;)V
      38: return
}
