Compiled from "QueryIteratorWrapper.java"
public class org.apache.jena.sparql.engine.iterator.QueryIteratorWrapper extends org.apache.jena.sparql.engine.iterator.QueryIteratorBase {
  protected org.apache.jena.sparql.engine.QueryIterator iterator;

  public org.apache.jena.sparql.engine.iterator.QueryIteratorWrapper(org.apache.jena.sparql.engine.QueryIterator);
    Code:
       0: aload_0
       1: invokespecial #1                  // Method org/apache/jena/sparql/engine/iterator/QueryIteratorBase."<init>":()V
       4: aload_0
       5: aload_1
       6: putfield      #2                  // Field iterator:Lorg/apache/jena/sparql/engine/QueryIterator;
       9: return

  protected boolean hasNextBinding();
    Code:
       0: aload_0
       1: getfield      #2                  // Field iterator:Lorg/apache/jena/sparql/engine/QueryIterator;
       4: invokeinterface #3,  1            // InterfaceMethod org/apache/jena/sparql/engine/QueryIterator.hasNext:()Z
       9: ireturn

  protected org.apache.jena.sparql.engine.binding.Binding moveToNextBinding();
    Code:
       0: aload_0
       1: getfield      #2                  // Field iterator:Lorg/apache/jena/sparql/engine/QueryIterator;
       4: invokeinterface #4,  1            // InterfaceMethod org/apache/jena/sparql/engine/QueryIterator.nextBinding:()Lorg/apache/jena/sparql/engine/binding/Binding;
       9: areturn

  protected void closeIterator();
    Code:
       0: aload_0
       1: getfield      #2                  // Field iterator:Lorg/apache/jena/sparql/engine/QueryIterator;
       4: ifnull        21
       7: aload_0
       8: getfield      #2                  // Field iterator:Lorg/apache/jena/sparql/engine/QueryIterator;
      11: invokeinterface #5,  1            // InterfaceMethod org/apache/jena/sparql/engine/QueryIterator.close:()V
      16: aload_0
      17: aconst_null
      18: putfield      #2                  // Field iterator:Lorg/apache/jena/sparql/engine/QueryIterator;
      21: return

  protected void requestCancel();
    Code:
       0: aload_0
       1: getfield      #2                  // Field iterator:Lorg/apache/jena/sparql/engine/QueryIterator;
       4: ifnull        16
       7: aload_0
       8: getfield      #2                  // Field iterator:Lorg/apache/jena/sparql/engine/QueryIterator;
      11: invokeinterface #6,  1            // InterfaceMethod org/apache/jena/sparql/engine/QueryIterator.cancel:()V
      16: return

  public void output(org.apache.jena.atlas.io.IndentedWriter, org.apache.jena.sparql.serializer.SerializationContext);
    Code:
       0: aload_1
       1: new           #7                  // class java/lang/StringBuilder
       4: dup
       5: invokespecial #8                  // Method java/lang/StringBuilder."<init>":()V
       8: aload_0
       9: invokestatic  #9                  // Method org/apache/jena/atlas/lib/Lib.className:(Ljava/lang/Object;)Ljava/lang/String;
      12: invokevirtual #10                 // Method java/lang/StringBuilder.append:(Ljava/lang/String;)Ljava/lang/StringBuilder;
      15: ldc           #11                 // String /
      17: invokevirtual #10                 // Method java/lang/StringBuilder.append:(Ljava/lang/String;)Ljava/lang/StringBuilder;
      20: aload_0
      21: getfield      #2                  // Field iterator:Lorg/apache/jena/sparql/engine/QueryIterator;
      24: invokestatic  #9                  // Method org/apache/jena/atlas/lib/Lib.className:(Ljava/lang/Object;)Ljava/lang/String;
      27: invokevirtual #10                 // Method java/lang/StringBuilder.append:(Ljava/lang/String;)Ljava/lang/StringBuilder;
      30: invokevirtual #12                 // Method java/lang/StringBuilder.toString:()Ljava/lang/String;
      33: invokevirtual #13                 // Method org/apache/jena/atlas/io/IndentedWriter.println:(Ljava/lang/String;)V
      36: aload_1
      37: invokevirtual #14                 // Method org/apache/jena/atlas/io/IndentedWriter.incIndent:()V
      40: aload_0
      41: getfield      #2                  // Field iterator:Lorg/apache/jena/sparql/engine/QueryIterator;
      44: aload_1
      45: aload_2
      46: invokeinterface #15,  3           // InterfaceMethod org/apache/jena/sparql/engine/QueryIterator.output:(Lorg/apache/jena/atlas/io/IndentedWriter;Lorg/apache/jena/sparql/serializer/SerializationContext;)V
      51: aload_1
      52: invokevirtual #16                 // Method org/apache/jena/atlas/io/IndentedWriter.decIndent:()V
      55: return
}
