Compiled from "QueryIterSort.java"
class org.apache.jena.sparql.engine.iterator.QueryIterSort$SortedBindingIterator extends org.apache.jena.atlas.iterator.IteratorDelayedInitialization<org.apache.jena.sparql.engine.binding.Binding> implements org.apache.jena.atlas.lib.Closeable {
  private final org.apache.jena.sparql.engine.QueryIterator qIter;

  final org.apache.jena.sparql.engine.iterator.QueryIterSort this$0;

  public org.apache.jena.sparql.engine.iterator.QueryIterSort$SortedBindingIterator(org.apache.jena.sparql.engine.iterator.QueryIterSort, org.apache.jena.sparql.engine.QueryIterator);
    Code:
       0: aload_0
       1: aload_1
       2: putfield      #1                  // Field this$0:Lorg/apache/jena/sparql/engine/iterator/QueryIterSort;
       5: aload_0
       6: invokespecial #2                  // Method org/apache/jena/atlas/iterator/IteratorDelayedInitialization."<init>":()V
       9: aload_0
      10: aload_2
      11: putfield      #3                  // Field qIter:Lorg/apache/jena/sparql/engine/QueryIterator;
      14: return

  protected java.util.Iterator<org.apache.jena.sparql.engine.binding.Binding> initializeIterator();
    Code:
       0: aload_0
       1: getfield      #1                  // Field this$0:Lorg/apache/jena/sparql/engine/iterator/QueryIterSort;
       4: getfield      #4                  // Field org/apache/jena/sparql/engine/iterator/QueryIterSort.db:Lorg/apache/jena/atlas/data/SortedDataBag;
       7: aload_0
       8: getfield      #3                  // Field qIter:Lorg/apache/jena/sparql/engine/QueryIterator;
      11: invokevirtual #5                  // Method org/apache/jena/atlas/data/SortedDataBag.addAll:(Ljava/util/Iterator;)V
      14: aload_0
      15: getfield      #1                  // Field this$0:Lorg/apache/jena/sparql/engine/iterator/QueryIterSort;
      18: getfield      #4                  // Field org/apache/jena/sparql/engine/iterator/QueryIterSort.db:Lorg/apache/jena/atlas/data/SortedDataBag;
      21: invokevirtual #6                  // Method org/apache/jena/atlas/data/SortedDataBag.iterator:()Ljava/util/Iterator;
      24: areturn
      25: astore_1
      26: aload_0
      27: getfield      #1                  // Field this$0:Lorg/apache/jena/sparql/engine/iterator/QueryIterSort;
      30: invokevirtual #8                  // Method org/apache/jena/sparql/engine/iterator/QueryIterSort.close:()V
      33: aload_0
      34: invokevirtual #9                  // Method close:()V
      37: aload_1
      38: athrow
    Exception table:
       from    to  target type
           0    24    25   Class org/apache/jena/query/QueryCancelledException

  public void close();
    Code:
       0: aload_0
       1: getfield      #1                  // Field this$0:Lorg/apache/jena/sparql/engine/iterator/QueryIterSort;
       4: getfield      #4                  // Field org/apache/jena/sparql/engine/iterator/QueryIterSort.db:Lorg/apache/jena/atlas/data/SortedDataBag;
       7: invokevirtual #10                 // Method org/apache/jena/atlas/data/SortedDataBag.close:()V
      10: return
}
