Compiled from "QueryIterDistinct.java"
public class org.apache.jena.sparql.engine.iterator.QueryIterDistinct extends org.apache.jena.sparql.engine.iterator.QueryIter1 {
  private long memThreshold;

  org.apache.jena.atlas.data.DistinctDataBag<org.apache.jena.sparql.engine.binding.Binding> db;

  private java.util.Iterator<org.apache.jena.sparql.engine.binding.Binding> iterator;

  private java.util.Set<org.apache.jena.sparql.engine.binding.Binding> seen;

  private org.apache.jena.sparql.engine.binding.Binding slot;

  public org.apache.jena.sparql.engine.iterator.QueryIterDistinct(org.apache.jena.sparql.engine.QueryIterator, org.apache.jena.sparql.engine.ExecutionContext);
    Code:
       0: aload_0
       1: aload_1
       2: aload_2
       3: invokespecial #1                  // Method org/apache/jena/sparql/engine/iterator/QueryIter1."<init>":(Lorg/apache/jena/sparql/engine/QueryIterator;Lorg/apache/jena/sparql/engine/ExecutionContext;)V
       6: aload_0
       7: ldc2_w        #3                  // long 9223372036854775807l
      10: putfield      #5                  // Field memThreshold:J
      13: aload_0
      14: aconst_null
      15: putfield      #6                  // Field db:Lorg/apache/jena/atlas/data/DistinctDataBag;
      18: aload_0
      19: aconst_null
      20: putfield      #7                  // Field iterator:Ljava/util/Iterator;
      23: aload_0
      24: new           #8                  // class java/util/HashSet
      27: dup
      28: invokespecial #9                  // Method java/util/HashSet."<init>":()V
      31: putfield      #10                 // Field seen:Ljava/util/Set;
      34: aload_0
      35: aconst_null
      36: putfield      #11                 // Field slot:Lorg/apache/jena/sparql/engine/binding/Binding;
      39: aload_2
      40: ifnull        100
      43: aload_0
      44: aload_2
      45: invokevirtual #12                 // Method org/apache/jena/sparql/engine/ExecutionContext.getContext:()Lorg/apache/jena/sparql/util/Context;
      48: getstatic     #13                 // Field org/apache/jena/query/ARQ.spillToDiskThreshold:Lorg/apache/jena/sparql/util/Symbol;
      51: aload_0
      52: getfield      #5                  // Field memThreshold:J
      55: invokevirtual #14                 // Method org/apache/jena/sparql/util/Context.getLong:(Lorg/apache/jena/sparql/util/Symbol;J)J
      58: putfield      #5                  // Field memThreshold:J
      61: aload_0
      62: getfield      #5                  // Field memThreshold:J
      65: lconst_0
      66: lcmp
      67: ifge          100
      70: new           #15                 // class org/apache/jena/sparql/ARQException
      73: dup
      74: new           #16                 // class java/lang/StringBuilder
      77: dup
      78: invokespecial #17                 // Method java/lang/StringBuilder."<init>":()V
      81: ldc           #18                 // String BAd spillToDiskThreshold:
      83: invokevirtual #19                 // Method java/lang/StringBuilder.append:(Ljava/lang/String;)Ljava/lang/StringBuilder;
      86: aload_0
      87: getfield      #5                  // Field memThreshold:J
      90: invokevirtual #20                 // Method java/lang/StringBuilder.append:(J)Ljava/lang/StringBuilder;
      93: invokevirtual #21                 // Method java/lang/StringBuilder.toString:()Ljava/lang/String;
      96: invokespecial #22                 // Method org/apache/jena/sparql/ARQException."<init>":(Ljava/lang/String;)V
      99: athrow
     100: return

  protected boolean hasNextBinding();
    Code:
       0: aload_0
       1: getfield      #11                 // Field slot:Lorg/apache/jena/sparql/engine/binding/Binding;
       4: ifnull        9
       7: iconst_1
       8: ireturn
       9: aload_0
      10: getfield      #7                  // Field iterator:Ljava/util/Iterator;
      13: ifnull        26
      16: aload_0
      17: getfield      #7                  // Field iterator:Ljava/util/Iterator;
      20: invokeinterface #23,  1           // InterfaceMethod java/util/Iterator.hasNext:()Z
      25: ireturn
      26: aload_0
      27: getfield      #10                 // Field seen:Ljava/util/Set;
      30: invokeinterface #24,  1           // InterfaceMethod java/util/Set.size:()I
      35: i2l
      36: aload_0
      37: getfield      #5                  // Field memThreshold:J
      40: lcmp
      41: ifge          73
      44: aload_0
      45: invokespecial #25                 // Method getInputNextUnseen:()Lorg/apache/jena/sparql/engine/binding/Binding;
      48: astore_1
      49: aload_1
      50: ifnonnull     55
      53: iconst_0
      54: ireturn
      55: aload_0
      56: getfield      #10                 // Field seen:Ljava/util/Set;
      59: aload_1
      60: invokeinterface #26,  2           // InterfaceMethod java/util/Set.add:(Ljava/lang/Object;)Z
      65: pop
      66: aload_0
      67: aload_1
      68: putfield      #11                 // Field slot:Lorg/apache/jena/sparql/engine/binding/Binding;
      71: iconst_1
      72: ireturn
      73: aload_0
      74: invokespecial #27                 // Method loadDataBag:()V
      77: aload_0
      78: aload_0
      79: getfield      #6                  // Field db:Lorg/apache/jena/atlas/data/DistinctDataBag;
      82: invokevirtual #28                 // Method org/apache/jena/atlas/data/DistinctDataBag.iterator:()Ljava/util/Iterator;
      85: putfield      #7                  // Field iterator:Ljava/util/Iterator;
      88: aload_0
      89: getfield      #7                  // Field iterator:Ljava/util/Iterator;
      92: invokeinterface #23,  1           // InterfaceMethod java/util/Iterator.hasNext:()Z
      97: ireturn

  private void loadDataBag();
    Code:
       0: aload_0
       1: invokespecial #29                 // Method org/apache/jena/sparql/engine/iterator/QueryIter1.getExecContext:()Lorg/apache/jena/sparql/engine/ExecutionContext;
       4: invokevirtual #12                 // Method org/apache/jena/sparql/engine/ExecutionContext.getContext:()Lorg/apache/jena/sparql/util/Context;
       7: invokestatic  #30                 // Method org/apache/jena/atlas/data/ThresholdPolicyFactory.policyFromContext:(Lorg/apache/jena/sparql/util/Context;)Lorg/apache/jena/atlas/data/ThresholdPolicy;
      10: astore_1
      11: new           #31                 // class org/apache/jena/sparql/engine/binding/BindingComparator
      14: dup
      15: new           #32                 // class java/util/ArrayList
      18: dup
      19: invokespecial #33                 // Method java/util/ArrayList."<init>":()V
      22: aload_0
      23: invokespecial #29                 // Method org/apache/jena/sparql/engine/iterator/QueryIter1.getExecContext:()Lorg/apache/jena/sparql/engine/ExecutionContext;
      26: invokespecial #34                 // Method org/apache/jena/sparql/engine/binding/BindingComparator."<init>":(Ljava/util/List;Lorg/apache/jena/sparql/engine/ExecutionContext;)V
      29: astore_2
      30: aload_0
      31: aload_1
      32: invokestatic  #35                 // Method org/apache/jena/riot/system/SerializationFactoryFinder.bindingSerializationFactory:()Lorg/apache/jena/atlas/data/SerializationFactory;
      35: aload_2
      36: invokestatic  #36                 // Method org/apache/jena/atlas/data/BagFactory.newDistinctBag:(Lorg/apache/jena/atlas/data/ThresholdPolicy;Lorg/apache/jena/atlas/data/SerializationFactory;Ljava/util/Comparator;)Lorg/apache/jena/atlas/data/DistinctDataBag;
      39: putfield      #6                  // Field db:Lorg/apache/jena/atlas/data/DistinctDataBag;
      42: aload_0
      43: invokespecial #25                 // Method getInputNextUnseen:()Lorg/apache/jena/sparql/engine/binding/Binding;
      46: astore_3
      47: aload_3
      48: ifnonnull     54
      51: goto          65
      54: aload_0
      55: getfield      #6                  // Field db:Lorg/apache/jena/atlas/data/DistinctDataBag;
      58: aload_3
      59: invokevirtual #37                 // Method org/apache/jena/atlas/data/DistinctDataBag.add:(Ljava/lang/Object;)V
      62: goto          42
      65: return

  private org.apache.jena.sparql.engine.binding.Binding getInputNextUnseen();
    Code:
       0: aload_0
       1: invokevirtual #38                 // Method getInput:()Lorg/apache/jena/sparql/engine/QueryIterator;
       4: invokeinterface #39,  1           // InterfaceMethod org/apache/jena/sparql/engine/QueryIterator.hasNext:()Z
       9: ifeq          35
      12: aload_0
      13: invokespecial #40                 // Method getInputNext:()Lorg/apache/jena/sparql/engine/binding/Binding;
      16: astore_1
      17: aload_0
      18: getfield      #10                 // Field seen:Ljava/util/Set;
      21: aload_1
      22: invokeinterface #41,  2           // InterfaceMethod java/util/Set.contains:(Ljava/lang/Object;)Z
      27: ifeq          33
      30: goto          0
      33: aload_1
      34: areturn
      35: aconst_null
      36: areturn

  private org.apache.jena.sparql.engine.binding.Binding getInputNext();
    Code:
       0: aload_0
       1: invokevirtual #38                 // Method getInput:()Lorg/apache/jena/sparql/engine/QueryIterator;
       4: invokeinterface #42,  1           // InterfaceMethod org/apache/jena/sparql/engine/QueryIterator.next:()Ljava/lang/Object;
       9: checkcast     #43                 // class org/apache/jena/sparql/engine/binding/Binding
      12: astore_1
      13: new           #44                 // class org/apache/jena/sparql/engine/binding/BindingProjectNamed
      16: dup
      17: aload_1
      18: invokespecial #45                 // Method org/apache/jena/sparql/engine/binding/BindingProjectNamed."<init>":(Lorg/apache/jena/sparql/engine/binding/Binding;)V
      21: astore_1
      22: aload_1
      23: areturn

  protected org.apache.jena.sparql.engine.binding.Binding moveToNextBinding();
    Code:
       0: aload_0
       1: getfield      #11                 // Field slot:Lorg/apache/jena/sparql/engine/binding/Binding;
       4: ifnull        19
       7: aload_0
       8: getfield      #11                 // Field slot:Lorg/apache/jena/sparql/engine/binding/Binding;
      11: astore_1
      12: aload_0
      13: aconst_null
      14: putfield      #11                 // Field slot:Lorg/apache/jena/sparql/engine/binding/Binding;
      17: aload_1
      18: areturn
      19: aload_0
      20: getfield      #7                  // Field iterator:Ljava/util/Iterator;
      23: ifnull        41
      26: aload_0
      27: getfield      #7                  // Field iterator:Ljava/util/Iterator;
      30: invokeinterface #46,  1           // InterfaceMethod java/util/Iterator.next:()Ljava/lang/Object;
      35: checkcast     #43                 // class org/apache/jena/sparql/engine/binding/Binding
      38: astore_1
      39: aload_1
      40: areturn
      41: new           #47                 // class org/apache/jena/atlas/lib/InternalErrorException
      44: dup
      45: invokespecial #48                 // Method org/apache/jena/atlas/lib/InternalErrorException."<init>":()V
      48: athrow

  protected void closeSubIterator();
    Code:
       0: aload_0
       1: getfield      #6                  // Field db:Lorg/apache/jena/atlas/data/DistinctDataBag;
       4: ifnull        19
       7: aload_0
       8: aconst_null
       9: putfield      #7                  // Field iterator:Ljava/util/Iterator;
      12: aload_0
      13: getfield      #6                  // Field db:Lorg/apache/jena/atlas/data/DistinctDataBag;
      16: invokevirtual #49                 // Method org/apache/jena/atlas/data/DistinctDataBag.close:()V
      19: aload_0
      20: aconst_null
      21: putfield      #6                  // Field db:Lorg/apache/jena/atlas/data/DistinctDataBag;
      24: return

  protected void requestSubCancel();
    Code:
       0: return
}
