Compiled from "FramedConnection.java"
public abstract class com.squareup.okhttp.internal.framed.FramedConnection$Listener {
  public static final com.squareup.okhttp.internal.framed.FramedConnection$Listener REFUSE_INCOMING_STREAMS;

  public com.squareup.okhttp.internal.framed.FramedConnection$Listener();
    Code:
       0: aload_0
       1: invokespecial #1                  // Method java/lang/Object."<init>":()V
       4: return

  public abstract void onStream(com.squareup.okhttp.internal.framed.FramedStream) throws java.io.IOException;

  public void onSettings(com.squareup.okhttp.internal.framed.FramedConnection);
    Code:
       0: return

  static {};
    Code:
       0: new           #2                  // class com/squareup/okhttp/internal/framed/FramedConnection$Listener$1
       3: dup
       4: invokespecial #3                  // Method com/squareup/okhttp/internal/framed/FramedConnection$Listener$1."<init>":()V
       7: putstatic     #4                  // Field REFUSE_INCOMING_STREAMS:Lcom/squareup/okhttp/internal/framed/FramedConnection$Listener;
      10: return
}
