Compiled from "AsyncCompletionHandler.java"
public abstract class org.asynchttpclient.AsyncCompletionHandler<T> implements org.asynchttpclient.handler.ProgressAsyncHandler<T> {
  private static final org.slf4j.Logger LOGGER;

  private final org.asynchttpclient.Response$ResponseBuilder builder;

  public org.asynchttpclient.AsyncCompletionHandler();
    Code:
       0: aload_0
       1: invokespecial #1                  // Method java/lang/Object."<init>":()V
       4: aload_0
       5: new           #2                  // class org/asynchttpclient/Response$ResponseBuilder
       8: dup
       9: invokespecial #3                  // Method org/asynchttpclient/Response$ResponseBuilder."<init>":()V
      12: putfield      #4                  // Field builder:Lorg/asynchttpclient/Response$ResponseBuilder;
      15: return

  public org.asynchttpclient.AsyncHandler$State onStatusReceived(org.asynchttpclient.HttpResponseStatus) throws java.lang.Exception;
    Code:
       0: aload_0
       1: getfield      #4                  // Field builder:Lorg/asynchttpclient/Response$ResponseBuilder;
       4: invokevirtual #5                  // Method org/asynchttpclient/Response$ResponseBuilder.reset:()V
       7: aload_0
       8: getfield      #4                  // Field builder:Lorg/asynchttpclient/Response$ResponseBuilder;
      11: aload_1
      12: invokevirtual #6                  // Method org/asynchttpclient/Response$ResponseBuilder.accumulate:(Lorg/asynchttpclient/HttpResponseStatus;)V
      15: getstatic     #7                  // Field org/asynchttpclient/AsyncHandler$State.CONTINUE:Lorg/asynchttpclient/AsyncHandler$State;
      18: areturn

  public org.asynchttpclient.AsyncHandler$State onHeadersReceived(io.netty.handler.codec.http.HttpHeaders) throws java.lang.Exception;
    Code:
       0: aload_0
       1: getfield      #4                  // Field builder:Lorg/asynchttpclient/Response$ResponseBuilder;
       4: aload_1
       5: invokevirtual #8                  // Method org/asynchttpclient/Response$ResponseBuilder.accumulate:(Lio/netty/handler/codec/http/HttpHeaders;)V
       8: getstatic     #7                  // Field org/asynchttpclient/AsyncHandler$State.CONTINUE:Lorg/asynchttpclient/AsyncHandler$State;
      11: areturn

  public org.asynchttpclient.AsyncHandler$State onBodyPartReceived(org.asynchttpclient.HttpResponseBodyPart) throws java.lang.Exception;
    Code:
       0: aload_0
       1: getfield      #4                  // Field builder:Lorg/asynchttpclient/Response$ResponseBuilder;
       4: aload_1
       5: invokevirtual #9                  // Method org/asynchttpclient/Response$ResponseBuilder.accumulate:(Lorg/asynchttpclient/HttpResponseBodyPart;)V
       8: getstatic     #7                  // Field org/asynchttpclient/AsyncHandler$State.CONTINUE:Lorg/asynchttpclient/AsyncHandler$State;
      11: areturn

  public org.asynchttpclient.AsyncHandler$State onTrailingHeadersReceived(io.netty.handler.codec.http.HttpHeaders) throws java.lang.Exception;
    Code:
       0: aload_0
       1: getfield      #4                  // Field builder:Lorg/asynchttpclient/Response$ResponseBuilder;
       4: aload_1
       5: invokevirtual #8                  // Method org/asynchttpclient/Response$ResponseBuilder.accumulate:(Lio/netty/handler/codec/http/HttpHeaders;)V
       8: getstatic     #7                  // Field org/asynchttpclient/AsyncHandler$State.CONTINUE:Lorg/asynchttpclient/AsyncHandler$State;
      11: areturn

  public final T onCompleted() throws java.lang.Exception;
    Code:
       0: aload_0
       1: aload_0
       2: getfield      #4                  // Field builder:Lorg/asynchttpclient/Response$ResponseBuilder;
       5: invokevirtual #10                 // Method org/asynchttpclient/Response$ResponseBuilder.build:()Lorg/asynchttpclient/Response;
       8: invokevirtual #11                 // Method onCompleted:(Lorg/asynchttpclient/Response;)Ljava/lang/Object;
      11: areturn

  public void onThrowable(java.lang.Throwable);
    Code:
       0: getstatic     #12                 // Field LOGGER:Lorg/slf4j/Logger;
       3: aload_1
       4: invokevirtual #13                 // Method java/lang/Throwable.getMessage:()Ljava/lang/String;
       7: aload_1
       8: invokeinterface #14,  3           // InterfaceMethod org/slf4j/Logger.debug:(Ljava/lang/String;Ljava/lang/Throwable;)V
      13: return

  public abstract T onCompleted(org.asynchttpclient.Response) throws java.lang.Exception;

  public org.asynchttpclient.AsyncHandler$State onHeadersWritten();
    Code:
       0: getstatic     #7                  // Field org/asynchttpclient/AsyncHandler$State.CONTINUE:Lorg/asynchttpclient/AsyncHandler$State;
       3: areturn

  public org.asynchttpclient.AsyncHandler$State onContentWritten();
    Code:
       0: getstatic     #7                  // Field org/asynchttpclient/AsyncHandler$State.CONTINUE:Lorg/asynchttpclient/AsyncHandler$State;
       3: areturn

  public org.asynchttpclient.AsyncHandler$State onContentWriteProgress(long, long, long);
    Code:
       0: getstatic     #7                  // Field org/asynchttpclient/AsyncHandler$State.CONTINUE:Lorg/asynchttpclient/AsyncHandler$State;
       3: areturn

  static {};
    Code:
       0: ldc           #15                 // class org/asynchttpclient/AsyncCompletionHandler
       2: invokestatic  #16                 // Method org/slf4j/LoggerFactory.getLogger:(Ljava/lang/Class;)Lorg/slf4j/Logger;
       5: putstatic     #12                 // Field LOGGER:Lorg/slf4j/Logger;
       8: return
}
