Compiled from "JodaDeserializers.java"
abstract class org.codehaus.jackson.map.ext.JodaDeserializers$JodaDeserializer<T> extends org.codehaus.jackson.map.deser.std.StdScalarDeserializer<T> {
  static final org.joda.time.format.DateTimeFormatter _localDateTimeFormat;

  protected org.codehaus.jackson.map.ext.JodaDeserializers$JodaDeserializer(java.lang.Class<T>);
    Code:
       0: aload_0
       1: aload_1
       2: invokespecial #1                  // Method org/codehaus/jackson/map/deser/std/StdScalarDeserializer."<init>":(Ljava/lang/Class;)V
       5: return

  protected org.joda.time.DateTime parseLocal(org.codehaus.jackson.JsonParser) throws java.io.IOException, org.codehaus.jackson.JsonProcessingException;
    Code:
       0: aload_1
       1: invokevirtual #2                  // Method org/codehaus/jackson/JsonParser.getText:()Ljava/lang/String;
       4: invokevirtual #3                  // Method java/lang/String.trim:()Ljava/lang/String;
       7: astore_2
       8: aload_2
       9: invokevirtual #4                  // Method java/lang/String.length:()I
      12: ifne          17
      15: aconst_null
      16: areturn
      17: getstatic     #5                  // Field _localDateTimeFormat:Lorg/joda/time/format/DateTimeFormatter;
      20: aload_2
      21: invokevirtual #6                  // Method org/joda/time/format/DateTimeFormatter.parseDateTime:(Ljava/lang/String;)Lorg/joda/time/DateTime;
      24: areturn

  static {};
    Code:
       0: invokestatic  #7                  // Method org/joda/time/format/ISODateTimeFormat.localDateOptionalTimeParser:()Lorg/joda/time/format/DateTimeFormatter;
       3: putstatic     #5                  // Field _localDateTimeFormat:Lorg/joda/time/format/DateTimeFormatter;
       6: return
}
