Compiled from "PastValidatorForThaiBuddhistDate.java"
public class org.hibernate.validator.internal.constraintvalidators.bv.time.past.PastValidatorForThaiBuddhistDate extends org.hibernate.validator.internal.constraintvalidators.bv.time.past.AbstractPastJavaTimeValidator<java.time.chrono.ThaiBuddhistDate> {
  public org.hibernate.validator.internal.constraintvalidators.bv.time.past.PastValidatorForThaiBuddhistDate();
    Code:
       0: aload_0
       1: invokespecial #1                  // Method org/hibernate/validator/internal/constraintvalidators/bv/time/past/AbstractPastJavaTimeValidator."<init>":()V
       4: return

  protected java.time.chrono.ThaiBuddhistDate getReferenceValue(java.time.Clock);
    Code:
       0: aload_1
       1: invokestatic  #7                  // Method java/time/chrono/ThaiBuddhistDate.now:(Ljava/time/Clock;)Ljava/time/chrono/ThaiBuddhistDate;
       4: areturn

  protected java.time.temporal.TemporalAccessor getReferenceValue(java.time.Clock);
    Code:
       0: aload_0
       1: aload_1
       2: invokevirtual #13                 // Method getReferenceValue:(Ljava/time/Clock;)Ljava/time/chrono/ThaiBuddhistDate;
       5: areturn
}
