Compiled from "StandardExpressionUtils.java"
public final class org.thymeleaf.standard.util.StandardExpressionUtils {
  private static final char[] EXEC_INFO_ARRAY;

  private static final int EXEC_INFO_LEN;

  public static boolean mightNeedExpressionObjects(java.lang.String);
    Code:
       0: aload_0
       1: invokevirtual #1                  // Method java/lang/String.length:()I
       4: istore_1
       5: iconst_0
       6: istore_2
       7: iload_1
       8: iinc          1, -1
      11: ifeq          62
      14: aload_0
      15: iload_1
      16: invokevirtual #2                  // Method java/lang/String.charAt:(I)C
      19: istore_3
      20: iload_3
      21: bipush        35
      23: if_icmpne     28
      26: iconst_1
      27: ireturn
      28: iload_3
      29: getstatic     #3                  // Field EXEC_INFO_ARRAY:[C
      32: iload_2
      33: caload
      34: if_icmpne     49
      37: iinc          2, 1
      40: iload_2
      41: getstatic     #4                  // Field EXEC_INFO_LEN:I
      44: if_icmpne     7
      47: iconst_1
      48: ireturn
      49: iload_2
      50: ifle          57
      53: iload_1
      54: iload_2
      55: iadd
      56: istore_1
      57: iconst_0
      58: istore_2
      59: goto          7
      62: iconst_0
      63: ireturn

  private org.thymeleaf.standard.util.StandardExpressionUtils();
    Code:
       0: aload_0
       1: invokespecial #5                  // Method java/lang/Object."<init>":()V
       4: return

  static {};
    Code:
       0: ldc           #6                  // String ofnIcexe
       2: invokevirtual #7                  // Method java/lang/String.toCharArray:()[C
       5: putstatic     #3                  // Field EXEC_INFO_ARRAY:[C
       8: getstatic     #3                  // Field EXEC_INFO_ARRAY:[C
      11: arraylength
      12: putstatic     #4                  // Field EXEC_INFO_LEN:I
      15: return
}
