Compiled from "Outputs.java"
public class software.amazon.awssdk.services.ioteventsdata.endpoints.internal.Outputs$Builder {
  private java.lang.String dnsSuffix;

  private java.lang.String dualStackDnsSuffix;

  private boolean supportsFips;

  private boolean supportsDualStack;

  public software.amazon.awssdk.services.ioteventsdata.endpoints.internal.Outputs$Builder();
    Code:
       0: aload_0
       1: invokespecial #5                  // Method java/lang/Object."<init>":()V
       4: return

  public software.amazon.awssdk.services.ioteventsdata.endpoints.internal.Outputs$Builder dnsSuffix(java.lang.String);
    Code:
       0: aload_0
       1: aload_1
       2: putfield      #4                  // Field dnsSuffix:Ljava/lang/String;
       5: aload_0
       6: areturn

  public software.amazon.awssdk.services.ioteventsdata.endpoints.internal.Outputs$Builder dualStackDnsSuffix(java.lang.String);
    Code:
       0: aload_0
       1: aload_1
       2: putfield      #3                  // Field dualStackDnsSuffix:Ljava/lang/String;
       5: aload_0
       6: areturn

  public software.amazon.awssdk.services.ioteventsdata.endpoints.internal.Outputs$Builder supportsFips(boolean);
    Code:
       0: aload_0
       1: iload_1
       2: putfield      #2                  // Field supportsFips:Z
       5: aload_0
       6: areturn

  public software.amazon.awssdk.services.ioteventsdata.endpoints.internal.Outputs$Builder supportsDualStack(boolean);
    Code:
       0: aload_0
       1: iload_1
       2: putfield      #1                  // Field supportsDualStack:Z
       5: aload_0
       6: areturn

  public software.amazon.awssdk.services.ioteventsdata.endpoints.internal.Outputs build();
    Code:
       0: new           #6                  // class software/amazon/awssdk/services/ioteventsdata/endpoints/internal/Outputs
       3: dup
       4: aload_0
       5: aconst_null
       6: invokespecial #7                  // Method software/amazon/awssdk/services/ioteventsdata/endpoints/internal/Outputs."<init>":(Lsoftware/amazon/awssdk/services/ioteventsdata/endpoints/internal/Outputs$Builder;Lsoftware/amazon/awssdk/services/ioteventsdata/endpoints/internal/Outputs$1;)V
       9: areturn

  static java.lang.String access$000(software.amazon.awssdk.services.ioteventsdata.endpoints.internal.Outputs$Builder);
    Code:
       0: aload_0
       1: getfield      #4                  // Field dnsSuffix:Ljava/lang/String;
       4: areturn

  static java.lang.String access$100(software.amazon.awssdk.services.ioteventsdata.endpoints.internal.Outputs$Builder);
    Code:
       0: aload_0
       1: getfield      #3                  // Field dualStackDnsSuffix:Ljava/lang/String;
       4: areturn

  static boolean access$200(software.amazon.awssdk.services.ioteventsdata.endpoints.internal.Outputs$Builder);
    Code:
       0: aload_0
       1: getfield      #2                  // Field supportsFips:Z
       4: ireturn

  static boolean access$300(software.amazon.awssdk.services.ioteventsdata.endpoints.internal.Outputs$Builder);
    Code:
       0: aload_0
       1: getfield      #1                  // Field supportsDualStack:Z
       4: ireturn
}
