Compiled from "SingleArgFn.java"
public abstract class software.amazon.awssdk.services.ioteventsdata.endpoints.internal.SingleArgFn extends software.amazon.awssdk.services.ioteventsdata.endpoints.internal.Fn {
  public software.amazon.awssdk.services.ioteventsdata.endpoints.internal.SingleArgFn(software.amazon.awssdk.services.ioteventsdata.endpoints.internal.FnNode);
    Code:
       0: aload_0
       1: aload_1
       2: invokespecial #1                  // Method software/amazon/awssdk/services/ioteventsdata/endpoints/internal/Fn."<init>":(Lsoftware/amazon/awssdk/services/ioteventsdata/endpoints/internal/FnNode;)V
       5: return

  public software.amazon.awssdk.services.ioteventsdata.endpoints.internal.Expr target();
    Code:
       0: aload_0
       1: invokevirtual #2                  // Method expectOneArg:()Lsoftware/amazon/awssdk/services/ioteventsdata/endpoints/internal/Expr;
       4: areturn

  public software.amazon.awssdk.services.ioteventsdata.endpoints.internal.Value eval(software.amazon.awssdk.services.ioteventsdata.endpoints.internal.Scope<software.amazon.awssdk.services.ioteventsdata.endpoints.internal.Value>);
    Code:
       0: aload_0
       1: aload_0
       2: invokevirtual #2                  // Method expectOneArg:()Lsoftware/amazon/awssdk/services/ioteventsdata/endpoints/internal/Expr;
       5: aload_1
       6: invokevirtual #3                  // Method software/amazon/awssdk/services/ioteventsdata/endpoints/internal/Expr.eval:(Lsoftware/amazon/awssdk/services/ioteventsdata/endpoints/internal/Scope;)Lsoftware/amazon/awssdk/services/ioteventsdata/endpoints/internal/Value;
       9: invokevirtual #4                  // Method evalArg:(Lsoftware/amazon/awssdk/services/ioteventsdata/endpoints/internal/Value;)Lsoftware/amazon/awssdk/services/ioteventsdata/endpoints/internal/Value;
      12: areturn

  protected abstract software.amazon.awssdk.services.ioteventsdata.endpoints.internal.Value evalArg(software.amazon.awssdk.services.ioteventsdata.endpoints.internal.Value);
}
