Compiled from "NonNullableTransientDependencies.java"
public final class org.hibernate.engine.internal.NonNullableTransientDependencies {
  private java.util.Map<java.lang.Object, java.util.Set<java.lang.String>> propertyPathsByTransientEntity;

  public org.hibernate.engine.internal.NonNullableTransientDependencies();
    Code:
       0: aload_0
       1: invokespecial #1                  // Method java/lang/Object."<init>":()V
       4: return

  void add(java.lang.String, java.lang.Object);
    Code:
       0: aload_0
       1: getfield      #2                  // Field propertyPathsByTransientEntity:Ljava/util/Map;
       4: ifnonnull     18
       7: aload_0
       8: new           #3                  // class java/util/IdentityHashMap
      11: dup
      12: invokespecial #4                  // Method java/util/IdentityHashMap."<init>":()V
      15: putfield      #2                  // Field propertyPathsByTransientEntity:Ljava/util/Map;
      18: aload_0
      19: getfield      #2                  // Field propertyPathsByTransientEntity:Ljava/util/Map;
      22: aload_2
      23: invokeinterface #5,  2            // InterfaceMethod java/util/Map.get:(Ljava/lang/Object;)Ljava/lang/Object;
      28: checkcast     #6                  // class java/util/Set
      31: astore_3
      32: aload_3
      33: ifnonnull     56
      36: new           #7                  // class java/util/HashSet
      39: dup
      40: invokespecial #8                  // Method java/util/HashSet."<init>":()V
      43: astore_3
      44: aload_0
      45: getfield      #2                  // Field propertyPathsByTransientEntity:Ljava/util/Map;
      48: aload_2
      49: aload_3
      50: invokeinterface #9,  3            // InterfaceMethod java/util/Map.put:(Ljava/lang/Object;Ljava/lang/Object;)Ljava/lang/Object;
      55: pop
      56: aload_3
      57: aload_1
      58: invokeinterface #10,  2           // InterfaceMethod java/util/Set.add:(Ljava/lang/Object;)Z
      63: pop
      64: return

  public java.lang.Iterable<java.lang.Object> getNonNullableTransientEntities();
    Code:
       0: aload_0
       1: getfield      #2                  // Field propertyPathsByTransientEntity:Ljava/util/Map;
       4: ifnonnull     11
       7: invokestatic  #11                 // Method java/util/Collections.emptyList:()Ljava/util/List;
      10: areturn
      11: aload_0
      12: getfield      #2                  // Field propertyPathsByTransientEntity:Ljava/util/Map;
      15: invokeinterface #12,  1           // InterfaceMethod java/util/Map.keySet:()Ljava/util/Set;
      20: areturn

  public java.lang.Iterable<java.lang.String> getNonNullableTransientPropertyPaths(java.lang.Object);
    Code:
       0: aload_0
       1: getfield      #2                  // Field propertyPathsByTransientEntity:Ljava/util/Map;
       4: ifnonnull     11
       7: invokestatic  #11                 // Method java/util/Collections.emptyList:()Ljava/util/List;
      10: areturn
      11: aload_0
      12: getfield      #2                  // Field propertyPathsByTransientEntity:Ljava/util/Map;
      15: aload_1
      16: invokeinterface #5,  2            // InterfaceMethod java/util/Map.get:(Ljava/lang/Object;)Ljava/lang/Object;
      21: checkcast     #13                 // class java/lang/Iterable
      24: areturn

  public boolean isEmpty();
    Code:
       0: aload_0
       1: getfield      #2                  // Field propertyPathsByTransientEntity:Ljava/util/Map;
       4: ifnull        19
       7: aload_0
       8: getfield      #2                  // Field propertyPathsByTransientEntity:Ljava/util/Map;
      11: invokeinterface #14,  1           // InterfaceMethod java/util/Map.isEmpty:()Z
      16: ifeq          23
      19: iconst_1
      20: goto          24
      23: iconst_0
      24: ireturn

  public void resolveNonNullableTransientEntity(java.lang.Object);
    Code:
       0: aload_0
       1: getfield      #2                  // Field propertyPathsByTransientEntity:Ljava/util/Map;
       4: ifnull        30
       7: aload_0
       8: getfield      #2                  // Field propertyPathsByTransientEntity:Ljava/util/Map;
      11: aload_1
      12: invokeinterface #15,  2           // InterfaceMethod java/util/Map.remove:(Ljava/lang/Object;)Ljava/lang/Object;
      17: ifnonnull     30
      20: new           #16                 // class java/lang/IllegalStateException
      23: dup
      24: ldc           #17                 // String Attempt to resolve a non-nullable, transient entity that is not a dependency.
      26: invokespecial #18                 // Method java/lang/IllegalStateException."<init>":(Ljava/lang/String;)V
      29: athrow
      30: return

  public java.lang.String toLoggableString(org.hibernate.engine.spi.SharedSessionContractImplementor);
    Code:
       0: new           #19                 // class java/lang/StringBuilder
       3: dup
       4: aload_0
       5: invokevirtual #20                 // Method java/lang/Object.getClass:()Ljava/lang/Class;
       8: invokevirtual #21                 // Method java/lang/Class.getSimpleName:()Ljava/lang/String;
      11: invokespecial #22                 // Method java/lang/StringBuilder."<init>":(Ljava/lang/String;)V
      14: bipush        91
      16: invokevirtual #23                 // Method java/lang/StringBuilder.append:(C)Ljava/lang/StringBuilder;
      19: astore_2
      20: aload_0
      21: getfield      #2                  // Field propertyPathsByTransientEntity:Ljava/util/Map;
      24: ifnull        105
      27: aload_0
      28: getfield      #2                  // Field propertyPathsByTransientEntity:Ljava/util/Map;
      31: invokeinterface #24,  1           // InterfaceMethod java/util/Map.entrySet:()Ljava/util/Set;
      36: invokeinterface #25,  1           // InterfaceMethod java/util/Set.iterator:()Ljava/util/Iterator;
      41: astore_3
      42: aload_3
      43: invokeinterface #26,  1           // InterfaceMethod java/util/Iterator.hasNext:()Z
      48: ifeq          105
      51: aload_3
      52: invokeinterface #27,  1           // InterfaceMethod java/util/Iterator.next:()Ljava/lang/Object;
      57: checkcast     #28                 // class java/util/Map$Entry
      60: astore        4
      62: aload_2
      63: ldc           #29                 // String transientEntityName=
      65: invokevirtual #30                 // Method java/lang/StringBuilder.append:(Ljava/lang/String;)Ljava/lang/StringBuilder;
      68: aload_1
      69: aload         4
      71: invokeinterface #31,  1           // InterfaceMethod java/util/Map$Entry.getKey:()Ljava/lang/Object;
      76: invokeinterface #32,  2           // InterfaceMethod org/hibernate/engine/spi/SharedSessionContractImplementor.bestGuessEntityName:(Ljava/lang/Object;)Ljava/lang/String;
      81: invokevirtual #30                 // Method java/lang/StringBuilder.append:(Ljava/lang/String;)Ljava/lang/StringBuilder;
      84: pop
      85: aload_2
      86: ldc           #33                 // String  requiredBy=
      88: invokevirtual #30                 // Method java/lang/StringBuilder.append:(Ljava/lang/String;)Ljava/lang/StringBuilder;
      91: aload         4
      93: invokeinterface #34,  1           // InterfaceMethod java/util/Map$Entry.getValue:()Ljava/lang/Object;
      98: invokevirtual #35                 // Method java/lang/StringBuilder.append:(Ljava/lang/Object;)Ljava/lang/StringBuilder;
     101: pop
     102: goto          42
     105: aload_2
     106: bipush        93
     108: invokevirtual #23                 // Method java/lang/StringBuilder.append:(C)Ljava/lang/StringBuilder;
     111: pop
     112: aload_2
     113: invokevirtual #36                 // Method java/lang/StringBuilder.toString:()Ljava/lang/String;
     116: areturn
}
