Compiled from "StatusHelper.java"
public abstract class org.omg.CosTransactions.StatusHelper {
  private static java.lang.String _id;

  private static org.omg.CORBA.TypeCode __typeCode;

  public org.omg.CosTransactions.StatusHelper();
    Code:
       0: aload_0
       1: invokespecial #1                  // Method java/lang/Object."<init>":()V
       4: return

  public static void insert(org.omg.CORBA.Any, org.omg.CosTransactions.Status);
    Code:
       0: aload_0
       1: invokevirtual #2                  // Method org/omg/CORBA/Any.create_output_stream:()Lorg/omg/CORBA/portable/OutputStream;
       4: astore_2
       5: aload_0
       6: invokestatic  #3                  // Method type:()Lorg/omg/CORBA/TypeCode;
       9: invokevirtual #4                  // Method org/omg/CORBA/Any.type:(Lorg/omg/CORBA/TypeCode;)V
      12: aload_2
      13: aload_1
      14: invokestatic  #5                  // Method write:(Lorg/omg/CORBA/portable/OutputStream;Lorg/omg/CosTransactions/Status;)V
      17: aload_0
      18: aload_2
      19: invokevirtual #6                  // Method org/omg/CORBA/portable/OutputStream.create_input_stream:()Lorg/omg/CORBA/portable/InputStream;
      22: invokestatic  #3                  // Method type:()Lorg/omg/CORBA/TypeCode;
      25: invokevirtual #7                  // Method org/omg/CORBA/Any.read_value:(Lorg/omg/CORBA/portable/InputStream;Lorg/omg/CORBA/TypeCode;)V
      28: return

  public static org.omg.CosTransactions.Status extract(org.omg.CORBA.Any);
    Code:
       0: aload_0
       1: invokevirtual #8                  // Method org/omg/CORBA/Any.create_input_stream:()Lorg/omg/CORBA/portable/InputStream;
       4: invokestatic  #9                  // Method read:(Lorg/omg/CORBA/portable/InputStream;)Lorg/omg/CosTransactions/Status;
       7: areturn

  public static synchronized org.omg.CORBA.TypeCode type();
    Code:
       0: getstatic     #10                 // Field __typeCode:Lorg/omg/CORBA/TypeCode;
       3: ifnonnull     79
       6: invokestatic  #11                 // Method org/omg/CORBA/ORB.init:()Lorg/omg/CORBA/ORB;
       9: invokestatic  #12                 // Method id:()Ljava/lang/String;
      12: ldc           #13                 // String Status
      14: bipush        10
      16: anewarray     #14                 // class java/lang/String
      19: dup
      20: iconst_0
      21: ldc           #15                 // String StatusActive
      23: aastore
      24: dup
      25: iconst_1
      26: ldc           #16                 // String StatusMarkedRollback
      28: aastore
      29: dup
      30: iconst_2
      31: ldc           #17                 // String StatusPrepared
      33: aastore
      34: dup
      35: iconst_3
      36: ldc           #18                 // String StatusCommitted
      38: aastore
      39: dup
      40: iconst_4
      41: ldc           #19                 // String StatusRolledBack
      43: aastore
      44: dup
      45: iconst_5
      46: ldc           #20                 // String StatusUnknown
      48: aastore
      49: dup
      50: bipush        6
      52: ldc           #21                 // String StatusPreparing
      54: aastore
      55: dup
      56: bipush        7
      58: ldc           #22                 // String StatusCommitting
      60: aastore
      61: dup
      62: bipush        8
      64: ldc           #23                 // String StatusRollingBack
      66: aastore
      67: dup
      68: bipush        9
      70: ldc           #24                 // String StatusNoTransaction
      72: aastore
      73: invokevirtual #25                 // Method org/omg/CORBA/ORB.create_enum_tc:(Ljava/lang/String;Ljava/lang/String;[Ljava/lang/String;)Lorg/omg/CORBA/TypeCode;
      76: putstatic     #10                 // Field __typeCode:Lorg/omg/CORBA/TypeCode;
      79: getstatic     #10                 // Field __typeCode:Lorg/omg/CORBA/TypeCode;
      82: areturn

  public static java.lang.String id();
    Code:
       0: getstatic     #26                 // Field _id:Ljava/lang/String;
       3: areturn

  public static org.omg.CosTransactions.Status read(org.omg.CORBA.portable.InputStream);
    Code:
       0: aload_0
       1: invokevirtual #27                 // Method org/omg/CORBA/portable/InputStream.read_long:()I
       4: invokestatic  #28                 // Method org/omg/CosTransactions/Status.from_int:(I)Lorg/omg/CosTransactions/Status;
       7: areturn

  public static void write(org.omg.CORBA.portable.OutputStream, org.omg.CosTransactions.Status);
    Code:
       0: aload_0
       1: aload_1
       2: invokevirtual #29                 // Method org/omg/CosTransactions/Status.value:()I
       5: invokevirtual #30                 // Method org/omg/CORBA/portable/OutputStream.write_long:(I)V
       8: return

  static {};
    Code:
       0: ldc           #31                 // String IDL:omg.org/CosTransactions/Status:1.0
       2: putstatic     #26                 // Field _id:Ljava/lang/String;
       5: aconst_null
       6: putstatic     #10                 // Field __typeCode:Lorg/omg/CORBA/TypeCode;
       9: return
}
