Compiled from "SubtransactionAwareResourcePOATie.java"
public class org.omg.CosTransactions.SubtransactionAwareResourcePOATie extends org.omg.CosTransactions.SubtransactionAwareResourcePOA {
  private org.omg.CosTransactions.SubtransactionAwareResourceOperations _impl;

  private org.omg.PortableServer.POA _poa;

  public org.omg.CosTransactions.SubtransactionAwareResourcePOATie(org.omg.CosTransactions.SubtransactionAwareResourceOperations);
    Code:
       0: aload_0
       1: invokespecial #1                  // Method org/omg/CosTransactions/SubtransactionAwareResourcePOA."<init>":()V
       4: aload_0
       5: aload_1
       6: putfield      #2                  // Field _impl:Lorg/omg/CosTransactions/SubtransactionAwareResourceOperations;
       9: return

  public org.omg.CosTransactions.SubtransactionAwareResourcePOATie(org.omg.CosTransactions.SubtransactionAwareResourceOperations, org.omg.PortableServer.POA);
    Code:
       0: aload_0
       1: invokespecial #1                  // Method org/omg/CosTransactions/SubtransactionAwareResourcePOA."<init>":()V
       4: aload_0
       5: aload_1
       6: putfield      #2                  // Field _impl:Lorg/omg/CosTransactions/SubtransactionAwareResourceOperations;
       9: aload_0
      10: aload_2
      11: putfield      #3                  // Field _poa:Lorg/omg/PortableServer/POA;
      14: return

  public org.omg.CosTransactions.SubtransactionAwareResourceOperations _delegate();
    Code:
       0: aload_0
       1: getfield      #2                  // Field _impl:Lorg/omg/CosTransactions/SubtransactionAwareResourceOperations;
       4: areturn

  public void _delegate(org.omg.CosTransactions.SubtransactionAwareResourceOperations);
    Code:
       0: aload_0
       1: aload_1
       2: putfield      #2                  // Field _impl:Lorg/omg/CosTransactions/SubtransactionAwareResourceOperations;
       5: return

  public org.omg.PortableServer.POA _default_POA();
    Code:
       0: aload_0
       1: getfield      #3                  // Field _poa:Lorg/omg/PortableServer/POA;
       4: ifnull        12
       7: aload_0
       8: getfield      #3                  // Field _poa:Lorg/omg/PortableServer/POA;
      11: areturn
      12: aload_0
      13: invokespecial #4                  // Method org/omg/CosTransactions/SubtransactionAwareResourcePOA._default_POA:()Lorg/omg/PortableServer/POA;
      16: areturn

  public void commit_subtransaction(org.omg.CosTransactions.Coordinator);
    Code:
       0: aload_0
       1: getfield      #2                  // Field _impl:Lorg/omg/CosTransactions/SubtransactionAwareResourceOperations;
       4: aload_1
       5: invokeinterface #5,  2            // InterfaceMethod org/omg/CosTransactions/SubtransactionAwareResourceOperations.commit_subtransaction:(Lorg/omg/CosTransactions/Coordinator;)V
      10: return

  public void rollback_subtransaction();
    Code:
       0: aload_0
       1: getfield      #2                  // Field _impl:Lorg/omg/CosTransactions/SubtransactionAwareResourceOperations;
       4: invokeinterface #6,  1            // InterfaceMethod org/omg/CosTransactions/SubtransactionAwareResourceOperations.rollback_subtransaction:()V
       9: return

  public org.omg.CosTransactions.Vote prepare() throws org.omg.CosTransactions.HeuristicMixed, org.omg.CosTransactions.HeuristicHazard;
    Code:
       0: aload_0
       1: getfield      #2                  // Field _impl:Lorg/omg/CosTransactions/SubtransactionAwareResourceOperations;
       4: invokeinterface #7,  1            // InterfaceMethod org/omg/CosTransactions/SubtransactionAwareResourceOperations.prepare:()Lorg/omg/CosTransactions/Vote;
       9: areturn

  public void rollback() throws org.omg.CosTransactions.HeuristicCommit, org.omg.CosTransactions.HeuristicMixed, org.omg.CosTransactions.HeuristicHazard;
    Code:
       0: aload_0
       1: getfield      #2                  // Field _impl:Lorg/omg/CosTransactions/SubtransactionAwareResourceOperations;
       4: invokeinterface #8,  1            // InterfaceMethod org/omg/CosTransactions/SubtransactionAwareResourceOperations.rollback:()V
       9: return

  public void commit() throws org.omg.CosTransactions.NotPrepared, org.omg.CosTransactions.HeuristicRollback, org.omg.CosTransactions.HeuristicMixed, org.omg.CosTransactions.HeuristicHazard;
    Code:
       0: aload_0
       1: getfield      #2                  // Field _impl:Lorg/omg/CosTransactions/SubtransactionAwareResourceOperations;
       4: invokeinterface #9,  1            // InterfaceMethod org/omg/CosTransactions/SubtransactionAwareResourceOperations.commit:()V
       9: return

  public void commit_one_phase() throws org.omg.CosTransactions.HeuristicHazard;
    Code:
       0: aload_0
       1: getfield      #2                  // Field _impl:Lorg/omg/CosTransactions/SubtransactionAwareResourceOperations;
       4: invokeinterface #10,  1           // InterfaceMethod org/omg/CosTransactions/SubtransactionAwareResourceOperations.commit_one_phase:()V
       9: return

  public void forget();
    Code:
       0: aload_0
       1: getfield      #2                  // Field _impl:Lorg/omg/CosTransactions/SubtransactionAwareResourceOperations;
       4: invokeinterface #11,  1           // InterfaceMethod org/omg/CosTransactions/SubtransactionAwareResourceOperations.forget:()V
       9: return
}
