Compiled from "SubversionSCM.java"
public final class hudson.scm.SubversionSCM$SvnInfo implements java.io.Serializable, java.lang.Comparable<hudson.scm.SubversionSCM$SvnInfo> {
  public final java.lang.String url;

  public final long revision;

  private static final long serialVersionUID;

  public hudson.scm.SubversionSCM$SvnInfo(java.lang.String, long);
    Code:
       0: aload_0
       1: invokespecial #1                  // Method java/lang/Object."<init>":()V
       4: aload_0
       5: aload_1
       6: putfield      #2                  // Field url:Ljava/lang/String;
       9: aload_0
      10: lload_2
      11: putfield      #3                  // Field revision:J
      14: return

  public hudson.scm.SubversionSCM$SvnInfo(org.tmatesoft.svn.core.wc.SVNInfo);
    Code:
       0: aload_0
       1: aload_1
       2: invokevirtual #4                  // Method org/tmatesoft/svn/core/wc/SVNInfo.getURL:()Lorg/tmatesoft/svn/core/SVNURL;
       5: invokevirtual #5                  // Method org/tmatesoft/svn/core/SVNURL.toDecodedString:()Ljava/lang/String;
       8: aload_1
       9: invokevirtual #6                  // Method org/tmatesoft/svn/core/wc/SVNInfo.getCommittedRevision:()Lorg/tmatesoft/svn/core/wc/SVNRevision;
      12: invokevirtual #7                  // Method org/tmatesoft/svn/core/wc/SVNRevision.getNumber:()J
      15: invokespecial #8                  // Method "<init>":(Ljava/lang/String;J)V
      18: return

  public org.tmatesoft.svn.core.SVNURL getSVNURL() throws org.tmatesoft.svn.core.SVNException;
    Code:
       0: aload_0
       1: getfield      #2                  // Field url:Ljava/lang/String;
       4: invokestatic  #9                  // Method org/tmatesoft/svn/core/SVNURL.parseURIDecoded:(Ljava/lang/String;)Lorg/tmatesoft/svn/core/SVNURL;
       7: areturn

  public int compareTo(hudson.scm.SubversionSCM$SvnInfo);
    Code:
       0: aload_0
       1: getfield      #2                  // Field url:Ljava/lang/String;
       4: aload_1
       5: getfield      #2                  // Field url:Ljava/lang/String;
       8: invokevirtual #10                 // Method java/lang/String.compareTo:(Ljava/lang/String;)I
      11: istore_2
      12: iload_2
      13: ifeq          18
      16: iload_2
      17: ireturn
      18: aload_0
      19: getfield      #3                  // Field revision:J
      22: aload_1
      23: getfield      #3                  // Field revision:J
      26: lcmp
      27: ifge          32
      30: iconst_m1
      31: ireturn
      32: aload_0
      33: getfield      #3                  // Field revision:J
      36: aload_1
      37: getfield      #3                  // Field revision:J
      40: lcmp
      41: ifle          46
      44: iconst_1
      45: ireturn
      46: iconst_0
      47: ireturn

  public boolean equals(java.lang.Object);
    Code:
       0: aload_0
       1: aload_1
       2: if_acmpne     7
       5: iconst_1
       6: ireturn
       7: aload_1
       8: ifnull        22
      11: aload_0
      12: invokevirtual #11                 // Method java/lang/Object.getClass:()Ljava/lang/Class;
      15: aload_1
      16: invokevirtual #11                 // Method java/lang/Object.getClass:()Ljava/lang/Class;
      19: if_acmpeq     24
      22: iconst_0
      23: ireturn
      24: aload_1
      25: checkcast     #12                 // class hudson/scm/SubversionSCM$SvnInfo
      28: astore_2
      29: aload_0
      30: getfield      #3                  // Field revision:J
      33: aload_2
      34: getfield      #3                  // Field revision:J
      37: lcmp
      38: ifeq          43
      41: iconst_0
      42: ireturn
      43: aload_0
      44: getfield      #2                  // Field url:Ljava/lang/String;
      47: aload_2
      48: getfield      #2                  // Field url:Ljava/lang/String;
      51: invokevirtual #13                 // Method java/lang/String.equals:(Ljava/lang/Object;)Z
      54: ireturn

  public int hashCode();
    Code:
       0: aload_0
       1: getfield      #2                  // Field url:Ljava/lang/String;
       4: invokevirtual #14                 // Method java/lang/String.hashCode:()I
       7: istore_1
       8: bipush        31
      10: iload_1
      11: imul
      12: aload_0
      13: getfield      #3                  // Field revision:J
      16: aload_0
      17: getfield      #3                  // Field revision:J
      20: bipush        32
      22: lushr
      23: lxor
      24: l2i
      25: iadd
      26: istore_1
      27: iload_1
      28: ireturn

  public java.lang.String toString();
    Code:
       0: ldc           #15                 // String %s (rev.%s)
       2: iconst_2
       3: anewarray     #16                 // class java/lang/Object
       6: dup
       7: iconst_0
       8: aload_0
       9: getfield      #2                  // Field url:Ljava/lang/String;
      12: aastore
      13: dup
      14: iconst_1
      15: aload_0
      16: getfield      #3                  // Field revision:J
      19: invokestatic  #17                 // Method java/lang/Long.valueOf:(J)Ljava/lang/Long;
      22: aastore
      23: invokestatic  #18                 // Method java/lang/String.format:(Ljava/lang/String;[Ljava/lang/Object;)Ljava/lang/String;
      26: areturn

  public int compareTo(java.lang.Object);
    Code:
       0: aload_0
       1: aload_1
       2: checkcast     #12                 // class hudson/scm/SubversionSCM$SvnInfo
       5: invokevirtual #19                 // Method compareTo:(Lhudson/scm/SubversionSCM$SvnInfo;)I
       8: ireturn
}
