Compiled from "HealthLakeAsyncClient.java"
public interface software.amazon.awssdk.services.healthlake.HealthLakeAsyncClient extends software.amazon.awssdk.awscore.AwsClient {
  public static final java.lang.String SERVICE_NAME;

  public static final java.lang.String SERVICE_METADATA_ID;

  public default java.util.concurrent.CompletableFuture<software.amazon.awssdk.services.healthlake.model.CreateFhirDatastoreResponse> createFHIRDatastore(software.amazon.awssdk.services.healthlake.model.CreateFhirDatastoreRequest);
    Code:
       0: new           #1                  // class java/lang/UnsupportedOperationException
       3: dup
       4: invokespecial #2                  // Method java/lang/UnsupportedOperationException."<init>":()V
       7: athrow

  public default java.util.concurrent.CompletableFuture<software.amazon.awssdk.services.healthlake.model.CreateFhirDatastoreResponse> createFHIRDatastore(java.util.function.Consumer<software.amazon.awssdk.services.healthlake.model.CreateFhirDatastoreRequest$Builder>);
    Code:
       0: aload_0
       1: invokestatic  #3                  // Method software/amazon/awssdk/services/healthlake/model/CreateFhirDatastoreRequest.builder:()Lsoftware/amazon/awssdk/services/healthlake/model/CreateFhirDatastoreRequest$Builder;
       4: aload_1
       5: invokeinterface #4,  2            // InterfaceMethod software/amazon/awssdk/services/healthlake/model/CreateFhirDatastoreRequest$Builder.applyMutation:(Ljava/util/function/Consumer;)Lsoftware/amazon/awssdk/utils/builder/SdkBuilder;
      10: checkcast     #5                  // class software/amazon/awssdk/services/healthlake/model/CreateFhirDatastoreRequest$Builder
      13: invokeinterface #6,  1            // InterfaceMethod software/amazon/awssdk/services/healthlake/model/CreateFhirDatastoreRequest$Builder.build:()Ljava/lang/Object;
      18: checkcast     #7                  // class software/amazon/awssdk/services/healthlake/model/CreateFhirDatastoreRequest
      21: invokeinterface #8,  2            // InterfaceMethod createFHIRDatastore:(Lsoftware/amazon/awssdk/services/healthlake/model/CreateFhirDatastoreRequest;)Ljava/util/concurrent/CompletableFuture;
      26: areturn

  public default java.util.concurrent.CompletableFuture<software.amazon.awssdk.services.healthlake.model.DeleteFhirDatastoreResponse> deleteFHIRDatastore(software.amazon.awssdk.services.healthlake.model.DeleteFhirDatastoreRequest);
    Code:
       0: new           #1                  // class java/lang/UnsupportedOperationException
       3: dup
       4: invokespecial #2                  // Method java/lang/UnsupportedOperationException."<init>":()V
       7: athrow

  public default java.util.concurrent.CompletableFuture<software.amazon.awssdk.services.healthlake.model.DeleteFhirDatastoreResponse> deleteFHIRDatastore(java.util.function.Consumer<software.amazon.awssdk.services.healthlake.model.DeleteFhirDatastoreRequest$Builder>);
    Code:
       0: aload_0
       1: invokestatic  #9                  // Method software/amazon/awssdk/services/healthlake/model/DeleteFhirDatastoreRequest.builder:()Lsoftware/amazon/awssdk/services/healthlake/model/DeleteFhirDatastoreRequest$Builder;
       4: aload_1
       5: invokeinterface #10,  2           // InterfaceMethod software/amazon/awssdk/services/healthlake/model/DeleteFhirDatastoreRequest$Builder.applyMutation:(Ljava/util/function/Consumer;)Lsoftware/amazon/awssdk/utils/builder/SdkBuilder;
      10: checkcast     #11                 // class software/amazon/awssdk/services/healthlake/model/DeleteFhirDatastoreRequest$Builder
      13: invokeinterface #12,  1           // InterfaceMethod software/amazon/awssdk/services/healthlake/model/DeleteFhirDatastoreRequest$Builder.build:()Ljava/lang/Object;
      18: checkcast     #13                 // class software/amazon/awssdk/services/healthlake/model/DeleteFhirDatastoreRequest
      21: invokeinterface #14,  2           // InterfaceMethod deleteFHIRDatastore:(Lsoftware/amazon/awssdk/services/healthlake/model/DeleteFhirDatastoreRequest;)Ljava/util/concurrent/CompletableFuture;
      26: areturn

  public default java.util.concurrent.CompletableFuture<software.amazon.awssdk.services.healthlake.model.DescribeFhirDatastoreResponse> describeFHIRDatastore(software.amazon.awssdk.services.healthlake.model.DescribeFhirDatastoreRequest);
    Code:
       0: new           #1                  // class java/lang/UnsupportedOperationException
       3: dup
       4: invokespecial #2                  // Method java/lang/UnsupportedOperationException."<init>":()V
       7: athrow

  public default java.util.concurrent.CompletableFuture<software.amazon.awssdk.services.healthlake.model.DescribeFhirDatastoreResponse> describeFHIRDatastore(java.util.function.Consumer<software.amazon.awssdk.services.healthlake.model.DescribeFhirDatastoreRequest$Builder>);
    Code:
       0: aload_0
       1: invokestatic  #15                 // Method software/amazon/awssdk/services/healthlake/model/DescribeFhirDatastoreRequest.builder:()Lsoftware/amazon/awssdk/services/healthlake/model/DescribeFhirDatastoreRequest$Builder;
       4: aload_1
       5: invokeinterface #16,  2           // InterfaceMethod software/amazon/awssdk/services/healthlake/model/DescribeFhirDatastoreRequest$Builder.applyMutation:(Ljava/util/function/Consumer;)Lsoftware/amazon/awssdk/utils/builder/SdkBuilder;
      10: checkcast     #17                 // class software/amazon/awssdk/services/healthlake/model/DescribeFhirDatastoreRequest$Builder
      13: invokeinterface #18,  1           // InterfaceMethod software/amazon/awssdk/services/healthlake/model/DescribeFhirDatastoreRequest$Builder.build:()Ljava/lang/Object;
      18: checkcast     #19                 // class software/amazon/awssdk/services/healthlake/model/DescribeFhirDatastoreRequest
      21: invokeinterface #20,  2           // InterfaceMethod describeFHIRDatastore:(Lsoftware/amazon/awssdk/services/healthlake/model/DescribeFhirDatastoreRequest;)Ljava/util/concurrent/CompletableFuture;
      26: areturn

  public default java.util.concurrent.CompletableFuture<software.amazon.awssdk.services.healthlake.model.DescribeFhirExportJobResponse> describeFHIRExportJob(software.amazon.awssdk.services.healthlake.model.DescribeFhirExportJobRequest);
    Code:
       0: new           #1                  // class java/lang/UnsupportedOperationException
       3: dup
       4: invokespecial #2                  // Method java/lang/UnsupportedOperationException."<init>":()V
       7: athrow

  public default java.util.concurrent.CompletableFuture<software.amazon.awssdk.services.healthlake.model.DescribeFhirExportJobResponse> describeFHIRExportJob(java.util.function.Consumer<software.amazon.awssdk.services.healthlake.model.DescribeFhirExportJobRequest$Builder>);
    Code:
       0: aload_0
       1: invokestatic  #21                 // Method software/amazon/awssdk/services/healthlake/model/DescribeFhirExportJobRequest.builder:()Lsoftware/amazon/awssdk/services/healthlake/model/DescribeFhirExportJobRequest$Builder;
       4: aload_1
       5: invokeinterface #22,  2           // InterfaceMethod software/amazon/awssdk/services/healthlake/model/DescribeFhirExportJobRequest$Builder.applyMutation:(Ljava/util/function/Consumer;)Lsoftware/amazon/awssdk/utils/builder/SdkBuilder;
      10: checkcast     #23                 // class software/amazon/awssdk/services/healthlake/model/DescribeFhirExportJobRequest$Builder
      13: invokeinterface #24,  1           // InterfaceMethod software/amazon/awssdk/services/healthlake/model/DescribeFhirExportJobRequest$Builder.build:()Ljava/lang/Object;
      18: checkcast     #25                 // class software/amazon/awssdk/services/healthlake/model/DescribeFhirExportJobRequest
      21: invokeinterface #26,  2           // InterfaceMethod describeFHIRExportJob:(Lsoftware/amazon/awssdk/services/healthlake/model/DescribeFhirExportJobRequest;)Ljava/util/concurrent/CompletableFuture;
      26: areturn

  public default java.util.concurrent.CompletableFuture<software.amazon.awssdk.services.healthlake.model.DescribeFhirImportJobResponse> describeFHIRImportJob(software.amazon.awssdk.services.healthlake.model.DescribeFhirImportJobRequest);
    Code:
       0: new           #1                  // class java/lang/UnsupportedOperationException
       3: dup
       4: invokespecial #2                  // Method java/lang/UnsupportedOperationException."<init>":()V
       7: athrow

  public default java.util.concurrent.CompletableFuture<software.amazon.awssdk.services.healthlake.model.DescribeFhirImportJobResponse> describeFHIRImportJob(java.util.function.Consumer<software.amazon.awssdk.services.healthlake.model.DescribeFhirImportJobRequest$Builder>);
    Code:
       0: aload_0
       1: invokestatic  #27                 // Method software/amazon/awssdk/services/healthlake/model/DescribeFhirImportJobRequest.builder:()Lsoftware/amazon/awssdk/services/healthlake/model/DescribeFhirImportJobRequest$Builder;
       4: aload_1
       5: invokeinterface #28,  2           // InterfaceMethod software/amazon/awssdk/services/healthlake/model/DescribeFhirImportJobRequest$Builder.applyMutation:(Ljava/util/function/Consumer;)Lsoftware/amazon/awssdk/utils/builder/SdkBuilder;
      10: checkcast     #29                 // class software/amazon/awssdk/services/healthlake/model/DescribeFhirImportJobRequest$Builder
      13: invokeinterface #30,  1           // InterfaceMethod software/amazon/awssdk/services/healthlake/model/DescribeFhirImportJobRequest$Builder.build:()Ljava/lang/Object;
      18: checkcast     #31                 // class software/amazon/awssdk/services/healthlake/model/DescribeFhirImportJobRequest
      21: invokeinterface #32,  2           // InterfaceMethod describeFHIRImportJob:(Lsoftware/amazon/awssdk/services/healthlake/model/DescribeFhirImportJobRequest;)Ljava/util/concurrent/CompletableFuture;
      26: areturn

  public default java.util.concurrent.CompletableFuture<software.amazon.awssdk.services.healthlake.model.ListFhirDatastoresResponse> listFHIRDatastores(software.amazon.awssdk.services.healthlake.model.ListFhirDatastoresRequest);
    Code:
       0: new           #1                  // class java/lang/UnsupportedOperationException
       3: dup
       4: invokespecial #2                  // Method java/lang/UnsupportedOperationException."<init>":()V
       7: athrow

  public default java.util.concurrent.CompletableFuture<software.amazon.awssdk.services.healthlake.model.ListFhirDatastoresResponse> listFHIRDatastores(java.util.function.Consumer<software.amazon.awssdk.services.healthlake.model.ListFhirDatastoresRequest$Builder>);
    Code:
       0: aload_0
       1: invokestatic  #33                 // Method software/amazon/awssdk/services/healthlake/model/ListFhirDatastoresRequest.builder:()Lsoftware/amazon/awssdk/services/healthlake/model/ListFhirDatastoresRequest$Builder;
       4: aload_1
       5: invokeinterface #34,  2           // InterfaceMethod software/amazon/awssdk/services/healthlake/model/ListFhirDatastoresRequest$Builder.applyMutation:(Ljava/util/function/Consumer;)Lsoftware/amazon/awssdk/utils/builder/SdkBuilder;
      10: checkcast     #35                 // class software/amazon/awssdk/services/healthlake/model/ListFhirDatastoresRequest$Builder
      13: invokeinterface #36,  1           // InterfaceMethod software/amazon/awssdk/services/healthlake/model/ListFhirDatastoresRequest$Builder.build:()Ljava/lang/Object;
      18: checkcast     #37                 // class software/amazon/awssdk/services/healthlake/model/ListFhirDatastoresRequest
      21: invokeinterface #38,  2           // InterfaceMethod listFHIRDatastores:(Lsoftware/amazon/awssdk/services/healthlake/model/ListFhirDatastoresRequest;)Ljava/util/concurrent/CompletableFuture;
      26: areturn

  public default software.amazon.awssdk.services.healthlake.paginators.ListFHIRDatastoresPublisher listFHIRDatastoresPaginator(software.amazon.awssdk.services.healthlake.model.ListFhirDatastoresRequest);
    Code:
       0: new           #39                 // class software/amazon/awssdk/services/healthlake/paginators/ListFHIRDatastoresPublisher
       3: dup
       4: aload_0
       5: aload_1
       6: invokespecial #40                 // Method software/amazon/awssdk/services/healthlake/paginators/ListFHIRDatastoresPublisher."<init>":(Lsoftware/amazon/awssdk/services/healthlake/HealthLakeAsyncClient;Lsoftware/amazon/awssdk/services/healthlake/model/ListFhirDatastoresRequest;)V
       9: areturn

  public default software.amazon.awssdk.services.healthlake.paginators.ListFHIRDatastoresPublisher listFHIRDatastoresPaginator(java.util.function.Consumer<software.amazon.awssdk.services.healthlake.model.ListFhirDatastoresRequest$Builder>);
    Code:
       0: aload_0
       1: invokestatic  #33                 // Method software/amazon/awssdk/services/healthlake/model/ListFhirDatastoresRequest.builder:()Lsoftware/amazon/awssdk/services/healthlake/model/ListFhirDatastoresRequest$Builder;
       4: aload_1
       5: invokeinterface #34,  2           // InterfaceMethod software/amazon/awssdk/services/healthlake/model/ListFhirDatastoresRequest$Builder.applyMutation:(Ljava/util/function/Consumer;)Lsoftware/amazon/awssdk/utils/builder/SdkBuilder;
      10: checkcast     #35                 // class software/amazon/awssdk/services/healthlake/model/ListFhirDatastoresRequest$Builder
      13: invokeinterface #36,  1           // InterfaceMethod software/amazon/awssdk/services/healthlake/model/ListFhirDatastoresRequest$Builder.build:()Ljava/lang/Object;
      18: checkcast     #37                 // class software/amazon/awssdk/services/healthlake/model/ListFhirDatastoresRequest
      21: invokeinterface #41,  2           // InterfaceMethod listFHIRDatastoresPaginator:(Lsoftware/amazon/awssdk/services/healthlake/model/ListFhirDatastoresRequest;)Lsoftware/amazon/awssdk/services/healthlake/paginators/ListFHIRDatastoresPublisher;
      26: areturn

  public default java.util.concurrent.CompletableFuture<software.amazon.awssdk.services.healthlake.model.ListFhirExportJobsResponse> listFHIRExportJobs(software.amazon.awssdk.services.healthlake.model.ListFhirExportJobsRequest);
    Code:
       0: new           #1                  // class java/lang/UnsupportedOperationException
       3: dup
       4: invokespecial #2                  // Method java/lang/UnsupportedOperationException."<init>":()V
       7: athrow

  public default java.util.concurrent.CompletableFuture<software.amazon.awssdk.services.healthlake.model.ListFhirExportJobsResponse> listFHIRExportJobs(java.util.function.Consumer<software.amazon.awssdk.services.healthlake.model.ListFhirExportJobsRequest$Builder>);
    Code:
       0: aload_0
       1: invokestatic  #42                 // Method software/amazon/awssdk/services/healthlake/model/ListFhirExportJobsRequest.builder:()Lsoftware/amazon/awssdk/services/healthlake/model/ListFhirExportJobsRequest$Builder;
       4: aload_1
       5: invokeinterface #43,  2           // InterfaceMethod software/amazon/awssdk/services/healthlake/model/ListFhirExportJobsRequest$Builder.applyMutation:(Ljava/util/function/Consumer;)Lsoftware/amazon/awssdk/utils/builder/SdkBuilder;
      10: checkcast     #44                 // class software/amazon/awssdk/services/healthlake/model/ListFhirExportJobsRequest$Builder
      13: invokeinterface #45,  1           // InterfaceMethod software/amazon/awssdk/services/healthlake/model/ListFhirExportJobsRequest$Builder.build:()Ljava/lang/Object;
      18: checkcast     #46                 // class software/amazon/awssdk/services/healthlake/model/ListFhirExportJobsRequest
      21: invokeinterface #47,  2           // InterfaceMethod listFHIRExportJobs:(Lsoftware/amazon/awssdk/services/healthlake/model/ListFhirExportJobsRequest;)Ljava/util/concurrent/CompletableFuture;
      26: areturn

  public default software.amazon.awssdk.services.healthlake.paginators.ListFHIRExportJobsPublisher listFHIRExportJobsPaginator(software.amazon.awssdk.services.healthlake.model.ListFhirExportJobsRequest);
    Code:
       0: new           #48                 // class software/amazon/awssdk/services/healthlake/paginators/ListFHIRExportJobsPublisher
       3: dup
       4: aload_0
       5: aload_1
       6: invokespecial #49                 // Method software/amazon/awssdk/services/healthlake/paginators/ListFHIRExportJobsPublisher."<init>":(Lsoftware/amazon/awssdk/services/healthlake/HealthLakeAsyncClient;Lsoftware/amazon/awssdk/services/healthlake/model/ListFhirExportJobsRequest;)V
       9: areturn

  public default software.amazon.awssdk.services.healthlake.paginators.ListFHIRExportJobsPublisher listFHIRExportJobsPaginator(java.util.function.Consumer<software.amazon.awssdk.services.healthlake.model.ListFhirExportJobsRequest$Builder>);
    Code:
       0: aload_0
       1: invokestatic  #42                 // Method software/amazon/awssdk/services/healthlake/model/ListFhirExportJobsRequest.builder:()Lsoftware/amazon/awssdk/services/healthlake/model/ListFhirExportJobsRequest$Builder;
       4: aload_1
       5: invokeinterface #43,  2           // InterfaceMethod software/amazon/awssdk/services/healthlake/model/ListFhirExportJobsRequest$Builder.applyMutation:(Ljava/util/function/Consumer;)Lsoftware/amazon/awssdk/utils/builder/SdkBuilder;
      10: checkcast     #44                 // class software/amazon/awssdk/services/healthlake/model/ListFhirExportJobsRequest$Builder
      13: invokeinterface #45,  1           // InterfaceMethod software/amazon/awssdk/services/healthlake/model/ListFhirExportJobsRequest$Builder.build:()Ljava/lang/Object;
      18: checkcast     #46                 // class software/amazon/awssdk/services/healthlake/model/ListFhirExportJobsRequest
      21: invokeinterface #50,  2           // InterfaceMethod listFHIRExportJobsPaginator:(Lsoftware/amazon/awssdk/services/healthlake/model/ListFhirExportJobsRequest;)Lsoftware/amazon/awssdk/services/healthlake/paginators/ListFHIRExportJobsPublisher;
      26: areturn

  public default java.util.concurrent.CompletableFuture<software.amazon.awssdk.services.healthlake.model.ListFhirImportJobsResponse> listFHIRImportJobs(software.amazon.awssdk.services.healthlake.model.ListFhirImportJobsRequest);
    Code:
       0: new           #1                  // class java/lang/UnsupportedOperationException
       3: dup
       4: invokespecial #2                  // Method java/lang/UnsupportedOperationException."<init>":()V
       7: athrow

  public default java.util.concurrent.CompletableFuture<software.amazon.awssdk.services.healthlake.model.ListFhirImportJobsResponse> listFHIRImportJobs(java.util.function.Consumer<software.amazon.awssdk.services.healthlake.model.ListFhirImportJobsRequest$Builder>);
    Code:
       0: aload_0
       1: invokestatic  #51                 // Method software/amazon/awssdk/services/healthlake/model/ListFhirImportJobsRequest.builder:()Lsoftware/amazon/awssdk/services/healthlake/model/ListFhirImportJobsRequest$Builder;
       4: aload_1
       5: invokeinterface #52,  2           // InterfaceMethod software/amazon/awssdk/services/healthlake/model/ListFhirImportJobsRequest$Builder.applyMutation:(Ljava/util/function/Consumer;)Lsoftware/amazon/awssdk/utils/builder/SdkBuilder;
      10: checkcast     #53                 // class software/amazon/awssdk/services/healthlake/model/ListFhirImportJobsRequest$Builder
      13: invokeinterface #54,  1           // InterfaceMethod software/amazon/awssdk/services/healthlake/model/ListFhirImportJobsRequest$Builder.build:()Ljava/lang/Object;
      18: checkcast     #55                 // class software/amazon/awssdk/services/healthlake/model/ListFhirImportJobsRequest
      21: invokeinterface #56,  2           // InterfaceMethod listFHIRImportJobs:(Lsoftware/amazon/awssdk/services/healthlake/model/ListFhirImportJobsRequest;)Ljava/util/concurrent/CompletableFuture;
      26: areturn

  public default software.amazon.awssdk.services.healthlake.paginators.ListFHIRImportJobsPublisher listFHIRImportJobsPaginator(software.amazon.awssdk.services.healthlake.model.ListFhirImportJobsRequest);
    Code:
       0: new           #57                 // class software/amazon/awssdk/services/healthlake/paginators/ListFHIRImportJobsPublisher
       3: dup
       4: aload_0
       5: aload_1
       6: invokespecial #58                 // Method software/amazon/awssdk/services/healthlake/paginators/ListFHIRImportJobsPublisher."<init>":(Lsoftware/amazon/awssdk/services/healthlake/HealthLakeAsyncClient;Lsoftware/amazon/awssdk/services/healthlake/model/ListFhirImportJobsRequest;)V
       9: areturn

  public default software.amazon.awssdk.services.healthlake.paginators.ListFHIRImportJobsPublisher listFHIRImportJobsPaginator(java.util.function.Consumer<software.amazon.awssdk.services.healthlake.model.ListFhirImportJobsRequest$Builder>);
    Code:
       0: aload_0
       1: invokestatic  #51                 // Method software/amazon/awssdk/services/healthlake/model/ListFhirImportJobsRequest.builder:()Lsoftware/amazon/awssdk/services/healthlake/model/ListFhirImportJobsRequest$Builder;
       4: aload_1
       5: invokeinterface #52,  2           // InterfaceMethod software/amazon/awssdk/services/healthlake/model/ListFhirImportJobsRequest$Builder.applyMutation:(Ljava/util/function/Consumer;)Lsoftware/amazon/awssdk/utils/builder/SdkBuilder;
      10: checkcast     #53                 // class software/amazon/awssdk/services/healthlake/model/ListFhirImportJobsRequest$Builder
      13: invokeinterface #54,  1           // InterfaceMethod software/amazon/awssdk/services/healthlake/model/ListFhirImportJobsRequest$Builder.build:()Ljava/lang/Object;
      18: checkcast     #55                 // class software/amazon/awssdk/services/healthlake/model/ListFhirImportJobsRequest
      21: invokeinterface #59,  2           // InterfaceMethod listFHIRImportJobsPaginator:(Lsoftware/amazon/awssdk/services/healthlake/model/ListFhirImportJobsRequest;)Lsoftware/amazon/awssdk/services/healthlake/paginators/ListFHIRImportJobsPublisher;
      26: areturn

  public default java.util.concurrent.CompletableFuture<software.amazon.awssdk.services.healthlake.model.ListTagsForResourceResponse> listTagsForResource(software.amazon.awssdk.services.healthlake.model.ListTagsForResourceRequest);
    Code:
       0: new           #1                  // class java/lang/UnsupportedOperationException
       3: dup
       4: invokespecial #2                  // Method java/lang/UnsupportedOperationException."<init>":()V
       7: athrow

  public default java.util.concurrent.CompletableFuture<software.amazon.awssdk.services.healthlake.model.ListTagsForResourceResponse> listTagsForResource(java.util.function.Consumer<software.amazon.awssdk.services.healthlake.model.ListTagsForResourceRequest$Builder>);
    Code:
       0: aload_0
       1: invokestatic  #60                 // Method software/amazon/awssdk/services/healthlake/model/ListTagsForResourceRequest.builder:()Lsoftware/amazon/awssdk/services/healthlake/model/ListTagsForResourceRequest$Builder;
       4: aload_1
       5: invokeinterface #61,  2           // InterfaceMethod software/amazon/awssdk/services/healthlake/model/ListTagsForResourceRequest$Builder.applyMutation:(Ljava/util/function/Consumer;)Lsoftware/amazon/awssdk/utils/builder/SdkBuilder;
      10: checkcast     #62                 // class software/amazon/awssdk/services/healthlake/model/ListTagsForResourceRequest$Builder
      13: invokeinterface #63,  1           // InterfaceMethod software/amazon/awssdk/services/healthlake/model/ListTagsForResourceRequest$Builder.build:()Ljava/lang/Object;
      18: checkcast     #64                 // class software/amazon/awssdk/services/healthlake/model/ListTagsForResourceRequest
      21: invokeinterface #65,  2           // InterfaceMethod listTagsForResource:(Lsoftware/amazon/awssdk/services/healthlake/model/ListTagsForResourceRequest;)Ljava/util/concurrent/CompletableFuture;
      26: areturn

  public default java.util.concurrent.CompletableFuture<software.amazon.awssdk.services.healthlake.model.StartFhirExportJobResponse> startFHIRExportJob(software.amazon.awssdk.services.healthlake.model.StartFhirExportJobRequest);
    Code:
       0: new           #1                  // class java/lang/UnsupportedOperationException
       3: dup
       4: invokespecial #2                  // Method java/lang/UnsupportedOperationException."<init>":()V
       7: athrow

  public default java.util.concurrent.CompletableFuture<software.amazon.awssdk.services.healthlake.model.StartFhirExportJobResponse> startFHIRExportJob(java.util.function.Consumer<software.amazon.awssdk.services.healthlake.model.StartFhirExportJobRequest$Builder>);
    Code:
       0: aload_0
       1: invokestatic  #66                 // Method software/amazon/awssdk/services/healthlake/model/StartFhirExportJobRequest.builder:()Lsoftware/amazon/awssdk/services/healthlake/model/StartFhirExportJobRequest$Builder;
       4: aload_1
       5: invokeinterface #67,  2           // InterfaceMethod software/amazon/awssdk/services/healthlake/model/StartFhirExportJobRequest$Builder.applyMutation:(Ljava/util/function/Consumer;)Lsoftware/amazon/awssdk/utils/builder/SdkBuilder;
      10: checkcast     #68                 // class software/amazon/awssdk/services/healthlake/model/StartFhirExportJobRequest$Builder
      13: invokeinterface #69,  1           // InterfaceMethod software/amazon/awssdk/services/healthlake/model/StartFhirExportJobRequest$Builder.build:()Ljava/lang/Object;
      18: checkcast     #70                 // class software/amazon/awssdk/services/healthlake/model/StartFhirExportJobRequest
      21: invokeinterface #71,  2           // InterfaceMethod startFHIRExportJob:(Lsoftware/amazon/awssdk/services/healthlake/model/StartFhirExportJobRequest;)Ljava/util/concurrent/CompletableFuture;
      26: areturn

  public default java.util.concurrent.CompletableFuture<software.amazon.awssdk.services.healthlake.model.StartFhirImportJobResponse> startFHIRImportJob(software.amazon.awssdk.services.healthlake.model.StartFhirImportJobRequest);
    Code:
       0: new           #1                  // class java/lang/UnsupportedOperationException
       3: dup
       4: invokespecial #2                  // Method java/lang/UnsupportedOperationException."<init>":()V
       7: athrow

  public default java.util.concurrent.CompletableFuture<software.amazon.awssdk.services.healthlake.model.StartFhirImportJobResponse> startFHIRImportJob(java.util.function.Consumer<software.amazon.awssdk.services.healthlake.model.StartFhirImportJobRequest$Builder>);
    Code:
       0: aload_0
       1: invokestatic  #72                 // Method software/amazon/awssdk/services/healthlake/model/StartFhirImportJobRequest.builder:()Lsoftware/amazon/awssdk/services/healthlake/model/StartFhirImportJobRequest$Builder;
       4: aload_1
       5: invokeinterface #73,  2           // InterfaceMethod software/amazon/awssdk/services/healthlake/model/StartFhirImportJobRequest$Builder.applyMutation:(Ljava/util/function/Consumer;)Lsoftware/amazon/awssdk/utils/builder/SdkBuilder;
      10: checkcast     #74                 // class software/amazon/awssdk/services/healthlake/model/StartFhirImportJobRequest$Builder
      13: invokeinterface #75,  1           // InterfaceMethod software/amazon/awssdk/services/healthlake/model/StartFhirImportJobRequest$Builder.build:()Ljava/lang/Object;
      18: checkcast     #76                 // class software/amazon/awssdk/services/healthlake/model/StartFhirImportJobRequest
      21: invokeinterface #77,  2           // InterfaceMethod startFHIRImportJob:(Lsoftware/amazon/awssdk/services/healthlake/model/StartFhirImportJobRequest;)Ljava/util/concurrent/CompletableFuture;
      26: areturn

  public default java.util.concurrent.CompletableFuture<software.amazon.awssdk.services.healthlake.model.TagResourceResponse> tagResource(software.amazon.awssdk.services.healthlake.model.TagResourceRequest);
    Code:
       0: new           #1                  // class java/lang/UnsupportedOperationException
       3: dup
       4: invokespecial #2                  // Method java/lang/UnsupportedOperationException."<init>":()V
       7: athrow

  public default java.util.concurrent.CompletableFuture<software.amazon.awssdk.services.healthlake.model.TagResourceResponse> tagResource(java.util.function.Consumer<software.amazon.awssdk.services.healthlake.model.TagResourceRequest$Builder>);
    Code:
       0: aload_0
       1: invokestatic  #78                 // Method software/amazon/awssdk/services/healthlake/model/TagResourceRequest.builder:()Lsoftware/amazon/awssdk/services/healthlake/model/TagResourceRequest$Builder;
       4: aload_1
       5: invokeinterface #79,  2           // InterfaceMethod software/amazon/awssdk/services/healthlake/model/TagResourceRequest$Builder.applyMutation:(Ljava/util/function/Consumer;)Lsoftware/amazon/awssdk/utils/builder/SdkBuilder;
      10: checkcast     #80                 // class software/amazon/awssdk/services/healthlake/model/TagResourceRequest$Builder
      13: invokeinterface #81,  1           // InterfaceMethod software/amazon/awssdk/services/healthlake/model/TagResourceRequest$Builder.build:()Ljava/lang/Object;
      18: checkcast     #82                 // class software/amazon/awssdk/services/healthlake/model/TagResourceRequest
      21: invokeinterface #83,  2           // InterfaceMethod tagResource:(Lsoftware/amazon/awssdk/services/healthlake/model/TagResourceRequest;)Ljava/util/concurrent/CompletableFuture;
      26: areturn

  public default java.util.concurrent.CompletableFuture<software.amazon.awssdk.services.healthlake.model.UntagResourceResponse> untagResource(software.amazon.awssdk.services.healthlake.model.UntagResourceRequest);
    Code:
       0: new           #1                  // class java/lang/UnsupportedOperationException
       3: dup
       4: invokespecial #2                  // Method java/lang/UnsupportedOperationException."<init>":()V
       7: athrow

  public default java.util.concurrent.CompletableFuture<software.amazon.awssdk.services.healthlake.model.UntagResourceResponse> untagResource(java.util.function.Consumer<software.amazon.awssdk.services.healthlake.model.UntagResourceRequest$Builder>);
    Code:
       0: aload_0
       1: invokestatic  #84                 // Method software/amazon/awssdk/services/healthlake/model/UntagResourceRequest.builder:()Lsoftware/amazon/awssdk/services/healthlake/model/UntagResourceRequest$Builder;
       4: aload_1
       5: invokeinterface #85,  2           // InterfaceMethod software/amazon/awssdk/services/healthlake/model/UntagResourceRequest$Builder.applyMutation:(Ljava/util/function/Consumer;)Lsoftware/amazon/awssdk/utils/builder/SdkBuilder;
      10: checkcast     #86                 // class software/amazon/awssdk/services/healthlake/model/UntagResourceRequest$Builder
      13: invokeinterface #87,  1           // InterfaceMethod software/amazon/awssdk/services/healthlake/model/UntagResourceRequest$Builder.build:()Ljava/lang/Object;
      18: checkcast     #88                 // class software/amazon/awssdk/services/healthlake/model/UntagResourceRequest
      21: invokeinterface #89,  2           // InterfaceMethod untagResource:(Lsoftware/amazon/awssdk/services/healthlake/model/UntagResourceRequest;)Ljava/util/concurrent/CompletableFuture;
      26: areturn

  public default software.amazon.awssdk.services.healthlake.HealthLakeServiceClientConfiguration serviceClientConfiguration();
    Code:
       0: new           #1                  // class java/lang/UnsupportedOperationException
       3: dup
       4: invokespecial #2                  // Method java/lang/UnsupportedOperationException."<init>":()V
       7: athrow

  public static software.amazon.awssdk.services.healthlake.HealthLakeAsyncClient create();
    Code:
       0: invokestatic  #90                 // InterfaceMethod builder:()Lsoftware/amazon/awssdk/services/healthlake/HealthLakeAsyncClientBuilder;
       3: invokeinterface #91,  1           // InterfaceMethod software/amazon/awssdk/services/healthlake/HealthLakeAsyncClientBuilder.build:()Ljava/lang/Object;
       8: checkcast     #92                 // class software/amazon/awssdk/services/healthlake/HealthLakeAsyncClient
      11: areturn

  public static software.amazon.awssdk.services.healthlake.HealthLakeAsyncClientBuilder builder();
    Code:
       0: new           #93                 // class software/amazon/awssdk/services/healthlake/DefaultHealthLakeAsyncClientBuilder
       3: dup
       4: invokespecial #94                 // Method software/amazon/awssdk/services/healthlake/DefaultHealthLakeAsyncClientBuilder."<init>":()V
       7: areturn

  public default software.amazon.awssdk.awscore.AwsServiceClientConfiguration serviceClientConfiguration();
    Code:
       0: aload_0
       1: invokeinterface #95,  1           // InterfaceMethod serviceClientConfiguration:()Lsoftware/amazon/awssdk/services/healthlake/HealthLakeServiceClientConfiguration;
       6: areturn

  public default software.amazon.awssdk.core.SdkServiceClientConfiguration serviceClientConfiguration();
    Code:
       0: aload_0
       1: invokeinterface #95,  1           // InterfaceMethod serviceClientConfiguration:()Lsoftware/amazon/awssdk/services/healthlake/HealthLakeServiceClientConfiguration;
       6: areturn
}
