Compiled from "ClassBinding.java"
public class org.glassfish.jersey.internal.inject.ClassBinding<T> extends org.glassfish.jersey.internal.inject.Binding<T, org.glassfish.jersey.internal.inject.ClassBinding<T>> {
  private final java.lang.Class<T> service;

  org.glassfish.jersey.internal.inject.ClassBinding(java.lang.Class<T>);
    Code:
       0: aload_0
       1: invokespecial #1                  // Method org/glassfish/jersey/internal/inject/Binding."<init>":()V
       4: aload_0
       5: aload_1
       6: putfield      #2                  // Field service:Ljava/lang/Class;
       9: aload_0
      10: aload_1
      11: invokevirtual #3                  // Method asType:(Ljava/lang/Class;)Lorg/glassfish/jersey/internal/inject/Binding;
      14: pop
      15: return

  public java.lang.Class<T> getService();
    Code:
       0: aload_0
       1: getfield      #2                  // Field service:Ljava/lang/Class;
       4: areturn
}
