Compiled from "Providers.java"
final class org.glassfish.jersey.internal.inject.Providers$ProviderRuntime extends java.lang.Enum<org.glassfish.jersey.internal.inject.Providers$ProviderRuntime> {
  public static final org.glassfish.jersey.internal.inject.Providers$ProviderRuntime BOTH;

  public static final org.glassfish.jersey.internal.inject.Providers$ProviderRuntime SERVER;

  public static final org.glassfish.jersey.internal.inject.Providers$ProviderRuntime CLIENT;

  private final javax.ws.rs.RuntimeType runtime;

  private static final org.glassfish.jersey.internal.inject.Providers$ProviderRuntime[] $VALUES;

  public static org.glassfish.jersey.internal.inject.Providers$ProviderRuntime[] values();
    Code:
       0: getstatic     #1                  // Field $VALUES:[Lorg/glassfish/jersey/internal/inject/Providers$ProviderRuntime;
       3: invokevirtual #2                  // Method "[Lorg/glassfish/jersey/internal/inject/Providers$ProviderRuntime;".clone:()Ljava/lang/Object;
       6: checkcast     #3                  // class "[Lorg/glassfish/jersey/internal/inject/Providers$ProviderRuntime;"
       9: areturn

  public static org.glassfish.jersey.internal.inject.Providers$ProviderRuntime valueOf(java.lang.String);
    Code:
       0: ldc           #4                  // class org/glassfish/jersey/internal/inject/Providers$ProviderRuntime
       2: aload_0
       3: invokestatic  #5                  // Method java/lang/Enum.valueOf:(Ljava/lang/Class;Ljava/lang/String;)Ljava/lang/Enum;
       6: checkcast     #4                  // class org/glassfish/jersey/internal/inject/Providers$ProviderRuntime
       9: areturn

  private org.glassfish.jersey.internal.inject.Providers$ProviderRuntime(javax.ws.rs.RuntimeType);
    Code:
       0: aload_0
       1: aload_1
       2: iload_2
       3: invokespecial #6                  // Method java/lang/Enum."<init>":(Ljava/lang/String;I)V
       6: aload_0
       7: aload_3
       8: putfield      #7                  // Field runtime:Ljavax/ws/rs/RuntimeType;
      11: return

  public javax.ws.rs.RuntimeType getRuntime();
    Code:
       0: aload_0
       1: getfield      #7                  // Field runtime:Ljavax/ws/rs/RuntimeType;
       4: areturn

  static {};
    Code:
       0: new           #4                  // class org/glassfish/jersey/internal/inject/Providers$ProviderRuntime
       3: dup
       4: ldc           #8                  // String BOTH
       6: iconst_0
       7: aconst_null
       8: invokespecial #9                  // Method "<init>":(Ljava/lang/String;ILjavax/ws/rs/RuntimeType;)V
      11: putstatic     #10                 // Field BOTH:Lorg/glassfish/jersey/internal/inject/Providers$ProviderRuntime;
      14: new           #4                  // class org/glassfish/jersey/internal/inject/Providers$ProviderRuntime
      17: dup
      18: ldc           #11                 // String SERVER
      20: iconst_1
      21: getstatic     #12                 // Field javax/ws/rs/RuntimeType.SERVER:Ljavax/ws/rs/RuntimeType;
      24: invokespecial #9                  // Method "<init>":(Ljava/lang/String;ILjavax/ws/rs/RuntimeType;)V
      27: putstatic     #13                 // Field SERVER:Lorg/glassfish/jersey/internal/inject/Providers$ProviderRuntime;
      30: new           #4                  // class org/glassfish/jersey/internal/inject/Providers$ProviderRuntime
      33: dup
      34: ldc           #14                 // String CLIENT
      36: iconst_2
      37: getstatic     #15                 // Field javax/ws/rs/RuntimeType.CLIENT:Ljavax/ws/rs/RuntimeType;
      40: invokespecial #9                  // Method "<init>":(Ljava/lang/String;ILjavax/ws/rs/RuntimeType;)V
      43: putstatic     #16                 // Field CLIENT:Lorg/glassfish/jersey/internal/inject/Providers$ProviderRuntime;
      46: iconst_3
      47: anewarray     #4                  // class org/glassfish/jersey/internal/inject/Providers$ProviderRuntime
      50: dup
      51: iconst_0
      52: getstatic     #10                 // Field BOTH:Lorg/glassfish/jersey/internal/inject/Providers$ProviderRuntime;
      55: aastore
      56: dup
      57: iconst_1
      58: getstatic     #13                 // Field SERVER:Lorg/glassfish/jersey/internal/inject/Providers$ProviderRuntime;
      61: aastore
      62: dup
      63: iconst_2
      64: getstatic     #16                 // Field CLIENT:Lorg/glassfish/jersey/internal/inject/Providers$ProviderRuntime;
      67: aastore
      68: putstatic     #1                  // Field $VALUES:[Lorg/glassfish/jersey/internal/inject/Providers$ProviderRuntime;
      71: return
}
