Compiled from "JSONOutputASK.java"
public class org.apache.jena.sparql.resultset.JSONOutputASK {
  private java.io.OutputStream outStream;

  public org.apache.jena.sparql.resultset.JSONOutputASK(java.io.OutputStream);
    Code:
       0: aload_0
       1: invokespecial #1                  // Method java/lang/Object."<init>":()V
       4: aload_0
       5: aload_1
       6: putfield      #2                  // Field outStream:Ljava/io/OutputStream;
       9: return

  public void exec(boolean);
    Code:
       0: new           #3                  // class org/apache/jena/atlas/json/io/JSWriter
       3: dup
       4: aload_0
       5: getfield      #2                  // Field outStream:Ljava/io/OutputStream;
       8: invokespecial #4                  // Method org/apache/jena/atlas/json/io/JSWriter."<init>":(Ljava/io/OutputStream;)V
      11: astore_2
      12: aload_2
      13: invokevirtual #5                  // Method org/apache/jena/atlas/json/io/JSWriter.startOutput:()V
      16: aload_2
      17: invokevirtual #6                  // Method org/apache/jena/atlas/json/io/JSWriter.startObject:()Lorg/apache/jena/atlas/json/io/JSWriter;
      20: pop
      21: aload_2
      22: getstatic     #7                  // Field org/apache/jena/sparql/resultset/JSONResultsKW.kHead:Ljava/lang/String;
      25: invokevirtual #8                  // Method org/apache/jena/atlas/json/io/JSWriter.key:(Ljava/lang/String;)Lorg/apache/jena/atlas/json/io/JSWriter;
      28: pop
      29: aload_2
      30: invokevirtual #6                  // Method org/apache/jena/atlas/json/io/JSWriter.startObject:()Lorg/apache/jena/atlas/json/io/JSWriter;
      33: pop
      34: aload_2
      35: invokevirtual #9                  // Method org/apache/jena/atlas/json/io/JSWriter.finishObject:()Lorg/apache/jena/atlas/json/io/JSWriter;
      38: pop
      39: aload_2
      40: getstatic     #10                 // Field org/apache/jena/sparql/resultset/JSONResultsKW.kBoolean:Ljava/lang/String;
      43: iload_1
      44: invokevirtual #11                 // Method org/apache/jena/atlas/json/io/JSWriter.pair:(Ljava/lang/String;Z)Lorg/apache/jena/atlas/json/io/JSWriter;
      47: pop
      48: aload_2
      49: invokevirtual #9                  // Method org/apache/jena/atlas/json/io/JSWriter.finishObject:()Lorg/apache/jena/atlas/json/io/JSWriter;
      52: pop
      53: aload_2
      54: invokevirtual #12                 // Method org/apache/jena/atlas/json/io/JSWriter.finishOutput:()V
      57: aload_0
      58: getfield      #2                  // Field outStream:Ljava/io/OutputStream;
      61: invokestatic  #13                 // Method org/apache/jena/atlas/io/IO.flush:(Ljava/io/OutputStream;)V
      64: return
}
