Compiled from "ResultSetPeeking.java"
public class org.apache.jena.sparql.resultset.ResultSetPeeking implements org.apache.jena.sparql.resultset.ResultSetPeekable,org.apache.jena.atlas.lib.Closeable {
  private static final org.slf4j.Logger LOGGER;

  public static boolean warnOnSyncErrors;

  private org.apache.jena.query.ResultSet results;

  private org.apache.jena.rdf.model.Model model;

  private org.apache.jena.sparql.engine.binding.Binding peeked;

  private int rowNumber;

  public org.apache.jena.sparql.resultset.ResultSetPeeking(org.apache.jena.query.ResultSet);
    Code:
       0: aload_0
       1: invokespecial #1                  // Method java/lang/Object."<init>":()V
       4: aload_0
       5: aconst_null
       6: putfield      #2                  // Field peeked:Lorg/apache/jena/sparql/engine/binding/Binding;
       9: aload_0
      10: iconst_0
      11: putfield      #3                  // Field rowNumber:I
      14: aload_1
      15: ifnonnull     28
      18: new           #4                  // class java/lang/IllegalArgumentException
      21: dup
      22: ldc           #5                  // String Inner result set cannot be null
      24: invokespecial #6                  // Method java/lang/IllegalArgumentException."<init>":(Ljava/lang/String;)V
      27: athrow
      28: aload_0
      29: aload_1
      30: putfield      #7                  // Field results:Lorg/apache/jena/query/ResultSet;
      33: aload_0
      34: aload_1
      35: invokeinterface #8,  1            // InterfaceMethod org/apache/jena/query/ResultSet.getResourceModel:()Lorg/apache/jena/rdf/model/Model;
      40: putfield      #9                  // Field model:Lorg/apache/jena/rdf/model/Model;
      43: return

  public boolean hasNext();
    Code:
       0: aload_0
       1: invokespecial #10                 // Method hasPeeked:()Z
       4: ifeq          9
       7: iconst_1
       8: ireturn
       9: aload_0
      10: invokespecial #11                 // Method canPeek:()Z
      13: ireturn

  public org.apache.jena.query.QuerySolution next();
    Code:
       0: new           #12                 // class org/apache/jena/sparql/core/ResultBinding
       3: dup
       4: aload_0
       5: getfield      #9                  // Field model:Lorg/apache/jena/rdf/model/Model;
       8: aload_0
       9: invokevirtual #13                 // Method nextBinding:()Lorg/apache/jena/sparql/engine/binding/Binding;
      12: invokespecial #14                 // Method org/apache/jena/sparql/core/ResultBinding."<init>":(Lorg/apache/jena/rdf/model/Model;Lorg/apache/jena/sparql/engine/binding/Binding;)V
      15: areturn

  public org.apache.jena.query.QuerySolution nextSolution();
    Code:
       0: aload_0
       1: invokevirtual #15                 // Method next:()Lorg/apache/jena/query/QuerySolution;
       4: areturn

  public org.apache.jena.sparql.engine.binding.Binding nextBinding();
    Code:
       0: aload_0
       1: invokespecial #10                 // Method hasPeeked:()Z
       4: ifeq          29
       7: aload_0
       8: getfield      #2                  // Field peeked:Lorg/apache/jena/sparql/engine/binding/Binding;
      11: astore_1
      12: aload_0
      13: aconst_null
      14: putfield      #2                  // Field peeked:Lorg/apache/jena/sparql/engine/binding/Binding;
      17: aload_0
      18: dup
      19: getfield      #3                  // Field rowNumber:I
      22: iconst_1
      23: iadd
      24: putfield      #3                  // Field rowNumber:I
      27: aload_1
      28: areturn
      29: aload_0
      30: invokespecial #11                 // Method canPeek:()Z
      33: ifeq          58
      36: aload_0
      37: invokevirtual #16                 // Method peekBinding:()Lorg/apache/jena/sparql/engine/binding/Binding;
      40: astore_1
      41: aload_0
      42: aconst_null
      43: putfield      #2                  // Field peeked:Lorg/apache/jena/sparql/engine/binding/Binding;
      46: aload_0
      47: dup
      48: getfield      #3                  // Field rowNumber:I
      51: iconst_1
      52: iadd
      53: putfield      #3                  // Field rowNumber:I
      56: aload_1
      57: areturn
      58: new           #17                 // class java/util/NoSuchElementException
      61: dup
      62: invokespecial #18                 // Method java/util/NoSuchElementException."<init>":()V
      65: athrow

  public int getRowNumber();
    Code:
       0: aload_0
       1: invokespecial #10                 // Method hasPeeked:()Z
       4: ifeq          21
       7: aload_0
       8: getfield      #7                  // Field results:Lorg/apache/jena/query/ResultSet;
      11: invokeinterface #19,  1           // InterfaceMethod org/apache/jena/query/ResultSet.getRowNumber:()I
      16: iconst_1
      17: isub
      18: goto          30
      21: aload_0
      22: getfield      #7                  // Field results:Lorg/apache/jena/query/ResultSet;
      25: invokeinterface #19,  1           // InterfaceMethod org/apache/jena/query/ResultSet.getRowNumber:()I
      30: ireturn

  public java.util.List<java.lang.String> getResultVars();
    Code:
       0: aload_0
       1: getfield      #7                  // Field results:Lorg/apache/jena/query/ResultSet;
       4: invokeinterface #20,  1           // InterfaceMethod org/apache/jena/query/ResultSet.getResultVars:()Ljava/util/List;
       9: areturn

  public org.apache.jena.rdf.model.Model getResourceModel();
    Code:
       0: aload_0
       1: getfield      #9                  // Field model:Lorg/apache/jena/rdf/model/Model;
       4: areturn

  public void remove();
    Code:
       0: new           #21                 // class java/lang/UnsupportedOperationException
       3: dup
       4: ldc           #22                 // String remove() is not supported
       6: invokespecial #23                 // Method java/lang/UnsupportedOperationException."<init>":(Ljava/lang/String;)V
       9: athrow

  private boolean hasPeeked();
    Code:
       0: aload_0
       1: getfield      #7                  // Field results:Lorg/apache/jena/query/ResultSet;
       4: invokeinterface #19,  1           // InterfaceMethod org/apache/jena/query/ResultSet.getRowNumber:()I
       9: aload_0
      10: getfield      #3                  // Field rowNumber:I
      13: isub
      14: istore_1
      15: iload_1
      16: ifne          21
      19: iconst_0
      20: ireturn
      21: iload_1
      22: iconst_1
      23: if_icmpne     35
      26: aload_0
      27: getfield      #2                  // Field peeked:Lorg/apache/jena/sparql/engine/binding/Binding;
      30: ifnull        35
      33: iconst_1
      34: ireturn
      35: iload_1
      36: iconst_1
      37: if_icmplt     100
      40: getstatic     #24                 // Field warnOnSyncErrors:Z
      43: ifeq          80
      46: getstatic     #25                 // Field LOGGER:Lorg/slf4j/Logger;
      49: new           #26                 // class java/lang/StringBuilder
      52: dup
      53: invokespecial #27                 // Method java/lang/StringBuilder."<init>":()V
      56: ldc           #28                 // String Underlying result set was moved forward
      58: invokevirtual #29                 // Method java/lang/StringBuilder.append:(Ljava/lang/String;)Ljava/lang/StringBuilder;
      61: iload_1
      62: iconst_1
      63: isub
      64: invokevirtual #30                 // Method java/lang/StringBuilder.append:(I)Ljava/lang/StringBuilder;
      67: ldc           #31                 // String  result(s), this result set was synced back up but some results have been missed
      69: invokevirtual #29                 // Method java/lang/StringBuilder.append:(Ljava/lang/String;)Ljava/lang/StringBuilder;
      72: invokevirtual #32                 // Method java/lang/StringBuilder.toString:()Ljava/lang/String;
      75: invokeinterface #33,  2           // InterfaceMethod org/slf4j/Logger.warn:(Ljava/lang/String;)V
      80: aload_0
      81: aload_0
      82: getfield      #7                  // Field results:Lorg/apache/jena/query/ResultSet;
      85: invokeinterface #19,  1           // InterfaceMethod org/apache/jena/query/ResultSet.getRowNumber:()I
      90: putfield      #3                  // Field rowNumber:I
      93: aload_0
      94: aconst_null
      95: putfield      #2                  // Field peeked:Lorg/apache/jena/sparql/engine/binding/Binding;
      98: iconst_0
      99: ireturn
     100: new           #34                 // class java/lang/IllegalStateException
     103: dup
     104: ldc           #35                 // String Underlying result set position has moved backwards, this result set is no longer usable
     106: invokespecial #36                 // Method java/lang/IllegalStateException."<init>":(Ljava/lang/String;)V
     109: athrow

  private boolean canPeek();
    Code:
       0: aload_0
       1: getfield      #7                  // Field results:Lorg/apache/jena/query/ResultSet;
       4: invokeinterface #37,  1           // InterfaceMethod org/apache/jena/query/ResultSet.hasNext:()Z
       9: ireturn

  public org.apache.jena.query.QuerySolution peek();
    Code:
       0: new           #12                 // class org/apache/jena/sparql/core/ResultBinding
       3: dup
       4: aload_0
       5: getfield      #9                  // Field model:Lorg/apache/jena/rdf/model/Model;
       8: aload_0
       9: invokevirtual #16                 // Method peekBinding:()Lorg/apache/jena/sparql/engine/binding/Binding;
      12: invokespecial #14                 // Method org/apache/jena/sparql/core/ResultBinding."<init>":(Lorg/apache/jena/rdf/model/Model;Lorg/apache/jena/sparql/engine/binding/Binding;)V
      15: areturn

  public org.apache.jena.sparql.engine.binding.Binding peekBinding();
    Code:
       0: aload_0
       1: invokespecial #10                 // Method hasPeeked:()Z
       4: ifeq          12
       7: aload_0
       8: getfield      #2                  // Field peeked:Lorg/apache/jena/sparql/engine/binding/Binding;
      11: areturn
      12: aload_0
      13: invokespecial #11                 // Method canPeek:()Z
      16: ifeq          37
      19: aload_0
      20: aload_0
      21: getfield      #7                  // Field results:Lorg/apache/jena/query/ResultSet;
      24: invokeinterface #38,  1           // InterfaceMethod org/apache/jena/query/ResultSet.nextBinding:()Lorg/apache/jena/sparql/engine/binding/Binding;
      29: putfield      #2                  // Field peeked:Lorg/apache/jena/sparql/engine/binding/Binding;
      32: aload_0
      33: getfield      #2                  // Field peeked:Lorg/apache/jena/sparql/engine/binding/Binding;
      36: areturn
      37: new           #17                 // class java/util/NoSuchElementException
      40: dup
      41: invokespecial #18                 // Method java/util/NoSuchElementException."<init>":()V
      44: athrow

  public void close();
    Code:
       0: aload_0
       1: getfield      #7                  // Field results:Lorg/apache/jena/query/ResultSet;
       4: instanceof    #39                 // class org/apache/jena/atlas/lib/Closeable
       7: ifeq          22
      10: aload_0
      11: getfield      #7                  // Field results:Lorg/apache/jena/query/ResultSet;
      14: checkcast     #39                 // class org/apache/jena/atlas/lib/Closeable
      17: invokeinterface #40,  1           // InterfaceMethod org/apache/jena/atlas/lib/Closeable.close:()V
      22: return

  public java.lang.Object next();
    Code:
       0: aload_0
       1: invokevirtual #15                 // Method next:()Lorg/apache/jena/query/QuerySolution;
       4: areturn

  static {};
    Code:
       0: ldc           #41                 // class org/apache/jena/sparql/resultset/ResultSetPeekable
       2: invokestatic  #42                 // Method org/slf4j/LoggerFactory.getLogger:(Ljava/lang/Class;)Lorg/slf4j/Logger;
       5: putstatic     #25                 // Field LOGGER:Lorg/slf4j/Logger;
       8: iconst_1
       9: putstatic     #24                 // Field warnOnSyncErrors:Z
      12: return
}
