Compiled from "PoolArena.java"
final class io.netty.buffer.PoolArena$SizeClass extends java.lang.Enum<io.netty.buffer.PoolArena$SizeClass> {
  public static final io.netty.buffer.PoolArena$SizeClass Tiny;

  public static final io.netty.buffer.PoolArena$SizeClass Small;

  public static final io.netty.buffer.PoolArena$SizeClass Normal;

  private static final io.netty.buffer.PoolArena$SizeClass[] $VALUES;

  public static io.netty.buffer.PoolArena$SizeClass[] values();
    Code:
       0: getstatic     #1                  // Field $VALUES:[Lio/netty/buffer/PoolArena$SizeClass;
       3: invokevirtual #2                  // Method "[Lio/netty/buffer/PoolArena$SizeClass;".clone:()Ljava/lang/Object;
       6: checkcast     #3                  // class "[Lio/netty/buffer/PoolArena$SizeClass;"
       9: areturn

  public static io.netty.buffer.PoolArena$SizeClass valueOf(java.lang.String);
    Code:
       0: ldc_w         #4                  // class io/netty/buffer/PoolArena$SizeClass
       3: aload_0
       4: invokestatic  #5                  // Method java/lang/Enum.valueOf:(Ljava/lang/Class;Ljava/lang/String;)Ljava/lang/Enum;
       7: checkcast     #4                  // class io/netty/buffer/PoolArena$SizeClass
      10: areturn

  private io.netty.buffer.PoolArena$SizeClass();
    Code:
       0: aload_0
       1: aload_1
       2: iload_2
       3: invokespecial #6                  // Method java/lang/Enum."<init>":(Ljava/lang/String;I)V
       6: return

  static {};
    Code:
       0: new           #4                  // class io/netty/buffer/PoolArena$SizeClass
       3: dup
       4: ldc           #7                  // String Tiny
       6: iconst_0
       7: invokespecial #8                  // Method "<init>":(Ljava/lang/String;I)V
      10: putstatic     #9                  // Field Tiny:Lio/netty/buffer/PoolArena$SizeClass;
      13: new           #4                  // class io/netty/buffer/PoolArena$SizeClass
      16: dup
      17: ldc           #10                 // String Small
      19: iconst_1
      20: invokespecial #8                  // Method "<init>":(Ljava/lang/String;I)V
      23: putstatic     #11                 // Field Small:Lio/netty/buffer/PoolArena$SizeClass;
      26: new           #4                  // class io/netty/buffer/PoolArena$SizeClass
      29: dup
      30: ldc           #12                 // String Normal
      32: iconst_2
      33: invokespecial #8                  // Method "<init>":(Ljava/lang/String;I)V
      36: putstatic     #13                 // Field Normal:Lio/netty/buffer/PoolArena$SizeClass;
      39: iconst_3
      40: anewarray     #4                  // class io/netty/buffer/PoolArena$SizeClass
      43: dup
      44: iconst_0
      45: getstatic     #9                  // Field Tiny:Lio/netty/buffer/PoolArena$SizeClass;
      48: aastore
      49: dup
      50: iconst_1
      51: getstatic     #11                 // Field Small:Lio/netty/buffer/PoolArena$SizeClass;
      54: aastore
      55: dup
      56: iconst_2
      57: getstatic     #13                 // Field Normal:Lio/netty/buffer/PoolArena$SizeClass;
      60: aastore
      61: putstatic     #1                  // Field $VALUES:[Lio/netty/buffer/PoolArena$SizeClass;
      64: return
}
