Compiled from "ParseErrorPanel.java"
public class org.protege.editor.owl.ui.error.ParseErrorPanel<O extends java.lang.Throwable> extends org.protege.editor.owl.ui.error.ErrorPanel<O> {
  public org.protege.editor.owl.ui.error.ParseErrorPanel(org.protege.editor.core.ui.error.ErrorExplainer$ErrorExplanation<? extends O>, java.net.URI);
    Code:
       0: aload_0
       1: aload_1
       2: aload_2
       3: invokespecial #1                  // Method org/protege/editor/owl/ui/error/ErrorPanel."<init>":(Lorg/protege/editor/core/ui/error/ErrorExplainer$ErrorExplanation;Ljava/net/URI;)V
       6: return

  protected static void removeComponentFromParent(javax.swing.JComponent);
    Code:
       0: aload_0
       1: invokevirtual #2                  // Method javax/swing/JComponent.getParent:()Ljava/awt/Container;
       4: ifnull        15
       7: aload_0
       8: invokevirtual #2                  // Method javax/swing/JComponent.getParent:()Ljava/awt/Container;
      11: aload_0
      12: invokevirtual #3                  // Method java/awt/Container.remove:(Ljava/awt/Component;)V
      15: return
}
