Compiled from "CertificateDetailJsonUnmarshaller.java"
public class com.amazonaws.services.certificatemanager.model.transform.CertificateDetailJsonUnmarshaller implements com.amazonaws.transform.Unmarshaller<com.amazonaws.services.certificatemanager.model.CertificateDetail, com.amazonaws.transform.JsonUnmarshallerContext> {
  private static com.amazonaws.services.certificatemanager.model.transform.CertificateDetailJsonUnmarshaller instance;

  public com.amazonaws.services.certificatemanager.model.transform.CertificateDetailJsonUnmarshaller();
    Code:
       0: aload_0
       1: invokespecial #1                  // Method java/lang/Object."<init>":()V
       4: return

  public com.amazonaws.services.certificatemanager.model.CertificateDetail unmarshall(com.amazonaws.transform.JsonUnmarshallerContext) throws java.lang.Exception;
    Code:
       0: new           #2                  // class com/amazonaws/services/certificatemanager/model/CertificateDetail
       3: dup
       4: invokespecial #3                  // Method com/amazonaws/services/certificatemanager/model/CertificateDetail."<init>":()V
       7: astore_2
       8: aload_1
       9: invokevirtual #4                  // Method com/amazonaws/transform/JsonUnmarshallerContext.getCurrentDepth:()I
      12: istore_3
      13: aload_1
      14: invokevirtual #5                  // Method com/amazonaws/transform/JsonUnmarshallerContext.getCurrentParentElement:()Ljava/lang/String;
      17: astore        4
      19: iload_3
      20: iconst_1
      21: iadd
      22: istore        5
      24: aload_1
      25: invokevirtual #6                  // Method com/amazonaws/transform/JsonUnmarshallerContext.getCurrentToken:()Lcom/fasterxml/jackson/core/JsonToken;
      28: astore        6
      30: aload         6
      32: ifnonnull     41
      35: aload_1
      36: invokevirtual #7                  // Method com/amazonaws/transform/JsonUnmarshallerContext.nextToken:()Lcom/fasterxml/jackson/core/JsonToken;
      39: astore        6
      41: aload         6
      43: getstatic     #8                  // Field com/fasterxml/jackson/core/JsonToken.VALUE_NULL:Lcom/fasterxml/jackson/core/JsonToken;
      46: if_acmpne     51
      49: aconst_null
      50: areturn
      51: aload         6
      53: ifnonnull     59
      56: goto          731
      59: aload         6
      61: getstatic     #9                  // Field com/fasterxml/jackson/core/JsonToken.FIELD_NAME:Lcom/fasterxml/jackson/core/JsonToken;
      64: if_acmpeq     75
      67: aload         6
      69: getstatic     #10                 // Field com/fasterxml/jackson/core/JsonToken.START_OBJECT:Lcom/fasterxml/jackson/core/JsonToken;
      72: if_acmpne     676
      75: aload_1
      76: ldc           #11                 // String CertificateArn
      78: iload         5
      80: invokevirtual #12                 // Method com/amazonaws/transform/JsonUnmarshallerContext.testExpression:(Ljava/lang/String;I)Z
      83: ifeq          110
      86: aload_1
      87: invokevirtual #7                  // Method com/amazonaws/transform/JsonUnmarshallerContext.nextToken:()Lcom/fasterxml/jackson/core/JsonToken;
      90: pop
      91: aload_2
      92: aload_1
      93: ldc           #13                 // class java/lang/String
      95: invokevirtual #14                 // Method com/amazonaws/transform/JsonUnmarshallerContext.getUnmarshaller:(Ljava/lang/Class;)Lcom/amazonaws/transform/Unmarshaller;
      98: aload_1
      99: invokeinterface #15,  2           // InterfaceMethod com/amazonaws/transform/Unmarshaller.unmarshall:(Ljava/lang/Object;)Ljava/lang/Object;
     104: checkcast     #13                 // class java/lang/String
     107: invokevirtual #16                 // Method com/amazonaws/services/certificatemanager/model/CertificateDetail.setCertificateArn:(Ljava/lang/String;)V
     110: aload_1
     111: ldc           #17                 // String DomainName
     113: iload         5
     115: invokevirtual #12                 // Method com/amazonaws/transform/JsonUnmarshallerContext.testExpression:(Ljava/lang/String;I)Z
     118: ifeq          145
     121: aload_1
     122: invokevirtual #7                  // Method com/amazonaws/transform/JsonUnmarshallerContext.nextToken:()Lcom/fasterxml/jackson/core/JsonToken;
     125: pop
     126: aload_2
     127: aload_1
     128: ldc           #13                 // class java/lang/String
     130: invokevirtual #14                 // Method com/amazonaws/transform/JsonUnmarshallerContext.getUnmarshaller:(Ljava/lang/Class;)Lcom/amazonaws/transform/Unmarshaller;
     133: aload_1
     134: invokeinterface #15,  2           // InterfaceMethod com/amazonaws/transform/Unmarshaller.unmarshall:(Ljava/lang/Object;)Ljava/lang/Object;
     139: checkcast     #13                 // class java/lang/String
     142: invokevirtual #18                 // Method com/amazonaws/services/certificatemanager/model/CertificateDetail.setDomainName:(Ljava/lang/String;)V
     145: aload_1
     146: ldc           #19                 // String SubjectAlternativeNames
     148: iload         5
     150: invokevirtual #12                 // Method com/amazonaws/transform/JsonUnmarshallerContext.testExpression:(Ljava/lang/String;I)Z
     153: ifeq          182
     156: aload_1
     157: invokevirtual #7                  // Method com/amazonaws/transform/JsonUnmarshallerContext.nextToken:()Lcom/fasterxml/jackson/core/JsonToken;
     160: pop
     161: aload_2
     162: new           #20                 // class com/amazonaws/transform/ListUnmarshaller
     165: dup
     166: aload_1
     167: ldc           #13                 // class java/lang/String
     169: invokevirtual #14                 // Method com/amazonaws/transform/JsonUnmarshallerContext.getUnmarshaller:(Ljava/lang/Class;)Lcom/amazonaws/transform/Unmarshaller;
     172: invokespecial #21                 // Method com/amazonaws/transform/ListUnmarshaller."<init>":(Lcom/amazonaws/transform/Unmarshaller;)V
     175: aload_1
     176: invokevirtual #22                 // Method com/amazonaws/transform/ListUnmarshaller.unmarshall:(Lcom/amazonaws/transform/JsonUnmarshallerContext;)Ljava/util/List;
     179: invokevirtual #23                 // Method com/amazonaws/services/certificatemanager/model/CertificateDetail.setSubjectAlternativeNames:(Ljava/util/Collection;)V
     182: aload_1
     183: ldc           #24                 // String DomainValidationOptions
     185: iload         5
     187: invokevirtual #12                 // Method com/amazonaws/transform/JsonUnmarshallerContext.testExpression:(Ljava/lang/String;I)Z
     190: ifeq          216
     193: aload_1
     194: invokevirtual #7                  // Method com/amazonaws/transform/JsonUnmarshallerContext.nextToken:()Lcom/fasterxml/jackson/core/JsonToken;
     197: pop
     198: aload_2
     199: new           #20                 // class com/amazonaws/transform/ListUnmarshaller
     202: dup
     203: invokestatic  #25                 // Method com/amazonaws/services/certificatemanager/model/transform/DomainValidationJsonUnmarshaller.getInstance:()Lcom/amazonaws/services/certificatemanager/model/transform/DomainValidationJsonUnmarshaller;
     206: invokespecial #21                 // Method com/amazonaws/transform/ListUnmarshaller."<init>":(Lcom/amazonaws/transform/Unmarshaller;)V
     209: aload_1
     210: invokevirtual #22                 // Method com/amazonaws/transform/ListUnmarshaller.unmarshall:(Lcom/amazonaws/transform/JsonUnmarshallerContext;)Ljava/util/List;
     213: invokevirtual #26                 // Method com/amazonaws/services/certificatemanager/model/CertificateDetail.setDomainValidationOptions:(Ljava/util/Collection;)V
     216: aload_1
     217: ldc           #27                 // String Serial
     219: iload         5
     221: invokevirtual #12                 // Method com/amazonaws/transform/JsonUnmarshallerContext.testExpression:(Ljava/lang/String;I)Z
     224: ifeq          251
     227: aload_1
     228: invokevirtual #7                  // Method com/amazonaws/transform/JsonUnmarshallerContext.nextToken:()Lcom/fasterxml/jackson/core/JsonToken;
     231: pop
     232: aload_2
     233: aload_1
     234: ldc           #13                 // class java/lang/String
     236: invokevirtual #14                 // Method com/amazonaws/transform/JsonUnmarshallerContext.getUnmarshaller:(Ljava/lang/Class;)Lcom/amazonaws/transform/Unmarshaller;
     239: aload_1
     240: invokeinterface #15,  2           // InterfaceMethod com/amazonaws/transform/Unmarshaller.unmarshall:(Ljava/lang/Object;)Ljava/lang/Object;
     245: checkcast     #13                 // class java/lang/String
     248: invokevirtual #28                 // Method com/amazonaws/services/certificatemanager/model/CertificateDetail.setSerial:(Ljava/lang/String;)V
     251: aload_1
     252: ldc           #29                 // String Subject
     254: iload         5
     256: invokevirtual #12                 // Method com/amazonaws/transform/JsonUnmarshallerContext.testExpression:(Ljava/lang/String;I)Z
     259: ifeq          286
     262: aload_1
     263: invokevirtual #7                  // Method com/amazonaws/transform/JsonUnmarshallerContext.nextToken:()Lcom/fasterxml/jackson/core/JsonToken;
     266: pop
     267: aload_2
     268: aload_1
     269: ldc           #13                 // class java/lang/String
     271: invokevirtual #14                 // Method com/amazonaws/transform/JsonUnmarshallerContext.getUnmarshaller:(Ljava/lang/Class;)Lcom/amazonaws/transform/Unmarshaller;
     274: aload_1
     275: invokeinterface #15,  2           // InterfaceMethod com/amazonaws/transform/Unmarshaller.unmarshall:(Ljava/lang/Object;)Ljava/lang/Object;
     280: checkcast     #13                 // class java/lang/String
     283: invokevirtual #30                 // Method com/amazonaws/services/certificatemanager/model/CertificateDetail.setSubject:(Ljava/lang/String;)V
     286: aload_1
     287: ldc           #31                 // String Issuer
     289: iload         5
     291: invokevirtual #12                 // Method com/amazonaws/transform/JsonUnmarshallerContext.testExpression:(Ljava/lang/String;I)Z
     294: ifeq          321
     297: aload_1
     298: invokevirtual #7                  // Method com/amazonaws/transform/JsonUnmarshallerContext.nextToken:()Lcom/fasterxml/jackson/core/JsonToken;
     301: pop
     302: aload_2
     303: aload_1
     304: ldc           #13                 // class java/lang/String
     306: invokevirtual #14                 // Method com/amazonaws/transform/JsonUnmarshallerContext.getUnmarshaller:(Ljava/lang/Class;)Lcom/amazonaws/transform/Unmarshaller;
     309: aload_1
     310: invokeinterface #15,  2           // InterfaceMethod com/amazonaws/transform/Unmarshaller.unmarshall:(Ljava/lang/Object;)Ljava/lang/Object;
     315: checkcast     #13                 // class java/lang/String
     318: invokevirtual #32                 // Method com/amazonaws/services/certificatemanager/model/CertificateDetail.setIssuer:(Ljava/lang/String;)V
     321: aload_1
     322: ldc           #33                 // String CreatedAt
     324: iload         5
     326: invokevirtual #12                 // Method com/amazonaws/transform/JsonUnmarshallerContext.testExpression:(Ljava/lang/String;I)Z
     329: ifeq          356
     332: aload_1
     333: invokevirtual #7                  // Method com/amazonaws/transform/JsonUnmarshallerContext.nextToken:()Lcom/fasterxml/jackson/core/JsonToken;
     336: pop
     337: aload_2
     338: aload_1
     339: ldc           #34                 // class java/util/Date
     341: invokevirtual #14                 // Method com/amazonaws/transform/JsonUnmarshallerContext.getUnmarshaller:(Ljava/lang/Class;)Lcom/amazonaws/transform/Unmarshaller;
     344: aload_1
     345: invokeinterface #15,  2           // InterfaceMethod com/amazonaws/transform/Unmarshaller.unmarshall:(Ljava/lang/Object;)Ljava/lang/Object;
     350: checkcast     #34                 // class java/util/Date
     353: invokevirtual #35                 // Method com/amazonaws/services/certificatemanager/model/CertificateDetail.setCreatedAt:(Ljava/util/Date;)V
     356: aload_1
     357: ldc           #36                 // String IssuedAt
     359: iload         5
     361: invokevirtual #12                 // Method com/amazonaws/transform/JsonUnmarshallerContext.testExpression:(Ljava/lang/String;I)Z
     364: ifeq          391
     367: aload_1
     368: invokevirtual #7                  // Method com/amazonaws/transform/JsonUnmarshallerContext.nextToken:()Lcom/fasterxml/jackson/core/JsonToken;
     371: pop
     372: aload_2
     373: aload_1
     374: ldc           #34                 // class java/util/Date
     376: invokevirtual #14                 // Method com/amazonaws/transform/JsonUnmarshallerContext.getUnmarshaller:(Ljava/lang/Class;)Lcom/amazonaws/transform/Unmarshaller;
     379: aload_1
     380: invokeinterface #15,  2           // InterfaceMethod com/amazonaws/transform/Unmarshaller.unmarshall:(Ljava/lang/Object;)Ljava/lang/Object;
     385: checkcast     #34                 // class java/util/Date
     388: invokevirtual #37                 // Method com/amazonaws/services/certificatemanager/model/CertificateDetail.setIssuedAt:(Ljava/util/Date;)V
     391: aload_1
     392: ldc           #38                 // String Status
     394: iload         5
     396: invokevirtual #12                 // Method com/amazonaws/transform/JsonUnmarshallerContext.testExpression:(Ljava/lang/String;I)Z
     399: ifeq          426
     402: aload_1
     403: invokevirtual #7                  // Method com/amazonaws/transform/JsonUnmarshallerContext.nextToken:()Lcom/fasterxml/jackson/core/JsonToken;
     406: pop
     407: aload_2
     408: aload_1
     409: ldc           #13                 // class java/lang/String
     411: invokevirtual #14                 // Method com/amazonaws/transform/JsonUnmarshallerContext.getUnmarshaller:(Ljava/lang/Class;)Lcom/amazonaws/transform/Unmarshaller;
     414: aload_1
     415: invokeinterface #15,  2           // InterfaceMethod com/amazonaws/transform/Unmarshaller.unmarshall:(Ljava/lang/Object;)Ljava/lang/Object;
     420: checkcast     #13                 // class java/lang/String
     423: invokevirtual #39                 // Method com/amazonaws/services/certificatemanager/model/CertificateDetail.setStatus:(Ljava/lang/String;)V
     426: aload_1
     427: ldc           #40                 // String RevokedAt
     429: iload         5
     431: invokevirtual #12                 // Method com/amazonaws/transform/JsonUnmarshallerContext.testExpression:(Ljava/lang/String;I)Z
     434: ifeq          461
     437: aload_1
     438: invokevirtual #7                  // Method com/amazonaws/transform/JsonUnmarshallerContext.nextToken:()Lcom/fasterxml/jackson/core/JsonToken;
     441: pop
     442: aload_2
     443: aload_1
     444: ldc           #34                 // class java/util/Date
     446: invokevirtual #14                 // Method com/amazonaws/transform/JsonUnmarshallerContext.getUnmarshaller:(Ljava/lang/Class;)Lcom/amazonaws/transform/Unmarshaller;
     449: aload_1
     450: invokeinterface #15,  2           // InterfaceMethod com/amazonaws/transform/Unmarshaller.unmarshall:(Ljava/lang/Object;)Ljava/lang/Object;
     455: checkcast     #34                 // class java/util/Date
     458: invokevirtual #41                 // Method com/amazonaws/services/certificatemanager/model/CertificateDetail.setRevokedAt:(Ljava/util/Date;)V
     461: aload_1
     462: ldc           #42                 // String RevocationReason
     464: iload         5
     466: invokevirtual #12                 // Method com/amazonaws/transform/JsonUnmarshallerContext.testExpression:(Ljava/lang/String;I)Z
     469: ifeq          496
     472: aload_1
     473: invokevirtual #7                  // Method com/amazonaws/transform/JsonUnmarshallerContext.nextToken:()Lcom/fasterxml/jackson/core/JsonToken;
     476: pop
     477: aload_2
     478: aload_1
     479: ldc           #13                 // class java/lang/String
     481: invokevirtual #14                 // Method com/amazonaws/transform/JsonUnmarshallerContext.getUnmarshaller:(Ljava/lang/Class;)Lcom/amazonaws/transform/Unmarshaller;
     484: aload_1
     485: invokeinterface #15,  2           // InterfaceMethod com/amazonaws/transform/Unmarshaller.unmarshall:(Ljava/lang/Object;)Ljava/lang/Object;
     490: checkcast     #13                 // class java/lang/String
     493: invokevirtual #43                 // Method com/amazonaws/services/certificatemanager/model/CertificateDetail.setRevocationReason:(Ljava/lang/String;)V
     496: aload_1
     497: ldc           #44                 // String NotBefore
     499: iload         5
     501: invokevirtual #12                 // Method com/amazonaws/transform/JsonUnmarshallerContext.testExpression:(Ljava/lang/String;I)Z
     504: ifeq          531
     507: aload_1
     508: invokevirtual #7                  // Method com/amazonaws/transform/JsonUnmarshallerContext.nextToken:()Lcom/fasterxml/jackson/core/JsonToken;
     511: pop
     512: aload_2
     513: aload_1
     514: ldc           #34                 // class java/util/Date
     516: invokevirtual #14                 // Method com/amazonaws/transform/JsonUnmarshallerContext.getUnmarshaller:(Ljava/lang/Class;)Lcom/amazonaws/transform/Unmarshaller;
     519: aload_1
     520: invokeinterface #15,  2           // InterfaceMethod com/amazonaws/transform/Unmarshaller.unmarshall:(Ljava/lang/Object;)Ljava/lang/Object;
     525: checkcast     #34                 // class java/util/Date
     528: invokevirtual #45                 // Method com/amazonaws/services/certificatemanager/model/CertificateDetail.setNotBefore:(Ljava/util/Date;)V
     531: aload_1
     532: ldc           #46                 // String NotAfter
     534: iload         5
     536: invokevirtual #12                 // Method com/amazonaws/transform/JsonUnmarshallerContext.testExpression:(Ljava/lang/String;I)Z
     539: ifeq          566
     542: aload_1
     543: invokevirtual #7                  // Method com/amazonaws/transform/JsonUnmarshallerContext.nextToken:()Lcom/fasterxml/jackson/core/JsonToken;
     546: pop
     547: aload_2
     548: aload_1
     549: ldc           #34                 // class java/util/Date
     551: invokevirtual #14                 // Method com/amazonaws/transform/JsonUnmarshallerContext.getUnmarshaller:(Ljava/lang/Class;)Lcom/amazonaws/transform/Unmarshaller;
     554: aload_1
     555: invokeinterface #15,  2           // InterfaceMethod com/amazonaws/transform/Unmarshaller.unmarshall:(Ljava/lang/Object;)Ljava/lang/Object;
     560: checkcast     #34                 // class java/util/Date
     563: invokevirtual #47                 // Method com/amazonaws/services/certificatemanager/model/CertificateDetail.setNotAfter:(Ljava/util/Date;)V
     566: aload_1
     567: ldc           #48                 // String KeyAlgorithm
     569: iload         5
     571: invokevirtual #12                 // Method com/amazonaws/transform/JsonUnmarshallerContext.testExpression:(Ljava/lang/String;I)Z
     574: ifeq          601
     577: aload_1
     578: invokevirtual #7                  // Method com/amazonaws/transform/JsonUnmarshallerContext.nextToken:()Lcom/fasterxml/jackson/core/JsonToken;
     581: pop
     582: aload_2
     583: aload_1
     584: ldc           #13                 // class java/lang/String
     586: invokevirtual #14                 // Method com/amazonaws/transform/JsonUnmarshallerContext.getUnmarshaller:(Ljava/lang/Class;)Lcom/amazonaws/transform/Unmarshaller;
     589: aload_1
     590: invokeinterface #15,  2           // InterfaceMethod com/amazonaws/transform/Unmarshaller.unmarshall:(Ljava/lang/Object;)Ljava/lang/Object;
     595: checkcast     #13                 // class java/lang/String
     598: invokevirtual #49                 // Method com/amazonaws/services/certificatemanager/model/CertificateDetail.setKeyAlgorithm:(Ljava/lang/String;)V
     601: aload_1
     602: ldc           #50                 // String SignatureAlgorithm
     604: iload         5
     606: invokevirtual #12                 // Method com/amazonaws/transform/JsonUnmarshallerContext.testExpression:(Ljava/lang/String;I)Z
     609: ifeq          636
     612: aload_1
     613: invokevirtual #7                  // Method com/amazonaws/transform/JsonUnmarshallerContext.nextToken:()Lcom/fasterxml/jackson/core/JsonToken;
     616: pop
     617: aload_2
     618: aload_1
     619: ldc           #13                 // class java/lang/String
     621: invokevirtual #14                 // Method com/amazonaws/transform/JsonUnmarshallerContext.getUnmarshaller:(Ljava/lang/Class;)Lcom/amazonaws/transform/Unmarshaller;
     624: aload_1
     625: invokeinterface #15,  2           // InterfaceMethod com/amazonaws/transform/Unmarshaller.unmarshall:(Ljava/lang/Object;)Ljava/lang/Object;
     630: checkcast     #13                 // class java/lang/String
     633: invokevirtual #51                 // Method com/amazonaws/services/certificatemanager/model/CertificateDetail.setSignatureAlgorithm:(Ljava/lang/String;)V
     636: aload_1
     637: ldc           #52                 // String InUseBy
     639: iload         5
     641: invokevirtual #12                 // Method com/amazonaws/transform/JsonUnmarshallerContext.testExpression:(Ljava/lang/String;I)Z
     644: ifeq          722
     647: aload_1
     648: invokevirtual #7                  // Method com/amazonaws/transform/JsonUnmarshallerContext.nextToken:()Lcom/fasterxml/jackson/core/JsonToken;
     651: pop
     652: aload_2
     653: new           #20                 // class com/amazonaws/transform/ListUnmarshaller
     656: dup
     657: aload_1
     658: ldc           #13                 // class java/lang/String
     660: invokevirtual #14                 // Method com/amazonaws/transform/JsonUnmarshallerContext.getUnmarshaller:(Ljava/lang/Class;)Lcom/amazonaws/transform/Unmarshaller;
     663: invokespecial #21                 // Method com/amazonaws/transform/ListUnmarshaller."<init>":(Lcom/amazonaws/transform/Unmarshaller;)V
     666: aload_1
     667: invokevirtual #22                 // Method com/amazonaws/transform/ListUnmarshaller.unmarshall:(Lcom/amazonaws/transform/JsonUnmarshallerContext;)Ljava/util/List;
     670: invokevirtual #53                 // Method com/amazonaws/services/certificatemanager/model/CertificateDetail.setInUseBy:(Ljava/util/Collection;)V
     673: goto          722
     676: aload         6
     678: getstatic     #54                 // Field com/fasterxml/jackson/core/JsonToken.END_ARRAY:Lcom/fasterxml/jackson/core/JsonToken;
     681: if_acmpeq     692
     684: aload         6
     686: getstatic     #55                 // Field com/fasterxml/jackson/core/JsonToken.END_OBJECT:Lcom/fasterxml/jackson/core/JsonToken;
     689: if_acmpne     722
     692: aload_1
     693: invokevirtual #56                 // Method com/amazonaws/transform/JsonUnmarshallerContext.getLastParsedParentElement:()Ljava/lang/String;
     696: ifnull        711
     699: aload_1
     700: invokevirtual #56                 // Method com/amazonaws/transform/JsonUnmarshallerContext.getLastParsedParentElement:()Ljava/lang/String;
     703: aload         4
     705: invokevirtual #57                 // Method java/lang/String.equals:(Ljava/lang/Object;)Z
     708: ifeq          722
     711: aload_1
     712: invokevirtual #4                  // Method com/amazonaws/transform/JsonUnmarshallerContext.getCurrentDepth:()I
     715: iload_3
     716: if_icmpgt     722
     719: goto          731
     722: aload_1
     723: invokevirtual #7                  // Method com/amazonaws/transform/JsonUnmarshallerContext.nextToken:()Lcom/fasterxml/jackson/core/JsonToken;
     726: astore        6
     728: goto          51
     731: aload_2
     732: areturn

  public static com.amazonaws.services.certificatemanager.model.transform.CertificateDetailJsonUnmarshaller getInstance();
    Code:
       0: getstatic     #58                 // Field instance:Lcom/amazonaws/services/certificatemanager/model/transform/CertificateDetailJsonUnmarshaller;
       3: ifnonnull     16
       6: new           #59                 // class com/amazonaws/services/certificatemanager/model/transform/CertificateDetailJsonUnmarshaller
       9: dup
      10: invokespecial #60                 // Method "<init>":()V
      13: putstatic     #58                 // Field instance:Lcom/amazonaws/services/certificatemanager/model/transform/CertificateDetailJsonUnmarshaller;
      16: getstatic     #58                 // Field instance:Lcom/amazonaws/services/certificatemanager/model/transform/CertificateDetailJsonUnmarshaller;
      19: areturn

  public java.lang.Object unmarshall(java.lang.Object) throws java.lang.Exception;
    Code:
       0: aload_0
       1: aload_1
       2: checkcast     #61                 // class com/amazonaws/transform/JsonUnmarshallerContext
       5: invokevirtual #62                 // Method unmarshall:(Lcom/amazonaws/transform/JsonUnmarshallerContext;)Lcom/amazonaws/services/certificatemanager/model/CertificateDetail;
       8: areturn
}
