Compiled from "SimpleLanguage.java"
public class org.apache.camel.language.simple.SimpleLanguage extends org.apache.camel.support.LanguageSupport {
  private static final org.apache.camel.language.simple.SimpleLanguage SIMPLE;

  protected boolean allowEscape;

  public org.apache.camel.language.simple.SimpleLanguage();
    Code:
       0: aload_0
       1: invokespecial #13                 // Method org/apache/camel/support/LanguageSupport."<init>":()V
       4: aload_0
       5: iconst_1
       6: putfield      #15                 // Field allowEscape:Z
       9: return

  public org.apache.camel.Predicate createPredicate(java.lang.String);
    Code:
       0: aload_1
       1: ldc           #20                 // String expression
       3: invokestatic  #26                 // Method org/apache/camel/util/ObjectHelper.notNull:(Ljava/lang/Object;Ljava/lang/String;)Ljava/lang/Object;
       6: pop
       7: aload_0
       8: aload_1
       9: invokevirtual #30                 // Method loadResource:(Ljava/lang/String;)Ljava/lang/String;
      12: astore_1
      13: aload_1
      14: aload_0
      15: getfield      #15                 // Field allowEscape:Z
      18: invokestatic  #36                 // Method org/apache/camel/language/simple/SimpleBackwardsCompatibleParser.parsePredicate:(Ljava/lang/String;Z)Lorg/apache/camel/Predicate;
      21: astore_2
      22: aload_2
      23: ifnonnull     44
      26: new           #38                 // class org/apache/camel/language/simple/SimplePredicateParser
      29: dup
      30: aload_1
      31: aload_0
      32: getfield      #15                 // Field allowEscape:Z
      35: invokespecial #41                 // Method org/apache/camel/language/simple/SimplePredicateParser."<init>":(Ljava/lang/String;Z)V
      38: astore_3
      39: aload_3
      40: invokevirtual #44                 // Method org/apache/camel/language/simple/SimplePredicateParser.parsePredicate:()Lorg/apache/camel/Predicate;
      43: astore_2
      44: aload_2
      45: areturn

  public org.apache.camel.Expression createExpression(java.lang.String);
    Code:
       0: aload_1
       1: ldc           #20                 // String expression
       3: invokestatic  #26                 // Method org/apache/camel/util/ObjectHelper.notNull:(Ljava/lang/Object;Ljava/lang/String;)Ljava/lang/Object;
       6: pop
       7: aload_0
       8: aload_1
       9: invokevirtual #30                 // Method loadResource:(Ljava/lang/String;)Ljava/lang/String;
      12: astore_1
      13: aload_1
      14: aload_0
      15: getfield      #15                 // Field allowEscape:Z
      18: invokestatic  #57                 // Method org/apache/camel/language/simple/SimpleBackwardsCompatibleParser.parseExpression:(Ljava/lang/String;Z)Lorg/apache/camel/Expression;
      21: astore_2
      22: aload_2
      23: ifnonnull     44
      26: new           #59                 // class org/apache/camel/language/simple/SimpleExpressionParser
      29: dup
      30: aload_1
      31: aload_0
      32: getfield      #15                 // Field allowEscape:Z
      35: invokespecial #60                 // Method org/apache/camel/language/simple/SimpleExpressionParser."<init>":(Ljava/lang/String;Z)V
      38: astore_3
      39: aload_3
      40: invokevirtual #63                 // Method org/apache/camel/language/simple/SimpleExpressionParser.parseExpression:()Lorg/apache/camel/Expression;
      43: astore_2
      44: aload_2
      45: areturn

  public static org.apache.camel.Expression simple(java.lang.String);
    Code:
       0: aload_0
       1: invokestatic  #70                 // Method expression:(Ljava/lang/String;)Lorg/apache/camel/Expression;
       4: areturn

  public static org.apache.camel.Expression simple(java.lang.String, java.lang.Class<?>);
    Code:
       0: new           #2                  // class org/apache/camel/language/simple/SimpleLanguage
       3: dup
       4: invokespecial #72                 // Method "<init>":()V
       7: aload_0
       8: aload_1
       9: invokevirtual #74                 // Method createExpression:(Ljava/lang/String;Ljava/lang/Class;)Lorg/apache/camel/Expression;
      12: areturn

  public org.apache.camel.Expression createExpression(java.lang.String, java.lang.Class<?>);
    Code:
       0: aload_2
       1: ldc           #79                 // class java/lang/Boolean
       3: if_acmpeq     13
       6: aload_2
       7: getstatic     #82                 // Field java/lang/Boolean.TYPE:Ljava/lang/Class;
      10: if_acmpne     24
      13: aload_0
      14: aload_1
      15: invokevirtual #84                 // Method createPredicate:(Ljava/lang/String;)Lorg/apache/camel/Predicate;
      18: astore_3
      19: aload_3
      20: invokestatic  #90                 // Method org/apache/camel/util/PredicateToExpressionAdapter.toExpression:(Lorg/apache/camel/Predicate;)Lorg/apache/camel/Expression;
      23: areturn
      24: aload_0
      25: aload_1
      26: invokevirtual #92                 // Method createExpression:(Ljava/lang/String;)Lorg/apache/camel/Expression;
      29: astore_3
      30: aload_2
      31: ifnull        40
      34: aload_3
      35: aload_2
      36: invokestatic  #98                 // Method org/apache/camel/builder/ExpressionBuilder.convertToExpression:(Lorg/apache/camel/Expression;Ljava/lang/Class;)Lorg/apache/camel/Expression;
      39: astore_3
      40: aload_3
      41: areturn

  public static org.apache.camel.Expression expression(java.lang.String);
    Code:
       0: getstatic     #102                // Field SIMPLE:Lorg/apache/camel/language/simple/SimpleLanguage;
       3: aload_0
       4: invokevirtual #92                 // Method createExpression:(Ljava/lang/String;)Lorg/apache/camel/Expression;
       7: areturn

  public static org.apache.camel.Predicate predicate(java.lang.String);
    Code:
       0: getstatic     #102                // Field SIMPLE:Lorg/apache/camel/language/simple/SimpleLanguage;
       3: aload_0
       4: invokevirtual #84                 // Method createPredicate:(Ljava/lang/String;)Lorg/apache/camel/Predicate;
       7: areturn

  public static boolean hasSimpleFunction(java.lang.String);
    Code:
       0: aload_0
       1: invokestatic  #109                // Method org/apache/camel/language/simple/SimpleTokenizer.hasFunctionStartToken:(Ljava/lang/String;)Z
       4: ireturn

  public static void changeFunctionStartToken(java.lang.String...);
    Code:
       0: aload_0
       1: invokestatic  #113                // Method org/apache/camel/language/simple/SimpleTokenizer.changeFunctionStartToken:([Ljava/lang/String;)V
       4: return

  public static void changeFunctionEndToken(java.lang.String...);
    Code:
       0: aload_0
       1: invokestatic  #118                // Method org/apache/camel/language/simple/SimpleTokenizer.changeFunctionEndToken:([Ljava/lang/String;)V
       4: return

  public void setFunctionStartToken(java.lang.String);
    Code:
       0: iconst_1
       1: anewarray     #123                // class java/lang/String
       4: dup
       5: iconst_0
       6: aload_1
       7: aastore
       8: invokestatic  #124                // Method changeFunctionStartToken:([Ljava/lang/String;)V
      11: return

  public void setFunctionEndToken(java.lang.String);
    Code:
       0: iconst_1
       1: anewarray     #123                // class java/lang/String
       4: dup
       5: iconst_0
       6: aload_1
       7: aastore
       8: invokestatic  #126                // Method changeFunctionEndToken:([Ljava/lang/String;)V
      11: return

  static {};
    Code:
       0: new           #2                  // class org/apache/camel/language/simple/SimpleLanguage
       3: dup
       4: invokespecial #72                 // Method "<init>":()V
       7: putstatic     #102                // Field SIMPLE:Lorg/apache/camel/language/simple/SimpleLanguage;
      10: return
}
