Compiled from "AmazonSimpleEmailServiceAsyncClient.java"
public class com.amazonaws.services.simpleemail.AmazonSimpleEmailServiceAsyncClient extends com.amazonaws.services.simpleemail.AmazonSimpleEmailServiceClient implements com.amazonaws.services.simpleemail.AmazonSimpleEmailServiceAsync {
  private static final int DEFAULT_THREAD_POOL_SIZE;

  private final java.util.concurrent.ExecutorService executorService;

  public com.amazonaws.services.simpleemail.AmazonSimpleEmailServiceAsyncClient();
    Code:
       0: aload_0
       1: new           #1                  // class com/amazonaws/auth/DefaultAWSCredentialsProviderChain
       4: dup
       5: invokespecial #2                  // Method com/amazonaws/auth/DefaultAWSCredentialsProviderChain."<init>":()V
       8: invokespecial #3                  // Method "<init>":(Lcom/amazonaws/auth/AWSCredentialsProvider;)V
      11: return

  public com.amazonaws.services.simpleemail.AmazonSimpleEmailServiceAsyncClient(com.amazonaws.ClientConfiguration);
    Code:
       0: aload_0
       1: new           #1                  // class com/amazonaws/auth/DefaultAWSCredentialsProviderChain
       4: dup
       5: invokespecial #2                  // Method com/amazonaws/auth/DefaultAWSCredentialsProviderChain."<init>":()V
       8: aload_1
       9: aload_1
      10: invokevirtual #4                  // Method com/amazonaws/ClientConfiguration.getMaxConnections:()I
      13: invokestatic  #5                  // Method java/util/concurrent/Executors.newFixedThreadPool:(I)Ljava/util/concurrent/ExecutorService;
      16: invokespecial #6                  // Method "<init>":(Lcom/amazonaws/auth/AWSCredentialsProvider;Lcom/amazonaws/ClientConfiguration;Ljava/util/concurrent/ExecutorService;)V
      19: return

  public com.amazonaws.services.simpleemail.AmazonSimpleEmailServiceAsyncClient(com.amazonaws.auth.AWSCredentials);
    Code:
       0: aload_0
       1: aload_1
       2: bipush        50
       4: invokestatic  #5                  // Method java/util/concurrent/Executors.newFixedThreadPool:(I)Ljava/util/concurrent/ExecutorService;
       7: invokespecial #8                  // Method "<init>":(Lcom/amazonaws/auth/AWSCredentials;Ljava/util/concurrent/ExecutorService;)V
      10: return

  public com.amazonaws.services.simpleemail.AmazonSimpleEmailServiceAsyncClient(com.amazonaws.auth.AWSCredentials, java.util.concurrent.ExecutorService);
    Code:
       0: aload_0
       1: aload_1
       2: getstatic     #9                  // Field configFactory:Lcom/amazonaws/ClientConfigurationFactory;
       5: invokevirtual #10                 // Method com/amazonaws/ClientConfigurationFactory.getConfig:()Lcom/amazonaws/ClientConfiguration;
       8: aload_2
       9: invokespecial #11                 // Method "<init>":(Lcom/amazonaws/auth/AWSCredentials;Lcom/amazonaws/ClientConfiguration;Ljava/util/concurrent/ExecutorService;)V
      12: return

  public com.amazonaws.services.simpleemail.AmazonSimpleEmailServiceAsyncClient(com.amazonaws.auth.AWSCredentials, com.amazonaws.ClientConfiguration, java.util.concurrent.ExecutorService);
    Code:
       0: aload_0
       1: aload_1
       2: aload_2
       3: invokespecial #12                 // Method com/amazonaws/services/simpleemail/AmazonSimpleEmailServiceClient."<init>":(Lcom/amazonaws/auth/AWSCredentials;Lcom/amazonaws/ClientConfiguration;)V
       6: aload_0
       7: aload_3
       8: putfield      #13                 // Field executorService:Ljava/util/concurrent/ExecutorService;
      11: return

  public com.amazonaws.services.simpleemail.AmazonSimpleEmailServiceAsyncClient(com.amazonaws.auth.AWSCredentialsProvider);
    Code:
       0: aload_0
       1: aload_1
       2: bipush        50
       4: invokestatic  #5                  // Method java/util/concurrent/Executors.newFixedThreadPool:(I)Ljava/util/concurrent/ExecutorService;
       7: invokespecial #14                 // Method "<init>":(Lcom/amazonaws/auth/AWSCredentialsProvider;Ljava/util/concurrent/ExecutorService;)V
      10: return

  public com.amazonaws.services.simpleemail.AmazonSimpleEmailServiceAsyncClient(com.amazonaws.auth.AWSCredentialsProvider, com.amazonaws.ClientConfiguration);
    Code:
       0: aload_0
       1: aload_1
       2: aload_2
       3: aload_2
       4: invokevirtual #4                  // Method com/amazonaws/ClientConfiguration.getMaxConnections:()I
       7: invokestatic  #5                  // Method java/util/concurrent/Executors.newFixedThreadPool:(I)Ljava/util/concurrent/ExecutorService;
      10: invokespecial #6                  // Method "<init>":(Lcom/amazonaws/auth/AWSCredentialsProvider;Lcom/amazonaws/ClientConfiguration;Ljava/util/concurrent/ExecutorService;)V
      13: return

  public com.amazonaws.services.simpleemail.AmazonSimpleEmailServiceAsyncClient(com.amazonaws.auth.AWSCredentialsProvider, java.util.concurrent.ExecutorService);
    Code:
       0: aload_0
       1: aload_1
       2: getstatic     #9                  // Field configFactory:Lcom/amazonaws/ClientConfigurationFactory;
       5: invokevirtual #10                 // Method com/amazonaws/ClientConfigurationFactory.getConfig:()Lcom/amazonaws/ClientConfiguration;
       8: aload_2
       9: invokespecial #6                  // Method "<init>":(Lcom/amazonaws/auth/AWSCredentialsProvider;Lcom/amazonaws/ClientConfiguration;Ljava/util/concurrent/ExecutorService;)V
      12: return

  public com.amazonaws.services.simpleemail.AmazonSimpleEmailServiceAsyncClient(com.amazonaws.auth.AWSCredentialsProvider, com.amazonaws.ClientConfiguration, java.util.concurrent.ExecutorService);
    Code:
       0: aload_0
       1: aload_1
       2: aload_2
       3: invokespecial #15                 // Method com/amazonaws/services/simpleemail/AmazonSimpleEmailServiceClient."<init>":(Lcom/amazonaws/auth/AWSCredentialsProvider;Lcom/amazonaws/ClientConfiguration;)V
       6: aload_0
       7: aload_3
       8: putfield      #13                 // Field executorService:Ljava/util/concurrent/ExecutorService;
      11: return

  com.amazonaws.services.simpleemail.AmazonSimpleEmailServiceAsyncClient(com.amazonaws.client.AwsAsyncClientParams);
    Code:
       0: aload_0
       1: aload_1
       2: invokespecial #16                 // Method com/amazonaws/services/simpleemail/AmazonSimpleEmailServiceClient."<init>":(Lcom/amazonaws/client/AwsSyncClientParams;)V
       5: aload_0
       6: aload_1
       7: invokevirtual #17                 // Method com/amazonaws/client/AwsAsyncClientParams.getExecutor:()Ljava/util/concurrent/ExecutorService;
      10: putfield      #13                 // Field executorService:Ljava/util/concurrent/ExecutorService;
      13: return

  public java.util.concurrent.ExecutorService getExecutorService();
    Code:
       0: aload_0
       1: getfield      #13                 // Field executorService:Ljava/util/concurrent/ExecutorService;
       4: areturn

  public java.util.concurrent.Future<com.amazonaws.services.simpleemail.model.CloneReceiptRuleSetResult> cloneReceiptRuleSetAsync(com.amazonaws.services.simpleemail.model.CloneReceiptRuleSetRequest);
    Code:
       0: aload_0
       1: aload_1
       2: aconst_null
       3: invokevirtual #18                 // Method cloneReceiptRuleSetAsync:(Lcom/amazonaws/services/simpleemail/model/CloneReceiptRuleSetRequest;Lcom/amazonaws/handlers/AsyncHandler;)Ljava/util/concurrent/Future;
       6: areturn

  public java.util.concurrent.Future<com.amazonaws.services.simpleemail.model.CloneReceiptRuleSetResult> cloneReceiptRuleSetAsync(com.amazonaws.services.simpleemail.model.CloneReceiptRuleSetRequest, com.amazonaws.handlers.AsyncHandler<com.amazonaws.services.simpleemail.model.CloneReceiptRuleSetRequest, com.amazonaws.services.simpleemail.model.CloneReceiptRuleSetResult>);
    Code:
       0: aload_0
       1: getfield      #13                 // Field executorService:Ljava/util/concurrent/ExecutorService;
       4: new           #19                 // class com/amazonaws/services/simpleemail/AmazonSimpleEmailServiceAsyncClient$1
       7: dup
       8: aload_0
       9: aload_1
      10: aload_2
      11: invokespecial #20                 // Method com/amazonaws/services/simpleemail/AmazonSimpleEmailServiceAsyncClient$1."<init>":(Lcom/amazonaws/services/simpleemail/AmazonSimpleEmailServiceAsyncClient;Lcom/amazonaws/services/simpleemail/model/CloneReceiptRuleSetRequest;Lcom/amazonaws/handlers/AsyncHandler;)V
      14: invokeinterface #21,  2           // InterfaceMethod java/util/concurrent/ExecutorService.submit:(Ljava/util/concurrent/Callable;)Ljava/util/concurrent/Future;
      19: areturn

  public java.util.concurrent.Future<com.amazonaws.services.simpleemail.model.CreateReceiptFilterResult> createReceiptFilterAsync(com.amazonaws.services.simpleemail.model.CreateReceiptFilterRequest);
    Code:
       0: aload_0
       1: aload_1
       2: aconst_null
       3: invokevirtual #22                 // Method createReceiptFilterAsync:(Lcom/amazonaws/services/simpleemail/model/CreateReceiptFilterRequest;Lcom/amazonaws/handlers/AsyncHandler;)Ljava/util/concurrent/Future;
       6: areturn

  public java.util.concurrent.Future<com.amazonaws.services.simpleemail.model.CreateReceiptFilterResult> createReceiptFilterAsync(com.amazonaws.services.simpleemail.model.CreateReceiptFilterRequest, com.amazonaws.handlers.AsyncHandler<com.amazonaws.services.simpleemail.model.CreateReceiptFilterRequest, com.amazonaws.services.simpleemail.model.CreateReceiptFilterResult>);
    Code:
       0: aload_0
       1: getfield      #13                 // Field executorService:Ljava/util/concurrent/ExecutorService;
       4: new           #23                 // class com/amazonaws/services/simpleemail/AmazonSimpleEmailServiceAsyncClient$2
       7: dup
       8: aload_0
       9: aload_1
      10: aload_2
      11: invokespecial #24                 // Method com/amazonaws/services/simpleemail/AmazonSimpleEmailServiceAsyncClient$2."<init>":(Lcom/amazonaws/services/simpleemail/AmazonSimpleEmailServiceAsyncClient;Lcom/amazonaws/services/simpleemail/model/CreateReceiptFilterRequest;Lcom/amazonaws/handlers/AsyncHandler;)V
      14: invokeinterface #21,  2           // InterfaceMethod java/util/concurrent/ExecutorService.submit:(Ljava/util/concurrent/Callable;)Ljava/util/concurrent/Future;
      19: areturn

  public java.util.concurrent.Future<com.amazonaws.services.simpleemail.model.CreateReceiptRuleResult> createReceiptRuleAsync(com.amazonaws.services.simpleemail.model.CreateReceiptRuleRequest);
    Code:
       0: aload_0
       1: aload_1
       2: aconst_null
       3: invokevirtual #25                 // Method createReceiptRuleAsync:(Lcom/amazonaws/services/simpleemail/model/CreateReceiptRuleRequest;Lcom/amazonaws/handlers/AsyncHandler;)Ljava/util/concurrent/Future;
       6: areturn

  public java.util.concurrent.Future<com.amazonaws.services.simpleemail.model.CreateReceiptRuleResult> createReceiptRuleAsync(com.amazonaws.services.simpleemail.model.CreateReceiptRuleRequest, com.amazonaws.handlers.AsyncHandler<com.amazonaws.services.simpleemail.model.CreateReceiptRuleRequest, com.amazonaws.services.simpleemail.model.CreateReceiptRuleResult>);
    Code:
       0: aload_0
       1: getfield      #13                 // Field executorService:Ljava/util/concurrent/ExecutorService;
       4: new           #26                 // class com/amazonaws/services/simpleemail/AmazonSimpleEmailServiceAsyncClient$3
       7: dup
       8: aload_0
       9: aload_1
      10: aload_2
      11: invokespecial #27                 // Method com/amazonaws/services/simpleemail/AmazonSimpleEmailServiceAsyncClient$3."<init>":(Lcom/amazonaws/services/simpleemail/AmazonSimpleEmailServiceAsyncClient;Lcom/amazonaws/services/simpleemail/model/CreateReceiptRuleRequest;Lcom/amazonaws/handlers/AsyncHandler;)V
      14: invokeinterface #21,  2           // InterfaceMethod java/util/concurrent/ExecutorService.submit:(Ljava/util/concurrent/Callable;)Ljava/util/concurrent/Future;
      19: areturn

  public java.util.concurrent.Future<com.amazonaws.services.simpleemail.model.CreateReceiptRuleSetResult> createReceiptRuleSetAsync(com.amazonaws.services.simpleemail.model.CreateReceiptRuleSetRequest);
    Code:
       0: aload_0
       1: aload_1
       2: aconst_null
       3: invokevirtual #28                 // Method createReceiptRuleSetAsync:(Lcom/amazonaws/services/simpleemail/model/CreateReceiptRuleSetRequest;Lcom/amazonaws/handlers/AsyncHandler;)Ljava/util/concurrent/Future;
       6: areturn

  public java.util.concurrent.Future<com.amazonaws.services.simpleemail.model.CreateReceiptRuleSetResult> createReceiptRuleSetAsync(com.amazonaws.services.simpleemail.model.CreateReceiptRuleSetRequest, com.amazonaws.handlers.AsyncHandler<com.amazonaws.services.simpleemail.model.CreateReceiptRuleSetRequest, com.amazonaws.services.simpleemail.model.CreateReceiptRuleSetResult>);
    Code:
       0: aload_0
       1: getfield      #13                 // Field executorService:Ljava/util/concurrent/ExecutorService;
       4: new           #29                 // class com/amazonaws/services/simpleemail/AmazonSimpleEmailServiceAsyncClient$4
       7: dup
       8: aload_0
       9: aload_1
      10: aload_2
      11: invokespecial #30                 // Method com/amazonaws/services/simpleemail/AmazonSimpleEmailServiceAsyncClient$4."<init>":(Lcom/amazonaws/services/simpleemail/AmazonSimpleEmailServiceAsyncClient;Lcom/amazonaws/services/simpleemail/model/CreateReceiptRuleSetRequest;Lcom/amazonaws/handlers/AsyncHandler;)V
      14: invokeinterface #21,  2           // InterfaceMethod java/util/concurrent/ExecutorService.submit:(Ljava/util/concurrent/Callable;)Ljava/util/concurrent/Future;
      19: areturn

  public java.util.concurrent.Future<com.amazonaws.services.simpleemail.model.DeleteIdentityResult> deleteIdentityAsync(com.amazonaws.services.simpleemail.model.DeleteIdentityRequest);
    Code:
       0: aload_0
       1: aload_1
       2: aconst_null
       3: invokevirtual #31                 // Method deleteIdentityAsync:(Lcom/amazonaws/services/simpleemail/model/DeleteIdentityRequest;Lcom/amazonaws/handlers/AsyncHandler;)Ljava/util/concurrent/Future;
       6: areturn

  public java.util.concurrent.Future<com.amazonaws.services.simpleemail.model.DeleteIdentityResult> deleteIdentityAsync(com.amazonaws.services.simpleemail.model.DeleteIdentityRequest, com.amazonaws.handlers.AsyncHandler<com.amazonaws.services.simpleemail.model.DeleteIdentityRequest, com.amazonaws.services.simpleemail.model.DeleteIdentityResult>);
    Code:
       0: aload_0
       1: getfield      #13                 // Field executorService:Ljava/util/concurrent/ExecutorService;
       4: new           #32                 // class com/amazonaws/services/simpleemail/AmazonSimpleEmailServiceAsyncClient$5
       7: dup
       8: aload_0
       9: aload_1
      10: aload_2
      11: invokespecial #33                 // Method com/amazonaws/services/simpleemail/AmazonSimpleEmailServiceAsyncClient$5."<init>":(Lcom/amazonaws/services/simpleemail/AmazonSimpleEmailServiceAsyncClient;Lcom/amazonaws/services/simpleemail/model/DeleteIdentityRequest;Lcom/amazonaws/handlers/AsyncHandler;)V
      14: invokeinterface #21,  2           // InterfaceMethod java/util/concurrent/ExecutorService.submit:(Ljava/util/concurrent/Callable;)Ljava/util/concurrent/Future;
      19: areturn

  public java.util.concurrent.Future<com.amazonaws.services.simpleemail.model.DeleteIdentityPolicyResult> deleteIdentityPolicyAsync(com.amazonaws.services.simpleemail.model.DeleteIdentityPolicyRequest);
    Code:
       0: aload_0
       1: aload_1
       2: aconst_null
       3: invokevirtual #34                 // Method deleteIdentityPolicyAsync:(Lcom/amazonaws/services/simpleemail/model/DeleteIdentityPolicyRequest;Lcom/amazonaws/handlers/AsyncHandler;)Ljava/util/concurrent/Future;
       6: areturn

  public java.util.concurrent.Future<com.amazonaws.services.simpleemail.model.DeleteIdentityPolicyResult> deleteIdentityPolicyAsync(com.amazonaws.services.simpleemail.model.DeleteIdentityPolicyRequest, com.amazonaws.handlers.AsyncHandler<com.amazonaws.services.simpleemail.model.DeleteIdentityPolicyRequest, com.amazonaws.services.simpleemail.model.DeleteIdentityPolicyResult>);
    Code:
       0: aload_0
       1: getfield      #13                 // Field executorService:Ljava/util/concurrent/ExecutorService;
       4: new           #35                 // class com/amazonaws/services/simpleemail/AmazonSimpleEmailServiceAsyncClient$6
       7: dup
       8: aload_0
       9: aload_1
      10: aload_2
      11: invokespecial #36                 // Method com/amazonaws/services/simpleemail/AmazonSimpleEmailServiceAsyncClient$6."<init>":(Lcom/amazonaws/services/simpleemail/AmazonSimpleEmailServiceAsyncClient;Lcom/amazonaws/services/simpleemail/model/DeleteIdentityPolicyRequest;Lcom/amazonaws/handlers/AsyncHandler;)V
      14: invokeinterface #21,  2           // InterfaceMethod java/util/concurrent/ExecutorService.submit:(Ljava/util/concurrent/Callable;)Ljava/util/concurrent/Future;
      19: areturn

  public java.util.concurrent.Future<com.amazonaws.services.simpleemail.model.DeleteReceiptFilterResult> deleteReceiptFilterAsync(com.amazonaws.services.simpleemail.model.DeleteReceiptFilterRequest);
    Code:
       0: aload_0
       1: aload_1
       2: aconst_null
       3: invokevirtual #37                 // Method deleteReceiptFilterAsync:(Lcom/amazonaws/services/simpleemail/model/DeleteReceiptFilterRequest;Lcom/amazonaws/handlers/AsyncHandler;)Ljava/util/concurrent/Future;
       6: areturn

  public java.util.concurrent.Future<com.amazonaws.services.simpleemail.model.DeleteReceiptFilterResult> deleteReceiptFilterAsync(com.amazonaws.services.simpleemail.model.DeleteReceiptFilterRequest, com.amazonaws.handlers.AsyncHandler<com.amazonaws.services.simpleemail.model.DeleteReceiptFilterRequest, com.amazonaws.services.simpleemail.model.DeleteReceiptFilterResult>);
    Code:
       0: aload_0
       1: getfield      #13                 // Field executorService:Ljava/util/concurrent/ExecutorService;
       4: new           #38                 // class com/amazonaws/services/simpleemail/AmazonSimpleEmailServiceAsyncClient$7
       7: dup
       8: aload_0
       9: aload_1
      10: aload_2
      11: invokespecial #39                 // Method com/amazonaws/services/simpleemail/AmazonSimpleEmailServiceAsyncClient$7."<init>":(Lcom/amazonaws/services/simpleemail/AmazonSimpleEmailServiceAsyncClient;Lcom/amazonaws/services/simpleemail/model/DeleteReceiptFilterRequest;Lcom/amazonaws/handlers/AsyncHandler;)V
      14: invokeinterface #21,  2           // InterfaceMethod java/util/concurrent/ExecutorService.submit:(Ljava/util/concurrent/Callable;)Ljava/util/concurrent/Future;
      19: areturn

  public java.util.concurrent.Future<com.amazonaws.services.simpleemail.model.DeleteReceiptRuleResult> deleteReceiptRuleAsync(com.amazonaws.services.simpleemail.model.DeleteReceiptRuleRequest);
    Code:
       0: aload_0
       1: aload_1
       2: aconst_null
       3: invokevirtual #40                 // Method deleteReceiptRuleAsync:(Lcom/amazonaws/services/simpleemail/model/DeleteReceiptRuleRequest;Lcom/amazonaws/handlers/AsyncHandler;)Ljava/util/concurrent/Future;
       6: areturn

  public java.util.concurrent.Future<com.amazonaws.services.simpleemail.model.DeleteReceiptRuleResult> deleteReceiptRuleAsync(com.amazonaws.services.simpleemail.model.DeleteReceiptRuleRequest, com.amazonaws.handlers.AsyncHandler<com.amazonaws.services.simpleemail.model.DeleteReceiptRuleRequest, com.amazonaws.services.simpleemail.model.DeleteReceiptRuleResult>);
    Code:
       0: aload_0
       1: getfield      #13                 // Field executorService:Ljava/util/concurrent/ExecutorService;
       4: new           #41                 // class com/amazonaws/services/simpleemail/AmazonSimpleEmailServiceAsyncClient$8
       7: dup
       8: aload_0
       9: aload_1
      10: aload_2
      11: invokespecial #42                 // Method com/amazonaws/services/simpleemail/AmazonSimpleEmailServiceAsyncClient$8."<init>":(Lcom/amazonaws/services/simpleemail/AmazonSimpleEmailServiceAsyncClient;Lcom/amazonaws/services/simpleemail/model/DeleteReceiptRuleRequest;Lcom/amazonaws/handlers/AsyncHandler;)V
      14: invokeinterface #21,  2           // InterfaceMethod java/util/concurrent/ExecutorService.submit:(Ljava/util/concurrent/Callable;)Ljava/util/concurrent/Future;
      19: areturn

  public java.util.concurrent.Future<com.amazonaws.services.simpleemail.model.DeleteReceiptRuleSetResult> deleteReceiptRuleSetAsync(com.amazonaws.services.simpleemail.model.DeleteReceiptRuleSetRequest);
    Code:
       0: aload_0
       1: aload_1
       2: aconst_null
       3: invokevirtual #43                 // Method deleteReceiptRuleSetAsync:(Lcom/amazonaws/services/simpleemail/model/DeleteReceiptRuleSetRequest;Lcom/amazonaws/handlers/AsyncHandler;)Ljava/util/concurrent/Future;
       6: areturn

  public java.util.concurrent.Future<com.amazonaws.services.simpleemail.model.DeleteReceiptRuleSetResult> deleteReceiptRuleSetAsync(com.amazonaws.services.simpleemail.model.DeleteReceiptRuleSetRequest, com.amazonaws.handlers.AsyncHandler<com.amazonaws.services.simpleemail.model.DeleteReceiptRuleSetRequest, com.amazonaws.services.simpleemail.model.DeleteReceiptRuleSetResult>);
    Code:
       0: aload_0
       1: getfield      #13                 // Field executorService:Ljava/util/concurrent/ExecutorService;
       4: new           #44                 // class com/amazonaws/services/simpleemail/AmazonSimpleEmailServiceAsyncClient$9
       7: dup
       8: aload_0
       9: aload_1
      10: aload_2
      11: invokespecial #45                 // Method com/amazonaws/services/simpleemail/AmazonSimpleEmailServiceAsyncClient$9."<init>":(Lcom/amazonaws/services/simpleemail/AmazonSimpleEmailServiceAsyncClient;Lcom/amazonaws/services/simpleemail/model/DeleteReceiptRuleSetRequest;Lcom/amazonaws/handlers/AsyncHandler;)V
      14: invokeinterface #21,  2           // InterfaceMethod java/util/concurrent/ExecutorService.submit:(Ljava/util/concurrent/Callable;)Ljava/util/concurrent/Future;
      19: areturn

  public java.util.concurrent.Future<com.amazonaws.services.simpleemail.model.DeleteVerifiedEmailAddressResult> deleteVerifiedEmailAddressAsync(com.amazonaws.services.simpleemail.model.DeleteVerifiedEmailAddressRequest);
    Code:
       0: aload_0
       1: aload_1
       2: aconst_null
       3: invokevirtual #46                 // Method deleteVerifiedEmailAddressAsync:(Lcom/amazonaws/services/simpleemail/model/DeleteVerifiedEmailAddressRequest;Lcom/amazonaws/handlers/AsyncHandler;)Ljava/util/concurrent/Future;
       6: areturn

  public java.util.concurrent.Future<com.amazonaws.services.simpleemail.model.DeleteVerifiedEmailAddressResult> deleteVerifiedEmailAddressAsync(com.amazonaws.services.simpleemail.model.DeleteVerifiedEmailAddressRequest, com.amazonaws.handlers.AsyncHandler<com.amazonaws.services.simpleemail.model.DeleteVerifiedEmailAddressRequest, com.amazonaws.services.simpleemail.model.DeleteVerifiedEmailAddressResult>);
    Code:
       0: aload_0
       1: getfield      #13                 // Field executorService:Ljava/util/concurrent/ExecutorService;
       4: new           #47                 // class com/amazonaws/services/simpleemail/AmazonSimpleEmailServiceAsyncClient$10
       7: dup
       8: aload_0
       9: aload_1
      10: aload_2
      11: invokespecial #48                 // Method com/amazonaws/services/simpleemail/AmazonSimpleEmailServiceAsyncClient$10."<init>":(Lcom/amazonaws/services/simpleemail/AmazonSimpleEmailServiceAsyncClient;Lcom/amazonaws/services/simpleemail/model/DeleteVerifiedEmailAddressRequest;Lcom/amazonaws/handlers/AsyncHandler;)V
      14: invokeinterface #21,  2           // InterfaceMethod java/util/concurrent/ExecutorService.submit:(Ljava/util/concurrent/Callable;)Ljava/util/concurrent/Future;
      19: areturn

  public java.util.concurrent.Future<com.amazonaws.services.simpleemail.model.DescribeActiveReceiptRuleSetResult> describeActiveReceiptRuleSetAsync(com.amazonaws.services.simpleemail.model.DescribeActiveReceiptRuleSetRequest);
    Code:
       0: aload_0
       1: aload_1
       2: aconst_null
       3: invokevirtual #49                 // Method describeActiveReceiptRuleSetAsync:(Lcom/amazonaws/services/simpleemail/model/DescribeActiveReceiptRuleSetRequest;Lcom/amazonaws/handlers/AsyncHandler;)Ljava/util/concurrent/Future;
       6: areturn

  public java.util.concurrent.Future<com.amazonaws.services.simpleemail.model.DescribeActiveReceiptRuleSetResult> describeActiveReceiptRuleSetAsync(com.amazonaws.services.simpleemail.model.DescribeActiveReceiptRuleSetRequest, com.amazonaws.handlers.AsyncHandler<com.amazonaws.services.simpleemail.model.DescribeActiveReceiptRuleSetRequest, com.amazonaws.services.simpleemail.model.DescribeActiveReceiptRuleSetResult>);
    Code:
       0: aload_0
       1: getfield      #13                 // Field executorService:Ljava/util/concurrent/ExecutorService;
       4: new           #50                 // class com/amazonaws/services/simpleemail/AmazonSimpleEmailServiceAsyncClient$11
       7: dup
       8: aload_0
       9: aload_1
      10: aload_2
      11: invokespecial #51                 // Method com/amazonaws/services/simpleemail/AmazonSimpleEmailServiceAsyncClient$11."<init>":(Lcom/amazonaws/services/simpleemail/AmazonSimpleEmailServiceAsyncClient;Lcom/amazonaws/services/simpleemail/model/DescribeActiveReceiptRuleSetRequest;Lcom/amazonaws/handlers/AsyncHandler;)V
      14: invokeinterface #21,  2           // InterfaceMethod java/util/concurrent/ExecutorService.submit:(Ljava/util/concurrent/Callable;)Ljava/util/concurrent/Future;
      19: areturn

  public java.util.concurrent.Future<com.amazonaws.services.simpleemail.model.DescribeReceiptRuleResult> describeReceiptRuleAsync(com.amazonaws.services.simpleemail.model.DescribeReceiptRuleRequest);
    Code:
       0: aload_0
       1: aload_1
       2: aconst_null
       3: invokevirtual #52                 // Method describeReceiptRuleAsync:(Lcom/amazonaws/services/simpleemail/model/DescribeReceiptRuleRequest;Lcom/amazonaws/handlers/AsyncHandler;)Ljava/util/concurrent/Future;
       6: areturn

  public java.util.concurrent.Future<com.amazonaws.services.simpleemail.model.DescribeReceiptRuleResult> describeReceiptRuleAsync(com.amazonaws.services.simpleemail.model.DescribeReceiptRuleRequest, com.amazonaws.handlers.AsyncHandler<com.amazonaws.services.simpleemail.model.DescribeReceiptRuleRequest, com.amazonaws.services.simpleemail.model.DescribeReceiptRuleResult>);
    Code:
       0: aload_0
       1: getfield      #13                 // Field executorService:Ljava/util/concurrent/ExecutorService;
       4: new           #53                 // class com/amazonaws/services/simpleemail/AmazonSimpleEmailServiceAsyncClient$12
       7: dup
       8: aload_0
       9: aload_1
      10: aload_2
      11: invokespecial #54                 // Method com/amazonaws/services/simpleemail/AmazonSimpleEmailServiceAsyncClient$12."<init>":(Lcom/amazonaws/services/simpleemail/AmazonSimpleEmailServiceAsyncClient;Lcom/amazonaws/services/simpleemail/model/DescribeReceiptRuleRequest;Lcom/amazonaws/handlers/AsyncHandler;)V
      14: invokeinterface #21,  2           // InterfaceMethod java/util/concurrent/ExecutorService.submit:(Ljava/util/concurrent/Callable;)Ljava/util/concurrent/Future;
      19: areturn

  public java.util.concurrent.Future<com.amazonaws.services.simpleemail.model.DescribeReceiptRuleSetResult> describeReceiptRuleSetAsync(com.amazonaws.services.simpleemail.model.DescribeReceiptRuleSetRequest);
    Code:
       0: aload_0
       1: aload_1
       2: aconst_null
       3: invokevirtual #55                 // Method describeReceiptRuleSetAsync:(Lcom/amazonaws/services/simpleemail/model/DescribeReceiptRuleSetRequest;Lcom/amazonaws/handlers/AsyncHandler;)Ljava/util/concurrent/Future;
       6: areturn

  public java.util.concurrent.Future<com.amazonaws.services.simpleemail.model.DescribeReceiptRuleSetResult> describeReceiptRuleSetAsync(com.amazonaws.services.simpleemail.model.DescribeReceiptRuleSetRequest, com.amazonaws.handlers.AsyncHandler<com.amazonaws.services.simpleemail.model.DescribeReceiptRuleSetRequest, com.amazonaws.services.simpleemail.model.DescribeReceiptRuleSetResult>);
    Code:
       0: aload_0
       1: getfield      #13                 // Field executorService:Ljava/util/concurrent/ExecutorService;
       4: new           #56                 // class com/amazonaws/services/simpleemail/AmazonSimpleEmailServiceAsyncClient$13
       7: dup
       8: aload_0
       9: aload_1
      10: aload_2
      11: invokespecial #57                 // Method com/amazonaws/services/simpleemail/AmazonSimpleEmailServiceAsyncClient$13."<init>":(Lcom/amazonaws/services/simpleemail/AmazonSimpleEmailServiceAsyncClient;Lcom/amazonaws/services/simpleemail/model/DescribeReceiptRuleSetRequest;Lcom/amazonaws/handlers/AsyncHandler;)V
      14: invokeinterface #21,  2           // InterfaceMethod java/util/concurrent/ExecutorService.submit:(Ljava/util/concurrent/Callable;)Ljava/util/concurrent/Future;
      19: areturn

  public java.util.concurrent.Future<com.amazonaws.services.simpleemail.model.GetIdentityDkimAttributesResult> getIdentityDkimAttributesAsync(com.amazonaws.services.simpleemail.model.GetIdentityDkimAttributesRequest);
    Code:
       0: aload_0
       1: aload_1
       2: aconst_null
       3: invokevirtual #58                 // Method getIdentityDkimAttributesAsync:(Lcom/amazonaws/services/simpleemail/model/GetIdentityDkimAttributesRequest;Lcom/amazonaws/handlers/AsyncHandler;)Ljava/util/concurrent/Future;
       6: areturn

  public java.util.concurrent.Future<com.amazonaws.services.simpleemail.model.GetIdentityDkimAttributesResult> getIdentityDkimAttributesAsync(com.amazonaws.services.simpleemail.model.GetIdentityDkimAttributesRequest, com.amazonaws.handlers.AsyncHandler<com.amazonaws.services.simpleemail.model.GetIdentityDkimAttributesRequest, com.amazonaws.services.simpleemail.model.GetIdentityDkimAttributesResult>);
    Code:
       0: aload_0
       1: getfield      #13                 // Field executorService:Ljava/util/concurrent/ExecutorService;
       4: new           #59                 // class com/amazonaws/services/simpleemail/AmazonSimpleEmailServiceAsyncClient$14
       7: dup
       8: aload_0
       9: aload_1
      10: aload_2
      11: invokespecial #60                 // Method com/amazonaws/services/simpleemail/AmazonSimpleEmailServiceAsyncClient$14."<init>":(Lcom/amazonaws/services/simpleemail/AmazonSimpleEmailServiceAsyncClient;Lcom/amazonaws/services/simpleemail/model/GetIdentityDkimAttributesRequest;Lcom/amazonaws/handlers/AsyncHandler;)V
      14: invokeinterface #21,  2           // InterfaceMethod java/util/concurrent/ExecutorService.submit:(Ljava/util/concurrent/Callable;)Ljava/util/concurrent/Future;
      19: areturn

  public java.util.concurrent.Future<com.amazonaws.services.simpleemail.model.GetIdentityMailFromDomainAttributesResult> getIdentityMailFromDomainAttributesAsync(com.amazonaws.services.simpleemail.model.GetIdentityMailFromDomainAttributesRequest);
    Code:
       0: aload_0
       1: aload_1
       2: aconst_null
       3: invokevirtual #61                 // Method getIdentityMailFromDomainAttributesAsync:(Lcom/amazonaws/services/simpleemail/model/GetIdentityMailFromDomainAttributesRequest;Lcom/amazonaws/handlers/AsyncHandler;)Ljava/util/concurrent/Future;
       6: areturn

  public java.util.concurrent.Future<com.amazonaws.services.simpleemail.model.GetIdentityMailFromDomainAttributesResult> getIdentityMailFromDomainAttributesAsync(com.amazonaws.services.simpleemail.model.GetIdentityMailFromDomainAttributesRequest, com.amazonaws.handlers.AsyncHandler<com.amazonaws.services.simpleemail.model.GetIdentityMailFromDomainAttributesRequest, com.amazonaws.services.simpleemail.model.GetIdentityMailFromDomainAttributesResult>);
    Code:
       0: aload_0
       1: getfield      #13                 // Field executorService:Ljava/util/concurrent/ExecutorService;
       4: new           #62                 // class com/amazonaws/services/simpleemail/AmazonSimpleEmailServiceAsyncClient$15
       7: dup
       8: aload_0
       9: aload_1
      10: aload_2
      11: invokespecial #63                 // Method com/amazonaws/services/simpleemail/AmazonSimpleEmailServiceAsyncClient$15."<init>":(Lcom/amazonaws/services/simpleemail/AmazonSimpleEmailServiceAsyncClient;Lcom/amazonaws/services/simpleemail/model/GetIdentityMailFromDomainAttributesRequest;Lcom/amazonaws/handlers/AsyncHandler;)V
      14: invokeinterface #21,  2           // InterfaceMethod java/util/concurrent/ExecutorService.submit:(Ljava/util/concurrent/Callable;)Ljava/util/concurrent/Future;
      19: areturn

  public java.util.concurrent.Future<com.amazonaws.services.simpleemail.model.GetIdentityNotificationAttributesResult> getIdentityNotificationAttributesAsync(com.amazonaws.services.simpleemail.model.GetIdentityNotificationAttributesRequest);
    Code:
       0: aload_0
       1: aload_1
       2: aconst_null
       3: invokevirtual #64                 // Method getIdentityNotificationAttributesAsync:(Lcom/amazonaws/services/simpleemail/model/GetIdentityNotificationAttributesRequest;Lcom/amazonaws/handlers/AsyncHandler;)Ljava/util/concurrent/Future;
       6: areturn

  public java.util.concurrent.Future<com.amazonaws.services.simpleemail.model.GetIdentityNotificationAttributesResult> getIdentityNotificationAttributesAsync(com.amazonaws.services.simpleemail.model.GetIdentityNotificationAttributesRequest, com.amazonaws.handlers.AsyncHandler<com.amazonaws.services.simpleemail.model.GetIdentityNotificationAttributesRequest, com.amazonaws.services.simpleemail.model.GetIdentityNotificationAttributesResult>);
    Code:
       0: aload_0
       1: getfield      #13                 // Field executorService:Ljava/util/concurrent/ExecutorService;
       4: new           #65                 // class com/amazonaws/services/simpleemail/AmazonSimpleEmailServiceAsyncClient$16
       7: dup
       8: aload_0
       9: aload_1
      10: aload_2
      11: invokespecial #66                 // Method com/amazonaws/services/simpleemail/AmazonSimpleEmailServiceAsyncClient$16."<init>":(Lcom/amazonaws/services/simpleemail/AmazonSimpleEmailServiceAsyncClient;Lcom/amazonaws/services/simpleemail/model/GetIdentityNotificationAttributesRequest;Lcom/amazonaws/handlers/AsyncHandler;)V
      14: invokeinterface #21,  2           // InterfaceMethod java/util/concurrent/ExecutorService.submit:(Ljava/util/concurrent/Callable;)Ljava/util/concurrent/Future;
      19: areturn

  public java.util.concurrent.Future<com.amazonaws.services.simpleemail.model.GetIdentityPoliciesResult> getIdentityPoliciesAsync(com.amazonaws.services.simpleemail.model.GetIdentityPoliciesRequest);
    Code:
       0: aload_0
       1: aload_1
       2: aconst_null
       3: invokevirtual #67                 // Method getIdentityPoliciesAsync:(Lcom/amazonaws/services/simpleemail/model/GetIdentityPoliciesRequest;Lcom/amazonaws/handlers/AsyncHandler;)Ljava/util/concurrent/Future;
       6: areturn

  public java.util.concurrent.Future<com.amazonaws.services.simpleemail.model.GetIdentityPoliciesResult> getIdentityPoliciesAsync(com.amazonaws.services.simpleemail.model.GetIdentityPoliciesRequest, com.amazonaws.handlers.AsyncHandler<com.amazonaws.services.simpleemail.model.GetIdentityPoliciesRequest, com.amazonaws.services.simpleemail.model.GetIdentityPoliciesResult>);
    Code:
       0: aload_0
       1: getfield      #13                 // Field executorService:Ljava/util/concurrent/ExecutorService;
       4: new           #68                 // class com/amazonaws/services/simpleemail/AmazonSimpleEmailServiceAsyncClient$17
       7: dup
       8: aload_0
       9: aload_1
      10: aload_2
      11: invokespecial #69                 // Method com/amazonaws/services/simpleemail/AmazonSimpleEmailServiceAsyncClient$17."<init>":(Lcom/amazonaws/services/simpleemail/AmazonSimpleEmailServiceAsyncClient;Lcom/amazonaws/services/simpleemail/model/GetIdentityPoliciesRequest;Lcom/amazonaws/handlers/AsyncHandler;)V
      14: invokeinterface #21,  2           // InterfaceMethod java/util/concurrent/ExecutorService.submit:(Ljava/util/concurrent/Callable;)Ljava/util/concurrent/Future;
      19: areturn

  public java.util.concurrent.Future<com.amazonaws.services.simpleemail.model.GetIdentityVerificationAttributesResult> getIdentityVerificationAttributesAsync(com.amazonaws.services.simpleemail.model.GetIdentityVerificationAttributesRequest);
    Code:
       0: aload_0
       1: aload_1
       2: aconst_null
       3: invokevirtual #70                 // Method getIdentityVerificationAttributesAsync:(Lcom/amazonaws/services/simpleemail/model/GetIdentityVerificationAttributesRequest;Lcom/amazonaws/handlers/AsyncHandler;)Ljava/util/concurrent/Future;
       6: areturn

  public java.util.concurrent.Future<com.amazonaws.services.simpleemail.model.GetIdentityVerificationAttributesResult> getIdentityVerificationAttributesAsync(com.amazonaws.services.simpleemail.model.GetIdentityVerificationAttributesRequest, com.amazonaws.handlers.AsyncHandler<com.amazonaws.services.simpleemail.model.GetIdentityVerificationAttributesRequest, com.amazonaws.services.simpleemail.model.GetIdentityVerificationAttributesResult>);
    Code:
       0: aload_0
       1: getfield      #13                 // Field executorService:Ljava/util/concurrent/ExecutorService;
       4: new           #71                 // class com/amazonaws/services/simpleemail/AmazonSimpleEmailServiceAsyncClient$18
       7: dup
       8: aload_0
       9: aload_1
      10: aload_2
      11: invokespecial #72                 // Method com/amazonaws/services/simpleemail/AmazonSimpleEmailServiceAsyncClient$18."<init>":(Lcom/amazonaws/services/simpleemail/AmazonSimpleEmailServiceAsyncClient;Lcom/amazonaws/services/simpleemail/model/GetIdentityVerificationAttributesRequest;Lcom/amazonaws/handlers/AsyncHandler;)V
      14: invokeinterface #21,  2           // InterfaceMethod java/util/concurrent/ExecutorService.submit:(Ljava/util/concurrent/Callable;)Ljava/util/concurrent/Future;
      19: areturn

  public java.util.concurrent.Future<com.amazonaws.services.simpleemail.model.GetSendQuotaResult> getSendQuotaAsync(com.amazonaws.services.simpleemail.model.GetSendQuotaRequest);
    Code:
       0: aload_0
       1: aload_1
       2: aconst_null
       3: invokevirtual #73                 // Method getSendQuotaAsync:(Lcom/amazonaws/services/simpleemail/model/GetSendQuotaRequest;Lcom/amazonaws/handlers/AsyncHandler;)Ljava/util/concurrent/Future;
       6: areturn

  public java.util.concurrent.Future<com.amazonaws.services.simpleemail.model.GetSendQuotaResult> getSendQuotaAsync(com.amazonaws.services.simpleemail.model.GetSendQuotaRequest, com.amazonaws.handlers.AsyncHandler<com.amazonaws.services.simpleemail.model.GetSendQuotaRequest, com.amazonaws.services.simpleemail.model.GetSendQuotaResult>);
    Code:
       0: aload_0
       1: getfield      #13                 // Field executorService:Ljava/util/concurrent/ExecutorService;
       4: new           #74                 // class com/amazonaws/services/simpleemail/AmazonSimpleEmailServiceAsyncClient$19
       7: dup
       8: aload_0
       9: aload_1
      10: aload_2
      11: invokespecial #75                 // Method com/amazonaws/services/simpleemail/AmazonSimpleEmailServiceAsyncClient$19."<init>":(Lcom/amazonaws/services/simpleemail/AmazonSimpleEmailServiceAsyncClient;Lcom/amazonaws/services/simpleemail/model/GetSendQuotaRequest;Lcom/amazonaws/handlers/AsyncHandler;)V
      14: invokeinterface #21,  2           // InterfaceMethod java/util/concurrent/ExecutorService.submit:(Ljava/util/concurrent/Callable;)Ljava/util/concurrent/Future;
      19: areturn

  public java.util.concurrent.Future<com.amazonaws.services.simpleemail.model.GetSendQuotaResult> getSendQuotaAsync();
    Code:
       0: aload_0
       1: new           #76                 // class com/amazonaws/services/simpleemail/model/GetSendQuotaRequest
       4: dup
       5: invokespecial #77                 // Method com/amazonaws/services/simpleemail/model/GetSendQuotaRequest."<init>":()V
       8: invokevirtual #78                 // Method getSendQuotaAsync:(Lcom/amazonaws/services/simpleemail/model/GetSendQuotaRequest;)Ljava/util/concurrent/Future;
      11: areturn

  public java.util.concurrent.Future<com.amazonaws.services.simpleemail.model.GetSendQuotaResult> getSendQuotaAsync(com.amazonaws.handlers.AsyncHandler<com.amazonaws.services.simpleemail.model.GetSendQuotaRequest, com.amazonaws.services.simpleemail.model.GetSendQuotaResult>);
    Code:
       0: aload_0
       1: new           #76                 // class com/amazonaws/services/simpleemail/model/GetSendQuotaRequest
       4: dup
       5: invokespecial #77                 // Method com/amazonaws/services/simpleemail/model/GetSendQuotaRequest."<init>":()V
       8: aload_1
       9: invokevirtual #73                 // Method getSendQuotaAsync:(Lcom/amazonaws/services/simpleemail/model/GetSendQuotaRequest;Lcom/amazonaws/handlers/AsyncHandler;)Ljava/util/concurrent/Future;
      12: areturn

  public java.util.concurrent.Future<com.amazonaws.services.simpleemail.model.GetSendStatisticsResult> getSendStatisticsAsync(com.amazonaws.services.simpleemail.model.GetSendStatisticsRequest);
    Code:
       0: aload_0
       1: aload_1
       2: aconst_null
       3: invokevirtual #79                 // Method getSendStatisticsAsync:(Lcom/amazonaws/services/simpleemail/model/GetSendStatisticsRequest;Lcom/amazonaws/handlers/AsyncHandler;)Ljava/util/concurrent/Future;
       6: areturn

  public java.util.concurrent.Future<com.amazonaws.services.simpleemail.model.GetSendStatisticsResult> getSendStatisticsAsync(com.amazonaws.services.simpleemail.model.GetSendStatisticsRequest, com.amazonaws.handlers.AsyncHandler<com.amazonaws.services.simpleemail.model.GetSendStatisticsRequest, com.amazonaws.services.simpleemail.model.GetSendStatisticsResult>);
    Code:
       0: aload_0
       1: getfield      #13                 // Field executorService:Ljava/util/concurrent/ExecutorService;
       4: new           #80                 // class com/amazonaws/services/simpleemail/AmazonSimpleEmailServiceAsyncClient$20
       7: dup
       8: aload_0
       9: aload_1
      10: aload_2
      11: invokespecial #81                 // Method com/amazonaws/services/simpleemail/AmazonSimpleEmailServiceAsyncClient$20."<init>":(Lcom/amazonaws/services/simpleemail/AmazonSimpleEmailServiceAsyncClient;Lcom/amazonaws/services/simpleemail/model/GetSendStatisticsRequest;Lcom/amazonaws/handlers/AsyncHandler;)V
      14: invokeinterface #21,  2           // InterfaceMethod java/util/concurrent/ExecutorService.submit:(Ljava/util/concurrent/Callable;)Ljava/util/concurrent/Future;
      19: areturn

  public java.util.concurrent.Future<com.amazonaws.services.simpleemail.model.GetSendStatisticsResult> getSendStatisticsAsync();
    Code:
       0: aload_0
       1: new           #82                 // class com/amazonaws/services/simpleemail/model/GetSendStatisticsRequest
       4: dup
       5: invokespecial #83                 // Method com/amazonaws/services/simpleemail/model/GetSendStatisticsRequest."<init>":()V
       8: invokevirtual #84                 // Method getSendStatisticsAsync:(Lcom/amazonaws/services/simpleemail/model/GetSendStatisticsRequest;)Ljava/util/concurrent/Future;
      11: areturn

  public java.util.concurrent.Future<com.amazonaws.services.simpleemail.model.GetSendStatisticsResult> getSendStatisticsAsync(com.amazonaws.handlers.AsyncHandler<com.amazonaws.services.simpleemail.model.GetSendStatisticsRequest, com.amazonaws.services.simpleemail.model.GetSendStatisticsResult>);
    Code:
       0: aload_0
       1: new           #82                 // class com/amazonaws/services/simpleemail/model/GetSendStatisticsRequest
       4: dup
       5: invokespecial #83                 // Method com/amazonaws/services/simpleemail/model/GetSendStatisticsRequest."<init>":()V
       8: aload_1
       9: invokevirtual #79                 // Method getSendStatisticsAsync:(Lcom/amazonaws/services/simpleemail/model/GetSendStatisticsRequest;Lcom/amazonaws/handlers/AsyncHandler;)Ljava/util/concurrent/Future;
      12: areturn

  public java.util.concurrent.Future<com.amazonaws.services.simpleemail.model.ListIdentitiesResult> listIdentitiesAsync(com.amazonaws.services.simpleemail.model.ListIdentitiesRequest);
    Code:
       0: aload_0
       1: aload_1
       2: aconst_null
       3: invokevirtual #85                 // Method listIdentitiesAsync:(Lcom/amazonaws/services/simpleemail/model/ListIdentitiesRequest;Lcom/amazonaws/handlers/AsyncHandler;)Ljava/util/concurrent/Future;
       6: areturn

  public java.util.concurrent.Future<com.amazonaws.services.simpleemail.model.ListIdentitiesResult> listIdentitiesAsync(com.amazonaws.services.simpleemail.model.ListIdentitiesRequest, com.amazonaws.handlers.AsyncHandler<com.amazonaws.services.simpleemail.model.ListIdentitiesRequest, com.amazonaws.services.simpleemail.model.ListIdentitiesResult>);
    Code:
       0: aload_0
       1: getfield      #13                 // Field executorService:Ljava/util/concurrent/ExecutorService;
       4: new           #86                 // class com/amazonaws/services/simpleemail/AmazonSimpleEmailServiceAsyncClient$21
       7: dup
       8: aload_0
       9: aload_1
      10: aload_2
      11: invokespecial #87                 // Method com/amazonaws/services/simpleemail/AmazonSimpleEmailServiceAsyncClient$21."<init>":(Lcom/amazonaws/services/simpleemail/AmazonSimpleEmailServiceAsyncClient;Lcom/amazonaws/services/simpleemail/model/ListIdentitiesRequest;Lcom/amazonaws/handlers/AsyncHandler;)V
      14: invokeinterface #21,  2           // InterfaceMethod java/util/concurrent/ExecutorService.submit:(Ljava/util/concurrent/Callable;)Ljava/util/concurrent/Future;
      19: areturn

  public java.util.concurrent.Future<com.amazonaws.services.simpleemail.model.ListIdentitiesResult> listIdentitiesAsync();
    Code:
       0: aload_0
       1: new           #88                 // class com/amazonaws/services/simpleemail/model/ListIdentitiesRequest
       4: dup
       5: invokespecial #89                 // Method com/amazonaws/services/simpleemail/model/ListIdentitiesRequest."<init>":()V
       8: invokevirtual #90                 // Method listIdentitiesAsync:(Lcom/amazonaws/services/simpleemail/model/ListIdentitiesRequest;)Ljava/util/concurrent/Future;
      11: areturn

  public java.util.concurrent.Future<com.amazonaws.services.simpleemail.model.ListIdentitiesResult> listIdentitiesAsync(com.amazonaws.handlers.AsyncHandler<com.amazonaws.services.simpleemail.model.ListIdentitiesRequest, com.amazonaws.services.simpleemail.model.ListIdentitiesResult>);
    Code:
       0: aload_0
       1: new           #88                 // class com/amazonaws/services/simpleemail/model/ListIdentitiesRequest
       4: dup
       5: invokespecial #89                 // Method com/amazonaws/services/simpleemail/model/ListIdentitiesRequest."<init>":()V
       8: aload_1
       9: invokevirtual #85                 // Method listIdentitiesAsync:(Lcom/amazonaws/services/simpleemail/model/ListIdentitiesRequest;Lcom/amazonaws/handlers/AsyncHandler;)Ljava/util/concurrent/Future;
      12: areturn

  public java.util.concurrent.Future<com.amazonaws.services.simpleemail.model.ListIdentityPoliciesResult> listIdentityPoliciesAsync(com.amazonaws.services.simpleemail.model.ListIdentityPoliciesRequest);
    Code:
       0: aload_0
       1: aload_1
       2: aconst_null
       3: invokevirtual #91                 // Method listIdentityPoliciesAsync:(Lcom/amazonaws/services/simpleemail/model/ListIdentityPoliciesRequest;Lcom/amazonaws/handlers/AsyncHandler;)Ljava/util/concurrent/Future;
       6: areturn

  public java.util.concurrent.Future<com.amazonaws.services.simpleemail.model.ListIdentityPoliciesResult> listIdentityPoliciesAsync(com.amazonaws.services.simpleemail.model.ListIdentityPoliciesRequest, com.amazonaws.handlers.AsyncHandler<com.amazonaws.services.simpleemail.model.ListIdentityPoliciesRequest, com.amazonaws.services.simpleemail.model.ListIdentityPoliciesResult>);
    Code:
       0: aload_0
       1: getfield      #13                 // Field executorService:Ljava/util/concurrent/ExecutorService;
       4: new           #92                 // class com/amazonaws/services/simpleemail/AmazonSimpleEmailServiceAsyncClient$22
       7: dup
       8: aload_0
       9: aload_1
      10: aload_2
      11: invokespecial #93                 // Method com/amazonaws/services/simpleemail/AmazonSimpleEmailServiceAsyncClient$22."<init>":(Lcom/amazonaws/services/simpleemail/AmazonSimpleEmailServiceAsyncClient;Lcom/amazonaws/services/simpleemail/model/ListIdentityPoliciesRequest;Lcom/amazonaws/handlers/AsyncHandler;)V
      14: invokeinterface #21,  2           // InterfaceMethod java/util/concurrent/ExecutorService.submit:(Ljava/util/concurrent/Callable;)Ljava/util/concurrent/Future;
      19: areturn

  public java.util.concurrent.Future<com.amazonaws.services.simpleemail.model.ListReceiptFiltersResult> listReceiptFiltersAsync(com.amazonaws.services.simpleemail.model.ListReceiptFiltersRequest);
    Code:
       0: aload_0
       1: aload_1
       2: aconst_null
       3: invokevirtual #94                 // Method listReceiptFiltersAsync:(Lcom/amazonaws/services/simpleemail/model/ListReceiptFiltersRequest;Lcom/amazonaws/handlers/AsyncHandler;)Ljava/util/concurrent/Future;
       6: areturn

  public java.util.concurrent.Future<com.amazonaws.services.simpleemail.model.ListReceiptFiltersResult> listReceiptFiltersAsync(com.amazonaws.services.simpleemail.model.ListReceiptFiltersRequest, com.amazonaws.handlers.AsyncHandler<com.amazonaws.services.simpleemail.model.ListReceiptFiltersRequest, com.amazonaws.services.simpleemail.model.ListReceiptFiltersResult>);
    Code:
       0: aload_0
       1: getfield      #13                 // Field executorService:Ljava/util/concurrent/ExecutorService;
       4: new           #95                 // class com/amazonaws/services/simpleemail/AmazonSimpleEmailServiceAsyncClient$23
       7: dup
       8: aload_0
       9: aload_1
      10: aload_2
      11: invokespecial #96                 // Method com/amazonaws/services/simpleemail/AmazonSimpleEmailServiceAsyncClient$23."<init>":(Lcom/amazonaws/services/simpleemail/AmazonSimpleEmailServiceAsyncClient;Lcom/amazonaws/services/simpleemail/model/ListReceiptFiltersRequest;Lcom/amazonaws/handlers/AsyncHandler;)V
      14: invokeinterface #21,  2           // InterfaceMethod java/util/concurrent/ExecutorService.submit:(Ljava/util/concurrent/Callable;)Ljava/util/concurrent/Future;
      19: areturn

  public java.util.concurrent.Future<com.amazonaws.services.simpleemail.model.ListReceiptRuleSetsResult> listReceiptRuleSetsAsync(com.amazonaws.services.simpleemail.model.ListReceiptRuleSetsRequest);
    Code:
       0: aload_0
       1: aload_1
       2: aconst_null
       3: invokevirtual #97                 // Method listReceiptRuleSetsAsync:(Lcom/amazonaws/services/simpleemail/model/ListReceiptRuleSetsRequest;Lcom/amazonaws/handlers/AsyncHandler;)Ljava/util/concurrent/Future;
       6: areturn

  public java.util.concurrent.Future<com.amazonaws.services.simpleemail.model.ListReceiptRuleSetsResult> listReceiptRuleSetsAsync(com.amazonaws.services.simpleemail.model.ListReceiptRuleSetsRequest, com.amazonaws.handlers.AsyncHandler<com.amazonaws.services.simpleemail.model.ListReceiptRuleSetsRequest, com.amazonaws.services.simpleemail.model.ListReceiptRuleSetsResult>);
    Code:
       0: aload_0
       1: getfield      #13                 // Field executorService:Ljava/util/concurrent/ExecutorService;
       4: new           #98                 // class com/amazonaws/services/simpleemail/AmazonSimpleEmailServiceAsyncClient$24
       7: dup
       8: aload_0
       9: aload_1
      10: aload_2
      11: invokespecial #99                 // Method com/amazonaws/services/simpleemail/AmazonSimpleEmailServiceAsyncClient$24."<init>":(Lcom/amazonaws/services/simpleemail/AmazonSimpleEmailServiceAsyncClient;Lcom/amazonaws/services/simpleemail/model/ListReceiptRuleSetsRequest;Lcom/amazonaws/handlers/AsyncHandler;)V
      14: invokeinterface #21,  2           // InterfaceMethod java/util/concurrent/ExecutorService.submit:(Ljava/util/concurrent/Callable;)Ljava/util/concurrent/Future;
      19: areturn

  public java.util.concurrent.Future<com.amazonaws.services.simpleemail.model.ListVerifiedEmailAddressesResult> listVerifiedEmailAddressesAsync(com.amazonaws.services.simpleemail.model.ListVerifiedEmailAddressesRequest);
    Code:
       0: aload_0
       1: aload_1
       2: aconst_null
       3: invokevirtual #100                // Method listVerifiedEmailAddressesAsync:(Lcom/amazonaws/services/simpleemail/model/ListVerifiedEmailAddressesRequest;Lcom/amazonaws/handlers/AsyncHandler;)Ljava/util/concurrent/Future;
       6: areturn

  public java.util.concurrent.Future<com.amazonaws.services.simpleemail.model.ListVerifiedEmailAddressesResult> listVerifiedEmailAddressesAsync(com.amazonaws.services.simpleemail.model.ListVerifiedEmailAddressesRequest, com.amazonaws.handlers.AsyncHandler<com.amazonaws.services.simpleemail.model.ListVerifiedEmailAddressesRequest, com.amazonaws.services.simpleemail.model.ListVerifiedEmailAddressesResult>);
    Code:
       0: aload_0
       1: getfield      #13                 // Field executorService:Ljava/util/concurrent/ExecutorService;
       4: new           #101                // class com/amazonaws/services/simpleemail/AmazonSimpleEmailServiceAsyncClient$25
       7: dup
       8: aload_0
       9: aload_1
      10: aload_2
      11: invokespecial #102                // Method com/amazonaws/services/simpleemail/AmazonSimpleEmailServiceAsyncClient$25."<init>":(Lcom/amazonaws/services/simpleemail/AmazonSimpleEmailServiceAsyncClient;Lcom/amazonaws/services/simpleemail/model/ListVerifiedEmailAddressesRequest;Lcom/amazonaws/handlers/AsyncHandler;)V
      14: invokeinterface #21,  2           // InterfaceMethod java/util/concurrent/ExecutorService.submit:(Ljava/util/concurrent/Callable;)Ljava/util/concurrent/Future;
      19: areturn

  public java.util.concurrent.Future<com.amazonaws.services.simpleemail.model.ListVerifiedEmailAddressesResult> listVerifiedEmailAddressesAsync();
    Code:
       0: aload_0
       1: new           #103                // class com/amazonaws/services/simpleemail/model/ListVerifiedEmailAddressesRequest
       4: dup
       5: invokespecial #104                // Method com/amazonaws/services/simpleemail/model/ListVerifiedEmailAddressesRequest."<init>":()V
       8: invokevirtual #105                // Method listVerifiedEmailAddressesAsync:(Lcom/amazonaws/services/simpleemail/model/ListVerifiedEmailAddressesRequest;)Ljava/util/concurrent/Future;
      11: areturn

  public java.util.concurrent.Future<com.amazonaws.services.simpleemail.model.ListVerifiedEmailAddressesResult> listVerifiedEmailAddressesAsync(com.amazonaws.handlers.AsyncHandler<com.amazonaws.services.simpleemail.model.ListVerifiedEmailAddressesRequest, com.amazonaws.services.simpleemail.model.ListVerifiedEmailAddressesResult>);
    Code:
       0: aload_0
       1: new           #103                // class com/amazonaws/services/simpleemail/model/ListVerifiedEmailAddressesRequest
       4: dup
       5: invokespecial #104                // Method com/amazonaws/services/simpleemail/model/ListVerifiedEmailAddressesRequest."<init>":()V
       8: aload_1
       9: invokevirtual #100                // Method listVerifiedEmailAddressesAsync:(Lcom/amazonaws/services/simpleemail/model/ListVerifiedEmailAddressesRequest;Lcom/amazonaws/handlers/AsyncHandler;)Ljava/util/concurrent/Future;
      12: areturn

  public java.util.concurrent.Future<com.amazonaws.services.simpleemail.model.PutIdentityPolicyResult> putIdentityPolicyAsync(com.amazonaws.services.simpleemail.model.PutIdentityPolicyRequest);
    Code:
       0: aload_0
       1: aload_1
       2: aconst_null
       3: invokevirtual #106                // Method putIdentityPolicyAsync:(Lcom/amazonaws/services/simpleemail/model/PutIdentityPolicyRequest;Lcom/amazonaws/handlers/AsyncHandler;)Ljava/util/concurrent/Future;
       6: areturn

  public java.util.concurrent.Future<com.amazonaws.services.simpleemail.model.PutIdentityPolicyResult> putIdentityPolicyAsync(com.amazonaws.services.simpleemail.model.PutIdentityPolicyRequest, com.amazonaws.handlers.AsyncHandler<com.amazonaws.services.simpleemail.model.PutIdentityPolicyRequest, com.amazonaws.services.simpleemail.model.PutIdentityPolicyResult>);
    Code:
       0: aload_0
       1: getfield      #13                 // Field executorService:Ljava/util/concurrent/ExecutorService;
       4: new           #107                // class com/amazonaws/services/simpleemail/AmazonSimpleEmailServiceAsyncClient$26
       7: dup
       8: aload_0
       9: aload_1
      10: aload_2
      11: invokespecial #108                // Method com/amazonaws/services/simpleemail/AmazonSimpleEmailServiceAsyncClient$26."<init>":(Lcom/amazonaws/services/simpleemail/AmazonSimpleEmailServiceAsyncClient;Lcom/amazonaws/services/simpleemail/model/PutIdentityPolicyRequest;Lcom/amazonaws/handlers/AsyncHandler;)V
      14: invokeinterface #21,  2           // InterfaceMethod java/util/concurrent/ExecutorService.submit:(Ljava/util/concurrent/Callable;)Ljava/util/concurrent/Future;
      19: areturn

  public java.util.concurrent.Future<com.amazonaws.services.simpleemail.model.ReorderReceiptRuleSetResult> reorderReceiptRuleSetAsync(com.amazonaws.services.simpleemail.model.ReorderReceiptRuleSetRequest);
    Code:
       0: aload_0
       1: aload_1
       2: aconst_null
       3: invokevirtual #109                // Method reorderReceiptRuleSetAsync:(Lcom/amazonaws/services/simpleemail/model/ReorderReceiptRuleSetRequest;Lcom/amazonaws/handlers/AsyncHandler;)Ljava/util/concurrent/Future;
       6: areturn

  public java.util.concurrent.Future<com.amazonaws.services.simpleemail.model.ReorderReceiptRuleSetResult> reorderReceiptRuleSetAsync(com.amazonaws.services.simpleemail.model.ReorderReceiptRuleSetRequest, com.amazonaws.handlers.AsyncHandler<com.amazonaws.services.simpleemail.model.ReorderReceiptRuleSetRequest, com.amazonaws.services.simpleemail.model.ReorderReceiptRuleSetResult>);
    Code:
       0: aload_0
       1: getfield      #13                 // Field executorService:Ljava/util/concurrent/ExecutorService;
       4: new           #110                // class com/amazonaws/services/simpleemail/AmazonSimpleEmailServiceAsyncClient$27
       7: dup
       8: aload_0
       9: aload_1
      10: aload_2
      11: invokespecial #111                // Method com/amazonaws/services/simpleemail/AmazonSimpleEmailServiceAsyncClient$27."<init>":(Lcom/amazonaws/services/simpleemail/AmazonSimpleEmailServiceAsyncClient;Lcom/amazonaws/services/simpleemail/model/ReorderReceiptRuleSetRequest;Lcom/amazonaws/handlers/AsyncHandler;)V
      14: invokeinterface #21,  2           // InterfaceMethod java/util/concurrent/ExecutorService.submit:(Ljava/util/concurrent/Callable;)Ljava/util/concurrent/Future;
      19: areturn

  public java.util.concurrent.Future<com.amazonaws.services.simpleemail.model.SendBounceResult> sendBounceAsync(com.amazonaws.services.simpleemail.model.SendBounceRequest);
    Code:
       0: aload_0
       1: aload_1
       2: aconst_null
       3: invokevirtual #112                // Method sendBounceAsync:(Lcom/amazonaws/services/simpleemail/model/SendBounceRequest;Lcom/amazonaws/handlers/AsyncHandler;)Ljava/util/concurrent/Future;
       6: areturn

  public java.util.concurrent.Future<com.amazonaws.services.simpleemail.model.SendBounceResult> sendBounceAsync(com.amazonaws.services.simpleemail.model.SendBounceRequest, com.amazonaws.handlers.AsyncHandler<com.amazonaws.services.simpleemail.model.SendBounceRequest, com.amazonaws.services.simpleemail.model.SendBounceResult>);
    Code:
       0: aload_0
       1: getfield      #13                 // Field executorService:Ljava/util/concurrent/ExecutorService;
       4: new           #113                // class com/amazonaws/services/simpleemail/AmazonSimpleEmailServiceAsyncClient$28
       7: dup
       8: aload_0
       9: aload_1
      10: aload_2
      11: invokespecial #114                // Method com/amazonaws/services/simpleemail/AmazonSimpleEmailServiceAsyncClient$28."<init>":(Lcom/amazonaws/services/simpleemail/AmazonSimpleEmailServiceAsyncClient;Lcom/amazonaws/services/simpleemail/model/SendBounceRequest;Lcom/amazonaws/handlers/AsyncHandler;)V
      14: invokeinterface #21,  2           // InterfaceMethod java/util/concurrent/ExecutorService.submit:(Ljava/util/concurrent/Callable;)Ljava/util/concurrent/Future;
      19: areturn

  public java.util.concurrent.Future<com.amazonaws.services.simpleemail.model.SendEmailResult> sendEmailAsync(com.amazonaws.services.simpleemail.model.SendEmailRequest);
    Code:
       0: aload_0
       1: aload_1
       2: aconst_null
       3: invokevirtual #115                // Method sendEmailAsync:(Lcom/amazonaws/services/simpleemail/model/SendEmailRequest;Lcom/amazonaws/handlers/AsyncHandler;)Ljava/util/concurrent/Future;
       6: areturn

  public java.util.concurrent.Future<com.amazonaws.services.simpleemail.model.SendEmailResult> sendEmailAsync(com.amazonaws.services.simpleemail.model.SendEmailRequest, com.amazonaws.handlers.AsyncHandler<com.amazonaws.services.simpleemail.model.SendEmailRequest, com.amazonaws.services.simpleemail.model.SendEmailResult>);
    Code:
       0: aload_0
       1: getfield      #13                 // Field executorService:Ljava/util/concurrent/ExecutorService;
       4: new           #116                // class com/amazonaws/services/simpleemail/AmazonSimpleEmailServiceAsyncClient$29
       7: dup
       8: aload_0
       9: aload_1
      10: aload_2
      11: invokespecial #117                // Method com/amazonaws/services/simpleemail/AmazonSimpleEmailServiceAsyncClient$29."<init>":(Lcom/amazonaws/services/simpleemail/AmazonSimpleEmailServiceAsyncClient;Lcom/amazonaws/services/simpleemail/model/SendEmailRequest;Lcom/amazonaws/handlers/AsyncHandler;)V
      14: invokeinterface #21,  2           // InterfaceMethod java/util/concurrent/ExecutorService.submit:(Ljava/util/concurrent/Callable;)Ljava/util/concurrent/Future;
      19: areturn

  public java.util.concurrent.Future<com.amazonaws.services.simpleemail.model.SendRawEmailResult> sendRawEmailAsync(com.amazonaws.services.simpleemail.model.SendRawEmailRequest);
    Code:
       0: aload_0
       1: aload_1
       2: aconst_null
       3: invokevirtual #118                // Method sendRawEmailAsync:(Lcom/amazonaws/services/simpleemail/model/SendRawEmailRequest;Lcom/amazonaws/handlers/AsyncHandler;)Ljava/util/concurrent/Future;
       6: areturn

  public java.util.concurrent.Future<com.amazonaws.services.simpleemail.model.SendRawEmailResult> sendRawEmailAsync(com.amazonaws.services.simpleemail.model.SendRawEmailRequest, com.amazonaws.handlers.AsyncHandler<com.amazonaws.services.simpleemail.model.SendRawEmailRequest, com.amazonaws.services.simpleemail.model.SendRawEmailResult>);
    Code:
       0: aload_0
       1: getfield      #13                 // Field executorService:Ljava/util/concurrent/ExecutorService;
       4: new           #119                // class com/amazonaws/services/simpleemail/AmazonSimpleEmailServiceAsyncClient$30
       7: dup
       8: aload_0
       9: aload_1
      10: aload_2
      11: invokespecial #120                // Method com/amazonaws/services/simpleemail/AmazonSimpleEmailServiceAsyncClient$30."<init>":(Lcom/amazonaws/services/simpleemail/AmazonSimpleEmailServiceAsyncClient;Lcom/amazonaws/services/simpleemail/model/SendRawEmailRequest;Lcom/amazonaws/handlers/AsyncHandler;)V
      14: invokeinterface #21,  2           // InterfaceMethod java/util/concurrent/ExecutorService.submit:(Ljava/util/concurrent/Callable;)Ljava/util/concurrent/Future;
      19: areturn

  public java.util.concurrent.Future<com.amazonaws.services.simpleemail.model.SetActiveReceiptRuleSetResult> setActiveReceiptRuleSetAsync(com.amazonaws.services.simpleemail.model.SetActiveReceiptRuleSetRequest);
    Code:
       0: aload_0
       1: aload_1
       2: aconst_null
       3: invokevirtual #121                // Method setActiveReceiptRuleSetAsync:(Lcom/amazonaws/services/simpleemail/model/SetActiveReceiptRuleSetRequest;Lcom/amazonaws/handlers/AsyncHandler;)Ljava/util/concurrent/Future;
       6: areturn

  public java.util.concurrent.Future<com.amazonaws.services.simpleemail.model.SetActiveReceiptRuleSetResult> setActiveReceiptRuleSetAsync(com.amazonaws.services.simpleemail.model.SetActiveReceiptRuleSetRequest, com.amazonaws.handlers.AsyncHandler<com.amazonaws.services.simpleemail.model.SetActiveReceiptRuleSetRequest, com.amazonaws.services.simpleemail.model.SetActiveReceiptRuleSetResult>);
    Code:
       0: aload_0
       1: getfield      #13                 // Field executorService:Ljava/util/concurrent/ExecutorService;
       4: new           #122                // class com/amazonaws/services/simpleemail/AmazonSimpleEmailServiceAsyncClient$31
       7: dup
       8: aload_0
       9: aload_1
      10: aload_2
      11: invokespecial #123                // Method com/amazonaws/services/simpleemail/AmazonSimpleEmailServiceAsyncClient$31."<init>":(Lcom/amazonaws/services/simpleemail/AmazonSimpleEmailServiceAsyncClient;Lcom/amazonaws/services/simpleemail/model/SetActiveReceiptRuleSetRequest;Lcom/amazonaws/handlers/AsyncHandler;)V
      14: invokeinterface #21,  2           // InterfaceMethod java/util/concurrent/ExecutorService.submit:(Ljava/util/concurrent/Callable;)Ljava/util/concurrent/Future;
      19: areturn

  public java.util.concurrent.Future<com.amazonaws.services.simpleemail.model.SetIdentityDkimEnabledResult> setIdentityDkimEnabledAsync(com.amazonaws.services.simpleemail.model.SetIdentityDkimEnabledRequest);
    Code:
       0: aload_0
       1: aload_1
       2: aconst_null
       3: invokevirtual #124                // Method setIdentityDkimEnabledAsync:(Lcom/amazonaws/services/simpleemail/model/SetIdentityDkimEnabledRequest;Lcom/amazonaws/handlers/AsyncHandler;)Ljava/util/concurrent/Future;
       6: areturn

  public java.util.concurrent.Future<com.amazonaws.services.simpleemail.model.SetIdentityDkimEnabledResult> setIdentityDkimEnabledAsync(com.amazonaws.services.simpleemail.model.SetIdentityDkimEnabledRequest, com.amazonaws.handlers.AsyncHandler<com.amazonaws.services.simpleemail.model.SetIdentityDkimEnabledRequest, com.amazonaws.services.simpleemail.model.SetIdentityDkimEnabledResult>);
    Code:
       0: aload_0
       1: getfield      #13                 // Field executorService:Ljava/util/concurrent/ExecutorService;
       4: new           #125                // class com/amazonaws/services/simpleemail/AmazonSimpleEmailServiceAsyncClient$32
       7: dup
       8: aload_0
       9: aload_1
      10: aload_2
      11: invokespecial #126                // Method com/amazonaws/services/simpleemail/AmazonSimpleEmailServiceAsyncClient$32."<init>":(Lcom/amazonaws/services/simpleemail/AmazonSimpleEmailServiceAsyncClient;Lcom/amazonaws/services/simpleemail/model/SetIdentityDkimEnabledRequest;Lcom/amazonaws/handlers/AsyncHandler;)V
      14: invokeinterface #21,  2           // InterfaceMethod java/util/concurrent/ExecutorService.submit:(Ljava/util/concurrent/Callable;)Ljava/util/concurrent/Future;
      19: areturn

  public java.util.concurrent.Future<com.amazonaws.services.simpleemail.model.SetIdentityFeedbackForwardingEnabledResult> setIdentityFeedbackForwardingEnabledAsync(com.amazonaws.services.simpleemail.model.SetIdentityFeedbackForwardingEnabledRequest);
    Code:
       0: aload_0
       1: aload_1
       2: aconst_null
       3: invokevirtual #127                // Method setIdentityFeedbackForwardingEnabledAsync:(Lcom/amazonaws/services/simpleemail/model/SetIdentityFeedbackForwardingEnabledRequest;Lcom/amazonaws/handlers/AsyncHandler;)Ljava/util/concurrent/Future;
       6: areturn

  public java.util.concurrent.Future<com.amazonaws.services.simpleemail.model.SetIdentityFeedbackForwardingEnabledResult> setIdentityFeedbackForwardingEnabledAsync(com.amazonaws.services.simpleemail.model.SetIdentityFeedbackForwardingEnabledRequest, com.amazonaws.handlers.AsyncHandler<com.amazonaws.services.simpleemail.model.SetIdentityFeedbackForwardingEnabledRequest, com.amazonaws.services.simpleemail.model.SetIdentityFeedbackForwardingEnabledResult>);
    Code:
       0: aload_0
       1: getfield      #13                 // Field executorService:Ljava/util/concurrent/ExecutorService;
       4: new           #128                // class com/amazonaws/services/simpleemail/AmazonSimpleEmailServiceAsyncClient$33
       7: dup
       8: aload_0
       9: aload_1
      10: aload_2
      11: invokespecial #129                // Method com/amazonaws/services/simpleemail/AmazonSimpleEmailServiceAsyncClient$33."<init>":(Lcom/amazonaws/services/simpleemail/AmazonSimpleEmailServiceAsyncClient;Lcom/amazonaws/services/simpleemail/model/SetIdentityFeedbackForwardingEnabledRequest;Lcom/amazonaws/handlers/AsyncHandler;)V
      14: invokeinterface #21,  2           // InterfaceMethod java/util/concurrent/ExecutorService.submit:(Ljava/util/concurrent/Callable;)Ljava/util/concurrent/Future;
      19: areturn

  public java.util.concurrent.Future<com.amazonaws.services.simpleemail.model.SetIdentityHeadersInNotificationsEnabledResult> setIdentityHeadersInNotificationsEnabledAsync(com.amazonaws.services.simpleemail.model.SetIdentityHeadersInNotificationsEnabledRequest);
    Code:
       0: aload_0
       1: aload_1
       2: aconst_null
       3: invokevirtual #130                // Method setIdentityHeadersInNotificationsEnabledAsync:(Lcom/amazonaws/services/simpleemail/model/SetIdentityHeadersInNotificationsEnabledRequest;Lcom/amazonaws/handlers/AsyncHandler;)Ljava/util/concurrent/Future;
       6: areturn

  public java.util.concurrent.Future<com.amazonaws.services.simpleemail.model.SetIdentityHeadersInNotificationsEnabledResult> setIdentityHeadersInNotificationsEnabledAsync(com.amazonaws.services.simpleemail.model.SetIdentityHeadersInNotificationsEnabledRequest, com.amazonaws.handlers.AsyncHandler<com.amazonaws.services.simpleemail.model.SetIdentityHeadersInNotificationsEnabledRequest, com.amazonaws.services.simpleemail.model.SetIdentityHeadersInNotificationsEnabledResult>);
    Code:
       0: aload_0
       1: getfield      #13                 // Field executorService:Ljava/util/concurrent/ExecutorService;
       4: new           #131                // class com/amazonaws/services/simpleemail/AmazonSimpleEmailServiceAsyncClient$34
       7: dup
       8: aload_0
       9: aload_1
      10: aload_2
      11: invokespecial #132                // Method com/amazonaws/services/simpleemail/AmazonSimpleEmailServiceAsyncClient$34."<init>":(Lcom/amazonaws/services/simpleemail/AmazonSimpleEmailServiceAsyncClient;Lcom/amazonaws/services/simpleemail/model/SetIdentityHeadersInNotificationsEnabledRequest;Lcom/amazonaws/handlers/AsyncHandler;)V
      14: invokeinterface #21,  2           // InterfaceMethod java/util/concurrent/ExecutorService.submit:(Ljava/util/concurrent/Callable;)Ljava/util/concurrent/Future;
      19: areturn

  public java.util.concurrent.Future<com.amazonaws.services.simpleemail.model.SetIdentityMailFromDomainResult> setIdentityMailFromDomainAsync(com.amazonaws.services.simpleemail.model.SetIdentityMailFromDomainRequest);
    Code:
       0: aload_0
       1: aload_1
       2: aconst_null
       3: invokevirtual #133                // Method setIdentityMailFromDomainAsync:(Lcom/amazonaws/services/simpleemail/model/SetIdentityMailFromDomainRequest;Lcom/amazonaws/handlers/AsyncHandler;)Ljava/util/concurrent/Future;
       6: areturn

  public java.util.concurrent.Future<com.amazonaws.services.simpleemail.model.SetIdentityMailFromDomainResult> setIdentityMailFromDomainAsync(com.amazonaws.services.simpleemail.model.SetIdentityMailFromDomainRequest, com.amazonaws.handlers.AsyncHandler<com.amazonaws.services.simpleemail.model.SetIdentityMailFromDomainRequest, com.amazonaws.services.simpleemail.model.SetIdentityMailFromDomainResult>);
    Code:
       0: aload_0
       1: getfield      #13                 // Field executorService:Ljava/util/concurrent/ExecutorService;
       4: new           #134                // class com/amazonaws/services/simpleemail/AmazonSimpleEmailServiceAsyncClient$35
       7: dup
       8: aload_0
       9: aload_1
      10: aload_2
      11: invokespecial #135                // Method com/amazonaws/services/simpleemail/AmazonSimpleEmailServiceAsyncClient$35."<init>":(Lcom/amazonaws/services/simpleemail/AmazonSimpleEmailServiceAsyncClient;Lcom/amazonaws/services/simpleemail/model/SetIdentityMailFromDomainRequest;Lcom/amazonaws/handlers/AsyncHandler;)V
      14: invokeinterface #21,  2           // InterfaceMethod java/util/concurrent/ExecutorService.submit:(Ljava/util/concurrent/Callable;)Ljava/util/concurrent/Future;
      19: areturn

  public java.util.concurrent.Future<com.amazonaws.services.simpleemail.model.SetIdentityNotificationTopicResult> setIdentityNotificationTopicAsync(com.amazonaws.services.simpleemail.model.SetIdentityNotificationTopicRequest);
    Code:
       0: aload_0
       1: aload_1
       2: aconst_null
       3: invokevirtual #136                // Method setIdentityNotificationTopicAsync:(Lcom/amazonaws/services/simpleemail/model/SetIdentityNotificationTopicRequest;Lcom/amazonaws/handlers/AsyncHandler;)Ljava/util/concurrent/Future;
       6: areturn

  public java.util.concurrent.Future<com.amazonaws.services.simpleemail.model.SetIdentityNotificationTopicResult> setIdentityNotificationTopicAsync(com.amazonaws.services.simpleemail.model.SetIdentityNotificationTopicRequest, com.amazonaws.handlers.AsyncHandler<com.amazonaws.services.simpleemail.model.SetIdentityNotificationTopicRequest, com.amazonaws.services.simpleemail.model.SetIdentityNotificationTopicResult>);
    Code:
       0: aload_0
       1: getfield      #13                 // Field executorService:Ljava/util/concurrent/ExecutorService;
       4: new           #137                // class com/amazonaws/services/simpleemail/AmazonSimpleEmailServiceAsyncClient$36
       7: dup
       8: aload_0
       9: aload_1
      10: aload_2
      11: invokespecial #138                // Method com/amazonaws/services/simpleemail/AmazonSimpleEmailServiceAsyncClient$36."<init>":(Lcom/amazonaws/services/simpleemail/AmazonSimpleEmailServiceAsyncClient;Lcom/amazonaws/services/simpleemail/model/SetIdentityNotificationTopicRequest;Lcom/amazonaws/handlers/AsyncHandler;)V
      14: invokeinterface #21,  2           // InterfaceMethod java/util/concurrent/ExecutorService.submit:(Ljava/util/concurrent/Callable;)Ljava/util/concurrent/Future;
      19: areturn

  public java.util.concurrent.Future<com.amazonaws.services.simpleemail.model.SetReceiptRulePositionResult> setReceiptRulePositionAsync(com.amazonaws.services.simpleemail.model.SetReceiptRulePositionRequest);
    Code:
       0: aload_0
       1: aload_1
       2: aconst_null
       3: invokevirtual #139                // Method setReceiptRulePositionAsync:(Lcom/amazonaws/services/simpleemail/model/SetReceiptRulePositionRequest;Lcom/amazonaws/handlers/AsyncHandler;)Ljava/util/concurrent/Future;
       6: areturn

  public java.util.concurrent.Future<com.amazonaws.services.simpleemail.model.SetReceiptRulePositionResult> setReceiptRulePositionAsync(com.amazonaws.services.simpleemail.model.SetReceiptRulePositionRequest, com.amazonaws.handlers.AsyncHandler<com.amazonaws.services.simpleemail.model.SetReceiptRulePositionRequest, com.amazonaws.services.simpleemail.model.SetReceiptRulePositionResult>);
    Code:
       0: aload_0
       1: getfield      #13                 // Field executorService:Ljava/util/concurrent/ExecutorService;
       4: new           #140                // class com/amazonaws/services/simpleemail/AmazonSimpleEmailServiceAsyncClient$37
       7: dup
       8: aload_0
       9: aload_1
      10: aload_2
      11: invokespecial #141                // Method com/amazonaws/services/simpleemail/AmazonSimpleEmailServiceAsyncClient$37."<init>":(Lcom/amazonaws/services/simpleemail/AmazonSimpleEmailServiceAsyncClient;Lcom/amazonaws/services/simpleemail/model/SetReceiptRulePositionRequest;Lcom/amazonaws/handlers/AsyncHandler;)V
      14: invokeinterface #21,  2           // InterfaceMethod java/util/concurrent/ExecutorService.submit:(Ljava/util/concurrent/Callable;)Ljava/util/concurrent/Future;
      19: areturn

  public java.util.concurrent.Future<com.amazonaws.services.simpleemail.model.UpdateReceiptRuleResult> updateReceiptRuleAsync(com.amazonaws.services.simpleemail.model.UpdateReceiptRuleRequest);
    Code:
       0: aload_0
       1: aload_1
       2: aconst_null
       3: invokevirtual #142                // Method updateReceiptRuleAsync:(Lcom/amazonaws/services/simpleemail/model/UpdateReceiptRuleRequest;Lcom/amazonaws/handlers/AsyncHandler;)Ljava/util/concurrent/Future;
       6: areturn

  public java.util.concurrent.Future<com.amazonaws.services.simpleemail.model.UpdateReceiptRuleResult> updateReceiptRuleAsync(com.amazonaws.services.simpleemail.model.UpdateReceiptRuleRequest, com.amazonaws.handlers.AsyncHandler<com.amazonaws.services.simpleemail.model.UpdateReceiptRuleRequest, com.amazonaws.services.simpleemail.model.UpdateReceiptRuleResult>);
    Code:
       0: aload_0
       1: getfield      #13                 // Field executorService:Ljava/util/concurrent/ExecutorService;
       4: new           #143                // class com/amazonaws/services/simpleemail/AmazonSimpleEmailServiceAsyncClient$38
       7: dup
       8: aload_0
       9: aload_1
      10: aload_2
      11: invokespecial #144                // Method com/amazonaws/services/simpleemail/AmazonSimpleEmailServiceAsyncClient$38."<init>":(Lcom/amazonaws/services/simpleemail/AmazonSimpleEmailServiceAsyncClient;Lcom/amazonaws/services/simpleemail/model/UpdateReceiptRuleRequest;Lcom/amazonaws/handlers/AsyncHandler;)V
      14: invokeinterface #21,  2           // InterfaceMethod java/util/concurrent/ExecutorService.submit:(Ljava/util/concurrent/Callable;)Ljava/util/concurrent/Future;
      19: areturn

  public java.util.concurrent.Future<com.amazonaws.services.simpleemail.model.VerifyDomainDkimResult> verifyDomainDkimAsync(com.amazonaws.services.simpleemail.model.VerifyDomainDkimRequest);
    Code:
       0: aload_0
       1: aload_1
       2: aconst_null
       3: invokevirtual #145                // Method verifyDomainDkimAsync:(Lcom/amazonaws/services/simpleemail/model/VerifyDomainDkimRequest;Lcom/amazonaws/handlers/AsyncHandler;)Ljava/util/concurrent/Future;
       6: areturn

  public java.util.concurrent.Future<com.amazonaws.services.simpleemail.model.VerifyDomainDkimResult> verifyDomainDkimAsync(com.amazonaws.services.simpleemail.model.VerifyDomainDkimRequest, com.amazonaws.handlers.AsyncHandler<com.amazonaws.services.simpleemail.model.VerifyDomainDkimRequest, com.amazonaws.services.simpleemail.model.VerifyDomainDkimResult>);
    Code:
       0: aload_0
       1: getfield      #13                 // Field executorService:Ljava/util/concurrent/ExecutorService;
       4: new           #146                // class com/amazonaws/services/simpleemail/AmazonSimpleEmailServiceAsyncClient$39
       7: dup
       8: aload_0
       9: aload_1
      10: aload_2
      11: invokespecial #147                // Method com/amazonaws/services/simpleemail/AmazonSimpleEmailServiceAsyncClient$39."<init>":(Lcom/amazonaws/services/simpleemail/AmazonSimpleEmailServiceAsyncClient;Lcom/amazonaws/services/simpleemail/model/VerifyDomainDkimRequest;Lcom/amazonaws/handlers/AsyncHandler;)V
      14: invokeinterface #21,  2           // InterfaceMethod java/util/concurrent/ExecutorService.submit:(Ljava/util/concurrent/Callable;)Ljava/util/concurrent/Future;
      19: areturn

  public java.util.concurrent.Future<com.amazonaws.services.simpleemail.model.VerifyDomainIdentityResult> verifyDomainIdentityAsync(com.amazonaws.services.simpleemail.model.VerifyDomainIdentityRequest);
    Code:
       0: aload_0
       1: aload_1
       2: aconst_null
       3: invokevirtual #148                // Method verifyDomainIdentityAsync:(Lcom/amazonaws/services/simpleemail/model/VerifyDomainIdentityRequest;Lcom/amazonaws/handlers/AsyncHandler;)Ljava/util/concurrent/Future;
       6: areturn

  public java.util.concurrent.Future<com.amazonaws.services.simpleemail.model.VerifyDomainIdentityResult> verifyDomainIdentityAsync(com.amazonaws.services.simpleemail.model.VerifyDomainIdentityRequest, com.amazonaws.handlers.AsyncHandler<com.amazonaws.services.simpleemail.model.VerifyDomainIdentityRequest, com.amazonaws.services.simpleemail.model.VerifyDomainIdentityResult>);
    Code:
       0: aload_0
       1: getfield      #13                 // Field executorService:Ljava/util/concurrent/ExecutorService;
       4: new           #149                // class com/amazonaws/services/simpleemail/AmazonSimpleEmailServiceAsyncClient$40
       7: dup
       8: aload_0
       9: aload_1
      10: aload_2
      11: invokespecial #150                // Method com/amazonaws/services/simpleemail/AmazonSimpleEmailServiceAsyncClient$40."<init>":(Lcom/amazonaws/services/simpleemail/AmazonSimpleEmailServiceAsyncClient;Lcom/amazonaws/services/simpleemail/model/VerifyDomainIdentityRequest;Lcom/amazonaws/handlers/AsyncHandler;)V
      14: invokeinterface #21,  2           // InterfaceMethod java/util/concurrent/ExecutorService.submit:(Ljava/util/concurrent/Callable;)Ljava/util/concurrent/Future;
      19: areturn

  public java.util.concurrent.Future<com.amazonaws.services.simpleemail.model.VerifyEmailAddressResult> verifyEmailAddressAsync(com.amazonaws.services.simpleemail.model.VerifyEmailAddressRequest);
    Code:
       0: aload_0
       1: aload_1
       2: aconst_null
       3: invokevirtual #151                // Method verifyEmailAddressAsync:(Lcom/amazonaws/services/simpleemail/model/VerifyEmailAddressRequest;Lcom/amazonaws/handlers/AsyncHandler;)Ljava/util/concurrent/Future;
       6: areturn

  public java.util.concurrent.Future<com.amazonaws.services.simpleemail.model.VerifyEmailAddressResult> verifyEmailAddressAsync(com.amazonaws.services.simpleemail.model.VerifyEmailAddressRequest, com.amazonaws.handlers.AsyncHandler<com.amazonaws.services.simpleemail.model.VerifyEmailAddressRequest, com.amazonaws.services.simpleemail.model.VerifyEmailAddressResult>);
    Code:
       0: aload_0
       1: getfield      #13                 // Field executorService:Ljava/util/concurrent/ExecutorService;
       4: new           #152                // class com/amazonaws/services/simpleemail/AmazonSimpleEmailServiceAsyncClient$41
       7: dup
       8: aload_0
       9: aload_1
      10: aload_2
      11: invokespecial #153                // Method com/amazonaws/services/simpleemail/AmazonSimpleEmailServiceAsyncClient$41."<init>":(Lcom/amazonaws/services/simpleemail/AmazonSimpleEmailServiceAsyncClient;Lcom/amazonaws/services/simpleemail/model/VerifyEmailAddressRequest;Lcom/amazonaws/handlers/AsyncHandler;)V
      14: invokeinterface #21,  2           // InterfaceMethod java/util/concurrent/ExecutorService.submit:(Ljava/util/concurrent/Callable;)Ljava/util/concurrent/Future;
      19: areturn

  public java.util.concurrent.Future<com.amazonaws.services.simpleemail.model.VerifyEmailIdentityResult> verifyEmailIdentityAsync(com.amazonaws.services.simpleemail.model.VerifyEmailIdentityRequest);
    Code:
       0: aload_0
       1: aload_1
       2: aconst_null
       3: invokevirtual #154                // Method verifyEmailIdentityAsync:(Lcom/amazonaws/services/simpleemail/model/VerifyEmailIdentityRequest;Lcom/amazonaws/handlers/AsyncHandler;)Ljava/util/concurrent/Future;
       6: areturn

  public java.util.concurrent.Future<com.amazonaws.services.simpleemail.model.VerifyEmailIdentityResult> verifyEmailIdentityAsync(com.amazonaws.services.simpleemail.model.VerifyEmailIdentityRequest, com.amazonaws.handlers.AsyncHandler<com.amazonaws.services.simpleemail.model.VerifyEmailIdentityRequest, com.amazonaws.services.simpleemail.model.VerifyEmailIdentityResult>);
    Code:
       0: aload_0
       1: getfield      #13                 // Field executorService:Ljava/util/concurrent/ExecutorService;
       4: new           #155                // class com/amazonaws/services/simpleemail/AmazonSimpleEmailServiceAsyncClient$42
       7: dup
       8: aload_0
       9: aload_1
      10: aload_2
      11: invokespecial #156                // Method com/amazonaws/services/simpleemail/AmazonSimpleEmailServiceAsyncClient$42."<init>":(Lcom/amazonaws/services/simpleemail/AmazonSimpleEmailServiceAsyncClient;Lcom/amazonaws/services/simpleemail/model/VerifyEmailIdentityRequest;Lcom/amazonaws/handlers/AsyncHandler;)V
      14: invokeinterface #21,  2           // InterfaceMethod java/util/concurrent/ExecutorService.submit:(Ljava/util/concurrent/Callable;)Ljava/util/concurrent/Future;
      19: areturn

  public void shutdown();
    Code:
       0: aload_0
       1: invokespecial #157                // Method com/amazonaws/services/simpleemail/AmazonSimpleEmailServiceClient.shutdown:()V
       4: aload_0
       5: getfield      #13                 // Field executorService:Ljava/util/concurrent/ExecutorService;
       8: invokeinterface #158,  1          // InterfaceMethod java/util/concurrent/ExecutorService.shutdownNow:()Ljava/util/List;
      13: pop
      14: return
}
