Compiled from "AWSJavaMailTransport.java"
public class com.amazonaws.services.simpleemail.AWSJavaMailTransport extends javax.mail.Transport {
  public static final java.lang.String AWS_EMAIL_SERVICE_ENDPOINT_PROPERTY;

  public static final java.lang.String AWS_SECRET_KEY_PROPERTY;

  public static final java.lang.String AWS_ACCESS_KEY_PROPERTY;

  private com.amazonaws.services.simpleemail.AmazonSimpleEmailServiceClient emailService;

  private final java.lang.String accessKey;

  private final java.lang.String secretKey;

  private final java.lang.String httpsEndpoint;

  private java.lang.String lastMessageId;

  private static final java.lang.String USER_AGENT;

  public com.amazonaws.services.simpleemail.AWSJavaMailTransport(javax.mail.Session, javax.mail.URLName);
    Code:
       0: aload_0
       1: aload_1
       2: aload_2
       3: invokespecial #1                  // Method javax/mail/Transport."<init>":(Ljavax/mail/Session;Ljavax/mail/URLName;)V
       6: aload_0
       7: aload_1
       8: ldc           #3                  // String mail.aws.user
      10: invokevirtual #4                  // Method javax/mail/Session.getProperty:(Ljava/lang/String;)Ljava/lang/String;
      13: putfield      #5                  // Field accessKey:Ljava/lang/String;
      16: aload_0
      17: aload_1
      18: ldc           #6                  // String mail.aws.password
      20: invokevirtual #4                  // Method javax/mail/Session.getProperty:(Ljava/lang/String;)Ljava/lang/String;
      23: putfield      #7                  // Field secretKey:Ljava/lang/String;
      26: aload_0
      27: aload_1
      28: ldc           #8                  // String mail.aws.host
      30: invokevirtual #4                  // Method javax/mail/Session.getProperty:(Ljava/lang/String;)Ljava/lang/String;
      33: putfield      #9                  // Field httpsEndpoint:Ljava/lang/String;
      36: return

  public void sendMessage(javax.mail.Message, javax.mail.Address[]) throws javax.mail.MessagingException, javax.mail.SendFailedException;
    Code:
       0: aload_0
       1: invokespecial #10                 // Method checkConnection:()V
       4: aload_0
       5: aload_1
       6: invokespecial #11                 // Method checkMessage:(Ljavax/mail/Message;)V
       9: aload_0
      10: aload_1
      11: aload_2
      12: invokespecial #12                 // Method checkAddresses:(Ljavax/mail/Message;[Ljavax/mail/Address;)V
      15: aload_0
      16: aload_1
      17: aload_2
      18: invokespecial #13                 // Method collateRecipients:(Ljavax/mail/Message;[Ljavax/mail/Address;)V
      21: aload_0
      22: aload_1
      23: invokespecial #14                 // Method prepareEmail:(Ljavax/mail/Message;)Lcom/amazonaws/services/simpleemail/model/SendRawEmailRequest;
      26: astore_3
      27: aload_0
      28: aload_1
      29: aload_3
      30: invokespecial #15                 // Method sendEmail:(Ljavax/mail/Message;Lcom/amazonaws/services/simpleemail/model/SendRawEmailRequest;)V
      33: return

  private void checkConnection();
    Code:
       0: aload_0
       1: getfield      #16                 // Field emailService:Lcom/amazonaws/services/simpleemail/AmazonSimpleEmailServiceClient;
       4: ifnull        14
       7: aload_0
       8: invokespecial #17                 // Method javax/mail/Transport.isConnected:()Z
      11: ifne          24
      14: new           #18                 // class java/lang/IllegalStateException
      17: dup
      18: ldc           #19                 // String Not connected
      20: invokespecial #20                 // Method java/lang/IllegalStateException."<init>":(Ljava/lang/String;)V
      23: athrow
      24: return

  private void checkMessage(javax.mail.Message) throws javax.mail.MessagingException;
    Code:
       0: aload_1
       1: ifnonnull     14
       4: new           #21                 // class javax/mail/MessagingException
       7: dup
       8: ldc           #22                 // String Message is null
      10: invokespecial #23                 // Method javax/mail/MessagingException."<init>":(Ljava/lang/String;)V
      13: athrow
      14: aload_1
      15: instanceof    #24                 // class javax/mail/internet/MimeMessage
      18: ifne          31
      21: new           #21                 // class javax/mail/MessagingException
      24: dup
      25: ldc           #25                 // String AWS Mail Service can only send MimeMessages
      27: invokespecial #23                 // Method javax/mail/MessagingException."<init>":(Ljava/lang/String;)V
      30: athrow
      31: return

  private void checkAddresses(javax.mail.Message, javax.mail.Address[]) throws javax.mail.MessagingException, javax.mail.SendFailedException;
    Code:
       0: aload_2
       1: checkcast     #26                 // class "[Ljava/lang/Object;"
       4: invokestatic  #27                 // Method isNullOrEmpty:([Ljava/lang/Object;)Z
       7: ifeq          68
      10: aload_1
      11: getstatic     #28                 // Field javax/mail/Message$RecipientType.TO:Ljavax/mail/Message$RecipientType;
      14: invokevirtual #29                 // Method javax/mail/Message.getRecipients:(Ljavax/mail/Message$RecipientType;)[Ljavax/mail/Address;
      17: checkcast     #26                 // class "[Ljava/lang/Object;"
      20: invokestatic  #27                 // Method isNullOrEmpty:([Ljava/lang/Object;)Z
      23: ifeq          68
      26: aload_1
      27: getstatic     #30                 // Field javax/mail/Message$RecipientType.CC:Ljavax/mail/Message$RecipientType;
      30: invokevirtual #29                 // Method javax/mail/Message.getRecipients:(Ljavax/mail/Message$RecipientType;)[Ljavax/mail/Address;
      33: checkcast     #26                 // class "[Ljava/lang/Object;"
      36: invokestatic  #27                 // Method isNullOrEmpty:([Ljava/lang/Object;)Z
      39: ifeq          68
      42: aload_1
      43: getstatic     #31                 // Field javax/mail/Message$RecipientType.BCC:Ljavax/mail/Message$RecipientType;
      46: invokevirtual #29                 // Method javax/mail/Message.getRecipients:(Ljavax/mail/Message$RecipientType;)[Ljavax/mail/Address;
      49: checkcast     #26                 // class "[Ljava/lang/Object;"
      52: invokestatic  #27                 // Method isNullOrEmpty:([Ljava/lang/Object;)Z
      55: ifeq          68
      58: new           #32                 // class javax/mail/SendFailedException
      61: dup
      62: ldc           #33                 // String No recipient addresses
      64: invokespecial #34                 // Method javax/mail/SendFailedException."<init>":(Ljava/lang/String;)V
      67: athrow
      68: new           #35                 // class java/util/HashSet
      71: dup
      72: invokespecial #36                 // Method java/util/HashSet."<init>":()V
      75: astore_3
      76: iconst_4
      77: anewarray     #37                 // class "[Ljavax/mail/Address;"
      80: dup
      81: iconst_0
      82: aload_1
      83: getstatic     #28                 // Field javax/mail/Message$RecipientType.TO:Ljavax/mail/Message$RecipientType;
      86: invokevirtual #29                 // Method javax/mail/Message.getRecipients:(Ljavax/mail/Message$RecipientType;)[Ljavax/mail/Address;
      89: aastore
      90: dup
      91: iconst_1
      92: aload_1
      93: getstatic     #30                 // Field javax/mail/Message$RecipientType.CC:Ljavax/mail/Message$RecipientType;
      96: invokevirtual #29                 // Method javax/mail/Message.getRecipients:(Ljavax/mail/Message$RecipientType;)[Ljavax/mail/Address;
      99: aastore
     100: dup
     101: iconst_2
     102: aload_1
     103: getstatic     #31                 // Field javax/mail/Message$RecipientType.BCC:Ljavax/mail/Message$RecipientType;
     106: invokevirtual #29                 // Method javax/mail/Message.getRecipients:(Ljavax/mail/Message$RecipientType;)[Ljavax/mail/Address;
     109: aastore
     110: dup
     111: iconst_3
     112: aload_2
     113: aastore
     114: astore        4
     116: aload         4
     118: arraylength
     119: istore        5
     121: iconst_0
     122: istore        6
     124: iload         6
     126: iload         5
     128: if_icmpge     201
     131: aload         4
     133: iload         6
     135: aaload
     136: astore        7
     138: aload         7
     140: invokestatic  #27                 // Method isNullOrEmpty:([Ljava/lang/Object;)Z
     143: ifne          195
     146: aload         7
     148: astore        8
     150: aload         8
     152: arraylength
     153: istore        9
     155: iconst_0
     156: istore        10
     158: iload         10
     160: iload         9
     162: if_icmpge     195
     165: aload         8
     167: iload         10
     169: aaload
     170: astore        11
     172: aload         11
     174: instanceof    #38                 // class javax/mail/internet/InternetAddress
     177: ifne          189
     180: aload_3
     181: aload         11
     183: invokeinterface #39,  2           // InterfaceMethod java/util/Set.add:(Ljava/lang/Object;)Z
     188: pop
     189: iinc          10, 1
     192: goto          158
     195: iinc          6, 1
     198: goto          124
     201: aload_3
     202: invokeinterface #40,  1           // InterfaceMethod java/util/Set.isEmpty:()Z
     207: ifne          260
     210: iconst_0
     211: anewarray     #41                 // class javax/mail/Address
     214: astore        4
     216: iconst_0
     217: anewarray     #41                 // class javax/mail/Address
     220: astore        5
     222: aload_0
     223: iconst_2
     224: aload         4
     226: aload         5
     228: aload_3
     229: aload_3
     230: invokeinterface #43,  1           // InterfaceMethod java/util/Set.size:()I
     235: anewarray     #41                 // class javax/mail/Address
     238: invokeinterface #44,  2           // InterfaceMethod java/util/Set.toArray:([Ljava/lang/Object;)[Ljava/lang/Object;
     243: checkcast     #37                 // class "[Ljavax/mail/Address;"
     246: aload_1
     247: invokespecial #45                 // Method javax/mail/Transport.notifyTransportListeners:(I[Ljavax/mail/Address;[Ljavax/mail/Address;[Ljavax/mail/Address;Ljavax/mail/Message;)V
     250: new           #32                 // class javax/mail/SendFailedException
     253: dup
     254: ldc           #46                 // String AWS Mail Service can only send to InternetAddresses
     256: invokespecial #34                 // Method javax/mail/SendFailedException."<init>":(Ljava/lang/String;)V
     259: athrow
     260: return

  private void collateRecipients(javax.mail.Message, javax.mail.Address[]) throws javax.mail.MessagingException;
    Code:
       0: aload_2
       1: invokestatic  #27                 // Method isNullOrEmpty:([Ljava/lang/Object;)Z
       4: ifne          365
       7: new           #47                 // class java/util/Hashtable
      10: dup
      11: invokespecial #48                 // Method java/util/Hashtable."<init>":()V
      14: astore_3
      15: aload_2
      16: astore        4
      18: aload         4
      20: arraylength
      21: istore        5
      23: iconst_0
      24: istore        6
      26: iload         6
      28: iload         5
      30: if_icmpge     56
      33: aload         4
      35: iload         6
      37: aaload
      38: astore        7
      40: aload_3
      41: aload         7
      43: getstatic     #28                 // Field javax/mail/Message$RecipientType.TO:Ljavax/mail/Message$RecipientType;
      46: invokevirtual #49                 // Method java/util/Hashtable.put:(Ljava/lang/Object;Ljava/lang/Object;)Ljava/lang/Object;
      49: pop
      50: iinc          6, 1
      53: goto          26
      56: aload_1
      57: getstatic     #28                 // Field javax/mail/Message$RecipientType.TO:Ljavax/mail/Message$RecipientType;
      60: invokevirtual #29                 // Method javax/mail/Message.getRecipients:(Ljavax/mail/Message$RecipientType;)[Ljavax/mail/Address;
      63: invokestatic  #27                 // Method isNullOrEmpty:([Ljava/lang/Object;)Z
      66: ifne          116
      69: aload_1
      70: getstatic     #28                 // Field javax/mail/Message$RecipientType.TO:Ljavax/mail/Message$RecipientType;
      73: invokevirtual #29                 // Method javax/mail/Message.getRecipients:(Ljavax/mail/Message$RecipientType;)[Ljavax/mail/Address;
      76: astore        4
      78: aload         4
      80: arraylength
      81: istore        5
      83: iconst_0
      84: istore        6
      86: iload         6
      88: iload         5
      90: if_icmpge     116
      93: aload         4
      95: iload         6
      97: aaload
      98: astore        7
     100: aload_3
     101: aload         7
     103: getstatic     #28                 // Field javax/mail/Message$RecipientType.TO:Ljavax/mail/Message$RecipientType;
     106: invokevirtual #49                 // Method java/util/Hashtable.put:(Ljava/lang/Object;Ljava/lang/Object;)Ljava/lang/Object;
     109: pop
     110: iinc          6, 1
     113: goto          86
     116: aload_1
     117: getstatic     #30                 // Field javax/mail/Message$RecipientType.CC:Ljavax/mail/Message$RecipientType;
     120: invokevirtual #29                 // Method javax/mail/Message.getRecipients:(Ljavax/mail/Message$RecipientType;)[Ljavax/mail/Address;
     123: invokestatic  #27                 // Method isNullOrEmpty:([Ljava/lang/Object;)Z
     126: ifne          176
     129: aload_1
     130: getstatic     #30                 // Field javax/mail/Message$RecipientType.CC:Ljavax/mail/Message$RecipientType;
     133: invokevirtual #29                 // Method javax/mail/Message.getRecipients:(Ljavax/mail/Message$RecipientType;)[Ljavax/mail/Address;
     136: astore        4
     138: aload         4
     140: arraylength
     141: istore        5
     143: iconst_0
     144: istore        6
     146: iload         6
     148: iload         5
     150: if_icmpge     176
     153: aload         4
     155: iload         6
     157: aaload
     158: astore        7
     160: aload_3
     161: aload         7
     163: getstatic     #30                 // Field javax/mail/Message$RecipientType.CC:Ljavax/mail/Message$RecipientType;
     166: invokevirtual #49                 // Method java/util/Hashtable.put:(Ljava/lang/Object;Ljava/lang/Object;)Ljava/lang/Object;
     169: pop
     170: iinc          6, 1
     173: goto          146
     176: aload_1
     177: getstatic     #31                 // Field javax/mail/Message$RecipientType.BCC:Ljavax/mail/Message$RecipientType;
     180: invokevirtual #29                 // Method javax/mail/Message.getRecipients:(Ljavax/mail/Message$RecipientType;)[Ljavax/mail/Address;
     183: invokestatic  #27                 // Method isNullOrEmpty:([Ljava/lang/Object;)Z
     186: ifne          236
     189: aload_1
     190: getstatic     #31                 // Field javax/mail/Message$RecipientType.BCC:Ljavax/mail/Message$RecipientType;
     193: invokevirtual #29                 // Method javax/mail/Message.getRecipients:(Ljavax/mail/Message$RecipientType;)[Ljavax/mail/Address;
     196: astore        4
     198: aload         4
     200: arraylength
     201: istore        5
     203: iconst_0
     204: istore        6
     206: iload         6
     208: iload         5
     210: if_icmpge     236
     213: aload         4
     215: iload         6
     217: aaload
     218: astore        7
     220: aload_3
     221: aload         7
     223: getstatic     #31                 // Field javax/mail/Message$RecipientType.BCC:Ljavax/mail/Message$RecipientType;
     226: invokevirtual #49                 // Method java/util/Hashtable.put:(Ljava/lang/Object;Ljava/lang/Object;)Ljava/lang/Object;
     229: pop
     230: iinc          6, 1
     233: goto          206
     236: aload_1
     237: getstatic     #28                 // Field javax/mail/Message$RecipientType.TO:Ljavax/mail/Message$RecipientType;
     240: iconst_0
     241: anewarray     #41                 // class javax/mail/Address
     244: invokevirtual #50                 // Method javax/mail/Message.setRecipients:(Ljavax/mail/Message$RecipientType;[Ljavax/mail/Address;)V
     247: aload_1
     248: getstatic     #30                 // Field javax/mail/Message$RecipientType.CC:Ljavax/mail/Message$RecipientType;
     251: iconst_0
     252: anewarray     #41                 // class javax/mail/Address
     255: invokevirtual #50                 // Method javax/mail/Message.setRecipients:(Ljavax/mail/Message$RecipientType;[Ljavax/mail/Address;)V
     258: aload_1
     259: getstatic     #31                 // Field javax/mail/Message$RecipientType.BCC:Ljavax/mail/Message$RecipientType;
     262: iconst_0
     263: anewarray     #41                 // class javax/mail/Address
     266: invokevirtual #50                 // Method javax/mail/Message.setRecipients:(Ljavax/mail/Message$RecipientType;[Ljavax/mail/Address;)V
     269: aload_3
     270: invokevirtual #51                 // Method java/util/Hashtable.keySet:()Ljava/util/Set;
     273: invokeinterface #52,  1           // InterfaceMethod java/util/Set.iterator:()Ljava/util/Iterator;
     278: astore        4
     280: aload         4
     282: invokeinterface #53,  1           // InterfaceMethod java/util/Iterator.hasNext:()Z
     287: ifeq          320
     290: aload         4
     292: invokeinterface #54,  1           // InterfaceMethod java/util/Iterator.next:()Ljava/lang/Object;
     297: checkcast     #41                 // class javax/mail/Address
     300: astore        5
     302: aload_1
     303: aload_3
     304: aload         5
     306: invokevirtual #55                 // Method java/util/Hashtable.get:(Ljava/lang/Object;)Ljava/lang/Object;
     309: checkcast     #56                 // class javax/mail/Message$RecipientType
     312: aload         5
     314: invokevirtual #57                 // Method javax/mail/Message.addRecipient:(Ljavax/mail/Message$RecipientType;Ljavax/mail/Address;)V
     317: goto          280
     320: aload_1
     321: getstatic     #28                 // Field javax/mail/Message$RecipientType.TO:Ljavax/mail/Message$RecipientType;
     324: invokevirtual #29                 // Method javax/mail/Message.getRecipients:(Ljavax/mail/Message$RecipientType;)[Ljavax/mail/Address;
     327: ifnull        341
     330: aload_1
     331: getstatic     #28                 // Field javax/mail/Message$RecipientType.TO:Ljavax/mail/Message$RecipientType;
     334: invokevirtual #29                 // Method javax/mail/Message.getRecipients:(Ljavax/mail/Message$RecipientType;)[Ljavax/mail/Address;
     337: arraylength
     338: ifne          365
     341: aload_1
     342: getstatic     #28                 // Field javax/mail/Message$RecipientType.TO:Ljavax/mail/Message$RecipientType;
     345: aload_3
     346: invokevirtual #51                 // Method java/util/Hashtable.keySet:()Ljava/util/Set;
     349: invokeinterface #52,  1           // InterfaceMethod java/util/Set.iterator:()Ljava/util/Iterator;
     354: invokeinterface #54,  1           // InterfaceMethod java/util/Iterator.next:()Ljava/lang/Object;
     359: checkcast     #41                 // class javax/mail/Address
     362: invokevirtual #58                 // Method javax/mail/Message.setRecipient:(Ljavax/mail/Message$RecipientType;Ljavax/mail/Address;)V
     365: return

  private com.amazonaws.services.simpleemail.model.SendRawEmailRequest prepareEmail(javax.mail.Message) throws javax.mail.MessagingException;
    Code:
       0: new           #59                 // class java/io/ByteArrayOutputStream
       3: dup
       4: invokespecial #60                 // Method java/io/ByteArrayOutputStream."<init>":()V
       7: astore_2
       8: aload_1
       9: aload_2
      10: invokevirtual #61                 // Method javax/mail/Message.writeTo:(Ljava/io/OutputStream;)V
      13: new           #62                 // class com/amazonaws/services/simpleemail/model/SendRawEmailRequest
      16: dup
      17: invokespecial #63                 // Method com/amazonaws/services/simpleemail/model/SendRawEmailRequest."<init>":()V
      20: astore_3
      21: aload_2
      22: checkcast     #59                 // class java/io/ByteArrayOutputStream
      25: invokevirtual #64                 // Method java/io/ByteArrayOutputStream.toByteArray:()[B
      28: astore        4
      30: new           #65                 // class com/amazonaws/services/simpleemail/model/RawMessage
      33: dup
      34: invokespecial #66                 // Method com/amazonaws/services/simpleemail/model/RawMessage."<init>":()V
      37: astore        5
      39: aload         5
      41: aload         4
      43: invokestatic  #67                 // Method java/nio/ByteBuffer.wrap:([B)Ljava/nio/ByteBuffer;
      46: invokevirtual #68                 // Method com/amazonaws/services/simpleemail/model/RawMessage.setData:(Ljava/nio/ByteBuffer;)V
      49: aload_3
      50: aload         5
      52: invokevirtual #69                 // Method com/amazonaws/services/simpleemail/model/SendRawEmailRequest.setRawMessage:(Lcom/amazonaws/services/simpleemail/model/RawMessage;)V
      55: aload_3
      56: areturn
      57: astore_2
      58: iconst_0
      59: anewarray     #41                 // class javax/mail/Address
      62: astore_3
      63: iconst_0
      64: anewarray     #41                 // class javax/mail/Address
      67: astore        4
      69: aload_1
      70: invokevirtual #71                 // Method javax/mail/Message.getAllRecipients:()[Ljavax/mail/Address;
      73: astore        5
      75: aload_0
      76: iconst_2
      77: aload_3
      78: aload         4
      80: aload         5
      82: aload_1
      83: invokespecial #45                 // Method javax/mail/Transport.notifyTransportListeners:(I[Ljavax/mail/Address;[Ljavax/mail/Address;[Ljavax/mail/Address;Ljavax/mail/Message;)V
      86: new           #21                 // class javax/mail/MessagingException
      89: dup
      90: new           #72                 // class java/lang/StringBuilder
      93: dup
      94: invokespecial #73                 // Method java/lang/StringBuilder."<init>":()V
      97: ldc           #74                 // String Unable to write message:
      99: invokevirtual #75                 // Method java/lang/StringBuilder.append:(Ljava/lang/String;)Ljava/lang/StringBuilder;
     102: aload_1
     103: invokevirtual #76                 // Method java/lang/Object.toString:()Ljava/lang/String;
     106: invokevirtual #75                 // Method java/lang/StringBuilder.append:(Ljava/lang/String;)Ljava/lang/StringBuilder;
     109: invokevirtual #77                 // Method java/lang/StringBuilder.toString:()Ljava/lang/String;
     112: aload_2
     113: invokespecial #78                 // Method javax/mail/MessagingException."<init>":(Ljava/lang/String;Ljava/lang/Exception;)V
     116: athrow
    Exception table:
       from    to  target type
           0    56    57   Class java/lang/Exception

  private void sendEmail(javax.mail.Message, com.amazonaws.services.simpleemail.model.SendRawEmailRequest) throws javax.mail.SendFailedException, javax.mail.MessagingException;
    Code:
       0: aconst_null
       1: astore_3
       2: aconst_null
       3: astore        4
       5: aconst_null
       6: astore        5
       8: aload_0
       9: aload_2
      10: getstatic     #79                 // Field USER_AGENT:Ljava/lang/String;
      13: invokevirtual #80                 // Method appendUserAgent:(Lcom/amazonaws/AmazonWebServiceRequest;Ljava/lang/String;)Lcom/amazonaws/AmazonWebServiceRequest;
      16: pop
      17: aload_0
      18: getfield      #16                 // Field emailService:Lcom/amazonaws/services/simpleemail/AmazonSimpleEmailServiceClient;
      21: aload_2
      22: invokevirtual #81                 // Method com/amazonaws/services/simpleemail/AmazonSimpleEmailServiceClient.sendRawEmail:(Lcom/amazonaws/services/simpleemail/model/SendRawEmailRequest;)Lcom/amazonaws/services/simpleemail/model/SendRawEmailResult;
      25: astore        6
      27: aload_0
      28: aload         6
      30: invokevirtual #82                 // Method com/amazonaws/services/simpleemail/model/SendRawEmailResult.getMessageId:()Ljava/lang/String;
      33: putfield      #83                 // Field lastMessageId:Ljava/lang/String;
      36: aload_1
      37: invokevirtual #71                 // Method javax/mail/Message.getAllRecipients:()[Ljavax/mail/Address;
      40: astore_3
      41: iconst_0
      42: anewarray     #41                 // class javax/mail/Address
      45: astore        4
      47: iconst_0
      48: anewarray     #41                 // class javax/mail/Address
      51: astore        5
      53: aload_0
      54: iconst_1
      55: aload_3
      56: aload         4
      58: aload         5
      60: aload_1
      61: invokespecial #45                 // Method javax/mail/Transport.notifyTransportListeners:(I[Ljavax/mail/Address;[Ljavax/mail/Address;[Ljavax/mail/Address;Ljavax/mail/Message;)V
      64: goto          114
      67: astore        6
      69: iconst_0
      70: anewarray     #41                 // class javax/mail/Address
      73: astore_3
      74: aload_1
      75: invokevirtual #71                 // Method javax/mail/Message.getAllRecipients:()[Ljavax/mail/Address;
      78: astore        4
      80: iconst_0
      81: anewarray     #41                 // class javax/mail/Address
      84: astore        5
      86: aload_0
      87: iconst_2
      88: aload_3
      89: aload         4
      91: aload         5
      93: aload_1
      94: invokespecial #45                 // Method javax/mail/Transport.notifyTransportListeners:(I[Ljavax/mail/Address;[Ljavax/mail/Address;[Ljavax/mail/Address;Ljavax/mail/Message;)V
      97: new           #32                 // class javax/mail/SendFailedException
     100: dup
     101: ldc           #84                 // String Unable to send email
     103: aload         6
     105: aload_3
     106: aload         4
     108: aload         5
     110: invokespecial #85                 // Method javax/mail/SendFailedException."<init>":(Ljava/lang/String;Ljava/lang/Exception;[Ljavax/mail/Address;[Ljavax/mail/Address;[Ljavax/mail/Address;)V
     113: athrow
     114: return
    Exception table:
       from    to  target type
           8    64    67   Class java/lang/Exception

  protected boolean protocolConnect(java.lang.String, int, java.lang.String, java.lang.String);
    Code:
       0: aload_0
       1: invokevirtual #86                 // Method isConnected:()Z
       4: ifeq          17
       7: new           #18                 // class java/lang/IllegalStateException
      10: dup
      11: ldc           #87                 // String Already connected
      13: invokespecial #20                 // Method java/lang/IllegalStateException."<init>":(Ljava/lang/String;)V
      16: athrow
      17: aload_3
      18: invokestatic  #88                 // Method isNullOrEmpty:(Ljava/lang/String;)Z
      21: ifne          32
      24: aload         4
      26: invokestatic  #88                 // Method isNullOrEmpty:(Ljava/lang/String;)Z
      29: ifeq          74
      32: aload_0
      33: getfield      #5                  // Field accessKey:Ljava/lang/String;
      36: invokestatic  #88                 // Method isNullOrEmpty:(Ljava/lang/String;)Z
      39: ifne          52
      42: aload_0
      43: getfield      #7                  // Field secretKey:Ljava/lang/String;
      46: invokestatic  #88                 // Method isNullOrEmpty:(Ljava/lang/String;)Z
      49: ifeq          63
      52: aload_0
      53: new           #89                 // class com/amazonaws/services/simpleemail/AmazonSimpleEmailServiceClient
      56: dup
      57: invokespecial #90                 // Method com/amazonaws/services/simpleemail/AmazonSimpleEmailServiceClient."<init>":()V
      60: putfield      #16                 // Field emailService:Lcom/amazonaws/services/simpleemail/AmazonSimpleEmailServiceClient;
      63: aload_0
      64: getfield      #5                  // Field accessKey:Ljava/lang/String;
      67: astore_3
      68: aload_0
      69: getfield      #7                  // Field secretKey:Ljava/lang/String;
      72: astore        4
      74: aload_0
      75: getfield      #16                 // Field emailService:Lcom/amazonaws/services/simpleemail/AmazonSimpleEmailServiceClient;
      78: ifnonnull     102
      81: aload_0
      82: new           #89                 // class com/amazonaws/services/simpleemail/AmazonSimpleEmailServiceClient
      85: dup
      86: new           #91                 // class com/amazonaws/auth/BasicAWSCredentials
      89: dup
      90: aload_3
      91: aload         4
      93: invokespecial #92                 // Method com/amazonaws/auth/BasicAWSCredentials."<init>":(Ljava/lang/String;Ljava/lang/String;)V
      96: invokespecial #93                 // Method com/amazonaws/services/simpleemail/AmazonSimpleEmailServiceClient."<init>":(Lcom/amazonaws/auth/AWSCredentials;)V
      99: putfield      #16                 // Field emailService:Lcom/amazonaws/services/simpleemail/AmazonSimpleEmailServiceClient;
     102: aload_1
     103: invokestatic  #88                 // Method isNullOrEmpty:(Ljava/lang/String;)Z
     106: ifne          120
     109: aload_0
     110: getfield      #16                 // Field emailService:Lcom/amazonaws/services/simpleemail/AmazonSimpleEmailServiceClient;
     113: aload_1
     114: invokevirtual #94                 // Method com/amazonaws/services/simpleemail/AmazonSimpleEmailServiceClient.setEndpoint:(Ljava/lang/String;)V
     117: goto          138
     120: aload_0
     121: getfield      #9                  // Field httpsEndpoint:Ljava/lang/String;
     124: ifnull        138
     127: aload_0
     128: getfield      #16                 // Field emailService:Lcom/amazonaws/services/simpleemail/AmazonSimpleEmailServiceClient;
     131: aload_0
     132: getfield      #9                  // Field httpsEndpoint:Ljava/lang/String;
     135: invokevirtual #94                 // Method com/amazonaws/services/simpleemail/AmazonSimpleEmailServiceClient.setEndpoint:(Ljava/lang/String;)V
     138: aload_0
     139: iconst_1
     140: invokespecial #95                 // Method javax/mail/Transport.setConnected:(Z)V
     143: iconst_1
     144: ireturn

  public void close() throws javax.mail.MessagingException;
    Code:
       0: aload_0
       1: invokespecial #96                 // Method javax/mail/Transport.close:()V
       4: aload_0
       5: aconst_null
       6: putfield      #16                 // Field emailService:Lcom/amazonaws/services/simpleemail/AmazonSimpleEmailServiceClient;
       9: return

  public java.lang.String getLastMessageId();
    Code:
       0: aload_0
       1: getfield      #83                 // Field lastMessageId:Ljava/lang/String;
       4: areturn

  private static boolean isNullOrEmpty(java.lang.String);
    Code:
       0: aload_0
       1: ifnull        11
       4: aload_0
       5: invokevirtual #97                 // Method java/lang/String.length:()I
       8: ifne          15
      11: iconst_1
      12: goto          16
      15: iconst_0
      16: ireturn

  private static boolean isNullOrEmpty(java.lang.Object[]);
    Code:
       0: aload_0
       1: ifnull        9
       4: aload_0
       5: arraylength
       6: ifne          13
       9: iconst_1
      10: goto          14
      13: iconst_0
      14: ireturn

  public <X extends com.amazonaws.AmazonWebServiceRequest> X appendUserAgent(X, java.lang.String);
    Code:
       0: aload_1
       1: invokevirtual #98                 // Method com/amazonaws/AmazonWebServiceRequest.getRequestClientOptions:()Lcom/amazonaws/RequestClientOptions;
       4: getstatic     #79                 // Field USER_AGENT:Ljava/lang/String;
       7: invokevirtual #99                 // Method com/amazonaws/RequestClientOptions.appendUserAgent:(Ljava/lang/String;)V
      10: aload_1
      11: areturn

  static {};
    Code:
       0: new           #72                 // class java/lang/StringBuilder
       3: dup
       4: invokespecial #73                 // Method java/lang/StringBuilder."<init>":()V
       7: ldc           #2                  // class com/amazonaws/services/simpleemail/AWSJavaMailTransport
       9: invokevirtual #100                // Method java/lang/Class.getName:()Ljava/lang/String;
      12: invokevirtual #75                 // Method java/lang/StringBuilder.append:(Ljava/lang/String;)Ljava/lang/StringBuilder;
      15: ldc           #101                // String /
      17: invokevirtual #75                 // Method java/lang/StringBuilder.append:(Ljava/lang/String;)Ljava/lang/StringBuilder;
      20: invokestatic  #102                // Method com/amazonaws/util/VersionInfoUtils.getVersion:()Ljava/lang/String;
      23: invokevirtual #75                 // Method java/lang/StringBuilder.append:(Ljava/lang/String;)Ljava/lang/StringBuilder;
      26: invokevirtual #77                 // Method java/lang/StringBuilder.toString:()Ljava/lang/String;
      29: putstatic     #79                 // Field USER_AGENT:Ljava/lang/String;
      32: return
}
