Compiled from "SampleRule.java"
public class org.jgroups.protocols.rules.SampleRule extends org.jgroups.protocols.rules.Rule {
  public org.jgroups.protocols.rules.SampleRule();
    Code:
       0: aload_0
       1: invokespecial #1                  // Method org/jgroups/protocols/rules/Rule."<init>":()V
       4: return

  public java.lang.String name();
    Code:
       0: ldc           #2                  // String SampleRule
       2: areturn

  public java.lang.String description();
    Code:
       0: ldc           #3                  // String Sample rule
       2: areturn

  public boolean eval();
    Code:
       0: iconst_1
       1: ireturn

  public java.lang.String condition();
    Code:
       0: ldc           #4                  // String Dummy condition
       2: areturn

  public void trigger() throws java.lang.Throwable;
    Code:
       0: getstatic     #5                  // Field java/lang/System.out:Ljava/io/PrintStream;
       3: ldc           #6                  // String SampleRule was triggered
       5: invokevirtual #7                  // Method java/io/PrintStream.println:(Ljava/lang/String;)V
       8: return
}
