Compiled from "SFTPInputStream.java"
class org.apache.hadoop.fs.sftp.SFTPInputStream extends org.apache.hadoop.fs.FSInputStream {
  public static final java.lang.String E_SEEK_NOTSUPPORTED;

  public static final java.lang.String E_CLIENT_NULL;

  public static final java.lang.String E_NULL_INPUTSTREAM;

  public static final java.lang.String E_STREAM_CLOSED;

  public static final java.lang.String E_CLIENT_NOTCONNECTED;

  private java.io.InputStream wrappedStream;

  private com.jcraft.jsch.ChannelSftp channel;

  private org.apache.hadoop.fs.FileSystem$Statistics stats;

  private boolean closed;

  private long pos;

  org.apache.hadoop.fs.sftp.SFTPInputStream(java.io.InputStream, com.jcraft.jsch.ChannelSftp, org.apache.hadoop.fs.FileSystem$Statistics);
    Code:
       0: aload_0
       1: invokespecial #1                  // Method org/apache/hadoop/fs/FSInputStream."<init>":()V
       4: aload_1
       5: ifnonnull     18
       8: new           #2                  // class java/lang/IllegalArgumentException
      11: dup
      12: ldc           #4                  // String Null InputStream
      14: invokespecial #5                  // Method java/lang/IllegalArgumentException."<init>":(Ljava/lang/String;)V
      17: athrow
      18: aload_2
      19: ifnull        29
      22: aload_2
      23: invokevirtual #6                  // Method com/jcraft/jsch/ChannelSftp.isConnected:()Z
      26: ifne          39
      29: new           #2                  // class java/lang/IllegalArgumentException
      32: dup
      33: ldc           #7                  // String SFTP client null or not connected
      35: invokespecial #5                  // Method java/lang/IllegalArgumentException."<init>":(Ljava/lang/String;)V
      38: athrow
      39: aload_0
      40: aload_1
      41: putfield      #8                  // Field wrappedStream:Ljava/io/InputStream;
      44: aload_0
      45: aload_2
      46: putfield      #9                  // Field channel:Lcom/jcraft/jsch/ChannelSftp;
      49: aload_0
      50: aload_3
      51: putfield      #10                 // Field stats:Lorg/apache/hadoop/fs/FileSystem$Statistics;
      54: aload_0
      55: lconst_0
      56: putfield      #11                 // Field pos:J
      59: aload_0
      60: iconst_0
      61: putfield      #12                 // Field closed:Z
      64: return

  public void seek(long) throws java.io.IOException;
    Code:
       0: new           #13                 // class java/io/IOException
       3: dup
       4: ldc           #14                 // String Seek not supported
       6: invokespecial #15                 // Method java/io/IOException."<init>":(Ljava/lang/String;)V
       9: athrow

  public boolean seekToNewSource(long) throws java.io.IOException;
    Code:
       0: new           #13                 // class java/io/IOException
       3: dup
       4: ldc           #14                 // String Seek not supported
       6: invokespecial #15                 // Method java/io/IOException."<init>":(Ljava/lang/String;)V
       9: athrow

  public long getPos() throws java.io.IOException;
    Code:
       0: aload_0
       1: getfield      #11                 // Field pos:J
       4: lreturn

  public synchronized int read() throws java.io.IOException;
    Code:
       0: aload_0
       1: getfield      #12                 // Field closed:Z
       4: ifeq          17
       7: new           #13                 // class java/io/IOException
      10: dup
      11: ldc           #16                 // String Stream closed
      13: invokespecial #15                 // Method java/io/IOException."<init>":(Ljava/lang/String;)V
      16: athrow
      17: aload_0
      18: getfield      #8                  // Field wrappedStream:Ljava/io/InputStream;
      21: invokevirtual #17                 // Method java/io/InputStream.read:()I
      24: istore_1
      25: iload_1
      26: iflt          39
      29: aload_0
      30: dup
      31: getfield      #11                 // Field pos:J
      34: lconst_1
      35: ladd
      36: putfield      #11                 // Field pos:J
      39: aload_0
      40: getfield      #10                 // Field stats:Lorg/apache/hadoop/fs/FileSystem$Statistics;
      43: ifnull        50
      46: iconst_1
      47: goto          51
      50: iconst_0
      51: iload_1
      52: iflt          59
      55: iconst_1
      56: goto          60
      59: iconst_0
      60: iand
      61: ifeq          72
      64: aload_0
      65: getfield      #10                 // Field stats:Lorg/apache/hadoop/fs/FileSystem$Statistics;
      68: lconst_1
      69: invokevirtual #18                 // Method org/apache/hadoop/fs/FileSystem$Statistics.incrementBytesRead:(J)V
      72: iload_1
      73: ireturn

  public synchronized int read(byte[], int, int) throws java.io.IOException;
    Code:
       0: aload_0
       1: getfield      #12                 // Field closed:Z
       4: ifeq          17
       7: new           #13                 // class java/io/IOException
      10: dup
      11: ldc           #16                 // String Stream closed
      13: invokespecial #15                 // Method java/io/IOException."<init>":(Ljava/lang/String;)V
      16: athrow
      17: aload_0
      18: getfield      #8                  // Field wrappedStream:Ljava/io/InputStream;
      21: aload_1
      22: iload_2
      23: iload_3
      24: invokevirtual #19                 // Method java/io/InputStream.read:([BII)I
      27: istore        4
      29: iload         4
      31: ifle          46
      34: aload_0
      35: dup
      36: getfield      #11                 // Field pos:J
      39: iload         4
      41: i2l
      42: ladd
      43: putfield      #11                 // Field pos:J
      46: aload_0
      47: getfield      #10                 // Field stats:Lorg/apache/hadoop/fs/FileSystem$Statistics;
      50: ifnull        57
      53: iconst_1
      54: goto          58
      57: iconst_0
      58: iload         4
      60: ifle          67
      63: iconst_1
      64: goto          68
      67: iconst_0
      68: iand
      69: ifeq          82
      72: aload_0
      73: getfield      #10                 // Field stats:Lorg/apache/hadoop/fs/FileSystem$Statistics;
      76: iload         4
      78: i2l
      79: invokevirtual #18                 // Method org/apache/hadoop/fs/FileSystem$Statistics.incrementBytesRead:(J)V
      82: iload         4
      84: ireturn

  public synchronized void close() throws java.io.IOException;
    Code:
       0: aload_0
       1: getfield      #12                 // Field closed:Z
       4: ifeq          8
       7: return
       8: aload_0
       9: invokespecial #20                 // Method org/apache/hadoop/fs/FSInputStream.close:()V
      12: aload_0
      13: iconst_1
      14: putfield      #12                 // Field closed:Z
      17: aload_0
      18: getfield      #9                  // Field channel:Lcom/jcraft/jsch/ChannelSftp;
      21: invokevirtual #6                  // Method com/jcraft/jsch/ChannelSftp.isConnected:()Z
      24: ifne          37
      27: new           #13                 // class java/io/IOException
      30: dup
      31: ldc           #21                 // String Client not connected
      33: invokespecial #15                 // Method java/io/IOException."<init>":(Ljava/lang/String;)V
      36: athrow
      37: aload_0
      38: getfield      #9                  // Field channel:Lcom/jcraft/jsch/ChannelSftp;
      41: invokevirtual #22                 // Method com/jcraft/jsch/ChannelSftp.getSession:()Lcom/jcraft/jsch/Session;
      44: astore_1
      45: aload_0
      46: getfield      #9                  // Field channel:Lcom/jcraft/jsch/ChannelSftp;
      49: invokevirtual #23                 // Method com/jcraft/jsch/ChannelSftp.disconnect:()V
      52: aload_1
      53: invokevirtual #24                 // Method com/jcraft/jsch/Session.disconnect:()V
      56: goto          72
      59: astore_1
      60: new           #13                 // class java/io/IOException
      63: dup
      64: aload_1
      65: invokestatic  #26                 // Method org/apache/hadoop/util/StringUtils.stringifyException:(Ljava/lang/Throwable;)Ljava/lang/String;
      68: invokespecial #15                 // Method java/io/IOException."<init>":(Ljava/lang/String;)V
      71: athrow
      72: return
    Exception table:
       from    to  target type
          37    56    59   Class com/jcraft/jsch/JSchException
}
