Compiled from "NettyRuntime.java"
public final class io.netty.util.NettyRuntime {
  private static final io.netty.util.NettyRuntime$AvailableProcessorsHolder holder;

  public static void setAvailableProcessors(int);
    Code:
       0: getstatic     #14                 // Field holder:Lio/netty/util/NettyRuntime$AvailableProcessorsHolder;
       3: iload_0
       4: invokevirtual #16                 // Method io/netty/util/NettyRuntime$AvailableProcessorsHolder.setAvailableProcessors:(I)V
       7: return

  public static int availableProcessors();
    Code:
       0: getstatic     #14                 // Field holder:Lio/netty/util/NettyRuntime$AvailableProcessorsHolder;
       3: invokevirtual #21                 // Method io/netty/util/NettyRuntime$AvailableProcessorsHolder.availableProcessors:()I
       6: ireturn

  private io.netty.util.NettyRuntime();
    Code:
       0: aload_0
       1: invokespecial #25                 // Method java/lang/Object."<init>":()V
       4: return

  static {};
    Code:
       0: new           #7                  // class io/netty/util/NettyRuntime$AvailableProcessorsHolder
       3: dup
       4: invokespecial #29                 // Method io/netty/util/NettyRuntime$AvailableProcessorsHolder."<init>":()V
       7: putstatic     #14                 // Field holder:Lio/netty/util/NettyRuntime$AvailableProcessorsHolder;
      10: return
}
