Compiled from "JaasKrbUtil.java"
class org.apache.kerby.kerberos.kerb.client.JaasKrbUtil$TicketCacheJaasConf extends javax.security.auth.login.Configuration {
  private java.lang.String principal;

  private java.io.File clientCredentialFile;

  org.apache.kerby.kerberos.kerb.client.JaasKrbUtil$TicketCacheJaasConf(java.lang.String, java.io.File);
    Code:
       0: aload_0
       1: invokespecial #1                  // Method javax/security/auth/login/Configuration."<init>":()V
       4: aload_0
       5: aload_1
       6: putfield      #2                  // Field principal:Ljava/lang/String;
       9: aload_0
      10: aload_2
      11: putfield      #3                  // Field clientCredentialFile:Ljava/io/File;
      14: return

  public javax.security.auth.login.AppConfigurationEntry[] getAppConfigurationEntry(java.lang.String);
    Code:
       0: new           #4                  // class java/util/HashMap
       3: dup
       4: invokespecial #5                  // Method java/util/HashMap."<init>":()V
       7: astore_2
       8: aload_2
       9: ldc           #6                  // String principal
      11: aload_0
      12: getfield      #2                  // Field principal:Ljava/lang/String;
      15: invokeinterface #7,  3            // InterfaceMethod java/util/Map.put:(Ljava/lang/Object;Ljava/lang/Object;)Ljava/lang/Object;
      20: pop
      21: aload_2
      22: ldc           #8                  // String storeKey
      24: ldc           #9                  // String false
      26: invokeinterface #7,  3            // InterfaceMethod java/util/Map.put:(Ljava/lang/Object;Ljava/lang/Object;)Ljava/lang/Object;
      31: pop
      32: aload_2
      33: ldc           #10                 // String doNotPrompt
      35: ldc           #9                  // String false
      37: invokeinterface #7,  3            // InterfaceMethod java/util/Map.put:(Ljava/lang/Object;Ljava/lang/Object;)Ljava/lang/Object;
      42: pop
      43: aload_2
      44: ldc           #11                 // String useTicketCache
      46: ldc           #12                 // String true
      48: invokeinterface #7,  3            // InterfaceMethod java/util/Map.put:(Ljava/lang/Object;Ljava/lang/Object;)Ljava/lang/Object;
      53: pop
      54: aload_2
      55: ldc           #13                 // String renewTGT
      57: ldc           #12                 // String true
      59: invokeinterface #7,  3            // InterfaceMethod java/util/Map.put:(Ljava/lang/Object;Ljava/lang/Object;)Ljava/lang/Object;
      64: pop
      65: aload_2
      66: ldc           #14                 // String refreshKrb5Config
      68: ldc           #12                 // String true
      70: invokeinterface #7,  3            // InterfaceMethod java/util/Map.put:(Ljava/lang/Object;Ljava/lang/Object;)Ljava/lang/Object;
      75: pop
      76: aload_2
      77: ldc           #15                 // String isInitiator
      79: ldc           #12                 // String true
      81: invokeinterface #7,  3            // InterfaceMethod java/util/Map.put:(Ljava/lang/Object;Ljava/lang/Object;)Ljava/lang/Object;
      86: pop
      87: aload_2
      88: ldc           #16                 // String ticketCache
      90: aload_0
      91: getfield      #3                  // Field clientCredentialFile:Ljava/io/File;
      94: invokevirtual #17                 // Method java/io/File.getAbsolutePath:()Ljava/lang/String;
      97: invokeinterface #7,  3            // InterfaceMethod java/util/Map.put:(Ljava/lang/Object;Ljava/lang/Object;)Ljava/lang/Object;
     102: pop
     103: aload_2
     104: ldc           #18                 // String debug
     106: iconst_0
     107: invokestatic  #19                 // Method java/lang/String.valueOf:(Z)Ljava/lang/String;
     110: invokeinterface #7,  3            // InterfaceMethod java/util/Map.put:(Ljava/lang/Object;Ljava/lang/Object;)Ljava/lang/Object;
     115: pop
     116: iconst_1
     117: anewarray     #20                 // class javax/security/auth/login/AppConfigurationEntry
     120: dup
     121: iconst_0
     122: new           #20                 // class javax/security/auth/login/AppConfigurationEntry
     125: dup
     126: invokestatic  #21                 // Method org/apache/kerby/kerberos/kerb/client/JaasKrbUtil.access$000:()Ljava/lang/String;
     129: getstatic     #22                 // Field javax/security/auth/login/AppConfigurationEntry$LoginModuleControlFlag.REQUIRED:Ljavax/security/auth/login/AppConfigurationEntry$LoginModuleControlFlag;
     132: aload_2
     133: invokespecial #23                 // Method javax/security/auth/login/AppConfigurationEntry."<init>":(Ljava/lang/String;Ljavax/security/auth/login/AppConfigurationEntry$LoginModuleControlFlag;Ljava/util/Map;)V
     136: aastore
     137: areturn
}
