Compiled from "MetroJAXBUtil.java"
public class org.jpmml.model.metro.MetroJAXBUtil {
  private org.jpmml.model.metro.MetroJAXBUtil();
    Code:
       0: aload_0
       1: invokespecial #1                  // Method java/lang/Object."<init>":()V
       4: return

  public static void marshalPMML(org.dmg.pmml.PMML, java.io.OutputStream) throws javax.xml.bind.JAXBException;
    Code:
       0: aload_0
       1: aload_1
       2: invokestatic  #2                  // Method marshal:(Lorg/dmg/pmml/PMMLObject;Ljava/io/OutputStream;)V
       5: return

  public static void marshal(org.dmg.pmml.PMMLObject, java.io.OutputStream) throws javax.xml.bind.JAXBException;
    Code:
       0: invokestatic  #3                  // Method org/jpmml/model/JAXBUtil.getContext:()Ljavax/xml/bind/JAXBContext;
       3: checkcast     #4                  // class com/sun/xml/bind/v2/runtime/JAXBContextImpl
       6: astore_2
       7: goto          22
      10: astore_3
      11: new           #6                  // class java/lang/IllegalStateException
      14: dup
      15: ldc           #7                  // String Not a GlassFish Metro runtime
      17: aload_3
      18: invokespecial #8                  // Method java/lang/IllegalStateException."<init>":(Ljava/lang/String;Ljava/lang/Throwable;)V
      21: athrow
      22: aload_2
      23: invokevirtual #9                  // Method com/sun/xml/bind/v2/runtime/JAXBContextImpl.createMarshaller:()Lcom/sun/xml/bind/v2/runtime/MarshallerImpl;
      26: astore_3
      27: new           #10                 // class org/jpmml/model/metro/PrettyUTF8XmlOutput
      30: dup
      31: aload_1
      32: aload_2
      33: invokevirtual #11                 // Method com/sun/xml/bind/v2/runtime/JAXBContextImpl.getUTF8NameTable:()[Lcom/sun/xml/bind/v2/runtime/output/Encoded;
      36: invokespecial #12                 // Method org/jpmml/model/metro/PrettyUTF8XmlOutput."<init>":(Ljava/io/OutputStream;[Lcom/sun/xml/bind/v2/runtime/output/Encoded;)V
      39: astore        4
      41: aload_3
      42: aload_0
      43: aload         4
      45: invokevirtual #13                 // Method com/sun/xml/bind/v2/runtime/MarshallerImpl.marshal:(Ljava/lang/Object;Lcom/sun/xml/bind/v2/runtime/output/XmlOutput;)V
      48: return
    Exception table:
       from    to  target type
           0     7    10   Class java/lang/ClassCastException
}
