Compiled from "ScanningCoordinator.java"
public class org.hibernate.boot.model.process.internal.ScanningCoordinator {
  private static final org.jboss.logging.Logger log;

  public static final org.hibernate.boot.model.process.internal.ScanningCoordinator INSTANCE;

  private static final java.lang.Class[] SINGLE_ARG;

  private org.hibernate.boot.model.process.internal.ScanningCoordinator();
    Code:
       0: aload_0
       1: invokespecial #1                  // Method java/lang/Object."<init>":()V
       4: return

  public void coordinateScan(org.hibernate.boot.model.process.internal.ManagedResourcesImpl, org.hibernate.boot.spi.MetadataBuildingOptions, org.hibernate.boot.spi.XmlMappingBinderAccess);
    Code:
       0: aload_2
       1: invokeinterface #2,  1            // InterfaceMethod org/hibernate/boot/spi/MetadataBuildingOptions.getScanEnvironment:()Lorg/hibernate/boot/archive/scan/spi/ScanEnvironment;
       6: ifnonnull     10
       9: return
      10: aload_2
      11: invokeinterface #3,  1            // InterfaceMethod org/hibernate/boot/spi/MetadataBuildingOptions.getServiceRegistry:()Lorg/hibernate/boot/registry/StandardServiceRegistry;
      16: ldc           #4                  // class org/hibernate/boot/registry/classloading/spi/ClassLoaderService
      18: invokeinterface #5,  2            // InterfaceMethod org/hibernate/boot/registry/StandardServiceRegistry.getService:(Ljava/lang/Class;)Lorg/hibernate/service/Service;
      23: checkcast     #4                  // class org/hibernate/boot/registry/classloading/spi/ClassLoaderService
      26: astore        4
      28: new           #6                  // class org/hibernate/boot/internal/ClassLoaderAccessImpl
      31: dup
      32: aload_2
      33: invokeinterface #7,  1            // InterfaceMethod org/hibernate/boot/spi/MetadataBuildingOptions.getTempClassLoader:()Ljava/lang/ClassLoader;
      38: aload         4
      40: invokespecial #8                  // Method org/hibernate/boot/internal/ClassLoaderAccessImpl."<init>":(Ljava/lang/ClassLoader;Lorg/hibernate/boot/registry/classloading/spi/ClassLoaderService;)V
      43: astore        5
      45: aload_2
      46: aload         5
      48: invokestatic  #9                  // Method buildScanner:(Lorg/hibernate/boot/spi/MetadataBuildingOptions;Lorg/hibernate/boot/spi/ClassLoaderAccess;)Lorg/hibernate/boot/archive/scan/spi/Scanner;
      51: astore        6
      53: aload         6
      55: aload_2
      56: invokeinterface #2,  1            // InterfaceMethod org/hibernate/boot/spi/MetadataBuildingOptions.getScanEnvironment:()Lorg/hibernate/boot/archive/scan/spi/ScanEnvironment;
      61: aload_2
      62: invokeinterface #10,  1           // InterfaceMethod org/hibernate/boot/spi/MetadataBuildingOptions.getScanOptions:()Lorg/hibernate/boot/archive/scan/spi/ScanOptions;
      67: getstatic     #11                 // Field org/hibernate/boot/archive/scan/internal/StandardScanParameters.INSTANCE:Lorg/hibernate/boot/archive/scan/internal/StandardScanParameters;
      70: invokeinterface #12,  4           // InterfaceMethod org/hibernate/boot/archive/scan/spi/Scanner.scan:(Lorg/hibernate/boot/archive/scan/spi/ScanEnvironment;Lorg/hibernate/boot/archive/scan/spi/ScanOptions;Lorg/hibernate/boot/archive/scan/spi/ScanParameters;)Lorg/hibernate/boot/archive/scan/spi/ScanResult;
      75: astore        7
      77: aload_0
      78: aload_1
      79: aload         7
      81: aload_2
      82: aload_3
      83: invokevirtual #13                 // Method applyScanResultsToManagedResources:(Lorg/hibernate/boot/model/process/internal/ManagedResourcesImpl;Lorg/hibernate/boot/archive/scan/spi/ScanResult;Lorg/hibernate/boot/spi/MetadataBuildingOptions;Lorg/hibernate/boot/spi/XmlMappingBinderAccess;)V
      86: return

  private static org.hibernate.boot.archive.scan.spi.Scanner buildScanner(org.hibernate.boot.spi.MetadataBuildingOptions, org.hibernate.boot.spi.ClassLoaderAccess);
    Code:
       0: aload_0
       1: invokeinterface #14,  1           // InterfaceMethod org/hibernate/boot/spi/MetadataBuildingOptions.getScanner:()Ljava/lang/Object;
       6: astore_2
       7: aload_0
       8: invokeinterface #15,  1           // InterfaceMethod org/hibernate/boot/spi/MetadataBuildingOptions.getArchiveDescriptorFactory:()Lorg/hibernate/boot/archive/spi/ArchiveDescriptorFactory;
      13: astore_3
      14: aload_2
      15: ifnonnull     39
      18: aload_3
      19: ifnonnull     30
      22: new           #16                 // class org/hibernate/boot/archive/scan/internal/StandardScanner
      25: dup
      26: invokespecial #17                 // Method org/hibernate/boot/archive/scan/internal/StandardScanner."<init>":()V
      29: areturn
      30: new           #16                 // class org/hibernate/boot/archive/scan/internal/StandardScanner
      33: dup
      34: aload_3
      35: invokespecial #18                 // Method org/hibernate/boot/archive/scan/internal/StandardScanner."<init>":(Lorg/hibernate/boot/archive/spi/ArchiveDescriptorFactory;)V
      38: areturn
      39: ldc           #19                 // class org/hibernate/boot/archive/scan/spi/Scanner
      41: aload_2
      42: invokevirtual #20                 // Method java/lang/Class.isInstance:(Ljava/lang/Object;)Z
      45: ifeq          67
      48: aload_3
      49: ifnull        62
      52: new           #21                 // class java/lang/IllegalStateException
      55: dup
      56: ldc           #22                 // String A Scanner instance and an ArchiveDescriptorFactory were both specified; please specify one or the other, or if you need to supply both, Scanner class to use (assuming it has a constructor accepting a ArchiveDescriptorFactory).  Alternatively, just pass the ArchiveDescriptorFactory during your own Scanner constructor assuming it is statically known.
      58: invokespecial #23                 // Method java/lang/IllegalStateException."<init>":(Ljava/lang/String;)V
      61: athrow
      62: aload_2
      63: checkcast     #19                 // class org/hibernate/boot/archive/scan/spi/Scanner
      66: areturn
      67: ldc           #24                 // class java/lang/Class
      69: aload_2
      70: invokevirtual #20                 // Method java/lang/Class.isInstance:(Ljava/lang/Object;)Z
      73: ifeq          85
      76: aload_2
      77: checkcast     #24                 // class java/lang/Class
      80: astore        4
      82: goto          97
      85: aload_1
      86: aload_2
      87: invokevirtual #25                 // Method java/lang/Object.toString:()Ljava/lang/String;
      90: invokeinterface #26,  2           // InterfaceMethod org/hibernate/boot/spi/ClassLoaderAccess.classForName:(Ljava/lang/String;)Ljava/lang/Class;
      95: astore        4
      97: aload_3
      98: ifnull        180
     101: aload         4
     103: getstatic     #27                 // Field SINGLE_ARG:[Ljava/lang/Class;
     106: invokevirtual #28                 // Method java/lang/Class.getConstructor:([Ljava/lang/Class;)Ljava/lang/reflect/Constructor;
     109: astore        5
     111: aload         5
     113: iconst_1
     114: anewarray     #29                 // class java/lang/Object
     117: dup
     118: iconst_0
     119: aload_3
     120: aastore
     121: invokevirtual #30                 // Method java/lang/reflect/Constructor.newInstance:([Ljava/lang/Object;)Ljava/lang/Object;
     124: checkcast     #19                 // class org/hibernate/boot/archive/scan/spi/Scanner
     127: areturn
     128: astore        6
     130: new           #21                 // class java/lang/IllegalStateException
     133: dup
     134: new           #32                 // class java/lang/StringBuilder
     137: dup
     138: invokespecial #33                 // Method java/lang/StringBuilder."<init>":()V
     141: ldc           #34                 // String Error trying to instantiate custom specified Scanner [
     143: invokevirtual #35                 // Method java/lang/StringBuilder.append:(Ljava/lang/String;)Ljava/lang/StringBuilder;
     146: aload         4
     148: invokevirtual #36                 // Method java/lang/Class.getName:()Ljava/lang/String;
     151: invokevirtual #35                 // Method java/lang/StringBuilder.append:(Ljava/lang/String;)Ljava/lang/StringBuilder;
     154: ldc           #37                 // String ]
     156: invokevirtual #35                 // Method java/lang/StringBuilder.append:(Ljava/lang/String;)Ljava/lang/StringBuilder;
     159: invokevirtual #38                 // Method java/lang/StringBuilder.toString:()Ljava/lang/String;
     162: aload         6
     164: invokespecial #39                 // Method java/lang/IllegalStateException."<init>":(Ljava/lang/String;Ljava/lang/Throwable;)V
     167: athrow
     168: astore        5
     170: new           #41                 // class java/lang/IllegalArgumentException
     173: dup
     174: ldc           #42                 // String Configuration named a custom Scanner and a custom ArchiveDescriptorFactory, but Scanner impl did not define a constructor accepting ArchiveDescriptorFactory
     176: invokespecial #43                 // Method java/lang/IllegalArgumentException."<init>":(Ljava/lang/String;)V
     179: athrow
     180: aload         4
     182: getstatic     #27                 // Field SINGLE_ARG:[Ljava/lang/Class;
     185: invokevirtual #28                 // Method java/lang/Class.getConstructor:([Ljava/lang/Class;)Ljava/lang/reflect/Constructor;
     188: astore        5
     190: aload         5
     192: iconst_1
     193: anewarray     #29                 // class java/lang/Object
     196: dup
     197: iconst_0
     198: getstatic     #44                 // Field org/hibernate/boot/archive/internal/StandardArchiveDescriptorFactory.INSTANCE:Lorg/hibernate/boot/archive/internal/StandardArchiveDescriptorFactory;
     201: aastore
     202: invokevirtual #30                 // Method java/lang/reflect/Constructor.newInstance:([Ljava/lang/Object;)Ljava/lang/Object;
     205: checkcast     #19                 // class org/hibernate/boot/archive/scan/spi/Scanner
     208: areturn
     209: astore        6
     211: new           #21                 // class java/lang/IllegalStateException
     214: dup
     215: new           #32                 // class java/lang/StringBuilder
     218: dup
     219: invokespecial #33                 // Method java/lang/StringBuilder."<init>":()V
     222: ldc           #34                 // String Error trying to instantiate custom specified Scanner [
     224: invokevirtual #35                 // Method java/lang/StringBuilder.append:(Ljava/lang/String;)Ljava/lang/StringBuilder;
     227: aload         4
     229: invokevirtual #36                 // Method java/lang/Class.getName:()Ljava/lang/String;
     232: invokevirtual #35                 // Method java/lang/StringBuilder.append:(Ljava/lang/String;)Ljava/lang/StringBuilder;
     235: ldc           #37                 // String ]
     237: invokevirtual #35                 // Method java/lang/StringBuilder.append:(Ljava/lang/String;)Ljava/lang/StringBuilder;
     240: invokevirtual #38                 // Method java/lang/StringBuilder.toString:()Ljava/lang/String;
     243: aload         6
     245: invokespecial #39                 // Method java/lang/IllegalStateException."<init>":(Ljava/lang/String;Ljava/lang/Throwable;)V
     248: athrow
     249: astore        5
     251: aload         4
     253: iconst_0
     254: anewarray     #24                 // class java/lang/Class
     257: invokevirtual #28                 // Method java/lang/Class.getConstructor:([Ljava/lang/Class;)Ljava/lang/reflect/Constructor;
     260: astore        6
     262: aload         6
     264: iconst_0
     265: anewarray     #29                 // class java/lang/Object
     268: invokevirtual #30                 // Method java/lang/reflect/Constructor.newInstance:([Ljava/lang/Object;)Ljava/lang/Object;
     271: checkcast     #19                 // class org/hibernate/boot/archive/scan/spi/Scanner
     274: areturn
     275: astore        7
     277: new           #21                 // class java/lang/IllegalStateException
     280: dup
     281: new           #32                 // class java/lang/StringBuilder
     284: dup
     285: invokespecial #33                 // Method java/lang/StringBuilder."<init>":()V
     288: ldc           #34                 // String Error trying to instantiate custom specified Scanner [
     290: invokevirtual #35                 // Method java/lang/StringBuilder.append:(Ljava/lang/String;)Ljava/lang/StringBuilder;
     293: aload         4
     295: invokevirtual #36                 // Method java/lang/Class.getName:()Ljava/lang/String;
     298: invokevirtual #35                 // Method java/lang/StringBuilder.append:(Ljava/lang/String;)Ljava/lang/StringBuilder;
     301: ldc           #37                 // String ]
     303: invokevirtual #35                 // Method java/lang/StringBuilder.append:(Ljava/lang/String;)Ljava/lang/StringBuilder;
     306: invokevirtual #38                 // Method java/lang/StringBuilder.toString:()Ljava/lang/String;
     309: aload         7
     311: invokespecial #39                 // Method java/lang/IllegalStateException."<init>":(Ljava/lang/String;Ljava/lang/Throwable;)V
     314: athrow
     315: astore        6
     317: new           #41                 // class java/lang/IllegalArgumentException
     320: dup
     321: ldc           #45                 // String Configuration named a custom Scanner, but we were unable to locate an appropriate constructor
     323: invokespecial #43                 // Method java/lang/IllegalArgumentException."<init>":(Ljava/lang/String;)V
     326: athrow
    Exception table:
       from    to  target type
         111   127   128   Class java/lang/Exception
         101   127   168   Class java/lang/NoSuchMethodException
         128   168   168   Class java/lang/NoSuchMethodException
         190   208   209   Class java/lang/Exception
         180   208   249   Class java/lang/NoSuchMethodException
         209   249   249   Class java/lang/NoSuchMethodException
         262   274   275   Class java/lang/Exception
         251   274   315   Class java/lang/NoSuchMethodException
         275   315   315   Class java/lang/NoSuchMethodException

  public void applyScanResultsToManagedResources(org.hibernate.boot.model.process.internal.ManagedResourcesImpl, org.hibernate.boot.archive.scan.spi.ScanResult, org.hibernate.boot.spi.MetadataBuildingOptions, org.hibernate.boot.spi.XmlMappingBinderAccess);
    Code:
       0: aload_3
       1: invokeinterface #2,  1            // InterfaceMethod org/hibernate/boot/spi/MetadataBuildingOptions.getScanEnvironment:()Lorg/hibernate/boot/archive/scan/spi/ScanEnvironment;
       6: astore        5
       8: aload_3
       9: invokeinterface #3,  1            // InterfaceMethod org/hibernate/boot/spi/MetadataBuildingOptions.getServiceRegistry:()Lorg/hibernate/boot/registry/StandardServiceRegistry;
      14: astore        6
      16: aload         6
      18: ldc           #4                  // class org/hibernate/boot/registry/classloading/spi/ClassLoaderService
      20: invokeinterface #46,  2           // InterfaceMethod org/hibernate/service/ServiceRegistry.getService:(Ljava/lang/Class;)Lorg/hibernate/service/Service;
      25: checkcast     #4                  // class org/hibernate/boot/registry/classloading/spi/ClassLoaderService
      28: astore        7
      30: new           #47                 // class java/util/HashSet
      33: dup
      34: invokespecial #48                 // Method java/util/HashSet."<init>":()V
      37: astore        8
      39: aload         5
      41: invokeinterface #49,  1           // InterfaceMethod org/hibernate/boot/archive/scan/spi/ScanEnvironment.getExplicitlyListedMappingFiles:()Ljava/util/List;
      46: astore        9
      48: aload         9
      50: ifnull        63
      53: aload         8
      55: aload         9
      57: invokeinterface #50,  2           // InterfaceMethod java/util/Set.addAll:(Ljava/util/Collection;)Z
      62: pop
      63: aload_2
      64: invokeinterface #51,  1           // InterfaceMethod org/hibernate/boot/archive/scan/spi/ScanResult.getLocatedMappingFiles:()Ljava/util/Set;
      69: invokeinterface #52,  1           // InterfaceMethod java/util/Set.iterator:()Ljava/util/Iterator;
      74: astore        10
      76: aload         10
      78: invokeinterface #53,  1           // InterfaceMethod java/util/Iterator.hasNext:()Z
      83: ifeq          132
      86: aload         10
      88: invokeinterface #54,  1           // InterfaceMethod java/util/Iterator.next:()Ljava/lang/Object;
      93: checkcast     #55                 // class org/hibernate/boot/archive/scan/spi/MappingFileDescriptor
      96: astore        11
      98: aload_1
      99: aload         4
     101: aload         11
     103: invokeinterface #56,  1           // InterfaceMethod org/hibernate/boot/archive/scan/spi/MappingFileDescriptor.getStreamAccess:()Lorg/hibernate/boot/archive/spi/InputStreamAccess;
     108: invokevirtual #57                 // Method org/hibernate/boot/spi/XmlMappingBinderAccess.bind:(Lorg/hibernate/boot/archive/spi/InputStreamAccess;)Lorg/hibernate/boot/jaxb/spi/Binding;
     111: invokevirtual #58                 // Method org/hibernate/boot/model/process/internal/ManagedResourcesImpl.addXmlBinding:(Lorg/hibernate/boot/jaxb/spi/Binding;)V
     114: aload         8
     116: aload         11
     118: invokeinterface #59,  1           // InterfaceMethod org/hibernate/boot/archive/scan/spi/MappingFileDescriptor.getName:()Ljava/lang/String;
     123: invokeinterface #60,  2           // InterfaceMethod java/util/Set.remove:(Ljava/lang/Object;)Z
     128: pop
     129: goto          76
     132: aload         8
     134: invokeinterface #52,  1           // InterfaceMethod java/util/Set.iterator:()Ljava/util/Iterator;
     139: astore        10
     141: aload         10
     143: invokeinterface #53,  1           // InterfaceMethod java/util/Iterator.hasNext:()Z
     148: ifeq          244
     151: aload         10
     153: invokeinterface #54,  1           // InterfaceMethod java/util/Iterator.next:()Ljava/lang/Object;
     158: checkcast     #61                 // class java/lang/String
     161: astore        11
     163: aload         7
     165: aload         11
     167: invokeinterface #62,  2           // InterfaceMethod org/hibernate/boot/registry/classloading/spi/ClassLoaderService.locateResource:(Ljava/lang/String;)Ljava/net/URL;
     172: astore        12
     174: aload         12
     176: ifnonnull     219
     179: new           #63                 // class org/hibernate/boot/MappingException
     182: dup
     183: new           #32                 // class java/lang/StringBuilder
     186: dup
     187: invokespecial #33                 // Method java/lang/StringBuilder."<init>":()V
     190: ldc           #64                 // String Unable to resolve explicitly named mapping-file :
     192: invokevirtual #35                 // Method java/lang/StringBuilder.append:(Ljava/lang/String;)Ljava/lang/StringBuilder;
     195: aload         11
     197: invokevirtual #35                 // Method java/lang/StringBuilder.append:(Ljava/lang/String;)Ljava/lang/StringBuilder;
     200: invokevirtual #38                 // Method java/lang/StringBuilder.toString:()Ljava/lang/String;
     203: new           #65                 // class org/hibernate/boot/jaxb/Origin
     206: dup
     207: getstatic     #66                 // Field org/hibernate/boot/jaxb/SourceType.RESOURCE:Lorg/hibernate/boot/jaxb/SourceType;
     210: aload         11
     212: invokespecial #67                 // Method org/hibernate/boot/jaxb/Origin."<init>":(Lorg/hibernate/boot/jaxb/SourceType;Ljava/lang/String;)V
     215: invokespecial #68                 // Method org/hibernate/boot/MappingException."<init>":(Ljava/lang/String;Lorg/hibernate/boot/jaxb/Origin;)V
     218: athrow
     219: new           #69                 // class org/hibernate/boot/archive/internal/UrlInputStreamAccess
     222: dup
     223: aload         12
     225: invokespecial #70                 // Method org/hibernate/boot/archive/internal/UrlInputStreamAccess."<init>":(Ljava/net/URL;)V
     228: astore        13
     230: aload_1
     231: aload         4
     233: aload         13
     235: invokevirtual #57                 // Method org/hibernate/boot/spi/XmlMappingBinderAccess.bind:(Lorg/hibernate/boot/archive/spi/InputStreamAccess;)Lorg/hibernate/boot/jaxb/spi/Binding;
     238: invokevirtual #58                 // Method org/hibernate/boot/model/process/internal/ManagedResourcesImpl.addXmlBinding:(Lorg/hibernate/boot/jaxb/spi/Binding;)V
     241: goto          141
     244: aload         5
     246: invokeinterface #71,  1           // InterfaceMethod org/hibernate/boot/archive/scan/spi/ScanEnvironment.getExplicitlyListedClassNames:()Ljava/util/List;
     251: ifnonnull     264
     254: new           #72                 // class java/util/ArrayList
     257: dup
     258: invokespecial #73                 // Method java/util/ArrayList."<init>":()V
     261: goto          278
     264: new           #72                 // class java/util/ArrayList
     267: dup
     268: aload         5
     270: invokeinterface #71,  1           // InterfaceMethod org/hibernate/boot/archive/scan/spi/ScanEnvironment.getExplicitlyListedClassNames:()Ljava/util/List;
     275: invokespecial #74                 // Method java/util/ArrayList."<init>":(Ljava/util/Collection;)V
     278: astore        10
     280: aload_2
     281: invokeinterface #75,  1           // InterfaceMethod org/hibernate/boot/archive/scan/spi/ScanResult.getLocatedClasses:()Ljava/util/Set;
     286: invokeinterface #52,  1           // InterfaceMethod java/util/Set.iterator:()Ljava/util/Iterator;
     291: astore        11
     293: aload         11
     295: invokeinterface #53,  1           // InterfaceMethod java/util/Iterator.hasNext:()Z
     300: ifeq          394
     303: aload         11
     305: invokeinterface #54,  1           // InterfaceMethod java/util/Iterator.next:()Ljava/lang/Object;
     310: checkcast     #76                 // class org/hibernate/boot/archive/scan/spi/ClassDescriptor
     313: astore        12
     315: aload         12
     317: invokeinterface #77,  1           // InterfaceMethod org/hibernate/boot/archive/scan/spi/ClassDescriptor.getCategorization:()Lorg/hibernate/boot/archive/scan/spi/ClassDescriptor$Categorization;
     322: getstatic     #78                 // Field org/hibernate/boot/archive/scan/spi/ClassDescriptor$Categorization.CONVERTER:Lorg/hibernate/boot/archive/scan/spi/ClassDescriptor$Categorization;
     325: if_acmpne     352
     328: aload_1
     329: aload         7
     331: aload         12
     333: invokeinterface #79,  1           // InterfaceMethod org/hibernate/boot/archive/scan/spi/ClassDescriptor.getName:()Ljava/lang/String;
     338: invokeinterface #80,  2           // InterfaceMethod org/hibernate/boot/registry/classloading/spi/ClassLoaderService.classForName:(Ljava/lang/String;)Ljava/lang/Class;
     343: invokestatic  #81                 // Method org/hibernate/cfg/AttributeConverterDefinition.from:(Ljava/lang/Class;)Lorg/hibernate/cfg/AttributeConverterDefinition;
     346: invokevirtual #82                 // Method org/hibernate/boot/model/process/internal/ManagedResourcesImpl.addAttributeConverterDefinition:(Lorg/hibernate/cfg/AttributeConverterDefinition;)V
     349: goto          376
     352: aload         12
     354: invokeinterface #77,  1           // InterfaceMethod org/hibernate/boot/archive/scan/spi/ClassDescriptor.getCategorization:()Lorg/hibernate/boot/archive/scan/spi/ClassDescriptor$Categorization;
     359: getstatic     #83                 // Field org/hibernate/boot/archive/scan/spi/ClassDescriptor$Categorization.MODEL:Lorg/hibernate/boot/archive/scan/spi/ClassDescriptor$Categorization;
     362: if_acmpne     376
     365: aload_1
     366: aload         12
     368: invokeinterface #79,  1           // InterfaceMethod org/hibernate/boot/archive/scan/spi/ClassDescriptor.getName:()Ljava/lang/String;
     373: invokevirtual #84                 // Method org/hibernate/boot/model/process/internal/ManagedResourcesImpl.addAnnotatedClassName:(Ljava/lang/String;)V
     376: aload         10
     378: aload         12
     380: invokeinterface #79,  1           // InterfaceMethod org/hibernate/boot/archive/scan/spi/ClassDescriptor.getName:()Ljava/lang/String;
     385: invokeinterface #85,  2           // InterfaceMethod java/util/List.remove:(Ljava/lang/Object;)Z
     390: pop
     391: goto          293
     394: aload_2
     395: invokeinterface #86,  1           // InterfaceMethod org/hibernate/boot/archive/scan/spi/ScanResult.getLocatedPackages:()Ljava/util/Set;
     400: invokeinterface #52,  1           // InterfaceMethod java/util/Set.iterator:()Ljava/util/Iterator;
     405: astore        11
     407: aload         11
     409: invokeinterface #53,  1           // InterfaceMethod java/util/Iterator.hasNext:()Z
     414: ifeq          458
     417: aload         11
     419: invokeinterface #54,  1           // InterfaceMethod java/util/Iterator.next:()Ljava/lang/Object;
     424: checkcast     #87                 // class org/hibernate/boot/archive/scan/spi/PackageDescriptor
     427: astore        12
     429: aload_1
     430: aload         12
     432: invokeinterface #88,  1           // InterfaceMethod org/hibernate/boot/archive/scan/spi/PackageDescriptor.getName:()Ljava/lang/String;
     437: invokevirtual #89                 // Method org/hibernate/boot/model/process/internal/ManagedResourcesImpl.addAnnotatedPackageName:(Ljava/lang/String;)V
     440: aload         10
     442: aload         12
     444: invokeinterface #88,  1           // InterfaceMethod org/hibernate/boot/archive/scan/spi/PackageDescriptor.getName:()Ljava/lang/String;
     449: invokeinterface #85,  2           // InterfaceMethod java/util/List.remove:(Ljava/lang/Object;)Z
     454: pop
     455: goto          407
     458: aload         10
     460: invokeinterface #90,  1           // InterfaceMethod java/util/List.iterator:()Ljava/util/Iterator;
     465: astore        11
     467: aload         11
     469: invokeinterface #53,  1           // InterfaceMethod java/util/Iterator.hasNext:()Z
     474: ifeq          620
     477: aload         11
     479: invokeinterface #54,  1           // InterfaceMethod java/util/Iterator.next:()Ljava/lang/Object;
     484: checkcast     #61                 // class java/lang/String
     487: astore        12
     489: new           #32                 // class java/lang/StringBuilder
     492: dup
     493: invokespecial #33                 // Method java/lang/StringBuilder."<init>":()V
     496: aload         12
     498: bipush        46
     500: bipush        47
     502: invokevirtual #91                 // Method java/lang/String.replace:(CC)Ljava/lang/String;
     505: invokevirtual #35                 // Method java/lang/StringBuilder.append:(Ljava/lang/String;)Ljava/lang/StringBuilder;
     508: ldc           #92                 // String .class
     510: invokevirtual #35                 // Method java/lang/StringBuilder.append:(Ljava/lang/String;)Ljava/lang/StringBuilder;
     513: invokevirtual #38                 // Method java/lang/StringBuilder.toString:()Ljava/lang/String;
     516: astore        13
     518: aload         7
     520: aload         13
     522: invokeinterface #62,  2           // InterfaceMethod org/hibernate/boot/registry/classloading/spi/ClassLoaderService.locateResource:(Ljava/lang/String;)Ljava/net/URL;
     527: astore        14
     529: aload         14
     531: ifnull        543
     534: aload_1
     535: aload         12
     537: invokevirtual #84                 // Method org/hibernate/boot/model/process/internal/ManagedResourcesImpl.addAnnotatedClassName:(Ljava/lang/String;)V
     540: goto          467
     543: new           #32                 // class java/lang/StringBuilder
     546: dup
     547: invokespecial #33                 // Method java/lang/StringBuilder."<init>":()V
     550: aload         12
     552: bipush        46
     554: bipush        47
     556: invokevirtual #91                 // Method java/lang/String.replace:(CC)Ljava/lang/String;
     559: invokevirtual #35                 // Method java/lang/StringBuilder.append:(Ljava/lang/String;)Ljava/lang/StringBuilder;
     562: ldc           #93                 // String /package-info.class
     564: invokevirtual #35                 // Method java/lang/StringBuilder.append:(Ljava/lang/String;)Ljava/lang/StringBuilder;
     567: invokevirtual #38                 // Method java/lang/StringBuilder.toString:()Ljava/lang/String;
     570: astore        15
     572: aload         7
     574: aload         15
     576: invokeinterface #62,  2           // InterfaceMethod org/hibernate/boot/registry/classloading/spi/ClassLoaderService.locateResource:(Ljava/lang/String;)Ljava/net/URL;
     581: astore        16
     583: aload         16
     585: ifnull        597
     588: aload_1
     589: aload         12
     591: invokevirtual #89                 // Method org/hibernate/boot/model/process/internal/ManagedResourcesImpl.addAnnotatedPackageName:(Ljava/lang/String;)V
     594: goto          467
     597: getstatic     #94                 // Field log:Lorg/jboss/logging/Logger;
     600: ldc           #95                 // String Unable to resolve class [%s] named in persistence unit [%s]
     602: aload         12
     604: aload         5
     606: invokeinterface #96,  1           // InterfaceMethod org/hibernate/boot/archive/scan/spi/ScanEnvironment.getRootUrl:()Ljava/net/URL;
     611: invokevirtual #97                 // Method java/net/URL.toExternalForm:()Ljava/lang/String;
     614: invokevirtual #98                 // Method org/jboss/logging/Logger.debugf:(Ljava/lang/String;Ljava/lang/Object;Ljava/lang/Object;)V
     617: goto          467
     620: return

  static {};
    Code:
       0: ldc           #99                 // class org/hibernate/boot/model/process/internal/ScanningCoordinator
       2: invokestatic  #100                // Method org/jboss/logging/Logger.getLogger:(Ljava/lang/Class;)Lorg/jboss/logging/Logger;
       5: putstatic     #94                 // Field log:Lorg/jboss/logging/Logger;
       8: new           #99                 // class org/hibernate/boot/model/process/internal/ScanningCoordinator
      11: dup
      12: invokespecial #101                // Method "<init>":()V
      15: putstatic     #102                // Field INSTANCE:Lorg/hibernate/boot/model/process/internal/ScanningCoordinator;
      18: iconst_1
      19: anewarray     #24                 // class java/lang/Class
      22: dup
      23: iconst_0
      24: ldc           #103                // class org/hibernate/boot/archive/spi/ArchiveDescriptorFactory
      26: aastore
      27: putstatic     #27                 // Field SINGLE_ARG:[Ljava/lang/Class;
      30: return
}
