Compiled from "EncryptionCipherSuitePredicate.java"
final class org.wildfly.security.ssl.EncryptionCipherSuitePredicate extends org.wildfly.security.ssl.CipherSuitePredicate {
  private final java.util.EnumSet<org.wildfly.security.ssl.Encryption> set;

  org.wildfly.security.ssl.EncryptionCipherSuitePredicate(java.util.EnumSet<org.wildfly.security.ssl.Encryption>);
    Code:
       0: aload_0
       1: invokespecial #1                  // Method org/wildfly/security/ssl/CipherSuitePredicate."<init>":()V
       4: aload_0
       5: aload_1
       6: putfield      #2                  // Field set:Ljava/util/EnumSet;
       9: return

  public boolean test(org.wildfly.security.ssl.MechanismDatabase$Entry);
    Code:
       0: aload_0
       1: getfield      #2                  // Field set:Ljava/util/EnumSet;
       4: aload_1
       5: invokevirtual #3                  // Method org/wildfly/security/ssl/MechanismDatabase$Entry.getEncryption:()Lorg/wildfly/security/ssl/Encryption;
       8: invokevirtual #4                  // Method java/util/EnumSet.contains:(Ljava/lang/Object;)Z
      11: ireturn

  boolean isAlwaysTrue();
    Code:
       0: aload_0
       1: getfield      #2                  // Field set:Ljava/util/EnumSet;
       4: invokevirtual #5                  // Method java/util/EnumSet.size:()I
       7: getstatic     #6                  // Field org/wildfly/security/ssl/Encryption.fullSize:I
      10: if_icmpne     17
      13: iconst_1
      14: goto          18
      17: iconst_0
      18: ireturn

  boolean isAlwaysFalse();
    Code:
       0: aload_0
       1: getfield      #2                  // Field set:Ljava/util/EnumSet;
       4: invokevirtual #7                  // Method java/util/EnumSet.isEmpty:()Z
       7: ireturn
}
