Compiled from "AnnotatedConstructor.java"
final class io.dekorate.deps.jackson.databind.introspect.AnnotatedConstructor$Serialization implements java.io.Serializable {
  private static final long serialVersionUID;

  protected java.lang.Class<?> clazz;

  protected java.lang.Class<?>[] args;

  public io.dekorate.deps.jackson.databind.introspect.AnnotatedConstructor$Serialization(java.lang.reflect.Constructor<?>);
    Code:
       0: aload_0
       1: invokespecial #26                 // Method java/lang/Object."<init>":()V
       4: aload_0
       5: aload_1
       6: invokevirtual #32                 // Method java/lang/reflect/Constructor.getDeclaringClass:()Ljava/lang/Class;
       9: putfield      #34                 // Field clazz:Ljava/lang/Class;
      12: aload_0
      13: aload_1
      14: invokevirtual #38                 // Method java/lang/reflect/Constructor.getParameterTypes:()[Ljava/lang/Class;
      17: putfield      #40                 // Field args:[Ljava/lang/Class;
      20: return
}
