Compiled from "RawType.kt"
final class kotlin.reflect.jvm.internal.impl.load.java.lazy.types.RawTypeImpl$render$1 extends kotlin.jvm.internal.Lambda implements kotlin.jvm.functions.Function2<java.lang.String, java.lang.String, java.lang.Boolean> {
  public static final kotlin.reflect.jvm.internal.impl.load.java.lazy.types.RawTypeImpl$render$1 INSTANCE;

  public java.lang.Object invoke(java.lang.Object, java.lang.Object);
    Code:
       0: aload_0
       1: aload_1
       2: checkcast     #7                  // class java/lang/String
       5: aload_2
       6: checkcast     #7                  // class java/lang/String
       9: invokevirtual #20                 // Method invoke:(Ljava/lang/String;Ljava/lang/String;)Z
      12: invokestatic  #15                 // Method java/lang/Boolean.valueOf:(Z)Ljava/lang/Boolean;
      15: areturn

  public final boolean invoke(java.lang.String, java.lang.String);
    Code:
       0: aload_1
       1: ldc           #2                  // String first
       3: invokestatic  #17                 // Method kotlin/jvm/internal/Intrinsics.checkParameterIsNotNull:(Ljava/lang/Object;Ljava/lang/String;)V
       6: aload_2
       7: ldc           #4                  // String second
       9: invokestatic  #17                 // Method kotlin/jvm/internal/Intrinsics.checkParameterIsNotNull:(Ljava/lang/Object;Ljava/lang/String;)V
      12: aload_1
      13: aload_2
      14: ldc           #3                  // String out
      16: checkcast     #6                  // class java/lang/CharSequence
      19: invokestatic  #21                 // Method kotlin/text/StringsKt.removePrefix:(Ljava/lang/String;Ljava/lang/CharSequence;)Ljava/lang/String;
      22: invokestatic  #16                 // Method kotlin/jvm/internal/Intrinsics.areEqual:(Ljava/lang/Object;Ljava/lang/Object;)Z
      25: ifne          37
      28: aload_2
      29: ldc           #1                  // String *
      31: invokestatic  #16                 // Method kotlin/jvm/internal/Intrinsics.areEqual:(Ljava/lang/Object;Ljava/lang/Object;)Z
      34: ifeq          41
      37: iconst_1
      38: goto          42
      41: iconst_0
      42: ireturn

  kotlin.reflect.jvm.internal.impl.load.java.lazy.types.RawTypeImpl$render$1();
    Code:
       0: aload_0
       1: iconst_2
       2: invokespecial #18                 // Method kotlin/jvm/internal/Lambda."<init>":(I)V
       5: return

  static {};
    Code:
       0: new           #12                 // class kotlin/reflect/jvm/internal/impl/load/java/lazy/types/RawTypeImpl$render$1
       3: dup
       4: invokespecial #19                 // Method "<init>":()V
       7: putstatic     #14                 // Field INSTANCE:Lkotlin/reflect/jvm/internal/impl/load/java/lazy/types/RawTypeImpl$render$1;
      10: return
}
