Compiled from "AppliesToConsumer.java"
public interface org.wildfly.swarm.config.management.access.constraint.type.classification.AppliesToConsumer<T extends org.wildfly.swarm.config.management.access.constraint.type.classification.AppliesTo<T>> {
  public abstract void accept(T);

  public default org.wildfly.swarm.config.management.access.constraint.type.classification.AppliesToConsumer<T> andThen(org.wildfly.swarm.config.management.access.constraint.type.classification.AppliesToConsumer<T>);
    Code:
       0: aload_0
       1: aload_1
       2: invokedynamic #1,  0              // InvokeDynamic #0:accept:(Lorg/wildfly/swarm/config/management/access/constraint/type/classification/AppliesToConsumer;Lorg/wildfly/swarm/config/management/access/constraint/type/classification/AppliesToConsumer;)Lorg/wildfly/swarm/config/management/access/constraint/type/classification/AppliesToConsumer;
       7: areturn

  private void lambda$andThen$299(org.wildfly.swarm.config.management.access.constraint.type.classification.AppliesToConsumer, org.wildfly.swarm.config.management.access.constraint.type.classification.AppliesTo);
    Code:
       0: aload_0
       1: aload_2
       2: invokeinterface #2,  2            // InterfaceMethod accept:(Lorg/wildfly/swarm/config/management/access/constraint/type/classification/AppliesTo;)V
       7: aload_1
       8: aload_2
       9: invokeinterface #2,  2            // InterfaceMethod accept:(Lorg/wildfly/swarm/config/management/access/constraint/type/classification/AppliesTo;)V
      14: return
}
