Compiled from "HttpRequester.java"
public class org.apache.hc.core5.http.impl.bootstrap.HttpRequester implements org.apache.hc.core5.pool.ConnPoolControl<org.apache.hc.core5.http.HttpHost>, org.apache.hc.core5.io.ModalCloseable {
  private final org.apache.hc.core5.http.impl.io.HttpRequestExecutor requestExecutor;

  private final org.apache.hc.core5.http.protocol.HttpProcessor httpProcessor;

  private final org.apache.hc.core5.pool.ManagedConnPool<org.apache.hc.core5.http.HttpHost, org.apache.hc.core5.http.io.HttpClientConnection> connPool;

  private final org.apache.hc.core5.http.io.SocketConfig socketConfig;

  private final org.apache.hc.core5.http.io.HttpConnectionFactory<? extends org.apache.hc.core5.http.io.HttpClientConnection> connectFactory;

  private final javax.net.ssl.SSLSocketFactory sslSocketFactory;

  private final org.apache.hc.core5.function.Callback<javax.net.ssl.SSLParameters> sslSetupHandler;

  private final org.apache.hc.core5.http.io.ssl.SSLSessionVerifier sslSessionVerifier;

  private final org.apache.hc.core5.function.Resolver<org.apache.hc.core5.http.HttpHost, java.net.InetSocketAddress> addressResolver;

  public org.apache.hc.core5.http.impl.bootstrap.HttpRequester(org.apache.hc.core5.http.impl.io.HttpRequestExecutor, org.apache.hc.core5.http.protocol.HttpProcessor, org.apache.hc.core5.pool.ManagedConnPool<org.apache.hc.core5.http.HttpHost, org.apache.hc.core5.http.io.HttpClientConnection>, org.apache.hc.core5.http.io.SocketConfig, org.apache.hc.core5.http.io.HttpConnectionFactory<? extends org.apache.hc.core5.http.io.HttpClientConnection>, javax.net.ssl.SSLSocketFactory, org.apache.hc.core5.function.Callback<javax.net.ssl.SSLParameters>, org.apache.hc.core5.http.io.ssl.SSLSessionVerifier, org.apache.hc.core5.function.Resolver<org.apache.hc.core5.http.HttpHost, java.net.InetSocketAddress>);
    Code:
       0: aload_0
       1: invokespecial #4                  // Method java/lang/Object."<init>":()V
       4: aload_0
       5: aload_1
       6: ldc           #5                  // String Request executor
       8: invokestatic  #6                  // Method org/apache/hc/core5/util/Args.notNull:(Ljava/lang/Object;Ljava/lang/String;)Ljava/lang/Object;
      11: checkcast     #7                  // class org/apache/hc/core5/http/impl/io/HttpRequestExecutor
      14: putfield      #2                  // Field requestExecutor:Lorg/apache/hc/core5/http/impl/io/HttpRequestExecutor;
      17: aload_0
      18: aload_2
      19: ldc           #8                  // String HTTP processor
      21: invokestatic  #6                  // Method org/apache/hc/core5/util/Args.notNull:(Ljava/lang/Object;Ljava/lang/String;)Ljava/lang/Object;
      24: checkcast     #9                  // class org/apache/hc/core5/http/protocol/HttpProcessor
      27: putfield      #10                 // Field httpProcessor:Lorg/apache/hc/core5/http/protocol/HttpProcessor;
      30: aload_0
      31: aload_3
      32: ldc           #11                 // String Connection pool
      34: invokestatic  #6                  // Method org/apache/hc/core5/util/Args.notNull:(Ljava/lang/Object;Ljava/lang/String;)Ljava/lang/Object;
      37: checkcast     #12                 // class org/apache/hc/core5/pool/ManagedConnPool
      40: putfield      #1                  // Field connPool:Lorg/apache/hc/core5/pool/ManagedConnPool;
      43: aload_0
      44: aload         4
      46: ifnull        54
      49: aload         4
      51: goto          57
      54: getstatic     #13                 // Field org/apache/hc/core5/http/io/SocketConfig.DEFAULT:Lorg/apache/hc/core5/http/io/SocketConfig;
      57: putfield      #3                  // Field socketConfig:Lorg/apache/hc/core5/http/io/SocketConfig;
      60: aload_0
      61: aload         5
      63: ifnull        71
      66: aload         5
      68: goto          84
      71: new           #14                 // class org/apache/hc/core5/http/impl/io/DefaultBHttpClientConnectionFactory
      74: dup
      75: getstatic     #15                 // Field org/apache/hc/core5/http/config/Http1Config.DEFAULT:Lorg/apache/hc/core5/http/config/Http1Config;
      78: getstatic     #16                 // Field org/apache/hc/core5/http/config/CharCodingConfig.DEFAULT:Lorg/apache/hc/core5/http/config/CharCodingConfig;
      81: invokespecial #17                 // Method org/apache/hc/core5/http/impl/io/DefaultBHttpClientConnectionFactory."<init>":(Lorg/apache/hc/core5/http/config/Http1Config;Lorg/apache/hc/core5/http/config/CharCodingConfig;)V
      84: putfield      #18                 // Field connectFactory:Lorg/apache/hc/core5/http/io/HttpConnectionFactory;
      87: aload_0
      88: aload         6
      90: ifnull        98
      93: aload         6
      95: goto          104
      98: invokestatic  #19                 // Method javax/net/ssl/SSLSocketFactory.getDefault:()Ljavax/net/SocketFactory;
     101: checkcast     #20                 // class javax/net/ssl/SSLSocketFactory
     104: putfield      #21                 // Field sslSocketFactory:Ljavax/net/ssl/SSLSocketFactory;
     107: aload_0
     108: aload         7
     110: putfield      #22                 // Field sslSetupHandler:Lorg/apache/hc/core5/function/Callback;
     113: aload_0
     114: aload         8
     116: putfield      #23                 // Field sslSessionVerifier:Lorg/apache/hc/core5/http/io/ssl/SSLSessionVerifier;
     119: aload_0
     120: aload         9
     122: ifnull        130
     125: aload         9
     127: goto          133
     130: getstatic     #24                 // Field org/apache/hc/core5/http/impl/DefaultAddressResolver.INSTANCE:Lorg/apache/hc/core5/http/impl/DefaultAddressResolver;
     133: putfield      #25                 // Field addressResolver:Lorg/apache/hc/core5/function/Resolver;
     136: return

  public org.apache.hc.core5.pool.PoolStats getTotalStats();
    Code:
       0: aload_0
       1: getfield      #1                  // Field connPool:Lorg/apache/hc/core5/pool/ManagedConnPool;
       4: invokeinterface #26,  1           // InterfaceMethod org/apache/hc/core5/pool/ManagedConnPool.getTotalStats:()Lorg/apache/hc/core5/pool/PoolStats;
       9: areturn

  public org.apache.hc.core5.pool.PoolStats getStats(org.apache.hc.core5.http.HttpHost);
    Code:
       0: aload_0
       1: getfield      #1                  // Field connPool:Lorg/apache/hc/core5/pool/ManagedConnPool;
       4: aload_1
       5: invokeinterface #27,  2           // InterfaceMethod org/apache/hc/core5/pool/ManagedConnPool.getStats:(Ljava/lang/Object;)Lorg/apache/hc/core5/pool/PoolStats;
      10: areturn

  public void setMaxTotal(int);
    Code:
       0: aload_0
       1: getfield      #1                  // Field connPool:Lorg/apache/hc/core5/pool/ManagedConnPool;
       4: iload_1
       5: invokeinterface #28,  2           // InterfaceMethod org/apache/hc/core5/pool/ManagedConnPool.setMaxTotal:(I)V
      10: return

  public int getMaxTotal();
    Code:
       0: aload_0
       1: getfield      #1                  // Field connPool:Lorg/apache/hc/core5/pool/ManagedConnPool;
       4: invokeinterface #29,  1           // InterfaceMethod org/apache/hc/core5/pool/ManagedConnPool.getMaxTotal:()I
       9: ireturn

  public void setDefaultMaxPerRoute(int);
    Code:
       0: aload_0
       1: getfield      #1                  // Field connPool:Lorg/apache/hc/core5/pool/ManagedConnPool;
       4: iload_1
       5: invokeinterface #30,  2           // InterfaceMethod org/apache/hc/core5/pool/ManagedConnPool.setDefaultMaxPerRoute:(I)V
      10: return

  public int getDefaultMaxPerRoute();
    Code:
       0: aload_0
       1: getfield      #1                  // Field connPool:Lorg/apache/hc/core5/pool/ManagedConnPool;
       4: invokeinterface #31,  1           // InterfaceMethod org/apache/hc/core5/pool/ManagedConnPool.getDefaultMaxPerRoute:()I
       9: ireturn

  public void setMaxPerRoute(org.apache.hc.core5.http.HttpHost, int);
    Code:
       0: aload_0
       1: getfield      #1                  // Field connPool:Lorg/apache/hc/core5/pool/ManagedConnPool;
       4: aload_1
       5: iload_2
       6: invokeinterface #32,  3           // InterfaceMethod org/apache/hc/core5/pool/ManagedConnPool.setMaxPerRoute:(Ljava/lang/Object;I)V
      11: return

  public int getMaxPerRoute(org.apache.hc.core5.http.HttpHost);
    Code:
       0: aload_0
       1: getfield      #1                  // Field connPool:Lorg/apache/hc/core5/pool/ManagedConnPool;
       4: aload_1
       5: invokeinterface #33,  2           // InterfaceMethod org/apache/hc/core5/pool/ManagedConnPool.getMaxPerRoute:(Ljava/lang/Object;)I
      10: ireturn

  public void closeIdle(org.apache.hc.core5.util.TimeValue);
    Code:
       0: aload_0
       1: getfield      #1                  // Field connPool:Lorg/apache/hc/core5/pool/ManagedConnPool;
       4: aload_1
       5: invokeinterface #34,  2           // InterfaceMethod org/apache/hc/core5/pool/ManagedConnPool.closeIdle:(Lorg/apache/hc/core5/util/TimeValue;)V
      10: return

  public void closeExpired();
    Code:
       0: aload_0
       1: getfield      #1                  // Field connPool:Lorg/apache/hc/core5/pool/ManagedConnPool;
       4: invokeinterface #35,  1           // InterfaceMethod org/apache/hc/core5/pool/ManagedConnPool.closeExpired:()V
       9: return

  public java.util.Set<org.apache.hc.core5.http.HttpHost> getRoutes();
    Code:
       0: aload_0
       1: getfield      #1                  // Field connPool:Lorg/apache/hc/core5/pool/ManagedConnPool;
       4: invokeinterface #36,  1           // InterfaceMethod org/apache/hc/core5/pool/ManagedConnPool.getRoutes:()Ljava/util/Set;
       9: areturn

  public org.apache.hc.core5.http.ClassicHttpResponse execute(org.apache.hc.core5.http.io.HttpClientConnection, org.apache.hc.core5.http.ClassicHttpRequest, org.apache.hc.core5.http.io.HttpResponseInformationCallback, org.apache.hc.core5.http.protocol.HttpContext) throws org.apache.hc.core5.http.HttpException, java.io.IOException;
    Code:
       0: aload_1
       1: ldc           #37                 // String HTTP connection
       3: invokestatic  #6                  // Method org/apache/hc/core5/util/Args.notNull:(Ljava/lang/Object;Ljava/lang/String;)Ljava/lang/Object;
       6: pop
       7: aload_2
       8: ldc           #38                 // String HTTP request
      10: invokestatic  #6                  // Method org/apache/hc/core5/util/Args.notNull:(Ljava/lang/Object;Ljava/lang/String;)Ljava/lang/Object;
      13: pop
      14: aload         4
      16: ldc           #39                 // String HTTP context
      18: invokestatic  #6                  // Method org/apache/hc/core5/util/Args.notNull:(Ljava/lang/Object;Ljava/lang/String;)Ljava/lang/Object;
      21: pop
      22: aload_1
      23: invokeinterface #40,  1           // InterfaceMethod org/apache/hc/core5/http/io/HttpClientConnection.isOpen:()Z
      28: ifne          39
      31: new           #41                 // class org/apache/hc/core5/http/ConnectionClosedException
      34: dup
      35: invokespecial #42                 // Method org/apache/hc/core5/http/ConnectionClosedException."<init>":()V
      38: athrow
      39: aload_0
      40: getfield      #2                  // Field requestExecutor:Lorg/apache/hc/core5/http/impl/io/HttpRequestExecutor;
      43: aload_2
      44: aload_0
      45: getfield      #10                 // Field httpProcessor:Lorg/apache/hc/core5/http/protocol/HttpProcessor;
      48: aload         4
      50: invokevirtual #43                 // Method org/apache/hc/core5/http/impl/io/HttpRequestExecutor.preProcess:(Lorg/apache/hc/core5/http/ClassicHttpRequest;Lorg/apache/hc/core5/http/protocol/HttpProcessor;Lorg/apache/hc/core5/http/protocol/HttpContext;)V
      53: aload_0
      54: getfield      #2                  // Field requestExecutor:Lorg/apache/hc/core5/http/impl/io/HttpRequestExecutor;
      57: aload_2
      58: aload_1
      59: aload_3
      60: aload         4
      62: invokevirtual #44                 // Method org/apache/hc/core5/http/impl/io/HttpRequestExecutor.execute:(Lorg/apache/hc/core5/http/ClassicHttpRequest;Lorg/apache/hc/core5/http/io/HttpClientConnection;Lorg/apache/hc/core5/http/io/HttpResponseInformationCallback;Lorg/apache/hc/core5/http/protocol/HttpContext;)Lorg/apache/hc/core5/http/ClassicHttpResponse;
      65: astore        5
      67: aload_0
      68: getfield      #2                  // Field requestExecutor:Lorg/apache/hc/core5/http/impl/io/HttpRequestExecutor;
      71: aload         5
      73: aload_0
      74: getfield      #10                 // Field httpProcessor:Lorg/apache/hc/core5/http/protocol/HttpProcessor;
      77: aload         4
      79: invokevirtual #45                 // Method org/apache/hc/core5/http/impl/io/HttpRequestExecutor.postProcess:(Lorg/apache/hc/core5/http/ClassicHttpResponse;Lorg/apache/hc/core5/http/protocol/HttpProcessor;Lorg/apache/hc/core5/http/protocol/HttpContext;)V
      82: aload         5
      84: areturn

  public org.apache.hc.core5.http.ClassicHttpResponse execute(org.apache.hc.core5.http.io.HttpClientConnection, org.apache.hc.core5.http.ClassicHttpRequest, org.apache.hc.core5.http.protocol.HttpContext) throws org.apache.hc.core5.http.HttpException, java.io.IOException;
    Code:
       0: aload_0
       1: aload_1
       2: aload_2
       3: aconst_null
       4: aload_3
       5: invokevirtual #46                 // Method execute:(Lorg/apache/hc/core5/http/io/HttpClientConnection;Lorg/apache/hc/core5/http/ClassicHttpRequest;Lorg/apache/hc/core5/http/io/HttpResponseInformationCallback;Lorg/apache/hc/core5/http/protocol/HttpContext;)Lorg/apache/hc/core5/http/ClassicHttpResponse;
       8: areturn

  public boolean keepAlive(org.apache.hc.core5.http.io.HttpClientConnection, org.apache.hc.core5.http.ClassicHttpRequest, org.apache.hc.core5.http.ClassicHttpResponse, org.apache.hc.core5.http.protocol.HttpContext) throws java.io.IOException;
    Code:
       0: aload_0
       1: getfield      #2                  // Field requestExecutor:Lorg/apache/hc/core5/http/impl/io/HttpRequestExecutor;
       4: aload_2
       5: aload_3
       6: aload_1
       7: aload         4
       9: invokevirtual #47                 // Method org/apache/hc/core5/http/impl/io/HttpRequestExecutor.keepAlive:(Lorg/apache/hc/core5/http/ClassicHttpRequest;Lorg/apache/hc/core5/http/ClassicHttpResponse;Lorg/apache/hc/core5/http/io/HttpClientConnection;Lorg/apache/hc/core5/http/protocol/HttpContext;)Z
      12: istore        5
      14: iload         5
      16: ifne          25
      19: aload_1
      20: invokeinterface #48,  1           // InterfaceMethod org/apache/hc/core5/http/io/HttpClientConnection.close:()V
      25: iload         5
      27: ireturn

  public <T> T execute(org.apache.hc.core5.http.io.HttpClientConnection, org.apache.hc.core5.http.ClassicHttpRequest, org.apache.hc.core5.http.protocol.HttpContext, org.apache.hc.core5.http.io.HttpClientResponseHandler<T>) throws org.apache.hc.core5.http.HttpException, java.io.IOException;
    Code:
       0: aload_0
       1: aload_1
       2: aload_2
       3: aload_3
       4: invokevirtual #49                 // Method execute:(Lorg/apache/hc/core5/http/io/HttpClientConnection;Lorg/apache/hc/core5/http/ClassicHttpRequest;Lorg/apache/hc/core5/http/protocol/HttpContext;)Lorg/apache/hc/core5/http/ClassicHttpResponse;
       7: astore        5
       9: aconst_null
      10: astore        6
      12: aload         4
      14: aload         5
      16: invokeinterface #50,  2           // InterfaceMethod org/apache/hc/core5/http/io/HttpClientResponseHandler.handleResponse:(Lorg/apache/hc/core5/http/ClassicHttpResponse;)Ljava/lang/Object;
      21: astore        7
      23: aload         5
      25: invokeinterface #51,  1           // InterfaceMethod org/apache/hc/core5/http/ClassicHttpResponse.getEntity:()Lorg/apache/hc/core5/http/HttpEntity;
      30: invokestatic  #52                 // Method org/apache/hc/core5/http/io/entity/EntityUtils.consume:(Lorg/apache/hc/core5/http/HttpEntity;)V
      33: aload_0
      34: getfield      #2                  // Field requestExecutor:Lorg/apache/hc/core5/http/impl/io/HttpRequestExecutor;
      37: aload_2
      38: aload         5
      40: aload_1
      41: aload_3
      42: invokevirtual #47                 // Method org/apache/hc/core5/http/impl/io/HttpRequestExecutor.keepAlive:(Lorg/apache/hc/core5/http/ClassicHttpRequest;Lorg/apache/hc/core5/http/ClassicHttpResponse;Lorg/apache/hc/core5/http/io/HttpClientConnection;Lorg/apache/hc/core5/http/protocol/HttpContext;)Z
      45: istore        8
      47: iload         8
      49: ifne          58
      52: aload_1
      53: invokeinterface #48,  1           // InterfaceMethod org/apache/hc/core5/http/io/HttpClientConnection.close:()V
      58: aload         7
      60: astore        9
      62: aload         5
      64: ifnull        101
      67: aload         6
      69: ifnull        94
      72: aload         5
      74: invokeinterface #53,  1           // InterfaceMethod org/apache/hc/core5/http/ClassicHttpResponse.close:()V
      79: goto          101
      82: astore        10
      84: aload         6
      86: aload         10
      88: invokevirtual #55                 // Method java/lang/Throwable.addSuppressed:(Ljava/lang/Throwable;)V
      91: goto          101
      94: aload         5
      96: invokeinterface #53,  1           // InterfaceMethod org/apache/hc/core5/http/ClassicHttpResponse.close:()V
     101: aload         9
     103: areturn
     104: astore        7
     106: aload         7
     108: astore        6
     110: aload         7
     112: athrow
     113: astore        11
     115: aload         5
     117: ifnull        154
     120: aload         6
     122: ifnull        147
     125: aload         5
     127: invokeinterface #53,  1           // InterfaceMethod org/apache/hc/core5/http/ClassicHttpResponse.close:()V
     132: goto          154
     135: astore        12
     137: aload         6
     139: aload         12
     141: invokevirtual #55                 // Method java/lang/Throwable.addSuppressed:(Ljava/lang/Throwable;)V
     144: goto          154
     147: aload         5
     149: invokeinterface #53,  1           // InterfaceMethod org/apache/hc/core5/http/ClassicHttpResponse.close:()V
     154: aload         11
     156: athrow
     157: astore        5
     159: aload_1
     160: getstatic     #59                 // Field org/apache/hc/core5/io/CloseMode.IMMEDIATE:Lorg/apache/hc/core5/io/CloseMode;
     163: invokeinterface #60,  2           // InterfaceMethod org/apache/hc/core5/http/io/HttpClientConnection.close:(Lorg/apache/hc/core5/io/CloseMode;)V
     168: aload         5
     170: athrow
    Exception table:
       from    to  target type
          72    79    82   Class java/lang/Throwable
          12    62   104   Class java/lang/Throwable
          12    62   113   any
         125   132   135   Class java/lang/Throwable
         104   115   113   any
           0   101   157   Class org/apache/hc/core5/http/HttpException
           0   101   157   Class java/io/IOException
           0   101   157   Class java/lang/RuntimeException
         104   157   157   Class org/apache/hc/core5/http/HttpException
         104   157   157   Class java/io/IOException
         104   157   157   Class java/lang/RuntimeException

  private java.net.Socket createSocket(org.apache.hc.core5.http.HttpHost) throws java.io.IOException;
    Code:
       0: aload_0
       1: getfield      #3                  // Field socketConfig:Lorg/apache/hc/core5/http/io/SocketConfig;
       4: invokevirtual #61                 // Method org/apache/hc/core5/http/io/SocketConfig.getSocksProxyAddress:()Ljava/net/SocketAddress;
       7: ifnull        38
      10: new           #62                 // class java/net/Socket
      13: dup
      14: new           #63                 // class java/net/Proxy
      17: dup
      18: getstatic     #64                 // Field java/net/Proxy$Type.SOCKS:Ljava/net/Proxy$Type;
      21: aload_0
      22: getfield      #3                  // Field socketConfig:Lorg/apache/hc/core5/http/io/SocketConfig;
      25: invokevirtual #61                 // Method org/apache/hc/core5/http/io/SocketConfig.getSocksProxyAddress:()Ljava/net/SocketAddress;
      28: invokespecial #65                 // Method java/net/Proxy."<init>":(Ljava/net/Proxy$Type;Ljava/net/SocketAddress;)V
      31: invokespecial #66                 // Method java/net/Socket."<init>":(Ljava/net/Proxy;)V
      34: astore_2
      35: goto          46
      38: new           #62                 // class java/net/Socket
      41: dup
      42: invokespecial #67                 // Method java/net/Socket."<init>":()V
      45: astore_2
      46: aload_2
      47: aload_0
      48: getfield      #3                  // Field socketConfig:Lorg/apache/hc/core5/http/io/SocketConfig;
      51: invokevirtual #68                 // Method org/apache/hc/core5/http/io/SocketConfig.getSoTimeout:()Lorg/apache/hc/core5/util/Timeout;
      54: invokevirtual #69                 // Method org/apache/hc/core5/util/Timeout.toMillisecondsIntBound:()I
      57: invokevirtual #70                 // Method java/net/Socket.setSoTimeout:(I)V
      60: aload_2
      61: aload_0
      62: getfield      #3                  // Field socketConfig:Lorg/apache/hc/core5/http/io/SocketConfig;
      65: invokevirtual #71                 // Method org/apache/hc/core5/http/io/SocketConfig.isSoReuseAddress:()Z
      68: invokevirtual #72                 // Method java/net/Socket.setReuseAddress:(Z)V
      71: aload_2
      72: aload_0
      73: getfield      #3                  // Field socketConfig:Lorg/apache/hc/core5/http/io/SocketConfig;
      76: invokevirtual #73                 // Method org/apache/hc/core5/http/io/SocketConfig.isTcpNoDelay:()Z
      79: invokevirtual #74                 // Method java/net/Socket.setTcpNoDelay:(Z)V
      82: aload_2
      83: aload_0
      84: getfield      #3                  // Field socketConfig:Lorg/apache/hc/core5/http/io/SocketConfig;
      87: invokevirtual #75                 // Method org/apache/hc/core5/http/io/SocketConfig.isSoKeepAlive:()Z
      90: invokevirtual #76                 // Method java/net/Socket.setKeepAlive:(Z)V
      93: aload_0
      94: getfield      #3                  // Field socketConfig:Lorg/apache/hc/core5/http/io/SocketConfig;
      97: invokevirtual #77                 // Method org/apache/hc/core5/http/io/SocketConfig.getRcvBufSize:()I
     100: ifle          114
     103: aload_2
     104: aload_0
     105: getfield      #3                  // Field socketConfig:Lorg/apache/hc/core5/http/io/SocketConfig;
     108: invokevirtual #77                 // Method org/apache/hc/core5/http/io/SocketConfig.getRcvBufSize:()I
     111: invokevirtual #78                 // Method java/net/Socket.setReceiveBufferSize:(I)V
     114: aload_0
     115: getfield      #3                  // Field socketConfig:Lorg/apache/hc/core5/http/io/SocketConfig;
     118: invokevirtual #79                 // Method org/apache/hc/core5/http/io/SocketConfig.getSndBufSize:()I
     121: ifle          135
     124: aload_2
     125: aload_0
     126: getfield      #3                  // Field socketConfig:Lorg/apache/hc/core5/http/io/SocketConfig;
     129: invokevirtual #79                 // Method org/apache/hc/core5/http/io/SocketConfig.getSndBufSize:()I
     132: invokevirtual #80                 // Method java/net/Socket.setSendBufferSize:(I)V
     135: aload_0
     136: getfield      #3                  // Field socketConfig:Lorg/apache/hc/core5/http/io/SocketConfig;
     139: invokevirtual #81                 // Method org/apache/hc/core5/http/io/SocketConfig.getSoLinger:()Lorg/apache/hc/core5/util/TimeValue;
     142: invokevirtual #82                 // Method org/apache/hc/core5/util/TimeValue.toMillisecondsIntBound:()I
     145: istore_3
     146: iload_3
     147: iflt          156
     150: aload_2
     151: iconst_1
     152: iload_3
     153: invokevirtual #83                 // Method java/net/Socket.setSoLinger:(ZI)V
     156: aload_0
     157: getfield      #25                 // Field addressResolver:Lorg/apache/hc/core5/function/Resolver;
     160: aload_1
     161: invokeinterface #84,  2           // InterfaceMethod org/apache/hc/core5/function/Resolver.resolve:(Ljava/lang/Object;)Ljava/lang/Object;
     166: checkcast     #85                 // class java/net/InetSocketAddress
     169: astore        4
     171: new           #86                 // class org/apache/hc/core5/http/impl/bootstrap/HttpRequester$1
     174: dup
     175: aload_0
     176: aload_2
     177: aload         4
     179: invokespecial #87                 // Method org/apache/hc/core5/http/impl/bootstrap/HttpRequester$1."<init>":(Lorg/apache/hc/core5/http/impl/bootstrap/HttpRequester;Ljava/net/Socket;Ljava/net/InetSocketAddress;)V
     182: invokestatic  #88                 // Method java/security/AccessController.doPrivileged:(Ljava/security/PrivilegedExceptionAction;)Ljava/lang/Object;
     185: pop
     186: goto          234
     189: astore        5
     191: aload         5
     193: invokevirtual #90                 // Method java/security/PrivilegedActionException.getCause:()Ljava/lang/Throwable;
     196: instanceof    #57                 // class java/io/IOException
     199: new           #91                 // class java/lang/StringBuilder
     202: dup
     203: invokespecial #92                 // Method java/lang/StringBuilder."<init>":()V
     206: ldc           #93                 // String method contract violation only checked exceptions are wrapped:
     208: invokevirtual #94                 // Method java/lang/StringBuilder.append:(Ljava/lang/String;)Ljava/lang/StringBuilder;
     211: aload         5
     213: invokevirtual #90                 // Method java/security/PrivilegedActionException.getCause:()Ljava/lang/Throwable;
     216: invokevirtual #95                 // Method java/lang/StringBuilder.append:(Ljava/lang/Object;)Ljava/lang/StringBuilder;
     219: invokevirtual #96                 // Method java/lang/StringBuilder.toString:()Ljava/lang/String;
     222: invokestatic  #97                 // Method org/apache/hc/core5/util/Asserts.check:(ZLjava/lang/String;)V
     225: aload         5
     227: invokevirtual #90                 // Method java/security/PrivilegedActionException.getCause:()Ljava/lang/Throwable;
     230: checkcast     #57                 // class java/io/IOException
     233: athrow
     234: getstatic     #98                 // Field org/apache/hc/core5/http/URIScheme.HTTPS:Lorg/apache/hc/core5/http/URIScheme;
     237: aload_1
     238: invokevirtual #99                 // Method org/apache/hc/core5/http/HttpHost.getSchemeName:()Ljava/lang/String;
     241: invokevirtual #100                // Method org/apache/hc/core5/http/URIScheme.same:(Ljava/lang/String;)Z
     244: ifeq          364
     247: aload_0
     248: getfield      #21                 // Field sslSocketFactory:Ljavax/net/ssl/SSLSocketFactory;
     251: aload_2
     252: aload_1
     253: invokevirtual #101                // Method org/apache/hc/core5/http/HttpHost.getHostName:()Ljava/lang/String;
     256: aload         4
     258: invokevirtual #102                // Method java/net/InetSocketAddress.getPort:()I
     261: iconst_1
     262: invokevirtual #103                // Method javax/net/ssl/SSLSocketFactory.createSocket:(Ljava/net/Socket;Ljava/lang/String;IZ)Ljava/net/Socket;
     265: checkcast     #104                // class javax/net/ssl/SSLSocket
     268: astore        5
     270: aload_0
     271: getfield      #22                 // Field sslSetupHandler:Lorg/apache/hc/core5/function/Callback;
     274: ifnull        302
     277: aload         5
     279: invokevirtual #105                // Method javax/net/ssl/SSLSocket.getSSLParameters:()Ljavax/net/ssl/SSLParameters;
     282: astore        6
     284: aload_0
     285: getfield      #22                 // Field sslSetupHandler:Lorg/apache/hc/core5/function/Callback;
     288: aload         6
     290: invokeinterface #106,  2          // InterfaceMethod org/apache/hc/core5/function/Callback.execute:(Ljava/lang/Object;)V
     295: aload         5
     297: aload         6
     299: invokevirtual #107                // Method javax/net/ssl/SSLSocket.setSSLParameters:(Ljavax/net/ssl/SSLParameters;)V
     302: aload         5
     304: invokevirtual #108                // Method javax/net/ssl/SSLSocket.startHandshake:()V
     307: aload         5
     309: invokevirtual #109                // Method javax/net/ssl/SSLSocket.getSession:()Ljavax/net/ssl/SSLSession;
     312: astore        6
     314: aload         6
     316: ifnonnull     329
     319: new           #110                // class javax/net/ssl/SSLHandshakeException
     322: dup
     323: ldc           #111                // String SSL session not available
     325: invokespecial #112                // Method javax/net/ssl/SSLHandshakeException."<init>":(Ljava/lang/String;)V
     328: athrow
     329: aload_0
     330: getfield      #23                 // Field sslSessionVerifier:Lorg/apache/hc/core5/http/io/ssl/SSLSessionVerifier;
     333: ifnull        348
     336: aload_0
     337: getfield      #23                 // Field sslSessionVerifier:Lorg/apache/hc/core5/http/io/ssl/SSLSessionVerifier;
     340: aload_1
     341: aload         6
     343: invokeinterface #113,  3          // InterfaceMethod org/apache/hc/core5/http/io/ssl/SSLSessionVerifier.verify:(Lorg/apache/hc/core5/http/HttpHost;Ljavax/net/ssl/SSLSession;)V
     348: goto          361
     351: astore        6
     353: aload         5
     355: invokestatic  #114                // Method org/apache/hc/core5/io/Closer.closeQuietly:(Ljava/io/Closeable;)V
     358: aload         6
     360: athrow
     361: aload         5
     363: areturn
     364: aload_2
     365: areturn
    Exception table:
       from    to  target type
         171   186   189   Class java/security/PrivilegedActionException
         302   348   351   Class java/io/IOException

  public org.apache.hc.core5.http.ClassicHttpResponse execute(org.apache.hc.core5.http.HttpHost, org.apache.hc.core5.http.ClassicHttpRequest, org.apache.hc.core5.http.io.HttpResponseInformationCallback, org.apache.hc.core5.util.Timeout, org.apache.hc.core5.http.protocol.HttpContext) throws org.apache.hc.core5.http.HttpException, java.io.IOException;
    Code:
       0: aload_1
       1: ldc           #115                // String HTTP host
       3: invokestatic  #6                  // Method org/apache/hc/core5/util/Args.notNull:(Ljava/lang/Object;Ljava/lang/String;)Ljava/lang/Object;
       6: pop
       7: aload_2
       8: ldc           #38                 // String HTTP request
      10: invokestatic  #6                  // Method org/apache/hc/core5/util/Args.notNull:(Ljava/lang/Object;Ljava/lang/String;)Ljava/lang/Object;
      13: pop
      14: aload_0
      15: getfield      #1                  // Field connPool:Lorg/apache/hc/core5/pool/ManagedConnPool;
      18: aload_1
      19: aconst_null
      20: aload         4
      22: aconst_null
      23: invokeinterface #116,  5          // InterfaceMethod org/apache/hc/core5/pool/ManagedConnPool.lease:(Ljava/lang/Object;Ljava/lang/Object;Lorg/apache/hc/core5/util/Timeout;Lorg/apache/hc/core5/concurrent/FutureCallback;)Ljava/util/concurrent/Future;
      28: astore        6
      30: aload         4
      32: invokestatic  #117                // Method org/apache/hc/core5/util/Timeout.defaultsToDisabled:(Lorg/apache/hc/core5/util/Timeout;)Lorg/apache/hc/core5/util/Timeout;
      35: astore        8
      37: aload         6
      39: aload         8
      41: invokevirtual #118                // Method org/apache/hc/core5/util/Timeout.getDuration:()J
      44: aload         8
      46: invokevirtual #119                // Method org/apache/hc/core5/util/Timeout.getTimeUnit:()Ljava/util/concurrent/TimeUnit;
      49: invokeinterface #120,  4          // InterfaceMethod java/util/concurrent/Future.get:(JLjava/util/concurrent/TimeUnit;)Ljava/lang/Object;
      54: checkcast     #121                // class org/apache/hc/core5/pool/PoolEntry
      57: astore        7
      59: goto          109
      62: astore        9
      64: invokestatic  #123                // Method java/lang/Thread.currentThread:()Ljava/lang/Thread;
      67: invokevirtual #124                // Method java/lang/Thread.interrupt:()V
      70: new           #125                // class java/io/InterruptedIOException
      73: dup
      74: aload         9
      76: invokevirtual #126                // Method java/lang/InterruptedException.getMessage:()Ljava/lang/String;
      79: invokespecial #127                // Method java/io/InterruptedIOException."<init>":(Ljava/lang/String;)V
      82: athrow
      83: astore        9
      85: new           #56                 // class org/apache/hc/core5/http/HttpException
      88: dup
      89: ldc           #129                // String Unexpected failure leasing connection
      91: aload         9
      93: invokespecial #130                // Method org/apache/hc/core5/http/HttpException."<init>":(Ljava/lang/String;Ljava/lang/Throwable;)V
      96: athrow
      97: astore        9
      99: new           #132                // class org/apache/hc/core5/http/ConnectionRequestTimeoutException
     102: dup
     103: ldc           #133                // String Connection request timeout
     105: invokespecial #134                // Method org/apache/hc/core5/http/ConnectionRequestTimeoutException."<init>":(Ljava/lang/String;)V
     108: athrow
     109: new           #135                // class org/apache/hc/core5/http/impl/bootstrap/HttpRequester$PoolEntryHolder
     112: dup
     113: aload_0
     114: aload         7
     116: invokespecial #136                // Method org/apache/hc/core5/http/impl/bootstrap/HttpRequester$PoolEntryHolder."<init>":(Lorg/apache/hc/core5/http/impl/bootstrap/HttpRequester;Lorg/apache/hc/core5/pool/PoolEntry;)V
     119: astore        9
     121: aload         7
     123: invokevirtual #137                // Method org/apache/hc/core5/pool/PoolEntry.getConnection:()Lorg/apache/hc/core5/io/ModalCloseable;
     126: checkcast     #138                // class org/apache/hc/core5/http/io/HttpClientConnection
     129: astore        10
     131: aload         10
     133: ifnonnull     166
     136: aload_0
     137: aload_1
     138: invokespecial #139                // Method createSocket:(Lorg/apache/hc/core5/http/HttpHost;)Ljava/net/Socket;
     141: astore        11
     143: aload_0
     144: getfield      #18                 // Field connectFactory:Lorg/apache/hc/core5/http/io/HttpConnectionFactory;
     147: aload         11
     149: invokeinterface #140,  2          // InterfaceMethod org/apache/hc/core5/http/io/HttpConnectionFactory.createConnection:(Ljava/net/Socket;)Lorg/apache/hc/core5/http/HttpConnection;
     154: checkcast     #138                // class org/apache/hc/core5/http/io/HttpClientConnection
     157: astore        10
     159: aload         7
     161: aload         10
     163: invokevirtual #141                // Method org/apache/hc/core5/pool/PoolEntry.assignConnection:(Lorg/apache/hc/core5/io/ModalCloseable;)V
     166: aload_2
     167: invokeinterface #142,  1          // InterfaceMethod org/apache/hc/core5/http/ClassicHttpRequest.getAuthority:()Lorg/apache/hc/core5/net/URIAuthority;
     172: ifnonnull     196
     175: aload_2
     176: new           #143                // class org/apache/hc/core5/net/URIAuthority
     179: dup
     180: aload_1
     181: invokevirtual #101                // Method org/apache/hc/core5/http/HttpHost.getHostName:()Ljava/lang/String;
     184: aload_1
     185: invokevirtual #144                // Method org/apache/hc/core5/http/HttpHost.getPort:()I
     188: invokespecial #145                // Method org/apache/hc/core5/net/URIAuthority."<init>":(Ljava/lang/String;I)V
     191: invokeinterface #146,  2          // InterfaceMethod org/apache/hc/core5/http/ClassicHttpRequest.setAuthority:(Lorg/apache/hc/core5/net/URIAuthority;)V
     196: aload_0
     197: aload         10
     199: aload_2
     200: aload_3
     201: aload         5
     203: invokevirtual #46                 // Method execute:(Lorg/apache/hc/core5/http/io/HttpClientConnection;Lorg/apache/hc/core5/http/ClassicHttpRequest;Lorg/apache/hc/core5/http/io/HttpResponseInformationCallback;Lorg/apache/hc/core5/http/protocol/HttpContext;)Lorg/apache/hc/core5/http/ClassicHttpResponse;
     206: astore        11
     208: aload         11
     210: invokeinterface #51,  1           // InterfaceMethod org/apache/hc/core5/http/ClassicHttpResponse.getEntity:()Lorg/apache/hc/core5/http/HttpEntity;
     215: astore        12
     217: aload         12
     219: ifnull        249
     222: aload         11
     224: new           #147                // class org/apache/hc/core5/http/impl/bootstrap/HttpRequester$2
     227: dup
     228: aload_0
     229: aload         12
     231: aload         9
     233: aload_2
     234: aload         11
     236: aload         5
     238: invokespecial #148                // Method org/apache/hc/core5/http/impl/bootstrap/HttpRequester$2."<init>":(Lorg/apache/hc/core5/http/impl/bootstrap/HttpRequester;Lorg/apache/hc/core5/http/HttpEntity;Lorg/apache/hc/core5/http/impl/bootstrap/HttpRequester$PoolEntryHolder;Lorg/apache/hc/core5/http/ClassicHttpRequest;Lorg/apache/hc/core5/http/ClassicHttpResponse;Lorg/apache/hc/core5/http/protocol/HttpContext;)V
     241: invokeinterface #149,  2          // InterfaceMethod org/apache/hc/core5/http/ClassicHttpResponse.setEntity:(Lorg/apache/hc/core5/http/HttpEntity;)V
     246: goto          285
     249: aload         9
     251: invokevirtual #150                // Method org/apache/hc/core5/http/impl/bootstrap/HttpRequester$PoolEntryHolder.getConnection:()Lorg/apache/hc/core5/http/io/HttpClientConnection;
     254: astore        13
     256: aload_0
     257: getfield      #2                  // Field requestExecutor:Lorg/apache/hc/core5/http/impl/io/HttpRequestExecutor;
     260: aload_2
     261: aload         11
     263: aload         13
     265: aload         5
     267: invokevirtual #47                 // Method org/apache/hc/core5/http/impl/io/HttpRequestExecutor.keepAlive:(Lorg/apache/hc/core5/http/ClassicHttpRequest;Lorg/apache/hc/core5/http/ClassicHttpResponse;Lorg/apache/hc/core5/http/io/HttpClientConnection;Lorg/apache/hc/core5/http/protocol/HttpContext;)Z
     270: ifne          280
     273: aload         13
     275: invokeinterface #48,  1           // InterfaceMethod org/apache/hc/core5/http/io/HttpClientConnection.close:()V
     280: aload         9
     282: invokevirtual #151                // Method org/apache/hc/core5/http/impl/bootstrap/HttpRequester$PoolEntryHolder.releaseConnection:()V
     285: aload         11
     287: areturn
     288: astore        10
     290: aload         9
     292: invokevirtual #152                // Method org/apache/hc/core5/http/impl/bootstrap/HttpRequester$PoolEntryHolder.discardConnection:()V
     295: aload         10
     297: athrow
    Exception table:
       from    to  target type
          37    59    62   Class java/lang/InterruptedException
          37    59    83   Class java/util/concurrent/ExecutionException
          37    59    97   Class java/util/concurrent/TimeoutException
         121   287   288   Class org/apache/hc/core5/http/HttpException
         121   287   288   Class java/io/IOException
         121   287   288   Class java/lang/RuntimeException

  public org.apache.hc.core5.http.ClassicHttpResponse execute(org.apache.hc.core5.http.HttpHost, org.apache.hc.core5.http.ClassicHttpRequest, org.apache.hc.core5.util.Timeout, org.apache.hc.core5.http.protocol.HttpContext) throws org.apache.hc.core5.http.HttpException, java.io.IOException;
    Code:
       0: aload_0
       1: aload_1
       2: aload_2
       3: aconst_null
       4: aload_3
       5: aload         4
       7: invokevirtual #153                // Method execute:(Lorg/apache/hc/core5/http/HttpHost;Lorg/apache/hc/core5/http/ClassicHttpRequest;Lorg/apache/hc/core5/http/io/HttpResponseInformationCallback;Lorg/apache/hc/core5/util/Timeout;Lorg/apache/hc/core5/http/protocol/HttpContext;)Lorg/apache/hc/core5/http/ClassicHttpResponse;
      10: areturn

  public <T> T execute(org.apache.hc.core5.http.HttpHost, org.apache.hc.core5.http.ClassicHttpRequest, org.apache.hc.core5.util.Timeout, org.apache.hc.core5.http.protocol.HttpContext, org.apache.hc.core5.http.io.HttpClientResponseHandler<T>) throws org.apache.hc.core5.http.HttpException, java.io.IOException;
    Code:
       0: aload_0
       1: aload_1
       2: aload_2
       3: aconst_null
       4: aload_3
       5: aload         4
       7: invokevirtual #153                // Method execute:(Lorg/apache/hc/core5/http/HttpHost;Lorg/apache/hc/core5/http/ClassicHttpRequest;Lorg/apache/hc/core5/http/io/HttpResponseInformationCallback;Lorg/apache/hc/core5/util/Timeout;Lorg/apache/hc/core5/http/protocol/HttpContext;)Lorg/apache/hc/core5/http/ClassicHttpResponse;
      10: astore        6
      12: aconst_null
      13: astore        7
      15: aload         5
      17: aload         6
      19: invokeinterface #50,  2           // InterfaceMethod org/apache/hc/core5/http/io/HttpClientResponseHandler.handleResponse:(Lorg/apache/hc/core5/http/ClassicHttpResponse;)Ljava/lang/Object;
      24: astore        8
      26: aload         6
      28: invokeinterface #51,  1           // InterfaceMethod org/apache/hc/core5/http/ClassicHttpResponse.getEntity:()Lorg/apache/hc/core5/http/HttpEntity;
      33: invokestatic  #52                 // Method org/apache/hc/core5/http/io/entity/EntityUtils.consume:(Lorg/apache/hc/core5/http/HttpEntity;)V
      36: aload         8
      38: astore        9
      40: aload         6
      42: ifnull        79
      45: aload         7
      47: ifnull        72
      50: aload         6
      52: invokeinterface #53,  1           // InterfaceMethod org/apache/hc/core5/http/ClassicHttpResponse.close:()V
      57: goto          79
      60: astore        10
      62: aload         7
      64: aload         10
      66: invokevirtual #55                 // Method java/lang/Throwable.addSuppressed:(Ljava/lang/Throwable;)V
      69: goto          79
      72: aload         6
      74: invokeinterface #53,  1           // InterfaceMethod org/apache/hc/core5/http/ClassicHttpResponse.close:()V
      79: aload         9
      81: areturn
      82: astore        8
      84: aload         8
      86: astore        7
      88: aload         8
      90: athrow
      91: astore        11
      93: aload         6
      95: ifnull        132
      98: aload         7
     100: ifnull        125
     103: aload         6
     105: invokeinterface #53,  1           // InterfaceMethod org/apache/hc/core5/http/ClassicHttpResponse.close:()V
     110: goto          132
     113: astore        12
     115: aload         7
     117: aload         12
     119: invokevirtual #55                 // Method java/lang/Throwable.addSuppressed:(Ljava/lang/Throwable;)V
     122: goto          132
     125: aload         6
     127: invokeinterface #53,  1           // InterfaceMethod org/apache/hc/core5/http/ClassicHttpResponse.close:()V
     132: aload         11
     134: athrow
    Exception table:
       from    to  target type
          50    57    60   Class java/lang/Throwable
          15    40    82   Class java/lang/Throwable
          15    40    91   any
         103   110   113   Class java/lang/Throwable
          82    93    91   any

  public org.apache.hc.core5.pool.ConnPoolControl<org.apache.hc.core5.http.HttpHost> getConnPoolControl();
    Code:
       0: aload_0
       1: getfield      #1                  // Field connPool:Lorg/apache/hc/core5/pool/ManagedConnPool;
       4: areturn

  public void close(org.apache.hc.core5.io.CloseMode);
    Code:
       0: aload_0
       1: getfield      #1                  // Field connPool:Lorg/apache/hc/core5/pool/ManagedConnPool;
       4: aload_1
       5: invokeinterface #154,  2          // InterfaceMethod org/apache/hc/core5/pool/ManagedConnPool.close:(Lorg/apache/hc/core5/io/CloseMode;)V
      10: return

  public void close() throws java.io.IOException;
    Code:
       0: aload_0
       1: getfield      #1                  // Field connPool:Lorg/apache/hc/core5/pool/ManagedConnPool;
       4: invokeinterface #155,  1          // InterfaceMethod org/apache/hc/core5/pool/ManagedConnPool.close:()V
       9: return

  public int getMaxPerRoute(java.lang.Object);
    Code:
       0: aload_0
       1: aload_1
       2: checkcast     #156                // class org/apache/hc/core5/http/HttpHost
       5: invokevirtual #157                // Method getMaxPerRoute:(Lorg/apache/hc/core5/http/HttpHost;)I
       8: ireturn

  public void setMaxPerRoute(java.lang.Object, int);
    Code:
       0: aload_0
       1: aload_1
       2: checkcast     #156                // class org/apache/hc/core5/http/HttpHost
       5: iload_2
       6: invokevirtual #158                // Method setMaxPerRoute:(Lorg/apache/hc/core5/http/HttpHost;I)V
       9: return

  public org.apache.hc.core5.pool.PoolStats getStats(java.lang.Object);
    Code:
       0: aload_0
       1: aload_1
       2: checkcast     #156                // class org/apache/hc/core5/http/HttpHost
       5: invokevirtual #159                // Method getStats:(Lorg/apache/hc/core5/http/HttpHost;)Lorg/apache/hc/core5/pool/PoolStats;
       8: areturn

  static org.apache.hc.core5.http.io.SocketConfig access$000(org.apache.hc.core5.http.impl.bootstrap.HttpRequester);
    Code:
       0: aload_0
       1: getfield      #3                  // Field socketConfig:Lorg/apache/hc/core5/http/io/SocketConfig;
       4: areturn

  static org.apache.hc.core5.http.impl.io.HttpRequestExecutor access$100(org.apache.hc.core5.http.impl.bootstrap.HttpRequester);
    Code:
       0: aload_0
       1: getfield      #2                  // Field requestExecutor:Lorg/apache/hc/core5/http/impl/io/HttpRequestExecutor;
       4: areturn

  static org.apache.hc.core5.pool.ManagedConnPool access$400(org.apache.hc.core5.http.impl.bootstrap.HttpRequester);
    Code:
       0: aload_0
       1: getfield      #1                  // Field connPool:Lorg/apache/hc/core5/pool/ManagedConnPool;
       4: areturn
}
