Compiled from "WeavingAdaptor.java"
public class org.aspectj.weaver.tools.WeavingAdaptor$WeavingAdaptorMessageHolder extends org.aspectj.bridge.MessageHandler {
  private org.aspectj.bridge.IMessageHandler delegate;

  private java.util.List<org.aspectj.bridge.IMessage> savedMessages;

  protected boolean traceMessages;

  final org.aspectj.weaver.tools.WeavingAdaptor this$0;

  public org.aspectj.weaver.tools.WeavingAdaptor$WeavingAdaptorMessageHolder(org.aspectj.weaver.tools.WeavingAdaptor, java.io.PrintWriter);
    Code:
       0: aload_0
       1: aload_1
       2: putfield      #2                  // Field this$0:Lorg/aspectj/weaver/tools/WeavingAdaptor;
       5: aload_0
       6: invokespecial #3                  // Method org/aspectj/bridge/MessageHandler."<init>":()V
       9: aload_0
      10: ldc           #4                  // String org.aspectj.tracing.messages
      12: invokestatic  #5                  // Method java/lang/Boolean.getBoolean:(Ljava/lang/String;)Z
      15: putfield      #6                  // Field traceMessages:Z
      18: aload_0
      19: new           #7                  // class org/aspectj/weaver/tools/WeavingAdaptor$WeavingAdaptorMessageWriter
      22: dup
      23: aload_1
      24: aload_2
      25: invokespecial #8                  // Method org/aspectj/weaver/tools/WeavingAdaptor$WeavingAdaptorMessageWriter."<init>":(Lorg/aspectj/weaver/tools/WeavingAdaptor;Ljava/io/PrintWriter;)V
      28: putfield      #9                  // Field delegate:Lorg/aspectj/bridge/IMessageHandler;
      31: aload_0
      32: getstatic     #10                 // Field org/aspectj/bridge/IMessage.WEAVEINFO:Lorg/aspectj/bridge/IMessage$Kind;
      35: invokespecial #11                 // Method org/aspectj/bridge/MessageHandler.dontIgnore:(Lorg/aspectj/bridge/IMessage$Kind;)V
      38: return

  private void traceMessage(org.aspectj.bridge.IMessage);
    Code:
       0: aload_1
       1: instanceof    #12                 // class org/aspectj/bridge/WeaveMessage
       4: ifeq          23
       7: invokestatic  #13                 // Method org/aspectj/weaver/tools/WeavingAdaptor.access$000:()Lorg/aspectj/weaver/tools/Trace;
      10: aload_0
      11: aload_1
      12: invokevirtual #14                 // Method render:(Lorg/aspectj/bridge/IMessage;)Ljava/lang/String;
      15: invokeinterface #15,  2           // InterfaceMethod org/aspectj/weaver/tools/Trace.debug:(Ljava/lang/String;)V
      20: goto          216
      23: aload_1
      24: invokeinterface #16,  1           // InterfaceMethod org/aspectj/bridge/IMessage.isDebug:()Z
      29: ifeq          48
      32: invokestatic  #13                 // Method org/aspectj/weaver/tools/WeavingAdaptor.access$000:()Lorg/aspectj/weaver/tools/Trace;
      35: aload_0
      36: aload_1
      37: invokevirtual #14                 // Method render:(Lorg/aspectj/bridge/IMessage;)Ljava/lang/String;
      40: invokeinterface #15,  2           // InterfaceMethod org/aspectj/weaver/tools/Trace.debug:(Ljava/lang/String;)V
      45: goto          216
      48: aload_1
      49: invokeinterface #17,  1           // InterfaceMethod org/aspectj/bridge/IMessage.isInfo:()Z
      54: ifeq          73
      57: invokestatic  #13                 // Method org/aspectj/weaver/tools/WeavingAdaptor.access$000:()Lorg/aspectj/weaver/tools/Trace;
      60: aload_0
      61: aload_1
      62: invokevirtual #14                 // Method render:(Lorg/aspectj/bridge/IMessage;)Ljava/lang/String;
      65: invokeinterface #18,  2           // InterfaceMethod org/aspectj/weaver/tools/Trace.info:(Ljava/lang/String;)V
      70: goto          216
      73: aload_1
      74: invokeinterface #19,  1           // InterfaceMethod org/aspectj/bridge/IMessage.isWarning:()Z
      79: ifeq          104
      82: invokestatic  #13                 // Method org/aspectj/weaver/tools/WeavingAdaptor.access$000:()Lorg/aspectj/weaver/tools/Trace;
      85: aload_0
      86: aload_1
      87: invokevirtual #14                 // Method render:(Lorg/aspectj/bridge/IMessage;)Ljava/lang/String;
      90: aload_1
      91: invokeinterface #20,  1           // InterfaceMethod org/aspectj/bridge/IMessage.getThrown:()Ljava/lang/Throwable;
      96: invokeinterface #21,  3           // InterfaceMethod org/aspectj/weaver/tools/Trace.warn:(Ljava/lang/String;Ljava/lang/Throwable;)V
     101: goto          216
     104: aload_1
     105: invokeinterface #22,  1           // InterfaceMethod org/aspectj/bridge/IMessage.isError:()Z
     110: ifeq          135
     113: invokestatic  #13                 // Method org/aspectj/weaver/tools/WeavingAdaptor.access$000:()Lorg/aspectj/weaver/tools/Trace;
     116: aload_0
     117: aload_1
     118: invokevirtual #14                 // Method render:(Lorg/aspectj/bridge/IMessage;)Ljava/lang/String;
     121: aload_1
     122: invokeinterface #20,  1           // InterfaceMethod org/aspectj/bridge/IMessage.getThrown:()Ljava/lang/Throwable;
     127: invokeinterface #23,  3           // InterfaceMethod org/aspectj/weaver/tools/Trace.error:(Ljava/lang/String;Ljava/lang/Throwable;)V
     132: goto          216
     135: aload_1
     136: invokeinterface #24,  1           // InterfaceMethod org/aspectj/bridge/IMessage.isFailed:()Z
     141: ifeq          166
     144: invokestatic  #13                 // Method org/aspectj/weaver/tools/WeavingAdaptor.access$000:()Lorg/aspectj/weaver/tools/Trace;
     147: aload_0
     148: aload_1
     149: invokevirtual #14                 // Method render:(Lorg/aspectj/bridge/IMessage;)Ljava/lang/String;
     152: aload_1
     153: invokeinterface #20,  1           // InterfaceMethod org/aspectj/bridge/IMessage.getThrown:()Ljava/lang/Throwable;
     158: invokeinterface #25,  3           // InterfaceMethod org/aspectj/weaver/tools/Trace.fatal:(Ljava/lang/String;Ljava/lang/Throwable;)V
     163: goto          216
     166: aload_1
     167: invokeinterface #26,  1           // InterfaceMethod org/aspectj/bridge/IMessage.isAbort:()Z
     172: ifeq          197
     175: invokestatic  #13                 // Method org/aspectj/weaver/tools/WeavingAdaptor.access$000:()Lorg/aspectj/weaver/tools/Trace;
     178: aload_0
     179: aload_1
     180: invokevirtual #14                 // Method render:(Lorg/aspectj/bridge/IMessage;)Ljava/lang/String;
     183: aload_1
     184: invokeinterface #20,  1           // InterfaceMethod org/aspectj/bridge/IMessage.getThrown:()Ljava/lang/Throwable;
     189: invokeinterface #25,  3           // InterfaceMethod org/aspectj/weaver/tools/Trace.fatal:(Ljava/lang/String;Ljava/lang/Throwable;)V
     194: goto          216
     197: invokestatic  #13                 // Method org/aspectj/weaver/tools/WeavingAdaptor.access$000:()Lorg/aspectj/weaver/tools/Trace;
     200: aload_0
     201: aload_1
     202: invokevirtual #14                 // Method render:(Lorg/aspectj/bridge/IMessage;)Ljava/lang/String;
     205: aload_1
     206: invokeinterface #20,  1           // InterfaceMethod org/aspectj/bridge/IMessage.getThrown:()Ljava/lang/Throwable;
     211: invokeinterface #23,  3           // InterfaceMethod org/aspectj/weaver/tools/Trace.error:(Ljava/lang/String;Ljava/lang/Throwable;)V
     216: return

  protected java.lang.String render(org.aspectj.bridge.IMessage);
    Code:
       0: new           #27                 // class java/lang/StringBuilder
       3: dup
       4: invokespecial #28                 // Method java/lang/StringBuilder."<init>":()V
       7: ldc           #29                 // String [
       9: invokevirtual #30                 // Method java/lang/StringBuilder.append:(Ljava/lang/String;)Ljava/lang/StringBuilder;
      12: aload_0
      13: getfield      #2                  // Field this$0:Lorg/aspectj/weaver/tools/WeavingAdaptor;
      16: invokevirtual #31                 // Method org/aspectj/weaver/tools/WeavingAdaptor.getContextId:()Ljava/lang/String;
      19: invokevirtual #30                 // Method java/lang/StringBuilder.append:(Ljava/lang/String;)Ljava/lang/StringBuilder;
      22: ldc           #32                 // String ]
      24: invokevirtual #30                 // Method java/lang/StringBuilder.append:(Ljava/lang/String;)Ljava/lang/StringBuilder;
      27: aload_1
      28: invokevirtual #33                 // Method java/lang/Object.toString:()Ljava/lang/String;
      31: invokevirtual #30                 // Method java/lang/StringBuilder.append:(Ljava/lang/String;)Ljava/lang/StringBuilder;
      34: invokevirtual #34                 // Method java/lang/StringBuilder.toString:()Ljava/lang/String;
      37: areturn

  public void flushMessages();
    Code:
       0: aload_0
       1: getfield      #35                 // Field savedMessages:Ljava/util/List;
       4: ifnonnull     79
       7: aload_0
       8: new           #36                 // class java/util/ArrayList
      11: dup
      12: invokespecial #37                 // Method java/util/ArrayList."<init>":()V
      15: putfield      #35                 // Field savedMessages:Ljava/util/List;
      18: aload_0
      19: getfield      #35                 // Field savedMessages:Ljava/util/List;
      22: aload_0
      23: invokespecial #38                 // Method org/aspectj/bridge/MessageHandler.getUnmodifiableListView:()Ljava/util/List;
      26: invokeinterface #39,  2           // InterfaceMethod java/util/List.addAll:(Ljava/util/Collection;)Z
      31: pop
      32: aload_0
      33: invokevirtual #40                 // Method clearMessages:()V
      36: aload_0
      37: getfield      #35                 // Field savedMessages:Ljava/util/List;
      40: invokeinterface #41,  1           // InterfaceMethod java/util/List.iterator:()Ljava/util/Iterator;
      45: astore_1
      46: aload_1
      47: invokeinterface #42,  1           // InterfaceMethod java/util/Iterator.hasNext:()Z
      52: ifeq          79
      55: aload_1
      56: invokeinterface #43,  1           // InterfaceMethod java/util/Iterator.next:()Ljava/lang/Object;
      61: checkcast     #44                 // class org/aspectj/bridge/IMessage
      64: astore_2
      65: aload_0
      66: getfield      #9                  // Field delegate:Lorg/aspectj/bridge/IMessageHandler;
      69: aload_2
      70: invokeinterface #45,  2           // InterfaceMethod org/aspectj/bridge/IMessageHandler.handleMessage:(Lorg/aspectj/bridge/IMessage;)Z
      75: pop
      76: goto          46
      79: return

  public void setDelegate(org.aspectj.bridge.IMessageHandler);
    Code:
       0: aload_0
       1: aload_1
       2: putfield      #9                  // Field delegate:Lorg/aspectj/bridge/IMessageHandler;
       5: return

  public boolean handleMessage(org.aspectj.bridge.IMessage) throws org.aspectj.bridge.AbortException;
    Code:
       0: aload_0
       1: getfield      #6                  // Field traceMessages:Z
       4: ifeq          12
       7: aload_0
       8: aload_1
       9: invokespecial #46                 // Method traceMessage:(Lorg/aspectj/bridge/IMessage;)V
      12: aload_0
      13: aload_1
      14: invokespecial #47                 // Method org/aspectj/bridge/MessageHandler.handleMessage:(Lorg/aspectj/bridge/IMessage;)Z
      17: pop
      18: aload_0
      19: getfield      #2                  // Field this$0:Lorg/aspectj/weaver/tools/WeavingAdaptor;
      22: invokestatic  #48                 // Method org/aspectj/weaver/tools/WeavingAdaptor.access$100:(Lorg/aspectj/weaver/tools/WeavingAdaptor;)Z
      25: ifeq          53
      28: iconst_0
      29: aload_1
      30: invokeinterface #49,  1           // InterfaceMethod org/aspectj/bridge/IMessage.getKind:()Lorg/aspectj/bridge/IMessage$Kind;
      35: getstatic     #50                 // Field org/aspectj/bridge/IMessage.ERROR:Lorg/aspectj/bridge/IMessage$Kind;
      38: invokevirtual #51                 // Method org/aspectj/bridge/IMessage$Kind.compareTo:(Lorg/aspectj/bridge/IMessage$Kind;)I
      41: if_icmpgt     53
      44: new           #52                 // class org/aspectj/bridge/AbortException
      47: dup
      48: aload_1
      49: invokespecial #53                 // Method org/aspectj/bridge/AbortException."<init>":(Lorg/aspectj/bridge/IMessage;)V
      52: athrow
      53: aload_0
      54: getfield      #35                 // Field savedMessages:Ljava/util/List;
      57: ifnull        71
      60: aload_0
      61: getfield      #9                  // Field delegate:Lorg/aspectj/bridge/IMessageHandler;
      64: aload_1
      65: invokeinterface #45,  2           // InterfaceMethod org/aspectj/bridge/IMessageHandler.handleMessage:(Lorg/aspectj/bridge/IMessage;)Z
      70: pop
      71: iconst_1
      72: ireturn

  public boolean isIgnoring(org.aspectj.bridge.IMessage$Kind);
    Code:
       0: aload_0
       1: getfield      #9                  // Field delegate:Lorg/aspectj/bridge/IMessageHandler;
       4: aload_1
       5: invokeinterface #54,  2           // InterfaceMethod org/aspectj/bridge/IMessageHandler.isIgnoring:(Lorg/aspectj/bridge/IMessage$Kind;)Z
      10: ireturn

  public void dontIgnore(org.aspectj.bridge.IMessage$Kind);
    Code:
       0: aconst_null
       1: aload_1
       2: if_acmpeq     22
       5: aload_0
       6: getfield      #9                  // Field delegate:Lorg/aspectj/bridge/IMessageHandler;
       9: ifnull        22
      12: aload_0
      13: getfield      #9                  // Field delegate:Lorg/aspectj/bridge/IMessageHandler;
      16: aload_1
      17: invokeinterface #55,  2           // InterfaceMethod org/aspectj/bridge/IMessageHandler.dontIgnore:(Lorg/aspectj/bridge/IMessage$Kind;)V
      22: return

  public void ignore(org.aspectj.bridge.IMessage$Kind);
    Code:
       0: aconst_null
       1: aload_1
       2: if_acmpeq     22
       5: aload_0
       6: getfield      #9                  // Field delegate:Lorg/aspectj/bridge/IMessageHandler;
       9: ifnull        22
      12: aload_0
      13: getfield      #9                  // Field delegate:Lorg/aspectj/bridge/IMessageHandler;
      16: aload_1
      17: invokeinterface #56,  2           // InterfaceMethod org/aspectj/bridge/IMessageHandler.ignore:(Lorg/aspectj/bridge/IMessage$Kind;)V
      22: return

  public java.util.List<org.aspectj.bridge.IMessage> getUnmodifiableListView();
    Code:
       0: new           #36                 // class java/util/ArrayList
       3: dup
       4: invokespecial #37                 // Method java/util/ArrayList."<init>":()V
       7: astore_1
       8: aload_1
       9: aload_0
      10: getfield      #35                 // Field savedMessages:Ljava/util/List;
      13: invokeinterface #39,  2           // InterfaceMethod java/util/List.addAll:(Ljava/util/Collection;)Z
      18: pop
      19: aload_1
      20: aload_0
      21: invokespecial #38                 // Method org/aspectj/bridge/MessageHandler.getUnmodifiableListView:()Ljava/util/List;
      24: invokeinterface #39,  2           // InterfaceMethod java/util/List.addAll:(Ljava/util/Collection;)Z
      29: pop
      30: aload_1
      31: areturn
}
