Compiled from "ELNode.java"
public class org.apache.jasper.compiler.ELNode$Function extends org.apache.jasper.compiler.ELNode {
  private final java.lang.String prefix;

  private final java.lang.String name;

  private final java.lang.String originalText;

  private java.lang.String uri;

  private javax.servlet.jsp.tagext.FunctionInfo functionInfo;

  private java.lang.String methodName;

  private java.lang.String[] parameters;

  org.apache.jasper.compiler.ELNode$Function(java.lang.String, java.lang.String, java.lang.String);
    Code:
       0: aload_0
       1: invokespecial #1                  // Method org/apache/jasper/compiler/ELNode."<init>":()V
       4: aload_0
       5: aload_1
       6: putfield      #2                  // Field prefix:Ljava/lang/String;
       9: aload_0
      10: aload_2
      11: putfield      #3                  // Field name:Ljava/lang/String;
      14: aload_0
      15: aload_3
      16: putfield      #4                  // Field originalText:Ljava/lang/String;
      19: return

  public void accept(org.apache.jasper.compiler.ELNode$Visitor) throws org.apache.jasper.JasperException;
    Code:
       0: aload_1
       1: aload_0
       2: invokevirtual #5                  // Method org/apache/jasper/compiler/ELNode$Visitor.visit:(Lorg/apache/jasper/compiler/ELNode$Function;)V
       5: return

  public java.lang.String getPrefix();
    Code:
       0: aload_0
       1: getfield      #2                  // Field prefix:Ljava/lang/String;
       4: areturn

  public java.lang.String getName();
    Code:
       0: aload_0
       1: getfield      #3                  // Field name:Ljava/lang/String;
       4: areturn

  public java.lang.String getOriginalText();
    Code:
       0: aload_0
       1: getfield      #4                  // Field originalText:Ljava/lang/String;
       4: areturn

  public void setUri(java.lang.String);
    Code:
       0: aload_0
       1: aload_1
       2: putfield      #6                  // Field uri:Ljava/lang/String;
       5: return

  public java.lang.String getUri();
    Code:
       0: aload_0
       1: getfield      #6                  // Field uri:Ljava/lang/String;
       4: areturn

  public void setFunctionInfo(javax.servlet.jsp.tagext.FunctionInfo);
    Code:
       0: aload_0
       1: aload_1
       2: putfield      #7                  // Field functionInfo:Ljavax/servlet/jsp/tagext/FunctionInfo;
       5: return

  public javax.servlet.jsp.tagext.FunctionInfo getFunctionInfo();
    Code:
       0: aload_0
       1: getfield      #7                  // Field functionInfo:Ljavax/servlet/jsp/tagext/FunctionInfo;
       4: areturn

  public void setMethodName(java.lang.String);
    Code:
       0: aload_0
       1: aload_1
       2: putfield      #8                  // Field methodName:Ljava/lang/String;
       5: return

  public java.lang.String getMethodName();
    Code:
       0: aload_0
       1: getfield      #8                  // Field methodName:Ljava/lang/String;
       4: areturn

  public void setParameters(java.lang.String[]);
    Code:
       0: aload_0
       1: aload_1
       2: putfield      #9                  // Field parameters:[Ljava/lang/String;
       5: return

  public java.lang.String[] getParameters();
    Code:
       0: aload_0
       1: getfield      #9                  // Field parameters:[Ljava/lang/String;
       4: areturn
}
