Compiled from "Generator.java"
class org.apache.jasper.compiler.Generator$FragmentHelperClass$Fragment {
  private org.apache.jasper.compiler.Generator$GenBuffer genBuffer;

  private int id;

  public org.apache.jasper.compiler.Generator$FragmentHelperClass$Fragment(int, org.apache.jasper.compiler.Node);
    Code:
       0: aload_0
       1: invokespecial #1                  // Method java/lang/Object."<init>":()V
       4: aload_0
       5: iload_1
       6: putfield      #2                  // Field id:I
       9: aload_0
      10: new           #3                  // class org/apache/jasper/compiler/Generator$GenBuffer
      13: dup
      14: aconst_null
      15: aload_2
      16: invokevirtual #4                  // Method org/apache/jasper/compiler/Node.getBody:()Lorg/apache/jasper/compiler/Node$Nodes;
      19: invokespecial #5                  // Method org/apache/jasper/compiler/Generator$GenBuffer."<init>":(Lorg/apache/jasper/compiler/Node;Lorg/apache/jasper/compiler/Node$Nodes;)V
      22: putfield      #6                  // Field genBuffer:Lorg/apache/jasper/compiler/Generator$GenBuffer;
      25: return

  public org.apache.jasper.compiler.Generator$GenBuffer getGenBuffer();
    Code:
       0: aload_0
       1: getfield      #6                  // Field genBuffer:Lorg/apache/jasper/compiler/Generator$GenBuffer;
       4: areturn

  public int getId();
    Code:
       0: aload_0
       1: getfield      #2                  // Field id:I
       4: ireturn
}
