Compiled from "Generator.java"
class org.apache.jasper.compiler.Generator$GenerateVisitor$2ParamVisitor extends org.apache.jasper.compiler.Node$Visitor {
  private final boolean ie;

  final org.apache.jasper.compiler.Generator$GenerateVisitor this$1;

  org.apache.jasper.compiler.Generator$GenerateVisitor$2ParamVisitor(org.apache.jasper.compiler.Generator$GenerateVisitor, boolean);
    Code:
       0: aload_0
       1: aload_1
       2: putfield      #1                  // Field this$1:Lorg/apache/jasper/compiler/Generator$GenerateVisitor;
       5: aload_0
       6: invokespecial #2                  // Method org/apache/jasper/compiler/Node$Visitor."<init>":()V
       9: aload_0
      10: iload_2
      11: putfield      #3                  // Field ie:Z
      14: return

  public void visit(org.apache.jasper.compiler.Node$ParamAction) throws org.apache.jasper.JasperException;
    Code:
       0: aload_1
       1: ldc           #4                  // String name
       3: invokevirtual #5                  // Method org/apache/jasper/compiler/Node$ParamAction.getTextAttribute:(Ljava/lang/String;)Ljava/lang/String;
       6: astore_2
       7: aload_2
       8: ldc           #6                  // String object
      10: invokevirtual #7                  // Method java/lang/String.equalsIgnoreCase:(Ljava/lang/String;)Z
      13: ifeq          22
      16: ldc           #8                  // String java_object
      18: astore_2
      19: goto          34
      22: aload_2
      23: ldc           #9                  // String type
      25: invokevirtual #7                  // Method java/lang/String.equalsIgnoreCase:(Ljava/lang/String;)Z
      28: ifeq          34
      31: ldc           #10                 // String java_type
      33: astore_2
      34: aload_1
      35: aload_0
      36: getfield      #1                  // Field this$1:Lorg/apache/jasper/compiler/Generator$GenerateVisitor;
      39: invokestatic  #11                 // Method org/apache/jasper/compiler/Generator$GenerateVisitor.access$300:(Lorg/apache/jasper/compiler/Generator$GenerateVisitor;)Lorg/apache/jasper/compiler/ServletWriter;
      42: invokevirtual #12                 // Method org/apache/jasper/compiler/ServletWriter.getJavaLine:()I
      45: invokevirtual #13                 // Method org/apache/jasper/compiler/Node$ParamAction.setBeginJavaLine:(I)V
      48: aload_0
      49: getfield      #3                  // Field ie:Z
      52: ifeq          129
      55: aload_0
      56: getfield      #1                  // Field this$1:Lorg/apache/jasper/compiler/Generator$GenerateVisitor;
      59: invokestatic  #11                 // Method org/apache/jasper/compiler/Generator$GenerateVisitor.access$300:(Lorg/apache/jasper/compiler/Generator$GenerateVisitor;)Lorg/apache/jasper/compiler/ServletWriter;
      62: new           #14                 // class java/lang/StringBuilder
      65: dup
      66: invokespecial #15                 // Method java/lang/StringBuilder."<init>":()V
      69: ldc           #16                 // String out.write( \"<param name=\\\"
      71: invokevirtual #17                 // Method java/lang/StringBuilder.append:(Ljava/lang/String;)Ljava/lang/StringBuilder;
      74: aload_2
      75: invokestatic  #18                 // Method org/apache/jasper/compiler/Generator.escape:(Ljava/lang/String;)Ljava/lang/String;
      78: invokevirtual #17                 // Method java/lang/StringBuilder.append:(Ljava/lang/String;)Ljava/lang/StringBuilder;
      81: ldc           #19                 // String \\\" value=\\\"\" +
      83: invokevirtual #17                 // Method java/lang/StringBuilder.append:(Ljava/lang/String;)Ljava/lang/StringBuilder;
      86: aload_0
      87: getfield      #1                  // Field this$1:Lorg/apache/jasper/compiler/Generator$GenerateVisitor;
      90: aload_1
      91: invokevirtual #20                 // Method org/apache/jasper/compiler/Node$ParamAction.getValue:()Lorg/apache/jasper/compiler/Node$JspAttribute;
      94: iconst_0
      95: ldc           #21                 // class java/lang/String
      97: invokestatic  #22                 // Method org/apache/jasper/compiler/Generator$GenerateVisitor.access$400:(Lorg/apache/jasper/compiler/Generator$GenerateVisitor;Lorg/apache/jasper/compiler/Node$JspAttribute;ZLjava/lang/Class;)Ljava/lang/String;
     100: invokevirtual #17                 // Method java/lang/StringBuilder.append:(Ljava/lang/String;)Ljava/lang/StringBuilder;
     103: ldc           #23                 // String  + \"\\\">\" );
     105: invokevirtual #17                 // Method java/lang/StringBuilder.append:(Ljava/lang/String;)Ljava/lang/StringBuilder;
     108: invokevirtual #24                 // Method java/lang/StringBuilder.toString:()Ljava/lang/String;
     111: invokevirtual #25                 // Method org/apache/jasper/compiler/ServletWriter.printil:(Ljava/lang/String;)V
     114: aload_0
     115: getfield      #1                  // Field this$1:Lorg/apache/jasper/compiler/Generator$GenerateVisitor;
     118: invokestatic  #11                 // Method org/apache/jasper/compiler/Generator$GenerateVisitor.access$300:(Lorg/apache/jasper/compiler/Generator$GenerateVisitor;)Lorg/apache/jasper/compiler/ServletWriter;
     121: ldc           #26                 // String out.write(\"\\n\");
     123: invokevirtual #25                 // Method org/apache/jasper/compiler/ServletWriter.printil:(Ljava/lang/String;)V
     126: goto          188
     129: aload_0
     130: getfield      #1                  // Field this$1:Lorg/apache/jasper/compiler/Generator$GenerateVisitor;
     133: invokestatic  #11                 // Method org/apache/jasper/compiler/Generator$GenerateVisitor.access$300:(Lorg/apache/jasper/compiler/Generator$GenerateVisitor;)Lorg/apache/jasper/compiler/ServletWriter;
     136: new           #14                 // class java/lang/StringBuilder
     139: dup
     140: invokespecial #15                 // Method java/lang/StringBuilder."<init>":()V
     143: ldc           #27                 // String out.write( \"
     145: invokevirtual #17                 // Method java/lang/StringBuilder.append:(Ljava/lang/String;)Ljava/lang/StringBuilder;
     148: aload_2
     149: invokestatic  #18                 // Method org/apache/jasper/compiler/Generator.escape:(Ljava/lang/String;)Ljava/lang/String;
     152: invokevirtual #17                 // Method java/lang/StringBuilder.append:(Ljava/lang/String;)Ljava/lang/StringBuilder;
     155: ldc           #28                 // String =\\\"\" +
     157: invokevirtual #17                 // Method java/lang/StringBuilder.append:(Ljava/lang/String;)Ljava/lang/StringBuilder;
     160: aload_0
     161: getfield      #1                  // Field this$1:Lorg/apache/jasper/compiler/Generator$GenerateVisitor;
     164: aload_1
     165: invokevirtual #20                 // Method org/apache/jasper/compiler/Node$ParamAction.getValue:()Lorg/apache/jasper/compiler/Node$JspAttribute;
     168: iconst_0
     169: ldc           #21                 // class java/lang/String
     171: invokestatic  #22                 // Method org/apache/jasper/compiler/Generator$GenerateVisitor.access$400:(Lorg/apache/jasper/compiler/Generator$GenerateVisitor;Lorg/apache/jasper/compiler/Node$JspAttribute;ZLjava/lang/Class;)Ljava/lang/String;
     174: invokevirtual #17                 // Method java/lang/StringBuilder.append:(Ljava/lang/String;)Ljava/lang/StringBuilder;
     177: ldc           #29                 // String  + \"\\\"\" );
     179: invokevirtual #17                 // Method java/lang/StringBuilder.append:(Ljava/lang/String;)Ljava/lang/StringBuilder;
     182: invokevirtual #24                 // Method java/lang/StringBuilder.toString:()Ljava/lang/String;
     185: invokevirtual #25                 // Method org/apache/jasper/compiler/ServletWriter.printil:(Ljava/lang/String;)V
     188: aload_1
     189: aload_0
     190: getfield      #1                  // Field this$1:Lorg/apache/jasper/compiler/Generator$GenerateVisitor;
     193: invokestatic  #11                 // Method org/apache/jasper/compiler/Generator$GenerateVisitor.access$300:(Lorg/apache/jasper/compiler/Generator$GenerateVisitor;)Lorg/apache/jasper/compiler/ServletWriter;
     196: invokevirtual #12                 // Method org/apache/jasper/compiler/ServletWriter.getJavaLine:()I
     199: invokevirtual #30                 // Method org/apache/jasper/compiler/Node$ParamAction.setEndJavaLine:(I)V
     202: return
}
