Compiled from "Validator.java"
class org.apache.jasper.compiler.Validator$ValidateVisitor$XmlEscapeNonELVisitor extends org.apache.jasper.compiler.ELParser$TextBuilder {
  protected org.apache.jasper.compiler.Validator$ValidateVisitor$XmlEscapeNonELVisitor(boolean);
    Code:
       0: aload_0
       1: iload_1
       2: invokespecial #1                  // Method org/apache/jasper/compiler/ELParser$TextBuilder."<init>":(Z)V
       5: return

  public void visit(org.apache.jasper.compiler.ELNode$Text) throws org.apache.jasper.JasperException;
    Code:
       0: aload_0
       1: getfield      #2                  // Field output:Ljava/lang/StringBuilder;
       4: aload_1
       5: invokevirtual #3                  // Method org/apache/jasper/compiler/ELNode$Text.getText:()Ljava/lang/String;
       8: invokestatic  #4                  // Method org/apache/jasper/compiler/Validator.xmlEscape:(Ljava/lang/String;)Ljava/lang/String;
      11: aload_0
      12: getfield      #5                  // Field isDeferredSyntaxAllowedAsLiteral:Z
      15: invokestatic  #6                  // Method org/apache/jasper/compiler/ELParser.escapeLiteralExpression:(Ljava/lang/String;Z)Ljava/lang/String;
      18: invokevirtual #7                  // Method java/lang/StringBuilder.append:(Ljava/lang/String;)Ljava/lang/StringBuilder;
      21: pop
      22: return
}
