Compiled from "Tasks.scala"
public class scala.collection.parallel.AdaptiveWorkStealingForkJoinTasks$WrappedTask<R, Tp> extends scala.concurrent.forkjoin.RecursiveAction implements scala.collection.parallel.ForkJoinTasks$WrappedTask<R, Tp>, scala.collection.parallel.AdaptiveWorkStealingTasks$WrappedTask<R, Tp> {
  private final scala.collection.parallel.Task<R, Tp> body;

  public final scala.collection.parallel.AdaptiveWorkStealingForkJoinTasks $outer;

  private volatile scala.collection.parallel.AdaptiveWorkStealingTasks$WrappedTask<java.lang.Object, java.lang.Object> next;

  private volatile boolean shouldWaitFor;

  public scala.collection.parallel.AdaptiveWorkStealingTasks$WrappedTask<R, Tp> next();
    Code:
       0: aload_0
       1: getfield      #23                 // Field next:Lscala/collection/parallel/AdaptiveWorkStealingTasks$WrappedTask;
       4: areturn

  public void next_$eq(scala.collection.parallel.AdaptiveWorkStealingTasks$WrappedTask<R, Tp>);
    Code:
       0: aload_0
       1: aload_1
       2: putfield      #23                 // Field next:Lscala/collection/parallel/AdaptiveWorkStealingTasks$WrappedTask;
       5: return

  public boolean shouldWaitFor();
    Code:
       0: aload_0
       1: getfield      #32                 // Field shouldWaitFor:Z
       4: ireturn

  public void shouldWaitFor_$eq(boolean);
    Code:
       0: aload_0
       1: iload_1
       2: putfield      #32                 // Field shouldWaitFor:Z
       5: return

  public void compute();
    Code:
       0: aload_0
       1: invokestatic  #40                 // Method scala/collection/parallel/AdaptiveWorkStealingTasks$WrappedTask$class.compute:(Lscala/collection/parallel/AdaptiveWorkStealingTasks$WrappedTask;)V
       4: return

  public void internal();
    Code:
       0: aload_0
       1: invokestatic  #43                 // Method scala/collection/parallel/AdaptiveWorkStealingTasks$WrappedTask$class.internal:(Lscala/collection/parallel/AdaptiveWorkStealingTasks$WrappedTask;)V
       4: return

  public scala.collection.parallel.AdaptiveWorkStealingTasks$WrappedTask<R, Tp> spawnSubtasks();
    Code:
       0: aload_0
       1: invokestatic  #47                 // Method scala/collection/parallel/AdaptiveWorkStealingTasks$WrappedTask$class.spawnSubtasks:(Lscala/collection/parallel/AdaptiveWorkStealingTasks$WrappedTask;)Lscala/collection/parallel/AdaptiveWorkStealingTasks$WrappedTask;
       4: areturn

  public void printChain();
    Code:
       0: aload_0
       1: invokestatic  #50                 // Method scala/collection/parallel/AdaptiveWorkStealingTasks$WrappedTask$class.printChain:(Lscala/collection/parallel/AdaptiveWorkStealingTasks$WrappedTask;)V
       4: return

  public void start();
    Code:
       0: aload_0
       1: invokestatic  #56                 // Method scala/collection/parallel/ForkJoinTasks$WrappedTask$class.start:(Lscala/collection/parallel/ForkJoinTasks$WrappedTask;)V
       4: return

  public void sync();
    Code:
       0: aload_0
       1: invokestatic  #59                 // Method scala/collection/parallel/ForkJoinTasks$WrappedTask$class.sync:(Lscala/collection/parallel/ForkJoinTasks$WrappedTask;)V
       4: return

  public boolean tryCancel();
    Code:
       0: aload_0
       1: invokestatic  #63                 // Method scala/collection/parallel/ForkJoinTasks$WrappedTask$class.tryCancel:(Lscala/collection/parallel/ForkJoinTasks$WrappedTask;)Z
       4: ireturn

  public void release();
    Code:
       0: aload_0
       1: invokestatic  #69                 // Method scala/collection/parallel/Tasks$WrappedTask$class.release:(Lscala/collection/parallel/Tasks$WrappedTask;)V
       4: return

  public scala.collection.parallel.Task<R, Tp> body();
    Code:
       0: aload_0
       1: getfield      #72                 // Field body:Lscala/collection/parallel/Task;
       4: areturn

  public scala.collection.Seq<scala.collection.parallel.AdaptiveWorkStealingTasks$WrappedTask<R, Tp>> split();
    Code:
       0: aload_0
       1: invokevirtual #76                 // Method body:()Lscala/collection/parallel/Task;
       4: invokeinterface #80,  1           // InterfaceMethod scala/collection/parallel/Task.split:()Lscala/collection/Seq;
       9: new           #82                 // class scala/collection/parallel/AdaptiveWorkStealingForkJoinTasks$WrappedTask$$anonfun$split$1
      12: dup
      13: aload_0
      14: invokespecial #86                 // Method scala/collection/parallel/AdaptiveWorkStealingForkJoinTasks$WrappedTask$$anonfun$split$1."<init>":(Lscala/collection/parallel/AdaptiveWorkStealingForkJoinTasks$WrappedTask;)V
      17: getstatic     #92                 // Field scala/collection/Seq$.MODULE$:Lscala/collection/Seq$;
      20: invokevirtual #96                 // Method scala/collection/Seq$.canBuildFrom:()Lscala/collection/generic/CanBuildFrom;
      23: invokeinterface #102,  3          // InterfaceMethod scala/collection/Seq.map:(Lscala/Function1;Lscala/collection/generic/CanBuildFrom;)Ljava/lang/Object;
      28: checkcast     #98                 // class scala/collection/Seq
      31: areturn

  public scala.collection.parallel.AdaptiveWorkStealingForkJoinTasks scala$collection$parallel$AdaptiveWorkStealingForkJoinTasks$WrappedTask$$$outer();
    Code:
       0: aload_0
       1: getfield      #106                // Field $outer:Lscala/collection/parallel/AdaptiveWorkStealingForkJoinTasks;
       4: areturn

  public scala.collection.parallel.AdaptiveWorkStealingTasks scala$collection$parallel$AdaptiveWorkStealingTasks$WrappedTask$$$outer();
    Code:
       0: aload_0
       1: invokevirtual #110                // Method scala$collection$parallel$AdaptiveWorkStealingForkJoinTasks$WrappedTask$$$outer:()Lscala/collection/parallel/AdaptiveWorkStealingForkJoinTasks;
       4: areturn

  public scala.collection.parallel.ForkJoinTasks scala$collection$parallel$ForkJoinTasks$WrappedTask$$$outer();
    Code:
       0: aload_0
       1: invokevirtual #110                // Method scala$collection$parallel$AdaptiveWorkStealingForkJoinTasks$WrappedTask$$$outer:()Lscala/collection/parallel/AdaptiveWorkStealingForkJoinTasks;
       4: areturn

  public scala.collection.parallel.Tasks scala$collection$parallel$Tasks$WrappedTask$$$outer();
    Code:
       0: aload_0
       1: invokevirtual #110                // Method scala$collection$parallel$AdaptiveWorkStealingForkJoinTasks$WrappedTask$$$outer:()Lscala/collection/parallel/AdaptiveWorkStealingForkJoinTasks;
       4: areturn

  public scala.collection.parallel.AdaptiveWorkStealingForkJoinTasks$WrappedTask(scala.collection.parallel.AdaptiveWorkStealingForkJoinTasks, scala.collection.parallel.Task<R, Tp>);
    Code:
       0: aload_0
       1: aload_2
       2: putfield      #72                 // Field body:Lscala/collection/parallel/Task;
       5: aload_1
       6: ifnonnull     11
       9: aconst_null
      10: athrow
      11: aload_0
      12: aload_1
      13: putfield      #106                // Field $outer:Lscala/collection/parallel/AdaptiveWorkStealingForkJoinTasks;
      16: aload_0
      17: invokespecial #117                // Method scala/concurrent/forkjoin/RecursiveAction."<init>":()V
      20: aload_0
      21: invokestatic  #120                // Method scala/collection/parallel/Tasks$WrappedTask$class.$init$:(Lscala/collection/parallel/Tasks$WrappedTask;)V
      24: aload_0
      25: invokestatic  #122                // Method scala/collection/parallel/ForkJoinTasks$WrappedTask$class.$init$:(Lscala/collection/parallel/ForkJoinTasks$WrappedTask;)V
      28: aload_0
      29: invokestatic  #124                // Method scala/collection/parallel/AdaptiveWorkStealingTasks$WrappedTask$class.$init$:(Lscala/collection/parallel/AdaptiveWorkStealingTasks$WrappedTask;)V
      32: return
}
