Compiled from "Tasks.scala"
public final class scala.collection.parallel.FutureTasks$$anonfun$scala$collection$parallel$FutureTasks$$compute$1$3 extends scala.runtime.AbstractFunction0<scala.collection.parallel.Task<R, Tp>> implements scala.Serializable {
  public static final long serialVersionUID;

  private final scala.collection.parallel.Task task$1;

  public final scala.collection.parallel.Task<R, Tp> apply();
    Code:
       0: aload_0
       1: getfield      #23                 // Field task$1:Lscala/collection/parallel/Task;
       4: getstatic     #29                 // Field scala/None$.MODULE$:Lscala/None$;
       7: invokeinterface #35,  2           // InterfaceMethod scala/collection/parallel/Task.tryLeaf:(Lscala/Option;)V
      12: aload_0
      13: getfield      #23                 // Field task$1:Lscala/collection/parallel/Task;
      16: areturn

  public final java.lang.Object apply();
    Code:
       0: aload_0
       1: invokevirtual #40                 // Method apply:()Lscala/collection/parallel/Task;
       4: areturn

  public scala.collection.parallel.FutureTasks$$anonfun$scala$collection$parallel$FutureTasks$$compute$1$3(scala.collection.parallel.FutureTasks, scala.collection.parallel.Task);
    Code:
       0: aload_0
       1: aload_2
       2: putfield      #23                 // Field task$1:Lscala/collection/parallel/Task;
       5: aload_0
       6: invokespecial #45                 // Method scala/runtime/AbstractFunction0."<init>":()V
       9: return
}
