Compiled from "RemainsIterator.scala"
public final class scala.collection.parallel.IterableSplitter$Taken$$anonfun$split$1 extends scala.runtime.AbstractFunction2<scala.collection.parallel.IterableSplitter<T>, java.lang.Object, scala.collection.parallel.IterableSplitter<T>> implements scala.Serializable {
  public static final long serialVersionUID;

  public final scala.collection.parallel.IterableSplitter<T> apply(scala.collection.parallel.IterableSplitter<T>, int);
    Code:
       0: aload_1
       1: iload_2
       2: invokeinterface #25,  2           // InterfaceMethod scala/collection/parallel/IterableSplitter.take:(I)Lscala/collection/parallel/IterableSplitter;
       7: areturn

  public final java.lang.Object apply(java.lang.Object, java.lang.Object);
    Code:
       0: aload_0
       1: aload_1
       2: checkcast     #21                 // class scala/collection/parallel/IterableSplitter
       5: aload_2
       6: invokestatic  #38                 // Method scala/runtime/BoxesRunTime.unboxToInt:(Ljava/lang/Object;)I
       9: invokevirtual #40                 // Method apply:(Lscala/collection/parallel/IterableSplitter;I)Lscala/collection/parallel/IterableSplitter;
      12: areturn

  public scala.collection.parallel.IterableSplitter$Taken$$anonfun$split$1(scala.collection.parallel.IterableSplitter<T>.Taken);
    Code:
       0: aload_0
       1: invokespecial #48                 // Method scala/runtime/AbstractFunction2."<init>":()V
       4: return
}
