Compiled from "package.scala"
public final class scala.collection.parallel.package$ {
  public static final scala.collection.parallel.package$ MODULE$;

  private final int MIN_FOR_COPY;

  private final int CHECK_RATE;

  private final double SQRT2;

  private final int availableProcessors;

  private final scala.collection.parallel.TaskSupport defaultTaskSupport;

  public static {};
    Code:
       0: new           #2                  // class scala/collection/parallel/package$
       3: invokespecial #12                 // Method "<init>":()V
       6: return

  public int MIN_FOR_COPY();
    Code:
       0: aload_0
       1: getfield      #23                 // Field MIN_FOR_COPY:I
       4: ireturn

  public int CHECK_RATE();
    Code:
       0: aload_0
       1: getfield      #26                 // Field CHECK_RATE:I
       4: ireturn

  public double SQRT2();
    Code:
       0: aload_0
       1: getfield      #29                 // Field SQRT2:D
       4: dreturn

  public int availableProcessors();
    Code:
       0: aload_0
       1: getfield      #31                 // Field availableProcessors:I
       4: ireturn

  public int thresholdFromSize(int, int);
    Code:
       0: iload_2
       1: iconst_1
       2: if_icmple     16
       5: iconst_1
       6: iload_1
       7: bipush        8
       9: iload_2
      10: imul
      11: idiv
      12: iadd
      13: goto          17
      16: iload_1
      17: ireturn

  public scala.runtime.Nothing$ unsupported();
    Code:
       0: new           #39                 // class java/lang/UnsupportedOperationException
       3: dup
       4: invokespecial #40                 // Method java/lang/UnsupportedOperationException."<init>":()V
       7: athrow

  public scala.runtime.Nothing$ unsupportedop(java.lang.String);
    Code:
       0: new           #39                 // class java/lang/UnsupportedOperationException
       3: dup
       4: aload_1
       5: invokespecial #45                 // Method java/lang/UnsupportedOperationException."<init>":(Ljava/lang/String;)V
       8: athrow

  public scala.runtime.Nothing$ outofbounds(int);
    Code:
       0: new           #51                 // class java/lang/IndexOutOfBoundsException
       3: dup
       4: iload_1
       5: invokestatic  #57                 // Method scala/runtime/BoxesRunTime.boxToInteger:(I)Ljava/lang/Integer;
       8: invokevirtual #61                 // Method java/lang/Object.toString:()Ljava/lang/String;
      11: invokespecial #62                 // Method java/lang/IndexOutOfBoundsException."<init>":(Ljava/lang/String;)V
      14: athrow

  public scala.collection.parallel.TaskSupport getTaskSupport();
    Code:
       0: new           #67                 // class scala/collection/parallel/ExecutionContextTaskSupport
       3: dup
       4: getstatic     #72                 // Field scala/collection/parallel/ExecutionContextTaskSupport$.MODULE$:Lscala/collection/parallel/ExecutionContextTaskSupport$;
       7: invokevirtual #76                 // Method scala/collection/parallel/ExecutionContextTaskSupport$.$lessinit$greater$default$1:()Lscala/concurrent/ExecutionContext;
      10: invokespecial #79                 // Method scala/collection/parallel/ExecutionContextTaskSupport."<init>":(Lscala/concurrent/ExecutionContext;)V
      13: areturn

  public scala.collection.parallel.TaskSupport defaultTaskSupport();
    Code:
       0: aload_0
       1: getfield      #81                 // Field defaultTaskSupport:Lscala/collection/parallel/TaskSupport;
       4: areturn

  public <Coll> Coll setTaskSupport(Coll, scala.collection.parallel.TaskSupport);
    Code:
       0: aload_1
       1: instanceof    #85                 // class scala/collection/parallel/ParIterableLike
       4: ifeq          24
       7: aload_1
       8: checkcast     #85                 // class scala/collection/parallel/ParIterableLike
      11: aload_2
      12: invokeinterface #89,  2           // InterfaceMethod scala/collection/parallel/ParIterableLike.tasksupport_$eq:(Lscala/collection/parallel/TaskSupport;)V
      17: getstatic     #95                 // Field scala/runtime/BoxedUnit.UNIT:Lscala/runtime/BoxedUnit;
      20: pop
      21: goto          28
      24: getstatic     #95                 // Field scala/runtime/BoxedUnit.UNIT:Lscala/runtime/BoxedUnit;
      27: pop
      28: aload_1
      29: areturn

  public <C, T> scala.collection.parallel.package$CollectionsHaveToParArray<C, T> CollectionsHaveToParArray(C, scala.Function1<C, scala.collection.GenTraversableOnce<T>>);
    Code:
       0: new           #102                // class scala/collection/parallel/package$CollectionsHaveToParArray
       3: dup
       4: aload_1
       5: aload_2
       6: invokespecial #105                // Method scala/collection/parallel/package$CollectionsHaveToParArray."<init>":(Ljava/lang/Object;Lscala/Function1;)V
       9: areturn

  private scala.collection.parallel.package$();
    Code:
       0: aload_0
       1: invokespecial #108                // Method java/lang/Object."<init>":()V
       4: aload_0
       5: putstatic     #110                // Field MODULE$:Lscala/collection/parallel/package$;
       8: aload_0
       9: sipush        512
      12: putfield      #23                 // Field MIN_FOR_COPY:I
      15: aload_0
      16: sipush        512
      19: putfield      #26                 // Field CHECK_RATE:I
      22: aload_0
      23: getstatic     #115                // Field scala/math/package$.MODULE$:Lscala/math/package$;
      26: ldc2_w        #116                // double 2.0d
      29: invokevirtual #121                // Method scala/math/package$.sqrt:(D)D
      32: putfield      #29                 // Field SQRT2:D
      35: aload_0
      36: invokestatic  #127                // Method java/lang/Runtime.getRuntime:()Ljava/lang/Runtime;
      39: invokevirtual #129                // Method java/lang/Runtime.availableProcessors:()I
      42: putfield      #31                 // Field availableProcessors:I
      45: aload_0
      46: aload_0
      47: invokevirtual #131                // Method getTaskSupport:()Lscala/collection/parallel/TaskSupport;
      50: putfield      #81                 // Field defaultTaskSupport:Lscala/collection/parallel/TaskSupport;
      53: return
}
