Compiled from "package.scala"
public final class scala.collection.parallel.ParallelCollectionImplicits$$anon$2 implements scala.collection.parallel.TraversableOps<T> {
  private final scala.collection.GenTraversableOnce t$1;

  public boolean isParallel();
    Code:
       0: aload_0
       1: getfield      #19                 // Field t$1:Lscala/collection/GenTraversableOnce;
       4: instanceof    #21                 // class scala/collection/Parallel
       7: ireturn

  public boolean isParIterable();
    Code:
       0: aload_0
       1: getfield      #19                 // Field t$1:Lscala/collection/GenTraversableOnce;
       4: instanceof    #26                 // class scala/collection/parallel/ParIterable
       7: ireturn

  public scala.collection.parallel.ParIterable<T> asParIterable();
    Code:
       0: aload_0
       1: getfield      #19                 // Field t$1:Lscala/collection/GenTraversableOnce;
       4: checkcast     #26                 // class scala/collection/parallel/ParIterable
       7: areturn

  public boolean isParSeq();
    Code:
       0: aload_0
       1: getfield      #19                 // Field t$1:Lscala/collection/GenTraversableOnce;
       4: instanceof    #31                 // class scala/collection/parallel/ParSeq
       7: ireturn

  public scala.collection.parallel.ParSeq<T> asParSeq();
    Code:
       0: aload_0
       1: getfield      #19                 // Field t$1:Lscala/collection/GenTraversableOnce;
       4: checkcast     #31                 // class scala/collection/parallel/ParSeq
       7: areturn

  public <R> java.lang.Object ifParSeq(scala.Function1<scala.collection.parallel.ParSeq<T>, R>);
    Code:
       0: new           #37                 // class scala/collection/parallel/ParallelCollectionImplicits$$anon$2$$anon$3
       3: dup
       4: aload_0
       5: aload_1
       6: invokespecial #41                 // Method scala/collection/parallel/ParallelCollectionImplicits$$anon$2$$anon$3."<init>":(Lscala/collection/parallel/ParallelCollectionImplicits$$anon$2;Lscala/Function1;)V
       9: areturn

  public scala.collection.parallel.ParallelCollectionImplicits$$anon$2(scala.collection.GenTraversableOnce);
    Code:
       0: aload_0
       1: aload_1
       2: putfield      #19                 // Field t$1:Lscala/collection/GenTraversableOnce;
       5: aload_0
       6: invokespecial #47                 // Method java/lang/Object."<init>":()V
       9: aload_0
      10: invokestatic  #53                 // Method scala/collection/parallel/TraversableOps$class.$init$:(Lscala/collection/parallel/TraversableOps;)V
      13: return
}
