Compiled from "ParIterableLike.scala"
public final class scala.collection.parallel.ParIterableLike$$anon$19 implements scala.collection.parallel.CombinerFactory<T, Repr> {
  private final scala.collection.parallel.ParIterableLike $outer;

  public scala.collection.parallel.Combiner<T, Repr> apply();
    Code:
       0: aload_0
       1: getfield      #19                 // Field $outer:Lscala/collection/parallel/ParIterableLike;
       4: invokeinterface #22,  1           // InterfaceMethod scala/collection/parallel/ParIterableLike.newCombiner:()Lscala/collection/parallel/Combiner;
       9: areturn

  public boolean doesShareCombiners();
    Code:
       0: iconst_0
       1: ireturn

  public scala.collection.parallel.ParIterableLike$$anon$19(scala.collection.parallel.ParIterableLike<T, Repr, Sequential>);
    Code:
       0: aload_1
       1: ifnonnull     6
       4: aconst_null
       5: athrow
       6: aload_0
       7: aload_1
       8: putfield      #19                 // Field $outer:Lscala/collection/parallel/ParIterableLike;
      11: aload_0
      12: invokespecial #31                 // Method java/lang/Object."<init>":()V
      15: return
}
