Compiled from "ParSeqLike.scala"
public final class scala.collection.parallel.ParSeqLike$$anonfun$diff$1 extends scala.runtime.AbstractFunction1<Sequential, Sequential> implements scala.Serializable {
  public static final long serialVersionUID;

  private final scala.collection.GenSeq that$6;

  public final Sequential apply(Sequential);
    Code:
       0: aload_1
       1: aload_0
       2: getfield      #23                 // Field that$6:Lscala/collection/GenSeq;
       5: invokeinterface #28,  2           // InterfaceMethod scala/collection/Seq.diff:(Lscala/collection/GenSeq;)Ljava/lang/Object;
      10: checkcast     #25                 // class scala/collection/Seq
      13: areturn

  public final java.lang.Object apply(java.lang.Object);
    Code:
       0: aload_0
       1: aload_1
       2: checkcast     #25                 // class scala/collection/Seq
       5: invokevirtual #35                 // Method apply:(Lscala/collection/Seq;)Lscala/collection/Seq;
       8: areturn

  public scala.collection.parallel.ParSeqLike$$anonfun$diff$1(scala.collection.parallel.ParSeqLike<T, Repr, Sequential>);
    Code:
       0: aload_0
       1: aload_2
       2: putfield      #23                 // Field that$6:Lscala/collection/GenSeq;
       5: aload_0
       6: invokespecial #42                 // Method scala/runtime/AbstractFunction1."<init>":()V
       9: return
}
