Compiled from "ParSeqLike.scala"
public final class scala.collection.parallel.ParSeqLike$$anonfun$endsWith$1 extends scala.runtime.AbstractFunction0$mcZ$sp implements scala.Serializable {
  public static final long serialVersionUID;

  public final scala.collection.parallel.ParSeqLike $outer;

  public final scala.collection.GenSeq that$4;

  public final boolean apply();
    Code:
       0: aload_0
       1: getfield      #24                 // Field $outer:Lscala/collection/parallel/ParSeqLike;
       4: invokeinterface #28,  1           // InterfaceMethod scala/collection/parallel/ParSeqLike.seq:()Lscala/collection/Iterable;
       9: checkcast     #30                 // class scala/collection/SeqLike
      12: aload_0
      13: getfield      #32                 // Field that$4:Lscala/collection/GenSeq;
      16: invokeinterface #33,  2           // InterfaceMethod scala/collection/SeqLike.endsWith:(Lscala/collection/GenSeq;)Z
      21: ireturn

  public boolean apply$mcZ$sp();
    Code:
       0: aload_0
       1: getfield      #24                 // Field $outer:Lscala/collection/parallel/ParSeqLike;
       4: invokeinterface #28,  1           // InterfaceMethod scala/collection/parallel/ParSeqLike.seq:()Lscala/collection/Iterable;
       9: checkcast     #30                 // class scala/collection/SeqLike
      12: aload_0
      13: getfield      #32                 // Field that$4:Lscala/collection/GenSeq;
      16: invokeinterface #33,  2           // InterfaceMethod scala/collection/SeqLike.endsWith:(Lscala/collection/GenSeq;)Z
      21: ireturn

  public final java.lang.Object apply();
    Code:
       0: aload_0
       1: invokevirtual #39                 // Method apply:()Z
       4: invokestatic  #45                 // Method scala/runtime/BoxesRunTime.boxToBoolean:(Z)Ljava/lang/Boolean;
       7: areturn

  public scala.collection.parallel.ParSeqLike$$anonfun$endsWith$1(scala.collection.parallel.ParSeqLike<T, Repr, Sequential>);
    Code:
       0: aload_1
       1: ifnonnull     6
       4: aconst_null
       5: athrow
       6: aload_0
       7: aload_1
       8: putfield      #24                 // Field $outer:Lscala/collection/parallel/ParSeqLike;
      11: aload_0
      12: aload_2
      13: putfield      #32                 // Field that$4:Lscala/collection/GenSeq;
      16: aload_0
      17: invokespecial #50                 // Method scala/runtime/AbstractFunction0$mcZ$sp."<init>":()V
      20: return
}
