Compiled from "ParSetLike.scala"
public abstract class scala.collection.parallel.ParSetLike$class {
  public static scala.collection.parallel.ParSet union(scala.collection.parallel.ParSetLike, scala.collection.GenSet);
    Code:
       0: aload_0
       1: new           #9                  // class scala/collection/parallel/ParSetLike$$anonfun$union$1
       4: dup
       5: aload_0
       6: aload_1
       7: invokespecial #13                 // Method scala/collection/parallel/ParSetLike$$anonfun$union$1."<init>":(Lscala/collection/parallel/ParSetLike;Lscala/collection/GenSet;)V
      10: invokeinterface #19,  2           // InterfaceMethod scala/collection/parallel/ParSetLike.sequentially:(Lscala/Function1;)Lscala/collection/parallel/ParIterable;
      15: checkcast     #21                 // class scala/collection/parallel/ParSet
      18: areturn

  public static scala.collection.parallel.ParSet diff(scala.collection.parallel.ParSetLike, scala.collection.GenSet);
    Code:
       0: aload_0
       1: new           #28                 // class scala/collection/parallel/ParSetLike$$anonfun$diff$1
       4: dup
       5: aload_0
       6: aload_1
       7: invokespecial #29                 // Method scala/collection/parallel/ParSetLike$$anonfun$diff$1."<init>":(Lscala/collection/parallel/ParSetLike;Lscala/collection/GenSet;)V
      10: invokeinterface #19,  2           // InterfaceMethod scala/collection/parallel/ParSetLike.sequentially:(Lscala/Function1;)Lscala/collection/parallel/ParIterable;
      15: checkcast     #21                 // class scala/collection/parallel/ParSet
      18: areturn

  public static void $init$(scala.collection.parallel.ParSetLike);
    Code:
       0: return
}
