Compiled from "Helper.java"
public class io.fabric8.kubernetes.model.util.Helper {
  public io.fabric8.kubernetes.model.util.Helper();
    Code:
       0: aload_0
       1: invokespecial #1                  // Method java/lang/Object."<init>":()V
       4: return

  public static java.lang.String loadJson(java.lang.String);
    Code:
       0: ldc           #2                  // class io/fabric8/kubernetes/model/util/Helper
       2: aload_0
       3: invokevirtual #3                  // Method java/lang/Class.getResourceAsStream:(Ljava/lang/String;)Ljava/io/InputStream;
       6: astore_1
       7: aconst_null
       8: astore_2
       9: new           #4                  // class java/util/Scanner
      12: dup
      13: aload_1
      14: invokespecial #5                  // Method java/util/Scanner."<init>":(Ljava/io/InputStream;)V
      17: ldc           #6                  // String \\A
      19: invokevirtual #7                  // Method java/util/Scanner.useDelimiter:(Ljava/lang/String;)Ljava/util/Scanner;
      22: astore_3
      23: aload_3
      24: invokevirtual #8                  // Method java/util/Scanner.hasNext:()Z
      27: ifeq          37
      30: aload_3
      31: invokevirtual #9                  // Method java/util/Scanner.next:()Ljava/lang/String;
      34: goto          39
      37: ldc           #10                 // String
      39: astore        4
      41: aload_1
      42: ifnull        71
      45: aload_2
      46: ifnull        67
      49: aload_1
      50: invokevirtual #11                 // Method java/io/InputStream.close:()V
      53: goto          71
      56: astore        5
      58: aload_2
      59: aload         5
      61: invokevirtual #13                 // Method java/lang/Throwable.addSuppressed:(Ljava/lang/Throwable;)V
      64: goto          71
      67: aload_1
      68: invokevirtual #11                 // Method java/io/InputStream.close:()V
      71: aload         4
      73: areturn
      74: astore_3
      75: aload_3
      76: astore_2
      77: aload_3
      78: athrow
      79: astore        6
      81: aload_1
      82: ifnull        111
      85: aload_2
      86: ifnull        107
      89: aload_1
      90: invokevirtual #11                 // Method java/io/InputStream.close:()V
      93: goto          111
      96: astore        7
      98: aload_2
      99: aload         7
     101: invokevirtual #13                 // Method java/lang/Throwable.addSuppressed:(Ljava/lang/Throwable;)V
     104: goto          111
     107: aload_1
     108: invokevirtual #11                 // Method java/io/InputStream.close:()V
     111: aload         6
     113: athrow
     114: astore_1
     115: new           #15                 // class java/lang/RuntimeException
     118: dup
     119: aload_1
     120: invokespecial #16                 // Method java/lang/RuntimeException."<init>":(Ljava/lang/Throwable;)V
     123: athrow
    Exception table:
       from    to  target type
          49    53    56   Class java/lang/Throwable
           9    41    74   Class java/lang/Throwable
           9    41    79   any
          89    93    96   Class java/lang/Throwable
          74    81    79   any
           0    71   114   Class java/io/IOException
          74   114   114   Class java/io/IOException

  public static java.lang.String getAnnotationValue(java.lang.Class, java.lang.Class);
    Code:
       0: aload_0
       1: aload_1
       2: invokestatic  #17                 // Method getAnnotation:(Ljava/lang/Class;Ljava/lang/Class;)Ljava/lang/annotation/Annotation;
       5: astore_2
       6: aload_2
       7: instanceof    #18                 // class io/fabric8/kubernetes/model/annotation/ApiGroup
      10: ifeq          23
      13: aload_2
      14: checkcast     #18                 // class io/fabric8/kubernetes/model/annotation/ApiGroup
      17: invokeinterface #19,  1           // InterfaceMethod io/fabric8/kubernetes/model/annotation/ApiGroup.value:()Ljava/lang/String;
      22: areturn
      23: aload_2
      24: instanceof    #20                 // class io/fabric8/kubernetes/model/annotation/ApiVersion
      27: ifeq          40
      30: aload_2
      31: checkcast     #20                 // class io/fabric8/kubernetes/model/annotation/ApiVersion
      34: invokeinterface #21,  1           // InterfaceMethod io/fabric8/kubernetes/model/annotation/ApiVersion.value:()Ljava/lang/String;
      39: areturn
      40: aconst_null
      41: areturn

  private static java.lang.annotation.Annotation getAnnotation(java.lang.Class, java.lang.Class);
    Code:
       0: aload_0
       1: invokevirtual #22                 // Method java/lang/Class.getAnnotations:()[Ljava/lang/annotation/Annotation;
       4: invokestatic  #23                 // Method java/util/Arrays.stream:([Ljava/lang/Object;)Ljava/util/stream/Stream;
       7: aload_1
       8: invokedynamic #24,  0             // InvokeDynamic #0:test:(Ljava/lang/Class;)Ljava/util/function/Predicate;
      13: invokeinterface #25,  2           // InterfaceMethod java/util/stream/Stream.filter:(Ljava/util/function/Predicate;)Ljava/util/stream/Stream;
      18: invokeinterface #26,  1           // InterfaceMethod java/util/stream/Stream.findFirst:()Ljava/util/Optional;
      23: aconst_null
      24: invokevirtual #27                 // Method java/util/Optional.orElse:(Ljava/lang/Object;)Ljava/lang/Object;
      27: checkcast     #28                 // class java/lang/annotation/Annotation
      30: areturn

  private static boolean lambda$getAnnotation$0(java.lang.Class, java.lang.annotation.Annotation);
    Code:
       0: aload_1
       1: invokeinterface #29,  1           // InterfaceMethod java/lang/annotation/Annotation.annotationType:()Ljava/lang/Class;
       6: aload_0
       7: invokevirtual #30                 // Method java/lang/Object.equals:(Ljava/lang/Object;)Z
      10: ireturn
}
