Compiled from "EncoderFactory.java"
class org.apache.avro.io.EncoderFactory$DefaultEncoderFactory extends org.apache.avro.io.EncoderFactory {
  private org.apache.avro.io.EncoderFactory$DefaultEncoderFactory();
    Code:
       0: aload_0
       1: invokespecial #2                  // Method org/apache/avro/io/EncoderFactory."<init>":()V
       4: return

  public org.apache.avro.io.EncoderFactory configureBlockSize(int);
    Code:
       0: new           #3                  // class org/apache/avro/AvroRuntimeException
       3: dup
       4: ldc           #4                  // String Default EncoderFactory cannot be configured
       6: invokespecial #5                  // Method org/apache/avro/AvroRuntimeException."<init>":(Ljava/lang/String;)V
       9: athrow

  public org.apache.avro.io.EncoderFactory configureBufferSize(int);
    Code:
       0: new           #3                  // class org/apache/avro/AvroRuntimeException
       3: dup
       4: ldc           #4                  // String Default EncoderFactory cannot be configured
       6: invokespecial #5                  // Method org/apache/avro/AvroRuntimeException."<init>":(Ljava/lang/String;)V
       9: athrow

  org.apache.avro.io.EncoderFactory$DefaultEncoderFactory(org.apache.avro.io.EncoderFactory$1);
    Code:
       0: aload_0
       1: invokespecial #1                  // Method "<init>":()V
       4: return
}
