Compiled from "JsonDecoder.java"
public class org.apache.avro.io.JsonDecoder extends org.apache.avro.io.ParsingDecoder implements org.apache.avro.io.parsing.Parser$ActionHandler {
  private com.fasterxml.jackson.core.JsonParser in;

  private static com.fasterxml.jackson.core.JsonFactory jsonFactory;

  java.util.Stack<org.apache.avro.io.JsonDecoder$ReorderBuffer> reorderBuffers;

  org.apache.avro.io.JsonDecoder$ReorderBuffer currentReorderBuffer;

  private org.apache.avro.io.JsonDecoder(org.apache.avro.io.parsing.Symbol, java.io.InputStream) throws java.io.IOException;
    Code:
       0: aload_0
       1: aload_1
       2: invokespecial #1                  // Method org/apache/avro/io/ParsingDecoder."<init>":(Lorg/apache/avro/io/parsing/Symbol;)V
       5: aload_0
       6: new           #2                  // class java/util/Stack
       9: dup
      10: invokespecial #3                  // Method java/util/Stack."<init>":()V
      13: putfield      #4                  // Field reorderBuffers:Ljava/util/Stack;
      16: aload_0
      17: aload_2
      18: invokevirtual #5                  // Method configure:(Ljava/io/InputStream;)Lorg/apache/avro/io/JsonDecoder;
      21: pop
      22: return

  private org.apache.avro.io.JsonDecoder(org.apache.avro.io.parsing.Symbol, java.lang.String) throws java.io.IOException;
    Code:
       0: aload_0
       1: aload_1
       2: invokespecial #1                  // Method org/apache/avro/io/ParsingDecoder."<init>":(Lorg/apache/avro/io/parsing/Symbol;)V
       5: aload_0
       6: new           #2                  // class java/util/Stack
       9: dup
      10: invokespecial #3                  // Method java/util/Stack."<init>":()V
      13: putfield      #4                  // Field reorderBuffers:Ljava/util/Stack;
      16: aload_0
      17: aload_2
      18: invokevirtual #6                  // Method configure:(Ljava/lang/String;)Lorg/apache/avro/io/JsonDecoder;
      21: pop
      22: return

  org.apache.avro.io.JsonDecoder(org.apache.avro.Schema, java.io.InputStream) throws java.io.IOException;
    Code:
       0: aload_0
       1: aload_1
       2: invokestatic  #7                  // Method getSymbol:(Lorg/apache/avro/Schema;)Lorg/apache/avro/io/parsing/Symbol;
       5: aload_2
       6: invokespecial #8                  // Method "<init>":(Lorg/apache/avro/io/parsing/Symbol;Ljava/io/InputStream;)V
       9: return

  org.apache.avro.io.JsonDecoder(org.apache.avro.Schema, java.lang.String) throws java.io.IOException;
    Code:
       0: aload_0
       1: aload_1
       2: invokestatic  #7                  // Method getSymbol:(Lorg/apache/avro/Schema;)Lorg/apache/avro/io/parsing/Symbol;
       5: aload_2
       6: invokespecial #9                  // Method "<init>":(Lorg/apache/avro/io/parsing/Symbol;Ljava/lang/String;)V
       9: return

  private static org.apache.avro.io.parsing.Symbol getSymbol(org.apache.avro.Schema);
    Code:
       0: aload_0
       1: ldc           #10                 // String Schema cannot be null
       3: invokestatic  #11                 // Method java/util/Objects.requireNonNull:(Ljava/lang/Object;Ljava/lang/String;)Ljava/lang/Object;
       6: pop
       7: new           #12                 // class org/apache/avro/io/parsing/JsonGrammarGenerator
      10: dup
      11: invokespecial #13                 // Method org/apache/avro/io/parsing/JsonGrammarGenerator."<init>":()V
      14: aload_0
      15: invokevirtual #14                 // Method org/apache/avro/io/parsing/JsonGrammarGenerator.generate:(Lorg/apache/avro/Schema;)Lorg/apache/avro/io/parsing/Symbol;
      18: areturn

  public org.apache.avro.io.JsonDecoder configure(java.io.InputStream) throws java.io.IOException;
    Code:
       0: aload_1
       1: ldc           #15                 // String InputStream cannot be null
       3: invokestatic  #11                 // Method java/util/Objects.requireNonNull:(Ljava/lang/Object;Ljava/lang/String;)Ljava/lang/Object;
       6: pop
       7: aload_0
       8: getfield      #16                 // Field parser:Lorg/apache/avro/io/parsing/SkipParser;
      11: invokevirtual #17                 // Method org/apache/avro/io/parsing/SkipParser.reset:()V
      14: aload_0
      15: getfield      #4                  // Field reorderBuffers:Ljava/util/Stack;
      18: invokevirtual #18                 // Method java/util/Stack.clear:()V
      21: aload_0
      22: aconst_null
      23: putfield      #19                 // Field currentReorderBuffer:Lorg/apache/avro/io/JsonDecoder$ReorderBuffer;
      26: aload_0
      27: getstatic     #20                 // Field jsonFactory:Lcom/fasterxml/jackson/core/JsonFactory;
      30: aload_1
      31: invokevirtual #21                 // Method com/fasterxml/jackson/core/JsonFactory.createParser:(Ljava/io/InputStream;)Lcom/fasterxml/jackson/core/JsonParser;
      34: putfield      #22                 // Field in:Lcom/fasterxml/jackson/core/JsonParser;
      37: aload_0
      38: getfield      #22                 // Field in:Lcom/fasterxml/jackson/core/JsonParser;
      41: invokevirtual #23                 // Method com/fasterxml/jackson/core/JsonParser.nextToken:()Lcom/fasterxml/jackson/core/JsonToken;
      44: pop
      45: aload_0
      46: areturn

  public org.apache.avro.io.JsonDecoder configure(java.lang.String) throws java.io.IOException;
    Code:
       0: aload_1
       1: ldc           #24                 // String String to read from cannot be null
       3: invokestatic  #11                 // Method java/util/Objects.requireNonNull:(Ljava/lang/Object;Ljava/lang/String;)Ljava/lang/Object;
       6: pop
       7: aload_0
       8: getfield      #16                 // Field parser:Lorg/apache/avro/io/parsing/SkipParser;
      11: invokevirtual #17                 // Method org/apache/avro/io/parsing/SkipParser.reset:()V
      14: aload_0
      15: getfield      #4                  // Field reorderBuffers:Ljava/util/Stack;
      18: invokevirtual #18                 // Method java/util/Stack.clear:()V
      21: aload_0
      22: aconst_null
      23: putfield      #19                 // Field currentReorderBuffer:Lorg/apache/avro/io/JsonDecoder$ReorderBuffer;
      26: aload_0
      27: new           #25                 // class com/fasterxml/jackson/core/JsonFactory
      30: dup
      31: invokespecial #26                 // Method com/fasterxml/jackson/core/JsonFactory."<init>":()V
      34: aload_1
      35: invokevirtual #27                 // Method com/fasterxml/jackson/core/JsonFactory.createParser:(Ljava/lang/String;)Lcom/fasterxml/jackson/core/JsonParser;
      38: putfield      #22                 // Field in:Lcom/fasterxml/jackson/core/JsonParser;
      41: aload_0
      42: getfield      #22                 // Field in:Lcom/fasterxml/jackson/core/JsonParser;
      45: invokevirtual #23                 // Method com/fasterxml/jackson/core/JsonParser.nextToken:()Lcom/fasterxml/jackson/core/JsonToken;
      48: pop
      49: aload_0
      50: areturn

  private void advance(org.apache.avro.io.parsing.Symbol) throws java.io.IOException;
    Code:
       0: aload_0
       1: getfield      #16                 // Field parser:Lorg/apache/avro/io/parsing/SkipParser;
       4: invokevirtual #28                 // Method org/apache/avro/io/parsing/SkipParser.processTrailingImplicitActions:()V
       7: aload_0
       8: getfield      #22                 // Field in:Lcom/fasterxml/jackson/core/JsonParser;
      11: invokevirtual #29                 // Method com/fasterxml/jackson/core/JsonParser.getCurrentToken:()Lcom/fasterxml/jackson/core/JsonToken;
      14: ifnonnull     36
      17: aload_0
      18: getfield      #16                 // Field parser:Lorg/apache/avro/io/parsing/SkipParser;
      21: invokevirtual #30                 // Method org/apache/avro/io/parsing/SkipParser.depth:()I
      24: iconst_1
      25: if_icmpne     36
      28: new           #31                 // class java/io/EOFException
      31: dup
      32: invokespecial #32                 // Method java/io/EOFException."<init>":()V
      35: athrow
      36: aload_0
      37: getfield      #16                 // Field parser:Lorg/apache/avro/io/parsing/SkipParser;
      40: aload_1
      41: invokevirtual #33                 // Method org/apache/avro/io/parsing/SkipParser.advance:(Lorg/apache/avro/io/parsing/Symbol;)Lorg/apache/avro/io/parsing/Symbol;
      44: pop
      45: return

  public void readNull() throws java.io.IOException;
    Code:
       0: aload_0
       1: getstatic     #34                 // Field org/apache/avro/io/parsing/Symbol.NULL:Lorg/apache/avro/io/parsing/Symbol;
       4: invokespecial #35                 // Method advance:(Lorg/apache/avro/io/parsing/Symbol;)V
       7: aload_0
       8: getfield      #22                 // Field in:Lcom/fasterxml/jackson/core/JsonParser;
      11: invokevirtual #29                 // Method com/fasterxml/jackson/core/JsonParser.getCurrentToken:()Lcom/fasterxml/jackson/core/JsonToken;
      14: getstatic     #36                 // Field com/fasterxml/jackson/core/JsonToken.VALUE_NULL:Lcom/fasterxml/jackson/core/JsonToken;
      17: if_acmpne     31
      20: aload_0
      21: getfield      #22                 // Field in:Lcom/fasterxml/jackson/core/JsonParser;
      24: invokevirtual #23                 // Method com/fasterxml/jackson/core/JsonParser.nextToken:()Lcom/fasterxml/jackson/core/JsonToken;
      27: pop
      28: goto          38
      31: aload_0
      32: ldc           #37                 // String null
      34: invokespecial #38                 // Method error:(Ljava/lang/String;)Lorg/apache/avro/AvroTypeException;
      37: athrow
      38: return

  public boolean readBoolean() throws java.io.IOException;
    Code:
       0: aload_0
       1: getstatic     #39                 // Field org/apache/avro/io/parsing/Symbol.BOOLEAN:Lorg/apache/avro/io/parsing/Symbol;
       4: invokespecial #35                 // Method advance:(Lorg/apache/avro/io/parsing/Symbol;)V
       7: aload_0
       8: getfield      #22                 // Field in:Lcom/fasterxml/jackson/core/JsonParser;
      11: invokevirtual #29                 // Method com/fasterxml/jackson/core/JsonParser.getCurrentToken:()Lcom/fasterxml/jackson/core/JsonToken;
      14: astore_1
      15: aload_1
      16: getstatic     #40                 // Field com/fasterxml/jackson/core/JsonToken.VALUE_TRUE:Lcom/fasterxml/jackson/core/JsonToken;
      19: if_acmpeq     29
      22: aload_1
      23: getstatic     #41                 // Field com/fasterxml/jackson/core/JsonToken.VALUE_FALSE:Lcom/fasterxml/jackson/core/JsonToken;
      26: if_acmpne     50
      29: aload_0
      30: getfield      #22                 // Field in:Lcom/fasterxml/jackson/core/JsonParser;
      33: invokevirtual #23                 // Method com/fasterxml/jackson/core/JsonParser.nextToken:()Lcom/fasterxml/jackson/core/JsonToken;
      36: pop
      37: aload_1
      38: getstatic     #40                 // Field com/fasterxml/jackson/core/JsonToken.VALUE_TRUE:Lcom/fasterxml/jackson/core/JsonToken;
      41: if_acmpne     48
      44: iconst_1
      45: goto          49
      48: iconst_0
      49: ireturn
      50: aload_0
      51: ldc           #42                 // String boolean
      53: invokespecial #38                 // Method error:(Ljava/lang/String;)Lorg/apache/avro/AvroTypeException;
      56: athrow

  public int readInt() throws java.io.IOException;
    Code:
       0: aload_0
       1: getstatic     #43                 // Field org/apache/avro/io/parsing/Symbol.INT:Lorg/apache/avro/io/parsing/Symbol;
       4: invokespecial #35                 // Method advance:(Lorg/apache/avro/io/parsing/Symbol;)V
       7: aload_0
       8: getfield      #22                 // Field in:Lcom/fasterxml/jackson/core/JsonParser;
      11: invokevirtual #29                 // Method com/fasterxml/jackson/core/JsonParser.getCurrentToken:()Lcom/fasterxml/jackson/core/JsonToken;
      14: invokevirtual #44                 // Method com/fasterxml/jackson/core/JsonToken.isNumeric:()Z
      17: ifeq          38
      20: aload_0
      21: getfield      #22                 // Field in:Lcom/fasterxml/jackson/core/JsonParser;
      24: invokevirtual #45                 // Method com/fasterxml/jackson/core/JsonParser.getIntValue:()I
      27: istore_1
      28: aload_0
      29: getfield      #22                 // Field in:Lcom/fasterxml/jackson/core/JsonParser;
      32: invokevirtual #23                 // Method com/fasterxml/jackson/core/JsonParser.nextToken:()Lcom/fasterxml/jackson/core/JsonToken;
      35: pop
      36: iload_1
      37: ireturn
      38: aload_0
      39: ldc           #46                 // String int
      41: invokespecial #38                 // Method error:(Ljava/lang/String;)Lorg/apache/avro/AvroTypeException;
      44: athrow

  public long readLong() throws java.io.IOException;
    Code:
       0: aload_0
       1: getstatic     #47                 // Field org/apache/avro/io/parsing/Symbol.LONG:Lorg/apache/avro/io/parsing/Symbol;
       4: invokespecial #35                 // Method advance:(Lorg/apache/avro/io/parsing/Symbol;)V
       7: aload_0
       8: getfield      #22                 // Field in:Lcom/fasterxml/jackson/core/JsonParser;
      11: invokevirtual #29                 // Method com/fasterxml/jackson/core/JsonParser.getCurrentToken:()Lcom/fasterxml/jackson/core/JsonToken;
      14: invokevirtual #44                 // Method com/fasterxml/jackson/core/JsonToken.isNumeric:()Z
      17: ifeq          38
      20: aload_0
      21: getfield      #22                 // Field in:Lcom/fasterxml/jackson/core/JsonParser;
      24: invokevirtual #48                 // Method com/fasterxml/jackson/core/JsonParser.getLongValue:()J
      27: lstore_1
      28: aload_0
      29: getfield      #22                 // Field in:Lcom/fasterxml/jackson/core/JsonParser;
      32: invokevirtual #23                 // Method com/fasterxml/jackson/core/JsonParser.nextToken:()Lcom/fasterxml/jackson/core/JsonToken;
      35: pop
      36: lload_1
      37: lreturn
      38: aload_0
      39: ldc           #49                 // String long
      41: invokespecial #38                 // Method error:(Ljava/lang/String;)Lorg/apache/avro/AvroTypeException;
      44: athrow

  public float readFloat() throws java.io.IOException;
    Code:
       0: aload_0
       1: getstatic     #50                 // Field org/apache/avro/io/parsing/Symbol.FLOAT:Lorg/apache/avro/io/parsing/Symbol;
       4: invokespecial #35                 // Method advance:(Lorg/apache/avro/io/parsing/Symbol;)V
       7: aload_0
       8: getfield      #22                 // Field in:Lcom/fasterxml/jackson/core/JsonParser;
      11: invokevirtual #29                 // Method com/fasterxml/jackson/core/JsonParser.getCurrentToken:()Lcom/fasterxml/jackson/core/JsonToken;
      14: invokevirtual #44                 // Method com/fasterxml/jackson/core/JsonToken.isNumeric:()Z
      17: ifeq          38
      20: aload_0
      21: getfield      #22                 // Field in:Lcom/fasterxml/jackson/core/JsonParser;
      24: invokevirtual #51                 // Method com/fasterxml/jackson/core/JsonParser.getFloatValue:()F
      27: fstore_1
      28: aload_0
      29: getfield      #22                 // Field in:Lcom/fasterxml/jackson/core/JsonParser;
      32: invokevirtual #23                 // Method com/fasterxml/jackson/core/JsonParser.nextToken:()Lcom/fasterxml/jackson/core/JsonToken;
      35: pop
      36: fload_1
      37: freturn
      38: aload_0
      39: ldc           #52                 // String float
      41: invokespecial #38                 // Method error:(Ljava/lang/String;)Lorg/apache/avro/AvroTypeException;
      44: athrow

  public double readDouble() throws java.io.IOException;
    Code:
       0: aload_0
       1: getstatic     #53                 // Field org/apache/avro/io/parsing/Symbol.DOUBLE:Lorg/apache/avro/io/parsing/Symbol;
       4: invokespecial #35                 // Method advance:(Lorg/apache/avro/io/parsing/Symbol;)V
       7: aload_0
       8: getfield      #22                 // Field in:Lcom/fasterxml/jackson/core/JsonParser;
      11: invokevirtual #29                 // Method com/fasterxml/jackson/core/JsonParser.getCurrentToken:()Lcom/fasterxml/jackson/core/JsonToken;
      14: invokevirtual #44                 // Method com/fasterxml/jackson/core/JsonToken.isNumeric:()Z
      17: ifeq          38
      20: aload_0
      21: getfield      #22                 // Field in:Lcom/fasterxml/jackson/core/JsonParser;
      24: invokevirtual #54                 // Method com/fasterxml/jackson/core/JsonParser.getDoubleValue:()D
      27: dstore_1
      28: aload_0
      29: getfield      #22                 // Field in:Lcom/fasterxml/jackson/core/JsonParser;
      32: invokevirtual #23                 // Method com/fasterxml/jackson/core/JsonParser.nextToken:()Lcom/fasterxml/jackson/core/JsonToken;
      35: pop
      36: dload_1
      37: dreturn
      38: aload_0
      39: ldc           #55                 // String double
      41: invokespecial #38                 // Method error:(Ljava/lang/String;)Lorg/apache/avro/AvroTypeException;
      44: athrow

  public org.apache.avro.util.Utf8 readString(org.apache.avro.util.Utf8) throws java.io.IOException;
    Code:
       0: new           #56                 // class org/apache/avro/util/Utf8
       3: dup
       4: aload_0
       5: invokevirtual #57                 // Method readString:()Ljava/lang/String;
       8: invokespecial #58                 // Method org/apache/avro/util/Utf8."<init>":(Ljava/lang/String;)V
      11: areturn

  public java.lang.String readString() throws java.io.IOException;
    Code:
       0: aload_0
       1: getstatic     #59                 // Field org/apache/avro/io/parsing/Symbol.STRING:Lorg/apache/avro/io/parsing/Symbol;
       4: invokespecial #35                 // Method advance:(Lorg/apache/avro/io/parsing/Symbol;)V
       7: aload_0
       8: getfield      #16                 // Field parser:Lorg/apache/avro/io/parsing/SkipParser;
      11: invokevirtual #60                 // Method org/apache/avro/io/parsing/SkipParser.topSymbol:()Lorg/apache/avro/io/parsing/Symbol;
      14: getstatic     #61                 // Field org/apache/avro/io/parsing/Symbol.MAP_KEY_MARKER:Lorg/apache/avro/io/parsing/Symbol;
      17: if_acmpne     51
      20: aload_0
      21: getfield      #16                 // Field parser:Lorg/apache/avro/io/parsing/SkipParser;
      24: getstatic     #61                 // Field org/apache/avro/io/parsing/Symbol.MAP_KEY_MARKER:Lorg/apache/avro/io/parsing/Symbol;
      27: invokevirtual #33                 // Method org/apache/avro/io/parsing/SkipParser.advance:(Lorg/apache/avro/io/parsing/Symbol;)Lorg/apache/avro/io/parsing/Symbol;
      30: pop
      31: aload_0
      32: getfield      #22                 // Field in:Lcom/fasterxml/jackson/core/JsonParser;
      35: invokevirtual #29                 // Method com/fasterxml/jackson/core/JsonParser.getCurrentToken:()Lcom/fasterxml/jackson/core/JsonToken;
      38: getstatic     #62                 // Field com/fasterxml/jackson/core/JsonToken.FIELD_NAME:Lcom/fasterxml/jackson/core/JsonToken;
      41: if_acmpeq     71
      44: aload_0
      45: ldc           #63                 // String map-key
      47: invokespecial #38                 // Method error:(Ljava/lang/String;)Lorg/apache/avro/AvroTypeException;
      50: athrow
      51: aload_0
      52: getfield      #22                 // Field in:Lcom/fasterxml/jackson/core/JsonParser;
      55: invokevirtual #29                 // Method com/fasterxml/jackson/core/JsonParser.getCurrentToken:()Lcom/fasterxml/jackson/core/JsonToken;
      58: getstatic     #64                 // Field com/fasterxml/jackson/core/JsonToken.VALUE_STRING:Lcom/fasterxml/jackson/core/JsonToken;
      61: if_acmpeq     71
      64: aload_0
      65: ldc           #65                 // String string
      67: invokespecial #38                 // Method error:(Ljava/lang/String;)Lorg/apache/avro/AvroTypeException;
      70: athrow
      71: aload_0
      72: getfield      #22                 // Field in:Lcom/fasterxml/jackson/core/JsonParser;
      75: invokevirtual #66                 // Method com/fasterxml/jackson/core/JsonParser.getText:()Ljava/lang/String;
      78: astore_1
      79: aload_0
      80: getfield      #22                 // Field in:Lcom/fasterxml/jackson/core/JsonParser;
      83: invokevirtual #23                 // Method com/fasterxml/jackson/core/JsonParser.nextToken:()Lcom/fasterxml/jackson/core/JsonToken;
      86: pop
      87: aload_1
      88: areturn

  public void skipString() throws java.io.IOException;
    Code:
       0: aload_0
       1: getstatic     #59                 // Field org/apache/avro/io/parsing/Symbol.STRING:Lorg/apache/avro/io/parsing/Symbol;
       4: invokespecial #35                 // Method advance:(Lorg/apache/avro/io/parsing/Symbol;)V
       7: aload_0
       8: getfield      #16                 // Field parser:Lorg/apache/avro/io/parsing/SkipParser;
      11: invokevirtual #60                 // Method org/apache/avro/io/parsing/SkipParser.topSymbol:()Lorg/apache/avro/io/parsing/Symbol;
      14: getstatic     #61                 // Field org/apache/avro/io/parsing/Symbol.MAP_KEY_MARKER:Lorg/apache/avro/io/parsing/Symbol;
      17: if_acmpne     51
      20: aload_0
      21: getfield      #16                 // Field parser:Lorg/apache/avro/io/parsing/SkipParser;
      24: getstatic     #61                 // Field org/apache/avro/io/parsing/Symbol.MAP_KEY_MARKER:Lorg/apache/avro/io/parsing/Symbol;
      27: invokevirtual #33                 // Method org/apache/avro/io/parsing/SkipParser.advance:(Lorg/apache/avro/io/parsing/Symbol;)Lorg/apache/avro/io/parsing/Symbol;
      30: pop
      31: aload_0
      32: getfield      #22                 // Field in:Lcom/fasterxml/jackson/core/JsonParser;
      35: invokevirtual #29                 // Method com/fasterxml/jackson/core/JsonParser.getCurrentToken:()Lcom/fasterxml/jackson/core/JsonToken;
      38: getstatic     #62                 // Field com/fasterxml/jackson/core/JsonToken.FIELD_NAME:Lcom/fasterxml/jackson/core/JsonToken;
      41: if_acmpeq     71
      44: aload_0
      45: ldc           #63                 // String map-key
      47: invokespecial #38                 // Method error:(Ljava/lang/String;)Lorg/apache/avro/AvroTypeException;
      50: athrow
      51: aload_0
      52: getfield      #22                 // Field in:Lcom/fasterxml/jackson/core/JsonParser;
      55: invokevirtual #29                 // Method com/fasterxml/jackson/core/JsonParser.getCurrentToken:()Lcom/fasterxml/jackson/core/JsonToken;
      58: getstatic     #64                 // Field com/fasterxml/jackson/core/JsonToken.VALUE_STRING:Lcom/fasterxml/jackson/core/JsonToken;
      61: if_acmpeq     71
      64: aload_0
      65: ldc           #65                 // String string
      67: invokespecial #38                 // Method error:(Ljava/lang/String;)Lorg/apache/avro/AvroTypeException;
      70: athrow
      71: aload_0
      72: getfield      #22                 // Field in:Lcom/fasterxml/jackson/core/JsonParser;
      75: invokevirtual #23                 // Method com/fasterxml/jackson/core/JsonParser.nextToken:()Lcom/fasterxml/jackson/core/JsonToken;
      78: pop
      79: return

  public java.nio.ByteBuffer readBytes(java.nio.ByteBuffer) throws java.io.IOException;
    Code:
       0: aload_0
       1: getstatic     #67                 // Field org/apache/avro/io/parsing/Symbol.BYTES:Lorg/apache/avro/io/parsing/Symbol;
       4: invokespecial #35                 // Method advance:(Lorg/apache/avro/io/parsing/Symbol;)V
       7: aload_0
       8: getfield      #22                 // Field in:Lcom/fasterxml/jackson/core/JsonParser;
      11: invokevirtual #29                 // Method com/fasterxml/jackson/core/JsonParser.getCurrentToken:()Lcom/fasterxml/jackson/core/JsonToken;
      14: getstatic     #64                 // Field com/fasterxml/jackson/core/JsonToken.VALUE_STRING:Lcom/fasterxml/jackson/core/JsonToken;
      17: if_acmpne     38
      20: aload_0
      21: invokespecial #68                 // Method readByteArray:()[B
      24: astore_2
      25: aload_0
      26: getfield      #22                 // Field in:Lcom/fasterxml/jackson/core/JsonParser;
      29: invokevirtual #23                 // Method com/fasterxml/jackson/core/JsonParser.nextToken:()Lcom/fasterxml/jackson/core/JsonToken;
      32: pop
      33: aload_2
      34: invokestatic  #69                 // Method java/nio/ByteBuffer.wrap:([B)Ljava/nio/ByteBuffer;
      37: areturn
      38: aload_0
      39: ldc           #70                 // String bytes
      41: invokespecial #38                 // Method error:(Ljava/lang/String;)Lorg/apache/avro/AvroTypeException;
      44: athrow

  private byte[] readByteArray() throws java.io.IOException;
    Code:
       0: aload_0
       1: getfield      #22                 // Field in:Lcom/fasterxml/jackson/core/JsonParser;
       4: invokevirtual #66                 // Method com/fasterxml/jackson/core/JsonParser.getText:()Ljava/lang/String;
       7: getstatic     #71                 // Field java/nio/charset/StandardCharsets.ISO_8859_1:Ljava/nio/charset/Charset;
      10: invokevirtual #72                 // Method java/lang/String.getBytes:(Ljava/nio/charset/Charset;)[B
      13: astore_1
      14: aload_1
      15: areturn

  public void skipBytes() throws java.io.IOException;
    Code:
       0: aload_0
       1: getstatic     #67                 // Field org/apache/avro/io/parsing/Symbol.BYTES:Lorg/apache/avro/io/parsing/Symbol;
       4: invokespecial #35                 // Method advance:(Lorg/apache/avro/io/parsing/Symbol;)V
       7: aload_0
       8: getfield      #22                 // Field in:Lcom/fasterxml/jackson/core/JsonParser;
      11: invokevirtual #29                 // Method com/fasterxml/jackson/core/JsonParser.getCurrentToken:()Lcom/fasterxml/jackson/core/JsonToken;
      14: getstatic     #64                 // Field com/fasterxml/jackson/core/JsonToken.VALUE_STRING:Lcom/fasterxml/jackson/core/JsonToken;
      17: if_acmpne     31
      20: aload_0
      21: getfield      #22                 // Field in:Lcom/fasterxml/jackson/core/JsonParser;
      24: invokevirtual #23                 // Method com/fasterxml/jackson/core/JsonParser.nextToken:()Lcom/fasterxml/jackson/core/JsonToken;
      27: pop
      28: goto          38
      31: aload_0
      32: ldc           #70                 // String bytes
      34: invokespecial #38                 // Method error:(Ljava/lang/String;)Lorg/apache/avro/AvroTypeException;
      37: athrow
      38: return

  private void checkFixed(int) throws java.io.IOException;
    Code:
       0: aload_0
       1: getstatic     #73                 // Field org/apache/avro/io/parsing/Symbol.FIXED:Lorg/apache/avro/io/parsing/Symbol;
       4: invokespecial #35                 // Method advance:(Lorg/apache/avro/io/parsing/Symbol;)V
       7: aload_0
       8: getfield      #16                 // Field parser:Lorg/apache/avro/io/parsing/SkipParser;
      11: invokevirtual #74                 // Method org/apache/avro/io/parsing/SkipParser.popSymbol:()Lorg/apache/avro/io/parsing/Symbol;
      14: checkcast     #75                 // class org/apache/avro/io/parsing/Symbol$IntCheckAction
      17: astore_2
      18: iload_1
      19: aload_2
      20: getfield      #76                 // Field org/apache/avro/io/parsing/Symbol$IntCheckAction.size:I
      23: if_icmpeq     70
      26: new           #77                 // class org/apache/avro/AvroTypeException
      29: dup
      30: new           #78                 // class java/lang/StringBuilder
      33: dup
      34: invokespecial #79                 // Method java/lang/StringBuilder."<init>":()V
      37: ldc           #80                 // String Incorrect length for fixed binary: expected
      39: invokevirtual #81                 // Method java/lang/StringBuilder.append:(Ljava/lang/String;)Ljava/lang/StringBuilder;
      42: aload_2
      43: getfield      #76                 // Field org/apache/avro/io/parsing/Symbol$IntCheckAction.size:I
      46: invokevirtual #82                 // Method java/lang/StringBuilder.append:(I)Ljava/lang/StringBuilder;
      49: ldc           #83                 // String  but received
      51: invokevirtual #81                 // Method java/lang/StringBuilder.append:(Ljava/lang/String;)Ljava/lang/StringBuilder;
      54: iload_1
      55: invokevirtual #82                 // Method java/lang/StringBuilder.append:(I)Ljava/lang/StringBuilder;
      58: ldc           #84                 // String  bytes.
      60: invokevirtual #81                 // Method java/lang/StringBuilder.append:(Ljava/lang/String;)Ljava/lang/StringBuilder;
      63: invokevirtual #85                 // Method java/lang/StringBuilder.toString:()Ljava/lang/String;
      66: invokespecial #86                 // Method org/apache/avro/AvroTypeException."<init>":(Ljava/lang/String;)V
      69: athrow
      70: return

  public void readFixed(byte[], int, int) throws java.io.IOException;
    Code:
       0: aload_0
       1: iload_3
       2: invokespecial #87                 // Method checkFixed:(I)V
       5: aload_0
       6: getfield      #22                 // Field in:Lcom/fasterxml/jackson/core/JsonParser;
       9: invokevirtual #29                 // Method com/fasterxml/jackson/core/JsonParser.getCurrentToken:()Lcom/fasterxml/jackson/core/JsonToken;
      12: getstatic     #64                 // Field com/fasterxml/jackson/core/JsonToken.VALUE_STRING:Lcom/fasterxml/jackson/core/JsonToken;
      15: if_acmpne     89
      18: aload_0
      19: invokespecial #68                 // Method readByteArray:()[B
      22: astore        4
      24: aload_0
      25: getfield      #22                 // Field in:Lcom/fasterxml/jackson/core/JsonParser;
      28: invokevirtual #23                 // Method com/fasterxml/jackson/core/JsonParser.nextToken:()Lcom/fasterxml/jackson/core/JsonToken;
      31: pop
      32: aload         4
      34: arraylength
      35: iload_3
      36: if_icmpeq     77
      39: new           #77                 // class org/apache/avro/AvroTypeException
      42: dup
      43: new           #78                 // class java/lang/StringBuilder
      46: dup
      47: invokespecial #79                 // Method java/lang/StringBuilder."<init>":()V
      50: ldc           #88                 // String Expected fixed length
      52: invokevirtual #81                 // Method java/lang/StringBuilder.append:(Ljava/lang/String;)Ljava/lang/StringBuilder;
      55: iload_3
      56: invokevirtual #82                 // Method java/lang/StringBuilder.append:(I)Ljava/lang/StringBuilder;
      59: ldc           #89                 // String , but got
      61: invokevirtual #81                 // Method java/lang/StringBuilder.append:(Ljava/lang/String;)Ljava/lang/StringBuilder;
      64: aload         4
      66: arraylength
      67: invokevirtual #82                 // Method java/lang/StringBuilder.append:(I)Ljava/lang/StringBuilder;
      70: invokevirtual #85                 // Method java/lang/StringBuilder.toString:()Ljava/lang/String;
      73: invokespecial #86                 // Method org/apache/avro/AvroTypeException."<init>":(Ljava/lang/String;)V
      76: athrow
      77: aload         4
      79: iconst_0
      80: aload_1
      81: iload_2
      82: iload_3
      83: invokestatic  #90                 // Method java/lang/System.arraycopy:(Ljava/lang/Object;ILjava/lang/Object;II)V
      86: goto          96
      89: aload_0
      90: ldc           #91                 // String fixed
      92: invokespecial #38                 // Method error:(Ljava/lang/String;)Lorg/apache/avro/AvroTypeException;
      95: athrow
      96: return

  public void skipFixed(int) throws java.io.IOException;
    Code:
       0: aload_0
       1: iload_1
       2: invokespecial #87                 // Method checkFixed:(I)V
       5: aload_0
       6: iload_1
       7: invokespecial #92                 // Method doSkipFixed:(I)V
      10: return

  private void doSkipFixed(int) throws java.io.IOException;
    Code:
       0: aload_0
       1: getfield      #22                 // Field in:Lcom/fasterxml/jackson/core/JsonParser;
       4: invokevirtual #29                 // Method com/fasterxml/jackson/core/JsonParser.getCurrentToken:()Lcom/fasterxml/jackson/core/JsonToken;
       7: getstatic     #64                 // Field com/fasterxml/jackson/core/JsonToken.VALUE_STRING:Lcom/fasterxml/jackson/core/JsonToken;
      10: if_acmpne     72
      13: aload_0
      14: invokespecial #68                 // Method readByteArray:()[B
      17: astore_2
      18: aload_0
      19: getfield      #22                 // Field in:Lcom/fasterxml/jackson/core/JsonParser;
      22: invokevirtual #23                 // Method com/fasterxml/jackson/core/JsonParser.nextToken:()Lcom/fasterxml/jackson/core/JsonToken;
      25: pop
      26: aload_2
      27: arraylength
      28: iload_1
      29: if_icmpeq     69
      32: new           #77                 // class org/apache/avro/AvroTypeException
      35: dup
      36: new           #78                 // class java/lang/StringBuilder
      39: dup
      40: invokespecial #79                 // Method java/lang/StringBuilder."<init>":()V
      43: ldc           #88                 // String Expected fixed length
      45: invokevirtual #81                 // Method java/lang/StringBuilder.append:(Ljava/lang/String;)Ljava/lang/StringBuilder;
      48: iload_1
      49: invokevirtual #82                 // Method java/lang/StringBuilder.append:(I)Ljava/lang/StringBuilder;
      52: ldc           #89                 // String , but got
      54: invokevirtual #81                 // Method java/lang/StringBuilder.append:(Ljava/lang/String;)Ljava/lang/StringBuilder;
      57: aload_2
      58: arraylength
      59: invokevirtual #82                 // Method java/lang/StringBuilder.append:(I)Ljava/lang/StringBuilder;
      62: invokevirtual #85                 // Method java/lang/StringBuilder.toString:()Ljava/lang/String;
      65: invokespecial #86                 // Method org/apache/avro/AvroTypeException."<init>":(Ljava/lang/String;)V
      68: athrow
      69: goto          79
      72: aload_0
      73: ldc           #91                 // String fixed
      75: invokespecial #38                 // Method error:(Ljava/lang/String;)Lorg/apache/avro/AvroTypeException;
      78: athrow
      79: return

  protected void skipFixed() throws java.io.IOException;
    Code:
       0: aload_0
       1: getstatic     #73                 // Field org/apache/avro/io/parsing/Symbol.FIXED:Lorg/apache/avro/io/parsing/Symbol;
       4: invokespecial #35                 // Method advance:(Lorg/apache/avro/io/parsing/Symbol;)V
       7: aload_0
       8: getfield      #16                 // Field parser:Lorg/apache/avro/io/parsing/SkipParser;
      11: invokevirtual #74                 // Method org/apache/avro/io/parsing/SkipParser.popSymbol:()Lorg/apache/avro/io/parsing/Symbol;
      14: checkcast     #75                 // class org/apache/avro/io/parsing/Symbol$IntCheckAction
      17: astore_1
      18: aload_0
      19: aload_1
      20: getfield      #76                 // Field org/apache/avro/io/parsing/Symbol$IntCheckAction.size:I
      23: invokespecial #92                 // Method doSkipFixed:(I)V
      26: return

  public int readEnum() throws java.io.IOException;
    Code:
       0: aload_0
       1: getstatic     #93                 // Field org/apache/avro/io/parsing/Symbol.ENUM:Lorg/apache/avro/io/parsing/Symbol;
       4: invokespecial #35                 // Method advance:(Lorg/apache/avro/io/parsing/Symbol;)V
       7: aload_0
       8: getfield      #16                 // Field parser:Lorg/apache/avro/io/parsing/SkipParser;
      11: invokevirtual #74                 // Method org/apache/avro/io/parsing/SkipParser.popSymbol:()Lorg/apache/avro/io/parsing/Symbol;
      14: checkcast     #94                 // class org/apache/avro/io/parsing/Symbol$EnumLabelsAction
      17: astore_1
      18: aload_0
      19: getfield      #22                 // Field in:Lcom/fasterxml/jackson/core/JsonParser;
      22: invokevirtual #29                 // Method com/fasterxml/jackson/core/JsonParser.getCurrentToken:()Lcom/fasterxml/jackson/core/JsonToken;
      25: getstatic     #64                 // Field com/fasterxml/jackson/core/JsonToken.VALUE_STRING:Lcom/fasterxml/jackson/core/JsonToken;
      28: if_acmpne     98
      31: aload_0
      32: getfield      #22                 // Field in:Lcom/fasterxml/jackson/core/JsonParser;
      35: invokevirtual #66                 // Method com/fasterxml/jackson/core/JsonParser.getText:()Ljava/lang/String;
      38: pop
      39: aload_1
      40: aload_0
      41: getfield      #22                 // Field in:Lcom/fasterxml/jackson/core/JsonParser;
      44: invokevirtual #66                 // Method com/fasterxml/jackson/core/JsonParser.getText:()Ljava/lang/String;
      47: invokevirtual #95                 // Method org/apache/avro/io/parsing/Symbol$EnumLabelsAction.findLabel:(Ljava/lang/String;)I
      50: istore_2
      51: iload_2
      52: iflt          65
      55: aload_0
      56: getfield      #22                 // Field in:Lcom/fasterxml/jackson/core/JsonParser;
      59: invokevirtual #23                 // Method com/fasterxml/jackson/core/JsonParser.nextToken:()Lcom/fasterxml/jackson/core/JsonToken;
      62: pop
      63: iload_2
      64: ireturn
      65: new           #77                 // class org/apache/avro/AvroTypeException
      68: dup
      69: new           #78                 // class java/lang/StringBuilder
      72: dup
      73: invokespecial #79                 // Method java/lang/StringBuilder."<init>":()V
      76: ldc           #96                 // String Unknown symbol in enum
      78: invokevirtual #81                 // Method java/lang/StringBuilder.append:(Ljava/lang/String;)Ljava/lang/StringBuilder;
      81: aload_0
      82: getfield      #22                 // Field in:Lcom/fasterxml/jackson/core/JsonParser;
      85: invokevirtual #66                 // Method com/fasterxml/jackson/core/JsonParser.getText:()Ljava/lang/String;
      88: invokevirtual #81                 // Method java/lang/StringBuilder.append:(Ljava/lang/String;)Ljava/lang/StringBuilder;
      91: invokevirtual #85                 // Method java/lang/StringBuilder.toString:()Ljava/lang/String;
      94: invokespecial #86                 // Method org/apache/avro/AvroTypeException."<init>":(Ljava/lang/String;)V
      97: athrow
      98: aload_0
      99: ldc           #91                 // String fixed
     101: invokespecial #38                 // Method error:(Ljava/lang/String;)Lorg/apache/avro/AvroTypeException;
     104: athrow

  public long readArrayStart() throws java.io.IOException;
    Code:
       0: aload_0
       1: getstatic     #97                 // Field org/apache/avro/io/parsing/Symbol.ARRAY_START:Lorg/apache/avro/io/parsing/Symbol;
       4: invokespecial #35                 // Method advance:(Lorg/apache/avro/io/parsing/Symbol;)V
       7: aload_0
       8: getfield      #22                 // Field in:Lcom/fasterxml/jackson/core/JsonParser;
      11: invokevirtual #29                 // Method com/fasterxml/jackson/core/JsonParser.getCurrentToken:()Lcom/fasterxml/jackson/core/JsonToken;
      14: getstatic     #98                 // Field com/fasterxml/jackson/core/JsonToken.START_ARRAY:Lcom/fasterxml/jackson/core/JsonToken;
      17: if_acmpne     33
      20: aload_0
      21: getfield      #22                 // Field in:Lcom/fasterxml/jackson/core/JsonParser;
      24: invokevirtual #23                 // Method com/fasterxml/jackson/core/JsonParser.nextToken:()Lcom/fasterxml/jackson/core/JsonToken;
      27: pop
      28: aload_0
      29: invokespecial #99                 // Method doArrayNext:()J
      32: lreturn
      33: aload_0
      34: ldc           #100                // String array-start
      36: invokespecial #38                 // Method error:(Ljava/lang/String;)Lorg/apache/avro/AvroTypeException;
      39: athrow

  public long arrayNext() throws java.io.IOException;
    Code:
       0: aload_0
       1: getstatic     #101                // Field org/apache/avro/io/parsing/Symbol.ITEM_END:Lorg/apache/avro/io/parsing/Symbol;
       4: invokespecial #35                 // Method advance:(Lorg/apache/avro/io/parsing/Symbol;)V
       7: aload_0
       8: invokespecial #99                 // Method doArrayNext:()J
      11: lreturn

  private long doArrayNext() throws java.io.IOException;
    Code:
       0: aload_0
       1: getfield      #22                 // Field in:Lcom/fasterxml/jackson/core/JsonParser;
       4: invokevirtual #29                 // Method com/fasterxml/jackson/core/JsonParser.getCurrentToken:()Lcom/fasterxml/jackson/core/JsonToken;
       7: getstatic     #102                // Field com/fasterxml/jackson/core/JsonToken.END_ARRAY:Lcom/fasterxml/jackson/core/JsonToken;
      10: if_acmpne     34
      13: aload_0
      14: getfield      #16                 // Field parser:Lorg/apache/avro/io/parsing/SkipParser;
      17: getstatic     #103                // Field org/apache/avro/io/parsing/Symbol.ARRAY_END:Lorg/apache/avro/io/parsing/Symbol;
      20: invokevirtual #33                 // Method org/apache/avro/io/parsing/SkipParser.advance:(Lorg/apache/avro/io/parsing/Symbol;)Lorg/apache/avro/io/parsing/Symbol;
      23: pop
      24: aload_0
      25: getfield      #22                 // Field in:Lcom/fasterxml/jackson/core/JsonParser;
      28: invokevirtual #23                 // Method com/fasterxml/jackson/core/JsonParser.nextToken:()Lcom/fasterxml/jackson/core/JsonToken;
      31: pop
      32: lconst_0
      33: lreturn
      34: lconst_1
      35: lreturn

  public long skipArray() throws java.io.IOException;
    Code:
       0: aload_0
       1: getstatic     #97                 // Field org/apache/avro/io/parsing/Symbol.ARRAY_START:Lorg/apache/avro/io/parsing/Symbol;
       4: invokespecial #35                 // Method advance:(Lorg/apache/avro/io/parsing/Symbol;)V
       7: aload_0
       8: getfield      #22                 // Field in:Lcom/fasterxml/jackson/core/JsonParser;
      11: invokevirtual #29                 // Method com/fasterxml/jackson/core/JsonParser.getCurrentToken:()Lcom/fasterxml/jackson/core/JsonToken;
      14: getstatic     #98                 // Field com/fasterxml/jackson/core/JsonToken.START_ARRAY:Lcom/fasterxml/jackson/core/JsonToken;
      17: if_acmpne     46
      20: aload_0
      21: getfield      #22                 // Field in:Lcom/fasterxml/jackson/core/JsonParser;
      24: invokevirtual #104                // Method com/fasterxml/jackson/core/JsonParser.skipChildren:()Lcom/fasterxml/jackson/core/JsonParser;
      27: pop
      28: aload_0
      29: getfield      #22                 // Field in:Lcom/fasterxml/jackson/core/JsonParser;
      32: invokevirtual #23                 // Method com/fasterxml/jackson/core/JsonParser.nextToken:()Lcom/fasterxml/jackson/core/JsonToken;
      35: pop
      36: aload_0
      37: getstatic     #103                // Field org/apache/avro/io/parsing/Symbol.ARRAY_END:Lorg/apache/avro/io/parsing/Symbol;
      40: invokespecial #35                 // Method advance:(Lorg/apache/avro/io/parsing/Symbol;)V
      43: goto          53
      46: aload_0
      47: ldc           #100                // String array-start
      49: invokespecial #38                 // Method error:(Ljava/lang/String;)Lorg/apache/avro/AvroTypeException;
      52: athrow
      53: lconst_0
      54: lreturn

  public long readMapStart() throws java.io.IOException;
    Code:
       0: aload_0
       1: getstatic     #105                // Field org/apache/avro/io/parsing/Symbol.MAP_START:Lorg/apache/avro/io/parsing/Symbol;
       4: invokespecial #35                 // Method advance:(Lorg/apache/avro/io/parsing/Symbol;)V
       7: aload_0
       8: getfield      #22                 // Field in:Lcom/fasterxml/jackson/core/JsonParser;
      11: invokevirtual #29                 // Method com/fasterxml/jackson/core/JsonParser.getCurrentToken:()Lcom/fasterxml/jackson/core/JsonToken;
      14: getstatic     #106                // Field com/fasterxml/jackson/core/JsonToken.START_OBJECT:Lcom/fasterxml/jackson/core/JsonToken;
      17: if_acmpne     33
      20: aload_0
      21: getfield      #22                 // Field in:Lcom/fasterxml/jackson/core/JsonParser;
      24: invokevirtual #23                 // Method com/fasterxml/jackson/core/JsonParser.nextToken:()Lcom/fasterxml/jackson/core/JsonToken;
      27: pop
      28: aload_0
      29: invokespecial #107                // Method doMapNext:()J
      32: lreturn
      33: aload_0
      34: ldc           #108                // String map-start
      36: invokespecial #38                 // Method error:(Ljava/lang/String;)Lorg/apache/avro/AvroTypeException;
      39: athrow

  public long mapNext() throws java.io.IOException;
    Code:
       0: aload_0
       1: getstatic     #101                // Field org/apache/avro/io/parsing/Symbol.ITEM_END:Lorg/apache/avro/io/parsing/Symbol;
       4: invokespecial #35                 // Method advance:(Lorg/apache/avro/io/parsing/Symbol;)V
       7: aload_0
       8: invokespecial #107                // Method doMapNext:()J
      11: lreturn

  private long doMapNext() throws java.io.IOException;
    Code:
       0: aload_0
       1: getfield      #22                 // Field in:Lcom/fasterxml/jackson/core/JsonParser;
       4: invokevirtual #29                 // Method com/fasterxml/jackson/core/JsonParser.getCurrentToken:()Lcom/fasterxml/jackson/core/JsonToken;
       7: getstatic     #109                // Field com/fasterxml/jackson/core/JsonToken.END_OBJECT:Lcom/fasterxml/jackson/core/JsonToken;
      10: if_acmpne     30
      13: aload_0
      14: getfield      #22                 // Field in:Lcom/fasterxml/jackson/core/JsonParser;
      17: invokevirtual #23                 // Method com/fasterxml/jackson/core/JsonParser.nextToken:()Lcom/fasterxml/jackson/core/JsonToken;
      20: pop
      21: aload_0
      22: getstatic     #110                // Field org/apache/avro/io/parsing/Symbol.MAP_END:Lorg/apache/avro/io/parsing/Symbol;
      25: invokespecial #35                 // Method advance:(Lorg/apache/avro/io/parsing/Symbol;)V
      28: lconst_0
      29: lreturn
      30: lconst_1
      31: lreturn

  public long skipMap() throws java.io.IOException;
    Code:
       0: aload_0
       1: getstatic     #105                // Field org/apache/avro/io/parsing/Symbol.MAP_START:Lorg/apache/avro/io/parsing/Symbol;
       4: invokespecial #35                 // Method advance:(Lorg/apache/avro/io/parsing/Symbol;)V
       7: aload_0
       8: getfield      #22                 // Field in:Lcom/fasterxml/jackson/core/JsonParser;
      11: invokevirtual #29                 // Method com/fasterxml/jackson/core/JsonParser.getCurrentToken:()Lcom/fasterxml/jackson/core/JsonToken;
      14: getstatic     #106                // Field com/fasterxml/jackson/core/JsonToken.START_OBJECT:Lcom/fasterxml/jackson/core/JsonToken;
      17: if_acmpne     46
      20: aload_0
      21: getfield      #22                 // Field in:Lcom/fasterxml/jackson/core/JsonParser;
      24: invokevirtual #104                // Method com/fasterxml/jackson/core/JsonParser.skipChildren:()Lcom/fasterxml/jackson/core/JsonParser;
      27: pop
      28: aload_0
      29: getfield      #22                 // Field in:Lcom/fasterxml/jackson/core/JsonParser;
      32: invokevirtual #23                 // Method com/fasterxml/jackson/core/JsonParser.nextToken:()Lcom/fasterxml/jackson/core/JsonToken;
      35: pop
      36: aload_0
      37: getstatic     #110                // Field org/apache/avro/io/parsing/Symbol.MAP_END:Lorg/apache/avro/io/parsing/Symbol;
      40: invokespecial #35                 // Method advance:(Lorg/apache/avro/io/parsing/Symbol;)V
      43: goto          53
      46: aload_0
      47: ldc           #108                // String map-start
      49: invokespecial #38                 // Method error:(Ljava/lang/String;)Lorg/apache/avro/AvroTypeException;
      52: athrow
      53: lconst_0
      54: lreturn

  public int readIndex() throws java.io.IOException;
    Code:
       0: aload_0
       1: getstatic     #111                // Field org/apache/avro/io/parsing/Symbol.UNION:Lorg/apache/avro/io/parsing/Symbol;
       4: invokespecial #35                 // Method advance:(Lorg/apache/avro/io/parsing/Symbol;)V
       7: aload_0
       8: getfield      #16                 // Field parser:Lorg/apache/avro/io/parsing/SkipParser;
      11: invokevirtual #74                 // Method org/apache/avro/io/parsing/SkipParser.popSymbol:()Lorg/apache/avro/io/parsing/Symbol;
      14: checkcast     #112                // class org/apache/avro/io/parsing/Symbol$Alternative
      17: astore_1
      18: aload_0
      19: getfield      #22                 // Field in:Lcom/fasterxml/jackson/core/JsonParser;
      22: invokevirtual #29                 // Method com/fasterxml/jackson/core/JsonParser.getCurrentToken:()Lcom/fasterxml/jackson/core/JsonToken;
      25: getstatic     #36                 // Field com/fasterxml/jackson/core/JsonToken.VALUE_NULL:Lcom/fasterxml/jackson/core/JsonToken;
      28: if_acmpne     37
      31: ldc           #37                 // String null
      33: astore_2
      34: goto          99
      37: aload_0
      38: getfield      #22                 // Field in:Lcom/fasterxml/jackson/core/JsonParser;
      41: invokevirtual #29                 // Method com/fasterxml/jackson/core/JsonParser.getCurrentToken:()Lcom/fasterxml/jackson/core/JsonToken;
      44: getstatic     #106                // Field com/fasterxml/jackson/core/JsonToken.START_OBJECT:Lcom/fasterxml/jackson/core/JsonToken;
      47: if_acmpne     92
      50: aload_0
      51: getfield      #22                 // Field in:Lcom/fasterxml/jackson/core/JsonParser;
      54: invokevirtual #23                 // Method com/fasterxml/jackson/core/JsonParser.nextToken:()Lcom/fasterxml/jackson/core/JsonToken;
      57: getstatic     #62                 // Field com/fasterxml/jackson/core/JsonToken.FIELD_NAME:Lcom/fasterxml/jackson/core/JsonToken;
      60: if_acmpne     92
      63: aload_0
      64: getfield      #22                 // Field in:Lcom/fasterxml/jackson/core/JsonParser;
      67: invokevirtual #66                 // Method com/fasterxml/jackson/core/JsonParser.getText:()Ljava/lang/String;
      70: astore_2
      71: aload_0
      72: getfield      #22                 // Field in:Lcom/fasterxml/jackson/core/JsonParser;
      75: invokevirtual #23                 // Method com/fasterxml/jackson/core/JsonParser.nextToken:()Lcom/fasterxml/jackson/core/JsonToken;
      78: pop
      79: aload_0
      80: getfield      #16                 // Field parser:Lorg/apache/avro/io/parsing/SkipParser;
      83: getstatic     #113                // Field org/apache/avro/io/parsing/Symbol.UNION_END:Lorg/apache/avro/io/parsing/Symbol;
      86: invokevirtual #114                // Method org/apache/avro/io/parsing/SkipParser.pushSymbol:(Lorg/apache/avro/io/parsing/Symbol;)V
      89: goto          99
      92: aload_0
      93: ldc           #115                // String start-union
      95: invokespecial #38                 // Method error:(Ljava/lang/String;)Lorg/apache/avro/AvroTypeException;
      98: athrow
      99: aload_1
     100: aload_2
     101: invokevirtual #116                // Method org/apache/avro/io/parsing/Symbol$Alternative.findLabel:(Ljava/lang/String;)I
     104: istore_3
     105: iload_3
     106: ifge          136
     109: new           #77                 // class org/apache/avro/AvroTypeException
     112: dup
     113: new           #78                 // class java/lang/StringBuilder
     116: dup
     117: invokespecial #79                 // Method java/lang/StringBuilder."<init>":()V
     120: ldc           #117                // String Unknown union branch
     122: invokevirtual #81                 // Method java/lang/StringBuilder.append:(Ljava/lang/String;)Ljava/lang/StringBuilder;
     125: aload_2
     126: invokevirtual #81                 // Method java/lang/StringBuilder.append:(Ljava/lang/String;)Ljava/lang/StringBuilder;
     129: invokevirtual #85                 // Method java/lang/StringBuilder.toString:()Ljava/lang/String;
     132: invokespecial #86                 // Method org/apache/avro/AvroTypeException."<init>":(Ljava/lang/String;)V
     135: athrow
     136: aload_0
     137: getfield      #16                 // Field parser:Lorg/apache/avro/io/parsing/SkipParser;
     140: aload_1
     141: iload_3
     142: invokevirtual #118                // Method org/apache/avro/io/parsing/Symbol$Alternative.getSymbol:(I)Lorg/apache/avro/io/parsing/Symbol;
     145: invokevirtual #114                // Method org/apache/avro/io/parsing/SkipParser.pushSymbol:(Lorg/apache/avro/io/parsing/Symbol;)V
     148: iload_3
     149: ireturn

  public org.apache.avro.io.parsing.Symbol doAction(org.apache.avro.io.parsing.Symbol, org.apache.avro.io.parsing.Symbol) throws java.io.IOException;
    Code:
       0: aload_2
       1: instanceof    #119                // class org/apache/avro/io/parsing/Symbol$FieldAdjustAction
       4: ifeq          481
       7: aload_2
       8: checkcast     #119                // class org/apache/avro/io/parsing/Symbol$FieldAdjustAction
      11: astore_3
      12: aload_3
      13: getfield      #120                // Field org/apache/avro/io/parsing/Symbol$FieldAdjustAction.fname:Ljava/lang/String;
      16: astore        4
      18: aload_0
      19: getfield      #19                 // Field currentReorderBuffer:Lorg/apache/avro/io/JsonDecoder$ReorderBuffer;
      22: ifnull        223
      25: aload_0
      26: getfield      #19                 // Field currentReorderBuffer:Lorg/apache/avro/io/JsonDecoder$ReorderBuffer;
      29: getfield      #121                // Field org/apache/avro/io/JsonDecoder$ReorderBuffer.savedFields:Ljava/util/Map;
      32: aload         4
      34: invokeinterface #122,  2          // InterfaceMethod java/util/Map.get:(Ljava/lang/Object;)Ljava/lang/Object;
      39: checkcast     #123                // class com/fasterxml/jackson/databind/util/TokenBuffer
      42: astore        5
      44: aconst_null
      45: astore        6
      47: aload         5
      49: ifnull        136
      52: aload_0
      53: getfield      #19                 // Field currentReorderBuffer:Lorg/apache/avro/io/JsonDecoder$ReorderBuffer;
      56: getfield      #121                // Field org/apache/avro/io/JsonDecoder$ReorderBuffer.savedFields:Ljava/util/Map;
      59: aload         4
      61: invokeinterface #124,  2          // InterfaceMethod java/util/Map.remove:(Ljava/lang/Object;)Ljava/lang/Object;
      66: pop
      67: aload_0
      68: getfield      #19                 // Field currentReorderBuffer:Lorg/apache/avro/io/JsonDecoder$ReorderBuffer;
      71: aload_0
      72: getfield      #22                 // Field in:Lcom/fasterxml/jackson/core/JsonParser;
      75: putfield      #125                // Field org/apache/avro/io/JsonDecoder$ReorderBuffer.origParser:Lcom/fasterxml/jackson/core/JsonParser;
      78: aload_0
      79: aload         5
      81: invokevirtual #126                // Method com/fasterxml/jackson/databind/util/TokenBuffer.asParser:()Lcom/fasterxml/jackson/core/JsonParser;
      84: putfield      #22                 // Field in:Lcom/fasterxml/jackson/core/JsonParser;
      87: aload_0
      88: getfield      #22                 // Field in:Lcom/fasterxml/jackson/core/JsonParser;
      91: invokevirtual #23                 // Method com/fasterxml/jackson/core/JsonParser.nextToken:()Lcom/fasterxml/jackson/core/JsonToken;
      94: pop
      95: aconst_null
      96: astore        7
      98: aload         5
     100: ifnull        133
     103: aload         6
     105: ifnull        128
     108: aload         5
     110: invokevirtual #127                // Method com/fasterxml/jackson/databind/util/TokenBuffer.close:()V
     113: goto          133
     116: astore        8
     118: aload         6
     120: aload         8
     122: invokevirtual #129                // Method java/lang/Throwable.addSuppressed:(Ljava/lang/Throwable;)V
     125: goto          133
     128: aload         5
     130: invokevirtual #127                // Method com/fasterxml/jackson/databind/util/TokenBuffer.close:()V
     133: aload         7
     135: areturn
     136: aload         5
     138: ifnull        223
     141: aload         6
     143: ifnull        166
     146: aload         5
     148: invokevirtual #127                // Method com/fasterxml/jackson/databind/util/TokenBuffer.close:()V
     151: goto          223
     154: astore        7
     156: aload         6
     158: aload         7
     160: invokevirtual #129                // Method java/lang/Throwable.addSuppressed:(Ljava/lang/Throwable;)V
     163: goto          223
     166: aload         5
     168: invokevirtual #127                // Method com/fasterxml/jackson/databind/util/TokenBuffer.close:()V
     171: goto          223
     174: astore        7
     176: aload         7
     178: astore        6
     180: aload         7
     182: athrow
     183: astore        9
     185: aload         5
     187: ifnull        220
     190: aload         6
     192: ifnull        215
     195: aload         5
     197: invokevirtual #127                // Method com/fasterxml/jackson/databind/util/TokenBuffer.close:()V
     200: goto          220
     203: astore        10
     205: aload         6
     207: aload         10
     209: invokevirtual #129                // Method java/lang/Throwable.addSuppressed:(Ljava/lang/Throwable;)V
     212: goto          220
     215: aload         5
     217: invokevirtual #127                // Method com/fasterxml/jackson/databind/util/TokenBuffer.close:()V
     220: aload         9
     222: athrow
     223: aload_0
     224: getfield      #22                 // Field in:Lcom/fasterxml/jackson/core/JsonParser;
     227: invokevirtual #29                 // Method com/fasterxml/jackson/core/JsonParser.getCurrentToken:()Lcom/fasterxml/jackson/core/JsonToken;
     230: getstatic     #62                 // Field com/fasterxml/jackson/core/JsonToken.FIELD_NAME:Lcom/fasterxml/jackson/core/JsonToken;
     233: if_acmpne     478
     236: aload_0
     237: getfield      #22                 // Field in:Lcom/fasterxml/jackson/core/JsonParser;
     240: invokevirtual #66                 // Method com/fasterxml/jackson/core/JsonParser.getText:()Ljava/lang/String;
     243: astore        5
     245: aload_0
     246: getfield      #22                 // Field in:Lcom/fasterxml/jackson/core/JsonParser;
     249: invokevirtual #23                 // Method com/fasterxml/jackson/core/JsonParser.nextToken:()Lcom/fasterxml/jackson/core/JsonToken;
     252: pop
     253: aload         4
     255: aload         5
     257: invokevirtual #130                // Method java/lang/String.equals:(Ljava/lang/Object;)Z
     260: ifne          277
     263: aload_3
     264: getfield      #131                // Field org/apache/avro/io/parsing/Symbol$FieldAdjustAction.aliases:Ljava/util/Set;
     267: aload         5
     269: invokeinterface #132,  2          // InterfaceMethod java/util/Set.contains:(Ljava/lang/Object;)Z
     274: ifeq          279
     277: aconst_null
     278: areturn
     279: aload_0
     280: getfield      #19                 // Field currentReorderBuffer:Lorg/apache/avro/io/JsonDecoder$ReorderBuffer;
     283: ifnonnull     298
     286: aload_0
     287: new           #133                // class org/apache/avro/io/JsonDecoder$ReorderBuffer
     290: dup
     291: aconst_null
     292: invokespecial #134                // Method org/apache/avro/io/JsonDecoder$ReorderBuffer."<init>":(Lorg/apache/avro/io/JsonDecoder$1;)V
     295: putfield      #19                 // Field currentReorderBuffer:Lorg/apache/avro/io/JsonDecoder$ReorderBuffer;
     298: new           #123                // class com/fasterxml/jackson/databind/util/TokenBuffer
     301: dup
     302: aload_0
     303: getfield      #22                 // Field in:Lcom/fasterxml/jackson/core/JsonParser;
     306: invokespecial #135                // Method com/fasterxml/jackson/databind/util/TokenBuffer."<init>":(Lcom/fasterxml/jackson/core/JsonParser;)V
     309: astore        6
     311: aconst_null
     312: astore        7
     314: aload         6
     316: aload_0
     317: getfield      #22                 // Field in:Lcom/fasterxml/jackson/core/JsonParser;
     320: invokevirtual #136                // Method com/fasterxml/jackson/databind/util/TokenBuffer.copyCurrentStructure:(Lcom/fasterxml/jackson/core/JsonParser;)V
     323: aload_0
     324: getfield      #19                 // Field currentReorderBuffer:Lorg/apache/avro/io/JsonDecoder$ReorderBuffer;
     327: getfield      #121                // Field org/apache/avro/io/JsonDecoder$ReorderBuffer.savedFields:Ljava/util/Map;
     330: aload         5
     332: aload         6
     334: invokeinterface #137,  3          // InterfaceMethod java/util/Map.put:(Ljava/lang/Object;Ljava/lang/Object;)Ljava/lang/Object;
     339: pop
     340: aload         6
     342: ifnull        427
     345: aload         7
     347: ifnull        370
     350: aload         6
     352: invokevirtual #127                // Method com/fasterxml/jackson/databind/util/TokenBuffer.close:()V
     355: goto          427
     358: astore        8
     360: aload         7
     362: aload         8
     364: invokevirtual #129                // Method java/lang/Throwable.addSuppressed:(Ljava/lang/Throwable;)V
     367: goto          427
     370: aload         6
     372: invokevirtual #127                // Method com/fasterxml/jackson/databind/util/TokenBuffer.close:()V
     375: goto          427
     378: astore        8
     380: aload         8
     382: astore        7
     384: aload         8
     386: athrow
     387: astore        11
     389: aload         6
     391: ifnull        424
     394: aload         7
     396: ifnull        419
     399: aload         6
     401: invokevirtual #127                // Method com/fasterxml/jackson/databind/util/TokenBuffer.close:()V
     404: goto          424
     407: astore        12
     409: aload         7
     411: aload         12
     413: invokevirtual #129                // Method java/lang/Throwable.addSuppressed:(Ljava/lang/Throwable;)V
     416: goto          424
     419: aload         6
     421: invokevirtual #127                // Method com/fasterxml/jackson/databind/util/TokenBuffer.close:()V
     424: aload         11
     426: athrow
     427: aload_0
     428: getfield      #22                 // Field in:Lcom/fasterxml/jackson/core/JsonParser;
     431: invokevirtual #23                 // Method com/fasterxml/jackson/core/JsonParser.nextToken:()Lcom/fasterxml/jackson/core/JsonToken;
     434: pop
     435: aload_0
     436: getfield      #22                 // Field in:Lcom/fasterxml/jackson/core/JsonParser;
     439: invokevirtual #29                 // Method com/fasterxml/jackson/core/JsonParser.getCurrentToken:()Lcom/fasterxml/jackson/core/JsonToken;
     442: getstatic     #62                 // Field com/fasterxml/jackson/core/JsonToken.FIELD_NAME:Lcom/fasterxml/jackson/core/JsonToken;
     445: if_acmpeq     236
     448: new           #77                 // class org/apache/avro/AvroTypeException
     451: dup
     452: new           #78                 // class java/lang/StringBuilder
     455: dup
     456: invokespecial #79                 // Method java/lang/StringBuilder."<init>":()V
     459: ldc           #138                // String Expected field name not found:
     461: invokevirtual #81                 // Method java/lang/StringBuilder.append:(Ljava/lang/String;)Ljava/lang/StringBuilder;
     464: aload_3
     465: getfield      #120                // Field org/apache/avro/io/parsing/Symbol$FieldAdjustAction.fname:Ljava/lang/String;
     468: invokevirtual #81                 // Method java/lang/StringBuilder.append:(Ljava/lang/String;)Ljava/lang/StringBuilder;
     471: invokevirtual #85                 // Method java/lang/StringBuilder.toString:()Ljava/lang/String;
     474: invokespecial #86                 // Method org/apache/avro/AvroTypeException."<init>":(Ljava/lang/String;)V
     477: athrow
     478: goto          736
     481: aload_2
     482: getstatic     #139                // Field org/apache/avro/io/parsing/Symbol.FIELD_END:Lorg/apache/avro/io/parsing/Symbol;
     485: if_acmpne     527
     488: aload_0
     489: getfield      #19                 // Field currentReorderBuffer:Lorg/apache/avro/io/JsonDecoder$ReorderBuffer;
     492: ifnull        736
     495: aload_0
     496: getfield      #19                 // Field currentReorderBuffer:Lorg/apache/avro/io/JsonDecoder$ReorderBuffer;
     499: getfield      #125                // Field org/apache/avro/io/JsonDecoder$ReorderBuffer.origParser:Lcom/fasterxml/jackson/core/JsonParser;
     502: ifnull        736
     505: aload_0
     506: aload_0
     507: getfield      #19                 // Field currentReorderBuffer:Lorg/apache/avro/io/JsonDecoder$ReorderBuffer;
     510: getfield      #125                // Field org/apache/avro/io/JsonDecoder$ReorderBuffer.origParser:Lcom/fasterxml/jackson/core/JsonParser;
     513: putfield      #22                 // Field in:Lcom/fasterxml/jackson/core/JsonParser;
     516: aload_0
     517: getfield      #19                 // Field currentReorderBuffer:Lorg/apache/avro/io/JsonDecoder$ReorderBuffer;
     520: aconst_null
     521: putfield      #125                // Field org/apache/avro/io/JsonDecoder$ReorderBuffer.origParser:Lcom/fasterxml/jackson/core/JsonParser;
     524: goto          736
     527: aload_2
     528: getstatic     #140                // Field org/apache/avro/io/parsing/Symbol.RECORD_START:Lorg/apache/avro/io/parsing/Symbol;
     531: if_acmpne     582
     534: aload_0
     535: getfield      #22                 // Field in:Lcom/fasterxml/jackson/core/JsonParser;
     538: invokevirtual #29                 // Method com/fasterxml/jackson/core/JsonParser.getCurrentToken:()Lcom/fasterxml/jackson/core/JsonToken;
     541: getstatic     #106                // Field com/fasterxml/jackson/core/JsonToken.START_OBJECT:Lcom/fasterxml/jackson/core/JsonToken;
     544: if_acmpne     575
     547: aload_0
     548: getfield      #22                 // Field in:Lcom/fasterxml/jackson/core/JsonParser;
     551: invokevirtual #23                 // Method com/fasterxml/jackson/core/JsonParser.nextToken:()Lcom/fasterxml/jackson/core/JsonToken;
     554: pop
     555: aload_0
     556: getfield      #4                  // Field reorderBuffers:Ljava/util/Stack;
     559: aload_0
     560: getfield      #19                 // Field currentReorderBuffer:Lorg/apache/avro/io/JsonDecoder$ReorderBuffer;
     563: invokevirtual #141                // Method java/util/Stack.push:(Ljava/lang/Object;)Ljava/lang/Object;
     566: pop
     567: aload_0
     568: aconst_null
     569: putfield      #19                 // Field currentReorderBuffer:Lorg/apache/avro/io/JsonDecoder$ReorderBuffer;
     572: goto          736
     575: aload_0
     576: ldc           #142                // String record-start
     578: invokespecial #38                 // Method error:(Ljava/lang/String;)Lorg/apache/avro/AvroTypeException;
     581: athrow
     582: aload_2
     583: getstatic     #143                // Field org/apache/avro/io/parsing/Symbol.RECORD_END:Lorg/apache/avro/io/parsing/Symbol;
     586: if_acmpeq     596
     589: aload_2
     590: getstatic     #113                // Field org/apache/avro/io/parsing/Symbol.UNION_END:Lorg/apache/avro/io/parsing/Symbol;
     593: if_acmpne     709
     596: aload_0
     597: getfield      #22                 // Field in:Lcom/fasterxml/jackson/core/JsonParser;
     600: invokevirtual #29                 // Method com/fasterxml/jackson/core/JsonParser.getCurrentToken:()Lcom/fasterxml/jackson/core/JsonToken;
     603: getstatic     #109                // Field com/fasterxml/jackson/core/JsonToken.END_OBJECT:Lcom/fasterxml/jackson/core/JsonToken;
     606: if_acmpeq     620
     609: aload_0
     610: getfield      #22                 // Field in:Lcom/fasterxml/jackson/core/JsonParser;
     613: invokevirtual #23                 // Method com/fasterxml/jackson/core/JsonParser.nextToken:()Lcom/fasterxml/jackson/core/JsonToken;
     616: pop
     617: goto          596
     620: aload_2
     621: getstatic     #143                // Field org/apache/avro/io/parsing/Symbol.RECORD_END:Lorg/apache/avro/io/parsing/Symbol;
     624: if_acmpne     698
     627: aload_0
     628: getfield      #19                 // Field currentReorderBuffer:Lorg/apache/avro/io/JsonDecoder$ReorderBuffer;
     631: ifnull        684
     634: aload_0
     635: getfield      #19                 // Field currentReorderBuffer:Lorg/apache/avro/io/JsonDecoder$ReorderBuffer;
     638: getfield      #121                // Field org/apache/avro/io/JsonDecoder$ReorderBuffer.savedFields:Ljava/util/Map;
     641: invokeinterface #144,  1          // InterfaceMethod java/util/Map.isEmpty:()Z
     646: ifne          684
     649: aload_0
     650: new           #78                 // class java/lang/StringBuilder
     653: dup
     654: invokespecial #79                 // Method java/lang/StringBuilder."<init>":()V
     657: ldc           #145                // String Unknown fields:
     659: invokevirtual #81                 // Method java/lang/StringBuilder.append:(Ljava/lang/String;)Ljava/lang/StringBuilder;
     662: aload_0
     663: getfield      #19                 // Field currentReorderBuffer:Lorg/apache/avro/io/JsonDecoder$ReorderBuffer;
     666: getfield      #121                // Field org/apache/avro/io/JsonDecoder$ReorderBuffer.savedFields:Ljava/util/Map;
     669: invokeinterface #146,  1          // InterfaceMethod java/util/Map.keySet:()Ljava/util/Set;
     674: invokevirtual #147                // Method java/lang/StringBuilder.append:(Ljava/lang/Object;)Ljava/lang/StringBuilder;
     677: invokevirtual #85                 // Method java/lang/StringBuilder.toString:()Ljava/lang/String;
     680: invokespecial #38                 // Method error:(Ljava/lang/String;)Lorg/apache/avro/AvroTypeException;
     683: athrow
     684: aload_0
     685: aload_0
     686: getfield      #4                  // Field reorderBuffers:Ljava/util/Stack;
     689: invokevirtual #148                // Method java/util/Stack.pop:()Ljava/lang/Object;
     692: checkcast     #133                // class org/apache/avro/io/JsonDecoder$ReorderBuffer
     695: putfield      #19                 // Field currentReorderBuffer:Lorg/apache/avro/io/JsonDecoder$ReorderBuffer;
     698: aload_0
     699: getfield      #22                 // Field in:Lcom/fasterxml/jackson/core/JsonParser;
     702: invokevirtual #23                 // Method com/fasterxml/jackson/core/JsonParser.nextToken:()Lcom/fasterxml/jackson/core/JsonToken;
     705: pop
     706: goto          736
     709: new           #77                 // class org/apache/avro/AvroTypeException
     712: dup
     713: new           #78                 // class java/lang/StringBuilder
     716: dup
     717: invokespecial #79                 // Method java/lang/StringBuilder."<init>":()V
     720: ldc           #149                // String Unknown action symbol
     722: invokevirtual #81                 // Method java/lang/StringBuilder.append:(Ljava/lang/String;)Ljava/lang/StringBuilder;
     725: aload_2
     726: invokevirtual #147                // Method java/lang/StringBuilder.append:(Ljava/lang/Object;)Ljava/lang/StringBuilder;
     729: invokevirtual #85                 // Method java/lang/StringBuilder.toString:()Ljava/lang/String;
     732: invokespecial #86                 // Method org/apache/avro/AvroTypeException."<init>":(Ljava/lang/String;)V
     735: athrow
     736: aconst_null
     737: areturn
    Exception table:
       from    to  target type
         108   113   116   Class java/lang/Throwable
         146   151   154   Class java/lang/Throwable
          47    98   174   Class java/lang/Throwable
          47    98   183   any
         195   200   203   Class java/lang/Throwable
         174   185   183   any
         350   355   358   Class java/lang/Throwable
         314   340   378   Class java/lang/Throwable
         314   340   387   any
         399   404   407   Class java/lang/Throwable
         378   389   387   any

  private org.apache.avro.AvroTypeException error(java.lang.String);
    Code:
       0: new           #77                 // class org/apache/avro/AvroTypeException
       3: dup
       4: new           #78                 // class java/lang/StringBuilder
       7: dup
       8: invokespecial #79                 // Method java/lang/StringBuilder."<init>":()V
      11: ldc           #150                // String Expected
      13: invokevirtual #81                 // Method java/lang/StringBuilder.append:(Ljava/lang/String;)Ljava/lang/StringBuilder;
      16: aload_1
      17: invokevirtual #81                 // Method java/lang/StringBuilder.append:(Ljava/lang/String;)Ljava/lang/StringBuilder;
      20: ldc           #151                // String . Got
      22: invokevirtual #81                 // Method java/lang/StringBuilder.append:(Ljava/lang/String;)Ljava/lang/StringBuilder;
      25: aload_0
      26: getfield      #22                 // Field in:Lcom/fasterxml/jackson/core/JsonParser;
      29: invokevirtual #29                 // Method com/fasterxml/jackson/core/JsonParser.getCurrentToken:()Lcom/fasterxml/jackson/core/JsonToken;
      32: invokevirtual #147                // Method java/lang/StringBuilder.append:(Ljava/lang/Object;)Ljava/lang/StringBuilder;
      35: invokevirtual #85                 // Method java/lang/StringBuilder.toString:()Ljava/lang/String;
      38: invokespecial #86                 // Method org/apache/avro/AvroTypeException."<init>":(Ljava/lang/String;)V
      41: areturn

  static {};
    Code:
       0: new           #25                 // class com/fasterxml/jackson/core/JsonFactory
       3: dup
       4: invokespecial #26                 // Method com/fasterxml/jackson/core/JsonFactory."<init>":()V
       7: putstatic     #20                 // Field jsonFactory:Lcom/fasterxml/jackson/core/JsonFactory;
      10: return
}
