Compiled from "UndertowServletWebServerFactory.java"
final class org.springframework.boot.web.embedded.undertow.UndertowServletWebServerFactory$MetaInfResourcesResourceManager implements io.undertow.server.handlers.resource.ResourceManager {
  private final java.util.List<java.net.URL> metaInfResourceJarUrls;

  private org.springframework.boot.web.embedded.undertow.UndertowServletWebServerFactory$MetaInfResourcesResourceManager(java.util.List<java.net.URL>);
    Code:
       0: aload_0
       1: invokespecial #2                  // Method java/lang/Object."<init>":()V
       4: aload_0
       5: aload_1
       6: putfield      #3                  // Field metaInfResourceJarUrls:Ljava/util/List;
       9: return

  public void close() throws java.io.IOException;
    Code:
       0: return

  public io.undertow.server.handlers.resource.Resource getResource(java.lang.String);
    Code:
       0: aload_0
       1: getfield      #3                  // Field metaInfResourceJarUrls:Ljava/util/List;
       4: invokeinterface #4,  1            // InterfaceMethod java/util/List.iterator:()Ljava/util/Iterator;
       9: astore_2
      10: aload_2
      11: invokeinterface #5,  1            // InterfaceMethod java/util/Iterator.hasNext:()Z
      16: ifeq          48
      19: aload_2
      20: invokeinterface #6,  1            // InterfaceMethod java/util/Iterator.next:()Ljava/lang/Object;
      25: checkcast     #7                  // class java/net/URL
      28: astore_3
      29: aload_0
      30: aload_3
      31: aload_1
      32: invokespecial #8                  // Method getMetaInfResource:(Ljava/net/URL;Ljava/lang/String;)Lio/undertow/server/handlers/resource/URLResource;
      35: astore        4
      37: aload         4
      39: ifnull        45
      42: aload         4
      44: areturn
      45: goto          10
      48: aconst_null
      49: areturn

  public boolean isResourceChangeListenerSupported();
    Code:
       0: iconst_0
       1: ireturn

  public void registerResourceChangeListener(io.undertow.server.handlers.resource.ResourceChangeListener);
    Code:
       0: return

  public void removeResourceChangeListener(io.undertow.server.handlers.resource.ResourceChangeListener);
    Code:
       0: return

  private io.undertow.server.handlers.resource.URLResource getMetaInfResource(java.net.URL, java.lang.String);
    Code:
       0: invokestatic  #9                  // Method org/springframework/boot/web/embedded/undertow/UndertowServletWebServerFactory.access$200:()Ljava/util/regex/Pattern;
       3: aload_2
       4: invokevirtual #10                 // Method java/util/regex/Pattern.matcher:(Ljava/lang/CharSequence;)Ljava/util/regex/Matcher;
       7: ldc           #11                 // String /
       9: invokevirtual #12                 // Method java/util/regex/Matcher.replaceAll:(Ljava/lang/String;)Ljava/lang/String;
      12: ldc           #13                 // String UTF-8
      14: invokestatic  #14                 // Method java/net/URLEncoder.encode:(Ljava/lang/String;Ljava/lang/String;)Ljava/lang/String;
      17: astore_3
      18: new           #7                  // class java/net/URL
      21: dup
      22: new           #15                 // class java/lang/StringBuilder
      25: dup
      26: invokespecial #16                 // Method java/lang/StringBuilder."<init>":()V
      29: aload_1
      30: invokevirtual #17                 // Method java/lang/StringBuilder.append:(Ljava/lang/Object;)Ljava/lang/StringBuilder;
      33: ldc           #18                 // String META-INF/resources
      35: invokevirtual #19                 // Method java/lang/StringBuilder.append:(Ljava/lang/String;)Ljava/lang/StringBuilder;
      38: aload_3
      39: invokevirtual #19                 // Method java/lang/StringBuilder.append:(Ljava/lang/String;)Ljava/lang/StringBuilder;
      42: invokevirtual #20                 // Method java/lang/StringBuilder.toString:()Ljava/lang/String;
      45: invokespecial #21                 // Method java/net/URL."<init>":(Ljava/lang/String;)V
      48: astore        4
      50: new           #22                 // class io/undertow/server/handlers/resource/URLResource
      53: dup
      54: aload         4
      56: aload_2
      57: invokespecial #23                 // Method io/undertow/server/handlers/resource/URLResource."<init>":(Ljava/net/URL;Ljava/lang/String;)V
      60: astore        5
      62: aload         5
      64: invokevirtual #24                 // Method io/undertow/server/handlers/resource/URLResource.getContentLength:()Ljava/lang/Long;
      67: invokevirtual #25                 // Method java/lang/Long.longValue:()J
      70: lconst_0
      71: lcmp
      72: ifge          77
      75: aconst_null
      76: areturn
      77: aload         5
      79: areturn
      80: astore_3
      81: aconst_null
      82: areturn
    Exception table:
       from    to  target type
           0    76    80   Class java/lang/Exception
          77    79    80   Class java/lang/Exception

  org.springframework.boot.web.embedded.undertow.UndertowServletWebServerFactory$MetaInfResourcesResourceManager(java.util.List, org.springframework.boot.web.embedded.undertow.UndertowServletWebServerFactory$1);
    Code:
       0: aload_0
       1: aload_1
       2: invokespecial #1                  // Method "<init>":(Ljava/util/List;)V
       5: return
}
