Compiled from "GroovyScriptEngine.java"
class groovy.util.GroovyScriptEngine$LocalData {
  org.codehaus.groovy.control.CompilationUnit cu;

  org.codehaus.groovy.tools.gse.StringSetMap dependencyCache;

  java.util.Map<java.lang.String, java.lang.String> precompiledEntries;

  private groovy.util.GroovyScriptEngine$LocalData();
    Code:
       0: aload_0
       1: invokespecial #21                 // Method java/lang/Object."<init>":()V
       4: aload_0
       5: new           #23                 // class org/codehaus/groovy/tools/gse/StringSetMap
       8: dup
       9: invokespecial #24                 // Method org/codehaus/groovy/tools/gse/StringSetMap."<init>":()V
      12: putfield      #26                 // Field dependencyCache:Lorg/codehaus/groovy/tools/gse/StringSetMap;
      15: aload_0
      16: new           #28                 // class java/util/HashMap
      19: dup
      20: invokespecial #29                 // Method java/util/HashMap."<init>":()V
      23: putfield      #31                 // Field precompiledEntries:Ljava/util/Map;
      26: return

  groovy.util.GroovyScriptEngine$LocalData(groovy.util.GroovyScriptEngine$1);
    Code:
       0: aload_0
       1: invokespecial #35                 // Method "<init>":()V
       4: return
}
