Compiled from "GroovyTestSuite.java"
public class groovy.util.GroovyTestSuite extends junit.framework.TestSuite {
  protected static java.lang.String file;

  protected final groovy.lang.GroovyClassLoader loader;

  public groovy.util.GroovyTestSuite();
    Code:
       0: aload_0
       1: invokespecial #15                 // Method junit/framework/TestSuite."<init>":()V
       4: aload_0
       5: new           #7                  // class groovy/util/GroovyTestSuite$1
       8: dup
       9: aload_0
      10: invokespecial #18                 // Method groovy/util/GroovyTestSuite$1."<init>":(Lgroovy/util/GroovyTestSuite;)V
      13: invokestatic  #24                 // Method java/security/AccessController.doPrivileged:(Ljava/security/PrivilegedAction;)Ljava/lang/Object;
      16: checkcast     #26                 // class groovy/lang/GroovyClassLoader
      19: putfield      #28                 // Field loader:Lgroovy/lang/GroovyClassLoader;
      22: return

  public static void main(java.lang.String[]);
    Code:
       0: aload_0
       1: arraylength
       2: ifle          11
       5: aload_0
       6: iconst_0
       7: aaload
       8: putstatic     #34                 // Field file:Ljava/lang/String;
      11: invokestatic  #38                 // Method suite:()Ljunit/framework/Test;
      14: invokestatic  #44                 // Method junit/textui/TestRunner.run:(Ljunit/framework/Test;)Ljunit/framework/TestResult;
      17: pop
      18: return

  public static junit.framework.Test suite();
    Code:
       0: new           #2                  // class groovy/util/GroovyTestSuite
       3: dup
       4: invokespecial #49                 // Method "<init>":()V
       7: astore_0
       8: aload_0
       9: invokevirtual #52                 // Method loadTestSuite:()V
      12: goto          44
      15: astore_1
      16: new           #54                 // class java/lang/RuntimeException
      19: dup
      20: new           #56                 // class java/lang/StringBuilder
      23: dup
      24: invokespecial #57                 // Method java/lang/StringBuilder."<init>":()V
      27: ldc           #59                 // String Could not create the test suite:
      29: invokevirtual #63                 // Method java/lang/StringBuilder.append:(Ljava/lang/String;)Ljava/lang/StringBuilder;
      32: aload_1
      33: invokevirtual #66                 // Method java/lang/StringBuilder.append:(Ljava/lang/Object;)Ljava/lang/StringBuilder;
      36: invokevirtual #70                 // Method java/lang/StringBuilder.toString:()Ljava/lang/String;
      39: aload_1
      40: invokespecial #73                 // Method java/lang/RuntimeException."<init>":(Ljava/lang/String;Ljava/lang/Throwable;)V
      43: athrow
      44: aload_0
      45: areturn
    Exception table:
       from    to  target type
           8    12    15   Class java/lang/Exception

  public void loadTestSuite() throws java.lang.Exception;
    Code:
       0: ldc           #77                 // String test
       2: getstatic     #34                 // Field file:Ljava/lang/String;
       5: invokestatic  #83                 // Method java/lang/System.getProperty:(Ljava/lang/String;Ljava/lang/String;)Ljava/lang/String;
       8: astore_1
       9: aload_1
      10: ifnonnull     23
      13: new           #54                 // class java/lang/RuntimeException
      16: dup
      17: ldc           #85                 // String No filename given in the \'test\' system property so cannot run a Groovy unit test
      19: invokespecial #88                 // Method java/lang/RuntimeException."<init>":(Ljava/lang/String;)V
      22: athrow
      23: getstatic     #94                 // Field java/lang/System.out:Ljava/io/PrintStream;
      26: new           #56                 // class java/lang/StringBuilder
      29: dup
      30: invokespecial #57                 // Method java/lang/StringBuilder."<init>":()V
      33: ldc           #96                 // String Compiling:
      35: invokevirtual #63                 // Method java/lang/StringBuilder.append:(Ljava/lang/String;)Ljava/lang/StringBuilder;
      38: aload_1
      39: invokevirtual #63                 // Method java/lang/StringBuilder.append:(Ljava/lang/String;)Ljava/lang/StringBuilder;
      42: invokevirtual #70                 // Method java/lang/StringBuilder.toString:()Ljava/lang/String;
      45: invokevirtual #101                // Method java/io/PrintStream.println:(Ljava/lang/String;)V
      48: aload_0
      49: aload_1
      50: invokevirtual #105                // Method compile:(Ljava/lang/String;)Ljava/lang/Class;
      53: astore_2
      54: iconst_0
      55: anewarray     #90                 // class java/lang/String
      58: astore_3
      59: ldc           #107                // class junit/framework/Test
      61: aload_2
      62: invokevirtual #113                // Method java/lang/Class.isAssignableFrom:(Ljava/lang/Class;)Z
      65: ifne          93
      68: ldc           #115                // class groovy/lang/Script
      70: aload_2
      71: invokevirtual #113                // Method java/lang/Class.isAssignableFrom:(Ljava/lang/Class;)Z
      74: ifeq          93
      77: aload_0
      78: new           #117                // class org/codehaus/groovy/runtime/ScriptTestAdapter
      81: dup
      82: aload_2
      83: aload_3
      84: invokespecial #120                // Method org/codehaus/groovy/runtime/ScriptTestAdapter."<init>":(Ljava/lang/Class;[Ljava/lang/String;)V
      87: invokevirtual #124                // Method addTest:(Ljunit/framework/Test;)V
      90: goto          98
      93: aload_0
      94: aload_2
      95: invokevirtual #129                // Method addTestSuite:(Ljava/lang/Class;)V
      98: return

  public java.lang.Class compile(java.lang.String) throws java.lang.Exception;
    Code:
       0: aload_0
       1: getfield      #28                 // Field loader:Lgroovy/lang/GroovyClassLoader;
       4: new           #134                // class java/io/File
       7: dup
       8: aload_1
       9: invokespecial #135                // Method java/io/File."<init>":(Ljava/lang/String;)V
      12: invokevirtual #139                // Method groovy/lang/GroovyClassLoader.parseClass:(Ljava/io/File;)Ljava/lang/Class;
      15: areturn

  static {};
    Code:
       0: aconst_null
       1: putstatic     #34                 // Field file:Ljava/lang/String;
       4: return
}
