Compiled from "ObservableList.java"
public abstract class groovy.util.ObservableList$ElementEvent extends java.beans.PropertyChangeEvent {
  private final groovy.util.ObservableList$ChangeType type;

  private final int index;

  public groovy.util.ObservableList$ElementEvent(java.lang.Object, java.lang.Object, java.lang.Object, int, groovy.util.ObservableList$ChangeType);
    Code:
       0: aload_0
       1: aload_1
       2: ldc           #19                 // String content
       4: aload_2
       5: aload_3
       6: invokespecial #22                 // Method java/beans/PropertyChangeEvent."<init>":(Ljava/lang/Object;Ljava/lang/String;Ljava/lang/Object;Ljava/lang/Object;)V
       9: aload_0
      10: aload         5
      12: putfield      #24                 // Field type:Lgroovy/util/ObservableList$ChangeType;
      15: aload_0
      16: iload         4
      18: putfield      #26                 // Field index:I
      21: return

  public int getIndex();
    Code:
       0: aload_0
       1: getfield      #26                 // Field index:I
       4: ireturn

  public int getType();
    Code:
       0: aload_0
       1: getfield      #24                 // Field type:Lgroovy/util/ObservableList$ChangeType;
       4: invokevirtual #38                 // Method groovy/util/ObservableList$ChangeType.ordinal:()I
       7: ireturn

  public groovy.util.ObservableList$ChangeType getChangeType();
    Code:
       0: aload_0
       1: getfield      #24                 // Field type:Lgroovy/util/ObservableList$ChangeType;
       4: areturn

  public java.lang.String getTypeAsString();
    Code:
       0: aload_0
       1: getfield      #24                 // Field type:Lgroovy/util/ObservableList$ChangeType;
       4: invokevirtual #45                 // Method groovy/util/ObservableList$ChangeType.name:()Ljava/lang/String;
       7: invokevirtual #50                 // Method java/lang/String.toUpperCase:()Ljava/lang/String;
      10: areturn
}
