Compiled from "ProxyGenerator.java"
final class groovy.util.ProxyGenerator$1 extends groovy.lang.DelegatingMetaClass {
  groovy.util.ProxyGenerator$1(groovy.lang.MetaClass);
    Code:
       0: aload_0
       1: aload_1
       2: invokespecial #13                 // Method groovy/lang/DelegatingMetaClass."<init>":(Lgroovy/lang/MetaClass;)V
       5: return

  public java.lang.Object invokeStaticMethod(java.lang.Object, java.lang.String, java.lang.Object[]);
    Code:
       0: getstatic     #23                 // Field groovy/util/ProxyGenerator.INSTANCE:Lgroovy/util/ProxyGenerator;
       3: aload_2
       4: aload_3
       5: invokestatic  #29                 // Method org/codehaus/groovy/runtime/InvokerHelper.invokeMethod:(Ljava/lang/Object;Ljava/lang/String;Ljava/lang/Object;)Ljava/lang/Object;
       8: areturn
}
