Compiled from "SiftModelHandler.java"
public class ch.qos.logback.core.sift.SiftModelHandler extends ch.qos.logback.core.model.processor.ModelHandlerBase {
  static final java.lang.String ONE_AND_ONLY_ONE_URL;

  public ch.qos.logback.core.sift.SiftModelHandler(ch.qos.logback.core.Context);
    Code:
       0: aload_0
       1: aload_1
       2: invokespecial #3                  // Method ch/qos/logback/core/model/processor/ModelHandlerBase."<init>":(Lch/qos/logback/core/Context;)V
       5: return

  public static ch.qos.logback.core.sift.SiftModelHandler makeInstance(ch.qos.logback.core.Context, ch.qos.logback.core.model.processor.ModelInterpretationContext);
    Code:
       0: new           #9                  // class ch/qos/logback/core/sift/SiftModelHandler
       3: dup
       4: aload_0
       5: invokespecial #11                 // Method "<init>":(Lch/qos/logback/core/Context;)V
       8: areturn

  protected java.lang.Class<ch.qos.logback.core.model.SiftModel> getSupportedModelClass();
    Code:
       0: ldc           #12                 // class ch/qos/logback/core/model/SiftModel
       2: areturn

  public void handle(ch.qos.logback.core.model.processor.ModelInterpretationContext, ch.qos.logback.core.model.Model) throws ch.qos.logback.core.model.processor.ModelHandlerException;
    Code:
       0: aload_2
       1: checkcast     #12                 // class ch/qos/logback/core/model/SiftModel
       4: astore_3
       5: aload_3
       6: invokevirtual #14                 // Method ch/qos/logback/core/model/SiftModel.markAsSkipped:()V
       9: aload_0
      10: aload_3
      11: invokevirtual #18                 // Method computeAppenderModelCount:(Lch/qos/logback/core/model/SiftModel;)J
      14: lstore        4
      16: lload         4
      18: lconst_0
      19: lcmp
      20: ifne          34
      23: ldc           #22                 // String No nested appenders found within the <sift> element in SiftingAppender.
      25: astore        6
      27: aload_0
      28: aload         6
      30: invokevirtual #24                 // Method addError:(Ljava/lang/String;)V
      33: return
      34: lload         4
      36: lconst_1
      37: lcmp
      38: ifle          52
      41: ldc           #28                 // String Only and only one appender can be nested the <sift> element in SiftingAppender. See also http://logback.qos.ch/codes.html#1andOnly1
      43: astore        6
      45: aload_0
      46: aload         6
      48: invokevirtual #24                 // Method addError:(Ljava/lang/String;)V
      51: return
      52: aload_1
      53: invokevirtual #30                 // Method ch/qos/logback/core/model/processor/ModelInterpretationContext.peekObject:()Ljava/lang/Object;
      56: astore        6
      58: aload         6
      60: instanceof    #36                 // class ch/qos/logback/core/sift/SiftingAppenderBase
      63: ifeq          103
      66: aload         6
      68: checkcast     #36                 // class ch/qos/logback/core/sift/SiftingAppenderBase
      71: astore        7
      73: aload         7
      75: invokevirtual #38                 // Method ch/qos/logback/core/sift/SiftingAppenderBase.getDiscriminatorKey:()Ljava/lang/String;
      78: astore        8
      80: new           #42                 // class ch/qos/logback/core/sift/AppenderFactoryUsingSiftModel
      83: dup
      84: aload_1
      85: aload_3
      86: aload         8
      88: invokespecial #44                 // Method ch/qos/logback/core/sift/AppenderFactoryUsingSiftModel."<init>":(Lch/qos/logback/core/model/processor/ModelInterpretationContext;Lch/qos/logback/core/model/Model;Ljava/lang/String;)V
      91: astore        9
      93: aload         7
      95: aload         9
      97: invokevirtual #47                 // Method ch/qos/logback/core/sift/SiftingAppenderBase.setAppenderFactory:(Lch/qos/logback/core/sift/AppenderFactory;)V
     100: goto          117
     103: aload_0
     104: aload         6
     106: invokestatic  #51                 // Method java/lang/String.valueOf:(Ljava/lang/Object;)Ljava/lang/String;
     109: invokedynamic #57,  0             // InvokeDynamic #0:makeConcatWithConstants:(Ljava/lang/String;)Ljava/lang/String;
     114: invokevirtual #24                 // Method addError:(Ljava/lang/String;)V
     117: return

  private long computeAppenderModelCount(ch.qos.logback.core.model.SiftModel);
    Code:
       0: aload_1
       1: invokevirtual #61                 // Method ch/qos/logback/core/model/SiftModel.getSubModels:()Ljava/util/List;
       4: invokeinterface #65,  1           // InterfaceMethod java/util/List.stream:()Ljava/util/stream/Stream;
       9: astore_2
      10: aload_2
      11: invokedynamic #71,  0             // InvokeDynamic #1:test:()Ljava/util/function/Predicate;
      16: invokeinterface #75,  2           // InterfaceMethod java/util/stream/Stream.filter:(Ljava/util/function/Predicate;)Ljava/util/stream/Stream;
      21: invokeinterface #81,  1           // InterfaceMethod java/util/stream/Stream.count:()J
      26: lstore_3
      27: lload_3
      28: lreturn

  private static boolean lambda$computeAppenderModelCount$0(ch.qos.logback.core.model.Model);
    Code:
       0: aload_0
       1: instanceof    #85                 // class ch/qos/logback/core/model/AppenderModel
       4: ireturn
}
