Compiled from "AbstractHttp11Protocol.java"
public abstract class org.apache.coyote.http11.AbstractHttp11Protocol<S> extends org.apache.coyote.AbstractProtocol<S> {
  protected static final org.apache.tomcat.util.res.StringManager sm;

  private final org.apache.coyote.CompressionConfig compressionConfig;

  private org.apache.coyote.ContinueResponseTiming continueResponseTiming;

  private boolean useKeepAliveResponseHeader;

  private java.lang.String relaxedPathChars;

  private java.lang.String relaxedQueryChars;

  private boolean allowHostHeaderMismatch;

  private boolean rejectIllegalHeader;

  private int maxSavePostSize;

  private int maxHttpHeaderSize;

  private int connectionUploadTimeout;

  private boolean disableUploadTimeout;

  private java.util.regex.Pattern restrictedUserAgents;

  private java.lang.String server;

  private boolean serverRemoveAppProvidedValues;

  private int maxTrailerSize;

  private int maxExtensionSize;

  private int maxSwallowSize;

  private boolean secure;

  private java.util.Set<java.lang.String> allowedTrailerHeaders;

  private final java.util.List<org.apache.coyote.UpgradeProtocol> upgradeProtocols;

  private final java.util.Map<java.lang.String, org.apache.coyote.UpgradeProtocol> httpUpgradeProtocols;

  private final java.util.Map<java.lang.String, org.apache.coyote.UpgradeProtocol> negotiatedProtocols;

  private org.apache.tomcat.util.net.SSLHostConfig defaultSSLHostConfig;

  public org.apache.coyote.http11.AbstractHttp11Protocol(org.apache.tomcat.util.net.AbstractEndpoint<S, ?>);
    Code:
       0: aload_0
       1: aload_1
       2: invokespecial #1                  // Method org/apache/coyote/AbstractProtocol."<init>":(Lorg/apache/tomcat/util/net/AbstractEndpoint;)V
       5: aload_0
       6: new           #2                  // class org/apache/coyote/CompressionConfig
       9: dup
      10: invokespecial #3                  // Method org/apache/coyote/CompressionConfig."<init>":()V
      13: putfield      #4                  // Field compressionConfig:Lorg/apache/coyote/CompressionConfig;
      16: aload_0
      17: getstatic     #5                  // Field org/apache/coyote/ContinueResponseTiming.IMMEDIATELY:Lorg/apache/coyote/ContinueResponseTiming;
      20: putfield      #6                  // Field continueResponseTiming:Lorg/apache/coyote/ContinueResponseTiming;
      23: aload_0
      24: iconst_1
      25: putfield      #7                  // Field useKeepAliveResponseHeader:Z
      28: aload_0
      29: aconst_null
      30: putfield      #8                  // Field relaxedPathChars:Ljava/lang/String;
      33: aload_0
      34: aconst_null
      35: putfield      #9                  // Field relaxedQueryChars:Ljava/lang/String;
      38: aload_0
      39: iconst_0
      40: putfield      #10                 // Field allowHostHeaderMismatch:Z
      43: aload_0
      44: iconst_1
      45: putfield      #11                 // Field rejectIllegalHeader:Z
      48: aload_0
      49: sipush        4096
      52: putfield      #12                 // Field maxSavePostSize:I
      55: aload_0
      56: sipush        8192
      59: putfield      #13                 // Field maxHttpHeaderSize:I
      62: aload_0
      63: ldc           #14                 // int 300000
      65: putfield      #15                 // Field connectionUploadTimeout:I
      68: aload_0
      69: iconst_1
      70: putfield      #16                 // Field disableUploadTimeout:Z
      73: aload_0
      74: aconst_null
      75: putfield      #17                 // Field restrictedUserAgents:Ljava/util/regex/Pattern;
      78: aload_0
      79: iconst_0
      80: putfield      #18                 // Field serverRemoveAppProvidedValues:Z
      83: aload_0
      84: sipush        8192
      87: putfield      #19                 // Field maxTrailerSize:I
      90: aload_0
      91: sipush        8192
      94: putfield      #20                 // Field maxExtensionSize:I
      97: aload_0
      98: ldc           #21                 // int 2097152
     100: putfield      #22                 // Field maxSwallowSize:I
     103: aload_0
     104: new           #23                 // class java/util/concurrent/ConcurrentHashMap
     107: dup
     108: invokespecial #24                 // Method java/util/concurrent/ConcurrentHashMap."<init>":()V
     111: invokestatic  #25                 // Method java/util/Collections.newSetFromMap:(Ljava/util/Map;)Ljava/util/Set;
     114: putfield      #26                 // Field allowedTrailerHeaders:Ljava/util/Set;
     117: aload_0
     118: new           #27                 // class java/util/ArrayList
     121: dup
     122: invokespecial #28                 // Method java/util/ArrayList."<init>":()V
     125: putfield      #29                 // Field upgradeProtocols:Ljava/util/List;
     128: aload_0
     129: new           #30                 // class java/util/HashMap
     132: dup
     133: invokespecial #31                 // Method java/util/HashMap."<init>":()V
     136: putfield      #32                 // Field httpUpgradeProtocols:Ljava/util/Map;
     139: aload_0
     140: new           #30                 // class java/util/HashMap
     143: dup
     144: invokespecial #31                 // Method java/util/HashMap."<init>":()V
     147: putfield      #33                 // Field negotiatedProtocols:Ljava/util/Map;
     150: aload_0
     151: aconst_null
     152: putfield      #34                 // Field defaultSSLHostConfig:Lorg/apache/tomcat/util/net/SSLHostConfig;
     155: aload_0
     156: ldc           #36                 // int 60000
     158: invokevirtual #37                 // Method setConnectionTimeout:(I)V
     161: new           #38                 // class org/apache/coyote/AbstractProtocol$ConnectionHandler
     164: dup
     165: aload_0
     166: invokespecial #39                 // Method org/apache/coyote/AbstractProtocol$ConnectionHandler."<init>":(Lorg/apache/coyote/AbstractProtocol;)V
     169: astore_2
     170: aload_0
     171: aload_2
     172: invokevirtual #40                 // Method setHandler:(Lorg/apache/tomcat/util/net/AbstractEndpoint$Handler;)V
     175: aload_0
     176: invokevirtual #41                 // Method getEndpoint:()Lorg/apache/tomcat/util/net/AbstractEndpoint;
     179: aload_2
     180: invokevirtual #42                 // Method org/apache/tomcat/util/net/AbstractEndpoint.setHandler:(Lorg/apache/tomcat/util/net/AbstractEndpoint$Handler;)V
     183: return

  public void init() throws java.lang.Exception;
    Code:
       0: aload_0
       1: getfield      #29                 // Field upgradeProtocols:Ljava/util/List;
       4: invokeinterface #43,  1           // InterfaceMethod java/util/List.iterator:()Ljava/util/Iterator;
       9: astore_1
      10: aload_1
      11: invokeinterface #44,  1           // InterfaceMethod java/util/Iterator.hasNext:()Z
      16: ifeq          37
      19: aload_1
      20: invokeinterface #45,  1           // InterfaceMethod java/util/Iterator.next:()Ljava/lang/Object;
      25: checkcast     #46                 // class org/apache/coyote/UpgradeProtocol
      28: astore_2
      29: aload_0
      30: aload_2
      31: invokespecial #47                 // Method configureUpgradeProtocol:(Lorg/apache/coyote/UpgradeProtocol;)V
      34: goto          10
      37: aload_0
      38: invokespecial #48                 // Method org/apache/coyote/AbstractProtocol.init:()V
      41: return

  protected java.lang.String getProtocolName();
    Code:
       0: ldc           #49                 // String Http
       2: areturn

  protected org.apache.tomcat.util.net.AbstractEndpoint<S, ?> getEndpoint();
    Code:
       0: aload_0
       1: invokespecial #50                 // Method org/apache/coyote/AbstractProtocol.getEndpoint:()Lorg/apache/tomcat/util/net/AbstractEndpoint;
       4: areturn

  public java.lang.String getContinueResponseTiming();
    Code:
       0: aload_0
       1: getfield      #6                  // Field continueResponseTiming:Lorg/apache/coyote/ContinueResponseTiming;
       4: invokevirtual #51                 // Method org/apache/coyote/ContinueResponseTiming.toString:()Ljava/lang/String;
       7: areturn

  public void setContinueResponseTiming(java.lang.String);
    Code:
       0: aload_0
       1: aload_1
       2: invokestatic  #52                 // Method org/apache/coyote/ContinueResponseTiming.fromString:(Ljava/lang/String;)Lorg/apache/coyote/ContinueResponseTiming;
       5: putfield      #6                  // Field continueResponseTiming:Lorg/apache/coyote/ContinueResponseTiming;
       8: return

  public org.apache.coyote.ContinueResponseTiming getContinueResponseTimingInternal();
    Code:
       0: aload_0
       1: getfield      #6                  // Field continueResponseTiming:Lorg/apache/coyote/ContinueResponseTiming;
       4: areturn

  public boolean getUseKeepAliveResponseHeader();
    Code:
       0: aload_0
       1: getfield      #7                  // Field useKeepAliveResponseHeader:Z
       4: ireturn

  public void setUseKeepAliveResponseHeader(boolean);
    Code:
       0: aload_0
       1: iload_1
       2: putfield      #7                  // Field useKeepAliveResponseHeader:Z
       5: return

  public java.lang.String getRelaxedPathChars();
    Code:
       0: aload_0
       1: getfield      #8                  // Field relaxedPathChars:Ljava/lang/String;
       4: areturn

  public void setRelaxedPathChars(java.lang.String);
    Code:
       0: aload_0
       1: aload_1
       2: putfield      #8                  // Field relaxedPathChars:Ljava/lang/String;
       5: return

  public java.lang.String getRelaxedQueryChars();
    Code:
       0: aload_0
       1: getfield      #9                  // Field relaxedQueryChars:Ljava/lang/String;
       4: areturn

  public void setRelaxedQueryChars(java.lang.String);
    Code:
       0: aload_0
       1: aload_1
       2: putfield      #9                  // Field relaxedQueryChars:Ljava/lang/String;
       5: return

  public boolean getAllowHostHeaderMismatch();
    Code:
       0: aload_0
       1: getfield      #10                 // Field allowHostHeaderMismatch:Z
       4: ireturn

  public void setAllowHostHeaderMismatch(boolean);
    Code:
       0: aload_0
       1: iload_1
       2: putfield      #10                 // Field allowHostHeaderMismatch:Z
       5: return

  public boolean getRejectIllegalHeader();
    Code:
       0: aload_0
       1: getfield      #11                 // Field rejectIllegalHeader:Z
       4: ireturn

  public void setRejectIllegalHeader(boolean);
    Code:
       0: aload_0
       1: iload_1
       2: putfield      #11                 // Field rejectIllegalHeader:Z
       5: return

  public boolean getRejectIllegalHeaderName();
    Code:
       0: aload_0
       1: getfield      #11                 // Field rejectIllegalHeader:Z
       4: ireturn

  public void setRejectIllegalHeaderName(boolean);
    Code:
       0: aload_0
       1: iload_1
       2: putfield      #11                 // Field rejectIllegalHeader:Z
       5: return

  public int getMaxSavePostSize();
    Code:
       0: aload_0
       1: getfield      #12                 // Field maxSavePostSize:I
       4: ireturn

  public void setMaxSavePostSize(int);
    Code:
       0: aload_0
       1: iload_1
       2: putfield      #12                 // Field maxSavePostSize:I
       5: return

  public int getMaxHttpHeaderSize();
    Code:
       0: aload_0
       1: getfield      #13                 // Field maxHttpHeaderSize:I
       4: ireturn

  public void setMaxHttpHeaderSize(int);
    Code:
       0: aload_0
       1: iload_1
       2: putfield      #13                 // Field maxHttpHeaderSize:I
       5: return

  public int getConnectionUploadTimeout();
    Code:
       0: aload_0
       1: getfield      #15                 // Field connectionUploadTimeout:I
       4: ireturn

  public void setConnectionUploadTimeout(int);
    Code:
       0: aload_0
       1: iload_1
       2: putfield      #15                 // Field connectionUploadTimeout:I
       5: return

  public boolean getDisableUploadTimeout();
    Code:
       0: aload_0
       1: getfield      #16                 // Field disableUploadTimeout:Z
       4: ireturn

  public void setDisableUploadTimeout(boolean);
    Code:
       0: aload_0
       1: iload_1
       2: putfield      #16                 // Field disableUploadTimeout:Z
       5: return

  public void setCompression(java.lang.String);
    Code:
       0: aload_0
       1: getfield      #4                  // Field compressionConfig:Lorg/apache/coyote/CompressionConfig;
       4: aload_1
       5: invokevirtual #53                 // Method org/apache/coyote/CompressionConfig.setCompression:(Ljava/lang/String;)V
       8: return

  public java.lang.String getCompression();
    Code:
       0: aload_0
       1: getfield      #4                  // Field compressionConfig:Lorg/apache/coyote/CompressionConfig;
       4: invokevirtual #54                 // Method org/apache/coyote/CompressionConfig.getCompression:()Ljava/lang/String;
       7: areturn

  protected int getCompressionLevel();
    Code:
       0: aload_0
       1: getfield      #4                  // Field compressionConfig:Lorg/apache/coyote/CompressionConfig;
       4: invokevirtual #55                 // Method org/apache/coyote/CompressionConfig.getCompressionLevel:()I
       7: ireturn

  public java.lang.String getNoCompressionUserAgents();
    Code:
       0: aload_0
       1: getfield      #4                  // Field compressionConfig:Lorg/apache/coyote/CompressionConfig;
       4: invokevirtual #56                 // Method org/apache/coyote/CompressionConfig.getNoCompressionUserAgents:()Ljava/lang/String;
       7: areturn

  protected java.util.regex.Pattern getNoCompressionUserAgentsPattern();
    Code:
       0: aload_0
       1: getfield      #4                  // Field compressionConfig:Lorg/apache/coyote/CompressionConfig;
       4: invokevirtual #57                 // Method org/apache/coyote/CompressionConfig.getNoCompressionUserAgentsPattern:()Ljava/util/regex/Pattern;
       7: areturn

  public void setNoCompressionUserAgents(java.lang.String);
    Code:
       0: aload_0
       1: getfield      #4                  // Field compressionConfig:Lorg/apache/coyote/CompressionConfig;
       4: aload_1
       5: invokevirtual #58                 // Method org/apache/coyote/CompressionConfig.setNoCompressionUserAgents:(Ljava/lang/String;)V
       8: return

  public java.lang.String getCompressibleMimeType();
    Code:
       0: aload_0
       1: getfield      #4                  // Field compressionConfig:Lorg/apache/coyote/CompressionConfig;
       4: invokevirtual #59                 // Method org/apache/coyote/CompressionConfig.getCompressibleMimeType:()Ljava/lang/String;
       7: areturn

  public void setCompressibleMimeType(java.lang.String);
    Code:
       0: aload_0
       1: getfield      #4                  // Field compressionConfig:Lorg/apache/coyote/CompressionConfig;
       4: aload_1
       5: invokevirtual #60                 // Method org/apache/coyote/CompressionConfig.setCompressibleMimeType:(Ljava/lang/String;)V
       8: return

  public java.lang.String[] getCompressibleMimeTypes();
    Code:
       0: aload_0
       1: getfield      #4                  // Field compressionConfig:Lorg/apache/coyote/CompressionConfig;
       4: invokevirtual #61                 // Method org/apache/coyote/CompressionConfig.getCompressibleMimeTypes:()[Ljava/lang/String;
       7: areturn

  public int getCompressionMinSize();
    Code:
       0: aload_0
       1: getfield      #4                  // Field compressionConfig:Lorg/apache/coyote/CompressionConfig;
       4: invokevirtual #62                 // Method org/apache/coyote/CompressionConfig.getCompressionMinSize:()I
       7: ireturn

  public void setCompressionMinSize(int);
    Code:
       0: aload_0
       1: getfield      #4                  // Field compressionConfig:Lorg/apache/coyote/CompressionConfig;
       4: iload_1
       5: invokevirtual #63                 // Method org/apache/coyote/CompressionConfig.setCompressionMinSize:(I)V
       8: return

  public boolean getNoCompressionStrongETag();
    Code:
       0: aload_0
       1: getfield      #4                  // Field compressionConfig:Lorg/apache/coyote/CompressionConfig;
       4: invokevirtual #64                 // Method org/apache/coyote/CompressionConfig.getNoCompressionStrongETag:()Z
       7: ireturn

  public void setNoCompressionStrongETag(boolean);
    Code:
       0: aload_0
       1: getfield      #4                  // Field compressionConfig:Lorg/apache/coyote/CompressionConfig;
       4: iload_1
       5: invokevirtual #65                 // Method org/apache/coyote/CompressionConfig.setNoCompressionStrongETag:(Z)V
       8: return

  public boolean useCompression(org.apache.coyote.Request, org.apache.coyote.Response);
    Code:
       0: aload_0
       1: getfield      #4                  // Field compressionConfig:Lorg/apache/coyote/CompressionConfig;
       4: aload_1
       5: aload_2
       6: invokevirtual #66                 // Method org/apache/coyote/CompressionConfig.useCompression:(Lorg/apache/coyote/Request;Lorg/apache/coyote/Response;)Z
       9: ireturn

  public java.lang.String getRestrictedUserAgents();
    Code:
       0: aload_0
       1: getfield      #17                 // Field restrictedUserAgents:Ljava/util/regex/Pattern;
       4: ifnonnull     9
       7: aconst_null
       8: areturn
       9: aload_0
      10: getfield      #17                 // Field restrictedUserAgents:Ljava/util/regex/Pattern;
      13: invokevirtual #67                 // Method java/util/regex/Pattern.toString:()Ljava/lang/String;
      16: areturn

  protected java.util.regex.Pattern getRestrictedUserAgentsPattern();
    Code:
       0: aload_0
       1: getfield      #17                 // Field restrictedUserAgents:Ljava/util/regex/Pattern;
       4: areturn

  public void setRestrictedUserAgents(java.lang.String);
    Code:
       0: aload_1
       1: ifnull        11
       4: aload_1
       5: invokevirtual #68                 // Method java/lang/String.length:()I
       8: ifne          19
      11: aload_0
      12: aconst_null
      13: putfield      #17                 // Field restrictedUserAgents:Ljava/util/regex/Pattern;
      16: goto          27
      19: aload_0
      20: aload_1
      21: invokestatic  #69                 // Method java/util/regex/Pattern.compile:(Ljava/lang/String;)Ljava/util/regex/Pattern;
      24: putfield      #17                 // Field restrictedUserAgents:Ljava/util/regex/Pattern;
      27: return

  public java.lang.String getServer();
    Code:
       0: aload_0
       1: getfield      #70                 // Field server:Ljava/lang/String;
       4: areturn

  public void setServer(java.lang.String);
    Code:
       0: aload_0
       1: aload_1
       2: putfield      #70                 // Field server:Ljava/lang/String;
       5: return

  public boolean getServerRemoveAppProvidedValues();
    Code:
       0: aload_0
       1: getfield      #18                 // Field serverRemoveAppProvidedValues:Z
       4: ireturn

  public void setServerRemoveAppProvidedValues(boolean);
    Code:
       0: aload_0
       1: iload_1
       2: putfield      #18                 // Field serverRemoveAppProvidedValues:Z
       5: return

  public int getMaxTrailerSize();
    Code:
       0: aload_0
       1: getfield      #19                 // Field maxTrailerSize:I
       4: ireturn

  public void setMaxTrailerSize(int);
    Code:
       0: aload_0
       1: iload_1
       2: putfield      #19                 // Field maxTrailerSize:I
       5: return

  public int getMaxExtensionSize();
    Code:
       0: aload_0
       1: getfield      #20                 // Field maxExtensionSize:I
       4: ireturn

  public void setMaxExtensionSize(int);
    Code:
       0: aload_0
       1: iload_1
       2: putfield      #20                 // Field maxExtensionSize:I
       5: return

  public int getMaxSwallowSize();
    Code:
       0: aload_0
       1: getfield      #22                 // Field maxSwallowSize:I
       4: ireturn

  public void setMaxSwallowSize(int);
    Code:
       0: aload_0
       1: iload_1
       2: putfield      #22                 // Field maxSwallowSize:I
       5: return

  public boolean getSecure();
    Code:
       0: aload_0
       1: getfield      #71                 // Field secure:Z
       4: ireturn

  public void setSecure(boolean);
    Code:
       0: aload_0
       1: iload_1
       2: putfield      #71                 // Field secure:Z
       5: return

  public void setAllowedTrailerHeaders(java.lang.String);
    Code:
       0: new           #72                 // class java/util/HashSet
       3: dup
       4: aload_0
       5: getfield      #26                 // Field allowedTrailerHeaders:Ljava/util/Set;
       8: invokespecial #73                 // Method java/util/HashSet."<init>":(Ljava/util/Collection;)V
      11: astore_2
      12: aload_1
      13: ifnull        113
      16: aload_1
      17: ldc           #74                 // String ,
      19: invokevirtual #75                 // Method java/lang/String.split:(Ljava/lang/String;)[Ljava/lang/String;
      22: astore_3
      23: aload_3
      24: astore        4
      26: aload         4
      28: arraylength
      29: istore        5
      31: iconst_0
      32: istore        6
      34: iload         6
      36: iload         5
      38: if_icmpge     102
      41: aload         4
      43: iload         6
      45: aaload
      46: astore        7
      48: aload         7
      50: invokevirtual #76                 // Method java/lang/String.trim:()Ljava/lang/String;
      53: getstatic     #77                 // Field java/util/Locale.ENGLISH:Ljava/util/Locale;
      56: invokevirtual #78                 // Method java/lang/String.toLowerCase:(Ljava/util/Locale;)Ljava/lang/String;
      59: astore        8
      61: aload_2
      62: aload         8
      64: invokeinterface #79,  2           // InterfaceMethod java/util/Set.contains:(Ljava/lang/Object;)Z
      69: ifeq          84
      72: aload_2
      73: aload         8
      75: invokeinterface #80,  2           // InterfaceMethod java/util/Set.remove:(Ljava/lang/Object;)Z
      80: pop
      81: goto          96
      84: aload_0
      85: getfield      #26                 // Field allowedTrailerHeaders:Ljava/util/Set;
      88: aload         8
      90: invokeinterface #81,  2           // InterfaceMethod java/util/Set.add:(Ljava/lang/Object;)Z
      95: pop
      96: iinc          6, 1
      99: goto          34
     102: aload_0
     103: getfield      #26                 // Field allowedTrailerHeaders:Ljava/util/Set;
     106: aload_2
     107: invokeinterface #82,  2           // InterfaceMethod java/util/Set.removeAll:(Ljava/util/Collection;)Z
     112: pop
     113: return

  protected java.util.Set<java.lang.String> getAllowedTrailerHeadersInternal();
    Code:
       0: aload_0
       1: getfield      #26                 // Field allowedTrailerHeaders:Ljava/util/Set;
       4: areturn

  public java.lang.String getAllowedTrailerHeaders();
    Code:
       0: new           #27                 // class java/util/ArrayList
       3: dup
       4: aload_0
       5: getfield      #26                 // Field allowedTrailerHeaders:Ljava/util/Set;
       8: invokespecial #83                 // Method java/util/ArrayList."<init>":(Ljava/util/Collection;)V
      11: astore_1
      12: aload_1
      13: invokestatic  #84                 // Method org/apache/tomcat/util/buf/StringUtils.join:(Ljava/util/Collection;)Ljava/lang/String;
      16: areturn

  public void addAllowedTrailerHeader(java.lang.String);
    Code:
       0: aload_1
       1: ifnull        24
       4: aload_0
       5: getfield      #26                 // Field allowedTrailerHeaders:Ljava/util/Set;
       8: aload_1
       9: invokevirtual #76                 // Method java/lang/String.trim:()Ljava/lang/String;
      12: getstatic     #77                 // Field java/util/Locale.ENGLISH:Ljava/util/Locale;
      15: invokevirtual #78                 // Method java/lang/String.toLowerCase:(Ljava/util/Locale;)Ljava/lang/String;
      18: invokeinterface #81,  2           // InterfaceMethod java/util/Set.add:(Ljava/lang/Object;)Z
      23: pop
      24: return

  public void removeAllowedTrailerHeader(java.lang.String);
    Code:
       0: aload_1
       1: ifnull        24
       4: aload_0
       5: getfield      #26                 // Field allowedTrailerHeaders:Ljava/util/Set;
       8: aload_1
       9: invokevirtual #76                 // Method java/lang/String.trim:()Ljava/lang/String;
      12: getstatic     #77                 // Field java/util/Locale.ENGLISH:Ljava/util/Locale;
      15: invokevirtual #78                 // Method java/lang/String.toLowerCase:(Ljava/util/Locale;)Ljava/lang/String;
      18: invokeinterface #80,  2           // InterfaceMethod java/util/Set.remove:(Ljava/lang/Object;)Z
      23: pop
      24: return

  public void addUpgradeProtocol(org.apache.coyote.UpgradeProtocol);
    Code:
       0: aload_0
       1: getfield      #29                 // Field upgradeProtocols:Ljava/util/List;
       4: aload_1
       5: invokeinterface #85,  2           // InterfaceMethod java/util/List.add:(Ljava/lang/Object;)Z
      10: pop
      11: return

  public org.apache.coyote.UpgradeProtocol[] findUpgradeProtocols();
    Code:
       0: aload_0
       1: getfield      #29                 // Field upgradeProtocols:Ljava/util/List;
       4: iconst_0
       5: anewarray     #46                 // class org/apache/coyote/UpgradeProtocol
       8: invokeinterface #86,  2           // InterfaceMethod java/util/List.toArray:([Ljava/lang/Object;)[Ljava/lang/Object;
      13: checkcast     #87                 // class "[Lorg/apache/coyote/UpgradeProtocol;"
      16: areturn

  private void configureUpgradeProtocol(org.apache.coyote.UpgradeProtocol);
    Code:
       0: aload_1
       1: aload_0
       2: invokevirtual #41                 // Method getEndpoint:()Lorg/apache/tomcat/util/net/AbstractEndpoint;
       5: invokevirtual #88                 // Method org/apache/tomcat/util/net/AbstractEndpoint.isSSLEnabled:()Z
       8: invokeinterface #89,  2           // InterfaceMethod org/apache/coyote/UpgradeProtocol.getHttpUpgradeName:(Z)Ljava/lang/String;
      13: astore_2
      14: iconst_0
      15: istore_3
      16: aload_2
      17: ifnull        73
      20: aload_2
      21: invokevirtual #68                 // Method java/lang/String.length:()I
      24: ifle          73
      27: aload_0
      28: getfield      #32                 // Field httpUpgradeProtocols:Ljava/util/Map;
      31: aload_2
      32: aload_1
      33: invokeinterface #90,  3           // InterfaceMethod java/util/Map.put:(Ljava/lang/Object;Ljava/lang/Object;)Ljava/lang/Object;
      38: pop
      39: iconst_1
      40: istore_3
      41: aload_0
      42: invokevirtual #91                 // Method getLog:()Lorg/apache/juli/logging/Log;
      45: getstatic     #92                 // Field sm:Lorg/apache/tomcat/util/res/StringManager;
      48: ldc           #93                 // String abstractHttp11Protocol.httpUpgradeConfigured
      50: iconst_2
      51: anewarray     #94                 // class java/lang/Object
      54: dup
      55: iconst_0
      56: aload_0
      57: invokevirtual #95                 // Method getName:()Ljava/lang/String;
      60: aastore
      61: dup
      62: iconst_1
      63: aload_2
      64: aastore
      65: invokevirtual #96                 // Method org/apache/tomcat/util/res/StringManager.getString:(Ljava/lang/String;[Ljava/lang/Object;)Ljava/lang/String;
      68: invokeinterface #97,  2           // InterfaceMethod org/apache/juli/logging/Log.info:(Ljava/lang/Object;)V
      73: aload_1
      74: invokeinterface #98,  1           // InterfaceMethod org/apache/coyote/UpgradeProtocol.getAlpnName:()Ljava/lang/String;
      79: astore        4
      81: aload         4
      83: ifnull        209
      86: aload         4
      88: invokevirtual #68                 // Method java/lang/String.length:()I
      91: ifle          209
      94: aload_0
      95: invokevirtual #41                 // Method getEndpoint:()Lorg/apache/tomcat/util/net/AbstractEndpoint;
      98: invokevirtual #99                 // Method org/apache/tomcat/util/net/AbstractEndpoint.isAlpnSupported:()Z
     101: ifeq          162
     104: aload_0
     105: getfield      #33                 // Field negotiatedProtocols:Ljava/util/Map;
     108: aload         4
     110: aload_1
     111: invokeinterface #90,  3           // InterfaceMethod java/util/Map.put:(Ljava/lang/Object;Ljava/lang/Object;)Ljava/lang/Object;
     116: pop
     117: aload_0
     118: invokevirtual #41                 // Method getEndpoint:()Lorg/apache/tomcat/util/net/AbstractEndpoint;
     121: aload         4
     123: invokevirtual #100                // Method org/apache/tomcat/util/net/AbstractEndpoint.addNegotiatedProtocol:(Ljava/lang/String;)V
     126: aload_0
     127: invokevirtual #91                 // Method getLog:()Lorg/apache/juli/logging/Log;
     130: getstatic     #92                 // Field sm:Lorg/apache/tomcat/util/res/StringManager;
     133: ldc           #101                // String abstractHttp11Protocol.alpnConfigured
     135: iconst_2
     136: anewarray     #94                 // class java/lang/Object
     139: dup
     140: iconst_0
     141: aload_0
     142: invokevirtual #95                 // Method getName:()Ljava/lang/String;
     145: aastore
     146: dup
     147: iconst_1
     148: aload         4
     150: aastore
     151: invokevirtual #96                 // Method org/apache/tomcat/util/res/StringManager.getString:(Ljava/lang/String;[Ljava/lang/Object;)Ljava/lang/String;
     154: invokeinterface #97,  2           // InterfaceMethod org/apache/juli/logging/Log.info:(Ljava/lang/Object;)V
     159: goto          209
     162: iload_3
     163: ifne          209
     166: aload_0
     167: invokevirtual #91                 // Method getLog:()Lorg/apache/juli/logging/Log;
     170: getstatic     #92                 // Field sm:Lorg/apache/tomcat/util/res/StringManager;
     173: ldc           #102                // String abstractHttp11Protocol.alpnWithNoAlpn
     175: iconst_3
     176: anewarray     #94                 // class java/lang/Object
     179: dup
     180: iconst_0
     181: aload_1
     182: invokevirtual #103                // Method java/lang/Object.getClass:()Ljava/lang/Class;
     185: invokevirtual #104                // Method java/lang/Class.getName:()Ljava/lang/String;
     188: aastore
     189: dup
     190: iconst_1
     191: aload         4
     193: aastore
     194: dup
     195: iconst_2
     196: aload_0
     197: invokevirtual #95                 // Method getName:()Ljava/lang/String;
     200: aastore
     201: invokevirtual #96                 // Method org/apache/tomcat/util/res/StringManager.getString:(Ljava/lang/String;[Ljava/lang/Object;)Ljava/lang/String;
     204: invokeinterface #105,  2          // InterfaceMethod org/apache/juli/logging/Log.error:(Ljava/lang/Object;)V
     209: aload_1
     210: aload_0
     211: invokeinterface #106,  2          // InterfaceMethod org/apache/coyote/UpgradeProtocol.setHttp11Protocol:(Lorg/apache/coyote/AbstractProtocol;)V
     216: return

  public org.apache.coyote.UpgradeProtocol getNegotiatedProtocol(java.lang.String);
    Code:
       0: aload_0
       1: getfield      #33                 // Field negotiatedProtocols:Ljava/util/Map;
       4: aload_1
       5: invokeinterface #107,  2          // InterfaceMethod java/util/Map.get:(Ljava/lang/Object;)Ljava/lang/Object;
      10: checkcast     #46                 // class org/apache/coyote/UpgradeProtocol
      13: areturn

  public org.apache.coyote.UpgradeProtocol getUpgradeProtocol(java.lang.String);
    Code:
       0: aload_0
       1: getfield      #32                 // Field httpUpgradeProtocols:Ljava/util/Map;
       4: aload_1
       5: invokeinterface #107,  2          // InterfaceMethod java/util/Map.get:(Ljava/lang/Object;)Ljava/lang/Object;
      10: checkcast     #46                 // class org/apache/coyote/UpgradeProtocol
      13: areturn

  public boolean isSSLEnabled();
    Code:
       0: aload_0
       1: invokevirtual #41                 // Method getEndpoint:()Lorg/apache/tomcat/util/net/AbstractEndpoint;
       4: invokevirtual #88                 // Method org/apache/tomcat/util/net/AbstractEndpoint.isSSLEnabled:()Z
       7: ireturn

  public void setSSLEnabled(boolean);
    Code:
       0: aload_0
       1: invokevirtual #41                 // Method getEndpoint:()Lorg/apache/tomcat/util/net/AbstractEndpoint;
       4: iload_1
       5: invokevirtual #108                // Method org/apache/tomcat/util/net/AbstractEndpoint.setSSLEnabled:(Z)V
       8: return

  public boolean getUseSendfile();
    Code:
       0: aload_0
       1: invokevirtual #41                 // Method getEndpoint:()Lorg/apache/tomcat/util/net/AbstractEndpoint;
       4: invokevirtual #109                // Method org/apache/tomcat/util/net/AbstractEndpoint.getUseSendfile:()Z
       7: ireturn

  public void setUseSendfile(boolean);
    Code:
       0: aload_0
       1: invokevirtual #41                 // Method getEndpoint:()Lorg/apache/tomcat/util/net/AbstractEndpoint;
       4: iload_1
       5: invokevirtual #110                // Method org/apache/tomcat/util/net/AbstractEndpoint.setUseSendfile:(Z)V
       8: return

  public int getMaxKeepAliveRequests();
    Code:
       0: aload_0
       1: invokevirtual #41                 // Method getEndpoint:()Lorg/apache/tomcat/util/net/AbstractEndpoint;
       4: invokevirtual #111                // Method org/apache/tomcat/util/net/AbstractEndpoint.getMaxKeepAliveRequests:()I
       7: ireturn

  public void setMaxKeepAliveRequests(int);
    Code:
       0: aload_0
       1: invokevirtual #41                 // Method getEndpoint:()Lorg/apache/tomcat/util/net/AbstractEndpoint;
       4: iload_1
       5: invokevirtual #112                // Method org/apache/tomcat/util/net/AbstractEndpoint.setMaxKeepAliveRequests:(I)V
       8: return

  public java.lang.String getDefaultSSLHostConfigName();
    Code:
       0: aload_0
       1: invokevirtual #41                 // Method getEndpoint:()Lorg/apache/tomcat/util/net/AbstractEndpoint;
       4: invokevirtual #113                // Method org/apache/tomcat/util/net/AbstractEndpoint.getDefaultSSLHostConfigName:()Ljava/lang/String;
       7: areturn

  public void setDefaultSSLHostConfigName(java.lang.String);
    Code:
       0: aload_0
       1: invokevirtual #41                 // Method getEndpoint:()Lorg/apache/tomcat/util/net/AbstractEndpoint;
       4: aload_1
       5: invokevirtual #114                // Method org/apache/tomcat/util/net/AbstractEndpoint.setDefaultSSLHostConfigName:(Ljava/lang/String;)V
       8: aload_0
       9: getfield      #34                 // Field defaultSSLHostConfig:Lorg/apache/tomcat/util/net/SSLHostConfig;
      12: ifnull        23
      15: aload_0
      16: getfield      #34                 // Field defaultSSLHostConfig:Lorg/apache/tomcat/util/net/SSLHostConfig;
      19: aload_1
      20: invokevirtual #115                // Method org/apache/tomcat/util/net/SSLHostConfig.setHostName:(Ljava/lang/String;)V
      23: return

  public void addSslHostConfig(org.apache.tomcat.util.net.SSLHostConfig);
    Code:
       0: aload_0
       1: invokevirtual #41                 // Method getEndpoint:()Lorg/apache/tomcat/util/net/AbstractEndpoint;
       4: aload_1
       5: invokevirtual #116                // Method org/apache/tomcat/util/net/AbstractEndpoint.addSslHostConfig:(Lorg/apache/tomcat/util/net/SSLHostConfig;)V
       8: return

  public org.apache.tomcat.util.net.SSLHostConfig[] findSslHostConfigs();
    Code:
       0: aload_0
       1: invokevirtual #41                 // Method getEndpoint:()Lorg/apache/tomcat/util/net/AbstractEndpoint;
       4: invokevirtual #117                // Method org/apache/tomcat/util/net/AbstractEndpoint.findSslHostConfigs:()[Lorg/apache/tomcat/util/net/SSLHostConfig;
       7: areturn

  public void reloadSslHostConfigs();
    Code:
       0: aload_0
       1: invokevirtual #41                 // Method getEndpoint:()Lorg/apache/tomcat/util/net/AbstractEndpoint;
       4: invokevirtual #118                // Method org/apache/tomcat/util/net/AbstractEndpoint.reloadSslHostConfigs:()V
       7: return

  public void reloadSslHostConfig(java.lang.String);
    Code:
       0: aload_0
       1: invokevirtual #41                 // Method getEndpoint:()Lorg/apache/tomcat/util/net/AbstractEndpoint;
       4: aload_1
       5: invokevirtual #119                // Method org/apache/tomcat/util/net/AbstractEndpoint.reloadSslHostConfig:(Ljava/lang/String;)V
       8: return

  private void registerDefaultSSLHostConfig();
    Code:
       0: aload_0
       1: getfield      #34                 // Field defaultSSLHostConfig:Lorg/apache/tomcat/util/net/SSLHostConfig;
       4: ifnonnull     97
       7: aload_0
       8: invokevirtual #120                // Method findSslHostConfigs:()[Lorg/apache/tomcat/util/net/SSLHostConfig;
      11: astore_1
      12: aload_1
      13: arraylength
      14: istore_2
      15: iconst_0
      16: istore_3
      17: iload_3
      18: iload_2
      19: if_icmpge     57
      22: aload_1
      23: iload_3
      24: aaload
      25: astore        4
      27: aload_0
      28: invokevirtual #121                // Method getDefaultSSLHostConfigName:()Ljava/lang/String;
      31: aload         4
      33: invokevirtual #122                // Method org/apache/tomcat/util/net/SSLHostConfig.getHostName:()Ljava/lang/String;
      36: invokevirtual #123                // Method java/lang/String.equals:(Ljava/lang/Object;)Z
      39: ifeq          51
      42: aload_0
      43: aload         4
      45: putfield      #34                 // Field defaultSSLHostConfig:Lorg/apache/tomcat/util/net/SSLHostConfig;
      48: goto          57
      51: iinc          3, 1
      54: goto          17
      57: aload_0
      58: getfield      #34                 // Field defaultSSLHostConfig:Lorg/apache/tomcat/util/net/SSLHostConfig;
      61: ifnonnull     97
      64: aload_0
      65: new           #124                // class org/apache/tomcat/util/net/SSLHostConfig
      68: dup
      69: invokespecial #125                // Method org/apache/tomcat/util/net/SSLHostConfig."<init>":()V
      72: putfield      #34                 // Field defaultSSLHostConfig:Lorg/apache/tomcat/util/net/SSLHostConfig;
      75: aload_0
      76: getfield      #34                 // Field defaultSSLHostConfig:Lorg/apache/tomcat/util/net/SSLHostConfig;
      79: aload_0
      80: invokevirtual #121                // Method getDefaultSSLHostConfigName:()Ljava/lang/String;
      83: invokevirtual #115                // Method org/apache/tomcat/util/net/SSLHostConfig.setHostName:(Ljava/lang/String;)V
      86: aload_0
      87: invokevirtual #41                 // Method getEndpoint:()Lorg/apache/tomcat/util/net/AbstractEndpoint;
      90: aload_0
      91: getfield      #34                 // Field defaultSSLHostConfig:Lorg/apache/tomcat/util/net/SSLHostConfig;
      94: invokevirtual #116                // Method org/apache/tomcat/util/net/AbstractEndpoint.addSslHostConfig:(Lorg/apache/tomcat/util/net/SSLHostConfig;)V
      97: return

  public java.lang.String getSslEnabledProtocols();
    Code:
       0: aload_0
       1: invokespecial #126                // Method registerDefaultSSLHostConfig:()V
       4: aload_0
       5: getfield      #34                 // Field defaultSSLHostConfig:Lorg/apache/tomcat/util/net/SSLHostConfig;
       8: invokevirtual #127                // Method org/apache/tomcat/util/net/SSLHostConfig.getEnabledProtocols:()[Ljava/lang/String;
      11: invokestatic  #128                // Method org/apache/tomcat/util/buf/StringUtils.join:([Ljava/lang/String;)Ljava/lang/String;
      14: areturn

  public void setSslEnabledProtocols(java.lang.String);
    Code:
       0: aload_0
       1: invokespecial #126                // Method registerDefaultSSLHostConfig:()V
       4: aload_0
       5: getfield      #34                 // Field defaultSSLHostConfig:Lorg/apache/tomcat/util/net/SSLHostConfig;
       8: aload_1
       9: invokevirtual #129                // Method org/apache/tomcat/util/net/SSLHostConfig.setProtocols:(Ljava/lang/String;)V
      12: return

  public java.lang.String getSSLProtocol();
    Code:
       0: aload_0
       1: invokespecial #126                // Method registerDefaultSSLHostConfig:()V
       4: aload_0
       5: getfield      #34                 // Field defaultSSLHostConfig:Lorg/apache/tomcat/util/net/SSLHostConfig;
       8: invokevirtual #127                // Method org/apache/tomcat/util/net/SSLHostConfig.getEnabledProtocols:()[Ljava/lang/String;
      11: invokestatic  #128                // Method org/apache/tomcat/util/buf/StringUtils.join:([Ljava/lang/String;)Ljava/lang/String;
      14: areturn

  public void setSSLProtocol(java.lang.String);
    Code:
       0: aload_0
       1: invokespecial #126                // Method registerDefaultSSLHostConfig:()V
       4: aload_0
       5: getfield      #34                 // Field defaultSSLHostConfig:Lorg/apache/tomcat/util/net/SSLHostConfig;
       8: aload_1
       9: invokevirtual #129                // Method org/apache/tomcat/util/net/SSLHostConfig.setProtocols:(Ljava/lang/String;)V
      12: return

  public java.lang.String getKeystoreFile();
    Code:
       0: aload_0
       1: invokespecial #126                // Method registerDefaultSSLHostConfig:()V
       4: aload_0
       5: getfield      #34                 // Field defaultSSLHostConfig:Lorg/apache/tomcat/util/net/SSLHostConfig;
       8: invokevirtual #130                // Method org/apache/tomcat/util/net/SSLHostConfig.getCertificateKeystoreFile:()Ljava/lang/String;
      11: areturn

  public void setKeystoreFile(java.lang.String);
    Code:
       0: aload_0
       1: invokespecial #126                // Method registerDefaultSSLHostConfig:()V
       4: aload_0
       5: getfield      #34                 // Field defaultSSLHostConfig:Lorg/apache/tomcat/util/net/SSLHostConfig;
       8: aload_1
       9: invokevirtual #131                // Method org/apache/tomcat/util/net/SSLHostConfig.setCertificateKeystoreFile:(Ljava/lang/String;)V
      12: return

  public java.lang.String getSSLCertificateChainFile();
    Code:
       0: aload_0
       1: invokespecial #126                // Method registerDefaultSSLHostConfig:()V
       4: aload_0
       5: getfield      #34                 // Field defaultSSLHostConfig:Lorg/apache/tomcat/util/net/SSLHostConfig;
       8: invokevirtual #132                // Method org/apache/tomcat/util/net/SSLHostConfig.getCertificateChainFile:()Ljava/lang/String;
      11: areturn

  public void setSSLCertificateChainFile(java.lang.String);
    Code:
       0: aload_0
       1: invokespecial #126                // Method registerDefaultSSLHostConfig:()V
       4: aload_0
       5: getfield      #34                 // Field defaultSSLHostConfig:Lorg/apache/tomcat/util/net/SSLHostConfig;
       8: aload_1
       9: invokevirtual #133                // Method org/apache/tomcat/util/net/SSLHostConfig.setCertificateChainFile:(Ljava/lang/String;)V
      12: return

  public java.lang.String getSSLCertificateFile();
    Code:
       0: aload_0
       1: invokespecial #126                // Method registerDefaultSSLHostConfig:()V
       4: aload_0
       5: getfield      #34                 // Field defaultSSLHostConfig:Lorg/apache/tomcat/util/net/SSLHostConfig;
       8: invokevirtual #134                // Method org/apache/tomcat/util/net/SSLHostConfig.getCertificateFile:()Ljava/lang/String;
      11: areturn

  public void setSSLCertificateFile(java.lang.String);
    Code:
       0: aload_0
       1: invokespecial #126                // Method registerDefaultSSLHostConfig:()V
       4: aload_0
       5: getfield      #34                 // Field defaultSSLHostConfig:Lorg/apache/tomcat/util/net/SSLHostConfig;
       8: aload_1
       9: invokevirtual #135                // Method org/apache/tomcat/util/net/SSLHostConfig.setCertificateFile:(Ljava/lang/String;)V
      12: return

  public java.lang.String getSSLCertificateKeyFile();
    Code:
       0: aload_0
       1: invokespecial #126                // Method registerDefaultSSLHostConfig:()V
       4: aload_0
       5: getfield      #34                 // Field defaultSSLHostConfig:Lorg/apache/tomcat/util/net/SSLHostConfig;
       8: invokevirtual #136                // Method org/apache/tomcat/util/net/SSLHostConfig.getCertificateKeyFile:()Ljava/lang/String;
      11: areturn

  public void setSSLCertificateKeyFile(java.lang.String);
    Code:
       0: aload_0
       1: invokespecial #126                // Method registerDefaultSSLHostConfig:()V
       4: aload_0
       5: getfield      #34                 // Field defaultSSLHostConfig:Lorg/apache/tomcat/util/net/SSLHostConfig;
       8: aload_1
       9: invokevirtual #137                // Method org/apache/tomcat/util/net/SSLHostConfig.setCertificateKeyFile:(Ljava/lang/String;)V
      12: return

  public java.lang.String getAlgorithm();
    Code:
       0: aload_0
       1: invokespecial #126                // Method registerDefaultSSLHostConfig:()V
       4: aload_0
       5: getfield      #34                 // Field defaultSSLHostConfig:Lorg/apache/tomcat/util/net/SSLHostConfig;
       8: invokevirtual #138                // Method org/apache/tomcat/util/net/SSLHostConfig.getKeyManagerAlgorithm:()Ljava/lang/String;
      11: areturn

  public void setAlgorithm(java.lang.String);
    Code:
       0: aload_0
       1: invokespecial #126                // Method registerDefaultSSLHostConfig:()V
       4: aload_0
       5: getfield      #34                 // Field defaultSSLHostConfig:Lorg/apache/tomcat/util/net/SSLHostConfig;
       8: aload_1
       9: invokevirtual #139                // Method org/apache/tomcat/util/net/SSLHostConfig.setKeyManagerAlgorithm:(Ljava/lang/String;)V
      12: return

  public java.lang.String getClientAuth();
    Code:
       0: aload_0
       1: invokespecial #126                // Method registerDefaultSSLHostConfig:()V
       4: aload_0
       5: getfield      #34                 // Field defaultSSLHostConfig:Lorg/apache/tomcat/util/net/SSLHostConfig;
       8: invokevirtual #140                // Method org/apache/tomcat/util/net/SSLHostConfig.getCertificateVerificationAsString:()Ljava/lang/String;
      11: areturn

  public void setClientAuth(java.lang.String);
    Code:
       0: aload_0
       1: invokespecial #126                // Method registerDefaultSSLHostConfig:()V
       4: aload_0
       5: getfield      #34                 // Field defaultSSLHostConfig:Lorg/apache/tomcat/util/net/SSLHostConfig;
       8: aload_1
       9: invokevirtual #141                // Method org/apache/tomcat/util/net/SSLHostConfig.setCertificateVerification:(Ljava/lang/String;)V
      12: return

  public java.lang.String getSSLVerifyClient();
    Code:
       0: aload_0
       1: invokespecial #126                // Method registerDefaultSSLHostConfig:()V
       4: aload_0
       5: getfield      #34                 // Field defaultSSLHostConfig:Lorg/apache/tomcat/util/net/SSLHostConfig;
       8: invokevirtual #140                // Method org/apache/tomcat/util/net/SSLHostConfig.getCertificateVerificationAsString:()Ljava/lang/String;
      11: areturn

  public void setSSLVerifyClient(java.lang.String);
    Code:
       0: aload_0
       1: invokespecial #126                // Method registerDefaultSSLHostConfig:()V
       4: aload_0
       5: getfield      #34                 // Field defaultSSLHostConfig:Lorg/apache/tomcat/util/net/SSLHostConfig;
       8: aload_1
       9: invokevirtual #141                // Method org/apache/tomcat/util/net/SSLHostConfig.setCertificateVerification:(Ljava/lang/String;)V
      12: return

  public int getTrustMaxCertLength();
    Code:
       0: aload_0
       1: invokespecial #126                // Method registerDefaultSSLHostConfig:()V
       4: aload_0
       5: getfield      #34                 // Field defaultSSLHostConfig:Lorg/apache/tomcat/util/net/SSLHostConfig;
       8: invokevirtual #142                // Method org/apache/tomcat/util/net/SSLHostConfig.getCertificateVerificationDepth:()I
      11: ireturn

  public void setTrustMaxCertLength(int);
    Code:
       0: aload_0
       1: invokespecial #126                // Method registerDefaultSSLHostConfig:()V
       4: aload_0
       5: getfield      #34                 // Field defaultSSLHostConfig:Lorg/apache/tomcat/util/net/SSLHostConfig;
       8: iload_1
       9: invokevirtual #143                // Method org/apache/tomcat/util/net/SSLHostConfig.setCertificateVerificationDepth:(I)V
      12: return

  public int getSSLVerifyDepth();
    Code:
       0: aload_0
       1: invokespecial #126                // Method registerDefaultSSLHostConfig:()V
       4: aload_0
       5: getfield      #34                 // Field defaultSSLHostConfig:Lorg/apache/tomcat/util/net/SSLHostConfig;
       8: invokevirtual #142                // Method org/apache/tomcat/util/net/SSLHostConfig.getCertificateVerificationDepth:()I
      11: ireturn

  public void setSSLVerifyDepth(int);
    Code:
       0: aload_0
       1: invokespecial #126                // Method registerDefaultSSLHostConfig:()V
       4: aload_0
       5: getfield      #34                 // Field defaultSSLHostConfig:Lorg/apache/tomcat/util/net/SSLHostConfig;
       8: iload_1
       9: invokevirtual #143                // Method org/apache/tomcat/util/net/SSLHostConfig.setCertificateVerificationDepth:(I)V
      12: return

  public boolean getUseServerCipherSuitesOrder();
    Code:
       0: aload_0
       1: invokespecial #126                // Method registerDefaultSSLHostConfig:()V
       4: aload_0
       5: getfield      #34                 // Field defaultSSLHostConfig:Lorg/apache/tomcat/util/net/SSLHostConfig;
       8: invokevirtual #144                // Method org/apache/tomcat/util/net/SSLHostConfig.getHonorCipherOrder:()Z
      11: ireturn

  public void setUseServerCipherSuitesOrder(boolean);
    Code:
       0: aload_0
       1: invokespecial #126                // Method registerDefaultSSLHostConfig:()V
       4: aload_0
       5: getfield      #34                 // Field defaultSSLHostConfig:Lorg/apache/tomcat/util/net/SSLHostConfig;
       8: iload_1
       9: invokevirtual #145                // Method org/apache/tomcat/util/net/SSLHostConfig.setHonorCipherOrder:(Z)V
      12: return

  public boolean getSSLHonorCipherOrder();
    Code:
       0: aload_0
       1: invokespecial #126                // Method registerDefaultSSLHostConfig:()V
       4: aload_0
       5: getfield      #34                 // Field defaultSSLHostConfig:Lorg/apache/tomcat/util/net/SSLHostConfig;
       8: invokevirtual #144                // Method org/apache/tomcat/util/net/SSLHostConfig.getHonorCipherOrder:()Z
      11: ireturn

  public void setSSLHonorCipherOrder(boolean);
    Code:
       0: aload_0
       1: invokespecial #126                // Method registerDefaultSSLHostConfig:()V
       4: aload_0
       5: getfield      #34                 // Field defaultSSLHostConfig:Lorg/apache/tomcat/util/net/SSLHostConfig;
       8: iload_1
       9: invokevirtual #145                // Method org/apache/tomcat/util/net/SSLHostConfig.setHonorCipherOrder:(Z)V
      12: return

  public java.lang.String getCiphers();
    Code:
       0: aload_0
       1: invokespecial #126                // Method registerDefaultSSLHostConfig:()V
       4: aload_0
       5: getfield      #34                 // Field defaultSSLHostConfig:Lorg/apache/tomcat/util/net/SSLHostConfig;
       8: invokevirtual #146                // Method org/apache/tomcat/util/net/SSLHostConfig.getCiphers:()Ljava/lang/String;
      11: areturn

  public void setCiphers(java.lang.String);
    Code:
       0: aload_0
       1: invokespecial #126                // Method registerDefaultSSLHostConfig:()V
       4: aload_0
       5: getfield      #34                 // Field defaultSSLHostConfig:Lorg/apache/tomcat/util/net/SSLHostConfig;
       8: aload_1
       9: invokevirtual #147                // Method org/apache/tomcat/util/net/SSLHostConfig.setCiphers:(Ljava/lang/String;)V
      12: return

  public java.lang.String getSSLCipherSuite();
    Code:
       0: aload_0
       1: invokespecial #126                // Method registerDefaultSSLHostConfig:()V
       4: aload_0
       5: getfield      #34                 // Field defaultSSLHostConfig:Lorg/apache/tomcat/util/net/SSLHostConfig;
       8: invokevirtual #146                // Method org/apache/tomcat/util/net/SSLHostConfig.getCiphers:()Ljava/lang/String;
      11: areturn

  public void setSSLCipherSuite(java.lang.String);
    Code:
       0: aload_0
       1: invokespecial #126                // Method registerDefaultSSLHostConfig:()V
       4: aload_0
       5: getfield      #34                 // Field defaultSSLHostConfig:Lorg/apache/tomcat/util/net/SSLHostConfig;
       8: aload_1
       9: invokevirtual #147                // Method org/apache/tomcat/util/net/SSLHostConfig.setCiphers:(Ljava/lang/String;)V
      12: return

  public java.lang.String getKeystorePass();
    Code:
       0: aload_0
       1: invokespecial #126                // Method registerDefaultSSLHostConfig:()V
       4: aload_0
       5: getfield      #34                 // Field defaultSSLHostConfig:Lorg/apache/tomcat/util/net/SSLHostConfig;
       8: invokevirtual #148                // Method org/apache/tomcat/util/net/SSLHostConfig.getCertificateKeystorePassword:()Ljava/lang/String;
      11: areturn

  public void setKeystorePass(java.lang.String);
    Code:
       0: aload_0
       1: invokespecial #126                // Method registerDefaultSSLHostConfig:()V
       4: aload_0
       5: getfield      #34                 // Field defaultSSLHostConfig:Lorg/apache/tomcat/util/net/SSLHostConfig;
       8: aload_1
       9: invokevirtual #149                // Method org/apache/tomcat/util/net/SSLHostConfig.setCertificateKeystorePassword:(Ljava/lang/String;)V
      12: return

  public java.lang.String getKeyPass();
    Code:
       0: aload_0
       1: invokespecial #126                // Method registerDefaultSSLHostConfig:()V
       4: aload_0
       5: getfield      #34                 // Field defaultSSLHostConfig:Lorg/apache/tomcat/util/net/SSLHostConfig;
       8: invokevirtual #150                // Method org/apache/tomcat/util/net/SSLHostConfig.getCertificateKeyPassword:()Ljava/lang/String;
      11: areturn

  public void setKeyPass(java.lang.String);
    Code:
       0: aload_0
       1: invokespecial #126                // Method registerDefaultSSLHostConfig:()V
       4: aload_0
       5: getfield      #34                 // Field defaultSSLHostConfig:Lorg/apache/tomcat/util/net/SSLHostConfig;
       8: aload_1
       9: invokevirtual #151                // Method org/apache/tomcat/util/net/SSLHostConfig.setCertificateKeyPassword:(Ljava/lang/String;)V
      12: return

  public java.lang.String getSSLPassword();
    Code:
       0: aload_0
       1: invokespecial #126                // Method registerDefaultSSLHostConfig:()V
       4: aload_0
       5: getfield      #34                 // Field defaultSSLHostConfig:Lorg/apache/tomcat/util/net/SSLHostConfig;
       8: invokevirtual #150                // Method org/apache/tomcat/util/net/SSLHostConfig.getCertificateKeyPassword:()Ljava/lang/String;
      11: areturn

  public void setSSLPassword(java.lang.String);
    Code:
       0: aload_0
       1: invokespecial #126                // Method registerDefaultSSLHostConfig:()V
       4: aload_0
       5: getfield      #34                 // Field defaultSSLHostConfig:Lorg/apache/tomcat/util/net/SSLHostConfig;
       8: aload_1
       9: invokevirtual #151                // Method org/apache/tomcat/util/net/SSLHostConfig.setCertificateKeyPassword:(Ljava/lang/String;)V
      12: return

  public java.lang.String getCrlFile();
    Code:
       0: aload_0
       1: invokespecial #126                // Method registerDefaultSSLHostConfig:()V
       4: aload_0
       5: getfield      #34                 // Field defaultSSLHostConfig:Lorg/apache/tomcat/util/net/SSLHostConfig;
       8: invokevirtual #152                // Method org/apache/tomcat/util/net/SSLHostConfig.getCertificateRevocationListFile:()Ljava/lang/String;
      11: areturn

  public void setCrlFile(java.lang.String);
    Code:
       0: aload_0
       1: invokespecial #126                // Method registerDefaultSSLHostConfig:()V
       4: aload_0
       5: getfield      #34                 // Field defaultSSLHostConfig:Lorg/apache/tomcat/util/net/SSLHostConfig;
       8: aload_1
       9: invokevirtual #153                // Method org/apache/tomcat/util/net/SSLHostConfig.setCertificateRevocationListFile:(Ljava/lang/String;)V
      12: return

  public java.lang.String getSSLCARevocationFile();
    Code:
       0: aload_0
       1: invokespecial #126                // Method registerDefaultSSLHostConfig:()V
       4: aload_0
       5: getfield      #34                 // Field defaultSSLHostConfig:Lorg/apache/tomcat/util/net/SSLHostConfig;
       8: invokevirtual #152                // Method org/apache/tomcat/util/net/SSLHostConfig.getCertificateRevocationListFile:()Ljava/lang/String;
      11: areturn

  public void setSSLCARevocationFile(java.lang.String);
    Code:
       0: aload_0
       1: invokespecial #126                // Method registerDefaultSSLHostConfig:()V
       4: aload_0
       5: getfield      #34                 // Field defaultSSLHostConfig:Lorg/apache/tomcat/util/net/SSLHostConfig;
       8: aload_1
       9: invokevirtual #153                // Method org/apache/tomcat/util/net/SSLHostConfig.setCertificateRevocationListFile:(Ljava/lang/String;)V
      12: return

  public java.lang.String getSSLCARevocationPath();
    Code:
       0: aload_0
       1: invokespecial #126                // Method registerDefaultSSLHostConfig:()V
       4: aload_0
       5: getfield      #34                 // Field defaultSSLHostConfig:Lorg/apache/tomcat/util/net/SSLHostConfig;
       8: invokevirtual #154                // Method org/apache/tomcat/util/net/SSLHostConfig.getCertificateRevocationListPath:()Ljava/lang/String;
      11: areturn

  public void setSSLCARevocationPath(java.lang.String);
    Code:
       0: aload_0
       1: invokespecial #126                // Method registerDefaultSSLHostConfig:()V
       4: aload_0
       5: getfield      #34                 // Field defaultSSLHostConfig:Lorg/apache/tomcat/util/net/SSLHostConfig;
       8: aload_1
       9: invokevirtual #155                // Method org/apache/tomcat/util/net/SSLHostConfig.setCertificateRevocationListPath:(Ljava/lang/String;)V
      12: return

  public java.lang.String getKeystoreType();
    Code:
       0: aload_0
       1: invokespecial #126                // Method registerDefaultSSLHostConfig:()V
       4: aload_0
       5: getfield      #34                 // Field defaultSSLHostConfig:Lorg/apache/tomcat/util/net/SSLHostConfig;
       8: invokevirtual #156                // Method org/apache/tomcat/util/net/SSLHostConfig.getCertificateKeystoreType:()Ljava/lang/String;
      11: areturn

  public void setKeystoreType(java.lang.String);
    Code:
       0: aload_0
       1: invokespecial #126                // Method registerDefaultSSLHostConfig:()V
       4: aload_0
       5: getfield      #34                 // Field defaultSSLHostConfig:Lorg/apache/tomcat/util/net/SSLHostConfig;
       8: aload_1
       9: invokevirtual #157                // Method org/apache/tomcat/util/net/SSLHostConfig.setCertificateKeystoreType:(Ljava/lang/String;)V
      12: return

  public java.lang.String getKeystoreProvider();
    Code:
       0: aload_0
       1: invokespecial #126                // Method registerDefaultSSLHostConfig:()V
       4: aload_0
       5: getfield      #34                 // Field defaultSSLHostConfig:Lorg/apache/tomcat/util/net/SSLHostConfig;
       8: invokevirtual #158                // Method org/apache/tomcat/util/net/SSLHostConfig.getCertificateKeystoreProvider:()Ljava/lang/String;
      11: areturn

  public void setKeystoreProvider(java.lang.String);
    Code:
       0: aload_0
       1: invokespecial #126                // Method registerDefaultSSLHostConfig:()V
       4: aload_0
       5: getfield      #34                 // Field defaultSSLHostConfig:Lorg/apache/tomcat/util/net/SSLHostConfig;
       8: aload_1
       9: invokevirtual #159                // Method org/apache/tomcat/util/net/SSLHostConfig.setCertificateKeystoreProvider:(Ljava/lang/String;)V
      12: return

  public java.lang.String getKeyAlias();
    Code:
       0: aload_0
       1: invokespecial #126                // Method registerDefaultSSLHostConfig:()V
       4: aload_0
       5: getfield      #34                 // Field defaultSSLHostConfig:Lorg/apache/tomcat/util/net/SSLHostConfig;
       8: invokevirtual #160                // Method org/apache/tomcat/util/net/SSLHostConfig.getCertificateKeyAlias:()Ljava/lang/String;
      11: areturn

  public void setKeyAlias(java.lang.String);
    Code:
       0: aload_0
       1: invokespecial #126                // Method registerDefaultSSLHostConfig:()V
       4: aload_0
       5: getfield      #34                 // Field defaultSSLHostConfig:Lorg/apache/tomcat/util/net/SSLHostConfig;
       8: aload_1
       9: invokevirtual #161                // Method org/apache/tomcat/util/net/SSLHostConfig.setCertificateKeyAlias:(Ljava/lang/String;)V
      12: return

  public java.lang.String getTruststoreAlgorithm();
    Code:
       0: aload_0
       1: invokespecial #126                // Method registerDefaultSSLHostConfig:()V
       4: aload_0
       5: getfield      #34                 // Field defaultSSLHostConfig:Lorg/apache/tomcat/util/net/SSLHostConfig;
       8: invokevirtual #162                // Method org/apache/tomcat/util/net/SSLHostConfig.getTruststoreAlgorithm:()Ljava/lang/String;
      11: areturn

  public void setTruststoreAlgorithm(java.lang.String);
    Code:
       0: aload_0
       1: invokespecial #126                // Method registerDefaultSSLHostConfig:()V
       4: aload_0
       5: getfield      #34                 // Field defaultSSLHostConfig:Lorg/apache/tomcat/util/net/SSLHostConfig;
       8: aload_1
       9: invokevirtual #163                // Method org/apache/tomcat/util/net/SSLHostConfig.setTruststoreAlgorithm:(Ljava/lang/String;)V
      12: return

  public java.lang.String getTruststoreFile();
    Code:
       0: aload_0
       1: invokespecial #126                // Method registerDefaultSSLHostConfig:()V
       4: aload_0
       5: getfield      #34                 // Field defaultSSLHostConfig:Lorg/apache/tomcat/util/net/SSLHostConfig;
       8: invokevirtual #164                // Method org/apache/tomcat/util/net/SSLHostConfig.getTruststoreFile:()Ljava/lang/String;
      11: areturn

  public void setTruststoreFile(java.lang.String);
    Code:
       0: aload_0
       1: invokespecial #126                // Method registerDefaultSSLHostConfig:()V
       4: aload_0
       5: getfield      #34                 // Field defaultSSLHostConfig:Lorg/apache/tomcat/util/net/SSLHostConfig;
       8: aload_1
       9: invokevirtual #165                // Method org/apache/tomcat/util/net/SSLHostConfig.setTruststoreFile:(Ljava/lang/String;)V
      12: return

  public java.lang.String getTruststorePass();
    Code:
       0: aload_0
       1: invokespecial #126                // Method registerDefaultSSLHostConfig:()V
       4: aload_0
       5: getfield      #34                 // Field defaultSSLHostConfig:Lorg/apache/tomcat/util/net/SSLHostConfig;
       8: invokevirtual #166                // Method org/apache/tomcat/util/net/SSLHostConfig.getTruststorePassword:()Ljava/lang/String;
      11: areturn

  public void setTruststorePass(java.lang.String);
    Code:
       0: aload_0
       1: invokespecial #126                // Method registerDefaultSSLHostConfig:()V
       4: aload_0
       5: getfield      #34                 // Field defaultSSLHostConfig:Lorg/apache/tomcat/util/net/SSLHostConfig;
       8: aload_1
       9: invokevirtual #167                // Method org/apache/tomcat/util/net/SSLHostConfig.setTruststorePassword:(Ljava/lang/String;)V
      12: return

  public java.lang.String getTruststoreType();
    Code:
       0: aload_0
       1: invokespecial #126                // Method registerDefaultSSLHostConfig:()V
       4: aload_0
       5: getfield      #34                 // Field defaultSSLHostConfig:Lorg/apache/tomcat/util/net/SSLHostConfig;
       8: invokevirtual #168                // Method org/apache/tomcat/util/net/SSLHostConfig.getTruststoreType:()Ljava/lang/String;
      11: areturn

  public void setTruststoreType(java.lang.String);
    Code:
       0: aload_0
       1: invokespecial #126                // Method registerDefaultSSLHostConfig:()V
       4: aload_0
       5: getfield      #34                 // Field defaultSSLHostConfig:Lorg/apache/tomcat/util/net/SSLHostConfig;
       8: aload_1
       9: invokevirtual #169                // Method org/apache/tomcat/util/net/SSLHostConfig.setTruststoreType:(Ljava/lang/String;)V
      12: return

  public java.lang.String getTruststoreProvider();
    Code:
       0: aload_0
       1: invokespecial #126                // Method registerDefaultSSLHostConfig:()V
       4: aload_0
       5: getfield      #34                 // Field defaultSSLHostConfig:Lorg/apache/tomcat/util/net/SSLHostConfig;
       8: invokevirtual #170                // Method org/apache/tomcat/util/net/SSLHostConfig.getTruststoreProvider:()Ljava/lang/String;
      11: areturn

  public void setTruststoreProvider(java.lang.String);
    Code:
       0: aload_0
       1: invokespecial #126                // Method registerDefaultSSLHostConfig:()V
       4: aload_0
       5: getfield      #34                 // Field defaultSSLHostConfig:Lorg/apache/tomcat/util/net/SSLHostConfig;
       8: aload_1
       9: invokevirtual #171                // Method org/apache/tomcat/util/net/SSLHostConfig.setTruststoreProvider:(Ljava/lang/String;)V
      12: return

  public java.lang.String getSslProtocol();
    Code:
       0: aload_0
       1: invokespecial #126                // Method registerDefaultSSLHostConfig:()V
       4: aload_0
       5: getfield      #34                 // Field defaultSSLHostConfig:Lorg/apache/tomcat/util/net/SSLHostConfig;
       8: invokevirtual #172                // Method org/apache/tomcat/util/net/SSLHostConfig.getSslProtocol:()Ljava/lang/String;
      11: areturn

  public void setSslProtocol(java.lang.String);
    Code:
       0: aload_0
       1: invokespecial #126                // Method registerDefaultSSLHostConfig:()V
       4: aload_0
       5: getfield      #34                 // Field defaultSSLHostConfig:Lorg/apache/tomcat/util/net/SSLHostConfig;
       8: aload_1
       9: invokevirtual #173                // Method org/apache/tomcat/util/net/SSLHostConfig.setSslProtocol:(Ljava/lang/String;)V
      12: return

  public int getSessionCacheSize();
    Code:
       0: aload_0
       1: invokespecial #126                // Method registerDefaultSSLHostConfig:()V
       4: aload_0
       5: getfield      #34                 // Field defaultSSLHostConfig:Lorg/apache/tomcat/util/net/SSLHostConfig;
       8: invokevirtual #174                // Method org/apache/tomcat/util/net/SSLHostConfig.getSessionCacheSize:()I
      11: ireturn

  public void setSessionCacheSize(int);
    Code:
       0: aload_0
       1: invokespecial #126                // Method registerDefaultSSLHostConfig:()V
       4: aload_0
       5: getfield      #34                 // Field defaultSSLHostConfig:Lorg/apache/tomcat/util/net/SSLHostConfig;
       8: iload_1
       9: invokevirtual #175                // Method org/apache/tomcat/util/net/SSLHostConfig.setSessionCacheSize:(I)V
      12: return

  public int getSessionTimeout();
    Code:
       0: aload_0
       1: invokespecial #126                // Method registerDefaultSSLHostConfig:()V
       4: aload_0
       5: getfield      #34                 // Field defaultSSLHostConfig:Lorg/apache/tomcat/util/net/SSLHostConfig;
       8: invokevirtual #176                // Method org/apache/tomcat/util/net/SSLHostConfig.getSessionTimeout:()I
      11: ireturn

  public void setSessionTimeout(int);
    Code:
       0: aload_0
       1: invokespecial #126                // Method registerDefaultSSLHostConfig:()V
       4: aload_0
       5: getfield      #34                 // Field defaultSSLHostConfig:Lorg/apache/tomcat/util/net/SSLHostConfig;
       8: iload_1
       9: invokevirtual #177                // Method org/apache/tomcat/util/net/SSLHostConfig.setSessionTimeout:(I)V
      12: return

  public java.lang.String getSSLCACertificatePath();
    Code:
       0: aload_0
       1: invokespecial #126                // Method registerDefaultSSLHostConfig:()V
       4: aload_0
       5: getfield      #34                 // Field defaultSSLHostConfig:Lorg/apache/tomcat/util/net/SSLHostConfig;
       8: invokevirtual #178                // Method org/apache/tomcat/util/net/SSLHostConfig.getCaCertificatePath:()Ljava/lang/String;
      11: areturn

  public void setSSLCACertificatePath(java.lang.String);
    Code:
       0: aload_0
       1: invokespecial #126                // Method registerDefaultSSLHostConfig:()V
       4: aload_0
       5: getfield      #34                 // Field defaultSSLHostConfig:Lorg/apache/tomcat/util/net/SSLHostConfig;
       8: aload_1
       9: invokevirtual #179                // Method org/apache/tomcat/util/net/SSLHostConfig.setCaCertificatePath:(Ljava/lang/String;)V
      12: return

  public java.lang.String getSSLCACertificateFile();
    Code:
       0: aload_0
       1: invokespecial #126                // Method registerDefaultSSLHostConfig:()V
       4: aload_0
       5: getfield      #34                 // Field defaultSSLHostConfig:Lorg/apache/tomcat/util/net/SSLHostConfig;
       8: invokevirtual #180                // Method org/apache/tomcat/util/net/SSLHostConfig.getCaCertificateFile:()Ljava/lang/String;
      11: areturn

  public void setSSLCACertificateFile(java.lang.String);
    Code:
       0: aload_0
       1: invokespecial #126                // Method registerDefaultSSLHostConfig:()V
       4: aload_0
       5: getfield      #34                 // Field defaultSSLHostConfig:Lorg/apache/tomcat/util/net/SSLHostConfig;
       8: aload_1
       9: invokevirtual #181                // Method org/apache/tomcat/util/net/SSLHostConfig.setCaCertificateFile:(Ljava/lang/String;)V
      12: return

  public boolean getSSLDisableCompression();
    Code:
       0: aload_0
       1: invokespecial #126                // Method registerDefaultSSLHostConfig:()V
       4: aload_0
       5: getfield      #34                 // Field defaultSSLHostConfig:Lorg/apache/tomcat/util/net/SSLHostConfig;
       8: invokevirtual #182                // Method org/apache/tomcat/util/net/SSLHostConfig.getDisableCompression:()Z
      11: ireturn

  public void setSSLDisableCompression(boolean);
    Code:
       0: aload_0
       1: invokespecial #126                // Method registerDefaultSSLHostConfig:()V
       4: aload_0
       5: getfield      #34                 // Field defaultSSLHostConfig:Lorg/apache/tomcat/util/net/SSLHostConfig;
       8: iload_1
       9: invokevirtual #183                // Method org/apache/tomcat/util/net/SSLHostConfig.setDisableCompression:(Z)V
      12: return

  public boolean getSSLDisableSessionTickets();
    Code:
       0: aload_0
       1: invokespecial #126                // Method registerDefaultSSLHostConfig:()V
       4: aload_0
       5: getfield      #34                 // Field defaultSSLHostConfig:Lorg/apache/tomcat/util/net/SSLHostConfig;
       8: invokevirtual #184                // Method org/apache/tomcat/util/net/SSLHostConfig.getDisableSessionTickets:()Z
      11: ireturn

  public void setSSLDisableSessionTickets(boolean);
    Code:
       0: aload_0
       1: invokespecial #126                // Method registerDefaultSSLHostConfig:()V
       4: aload_0
       5: getfield      #34                 // Field defaultSSLHostConfig:Lorg/apache/tomcat/util/net/SSLHostConfig;
       8: iload_1
       9: invokevirtual #185                // Method org/apache/tomcat/util/net/SSLHostConfig.setDisableSessionTickets:(Z)V
      12: return

  public java.lang.String getTrustManagerClassName();
    Code:
       0: aload_0
       1: invokespecial #126                // Method registerDefaultSSLHostConfig:()V
       4: aload_0
       5: getfield      #34                 // Field defaultSSLHostConfig:Lorg/apache/tomcat/util/net/SSLHostConfig;
       8: invokevirtual #186                // Method org/apache/tomcat/util/net/SSLHostConfig.getTrustManagerClassName:()Ljava/lang/String;
      11: areturn

  public void setTrustManagerClassName(java.lang.String);
    Code:
       0: aload_0
       1: invokespecial #126                // Method registerDefaultSSLHostConfig:()V
       4: aload_0
       5: getfield      #34                 // Field defaultSSLHostConfig:Lorg/apache/tomcat/util/net/SSLHostConfig;
       8: aload_1
       9: invokevirtual #187                // Method org/apache/tomcat/util/net/SSLHostConfig.setTrustManagerClassName:(Ljava/lang/String;)V
      12: return

  protected org.apache.coyote.Processor createProcessor();
    Code:
       0: new           #188                // class org/apache/coyote/http11/Http11Processor
       3: dup
       4: aload_0
       5: aload_0
       6: getfield      #189                // Field adapter:Lorg/apache/coyote/Adapter;
       9: invokespecial #190                // Method org/apache/coyote/http11/Http11Processor."<init>":(Lorg/apache/coyote/http11/AbstractHttp11Protocol;Lorg/apache/coyote/Adapter;)V
      12: astore_1
      13: aload_1
      14: areturn

  protected org.apache.coyote.Processor createUpgradeProcessor(org.apache.tomcat.util.net.SocketWrapperBase<?>, org.apache.coyote.UpgradeToken);
    Code:
       0: aload_2
       1: invokevirtual #191                // Method org/apache/coyote/UpgradeToken.getHttpUpgradeHandler:()Ljavax/servlet/http/HttpUpgradeHandler;
       4: astore_3
       5: aload_3
       6: instanceof    #192                // class org/apache/coyote/http11/upgrade/InternalHttpUpgradeHandler
       9: ifeq          22
      12: new           #193                // class org/apache/coyote/http11/upgrade/UpgradeProcessorInternal
      15: dup
      16: aload_1
      17: aload_2
      18: invokespecial #194                // Method org/apache/coyote/http11/upgrade/UpgradeProcessorInternal."<init>":(Lorg/apache/tomcat/util/net/SocketWrapperBase;Lorg/apache/coyote/UpgradeToken;)V
      21: areturn
      22: new           #195                // class org/apache/coyote/http11/upgrade/UpgradeProcessorExternal
      25: dup
      26: aload_1
      27: aload_2
      28: invokespecial #196                // Method org/apache/coyote/http11/upgrade/UpgradeProcessorExternal."<init>":(Lorg/apache/tomcat/util/net/SocketWrapperBase;Lorg/apache/coyote/UpgradeToken;)V
      31: areturn

  static {};
    Code:
       0: ldc           #197                // class org/apache/coyote/http11/AbstractHttp11Protocol
       2: invokestatic  #198                // Method org/apache/tomcat/util/res/StringManager.getManager:(Ljava/lang/Class;)Lorg/apache/tomcat/util/res/StringManager;
       5: putstatic     #92                 // Field sm:Lorg/apache/tomcat/util/res/StringManager;
       8: return
}
