Compiled from "Emitter.java"
class io.dekorate.deps.snakeyaml.emitter.Emitter$ExpectBlockMappingKey implements io.dekorate.deps.snakeyaml.emitter.EmitterState {
  private boolean first;

  final io.dekorate.deps.snakeyaml.emitter.Emitter this$0;

  public io.dekorate.deps.snakeyaml.emitter.Emitter$ExpectBlockMappingKey(io.dekorate.deps.snakeyaml.emitter.Emitter, boolean);
    Code:
       0: aload_0
       1: aload_1
       2: putfield      #26                 // Field this$0:Lio/dekorate/deps/snakeyaml/emitter/Emitter;
       5: aload_0
       6: invokespecial #29                 // Method java/lang/Object."<init>":()V
       9: aload_0
      10: iload_2
      11: putfield      #31                 // Field first:Z
      14: return

  public void expect() throws java.io.IOException;
    Code:
       0: aload_0
       1: getfield      #31                 // Field first:Z
       4: ifne          65
       7: aload_0
       8: getfield      #26                 // Field this$0:Lio/dekorate/deps/snakeyaml/emitter/Emitter;
      11: invokestatic  #40                 // Method io/dekorate/deps/snakeyaml/emitter/Emitter.access$100:(Lio/dekorate/deps/snakeyaml/emitter/Emitter;)Lio/dekorate/deps/snakeyaml/events/Event;
      14: instanceof    #42                 // class io/dekorate/deps/snakeyaml/events/MappingEndEvent
      17: ifeq          65
      20: aload_0
      21: getfield      #26                 // Field this$0:Lio/dekorate/deps/snakeyaml/emitter/Emitter;
      24: aload_0
      25: getfield      #26                 // Field this$0:Lio/dekorate/deps/snakeyaml/emitter/Emitter;
      28: invokestatic  #46                 // Method io/dekorate/deps/snakeyaml/emitter/Emitter.access$1900:(Lio/dekorate/deps/snakeyaml/emitter/Emitter;)Lio/dekorate/deps/snakeyaml/util/ArrayStack;
      31: invokevirtual #52                 // Method io/dekorate/deps/snakeyaml/util/ArrayStack.pop:()Ljava/lang/Object;
      34: checkcast     #54                 // class java/lang/Integer
      37: invokestatic  #58                 // Method io/dekorate/deps/snakeyaml/emitter/Emitter.access$1802:(Lio/dekorate/deps/snakeyaml/emitter/Emitter;Ljava/lang/Integer;)Ljava/lang/Integer;
      40: pop
      41: aload_0
      42: getfield      #26                 // Field this$0:Lio/dekorate/deps/snakeyaml/emitter/Emitter;
      45: aload_0
      46: getfield      #26                 // Field this$0:Lio/dekorate/deps/snakeyaml/emitter/Emitter;
      49: invokestatic  #61                 // Method io/dekorate/deps/snakeyaml/emitter/Emitter.access$1500:(Lio/dekorate/deps/snakeyaml/emitter/Emitter;)Lio/dekorate/deps/snakeyaml/util/ArrayStack;
      52: invokevirtual #52                 // Method io/dekorate/deps/snakeyaml/util/ArrayStack.pop:()Ljava/lang/Object;
      55: checkcast     #6                  // class io/dekorate/deps/snakeyaml/emitter/EmitterState
      58: invokestatic  #65                 // Method io/dekorate/deps/snakeyaml/emitter/Emitter.access$202:(Lio/dekorate/deps/snakeyaml/emitter/Emitter;Lio/dekorate/deps/snakeyaml/emitter/EmitterState;)Lio/dekorate/deps/snakeyaml/emitter/EmitterState;
      61: pop
      62: goto          161
      65: aload_0
      66: getfield      #26                 // Field this$0:Lio/dekorate/deps/snakeyaml/emitter/Emitter;
      69: invokevirtual #68                 // Method io/dekorate/deps/snakeyaml/emitter/Emitter.writeIndent:()V
      72: aload_0
      73: getfield      #26                 // Field this$0:Lio/dekorate/deps/snakeyaml/emitter/Emitter;
      76: invokestatic  #72                 // Method io/dekorate/deps/snakeyaml/emitter/Emitter.access$2700:(Lio/dekorate/deps/snakeyaml/emitter/Emitter;)Z
      79: ifeq          117
      82: aload_0
      83: getfield      #26                 // Field this$0:Lio/dekorate/deps/snakeyaml/emitter/Emitter;
      86: invokestatic  #61                 // Method io/dekorate/deps/snakeyaml/emitter/Emitter.access$1500:(Lio/dekorate/deps/snakeyaml/emitter/Emitter;)Lio/dekorate/deps/snakeyaml/util/ArrayStack;
      89: new           #12                 // class io/dekorate/deps/snakeyaml/emitter/Emitter$ExpectBlockMappingSimpleValue
      92: dup
      93: aload_0
      94: getfield      #26                 // Field this$0:Lio/dekorate/deps/snakeyaml/emitter/Emitter;
      97: aconst_null
      98: invokespecial #75                 // Method io/dekorate/deps/snakeyaml/emitter/Emitter$ExpectBlockMappingSimpleValue."<init>":(Lio/dekorate/deps/snakeyaml/emitter/Emitter;Lio/dekorate/deps/snakeyaml/emitter/Emitter$1;)V
     101: invokevirtual #79                 // Method io/dekorate/deps/snakeyaml/util/ArrayStack.push:(Ljava/lang/Object;)V
     104: aload_0
     105: getfield      #26                 // Field this$0:Lio/dekorate/deps/snakeyaml/emitter/Emitter;
     108: iconst_0
     109: iconst_1
     110: iconst_1
     111: invokestatic  #83                 // Method io/dekorate/deps/snakeyaml/emitter/Emitter.access$1600:(Lio/dekorate/deps/snakeyaml/emitter/Emitter;ZZZ)V
     114: goto          161
     117: aload_0
     118: getfield      #26                 // Field this$0:Lio/dekorate/deps/snakeyaml/emitter/Emitter;
     121: ldc           #85                 // String ?
     123: iconst_1
     124: iconst_0
     125: iconst_1
     126: invokevirtual #89                 // Method io/dekorate/deps/snakeyaml/emitter/Emitter.writeIndicator:(Ljava/lang/String;ZZZ)V
     129: aload_0
     130: getfield      #26                 // Field this$0:Lio/dekorate/deps/snakeyaml/emitter/Emitter;
     133: invokestatic  #61                 // Method io/dekorate/deps/snakeyaml/emitter/Emitter.access$1500:(Lio/dekorate/deps/snakeyaml/emitter/Emitter;)Lio/dekorate/deps/snakeyaml/util/ArrayStack;
     136: new           #15                 // class io/dekorate/deps/snakeyaml/emitter/Emitter$ExpectBlockMappingValue
     139: dup
     140: aload_0
     141: getfield      #26                 // Field this$0:Lio/dekorate/deps/snakeyaml/emitter/Emitter;
     144: aconst_null
     145: invokespecial #90                 // Method io/dekorate/deps/snakeyaml/emitter/Emitter$ExpectBlockMappingValue."<init>":(Lio/dekorate/deps/snakeyaml/emitter/Emitter;Lio/dekorate/deps/snakeyaml/emitter/Emitter$1;)V
     148: invokevirtual #79                 // Method io/dekorate/deps/snakeyaml/util/ArrayStack.push:(Ljava/lang/Object;)V
     151: aload_0
     152: getfield      #26                 // Field this$0:Lio/dekorate/deps/snakeyaml/emitter/Emitter;
     155: iconst_0
     156: iconst_1
     157: iconst_0
     158: invokestatic  #83                 // Method io/dekorate/deps/snakeyaml/emitter/Emitter.access$1600:(Lio/dekorate/deps/snakeyaml/emitter/Emitter;ZZZ)V
     161: return
}
