Compiled from "AbsoluteRange.java"
public abstract class org.graylog2.plugin.indexer.searches.timeranges.AbsoluteRange$Builder {
  public org.graylog2.plugin.indexer.searches.timeranges.AbsoluteRange$Builder();
    Code:
       0: aload_0
       1: invokespecial #1                  // Method java/lang/Object."<init>":()V
       4: return

  public abstract org.graylog2.plugin.indexer.searches.timeranges.AbsoluteRange build();

  public abstract org.graylog2.plugin.indexer.searches.timeranges.AbsoluteRange$Builder type(java.lang.String);

  public abstract org.graylog2.plugin.indexer.searches.timeranges.AbsoluteRange$Builder to(org.joda.time.DateTime);

  public abstract org.graylog2.plugin.indexer.searches.timeranges.AbsoluteRange$Builder from(org.joda.time.DateTime);

  public org.graylog2.plugin.indexer.searches.timeranges.AbsoluteRange$Builder to(java.lang.String) throws org.graylog2.plugin.indexer.searches.timeranges.InvalidRangeParametersException;
    Code:
       0: aload_0
       1: aload_0
       2: aload_1
       3: invokespecial #2                  // Method parseDateTime:(Ljava/lang/String;)Lorg/joda/time/DateTime;
       6: invokevirtual #3                  // Method to:(Lorg/joda/time/DateTime;)Lorg/graylog2/plugin/indexer/searches/timeranges/AbsoluteRange$Builder;
       9: areturn
      10: astore_2
      11: new           #5                  // class org/graylog2/plugin/indexer/searches/timeranges/InvalidRangeParametersException
      14: dup
      15: new           #6                  // class java/lang/StringBuilder
      18: dup
      19: invokespecial #7                  // Method java/lang/StringBuilder."<init>":()V
      22: ldc           #8                  // String Invalid end of range: <
      24: invokevirtual #9                  // Method java/lang/StringBuilder.append:(Ljava/lang/String;)Ljava/lang/StringBuilder;
      27: aload_1
      28: invokevirtual #9                  // Method java/lang/StringBuilder.append:(Ljava/lang/String;)Ljava/lang/StringBuilder;
      31: ldc           #10                 // String >
      33: invokevirtual #9                  // Method java/lang/StringBuilder.append:(Ljava/lang/String;)Ljava/lang/StringBuilder;
      36: invokevirtual #11                 // Method java/lang/StringBuilder.toString:()Ljava/lang/String;
      39: aload_2
      40: invokespecial #12                 // Method org/graylog2/plugin/indexer/searches/timeranges/InvalidRangeParametersException."<init>":(Ljava/lang/String;Ljava/lang/Throwable;)V
      43: athrow
    Exception table:
       from    to  target type
           0     9    10   Class java/lang/IllegalArgumentException

  public org.graylog2.plugin.indexer.searches.timeranges.AbsoluteRange$Builder from(java.lang.String) throws org.graylog2.plugin.indexer.searches.timeranges.InvalidRangeParametersException;
    Code:
       0: aload_0
       1: aload_0
       2: aload_1
       3: invokespecial #2                  // Method parseDateTime:(Ljava/lang/String;)Lorg/joda/time/DateTime;
       6: invokevirtual #13                 // Method from:(Lorg/joda/time/DateTime;)Lorg/graylog2/plugin/indexer/searches/timeranges/AbsoluteRange$Builder;
       9: areturn
      10: astore_2
      11: new           #5                  // class org/graylog2/plugin/indexer/searches/timeranges/InvalidRangeParametersException
      14: dup
      15: new           #6                  // class java/lang/StringBuilder
      18: dup
      19: invokespecial #7                  // Method java/lang/StringBuilder."<init>":()V
      22: ldc           #14                 // String Invalid start of range: <
      24: invokevirtual #9                  // Method java/lang/StringBuilder.append:(Ljava/lang/String;)Ljava/lang/StringBuilder;
      27: aload_1
      28: invokevirtual #9                  // Method java/lang/StringBuilder.append:(Ljava/lang/String;)Ljava/lang/StringBuilder;
      31: ldc           #10                 // String >
      33: invokevirtual #9                  // Method java/lang/StringBuilder.append:(Ljava/lang/String;)Ljava/lang/StringBuilder;
      36: invokevirtual #11                 // Method java/lang/StringBuilder.toString:()Ljava/lang/String;
      39: aload_2
      40: invokespecial #12                 // Method org/graylog2/plugin/indexer/searches/timeranges/InvalidRangeParametersException."<init>":(Ljava/lang/String;Ljava/lang/Throwable;)V
      43: athrow
    Exception table:
       from    to  target type
           0     9    10   Class java/lang/IllegalArgumentException

  private org.joda.time.DateTime parseDateTime(java.lang.String);
    Code:
       0: aload_1
       1: invokestatic  #15                 // Method com/google/common/base/Strings.isNullOrEmpty:(Ljava/lang/String;)Z
       4: ifeq          17
       7: new           #4                  // class java/lang/IllegalArgumentException
      10: dup
      11: ldc           #16                 // String Null or empty string
      13: invokespecial #17                 // Method java/lang/IllegalArgumentException."<init>":(Ljava/lang/String;)V
      16: athrow
      17: aload_1
      18: ldc           #18                 // String T
      20: invokevirtual #19                 // Method java/lang/String.contains:(Ljava/lang/CharSequence;)Z
      23: ifeq          33
      26: invokestatic  #20                 // Method org/joda/time/format/ISODateTimeFormat.dateTime:()Lorg/joda/time/format/DateTimeFormatter;
      29: astore_2
      30: goto          37
      33: invokestatic  #21                 // Method org/graylog2/plugin/Tools.timeFormatterWithOptionalMilliseconds:()Lorg/joda/time/format/DateTimeFormatter;
      36: astore_2
      37: aload_2
      38: invokevirtual #22                 // Method org/joda/time/format/DateTimeFormatter.withOffsetParsed:()Lorg/joda/time/format/DateTimeFormatter;
      41: aload_1
      42: invokevirtual #23                 // Method org/joda/time/format/DateTimeFormatter.parseDateTime:(Ljava/lang/String;)Lorg/joda/time/DateTime;
      45: areturn
}
