Compiled from "LocalEntryRetriever.java"
public class org.infinispan.iteration.impl.LocalEntryRetriever$ItrQueuerHandler<C> implements org.infinispan.iteration.impl.LocalEntryRetriever$BatchHandler<K, C> {
  final org.infinispan.iteration.impl.LocalEntryRetriever<K, V>.Itr<C> iterator;

  final org.infinispan.iteration.impl.LocalEntryRetriever this$0;

  public org.infinispan.iteration.impl.LocalEntryRetriever$ItrQueuerHandler(org.infinispan.iteration.impl.LocalEntryRetriever<K, V>.Itr<C>);
    Code:
       0: aload_0
       1: aload_1
       2: putfield      #1                  // Field this$0:Lorg/infinispan/iteration/impl/LocalEntryRetriever;
       5: aload_0
       6: invokespecial #2                  // Method java/lang/Object."<init>":()V
       9: aload_0
      10: aload_2
      11: putfield      #3                  // Field iterator:Lorg/infinispan/iteration/impl/LocalEntryRetriever$Itr;
      14: return

  public void handleBatch(boolean, java.util.Collection<org.infinispan.container.entries.CacheEntry<K, C>>) throws java.lang.InterruptedException;
    Code:
       0: aload_0
       1: getfield      #3                  // Field iterator:Lorg/infinispan/iteration/impl/LocalEntryRetriever$Itr;
       4: aload_2
       5: invokevirtual #4                  // Method org/infinispan/iteration/impl/LocalEntryRetriever$Itr.addEntries:(Ljava/util/Collection;)V
       8: iload_1
       9: ifeq          19
      12: aload_0
      13: getfield      #3                  // Field iterator:Lorg/infinispan/iteration/impl/LocalEntryRetriever$Itr;
      16: invokevirtual #5                  // Method org/infinispan/iteration/impl/LocalEntryRetriever$Itr.close:()V
      19: return
}
