Compiled from "LocalStreamManagerImpl.java"
class org.infinispan.stream.impl.LocalStreamManagerImpl$NonRehashIntermediateCollector$ResponseBlocker implements java.util.concurrent.ForkJoinPool$ManagedBlocker {
  private final R response;

  private boolean completed;

  final org.infinispan.stream.impl.LocalStreamManagerImpl$NonRehashIntermediateCollector this$1;

  org.infinispan.stream.impl.LocalStreamManagerImpl$NonRehashIntermediateCollector$ResponseBlocker(R);
    Code:
       0: aload_0
       1: aload_1
       2: putfield      #1                  // Field this$1:Lorg/infinispan/stream/impl/LocalStreamManagerImpl$NonRehashIntermediateCollector;
       5: aload_0
       6: invokespecial #2                  // Method java/lang/Object."<init>":()V
       9: aload_0
      10: iconst_0
      11: putfield      #3                  // Field completed:Z
      14: aload_0
      15: aload_2
      16: putfield      #4                  // Field response:Ljava/lang/Object;
      19: return

  public boolean block() throws java.lang.InterruptedException;
    Code:
       0: aload_0
       1: getfield      #3                  // Field completed:Z
       4: ifne          110
       7: aload_0
       8: getfield      #1                  // Field this$1:Lorg/infinispan/stream/impl/LocalStreamManagerImpl$NonRehashIntermediateCollector;
      11: dup
      12: astore_1
      13: monitorenter
      14: aload_0
      15: getfield      #1                  // Field this$1:Lorg/infinispan/stream/impl/LocalStreamManagerImpl$NonRehashIntermediateCollector;
      18: getfield      #5                  // Field org/infinispan/stream/impl/LocalStreamManagerImpl$NonRehashIntermediateCollector.this$0:Lorg/infinispan/stream/impl/LocalStreamManagerImpl;
      21: invokestatic  #6                  // Method org/infinispan/stream/impl/LocalStreamManagerImpl.access$400:(Lorg/infinispan/stream/impl/LocalStreamManagerImpl;)Lorg/infinispan/remoting/rpc/RpcManager;
      24: aload_0
      25: getfield      #1                  // Field this$1:Lorg/infinispan/stream/impl/LocalStreamManagerImpl$NonRehashIntermediateCollector;
      28: invokestatic  #7                  // Method org/infinispan/stream/impl/LocalStreamManagerImpl$NonRehashIntermediateCollector.access$500:(Lorg/infinispan/stream/impl/LocalStreamManagerImpl$NonRehashIntermediateCollector;)Lorg/infinispan/remoting/transport/Address;
      31: invokestatic  #8                  // Method java/util/Collections.singleton:(Ljava/lang/Object;)Ljava/util/Set;
      34: new           #9                  // class org/infinispan/stream/impl/StreamResponseCommand
      37: dup
      38: aload_0
      39: getfield      #1                  // Field this$1:Lorg/infinispan/stream/impl/LocalStreamManagerImpl$NonRehashIntermediateCollector;
      42: getfield      #5                  // Field org/infinispan/stream/impl/LocalStreamManagerImpl$NonRehashIntermediateCollector.this$0:Lorg/infinispan/stream/impl/LocalStreamManagerImpl;
      45: invokestatic  #10                 // Method org/infinispan/stream/impl/LocalStreamManagerImpl.access$200:(Lorg/infinispan/stream/impl/LocalStreamManagerImpl;)Lorg/infinispan/AdvancedCache;
      48: invokeinterface #11,  1           // InterfaceMethod org/infinispan/AdvancedCache.getName:()Ljava/lang/String;
      53: aload_0
      54: getfield      #1                  // Field this$1:Lorg/infinispan/stream/impl/LocalStreamManagerImpl$NonRehashIntermediateCollector;
      57: getfield      #5                  // Field org/infinispan/stream/impl/LocalStreamManagerImpl$NonRehashIntermediateCollector.this$0:Lorg/infinispan/stream/impl/LocalStreamManagerImpl;
      60: invokestatic  #12                 // Method org/infinispan/stream/impl/LocalStreamManagerImpl.access$300:(Lorg/infinispan/stream/impl/LocalStreamManagerImpl;)Lorg/infinispan/remoting/transport/Address;
      63: aload_0
      64: getfield      #1                  // Field this$1:Lorg/infinispan/stream/impl/LocalStreamManagerImpl$NonRehashIntermediateCollector;
      67: invokestatic  #13                 // Method org/infinispan/stream/impl/LocalStreamManagerImpl$NonRehashIntermediateCollector.access$600:(Lorg/infinispan/stream/impl/LocalStreamManagerImpl$NonRehashIntermediateCollector;)Ljava/util/UUID;
      70: iconst_0
      71: aload_0
      72: getfield      #4                  // Field response:Ljava/lang/Object;
      75: invokespecial #14                 // Method org/infinispan/stream/impl/StreamResponseCommand."<init>":(Ljava/lang/String;Lorg/infinispan/remoting/transport/Address;Ljava/util/UUID;ZLjava/lang/Object;)V
      78: aload_0
      79: getfield      #1                  // Field this$1:Lorg/infinispan/stream/impl/LocalStreamManagerImpl$NonRehashIntermediateCollector;
      82: getfield      #5                  // Field org/infinispan/stream/impl/LocalStreamManagerImpl$NonRehashIntermediateCollector.this$0:Lorg/infinispan/stream/impl/LocalStreamManagerImpl;
      85: invokestatic  #6                  // Method org/infinispan/stream/impl/LocalStreamManagerImpl.access$400:(Lorg/infinispan/stream/impl/LocalStreamManagerImpl;)Lorg/infinispan/remoting/rpc/RpcManager;
      88: iconst_1
      89: invokeinterface #15,  2           // InterfaceMethod org/infinispan/remoting/rpc/RpcManager.getDefaultRpcOptions:(Z)Lorg/infinispan/remoting/rpc/RpcOptions;
      94: invokeinterface #16,  4           // InterfaceMethod org/infinispan/remoting/rpc/RpcManager.invokeRemotely:(Ljava/util/Collection;Lorg/infinispan/commands/ReplicableCommand;Lorg/infinispan/remoting/rpc/RpcOptions;)Ljava/util/Map;
      99: pop
     100: aload_1
     101: monitorexit
     102: goto          110
     105: astore_2
     106: aload_1
     107: monitorexit
     108: aload_2
     109: athrow
     110: aload_0
     111: iconst_1
     112: putfield      #3                  // Field completed:Z
     115: aload_0
     116: getfield      #3                  // Field completed:Z
     119: ireturn
    Exception table:
       from    to  target type
          14   102   105   any
         105   108   105   any

  public boolean isReleasable();
    Code:
       0: aload_0
       1: getfield      #3                  // Field completed:Z
       4: ireturn
}
