Compiled from "TerminalFunctions.java"
final class org.infinispan.stream.impl.TerminalFunctions$AnyMatchIntFunction<T> implements java.util.function.Function<java.util.stream.IntStream, java.lang.Boolean> {
  private final java.util.function.IntPredicate predicate;

  private org.infinispan.stream.impl.TerminalFunctions$AnyMatchIntFunction(java.util.function.IntPredicate);
    Code:
       0: aload_0
       1: invokespecial #3                  // Method java/lang/Object."<init>":()V
       4: aload_0
       5: aload_1
       6: putfield      #1                  // Field predicate:Ljava/util/function/IntPredicate;
       9: return

  public java.lang.Boolean apply(java.util.stream.IntStream);
    Code:
       0: aload_1
       1: aload_0
       2: getfield      #1                  // Field predicate:Ljava/util/function/IntPredicate;
       5: invokeinterface #4,  2            // InterfaceMethod java/util/stream/IntStream.anyMatch:(Ljava/util/function/IntPredicate;)Z
      10: invokestatic  #5                  // Method java/lang/Boolean.valueOf:(Z)Ljava/lang/Boolean;
      13: areturn

  public java.lang.Object apply(java.lang.Object);
    Code:
       0: aload_0
       1: aload_1
       2: checkcast     #6                  // class java/util/stream/IntStream
       5: invokevirtual #7                  // Method apply:(Ljava/util/stream/IntStream;)Ljava/lang/Boolean;
       8: areturn

  org.infinispan.stream.impl.TerminalFunctions$AnyMatchIntFunction(java.util.function.IntPredicate, org.infinispan.stream.impl.TerminalFunctions$1);
    Code:
       0: aload_0
       1: aload_1
       2: invokespecial #2                  // Method "<init>":(Ljava/util/function/IntPredicate;)V
       5: return

  static java.util.function.IntPredicate access$3900(org.infinispan.stream.impl.TerminalFunctions$AnyMatchIntFunction);
    Code:
       0: aload_0
       1: getfield      #1                  // Field predicate:Ljava/util/function/IntPredicate;
       4: areturn
}
