Compiled from "MessageInflater.kt"
public final class okhttp3.internal.ws.MessageInflater implements java.io.Closeable {
  private final okio.Buffer deflatedBytes;

  private final java.util.zip.Inflater inflater;

  private final okio.InflaterSource inflaterSource;

  private final boolean noContextTakeover;

  public final void inflate(okio.Buffer) throws java.io.IOException;
    Code:
       0: aload_1
       1: ldc           #19                 // String buffer
       3: invokestatic  #25                 // Method kotlin/jvm/internal/Intrinsics.checkNotNullParameter:(Ljava/lang/Object;Ljava/lang/String;)V
       6: aload_0
       7: getfield      #27                 // Field deflatedBytes:Lokio/Buffer;
      10: invokevirtual #33                 // Method okio/Buffer.size:()J
      13: lconst_0
      14: lcmp
      15: ifne          22
      18: iconst_1
      19: goto          23
      22: iconst_0
      23: istore_2
      24: iconst_0
      25: istore_3
      26: iconst_0
      27: istore        4
      29: iconst_0
      30: istore        4
      32: iconst_0
      33: istore        5
      35: iload_2
      36: ifne          62
      39: iconst_0
      40: istore        6
      42: ldc           #35                 // String Failed requirement.
      44: astore        5
      46: new           #37                 // class java/lang/IllegalArgumentException
      49: dup
      50: aload         5
      52: invokevirtual #41                 // Method java/lang/Object.toString:()Ljava/lang/String;
      55: invokespecial #45                 // Method java/lang/IllegalArgumentException."<init>":(Ljava/lang/String;)V
      58: checkcast     #47                 // class java/lang/Throwable
      61: athrow
      62: aload_0
      63: getfield      #51                 // Field noContextTakeover:Z
      66: ifeq          76
      69: aload_0
      70: getfield      #53                 // Field inflater:Ljava/util/zip/Inflater;
      73: invokevirtual #59                 // Method java/util/zip/Inflater.reset:()V
      76: aload_0
      77: getfield      #27                 // Field deflatedBytes:Lokio/Buffer;
      80: aload_1
      81: checkcast     #61                 // class okio/Source
      84: invokevirtual #65                 // Method okio/Buffer.writeAll:(Lokio/Source;)J
      87: pop2
      88: aload_0
      89: getfield      #27                 // Field deflatedBytes:Lokio/Buffer;
      92: ldc           #66                 // int 65535
      94: invokevirtual #70                 // Method okio/Buffer.writeInt:(I)Lokio/Buffer;
      97: pop
      98: aload_0
      99: getfield      #53                 // Field inflater:Ljava/util/zip/Inflater;
     102: invokevirtual #73                 // Method java/util/zip/Inflater.getBytesRead:()J
     105: aload_0
     106: getfield      #27                 // Field deflatedBytes:Lokio/Buffer;
     109: invokevirtual #33                 // Method okio/Buffer.size:()J
     112: ladd
     113: lstore_2
     114: aload_0
     115: getfield      #75                 // Field inflaterSource:Lokio/InflaterSource;
     118: aload_1
     119: ldc2_w        #76                 // long 9223372036854775807l
     122: invokevirtual #83                 // Method okio/InflaterSource.readOrInflate:(Lokio/Buffer;J)J
     125: pop2
     126: aload_0
     127: getfield      #53                 // Field inflater:Ljava/util/zip/Inflater;
     130: invokevirtual #73                 // Method java/util/zip/Inflater.getBytesRead:()J
     133: lload_2
     134: lcmp
     135: iflt          114
     138: return

  public void close() throws java.io.IOException;
    Code:
       0: aload_0
       1: getfield      #75                 // Field inflaterSource:Lokio/InflaterSource;
       4: invokevirtual #90                 // Method okio/InflaterSource.close:()V
       7: return

  public okhttp3.internal.ws.MessageInflater(boolean);
    Code:
       0: aload_0
       1: invokespecial #93                 // Method java/lang/Object."<init>":()V
       4: aload_0
       5: iload_1
       6: putfield      #51                 // Field noContextTakeover:Z
       9: aload_0
      10: new           #29                 // class okio/Buffer
      13: dup
      14: invokespecial #94                 // Method okio/Buffer."<init>":()V
      17: putfield      #27                 // Field deflatedBytes:Lokio/Buffer;
      20: aload_0
      21: new           #55                 // class java/util/zip/Inflater
      24: dup
      25: iconst_1
      26: invokespecial #96                 // Method java/util/zip/Inflater."<init>":(Z)V
      29: putfield      #53                 // Field inflater:Ljava/util/zip/Inflater;
      32: aload_0
      33: new           #79                 // class okio/InflaterSource
      36: dup
      37: aload_0
      38: getfield      #27                 // Field deflatedBytes:Lokio/Buffer;
      41: checkcast     #61                 // class okio/Source
      44: aload_0
      45: getfield      #53                 // Field inflater:Ljava/util/zip/Inflater;
      48: invokespecial #99                 // Method okio/InflaterSource."<init>":(Lokio/Source;Ljava/util/zip/Inflater;)V
      51: putfield      #75                 // Field inflaterSource:Lokio/InflaterSource;
      54: return
}
