Compiled from "UnwrappingBeanPropertyWriter.java"
public class org.apache.htrace.shaded.fasterxml.jackson.databind.ser.impl.UnwrappingBeanPropertyWriter extends org.apache.htrace.shaded.fasterxml.jackson.databind.ser.BeanPropertyWriter {
  protected final org.apache.htrace.shaded.fasterxml.jackson.databind.util.NameTransformer _nameTransformer;

  public org.apache.htrace.shaded.fasterxml.jackson.databind.ser.impl.UnwrappingBeanPropertyWriter(org.apache.htrace.shaded.fasterxml.jackson.databind.ser.BeanPropertyWriter, org.apache.htrace.shaded.fasterxml.jackson.databind.util.NameTransformer);
    Code:
       0: aload_0
       1: aload_1
       2: invokespecial #17                 // Method org/apache/htrace/shaded/fasterxml/jackson/databind/ser/BeanPropertyWriter."<init>":(Lorg/apache/htrace/shaded/fasterxml/jackson/databind/ser/BeanPropertyWriter;)V
       5: aload_0
       6: aload_2
       7: putfield      #19                 // Field _nameTransformer:Lorg/apache/htrace/shaded/fasterxml/jackson/databind/util/NameTransformer;
      10: return

  private org.apache.htrace.shaded.fasterxml.jackson.databind.ser.impl.UnwrappingBeanPropertyWriter(org.apache.htrace.shaded.fasterxml.jackson.databind.ser.impl.UnwrappingBeanPropertyWriter, org.apache.htrace.shaded.fasterxml.jackson.databind.util.NameTransformer, org.apache.htrace.shaded.fasterxml.jackson.core.io.SerializedString);
    Code:
       0: aload_0
       1: aload_1
       2: aload_3
       3: invokespecial #28                 // Method org/apache/htrace/shaded/fasterxml/jackson/databind/ser/BeanPropertyWriter."<init>":(Lorg/apache/htrace/shaded/fasterxml/jackson/databind/ser/BeanPropertyWriter;Lorg/apache/htrace/shaded/fasterxml/jackson/core/io/SerializedString;)V
       6: aload_0
       7: aload_2
       8: putfield      #19                 // Field _nameTransformer:Lorg/apache/htrace/shaded/fasterxml/jackson/databind/util/NameTransformer;
      11: return

  public org.apache.htrace.shaded.fasterxml.jackson.databind.ser.impl.UnwrappingBeanPropertyWriter rename(org.apache.htrace.shaded.fasterxml.jackson.databind.util.NameTransformer);
    Code:
       0: aload_0
       1: getfield      #36                 // Field _name:Lorg/apache/htrace/shaded/fasterxml/jackson/core/io/SerializedString;
       4: invokevirtual #42                 // Method org/apache/htrace/shaded/fasterxml/jackson/core/io/SerializedString.getValue:()Ljava/lang/String;
       7: astore_2
       8: aload_1
       9: aload_2
      10: invokevirtual #48                 // Method org/apache/htrace/shaded/fasterxml/jackson/databind/util/NameTransformer.transform:(Ljava/lang/String;)Ljava/lang/String;
      13: astore_3
      14: aload_1
      15: aload_0
      16: getfield      #19                 // Field _nameTransformer:Lorg/apache/htrace/shaded/fasterxml/jackson/databind/util/NameTransformer;
      19: invokestatic  #52                 // Method org/apache/htrace/shaded/fasterxml/jackson/databind/util/NameTransformer.chainedTransformer:(Lorg/apache/htrace/shaded/fasterxml/jackson/databind/util/NameTransformer;Lorg/apache/htrace/shaded/fasterxml/jackson/databind/util/NameTransformer;)Lorg/apache/htrace/shaded/fasterxml/jackson/databind/util/NameTransformer;
      22: astore_1
      23: new           #2                  // class org/apache/htrace/shaded/fasterxml/jackson/databind/ser/impl/UnwrappingBeanPropertyWriter
      26: dup
      27: aload_0
      28: aload_1
      29: new           #38                 // class org/apache/htrace/shaded/fasterxml/jackson/core/io/SerializedString
      32: dup
      33: aload_3
      34: invokespecial #55                 // Method org/apache/htrace/shaded/fasterxml/jackson/core/io/SerializedString."<init>":(Ljava/lang/String;)V
      37: invokespecial #57                 // Method "<init>":(Lorg/apache/htrace/shaded/fasterxml/jackson/databind/ser/impl/UnwrappingBeanPropertyWriter;Lorg/apache/htrace/shaded/fasterxml/jackson/databind/util/NameTransformer;Lorg/apache/htrace/shaded/fasterxml/jackson/core/io/SerializedString;)V
      40: areturn

  public boolean isUnwrapping();
    Code:
       0: iconst_1
       1: ireturn

  public void serializeAsField(java.lang.Object, org.apache.htrace.shaded.fasterxml.jackson.core.JsonGenerator, org.apache.htrace.shaded.fasterxml.jackson.databind.SerializerProvider) throws java.lang.Exception;
    Code:
       0: aload_0
       1: aload_1
       2: invokevirtual #70                 // Method get:(Ljava/lang/Object;)Ljava/lang/Object;
       5: astore        4
       7: aload         4
       9: ifnonnull     13
      12: return
      13: aload_0
      14: getfield      #76                 // Field _serializer:Lorg/apache/htrace/shaded/fasterxml/jackson/databind/JsonSerializer;
      17: astore        5
      19: aload         5
      21: ifnonnull     62
      24: aload         4
      26: invokevirtual #80                 // Method java/lang/Object.getClass:()Ljava/lang/Class;
      29: astore        6
      31: aload_0
      32: getfield      #84                 // Field _dynamicSerializers:Lorg/apache/htrace/shaded/fasterxml/jackson/databind/ser/impl/PropertySerializerMap;
      35: astore        7
      37: aload         7
      39: aload         6
      41: invokevirtual #90                 // Method org/apache/htrace/shaded/fasterxml/jackson/databind/ser/impl/PropertySerializerMap.serializerFor:(Ljava/lang/Class;)Lorg/apache/htrace/shaded/fasterxml/jackson/databind/JsonSerializer;
      44: astore        5
      46: aload         5
      48: ifnonnull     62
      51: aload_0
      52: aload         7
      54: aload         6
      56: aload_3
      57: invokevirtual #94                 // Method _findAndAddDynamic:(Lorg/apache/htrace/shaded/fasterxml/jackson/databind/ser/impl/PropertySerializerMap;Ljava/lang/Class;Lorg/apache/htrace/shaded/fasterxml/jackson/databind/SerializerProvider;)Lorg/apache/htrace/shaded/fasterxml/jackson/databind/JsonSerializer;
      60: astore        5
      62: aload_0
      63: getfield      #100                // Field _suppressableValue:Ljava/lang/Object;
      66: ifnull        103
      69: getstatic     #103                // Field MARKER_FOR_EMPTY:Ljava/lang/Object;
      72: aload_0
      73: getfield      #100                // Field _suppressableValue:Ljava/lang/Object;
      76: if_acmpne     90
      79: aload         5
      81: aload         4
      83: invokevirtual #107                // Method org/apache/htrace/shaded/fasterxml/jackson/databind/JsonSerializer.isEmpty:(Ljava/lang/Object;)Z
      86: ifeq          103
      89: return
      90: aload_0
      91: getfield      #100                // Field _suppressableValue:Ljava/lang/Object;
      94: aload         4
      96: invokevirtual #110                // Method java/lang/Object.equals:(Ljava/lang/Object;)Z
      99: ifeq          103
     102: return
     103: aload         4
     105: aload_1
     106: if_acmpne     122
     109: aload_0
     110: aload_1
     111: aload_2
     112: aload_3
     113: aload         5
     115: invokevirtual #114                // Method _handleSelfReference:(Ljava/lang/Object;Lorg/apache/htrace/shaded/fasterxml/jackson/core/JsonGenerator;Lorg/apache/htrace/shaded/fasterxml/jackson/databind/SerializerProvider;Lorg/apache/htrace/shaded/fasterxml/jackson/databind/JsonSerializer;)Z
     118: ifeq          122
     121: return
     122: aload         5
     124: invokevirtual #117                // Method org/apache/htrace/shaded/fasterxml/jackson/databind/JsonSerializer.isUnwrappingSerializer:()Z
     127: ifne          138
     130: aload_2
     131: aload_0
     132: getfield      #36                 // Field _name:Lorg/apache/htrace/shaded/fasterxml/jackson/core/io/SerializedString;
     135: invokevirtual #123                // Method org/apache/htrace/shaded/fasterxml/jackson/core/JsonGenerator.writeFieldName:(Lorg/apache/htrace/shaded/fasterxml/jackson/core/SerializableString;)V
     138: aload_0
     139: getfield      #127                // Field _typeSerializer:Lorg/apache/htrace/shaded/fasterxml/jackson/databind/jsontype/TypeSerializer;
     142: ifnonnull     157
     145: aload         5
     147: aload         4
     149: aload_2
     150: aload_3
     151: invokevirtual #130                // Method org/apache/htrace/shaded/fasterxml/jackson/databind/JsonSerializer.serialize:(Ljava/lang/Object;Lorg/apache/htrace/shaded/fasterxml/jackson/core/JsonGenerator;Lorg/apache/htrace/shaded/fasterxml/jackson/databind/SerializerProvider;)V
     154: goto          170
     157: aload         5
     159: aload         4
     161: aload_2
     162: aload_3
     163: aload_0
     164: getfield      #127                // Field _typeSerializer:Lorg/apache/htrace/shaded/fasterxml/jackson/databind/jsontype/TypeSerializer;
     167: invokevirtual #134                // Method org/apache/htrace/shaded/fasterxml/jackson/databind/JsonSerializer.serializeWithType:(Ljava/lang/Object;Lorg/apache/htrace/shaded/fasterxml/jackson/core/JsonGenerator;Lorg/apache/htrace/shaded/fasterxml/jackson/databind/SerializerProvider;Lorg/apache/htrace/shaded/fasterxml/jackson/databind/jsontype/TypeSerializer;)V
     170: return

  public void assignSerializer(org.apache.htrace.shaded.fasterxml.jackson.databind.JsonSerializer<java.lang.Object>);
    Code:
       0: aload_0
       1: aload_1
       2: invokespecial #150                // Method org/apache/htrace/shaded/fasterxml/jackson/databind/ser/BeanPropertyWriter.assignSerializer:(Lorg/apache/htrace/shaded/fasterxml/jackson/databind/JsonSerializer;)V
       5: aload_0
       6: getfield      #76                 // Field _serializer:Lorg/apache/htrace/shaded/fasterxml/jackson/databind/JsonSerializer;
       9: ifnull        54
      12: aload_0
      13: getfield      #19                 // Field _nameTransformer:Lorg/apache/htrace/shaded/fasterxml/jackson/databind/util/NameTransformer;
      16: astore_2
      17: aload_0
      18: getfield      #76                 // Field _serializer:Lorg/apache/htrace/shaded/fasterxml/jackson/databind/JsonSerializer;
      21: invokevirtual #117                // Method org/apache/htrace/shaded/fasterxml/jackson/databind/JsonSerializer.isUnwrappingSerializer:()Z
      24: ifeq          42
      27: aload_2
      28: aload_0
      29: getfield      #76                 // Field _serializer:Lorg/apache/htrace/shaded/fasterxml/jackson/databind/JsonSerializer;
      32: checkcast     #152                // class org/apache/htrace/shaded/fasterxml/jackson/databind/ser/impl/UnwrappingBeanSerializer
      35: getfield      #153                // Field org/apache/htrace/shaded/fasterxml/jackson/databind/ser/impl/UnwrappingBeanSerializer._nameTransformer:Lorg/apache/htrace/shaded/fasterxml/jackson/databind/util/NameTransformer;
      38: invokestatic  #52                 // Method org/apache/htrace/shaded/fasterxml/jackson/databind/util/NameTransformer.chainedTransformer:(Lorg/apache/htrace/shaded/fasterxml/jackson/databind/util/NameTransformer;Lorg/apache/htrace/shaded/fasterxml/jackson/databind/util/NameTransformer;)Lorg/apache/htrace/shaded/fasterxml/jackson/databind/util/NameTransformer;
      41: astore_2
      42: aload_0
      43: aload_0
      44: getfield      #76                 // Field _serializer:Lorg/apache/htrace/shaded/fasterxml/jackson/databind/JsonSerializer;
      47: aload_2
      48: invokevirtual #157                // Method org/apache/htrace/shaded/fasterxml/jackson/databind/JsonSerializer.unwrappingSerializer:(Lorg/apache/htrace/shaded/fasterxml/jackson/databind/util/NameTransformer;)Lorg/apache/htrace/shaded/fasterxml/jackson/databind/JsonSerializer;
      51: putfield      #76                 // Field _serializer:Lorg/apache/htrace/shaded/fasterxml/jackson/databind/JsonSerializer;
      54: return

  protected void _depositSchemaProperty(org.apache.htrace.shaded.fasterxml.jackson.databind.node.ObjectNode, org.apache.htrace.shaded.fasterxml.jackson.databind.JsonNode);
    Code:
       0: aload_2
       1: ldc           #162                // String properties
       3: invokevirtual #167                // Method org/apache/htrace/shaded/fasterxml/jackson/databind/JsonNode.get:(Ljava/lang/String;)Lorg/apache/htrace/shaded/fasterxml/jackson/databind/JsonNode;
       6: astore_3
       7: aload_3
       8: ifnull        89
      11: aload_3
      12: invokevirtual #171                // Method org/apache/htrace/shaded/fasterxml/jackson/databind/JsonNode.fields:()Ljava/util/Iterator;
      15: astore        4
      17: aload         4
      19: invokeinterface #176,  1          // InterfaceMethod java/util/Iterator.hasNext:()Z
      24: ifeq          89
      27: aload         4
      29: invokeinterface #180,  1          // InterfaceMethod java/util/Iterator.next:()Ljava/lang/Object;
      34: checkcast     #7                  // class java/util/Map$Entry
      37: astore        5
      39: aload         5
      41: invokeinterface #183,  1          // InterfaceMethod java/util/Map$Entry.getKey:()Ljava/lang/Object;
      46: checkcast     #185                // class java/lang/String
      49: astore        6
      51: aload_0
      52: getfield      #19                 // Field _nameTransformer:Lorg/apache/htrace/shaded/fasterxml/jackson/databind/util/NameTransformer;
      55: ifnull        69
      58: aload_0
      59: getfield      #19                 // Field _nameTransformer:Lorg/apache/htrace/shaded/fasterxml/jackson/databind/util/NameTransformer;
      62: aload         6
      64: invokevirtual #48                 // Method org/apache/htrace/shaded/fasterxml/jackson/databind/util/NameTransformer.transform:(Ljava/lang/String;)Ljava/lang/String;
      67: astore        6
      69: aload_1
      70: aload         6
      72: aload         5
      74: invokeinterface #187,  1          // InterfaceMethod java/util/Map$Entry.getValue:()Ljava/lang/Object;
      79: checkcast     #164                // class org/apache/htrace/shaded/fasterxml/jackson/databind/JsonNode
      82: invokevirtual #193                // Method org/apache/htrace/shaded/fasterxml/jackson/databind/node/ObjectNode.set:(Ljava/lang/String;Lorg/apache/htrace/shaded/fasterxml/jackson/databind/JsonNode;)Lorg/apache/htrace/shaded/fasterxml/jackson/databind/JsonNode;
      85: pop
      86: goto          17
      89: return

  protected org.apache.htrace.shaded.fasterxml.jackson.databind.JsonSerializer<java.lang.Object> _findAndAddDynamic(org.apache.htrace.shaded.fasterxml.jackson.databind.ser.impl.PropertySerializerMap, java.lang.Class<?>, org.apache.htrace.shaded.fasterxml.jackson.databind.SerializerProvider) throws org.apache.htrace.shaded.fasterxml.jackson.databind.JsonMappingException;
    Code:
       0: aload_0
       1: getfield      #210                // Field _nonTrivialBaseType:Lorg/apache/htrace/shaded/fasterxml/jackson/databind/JavaType;
       4: ifnull        30
       7: aload_3
       8: aload_0
       9: getfield      #210                // Field _nonTrivialBaseType:Lorg/apache/htrace/shaded/fasterxml/jackson/databind/JavaType;
      12: aload_2
      13: invokevirtual #216                // Method org/apache/htrace/shaded/fasterxml/jackson/databind/SerializerProvider.constructSpecializedType:(Lorg/apache/htrace/shaded/fasterxml/jackson/databind/JavaType;Ljava/lang/Class;)Lorg/apache/htrace/shaded/fasterxml/jackson/databind/JavaType;
      16: astore        4
      18: aload_3
      19: aload         4
      21: aload_0
      22: invokevirtual #220                // Method org/apache/htrace/shaded/fasterxml/jackson/databind/SerializerProvider.findValueSerializer:(Lorg/apache/htrace/shaded/fasterxml/jackson/databind/JavaType;Lorg/apache/htrace/shaded/fasterxml/jackson/databind/BeanProperty;)Lorg/apache/htrace/shaded/fasterxml/jackson/databind/JsonSerializer;
      25: astore        5
      27: goto          38
      30: aload_3
      31: aload_2
      32: aload_0
      33: invokevirtual #223                // Method org/apache/htrace/shaded/fasterxml/jackson/databind/SerializerProvider.findValueSerializer:(Ljava/lang/Class;Lorg/apache/htrace/shaded/fasterxml/jackson/databind/BeanProperty;)Lorg/apache/htrace/shaded/fasterxml/jackson/databind/JsonSerializer;
      36: astore        5
      38: aload_0
      39: getfield      #19                 // Field _nameTransformer:Lorg/apache/htrace/shaded/fasterxml/jackson/databind/util/NameTransformer;
      42: astore        4
      44: aload         5
      46: invokevirtual #117                // Method org/apache/htrace/shaded/fasterxml/jackson/databind/JsonSerializer.isUnwrappingSerializer:()Z
      49: ifeq          67
      52: aload         4
      54: aload         5
      56: checkcast     #152                // class org/apache/htrace/shaded/fasterxml/jackson/databind/ser/impl/UnwrappingBeanSerializer
      59: getfield      #153                // Field org/apache/htrace/shaded/fasterxml/jackson/databind/ser/impl/UnwrappingBeanSerializer._nameTransformer:Lorg/apache/htrace/shaded/fasterxml/jackson/databind/util/NameTransformer;
      62: invokestatic  #52                 // Method org/apache/htrace/shaded/fasterxml/jackson/databind/util/NameTransformer.chainedTransformer:(Lorg/apache/htrace/shaded/fasterxml/jackson/databind/util/NameTransformer;Lorg/apache/htrace/shaded/fasterxml/jackson/databind/util/NameTransformer;)Lorg/apache/htrace/shaded/fasterxml/jackson/databind/util/NameTransformer;
      65: astore        4
      67: aload         5
      69: aload         4
      71: invokevirtual #157                // Method org/apache/htrace/shaded/fasterxml/jackson/databind/JsonSerializer.unwrappingSerializer:(Lorg/apache/htrace/shaded/fasterxml/jackson/databind/util/NameTransformer;)Lorg/apache/htrace/shaded/fasterxml/jackson/databind/JsonSerializer;
      74: astore        5
      76: aload_0
      77: aload_0
      78: getfield      #84                 // Field _dynamicSerializers:Lorg/apache/htrace/shaded/fasterxml/jackson/databind/ser/impl/PropertySerializerMap;
      81: aload_2
      82: aload         5
      84: invokevirtual #229                // Method org/apache/htrace/shaded/fasterxml/jackson/databind/ser/impl/PropertySerializerMap.newWith:(Ljava/lang/Class;Lorg/apache/htrace/shaded/fasterxml/jackson/databind/JsonSerializer;)Lorg/apache/htrace/shaded/fasterxml/jackson/databind/ser/impl/PropertySerializerMap;
      87: putfield      #84                 // Field _dynamicSerializers:Lorg/apache/htrace/shaded/fasterxml/jackson/databind/ser/impl/PropertySerializerMap;
      90: aload         5
      92: areturn

  public org.apache.htrace.shaded.fasterxml.jackson.databind.ser.BeanPropertyWriter rename(org.apache.htrace.shaded.fasterxml.jackson.databind.util.NameTransformer);
    Code:
       0: aload_0
       1: aload_1
       2: invokevirtual #236                // Method rename:(Lorg/apache/htrace/shaded/fasterxml/jackson/databind/util/NameTransformer;)Lorg/apache/htrace/shaded/fasterxml/jackson/databind/ser/impl/UnwrappingBeanPropertyWriter;
       5: areturn
}
