Compiled from "SchemaPerNodeDataLoaderFilter.java"
public class org.jumpmind.symmetric.load.SchemaPerNodeDataLoaderFilter extends org.jumpmind.symmetric.io.data.writer.DatabaseWriterFilterAdapter {
  private java.lang.String tablePrefix;

  private java.lang.String schemaPrefix;

  public org.jumpmind.symmetric.load.SchemaPerNodeDataLoaderFilter();
    Code:
       0: aload_0
       1: invokespecial #1                  // Method org/jumpmind/symmetric/io/data/writer/DatabaseWriterFilterAdapter."<init>":()V
       4: return

  public boolean beforeWrite(org.jumpmind.symmetric.io.data.DataContext, org.jumpmind.db.model.Table, org.jumpmind.symmetric.io.data.CsvData);
    Code:
       0: aload_2
       1: invokevirtual #2                  // Method org/jumpmind/db/model/Table.getName:()Ljava/lang/String;
       4: aload_0
       5: getfield      #3                  // Field tablePrefix:Ljava/lang/String;
       8: invokevirtual #4                  // Method java/lang/String.startsWith:(Ljava/lang/String;)Z
      11: ifne          65
      14: aload_1
      15: invokevirtual #5                  // Method org/jumpmind/symmetric/io/data/DataContext.getBatch:()Lorg/jumpmind/symmetric/io/data/Batch;
      18: astore        4
      20: aload         4
      22: invokevirtual #6                  // Method org/jumpmind/symmetric/io/data/Batch.getNodeId:()Ljava/lang/String;
      25: astore        5
      27: aload_2
      28: aload_0
      29: getfield      #7                  // Field schemaPrefix:Ljava/lang/String;
      32: ifnull        60
      35: new           #8                  // class java/lang/StringBuilder
      38: dup
      39: invokespecial #9                  // Method java/lang/StringBuilder."<init>":()V
      42: aload_0
      43: getfield      #7                  // Field schemaPrefix:Ljava/lang/String;
      46: invokevirtual #10                 // Method java/lang/StringBuilder.append:(Ljava/lang/String;)Ljava/lang/StringBuilder;
      49: aload         5
      51: invokevirtual #10                 // Method java/lang/StringBuilder.append:(Ljava/lang/String;)Ljava/lang/StringBuilder;
      54: invokevirtual #11                 // Method java/lang/StringBuilder.toString:()Ljava/lang/String;
      57: goto          62
      60: aload         5
      62: invokevirtual #12                 // Method org/jumpmind/db/model/Table.setSchema:(Ljava/lang/String;)V
      65: iconst_1
      66: ireturn

  public void setTablePrefix(java.lang.String);
    Code:
       0: aload_0
       1: aload_1
       2: putfield      #3                  // Field tablePrefix:Ljava/lang/String;
       5: return

  public void setSchemaPrefix(java.lang.String);
    Code:
       0: aload_0
       1: aload_1
       2: putfield      #7                  // Field schemaPrefix:Ljava/lang/String;
       5: return
}
