Compiled from "EnumUtils.java"
public class nl.basjes.shaded.org.yaml.snakeyaml.util.EnumUtils {
  public nl.basjes.shaded.org.yaml.snakeyaml.util.EnumUtils();
    Code:
       0: aload_0
       1: invokespecial #9                  // Method java/lang/Object."<init>":()V
       4: return

  public static <T extends java.lang.Enum<T>> T findEnumInsensitiveCase(java.lang.Class<T>, java.lang.String);
    Code:
       0: aload_0
       1: invokevirtual #20                 // Method java/lang/Class.getEnumConstants:()[Ljava/lang/Object;
       4: checkcast     #22                 // class "[Ljava/lang/Enum;"
       7: astore_2
       8: aload_2
       9: arraylength
      10: istore_3
      11: iconst_0
      12: istore        4
      14: iload         4
      16: iload_3
      17: if_icmpge     47
      20: aload_2
      21: iload         4
      23: aaload
      24: astore        5
      26: aload         5
      28: invokevirtual #28                 // Method java/lang/Enum.name:()Ljava/lang/String;
      31: aload_1
      32: invokevirtual #34                 // Method java/lang/String.compareToIgnoreCase:(Ljava/lang/String;)I
      35: ifne          41
      38: aload         5
      40: areturn
      41: iinc          4, 1
      44: goto          14
      47: new           #36                 // class java/lang/IllegalArgumentException
      50: dup
      51: new           #38                 // class java/lang/StringBuilder
      54: dup
      55: invokespecial #39                 // Method java/lang/StringBuilder."<init>":()V
      58: ldc           #41                 // String No enum constant
      60: invokevirtual #45                 // Method java/lang/StringBuilder.append:(Ljava/lang/String;)Ljava/lang/StringBuilder;
      63: aload_0
      64: invokevirtual #48                 // Method java/lang/Class.getCanonicalName:()Ljava/lang/String;
      67: invokevirtual #45                 // Method java/lang/StringBuilder.append:(Ljava/lang/String;)Ljava/lang/StringBuilder;
      70: ldc           #50                 // String .
      72: invokevirtual #45                 // Method java/lang/StringBuilder.append:(Ljava/lang/String;)Ljava/lang/StringBuilder;
      75: aload_1
      76: invokevirtual #45                 // Method java/lang/StringBuilder.append:(Ljava/lang/String;)Ljava/lang/StringBuilder;
      79: invokevirtual #53                 // Method java/lang/StringBuilder.toString:()Ljava/lang/String;
      82: invokespecial #56                 // Method java/lang/IllegalArgumentException."<init>":(Ljava/lang/String;)V
      85: athrow
}
