Compiled from "RBGNonce.java"
public class org.cryptacular.generator.sp80038a.RBGNonce implements org.cryptacular.generator.Nonce {
  private final int length;

  private final org.bouncycastle.crypto.prng.drbg.SP80090DRBG rbg;

  public org.cryptacular.generator.sp80038a.RBGNonce();
    Code:
       0: aload_0
       1: bipush        16
       3: invokespecial #1                  // Method "<init>":(I)V
       6: return

  public org.cryptacular.generator.sp80038a.RBGNonce(int);
    Code:
       0: aload_0
       1: invokespecial #2                  // Method java/lang/Object."<init>":()V
       4: iload_1
       5: iconst_1
       6: if_icmpge     19
       9: new           #3                  // class java/lang/IllegalArgumentException
      12: dup
      13: ldc           #4                  // String Length must be positive
      15: invokespecial #5                  // Method java/lang/IllegalArgumentException."<init>":(Ljava/lang/String;)V
      18: athrow
      19: aload_0
      20: iload_1
      21: putfield      #6                  // Field length:I
      24: aload_0
      25: iload_1
      26: invokestatic  #7                  // Method org/cryptacular/util/NonceUtil.newRBG:(I)Lorg/bouncycastle/crypto/prng/drbg/SP80090DRBG;
      29: putfield      #8                  // Field rbg:Lorg/bouncycastle/crypto/prng/drbg/SP80090DRBG;
      32: return

  public byte[] generate() throws org.cryptacular.generator.LimitException;
    Code:
       0: aload_0
       1: getfield      #6                  // Field length:I
       4: newarray       byte
       6: astore_1
       7: aload_0
       8: getfield      #8                  // Field rbg:Lorg/bouncycastle/crypto/prng/drbg/SP80090DRBG;
      11: dup
      12: astore_2
      13: monitorenter
      14: aload_0
      15: getfield      #8                  // Field rbg:Lorg/bouncycastle/crypto/prng/drbg/SP80090DRBG;
      18: aload_1
      19: aconst_null
      20: iconst_0
      21: invokeinterface #9,  4            // InterfaceMethod org/bouncycastle/crypto/prng/drbg/SP80090DRBG.generate:([B[BZ)I
      26: pop
      27: aload_2
      28: monitorexit
      29: goto          37
      32: astore_3
      33: aload_2
      34: monitorexit
      35: aload_3
      36: athrow
      37: aload_1
      38: areturn
    Exception table:
       from    to  target type
          14    29    32   any
          32    35    32   any

  public int getLength();
    Code:
       0: aload_0
       1: getfield      #6                  // Field length:I
       4: ireturn
}
