Compiled from "InitMethodMetaData.java"
public class org.jboss.metadata.ejb.spec.InitMethodMetaData extends org.jboss.metadata.javaee.support.IdMetaDataImpl {
  private static final long serialVersionUID;

  private org.jboss.metadata.ejb.spec.NamedMethodMetaData createMethod;

  private org.jboss.metadata.ejb.spec.NamedMethodMetaData beanMethod;

  public org.jboss.metadata.ejb.spec.InitMethodMetaData();
    Code:
       0: aload_0
       1: invokespecial #1                  // Method org/jboss/metadata/javaee/support/IdMetaDataImpl."<init>":()V
       4: return

  public org.jboss.metadata.ejb.spec.NamedMethodMetaData getCreateMethod();
    Code:
       0: aload_0
       1: getfield      #2                  // Field createMethod:Lorg/jboss/metadata/ejb/spec/NamedMethodMetaData;
       4: areturn

  public void setCreateMethod(org.jboss.metadata.ejb.spec.NamedMethodMetaData);
    Code:
       0: aload_1
       1: ifnonnull     14
       4: new           #3                  // class java/lang/IllegalArgumentException
       7: dup
       8: ldc           #4                  // String Null createMethod
      10: invokespecial #5                  // Method java/lang/IllegalArgumentException."<init>":(Ljava/lang/String;)V
      13: athrow
      14: aload_0
      15: aload_1
      16: putfield      #2                  // Field createMethod:Lorg/jboss/metadata/ejb/spec/NamedMethodMetaData;
      19: return

  public org.jboss.metadata.ejb.spec.NamedMethodMetaData getBeanMethod();
    Code:
       0: aload_0
       1: getfield      #6                  // Field beanMethod:Lorg/jboss/metadata/ejb/spec/NamedMethodMetaData;
       4: areturn

  public void setBeanMethod(org.jboss.metadata.ejb.spec.NamedMethodMetaData);
    Code:
       0: aload_1
       1: ifnonnull     14
       4: new           #3                  // class java/lang/IllegalArgumentException
       7: dup
       8: ldc           #7                  // String Null beanMethod
      10: invokespecial #5                  // Method java/lang/IllegalArgumentException."<init>":(Ljava/lang/String;)V
      13: athrow
      14: aload_0
      15: aload_1
      16: putfield      #6                  // Field beanMethod:Lorg/jboss/metadata/ejb/spec/NamedMethodMetaData;
      19: return
}
