Compiled from "RelationRoleMetaData.java"
public class org.jboss.metadata.ejb.spec.RelationRoleMetaData extends org.jboss.metadata.javaee.support.NamedMetaDataWithDescriptions {
  private static final long serialVersionUID;

  private org.jboss.metadata.ejb.spec.MultiplicityType multiplicityType;

  private org.jboss.metadata.javaee.spec.EmptyMetaData cascadedDelete;

  private org.jboss.metadata.ejb.spec.RelationMetaData relation;

  private org.jboss.metadata.ejb.spec.RelationRoleSourceMetaData roleSource;

  private org.jboss.metadata.ejb.spec.CMRFieldMetaData cmrField;

  public org.jboss.metadata.ejb.spec.RelationRoleMetaData();
    Code:
       0: aload_0
       1: invokespecial #1                  // Method org/jboss/metadata/javaee/support/NamedMetaDataWithDescriptions."<init>":()V
       4: return

  public java.lang.String getEjbRelationshipRoleName();
    Code:
       0: aload_0
       1: invokevirtual #2                  // Method getName:()Ljava/lang/String;
       4: areturn

  public void setEjbRelationshipRoleName(java.lang.String);
    Code:
       0: aload_0
       1: aload_1
       2: invokevirtual #3                  // Method setName:(Ljava/lang/String;)V
       5: return

  public org.jboss.metadata.ejb.spec.MultiplicityType getMultiplicity();
    Code:
       0: aload_0
       1: getfield      #4                  // Field multiplicityType:Lorg/jboss/metadata/ejb/spec/MultiplicityType;
       4: areturn

  public void setMultiplicity(org.jboss.metadata.ejb.spec.MultiplicityType);
    Code:
       0: aload_1
       1: ifnonnull     14
       4: new           #5                  // class java/lang/IllegalArgumentException
       7: dup
       8: ldc           #6                  // String Null multiplicityType
      10: invokespecial #7                  // Method java/lang/IllegalArgumentException."<init>":(Ljava/lang/String;)V
      13: athrow
      14: aload_0
      15: aload_1
      16: putfield      #4                  // Field multiplicityType:Lorg/jboss/metadata/ejb/spec/MultiplicityType;
      19: return

  public boolean isMultiplicityOne();
    Code:
       0: aload_0
       1: getfield      #4                  // Field multiplicityType:Lorg/jboss/metadata/ejb/spec/MultiplicityType;
       4: getstatic     #8                  // Field org/jboss/metadata/ejb/spec/MultiplicityType.One:Lorg/jboss/metadata/ejb/spec/MultiplicityType;
       7: if_acmpne     14
      10: iconst_1
      11: goto          15
      14: iconst_0
      15: ireturn

  public boolean isMultiplicityMany();
    Code:
       0: aload_0
       1: getfield      #4                  // Field multiplicityType:Lorg/jboss/metadata/ejb/spec/MultiplicityType;
       4: getstatic     #9                  // Field org/jboss/metadata/ejb/spec/MultiplicityType.Many:Lorg/jboss/metadata/ejb/spec/MultiplicityType;
       7: if_acmpne     14
      10: iconst_1
      11: goto          15
      14: iconst_0
      15: ireturn

  public boolean isCascadedDelete();
    Code:
       0: aload_0
       1: getfield      #10                 // Field cascadedDelete:Lorg/jboss/metadata/javaee/spec/EmptyMetaData;
       4: ifnull        11
       7: iconst_1
       8: goto          12
      11: iconst_0
      12: ireturn

  public org.jboss.metadata.javaee.spec.EmptyMetaData getCascadeDelete();
    Code:
       0: aload_0
       1: getfield      #10                 // Field cascadedDelete:Lorg/jboss/metadata/javaee/spec/EmptyMetaData;
       4: areturn

  public void setCascadeDelete(org.jboss.metadata.javaee.spec.EmptyMetaData);
    Code:
       0: aload_0
       1: aload_1
       2: putfield      #10                 // Field cascadedDelete:Lorg/jboss/metadata/javaee/spec/EmptyMetaData;
       5: return

  public org.jboss.metadata.ejb.spec.RelationMetaData getRelation();
    Code:
       0: aload_0
       1: getfield      #11                 // Field relation:Lorg/jboss/metadata/ejb/spec/RelationMetaData;
       4: areturn

  void setRelation(org.jboss.metadata.ejb.spec.RelationMetaData);
    Code:
       0: aload_1
       1: ifnonnull     14
       4: new           #5                  // class java/lang/IllegalArgumentException
       7: dup
       8: ldc           #12                 // String Null relation
      10: invokespecial #7                  // Method java/lang/IllegalArgumentException."<init>":(Ljava/lang/String;)V
      13: athrow
      14: aload_0
      15: aload_1
      16: putfield      #11                 // Field relation:Lorg/jboss/metadata/ejb/spec/RelationMetaData;
      19: return

  public org.jboss.metadata.ejb.spec.RelationRoleMetaData getRelatedRole();
    Code:
       0: aload_0
       1: getfield      #11                 // Field relation:Lorg/jboss/metadata/ejb/spec/RelationMetaData;
       4: ifnonnull     17
       7: new           #13                 // class java/lang/IllegalStateException
      10: dup
      11: ldc           #14                 // String Relation has not been set
      13: invokespecial #15                 // Method java/lang/IllegalStateException."<init>":(Ljava/lang/String;)V
      16: athrow
      17: aload_0
      18: getfield      #11                 // Field relation:Lorg/jboss/metadata/ejb/spec/RelationMetaData;
      21: aload_0
      22: invokevirtual #16                 // Method org/jboss/metadata/ejb/spec/RelationMetaData.getRelatedRole:(Lorg/jboss/metadata/ejb/spec/RelationRoleMetaData;)Lorg/jboss/metadata/ejb/spec/RelationRoleMetaData;
      25: areturn

  public org.jboss.metadata.ejb.spec.RelationRoleSourceMetaData getRoleSource();
    Code:
       0: aload_0
       1: getfield      #17                 // Field roleSource:Lorg/jboss/metadata/ejb/spec/RelationRoleSourceMetaData;
       4: areturn

  public void setRoleSource(org.jboss.metadata.ejb.spec.RelationRoleSourceMetaData);
    Code:
       0: aload_1
       1: ifnonnull     14
       4: new           #5                  // class java/lang/IllegalArgumentException
       7: dup
       8: ldc           #18                 // String Null roleSource
      10: invokespecial #7                  // Method java/lang/IllegalArgumentException."<init>":(Ljava/lang/String;)V
      13: athrow
      14: aload_0
      15: aload_1
      16: putfield      #17                 // Field roleSource:Lorg/jboss/metadata/ejb/spec/RelationRoleSourceMetaData;
      19: return

  public org.jboss.metadata.ejb.spec.CMRFieldMetaData getCmrField();
    Code:
       0: aload_0
       1: getfield      #19                 // Field cmrField:Lorg/jboss/metadata/ejb/spec/CMRFieldMetaData;
       4: areturn

  public void setCmrField(org.jboss.metadata.ejb.spec.CMRFieldMetaData);
    Code:
       0: aload_1
       1: ifnonnull     14
       4: new           #5                  // class java/lang/IllegalArgumentException
       7: dup
       8: ldc           #20                 // String Null cmrField
      10: invokespecial #7                  // Method java/lang/IllegalArgumentException."<init>":(Ljava/lang/String;)V
      13: athrow
      14: aload_0
      15: aload_1
      16: putfield      #19                 // Field cmrField:Lorg/jboss/metadata/ejb/spec/CMRFieldMetaData;
      19: return
}
