Compiled from "ArrayUtils.java"
public final class org.thymeleaf.util.ArrayUtils {
  public static java.lang.Object[] toArray(java.lang.Object);
    Code:
       0: aconst_null
       1: aload_0
       2: invokestatic  #1                  // Method toArray:(Ljava/lang/Class;Ljava/lang/Object;)[Ljava/lang/Object;
       5: areturn

  public static java.lang.Object[] toStringArray(java.lang.Object);
    Code:
       0: ldc           #2                  // class java/lang/String
       2: aload_0
       3: invokestatic  #1                  // Method toArray:(Ljava/lang/Class;Ljava/lang/Object;)[Ljava/lang/Object;
       6: areturn

  public static java.lang.Object[] toIntegerArray(java.lang.Object);
    Code:
       0: ldc           #3                  // class java/lang/Integer
       2: aload_0
       3: invokestatic  #1                  // Method toArray:(Ljava/lang/Class;Ljava/lang/Object;)[Ljava/lang/Object;
       6: areturn

  public static java.lang.Object[] toLongArray(java.lang.Object);
    Code:
       0: ldc           #4                  // class java/lang/Long
       2: aload_0
       3: invokestatic  #1                  // Method toArray:(Ljava/lang/Class;Ljava/lang/Object;)[Ljava/lang/Object;
       6: areturn

  public static java.lang.Object[] toDoubleArray(java.lang.Object);
    Code:
       0: ldc           #5                  // class java/lang/Double
       2: aload_0
       3: invokestatic  #1                  // Method toArray:(Ljava/lang/Class;Ljava/lang/Object;)[Ljava/lang/Object;
       6: areturn

  public static java.lang.Object[] toFloatArray(java.lang.Object);
    Code:
       0: ldc           #6                  // class java/lang/Float
       2: aload_0
       3: invokestatic  #1                  // Method toArray:(Ljava/lang/Class;Ljava/lang/Object;)[Ljava/lang/Object;
       6: areturn

  public static java.lang.Object[] toBooleanArray(java.lang.Object);
    Code:
       0: ldc           #7                  // class java/lang/Boolean
       2: aload_0
       3: invokestatic  #1                  // Method toArray:(Ljava/lang/Class;Ljava/lang/Object;)[Ljava/lang/Object;
       6: areturn

  public static int length(java.lang.Object[]);
    Code:
       0: aload_0
       1: ldc           #8                  // String Cannot get array length of null
       3: invokestatic  #9                  // Method org/thymeleaf/util/Validate.notNull:(Ljava/lang/Object;Ljava/lang/String;)V
       6: aload_0
       7: arraylength
       8: ireturn

  public static boolean isEmpty(java.lang.Object[]);
    Code:
       0: aload_0
       1: ifnull        9
       4: aload_0
       5: arraylength
       6: ifgt          13
       9: iconst_1
      10: goto          14
      13: iconst_0
      14: ireturn

  public static boolean contains(java.lang.Object[], java.lang.Object);
    Code:
       0: aload_0
       1: ldc           #10                 // String Cannot execute array contains: target is null
       3: invokestatic  #9                  // Method org/thymeleaf/util/Validate.notNull:(Ljava/lang/Object;Ljava/lang/String;)V
       6: aload_1
       7: ifnonnull     45
      10: aload_0
      11: astore_2
      12: aload_2
      13: arraylength
      14: istore_3
      15: iconst_0
      16: istore        4
      18: iload         4
      20: iload_3
      21: if_icmpge     43
      24: aload_2
      25: iload         4
      27: aaload
      28: astore        5
      30: aload         5
      32: ifnonnull     37
      35: iconst_1
      36: ireturn
      37: iinc          4, 1
      40: goto          18
      43: iconst_0
      44: ireturn
      45: aload_0
      46: astore_2
      47: aload_2
      48: arraylength
      49: istore_3
      50: iconst_0
      51: istore        4
      53: iload         4
      55: iload_3
      56: if_icmpge     82
      59: aload_2
      60: iload         4
      62: aaload
      63: astore        5
      65: aload_1
      66: aload         5
      68: invokevirtual #11                 // Method java/lang/Object.equals:(Ljava/lang/Object;)Z
      71: ifeq          76
      74: iconst_1
      75: ireturn
      76: iinc          4, 1
      79: goto          53
      82: iconst_0
      83: ireturn

  public static boolean containsAll(java.lang.Object[], java.lang.Object[]);
    Code:
       0: aload_0
       1: ldc           #12                 // String Cannot execute array containsAll: target is null
       3: invokestatic  #9                  // Method org/thymeleaf/util/Validate.notNull:(Ljava/lang/Object;Ljava/lang/String;)V
       6: aload_1
       7: ldc           #13                 // String Cannot execute array containsAll: elements is null
       9: invokestatic  #9                  // Method org/thymeleaf/util/Validate.notNull:(Ljava/lang/Object;Ljava/lang/String;)V
      12: aload_0
      13: aload_1
      14: invokestatic  #14                 // Method java/util/Arrays.asList:([Ljava/lang/Object;)Ljava/util/List;
      17: invokestatic  #15                 // Method containsAll:([Ljava/lang/Object;Ljava/util/Collection;)Z
      20: ireturn

  public static boolean containsAll(java.lang.Object[], java.util.Collection<?>);
    Code:
       0: aload_0
       1: ldc           #10                 // String Cannot execute array contains: target is null
       3: invokestatic  #9                  // Method org/thymeleaf/util/Validate.notNull:(Ljava/lang/Object;Ljava/lang/String;)V
       6: aload_1
       7: ldc           #13                 // String Cannot execute array containsAll: elements is null
       9: invokestatic  #9                  // Method org/thymeleaf/util/Validate.notNull:(Ljava/lang/Object;Ljava/lang/String;)V
      12: new           #16                 // class java/util/HashSet
      15: dup
      16: aload_1
      17: invokespecial #17                 // Method java/util/HashSet."<init>":(Ljava/util/Collection;)V
      20: astore_2
      21: aload_2
      22: aload_0
      23: invokestatic  #14                 // Method java/util/Arrays.asList:([Ljava/lang/Object;)Ljava/util/List;
      26: invokeinterface #18,  2           // InterfaceMethod java/util/Set.removeAll:(Ljava/util/Collection;)Z
      31: pop
      32: aload_2
      33: invokeinterface #19,  1           // InterfaceMethod java/util/Set.isEmpty:()Z
      38: ireturn

  private static java.lang.Object[] toArray(java.lang.Class<?>, java.lang.Object);
    Code:
       0: aload_1
       1: ldc           #20                 // String Cannot convert null to array
       3: invokestatic  #9                  // Method org/thymeleaf/util/Validate.notNull:(Ljava/lang/Object;Ljava/lang/String;)V
       6: aload_1
       7: invokevirtual #21                 // Method java/lang/Object.getClass:()Ljava/lang/Class;
      10: invokevirtual #22                 // Method java/lang/Class.isArray:()Z
      13: ifeq          91
      16: aload_0
      17: ifnonnull     25
      20: aload_1
      21: checkcast     #23                 // class "[Ljava/lang/Object;"
      24: areturn
      25: aload_1
      26: invokevirtual #21                 // Method java/lang/Object.getClass:()Ljava/lang/Class;
      29: invokevirtual #24                 // Method java/lang/Class.getComponentType:()Ljava/lang/Class;
      32: astore_2
      33: aload_0
      34: aload_2
      35: invokevirtual #25                 // Method java/lang/Class.isAssignableFrom:(Ljava/lang/Class;)Z
      38: ifeq          46
      41: aload_1
      42: checkcast     #23                 // class "[Ljava/lang/Object;"
      45: areturn
      46: new           #26                 // class java/lang/IllegalArgumentException
      49: dup
      50: new           #27                 // class java/lang/StringBuilder
      53: dup
      54: invokespecial #28                 // Method java/lang/StringBuilder."<init>":()V
      57: ldc           #29                 // String Cannot convert object of class \"
      59: invokevirtual #30                 // Method java/lang/StringBuilder.append:(Ljava/lang/String;)Ljava/lang/StringBuilder;
      62: aload_2
      63: invokevirtual #31                 // Method java/lang/Class.getName:()Ljava/lang/String;
      66: invokevirtual #30                 // Method java/lang/StringBuilder.append:(Ljava/lang/String;)Ljava/lang/StringBuilder;
      69: ldc           #32                 // String []\" to an array of
      71: invokevirtual #30                 // Method java/lang/StringBuilder.append:(Ljava/lang/String;)Ljava/lang/StringBuilder;
      74: aload_0
      75: invokevirtual #21                 // Method java/lang/Object.getClass:()Ljava/lang/Class;
      78: invokevirtual #33                 // Method java/lang/Class.getSimpleName:()Ljava/lang/String;
      81: invokevirtual #30                 // Method java/lang/StringBuilder.append:(Ljava/lang/String;)Ljava/lang/StringBuilder;
      84: invokevirtual #34                 // Method java/lang/StringBuilder.toString:()Ljava/lang/String;
      87: invokespecial #35                 // Method java/lang/IllegalArgumentException."<init>":(Ljava/lang/String;)V
      90: athrow
      91: aload_1
      92: instanceof    #36                 // class java/lang/Iterable
      95: ifeq          242
      98: aconst_null
      99: astore_2
     100: aload_1
     101: checkcast     #36                 // class java/lang/Iterable
     104: astore_3
     105: new           #37                 // class java/util/ArrayList
     108: dup
     109: iconst_5
     110: invokespecial #38                 // Method java/util/ArrayList."<init>":(I)V
     113: astore        4
     115: aload_3
     116: invokeinterface #39,  1           // InterfaceMethod java/lang/Iterable.iterator:()Ljava/util/Iterator;
     121: astore        5
     123: aload         5
     125: invokeinterface #40,  1           // InterfaceMethod java/util/Iterator.hasNext:()Z
     130: ifeq          201
     133: aload         5
     135: invokeinterface #41,  1           // InterfaceMethod java/util/Iterator.next:()Ljava/lang/Object;
     140: astore        6
     142: aload_0
     143: ifnonnull     188
     146: aload         6
     148: ifnull        188
     151: aload_2
     152: ifnonnull     164
     155: aload         6
     157: invokevirtual #21                 // Method java/lang/Object.getClass:()Ljava/lang/Class;
     160: astore_2
     161: goto          188
     164: aload_2
     165: ldc           #42                 // class java/lang/Object
     167: invokevirtual #11                 // Method java/lang/Object.equals:(Ljava/lang/Object;)Z
     170: ifne          188
     173: aload_2
     174: aload         6
     176: invokevirtual #21                 // Method java/lang/Object.getClass:()Ljava/lang/Class;
     179: invokevirtual #11                 // Method java/lang/Object.equals:(Ljava/lang/Object;)Z
     182: ifne          188
     185: ldc           #42                 // class java/lang/Object
     187: astore_2
     188: aload         4
     190: aload         6
     192: invokeinterface #43,  2           // InterfaceMethod java/util/List.add:(Ljava/lang/Object;)Z
     197: pop
     198: goto          123
     201: aload_2
     202: ifnonnull     216
     205: aload_0
     206: ifnull        213
     209: aload_0
     210: goto          215
     213: ldc           #42                 // class java/lang/Object
     215: astore_2
     216: aload_2
     217: aload         4
     219: invokeinterface #44,  1           // InterfaceMethod java/util/List.size:()I
     224: invokestatic  #45                 // Method java/lang/reflect/Array.newInstance:(Ljava/lang/Class;I)Ljava/lang/Object;
     227: checkcast     #23                 // class "[Ljava/lang/Object;"
     230: astore        5
     232: aload         4
     234: aload         5
     236: invokeinterface #46,  2           // InterfaceMethod java/util/List.toArray:([Ljava/lang/Object;)[Ljava/lang/Object;
     241: areturn
     242: new           #26                 // class java/lang/IllegalArgumentException
     245: dup
     246: new           #27                 // class java/lang/StringBuilder
     249: dup
     250: invokespecial #28                 // Method java/lang/StringBuilder."<init>":()V
     253: ldc           #29                 // String Cannot convert object of class \"
     255: invokevirtual #30                 // Method java/lang/StringBuilder.append:(Ljava/lang/String;)Ljava/lang/StringBuilder;
     258: aload_1
     259: invokevirtual #21                 // Method java/lang/Object.getClass:()Ljava/lang/Class;
     262: invokevirtual #31                 // Method java/lang/Class.getName:()Ljava/lang/String;
     265: invokevirtual #30                 // Method java/lang/StringBuilder.append:(Ljava/lang/String;)Ljava/lang/StringBuilder;
     268: ldc           #47                 // String \" to an array
     270: invokevirtual #30                 // Method java/lang/StringBuilder.append:(Ljava/lang/String;)Ljava/lang/StringBuilder;
     273: aload_0
     274: ifnonnull     282
     277: ldc           #48                 // String
     279: goto          307
     282: new           #27                 // class java/lang/StringBuilder
     285: dup
     286: invokespecial #28                 // Method java/lang/StringBuilder."<init>":()V
     289: ldc           #49                 // String  of
     291: invokevirtual #30                 // Method java/lang/StringBuilder.append:(Ljava/lang/String;)Ljava/lang/StringBuilder;
     294: aload_0
     295: invokevirtual #21                 // Method java/lang/Object.getClass:()Ljava/lang/Class;
     298: invokevirtual #33                 // Method java/lang/Class.getSimpleName:()Ljava/lang/String;
     301: invokevirtual #30                 // Method java/lang/StringBuilder.append:(Ljava/lang/String;)Ljava/lang/StringBuilder;
     304: invokevirtual #34                 // Method java/lang/StringBuilder.toString:()Ljava/lang/String;
     307: invokevirtual #30                 // Method java/lang/StringBuilder.append:(Ljava/lang/String;)Ljava/lang/StringBuilder;
     310: invokevirtual #34                 // Method java/lang/StringBuilder.toString:()Ljava/lang/String;
     313: invokespecial #35                 // Method java/lang/IllegalArgumentException."<init>":(Ljava/lang/String;)V
     316: athrow

  public static <T, X> X[] copyOf(T[], int, java.lang.Class<? extends X[]>);
    Code:
       0: aload_2
       1: ldc           #23                 // class "[Ljava/lang/Object;"
       3: if_acmpne     13
       6: iload_1
       7: anewarray     #42                 // class java/lang/Object
      10: goto          24
      13: aload_2
      14: invokevirtual #24                 // Method java/lang/Class.getComponentType:()Ljava/lang/Class;
      17: iload_1
      18: invokestatic  #45                 // Method java/lang/reflect/Array.newInstance:(Ljava/lang/Class;I)Ljava/lang/Object;
      21: checkcast     #23                 // class "[Ljava/lang/Object;"
      24: astore_3
      25: aload_0
      26: iconst_0
      27: aload_3
      28: iconst_0
      29: aload_0
      30: arraylength
      31: iload_1
      32: invokestatic  #50                 // Method java/lang/Math.min:(II)I
      35: invokestatic  #51                 // Method java/lang/System.arraycopy:(Ljava/lang/Object;ILjava/lang/Object;II)V
      38: aload_3
      39: areturn

  public static <T> T[] copyOf(T[], int);
    Code:
       0: aload_0
       1: iload_1
       2: aload_0
       3: invokevirtual #21                 // Method java/lang/Object.getClass:()Ljava/lang/Class;
       6: invokestatic  #52                 // Method copyOf:([Ljava/lang/Object;ILjava/lang/Class;)[Ljava/lang/Object;
       9: areturn

  public static char[] copyOf(char[], int);
    Code:
       0: iload_1
       1: newarray       char
       3: astore_2
       4: aload_0
       5: iconst_0
       6: aload_2
       7: iconst_0
       8: aload_0
       9: arraylength
      10: iload_1
      11: invokestatic  #50                 // Method java/lang/Math.min:(II)I
      14: invokestatic  #51                 // Method java/lang/System.arraycopy:(Ljava/lang/Object;ILjava/lang/Object;II)V
      17: aload_2
      18: areturn

  public static char[] copyOfRange(char[], int, int);
    Code:
       0: iload_2
       1: iload_1
       2: isub
       3: istore_3
       4: iload_3
       5: ifge          44
       8: new           #26                 // class java/lang/IllegalArgumentException
      11: dup
      12: new           #27                 // class java/lang/StringBuilder
      15: dup
      16: invokespecial #28                 // Method java/lang/StringBuilder."<init>":()V
      19: ldc           #53                 // String Cannot copy array range with indexes
      21: invokevirtual #30                 // Method java/lang/StringBuilder.append:(Ljava/lang/String;)Ljava/lang/StringBuilder;
      24: iload_1
      25: invokevirtual #54                 // Method java/lang/StringBuilder.append:(I)Ljava/lang/StringBuilder;
      28: ldc           #55                 // String  and
      30: invokevirtual #30                 // Method java/lang/StringBuilder.append:(Ljava/lang/String;)Ljava/lang/StringBuilder;
      33: iload_2
      34: invokevirtual #54                 // Method java/lang/StringBuilder.append:(I)Ljava/lang/StringBuilder;
      37: invokevirtual #34                 // Method java/lang/StringBuilder.toString:()Ljava/lang/String;
      40: invokespecial #35                 // Method java/lang/IllegalArgumentException."<init>":(Ljava/lang/String;)V
      43: athrow
      44: iload_3
      45: newarray       char
      47: astore        4
      49: aload_0
      50: iload_1
      51: aload         4
      53: iconst_0
      54: aload_0
      55: arraylength
      56: iload_1
      57: isub
      58: iload_3
      59: invokestatic  #50                 // Method java/lang/Math.min:(II)I
      62: invokestatic  #51                 // Method java/lang/System.arraycopy:(Ljava/lang/Object;ILjava/lang/Object;II)V
      65: aload         4
      67: areturn

  private org.thymeleaf.util.ArrayUtils();
    Code:
       0: aload_0
       1: invokespecial #56                 // Method java/lang/Object."<init>":()V
       4: return
}
