Compiled from "NumberPointType.java"
public final class org.thymeleaf.util.NumberPointType extends java.lang.Enum<org.thymeleaf.util.NumberPointType> {
  public static final org.thymeleaf.util.NumberPointType POINT;

  public static final org.thymeleaf.util.NumberPointType COMMA;

  public static final org.thymeleaf.util.NumberPointType WHITESPACE;

  public static final org.thymeleaf.util.NumberPointType NONE;

  public static final org.thymeleaf.util.NumberPointType DEFAULT;

  private final java.lang.String name;

  private static final org.thymeleaf.util.NumberPointType[] $VALUES;

  public static org.thymeleaf.util.NumberPointType[] values();
    Code:
       0: getstatic     #1                  // Field $VALUES:[Lorg/thymeleaf/util/NumberPointType;
       3: invokevirtual #2                  // Method "[Lorg/thymeleaf/util/NumberPointType;".clone:()Ljava/lang/Object;
       6: checkcast     #3                  // class "[Lorg/thymeleaf/util/NumberPointType;"
       9: areturn

  public static org.thymeleaf.util.NumberPointType valueOf(java.lang.String);
    Code:
       0: ldc           #4                  // class org/thymeleaf/util/NumberPointType
       2: aload_0
       3: invokestatic  #5                  // Method java/lang/Enum.valueOf:(Ljava/lang/Class;Ljava/lang/String;)Ljava/lang/Enum;
       6: checkcast     #4                  // class org/thymeleaf/util/NumberPointType
       9: areturn

  public static org.thymeleaf.util.NumberPointType match(java.lang.String);
    Code:
       0: ldc           #6                  // String NONE
       2: aload_0
       3: invokevirtual #7                  // Method java/lang/String.equals:(Ljava/lang/Object;)Z
       6: ifeq          13
       9: getstatic     #8                  // Field NONE:Lorg/thymeleaf/util/NumberPointType;
      12: areturn
      13: ldc           #9                  // String DEFAULT
      15: aload_0
      16: invokevirtual #7                  // Method java/lang/String.equals:(Ljava/lang/Object;)Z
      19: ifeq          26
      22: getstatic     #10                 // Field DEFAULT:Lorg/thymeleaf/util/NumberPointType;
      25: areturn
      26: ldc           #11                 // String POINT
      28: aload_0
      29: invokevirtual #7                  // Method java/lang/String.equals:(Ljava/lang/Object;)Z
      32: ifeq          39
      35: getstatic     #12                 // Field POINT:Lorg/thymeleaf/util/NumberPointType;
      38: areturn
      39: ldc           #13                 // String COMMA
      41: aload_0
      42: invokevirtual #7                  // Method java/lang/String.equals:(Ljava/lang/Object;)Z
      45: ifeq          52
      48: getstatic     #14                 // Field COMMA:Lorg/thymeleaf/util/NumberPointType;
      51: areturn
      52: ldc           #15                 // String WHITESPACE
      54: aload_0
      55: invokevirtual #7                  // Method java/lang/String.equals:(Ljava/lang/Object;)Z
      58: ifeq          65
      61: getstatic     #16                 // Field WHITESPACE:Lorg/thymeleaf/util/NumberPointType;
      64: areturn
      65: aconst_null
      66: areturn

  private org.thymeleaf.util.NumberPointType(java.lang.String);
    Code:
       0: aload_0
       1: aload_1
       2: iload_2
       3: invokespecial #17                 // Method java/lang/Enum."<init>":(Ljava/lang/String;I)V
       6: aload_0
       7: aload_3
       8: putfield      #18                 // Field name:Ljava/lang/String;
      11: return

  public java.lang.String getName();
    Code:
       0: aload_0
       1: getfield      #18                 // Field name:Ljava/lang/String;
       4: areturn

  public java.lang.String toString();
    Code:
       0: aload_0
       1: getfield      #18                 // Field name:Ljava/lang/String;
       4: areturn

  static {};
    Code:
       0: new           #4                  // class org/thymeleaf/util/NumberPointType
       3: dup
       4: ldc           #11                 // String POINT
       6: iconst_0
       7: ldc           #11                 // String POINT
       9: invokespecial #19                 // Method "<init>":(Ljava/lang/String;ILjava/lang/String;)V
      12: putstatic     #12                 // Field POINT:Lorg/thymeleaf/util/NumberPointType;
      15: new           #4                  // class org/thymeleaf/util/NumberPointType
      18: dup
      19: ldc           #13                 // String COMMA
      21: iconst_1
      22: ldc           #13                 // String COMMA
      24: invokespecial #19                 // Method "<init>":(Ljava/lang/String;ILjava/lang/String;)V
      27: putstatic     #14                 // Field COMMA:Lorg/thymeleaf/util/NumberPointType;
      30: new           #4                  // class org/thymeleaf/util/NumberPointType
      33: dup
      34: ldc           #15                 // String WHITESPACE
      36: iconst_2
      37: ldc           #15                 // String WHITESPACE
      39: invokespecial #19                 // Method "<init>":(Ljava/lang/String;ILjava/lang/String;)V
      42: putstatic     #16                 // Field WHITESPACE:Lorg/thymeleaf/util/NumberPointType;
      45: new           #4                  // class org/thymeleaf/util/NumberPointType
      48: dup
      49: ldc           #6                  // String NONE
      51: iconst_3
      52: ldc           #6                  // String NONE
      54: invokespecial #19                 // Method "<init>":(Ljava/lang/String;ILjava/lang/String;)V
      57: putstatic     #8                  // Field NONE:Lorg/thymeleaf/util/NumberPointType;
      60: new           #4                  // class org/thymeleaf/util/NumberPointType
      63: dup
      64: ldc           #9                  // String DEFAULT
      66: iconst_4
      67: ldc           #9                  // String DEFAULT
      69: invokespecial #19                 // Method "<init>":(Ljava/lang/String;ILjava/lang/String;)V
      72: putstatic     #10                 // Field DEFAULT:Lorg/thymeleaf/util/NumberPointType;
      75: iconst_5
      76: anewarray     #4                  // class org/thymeleaf/util/NumberPointType
      79: dup
      80: iconst_0
      81: getstatic     #12                 // Field POINT:Lorg/thymeleaf/util/NumberPointType;
      84: aastore
      85: dup
      86: iconst_1
      87: getstatic     #14                 // Field COMMA:Lorg/thymeleaf/util/NumberPointType;
      90: aastore
      91: dup
      92: iconst_2
      93: getstatic     #16                 // Field WHITESPACE:Lorg/thymeleaf/util/NumberPointType;
      96: aastore
      97: dup
      98: iconst_3
      99: getstatic     #8                  // Field NONE:Lorg/thymeleaf/util/NumberPointType;
     102: aastore
     103: dup
     104: iconst_4
     105: getstatic     #10                 // Field DEFAULT:Lorg/thymeleaf/util/NumberPointType;
     108: aastore
     109: putstatic     #1                  // Field $VALUES:[Lorg/thymeleaf/util/NumberPointType;
     112: return
}
