Compiled from "ProcessorConfigurationUtils.java"
abstract class org.thymeleaf.util.ProcessorConfigurationUtils$AbstractProcessorWrapper implements org.thymeleaf.processor.IProcessor,org.thymeleaf.engine.IAttributeDefinitionsAware,org.thymeleaf.engine.IElementDefinitionsAware {
  private final int dialectPrecedence;

  private final int processorPrecedence;

  private final org.thymeleaf.dialect.IProcessorDialect dialect;

  private final org.thymeleaf.processor.IProcessor processor;

  org.thymeleaf.util.ProcessorConfigurationUtils$AbstractProcessorWrapper(org.thymeleaf.processor.IProcessor, org.thymeleaf.dialect.IProcessorDialect);
    Code:
       0: aload_0
       1: invokespecial #1                  // Method java/lang/Object."<init>":()V
       4: aload_0
       5: aload_2
       6: putfield      #2                  // Field dialect:Lorg/thymeleaf/dialect/IProcessorDialect;
       9: aload_0
      10: aload_1
      11: putfield      #3                  // Field processor:Lorg/thymeleaf/processor/IProcessor;
      14: aload_0
      15: aload_0
      16: getfield      #2                  // Field dialect:Lorg/thymeleaf/dialect/IProcessorDialect;
      19: invokeinterface #4,  1            // InterfaceMethod org/thymeleaf/dialect/IProcessorDialect.getDialectProcessorPrecedence:()I
      24: putfield      #5                  // Field dialectPrecedence:I
      27: aload_0
      28: aload_0
      29: getfield      #3                  // Field processor:Lorg/thymeleaf/processor/IProcessor;
      32: invokeinterface #6,  1            // InterfaceMethod org/thymeleaf/processor/IProcessor.getPrecedence:()I
      37: putfield      #7                  // Field processorPrecedence:I
      40: return

  public final org.thymeleaf.templatemode.TemplateMode getTemplateMode();
    Code:
       0: aload_0
       1: getfield      #3                  // Field processor:Lorg/thymeleaf/processor/IProcessor;
       4: invokeinterface #8,  1            // InterfaceMethod org/thymeleaf/processor/IProcessor.getTemplateMode:()Lorg/thymeleaf/templatemode/TemplateMode;
       9: areturn

  public final int getDialectPrecedence();
    Code:
       0: aload_0
       1: getfield      #5                  // Field dialectPrecedence:I
       4: ireturn

  public final int getPrecedence();
    Code:
       0: aload_0
       1: getfield      #7                  // Field processorPrecedence:I
       4: ireturn

  public final org.thymeleaf.dialect.IProcessorDialect getDialect();
    Code:
       0: aload_0
       1: getfield      #2                  // Field dialect:Lorg/thymeleaf/dialect/IProcessorDialect;
       4: areturn

  public final org.thymeleaf.processor.IProcessor unwrap();
    Code:
       0: aload_0
       1: getfield      #3                  // Field processor:Lorg/thymeleaf/processor/IProcessor;
       4: areturn

  public final void setAttributeDefinitions(org.thymeleaf.engine.AttributeDefinitions);
    Code:
       0: aload_0
       1: getfield      #3                  // Field processor:Lorg/thymeleaf/processor/IProcessor;
       4: instanceof    #9                  // class org/thymeleaf/engine/IAttributeDefinitionsAware
       7: ifeq          23
      10: aload_0
      11: getfield      #3                  // Field processor:Lorg/thymeleaf/processor/IProcessor;
      14: checkcast     #9                  // class org/thymeleaf/engine/IAttributeDefinitionsAware
      17: aload_1
      18: invokeinterface #10,  2           // InterfaceMethod org/thymeleaf/engine/IAttributeDefinitionsAware.setAttributeDefinitions:(Lorg/thymeleaf/engine/AttributeDefinitions;)V
      23: return

  public final void setElementDefinitions(org.thymeleaf.engine.ElementDefinitions);
    Code:
       0: aload_0
       1: getfield      #3                  // Field processor:Lorg/thymeleaf/processor/IProcessor;
       4: instanceof    #11                 // class org/thymeleaf/engine/IElementDefinitionsAware
       7: ifeq          23
      10: aload_0
      11: getfield      #3                  // Field processor:Lorg/thymeleaf/processor/IProcessor;
      14: checkcast     #11                 // class org/thymeleaf/engine/IElementDefinitionsAware
      17: aload_1
      18: invokeinterface #12,  2           // InterfaceMethod org/thymeleaf/engine/IElementDefinitionsAware.setElementDefinitions:(Lorg/thymeleaf/engine/ElementDefinitions;)V
      23: return

  public java.lang.String toString();
    Code:
       0: aload_0
       1: getfield      #3                  // Field processor:Lorg/thymeleaf/processor/IProcessor;
       4: invokevirtual #13                 // Method java/lang/Object.toString:()Ljava/lang/String;
       7: areturn
}
