Compiled from "ForwardingClientCallListener.java"
public abstract class io.grpc.ForwardingClientCallListener$SimpleForwardingClientCallListener<RespT> extends io.grpc.ForwardingClientCallListener<RespT> {
  private final io.grpc.ClientCall$Listener<RespT> delegate;

  protected io.grpc.ForwardingClientCallListener$SimpleForwardingClientCallListener(io.grpc.ClientCall$Listener<RespT>);
    Code:
       0: aload_0
       1: invokespecial #1                  // Method io/grpc/ForwardingClientCallListener."<init>":()V
       4: aload_0
       5: aload_1
       6: putfield      #2                  // Field delegate:Lio/grpc/ClientCall$Listener;
       9: return

  protected io.grpc.ClientCall$Listener<RespT> delegate();
    Code:
       0: aload_0
       1: getfield      #2                  // Field delegate:Lio/grpc/ClientCall$Listener;
       4: areturn

  public java.lang.String toString();
    Code:
       0: aload_0
       1: invokespecial #3                  // Method io/grpc/ForwardingClientCallListener.toString:()Ljava/lang/String;
       4: areturn

  public void onReady();
    Code:
       0: aload_0
       1: invokespecial #4                  // Method io/grpc/ForwardingClientCallListener.onReady:()V
       4: return

  public void onClose(io.grpc.Status, io.grpc.Metadata);
    Code:
       0: aload_0
       1: aload_1
       2: aload_2
       3: invokespecial #5                  // Method io/grpc/ForwardingClientCallListener.onClose:(Lio/grpc/Status;Lio/grpc/Metadata;)V
       6: return

  public void onHeaders(io.grpc.Metadata);
    Code:
       0: aload_0
       1: aload_1
       2: invokespecial #6                  // Method io/grpc/ForwardingClientCallListener.onHeaders:(Lio/grpc/Metadata;)V
       5: return
}
