Compiled from "InternalChannelz.java"
public final class io.grpc.InternalChannelz$ServerStats {
  public final long callsStarted;

  public final long callsSucceeded;

  public final long callsFailed;

  public final long lastCallStartedNanos;

  public final java.util.List<io.grpc.InternalInstrumented<io.grpc.InternalChannelz$SocketStats>> listenSockets;

  public io.grpc.InternalChannelz$ServerStats(long, long, long, long, java.util.List<io.grpc.InternalInstrumented<io.grpc.InternalChannelz$SocketStats>>);
    Code:
       0: aload_0
       1: invokespecial #1                  // Method java/lang/Object."<init>":()V
       4: aload_0
       5: lload_1
       6: putfield      #2                  // Field callsStarted:J
       9: aload_0
      10: lload_3
      11: putfield      #3                  // Field callsSucceeded:J
      14: aload_0
      15: lload         5
      17: putfield      #4                  // Field callsFailed:J
      20: aload_0
      21: lload         7
      23: putfield      #5                  // Field lastCallStartedNanos:J
      26: aload_0
      27: aload         9
      29: invokestatic  #6                  // Method com/google/common/base/Preconditions.checkNotNull:(Ljava/lang/Object;)Ljava/lang/Object;
      32: checkcast     #7                  // class java/util/List
      35: putfield      #8                  // Field listenSockets:Ljava/util/List;
      38: return
}
