Compiled from "ManagedChannelRegistry.java"
final class io.grpc.ManagedChannelRegistry$ManagedChannelPriorityAccessor implements io.grpc.ServiceProviders$PriorityAccessor<io.grpc.ManagedChannelProvider> {
  private io.grpc.ManagedChannelRegistry$ManagedChannelPriorityAccessor();
    Code:
       0: aload_0
       1: invokespecial #2                  // Method java/lang/Object."<init>":()V
       4: return

  public boolean isAvailable(io.grpc.ManagedChannelProvider);
    Code:
       0: aload_1
       1: invokevirtual #3                  // Method io/grpc/ManagedChannelProvider.isAvailable:()Z
       4: ireturn

  public int getPriority(io.grpc.ManagedChannelProvider);
    Code:
       0: aload_1
       1: invokevirtual #4                  // Method io/grpc/ManagedChannelProvider.priority:()I
       4: ireturn

  public int getPriority(java.lang.Object);
    Code:
       0: aload_0
       1: aload_1
       2: checkcast     #5                  // class io/grpc/ManagedChannelProvider
       5: invokevirtual #6                  // Method getPriority:(Lio/grpc/ManagedChannelProvider;)I
       8: ireturn

  public boolean isAvailable(java.lang.Object);
    Code:
       0: aload_0
       1: aload_1
       2: checkcast     #5                  // class io/grpc/ManagedChannelProvider
       5: invokevirtual #7                  // Method isAvailable:(Lio/grpc/ManagedChannelProvider;)Z
       8: ireturn

  io.grpc.ManagedChannelRegistry$ManagedChannelPriorityAccessor(io.grpc.ManagedChannelRegistry$1);
    Code:
       0: aload_0
       1: invokespecial #1                  // Method "<init>":()V
       4: return
}
