Compiled from "Parameter.java"
public final class org.jboss.resteasy.spi.metadata.Parameter$ParamType extends java.lang.Enum<org.jboss.resteasy.spi.metadata.Parameter$ParamType> {
  public static final org.jboss.resteasy.spi.metadata.Parameter$ParamType BEAN_PARAM;

  public static final org.jboss.resteasy.spi.metadata.Parameter$ParamType CONTEXT;

  public static final org.jboss.resteasy.spi.metadata.Parameter$ParamType COOKIE_PARAM;

  public static final org.jboss.resteasy.spi.metadata.Parameter$ParamType FORM_PARAM;

  public static final org.jboss.resteasy.spi.metadata.Parameter$ParamType HEADER_PARAM;

  public static final org.jboss.resteasy.spi.metadata.Parameter$ParamType MATRIX_PARAM;

  public static final org.jboss.resteasy.spi.metadata.Parameter$ParamType MESSAGE_BODY;

  public static final org.jboss.resteasy.spi.metadata.Parameter$ParamType PATH_PARAM;

  public static final org.jboss.resteasy.spi.metadata.Parameter$ParamType QUERY_PARAM;

  public static final org.jboss.resteasy.spi.metadata.Parameter$ParamType SUSPENDED;

  public static final org.jboss.resteasy.spi.metadata.Parameter$ParamType UNKNOWN;

  public static final org.jboss.resteasy.spi.metadata.Parameter$ParamType FORM;

  public static final org.jboss.resteasy.spi.metadata.Parameter$ParamType QUERY;

  public static final org.jboss.resteasy.spi.metadata.Parameter$ParamType SUSPEND;

  private static final org.jboss.resteasy.spi.metadata.Parameter$ParamType[] $VALUES;

  public static org.jboss.resteasy.spi.metadata.Parameter$ParamType[] values();
    Code:
       0: getstatic     #1                  // Field $VALUES:[Lorg/jboss/resteasy/spi/metadata/Parameter$ParamType;
       3: invokevirtual #2                  // Method "[Lorg/jboss/resteasy/spi/metadata/Parameter$ParamType;".clone:()Ljava/lang/Object;
       6: checkcast     #3                  // class "[Lorg/jboss/resteasy/spi/metadata/Parameter$ParamType;"
       9: areturn

  public static org.jboss.resteasy.spi.metadata.Parameter$ParamType valueOf(java.lang.String);
    Code:
       0: ldc           #4                  // class org/jboss/resteasy/spi/metadata/Parameter$ParamType
       2: aload_0
       3: invokestatic  #5                  // Method java/lang/Enum.valueOf:(Ljava/lang/Class;Ljava/lang/String;)Ljava/lang/Enum;
       6: checkcast     #4                  // class org/jboss/resteasy/spi/metadata/Parameter$ParamType
       9: areturn

  private org.jboss.resteasy.spi.metadata.Parameter$ParamType();
    Code:
       0: aload_0
       1: aload_1
       2: iload_2
       3: invokespecial #6                  // Method java/lang/Enum."<init>":(Ljava/lang/String;I)V
       6: return

  static {};
    Code:
       0: new           #4                  // class org/jboss/resteasy/spi/metadata/Parameter$ParamType
       3: dup
       4: ldc           #7                  // String BEAN_PARAM
       6: iconst_0
       7: invokespecial #8                  // Method "<init>":(Ljava/lang/String;I)V
      10: putstatic     #9                  // Field BEAN_PARAM:Lorg/jboss/resteasy/spi/metadata/Parameter$ParamType;
      13: new           #4                  // class org/jboss/resteasy/spi/metadata/Parameter$ParamType
      16: dup
      17: ldc           #10                 // String CONTEXT
      19: iconst_1
      20: invokespecial #8                  // Method "<init>":(Ljava/lang/String;I)V
      23: putstatic     #11                 // Field CONTEXT:Lorg/jboss/resteasy/spi/metadata/Parameter$ParamType;
      26: new           #4                  // class org/jboss/resteasy/spi/metadata/Parameter$ParamType
      29: dup
      30: ldc           #12                 // String COOKIE_PARAM
      32: iconst_2
      33: invokespecial #8                  // Method "<init>":(Ljava/lang/String;I)V
      36: putstatic     #13                 // Field COOKIE_PARAM:Lorg/jboss/resteasy/spi/metadata/Parameter$ParamType;
      39: new           #4                  // class org/jboss/resteasy/spi/metadata/Parameter$ParamType
      42: dup
      43: ldc           #14                 // String FORM_PARAM
      45: iconst_3
      46: invokespecial #8                  // Method "<init>":(Ljava/lang/String;I)V
      49: putstatic     #15                 // Field FORM_PARAM:Lorg/jboss/resteasy/spi/metadata/Parameter$ParamType;
      52: new           #4                  // class org/jboss/resteasy/spi/metadata/Parameter$ParamType
      55: dup
      56: ldc           #16                 // String HEADER_PARAM
      58: iconst_4
      59: invokespecial #8                  // Method "<init>":(Ljava/lang/String;I)V
      62: putstatic     #17                 // Field HEADER_PARAM:Lorg/jboss/resteasy/spi/metadata/Parameter$ParamType;
      65: new           #4                  // class org/jboss/resteasy/spi/metadata/Parameter$ParamType
      68: dup
      69: ldc           #18                 // String MATRIX_PARAM
      71: iconst_5
      72: invokespecial #8                  // Method "<init>":(Ljava/lang/String;I)V
      75: putstatic     #19                 // Field MATRIX_PARAM:Lorg/jboss/resteasy/spi/metadata/Parameter$ParamType;
      78: new           #4                  // class org/jboss/resteasy/spi/metadata/Parameter$ParamType
      81: dup
      82: ldc           #20                 // String MESSAGE_BODY
      84: bipush        6
      86: invokespecial #8                  // Method "<init>":(Ljava/lang/String;I)V
      89: putstatic     #21                 // Field MESSAGE_BODY:Lorg/jboss/resteasy/spi/metadata/Parameter$ParamType;
      92: new           #4                  // class org/jboss/resteasy/spi/metadata/Parameter$ParamType
      95: dup
      96: ldc           #22                 // String PATH_PARAM
      98: bipush        7
     100: invokespecial #8                  // Method "<init>":(Ljava/lang/String;I)V
     103: putstatic     #23                 // Field PATH_PARAM:Lorg/jboss/resteasy/spi/metadata/Parameter$ParamType;
     106: new           #4                  // class org/jboss/resteasy/spi/metadata/Parameter$ParamType
     109: dup
     110: ldc           #24                 // String QUERY_PARAM
     112: bipush        8
     114: invokespecial #8                  // Method "<init>":(Ljava/lang/String;I)V
     117: putstatic     #25                 // Field QUERY_PARAM:Lorg/jboss/resteasy/spi/metadata/Parameter$ParamType;
     120: new           #4                  // class org/jboss/resteasy/spi/metadata/Parameter$ParamType
     123: dup
     124: ldc           #26                 // String SUSPENDED
     126: bipush        9
     128: invokespecial #8                  // Method "<init>":(Ljava/lang/String;I)V
     131: putstatic     #27                 // Field SUSPENDED:Lorg/jboss/resteasy/spi/metadata/Parameter$ParamType;
     134: new           #4                  // class org/jboss/resteasy/spi/metadata/Parameter$ParamType
     137: dup
     138: ldc           #28                 // String UNKNOWN
     140: bipush        10
     142: invokespecial #8                  // Method "<init>":(Ljava/lang/String;I)V
     145: putstatic     #29                 // Field UNKNOWN:Lorg/jboss/resteasy/spi/metadata/Parameter$ParamType;
     148: new           #4                  // class org/jboss/resteasy/spi/metadata/Parameter$ParamType
     151: dup
     152: ldc           #30                 // String FORM
     154: bipush        11
     156: invokespecial #8                  // Method "<init>":(Ljava/lang/String;I)V
     159: putstatic     #31                 // Field FORM:Lorg/jboss/resteasy/spi/metadata/Parameter$ParamType;
     162: new           #4                  // class org/jboss/resteasy/spi/metadata/Parameter$ParamType
     165: dup
     166: ldc           #32                 // String QUERY
     168: bipush        12
     170: invokespecial #8                  // Method "<init>":(Ljava/lang/String;I)V
     173: putstatic     #33                 // Field QUERY:Lorg/jboss/resteasy/spi/metadata/Parameter$ParamType;
     176: new           #4                  // class org/jboss/resteasy/spi/metadata/Parameter$ParamType
     179: dup
     180: ldc           #34                 // String SUSPEND
     182: bipush        13
     184: invokespecial #8                  // Method "<init>":(Ljava/lang/String;I)V
     187: putstatic     #35                 // Field SUSPEND:Lorg/jboss/resteasy/spi/metadata/Parameter$ParamType;
     190: bipush        14
     192: anewarray     #4                  // class org/jboss/resteasy/spi/metadata/Parameter$ParamType
     195: dup
     196: iconst_0
     197: getstatic     #9                  // Field BEAN_PARAM:Lorg/jboss/resteasy/spi/metadata/Parameter$ParamType;
     200: aastore
     201: dup
     202: iconst_1
     203: getstatic     #11                 // Field CONTEXT:Lorg/jboss/resteasy/spi/metadata/Parameter$ParamType;
     206: aastore
     207: dup
     208: iconst_2
     209: getstatic     #13                 // Field COOKIE_PARAM:Lorg/jboss/resteasy/spi/metadata/Parameter$ParamType;
     212: aastore
     213: dup
     214: iconst_3
     215: getstatic     #15                 // Field FORM_PARAM:Lorg/jboss/resteasy/spi/metadata/Parameter$ParamType;
     218: aastore
     219: dup
     220: iconst_4
     221: getstatic     #17                 // Field HEADER_PARAM:Lorg/jboss/resteasy/spi/metadata/Parameter$ParamType;
     224: aastore
     225: dup
     226: iconst_5
     227: getstatic     #19                 // Field MATRIX_PARAM:Lorg/jboss/resteasy/spi/metadata/Parameter$ParamType;
     230: aastore
     231: dup
     232: bipush        6
     234: getstatic     #21                 // Field MESSAGE_BODY:Lorg/jboss/resteasy/spi/metadata/Parameter$ParamType;
     237: aastore
     238: dup
     239: bipush        7
     241: getstatic     #23                 // Field PATH_PARAM:Lorg/jboss/resteasy/spi/metadata/Parameter$ParamType;
     244: aastore
     245: dup
     246: bipush        8
     248: getstatic     #25                 // Field QUERY_PARAM:Lorg/jboss/resteasy/spi/metadata/Parameter$ParamType;
     251: aastore
     252: dup
     253: bipush        9
     255: getstatic     #27                 // Field SUSPENDED:Lorg/jboss/resteasy/spi/metadata/Parameter$ParamType;
     258: aastore
     259: dup
     260: bipush        10
     262: getstatic     #29                 // Field UNKNOWN:Lorg/jboss/resteasy/spi/metadata/Parameter$ParamType;
     265: aastore
     266: dup
     267: bipush        11
     269: getstatic     #31                 // Field FORM:Lorg/jboss/resteasy/spi/metadata/Parameter$ParamType;
     272: aastore
     273: dup
     274: bipush        12
     276: getstatic     #33                 // Field QUERY:Lorg/jboss/resteasy/spi/metadata/Parameter$ParamType;
     279: aastore
     280: dup
     281: bipush        13
     283: getstatic     #35                 // Field SUSPEND:Lorg/jboss/resteasy/spi/metadata/Parameter$ParamType;
     286: aastore
     287: putstatic     #1                  // Field $VALUES:[Lorg/jboss/resteasy/spi/metadata/Parameter$ParamType;
     290: return
}
