Compiled from "TarArchiveSparseEntry.java"
public class io.dekorate.deps.commons.compress.archivers.tar.TarArchiveSparseEntry implements io.dekorate.deps.commons.compress.archivers.tar.TarConstants {
  private final boolean isExtended;

  public io.dekorate.deps.commons.compress.archivers.tar.TarArchiveSparseEntry(byte[]) throws java.io.IOException;
    Code:
       0: aload_0
       1: invokespecial #16                 // Method java/lang/Object."<init>":()V
       4: iconst_0
       5: istore_2
       6: iinc_w        2, 504
      12: aload_0
      13: aload_1
      14: iload_2
      15: invokestatic  #22                 // Method io/dekorate/deps/commons/compress/archivers/tar/TarUtils.parseBoolean:([BI)Z
      18: putfield      #24                 // Field isExtended:Z
      21: return

  public boolean isExtended();
    Code:
       0: aload_0
       1: getfield      #24                 // Field isExtended:Z
       4: ireturn
}
