Compiled from "AbstractCircuitBreaker.java"
final class org.apache.commons.lang3.concurrent.AbstractCircuitBreaker$State$1 extends org.apache.commons.lang3.concurrent.AbstractCircuitBreaker$State {
  org.apache.commons.lang3.concurrent.AbstractCircuitBreaker$State$1(java.lang.String, int);
    Code:
       0: aload_0
       1: aload_1
       2: iload_2
       3: aconst_null
       4: invokespecial #1                  // Method org/apache/commons/lang3/concurrent/AbstractCircuitBreaker$State."<init>":(Ljava/lang/String;ILorg/apache/commons/lang3/concurrent/AbstractCircuitBreaker$1;)V
       7: return

  public org.apache.commons.lang3.concurrent.AbstractCircuitBreaker$State oppositeState();
    Code:
       0: getstatic     #2                  // Field OPEN:Lorg/apache/commons/lang3/concurrent/AbstractCircuitBreaker$State;
       3: areturn
}
