Compiled from "NullStatsLogger.java"
class org.apache.bookkeeper.stats.NullStatsLogger$NullCounter implements org.apache.bookkeeper.stats.Counter {
  org.apache.bookkeeper.stats.NullStatsLogger$NullCounter();
    Code:
       0: aload_0
       1: invokespecial #1                  // Method java/lang/Object."<init>":()V
       4: return

  public void clear();
    Code:
       0: return

  public void inc();
    Code:
       0: return

  public void dec();
    Code:
       0: return

  public void add(long);
    Code:
       0: return

  public java.lang.Long get();
    Code:
       0: lconst_0
       1: invokestatic  #2                  // Method java/lang/Long.valueOf:(J)Ljava/lang/Long;
       4: areturn
}
