Compiled from "OpStatsData.java"
public class org.apache.bookkeeper.stats.OpStatsData {
  private final long numSuccessfulEvents;

  private final long numFailedEvents;

  private final double avgLatencyMillis;

  private final long[] percentileLatenciesMillis;

  public org.apache.bookkeeper.stats.OpStatsData(long, long, double, long[]);
    Code:
       0: aload_0
       1: invokespecial #1                  // Method java/lang/Object."<init>":()V
       4: aload_0
       5: lload_1
       6: putfield      #2                  // Field numSuccessfulEvents:J
       9: aload_0
      10: lload_3
      11: putfield      #3                  // Field numFailedEvents:J
      14: aload_0
      15: dload         5
      17: putfield      #4                  // Field avgLatencyMillis:D
      20: aload_0
      21: aload         7
      23: aload         7
      25: arraylength
      26: invokestatic  #5                  // Method java/util/Arrays.copyOf:([JI)[J
      29: putfield      #6                  // Field percentileLatenciesMillis:[J
      32: return

  public long getP10Latency();
    Code:
       0: aload_0
       1: getfield      #6                  // Field percentileLatenciesMillis:[J
       4: iconst_0
       5: laload
       6: lreturn

  public long getP50Latency();
    Code:
       0: aload_0
       1: getfield      #6                  // Field percentileLatenciesMillis:[J
       4: iconst_1
       5: laload
       6: lreturn

  public long getP90Latency();
    Code:
       0: aload_0
       1: getfield      #6                  // Field percentileLatenciesMillis:[J
       4: iconst_2
       5: laload
       6: lreturn

  public long getP99Latency();
    Code:
       0: aload_0
       1: getfield      #6                  // Field percentileLatenciesMillis:[J
       4: iconst_3
       5: laload
       6: lreturn

  public long getP999Latency();
    Code:
       0: aload_0
       1: getfield      #6                  // Field percentileLatenciesMillis:[J
       4: iconst_4
       5: laload
       6: lreturn

  public long getP9999Latency();
    Code:
       0: aload_0
       1: getfield      #6                  // Field percentileLatenciesMillis:[J
       4: iconst_5
       5: laload
       6: lreturn

  public long getNumSuccessfulEvents();
    Code:
       0: aload_0
       1: getfield      #2                  // Field numSuccessfulEvents:J
       4: lreturn

  public long getNumFailedEvents();
    Code:
       0: aload_0
       1: getfield      #3                  // Field numFailedEvents:J
       4: lreturn

  public double getAvgLatencyMillis();
    Code:
       0: aload_0
       1: getfield      #4                  // Field avgLatencyMillis:D
       4: dreturn
}
