Compiled from "GuardKeyForPublicKeyHelper.java"
public class org.adorsys.docusafe.service.impl.guardHelper.GuardKeyForPublicKeyHelper implements org.adorsys.docusafe.service.impl.guardHelper.GuardKeyHelper {
  private static final org.slf4j.Logger LOGGER;

  public org.adorsys.docusafe.service.impl.guardHelper.GuardKeyForPublicKeyHelper();
    Code:
       0: aload_0
       1: invokespecial #1                  // Method java/lang/Object."<init>":()V
       4: return

  public org.adorsys.docusafe.service.impl.guardHelper.KeySourceAndGuardKeyID getKeySourceAndGuardKeyID(org.adorsys.encobject.service.api.KeystorePersistence, org.adorsys.encobject.domain.KeyStoreAccess, org.adorsys.docusafe.service.types.complextypes.DocumentKeyIDWithKeyAndAccessType);
    Code:
       0: aload_1
       1: aload_2
       2: invokestatic  #2                  // Method org/adorsys/encobject/service/api/KeyStore2KeySourceHelper.getForPublicKey:(Lorg/adorsys/encobject/service/api/KeystorePersistence;Lorg/adorsys/encobject/domain/KeyStoreAccess;)Lorg/adorsys/encobject/service/api/KeyStore2KeySourceHelper$KeySourceAndKeyID;
       5: astore        4
       7: new           #3                  // class org/adorsys/docusafe/service/types/GuardKeyID
      10: dup
      11: aload         4
      13: invokevirtual #4                  // Method org/adorsys/encobject/service/api/KeyStore2KeySourceHelper$KeySourceAndKeyID.getKeyID:()Lorg/adorsys/encobject/types/KeyID;
      16: invokevirtual #5                  // Method org/adorsys/encobject/types/KeyID.getValue:()Ljava/lang/String;
      19: invokespecial #6                  // Method org/adorsys/docusafe/service/types/GuardKeyID."<init>":(Ljava/lang/String;)V
      22: astore        5
      24: getstatic     #7                  // Field LOGGER:Lorg/slf4j/Logger;
      27: new           #8                  // class java/lang/StringBuilder
      30: dup
      31: invokespecial #9                  // Method java/lang/StringBuilder."<init>":()V
      34: ldc           #10                 // String Guard created with asymmetric KeyID :
      36: invokevirtual #11                 // Method java/lang/StringBuilder.append:(Ljava/lang/String;)Ljava/lang/StringBuilder;
      39: aload         5
      41: invokevirtual #12                 // Method java/lang/StringBuilder.append:(Ljava/lang/Object;)Ljava/lang/StringBuilder;
      44: invokevirtual #13                 // Method java/lang/StringBuilder.toString:()Ljava/lang/String;
      47: invokeinterface #14,  2           // InterfaceMethod org/slf4j/Logger.debug:(Ljava/lang/String;)V
      52: new           #15                 // class org/adorsys/docusafe/service/impl/guardHelper/KeySourceAndGuardKeyID
      55: dup
      56: aload         4
      58: invokevirtual #16                 // Method org/adorsys/encobject/service/api/KeyStore2KeySourceHelper$KeySourceAndKeyID.getKeySource:()Lorg/adorsys/encobject/service/api/KeySource;
      61: aload         5
      63: invokespecial #17                 // Method org/adorsys/docusafe/service/impl/guardHelper/KeySourceAndGuardKeyID."<init>":(Lorg/adorsys/encobject/service/api/KeySource;Lorg/adorsys/docusafe/service/types/GuardKeyID;)V
      66: areturn

  static {};
    Code:
       0: ldc           #18                 // class org/adorsys/docusafe/service/impl/guardHelper/GuardKeyForPublicKeyHelper
       2: invokestatic  #19                 // Method org/slf4j/LoggerFactory.getLogger:(Ljava/lang/Class;)Lorg/slf4j/Logger;
       5: putstatic     #7                  // Field LOGGER:Lorg/slf4j/Logger;
       8: return
}
