Compiled from "AbstractHttpConnection.java"
class org.eclipse.jetty.client.AbstractHttpConnection$NonFinalResponseListener implements org.eclipse.jetty.client.HttpEventListener {
  final org.eclipse.jetty.client.HttpExchange _exchange;

  final org.eclipse.jetty.client.HttpEventListener _next;

  final org.eclipse.jetty.client.AbstractHttpConnection this$0;

  public org.eclipse.jetty.client.AbstractHttpConnection$NonFinalResponseListener(org.eclipse.jetty.client.AbstractHttpConnection, org.eclipse.jetty.client.HttpExchange);
    Code:
       0: aload_0
       1: aload_1
       2: putfield      #1                  // Field this$0:Lorg/eclipse/jetty/client/AbstractHttpConnection;
       5: aload_0
       6: invokespecial #2                  // Method java/lang/Object."<init>":()V
       9: aload_0
      10: aload_2
      11: putfield      #3                  // Field _exchange:Lorg/eclipse/jetty/client/HttpExchange;
      14: aload_0
      15: aload_2
      16: invokevirtual #4                  // Method org/eclipse/jetty/client/HttpExchange.getEventListener:()Lorg/eclipse/jetty/client/HttpEventListener;
      19: putfield      #5                  // Field _next:Lorg/eclipse/jetty/client/HttpEventListener;
      22: return

  public void onRequestCommitted() throws java.io.IOException;
    Code:
       0: return

  public void onRequestComplete() throws java.io.IOException;
    Code:
       0: return

  public void onResponseStatus(org.eclipse.jetty.io.Buffer, int, org.eclipse.jetty.io.Buffer) throws java.io.IOException;
    Code:
       0: return

  public void onResponseHeader(org.eclipse.jetty.io.Buffer, org.eclipse.jetty.io.Buffer) throws java.io.IOException;
    Code:
       0: aload_0
       1: getfield      #5                  // Field _next:Lorg/eclipse/jetty/client/HttpEventListener;
       4: aload_1
       5: aload_2
       6: invokeinterface #6,  3            // InterfaceMethod org/eclipse/jetty/client/HttpEventListener.onResponseHeader:(Lorg/eclipse/jetty/io/Buffer;Lorg/eclipse/jetty/io/Buffer;)V
      11: return

  public void onResponseHeaderComplete() throws java.io.IOException;
    Code:
       0: aload_0
       1: getfield      #5                  // Field _next:Lorg/eclipse/jetty/client/HttpEventListener;
       4: invokeinterface #7,  1            // InterfaceMethod org/eclipse/jetty/client/HttpEventListener.onResponseHeaderComplete:()V
       9: return

  public void onResponseContent(org.eclipse.jetty.io.Buffer) throws java.io.IOException;
    Code:
       0: return

  public void onResponseComplete() throws java.io.IOException;
    Code:
       0: aload_0
       1: getfield      #3                  // Field _exchange:Lorg/eclipse/jetty/client/HttpExchange;
       4: aload_0
       5: getfield      #5                  // Field _next:Lorg/eclipse/jetty/client/HttpEventListener;
       8: invokevirtual #8                  // Method org/eclipse/jetty/client/HttpExchange.setEventListener:(Lorg/eclipse/jetty/client/HttpEventListener;)V
      11: aload_0
      12: getfield      #3                  // Field _exchange:Lorg/eclipse/jetty/client/HttpExchange;
      15: iconst_4
      16: invokevirtual #9                  // Method org/eclipse/jetty/client/HttpExchange.setStatus:(I)Z
      19: pop
      20: aload_0
      21: getfield      #1                  // Field this$0:Lorg/eclipse/jetty/client/AbstractHttpConnection;
      24: getfield      #10                 // Field org/eclipse/jetty/client/AbstractHttpConnection._parser:Lorg/eclipse/jetty/http/HttpParser;
      27: invokevirtual #11                 // Method org/eclipse/jetty/http/HttpParser.reset:()V
      30: return

  public void onConnectionFailed(java.lang.Throwable);
    Code:
       0: aload_0
       1: getfield      #3                  // Field _exchange:Lorg/eclipse/jetty/client/HttpExchange;
       4: aload_0
       5: getfield      #5                  // Field _next:Lorg/eclipse/jetty/client/HttpEventListener;
       8: invokevirtual #8                  // Method org/eclipse/jetty/client/HttpExchange.setEventListener:(Lorg/eclipse/jetty/client/HttpEventListener;)V
      11: aload_0
      12: getfield      #5                  // Field _next:Lorg/eclipse/jetty/client/HttpEventListener;
      15: aload_1
      16: invokeinterface #12,  2           // InterfaceMethod org/eclipse/jetty/client/HttpEventListener.onConnectionFailed:(Ljava/lang/Throwable;)V
      21: return

  public void onException(java.lang.Throwable);
    Code:
       0: aload_0
       1: getfield      #3                  // Field _exchange:Lorg/eclipse/jetty/client/HttpExchange;
       4: aload_0
       5: getfield      #5                  // Field _next:Lorg/eclipse/jetty/client/HttpEventListener;
       8: invokevirtual #8                  // Method org/eclipse/jetty/client/HttpExchange.setEventListener:(Lorg/eclipse/jetty/client/HttpEventListener;)V
      11: aload_0
      12: getfield      #5                  // Field _next:Lorg/eclipse/jetty/client/HttpEventListener;
      15: aload_1
      16: invokeinterface #13,  2           // InterfaceMethod org/eclipse/jetty/client/HttpEventListener.onException:(Ljava/lang/Throwable;)V
      21: return

  public void onExpire();
    Code:
       0: aload_0
       1: getfield      #3                  // Field _exchange:Lorg/eclipse/jetty/client/HttpExchange;
       4: aload_0
       5: getfield      #5                  // Field _next:Lorg/eclipse/jetty/client/HttpEventListener;
       8: invokevirtual #8                  // Method org/eclipse/jetty/client/HttpExchange.setEventListener:(Lorg/eclipse/jetty/client/HttpEventListener;)V
      11: aload_0
      12: getfield      #5                  // Field _next:Lorg/eclipse/jetty/client/HttpEventListener;
      15: invokeinterface #14,  1           // InterfaceMethod org/eclipse/jetty/client/HttpEventListener.onExpire:()V
      20: return

  public void onRetry();
    Code:
       0: aload_0
       1: getfield      #3                  // Field _exchange:Lorg/eclipse/jetty/client/HttpExchange;
       4: aload_0
       5: getfield      #5                  // Field _next:Lorg/eclipse/jetty/client/HttpEventListener;
       8: invokevirtual #8                  // Method org/eclipse/jetty/client/HttpExchange.setEventListener:(Lorg/eclipse/jetty/client/HttpEventListener;)V
      11: aload_0
      12: getfield      #5                  // Field _next:Lorg/eclipse/jetty/client/HttpEventListener;
      15: invokeinterface #15,  1           // InterfaceMethod org/eclipse/jetty/client/HttpEventListener.onRetry:()V
      20: return
}
