Compiled from "ForwardingMap.java"
public abstract class com.google.common.collect.ForwardingMap<K, V> extends com.google.common.collect.ForwardingObject implements java.util.Map<K, V> {
  protected com.google.common.collect.ForwardingMap();
    Code:
       0: aload_0
       1: invokespecial #1                  // Method com/google/common/collect/ForwardingObject."<init>":()V
       4: return

  protected abstract java.util.Map<K, V> delegate();

  public int size();
    Code:
       0: aload_0
       1: invokevirtual #2                  // Method delegate:()Ljava/util/Map;
       4: invokeinterface #3,  1            // InterfaceMethod java/util/Map.size:()I
       9: ireturn

  public boolean isEmpty();
    Code:
       0: aload_0
       1: invokevirtual #2                  // Method delegate:()Ljava/util/Map;
       4: invokeinterface #4,  1            // InterfaceMethod java/util/Map.isEmpty:()Z
       9: ireturn

  public V remove(java.lang.Object);
    Code:
       0: aload_0
       1: invokevirtual #2                  // Method delegate:()Ljava/util/Map;
       4: aload_1
       5: invokeinterface #5,  2            // InterfaceMethod java/util/Map.remove:(Ljava/lang/Object;)Ljava/lang/Object;
      10: areturn

  public void clear();
    Code:
       0: aload_0
       1: invokevirtual #2                  // Method delegate:()Ljava/util/Map;
       4: invokeinterface #6,  1            // InterfaceMethod java/util/Map.clear:()V
       9: return

  public boolean containsKey(java.lang.Object);
    Code:
       0: aload_0
       1: invokevirtual #2                  // Method delegate:()Ljava/util/Map;
       4: aload_1
       5: invokeinterface #7,  2            // InterfaceMethod java/util/Map.containsKey:(Ljava/lang/Object;)Z
      10: ireturn

  public boolean containsValue(java.lang.Object);
    Code:
       0: aload_0
       1: invokevirtual #2                  // Method delegate:()Ljava/util/Map;
       4: aload_1
       5: invokeinterface #8,  2            // InterfaceMethod java/util/Map.containsValue:(Ljava/lang/Object;)Z
      10: ireturn

  public V get(java.lang.Object);
    Code:
       0: aload_0
       1: invokevirtual #2                  // Method delegate:()Ljava/util/Map;
       4: aload_1
       5: invokeinterface #9,  2            // InterfaceMethod java/util/Map.get:(Ljava/lang/Object;)Ljava/lang/Object;
      10: areturn

  public V put(K, V);
    Code:
       0: aload_0
       1: invokevirtual #2                  // Method delegate:()Ljava/util/Map;
       4: aload_1
       5: aload_2
       6: invokeinterface #10,  3           // InterfaceMethod java/util/Map.put:(Ljava/lang/Object;Ljava/lang/Object;)Ljava/lang/Object;
      11: areturn

  public void putAll(java.util.Map<? extends K, ? extends V>);
    Code:
       0: aload_0
       1: invokevirtual #2                  // Method delegate:()Ljava/util/Map;
       4: aload_1
       5: invokeinterface #11,  2           // InterfaceMethod java/util/Map.putAll:(Ljava/util/Map;)V
      10: return

  public java.util.Set<K> keySet();
    Code:
       0: aload_0
       1: invokevirtual #2                  // Method delegate:()Ljava/util/Map;
       4: invokeinterface #12,  1           // InterfaceMethod java/util/Map.keySet:()Ljava/util/Set;
       9: areturn

  public java.util.Collection<V> values();
    Code:
       0: aload_0
       1: invokevirtual #2                  // Method delegate:()Ljava/util/Map;
       4: invokeinterface #13,  1           // InterfaceMethod java/util/Map.values:()Ljava/util/Collection;
       9: areturn

  public java.util.Set<java.util.Map$Entry<K, V>> entrySet();
    Code:
       0: aload_0
       1: invokevirtual #2                  // Method delegate:()Ljava/util/Map;
       4: invokeinterface #14,  1           // InterfaceMethod java/util/Map.entrySet:()Ljava/util/Set;
       9: areturn

  public boolean equals(java.lang.Object);
    Code:
       0: aload_1
       1: aload_0
       2: if_acmpeq     18
       5: aload_0
       6: invokevirtual #2                  // Method delegate:()Ljava/util/Map;
       9: aload_1
      10: invokeinterface #15,  2           // InterfaceMethod java/util/Map.equals:(Ljava/lang/Object;)Z
      15: ifeq          22
      18: iconst_1
      19: goto          23
      22: iconst_0
      23: ireturn

  public int hashCode();
    Code:
       0: aload_0
       1: invokevirtual #2                  // Method delegate:()Ljava/util/Map;
       4: invokeinterface #16,  1           // InterfaceMethod java/util/Map.hashCode:()I
       9: ireturn

  protected void standardPutAll(java.util.Map<? extends K, ? extends V>);
    Code:
       0: aload_0
       1: aload_1
       2: invokestatic  #17                 // Method com/google/common/collect/Maps.putAllImpl:(Ljava/util/Map;Ljava/util/Map;)V
       5: return

  protected V standardRemove(java.lang.Object);
    Code:
       0: aload_0
       1: invokevirtual #18                 // Method entrySet:()Ljava/util/Set;
       4: invokeinterface #19,  1           // InterfaceMethod java/util/Set.iterator:()Ljava/util/Iterator;
       9: astore_2
      10: aload_2
      11: invokeinterface #20,  1           // InterfaceMethod java/util/Iterator.hasNext:()Z
      16: ifeq          62
      19: aload_2
      20: invokeinterface #21,  1           // InterfaceMethod java/util/Iterator.next:()Ljava/lang/Object;
      25: checkcast     #22                 // class java/util/Map$Entry
      28: astore_3
      29: aload_3
      30: invokeinterface #23,  1           // InterfaceMethod java/util/Map$Entry.getKey:()Ljava/lang/Object;
      35: aload_1
      36: invokestatic  #24                 // Method com/google/common/base/Objects.equal:(Ljava/lang/Object;Ljava/lang/Object;)Z
      39: ifeq          59
      42: aload_3
      43: invokeinterface #25,  1           // InterfaceMethod java/util/Map$Entry.getValue:()Ljava/lang/Object;
      48: astore        4
      50: aload_2
      51: invokeinterface #26,  1           // InterfaceMethod java/util/Iterator.remove:()V
      56: aload         4
      58: areturn
      59: goto          10
      62: aconst_null
      63: areturn

  protected void standardClear();
    Code:
       0: aload_0
       1: invokevirtual #18                 // Method entrySet:()Ljava/util/Set;
       4: invokeinterface #19,  1           // InterfaceMethod java/util/Set.iterator:()Ljava/util/Iterator;
       9: invokestatic  #27                 // Method com/google/common/collect/Iterators.clear:(Ljava/util/Iterator;)V
      12: return

  protected boolean standardContainsKey(java.lang.Object);
    Code:
       0: aload_0
       1: aload_1
       2: invokestatic  #28                 // Method com/google/common/collect/Maps.containsKeyImpl:(Ljava/util/Map;Ljava/lang/Object;)Z
       5: ireturn

  protected boolean standardContainsValue(java.lang.Object);
    Code:
       0: aload_0
       1: aload_1
       2: invokestatic  #29                 // Method com/google/common/collect/Maps.containsValueImpl:(Ljava/util/Map;Ljava/lang/Object;)Z
       5: ireturn

  protected boolean standardIsEmpty();
    Code:
       0: aload_0
       1: invokevirtual #18                 // Method entrySet:()Ljava/util/Set;
       4: invokeinterface #19,  1           // InterfaceMethod java/util/Set.iterator:()Ljava/util/Iterator;
       9: invokeinterface #20,  1           // InterfaceMethod java/util/Iterator.hasNext:()Z
      14: ifne          21
      17: iconst_1
      18: goto          22
      21: iconst_0
      22: ireturn

  protected boolean standardEquals(java.lang.Object);
    Code:
       0: aload_0
       1: aload_1
       2: invokestatic  #30                 // Method com/google/common/collect/Maps.equalsImpl:(Ljava/util/Map;Ljava/lang/Object;)Z
       5: ireturn

  protected int standardHashCode();
    Code:
       0: aload_0
       1: invokevirtual #18                 // Method entrySet:()Ljava/util/Set;
       4: invokestatic  #31                 // Method com/google/common/collect/Sets.hashCodeImpl:(Ljava/util/Set;)I
       7: ireturn

  protected java.lang.String standardToString();
    Code:
       0: aload_0
       1: invokestatic  #32                 // Method com/google/common/collect/Maps.toStringImpl:(Ljava/util/Map;)Ljava/lang/String;
       4: areturn

  protected java.lang.Object delegate();
    Code:
       0: aload_0
       1: invokevirtual #2                  // Method delegate:()Ljava/util/Map;
       4: areturn
}
