Compiled from "ImmutableRangeSet.java"
public final class com.google.common.collect.ImmutableRangeSet<C extends java.lang.Comparable> extends com.google.common.collect.AbstractRangeSet<C> implements java.io.Serializable {
  private static final com.google.common.collect.ImmutableRangeSet<java.lang.Comparable<?>> EMPTY;

  private static final com.google.common.collect.ImmutableRangeSet<java.lang.Comparable<?>> ALL;

  private final transient com.google.common.collect.ImmutableList<com.google.common.collect.Range<C>> ranges;

  private transient com.google.common.collect.ImmutableRangeSet<C> complement;

  public static <C extends java.lang.Comparable> com.google.common.collect.ImmutableRangeSet<C> of();
    Code:
       0: getstatic     #2                  // Field EMPTY:Lcom/google/common/collect/ImmutableRangeSet;
       3: areturn

  static <C extends java.lang.Comparable> com.google.common.collect.ImmutableRangeSet<C> all();
    Code:
       0: getstatic     #3                  // Field ALL:Lcom/google/common/collect/ImmutableRangeSet;
       3: areturn

  public static <C extends java.lang.Comparable> com.google.common.collect.ImmutableRangeSet<C> of(com.google.common.collect.Range<C>);
    Code:
       0: aload_0
       1: invokestatic  #4                  // Method com/google/common/base/Preconditions.checkNotNull:(Ljava/lang/Object;)Ljava/lang/Object;
       4: pop
       5: aload_0
       6: invokevirtual #5                  // Method com/google/common/collect/Range.isEmpty:()Z
       9: ifeq          16
      12: invokestatic  #6                  // Method of:()Lcom/google/common/collect/ImmutableRangeSet;
      15: areturn
      16: aload_0
      17: invokestatic  #7                  // Method com/google/common/collect/Range.all:()Lcom/google/common/collect/Range;
      20: invokevirtual #8                  // Method com/google/common/collect/Range.equals:(Ljava/lang/Object;)Z
      23: ifeq          30
      26: invokestatic  #9                  // Method all:()Lcom/google/common/collect/ImmutableRangeSet;
      29: areturn
      30: new           #10                 // class com/google/common/collect/ImmutableRangeSet
      33: dup
      34: aload_0
      35: invokestatic  #11                 // Method com/google/common/collect/ImmutableList.of:(Ljava/lang/Object;)Lcom/google/common/collect/ImmutableList;
      38: invokespecial #12                 // Method "<init>":(Lcom/google/common/collect/ImmutableList;)V
      41: areturn

  public static <C extends java.lang.Comparable> com.google.common.collect.ImmutableRangeSet<C> copyOf(com.google.common.collect.RangeSet<C>);
    Code:
       0: aload_0
       1: invokestatic  #4                  // Method com/google/common/base/Preconditions.checkNotNull:(Ljava/lang/Object;)Ljava/lang/Object;
       4: pop
       5: aload_0
       6: invokeinterface #13,  1           // InterfaceMethod com/google/common/collect/RangeSet.isEmpty:()Z
      11: ifeq          18
      14: invokestatic  #6                  // Method of:()Lcom/google/common/collect/ImmutableRangeSet;
      17: areturn
      18: aload_0
      19: invokestatic  #7                  // Method com/google/common/collect/Range.all:()Lcom/google/common/collect/Range;
      22: invokeinterface #14,  2           // InterfaceMethod com/google/common/collect/RangeSet.encloses:(Lcom/google/common/collect/Range;)Z
      27: ifeq          34
      30: invokestatic  #9                  // Method all:()Lcom/google/common/collect/ImmutableRangeSet;
      33: areturn
      34: aload_0
      35: instanceof    #10                 // class com/google/common/collect/ImmutableRangeSet
      38: ifeq          55
      41: aload_0
      42: checkcast     #10                 // class com/google/common/collect/ImmutableRangeSet
      45: astore_1
      46: aload_1
      47: invokevirtual #15                 // Method isPartialView:()Z
      50: ifne          55
      53: aload_1
      54: areturn
      55: new           #10                 // class com/google/common/collect/ImmutableRangeSet
      58: dup
      59: aload_0
      60: invokeinterface #16,  1           // InterfaceMethod com/google/common/collect/RangeSet.asRanges:()Ljava/util/Set;
      65: invokestatic  #17                 // Method com/google/common/collect/ImmutableList.copyOf:(Ljava/util/Collection;)Lcom/google/common/collect/ImmutableList;
      68: invokespecial #12                 // Method "<init>":(Lcom/google/common/collect/ImmutableList;)V
      71: areturn

  public static <C extends java.lang.Comparable<?>> com.google.common.collect.ImmutableRangeSet<C> unionOf(java.lang.Iterable<com.google.common.collect.Range<C>>);
    Code:
       0: aload_0
       1: invokestatic  #18                 // Method com/google/common/collect/TreeRangeSet.create:(Ljava/lang/Iterable;)Lcom/google/common/collect/TreeRangeSet;
       4: invokestatic  #19                 // Method copyOf:(Lcom/google/common/collect/RangeSet;)Lcom/google/common/collect/ImmutableRangeSet;
       7: areturn

  public static <C extends java.lang.Comparable<?>> com.google.common.collect.ImmutableRangeSet<C> copyOf(java.lang.Iterable<com.google.common.collect.Range<C>>);
    Code:
       0: new           #20                 // class com/google/common/collect/ImmutableRangeSet$Builder
       3: dup
       4: invokespecial #21                 // Method com/google/common/collect/ImmutableRangeSet$Builder."<init>":()V
       7: aload_0
       8: invokevirtual #22                 // Method com/google/common/collect/ImmutableRangeSet$Builder.addAll:(Ljava/lang/Iterable;)Lcom/google/common/collect/ImmutableRangeSet$Builder;
      11: invokevirtual #23                 // Method com/google/common/collect/ImmutableRangeSet$Builder.build:()Lcom/google/common/collect/ImmutableRangeSet;
      14: areturn

  com.google.common.collect.ImmutableRangeSet(com.google.common.collect.ImmutableList<com.google.common.collect.Range<C>>);
    Code:
       0: aload_0
       1: invokespecial #24                 // Method com/google/common/collect/AbstractRangeSet."<init>":()V
       4: aload_0
       5: aload_1
       6: putfield      #1                  // Field ranges:Lcom/google/common/collect/ImmutableList;
       9: return

  private com.google.common.collect.ImmutableRangeSet(com.google.common.collect.ImmutableList<com.google.common.collect.Range<C>>, com.google.common.collect.ImmutableRangeSet<C>);
    Code:
       0: aload_0
       1: invokespecial #24                 // Method com/google/common/collect/AbstractRangeSet."<init>":()V
       4: aload_0
       5: aload_1
       6: putfield      #1                  // Field ranges:Lcom/google/common/collect/ImmutableList;
       9: aload_0
      10: aload_2
      11: putfield      #25                 // Field complement:Lcom/google/common/collect/ImmutableRangeSet;
      14: return

  public boolean intersects(com.google.common.collect.Range<C>);
    Code:
       0: aload_0
       1: getfield      #1                  // Field ranges:Lcom/google/common/collect/ImmutableList;
       4: invokestatic  #26                 // Method com/google/common/collect/Range.lowerBoundFn:()Lcom/google/common/base/Function;
       7: aload_1
       8: getfield      #27                 // Field com/google/common/collect/Range.lowerBound:Lcom/google/common/collect/Cut;
      11: invokestatic  #28                 // Method com/google/common/collect/Ordering.natural:()Lcom/google/common/collect/Ordering;
      14: getstatic     #29                 // Field com/google/common/collect/SortedLists$KeyPresentBehavior.ANY_PRESENT:Lcom/google/common/collect/SortedLists$KeyPresentBehavior;
      17: getstatic     #30                 // Field com/google/common/collect/SortedLists$KeyAbsentBehavior.NEXT_HIGHER:Lcom/google/common/collect/SortedLists$KeyAbsentBehavior;
      20: invokestatic  #31                 // Method com/google/common/collect/SortedLists.binarySearch:(Ljava/util/List;Lcom/google/common/base/Function;Ljava/lang/Object;Ljava/util/Comparator;Lcom/google/common/collect/SortedLists$KeyPresentBehavior;Lcom/google/common/collect/SortedLists$KeyAbsentBehavior;)I
      23: istore_2
      24: iload_2
      25: aload_0
      26: getfield      #1                  // Field ranges:Lcom/google/common/collect/ImmutableList;
      29: invokevirtual #32                 // Method com/google/common/collect/ImmutableList.size:()I
      32: if_icmpge     76
      35: aload_0
      36: getfield      #1                  // Field ranges:Lcom/google/common/collect/ImmutableList;
      39: iload_2
      40: invokevirtual #33                 // Method com/google/common/collect/ImmutableList.get:(I)Ljava/lang/Object;
      43: checkcast     #34                 // class com/google/common/collect/Range
      46: aload_1
      47: invokevirtual #35                 // Method com/google/common/collect/Range.isConnected:(Lcom/google/common/collect/Range;)Z
      50: ifeq          76
      53: aload_0
      54: getfield      #1                  // Field ranges:Lcom/google/common/collect/ImmutableList;
      57: iload_2
      58: invokevirtual #33                 // Method com/google/common/collect/ImmutableList.get:(I)Ljava/lang/Object;
      61: checkcast     #34                 // class com/google/common/collect/Range
      64: aload_1
      65: invokevirtual #36                 // Method com/google/common/collect/Range.intersection:(Lcom/google/common/collect/Range;)Lcom/google/common/collect/Range;
      68: invokevirtual #5                  // Method com/google/common/collect/Range.isEmpty:()Z
      71: ifne          76
      74: iconst_1
      75: ireturn
      76: iload_2
      77: ifle          127
      80: aload_0
      81: getfield      #1                  // Field ranges:Lcom/google/common/collect/ImmutableList;
      84: iload_2
      85: iconst_1
      86: isub
      87: invokevirtual #33                 // Method com/google/common/collect/ImmutableList.get:(I)Ljava/lang/Object;
      90: checkcast     #34                 // class com/google/common/collect/Range
      93: aload_1
      94: invokevirtual #35                 // Method com/google/common/collect/Range.isConnected:(Lcom/google/common/collect/Range;)Z
      97: ifeq          127
     100: aload_0
     101: getfield      #1                  // Field ranges:Lcom/google/common/collect/ImmutableList;
     104: iload_2
     105: iconst_1
     106: isub
     107: invokevirtual #33                 // Method com/google/common/collect/ImmutableList.get:(I)Ljava/lang/Object;
     110: checkcast     #34                 // class com/google/common/collect/Range
     113: aload_1
     114: invokevirtual #36                 // Method com/google/common/collect/Range.intersection:(Lcom/google/common/collect/Range;)Lcom/google/common/collect/Range;
     117: invokevirtual #5                  // Method com/google/common/collect/Range.isEmpty:()Z
     120: ifne          127
     123: iconst_1
     124: goto          128
     127: iconst_0
     128: ireturn

  public boolean encloses(com.google.common.collect.Range<C>);
    Code:
       0: aload_0
       1: getfield      #1                  // Field ranges:Lcom/google/common/collect/ImmutableList;
       4: invokestatic  #26                 // Method com/google/common/collect/Range.lowerBoundFn:()Lcom/google/common/base/Function;
       7: aload_1
       8: getfield      #27                 // Field com/google/common/collect/Range.lowerBound:Lcom/google/common/collect/Cut;
      11: invokestatic  #28                 // Method com/google/common/collect/Ordering.natural:()Lcom/google/common/collect/Ordering;
      14: getstatic     #29                 // Field com/google/common/collect/SortedLists$KeyPresentBehavior.ANY_PRESENT:Lcom/google/common/collect/SortedLists$KeyPresentBehavior;
      17: getstatic     #37                 // Field com/google/common/collect/SortedLists$KeyAbsentBehavior.NEXT_LOWER:Lcom/google/common/collect/SortedLists$KeyAbsentBehavior;
      20: invokestatic  #31                 // Method com/google/common/collect/SortedLists.binarySearch:(Ljava/util/List;Lcom/google/common/base/Function;Ljava/lang/Object;Ljava/util/Comparator;Lcom/google/common/collect/SortedLists$KeyPresentBehavior;Lcom/google/common/collect/SortedLists$KeyAbsentBehavior;)I
      23: istore_2
      24: iload_2
      25: iconst_m1
      26: if_icmpeq     51
      29: aload_0
      30: getfield      #1                  // Field ranges:Lcom/google/common/collect/ImmutableList;
      33: iload_2
      34: invokevirtual #33                 // Method com/google/common/collect/ImmutableList.get:(I)Ljava/lang/Object;
      37: checkcast     #34                 // class com/google/common/collect/Range
      40: aload_1
      41: invokevirtual #38                 // Method com/google/common/collect/Range.encloses:(Lcom/google/common/collect/Range;)Z
      44: ifeq          51
      47: iconst_1
      48: goto          52
      51: iconst_0
      52: ireturn

  public com.google.common.collect.Range<C> rangeContaining(C);
    Code:
       0: aload_0
       1: getfield      #1                  // Field ranges:Lcom/google/common/collect/ImmutableList;
       4: invokestatic  #26                 // Method com/google/common/collect/Range.lowerBoundFn:()Lcom/google/common/base/Function;
       7: aload_1
       8: invokestatic  #39                 // Method com/google/common/collect/Cut.belowValue:(Ljava/lang/Comparable;)Lcom/google/common/collect/Cut;
      11: invokestatic  #28                 // Method com/google/common/collect/Ordering.natural:()Lcom/google/common/collect/Ordering;
      14: getstatic     #29                 // Field com/google/common/collect/SortedLists$KeyPresentBehavior.ANY_PRESENT:Lcom/google/common/collect/SortedLists$KeyPresentBehavior;
      17: getstatic     #37                 // Field com/google/common/collect/SortedLists$KeyAbsentBehavior.NEXT_LOWER:Lcom/google/common/collect/SortedLists$KeyAbsentBehavior;
      20: invokestatic  #31                 // Method com/google/common/collect/SortedLists.binarySearch:(Ljava/util/List;Lcom/google/common/base/Function;Ljava/lang/Object;Ljava/util/Comparator;Lcom/google/common/collect/SortedLists$KeyPresentBehavior;Lcom/google/common/collect/SortedLists$KeyAbsentBehavior;)I
      23: istore_2
      24: iload_2
      25: iconst_m1
      26: if_icmpeq     55
      29: aload_0
      30: getfield      #1                  // Field ranges:Lcom/google/common/collect/ImmutableList;
      33: iload_2
      34: invokevirtual #33                 // Method com/google/common/collect/ImmutableList.get:(I)Ljava/lang/Object;
      37: checkcast     #34                 // class com/google/common/collect/Range
      40: astore_3
      41: aload_3
      42: aload_1
      43: invokevirtual #40                 // Method com/google/common/collect/Range.contains:(Ljava/lang/Comparable;)Z
      46: ifeq          53
      49: aload_3
      50: goto          54
      53: aconst_null
      54: areturn
      55: aconst_null
      56: areturn

  public com.google.common.collect.Range<C> span();
    Code:
       0: aload_0
       1: getfield      #1                  // Field ranges:Lcom/google/common/collect/ImmutableList;
       4: invokevirtual #41                 // Method com/google/common/collect/ImmutableList.isEmpty:()Z
       7: ifeq          18
      10: new           #42                 // class java/util/NoSuchElementException
      13: dup
      14: invokespecial #43                 // Method java/util/NoSuchElementException."<init>":()V
      17: athrow
      18: aload_0
      19: getfield      #1                  // Field ranges:Lcom/google/common/collect/ImmutableList;
      22: iconst_0
      23: invokevirtual #33                 // Method com/google/common/collect/ImmutableList.get:(I)Ljava/lang/Object;
      26: checkcast     #34                 // class com/google/common/collect/Range
      29: getfield      #27                 // Field com/google/common/collect/Range.lowerBound:Lcom/google/common/collect/Cut;
      32: aload_0
      33: getfield      #1                  // Field ranges:Lcom/google/common/collect/ImmutableList;
      36: aload_0
      37: getfield      #1                  // Field ranges:Lcom/google/common/collect/ImmutableList;
      40: invokevirtual #32                 // Method com/google/common/collect/ImmutableList.size:()I
      43: iconst_1
      44: isub
      45: invokevirtual #33                 // Method com/google/common/collect/ImmutableList.get:(I)Ljava/lang/Object;
      48: checkcast     #34                 // class com/google/common/collect/Range
      51: getfield      #44                 // Field com/google/common/collect/Range.upperBound:Lcom/google/common/collect/Cut;
      54: invokestatic  #45                 // Method com/google/common/collect/Range.create:(Lcom/google/common/collect/Cut;Lcom/google/common/collect/Cut;)Lcom/google/common/collect/Range;
      57: areturn

  public boolean isEmpty();
    Code:
       0: aload_0
       1: getfield      #1                  // Field ranges:Lcom/google/common/collect/ImmutableList;
       4: invokevirtual #41                 // Method com/google/common/collect/ImmutableList.isEmpty:()Z
       7: ireturn

  public void add(com.google.common.collect.Range<C>);
    Code:
       0: new           #46                 // class java/lang/UnsupportedOperationException
       3: dup
       4: invokespecial #47                 // Method java/lang/UnsupportedOperationException."<init>":()V
       7: athrow

  public void addAll(com.google.common.collect.RangeSet<C>);
    Code:
       0: new           #46                 // class java/lang/UnsupportedOperationException
       3: dup
       4: invokespecial #47                 // Method java/lang/UnsupportedOperationException."<init>":()V
       7: athrow

  public void addAll(java.lang.Iterable<com.google.common.collect.Range<C>>);
    Code:
       0: new           #46                 // class java/lang/UnsupportedOperationException
       3: dup
       4: invokespecial #47                 // Method java/lang/UnsupportedOperationException."<init>":()V
       7: athrow

  public void remove(com.google.common.collect.Range<C>);
    Code:
       0: new           #46                 // class java/lang/UnsupportedOperationException
       3: dup
       4: invokespecial #47                 // Method java/lang/UnsupportedOperationException."<init>":()V
       7: athrow

  public void removeAll(com.google.common.collect.RangeSet<C>);
    Code:
       0: new           #46                 // class java/lang/UnsupportedOperationException
       3: dup
       4: invokespecial #47                 // Method java/lang/UnsupportedOperationException."<init>":()V
       7: athrow

  public void removeAll(java.lang.Iterable<com.google.common.collect.Range<C>>);
    Code:
       0: new           #46                 // class java/lang/UnsupportedOperationException
       3: dup
       4: invokespecial #47                 // Method java/lang/UnsupportedOperationException."<init>":()V
       7: athrow

  public com.google.common.collect.ImmutableSet<com.google.common.collect.Range<C>> asRanges();
    Code:
       0: aload_0
       1: getfield      #1                  // Field ranges:Lcom/google/common/collect/ImmutableList;
       4: invokevirtual #41                 // Method com/google/common/collect/ImmutableList.isEmpty:()Z
       7: ifeq          14
      10: invokestatic  #48                 // Method com/google/common/collect/ImmutableSet.of:()Lcom/google/common/collect/ImmutableSet;
      13: areturn
      14: new           #49                 // class com/google/common/collect/RegularImmutableSortedSet
      17: dup
      18: aload_0
      19: getfield      #1                  // Field ranges:Lcom/google/common/collect/ImmutableList;
      22: invokestatic  #50                 // Method com/google/common/collect/Range.rangeLexOrdering:()Lcom/google/common/collect/Ordering;
      25: invokespecial #51                 // Method com/google/common/collect/RegularImmutableSortedSet."<init>":(Lcom/google/common/collect/ImmutableList;Ljava/util/Comparator;)V
      28: areturn

  public com.google.common.collect.ImmutableSet<com.google.common.collect.Range<C>> asDescendingSetOfRanges();
    Code:
       0: aload_0
       1: getfield      #1                  // Field ranges:Lcom/google/common/collect/ImmutableList;
       4: invokevirtual #41                 // Method com/google/common/collect/ImmutableList.isEmpty:()Z
       7: ifeq          14
      10: invokestatic  #48                 // Method com/google/common/collect/ImmutableSet.of:()Lcom/google/common/collect/ImmutableSet;
      13: areturn
      14: new           #49                 // class com/google/common/collect/RegularImmutableSortedSet
      17: dup
      18: aload_0
      19: getfield      #1                  // Field ranges:Lcom/google/common/collect/ImmutableList;
      22: invokevirtual #52                 // Method com/google/common/collect/ImmutableList.reverse:()Lcom/google/common/collect/ImmutableList;
      25: invokestatic  #50                 // Method com/google/common/collect/Range.rangeLexOrdering:()Lcom/google/common/collect/Ordering;
      28: invokevirtual #53                 // Method com/google/common/collect/Ordering.reverse:()Lcom/google/common/collect/Ordering;
      31: invokespecial #51                 // Method com/google/common/collect/RegularImmutableSortedSet."<init>":(Lcom/google/common/collect/ImmutableList;Ljava/util/Comparator;)V
      34: areturn

  public com.google.common.collect.ImmutableRangeSet<C> complement();
    Code:
       0: aload_0
       1: getfield      #25                 // Field complement:Lcom/google/common/collect/ImmutableRangeSet;
       4: astore_1
       5: aload_1
       6: ifnull        11
       9: aload_1
      10: areturn
      11: aload_0
      12: getfield      #1                  // Field ranges:Lcom/google/common/collect/ImmutableList;
      15: invokevirtual #41                 // Method com/google/common/collect/ImmutableList.isEmpty:()Z
      18: ifeq          30
      21: aload_0
      22: invokestatic  #9                  // Method all:()Lcom/google/common/collect/ImmutableRangeSet;
      25: dup_x1
      26: putfield      #25                 // Field complement:Lcom/google/common/collect/ImmutableRangeSet;
      29: areturn
      30: aload_0
      31: getfield      #1                  // Field ranges:Lcom/google/common/collect/ImmutableList;
      34: invokevirtual #32                 // Method com/google/common/collect/ImmutableList.size:()I
      37: iconst_1
      38: if_icmpne     70
      41: aload_0
      42: getfield      #1                  // Field ranges:Lcom/google/common/collect/ImmutableList;
      45: iconst_0
      46: invokevirtual #33                 // Method com/google/common/collect/ImmutableList.get:(I)Ljava/lang/Object;
      49: checkcast     #34                 // class com/google/common/collect/Range
      52: invokestatic  #7                  // Method com/google/common/collect/Range.all:()Lcom/google/common/collect/Range;
      55: invokevirtual #8                  // Method com/google/common/collect/Range.equals:(Ljava/lang/Object;)Z
      58: ifeq          70
      61: aload_0
      62: invokestatic  #6                  // Method of:()Lcom/google/common/collect/ImmutableRangeSet;
      65: dup_x1
      66: putfield      #25                 // Field complement:Lcom/google/common/collect/ImmutableRangeSet;
      69: areturn
      70: new           #54                 // class com/google/common/collect/ImmutableRangeSet$ComplementRanges
      73: dup
      74: aload_0
      75: invokespecial #55                 // Method com/google/common/collect/ImmutableRangeSet$ComplementRanges."<init>":(Lcom/google/common/collect/ImmutableRangeSet;)V
      78: astore_2
      79: aload_0
      80: new           #10                 // class com/google/common/collect/ImmutableRangeSet
      83: dup
      84: aload_2
      85: aload_0
      86: invokespecial #56                 // Method "<init>":(Lcom/google/common/collect/ImmutableList;Lcom/google/common/collect/ImmutableRangeSet;)V
      89: dup_x1
      90: putfield      #25                 // Field complement:Lcom/google/common/collect/ImmutableRangeSet;
      93: astore_1
      94: aload_1
      95: areturn

  public com.google.common.collect.ImmutableRangeSet<C> union(com.google.common.collect.RangeSet<C>);
    Code:
       0: aload_0
       1: invokevirtual #57                 // Method asRanges:()Lcom/google/common/collect/ImmutableSet;
       4: aload_1
       5: invokeinterface #16,  1           // InterfaceMethod com/google/common/collect/RangeSet.asRanges:()Ljava/util/Set;
      10: invokestatic  #58                 // Method com/google/common/collect/Iterables.concat:(Ljava/lang/Iterable;Ljava/lang/Iterable;)Ljava/lang/Iterable;
      13: invokestatic  #59                 // Method unionOf:(Ljava/lang/Iterable;)Lcom/google/common/collect/ImmutableRangeSet;
      16: areturn

  public com.google.common.collect.ImmutableRangeSet<C> intersection(com.google.common.collect.RangeSet<C>);
    Code:
       0: aload_0
       1: invokestatic  #60                 // Method com/google/common/collect/TreeRangeSet.create:(Lcom/google/common/collect/RangeSet;)Lcom/google/common/collect/TreeRangeSet;
       4: astore_2
       5: aload_2
       6: aload_1
       7: invokeinterface #61,  1           // InterfaceMethod com/google/common/collect/RangeSet.complement:()Lcom/google/common/collect/RangeSet;
      12: invokeinterface #62,  2           // InterfaceMethod com/google/common/collect/RangeSet.removeAll:(Lcom/google/common/collect/RangeSet;)V
      17: aload_2
      18: invokestatic  #19                 // Method copyOf:(Lcom/google/common/collect/RangeSet;)Lcom/google/common/collect/ImmutableRangeSet;
      21: areturn

  public com.google.common.collect.ImmutableRangeSet<C> difference(com.google.common.collect.RangeSet<C>);
    Code:
       0: aload_0
       1: invokestatic  #60                 // Method com/google/common/collect/TreeRangeSet.create:(Lcom/google/common/collect/RangeSet;)Lcom/google/common/collect/TreeRangeSet;
       4: astore_2
       5: aload_2
       6: aload_1
       7: invokeinterface #62,  2           // InterfaceMethod com/google/common/collect/RangeSet.removeAll:(Lcom/google/common/collect/RangeSet;)V
      12: aload_2
      13: invokestatic  #19                 // Method copyOf:(Lcom/google/common/collect/RangeSet;)Lcom/google/common/collect/ImmutableRangeSet;
      16: areturn

  private com.google.common.collect.ImmutableList<com.google.common.collect.Range<C>> intersectRanges(com.google.common.collect.Range<C>);
    Code:
       0: aload_0
       1: getfield      #1                  // Field ranges:Lcom/google/common/collect/ImmutableList;
       4: invokevirtual #41                 // Method com/google/common/collect/ImmutableList.isEmpty:()Z
       7: ifne          17
      10: aload_1
      11: invokevirtual #5                  // Method com/google/common/collect/Range.isEmpty:()Z
      14: ifeq          21
      17: invokestatic  #63                 // Method com/google/common/collect/ImmutableList.of:()Lcom/google/common/collect/ImmutableList;
      20: areturn
      21: aload_1
      22: aload_0
      23: invokevirtual #64                 // Method span:()Lcom/google/common/collect/Range;
      26: invokevirtual #38                 // Method com/google/common/collect/Range.encloses:(Lcom/google/common/collect/Range;)Z
      29: ifeq          37
      32: aload_0
      33: getfield      #1                  // Field ranges:Lcom/google/common/collect/ImmutableList;
      36: areturn
      37: aload_1
      38: invokevirtual #65                 // Method com/google/common/collect/Range.hasLowerBound:()Z
      41: ifeq          68
      44: aload_0
      45: getfield      #1                  // Field ranges:Lcom/google/common/collect/ImmutableList;
      48: invokestatic  #66                 // Method com/google/common/collect/Range.upperBoundFn:()Lcom/google/common/base/Function;
      51: aload_1
      52: getfield      #27                 // Field com/google/common/collect/Range.lowerBound:Lcom/google/common/collect/Cut;
      55: getstatic     #67                 // Field com/google/common/collect/SortedLists$KeyPresentBehavior.FIRST_AFTER:Lcom/google/common/collect/SortedLists$KeyPresentBehavior;
      58: getstatic     #30                 // Field com/google/common/collect/SortedLists$KeyAbsentBehavior.NEXT_HIGHER:Lcom/google/common/collect/SortedLists$KeyAbsentBehavior;
      61: invokestatic  #68                 // Method com/google/common/collect/SortedLists.binarySearch:(Ljava/util/List;Lcom/google/common/base/Function;Ljava/lang/Comparable;Lcom/google/common/collect/SortedLists$KeyPresentBehavior;Lcom/google/common/collect/SortedLists$KeyAbsentBehavior;)I
      64: istore_2
      65: goto          70
      68: iconst_0
      69: istore_2
      70: aload_1
      71: invokevirtual #69                 // Method com/google/common/collect/Range.hasUpperBound:()Z
      74: ifeq          101
      77: aload_0
      78: getfield      #1                  // Field ranges:Lcom/google/common/collect/ImmutableList;
      81: invokestatic  #26                 // Method com/google/common/collect/Range.lowerBoundFn:()Lcom/google/common/base/Function;
      84: aload_1
      85: getfield      #44                 // Field com/google/common/collect/Range.upperBound:Lcom/google/common/collect/Cut;
      88: getstatic     #70                 // Field com/google/common/collect/SortedLists$KeyPresentBehavior.FIRST_PRESENT:Lcom/google/common/collect/SortedLists$KeyPresentBehavior;
      91: getstatic     #30                 // Field com/google/common/collect/SortedLists$KeyAbsentBehavior.NEXT_HIGHER:Lcom/google/common/collect/SortedLists$KeyAbsentBehavior;
      94: invokestatic  #68                 // Method com/google/common/collect/SortedLists.binarySearch:(Ljava/util/List;Lcom/google/common/base/Function;Ljava/lang/Comparable;Lcom/google/common/collect/SortedLists$KeyPresentBehavior;Lcom/google/common/collect/SortedLists$KeyAbsentBehavior;)I
      97: istore_3
      98: goto          109
     101: aload_0
     102: getfield      #1                  // Field ranges:Lcom/google/common/collect/ImmutableList;
     105: invokevirtual #32                 // Method com/google/common/collect/ImmutableList.size:()I
     108: istore_3
     109: iload_3
     110: iload_2
     111: isub
     112: istore        4
     114: iload         4
     116: ifne          123
     119: invokestatic  #63                 // Method com/google/common/collect/ImmutableList.of:()Lcom/google/common/collect/ImmutableList;
     122: areturn
     123: new           #71                 // class com/google/common/collect/ImmutableRangeSet$1
     126: dup
     127: aload_0
     128: iload         4
     130: iload_2
     131: aload_1
     132: invokespecial #72                 // Method com/google/common/collect/ImmutableRangeSet$1."<init>":(Lcom/google/common/collect/ImmutableRangeSet;IILcom/google/common/collect/Range;)V
     135: areturn

  public com.google.common.collect.ImmutableRangeSet<C> subRangeSet(com.google.common.collect.Range<C>);
    Code:
       0: aload_0
       1: invokevirtual #73                 // Method isEmpty:()Z
       4: ifne          43
       7: aload_0
       8: invokevirtual #64                 // Method span:()Lcom/google/common/collect/Range;
      11: astore_2
      12: aload_1
      13: aload_2
      14: invokevirtual #38                 // Method com/google/common/collect/Range.encloses:(Lcom/google/common/collect/Range;)Z
      17: ifeq          22
      20: aload_0
      21: areturn
      22: aload_1
      23: aload_2
      24: invokevirtual #35                 // Method com/google/common/collect/Range.isConnected:(Lcom/google/common/collect/Range;)Z
      27: ifeq          43
      30: new           #10                 // class com/google/common/collect/ImmutableRangeSet
      33: dup
      34: aload_0
      35: aload_1
      36: invokespecial #74                 // Method intersectRanges:(Lcom/google/common/collect/Range;)Lcom/google/common/collect/ImmutableList;
      39: invokespecial #12                 // Method "<init>":(Lcom/google/common/collect/ImmutableList;)V
      42: areturn
      43: invokestatic  #6                  // Method of:()Lcom/google/common/collect/ImmutableRangeSet;
      46: areturn

  public com.google.common.collect.ImmutableSortedSet<C> asSet(com.google.common.collect.DiscreteDomain<C>);
    Code:
       0: aload_1
       1: invokestatic  #4                  // Method com/google/common/base/Preconditions.checkNotNull:(Ljava/lang/Object;)Ljava/lang/Object;
       4: pop
       5: aload_0
       6: invokevirtual #73                 // Method isEmpty:()Z
       9: ifeq          16
      12: invokestatic  #75                 // Method com/google/common/collect/ImmutableSortedSet.of:()Lcom/google/common/collect/ImmutableSortedSet;
      15: areturn
      16: aload_0
      17: invokevirtual #64                 // Method span:()Lcom/google/common/collect/Range;
      20: aload_1
      21: invokevirtual #76                 // Method com/google/common/collect/Range.canonical:(Lcom/google/common/collect/DiscreteDomain;)Lcom/google/common/collect/Range;
      24: astore_2
      25: aload_2
      26: invokevirtual #65                 // Method com/google/common/collect/Range.hasLowerBound:()Z
      29: ifne          42
      32: new           #77                 // class java/lang/IllegalArgumentException
      35: dup
      36: ldc           #78                 // String Neither the DiscreteDomain nor this range set are bounded below
      38: invokespecial #79                 // Method java/lang/IllegalArgumentException."<init>":(Ljava/lang/String;)V
      41: athrow
      42: aload_2
      43: invokevirtual #69                 // Method com/google/common/collect/Range.hasUpperBound:()Z
      46: ifne          68
      49: aload_1
      50: invokevirtual #80                 // Method com/google/common/collect/DiscreteDomain.maxValue:()Ljava/lang/Comparable;
      53: pop
      54: goto          68
      57: astore_3
      58: new           #77                 // class java/lang/IllegalArgumentException
      61: dup
      62: ldc           #81                 // String Neither the DiscreteDomain nor this range set are bounded above
      64: invokespecial #79                 // Method java/lang/IllegalArgumentException."<init>":(Ljava/lang/String;)V
      67: athrow
      68: new           #82                 // class com/google/common/collect/ImmutableRangeSet$AsSet
      71: dup
      72: aload_0
      73: aload_1
      74: invokespecial #83                 // Method com/google/common/collect/ImmutableRangeSet$AsSet."<init>":(Lcom/google/common/collect/ImmutableRangeSet;Lcom/google/common/collect/DiscreteDomain;)V
      77: areturn
    Exception table:
       from    to  target type
          49    54    57   Class java/util/NoSuchElementException

  boolean isPartialView();
    Code:
       0: aload_0
       1: getfield      #1                  // Field ranges:Lcom/google/common/collect/ImmutableList;
       4: invokevirtual #84                 // Method com/google/common/collect/ImmutableList.isPartialView:()Z
       7: ireturn

  public static <C extends java.lang.Comparable<?>> com.google.common.collect.ImmutableRangeSet$Builder<C> builder();
    Code:
       0: new           #20                 // class com/google/common/collect/ImmutableRangeSet$Builder
       3: dup
       4: invokespecial #21                 // Method com/google/common/collect/ImmutableRangeSet$Builder."<init>":()V
       7: areturn

  java.lang.Object writeReplace();
    Code:
       0: new           #85                 // class com/google/common/collect/ImmutableRangeSet$SerializedForm
       3: dup
       4: aload_0
       5: getfield      #1                  // Field ranges:Lcom/google/common/collect/ImmutableList;
       8: invokespecial #86                 // Method com/google/common/collect/ImmutableRangeSet$SerializedForm."<init>":(Lcom/google/common/collect/ImmutableList;)V
      11: areturn

  public boolean equals(java.lang.Object);
    Code:
       0: aload_0
       1: aload_1
       2: invokespecial #87                 // Method com/google/common/collect/AbstractRangeSet.equals:(Ljava/lang/Object;)Z
       5: ireturn

  public boolean enclosesAll(com.google.common.collect.RangeSet);
    Code:
       0: aload_0
       1: aload_1
       2: invokespecial #88                 // Method com/google/common/collect/AbstractRangeSet.enclosesAll:(Lcom/google/common/collect/RangeSet;)Z
       5: ireturn

  public void clear();
    Code:
       0: aload_0
       1: invokespecial #89                 // Method com/google/common/collect/AbstractRangeSet.clear:()V
       4: return

  public boolean contains(java.lang.Comparable);
    Code:
       0: aload_0
       1: aload_1
       2: invokespecial #90                 // Method com/google/common/collect/AbstractRangeSet.contains:(Ljava/lang/Comparable;)Z
       5: ireturn

  public com.google.common.collect.RangeSet subRangeSet(com.google.common.collect.Range);
    Code:
       0: aload_0
       1: aload_1
       2: invokevirtual #91                 // Method subRangeSet:(Lcom/google/common/collect/Range;)Lcom/google/common/collect/ImmutableRangeSet;
       5: areturn

  public com.google.common.collect.RangeSet complement();
    Code:
       0: aload_0
       1: invokevirtual #92                 // Method complement:()Lcom/google/common/collect/ImmutableRangeSet;
       4: areturn

  public java.util.Set asDescendingSetOfRanges();
    Code:
       0: aload_0
       1: invokevirtual #93                 // Method asDescendingSetOfRanges:()Lcom/google/common/collect/ImmutableSet;
       4: areturn

  public java.util.Set asRanges();
    Code:
       0: aload_0
       1: invokevirtual #57                 // Method asRanges:()Lcom/google/common/collect/ImmutableSet;
       4: areturn

  static com.google.common.collect.ImmutableList access$000(com.google.common.collect.ImmutableRangeSet);
    Code:
       0: aload_0
       1: getfield      #1                  // Field ranges:Lcom/google/common/collect/ImmutableList;
       4: areturn

  static {};
    Code:
       0: new           #10                 // class com/google/common/collect/ImmutableRangeSet
       3: dup
       4: invokestatic  #63                 // Method com/google/common/collect/ImmutableList.of:()Lcom/google/common/collect/ImmutableList;
       7: invokespecial #12                 // Method "<init>":(Lcom/google/common/collect/ImmutableList;)V
      10: putstatic     #2                  // Field EMPTY:Lcom/google/common/collect/ImmutableRangeSet;
      13: new           #10                 // class com/google/common/collect/ImmutableRangeSet
      16: dup
      17: invokestatic  #7                  // Method com/google/common/collect/Range.all:()Lcom/google/common/collect/Range;
      20: invokestatic  #11                 // Method com/google/common/collect/ImmutableList.of:(Ljava/lang/Object;)Lcom/google/common/collect/ImmutableList;
      23: invokespecial #12                 // Method "<init>":(Lcom/google/common/collect/ImmutableList;)V
      26: putstatic     #3                  // Field ALL:Lcom/google/common/collect/ImmutableRangeSet;
      29: return
}
