Compiled from "OMToDOMConverter.java"
public class org.apache.neethi.builders.converters.OMToDOMConverter extends org.apache.neethi.builders.converters.AbstractOMConverter implements org.apache.neethi.builders.converters.Converter<org.apache.axiom.om.OMElement, org.w3c.dom.Element> {
  public org.apache.neethi.builders.converters.OMToDOMConverter();
    Code:
       0: aload_0
       1: invokespecial #1                  // Method org/apache/neethi/builders/converters/AbstractOMConverter."<init>":()V
       4: return

  public org.w3c.dom.Element convert(org.apache.axiom.om.OMElement);
    Code:
       0: ldc           #2                  // String dom
       2: invokestatic  #3                  // Method org/apache/axiom/om/OMAbstractFactory.getMetaFactory:(Ljava/lang/String;)Lorg/apache/axiom/om/OMMetaFactory;
       5: invokeinterface #4,  1            // InterfaceMethod org/apache/axiom/om/OMMetaFactory.getOMFactory:()Lorg/apache/axiom/om/OMFactory;
      10: aload_1
      11: invokeinterface #5,  1            // InterfaceMethod org/apache/axiom/om/OMElement.getXMLStreamReader:()Ljavax/xml/stream/XMLStreamReader;
      16: invokestatic  #6                  // Method org/apache/axiom/om/OMXMLBuilderFactory.createStAXOMBuilder:(Lorg/apache/axiom/om/OMFactory;Ljavax/xml/stream/XMLStreamReader;)Lorg/apache/axiom/om/OMXMLParserWrapper;
      19: invokeinterface #7,  1            // InterfaceMethod org/apache/axiom/om/OMXMLParserWrapper.getDocumentElement:()Lorg/apache/axiom/om/OMElement;
      24: checkcast     #8                  // class org/w3c/dom/Element
      27: areturn
      28: astore_2
      29: new           #10                 // class org/apache/neethi/builders/converters/StaxToDOMConverter
      32: dup
      33: invokespecial #11                 // Method org/apache/neethi/builders/converters/StaxToDOMConverter."<init>":()V
      36: aload_1
      37: invokeinterface #5,  1            // InterfaceMethod org/apache/axiom/om/OMElement.getXMLStreamReader:()Ljavax/xml/stream/XMLStreamReader;
      42: invokevirtual #12                 // Method org/apache/neethi/builders/converters/StaxToDOMConverter.convert:(Ljavax/xml/stream/XMLStreamReader;)Lorg/w3c/dom/Element;
      45: areturn
    Exception table:
       from    to  target type
           0    27    28   Class org/apache/axiom/om/OMException

  public java.lang.Object convert(java.lang.Object);
    Code:
       0: aload_0
       1: aload_1
       2: checkcast     #13                 // class org/apache/axiom/om/OMElement
       5: invokevirtual #14                 // Method convert:(Lorg/apache/axiom/om/OMElement;)Lorg/w3c/dom/Element;
       8: areturn

  public java.util.Iterator getChildren(java.lang.Object);
    Code:
       0: aload_0
       1: aload_1
       2: checkcast     #13                 // class org/apache/axiom/om/OMElement
       5: invokespecial #15                 // Method org/apache/neethi/builders/converters/AbstractOMConverter.getChildren:(Lorg/apache/axiom/om/OMElement;)Ljava/util/Iterator;
       8: areturn

  public java.util.Map getAttributes(java.lang.Object);
    Code:
       0: aload_0
       1: aload_1
       2: checkcast     #13                 // class org/apache/axiom/om/OMElement
       5: invokespecial #16                 // Method org/apache/neethi/builders/converters/AbstractOMConverter.getAttributes:(Lorg/apache/axiom/om/OMElement;)Ljava/util/Map;
       8: areturn

  public javax.xml.namespace.QName getQName(java.lang.Object);
    Code:
       0: aload_0
       1: aload_1
       2: checkcast     #13                 // class org/apache/axiom/om/OMElement
       5: invokespecial #17                 // Method org/apache/neethi/builders/converters/AbstractOMConverter.getQName:(Lorg/apache/axiom/om/OMElement;)Ljavax/xml/namespace/QName;
       8: areturn
}
