Compiled from "InboundWSSecurityContextImpl.java"
public class org.apache.wss4j.stax.impl.InboundWSSecurityContextImpl extends org.apache.xml.security.stax.impl.InboundSecurityContextImpl implements org.apache.wss4j.stax.ext.WSInboundSecurityContext {
  private static final org.slf4j.Logger LOG;

  private final java.util.Deque<org.apache.xml.security.stax.securityEvent.SecurityEvent> securityEventQueue;

  private boolean operationSecurityEventOccured;

  private boolean messageEncryptionTokenOccured;

  private boolean allowRSA15KeyTransportAlgorithm;

  private boolean disableBSPEnforcement;

  private java.util.List<org.apache.wss4j.common.bsp.BSPRule> ignoredBSPRules;

  public org.apache.wss4j.stax.impl.InboundWSSecurityContextImpl();
    Code:
       0: aload_0
       1: invokespecial #1                  // Method org/apache/xml/security/stax/impl/InboundSecurityContextImpl."<init>":()V
       4: aload_0
       5: new           #2                  // class java/util/ArrayDeque
       8: dup
       9: invokespecial #3                  // Method java/util/ArrayDeque."<init>":()V
      12: putfield      #4                  // Field securityEventQueue:Ljava/util/Deque;
      15: aload_0
      16: iconst_0
      17: putfield      #5                  // Field operationSecurityEventOccured:Z
      20: aload_0
      21: iconst_0
      22: putfield      #6                  // Field messageEncryptionTokenOccured:Z
      25: aload_0
      26: iconst_0
      27: putfield      #7                  // Field allowRSA15KeyTransportAlgorithm:Z
      30: aload_0
      31: invokestatic  #8                  // Method java/util/Collections.emptyList:()Ljava/util/List;
      34: putfield      #9                  // Field ignoredBSPRules:Ljava/util/List;
      37: return

  public synchronized void registerSecurityEvent(org.apache.xml.security.stax.securityEvent.SecurityEvent) throws org.apache.xml.security.exceptions.XMLSecurityException;
    Code:
       0: getstatic     #10                 // Field org/apache/wss4j/stax/securityEvent/WSSecurityEventConstants.AlgorithmSuite:Lorg/apache/xml/security/stax/securityEvent/SecurityEventConstants$Event;
       3: aload_1
       4: invokevirtual #11                 // Method org/apache/xml/security/stax/securityEvent/SecurityEvent.getSecurityEventType:()Lorg/apache/xml/security/stax/securityEvent/SecurityEventConstants$Event;
       7: invokevirtual #12                 // Method org/apache/xml/security/stax/securityEvent/SecurityEventConstants$Event.equals:(Ljava/lang/Object;)Z
      10: ifeq          19
      13: aload_0
      14: aload_1
      15: invokevirtual #13                 // Method forwardSecurityEvent:(Lorg/apache/xml/security/stax/securityEvent/SecurityEvent;)V
      18: return
      19: aload_0
      20: getfield      #5                  // Field operationSecurityEventOccured:Z
      23: ifeq          112
      26: aload_0
      27: getfield      #6                  // Field messageEncryptionTokenOccured:Z
      30: ifne          106
      33: aload_1
      34: instanceof    #14                 // class org/apache/xml/security/stax/securityEvent/TokenSecurityEvent
      37: ifeq          106
      40: aload_1
      41: checkcast     #14                 // class org/apache/xml/security/stax/securityEvent/TokenSecurityEvent
      44: astore_2
      45: aload_2
      46: invokevirtual #15                 // Method org/apache/xml/security/stax/securityEvent/TokenSecurityEvent.getSecurityToken:()Lorg/apache/xml/security/stax/securityToken/SecurityToken;
      49: checkcast     #16                 // class org/apache/xml/security/stax/securityToken/InboundSecurityToken
      52: invokeinterface #17,  1           // InterfaceMethod org/apache/xml/security/stax/securityToken/InboundSecurityToken.getTokenUsages:()Ljava/util/List;
      57: getstatic     #18                 // Field org/apache/wss4j/stax/securityToken/WSSecurityTokenConstants.TokenUsage_Encryption:Lorg/apache/xml/security/stax/securityToken/SecurityTokenConstants$TokenUsage;
      60: invokeinterface #19,  2           // InterfaceMethod java/util/List.contains:(Ljava/lang/Object;)Z
      65: ifeq          106
      68: aload_2
      69: invokevirtual #15                 // Method org/apache/xml/security/stax/securityEvent/TokenSecurityEvent.getSecurityToken:()Lorg/apache/xml/security/stax/securityToken/SecurityToken;
      72: invokestatic  #20                 // Method org/apache/wss4j/stax/utils/WSSUtils.getRootToken:(Lorg/apache/xml/security/stax/securityToken/SecurityToken;)Lorg/apache/xml/security/stax/securityToken/SecurityToken;
      75: checkcast     #16                 // class org/apache/xml/security/stax/securityToken/InboundSecurityToken
      78: astore_3
      79: aload_3
      80: aload_2
      81: invokevirtual #21                 // Method org/apache/xml/security/stax/securityEvent/TokenSecurityEvent.getCorrelationID:()Ljava/lang/String;
      84: invokestatic  #22                 // Method org/apache/wss4j/stax/utils/WSSUtils.createTokenSecurityEvent:(Lorg/apache/xml/security/stax/securityToken/InboundSecurityToken;Ljava/lang/String;)Lorg/apache/xml/security/stax/securityEvent/TokenSecurityEvent;
      87: astore        4
      89: aload_0
      90: aload         4
      92: getstatic     #23                 // Field org/apache/wss4j/stax/securityToken/WSSecurityTokenConstants.TokenUsage_MainEncryption:Lorg/apache/xml/security/stax/securityToken/SecurityTokenConstants$TokenUsage;
      95: invokespecial #24                 // Method setTokenUsage:(Lorg/apache/xml/security/stax/securityEvent/TokenSecurityEvent;Lorg/apache/xml/security/stax/securityToken/SecurityTokenConstants$TokenUsage;)V
      98: aload         4
     100: astore_1
     101: aload_0
     102: iconst_1
     103: putfield      #6                  // Field messageEncryptionTokenOccured:Z
     106: aload_0
     107: aload_1
     108: invokevirtual #13                 // Method forwardSecurityEvent:(Lorg/apache/xml/security/stax/securityEvent/SecurityEvent;)V
     111: return
     112: getstatic     #25                 // Field org/apache/wss4j/stax/securityEvent/WSSecurityEventConstants.Operation:Lorg/apache/xml/security/stax/securityEvent/SecurityEventConstants$Event;
     115: aload_1
     116: invokevirtual #11                 // Method org/apache/xml/security/stax/securityEvent/SecurityEvent.getSecurityEventType:()Lorg/apache/xml/security/stax/securityEvent/SecurityEventConstants$Event;
     119: invokevirtual #12                 // Method org/apache/xml/security/stax/securityEvent/SecurityEventConstants$Event.equals:(Ljava/lang/Object;)Z
     122: ifeq          190
     125: aload_0
     126: iconst_1
     127: putfield      #5                  // Field operationSecurityEventOccured:Z
     130: aload_0
     131: aload_0
     132: getfield      #4                  // Field securityEventQueue:Ljava/util/Deque;
     135: invokespecial #26                 // Method identifySecurityTokenDepenedenciesAndUsage:(Ljava/util/Deque;)V
     138: aload_0
     139: getfield      #4                  // Field securityEventQueue:Ljava/util/Deque;
     142: invokeinterface #27,  1           // InterfaceMethod java/util/Deque.descendingIterator:()Ljava/util/Iterator;
     147: astore_2
     148: aload_2
     149: invokeinterface #28,  1           // InterfaceMethod java/util/Iterator.hasNext:()Z
     154: ifeq          175
     157: aload_2
     158: invokeinterface #29,  1           // InterfaceMethod java/util/Iterator.next:()Ljava/lang/Object;
     163: checkcast     #30                 // class org/apache/xml/security/stax/securityEvent/SecurityEvent
     166: astore_3
     167: aload_0
     168: aload_3
     169: invokevirtual #13                 // Method forwardSecurityEvent:(Lorg/apache/xml/security/stax/securityEvent/SecurityEvent;)V
     172: goto          148
     175: aload_0
     176: aload_1
     177: invokevirtual #13                 // Method forwardSecurityEvent:(Lorg/apache/xml/security/stax/securityEvent/SecurityEvent;)V
     180: aload_0
     181: getfield      #4                  // Field securityEventQueue:Ljava/util/Deque;
     184: invokeinterface #31,  1           // InterfaceMethod java/util/Deque.clear:()V
     189: return
     190: aload_0
     191: getfield      #4                  // Field securityEventQueue:Ljava/util/Deque;
     194: aload_1
     195: invokeinterface #32,  2           // InterfaceMethod java/util/Deque.push:(Ljava/lang/Object;)V
     200: return

  protected void forwardSecurityEvent(org.apache.xml.security.stax.securityEvent.SecurityEvent) throws org.apache.xml.security.exceptions.XMLSecurityException;
    Code:
       0: aload_0
       1: getfield      #7                  // Field allowRSA15KeyTransportAlgorithm:Z
       4: ifne          71
       7: getstatic     #33                 // Field org/apache/xml/security/stax/securityEvent/SecurityEventConstants.AlgorithmSuite:Lorg/apache/xml/security/stax/securityEvent/SecurityEventConstants$Event;
      10: aload_1
      11: invokevirtual #11                 // Method org/apache/xml/security/stax/securityEvent/SecurityEvent.getSecurityEventType:()Lorg/apache/xml/security/stax/securityEvent/SecurityEventConstants$Event;
      14: invokevirtual #12                 // Method org/apache/xml/security/stax/securityEvent/SecurityEventConstants$Event.equals:(Ljava/lang/Object;)Z
      17: ifeq          71
      20: aload_1
      21: checkcast     #34                 // class org/apache/xml/security/stax/securityEvent/AlgorithmSuiteSecurityEvent
      24: astore_2
      25: aload_0
      26: ldc           #35                 // String secureProcessing.AllowRSA15KeyTransportAlgorithm
      28: invokevirtual #36                 // Method get:(Ljava/lang/String;)Ljava/lang/Object;
      31: checkcast     #37                 // class java/lang/Boolean
      34: astore_3
      35: aload_3
      36: ifnull        46
      39: aload_3
      40: invokevirtual #38                 // Method java/lang/Boolean.booleanValue:()Z
      43: ifne          71
      46: ldc           #39                 // String http://www.w3.org/2001/04/xmlenc#rsa-1_5
      48: aload_2
      49: invokevirtual #40                 // Method org/apache/xml/security/stax/securityEvent/AlgorithmSuiteSecurityEvent.getAlgorithmURI:()Ljava/lang/String;
      52: invokevirtual #41                 // Method java/lang/String.equals:(Ljava/lang/Object;)Z
      55: ifeq          71
      58: new           #42                 // class org/apache/wss4j/common/ext/WSSecurityException
      61: dup
      62: getstatic     #43                 // Field org/apache/wss4j/common/ext/WSSecurityException$ErrorCode.FAILED_CHECK:Lorg/apache/wss4j/common/ext/WSSecurityException$ErrorCode;
      65: ldc           #35                 // String secureProcessing.AllowRSA15KeyTransportAlgorithm
      67: invokespecial #44                 // Method org/apache/wss4j/common/ext/WSSecurityException."<init>":(Lorg/apache/wss4j/common/ext/WSSecurityException$ErrorCode;Ljava/lang/String;)V
      70: athrow
      71: aload_0
      72: aload_1
      73: invokespecial #45                 // Method org/apache/xml/security/stax/impl/InboundSecurityContextImpl.forwardSecurityEvent:(Lorg/apache/xml/security/stax/securityEvent/SecurityEvent;)V
      76: goto          95
      79: astore_2
      80: aload_2
      81: athrow
      82: astore_2
      83: new           #42                 // class org/apache/wss4j/common/ext/WSSecurityException
      86: dup
      87: getstatic     #43                 // Field org/apache/wss4j/common/ext/WSSecurityException$ErrorCode.FAILED_CHECK:Lorg/apache/wss4j/common/ext/WSSecurityException$ErrorCode;
      90: aload_2
      91: invokespecial #47                 // Method org/apache/wss4j/common/ext/WSSecurityException."<init>":(Lorg/apache/wss4j/common/ext/WSSecurityException$ErrorCode;Ljava/lang/Exception;)V
      94: athrow
      95: return
    Exception table:
       from    to  target type
          71    76    79   Class org/apache/wss4j/common/ext/WSSecurityException
          71    76    82   Class org/apache/xml/security/exceptions/XMLSecurityException

  private void identifySecurityTokenDepenedenciesAndUsage(java.util.Deque<org.apache.xml.security.stax.securityEvent.SecurityEvent>) throws org.apache.xml.security.exceptions.XMLSecurityException;
    Code:
       0: invokestatic  #8                  // Method java/util/Collections.emptyList:()Ljava/util/List;
       3: astore_2
       4: invokestatic  #8                  // Method java/util/Collections.emptyList:()Ljava/util/List;
       7: astore_3
       8: invokestatic  #8                  // Method java/util/Collections.emptyList:()Ljava/util/List;
      11: astore        4
      13: invokestatic  #8                  // Method java/util/Collections.emptyList:()Ljava/util/List;
      16: astore        5
      18: invokestatic  #8                  // Method java/util/Collections.emptyList:()Ljava/util/List;
      21: astore        6
      23: invokestatic  #8                  // Method java/util/Collections.emptyList:()Ljava/util/List;
      26: astore        7
      28: invokestatic  #8                  // Method java/util/Collections.emptyList:()Ljava/util/List;
      31: astore        8
      33: invokestatic  #8                  // Method java/util/Collections.emptyList:()Ljava/util/List;
      36: astore        9
      38: invokestatic  #8                  // Method java/util/Collections.emptyList:()Ljava/util/List;
      41: astore        10
      43: invokestatic  #8                  // Method java/util/Collections.emptyList:()Ljava/util/List;
      46: astore        11
      48: aconst_null
      49: astore        12
      51: new           #48                 // class java/util/ArrayList
      54: dup
      55: invokespecial #49                 // Method java/util/ArrayList."<init>":()V
      58: astore        13
      60: aload_1
      61: invokeinterface #50,  1           // InterfaceMethod java/util/Deque.iterator:()Ljava/util/Iterator;
      66: astore        14
      68: aload         14
      70: invokeinterface #28,  1           // InterfaceMethod java/util/Iterator.hasNext:()Z
      75: ifeq          251
      78: aload         14
      80: invokeinterface #29,  1           // InterfaceMethod java/util/Iterator.next:()Ljava/lang/Object;
      85: checkcast     #30                 // class org/apache/xml/security/stax/securityEvent/SecurityEvent
      88: astore        15
      90: aload         15
      92: instanceof    #14                 // class org/apache/xml/security/stax/securityEvent/TokenSecurityEvent
      95: ifeq          248
      98: aload         15
     100: checkcast     #14                 // class org/apache/xml/security/stax/securityEvent/TokenSecurityEvent
     103: astore        16
     105: getstatic     #51                 // Field org/apache/wss4j/stax/securityEvent/WSSecurityEventConstants.HttpsToken:Lorg/apache/xml/security/stax/securityEvent/SecurityEventConstants$Event;
     108: aload         15
     110: invokevirtual #11                 // Method org/apache/xml/security/stax/securityEvent/SecurityEvent.getSecurityEventType:()Lorg/apache/xml/security/stax/securityEvent/SecurityEventConstants$Event;
     113: invokevirtual #12                 // Method org/apache/xml/security/stax/securityEvent/SecurityEventConstants$Event.equals:(Ljava/lang/Object;)Z
     116: ifeq          238
     119: aload         16
     121: checkcast     #52                 // class org/apache/wss4j/stax/securityEvent/HttpsTokenSecurityEvent
     124: astore        17
     126: aload         17
     128: invokevirtual #53                 // Method org/apache/wss4j/stax/securityEvent/HttpsTokenSecurityEvent.getSecurityToken:()Lorg/apache/xml/security/stax/securityToken/SecurityToken;
     131: checkcast     #54                 // class org/apache/wss4j/stax/securityToken/HttpsSecurityToken
     134: invokeinterface #55,  1           // InterfaceMethod org/apache/wss4j/stax/securityToken/HttpsSecurityToken.getTokenUsages:()Ljava/util/List;
     139: invokeinterface #56,  1           // InterfaceMethod java/util/List.clear:()V
     144: aload         17
     146: invokevirtual #53                 // Method org/apache/wss4j/stax/securityEvent/HttpsTokenSecurityEvent.getSecurityToken:()Lorg/apache/xml/security/stax/securityToken/SecurityToken;
     149: checkcast     #54                 // class org/apache/wss4j/stax/securityToken/HttpsSecurityToken
     152: getstatic     #57                 // Field org/apache/wss4j/stax/securityToken/WSSecurityTokenConstants.TokenUsage_MainSignature:Lorg/apache/xml/security/stax/securityToken/SecurityTokenConstants$TokenUsage;
     155: invokeinterface #58,  2           // InterfaceMethod org/apache/wss4j/stax/securityToken/HttpsSecurityToken.addTokenUsage:(Lorg/apache/xml/security/stax/securityToken/SecurityTokenConstants$TokenUsage;)V
     160: aload_0
     161: aload         17
     163: aload_2
     164: invokespecial #59                 // Method addTokenSecurityEvent:(Lorg/apache/xml/security/stax/securityEvent/TokenSecurityEvent;Ljava/util/List;)Ljava/util/List;
     167: astore_2
     168: new           #52                 // class org/apache/wss4j/stax/securityEvent/HttpsTokenSecurityEvent
     171: dup
     172: invokespecial #60                 // Method org/apache/wss4j/stax/securityEvent/HttpsTokenSecurityEvent."<init>":()V
     175: astore        18
     177: aload         18
     179: aload         17
     181: invokevirtual #61                 // Method org/apache/wss4j/stax/securityEvent/HttpsTokenSecurityEvent.getAuthenticationType:()Lorg/apache/wss4j/stax/securityEvent/HttpsTokenSecurityEvent$AuthenticationType;
     184: invokevirtual #62                 // Method org/apache/wss4j/stax/securityEvent/HttpsTokenSecurityEvent.setAuthenticationType:(Lorg/apache/wss4j/stax/securityEvent/HttpsTokenSecurityEvent$AuthenticationType;)V
     187: aload         18
     189: aload         17
     191: invokevirtual #63                 // Method org/apache/wss4j/stax/securityEvent/HttpsTokenSecurityEvent.getIssuerName:()Ljava/lang/String;
     194: invokevirtual #64                 // Method org/apache/wss4j/stax/securityEvent/HttpsTokenSecurityEvent.setIssuerName:(Ljava/lang/String;)V
     197: aload         18
     199: aload         17
     201: invokevirtual #53                 // Method org/apache/wss4j/stax/securityEvent/HttpsTokenSecurityEvent.getSecurityToken:()Lorg/apache/xml/security/stax/securityToken/SecurityToken;
     204: invokevirtual #65                 // Method org/apache/wss4j/stax/securityEvent/HttpsTokenSecurityEvent.setSecurityToken:(Lorg/apache/xml/security/stax/securityToken/SecurityToken;)V
     207: aload         18
     209: invokevirtual #53                 // Method org/apache/wss4j/stax/securityEvent/HttpsTokenSecurityEvent.getSecurityToken:()Lorg/apache/xml/security/stax/securityToken/SecurityToken;
     212: checkcast     #54                 // class org/apache/wss4j/stax/securityToken/HttpsSecurityToken
     215: getstatic     #23                 // Field org/apache/wss4j/stax/securityToken/WSSecurityTokenConstants.TokenUsage_MainEncryption:Lorg/apache/xml/security/stax/securityToken/SecurityTokenConstants$TokenUsage;
     218: invokeinterface #58,  2           // InterfaceMethod org/apache/wss4j/stax/securityToken/HttpsSecurityToken.addTokenUsage:(Lorg/apache/xml/security/stax/securityToken/SecurityTokenConstants$TokenUsage;)V
     223: aload_0
     224: aload         17
     226: aload_3
     227: invokespecial #59                 // Method addTokenSecurityEvent:(Lorg/apache/xml/security/stax/securityEvent/TokenSecurityEvent;Ljava/util/List;)Ljava/util/List;
     230: astore_3
     231: aload         18
     233: astore        12
     235: goto          68
     238: aload         13
     240: aload         16
     242: invokeinterface #66,  2           // InterfaceMethod java/util/List.add:(Ljava/lang/Object;)Z
     247: pop
     248: goto          68
     251: iconst_0
     252: istore        15
     254: iload         15
     256: aload         13
     258: invokeinterface #67,  1           // InterfaceMethod java/util/List.size:()I
     263: if_icmpge     350
     266: aload         13
     268: iload         15
     270: invokeinterface #68,  2           // InterfaceMethod java/util/List.get:(I)Ljava/lang/Object;
     275: checkcast     #14                 // class org/apache/xml/security/stax/securityEvent/TokenSecurityEvent
     278: astore        16
     280: aload         16
     282: invokevirtual #15                 // Method org/apache/xml/security/stax/securityEvent/TokenSecurityEvent.getSecurityToken:()Lorg/apache/xml/security/stax/securityToken/SecurityToken;
     285: invokestatic  #20                 // Method org/apache/wss4j/stax/utils/WSSUtils.getRootToken:(Lorg/apache/xml/security/stax/securityToken/SecurityToken;)Lorg/apache/xml/security/stax/securityToken/SecurityToken;
     288: checkcast     #16                 // class org/apache/xml/security/stax/securityToken/InboundSecurityToken
     291: astore        17
     293: aload_0
     294: aload         4
     296: aload         17
     298: invokespecial #69                 // Method containsSecurityToken:(Ljava/util/List;Lorg/apache/xml/security/stax/securityToken/SecurityToken;)Z
     301: ifne          335
     304: aload         17
     306: aload         16
     308: invokevirtual #21                 // Method org/apache/xml/security/stax/securityEvent/TokenSecurityEvent.getCorrelationID:()Ljava/lang/String;
     311: invokestatic  #22                 // Method org/apache/wss4j/stax/utils/WSSUtils.createTokenSecurityEvent:(Lorg/apache/xml/security/stax/securityToken/InboundSecurityToken;Ljava/lang/String;)Lorg/apache/xml/security/stax/securityEvent/TokenSecurityEvent;
     314: astore        18
     316: aload_0
     317: aload         18
     319: aload         4
     321: invokespecial #59                 // Method addTokenSecurityEvent:(Lorg/apache/xml/security/stax/securityEvent/TokenSecurityEvent;Ljava/util/List;)Ljava/util/List;
     324: astore        4
     326: aload_1
     327: aload         18
     329: invokeinterface #70,  2           // InterfaceMethod java/util/Deque.offer:(Ljava/lang/Object;)Z
     334: pop
     335: aload_1
     336: aload         16
     338: invokeinterface #71,  2           // InterfaceMethod java/util/Deque.remove:(Ljava/lang/Object;)Z
     343: pop
     344: iinc          15, 1
     347: goto          254
     350: aload         4
     352: invokeinterface #72,  1           // InterfaceMethod java/util/List.iterator:()Ljava/util/Iterator;
     357: astore        15
     359: aload         15
     361: invokeinterface #28,  1           // InterfaceMethod java/util/Iterator.hasNext:()Z
     366: ifeq          1178
     369: aload         15
     371: invokeinterface #29,  1           // InterfaceMethod java/util/Iterator.next:()Ljava/lang/Object;
     376: checkcast     #14                 // class org/apache/xml/security/stax/securityEvent/TokenSecurityEvent
     379: astore        16
     381: aload_0
     382: aload         16
     384: aload_1
     385: aload         12
     387: invokespecial #73                 // Method isSignedToken:(Lorg/apache/xml/security/stax/securityEvent/TokenSecurityEvent;Ljava/util/Deque;Lorg/apache/wss4j/stax/securityEvent/HttpsTokenSecurityEvent;)Ljava/util/List;
     390: astore        17
     392: new           #48                 // class java/util/ArrayList
     395: dup
     396: iconst_4
     397: invokespecial #74                 // Method java/util/ArrayList."<init>":(I)V
     400: astore        18
     402: aload         18
     404: getstatic     #75                 // Field org/apache/wss4j/stax/ext/WSSConstants.WSSE_SECURITY_HEADER_PATH:Ljava/util/List;
     407: invokeinterface #76,  2           // InterfaceMethod java/util/List.addAll:(Ljava/util/Collection;)Z
     412: pop
     413: aload         18
     415: getstatic     #77                 // Field org/apache/wss4j/stax/ext/WSSConstants.TAG_dsig_Signature:Ljavax/xml/namespace/QName;
     418: invokeinterface #66,  2           // InterfaceMethod java/util/List.add:(Ljava/lang/Object;)Z
     423: pop
     424: aload_0
     425: aload         16
     427: aload         18
     429: aload_1
     430: invokespecial #78                 // Method signsElement:(Lorg/apache/xml/security/stax/securityEvent/TokenSecurityEvent;Ljava/util/List;Ljava/util/Deque;)Z
     433: istore        19
     435: aload_0
     436: aload         16
     438: aload         18
     440: aload_1
     441: invokespecial #79                 // Method encryptsElement:(Lorg/apache/xml/security/stax/securityEvent/TokenSecurityEvent;Ljava/util/List;Ljava/util/Deque;)Z
     444: istore        20
     446: new           #48                 // class java/util/ArrayList
     449: dup
     450: iconst_4
     451: invokespecial #74                 // Method java/util/ArrayList."<init>":(I)V
     454: astore        21
     456: aload         21
     458: getstatic     #75                 // Field org/apache/wss4j/stax/ext/WSSConstants.WSSE_SECURITY_HEADER_PATH:Ljava/util/List;
     461: invokeinterface #76,  2           // InterfaceMethod java/util/List.addAll:(Ljava/util/Collection;)Z
     466: pop
     467: aload         21
     469: getstatic     #80                 // Field org/apache/wss4j/stax/ext/WSSConstants.TAG_wsse11_SignatureConfirmation:Ljavax/xml/namespace/QName;
     472: invokeinterface #66,  2           // InterfaceMethod java/util/List.add:(Ljava/lang/Object;)Z
     477: pop
     478: aload_0
     479: aload         16
     481: aload         21
     483: aload_1
     484: invokespecial #78                 // Method signsElement:(Lorg/apache/xml/security/stax/securityEvent/TokenSecurityEvent;Ljava/util/List;Ljava/util/Deque;)Z
     487: istore        22
     489: aload_0
     490: aload         16
     492: aload         21
     494: aload_1
     495: invokespecial #79                 // Method encryptsElement:(Lorg/apache/xml/security/stax/securityEvent/TokenSecurityEvent;Ljava/util/List;Ljava/util/Deque;)Z
     498: istore        23
     500: new           #48                 // class java/util/ArrayList
     503: dup
     504: iconst_4
     505: invokespecial #74                 // Method java/util/ArrayList."<init>":(I)V
     508: astore        24
     510: aload         24
     512: getstatic     #75                 // Field org/apache/wss4j/stax/ext/WSSConstants.WSSE_SECURITY_HEADER_PATH:Ljava/util/List;
     515: invokeinterface #76,  2           // InterfaceMethod java/util/List.addAll:(Ljava/util/Collection;)Z
     520: pop
     521: aload         24
     523: getstatic     #81                 // Field org/apache/wss4j/stax/ext/WSSConstants.TAG_wsu_Timestamp:Ljavax/xml/namespace/QName;
     526: invokeinterface #66,  2           // InterfaceMethod java/util/List.add:(Ljava/lang/Object;)Z
     531: pop
     532: aload_0
     533: aload         16
     535: aload         24
     537: aload_1
     538: invokespecial #78                 // Method signsElement:(Lorg/apache/xml/security/stax/securityEvent/TokenSecurityEvent;Ljava/util/List;Ljava/util/Deque;)Z
     541: istore        25
     543: new           #48                 // class java/util/ArrayList
     546: dup
     547: iconst_4
     548: invokespecial #74                 // Method java/util/ArrayList."<init>":(I)V
     551: astore        26
     553: aload         26
     555: getstatic     #75                 // Field org/apache/wss4j/stax/ext/WSSConstants.WSSE_SECURITY_HEADER_PATH:Ljava/util/List;
     558: invokeinterface #76,  2           // InterfaceMethod java/util/List.addAll:(Ljava/util/Collection;)Z
     563: pop
     564: aload         26
     566: getstatic     #82                 // Field org/apache/wss4j/stax/ext/WSSConstants.TAG_wsse_UsernameToken:Ljavax/xml/namespace/QName;
     569: invokeinterface #66,  2           // InterfaceMethod java/util/List.add:(Ljava/lang/Object;)Z
     574: pop
     575: aload_0
     576: aload         16
     578: aload         26
     580: aload_1
     581: invokespecial #79                 // Method encryptsElement:(Lorg/apache/xml/security/stax/securityEvent/TokenSecurityEvent;Ljava/util/List;Ljava/util/Deque;)Z
     584: istore        27
     586: getstatic     #83                 // Field java/lang/Boolean.TRUE:Ljava/lang/Boolean;
     589: aload_0
     590: ldc           #84                 // String transportSecurityActive
     592: invokevirtual #36                 // Method get:(Ljava/lang/String;)Ljava/lang/Object;
     595: if_acmpne     602
     598: iconst_1
     599: goto          603
     602: iconst_0
     603: istore        28
     605: aload_0
     606: aload         16
     608: aload_1
     609: aload         12
     611: invokespecial #85                 // Method isEncryptedToken:(Lorg/apache/xml/security/stax/securityEvent/TokenSecurityEvent;Ljava/util/Deque;Lorg/apache/wss4j/stax/securityEvent/HttpsTokenSecurityEvent;)Ljava/util/List;
     614: astore        29
     616: aload         16
     618: invokevirtual #15                 // Method org/apache/xml/security/stax/securityEvent/TokenSecurityEvent.getSecurityToken:()Lorg/apache/xml/security/stax/securityToken/SecurityToken;
     621: checkcast     #16                 // class org/apache/xml/security/stax/securityToken/InboundSecurityToken
     624: invokeinterface #17,  1           // InterfaceMethod org/apache/xml/security/stax/securityToken/InboundSecurityToken.getTokenUsages:()Ljava/util/List;
     629: getstatic     #86                 // Field org/apache/wss4j/stax/securityToken/WSSecurityTokenConstants.TokenUsage_Signature:Lorg/apache/xml/security/stax/securityToken/SecurityTokenConstants$TokenUsage;
     632: invokeinterface #19,  2           // InterfaceMethod java/util/List.contains:(Ljava/lang/Object;)Z
     637: istore        30
     639: aload         16
     641: invokevirtual #15                 // Method org/apache/xml/security/stax/securityEvent/TokenSecurityEvent.getSecurityToken:()Lorg/apache/xml/security/stax/securityToken/SecurityToken;
     644: checkcast     #16                 // class org/apache/xml/security/stax/securityToken/InboundSecurityToken
     647: invokeinterface #17,  1           // InterfaceMethod org/apache/xml/security/stax/securityToken/InboundSecurityToken.getTokenUsages:()Ljava/util/List;
     652: getstatic     #18                 // Field org/apache/wss4j/stax/securityToken/WSSecurityTokenConstants.TokenUsage_Encryption:Lorg/apache/xml/security/stax/securityToken/SecurityTokenConstants$TokenUsage;
     655: invokeinterface #19,  2           // InterfaceMethod java/util/List.contains:(Ljava/lang/Object;)Z
     660: istore        31
     662: iload         28
     664: ifne          713
     667: iload         22
     669: ifeq          713
     672: iload         25
     674: ifeq          713
     677: iload         19
     679: ifne          713
     682: aload         15
     684: invokeinterface #87,  1           // InterfaceMethod java/util/Iterator.remove:()V
     689: aload_0
     690: aload         16
     692: aload_2
     693: invokespecial #59                 // Method addTokenSecurityEvent:(Lorg/apache/xml/security/stax/securityEvent/TokenSecurityEvent;Ljava/util/List;)Ljava/util/List;
     696: astore_2
     697: iload         31
     699: ifeq          1175
     702: aload_0
     703: aload         16
     705: aload_3
     706: invokespecial #59                 // Method addTokenSecurityEvent:(Lorg/apache/xml/security/stax/securityEvent/TokenSecurityEvent;Ljava/util/List;)Ljava/util/List;
     709: astore_3
     710: goto          1175
     713: iload         28
     715: ifne          759
     718: iload         22
     720: ifeq          759
     723: iload         19
     725: ifne          759
     728: aload         15
     730: invokeinterface #87,  1           // InterfaceMethod java/util/Iterator.remove:()V
     735: aload_0
     736: aload         16
     738: aload_2
     739: invokespecial #59                 // Method addTokenSecurityEvent:(Lorg/apache/xml/security/stax/securityEvent/TokenSecurityEvent;Ljava/util/List;)Ljava/util/List;
     742: astore_2
     743: iload         31
     745: ifeq          1175
     748: aload_0
     749: aload         16
     751: aload_3
     752: invokespecial #59                 // Method addTokenSecurityEvent:(Lorg/apache/xml/security/stax/securityEvent/TokenSecurityEvent;Ljava/util/List;)Ljava/util/List;
     755: astore_3
     756: goto          1175
     759: iload         28
     761: ifne          805
     764: iload         25
     766: ifeq          805
     769: iload         19
     771: ifne          805
     774: aload         15
     776: invokeinterface #87,  1           // InterfaceMethod java/util/Iterator.remove:()V
     781: aload_0
     782: aload         16
     784: aload_2
     785: invokespecial #59                 // Method addTokenSecurityEvent:(Lorg/apache/xml/security/stax/securityEvent/TokenSecurityEvent;Ljava/util/List;)Ljava/util/List;
     788: astore_2
     789: iload         31
     791: ifeq          1175
     794: aload_0
     795: aload         16
     797: aload_3
     798: invokespecial #59                 // Method addTokenSecurityEvent:(Lorg/apache/xml/security/stax/securityEvent/TokenSecurityEvent;Ljava/util/List;)Ljava/util/List;
     801: astore_3
     802: goto          1175
     805: iload         28
     807: ifne          843
     810: iload         20
     812: ifne          825
     815: iload         23
     817: ifne          825
     820: iload         27
     822: ifeq          843
     825: aload         15
     827: invokeinterface #87,  1           // InterfaceMethod java/util/Iterator.remove:()V
     832: aload_0
     833: aload         16
     835: aload_3
     836: invokespecial #59                 // Method addTokenSecurityEvent:(Lorg/apache/xml/security/stax/securityEvent/TokenSecurityEvent;Ljava/util/List;)Ljava/util/List;
     839: astore_3
     840: goto          1175
     843: iload         19
     845: ifeq          888
     848: aload         17
     850: invokeinterface #67,  1           // InterfaceMethod java/util/List.size:()I
     855: ifle          888
     858: aload         29
     860: invokeinterface #67,  1           // InterfaceMethod java/util/List.size:()I
     865: ifle          888
     868: aload         15
     870: invokeinterface #87,  1           // InterfaceMethod java/util/Iterator.remove:()V
     875: aload_0
     876: aload         16
     878: aload         11
     880: invokespecial #59                 // Method addTokenSecurityEvent:(Lorg/apache/xml/security/stax/securityEvent/TokenSecurityEvent;Ljava/util/List;)Ljava/util/List;
     883: astore        11
     885: goto          1175
     888: iload         28
     890: ifeq          938
     893: iload         25
     895: ifeq          938
     898: aload         17
     900: invokeinterface #67,  1           // InterfaceMethod java/util/List.size:()I
     905: ifle          938
     908: aload         29
     910: invokeinterface #67,  1           // InterfaceMethod java/util/List.size:()I
     915: ifle          938
     918: aload         15
     920: invokeinterface #87,  1           // InterfaceMethod java/util/Iterator.remove:()V
     925: aload_0
     926: aload         16
     928: aload         11
     930: invokespecial #59                 // Method addTokenSecurityEvent:(Lorg/apache/xml/security/stax/securityEvent/TokenSecurityEvent;Ljava/util/List;)Ljava/util/List;
     933: astore        11
     935: goto          1175
     938: iload         19
     940: ifeq          983
     943: aload         17
     945: invokeinterface #67,  1           // InterfaceMethod java/util/List.size:()I
     950: ifne          983
     953: aload         29
     955: invokeinterface #67,  1           // InterfaceMethod java/util/List.size:()I
     960: ifle          983
     963: aload         15
     965: invokeinterface #87,  1           // InterfaceMethod java/util/Iterator.remove:()V
     970: aload_0
     971: aload         16
     973: aload         10
     975: invokespecial #59                 // Method addTokenSecurityEvent:(Lorg/apache/xml/security/stax/securityEvent/TokenSecurityEvent;Ljava/util/List;)Ljava/util/List;
     978: astore        10
     980: goto          1175
     983: iload         19
     985: ifeq          1018
     988: aload         17
     990: invokeinterface #67,  1           // InterfaceMethod java/util/List.size:()I
     995: ifle          1018
     998: aload         15
    1000: invokeinterface #87,  1           // InterfaceMethod java/util/Iterator.remove:()V
    1005: aload_0
    1006: aload         16
    1008: aload         7
    1010: invokespecial #59                 // Method addTokenSecurityEvent:(Lorg/apache/xml/security/stax/securityEvent/TokenSecurityEvent;Ljava/util/List;)Ljava/util/List;
    1013: astore        7
    1015: goto          1175
    1018: iload         30
    1020: ifeq          1053
    1023: aload         17
    1025: invokeinterface #67,  1           // InterfaceMethod java/util/List.size:()I
    1030: ifle          1053
    1033: aload         15
    1035: invokeinterface #87,  1           // InterfaceMethod java/util/Iterator.remove:()V
    1040: aload_0
    1041: aload         16
    1043: aload         7
    1045: invokespecial #59                 // Method addTokenSecurityEvent:(Lorg/apache/xml/security/stax/securityEvent/TokenSecurityEvent;Ljava/util/List;)Ljava/util/List;
    1048: astore        7
    1050: goto          1175
    1053: iload         19
    1055: ifeq          1078
    1058: aload         15
    1060: invokeinterface #87,  1           // InterfaceMethod java/util/Iterator.remove:()V
    1065: aload_0
    1066: aload         16
    1068: aload         6
    1070: invokespecial #59                 // Method addTokenSecurityEvent:(Lorg/apache/xml/security/stax/securityEvent/TokenSecurityEvent;Ljava/util/List;)Ljava/util/List;
    1073: astore        6
    1075: goto          1175
    1078: aload         17
    1080: invokeinterface #67,  1           // InterfaceMethod java/util/List.size:()I
    1085: ifle          1118
    1088: aload         29
    1090: invokeinterface #67,  1           // InterfaceMethod java/util/List.size:()I
    1095: ifle          1118
    1098: aload         15
    1100: invokeinterface #87,  1           // InterfaceMethod java/util/Iterator.remove:()V
    1105: aload_0
    1106: aload         16
    1108: aload         8
    1110: invokespecial #59                 // Method addTokenSecurityEvent:(Lorg/apache/xml/security/stax/securityEvent/TokenSecurityEvent;Ljava/util/List;)Ljava/util/List;
    1113: astore        8
    1115: goto          1175
    1118: aload         17
    1120: invokeinterface #67,  1           // InterfaceMethod java/util/List.size:()I
    1125: ifle          1148
    1128: aload         15
    1130: invokeinterface #87,  1           // InterfaceMethod java/util/Iterator.remove:()V
    1135: aload_0
    1136: aload         16
    1138: aload         5
    1140: invokespecial #59                 // Method addTokenSecurityEvent:(Lorg/apache/xml/security/stax/securityEvent/TokenSecurityEvent;Ljava/util/List;)Ljava/util/List;
    1143: astore        5
    1145: goto          1175
    1148: aload         29
    1150: invokeinterface #67,  1           // InterfaceMethod java/util/List.size:()I
    1155: ifle          1175
    1158: aload         15
    1160: invokeinterface #87,  1           // InterfaceMethod java/util/Iterator.remove:()V
    1165: aload_0
    1166: aload         16
    1168: aload         9
    1170: invokespecial #59                 // Method addTokenSecurityEvent:(Lorg/apache/xml/security/stax/securityEvent/TokenSecurityEvent;Ljava/util/List;)Ljava/util/List;
    1173: astore        9
    1175: goto          359
    1178: aload_2
    1179: invokeinterface #88,  1           // InterfaceMethod java/util/List.isEmpty:()Z
    1184: ifeq          1289
    1187: aload_0
    1188: aload         5
    1190: aload         7
    1192: aload         8
    1194: aload         11
    1196: aload_1
    1197: invokespecial #89                 // Method getSupportingTokenSigningToken:(Ljava/util/List;Ljava/util/List;Ljava/util/List;Ljava/util/List;Ljava/util/Deque;)Lorg/apache/xml/security/stax/securityToken/InboundSecurityToken;
    1200: astore        16
    1202: aload_0
    1203: aload         16
    1205: aload         13
    1207: invokespecial #90                 // Method getTokenSecurityEvent:(Lorg/apache/xml/security/stax/securityToken/InboundSecurityToken;Ljava/util/List;)Lorg/apache/xml/security/stax/securityEvent/TokenSecurityEvent;
    1210: astore        17
    1212: aload         17
    1214: ifnull        1289
    1217: aload_0
    1218: aload         17
    1220: aload         4
    1222: invokespecial #91                 // Method removeTokenSecurityEvent:(Lorg/apache/xml/security/stax/securityEvent/TokenSecurityEvent;Ljava/util/List;)V
    1225: aload_0
    1226: aload         17
    1228: aload         5
    1230: invokespecial #91                 // Method removeTokenSecurityEvent:(Lorg/apache/xml/security/stax/securityEvent/TokenSecurityEvent;Ljava/util/List;)V
    1233: aload_0
    1234: aload         17
    1236: aload         6
    1238: invokespecial #91                 // Method removeTokenSecurityEvent:(Lorg/apache/xml/security/stax/securityEvent/TokenSecurityEvent;Ljava/util/List;)V
    1241: aload_0
    1242: aload         17
    1244: aload         7
    1246: invokespecial #91                 // Method removeTokenSecurityEvent:(Lorg/apache/xml/security/stax/securityEvent/TokenSecurityEvent;Ljava/util/List;)V
    1249: aload_0
    1250: aload         17
    1252: aload         8
    1254: invokespecial #91                 // Method removeTokenSecurityEvent:(Lorg/apache/xml/security/stax/securityEvent/TokenSecurityEvent;Ljava/util/List;)V
    1257: aload_0
    1258: aload         17
    1260: aload         9
    1262: invokespecial #91                 // Method removeTokenSecurityEvent:(Lorg/apache/xml/security/stax/securityEvent/TokenSecurityEvent;Ljava/util/List;)V
    1265: aload_0
    1266: aload         17
    1268: aload         10
    1270: invokespecial #91                 // Method removeTokenSecurityEvent:(Lorg/apache/xml/security/stax/securityEvent/TokenSecurityEvent;Ljava/util/List;)V
    1273: aload_0
    1274: aload         17
    1276: aload         11
    1278: invokespecial #91                 // Method removeTokenSecurityEvent:(Lorg/apache/xml/security/stax/securityEvent/TokenSecurityEvent;Ljava/util/List;)V
    1281: aload_0
    1282: aload         17
    1284: aload_2
    1285: invokespecial #59                 // Method addTokenSecurityEvent:(Lorg/apache/xml/security/stax/securityEvent/TokenSecurityEvent;Ljava/util/List;)Ljava/util/List;
    1288: astore_2
    1289: aload_2
    1290: invokeinterface #88,  1           // InterfaceMethod java/util/List.isEmpty:()Z
    1295: ifeq          1374
    1298: aload         4
    1300: invokeinterface #72,  1           // InterfaceMethod java/util/List.iterator:()Ljava/util/Iterator;
    1305: astore        16
    1307: aload         16
    1309: invokeinterface #28,  1           // InterfaceMethod java/util/Iterator.hasNext:()Z
    1314: ifeq          1374
    1317: aload         16
    1319: invokeinterface #29,  1           // InterfaceMethod java/util/Iterator.next:()Ljava/lang/Object;
    1324: checkcast     #14                 // class org/apache/xml/security/stax/securityEvent/TokenSecurityEvent
    1327: astore        17
    1329: aload         17
    1331: invokevirtual #15                 // Method org/apache/xml/security/stax/securityEvent/TokenSecurityEvent.getSecurityToken:()Lorg/apache/xml/security/stax/securityToken/SecurityToken;
    1334: checkcast     #16                 // class org/apache/xml/security/stax/securityToken/InboundSecurityToken
    1337: invokeinterface #17,  1           // InterfaceMethod org/apache/xml/security/stax/securityToken/InboundSecurityToken.getTokenUsages:()Ljava/util/List;
    1342: getstatic     #86                 // Field org/apache/wss4j/stax/securityToken/WSSecurityTokenConstants.TokenUsage_Signature:Lorg/apache/xml/security/stax/securityToken/SecurityTokenConstants$TokenUsage;
    1345: invokeinterface #19,  2           // InterfaceMethod java/util/List.contains:(Ljava/lang/Object;)Z
    1350: ifeq          1371
    1353: aload         16
    1355: invokeinterface #87,  1           // InterfaceMethod java/util/Iterator.remove:()V
    1360: aload_0
    1361: aload         17
    1363: aload_2
    1364: invokespecial #59                 // Method addTokenSecurityEvent:(Lorg/apache/xml/security/stax/securityEvent/TokenSecurityEvent;Ljava/util/List;)Ljava/util/List;
    1367: astore_2
    1368: goto          1374
    1371: goto          1307
    1374: aload_3
    1375: invokeinterface #88,  1           // InterfaceMethod java/util/List.isEmpty:()Z
    1380: ifeq          1459
    1383: aload         4
    1385: invokeinterface #72,  1           // InterfaceMethod java/util/List.iterator:()Ljava/util/Iterator;
    1390: astore        16
    1392: aload         16
    1394: invokeinterface #28,  1           // InterfaceMethod java/util/Iterator.hasNext:()Z
    1399: ifeq          1459
    1402: aload         16
    1404: invokeinterface #29,  1           // InterfaceMethod java/util/Iterator.next:()Ljava/lang/Object;
    1409: checkcast     #14                 // class org/apache/xml/security/stax/securityEvent/TokenSecurityEvent
    1412: astore        17
    1414: aload         17
    1416: invokevirtual #15                 // Method org/apache/xml/security/stax/securityEvent/TokenSecurityEvent.getSecurityToken:()Lorg/apache/xml/security/stax/securityToken/SecurityToken;
    1419: checkcast     #16                 // class org/apache/xml/security/stax/securityToken/InboundSecurityToken
    1422: invokeinterface #17,  1           // InterfaceMethod org/apache/xml/security/stax/securityToken/InboundSecurityToken.getTokenUsages:()Ljava/util/List;
    1427: getstatic     #18                 // Field org/apache/wss4j/stax/securityToken/WSSecurityTokenConstants.TokenUsage_Encryption:Lorg/apache/xml/security/stax/securityToken/SecurityTokenConstants$TokenUsage;
    1430: invokeinterface #19,  2           // InterfaceMethod java/util/List.contains:(Ljava/lang/Object;)Z
    1435: ifeq          1456
    1438: aload         16
    1440: invokeinterface #87,  1           // InterfaceMethod java/util/Iterator.remove:()V
    1445: aload_0
    1446: aload         17
    1448: aload_3
    1449: invokespecial #59                 // Method addTokenSecurityEvent:(Lorg/apache/xml/security/stax/securityEvent/TokenSecurityEvent;Ljava/util/List;)Ljava/util/List;
    1452: astore_3
    1453: goto          1459
    1456: goto          1392
    1459: aload_3
    1460: invokeinterface #88,  1           // InterfaceMethod java/util/List.isEmpty:()Z
    1465: ifne          1473
    1468: aload_0
    1469: iconst_1
    1470: putfield      #6                  // Field messageEncryptionTokenOccured:Z
    1473: aload_0
    1474: aload_2
    1475: getstatic     #57                 // Field org/apache/wss4j/stax/securityToken/WSSecurityTokenConstants.TokenUsage_MainSignature:Lorg/apache/xml/security/stax/securityToken/SecurityTokenConstants$TokenUsage;
    1478: invokespecial #92                 // Method setTokenUsage:(Ljava/util/List;Lorg/apache/xml/security/stax/securityToken/SecurityTokenConstants$TokenUsage;)V
    1481: aload_0
    1482: aload_3
    1483: getstatic     #23                 // Field org/apache/wss4j/stax/securityToken/WSSecurityTokenConstants.TokenUsage_MainEncryption:Lorg/apache/xml/security/stax/securityToken/SecurityTokenConstants$TokenUsage;
    1486: invokespecial #92                 // Method setTokenUsage:(Ljava/util/List;Lorg/apache/xml/security/stax/securityToken/SecurityTokenConstants$TokenUsage;)V
    1489: aload_0
    1490: aload         4
    1492: getstatic     #93                 // Field org/apache/wss4j/stax/securityToken/WSSecurityTokenConstants.TokenUsage_SupportingTokens:Lorg/apache/xml/security/stax/securityToken/SecurityTokenConstants$TokenUsage;
    1495: invokespecial #92                 // Method setTokenUsage:(Ljava/util/List;Lorg/apache/xml/security/stax/securityToken/SecurityTokenConstants$TokenUsage;)V
    1498: aload_0
    1499: aload         5
    1501: getstatic     #94                 // Field org/apache/wss4j/stax/securityToken/WSSecurityTokenConstants.TokenUsage_SignedSupportingTokens:Lorg/apache/xml/security/stax/securityToken/SecurityTokenConstants$TokenUsage;
    1504: invokespecial #92                 // Method setTokenUsage:(Ljava/util/List;Lorg/apache/xml/security/stax/securityToken/SecurityTokenConstants$TokenUsage;)V
    1507: aload_0
    1508: aload         6
    1510: getstatic     #95                 // Field org/apache/wss4j/stax/securityToken/WSSecurityTokenConstants.TokenUsage_EndorsingSupportingTokens:Lorg/apache/xml/security/stax/securityToken/SecurityTokenConstants$TokenUsage;
    1513: invokespecial #92                 // Method setTokenUsage:(Ljava/util/List;Lorg/apache/xml/security/stax/securityToken/SecurityTokenConstants$TokenUsage;)V
    1516: aload_0
    1517: aload         7
    1519: getstatic     #96                 // Field org/apache/wss4j/stax/securityToken/WSSecurityTokenConstants.TokenUsage_SignedEndorsingSupportingTokens:Lorg/apache/xml/security/stax/securityToken/SecurityTokenConstants$TokenUsage;
    1522: invokespecial #92                 // Method setTokenUsage:(Ljava/util/List;Lorg/apache/xml/security/stax/securityToken/SecurityTokenConstants$TokenUsage;)V
    1525: aload_0
    1526: aload         8
    1528: getstatic     #97                 // Field org/apache/wss4j/stax/securityToken/WSSecurityTokenConstants.TokenUsage_SignedEncryptedSupportingTokens:Lorg/apache/xml/security/stax/securityToken/SecurityTokenConstants$TokenUsage;
    1531: invokespecial #92                 // Method setTokenUsage:(Ljava/util/List;Lorg/apache/xml/security/stax/securityToken/SecurityTokenConstants$TokenUsage;)V
    1534: aload_0
    1535: aload         9
    1537: getstatic     #98                 // Field org/apache/wss4j/stax/securityToken/WSSecurityTokenConstants.TokenUsage_EncryptedSupportingTokens:Lorg/apache/xml/security/stax/securityToken/SecurityTokenConstants$TokenUsage;
    1540: invokespecial #92                 // Method setTokenUsage:(Ljava/util/List;Lorg/apache/xml/security/stax/securityToken/SecurityTokenConstants$TokenUsage;)V
    1543: aload_0
    1544: aload         10
    1546: getstatic     #99                 // Field org/apache/wss4j/stax/securityToken/WSSecurityTokenConstants.TokenUsage_EndorsingEncryptedSupportingTokens:Lorg/apache/xml/security/stax/securityToken/SecurityTokenConstants$TokenUsage;
    1549: invokespecial #92                 // Method setTokenUsage:(Ljava/util/List;Lorg/apache/xml/security/stax/securityToken/SecurityTokenConstants$TokenUsage;)V
    1552: aload_0
    1553: aload         11
    1555: getstatic     #100                // Field org/apache/wss4j/stax/securityToken/WSSecurityTokenConstants.TokenUsage_SignedEndorsingEncryptedSupportingTokens:Lorg/apache/xml/security/stax/securityToken/SecurityTokenConstants$TokenUsage;
    1558: invokespecial #92                 // Method setTokenUsage:(Ljava/util/List;Lorg/apache/xml/security/stax/securityToken/SecurityTokenConstants$TokenUsage;)V
    1561: return

  private void removeTokenSecurityEvent(org.apache.xml.security.stax.securityEvent.TokenSecurityEvent<? extends org.apache.xml.security.stax.securityToken.InboundSecurityToken>, java.util.List<org.apache.xml.security.stax.securityEvent.TokenSecurityEvent<? extends org.apache.xml.security.stax.securityToken.InboundSecurityToken>>);
    Code:
       0: iconst_0
       1: istore_3
       2: iload_3
       3: aload_2
       4: invokeinterface #67,  1           // InterfaceMethod java/util/List.size:()I
       9: if_icmpge     71
      12: aload_2
      13: iload_3
      14: invokeinterface #68,  2           // InterfaceMethod java/util/List.get:(I)Ljava/lang/Object;
      19: checkcast     #14                 // class org/apache/xml/security/stax/securityEvent/TokenSecurityEvent
      22: astore        4
      24: aload         4
      26: invokevirtual #15                 // Method org/apache/xml/security/stax/securityEvent/TokenSecurityEvent.getSecurityToken:()Lorg/apache/xml/security/stax/securityToken/SecurityToken;
      29: checkcast     #16                 // class org/apache/xml/security/stax/securityToken/InboundSecurityToken
      32: invokeinterface #101,  1          // InterfaceMethod org/apache/xml/security/stax/securityToken/InboundSecurityToken.getId:()Ljava/lang/String;
      37: aload_1
      38: invokevirtual #15                 // Method org/apache/xml/security/stax/securityEvent/TokenSecurityEvent.getSecurityToken:()Lorg/apache/xml/security/stax/securityToken/SecurityToken;
      41: checkcast     #16                 // class org/apache/xml/security/stax/securityToken/InboundSecurityToken
      44: invokeinterface #101,  1          // InterfaceMethod org/apache/xml/security/stax/securityToken/InboundSecurityToken.getId:()Ljava/lang/String;
      49: invokevirtual #41                 // Method java/lang/String.equals:(Ljava/lang/Object;)Z
      52: ifeq          65
      55: aload_2
      56: aload         4
      58: invokeinterface #102,  2          // InterfaceMethod java/util/List.remove:(Ljava/lang/Object;)Z
      63: pop
      64: return
      65: iinc          3, 1
      68: goto          2
      71: return

  private java.util.List<org.apache.xml.security.stax.securityEvent.TokenSecurityEvent<? extends org.apache.xml.security.stax.securityToken.InboundSecurityToken>> addTokenSecurityEvent(org.apache.xml.security.stax.securityEvent.TokenSecurityEvent<? extends org.apache.xml.security.stax.securityToken.InboundSecurityToken>, java.util.List<org.apache.xml.security.stax.securityEvent.TokenSecurityEvent<? extends org.apache.xml.security.stax.securityToken.InboundSecurityToken>>);
    Code:
       0: aload_2
       1: invokestatic  #8                  // Method java/util/Collections.emptyList:()Ljava/util/List;
       4: if_acmpne     15
       7: new           #48                 // class java/util/ArrayList
      10: dup
      11: invokespecial #49                 // Method java/util/ArrayList."<init>":()V
      14: astore_2
      15: aload_2
      16: aload_1
      17: invokeinterface #66,  2           // InterfaceMethod java/util/List.add:(Ljava/lang/Object;)Z
      22: pop
      23: aload_2
      24: areturn

  private boolean containsSecurityToken(java.util.List<org.apache.xml.security.stax.securityEvent.TokenSecurityEvent<? extends org.apache.xml.security.stax.securityToken.InboundSecurityToken>>, org.apache.xml.security.stax.securityToken.SecurityToken);
    Code:
       0: aload_2
       1: ifnull        58
       4: iconst_0
       5: istore_3
       6: iload_3
       7: aload_1
       8: invokeinterface #67,  1           // InterfaceMethod java/util/List.size:()I
      13: if_icmpge     58
      16: aload_1
      17: iload_3
      18: invokeinterface #68,  2           // InterfaceMethod java/util/List.get:(I)Ljava/lang/Object;
      23: checkcast     #14                 // class org/apache/xml/security/stax/securityEvent/TokenSecurityEvent
      26: astore        4
      28: aload         4
      30: invokevirtual #15                 // Method org/apache/xml/security/stax/securityEvent/TokenSecurityEvent.getSecurityToken:()Lorg/apache/xml/security/stax/securityToken/SecurityToken;
      33: invokeinterface #103,  1          // InterfaceMethod org/apache/xml/security/stax/securityToken/SecurityToken.getId:()Ljava/lang/String;
      38: aload_2
      39: invokeinterface #103,  1          // InterfaceMethod org/apache/xml/security/stax/securityToken/SecurityToken.getId:()Ljava/lang/String;
      44: invokevirtual #41                 // Method java/lang/String.equals:(Ljava/lang/Object;)Z
      47: ifeq          52
      50: iconst_1
      51: ireturn
      52: iinc          3, 1
      55: goto          6
      58: iconst_0
      59: ireturn

  private org.apache.xml.security.stax.securityEvent.TokenSecurityEvent<? extends org.apache.xml.security.stax.securityToken.InboundSecurityToken> getTokenSecurityEvent(org.apache.xml.security.stax.securityToken.InboundSecurityToken, java.util.List<org.apache.xml.security.stax.securityEvent.TokenSecurityEvent<? extends org.apache.xml.security.stax.securityToken.InboundSecurityToken>>) throws org.apache.xml.security.exceptions.XMLSecurityException;
    Code:
       0: aload_1
       1: ifnull        62
       4: iconst_0
       5: istore_3
       6: iload_3
       7: aload_2
       8: invokeinterface #67,  1           // InterfaceMethod java/util/List.size:()I
      13: if_icmpge     62
      16: aload_2
      17: iload_3
      18: invokeinterface #68,  2           // InterfaceMethod java/util/List.get:(I)Ljava/lang/Object;
      23: checkcast     #14                 // class org/apache/xml/security/stax/securityEvent/TokenSecurityEvent
      26: astore        4
      28: aload         4
      30: invokevirtual #15                 // Method org/apache/xml/security/stax/securityEvent/TokenSecurityEvent.getSecurityToken:()Lorg/apache/xml/security/stax/securityToken/SecurityToken;
      33: checkcast     #16                 // class org/apache/xml/security/stax/securityToken/InboundSecurityToken
      36: invokeinterface #101,  1          // InterfaceMethod org/apache/xml/security/stax/securityToken/InboundSecurityToken.getId:()Ljava/lang/String;
      41: aload_1
      42: invokeinterface #101,  1          // InterfaceMethod org/apache/xml/security/stax/securityToken/InboundSecurityToken.getId:()Ljava/lang/String;
      47: invokevirtual #41                 // Method java/lang/String.equals:(Ljava/lang/Object;)Z
      50: ifeq          56
      53: aload         4
      55: areturn
      56: iinc          3, 1
      59: goto          6
      62: aconst_null
      63: areturn

  private org.apache.xml.security.stax.securityToken.InboundSecurityToken getSupportingTokenSigningToken(java.util.List<org.apache.xml.security.stax.securityEvent.TokenSecurityEvent<? extends org.apache.xml.security.stax.securityToken.InboundSecurityToken>>, java.util.List<org.apache.xml.security.stax.securityEvent.TokenSecurityEvent<? extends org.apache.xml.security.stax.securityToken.InboundSecurityToken>>, java.util.List<org.apache.xml.security.stax.securityEvent.TokenSecurityEvent<? extends org.apache.xml.security.stax.securityToken.InboundSecurityToken>>, java.util.List<org.apache.xml.security.stax.securityEvent.TokenSecurityEvent<? extends org.apache.xml.security.stax.securityToken.InboundSecurityToken>>, java.util.Deque<org.apache.xml.security.stax.securityEvent.SecurityEvent>) throws org.apache.xml.security.exceptions.XMLSecurityException;
    Code:
       0: iconst_0
       1: istore        6
       3: iload         6
       5: aload_1
       6: invokeinterface #67,  1           // InterfaceMethod java/util/List.size:()I
      11: if_icmpge     66
      14: aload_1
      15: iload         6
      17: invokeinterface #68,  2           // InterfaceMethod java/util/List.get:(I)Ljava/lang/Object;
      22: checkcast     #14                 // class org/apache/xml/security/stax/securityEvent/TokenSecurityEvent
      25: astore        7
      27: aload_0
      28: aload         7
      30: aload         5
      32: invokespecial #104                // Method getSigningToken:(Lorg/apache/xml/security/stax/securityEvent/TokenSecurityEvent;Ljava/util/Deque;)Ljava/util/List;
      35: astore        8
      37: aload         8
      39: invokeinterface #67,  1           // InterfaceMethod java/util/List.size:()I
      44: iconst_1
      45: if_icmpne     60
      48: aload         8
      50: iconst_0
      51: invokeinterface #68,  2           // InterfaceMethod java/util/List.get:(I)Ljava/lang/Object;
      56: checkcast     #16                 // class org/apache/xml/security/stax/securityToken/InboundSecurityToken
      59: areturn
      60: iinc          6, 1
      63: goto          3
      66: iconst_0
      67: istore        6
      69: iload         6
      71: aload_2
      72: invokeinterface #67,  1           // InterfaceMethod java/util/List.size:()I
      77: if_icmpge     132
      80: aload_2
      81: iload         6
      83: invokeinterface #68,  2           // InterfaceMethod java/util/List.get:(I)Ljava/lang/Object;
      88: checkcast     #14                 // class org/apache/xml/security/stax/securityEvent/TokenSecurityEvent
      91: astore        7
      93: aload_0
      94: aload         7
      96: aload         5
      98: invokespecial #104                // Method getSigningToken:(Lorg/apache/xml/security/stax/securityEvent/TokenSecurityEvent;Ljava/util/Deque;)Ljava/util/List;
     101: astore        8
     103: aload         8
     105: invokeinterface #67,  1           // InterfaceMethod java/util/List.size:()I
     110: iconst_1
     111: if_icmpne     126
     114: aload         8
     116: iconst_0
     117: invokeinterface #68,  2           // InterfaceMethod java/util/List.get:(I)Ljava/lang/Object;
     122: checkcast     #16                 // class org/apache/xml/security/stax/securityToken/InboundSecurityToken
     125: areturn
     126: iinc          6, 1
     129: goto          69
     132: iconst_0
     133: istore        6
     135: iload         6
     137: aload_3
     138: invokeinterface #67,  1           // InterfaceMethod java/util/List.size:()I
     143: if_icmpge     198
     146: aload_3
     147: iload         6
     149: invokeinterface #68,  2           // InterfaceMethod java/util/List.get:(I)Ljava/lang/Object;
     154: checkcast     #14                 // class org/apache/xml/security/stax/securityEvent/TokenSecurityEvent
     157: astore        7
     159: aload_0
     160: aload         7
     162: aload         5
     164: invokespecial #104                // Method getSigningToken:(Lorg/apache/xml/security/stax/securityEvent/TokenSecurityEvent;Ljava/util/Deque;)Ljava/util/List;
     167: astore        8
     169: aload         8
     171: invokeinterface #67,  1           // InterfaceMethod java/util/List.size:()I
     176: iconst_1
     177: if_icmpne     192
     180: aload         8
     182: iconst_0
     183: invokeinterface #68,  2           // InterfaceMethod java/util/List.get:(I)Ljava/lang/Object;
     188: checkcast     #16                 // class org/apache/xml/security/stax/securityToken/InboundSecurityToken
     191: areturn
     192: iinc          6, 1
     195: goto          135
     198: iconst_0
     199: istore        6
     201: iload         6
     203: aload         4
     205: invokeinterface #67,  1           // InterfaceMethod java/util/List.size:()I
     210: if_icmpge     266
     213: aload         4
     215: iload         6
     217: invokeinterface #68,  2           // InterfaceMethod java/util/List.get:(I)Ljava/lang/Object;
     222: checkcast     #14                 // class org/apache/xml/security/stax/securityEvent/TokenSecurityEvent
     225: astore        7
     227: aload_0
     228: aload         7
     230: aload         5
     232: invokespecial #104                // Method getSigningToken:(Lorg/apache/xml/security/stax/securityEvent/TokenSecurityEvent;Ljava/util/Deque;)Ljava/util/List;
     235: astore        8
     237: aload         8
     239: invokeinterface #67,  1           // InterfaceMethod java/util/List.size:()I
     244: iconst_1
     245: if_icmpne     260
     248: aload         8
     250: iconst_0
     251: invokeinterface #68,  2           // InterfaceMethod java/util/List.get:(I)Ljava/lang/Object;
     256: checkcast     #16                 // class org/apache/xml/security/stax/securityToken/InboundSecurityToken
     259: areturn
     260: iinc          6, 1
     263: goto          201
     266: aconst_null
     267: areturn

  private java.util.List<org.apache.xml.security.stax.securityToken.InboundSecurityToken> getSigningToken(org.apache.xml.security.stax.securityEvent.TokenSecurityEvent<? extends org.apache.xml.security.stax.securityToken.SecurityToken>, java.util.Deque<org.apache.xml.security.stax.securityEvent.SecurityEvent>) throws org.apache.xml.security.exceptions.XMLSecurityException;
    Code:
       0: new           #48                 // class java/util/ArrayList
       3: dup
       4: invokespecial #49                 // Method java/util/ArrayList."<init>":()V
       7: astore_3
       8: aload_2
       9: invokeinterface #50,  1           // InterfaceMethod java/util/Deque.iterator:()Ljava/util/Iterator;
      14: astore        4
      16: aload         4
      18: invokeinterface #28,  1           // InterfaceMethod java/util/Iterator.hasNext:()Z
      23: ifeq          110
      26: aload         4
      28: invokeinterface #29,  1           // InterfaceMethod java/util/Iterator.next:()Ljava/lang/Object;
      33: checkcast     #30                 // class org/apache/xml/security/stax/securityEvent/SecurityEvent
      36: astore        5
      38: getstatic     #105                // Field org/apache/wss4j/stax/securityEvent/WSSecurityEventConstants.SignedElement:Lorg/apache/xml/security/stax/securityEvent/SecurityEventConstants$Event;
      41: aload         5
      43: invokevirtual #11                 // Method org/apache/xml/security/stax/securityEvent/SecurityEvent.getSecurityEventType:()Lorg/apache/xml/security/stax/securityEvent/SecurityEventConstants$Event;
      46: invokevirtual #12                 // Method org/apache/xml/security/stax/securityEvent/SecurityEventConstants$Event.equals:(Ljava/lang/Object;)Z
      49: ifeq          107
      52: aload         5
      54: checkcast     #106                // class org/apache/xml/security/stax/securityEvent/SignedElementSecurityEvent
      57: astore        6
      59: aload         6
      61: invokevirtual #107                // Method org/apache/xml/security/stax/securityEvent/SignedElementSecurityEvent.isSigned:()Z
      64: ifeq          107
      67: aload         6
      69: invokevirtual #108                // Method org/apache/xml/security/stax/securityEvent/SignedElementSecurityEvent.getElementPath:()Ljava/util/List;
      72: aload_1
      73: invokevirtual #15                 // Method org/apache/xml/security/stax/securityEvent/TokenSecurityEvent.getSecurityToken:()Lorg/apache/xml/security/stax/securityToken/SecurityToken;
      76: checkcast     #16                 // class org/apache/xml/security/stax/securityToken/InboundSecurityToken
      79: invokeinterface #109,  1          // InterfaceMethod org/apache/xml/security/stax/securityToken/InboundSecurityToken.getElementPath:()Ljava/util/List;
      84: iconst_1
      85: iconst_0
      86: invokestatic  #110                // Method org/apache/wss4j/stax/utils/WSSUtils.pathMatches:(Ljava/util/List;Ljava/util/List;ZZ)Z
      89: ifeq          107
      92: aload_3
      93: aload         6
      95: invokevirtual #111                // Method org/apache/xml/security/stax/securityEvent/SignedElementSecurityEvent.getSecurityToken:()Lorg/apache/xml/security/stax/securityToken/SecurityToken;
      98: checkcast     #16                 // class org/apache/xml/security/stax/securityToken/InboundSecurityToken
     101: invokeinterface #66,  2           // InterfaceMethod java/util/List.add:(Ljava/lang/Object;)Z
     106: pop
     107: goto          16
     110: aload_3
     111: areturn

  private void setTokenUsage(java.util.List<org.apache.xml.security.stax.securityEvent.TokenSecurityEvent<? extends org.apache.xml.security.stax.securityToken.InboundSecurityToken>>, org.apache.xml.security.stax.securityToken.SecurityTokenConstants$TokenUsage) throws org.apache.xml.security.exceptions.XMLSecurityException;
    Code:
       0: iconst_0
       1: istore_3
       2: iload_3
       3: aload_1
       4: invokeinterface #67,  1           // InterfaceMethod java/util/List.size:()I
       9: if_icmpge     37
      12: aload_1
      13: iload_3
      14: invokeinterface #68,  2           // InterfaceMethod java/util/List.get:(I)Ljava/lang/Object;
      19: checkcast     #14                 // class org/apache/xml/security/stax/securityEvent/TokenSecurityEvent
      22: astore        4
      24: aload_0
      25: aload         4
      27: aload_2
      28: invokespecial #24                 // Method setTokenUsage:(Lorg/apache/xml/security/stax/securityEvent/TokenSecurityEvent;Lorg/apache/xml/security/stax/securityToken/SecurityTokenConstants$TokenUsage;)V
      31: iinc          3, 1
      34: goto          2
      37: return

  private void setTokenUsage(org.apache.xml.security.stax.securityEvent.TokenSecurityEvent<? extends org.apache.xml.security.stax.securityToken.InboundSecurityToken>, org.apache.xml.security.stax.securityToken.SecurityTokenConstants$TokenUsage) throws org.apache.xml.security.exceptions.XMLSecurityException;
    Code:
       0: aload_1
       1: invokevirtual #15                 // Method org/apache/xml/security/stax/securityEvent/TokenSecurityEvent.getSecurityToken:()Lorg/apache/xml/security/stax/securityToken/SecurityToken;
       4: checkcast     #16                 // class org/apache/xml/security/stax/securityToken/InboundSecurityToken
       7: invokeinterface #17,  1           // InterfaceMethod org/apache/xml/security/stax/securityToken/InboundSecurityToken.getTokenUsages:()Ljava/util/List;
      12: getstatic     #93                 // Field org/apache/wss4j/stax/securityToken/WSSecurityTokenConstants.TokenUsage_SupportingTokens:Lorg/apache/xml/security/stax/securityToken/SecurityTokenConstants$TokenUsage;
      15: invokeinterface #102,  2          // InterfaceMethod java/util/List.remove:(Ljava/lang/Object;)Z
      20: pop
      21: aload_1
      22: invokevirtual #15                 // Method org/apache/xml/security/stax/securityEvent/TokenSecurityEvent.getSecurityToken:()Lorg/apache/xml/security/stax/securityToken/SecurityToken;
      25: checkcast     #16                 // class org/apache/xml/security/stax/securityToken/InboundSecurityToken
      28: invokeinterface #17,  1           // InterfaceMethod org/apache/xml/security/stax/securityToken/InboundSecurityToken.getTokenUsages:()Ljava/util/List;
      33: getstatic     #86                 // Field org/apache/wss4j/stax/securityToken/WSSecurityTokenConstants.TokenUsage_Signature:Lorg/apache/xml/security/stax/securityToken/SecurityTokenConstants$TokenUsage;
      36: invokeinterface #102,  2          // InterfaceMethod java/util/List.remove:(Ljava/lang/Object;)Z
      41: pop
      42: aload_1
      43: invokevirtual #15                 // Method org/apache/xml/security/stax/securityEvent/TokenSecurityEvent.getSecurityToken:()Lorg/apache/xml/security/stax/securityToken/SecurityToken;
      46: checkcast     #16                 // class org/apache/xml/security/stax/securityToken/InboundSecurityToken
      49: invokeinterface #17,  1           // InterfaceMethod org/apache/xml/security/stax/securityToken/InboundSecurityToken.getTokenUsages:()Ljava/util/List;
      54: getstatic     #18                 // Field org/apache/wss4j/stax/securityToken/WSSecurityTokenConstants.TokenUsage_Encryption:Lorg/apache/xml/security/stax/securityToken/SecurityTokenConstants$TokenUsage;
      57: invokeinterface #102,  2          // InterfaceMethod java/util/List.remove:(Ljava/lang/Object;)Z
      62: pop
      63: aload_1
      64: invokevirtual #15                 // Method org/apache/xml/security/stax/securityEvent/TokenSecurityEvent.getSecurityToken:()Lorg/apache/xml/security/stax/securityToken/SecurityToken;
      67: checkcast     #16                 // class org/apache/xml/security/stax/securityToken/InboundSecurityToken
      70: aload_2
      71: invokeinterface #112,  2          // InterfaceMethod org/apache/xml/security/stax/securityToken/InboundSecurityToken.addTokenUsage:(Lorg/apache/xml/security/stax/securityToken/SecurityTokenConstants$TokenUsage;)V
      76: return

  private java.util.List<org.apache.xml.security.stax.securityToken.InboundSecurityToken> isSignedToken(org.apache.xml.security.stax.securityEvent.TokenSecurityEvent<? extends org.apache.xml.security.stax.securityToken.SecurityToken>, java.util.Deque<org.apache.xml.security.stax.securityEvent.SecurityEvent>, org.apache.wss4j.stax.securityEvent.HttpsTokenSecurityEvent) throws org.apache.xml.security.exceptions.XMLSecurityException;
    Code:
       0: new           #48                 // class java/util/ArrayList
       3: dup
       4: invokespecial #49                 // Method java/util/ArrayList."<init>":()V
       7: astore        4
       9: aload_3
      10: ifnull        28
      13: aload         4
      15: aload_3
      16: invokevirtual #53                 // Method org/apache/wss4j/stax/securityEvent/HttpsTokenSecurityEvent.getSecurityToken:()Lorg/apache/xml/security/stax/securityToken/SecurityToken;
      19: invokeinterface #66,  2           // InterfaceMethod java/util/List.add:(Ljava/lang/Object;)Z
      24: pop
      25: aload         4
      27: areturn
      28: aload_2
      29: invokeinterface #50,  1           // InterfaceMethod java/util/Deque.iterator:()Ljava/util/Iterator;
      34: astore        5
      36: aload         5
      38: invokeinterface #28,  1           // InterfaceMethod java/util/Iterator.hasNext:()Z
      43: ifeq          159
      46: aload         5
      48: invokeinterface #29,  1           // InterfaceMethod java/util/Iterator.next:()Ljava/lang/Object;
      53: checkcast     #30                 // class org/apache/xml/security/stax/securityEvent/SecurityEvent
      56: astore        6
      58: getstatic     #105                // Field org/apache/wss4j/stax/securityEvent/WSSecurityEventConstants.SignedElement:Lorg/apache/xml/security/stax/securityEvent/SecurityEventConstants$Event;
      61: aload         6
      63: invokevirtual #11                 // Method org/apache/xml/security/stax/securityEvent/SecurityEvent.getSecurityEventType:()Lorg/apache/xml/security/stax/securityEvent/SecurityEventConstants$Event;
      66: invokevirtual #12                 // Method org/apache/xml/security/stax/securityEvent/SecurityEventConstants$Event.equals:(Ljava/lang/Object;)Z
      69: ifeq          156
      72: aload         6
      74: checkcast     #106                // class org/apache/xml/security/stax/securityEvent/SignedElementSecurityEvent
      77: astore        7
      79: aload         7
      81: invokevirtual #107                // Method org/apache/xml/security/stax/securityEvent/SignedElementSecurityEvent.isSigned:()Z
      84: ifeq          156
      87: aload_1
      88: invokevirtual #15                 // Method org/apache/xml/security/stax/securityEvent/TokenSecurityEvent.getSecurityToken:()Lorg/apache/xml/security/stax/securityToken/SecurityToken;
      91: ifnull        156
      94: aload         7
      96: invokevirtual #113                // Method org/apache/xml/security/stax/securityEvent/SignedElementSecurityEvent.getXmlSecEvent:()Lorg/apache/xml/security/stax/ext/stax/XMLSecEvent;
      99: ifnull        156
     102: aload         7
     104: invokevirtual #113                // Method org/apache/xml/security/stax/securityEvent/SignedElementSecurityEvent.getXmlSecEvent:()Lorg/apache/xml/security/stax/ext/stax/XMLSecEvent;
     107: aload_1
     108: invokevirtual #15                 // Method org/apache/xml/security/stax/securityEvent/TokenSecurityEvent.getSecurityToken:()Lorg/apache/xml/security/stax/securityToken/SecurityToken;
     111: checkcast     #16                 // class org/apache/xml/security/stax/securityToken/InboundSecurityToken
     114: invokeinterface #114,  1          // InterfaceMethod org/apache/xml/security/stax/securityToken/InboundSecurityToken.getXMLSecEvent:()Lorg/apache/xml/security/stax/ext/stax/XMLSecEvent;
     119: if_acmpne     156
     122: aload         4
     124: aload         7
     126: invokevirtual #111                // Method org/apache/xml/security/stax/securityEvent/SignedElementSecurityEvent.getSecurityToken:()Lorg/apache/xml/security/stax/securityToken/SecurityToken;
     129: checkcast     #16                 // class org/apache/xml/security/stax/securityToken/InboundSecurityToken
     132: invokeinterface #19,  2           // InterfaceMethod java/util/List.contains:(Ljava/lang/Object;)Z
     137: ifne          156
     140: aload         4
     142: aload         7
     144: invokevirtual #111                // Method org/apache/xml/security/stax/securityEvent/SignedElementSecurityEvent.getSecurityToken:()Lorg/apache/xml/security/stax/securityToken/SecurityToken;
     147: checkcast     #16                 // class org/apache/xml/security/stax/securityToken/InboundSecurityToken
     150: invokeinterface #66,  2           // InterfaceMethod java/util/List.add:(Ljava/lang/Object;)Z
     155: pop
     156: goto          36
     159: aload         4
     161: areturn

  private java.util.List<org.apache.xml.security.stax.securityToken.InboundSecurityToken> isEncryptedToken(org.apache.xml.security.stax.securityEvent.TokenSecurityEvent<? extends org.apache.xml.security.stax.securityToken.SecurityToken>, java.util.Deque<org.apache.xml.security.stax.securityEvent.SecurityEvent>, org.apache.wss4j.stax.securityEvent.HttpsTokenSecurityEvent) throws org.apache.xml.security.exceptions.XMLSecurityException;
    Code:
       0: new           #48                 // class java/util/ArrayList
       3: dup
       4: invokespecial #49                 // Method java/util/ArrayList."<init>":()V
       7: astore        4
       9: aload_3
      10: ifnull        28
      13: aload         4
      15: aload_3
      16: invokevirtual #53                 // Method org/apache/wss4j/stax/securityEvent/HttpsTokenSecurityEvent.getSecurityToken:()Lorg/apache/xml/security/stax/securityToken/SecurityToken;
      19: invokeinterface #66,  2           // InterfaceMethod java/util/List.add:(Ljava/lang/Object;)Z
      24: pop
      25: aload         4
      27: areturn
      28: aload_2
      29: invokeinterface #50,  1           // InterfaceMethod java/util/Deque.iterator:()Ljava/util/Iterator;
      34: astore        5
      36: aload         5
      38: invokeinterface #28,  1           // InterfaceMethod java/util/Iterator.hasNext:()Z
      43: ifeq          159
      46: aload         5
      48: invokeinterface #29,  1           // InterfaceMethod java/util/Iterator.next:()Ljava/lang/Object;
      53: checkcast     #30                 // class org/apache/xml/security/stax/securityEvent/SecurityEvent
      56: astore        6
      58: getstatic     #115                // Field org/apache/wss4j/stax/securityEvent/WSSecurityEventConstants.EncryptedElement:Lorg/apache/xml/security/stax/securityEvent/SecurityEventConstants$Event;
      61: aload         6
      63: invokevirtual #11                 // Method org/apache/xml/security/stax/securityEvent/SecurityEvent.getSecurityEventType:()Lorg/apache/xml/security/stax/securityEvent/SecurityEventConstants$Event;
      66: invokevirtual #12                 // Method org/apache/xml/security/stax/securityEvent/SecurityEventConstants$Event.equals:(Ljava/lang/Object;)Z
      69: ifeq          156
      72: aload         6
      74: checkcast     #116                // class org/apache/xml/security/stax/securityEvent/EncryptedElementSecurityEvent
      77: astore        7
      79: aload         7
      81: invokevirtual #117                // Method org/apache/xml/security/stax/securityEvent/EncryptedElementSecurityEvent.isEncrypted:()Z
      84: ifeq          156
      87: aload_1
      88: invokevirtual #15                 // Method org/apache/xml/security/stax/securityEvent/TokenSecurityEvent.getSecurityToken:()Lorg/apache/xml/security/stax/securityToken/SecurityToken;
      91: ifnull        156
      94: aload         7
      96: invokevirtual #118                // Method org/apache/xml/security/stax/securityEvent/EncryptedElementSecurityEvent.getXmlSecEvent:()Lorg/apache/xml/security/stax/ext/stax/XMLSecEvent;
      99: ifnull        156
     102: aload         7
     104: invokevirtual #118                // Method org/apache/xml/security/stax/securityEvent/EncryptedElementSecurityEvent.getXmlSecEvent:()Lorg/apache/xml/security/stax/ext/stax/XMLSecEvent;
     107: aload_1
     108: invokevirtual #15                 // Method org/apache/xml/security/stax/securityEvent/TokenSecurityEvent.getSecurityToken:()Lorg/apache/xml/security/stax/securityToken/SecurityToken;
     111: checkcast     #16                 // class org/apache/xml/security/stax/securityToken/InboundSecurityToken
     114: invokeinterface #114,  1          // InterfaceMethod org/apache/xml/security/stax/securityToken/InboundSecurityToken.getXMLSecEvent:()Lorg/apache/xml/security/stax/ext/stax/XMLSecEvent;
     119: if_acmpne     156
     122: aload         4
     124: aload         7
     126: invokevirtual #119                // Method org/apache/xml/security/stax/securityEvent/EncryptedElementSecurityEvent.getSecurityToken:()Lorg/apache/xml/security/stax/securityToken/SecurityToken;
     129: checkcast     #16                 // class org/apache/xml/security/stax/securityToken/InboundSecurityToken
     132: invokeinterface #19,  2           // InterfaceMethod java/util/List.contains:(Ljava/lang/Object;)Z
     137: ifne          156
     140: aload         4
     142: aload         7
     144: invokevirtual #119                // Method org/apache/xml/security/stax/securityEvent/EncryptedElementSecurityEvent.getSecurityToken:()Lorg/apache/xml/security/stax/securityToken/SecurityToken;
     147: checkcast     #16                 // class org/apache/xml/security/stax/securityToken/InboundSecurityToken
     150: invokeinterface #66,  2           // InterfaceMethod java/util/List.add:(Ljava/lang/Object;)Z
     155: pop
     156: goto          36
     159: aload         4
     161: areturn

  private boolean signsElement(org.apache.xml.security.stax.securityEvent.TokenSecurityEvent<? extends org.apache.xml.security.stax.securityToken.SecurityToken>, java.util.List<javax.xml.namespace.QName>, java.util.Deque<org.apache.xml.security.stax.securityEvent.SecurityEvent>) throws org.apache.xml.security.exceptions.XMLSecurityException;
    Code:
       0: aload_3
       1: invokeinterface #50,  1           // InterfaceMethod java/util/Deque.iterator:()Ljava/util/Iterator;
       6: astore        4
       8: aload         4
      10: invokeinterface #28,  1           // InterfaceMethod java/util/Iterator.hasNext:()Z
      15: ifeq          102
      18: aload         4
      20: invokeinterface #29,  1           // InterfaceMethod java/util/Iterator.next:()Ljava/lang/Object;
      25: checkcast     #30                 // class org/apache/xml/security/stax/securityEvent/SecurityEvent
      28: astore        5
      30: getstatic     #105                // Field org/apache/wss4j/stax/securityEvent/WSSecurityEventConstants.SignedElement:Lorg/apache/xml/security/stax/securityEvent/SecurityEventConstants$Event;
      33: aload         5
      35: invokevirtual #11                 // Method org/apache/xml/security/stax/securityEvent/SecurityEvent.getSecurityEventType:()Lorg/apache/xml/security/stax/securityEvent/SecurityEventConstants$Event;
      38: invokevirtual #12                 // Method org/apache/xml/security/stax/securityEvent/SecurityEventConstants$Event.equals:(Ljava/lang/Object;)Z
      41: ifeq          99
      44: aload         5
      46: checkcast     #106                // class org/apache/xml/security/stax/securityEvent/SignedElementSecurityEvent
      49: astore        6
      51: aload         6
      53: invokevirtual #107                // Method org/apache/xml/security/stax/securityEvent/SignedElementSecurityEvent.isSigned:()Z
      56: ifeq          99
      59: aload_0
      60: aload_1
      61: invokevirtual #15                 // Method org/apache/xml/security/stax/securityEvent/TokenSecurityEvent.getSecurityToken:()Lorg/apache/xml/security/stax/securityToken/SecurityToken;
      64: aload         6
      66: invokevirtual #111                // Method org/apache/xml/security/stax/securityEvent/SignedElementSecurityEvent.getSecurityToken:()Lorg/apache/xml/security/stax/securityToken/SecurityToken;
      69: invokeinterface #103,  1          // InterfaceMethod org/apache/xml/security/stax/securityToken/SecurityToken.getId:()Ljava/lang/String;
      74: getstatic     #120                // Field org/apache/xml/security/stax/securityToken/SecurityTokenConstants.TokenUsage_Signature:Lorg/apache/xml/security/stax/securityToken/SecurityTokenConstants$TokenUsage;
      77: invokespecial #121                // Method matchesTokenOrWrappedTokenId:(Lorg/apache/xml/security/stax/securityToken/SecurityToken;Ljava/lang/String;Lorg/apache/xml/security/stax/securityToken/SecurityTokenConstants$TokenUsage;)Z
      80: ifeq          99
      83: aload_2
      84: aload         6
      86: invokevirtual #108                // Method org/apache/xml/security/stax/securityEvent/SignedElementSecurityEvent.getElementPath:()Ljava/util/List;
      89: iconst_1
      90: iconst_0
      91: invokestatic  #110                // Method org/apache/wss4j/stax/utils/WSSUtils.pathMatches:(Ljava/util/List;Ljava/util/List;ZZ)Z
      94: ifeq          99
      97: iconst_1
      98: ireturn
      99: goto          8
     102: iconst_0
     103: ireturn

  private boolean matchesTokenOrWrappedTokenId(org.apache.xml.security.stax.securityToken.SecurityToken, java.lang.String, org.apache.xml.security.stax.securityToken.SecurityTokenConstants$TokenUsage) throws org.apache.xml.security.exceptions.XMLSecurityException;
    Code:
       0: aload_1
       1: invokeinterface #103,  1          // InterfaceMethod org/apache/xml/security/stax/securityToken/SecurityToken.getId:()Ljava/lang/String;
       6: aload_2
       7: invokevirtual #41                 // Method java/lang/String.equals:(Ljava/lang/Object;)Z
      10: ifeq          30
      13: aload_1
      14: invokeinterface #122,  1          // InterfaceMethod org/apache/xml/security/stax/securityToken/SecurityToken.getTokenUsages:()Ljava/util/List;
      19: aload_3
      20: invokeinterface #19,  2           // InterfaceMethod java/util/List.contains:(Ljava/lang/Object;)Z
      25: ifeq          30
      28: iconst_1
      29: ireturn
      30: aload_1
      31: invokeinterface #123,  1          // InterfaceMethod org/apache/xml/security/stax/securityToken/SecurityToken.getWrappedTokens:()Ljava/util/List;
      36: astore        4
      38: iconst_0
      39: istore        5
      41: iload         5
      43: aload         4
      45: invokeinterface #67,  1           // InterfaceMethod java/util/List.size:()I
      50: if_icmpge     87
      53: aload_0
      54: aload         4
      56: iload         5
      58: invokeinterface #68,  2           // InterfaceMethod java/util/List.get:(I)Ljava/lang/Object;
      63: checkcast     #124                // class org/apache/xml/security/stax/securityToken/SecurityToken
      66: aload_2
      67: aload_3
      68: invokespecial #121                // Method matchesTokenOrWrappedTokenId:(Lorg/apache/xml/security/stax/securityToken/SecurityToken;Ljava/lang/String;Lorg/apache/xml/security/stax/securityToken/SecurityTokenConstants$TokenUsage;)Z
      71: istore        6
      73: iload         6
      75: ifeq          81
      78: iload         6
      80: ireturn
      81: iinc          5, 1
      84: goto          41
      87: iconst_0
      88: ireturn

  private boolean encryptsElement(org.apache.xml.security.stax.securityEvent.TokenSecurityEvent<? extends org.apache.xml.security.stax.securityToken.SecurityToken>, java.util.List<javax.xml.namespace.QName>, java.util.Deque<org.apache.xml.security.stax.securityEvent.SecurityEvent>) throws org.apache.xml.security.exceptions.XMLSecurityException;
    Code:
       0: aload_3
       1: invokeinterface #50,  1           // InterfaceMethod java/util/Deque.iterator:()Ljava/util/Iterator;
       6: astore        4
       8: aload         4
      10: invokeinterface #28,  1           // InterfaceMethod java/util/Iterator.hasNext:()Z
      15: ifeq          196
      18: aload         4
      20: invokeinterface #29,  1           // InterfaceMethod java/util/Iterator.next:()Ljava/lang/Object;
      25: checkcast     #30                 // class org/apache/xml/security/stax/securityEvent/SecurityEvent
      28: astore        5
      30: getstatic     #115                // Field org/apache/wss4j/stax/securityEvent/WSSecurityEventConstants.EncryptedElement:Lorg/apache/xml/security/stax/securityEvent/SecurityEventConstants$Event;
      33: aload         5
      35: invokevirtual #11                 // Method org/apache/xml/security/stax/securityEvent/SecurityEvent.getSecurityEventType:()Lorg/apache/xml/security/stax/securityEvent/SecurityEventConstants$Event;
      38: invokevirtual #12                 // Method org/apache/xml/security/stax/securityEvent/SecurityEventConstants$Event.equals:(Ljava/lang/Object;)Z
      41: ifeq          103
      44: aload         5
      46: checkcast     #116                // class org/apache/xml/security/stax/securityEvent/EncryptedElementSecurityEvent
      49: astore        6
      51: aload         6
      53: invokevirtual #117                // Method org/apache/xml/security/stax/securityEvent/EncryptedElementSecurityEvent.isEncrypted:()Z
      56: ifeq          100
      59: aload         6
      61: invokevirtual #119                // Method org/apache/xml/security/stax/securityEvent/EncryptedElementSecurityEvent.getSecurityToken:()Lorg/apache/xml/security/stax/securityToken/SecurityToken;
      64: invokeinterface #103,  1          // InterfaceMethod org/apache/xml/security/stax/securityToken/SecurityToken.getId:()Ljava/lang/String;
      69: aload_1
      70: invokevirtual #15                 // Method org/apache/xml/security/stax/securityEvent/TokenSecurityEvent.getSecurityToken:()Lorg/apache/xml/security/stax/securityToken/SecurityToken;
      73: invokeinterface #103,  1          // InterfaceMethod org/apache/xml/security/stax/securityToken/SecurityToken.getId:()Ljava/lang/String;
      78: invokevirtual #41                 // Method java/lang/String.equals:(Ljava/lang/Object;)Z
      81: ifeq          100
      84: aload_2
      85: aload         6
      87: invokevirtual #125                // Method org/apache/xml/security/stax/securityEvent/EncryptedElementSecurityEvent.getElementPath:()Ljava/util/List;
      90: iconst_1
      91: iconst_0
      92: invokestatic  #110                // Method org/apache/wss4j/stax/utils/WSSUtils.pathMatches:(Ljava/util/List;Ljava/util/List;ZZ)Z
      95: ifeq          100
      98: iconst_1
      99: ireturn
     100: goto          193
     103: getstatic     #126                // Field org/apache/wss4j/stax/securityEvent/WSSecurityEventConstants.ContentEncrypted:Lorg/apache/xml/security/stax/securityEvent/SecurityEventConstants$Event;
     106: aload         5
     108: invokevirtual #11                 // Method org/apache/xml/security/stax/securityEvent/SecurityEvent.getSecurityEventType:()Lorg/apache/xml/security/stax/securityEvent/SecurityEventConstants$Event;
     111: invokevirtual #12                 // Method org/apache/xml/security/stax/securityEvent/SecurityEventConstants$Event.equals:(Ljava/lang/Object;)Z
     114: ifeq          193
     117: aload         5
     119: checkcast     #127                // class org/apache/xml/security/stax/securityEvent/ContentEncryptedElementSecurityEvent
     122: astore        6
     124: aload         6
     126: invokevirtual #128                // Method org/apache/xml/security/stax/securityEvent/ContentEncryptedElementSecurityEvent.isEncrypted:()Z
     129: ifeq          193
     132: aload         6
     134: invokevirtual #129                // Method org/apache/xml/security/stax/securityEvent/ContentEncryptedElementSecurityEvent.getSecurityToken:()Lorg/apache/xml/security/stax/securityToken/SecurityToken;
     137: invokeinterface #103,  1          // InterfaceMethod org/apache/xml/security/stax/securityToken/SecurityToken.getId:()Ljava/lang/String;
     142: aload_1
     143: invokevirtual #15                 // Method org/apache/xml/security/stax/securityEvent/TokenSecurityEvent.getSecurityToken:()Lorg/apache/xml/security/stax/securityToken/SecurityToken;
     146: invokeinterface #103,  1          // InterfaceMethod org/apache/xml/security/stax/securityToken/SecurityToken.getId:()Ljava/lang/String;
     151: invokevirtual #41                 // Method java/lang/String.equals:(Ljava/lang/Object;)Z
     154: ifeq          193
     157: aload         6
     159: invokevirtual #130                // Method org/apache/xml/security/stax/securityEvent/ContentEncryptedElementSecurityEvent.getXmlSecEvent:()Lorg/apache/xml/security/stax/ext/stax/XMLSecEvent;
     162: aload_1
     163: invokevirtual #15                 // Method org/apache/xml/security/stax/securityEvent/TokenSecurityEvent.getSecurityToken:()Lorg/apache/xml/security/stax/securityToken/SecurityToken;
     166: checkcast     #16                 // class org/apache/xml/security/stax/securityToken/InboundSecurityToken
     169: invokeinterface #114,  1          // InterfaceMethod org/apache/xml/security/stax/securityToken/InboundSecurityToken.getXMLSecEvent:()Lorg/apache/xml/security/stax/ext/stax/XMLSecEvent;
     174: if_acmpne     193
     177: aload_2
     178: aload         6
     180: invokevirtual #131                // Method org/apache/xml/security/stax/securityEvent/ContentEncryptedElementSecurityEvent.getElementPath:()Ljava/util/List;
     183: iconst_1
     184: iconst_0
     185: invokestatic  #110                // Method org/apache/wss4j/stax/utils/WSSUtils.pathMatches:(Ljava/util/List;Ljava/util/List;ZZ)Z
     188: ifeq          193
     191: iconst_1
     192: ireturn
     193: goto          8
     196: iconst_0
     197: ireturn

  public void handleBSPRule(org.apache.wss4j.common.bsp.BSPRule) throws org.apache.wss4j.common.ext.WSSecurityException;
    Code:
       0: aload_0
       1: getfield      #132                // Field disableBSPEnforcement:Z
       4: ifeq          8
       7: return
       8: aload_0
       9: getfield      #9                  // Field ignoredBSPRules:Ljava/util/List;
      12: aload_1
      13: invokeinterface #19,  2           // InterfaceMethod java/util/List.contains:(Ljava/lang/Object;)Z
      18: ifne          75
      21: new           #42                 // class org/apache/wss4j/common/ext/WSSecurityException
      24: dup
      25: getstatic     #133                // Field org/apache/wss4j/common/ext/WSSecurityException$ErrorCode.INVALID_SECURITY:Lorg/apache/wss4j/common/ext/WSSecurityException$ErrorCode;
      28: ldc           #134                // String empty
      30: iconst_1
      31: anewarray     #135                // class java/lang/Object
      34: dup
      35: iconst_0
      36: new           #136                // class java/lang/StringBuilder
      39: dup
      40: invokespecial #137                // Method java/lang/StringBuilder."<init>":()V
      43: ldc           #138                // String BSP:
      45: invokevirtual #139                // Method java/lang/StringBuilder.append:(Ljava/lang/String;)Ljava/lang/StringBuilder;
      48: aload_1
      49: invokevirtual #140                // Method org/apache/wss4j/common/bsp/BSPRule.name:()Ljava/lang/String;
      52: invokevirtual #139                // Method java/lang/StringBuilder.append:(Ljava/lang/String;)Ljava/lang/StringBuilder;
      55: ldc           #141                // String :
      57: invokevirtual #139                // Method java/lang/StringBuilder.append:(Ljava/lang/String;)Ljava/lang/StringBuilder;
      60: aload_1
      61: invokevirtual #142                // Method org/apache/wss4j/common/bsp/BSPRule.getMsg:()Ljava/lang/String;
      64: invokevirtual #139                // Method java/lang/StringBuilder.append:(Ljava/lang/String;)Ljava/lang/StringBuilder;
      67: invokevirtual #143                // Method java/lang/StringBuilder.toString:()Ljava/lang/String;
      70: aastore
      71: invokespecial #144                // Method org/apache/wss4j/common/ext/WSSecurityException."<init>":(Lorg/apache/wss4j/common/ext/WSSecurityException$ErrorCode;Ljava/lang/String;[Ljava/lang/Object;)V
      74: athrow
      75: getstatic     #145                // Field LOG:Lorg/slf4j/Logger;
      78: new           #136                // class java/lang/StringBuilder
      81: dup
      82: invokespecial #137                // Method java/lang/StringBuilder."<init>":()V
      85: ldc           #138                // String BSP:
      87: invokevirtual #139                // Method java/lang/StringBuilder.append:(Ljava/lang/String;)Ljava/lang/StringBuilder;
      90: aload_1
      91: invokevirtual #140                // Method org/apache/wss4j/common/bsp/BSPRule.name:()Ljava/lang/String;
      94: invokevirtual #139                // Method java/lang/StringBuilder.append:(Ljava/lang/String;)Ljava/lang/StringBuilder;
      97: ldc           #141                // String :
      99: invokevirtual #139                // Method java/lang/StringBuilder.append:(Ljava/lang/String;)Ljava/lang/StringBuilder;
     102: aload_1
     103: invokevirtual #142                // Method org/apache/wss4j/common/bsp/BSPRule.getMsg:()Ljava/lang/String;
     106: invokevirtual #139                // Method java/lang/StringBuilder.append:(Ljava/lang/String;)Ljava/lang/StringBuilder;
     109: invokevirtual #143                // Method java/lang/StringBuilder.toString:()Ljava/lang/String;
     112: invokeinterface #146,  2          // InterfaceMethod org/slf4j/Logger.warn:(Ljava/lang/String;)V
     117: return

  public void ignoredBSPRules(java.util.List<org.apache.wss4j.common.bsp.BSPRule>);
    Code:
       0: aload_0
       1: new           #48                 // class java/util/ArrayList
       4: dup
       5: aload_1
       6: invokespecial #147                // Method java/util/ArrayList."<init>":(Ljava/util/Collection;)V
       9: putfield      #9                  // Field ignoredBSPRules:Ljava/util/List;
      12: return

  public boolean isDisableBSPEnforcement();
    Code:
       0: aload_0
       1: getfield      #132                // Field disableBSPEnforcement:Z
       4: ireturn

  public void setDisableBSPEnforcement(boolean);
    Code:
       0: aload_0
       1: iload_1
       2: putfield      #132                // Field disableBSPEnforcement:Z
       5: return

  public boolean isAllowRSA15KeyTransportAlgorithm();
    Code:
       0: aload_0
       1: getfield      #7                  // Field allowRSA15KeyTransportAlgorithm:Z
       4: ireturn

  public void setAllowRSA15KeyTransportAlgorithm(boolean);
    Code:
       0: aload_0
       1: iload_1
       2: putfield      #7                  // Field allowRSA15KeyTransportAlgorithm:Z
       5: return

  static {};
    Code:
       0: ldc_w         #148                // class org/apache/wss4j/stax/impl/InboundWSSecurityContextImpl
       3: invokestatic  #149                // Method org/slf4j/LoggerFactory.getLogger:(Ljava/lang/Class;)Lorg/slf4j/Logger;
       6: putstatic     #145                // Field LOG:Lorg/slf4j/Logger;
       9: return
}
