Compiled from "WSSecurityStreamReader.java"
public class org.apache.wss4j.stax.impl.WSSecurityStreamReader extends org.apache.xml.security.stax.impl.XMLSecurityStreamReader {
  private final boolean initiator;

  private final boolean returnSecurityError;

  public org.apache.wss4j.stax.impl.WSSecurityStreamReader(org.apache.xml.security.stax.ext.InputProcessorChain, org.apache.xml.security.stax.ext.XMLSecurityProperties, boolean, boolean);
    Code:
       0: aload_0
       1: aload_1
       2: aload_2
       3: invokespecial #1                  // Method org/apache/xml/security/stax/impl/XMLSecurityStreamReader."<init>":(Lorg/apache/xml/security/stax/ext/InputProcessorChain;Lorg/apache/xml/security/stax/ext/XMLSecurityProperties;)V
       6: aload_0
       7: iload_3
       8: putfield      #2                  // Field initiator:Z
      11: aload_0
      12: iload         4
      14: putfield      #3                  // Field returnSecurityError:Z
      17: return

  public int next() throws javax.xml.stream.XMLStreamException;
    Code:
       0: aload_0
       1: invokespecial #4                  // Method org/apache/xml/security/stax/impl/XMLSecurityStreamReader.next:()I
       4: ireturn
       5: astore_1
       6: aload_1
       7: invokevirtual #6                  // Method javax/xml/stream/XMLStreamException.getCause:()Ljava/lang/Throwable;
      10: astore_2
      11: aload_0
      12: getfield      #3                  // Field returnSecurityError:Z
      15: ifne          39
      18: aload_0
      19: getfield      #2                  // Field initiator:Z
      22: ifne          39
      25: aload_2
      26: ifnull        41
      29: aload_2
      30: invokevirtual #7                  // Method java/lang/Throwable.getCause:()Ljava/lang/Throwable;
      33: instanceof    #8                  // class org/apache/wss4j/common/WSSPolicyException
      36: ifeq          41
      39: aload_1
      40: athrow
      41: new           #5                  // class javax/xml/stream/XMLStreamException
      44: dup
      45: new           #9                  // class org/apache/wss4j/common/ext/WSSecurityException
      48: dup
      49: getstatic     #10                 // Field org/apache/wss4j/common/ext/WSSecurityException$ErrorCode.SECURITY_ERROR:Lorg/apache/wss4j/common/ext/WSSecurityException$ErrorCode;
      52: invokespecial #11                 // Method org/apache/wss4j/common/ext/WSSecurityException."<init>":(Lorg/apache/wss4j/common/ext/WSSecurityException$ErrorCode;)V
      55: invokespecial #12                 // Method javax/xml/stream/XMLStreamException."<init>":(Ljava/lang/Throwable;)V
      58: athrow
    Exception table:
       from    to  target type
           0     4     5   Class javax/xml/stream/XMLStreamException
}
