Compiled from "Log.java"
class org.eclipse.jetty.util.log.Log$1 implements java.security.PrivilegedAction<java.lang.Object> {
  org.eclipse.jetty.util.log.Log$1();
    Code:
       0: aload_0
       1: invokespecial #1                  // Method java/lang/Object."<init>":()V
       4: return

  public java.lang.Object run();
    Code:
       0: ldc           #2                  // String jetty-logging.properties
       2: getstatic     #3                  // Field org/eclipse/jetty/util/log/Log.__props:Ljava/util/Properties;
       5: invokestatic  #4                  // Method org/eclipse/jetty/util/log/Log.access$000:(Ljava/lang/String;Ljava/util/Properties;)V
       8: ldc           #5                  // String os.name
      10: invokestatic  #6                  // Method java/lang/System.getProperty:(Ljava/lang/String;)Ljava/lang/String;
      13: astore_1
      14: aload_1
      15: ifnull        70
      18: aload_1
      19: invokevirtual #7                  // Method java/lang/String.length:()I
      22: ifle          70
      25: aload_1
      26: getstatic     #8                  // Field java/util/Locale.ENGLISH:Ljava/util/Locale;
      29: invokevirtual #9                  // Method java/lang/String.toLowerCase:(Ljava/util/Locale;)Ljava/lang/String;
      32: bipush        32
      34: bipush        45
      36: invokevirtual #10                 // Method java/lang/String.replace:(CC)Ljava/lang/String;
      39: astore_1
      40: new           #11                 // class java/lang/StringBuilder
      43: dup
      44: invokespecial #12                 // Method java/lang/StringBuilder."<init>":()V
      47: ldc           #13                 // String jetty-logging-
      49: invokevirtual #14                 // Method java/lang/StringBuilder.append:(Ljava/lang/String;)Ljava/lang/StringBuilder;
      52: aload_1
      53: invokevirtual #14                 // Method java/lang/StringBuilder.append:(Ljava/lang/String;)Ljava/lang/StringBuilder;
      56: ldc           #15                 // String .properties
      58: invokevirtual #14                 // Method java/lang/StringBuilder.append:(Ljava/lang/String;)Ljava/lang/StringBuilder;
      61: invokevirtual #16                 // Method java/lang/StringBuilder.toString:()Ljava/lang/String;
      64: getstatic     #3                  // Field org/eclipse/jetty/util/log/Log.__props:Ljava/util/Properties;
      67: invokestatic  #4                  // Method org/eclipse/jetty/util/log/Log.access$000:(Ljava/lang/String;Ljava/util/Properties;)V
      70: invokestatic  #17                 // Method java/lang/System.getProperties:()Ljava/util/Properties;
      73: invokevirtual #18                 // Method java/util/Properties.propertyNames:()Ljava/util/Enumeration;
      76: astore_2
      77: aload_2
      78: invokeinterface #19,  1           // InterfaceMethod java/util/Enumeration.hasMoreElements:()Z
      83: ifeq          120
      86: aload_2
      87: invokeinterface #20,  1           // InterfaceMethod java/util/Enumeration.nextElement:()Ljava/lang/Object;
      92: checkcast     #21                 // class java/lang/String
      95: astore_3
      96: aload_3
      97: invokestatic  #6                  // Method java/lang/System.getProperty:(Ljava/lang/String;)Ljava/lang/String;
     100: astore        4
     102: aload         4
     104: ifnull        117
     107: getstatic     #3                  // Field org/eclipse/jetty/util/log/Log.__props:Ljava/util/Properties;
     110: aload_3
     111: aload         4
     113: invokevirtual #22                 // Method java/util/Properties.setProperty:(Ljava/lang/String;Ljava/lang/String;)Ljava/lang/Object;
     116: pop
     117: goto          77
     120: getstatic     #3                  // Field org/eclipse/jetty/util/log/Log.__props:Ljava/util/Properties;
     123: ldc           #23                 // String org.eclipse.jetty.util.log.class
     125: ldc           #24                 // String org.eclipse.jetty.util.log.Slf4jLog
     127: invokevirtual #25                 // Method java/util/Properties.getProperty:(Ljava/lang/String;Ljava/lang/String;)Ljava/lang/String;
     130: putstatic     #26                 // Field org/eclipse/jetty/util/log/Log.__logClass:Ljava/lang/String;
     133: getstatic     #3                  // Field org/eclipse/jetty/util/log/Log.__props:Ljava/util/Properties;
     136: ldc           #27                 // String org.eclipse.jetty.util.log.IGNORED
     138: ldc           #28                 // String false
     140: invokevirtual #25                 // Method java/util/Properties.getProperty:(Ljava/lang/String;Ljava/lang/String;)Ljava/lang/String;
     143: invokestatic  #29                 // Method java/lang/Boolean.parseBoolean:(Ljava/lang/String;)Z
     146: putstatic     #30                 // Field org/eclipse/jetty/util/log/Log.__ignored:Z
     149: aconst_null
     150: areturn
}
