Compiled from "JpaOrmXmlEventReader.java"
public class org.hibernate.boot.jaxb.internal.stax.JpaOrmXmlEventReader$BadVersionException extends java.lang.RuntimeException {
  private final java.lang.String requestedVersion;

  public org.hibernate.boot.jaxb.internal.stax.JpaOrmXmlEventReader$BadVersionException(java.lang.String);
    Code:
       0: aload_0
       1: invokespecial #1                  // Method java/lang/RuntimeException."<init>":()V
       4: aload_0
       5: aload_1
       6: putfield      #2                  // Field requestedVersion:Ljava/lang/String;
       9: return

  public java.lang.String getRequestedVersion();
    Code:
       0: aload_0
       1: getfield      #2                  // Field requestedVersion:Ljava/lang/String;
       4: areturn
}
