Compiled from "TcpKeepalive.java"
public final class io.grpc.xds.shaded.io.envoyproxy.envoy.api.v2.core.TcpKeepalive$Builder extends com.google.protobuf.GeneratedMessageV3$Builder<io.grpc.xds.shaded.io.envoyproxy.envoy.api.v2.core.TcpKeepalive$Builder> implements io.grpc.xds.shaded.io.envoyproxy.envoy.api.v2.core.TcpKeepaliveOrBuilder {
  private com.google.protobuf.UInt32Value keepaliveProbes_;

  private com.google.protobuf.SingleFieldBuilderV3<com.google.protobuf.UInt32Value, com.google.protobuf.UInt32Value$Builder, com.google.protobuf.UInt32ValueOrBuilder> keepaliveProbesBuilder_;

  private com.google.protobuf.UInt32Value keepaliveTime_;

  private com.google.protobuf.SingleFieldBuilderV3<com.google.protobuf.UInt32Value, com.google.protobuf.UInt32Value$Builder, com.google.protobuf.UInt32ValueOrBuilder> keepaliveTimeBuilder_;

  private com.google.protobuf.UInt32Value keepaliveInterval_;

  private com.google.protobuf.SingleFieldBuilderV3<com.google.protobuf.UInt32Value, com.google.protobuf.UInt32Value$Builder, com.google.protobuf.UInt32ValueOrBuilder> keepaliveIntervalBuilder_;

  public static final com.google.protobuf.Descriptors$Descriptor getDescriptor();
    Code:
       0: getstatic     #71                 // Field io/grpc/xds/shaded/io/envoyproxy/envoy/api/v2/core/AddressProto.internal_static_envoy_api_v2_core_TcpKeepalive_descriptor:Lcom/google/protobuf/Descriptors$Descriptor;
       3: areturn

  protected com.google.protobuf.GeneratedMessageV3$FieldAccessorTable internalGetFieldAccessorTable();
    Code:
       0: getstatic     #77                 // Field io/grpc/xds/shaded/io/envoyproxy/envoy/api/v2/core/AddressProto.internal_static_envoy_api_v2_core_TcpKeepalive_fieldAccessorTable:Lcom/google/protobuf/GeneratedMessageV3$FieldAccessorTable;
       3: ldc           #25                 // class io/grpc/xds/shaded/io/envoyproxy/envoy/api/v2/core/TcpKeepalive
       5: ldc           #2                  // class io/grpc/xds/shaded/io/envoyproxy/envoy/api/v2/core/TcpKeepalive$Builder
       7: invokevirtual #81                 // Method com/google/protobuf/GeneratedMessageV3$FieldAccessorTable.ensureFieldAccessorsInitialized:(Ljava/lang/Class;Ljava/lang/Class;)Lcom/google/protobuf/GeneratedMessageV3$FieldAccessorTable;
      10: areturn

  private io.grpc.xds.shaded.io.envoyproxy.envoy.api.v2.core.TcpKeepalive$Builder();
    Code:
       0: aload_0
       1: invokespecial #87                 // Method com/google/protobuf/GeneratedMessageV3$Builder."<init>":()V
       4: aload_0
       5: invokespecial #90                 // Method maybeForceBuilderInitialization:()V
       8: return

  private io.grpc.xds.shaded.io.envoyproxy.envoy.api.v2.core.TcpKeepalive$Builder(com.google.protobuf.GeneratedMessageV3$BuilderParent);
    Code:
       0: aload_0
       1: aload_1
       2: invokespecial #93                 // Method com/google/protobuf/GeneratedMessageV3$Builder."<init>":(Lcom/google/protobuf/GeneratedMessageV3$BuilderParent;)V
       5: aload_0
       6: invokespecial #90                 // Method maybeForceBuilderInitialization:()V
       9: return

  private void maybeForceBuilderInitialization();
    Code:
       0: invokestatic  #99                 // Method io/grpc/xds/shaded/io/envoyproxy/envoy/api/v2/core/TcpKeepalive.access$200:()Z
       3: ifeq          6
       6: return

  public io.grpc.xds.shaded.io.envoyproxy.envoy.api.v2.core.TcpKeepalive$Builder clear();
    Code:
       0: aload_0
       1: invokespecial #104                // Method com/google/protobuf/GeneratedMessageV3$Builder.clear:()Lcom/google/protobuf/GeneratedMessageV3$Builder;
       4: pop
       5: aload_0
       6: getfield      #106                // Field keepaliveProbesBuilder_:Lcom/google/protobuf/SingleFieldBuilderV3;
       9: ifnonnull     20
      12: aload_0
      13: aconst_null
      14: putfield      #108                // Field keepaliveProbes_:Lcom/google/protobuf/UInt32Value;
      17: goto          30
      20: aload_0
      21: aconst_null
      22: putfield      #108                // Field keepaliveProbes_:Lcom/google/protobuf/UInt32Value;
      25: aload_0
      26: aconst_null
      27: putfield      #106                // Field keepaliveProbesBuilder_:Lcom/google/protobuf/SingleFieldBuilderV3;
      30: aload_0
      31: getfield      #110                // Field keepaliveTimeBuilder_:Lcom/google/protobuf/SingleFieldBuilderV3;
      34: ifnonnull     45
      37: aload_0
      38: aconst_null
      39: putfield      #112                // Field keepaliveTime_:Lcom/google/protobuf/UInt32Value;
      42: goto          55
      45: aload_0
      46: aconst_null
      47: putfield      #112                // Field keepaliveTime_:Lcom/google/protobuf/UInt32Value;
      50: aload_0
      51: aconst_null
      52: putfield      #110                // Field keepaliveTimeBuilder_:Lcom/google/protobuf/SingleFieldBuilderV3;
      55: aload_0
      56: getfield      #114                // Field keepaliveIntervalBuilder_:Lcom/google/protobuf/SingleFieldBuilderV3;
      59: ifnonnull     70
      62: aload_0
      63: aconst_null
      64: putfield      #116                // Field keepaliveInterval_:Lcom/google/protobuf/UInt32Value;
      67: goto          80
      70: aload_0
      71: aconst_null
      72: putfield      #116                // Field keepaliveInterval_:Lcom/google/protobuf/UInt32Value;
      75: aload_0
      76: aconst_null
      77: putfield      #114                // Field keepaliveIntervalBuilder_:Lcom/google/protobuf/SingleFieldBuilderV3;
      80: aload_0
      81: areturn

  public com.google.protobuf.Descriptors$Descriptor getDescriptorForType();
    Code:
       0: getstatic     #71                 // Field io/grpc/xds/shaded/io/envoyproxy/envoy/api/v2/core/AddressProto.internal_static_envoy_api_v2_core_TcpKeepalive_descriptor:Lcom/google/protobuf/Descriptors$Descriptor;
       3: areturn

  public io.grpc.xds.shaded.io.envoyproxy.envoy.api.v2.core.TcpKeepalive getDefaultInstanceForType();
    Code:
       0: invokestatic  #122                // Method io/grpc/xds/shaded/io/envoyproxy/envoy/api/v2/core/TcpKeepalive.getDefaultInstance:()Lio/grpc/xds/shaded/io/envoyproxy/envoy/api/v2/core/TcpKeepalive;
       3: areturn

  public io.grpc.xds.shaded.io.envoyproxy.envoy.api.v2.core.TcpKeepalive build();
    Code:
       0: aload_0
       1: invokevirtual #126                // Method buildPartial:()Lio/grpc/xds/shaded/io/envoyproxy/envoy/api/v2/core/TcpKeepalive;
       4: astore_1
       5: aload_1
       6: invokevirtual #129                // Method io/grpc/xds/shaded/io/envoyproxy/envoy/api/v2/core/TcpKeepalive.isInitialized:()Z
       9: ifne          17
      12: aload_1
      13: invokestatic  #133                // Method newUninitializedMessageException:(Lcom/google/protobuf/Message;)Lcom/google/protobuf/UninitializedMessageException;
      16: athrow
      17: aload_1
      18: areturn

  public io.grpc.xds.shaded.io.envoyproxy.envoy.api.v2.core.TcpKeepalive buildPartial();
    Code:
       0: new           #25                 // class io/grpc/xds/shaded/io/envoyproxy/envoy/api/v2/core/TcpKeepalive
       3: dup
       4: aload_0
       5: aconst_null
       6: invokespecial #138                // Method io/grpc/xds/shaded/io/envoyproxy/envoy/api/v2/core/TcpKeepalive."<init>":(Lcom/google/protobuf/GeneratedMessageV3$Builder;Lio/grpc/xds/shaded/io/envoyproxy/envoy/api/v2/core/TcpKeepalive$1;)V
       9: astore_1
      10: aload_0
      11: getfield      #106                // Field keepaliveProbesBuilder_:Lcom/google/protobuf/SingleFieldBuilderV3;
      14: ifnonnull     29
      17: aload_1
      18: aload_0
      19: getfield      #108                // Field keepaliveProbes_:Lcom/google/protobuf/UInt32Value;
      22: invokestatic  #142                // Method io/grpc/xds/shaded/io/envoyproxy/envoy/api/v2/core/TcpKeepalive.access$402:(Lio/grpc/xds/shaded/io/envoyproxy/envoy/api/v2/core/TcpKeepalive;Lcom/google/protobuf/UInt32Value;)Lcom/google/protobuf/UInt32Value;
      25: pop
      26: goto          44
      29: aload_1
      30: aload_0
      31: getfield      #106                // Field keepaliveProbesBuilder_:Lcom/google/protobuf/SingleFieldBuilderV3;
      34: invokevirtual #147                // Method com/google/protobuf/SingleFieldBuilderV3.build:()Lcom/google/protobuf/AbstractMessage;
      37: checkcast     #12                 // class com/google/protobuf/UInt32Value
      40: invokestatic  #142                // Method io/grpc/xds/shaded/io/envoyproxy/envoy/api/v2/core/TcpKeepalive.access$402:(Lio/grpc/xds/shaded/io/envoyproxy/envoy/api/v2/core/TcpKeepalive;Lcom/google/protobuf/UInt32Value;)Lcom/google/protobuf/UInt32Value;
      43: pop
      44: aload_0
      45: getfield      #110                // Field keepaliveTimeBuilder_:Lcom/google/protobuf/SingleFieldBuilderV3;
      48: ifnonnull     63
      51: aload_1
      52: aload_0
      53: getfield      #112                // Field keepaliveTime_:Lcom/google/protobuf/UInt32Value;
      56: invokestatic  #150                // Method io/grpc/xds/shaded/io/envoyproxy/envoy/api/v2/core/TcpKeepalive.access$502:(Lio/grpc/xds/shaded/io/envoyproxy/envoy/api/v2/core/TcpKeepalive;Lcom/google/protobuf/UInt32Value;)Lcom/google/protobuf/UInt32Value;
      59: pop
      60: goto          78
      63: aload_1
      64: aload_0
      65: getfield      #110                // Field keepaliveTimeBuilder_:Lcom/google/protobuf/SingleFieldBuilderV3;
      68: invokevirtual #147                // Method com/google/protobuf/SingleFieldBuilderV3.build:()Lcom/google/protobuf/AbstractMessage;
      71: checkcast     #12                 // class com/google/protobuf/UInt32Value
      74: invokestatic  #150                // Method io/grpc/xds/shaded/io/envoyproxy/envoy/api/v2/core/TcpKeepalive.access$502:(Lio/grpc/xds/shaded/io/envoyproxy/envoy/api/v2/core/TcpKeepalive;Lcom/google/protobuf/UInt32Value;)Lcom/google/protobuf/UInt32Value;
      77: pop
      78: aload_0
      79: getfield      #114                // Field keepaliveIntervalBuilder_:Lcom/google/protobuf/SingleFieldBuilderV3;
      82: ifnonnull     97
      85: aload_1
      86: aload_0
      87: getfield      #116                // Field keepaliveInterval_:Lcom/google/protobuf/UInt32Value;
      90: invokestatic  #153                // Method io/grpc/xds/shaded/io/envoyproxy/envoy/api/v2/core/TcpKeepalive.access$602:(Lio/grpc/xds/shaded/io/envoyproxy/envoy/api/v2/core/TcpKeepalive;Lcom/google/protobuf/UInt32Value;)Lcom/google/protobuf/UInt32Value;
      93: pop
      94: goto          112
      97: aload_1
      98: aload_0
      99: getfield      #114                // Field keepaliveIntervalBuilder_:Lcom/google/protobuf/SingleFieldBuilderV3;
     102: invokevirtual #147                // Method com/google/protobuf/SingleFieldBuilderV3.build:()Lcom/google/protobuf/AbstractMessage;
     105: checkcast     #12                 // class com/google/protobuf/UInt32Value
     108: invokestatic  #153                // Method io/grpc/xds/shaded/io/envoyproxy/envoy/api/v2/core/TcpKeepalive.access$602:(Lio/grpc/xds/shaded/io/envoyproxy/envoy/api/v2/core/TcpKeepalive;Lcom/google/protobuf/UInt32Value;)Lcom/google/protobuf/UInt32Value;
     111: pop
     112: aload_0
     113: invokevirtual #156                // Method onBuilt:()V
     116: aload_1
     117: areturn

  public io.grpc.xds.shaded.io.envoyproxy.envoy.api.v2.core.TcpKeepalive$Builder clone();
    Code:
       0: aload_0
       1: invokespecial #159                // Method com/google/protobuf/GeneratedMessageV3$Builder.clone:()Lcom/google/protobuf/GeneratedMessageV3$Builder;
       4: checkcast     #2                  // class io/grpc/xds/shaded/io/envoyproxy/envoy/api/v2/core/TcpKeepalive$Builder
       7: areturn

  public io.grpc.xds.shaded.io.envoyproxy.envoy.api.v2.core.TcpKeepalive$Builder setField(com.google.protobuf.Descriptors$FieldDescriptor, java.lang.Object);
    Code:
       0: aload_0
       1: aload_1
       2: aload_2
       3: invokespecial #164                // Method com/google/protobuf/GeneratedMessageV3$Builder.setField:(Lcom/google/protobuf/Descriptors$FieldDescriptor;Ljava/lang/Object;)Lcom/google/protobuf/GeneratedMessageV3$Builder;
       6: checkcast     #2                  // class io/grpc/xds/shaded/io/envoyproxy/envoy/api/v2/core/TcpKeepalive$Builder
       9: areturn

  public io.grpc.xds.shaded.io.envoyproxy.envoy.api.v2.core.TcpKeepalive$Builder clearField(com.google.protobuf.Descriptors$FieldDescriptor);
    Code:
       0: aload_0
       1: aload_1
       2: invokespecial #173                // Method com/google/protobuf/GeneratedMessageV3$Builder.clearField:(Lcom/google/protobuf/Descriptors$FieldDescriptor;)Lcom/google/protobuf/GeneratedMessageV3$Builder;
       5: checkcast     #2                  // class io/grpc/xds/shaded/io/envoyproxy/envoy/api/v2/core/TcpKeepalive$Builder
       8: areturn

  public io.grpc.xds.shaded.io.envoyproxy.envoy.api.v2.core.TcpKeepalive$Builder clearOneof(com.google.protobuf.Descriptors$OneofDescriptor);
    Code:
       0: aload_0
       1: aload_1
       2: invokespecial #178                // Method com/google/protobuf/GeneratedMessageV3$Builder.clearOneof:(Lcom/google/protobuf/Descriptors$OneofDescriptor;)Lcom/google/protobuf/GeneratedMessageV3$Builder;
       5: checkcast     #2                  // class io/grpc/xds/shaded/io/envoyproxy/envoy/api/v2/core/TcpKeepalive$Builder
       8: areturn

  public io.grpc.xds.shaded.io.envoyproxy.envoy.api.v2.core.TcpKeepalive$Builder setRepeatedField(com.google.protobuf.Descriptors$FieldDescriptor, int, java.lang.Object);
    Code:
       0: aload_0
       1: aload_1
       2: iload_2
       3: aload_3
       4: invokespecial #185                // Method com/google/protobuf/GeneratedMessageV3$Builder.setRepeatedField:(Lcom/google/protobuf/Descriptors$FieldDescriptor;ILjava/lang/Object;)Lcom/google/protobuf/GeneratedMessageV3$Builder;
       7: checkcast     #2                  // class io/grpc/xds/shaded/io/envoyproxy/envoy/api/v2/core/TcpKeepalive$Builder
      10: areturn

  public io.grpc.xds.shaded.io.envoyproxy.envoy.api.v2.core.TcpKeepalive$Builder addRepeatedField(com.google.protobuf.Descriptors$FieldDescriptor, java.lang.Object);
    Code:
       0: aload_0
       1: aload_1
       2: aload_2
       3: invokespecial #190                // Method com/google/protobuf/GeneratedMessageV3$Builder.addRepeatedField:(Lcom/google/protobuf/Descriptors$FieldDescriptor;Ljava/lang/Object;)Lcom/google/protobuf/GeneratedMessageV3$Builder;
       6: checkcast     #2                  // class io/grpc/xds/shaded/io/envoyproxy/envoy/api/v2/core/TcpKeepalive$Builder
       9: areturn

  public io.grpc.xds.shaded.io.envoyproxy.envoy.api.v2.core.TcpKeepalive$Builder mergeFrom(com.google.protobuf.Message);
    Code:
       0: aload_1
       1: instanceof    #25                 // class io/grpc/xds/shaded/io/envoyproxy/envoy/api/v2/core/TcpKeepalive
       4: ifeq          16
       7: aload_0
       8: aload_1
       9: checkcast     #25                 // class io/grpc/xds/shaded/io/envoyproxy/envoy/api/v2/core/TcpKeepalive
      12: invokevirtual #195                // Method mergeFrom:(Lio/grpc/xds/shaded/io/envoyproxy/envoy/api/v2/core/TcpKeepalive;)Lio/grpc/xds/shaded/io/envoyproxy/envoy/api/v2/core/TcpKeepalive$Builder;
      15: areturn
      16: aload_0
      17: aload_1
      18: invokespecial #198                // Method com/google/protobuf/GeneratedMessageV3$Builder.mergeFrom:(Lcom/google/protobuf/Message;)Lcom/google/protobuf/AbstractMessage$Builder;
      21: pop
      22: aload_0
      23: areturn

  public io.grpc.xds.shaded.io.envoyproxy.envoy.api.v2.core.TcpKeepalive$Builder mergeFrom(io.grpc.xds.shaded.io.envoyproxy.envoy.api.v2.core.TcpKeepalive);
    Code:
       0: aload_1
       1: invokestatic  #122                // Method io/grpc/xds/shaded/io/envoyproxy/envoy/api/v2/core/TcpKeepalive.getDefaultInstance:()Lio/grpc/xds/shaded/io/envoyproxy/envoy/api/v2/core/TcpKeepalive;
       4: if_acmpne     9
       7: aload_0
       8: areturn
       9: aload_1
      10: invokevirtual #203                // Method io/grpc/xds/shaded/io/envoyproxy/envoy/api/v2/core/TcpKeepalive.hasKeepaliveProbes:()Z
      13: ifeq          25
      16: aload_0
      17: aload_1
      18: invokevirtual #207                // Method io/grpc/xds/shaded/io/envoyproxy/envoy/api/v2/core/TcpKeepalive.getKeepaliveProbes:()Lcom/google/protobuf/UInt32Value;
      21: invokevirtual #211                // Method mergeKeepaliveProbes:(Lcom/google/protobuf/UInt32Value;)Lio/grpc/xds/shaded/io/envoyproxy/envoy/api/v2/core/TcpKeepalive$Builder;
      24: pop
      25: aload_1
      26: invokevirtual #214                // Method io/grpc/xds/shaded/io/envoyproxy/envoy/api/v2/core/TcpKeepalive.hasKeepaliveTime:()Z
      29: ifeq          41
      32: aload_0
      33: aload_1
      34: invokevirtual #217                // Method io/grpc/xds/shaded/io/envoyproxy/envoy/api/v2/core/TcpKeepalive.getKeepaliveTime:()Lcom/google/protobuf/UInt32Value;
      37: invokevirtual #220                // Method mergeKeepaliveTime:(Lcom/google/protobuf/UInt32Value;)Lio/grpc/xds/shaded/io/envoyproxy/envoy/api/v2/core/TcpKeepalive$Builder;
      40: pop
      41: aload_1
      42: invokevirtual #223                // Method io/grpc/xds/shaded/io/envoyproxy/envoy/api/v2/core/TcpKeepalive.hasKeepaliveInterval:()Z
      45: ifeq          57
      48: aload_0
      49: aload_1
      50: invokevirtual #226                // Method io/grpc/xds/shaded/io/envoyproxy/envoy/api/v2/core/TcpKeepalive.getKeepaliveInterval:()Lcom/google/protobuf/UInt32Value;
      53: invokevirtual #229                // Method mergeKeepaliveInterval:(Lcom/google/protobuf/UInt32Value;)Lio/grpc/xds/shaded/io/envoyproxy/envoy/api/v2/core/TcpKeepalive$Builder;
      56: pop
      57: aload_0
      58: aload_1
      59: invokestatic  #233                // Method io/grpc/xds/shaded/io/envoyproxy/envoy/api/v2/core/TcpKeepalive.access$700:(Lio/grpc/xds/shaded/io/envoyproxy/envoy/api/v2/core/TcpKeepalive;)Lcom/google/protobuf/UnknownFieldSet;
      62: invokevirtual #237                // Method mergeUnknownFields:(Lcom/google/protobuf/UnknownFieldSet;)Lio/grpc/xds/shaded/io/envoyproxy/envoy/api/v2/core/TcpKeepalive$Builder;
      65: pop
      66: aload_0
      67: invokevirtual #240                // Method onChanged:()V
      70: aload_0
      71: areturn

  public final boolean isInitialized();
    Code:
       0: iconst_1
       1: ireturn

  public io.grpc.xds.shaded.io.envoyproxy.envoy.api.v2.core.TcpKeepalive$Builder mergeFrom(com.google.protobuf.CodedInputStream, com.google.protobuf.ExtensionRegistryLite) throws java.io.IOException;
    Code:
       0: aconst_null
       1: astore_3
       2: invokestatic  #249                // Method io/grpc/xds/shaded/io/envoyproxy/envoy/api/v2/core/TcpKeepalive.access$800:()Lcom/google/protobuf/Parser;
       5: aload_1
       6: aload_2
       7: invokeinterface #255,  3          // InterfaceMethod com/google/protobuf/Parser.parsePartialFrom:(Lcom/google/protobuf/CodedInputStream;Lcom/google/protobuf/ExtensionRegistryLite;)Ljava/lang/Object;
      12: checkcast     #25                 // class io/grpc/xds/shaded/io/envoyproxy/envoy/api/v2/core/TcpKeepalive
      15: astore_3
      16: aload_3
      17: ifnull        61
      20: aload_0
      21: aload_3
      22: invokevirtual #195                // Method mergeFrom:(Lio/grpc/xds/shaded/io/envoyproxy/envoy/api/v2/core/TcpKeepalive;)Lio/grpc/xds/shaded/io/envoyproxy/envoy/api/v2/core/TcpKeepalive$Builder;
      25: pop
      26: goto          61
      29: astore        4
      31: aload         4
      33: invokevirtual #263                // Method com/google/protobuf/InvalidProtocolBufferException.getUnfinishedMessage:()Lcom/google/protobuf/MessageLite;
      36: checkcast     #25                 // class io/grpc/xds/shaded/io/envoyproxy/envoy/api/v2/core/TcpKeepalive
      39: astore_3
      40: aload         4
      42: invokevirtual #267                // Method com/google/protobuf/InvalidProtocolBufferException.unwrapIOException:()Ljava/io/IOException;
      45: athrow
      46: astore        5
      48: aload_3
      49: ifnull        58
      52: aload_0
      53: aload_3
      54: invokevirtual #195                // Method mergeFrom:(Lio/grpc/xds/shaded/io/envoyproxy/envoy/api/v2/core/TcpKeepalive;)Lio/grpc/xds/shaded/io/envoyproxy/envoy/api/v2/core/TcpKeepalive$Builder;
      57: pop
      58: aload         5
      60: athrow
      61: aload_0
      62: areturn
    Exception table:
       from    to  target type
           2    16    29   Class com/google/protobuf/InvalidProtocolBufferException
           2    16    46   any
          29    48    46   any

  public boolean hasKeepaliveProbes();
    Code:
       0: aload_0
       1: getfield      #106                // Field keepaliveProbesBuilder_:Lcom/google/protobuf/SingleFieldBuilderV3;
       4: ifnonnull     14
       7: aload_0
       8: getfield      #108                // Field keepaliveProbes_:Lcom/google/protobuf/UInt32Value;
      11: ifnull        18
      14: iconst_1
      15: goto          19
      18: iconst_0
      19: ireturn

  public com.google.protobuf.UInt32Value getKeepaliveProbes();
    Code:
       0: aload_0
       1: getfield      #106                // Field keepaliveProbesBuilder_:Lcom/google/protobuf/SingleFieldBuilderV3;
       4: ifnonnull     25
       7: aload_0
       8: getfield      #108                // Field keepaliveProbes_:Lcom/google/protobuf/UInt32Value;
      11: ifnonnull     20
      14: invokestatic  #278                // Method com/google/protobuf/UInt32Value.getDefaultInstance:()Lcom/google/protobuf/UInt32Value;
      17: goto          24
      20: aload_0
      21: getfield      #108                // Field keepaliveProbes_:Lcom/google/protobuf/UInt32Value;
      24: areturn
      25: aload_0
      26: getfield      #106                // Field keepaliveProbesBuilder_:Lcom/google/protobuf/SingleFieldBuilderV3;
      29: invokevirtual #281                // Method com/google/protobuf/SingleFieldBuilderV3.getMessage:()Lcom/google/protobuf/AbstractMessage;
      32: checkcast     #12                 // class com/google/protobuf/UInt32Value
      35: areturn

  public io.grpc.xds.shaded.io.envoyproxy.envoy.api.v2.core.TcpKeepalive$Builder setKeepaliveProbes(com.google.protobuf.UInt32Value);
    Code:
       0: aload_0
       1: getfield      #106                // Field keepaliveProbesBuilder_:Lcom/google/protobuf/SingleFieldBuilderV3;
       4: ifnonnull     31
       7: aload_1
       8: ifnonnull     19
      11: new           #284                // class java/lang/NullPointerException
      14: dup
      15: invokespecial #285                // Method java/lang/NullPointerException."<init>":()V
      18: athrow
      19: aload_0
      20: aload_1
      21: putfield      #108                // Field keepaliveProbes_:Lcom/google/protobuf/UInt32Value;
      24: aload_0
      25: invokevirtual #240                // Method onChanged:()V
      28: goto          40
      31: aload_0
      32: getfield      #106                // Field keepaliveProbesBuilder_:Lcom/google/protobuf/SingleFieldBuilderV3;
      35: aload_1
      36: invokevirtual #289                // Method com/google/protobuf/SingleFieldBuilderV3.setMessage:(Lcom/google/protobuf/AbstractMessage;)Lcom/google/protobuf/SingleFieldBuilderV3;
      39: pop
      40: aload_0
      41: areturn

  public io.grpc.xds.shaded.io.envoyproxy.envoy.api.v2.core.TcpKeepalive$Builder setKeepaliveProbes(com.google.protobuf.UInt32Value$Builder);
    Code:
       0: aload_0
       1: getfield      #106                // Field keepaliveProbesBuilder_:Lcom/google/protobuf/SingleFieldBuilderV3;
       4: ifnonnull     22
       7: aload_0
       8: aload_1
       9: invokevirtual #292                // Method com/google/protobuf/UInt32Value$Builder.build:()Lcom/google/protobuf/UInt32Value;
      12: putfield      #108                // Field keepaliveProbes_:Lcom/google/protobuf/UInt32Value;
      15: aload_0
      16: invokevirtual #240                // Method onChanged:()V
      19: goto          34
      22: aload_0
      23: getfield      #106                // Field keepaliveProbesBuilder_:Lcom/google/protobuf/SingleFieldBuilderV3;
      26: aload_1
      27: invokevirtual #292                // Method com/google/protobuf/UInt32Value$Builder.build:()Lcom/google/protobuf/UInt32Value;
      30: invokevirtual #289                // Method com/google/protobuf/SingleFieldBuilderV3.setMessage:(Lcom/google/protobuf/AbstractMessage;)Lcom/google/protobuf/SingleFieldBuilderV3;
      33: pop
      34: aload_0
      35: areturn

  public io.grpc.xds.shaded.io.envoyproxy.envoy.api.v2.core.TcpKeepalive$Builder mergeKeepaliveProbes(com.google.protobuf.UInt32Value);
    Code:
       0: aload_0
       1: getfield      #106                // Field keepaliveProbesBuilder_:Lcom/google/protobuf/SingleFieldBuilderV3;
       4: ifnonnull     47
       7: aload_0
       8: getfield      #108                // Field keepaliveProbes_:Lcom/google/protobuf/UInt32Value;
      11: ifnull        35
      14: aload_0
      15: aload_0
      16: getfield      #108                // Field keepaliveProbes_:Lcom/google/protobuf/UInt32Value;
      19: invokestatic  #298                // Method com/google/protobuf/UInt32Value.newBuilder:(Lcom/google/protobuf/UInt32Value;)Lcom/google/protobuf/UInt32Value$Builder;
      22: aload_1
      23: invokevirtual #300                // Method com/google/protobuf/UInt32Value$Builder.mergeFrom:(Lcom/google/protobuf/UInt32Value;)Lcom/google/protobuf/UInt32Value$Builder;
      26: invokevirtual #302                // Method com/google/protobuf/UInt32Value$Builder.buildPartial:()Lcom/google/protobuf/UInt32Value;
      29: putfield      #108                // Field keepaliveProbes_:Lcom/google/protobuf/UInt32Value;
      32: goto          40
      35: aload_0
      36: aload_1
      37: putfield      #108                // Field keepaliveProbes_:Lcom/google/protobuf/UInt32Value;
      40: aload_0
      41: invokevirtual #240                // Method onChanged:()V
      44: goto          56
      47: aload_0
      48: getfield      #106                // Field keepaliveProbesBuilder_:Lcom/google/protobuf/SingleFieldBuilderV3;
      51: aload_1
      52: invokevirtual #304                // Method com/google/protobuf/SingleFieldBuilderV3.mergeFrom:(Lcom/google/protobuf/AbstractMessage;)Lcom/google/protobuf/SingleFieldBuilderV3;
      55: pop
      56: aload_0
      57: areturn

  public io.grpc.xds.shaded.io.envoyproxy.envoy.api.v2.core.TcpKeepalive$Builder clearKeepaliveProbes();
    Code:
       0: aload_0
       1: getfield      #106                // Field keepaliveProbesBuilder_:Lcom/google/protobuf/SingleFieldBuilderV3;
       4: ifnonnull     19
       7: aload_0
       8: aconst_null
       9: putfield      #108                // Field keepaliveProbes_:Lcom/google/protobuf/UInt32Value;
      12: aload_0
      13: invokevirtual #240                // Method onChanged:()V
      16: goto          29
      19: aload_0
      20: aconst_null
      21: putfield      #108                // Field keepaliveProbes_:Lcom/google/protobuf/UInt32Value;
      24: aload_0
      25: aconst_null
      26: putfield      #106                // Field keepaliveProbesBuilder_:Lcom/google/protobuf/SingleFieldBuilderV3;
      29: aload_0
      30: areturn

  public com.google.protobuf.UInt32Value$Builder getKeepaliveProbesBuilder();
    Code:
       0: aload_0
       1: invokevirtual #240                // Method onChanged:()V
       4: aload_0
       5: invokespecial #311                // Method getKeepaliveProbesFieldBuilder:()Lcom/google/protobuf/SingleFieldBuilderV3;
       8: invokevirtual #315                // Method com/google/protobuf/SingleFieldBuilderV3.getBuilder:()Lcom/google/protobuf/AbstractMessage$Builder;
      11: checkcast     #10                 // class com/google/protobuf/UInt32Value$Builder
      14: areturn

  public com.google.protobuf.UInt32ValueOrBuilder getKeepaliveProbesOrBuilder();
    Code:
       0: aload_0
       1: getfield      #106                // Field keepaliveProbesBuilder_:Lcom/google/protobuf/SingleFieldBuilderV3;
       4: ifnull        18
       7: aload_0
       8: getfield      #106                // Field keepaliveProbesBuilder_:Lcom/google/protobuf/SingleFieldBuilderV3;
      11: invokevirtual #321                // Method com/google/protobuf/SingleFieldBuilderV3.getMessageOrBuilder:()Lcom/google/protobuf/MessageOrBuilder;
      14: checkcast     #323                // class com/google/protobuf/UInt32ValueOrBuilder
      17: areturn
      18: aload_0
      19: getfield      #108                // Field keepaliveProbes_:Lcom/google/protobuf/UInt32Value;
      22: ifnonnull     31
      25: invokestatic  #278                // Method com/google/protobuf/UInt32Value.getDefaultInstance:()Lcom/google/protobuf/UInt32Value;
      28: goto          35
      31: aload_0
      32: getfield      #108                // Field keepaliveProbes_:Lcom/google/protobuf/UInt32Value;
      35: areturn

  private com.google.protobuf.SingleFieldBuilderV3<com.google.protobuf.UInt32Value, com.google.protobuf.UInt32Value$Builder, com.google.protobuf.UInt32ValueOrBuilder> getKeepaliveProbesFieldBuilder();
    Code:
       0: aload_0
       1: getfield      #106                // Field keepaliveProbesBuilder_:Lcom/google/protobuf/SingleFieldBuilderV3;
       4: ifnonnull     35
       7: aload_0
       8: new           #144                // class com/google/protobuf/SingleFieldBuilderV3
      11: dup
      12: aload_0
      13: invokevirtual #325                // Method getKeepaliveProbes:()Lcom/google/protobuf/UInt32Value;
      16: aload_0
      17: invokevirtual #329                // Method getParentForChildren:()Lcom/google/protobuf/GeneratedMessageV3$BuilderParent;
      20: aload_0
      21: invokevirtual #332                // Method isClean:()Z
      24: invokespecial #335                // Method com/google/protobuf/SingleFieldBuilderV3."<init>":(Lcom/google/protobuf/AbstractMessage;Lcom/google/protobuf/AbstractMessage$BuilderParent;Z)V
      27: putfield      #106                // Field keepaliveProbesBuilder_:Lcom/google/protobuf/SingleFieldBuilderV3;
      30: aload_0
      31: aconst_null
      32: putfield      #108                // Field keepaliveProbes_:Lcom/google/protobuf/UInt32Value;
      35: aload_0
      36: getfield      #106                // Field keepaliveProbesBuilder_:Lcom/google/protobuf/SingleFieldBuilderV3;
      39: areturn

  public boolean hasKeepaliveTime();
    Code:
       0: aload_0
       1: getfield      #110                // Field keepaliveTimeBuilder_:Lcom/google/protobuf/SingleFieldBuilderV3;
       4: ifnonnull     14
       7: aload_0
       8: getfield      #112                // Field keepaliveTime_:Lcom/google/protobuf/UInt32Value;
      11: ifnull        18
      14: iconst_1
      15: goto          19
      18: iconst_0
      19: ireturn

  public com.google.protobuf.UInt32Value getKeepaliveTime();
    Code:
       0: aload_0
       1: getfield      #110                // Field keepaliveTimeBuilder_:Lcom/google/protobuf/SingleFieldBuilderV3;
       4: ifnonnull     25
       7: aload_0
       8: getfield      #112                // Field keepaliveTime_:Lcom/google/protobuf/UInt32Value;
      11: ifnonnull     20
      14: invokestatic  #278                // Method com/google/protobuf/UInt32Value.getDefaultInstance:()Lcom/google/protobuf/UInt32Value;
      17: goto          24
      20: aload_0
      21: getfield      #112                // Field keepaliveTime_:Lcom/google/protobuf/UInt32Value;
      24: areturn
      25: aload_0
      26: getfield      #110                // Field keepaliveTimeBuilder_:Lcom/google/protobuf/SingleFieldBuilderV3;
      29: invokevirtual #281                // Method com/google/protobuf/SingleFieldBuilderV3.getMessage:()Lcom/google/protobuf/AbstractMessage;
      32: checkcast     #12                 // class com/google/protobuf/UInt32Value
      35: areturn

  public io.grpc.xds.shaded.io.envoyproxy.envoy.api.v2.core.TcpKeepalive$Builder setKeepaliveTime(com.google.protobuf.UInt32Value);
    Code:
       0: aload_0
       1: getfield      #110                // Field keepaliveTimeBuilder_:Lcom/google/protobuf/SingleFieldBuilderV3;
       4: ifnonnull     31
       7: aload_1
       8: ifnonnull     19
      11: new           #284                // class java/lang/NullPointerException
      14: dup
      15: invokespecial #285                // Method java/lang/NullPointerException."<init>":()V
      18: athrow
      19: aload_0
      20: aload_1
      21: putfield      #112                // Field keepaliveTime_:Lcom/google/protobuf/UInt32Value;
      24: aload_0
      25: invokevirtual #240                // Method onChanged:()V
      28: goto          40
      31: aload_0
      32: getfield      #110                // Field keepaliveTimeBuilder_:Lcom/google/protobuf/SingleFieldBuilderV3;
      35: aload_1
      36: invokevirtual #289                // Method com/google/protobuf/SingleFieldBuilderV3.setMessage:(Lcom/google/protobuf/AbstractMessage;)Lcom/google/protobuf/SingleFieldBuilderV3;
      39: pop
      40: aload_0
      41: areturn

  public io.grpc.xds.shaded.io.envoyproxy.envoy.api.v2.core.TcpKeepalive$Builder setKeepaliveTime(com.google.protobuf.UInt32Value$Builder);
    Code:
       0: aload_0
       1: getfield      #110                // Field keepaliveTimeBuilder_:Lcom/google/protobuf/SingleFieldBuilderV3;
       4: ifnonnull     22
       7: aload_0
       8: aload_1
       9: invokevirtual #292                // Method com/google/protobuf/UInt32Value$Builder.build:()Lcom/google/protobuf/UInt32Value;
      12: putfield      #112                // Field keepaliveTime_:Lcom/google/protobuf/UInt32Value;
      15: aload_0
      16: invokevirtual #240                // Method onChanged:()V
      19: goto          34
      22: aload_0
      23: getfield      #110                // Field keepaliveTimeBuilder_:Lcom/google/protobuf/SingleFieldBuilderV3;
      26: aload_1
      27: invokevirtual #292                // Method com/google/protobuf/UInt32Value$Builder.build:()Lcom/google/protobuf/UInt32Value;
      30: invokevirtual #289                // Method com/google/protobuf/SingleFieldBuilderV3.setMessage:(Lcom/google/protobuf/AbstractMessage;)Lcom/google/protobuf/SingleFieldBuilderV3;
      33: pop
      34: aload_0
      35: areturn

  public io.grpc.xds.shaded.io.envoyproxy.envoy.api.v2.core.TcpKeepalive$Builder mergeKeepaliveTime(com.google.protobuf.UInt32Value);
    Code:
       0: aload_0
       1: getfield      #110                // Field keepaliveTimeBuilder_:Lcom/google/protobuf/SingleFieldBuilderV3;
       4: ifnonnull     47
       7: aload_0
       8: getfield      #112                // Field keepaliveTime_:Lcom/google/protobuf/UInt32Value;
      11: ifnull        35
      14: aload_0
      15: aload_0
      16: getfield      #112                // Field keepaliveTime_:Lcom/google/protobuf/UInt32Value;
      19: invokestatic  #298                // Method com/google/protobuf/UInt32Value.newBuilder:(Lcom/google/protobuf/UInt32Value;)Lcom/google/protobuf/UInt32Value$Builder;
      22: aload_1
      23: invokevirtual #300                // Method com/google/protobuf/UInt32Value$Builder.mergeFrom:(Lcom/google/protobuf/UInt32Value;)Lcom/google/protobuf/UInt32Value$Builder;
      26: invokevirtual #302                // Method com/google/protobuf/UInt32Value$Builder.buildPartial:()Lcom/google/protobuf/UInt32Value;
      29: putfield      #112                // Field keepaliveTime_:Lcom/google/protobuf/UInt32Value;
      32: goto          40
      35: aload_0
      36: aload_1
      37: putfield      #112                // Field keepaliveTime_:Lcom/google/protobuf/UInt32Value;
      40: aload_0
      41: invokevirtual #240                // Method onChanged:()V
      44: goto          56
      47: aload_0
      48: getfield      #110                // Field keepaliveTimeBuilder_:Lcom/google/protobuf/SingleFieldBuilderV3;
      51: aload_1
      52: invokevirtual #304                // Method com/google/protobuf/SingleFieldBuilderV3.mergeFrom:(Lcom/google/protobuf/AbstractMessage;)Lcom/google/protobuf/SingleFieldBuilderV3;
      55: pop
      56: aload_0
      57: areturn

  public io.grpc.xds.shaded.io.envoyproxy.envoy.api.v2.core.TcpKeepalive$Builder clearKeepaliveTime();
    Code:
       0: aload_0
       1: getfield      #110                // Field keepaliveTimeBuilder_:Lcom/google/protobuf/SingleFieldBuilderV3;
       4: ifnonnull     19
       7: aload_0
       8: aconst_null
       9: putfield      #112                // Field keepaliveTime_:Lcom/google/protobuf/UInt32Value;
      12: aload_0
      13: invokevirtual #240                // Method onChanged:()V
      16: goto          29
      19: aload_0
      20: aconst_null
      21: putfield      #112                // Field keepaliveTime_:Lcom/google/protobuf/UInt32Value;
      24: aload_0
      25: aconst_null
      26: putfield      #110                // Field keepaliveTimeBuilder_:Lcom/google/protobuf/SingleFieldBuilderV3;
      29: aload_0
      30: areturn

  public com.google.protobuf.UInt32Value$Builder getKeepaliveTimeBuilder();
    Code:
       0: aload_0
       1: invokevirtual #240                // Method onChanged:()V
       4: aload_0
       5: invokespecial #341                // Method getKeepaliveTimeFieldBuilder:()Lcom/google/protobuf/SingleFieldBuilderV3;
       8: invokevirtual #315                // Method com/google/protobuf/SingleFieldBuilderV3.getBuilder:()Lcom/google/protobuf/AbstractMessage$Builder;
      11: checkcast     #10                 // class com/google/protobuf/UInt32Value$Builder
      14: areturn

  public com.google.protobuf.UInt32ValueOrBuilder getKeepaliveTimeOrBuilder();
    Code:
       0: aload_0
       1: getfield      #110                // Field keepaliveTimeBuilder_:Lcom/google/protobuf/SingleFieldBuilderV3;
       4: ifnull        18
       7: aload_0
       8: getfield      #110                // Field keepaliveTimeBuilder_:Lcom/google/protobuf/SingleFieldBuilderV3;
      11: invokevirtual #321                // Method com/google/protobuf/SingleFieldBuilderV3.getMessageOrBuilder:()Lcom/google/protobuf/MessageOrBuilder;
      14: checkcast     #323                // class com/google/protobuf/UInt32ValueOrBuilder
      17: areturn
      18: aload_0
      19: getfield      #112                // Field keepaliveTime_:Lcom/google/protobuf/UInt32Value;
      22: ifnonnull     31
      25: invokestatic  #278                // Method com/google/protobuf/UInt32Value.getDefaultInstance:()Lcom/google/protobuf/UInt32Value;
      28: goto          35
      31: aload_0
      32: getfield      #112                // Field keepaliveTime_:Lcom/google/protobuf/UInt32Value;
      35: areturn

  private com.google.protobuf.SingleFieldBuilderV3<com.google.protobuf.UInt32Value, com.google.protobuf.UInt32Value$Builder, com.google.protobuf.UInt32ValueOrBuilder> getKeepaliveTimeFieldBuilder();
    Code:
       0: aload_0
       1: getfield      #110                // Field keepaliveTimeBuilder_:Lcom/google/protobuf/SingleFieldBuilderV3;
       4: ifnonnull     35
       7: aload_0
       8: new           #144                // class com/google/protobuf/SingleFieldBuilderV3
      11: dup
      12: aload_0
      13: invokevirtual #343                // Method getKeepaliveTime:()Lcom/google/protobuf/UInt32Value;
      16: aload_0
      17: invokevirtual #329                // Method getParentForChildren:()Lcom/google/protobuf/GeneratedMessageV3$BuilderParent;
      20: aload_0
      21: invokevirtual #332                // Method isClean:()Z
      24: invokespecial #335                // Method com/google/protobuf/SingleFieldBuilderV3."<init>":(Lcom/google/protobuf/AbstractMessage;Lcom/google/protobuf/AbstractMessage$BuilderParent;Z)V
      27: putfield      #110                // Field keepaliveTimeBuilder_:Lcom/google/protobuf/SingleFieldBuilderV3;
      30: aload_0
      31: aconst_null
      32: putfield      #112                // Field keepaliveTime_:Lcom/google/protobuf/UInt32Value;
      35: aload_0
      36: getfield      #110                // Field keepaliveTimeBuilder_:Lcom/google/protobuf/SingleFieldBuilderV3;
      39: areturn

  public boolean hasKeepaliveInterval();
    Code:
       0: aload_0
       1: getfield      #114                // Field keepaliveIntervalBuilder_:Lcom/google/protobuf/SingleFieldBuilderV3;
       4: ifnonnull     14
       7: aload_0
       8: getfield      #116                // Field keepaliveInterval_:Lcom/google/protobuf/UInt32Value;
      11: ifnull        18
      14: iconst_1
      15: goto          19
      18: iconst_0
      19: ireturn

  public com.google.protobuf.UInt32Value getKeepaliveInterval();
    Code:
       0: aload_0
       1: getfield      #114                // Field keepaliveIntervalBuilder_:Lcom/google/protobuf/SingleFieldBuilderV3;
       4: ifnonnull     25
       7: aload_0
       8: getfield      #116                // Field keepaliveInterval_:Lcom/google/protobuf/UInt32Value;
      11: ifnonnull     20
      14: invokestatic  #278                // Method com/google/protobuf/UInt32Value.getDefaultInstance:()Lcom/google/protobuf/UInt32Value;
      17: goto          24
      20: aload_0
      21: getfield      #116                // Field keepaliveInterval_:Lcom/google/protobuf/UInt32Value;
      24: areturn
      25: aload_0
      26: getfield      #114                // Field keepaliveIntervalBuilder_:Lcom/google/protobuf/SingleFieldBuilderV3;
      29: invokevirtual #281                // Method com/google/protobuf/SingleFieldBuilderV3.getMessage:()Lcom/google/protobuf/AbstractMessage;
      32: checkcast     #12                 // class com/google/protobuf/UInt32Value
      35: areturn

  public io.grpc.xds.shaded.io.envoyproxy.envoy.api.v2.core.TcpKeepalive$Builder setKeepaliveInterval(com.google.protobuf.UInt32Value);
    Code:
       0: aload_0
       1: getfield      #114                // Field keepaliveIntervalBuilder_:Lcom/google/protobuf/SingleFieldBuilderV3;
       4: ifnonnull     31
       7: aload_1
       8: ifnonnull     19
      11: new           #284                // class java/lang/NullPointerException
      14: dup
      15: invokespecial #285                // Method java/lang/NullPointerException."<init>":()V
      18: athrow
      19: aload_0
      20: aload_1
      21: putfield      #116                // Field keepaliveInterval_:Lcom/google/protobuf/UInt32Value;
      24: aload_0
      25: invokevirtual #240                // Method onChanged:()V
      28: goto          40
      31: aload_0
      32: getfield      #114                // Field keepaliveIntervalBuilder_:Lcom/google/protobuf/SingleFieldBuilderV3;
      35: aload_1
      36: invokevirtual #289                // Method com/google/protobuf/SingleFieldBuilderV3.setMessage:(Lcom/google/protobuf/AbstractMessage;)Lcom/google/protobuf/SingleFieldBuilderV3;
      39: pop
      40: aload_0
      41: areturn

  public io.grpc.xds.shaded.io.envoyproxy.envoy.api.v2.core.TcpKeepalive$Builder setKeepaliveInterval(com.google.protobuf.UInt32Value$Builder);
    Code:
       0: aload_0
       1: getfield      #114                // Field keepaliveIntervalBuilder_:Lcom/google/protobuf/SingleFieldBuilderV3;
       4: ifnonnull     22
       7: aload_0
       8: aload_1
       9: invokevirtual #292                // Method com/google/protobuf/UInt32Value$Builder.build:()Lcom/google/protobuf/UInt32Value;
      12: putfield      #116                // Field keepaliveInterval_:Lcom/google/protobuf/UInt32Value;
      15: aload_0
      16: invokevirtual #240                // Method onChanged:()V
      19: goto          34
      22: aload_0
      23: getfield      #114                // Field keepaliveIntervalBuilder_:Lcom/google/protobuf/SingleFieldBuilderV3;
      26: aload_1
      27: invokevirtual #292                // Method com/google/protobuf/UInt32Value$Builder.build:()Lcom/google/protobuf/UInt32Value;
      30: invokevirtual #289                // Method com/google/protobuf/SingleFieldBuilderV3.setMessage:(Lcom/google/protobuf/AbstractMessage;)Lcom/google/protobuf/SingleFieldBuilderV3;
      33: pop
      34: aload_0
      35: areturn

  public io.grpc.xds.shaded.io.envoyproxy.envoy.api.v2.core.TcpKeepalive$Builder mergeKeepaliveInterval(com.google.protobuf.UInt32Value);
    Code:
       0: aload_0
       1: getfield      #114                // Field keepaliveIntervalBuilder_:Lcom/google/protobuf/SingleFieldBuilderV3;
       4: ifnonnull     47
       7: aload_0
       8: getfield      #116                // Field keepaliveInterval_:Lcom/google/protobuf/UInt32Value;
      11: ifnull        35
      14: aload_0
      15: aload_0
      16: getfield      #116                // Field keepaliveInterval_:Lcom/google/protobuf/UInt32Value;
      19: invokestatic  #298                // Method com/google/protobuf/UInt32Value.newBuilder:(Lcom/google/protobuf/UInt32Value;)Lcom/google/protobuf/UInt32Value$Builder;
      22: aload_1
      23: invokevirtual #300                // Method com/google/protobuf/UInt32Value$Builder.mergeFrom:(Lcom/google/protobuf/UInt32Value;)Lcom/google/protobuf/UInt32Value$Builder;
      26: invokevirtual #302                // Method com/google/protobuf/UInt32Value$Builder.buildPartial:()Lcom/google/protobuf/UInt32Value;
      29: putfield      #116                // Field keepaliveInterval_:Lcom/google/protobuf/UInt32Value;
      32: goto          40
      35: aload_0
      36: aload_1
      37: putfield      #116                // Field keepaliveInterval_:Lcom/google/protobuf/UInt32Value;
      40: aload_0
      41: invokevirtual #240                // Method onChanged:()V
      44: goto          56
      47: aload_0
      48: getfield      #114                // Field keepaliveIntervalBuilder_:Lcom/google/protobuf/SingleFieldBuilderV3;
      51: aload_1
      52: invokevirtual #304                // Method com/google/protobuf/SingleFieldBuilderV3.mergeFrom:(Lcom/google/protobuf/AbstractMessage;)Lcom/google/protobuf/SingleFieldBuilderV3;
      55: pop
      56: aload_0
      57: areturn

  public io.grpc.xds.shaded.io.envoyproxy.envoy.api.v2.core.TcpKeepalive$Builder clearKeepaliveInterval();
    Code:
       0: aload_0
       1: getfield      #114                // Field keepaliveIntervalBuilder_:Lcom/google/protobuf/SingleFieldBuilderV3;
       4: ifnonnull     19
       7: aload_0
       8: aconst_null
       9: putfield      #116                // Field keepaliveInterval_:Lcom/google/protobuf/UInt32Value;
      12: aload_0
      13: invokevirtual #240                // Method onChanged:()V
      16: goto          29
      19: aload_0
      20: aconst_null
      21: putfield      #116                // Field keepaliveInterval_:Lcom/google/protobuf/UInt32Value;
      24: aload_0
      25: aconst_null
      26: putfield      #114                // Field keepaliveIntervalBuilder_:Lcom/google/protobuf/SingleFieldBuilderV3;
      29: aload_0
      30: areturn

  public com.google.protobuf.UInt32Value$Builder getKeepaliveIntervalBuilder();
    Code:
       0: aload_0
       1: invokevirtual #240                // Method onChanged:()V
       4: aload_0
       5: invokespecial #349                // Method getKeepaliveIntervalFieldBuilder:()Lcom/google/protobuf/SingleFieldBuilderV3;
       8: invokevirtual #315                // Method com/google/protobuf/SingleFieldBuilderV3.getBuilder:()Lcom/google/protobuf/AbstractMessage$Builder;
      11: checkcast     #10                 // class com/google/protobuf/UInt32Value$Builder
      14: areturn

  public com.google.protobuf.UInt32ValueOrBuilder getKeepaliveIntervalOrBuilder();
    Code:
       0: aload_0
       1: getfield      #114                // Field keepaliveIntervalBuilder_:Lcom/google/protobuf/SingleFieldBuilderV3;
       4: ifnull        18
       7: aload_0
       8: getfield      #114                // Field keepaliveIntervalBuilder_:Lcom/google/protobuf/SingleFieldBuilderV3;
      11: invokevirtual #321                // Method com/google/protobuf/SingleFieldBuilderV3.getMessageOrBuilder:()Lcom/google/protobuf/MessageOrBuilder;
      14: checkcast     #323                // class com/google/protobuf/UInt32ValueOrBuilder
      17: areturn
      18: aload_0
      19: getfield      #116                // Field keepaliveInterval_:Lcom/google/protobuf/UInt32Value;
      22: ifnonnull     31
      25: invokestatic  #278                // Method com/google/protobuf/UInt32Value.getDefaultInstance:()Lcom/google/protobuf/UInt32Value;
      28: goto          35
      31: aload_0
      32: getfield      #116                // Field keepaliveInterval_:Lcom/google/protobuf/UInt32Value;
      35: areturn

  private com.google.protobuf.SingleFieldBuilderV3<com.google.protobuf.UInt32Value, com.google.protobuf.UInt32Value$Builder, com.google.protobuf.UInt32ValueOrBuilder> getKeepaliveIntervalFieldBuilder();
    Code:
       0: aload_0
       1: getfield      #114                // Field keepaliveIntervalBuilder_:Lcom/google/protobuf/SingleFieldBuilderV3;
       4: ifnonnull     35
       7: aload_0
       8: new           #144                // class com/google/protobuf/SingleFieldBuilderV3
      11: dup
      12: aload_0
      13: invokevirtual #351                // Method getKeepaliveInterval:()Lcom/google/protobuf/UInt32Value;
      16: aload_0
      17: invokevirtual #329                // Method getParentForChildren:()Lcom/google/protobuf/GeneratedMessageV3$BuilderParent;
      20: aload_0
      21: invokevirtual #332                // Method isClean:()Z
      24: invokespecial #335                // Method com/google/protobuf/SingleFieldBuilderV3."<init>":(Lcom/google/protobuf/AbstractMessage;Lcom/google/protobuf/AbstractMessage$BuilderParent;Z)V
      27: putfield      #114                // Field keepaliveIntervalBuilder_:Lcom/google/protobuf/SingleFieldBuilderV3;
      30: aload_0
      31: aconst_null
      32: putfield      #116                // Field keepaliveInterval_:Lcom/google/protobuf/UInt32Value;
      35: aload_0
      36: getfield      #114                // Field keepaliveIntervalBuilder_:Lcom/google/protobuf/SingleFieldBuilderV3;
      39: areturn

  public final io.grpc.xds.shaded.io.envoyproxy.envoy.api.v2.core.TcpKeepalive$Builder setUnknownFields(com.google.protobuf.UnknownFieldSet);
    Code:
       0: aload_0
       1: aload_1
       2: invokespecial #355                // Method com/google/protobuf/GeneratedMessageV3$Builder.setUnknownFields:(Lcom/google/protobuf/UnknownFieldSet;)Lcom/google/protobuf/GeneratedMessageV3$Builder;
       5: checkcast     #2                  // class io/grpc/xds/shaded/io/envoyproxy/envoy/api/v2/core/TcpKeepalive$Builder
       8: areturn

  public final io.grpc.xds.shaded.io.envoyproxy.envoy.api.v2.core.TcpKeepalive$Builder mergeUnknownFields(com.google.protobuf.UnknownFieldSet);
    Code:
       0: aload_0
       1: aload_1
       2: invokespecial #359                // Method com/google/protobuf/GeneratedMessageV3$Builder.mergeUnknownFields:(Lcom/google/protobuf/UnknownFieldSet;)Lcom/google/protobuf/GeneratedMessageV3$Builder;
       5: checkcast     #2                  // class io/grpc/xds/shaded/io/envoyproxy/envoy/api/v2/core/TcpKeepalive$Builder
       8: areturn

  public com.google.protobuf.GeneratedMessageV3$Builder mergeUnknownFields(com.google.protobuf.UnknownFieldSet);
    Code:
       0: aload_0
       1: aload_1
       2: invokevirtual #237                // Method mergeUnknownFields:(Lcom/google/protobuf/UnknownFieldSet;)Lio/grpc/xds/shaded/io/envoyproxy/envoy/api/v2/core/TcpKeepalive$Builder;
       5: areturn

  public com.google.protobuf.GeneratedMessageV3$Builder setUnknownFields(com.google.protobuf.UnknownFieldSet);
    Code:
       0: aload_0
       1: aload_1
       2: invokevirtual #361                // Method setUnknownFields:(Lcom/google/protobuf/UnknownFieldSet;)Lio/grpc/xds/shaded/io/envoyproxy/envoy/api/v2/core/TcpKeepalive$Builder;
       5: areturn

  public com.google.protobuf.GeneratedMessageV3$Builder addRepeatedField(com.google.protobuf.Descriptors$FieldDescriptor, java.lang.Object);
    Code:
       0: aload_0
       1: aload_1
       2: aload_2
       3: invokevirtual #363                // Method addRepeatedField:(Lcom/google/protobuf/Descriptors$FieldDescriptor;Ljava/lang/Object;)Lio/grpc/xds/shaded/io/envoyproxy/envoy/api/v2/core/TcpKeepalive$Builder;
       6: areturn

  public com.google.protobuf.GeneratedMessageV3$Builder setRepeatedField(com.google.protobuf.Descriptors$FieldDescriptor, int, java.lang.Object);
    Code:
       0: aload_0
       1: aload_1
       2: iload_2
       3: aload_3
       4: invokevirtual #365                // Method setRepeatedField:(Lcom/google/protobuf/Descriptors$FieldDescriptor;ILjava/lang/Object;)Lio/grpc/xds/shaded/io/envoyproxy/envoy/api/v2/core/TcpKeepalive$Builder;
       7: areturn

  public com.google.protobuf.GeneratedMessageV3$Builder clearOneof(com.google.protobuf.Descriptors$OneofDescriptor);
    Code:
       0: aload_0
       1: aload_1
       2: invokevirtual #367                // Method clearOneof:(Lcom/google/protobuf/Descriptors$OneofDescriptor;)Lio/grpc/xds/shaded/io/envoyproxy/envoy/api/v2/core/TcpKeepalive$Builder;
       5: areturn

  public com.google.protobuf.GeneratedMessageV3$Builder clearField(com.google.protobuf.Descriptors$FieldDescriptor);
    Code:
       0: aload_0
       1: aload_1
       2: invokevirtual #369                // Method clearField:(Lcom/google/protobuf/Descriptors$FieldDescriptor;)Lio/grpc/xds/shaded/io/envoyproxy/envoy/api/v2/core/TcpKeepalive$Builder;
       5: areturn

  public com.google.protobuf.GeneratedMessageV3$Builder setField(com.google.protobuf.Descriptors$FieldDescriptor, java.lang.Object);
    Code:
       0: aload_0
       1: aload_1
       2: aload_2
       3: invokevirtual #371                // Method setField:(Lcom/google/protobuf/Descriptors$FieldDescriptor;Ljava/lang/Object;)Lio/grpc/xds/shaded/io/envoyproxy/envoy/api/v2/core/TcpKeepalive$Builder;
       6: areturn

  public com.google.protobuf.GeneratedMessageV3$Builder clear();
    Code:
       0: aload_0
       1: invokevirtual #373                // Method clear:()Lio/grpc/xds/shaded/io/envoyproxy/envoy/api/v2/core/TcpKeepalive$Builder;
       4: areturn

  public com.google.protobuf.GeneratedMessageV3$Builder clone();
    Code:
       0: aload_0
       1: invokevirtual #375                // Method clone:()Lio/grpc/xds/shaded/io/envoyproxy/envoy/api/v2/core/TcpKeepalive$Builder;
       4: areturn

  public com.google.protobuf.AbstractMessage$Builder mergeUnknownFields(com.google.protobuf.UnknownFieldSet);
    Code:
       0: aload_0
       1: aload_1
       2: invokevirtual #237                // Method mergeUnknownFields:(Lcom/google/protobuf/UnknownFieldSet;)Lio/grpc/xds/shaded/io/envoyproxy/envoy/api/v2/core/TcpKeepalive$Builder;
       5: areturn

  public com.google.protobuf.AbstractMessage$Builder mergeFrom(com.google.protobuf.CodedInputStream, com.google.protobuf.ExtensionRegistryLite) throws java.io.IOException;
    Code:
       0: aload_0
       1: aload_1
       2: aload_2
       3: invokevirtual #379                // Method mergeFrom:(Lcom/google/protobuf/CodedInputStream;Lcom/google/protobuf/ExtensionRegistryLite;)Lio/grpc/xds/shaded/io/envoyproxy/envoy/api/v2/core/TcpKeepalive$Builder;
       6: areturn

  public com.google.protobuf.AbstractMessage$Builder mergeFrom(com.google.protobuf.Message);
    Code:
       0: aload_0
       1: aload_1
       2: invokevirtual #381                // Method mergeFrom:(Lcom/google/protobuf/Message;)Lio/grpc/xds/shaded/io/envoyproxy/envoy/api/v2/core/TcpKeepalive$Builder;
       5: areturn

  public com.google.protobuf.AbstractMessage$Builder clear();
    Code:
       0: aload_0
       1: invokevirtual #373                // Method clear:()Lio/grpc/xds/shaded/io/envoyproxy/envoy/api/v2/core/TcpKeepalive$Builder;
       4: areturn

  public com.google.protobuf.AbstractMessage$Builder clearOneof(com.google.protobuf.Descriptors$OneofDescriptor);
    Code:
       0: aload_0
       1: aload_1
       2: invokevirtual #367                // Method clearOneof:(Lcom/google/protobuf/Descriptors$OneofDescriptor;)Lio/grpc/xds/shaded/io/envoyproxy/envoy/api/v2/core/TcpKeepalive$Builder;
       5: areturn

  public com.google.protobuf.AbstractMessage$Builder clone();
    Code:
       0: aload_0
       1: invokevirtual #375                // Method clone:()Lio/grpc/xds/shaded/io/envoyproxy/envoy/api/v2/core/TcpKeepalive$Builder;
       4: areturn

  public com.google.protobuf.Message$Builder mergeUnknownFields(com.google.protobuf.UnknownFieldSet);
    Code:
       0: aload_0
       1: aload_1
       2: invokevirtual #237                // Method mergeUnknownFields:(Lcom/google/protobuf/UnknownFieldSet;)Lio/grpc/xds/shaded/io/envoyproxy/envoy/api/v2/core/TcpKeepalive$Builder;
       5: areturn

  public com.google.protobuf.Message$Builder setUnknownFields(com.google.protobuf.UnknownFieldSet);
    Code:
       0: aload_0
       1: aload_1
       2: invokevirtual #361                // Method setUnknownFields:(Lcom/google/protobuf/UnknownFieldSet;)Lio/grpc/xds/shaded/io/envoyproxy/envoy/api/v2/core/TcpKeepalive$Builder;
       5: areturn

  public com.google.protobuf.Message$Builder addRepeatedField(com.google.protobuf.Descriptors$FieldDescriptor, java.lang.Object);
    Code:
       0: aload_0
       1: aload_1
       2: aload_2
       3: invokevirtual #363                // Method addRepeatedField:(Lcom/google/protobuf/Descriptors$FieldDescriptor;Ljava/lang/Object;)Lio/grpc/xds/shaded/io/envoyproxy/envoy/api/v2/core/TcpKeepalive$Builder;
       6: areturn

  public com.google.protobuf.Message$Builder setRepeatedField(com.google.protobuf.Descriptors$FieldDescriptor, int, java.lang.Object);
    Code:
       0: aload_0
       1: aload_1
       2: iload_2
       3: aload_3
       4: invokevirtual #365                // Method setRepeatedField:(Lcom/google/protobuf/Descriptors$FieldDescriptor;ILjava/lang/Object;)Lio/grpc/xds/shaded/io/envoyproxy/envoy/api/v2/core/TcpKeepalive$Builder;
       7: areturn

  public com.google.protobuf.Message$Builder clearOneof(com.google.protobuf.Descriptors$OneofDescriptor);
    Code:
       0: aload_0
       1: aload_1
       2: invokevirtual #367                // Method clearOneof:(Lcom/google/protobuf/Descriptors$OneofDescriptor;)Lio/grpc/xds/shaded/io/envoyproxy/envoy/api/v2/core/TcpKeepalive$Builder;
       5: areturn

  public com.google.protobuf.Message$Builder clearField(com.google.protobuf.Descriptors$FieldDescriptor);
    Code:
       0: aload_0
       1: aload_1
       2: invokevirtual #369                // Method clearField:(Lcom/google/protobuf/Descriptors$FieldDescriptor;)Lio/grpc/xds/shaded/io/envoyproxy/envoy/api/v2/core/TcpKeepalive$Builder;
       5: areturn

  public com.google.protobuf.Message$Builder setField(com.google.protobuf.Descriptors$FieldDescriptor, java.lang.Object);
    Code:
       0: aload_0
       1: aload_1
       2: aload_2
       3: invokevirtual #371                // Method setField:(Lcom/google/protobuf/Descriptors$FieldDescriptor;Ljava/lang/Object;)Lio/grpc/xds/shaded/io/envoyproxy/envoy/api/v2/core/TcpKeepalive$Builder;
       6: areturn

  public com.google.protobuf.Message$Builder mergeFrom(com.google.protobuf.CodedInputStream, com.google.protobuf.ExtensionRegistryLite) throws java.io.IOException;
    Code:
       0: aload_0
       1: aload_1
       2: aload_2
       3: invokevirtual #379                // Method mergeFrom:(Lcom/google/protobuf/CodedInputStream;Lcom/google/protobuf/ExtensionRegistryLite;)Lio/grpc/xds/shaded/io/envoyproxy/envoy/api/v2/core/TcpKeepalive$Builder;
       6: areturn

  public com.google.protobuf.Message$Builder clone();
    Code:
       0: aload_0
       1: invokevirtual #375                // Method clone:()Lio/grpc/xds/shaded/io/envoyproxy/envoy/api/v2/core/TcpKeepalive$Builder;
       4: areturn

  public com.google.protobuf.Message buildPartial();
    Code:
       0: aload_0
       1: invokevirtual #126                // Method buildPartial:()Lio/grpc/xds/shaded/io/envoyproxy/envoy/api/v2/core/TcpKeepalive;
       4: areturn

  public com.google.protobuf.Message build();
    Code:
       0: aload_0
       1: invokevirtual #392                // Method build:()Lio/grpc/xds/shaded/io/envoyproxy/envoy/api/v2/core/TcpKeepalive;
       4: areturn

  public com.google.protobuf.Message$Builder mergeFrom(com.google.protobuf.Message);
    Code:
       0: aload_0
       1: aload_1
       2: invokevirtual #381                // Method mergeFrom:(Lcom/google/protobuf/Message;)Lio/grpc/xds/shaded/io/envoyproxy/envoy/api/v2/core/TcpKeepalive$Builder;
       5: areturn

  public com.google.protobuf.Message$Builder clear();
    Code:
       0: aload_0
       1: invokevirtual #373                // Method clear:()Lio/grpc/xds/shaded/io/envoyproxy/envoy/api/v2/core/TcpKeepalive$Builder;
       4: areturn

  public com.google.protobuf.MessageLite$Builder mergeFrom(com.google.protobuf.CodedInputStream, com.google.protobuf.ExtensionRegistryLite) throws java.io.IOException;
    Code:
       0: aload_0
       1: aload_1
       2: aload_2
       3: invokevirtual #379                // Method mergeFrom:(Lcom/google/protobuf/CodedInputStream;Lcom/google/protobuf/ExtensionRegistryLite;)Lio/grpc/xds/shaded/io/envoyproxy/envoy/api/v2/core/TcpKeepalive$Builder;
       6: areturn

  public com.google.protobuf.MessageLite$Builder clone();
    Code:
       0: aload_0
       1: invokevirtual #375                // Method clone:()Lio/grpc/xds/shaded/io/envoyproxy/envoy/api/v2/core/TcpKeepalive$Builder;
       4: areturn

  public com.google.protobuf.MessageLite buildPartial();
    Code:
       0: aload_0
       1: invokevirtual #126                // Method buildPartial:()Lio/grpc/xds/shaded/io/envoyproxy/envoy/api/v2/core/TcpKeepalive;
       4: areturn

  public com.google.protobuf.MessageLite build();
    Code:
       0: aload_0
       1: invokevirtual #392                // Method build:()Lio/grpc/xds/shaded/io/envoyproxy/envoy/api/v2/core/TcpKeepalive;
       4: areturn

  public com.google.protobuf.MessageLite$Builder clear();
    Code:
       0: aload_0
       1: invokevirtual #373                // Method clear:()Lio/grpc/xds/shaded/io/envoyproxy/envoy/api/v2/core/TcpKeepalive$Builder;
       4: areturn

  public com.google.protobuf.MessageLite getDefaultInstanceForType();
    Code:
       0: aload_0
       1: invokevirtual #397                // Method getDefaultInstanceForType:()Lio/grpc/xds/shaded/io/envoyproxy/envoy/api/v2/core/TcpKeepalive;
       4: areturn

  public com.google.protobuf.Message getDefaultInstanceForType();
    Code:
       0: aload_0
       1: invokevirtual #397                // Method getDefaultInstanceForType:()Lio/grpc/xds/shaded/io/envoyproxy/envoy/api/v2/core/TcpKeepalive;
       4: areturn

  public com.google.protobuf.AbstractMessageLite$Builder mergeFrom(com.google.protobuf.CodedInputStream, com.google.protobuf.ExtensionRegistryLite) throws java.io.IOException;
    Code:
       0: aload_0
       1: aload_1
       2: aload_2
       3: invokevirtual #379                // Method mergeFrom:(Lcom/google/protobuf/CodedInputStream;Lcom/google/protobuf/ExtensionRegistryLite;)Lio/grpc/xds/shaded/io/envoyproxy/envoy/api/v2/core/TcpKeepalive$Builder;
       6: areturn

  public com.google.protobuf.AbstractMessageLite$Builder clone();
    Code:
       0: aload_0
       1: invokevirtual #375                // Method clone:()Lio/grpc/xds/shaded/io/envoyproxy/envoy/api/v2/core/TcpKeepalive$Builder;
       4: areturn

  public java.lang.Object clone() throws java.lang.CloneNotSupportedException;
    Code:
       0: aload_0
       1: invokevirtual #375                // Method clone:()Lio/grpc/xds/shaded/io/envoyproxy/envoy/api/v2/core/TcpKeepalive$Builder;
       4: areturn

  io.grpc.xds.shaded.io.envoyproxy.envoy.api.v2.core.TcpKeepalive$Builder(io.grpc.xds.shaded.io.envoyproxy.envoy.api.v2.core.TcpKeepalive$1);
    Code:
       0: aload_0
       1: invokespecial #404                // Method "<init>":()V
       4: return

  io.grpc.xds.shaded.io.envoyproxy.envoy.api.v2.core.TcpKeepalive$Builder(com.google.protobuf.GeneratedMessageV3$BuilderParent, io.grpc.xds.shaded.io.envoyproxy.envoy.api.v2.core.TcpKeepalive$1);
    Code:
       0: aload_0
       1: aload_1
       2: invokespecial #408                // Method "<init>":(Lcom/google/protobuf/GeneratedMessageV3$BuilderParent;)V
       5: return
}
