Compiled from "ActorComponent.scala"
public class akka.camel.internal.component.ActorEndpoint extends org.apache.camel.impl.DefaultEndpoint implements akka.camel.internal.component.ActorEndpointConfig {
  private final akka.camel.internal.component.ActorEndpointPath path;

  private final akka.camel.Camel camel;

  private scala.concurrent.duration.FiniteDuration replyTimeout;

  private boolean autoAck;

  public scala.concurrent.duration.FiniteDuration replyTimeout();
    Code:
       0: aload_0
       1: getfield      #21                 // Field replyTimeout:Lscala/concurrent/duration/FiniteDuration;
       4: areturn

  public void replyTimeout_$eq(scala.concurrent.duration.FiniteDuration);
    Code:
       0: aload_0
       1: aload_1
       2: putfield      #21                 // Field replyTimeout:Lscala/concurrent/duration/FiniteDuration;
       5: return

  public boolean autoAck();
    Code:
       0: aload_0
       1: getfield      #29                 // Field autoAck:Z
       4: ireturn

  public void autoAck_$eq(boolean);
    Code:
       0: aload_0
       1: iload_1
       2: putfield      #29                 // Field autoAck:Z
       5: return

  public scala.concurrent.duration.FiniteDuration getReplyTimeout();
    Code:
       0: aload_0
       1: invokestatic  #37                 // Method akka/camel/internal/component/ActorEndpointConfig$class.getReplyTimeout:(Lakka/camel/internal/component/ActorEndpointConfig;)Lscala/concurrent/duration/FiniteDuration;
       4: areturn

  public void setReplyTimeout(scala.concurrent.duration.FiniteDuration);
    Code:
       0: aload_0
       1: aload_1
       2: invokestatic  #41                 // Method akka/camel/internal/component/ActorEndpointConfig$class.setReplyTimeout:(Lakka/camel/internal/component/ActorEndpointConfig;Lscala/concurrent/duration/FiniteDuration;)V
       5: return

  public boolean getAutoAck();
    Code:
       0: aload_0
       1: invokestatic  #45                 // Method akka/camel/internal/component/ActorEndpointConfig$class.getAutoAck:(Lakka/camel/internal/component/ActorEndpointConfig;)Z
       4: ireturn

  public void setAutoAck(boolean);
    Code:
       0: aload_0
       1: iload_1
       2: invokestatic  #49                 // Method akka/camel/internal/component/ActorEndpointConfig$class.setAutoAck:(Lakka/camel/internal/component/ActorEndpointConfig;Z)V
       5: return

  public akka.camel.internal.component.ActorEndpointPath path();
    Code:
       0: aload_0
       1: getfield      #52                 // Field path:Lakka/camel/internal/component/ActorEndpointPath;
       4: areturn

  public akka.camel.Camel camel();
    Code:
       0: aload_0
       1: getfield      #55                 // Field camel:Lakka/camel/Camel;
       4: areturn

  public org.apache.camel.Consumer createConsumer(org.apache.camel.Processor);
    Code:
       0: new           #59                 // class java/lang/UnsupportedOperationException
       3: dup
       4: ldc           #61                 // String actor consumer not supported yet
       6: invokespecial #65                 // Method java/lang/UnsupportedOperationException."<init>":(Ljava/lang/String;)V
       9: athrow

  public akka.camel.internal.component.ActorProducer createProducer();
    Code:
       0: new           #71                 // class akka/camel/internal/component/ActorProducer
       3: dup
       4: aload_0
       5: aload_0
       6: invokevirtual #73                 // Method camel:()Lakka/camel/Camel;
       9: invokespecial #76                 // Method akka/camel/internal/component/ActorProducer."<init>":(Lakka/camel/internal/component/ActorEndpoint;Lakka/camel/Camel;)V
      12: areturn

  public boolean isSingleton();
    Code:
       0: iconst_1
       1: ireturn

  public org.apache.camel.Producer createProducer();
    Code:
       0: aload_0
       1: invokevirtual #80                 // Method createProducer:()Lakka/camel/internal/component/ActorProducer;
       4: areturn

  public akka.camel.internal.component.ActorEndpoint(java.lang.String, akka.camel.internal.component.ActorComponent, akka.camel.internal.component.ActorEndpointPath, akka.camel.Camel);
    Code:
       0: aload_0
       1: aload_3
       2: putfield      #52                 // Field path:Lakka/camel/internal/component/ActorEndpointPath;
       5: aload_0
       6: aload         4
       8: putfield      #55                 // Field camel:Lakka/camel/Camel;
      11: aload_0
      12: aload_1
      13: aload_2
      14: invokespecial #84                 // Method org/apache/camel/impl/DefaultEndpoint."<init>":(Ljava/lang/String;Lorg/apache/camel/Component;)V
      17: aload_0
      18: invokestatic  #88                 // Method akka/camel/internal/component/ActorEndpointConfig$class.$init$:(Lakka/camel/internal/component/ActorEndpointConfig;)V
      21: return
}
