Compiled from "CorsBeanDefinitionParser.java"
public class org.springframework.security.config.http.CorsBeanDefinitionParser {
  private static final java.lang.String HANDLER_MAPPING_INTROSPECTOR;

  private static final java.lang.String ATT_SOURCE;

  private static final java.lang.String ATT_REF;

  public org.springframework.security.config.http.CorsBeanDefinitionParser();
    Code:
       0: aload_0
       1: invokespecial #1                  // Method java/lang/Object."<init>":()V
       4: return

  public org.springframework.beans.BeanMetadataElement parse(org.w3c.dom.Element, org.springframework.beans.factory.xml.ParserContext);
    Code:
       0: aload_1
       1: ifnonnull     6
       4: aconst_null
       5: areturn
       6: aload_1
       7: ldc           #3                  // String ref
       9: invokeinterface #4,  2            // InterfaceMethod org/w3c/dom/Element.getAttribute:(Ljava/lang/String;)Ljava/lang/String;
      14: astore_3
      15: aload_3
      16: invokestatic  #5                  // Method org/springframework/util/StringUtils.hasText:(Ljava/lang/String;)Z
      19: ifeq          31
      22: new           #6                  // class org/springframework/beans/factory/config/RuntimeBeanReference
      25: dup
      26: aload_3
      27: invokespecial #7                  // Method org/springframework/beans/factory/config/RuntimeBeanReference."<init>":(Ljava/lang/String;)V
      30: areturn
      31: aload_0
      32: aload_1
      33: aload_2
      34: invokevirtual #8                  // Method getSource:(Lorg/w3c/dom/Element;Lorg/springframework/beans/factory/xml/ParserContext;)Lorg/springframework/beans/BeanMetadataElement;
      37: astore        4
      39: aload         4
      41: ifnonnull     54
      44: new           #9                  // class org/springframework/beans/factory/BeanCreationException
      47: dup
      48: ldc           #10                 // String Could not create CorsFilter
      50: invokespecial #11                 // Method org/springframework/beans/factory/BeanCreationException."<init>":(Ljava/lang/String;)V
      53: athrow
      54: ldc           #12                 // class org/springframework/web/filter/CorsFilter
      56: invokestatic  #13                 // Method org/springframework/beans/factory/support/BeanDefinitionBuilder.rootBeanDefinition:(Ljava/lang/Class;)Lorg/springframework/beans/factory/support/BeanDefinitionBuilder;
      59: astore        5
      61: aload         5
      63: aload         4
      65: invokevirtual #14                 // Method org/springframework/beans/factory/support/BeanDefinitionBuilder.addConstructorArgValue:(Ljava/lang/Object;)Lorg/springframework/beans/factory/support/BeanDefinitionBuilder;
      68: pop
      69: aload         5
      71: invokevirtual #15                 // Method org/springframework/beans/factory/support/BeanDefinitionBuilder.getBeanDefinition:()Lorg/springframework/beans/factory/support/AbstractBeanDefinition;
      74: areturn

  public org.springframework.beans.BeanMetadataElement getSource(org.w3c.dom.Element, org.springframework.beans.factory.xml.ParserContext);
    Code:
       0: aload_1
       1: ldc           #16                 // String configuration-source-ref
       3: invokeinterface #4,  2            // InterfaceMethod org/w3c/dom/Element.getAttribute:(Ljava/lang/String;)Ljava/lang/String;
       8: astore_3
       9: aload_3
      10: invokestatic  #5                  // Method org/springframework/util/StringUtils.hasText:(Ljava/lang/String;)Z
      13: ifeq          25
      16: new           #6                  // class org/springframework/beans/factory/config/RuntimeBeanReference
      19: dup
      20: aload_3
      21: invokespecial #7                  // Method org/springframework/beans/factory/config/RuntimeBeanReference."<init>":(Ljava/lang/String;)V
      24: areturn
      25: ldc           #17                 // String org.springframework.web.servlet.handler.HandlerMappingIntrospector
      27: aload_0
      28: invokevirtual #18                 // Method java/lang/Object.getClass:()Ljava/lang/Class;
      31: invokevirtual #19                 // Method java/lang/Class.getClassLoader:()Ljava/lang/ClassLoader;
      34: invokestatic  #20                 // Method org/springframework/util/ClassUtils.isPresent:(Ljava/lang/String;Ljava/lang/ClassLoader;)Z
      37: istore        4
      39: iload         4
      41: ifne          46
      44: aconst_null
      45: areturn
      46: new           #21                 // class org/springframework/beans/factory/support/RootBeanDefinition
      49: dup
      50: ldc           #22                 // class org/springframework/security/config/http/HandlerMappingIntrospectorFactoryBean
      52: invokespecial #23                 // Method org/springframework/beans/factory/support/RootBeanDefinition."<init>":(Ljava/lang/Class;)V
      55: areturn
}
