Compiled from "BaseTypeBinding.java"
public class org.eclipse.jdt.internal.compiler.lookup.BaseTypeBinding extends org.eclipse.jdt.internal.compiler.lookup.TypeBinding {
  public static final int[] CONVERSIONS;

  public static final int IDENTITY;

  public static final int WIDENING;

  public static final int NARROWING;

  public static final int MAX_CONVERSIONS;

  public char[] simpleName;

  private char[] constantPoolName;

  static {};
    Code:
       0: invokestatic  #23                 // Method initializeConversions:()[I
       3: putstatic     #27                 // Field CONVERSIONS:[I
       6: return

  public static final int[] initializeConversions();
    Code:
       0: sipush        256
       3: newarray       int
       5: astore_0
       6: aload_0
       7: bipush        85
       9: iconst_1
      10: iastore
      11: aload_0
      12: bipush        51
      14: iconst_1
      15: iastore
      16: aload_0
      17: bipush        67
      19: iconst_2
      20: iastore
      21: aload_0
      22: bipush        35
      24: iconst_4
      25: iastore
      26: aload_0
      27: sipush        163
      30: iconst_2
      31: iastore
      32: aload_0
      33: bipush        115
      35: iconst_2
      36: iastore
      37: aload_0
      38: sipush        147
      41: iconst_2
      42: iastore
      43: aload_0
      44: sipush        131
      47: iconst_2
      48: iastore
      49: aload_0
      50: bipush        52
      52: iconst_4
      53: iastore
      54: aload_0
      55: bipush        68
      57: iconst_1
      58: iastore
      59: aload_0
      60: bipush        36
      62: iconst_4
      63: iastore
      64: aload_0
      65: sipush        164
      68: iconst_2
      69: iastore
      70: aload_0
      71: bipush        116
      73: iconst_2
      74: iastore
      75: aload_0
      76: sipush        148
      79: iconst_2
      80: iastore
      81: aload_0
      82: sipush        132
      85: iconst_2
      86: iastore
      87: aload_0
      88: bipush        50
      90: iconst_4
      91: iastore
      92: aload_0
      93: bipush        66
      95: iconst_4
      96: iastore
      97: aload_0
      98: bipush        34
     100: iconst_1
     101: iastore
     102: aload_0
     103: sipush        162
     106: iconst_2
     107: iastore
     108: aload_0
     109: bipush        114
     111: iconst_2
     112: iastore
     113: aload_0
     114: sipush        146
     117: iconst_2
     118: iastore
     119: aload_0
     120: sipush        130
     123: iconst_2
     124: iastore
     125: aload_0
     126: bipush        58
     128: iconst_4
     129: iastore
     130: aload_0
     131: bipush        74
     133: iconst_4
     134: iastore
     135: aload_0
     136: bipush        42
     138: iconst_4
     139: iastore
     140: aload_0
     141: sipush        170
     144: iconst_1
     145: iastore
     146: aload_0
     147: bipush        122
     149: iconst_2
     150: iastore
     151: aload_0
     152: sipush        154
     155: iconst_2
     156: iastore
     157: aload_0
     158: sipush        138
     161: iconst_2
     162: iastore
     163: aload_0
     164: bipush        55
     166: iconst_4
     167: iastore
     168: aload_0
     169: bipush        71
     171: iconst_4
     172: iastore
     173: aload_0
     174: bipush        39
     176: iconst_4
     177: iastore
     178: aload_0
     179: sipush        167
     182: iconst_4
     183: iastore
     184: aload_0
     185: bipush        119
     187: iconst_1
     188: iastore
     189: aload_0
     190: sipush        151
     193: iconst_2
     194: iastore
     195: aload_0
     196: sipush        135
     199: iconst_2
     200: iastore
     201: aload_0
     202: bipush        57
     204: iconst_4
     205: iastore
     206: aload_0
     207: bipush        73
     209: iconst_4
     210: iastore
     211: aload_0
     212: bipush        41
     214: iconst_4
     215: iastore
     216: aload_0
     217: sipush        169
     220: iconst_4
     221: iastore
     222: aload_0
     223: bipush        121
     225: iconst_4
     226: iastore
     227: aload_0
     228: sipush        153
     231: iconst_1
     232: iastore
     233: aload_0
     234: sipush        137
     237: iconst_2
     238: iastore
     239: aload_0
     240: bipush        56
     242: iconst_4
     243: iastore
     244: aload_0
     245: bipush        72
     247: iconst_4
     248: iastore
     249: aload_0
     250: bipush        40
     252: iconst_4
     253: iastore
     254: aload_0
     255: sipush        168
     258: iconst_4
     259: iastore
     260: aload_0
     261: bipush        120
     263: iconst_4
     264: iastore
     265: aload_0
     266: sipush        152
     269: iconst_4
     270: iastore
     271: aload_0
     272: sipush        136
     275: iconst_1
     276: iastore
     277: aload_0
     278: areturn

  public static final boolean isNarrowing(int, int);
    Code:
       0: iload_1
       1: iload_0
       2: iconst_4
       3: ishl
       4: iadd
       5: istore_2
       6: iload_2
       7: iflt          29
      10: iload_2
      11: sipush        256
      14: if_icmpge     29
      17: getstatic     #27                 // Field CONVERSIONS:[I
      20: iload_2
      21: iaload
      22: iconst_5
      23: iand
      24: ifeq          29
      27: iconst_1
      28: ireturn
      29: iconst_0
      30: ireturn

  public static final boolean isWidening(int, int);
    Code:
       0: iload_1
       1: iload_0
       2: iconst_4
       3: ishl
       4: iadd
       5: istore_2
       6: iload_2
       7: iflt          29
      10: iload_2
      11: sipush        256
      14: if_icmpge     29
      17: getstatic     #27                 // Field CONVERSIONS:[I
      20: iload_2
      21: iaload
      22: iconst_3
      23: iand
      24: ifeq          29
      27: iconst_1
      28: ireturn
      29: iconst_0
      30: ireturn

  org.eclipse.jdt.internal.compiler.lookup.BaseTypeBinding(int, char[], char[]);
    Code:
       0: aload_0
       1: invokespecial #41                 // Method org/eclipse/jdt/internal/compiler/lookup/TypeBinding."<init>":()V
       4: aload_0
       5: dup
       6: getfield      #43                 // Field tagBits:J
       9: ldc2_w        #47                 // long 2l
      12: lor
      13: putfield      #43                 // Field tagBits:J
      16: aload_0
      17: iload_1
      18: putfield      #49                 // Field id:I
      21: aload_0
      22: aload_2
      23: putfield      #52                 // Field simpleName:[C
      26: aload_0
      27: aload_3
      28: putfield      #54                 // Field constantPoolName:[C
      31: return

  public char[] computeUniqueKey(boolean);
    Code:
       0: aload_0
       1: invokevirtual #61                 // Method constantPoolName:()[C
       4: areturn

  public char[] constantPoolName();
    Code:
       0: aload_0
       1: getfield      #54                 // Field constantPoolName:[C
       4: areturn

  public org.eclipse.jdt.internal.compiler.lookup.TypeBinding clone(org.eclipse.jdt.internal.compiler.lookup.TypeBinding);
    Code:
       0: new           #1                  // class org/eclipse/jdt/internal/compiler/lookup/BaseTypeBinding
       3: dup
       4: aload_0
       5: getfield      #49                 // Field id:I
       8: aload_0
       9: getfield      #52                 // Field simpleName:[C
      12: aload_0
      13: getfield      #54                 // Field constantPoolName:[C
      16: invokespecial #68                 // Method "<init>":(I[C[C)V
      19: areturn

  public org.eclipse.jdt.internal.compiler.lookup.PackageBinding getPackage();
    Code:
       0: aconst_null
       1: areturn

  public final boolean isCompatibleWith(org.eclipse.jdt.internal.compiler.lookup.TypeBinding, org.eclipse.jdt.internal.compiler.lookup.Scope);
    Code:
       0: aload_0
       1: aload_1
       2: invokestatic  #76                 // Method equalsEquals:(Lorg/eclipse/jdt/internal/compiler/lookup/TypeBinding;Lorg/eclipse/jdt/internal/compiler/lookup/TypeBinding;)Z
       5: ifeq          10
       8: iconst_1
       9: ireturn
      10: aload_0
      11: getfield      #49                 // Field id:I
      14: aload_1
      15: getfield      #80                 // Field org/eclipse/jdt/internal/compiler/lookup/TypeBinding.id:I
      18: iconst_4
      19: ishl
      20: iadd
      21: istore_3
      22: iload_3
      23: iflt          45
      26: iload_3
      27: sipush        256
      30: if_icmpge     45
      33: getstatic     #27                 // Field CONVERSIONS:[I
      36: iload_3
      37: iaload
      38: iconst_3
      39: iand
      40: ifeq          45
      43: iconst_1
      44: ireturn
      45: aload_0
      46: getstatic     #81                 // Field org/eclipse/jdt/internal/compiler/lookup/TypeBinding.NULL:Lorg/eclipse/jdt/internal/compiler/lookup/NullTypeBinding;
      49: if_acmpne     61
      52: aload_1
      53: invokevirtual #85                 // Method org/eclipse/jdt/internal/compiler/lookup/TypeBinding.isBaseType:()Z
      56: ifne          61
      59: iconst_1
      60: ireturn
      61: iconst_0
      62: ireturn

  public void setTypeAnnotations(org.eclipse.jdt.internal.compiler.lookup.AnnotationBinding[], boolean);
    Code:
       0: aload_0
       1: aload_1
       2: iconst_0
       3: invokespecial #93                 // Method org/eclipse/jdt/internal/compiler/lookup/TypeBinding.setTypeAnnotations:([Lorg/eclipse/jdt/internal/compiler/lookup/AnnotationBinding;Z)V
       6: return

  public org.eclipse.jdt.internal.compiler.lookup.TypeBinding unannotated(boolean);
    Code:
       0: aload_0
       1: invokevirtual #100                // Method hasTypeAnnotations:()Z
       4: ifne          9
       7: aload_0
       8: areturn
       9: aload_0
      10: getfield      #49                 // Field id:I
      13: tableswitch   { // 2 to 10
                     2: 72
                     3: 68
                     4: 92
                     5: 64
                     6: 96
                     7: 88
                     8: 76
                     9: 80
                    10: 84
               default: 96
          }
      64: getstatic     #103                // Field org/eclipse/jdt/internal/compiler/lookup/TypeBinding.BOOLEAN:Lorg/eclipse/jdt/internal/compiler/lookup/BaseTypeBinding;
      67: areturn
      68: getstatic     #106                // Field org/eclipse/jdt/internal/compiler/lookup/TypeBinding.BYTE:Lorg/eclipse/jdt/internal/compiler/lookup/BaseTypeBinding;
      71: areturn
      72: getstatic     #109                // Field org/eclipse/jdt/internal/compiler/lookup/TypeBinding.CHAR:Lorg/eclipse/jdt/internal/compiler/lookup/BaseTypeBinding;
      75: areturn
      76: getstatic     #112                // Field org/eclipse/jdt/internal/compiler/lookup/TypeBinding.DOUBLE:Lorg/eclipse/jdt/internal/compiler/lookup/BaseTypeBinding;
      79: areturn
      80: getstatic     #115                // Field org/eclipse/jdt/internal/compiler/lookup/TypeBinding.FLOAT:Lorg/eclipse/jdt/internal/compiler/lookup/BaseTypeBinding;
      83: areturn
      84: getstatic     #118                // Field org/eclipse/jdt/internal/compiler/lookup/TypeBinding.INT:Lorg/eclipse/jdt/internal/compiler/lookup/BaseTypeBinding;
      87: areturn
      88: getstatic     #121                // Field org/eclipse/jdt/internal/compiler/lookup/TypeBinding.LONG:Lorg/eclipse/jdt/internal/compiler/lookup/BaseTypeBinding;
      91: areturn
      92: getstatic     #124                // Field org/eclipse/jdt/internal/compiler/lookup/TypeBinding.SHORT:Lorg/eclipse/jdt/internal/compiler/lookup/BaseTypeBinding;
      95: areturn
      96: new           #127                // class java/lang/IllegalStateException
      99: dup
     100: invokespecial #129                // Method java/lang/IllegalStateException."<init>":()V
     103: athrow

  public boolean isUncheckedException(boolean);
    Code:
       0: aload_0
       1: getstatic     #81                 // Field org/eclipse/jdt/internal/compiler/lookup/TypeBinding.NULL:Lorg/eclipse/jdt/internal/compiler/lookup/NullTypeBinding;
       4: if_acmpne     9
       7: iconst_1
       8: ireturn
       9: iconst_0
      10: ireturn

  public int kind();
    Code:
       0: sipush        132
       3: ireturn

  public char[] qualifiedSourceName();
    Code:
       0: aload_0
       1: getfield      #52                 // Field simpleName:[C
       4: areturn

  public char[] readableName();
    Code:
       0: aload_0
       1: getfield      #52                 // Field simpleName:[C
       4: areturn

  public char[] shortReadableName();
    Code:
       0: aload_0
       1: getfield      #52                 // Field simpleName:[C
       4: areturn

  public char[] sourceName();
    Code:
       0: aload_0
       1: getfield      #52                 // Field simpleName:[C
       4: areturn

  public java.lang.String toString();
    Code:
       0: aload_0
       1: invokevirtual #100                // Method hasTypeAnnotations:()Z
       4: ifeq          14
       7: aload_0
       8: invokevirtual #142                // Method annotatedDebugName:()Ljava/lang/String;
      11: goto          25
      14: new           #145                // class java/lang/String
      17: dup
      18: aload_0
      19: invokevirtual #147                // Method readableName:()[C
      22: invokespecial #149                // Method java/lang/String."<init>":([C)V
      25: areturn
}
