Compiled from "InferenceContext18.java"
class org.eclipse.jdt.internal.compiler.lookup.InferenceContext18$1 implements org.eclipse.jdt.internal.compiler.lookup.Substitution {
  final org.eclipse.jdt.internal.compiler.lookup.InferenceContext18 this$0;

  private final int val$numVars;

  private final org.eclipse.jdt.internal.compiler.lookup.InferenceVariable[] val$variables;

  private final org.eclipse.jdt.internal.compiler.lookup.CaptureBinding18[] val$zs;

  org.eclipse.jdt.internal.compiler.lookup.InferenceContext18$1(org.eclipse.jdt.internal.compiler.lookup.InferenceContext18, int, org.eclipse.jdt.internal.compiler.lookup.InferenceVariable[], org.eclipse.jdt.internal.compiler.lookup.CaptureBinding18[]);
    Code:
       0: aload_0
       1: aload_1
       2: putfield      #18                 // Field this$0:Lorg/eclipse/jdt/internal/compiler/lookup/InferenceContext18;
       5: aload_0
       6: iload_2
       7: putfield      #20                 // Field val$numVars:I
      10: aload_0
      11: aload_3
      12: putfield      #22                 // Field val$variables:[Lorg/eclipse/jdt/internal/compiler/lookup/InferenceVariable;
      15: aload_0
      16: aload         4
      18: putfield      #24                 // Field val$zs:[Lorg/eclipse/jdt/internal/compiler/lookup/CaptureBinding18;
      21: aload_0
      22: invokespecial #26                 // Method java/lang/Object."<init>":()V
      25: return

  public org.eclipse.jdt.internal.compiler.lookup.LookupEnvironment environment();
    Code:
       0: aload_0
       1: getfield      #18                 // Field this$0:Lorg/eclipse/jdt/internal/compiler/lookup/InferenceContext18;
       4: getfield      #35                 // Field org/eclipse/jdt/internal/compiler/lookup/InferenceContext18.environment:Lorg/eclipse/jdt/internal/compiler/lookup/LookupEnvironment;
       7: areturn

  public boolean isRawSubstitution();
    Code:
       0: iconst_0
       1: ireturn

  public org.eclipse.jdt.internal.compiler.lookup.TypeBinding substitute(org.eclipse.jdt.internal.compiler.lookup.TypeVariableBinding);
    Code:
       0: iconst_0
       1: istore_2
       2: goto          25
       5: aload_0
       6: getfield      #22                 // Field val$variables:[Lorg/eclipse/jdt/internal/compiler/lookup/InferenceVariable;
       9: iload_2
      10: aaload
      11: aload_1
      12: if_acmpne     22
      15: aload_0
      16: getfield      #24                 // Field val$zs:[Lorg/eclipse/jdt/internal/compiler/lookup/CaptureBinding18;
      19: iload_2
      20: aaload
      21: areturn
      22: iinc          2, 1
      25: iload_2
      26: aload_0
      27: getfield      #20                 // Field val$numVars:I
      30: if_icmplt     5
      33: aload_1
      34: areturn
}
