Compiled from "IntersectionCastTypeBinding.java"
public class org.eclipse.jdt.internal.compiler.lookup.IntersectionCastTypeBinding extends org.eclipse.jdt.internal.compiler.lookup.ReferenceBinding {
  public org.eclipse.jdt.internal.compiler.lookup.ReferenceBinding[] intersectingTypes;

  private org.eclipse.jdt.internal.compiler.lookup.ReferenceBinding javaLangObject;

  int length;

  public org.eclipse.jdt.internal.compiler.lookup.IntersectionCastTypeBinding(org.eclipse.jdt.internal.compiler.lookup.ReferenceBinding[], org.eclipse.jdt.internal.compiler.lookup.LookupEnvironment);
    Code:
       0: aload_0
       1: invokespecial #14                 // Method org/eclipse/jdt/internal/compiler/lookup/ReferenceBinding."<init>":()V
       4: aload_0
       5: aload_1
       6: putfield      #17                 // Field intersectingTypes:[Lorg/eclipse/jdt/internal/compiler/lookup/ReferenceBinding;
       9: aload_0
      10: aload_1
      11: arraylength
      12: putfield      #19                 // Field length:I
      15: aload_1
      16: iconst_0
      17: aaload
      18: invokevirtual #21                 // Method org/eclipse/jdt/internal/compiler/lookup/ReferenceBinding.isClass:()Z
      21: ifne          48
      24: aload_0
      25: aload_2
      26: getstatic     #25                 // Field org/eclipse/jdt/internal/compiler/lookup/TypeConstants.JAVA_LANG_OBJECT:[[C
      29: aconst_null
      30: invokevirtual #31                 // Method org/eclipse/jdt/internal/compiler/lookup/LookupEnvironment.getResolvedType:([[CLorg/eclipse/jdt/internal/compiler/lookup/Scope;)Lorg/eclipse/jdt/internal/compiler/lookup/ReferenceBinding;
      33: putfield      #37                 // Field javaLangObject:Lorg/eclipse/jdt/internal/compiler/lookup/ReferenceBinding;
      36: aload_0
      37: dup
      38: getfield      #39                 // Field modifiers:I
      41: sipush        512
      44: ior
      45: putfield      #39                 // Field modifiers:I
      48: return

  public org.eclipse.jdt.internal.compiler.lookup.MethodBinding getSingleAbstractMethod(org.eclipse.jdt.internal.compiler.lookup.Scope, boolean);
    Code:
       0: iload_2
       1: ifeq          8
       4: iconst_0
       5: goto          9
       8: iconst_1
       9: istore_3
      10: aload_0
      11: getfield      #52                 // Field singleAbstractMethod:[Lorg/eclipse/jdt/internal/compiler/lookup/MethodBinding;
      14: ifnull        33
      17: aload_0
      18: getfield      #52                 // Field singleAbstractMethod:[Lorg/eclipse/jdt/internal/compiler/lookup/MethodBinding;
      21: iload_3
      22: aaload
      23: ifnull        41
      26: aload_0
      27: getfield      #52                 // Field singleAbstractMethod:[Lorg/eclipse/jdt/internal/compiler/lookup/MethodBinding;
      30: iload_3
      31: aaload
      32: areturn
      33: aload_0
      34: iconst_2
      35: anewarray     #56                 // class org/eclipse/jdt/internal/compiler/lookup/MethodBinding
      38: putfield      #52                 // Field singleAbstractMethod:[Lorg/eclipse/jdt/internal/compiler/lookup/MethodBinding;
      41: getstatic     #58                 // Field samProblemBinding:Lorg/eclipse/jdt/internal/compiler/lookup/ProblemMethodBinding;
      44: astore        4
      46: iconst_0
      47: istore        5
      49: goto          115
      52: aload_0
      53: getfield      #17                 // Field intersectingTypes:[Lorg/eclipse/jdt/internal/compiler/lookup/ReferenceBinding;
      56: iload         5
      58: aaload
      59: aload_1
      60: iload_2
      61: invokevirtual #62                 // Method org/eclipse/jdt/internal/compiler/lookup/ReferenceBinding.getSingleAbstractMethod:(Lorg/eclipse/jdt/internal/compiler/lookup/Scope;Z)Lorg/eclipse/jdt/internal/compiler/lookup/MethodBinding;
      64: astore        6
      66: aload         6
      68: ifnull        112
      71: aload         6
      73: invokevirtual #64                 // Method org/eclipse/jdt/internal/compiler/lookup/MethodBinding.isValidBinding:()Z
      76: ifeq          112
      79: aload         4
      81: invokevirtual #64                 // Method org/eclipse/jdt/internal/compiler/lookup/MethodBinding.isValidBinding:()Z
      84: ifeq          108
      87: aload_0
      88: getfield      #52                 // Field singleAbstractMethod:[Lorg/eclipse/jdt/internal/compiler/lookup/MethodBinding;
      91: iload_3
      92: new           #67                 // class org/eclipse/jdt/internal/compiler/lookup/ProblemMethodBinding
      95: dup
      96: getstatic     #69                 // Field org/eclipse/jdt/internal/compiler/lookup/TypeConstants.ANONYMOUS_METHOD:[C
      99: aconst_null
     100: bipush        19
     102: invokespecial #73                 // Method org/eclipse/jdt/internal/compiler/lookup/ProblemMethodBinding."<init>":([C[Lorg/eclipse/jdt/internal/compiler/lookup/TypeBinding;I)V
     105: dup_x2
     106: aastore
     107: areturn
     108: aload         6
     110: astore        4
     112: iinc          5, 1
     115: iload         5
     117: aload_0
     118: getfield      #19                 // Field length:I
     121: if_icmplt     52
     124: aload_0
     125: getfield      #52                 // Field singleAbstractMethod:[Lorg/eclipse/jdt/internal/compiler/lookup/MethodBinding;
     128: iload_3
     129: aload         4
     131: dup_x2
     132: aastore
     133: areturn

  public boolean hasTypeBit(int);
    Code:
       0: iconst_0
       1: istore_2
       2: goto          23
       5: aload_0
       6: getfield      #17                 // Field intersectingTypes:[Lorg/eclipse/jdt/internal/compiler/lookup/ReferenceBinding;
       9: iload_2
      10: aaload
      11: iload_1
      12: invokevirtual #87                 // Method org/eclipse/jdt/internal/compiler/lookup/ReferenceBinding.hasTypeBit:(I)Z
      15: ifeq          20
      18: iconst_1
      19: ireturn
      20: iinc          2, 1
      23: iload_2
      24: aload_0
      25: getfield      #19                 // Field length:I
      28: if_icmplt     5
      31: iconst_0
      32: ireturn

  public boolean canBeInstantiated();
    Code:
       0: iconst_0
       1: ireturn

  public boolean canBeSeenBy(org.eclipse.jdt.internal.compiler.lookup.PackageBinding);
    Code:
       0: iconst_0
       1: istore_2
       2: goto          23
       5: aload_0
       6: getfield      #17                 // Field intersectingTypes:[Lorg/eclipse/jdt/internal/compiler/lookup/ReferenceBinding;
       9: iload_2
      10: aaload
      11: aload_1
      12: invokevirtual #93                 // Method org/eclipse/jdt/internal/compiler/lookup/ReferenceBinding.canBeSeenBy:(Lorg/eclipse/jdt/internal/compiler/lookup/PackageBinding;)Z
      15: ifne          20
      18: iconst_0
      19: ireturn
      20: iinc          2, 1
      23: iload_2
      24: aload_0
      25: getfield      #19                 // Field length:I
      28: if_icmplt     5
      31: iconst_1
      32: ireturn

  public boolean canBeSeenBy(org.eclipse.jdt.internal.compiler.lookup.Scope);
    Code:
       0: iconst_0
       1: istore_2
       2: goto          23
       5: aload_0
       6: getfield      #17                 // Field intersectingTypes:[Lorg/eclipse/jdt/internal/compiler/lookup/ReferenceBinding;
       9: iload_2
      10: aaload
      11: aload_1
      12: invokevirtual #98                 // Method org/eclipse/jdt/internal/compiler/lookup/ReferenceBinding.canBeSeenBy:(Lorg/eclipse/jdt/internal/compiler/lookup/Scope;)Z
      15: ifne          20
      18: iconst_0
      19: ireturn
      20: iinc          2, 1
      23: iload_2
      24: aload_0
      25: getfield      #19                 // Field length:I
      28: if_icmplt     5
      31: iconst_1
      32: ireturn

  public boolean canBeSeenBy(org.eclipse.jdt.internal.compiler.lookup.ReferenceBinding, org.eclipse.jdt.internal.compiler.lookup.ReferenceBinding);
    Code:
       0: iconst_0
       1: istore_3
       2: goto          24
       5: aload_0
       6: getfield      #17                 // Field intersectingTypes:[Lorg/eclipse/jdt/internal/compiler/lookup/ReferenceBinding;
       9: iload_3
      10: aaload
      11: aload_1
      12: aload_2
      13: invokevirtual #101                // Method org/eclipse/jdt/internal/compiler/lookup/ReferenceBinding.canBeSeenBy:(Lorg/eclipse/jdt/internal/compiler/lookup/ReferenceBinding;Lorg/eclipse/jdt/internal/compiler/lookup/ReferenceBinding;)Z
      16: ifne          21
      19: iconst_0
      20: ireturn
      21: iinc          3, 1
      24: iload_3
      25: aload_0
      26: getfield      #19                 // Field length:I
      29: if_icmplt     5
      32: iconst_1
      33: ireturn

  public char[] constantPoolName();
    Code:
       0: aload_0
       1: getfield      #17                 // Field intersectingTypes:[Lorg/eclipse/jdt/internal/compiler/lookup/ReferenceBinding;
       4: iconst_0
       5: aaload
       6: invokevirtual #107                // Method org/eclipse/jdt/internal/compiler/lookup/ReferenceBinding.constantPoolName:()[C
       9: areturn

  public org.eclipse.jdt.internal.compiler.lookup.PackageBinding getPackage();
    Code:
       0: new           #111                // class java/lang/UnsupportedOperationException
       3: dup
       4: invokespecial #113                // Method java/lang/UnsupportedOperationException."<init>":()V
       7: athrow

  public org.eclipse.jdt.internal.compiler.lookup.ReferenceBinding[] getIntersectingTypes();
    Code:
       0: aload_0
       1: getfield      #17                 // Field intersectingTypes:[Lorg/eclipse/jdt/internal/compiler/lookup/ReferenceBinding;
       4: areturn

  public org.eclipse.jdt.internal.compiler.lookup.ReferenceBinding superclass();
    Code:
       0: aload_0
       1: getfield      #17                 // Field intersectingTypes:[Lorg/eclipse/jdt/internal/compiler/lookup/ReferenceBinding;
       4: iconst_0
       5: aaload
       6: invokevirtual #21                 // Method org/eclipse/jdt/internal/compiler/lookup/ReferenceBinding.isClass:()Z
       9: ifeq          21
      12: aload_0
      13: getfield      #17                 // Field intersectingTypes:[Lorg/eclipse/jdt/internal/compiler/lookup/ReferenceBinding;
      16: iconst_0
      17: aaload
      18: goto          25
      21: aload_0
      22: getfield      #37                 // Field javaLangObject:Lorg/eclipse/jdt/internal/compiler/lookup/ReferenceBinding;
      25: areturn

  public org.eclipse.jdt.internal.compiler.lookup.ReferenceBinding[] superInterfaces();
    Code:
       0: aload_0
       1: getfield      #17                 // Field intersectingTypes:[Lorg/eclipse/jdt/internal/compiler/lookup/ReferenceBinding;
       4: iconst_0
       5: aaload
       6: invokevirtual #21                 // Method org/eclipse/jdt/internal/compiler/lookup/ReferenceBinding.isClass:()Z
       9: ifeq          40
      12: aload_0
      13: getfield      #19                 // Field length:I
      16: iconst_1
      17: isub
      18: anewarray     #3                  // class org/eclipse/jdt/internal/compiler/lookup/ReferenceBinding
      21: astore_1
      22: aload_0
      23: getfield      #17                 // Field intersectingTypes:[Lorg/eclipse/jdt/internal/compiler/lookup/ReferenceBinding;
      26: iconst_1
      27: aload_1
      28: iconst_0
      29: aload_0
      30: getfield      #19                 // Field length:I
      33: iconst_1
      34: isub
      35: invokestatic  #119                // Method java/lang/System.arraycopy:(Ljava/lang/Object;ILjava/lang/Object;II)V
      38: aload_1
      39: areturn
      40: aload_0
      41: getfield      #17                 // Field intersectingTypes:[Lorg/eclipse/jdt/internal/compiler/lookup/ReferenceBinding;
      44: areturn

  public boolean isBoxedPrimitiveType();
    Code:
       0: aload_0
       1: getfield      #17                 // Field intersectingTypes:[Lorg/eclipse/jdt/internal/compiler/lookup/ReferenceBinding;
       4: iconst_0
       5: aaload
       6: invokevirtual #126                // Method org/eclipse/jdt/internal/compiler/lookup/ReferenceBinding.isBoxedPrimitiveType:()Z
       9: ireturn

  public boolean isCompatibleWith(org.eclipse.jdt.internal.compiler.lookup.TypeBinding, org.eclipse.jdt.internal.compiler.lookup.Scope);
    Code:
       0: aload_0
       1: aload_1
       2: invokestatic  #130                // Method org/eclipse/jdt/internal/compiler/lookup/TypeBinding.equalsEquals:(Lorg/eclipse/jdt/internal/compiler/lookup/TypeBinding;Lorg/eclipse/jdt/internal/compiler/lookup/TypeBinding;)Z
       5: ifeq          10
       8: iconst_1
       9: ireturn
      10: aload_1
      11: invokevirtual #136                // Method org/eclipse/jdt/internal/compiler/lookup/TypeBinding.kind:()I
      14: istore_3
      15: aconst_null
      16: astore        4
      18: iload_3
      19: sipush        8196
      22: if_icmpne     63
      25: aload_1
      26: invokevirtual #140                // Method org/eclipse/jdt/internal/compiler/lookup/TypeBinding.boundKind:()I
      29: iconst_1
      30: if_icmpne     63
      33: aload_1
      34: checkcast     #143                // class org/eclipse/jdt/internal/compiler/lookup/WildcardBinding
      37: invokevirtual #145                // Method org/eclipse/jdt/internal/compiler/lookup/WildcardBinding.allBounds:()Lorg/eclipse/jdt/internal/compiler/lookup/TypeBinding;
      40: astore        5
      42: aload         5
      44: instanceof    #1                  // class org/eclipse/jdt/internal/compiler/lookup/IntersectionCastTypeBinding
      47: ifeq          78
      50: aload         5
      52: checkcast     #1                  // class org/eclipse/jdt/internal/compiler/lookup/IntersectionCastTypeBinding
      55: getfield      #17                 // Field intersectingTypes:[Lorg/eclipse/jdt/internal/compiler/lookup/ReferenceBinding;
      58: astore        4
      60: goto          78
      63: iload_3
      64: ldc           #149                // int 32772
      66: if_icmpne     78
      69: aload_1
      70: checkcast     #1                  // class org/eclipse/jdt/internal/compiler/lookup/IntersectionCastTypeBinding
      73: getfield      #17                 // Field intersectingTypes:[Lorg/eclipse/jdt/internal/compiler/lookup/ReferenceBinding;
      76: astore        4
      78: aload         4
      80: ifnull        193
      83: aload         4
      85: arraylength
      86: istore        5
      88: iload         5
      90: anewarray     #131                // class org/eclipse/jdt/internal/compiler/lookup/TypeBinding
      93: astore        6
      95: aload         4
      97: iconst_0
      98: aload         6
     100: iconst_0
     101: iload         5
     103: invokestatic  #119                // Method java/lang/System.arraycopy:(Ljava/lang/Object;ILjava/lang/Object;II)V
     106: iconst_0
     107: istore        7
     109: goto          182
     112: aload_0
     113: getfield      #17                 // Field intersectingTypes:[Lorg/eclipse/jdt/internal/compiler/lookup/ReferenceBinding;
     116: iload         7
     118: aaload
     119: astore        8
     121: iconst_0
     122: istore        9
     124: goto          171
     127: aload         6
     129: iload         9
     131: aaload
     132: ifnonnull     138
     135: goto          168
     138: aload         8
     140: aload         6
     142: iload         9
     144: aaload
     145: aload_2
     146: invokevirtual #150                // Method org/eclipse/jdt/internal/compiler/lookup/TypeBinding.isCompatibleWith:(Lorg/eclipse/jdt/internal/compiler/lookup/TypeBinding;Lorg/eclipse/jdt/internal/compiler/lookup/Scope;)Z
     149: ifeq          168
     152: aload         6
     154: iload         9
     156: aconst_null
     157: aastore
     158: iinc          5, -1
     161: iload         5
     163: ifne          179
     166: iconst_1
     167: ireturn
     168: iinc          9, 1
     171: iload         9
     173: aload         6
     175: arraylength
     176: if_icmplt     127
     179: iinc          7, 1
     182: iload         7
     184: aload_0
     185: getfield      #19                 // Field length:I
     188: if_icmplt     112
     191: iconst_0
     192: ireturn
     193: iconst_0
     194: istore        5
     196: goto          219
     199: aload_0
     200: getfield      #17                 // Field intersectingTypes:[Lorg/eclipse/jdt/internal/compiler/lookup/ReferenceBinding;
     203: iload         5
     205: aaload
     206: aload_1
     207: aload_2
     208: invokevirtual #152                // Method org/eclipse/jdt/internal/compiler/lookup/ReferenceBinding.isCompatibleWith:(Lorg/eclipse/jdt/internal/compiler/lookup/TypeBinding;Lorg/eclipse/jdt/internal/compiler/lookup/Scope;)Z
     211: ifeq          216
     214: iconst_1
     215: ireturn
     216: iinc          5, 1
     219: iload         5
     221: aload_0
     222: getfield      #19                 // Field length:I
     225: if_icmplt     199
     228: iconst_0
     229: ireturn

  public boolean isSubtypeOf(org.eclipse.jdt.internal.compiler.lookup.TypeBinding);
    Code:
       0: aload_0
       1: aload_1
       2: invokestatic  #130                // Method org/eclipse/jdt/internal/compiler/lookup/TypeBinding.equalsEquals:(Lorg/eclipse/jdt/internal/compiler/lookup/TypeBinding;Lorg/eclipse/jdt/internal/compiler/lookup/TypeBinding;)Z
       5: ifeq          10
       8: iconst_1
       9: ireturn
      10: iconst_0
      11: istore_2
      12: goto          33
      15: aload_0
      16: getfield      #17                 // Field intersectingTypes:[Lorg/eclipse/jdt/internal/compiler/lookup/ReferenceBinding;
      19: iload_2
      20: aaload
      21: aload_1
      22: invokevirtual #166                // Method org/eclipse/jdt/internal/compiler/lookup/ReferenceBinding.isSubtypeOf:(Lorg/eclipse/jdt/internal/compiler/lookup/TypeBinding;)Z
      25: ifeq          30
      28: iconst_1
      29: ireturn
      30: iinc          2, 1
      33: iload_2
      34: aload_0
      35: getfield      #17                 // Field intersectingTypes:[Lorg/eclipse/jdt/internal/compiler/lookup/ReferenceBinding;
      38: arraylength
      39: if_icmplt     15
      42: iconst_0
      43: ireturn

  public char[] qualifiedSourceName();
    Code:
       0: new           #170                // class java/lang/StringBuffer
       3: dup
       4: bipush        16
       6: invokespecial #172                // Method java/lang/StringBuffer."<init>":(I)V
       9: astore_1
      10: iconst_0
      11: istore_2
      12: goto          49
      15: aload_1
      16: aload_0
      17: getfield      #17                 // Field intersectingTypes:[Lorg/eclipse/jdt/internal/compiler/lookup/ReferenceBinding;
      20: iload_2
      21: aaload
      22: invokevirtual #175                // Method org/eclipse/jdt/internal/compiler/lookup/ReferenceBinding.qualifiedSourceName:()[C
      25: invokevirtual #177                // Method java/lang/StringBuffer.append:([C)Ljava/lang/StringBuffer;
      28: pop
      29: iload_2
      30: aload_0
      31: getfield      #19                 // Field length:I
      34: iconst_1
      35: isub
      36: if_icmpeq     46
      39: aload_1
      40: ldc           #181                // String  &
      42: invokevirtual #183                // Method java/lang/StringBuffer.append:(Ljava/lang/String;)Ljava/lang/StringBuffer;
      45: pop
      46: iinc          2, 1
      49: iload_2
      50: aload_0
      51: getfield      #19                 // Field length:I
      54: if_icmplt     15
      57: aload_1
      58: invokevirtual #186                // Method java/lang/StringBuffer.toString:()Ljava/lang/String;
      61: invokevirtual #190                // Method java/lang/String.toCharArray:()[C
      64: areturn

  public char[] sourceName();
    Code:
       0: new           #170                // class java/lang/StringBuffer
       3: dup
       4: bipush        16
       6: invokespecial #172                // Method java/lang/StringBuffer."<init>":(I)V
       9: astore_1
      10: iconst_0
      11: istore_2
      12: goto          49
      15: aload_1
      16: aload_0
      17: getfield      #17                 // Field intersectingTypes:[Lorg/eclipse/jdt/internal/compiler/lookup/ReferenceBinding;
      20: iload_2
      21: aaload
      22: invokevirtual #197                // Method org/eclipse/jdt/internal/compiler/lookup/ReferenceBinding.sourceName:()[C
      25: invokevirtual #177                // Method java/lang/StringBuffer.append:([C)Ljava/lang/StringBuffer;
      28: pop
      29: iload_2
      30: aload_0
      31: getfield      #19                 // Field length:I
      34: iconst_1
      35: isub
      36: if_icmpeq     46
      39: aload_1
      40: ldc           #181                // String  &
      42: invokevirtual #183                // Method java/lang/StringBuffer.append:(Ljava/lang/String;)Ljava/lang/StringBuffer;
      45: pop
      46: iinc          2, 1
      49: iload_2
      50: aload_0
      51: getfield      #19                 // Field length:I
      54: if_icmplt     15
      57: aload_1
      58: invokevirtual #186                // Method java/lang/StringBuffer.toString:()Ljava/lang/String;
      61: invokevirtual #190                // Method java/lang/String.toCharArray:()[C
      64: areturn

  public char[] readableName();
    Code:
       0: new           #170                // class java/lang/StringBuffer
       3: dup
       4: bipush        16
       6: invokespecial #172                // Method java/lang/StringBuffer."<init>":(I)V
       9: astore_1
      10: iconst_0
      11: istore_2
      12: goto          49
      15: aload_1
      16: aload_0
      17: getfield      #17                 // Field intersectingTypes:[Lorg/eclipse/jdt/internal/compiler/lookup/ReferenceBinding;
      20: iload_2
      21: aaload
      22: invokevirtual #201                // Method org/eclipse/jdt/internal/compiler/lookup/ReferenceBinding.readableName:()[C
      25: invokevirtual #177                // Method java/lang/StringBuffer.append:([C)Ljava/lang/StringBuffer;
      28: pop
      29: iload_2
      30: aload_0
      31: getfield      #19                 // Field length:I
      34: iconst_1
      35: isub
      36: if_icmpeq     46
      39: aload_1
      40: ldc           #181                // String  &
      42: invokevirtual #183                // Method java/lang/StringBuffer.append:(Ljava/lang/String;)Ljava/lang/StringBuffer;
      45: pop
      46: iinc          2, 1
      49: iload_2
      50: aload_0
      51: getfield      #19                 // Field length:I
      54: if_icmplt     15
      57: aload_1
      58: invokevirtual #186                // Method java/lang/StringBuffer.toString:()Ljava/lang/String;
      61: invokevirtual #190                // Method java/lang/String.toCharArray:()[C
      64: areturn

  public char[] shortReadableName();
    Code:
       0: new           #170                // class java/lang/StringBuffer
       3: dup
       4: bipush        16
       6: invokespecial #172                // Method java/lang/StringBuffer."<init>":(I)V
       9: astore_1
      10: iconst_0
      11: istore_2
      12: goto          49
      15: aload_1
      16: aload_0
      17: getfield      #17                 // Field intersectingTypes:[Lorg/eclipse/jdt/internal/compiler/lookup/ReferenceBinding;
      20: iload_2
      21: aaload
      22: invokevirtual #204                // Method org/eclipse/jdt/internal/compiler/lookup/ReferenceBinding.shortReadableName:()[C
      25: invokevirtual #177                // Method java/lang/StringBuffer.append:([C)Ljava/lang/StringBuffer;
      28: pop
      29: iload_2
      30: aload_0
      31: getfield      #19                 // Field length:I
      34: iconst_1
      35: isub
      36: if_icmpeq     46
      39: aload_1
      40: ldc           #181                // String  &
      42: invokevirtual #183                // Method java/lang/StringBuffer.append:(Ljava/lang/String;)Ljava/lang/StringBuffer;
      45: pop
      46: iinc          2, 1
      49: iload_2
      50: aload_0
      51: getfield      #19                 // Field length:I
      54: if_icmplt     15
      57: aload_1
      58: invokevirtual #186                // Method java/lang/StringBuffer.toString:()Ljava/lang/String;
      61: invokevirtual #190                // Method java/lang/String.toCharArray:()[C
      64: areturn

  public boolean isIntersectionCastType();
    Code:
       0: iconst_1
       1: ireturn

  public int kind();
    Code:
       0: ldc           #149                // int 32772
       2: ireturn

  public java.lang.String debugName();
    Code:
       0: new           #170                // class java/lang/StringBuffer
       3: dup
       4: bipush        16
       6: invokespecial #172                // Method java/lang/StringBuffer."<init>":(I)V
       9: astore_1
      10: iconst_0
      11: istore_2
      12: goto          49
      15: aload_1
      16: aload_0
      17: getfield      #17                 // Field intersectingTypes:[Lorg/eclipse/jdt/internal/compiler/lookup/ReferenceBinding;
      20: iload_2
      21: aaload
      22: invokevirtual #208                // Method org/eclipse/jdt/internal/compiler/lookup/ReferenceBinding.debugName:()Ljava/lang/String;
      25: invokevirtual #183                // Method java/lang/StringBuffer.append:(Ljava/lang/String;)Ljava/lang/StringBuffer;
      28: pop
      29: iload_2
      30: aload_0
      31: getfield      #19                 // Field length:I
      34: iconst_1
      35: isub
      36: if_icmpeq     46
      39: aload_1
      40: ldc           #181                // String  &
      42: invokevirtual #183                // Method java/lang/StringBuffer.append:(Ljava/lang/String;)Ljava/lang/StringBuffer;
      45: pop
      46: iinc          2, 1
      49: iload_2
      50: aload_0
      51: getfield      #19                 // Field length:I
      54: if_icmplt     15
      57: aload_1
      58: invokevirtual #186                // Method java/lang/StringBuffer.toString:()Ljava/lang/String;
      61: areturn

  public java.lang.String toString();
    Code:
       0: aload_0
       1: invokevirtual #210                // Method debugName:()Ljava/lang/String;
       4: areturn

  public org.eclipse.jdt.internal.compiler.lookup.TypeBinding getSAMType(org.eclipse.jdt.internal.compiler.lookup.Scope);
    Code:
       0: aconst_null
       1: astore_2
       2: iconst_0
       3: istore_3
       4: aload_0
       5: getfield      #17                 // Field intersectingTypes:[Lorg/eclipse/jdt/internal/compiler/lookup/ReferenceBinding;
       8: arraylength
       9: istore        4
      11: goto          67
      14: aload_0
      15: getfield      #17                 // Field intersectingTypes:[Lorg/eclipse/jdt/internal/compiler/lookup/ReferenceBinding;
      18: iload_3
      19: aaload
      20: astore        5
      22: aload         5
      24: aload_1
      25: iconst_1
      26: invokevirtual #213                // Method org/eclipse/jdt/internal/compiler/lookup/TypeBinding.getSingleAbstractMethod:(Lorg/eclipse/jdt/internal/compiler/lookup/Scope;Z)Lorg/eclipse/jdt/internal/compiler/lookup/MethodBinding;
      29: astore        6
      31: aload         6
      33: instanceof    #67                 // class org/eclipse/jdt/internal/compiler/lookup/ProblemMethodBinding
      36: ifeq          55
      39: aload         6
      41: checkcast     #67                 // class org/eclipse/jdt/internal/compiler/lookup/ProblemMethodBinding
      44: invokevirtual #214                // Method org/eclipse/jdt/internal/compiler/lookup/ProblemMethodBinding.problemId:()I
      47: bipush        17
      49: if_icmpne     55
      52: goto          64
      55: aload_2
      56: ifnull        61
      59: aconst_null
      60: areturn
      61: aload         5
      63: astore_2
      64: iinc          3, 1
      67: iload_3
      68: iload         4
      70: if_icmplt     14
      73: aload_2
      74: areturn

  void collectInferenceVariables(java.util.Set<org.eclipse.jdt.internal.compiler.lookup.InferenceVariable>);
    Code:
       0: iconst_0
       1: istore_2
       2: goto          18
       5: aload_0
       6: getfield      #17                 // Field intersectingTypes:[Lorg/eclipse/jdt/internal/compiler/lookup/ReferenceBinding;
       9: iload_2
      10: aaload
      11: aload_1
      12: invokevirtual #225                // Method org/eclipse/jdt/internal/compiler/lookup/ReferenceBinding.collectInferenceVariables:(Ljava/util/Set;)V
      15: iinc          2, 1
      18: iload_2
      19: aload_0
      20: getfield      #17                 // Field intersectingTypes:[Lorg/eclipse/jdt/internal/compiler/lookup/ReferenceBinding;
      23: arraylength
      24: if_icmplt     5
      27: return

  public boolean mentionsAny(org.eclipse.jdt.internal.compiler.lookup.TypeBinding[], int);
    Code:
       0: aload_0
       1: aload_1
       2: iload_2
       3: invokespecial #233                // Method org/eclipse/jdt/internal/compiler/lookup/ReferenceBinding.mentionsAny:([Lorg/eclipse/jdt/internal/compiler/lookup/TypeBinding;I)Z
       6: ifeq          11
       9: iconst_1
      10: ireturn
      11: iconst_0
      12: istore_3
      13: goto          35
      16: aload_0
      17: getfield      #17                 // Field intersectingTypes:[Lorg/eclipse/jdt/internal/compiler/lookup/ReferenceBinding;
      20: iload_3
      21: aaload
      22: aload_1
      23: iconst_m1
      24: invokevirtual #233                // Method org/eclipse/jdt/internal/compiler/lookup/ReferenceBinding.mentionsAny:([Lorg/eclipse/jdt/internal/compiler/lookup/TypeBinding;I)Z
      27: ifeq          32
      30: iconst_1
      31: ireturn
      32: iinc          3, 1
      35: iload_3
      36: aload_0
      37: getfield      #17                 // Field intersectingTypes:[Lorg/eclipse/jdt/internal/compiler/lookup/ReferenceBinding;
      40: arraylength
      41: if_icmplt     16
      44: iconst_0
      45: ireturn
}
