Compiled from "MostSpecificExceptionMethodBinding.java"
public class org.eclipse.jdt.internal.compiler.lookup.MostSpecificExceptionMethodBinding extends org.eclipse.jdt.internal.compiler.lookup.MethodBinding {
  private org.eclipse.jdt.internal.compiler.lookup.MethodBinding originalMethod;

  public org.eclipse.jdt.internal.compiler.lookup.MostSpecificExceptionMethodBinding(org.eclipse.jdt.internal.compiler.lookup.MethodBinding, org.eclipse.jdt.internal.compiler.lookup.ReferenceBinding[]);
    Code:
       0: aload_0
       1: aload_1
       2: getfield      #10                 // Field org/eclipse/jdt/internal/compiler/lookup/MethodBinding.modifiers:I
       5: aload_1
       6: getfield      #14                 // Field org/eclipse/jdt/internal/compiler/lookup/MethodBinding.selector:[C
       9: aload_1
      10: getfield      #18                 // Field org/eclipse/jdt/internal/compiler/lookup/MethodBinding.returnType:Lorg/eclipse/jdt/internal/compiler/lookup/TypeBinding;
      13: aload_1
      14: getfield      #22                 // Field org/eclipse/jdt/internal/compiler/lookup/MethodBinding.parameters:[Lorg/eclipse/jdt/internal/compiler/lookup/TypeBinding;
      17: aload_2
      18: aload_1
      19: getfield      #26                 // Field org/eclipse/jdt/internal/compiler/lookup/MethodBinding.declaringClass:Lorg/eclipse/jdt/internal/compiler/lookup/ReferenceBinding;
      22: invokespecial #30                 // Method org/eclipse/jdt/internal/compiler/lookup/MethodBinding."<init>":(I[CLorg/eclipse/jdt/internal/compiler/lookup/TypeBinding;[Lorg/eclipse/jdt/internal/compiler/lookup/TypeBinding;[Lorg/eclipse/jdt/internal/compiler/lookup/ReferenceBinding;Lorg/eclipse/jdt/internal/compiler/lookup/ReferenceBinding;)V
      25: aload_0
      26: aload_1
      27: putfield      #33                 // Field originalMethod:Lorg/eclipse/jdt/internal/compiler/lookup/MethodBinding;
      30: aload_0
      31: aload_1
      32: getfield      #35                 // Field org/eclipse/jdt/internal/compiler/lookup/MethodBinding.parameterNonNullness:[Ljava/lang/Boolean;
      35: putfield      #39                 // Field parameterNonNullness:[Ljava/lang/Boolean;
      38: aload_0
      39: aload_1
      40: getfield      #40                 // Field org/eclipse/jdt/internal/compiler/lookup/MethodBinding.defaultNullness:I
      43: putfield      #43                 // Field defaultNullness:I
      46: return

  public org.eclipse.jdt.internal.compiler.lookup.MethodBinding original();
    Code:
       0: aload_0
       1: getfield      #33                 // Field originalMethod:Lorg/eclipse/jdt/internal/compiler/lookup/MethodBinding;
       4: invokevirtual #52                 // Method org/eclipse/jdt/internal/compiler/lookup/MethodBinding.original:()Lorg/eclipse/jdt/internal/compiler/lookup/MethodBinding;
       7: areturn
}
