Compiled from "PolymorphicMethodBinding.java"
public class org.eclipse.jdt.internal.compiler.lookup.PolymorphicMethodBinding extends org.eclipse.jdt.internal.compiler.lookup.MethodBinding {
  protected org.eclipse.jdt.internal.compiler.lookup.MethodBinding polymorphicMethod;

  public org.eclipse.jdt.internal.compiler.lookup.PolymorphicMethodBinding(org.eclipse.jdt.internal.compiler.lookup.MethodBinding, org.eclipse.jdt.internal.compiler.lookup.TypeBinding[]);
    Code:
       0: aload_0
       1: aload_1
       2: getfield      #10                 // Field org/eclipse/jdt/internal/compiler/lookup/MethodBinding.modifiers:I
       5: aload_1
       6: getfield      #14                 // Field org/eclipse/jdt/internal/compiler/lookup/MethodBinding.selector:[C
       9: aload_1
      10: getfield      #18                 // Field org/eclipse/jdt/internal/compiler/lookup/MethodBinding.returnType:Lorg/eclipse/jdt/internal/compiler/lookup/TypeBinding;
      13: aload_2
      14: aload_1
      15: getfield      #22                 // Field org/eclipse/jdt/internal/compiler/lookup/MethodBinding.thrownExceptions:[Lorg/eclipse/jdt/internal/compiler/lookup/ReferenceBinding;
      18: aload_1
      19: getfield      #26                 // Field org/eclipse/jdt/internal/compiler/lookup/MethodBinding.declaringClass:Lorg/eclipse/jdt/internal/compiler/lookup/ReferenceBinding;
      22: invokespecial #30                 // Method org/eclipse/jdt/internal/compiler/lookup/MethodBinding."<init>":(I[CLorg/eclipse/jdt/internal/compiler/lookup/TypeBinding;[Lorg/eclipse/jdt/internal/compiler/lookup/TypeBinding;[Lorg/eclipse/jdt/internal/compiler/lookup/ReferenceBinding;Lorg/eclipse/jdt/internal/compiler/lookup/ReferenceBinding;)V
      25: aload_0
      26: aload_1
      27: putfield      #33                 // Field polymorphicMethod:Lorg/eclipse/jdt/internal/compiler/lookup/MethodBinding;
      30: aload_0
      31: aload_1
      32: getfield      #35                 // Field org/eclipse/jdt/internal/compiler/lookup/MethodBinding.tagBits:J
      35: putfield      #39                 // Field tagBits:J
      38: return

  public org.eclipse.jdt.internal.compiler.lookup.PolymorphicMethodBinding(org.eclipse.jdt.internal.compiler.lookup.MethodBinding, org.eclipse.jdt.internal.compiler.lookup.TypeBinding, org.eclipse.jdt.internal.compiler.lookup.TypeBinding[]);
    Code:
       0: aload_0
       1: aload_1
       2: getfield      #10                 // Field org/eclipse/jdt/internal/compiler/lookup/MethodBinding.modifiers:I
       5: aload_1
       6: getfield      #14                 // Field org/eclipse/jdt/internal/compiler/lookup/MethodBinding.selector:[C
       9: aload_2
      10: aload_3
      11: aload_1
      12: getfield      #22                 // Field org/eclipse/jdt/internal/compiler/lookup/MethodBinding.thrownExceptions:[Lorg/eclipse/jdt/internal/compiler/lookup/ReferenceBinding;
      15: aload_1
      16: getfield      #26                 // Field org/eclipse/jdt/internal/compiler/lookup/MethodBinding.declaringClass:Lorg/eclipse/jdt/internal/compiler/lookup/ReferenceBinding;
      19: invokespecial #30                 // Method org/eclipse/jdt/internal/compiler/lookup/MethodBinding."<init>":(I[CLorg/eclipse/jdt/internal/compiler/lookup/TypeBinding;[Lorg/eclipse/jdt/internal/compiler/lookup/TypeBinding;[Lorg/eclipse/jdt/internal/compiler/lookup/ReferenceBinding;Lorg/eclipse/jdt/internal/compiler/lookup/ReferenceBinding;)V
      22: aload_0
      23: aload_1
      24: putfield      #33                 // Field polymorphicMethod:Lorg/eclipse/jdt/internal/compiler/lookup/MethodBinding;
      27: aload_0
      28: aload_1
      29: getfield      #35                 // Field org/eclipse/jdt/internal/compiler/lookup/MethodBinding.tagBits:J
      32: putfield      #39                 // Field tagBits:J
      35: return

  public org.eclipse.jdt.internal.compiler.lookup.MethodBinding original();
    Code:
       0: aload_0
       1: getfield      #33                 // Field polymorphicMethod:Lorg/eclipse/jdt/internal/compiler/lookup/MethodBinding;
       4: areturn

  public boolean isPolymorphic();
    Code:
       0: iconst_1
       1: ireturn

  public boolean matches(org.eclipse.jdt.internal.compiler.lookup.TypeBinding[], org.eclipse.jdt.internal.compiler.lookup.TypeBinding);
    Code:
       0: aload_0
       1: getfield      #53                 // Field parameters:[Lorg/eclipse/jdt/internal/compiler/lookup/TypeBinding;
       4: ifnonnull     11
       7: iconst_0
       8: goto          16
      11: aload_0
      12: getfield      #53                 // Field parameters:[Lorg/eclipse/jdt/internal/compiler/lookup/TypeBinding;
      15: arraylength
      16: istore_3
      17: aload_1
      18: ifnonnull     25
      21: iconst_0
      22: goto          27
      25: aload_1
      26: arraylength
      27: istore        4
      29: iload         4
      31: iload_3
      32: if_icmpeq     37
      35: iconst_0
      36: ireturn
      37: iconst_0
      38: istore        5
      40: goto          65
      43: aload_0
      44: getfield      #53                 // Field parameters:[Lorg/eclipse/jdt/internal/compiler/lookup/TypeBinding;
      47: iload         5
      49: aaload
      50: aload_1
      51: iload         5
      53: aaload
      54: invokestatic  #56                 // Method org/eclipse/jdt/internal/compiler/lookup/TypeBinding.notEquals:(Lorg/eclipse/jdt/internal/compiler/lookup/TypeBinding;Lorg/eclipse/jdt/internal/compiler/lookup/TypeBinding;)Z
      57: ifeq          62
      60: iconst_0
      61: ireturn
      62: iinc          5, 1
      65: iload         5
      67: iload_3
      68: if_icmplt     43
      71: aload_0
      72: getfield      #62                 // Field returnType:Lorg/eclipse/jdt/internal/compiler/lookup/TypeBinding;
      75: astore        5
      77: aload_2
      78: ifnonnull     88
      81: aload         5
      83: ifnull        106
      86: iconst_0
      87: ireturn
      88: aload         5
      90: ifnonnull     95
      93: iconst_0
      94: ireturn
      95: aload_2
      96: aload         5
      98: invokestatic  #56                 // Method org/eclipse/jdt/internal/compiler/lookup/TypeBinding.notEquals:(Lorg/eclipse/jdt/internal/compiler/lookup/TypeBinding;Lorg/eclipse/jdt/internal/compiler/lookup/TypeBinding;)Z
     101: ifeq          106
     104: iconst_0
     105: ireturn
     106: iconst_1
     107: ireturn

  public boolean isVarargs();
    Code:
       0: iconst_0
       1: ireturn
}
