Compiled from "ClusterEvent.scala"
public final class akka.cluster.ClusterEvent {
  public static akka.cluster.ClusterEvent$ClusterShuttingDown$ getClusterShuttingDownInstance();
    Code:
       0: getstatic     #16                 // Field akka/cluster/ClusterEvent$.MODULE$:Lakka/cluster/ClusterEvent$;
       3: invokevirtual #18                 // Method akka/cluster/ClusterEvent$.getClusterShuttingDownInstance:()Lakka/cluster/ClusterEvent$ClusterShuttingDown$;
       6: areturn

  public static akka.cluster.ClusterEvent$InitialStateAsEvents$ initialStateAsEvents();
    Code:
       0: getstatic     #16                 // Field akka/cluster/ClusterEvent$.MODULE$:Lakka/cluster/ClusterEvent$;
       3: invokevirtual #22                 // Method akka/cluster/ClusterEvent$.initialStateAsEvents:()Lakka/cluster/ClusterEvent$InitialStateAsEvents$;
       6: areturn

  public static akka.cluster.ClusterEvent$InitialStateAsSnapshot$ initialStateAsSnapshot();
    Code:
       0: getstatic     #16                 // Field akka/cluster/ClusterEvent$.MODULE$:Lakka/cluster/ClusterEvent$;
       3: invokevirtual #26                 // Method akka/cluster/ClusterEvent$.initialStateAsSnapshot:()Lakka/cluster/ClusterEvent$InitialStateAsSnapshot$;
       6: areturn
}
