Compiled from "ClusterEvent.scala"
public final class akka.cluster.ClusterEvent$MemberRemoved implements akka.cluster.ClusterEvent$MemberEvent,scala.Product,scala.Serializable {
  private final akka.cluster.Member member;

  private final akka.cluster.MemberStatus previousStatus;

  public akka.cluster.Member member();
    Code:
       0: aload_0
       1: getfield      #18                 // Field member:Lakka/cluster/Member;
       4: areturn

  public akka.cluster.MemberStatus previousStatus();
    Code:
       0: aload_0
       1: getfield      #23                 // Field previousStatus:Lakka/cluster/MemberStatus;
       4: areturn

  public akka.cluster.ClusterEvent$MemberRemoved copy(akka.cluster.Member, akka.cluster.MemberStatus);
    Code:
       0: new           #2                  // class akka/cluster/ClusterEvent$MemberRemoved
       3: dup
       4: aload_1
       5: aload_2
       6: invokespecial #29                 // Method "<init>":(Lakka/cluster/Member;Lakka/cluster/MemberStatus;)V
       9: areturn

  public akka.cluster.Member copy$default$1();
    Code:
       0: aload_0
       1: invokevirtual #32                 // Method member:()Lakka/cluster/Member;
       4: areturn

  public akka.cluster.MemberStatus copy$default$2();
    Code:
       0: aload_0
       1: invokevirtual #35                 // Method previousStatus:()Lakka/cluster/MemberStatus;
       4: areturn

  public java.lang.String productPrefix();
    Code:
       0: ldc           #39                 // String MemberRemoved
       2: areturn

  public int productArity();
    Code:
       0: iconst_2
       1: ireturn

  public java.lang.Object productElement(int);
    Code:
       0: iload_1
       1: istore_2
       2: iload_2
       3: tableswitch   { // 0 to 1
                     0: 46
                     1: 39
               default: 24
          }
      24: new           #45                 // class java/lang/IndexOutOfBoundsException
      27: dup
      28: iload_1
      29: invokestatic  #51                 // Method scala/runtime/BoxesRunTime.boxToInteger:(I)Ljava/lang/Integer;
      32: invokevirtual #54                 // Method java/lang/Object.toString:()Ljava/lang/String;
      35: invokespecial #57                 // Method java/lang/IndexOutOfBoundsException."<init>":(Ljava/lang/String;)V
      38: athrow
      39: aload_0
      40: invokevirtual #35                 // Method previousStatus:()Lakka/cluster/MemberStatus;
      43: goto          50
      46: aload_0
      47: invokevirtual #32                 // Method member:()Lakka/cluster/Member;
      50: areturn

  public scala.collection.Iterator<java.lang.Object> productIterator();
    Code:
       0: getstatic     #67                 // Field scala/runtime/ScalaRunTime$.MODULE$:Lscala/runtime/ScalaRunTime$;
       3: aload_0
       4: invokevirtual #71                 // Method scala/runtime/ScalaRunTime$.typedProductIterator:(Lscala/Product;)Lscala/collection/Iterator;
       7: areturn

  public boolean canEqual(java.lang.Object);
    Code:
       0: aload_1
       1: instanceof    #2                  // class akka/cluster/ClusterEvent$MemberRemoved
       4: ireturn

  public int hashCode();
    Code:
       0: getstatic     #67                 // Field scala/runtime/ScalaRunTime$.MODULE$:Lscala/runtime/ScalaRunTime$;
       3: aload_0
       4: invokevirtual #79                 // Method scala/runtime/ScalaRunTime$._hashCode:(Lscala/Product;)I
       7: ireturn

  public java.lang.String toString();
    Code:
       0: getstatic     #67                 // Field scala/runtime/ScalaRunTime$.MODULE$:Lscala/runtime/ScalaRunTime$;
       3: aload_0
       4: invokevirtual #83                 // Method scala/runtime/ScalaRunTime$._toString:(Lscala/Product;)Ljava/lang/String;
       7: areturn

  public boolean equals(java.lang.Object);
    Code:
       0: aload_0
       1: aload_1
       2: if_acmpeq     103
       5: aload_1
       6: astore_2
       7: aload_2
       8: instanceof    #2                  // class akka/cluster/ClusterEvent$MemberRemoved
      11: ifeq          19
      14: iconst_1
      15: istore_3
      16: goto          21
      19: iconst_0
      20: istore_3
      21: iload_3
      22: ifeq          107
      25: aload_1
      26: checkcast     #2                  // class akka/cluster/ClusterEvent$MemberRemoved
      29: astore        4
      31: aload_0
      32: invokevirtual #32                 // Method member:()Lakka/cluster/Member;
      35: aload         4
      37: invokevirtual #32                 // Method member:()Lakka/cluster/Member;
      40: astore        5
      42: dup
      43: ifnonnull     55
      46: pop
      47: aload         5
      49: ifnull        63
      52: goto          99
      55: aload         5
      57: invokevirtual #86                 // Method java/lang/Object.equals:(Ljava/lang/Object;)Z
      60: ifeq          99
      63: aload_0
      64: invokevirtual #35                 // Method previousStatus:()Lakka/cluster/MemberStatus;
      67: aload         4
      69: invokevirtual #35                 // Method previousStatus:()Lakka/cluster/MemberStatus;
      72: astore        6
      74: dup
      75: ifnonnull     87
      78: pop
      79: aload         6
      81: ifnull        95
      84: goto          99
      87: aload         6
      89: invokevirtual #86                 // Method java/lang/Object.equals:(Ljava/lang/Object;)Z
      92: ifeq          99
      95: iconst_1
      96: goto          100
      99: iconst_0
     100: ifeq          107
     103: iconst_1
     104: goto          108
     107: iconst_0
     108: ireturn

  public akka.cluster.ClusterEvent$MemberRemoved(akka.cluster.Member, akka.cluster.MemberStatus);
    Code:
       0: aload_0
       1: aload_1
       2: putfield      #18                 // Field member:Lakka/cluster/Member;
       5: aload_0
       6: aload_2
       7: putfield      #23                 // Field previousStatus:Lakka/cluster/MemberStatus;
      10: aload_0
      11: invokespecial #93                 // Method java/lang/Object."<init>":()V
      14: aload_0
      15: invokestatic  #99                 // Method scala/Product$class.$init$:(Lscala/Product;)V
      18: aload_1
      19: invokevirtual #102                // Method akka/cluster/Member.status:()Lakka/cluster/MemberStatus;
      22: getstatic     #107                // Field akka/cluster/MemberStatus$Removed$.MODULE$:Lakka/cluster/MemberStatus$Removed$;
      25: astore_3
      26: dup
      27: ifnonnull     38
      30: pop
      31: aload_3
      32: ifnull        45
      35: goto          46
      38: aload_3
      39: invokevirtual #86                 // Method java/lang/Object.equals:(Ljava/lang/Object;)Z
      42: ifeq          46
      45: return
      46: new           #109                // class java/lang/IllegalArgumentException
      49: dup
      50: new           #111                // class scala/collection/mutable/StringBuilder
      53: dup
      54: invokespecial #112                // Method scala/collection/mutable/StringBuilder."<init>":()V
      57: ldc           #114                // String Expected Removed status, got:
      59: invokevirtual #118                // Method scala/collection/mutable/StringBuilder.append:(Ljava/lang/Object;)Lscala/collection/mutable/StringBuilder;
      62: aload_1
      63: invokevirtual #118                // Method scala/collection/mutable/StringBuilder.append:(Ljava/lang/Object;)Lscala/collection/mutable/StringBuilder;
      66: invokevirtual #119                // Method scala/collection/mutable/StringBuilder.toString:()Ljava/lang/String;
      69: invokespecial #120                // Method java/lang/IllegalArgumentException."<init>":(Ljava/lang/String;)V
      72: athrow
}
