Compiled from "ClusterReadView.scala"
public final class akka.cluster.ClusterReadView$$anonfun$1$$anon$1$$anonfun$receive$1 extends scala.runtime.AbstractPartialFunction<java.lang.Object, scala.runtime.BoxedUnit> implements scala.Serializable {
  public static final long serialVersionUID;

  private final akka.cluster.ClusterReadView$$anonfun$1$$anon$1 $outer;

  public final <A1, B1> B1 applyOrElse(A1, scala.Function1<A1, B1>);
    Code:
       0: aload_1
       1: astore_3
       2: aload_3
       3: instanceof    #23                 // class akka/cluster/ClusterEvent$ClusterDomainEvent
       6: ifeq          1184
       9: aload_3
      10: checkcast     #23                 // class akka/cluster/ClusterEvent$ClusterDomainEvent
      13: astore        4
      15: aload         4
      17: astore        6
      19: aload         6
      21: instanceof    #25                 // class akka/cluster/ClusterEvent$SeenChanged
      24: ifeq          124
      27: aload         6
      29: checkcast     #25                 // class akka/cluster/ClusterEvent$SeenChanged
      32: astore        7
      34: aload         7
      36: invokevirtual #29                 // Method akka/cluster/ClusterEvent$SeenChanged.seenBy:()Lscala/collection/immutable/Set;
      39: astore        8
      41: aload_0
      42: getfield      #31                 // Field $outer:Lakka/cluster/ClusterReadView$$anonfun$1$$anon$1;
      45: invokevirtual #35                 // Method akka/cluster/ClusterReadView$$anonfun$1$$anon$1.akka$cluster$ClusterReadView$$anonfun$$anon$$$outer:()Lakka/cluster/ClusterReadView$$anonfun$1;
      48: invokevirtual #41                 // Method akka/cluster/ClusterReadView$$anonfun$1.akka$cluster$ClusterReadView$$anonfun$$$outer:()Lakka/cluster/ClusterReadView;
      51: aload_0
      52: getfield      #31                 // Field $outer:Lakka/cluster/ClusterReadView$$anonfun$1$$anon$1;
      55: invokevirtual #35                 // Method akka/cluster/ClusterReadView$$anonfun$1$$anon$1.akka$cluster$ClusterReadView$$anonfun$$anon$$$outer:()Lakka/cluster/ClusterReadView$$anonfun$1;
      58: invokevirtual #41                 // Method akka/cluster/ClusterReadView$$anonfun$1.akka$cluster$ClusterReadView$$anonfun$$$outer:()Lakka/cluster/ClusterReadView;
      61: invokevirtual #47                 // Method akka/cluster/ClusterReadView.akka$cluster$ClusterReadView$$_state:()Lakka/cluster/ClusterEvent$CurrentClusterState;
      64: astore        10
      66: aload         8
      68: astore        11
      70: aload         10
      72: invokevirtual #53                 // Method akka/cluster/ClusterEvent$CurrentClusterState.copy$default$1:()Lscala/collection/immutable/SortedSet;
      75: astore        12
      77: aload         10
      79: invokevirtual #56                 // Method akka/cluster/ClusterEvent$CurrentClusterState.copy$default$2:()Lscala/collection/immutable/Set;
      82: astore        13
      84: aload         10
      86: invokevirtual #60                 // Method akka/cluster/ClusterEvent$CurrentClusterState.copy$default$4:()Lscala/Option;
      89: astore        14
      91: aload         10
      93: invokevirtual #64                 // Method akka/cluster/ClusterEvent$CurrentClusterState.copy$default$5:()Lscala/collection/immutable/Map;
      96: astore        15
      98: aload         10
     100: aload         12
     102: aload         13
     104: aload         11
     106: aload         14
     108: aload         15
     110: invokevirtual #68                 // Method akka/cluster/ClusterEvent$CurrentClusterState.copy:(Lscala/collection/immutable/SortedSet;Lscala/collection/immutable/Set;Lscala/collection/immutable/Set;Lscala/Option;Lscala/collection/immutable/Map;)Lakka/cluster/ClusterEvent$CurrentClusterState;
     113: invokevirtual #72                 // Method akka/cluster/ClusterReadView.akka$cluster$ClusterReadView$$_state_$eq:(Lakka/cluster/ClusterEvent$CurrentClusterState;)V
     116: getstatic     #78                 // Field scala/runtime/BoxedUnit.UNIT:Lscala/runtime/BoxedUnit;
     119: astore        9
     121: goto          1166
     124: aload         6
     126: instanceof    #80                 // class akka/cluster/ClusterEvent$ReachabilityChanged
     129: ifeq          169
     132: aload         6
     134: checkcast     #80                 // class akka/cluster/ClusterEvent$ReachabilityChanged
     137: astore        16
     139: aload         16
     141: invokevirtual #84                 // Method akka/cluster/ClusterEvent$ReachabilityChanged.reachability:()Lakka/cluster/Reachability;
     144: astore        17
     146: aload_0
     147: getfield      #31                 // Field $outer:Lakka/cluster/ClusterReadView$$anonfun$1$$anon$1;
     150: invokevirtual #35                 // Method akka/cluster/ClusterReadView$$anonfun$1$$anon$1.akka$cluster$ClusterReadView$$anonfun$$anon$$$outer:()Lakka/cluster/ClusterReadView$$anonfun$1;
     153: invokevirtual #41                 // Method akka/cluster/ClusterReadView$$anonfun$1.akka$cluster$ClusterReadView$$anonfun$$$outer:()Lakka/cluster/ClusterReadView;
     156: aload         17
     158: invokevirtual #88                 // Method akka/cluster/ClusterReadView.akka$cluster$ClusterReadView$$_reachability_$eq:(Lakka/cluster/Reachability;)V
     161: getstatic     #78                 // Field scala/runtime/BoxedUnit.UNIT:Lscala/runtime/BoxedUnit;
     164: astore        9
     166: goto          1166
     169: aload         6
     171: instanceof    #90                 // class akka/cluster/ClusterEvent$MemberRemoved
     174: ifeq          319
     177: aload         6
     179: checkcast     #90                 // class akka/cluster/ClusterEvent$MemberRemoved
     182: astore        18
     184: aload         18
     186: invokevirtual #94                 // Method akka/cluster/ClusterEvent$MemberRemoved.member:()Lakka/cluster/Member;
     189: astore        19
     191: aload_0
     192: getfield      #31                 // Field $outer:Lakka/cluster/ClusterReadView$$anonfun$1$$anon$1;
     195: invokevirtual #35                 // Method akka/cluster/ClusterReadView$$anonfun$1$$anon$1.akka$cluster$ClusterReadView$$anonfun$$anon$$$outer:()Lakka/cluster/ClusterReadView$$anonfun$1;
     198: invokevirtual #41                 // Method akka/cluster/ClusterReadView$$anonfun$1.akka$cluster$ClusterReadView$$anonfun$$$outer:()Lakka/cluster/ClusterReadView;
     201: aload_0
     202: getfield      #31                 // Field $outer:Lakka/cluster/ClusterReadView$$anonfun$1$$anon$1;
     205: invokevirtual #35                 // Method akka/cluster/ClusterReadView$$anonfun$1$$anon$1.akka$cluster$ClusterReadView$$anonfun$$anon$$$outer:()Lakka/cluster/ClusterReadView$$anonfun$1;
     208: invokevirtual #41                 // Method akka/cluster/ClusterReadView$$anonfun$1.akka$cluster$ClusterReadView$$anonfun$$$outer:()Lakka/cluster/ClusterReadView;
     211: invokevirtual #47                 // Method akka/cluster/ClusterReadView.akka$cluster$ClusterReadView$$_state:()Lakka/cluster/ClusterEvent$CurrentClusterState;
     214: astore        20
     216: aload_0
     217: getfield      #31                 // Field $outer:Lakka/cluster/ClusterReadView$$anonfun$1$$anon$1;
     220: invokevirtual #35                 // Method akka/cluster/ClusterReadView$$anonfun$1$$anon$1.akka$cluster$ClusterReadView$$anonfun$$anon$$$outer:()Lakka/cluster/ClusterReadView$$anonfun$1;
     223: invokevirtual #41                 // Method akka/cluster/ClusterReadView$$anonfun$1.akka$cluster$ClusterReadView$$anonfun$$$outer:()Lakka/cluster/ClusterReadView;
     226: invokevirtual #47                 // Method akka/cluster/ClusterReadView.akka$cluster$ClusterReadView$$_state:()Lakka/cluster/ClusterEvent$CurrentClusterState;
     229: invokevirtual #97                 // Method akka/cluster/ClusterEvent$CurrentClusterState.members:()Lscala/collection/immutable/SortedSet;
     232: aload         19
     234: invokeinterface #103,  2          // InterfaceMethod scala/collection/immutable/SortedSet.$minus:(Ljava/lang/Object;)Lscala/collection/Set;
     239: checkcast     #99                 // class scala/collection/immutable/SortedSet
     242: astore        21
     244: aload_0
     245: getfield      #31                 // Field $outer:Lakka/cluster/ClusterReadView$$anonfun$1$$anon$1;
     248: invokevirtual #35                 // Method akka/cluster/ClusterReadView$$anonfun$1$$anon$1.akka$cluster$ClusterReadView$$anonfun$$anon$$$outer:()Lakka/cluster/ClusterReadView$$anonfun$1;
     251: invokevirtual #41                 // Method akka/cluster/ClusterReadView$$anonfun$1.akka$cluster$ClusterReadView$$anonfun$$$outer:()Lakka/cluster/ClusterReadView;
     254: invokevirtual #47                 // Method akka/cluster/ClusterReadView.akka$cluster$ClusterReadView$$_state:()Lakka/cluster/ClusterEvent$CurrentClusterState;
     257: invokevirtual #106                // Method akka/cluster/ClusterEvent$CurrentClusterState.unreachable:()Lscala/collection/immutable/Set;
     260: aload         19
     262: invokeinterface #109,  2          // InterfaceMethod scala/collection/immutable/Set.$minus:(Ljava/lang/Object;)Lscala/collection/Set;
     267: checkcast     #108                // class scala/collection/immutable/Set
     270: astore        22
     272: aload         20
     274: invokevirtual #112                // Method akka/cluster/ClusterEvent$CurrentClusterState.copy$default$3:()Lscala/collection/immutable/Set;
     277: astore        23
     279: aload         20
     281: invokevirtual #60                 // Method akka/cluster/ClusterEvent$CurrentClusterState.copy$default$4:()Lscala/Option;
     284: astore        24
     286: aload         20
     288: invokevirtual #64                 // Method akka/cluster/ClusterEvent$CurrentClusterState.copy$default$5:()Lscala/collection/immutable/Map;
     291: astore        25
     293: aload         20
     295: aload         21
     297: aload         22
     299: aload         23
     301: aload         24
     303: aload         25
     305: invokevirtual #68                 // Method akka/cluster/ClusterEvent$CurrentClusterState.copy:(Lscala/collection/immutable/SortedSet;Lscala/collection/immutable/Set;Lscala/collection/immutable/Set;Lscala/Option;Lscala/collection/immutable/Map;)Lakka/cluster/ClusterEvent$CurrentClusterState;
     308: invokevirtual #72                 // Method akka/cluster/ClusterReadView.akka$cluster$ClusterReadView$$_state_$eq:(Lakka/cluster/ClusterEvent$CurrentClusterState;)V
     311: getstatic     #78                 // Field scala/runtime/BoxedUnit.UNIT:Lscala/runtime/BoxedUnit;
     314: astore        9
     316: goto          1166
     319: aload         6
     321: instanceof    #114                // class akka/cluster/ClusterEvent$UnreachableMember
     324: ifeq          455
     327: aload         6
     329: checkcast     #114                // class akka/cluster/ClusterEvent$UnreachableMember
     332: astore        26
     334: aload         26
     336: invokevirtual #115                // Method akka/cluster/ClusterEvent$UnreachableMember.member:()Lakka/cluster/Member;
     339: astore        27
     341: aload_0
     342: getfield      #31                 // Field $outer:Lakka/cluster/ClusterReadView$$anonfun$1$$anon$1;
     345: invokevirtual #35                 // Method akka/cluster/ClusterReadView$$anonfun$1$$anon$1.akka$cluster$ClusterReadView$$anonfun$$anon$$$outer:()Lakka/cluster/ClusterReadView$$anonfun$1;
     348: invokevirtual #41                 // Method akka/cluster/ClusterReadView$$anonfun$1.akka$cluster$ClusterReadView$$anonfun$$$outer:()Lakka/cluster/ClusterReadView;
     351: aload_0
     352: getfield      #31                 // Field $outer:Lakka/cluster/ClusterReadView$$anonfun$1$$anon$1;
     355: invokevirtual #35                 // Method akka/cluster/ClusterReadView$$anonfun$1$$anon$1.akka$cluster$ClusterReadView$$anonfun$$anon$$$outer:()Lakka/cluster/ClusterReadView$$anonfun$1;
     358: invokevirtual #41                 // Method akka/cluster/ClusterReadView$$anonfun$1.akka$cluster$ClusterReadView$$anonfun$$$outer:()Lakka/cluster/ClusterReadView;
     361: invokevirtual #47                 // Method akka/cluster/ClusterReadView.akka$cluster$ClusterReadView$$_state:()Lakka/cluster/ClusterEvent$CurrentClusterState;
     364: astore        28
     366: aload_0
     367: getfield      #31                 // Field $outer:Lakka/cluster/ClusterReadView$$anonfun$1$$anon$1;
     370: invokevirtual #35                 // Method akka/cluster/ClusterReadView$$anonfun$1$$anon$1.akka$cluster$ClusterReadView$$anonfun$$anon$$$outer:()Lakka/cluster/ClusterReadView$$anonfun$1;
     373: invokevirtual #41                 // Method akka/cluster/ClusterReadView$$anonfun$1.akka$cluster$ClusterReadView$$anonfun$$$outer:()Lakka/cluster/ClusterReadView;
     376: invokevirtual #47                 // Method akka/cluster/ClusterReadView.akka$cluster$ClusterReadView$$_state:()Lakka/cluster/ClusterEvent$CurrentClusterState;
     379: invokevirtual #106                // Method akka/cluster/ClusterEvent$CurrentClusterState.unreachable:()Lscala/collection/immutable/Set;
     382: aload         27
     384: invokeinterface #109,  2          // InterfaceMethod scala/collection/immutable/Set.$minus:(Ljava/lang/Object;)Lscala/collection/Set;
     389: aload         27
     391: invokeinterface #120,  2          // InterfaceMethod scala/collection/Set.$plus:(Ljava/lang/Object;)Lscala/collection/Set;
     396: checkcast     #108                // class scala/collection/immutable/Set
     399: astore        29
     401: aload         28
     403: invokevirtual #53                 // Method akka/cluster/ClusterEvent$CurrentClusterState.copy$default$1:()Lscala/collection/immutable/SortedSet;
     406: astore        30
     408: aload         28
     410: invokevirtual #112                // Method akka/cluster/ClusterEvent$CurrentClusterState.copy$default$3:()Lscala/collection/immutable/Set;
     413: astore        31
     415: aload         28
     417: invokevirtual #60                 // Method akka/cluster/ClusterEvent$CurrentClusterState.copy$default$4:()Lscala/Option;
     420: astore        32
     422: aload         28
     424: invokevirtual #64                 // Method akka/cluster/ClusterEvent$CurrentClusterState.copy$default$5:()Lscala/collection/immutable/Map;
     427: astore        33
     429: aload         28
     431: aload         30
     433: aload         29
     435: aload         31
     437: aload         32
     439: aload         33
     441: invokevirtual #68                 // Method akka/cluster/ClusterEvent$CurrentClusterState.copy:(Lscala/collection/immutable/SortedSet;Lscala/collection/immutable/Set;Lscala/collection/immutable/Set;Lscala/Option;Lscala/collection/immutable/Map;)Lakka/cluster/ClusterEvent$CurrentClusterState;
     444: invokevirtual #72                 // Method akka/cluster/ClusterReadView.akka$cluster$ClusterReadView$$_state_$eq:(Lakka/cluster/ClusterEvent$CurrentClusterState;)V
     447: getstatic     #78                 // Field scala/runtime/BoxedUnit.UNIT:Lscala/runtime/BoxedUnit;
     450: astore        9
     452: goto          1166
     455: aload         6
     457: instanceof    #122                // class akka/cluster/ClusterEvent$ReachableMember
     460: ifeq          584
     463: aload         6
     465: checkcast     #122                // class akka/cluster/ClusterEvent$ReachableMember
     468: astore        34
     470: aload         34
     472: invokevirtual #123                // Method akka/cluster/ClusterEvent$ReachableMember.member:()Lakka/cluster/Member;
     475: astore        35
     477: aload_0
     478: getfield      #31                 // Field $outer:Lakka/cluster/ClusterReadView$$anonfun$1$$anon$1;
     481: invokevirtual #35                 // Method akka/cluster/ClusterReadView$$anonfun$1$$anon$1.akka$cluster$ClusterReadView$$anonfun$$anon$$$outer:()Lakka/cluster/ClusterReadView$$anonfun$1;
     484: invokevirtual #41                 // Method akka/cluster/ClusterReadView$$anonfun$1.akka$cluster$ClusterReadView$$anonfun$$$outer:()Lakka/cluster/ClusterReadView;
     487: aload_0
     488: getfield      #31                 // Field $outer:Lakka/cluster/ClusterReadView$$anonfun$1$$anon$1;
     491: invokevirtual #35                 // Method akka/cluster/ClusterReadView$$anonfun$1$$anon$1.akka$cluster$ClusterReadView$$anonfun$$anon$$$outer:()Lakka/cluster/ClusterReadView$$anonfun$1;
     494: invokevirtual #41                 // Method akka/cluster/ClusterReadView$$anonfun$1.akka$cluster$ClusterReadView$$anonfun$$$outer:()Lakka/cluster/ClusterReadView;
     497: invokevirtual #47                 // Method akka/cluster/ClusterReadView.akka$cluster$ClusterReadView$$_state:()Lakka/cluster/ClusterEvent$CurrentClusterState;
     500: astore        36
     502: aload_0
     503: getfield      #31                 // Field $outer:Lakka/cluster/ClusterReadView$$anonfun$1$$anon$1;
     506: invokevirtual #35                 // Method akka/cluster/ClusterReadView$$anonfun$1$$anon$1.akka$cluster$ClusterReadView$$anonfun$$anon$$$outer:()Lakka/cluster/ClusterReadView$$anonfun$1;
     509: invokevirtual #41                 // Method akka/cluster/ClusterReadView$$anonfun$1.akka$cluster$ClusterReadView$$anonfun$$$outer:()Lakka/cluster/ClusterReadView;
     512: invokevirtual #47                 // Method akka/cluster/ClusterReadView.akka$cluster$ClusterReadView$$_state:()Lakka/cluster/ClusterEvent$CurrentClusterState;
     515: invokevirtual #106                // Method akka/cluster/ClusterEvent$CurrentClusterState.unreachable:()Lscala/collection/immutable/Set;
     518: aload         35
     520: invokeinterface #109,  2          // InterfaceMethod scala/collection/immutable/Set.$minus:(Ljava/lang/Object;)Lscala/collection/Set;
     525: checkcast     #108                // class scala/collection/immutable/Set
     528: astore        37
     530: aload         36
     532: invokevirtual #53                 // Method akka/cluster/ClusterEvent$CurrentClusterState.copy$default$1:()Lscala/collection/immutable/SortedSet;
     535: astore        38
     537: aload         36
     539: invokevirtual #112                // Method akka/cluster/ClusterEvent$CurrentClusterState.copy$default$3:()Lscala/collection/immutable/Set;
     542: astore        39
     544: aload         36
     546: invokevirtual #60                 // Method akka/cluster/ClusterEvent$CurrentClusterState.copy$default$4:()Lscala/Option;
     549: astore        40
     551: aload         36
     553: invokevirtual #64                 // Method akka/cluster/ClusterEvent$CurrentClusterState.copy$default$5:()Lscala/collection/immutable/Map;
     556: astore        41
     558: aload         36
     560: aload         38
     562: aload         37
     564: aload         39
     566: aload         40
     568: aload         41
     570: invokevirtual #68                 // Method akka/cluster/ClusterEvent$CurrentClusterState.copy:(Lscala/collection/immutable/SortedSet;Lscala/collection/immutable/Set;Lscala/collection/immutable/Set;Lscala/Option;Lscala/collection/immutable/Map;)Lakka/cluster/ClusterEvent$CurrentClusterState;
     573: invokevirtual #72                 // Method akka/cluster/ClusterReadView.akka$cluster$ClusterReadView$$_state_$eq:(Lakka/cluster/ClusterEvent$CurrentClusterState;)V
     576: getstatic     #78                 // Field scala/runtime/BoxedUnit.UNIT:Lscala/runtime/BoxedUnit;
     579: astore        9
     581: goto          1166
     584: aload         6
     586: instanceof    #125                // class akka/cluster/ClusterEvent$MemberEvent
     589: ifeq          815
     592: aload         6
     594: checkcast     #125                // class akka/cluster/ClusterEvent$MemberEvent
     597: astore        42
     599: aload_0
     600: getfield      #31                 // Field $outer:Lakka/cluster/ClusterReadView$$anonfun$1$$anon$1;
     603: invokevirtual #35                 // Method akka/cluster/ClusterReadView$$anonfun$1$$anon$1.akka$cluster$ClusterReadView$$anonfun$$anon$$$outer:()Lakka/cluster/ClusterReadView$$anonfun$1;
     606: invokevirtual #41                 // Method akka/cluster/ClusterReadView$$anonfun$1.akka$cluster$ClusterReadView$$anonfun$$$outer:()Lakka/cluster/ClusterReadView;
     609: invokevirtual #47                 // Method akka/cluster/ClusterReadView.akka$cluster$ClusterReadView$$_state:()Lakka/cluster/ClusterEvent$CurrentClusterState;
     612: invokevirtual #106                // Method akka/cluster/ClusterEvent$CurrentClusterState.unreachable:()Lscala/collection/immutable/Set;
     615: aload         42
     617: invokeinterface #126,  1          // InterfaceMethod akka/cluster/ClusterEvent$MemberEvent.member:()Lakka/cluster/Member;
     622: invokeinterface #130,  2          // InterfaceMethod scala/collection/immutable/Set.contains:(Ljava/lang/Object;)Z
     627: ifeq          676
     630: aload_0
     631: getfield      #31                 // Field $outer:Lakka/cluster/ClusterReadView$$anonfun$1$$anon$1;
     634: invokevirtual #35                 // Method akka/cluster/ClusterReadView$$anonfun$1$$anon$1.akka$cluster$ClusterReadView$$anonfun$$anon$$$outer:()Lakka/cluster/ClusterReadView$$anonfun$1;
     637: invokevirtual #41                 // Method akka/cluster/ClusterReadView$$anonfun$1.akka$cluster$ClusterReadView$$anonfun$$$outer:()Lakka/cluster/ClusterReadView;
     640: invokevirtual #47                 // Method akka/cluster/ClusterReadView.akka$cluster$ClusterReadView$$_state:()Lakka/cluster/ClusterEvent$CurrentClusterState;
     643: invokevirtual #106                // Method akka/cluster/ClusterEvent$CurrentClusterState.unreachable:()Lscala/collection/immutable/Set;
     646: aload         42
     648: invokeinterface #126,  1          // InterfaceMethod akka/cluster/ClusterEvent$MemberEvent.member:()Lakka/cluster/Member;
     653: invokeinterface #109,  2          // InterfaceMethod scala/collection/immutable/Set.$minus:(Ljava/lang/Object;)Lscala/collection/Set;
     658: aload         42
     660: invokeinterface #126,  1          // InterfaceMethod akka/cluster/ClusterEvent$MemberEvent.member:()Lakka/cluster/Member;
     665: invokeinterface #120,  2          // InterfaceMethod scala/collection/Set.$plus:(Ljava/lang/Object;)Lscala/collection/Set;
     670: checkcast     #108                // class scala/collection/immutable/Set
     673: goto          692
     676: aload_0
     677: getfield      #31                 // Field $outer:Lakka/cluster/ClusterReadView$$anonfun$1$$anon$1;
     680: invokevirtual #35                 // Method akka/cluster/ClusterReadView$$anonfun$1$$anon$1.akka$cluster$ClusterReadView$$anonfun$$anon$$$outer:()Lakka/cluster/ClusterReadView$$anonfun$1;
     683: invokevirtual #41                 // Method akka/cluster/ClusterReadView$$anonfun$1.akka$cluster$ClusterReadView$$anonfun$$$outer:()Lakka/cluster/ClusterReadView;
     686: invokevirtual #47                 // Method akka/cluster/ClusterReadView.akka$cluster$ClusterReadView$$_state:()Lakka/cluster/ClusterEvent$CurrentClusterState;
     689: invokevirtual #106                // Method akka/cluster/ClusterEvent$CurrentClusterState.unreachable:()Lscala/collection/immutable/Set;
     692: astore        43
     694: aload_0
     695: getfield      #31                 // Field $outer:Lakka/cluster/ClusterReadView$$anonfun$1$$anon$1;
     698: invokevirtual #35                 // Method akka/cluster/ClusterReadView$$anonfun$1$$anon$1.akka$cluster$ClusterReadView$$anonfun$$anon$$$outer:()Lakka/cluster/ClusterReadView$$anonfun$1;
     701: invokevirtual #41                 // Method akka/cluster/ClusterReadView$$anonfun$1.akka$cluster$ClusterReadView$$anonfun$$$outer:()Lakka/cluster/ClusterReadView;
     704: aload_0
     705: getfield      #31                 // Field $outer:Lakka/cluster/ClusterReadView$$anonfun$1$$anon$1;
     708: invokevirtual #35                 // Method akka/cluster/ClusterReadView$$anonfun$1$$anon$1.akka$cluster$ClusterReadView$$anonfun$$anon$$$outer:()Lakka/cluster/ClusterReadView$$anonfun$1;
     711: invokevirtual #41                 // Method akka/cluster/ClusterReadView$$anonfun$1.akka$cluster$ClusterReadView$$anonfun$$$outer:()Lakka/cluster/ClusterReadView;
     714: invokevirtual #47                 // Method akka/cluster/ClusterReadView.akka$cluster$ClusterReadView$$_state:()Lakka/cluster/ClusterEvent$CurrentClusterState;
     717: astore        44
     719: aload_0
     720: getfield      #31                 // Field $outer:Lakka/cluster/ClusterReadView$$anonfun$1$$anon$1;
     723: invokevirtual #35                 // Method akka/cluster/ClusterReadView$$anonfun$1$$anon$1.akka$cluster$ClusterReadView$$anonfun$$anon$$$outer:()Lakka/cluster/ClusterReadView$$anonfun$1;
     726: invokevirtual #41                 // Method akka/cluster/ClusterReadView$$anonfun$1.akka$cluster$ClusterReadView$$anonfun$$$outer:()Lakka/cluster/ClusterReadView;
     729: invokevirtual #47                 // Method akka/cluster/ClusterReadView.akka$cluster$ClusterReadView$$_state:()Lakka/cluster/ClusterEvent$CurrentClusterState;
     732: invokevirtual #97                 // Method akka/cluster/ClusterEvent$CurrentClusterState.members:()Lscala/collection/immutable/SortedSet;
     735: aload         42
     737: invokeinterface #126,  1          // InterfaceMethod akka/cluster/ClusterEvent$MemberEvent.member:()Lakka/cluster/Member;
     742: invokeinterface #103,  2          // InterfaceMethod scala/collection/immutable/SortedSet.$minus:(Ljava/lang/Object;)Lscala/collection/Set;
     747: aload         42
     749: invokeinterface #126,  1          // InterfaceMethod akka/cluster/ClusterEvent$MemberEvent.member:()Lakka/cluster/Member;
     754: invokeinterface #120,  2          // InterfaceMethod scala/collection/Set.$plus:(Ljava/lang/Object;)Lscala/collection/Set;
     759: checkcast     #99                 // class scala/collection/immutable/SortedSet
     762: astore        45
     764: aload         43
     766: astore        46
     768: aload         44
     770: invokevirtual #112                // Method akka/cluster/ClusterEvent$CurrentClusterState.copy$default$3:()Lscala/collection/immutable/Set;
     773: astore        47
     775: aload         44
     777: invokevirtual #60                 // Method akka/cluster/ClusterEvent$CurrentClusterState.copy$default$4:()Lscala/Option;
     780: astore        48
     782: aload         44
     784: invokevirtual #64                 // Method akka/cluster/ClusterEvent$CurrentClusterState.copy$default$5:()Lscala/collection/immutable/Map;
     787: astore        49
     789: aload         44
     791: aload         45
     793: aload         46
     795: aload         47
     797: aload         48
     799: aload         49
     801: invokevirtual #68                 // Method akka/cluster/ClusterEvent$CurrentClusterState.copy:(Lscala/collection/immutable/SortedSet;Lscala/collection/immutable/Set;Lscala/collection/immutable/Set;Lscala/Option;Lscala/collection/immutable/Map;)Lakka/cluster/ClusterEvent$CurrentClusterState;
     804: invokevirtual #72                 // Method akka/cluster/ClusterReadView.akka$cluster$ClusterReadView$$_state_$eq:(Lakka/cluster/ClusterEvent$CurrentClusterState;)V
     807: getstatic     #78                 // Field scala/runtime/BoxedUnit.UNIT:Lscala/runtime/BoxedUnit;
     810: astore        9
     812: goto          1166
     815: aload         6
     817: instanceof    #132                // class akka/cluster/ClusterEvent$LeaderChanged
     820: ifeq          920
     823: aload         6
     825: checkcast     #132                // class akka/cluster/ClusterEvent$LeaderChanged
     828: astore        50
     830: aload         50
     832: invokevirtual #135                // Method akka/cluster/ClusterEvent$LeaderChanged.leader:()Lscala/Option;
     835: astore        51
     837: aload_0
     838: getfield      #31                 // Field $outer:Lakka/cluster/ClusterReadView$$anonfun$1$$anon$1;
     841: invokevirtual #35                 // Method akka/cluster/ClusterReadView$$anonfun$1$$anon$1.akka$cluster$ClusterReadView$$anonfun$$anon$$$outer:()Lakka/cluster/ClusterReadView$$anonfun$1;
     844: invokevirtual #41                 // Method akka/cluster/ClusterReadView$$anonfun$1.akka$cluster$ClusterReadView$$anonfun$$$outer:()Lakka/cluster/ClusterReadView;
     847: aload_0
     848: getfield      #31                 // Field $outer:Lakka/cluster/ClusterReadView$$anonfun$1$$anon$1;
     851: invokevirtual #35                 // Method akka/cluster/ClusterReadView$$anonfun$1$$anon$1.akka$cluster$ClusterReadView$$anonfun$$anon$$$outer:()Lakka/cluster/ClusterReadView$$anonfun$1;
     854: invokevirtual #41                 // Method akka/cluster/ClusterReadView$$anonfun$1.akka$cluster$ClusterReadView$$anonfun$$$outer:()Lakka/cluster/ClusterReadView;
     857: invokevirtual #47                 // Method akka/cluster/ClusterReadView.akka$cluster$ClusterReadView$$_state:()Lakka/cluster/ClusterEvent$CurrentClusterState;
     860: astore        52
     862: aload         51
     864: astore        53
     866: aload         52
     868: invokevirtual #53                 // Method akka/cluster/ClusterEvent$CurrentClusterState.copy$default$1:()Lscala/collection/immutable/SortedSet;
     871: astore        54
     873: aload         52
     875: invokevirtual #56                 // Method akka/cluster/ClusterEvent$CurrentClusterState.copy$default$2:()Lscala/collection/immutable/Set;
     878: astore        55
     880: aload         52
     882: invokevirtual #112                // Method akka/cluster/ClusterEvent$CurrentClusterState.copy$default$3:()Lscala/collection/immutable/Set;
     885: astore        56
     887: aload         52
     889: invokevirtual #64                 // Method akka/cluster/ClusterEvent$CurrentClusterState.copy$default$5:()Lscala/collection/immutable/Map;
     892: astore        57
     894: aload         52
     896: aload         54
     898: aload         55
     900: aload         56
     902: aload         53
     904: aload         57
     906: invokevirtual #68                 // Method akka/cluster/ClusterEvent$CurrentClusterState.copy:(Lscala/collection/immutable/SortedSet;Lscala/collection/immutable/Set;Lscala/collection/immutable/Set;Lscala/Option;Lscala/collection/immutable/Map;)Lakka/cluster/ClusterEvent$CurrentClusterState;
     909: invokevirtual #72                 // Method akka/cluster/ClusterReadView.akka$cluster$ClusterReadView$$_state_$eq:(Lakka/cluster/ClusterEvent$CurrentClusterState;)V
     912: getstatic     #78                 // Field scala/runtime/BoxedUnit.UNIT:Lscala/runtime/BoxedUnit;
     915: astore        9
     917: goto          1166
     920: aload         6
     922: instanceof    #137                // class akka/cluster/ClusterEvent$RoleLeaderChanged
     925: ifeq          1067
     928: aload         6
     930: checkcast     #137                // class akka/cluster/ClusterEvent$RoleLeaderChanged
     933: astore        58
     935: aload         58
     937: invokevirtual #141                // Method akka/cluster/ClusterEvent$RoleLeaderChanged.role:()Ljava/lang/String;
     940: astore        59
     942: aload         58
     944: invokevirtual #142                // Method akka/cluster/ClusterEvent$RoleLeaderChanged.leader:()Lscala/Option;
     947: astore        60
     949: aload_0
     950: getfield      #31                 // Field $outer:Lakka/cluster/ClusterReadView$$anonfun$1$$anon$1;
     953: invokevirtual #35                 // Method akka/cluster/ClusterReadView$$anonfun$1$$anon$1.akka$cluster$ClusterReadView$$anonfun$$anon$$$outer:()Lakka/cluster/ClusterReadView$$anonfun$1;
     956: invokevirtual #41                 // Method akka/cluster/ClusterReadView$$anonfun$1.akka$cluster$ClusterReadView$$anonfun$$$outer:()Lakka/cluster/ClusterReadView;
     959: aload_0
     960: getfield      #31                 // Field $outer:Lakka/cluster/ClusterReadView$$anonfun$1$$anon$1;
     963: invokevirtual #35                 // Method akka/cluster/ClusterReadView$$anonfun$1$$anon$1.akka$cluster$ClusterReadView$$anonfun$$anon$$$outer:()Lakka/cluster/ClusterReadView$$anonfun$1;
     966: invokevirtual #41                 // Method akka/cluster/ClusterReadView$$anonfun$1.akka$cluster$ClusterReadView$$anonfun$$$outer:()Lakka/cluster/ClusterReadView;
     969: invokevirtual #47                 // Method akka/cluster/ClusterReadView.akka$cluster$ClusterReadView$$_state:()Lakka/cluster/ClusterEvent$CurrentClusterState;
     972: astore        61
     974: aload_0
     975: getfield      #31                 // Field $outer:Lakka/cluster/ClusterReadView$$anonfun$1$$anon$1;
     978: invokevirtual #35                 // Method akka/cluster/ClusterReadView$$anonfun$1$$anon$1.akka$cluster$ClusterReadView$$anonfun$$anon$$$outer:()Lakka/cluster/ClusterReadView$$anonfun$1;
     981: invokevirtual #41                 // Method akka/cluster/ClusterReadView$$anonfun$1.akka$cluster$ClusterReadView$$anonfun$$$outer:()Lakka/cluster/ClusterReadView;
     984: invokevirtual #47                 // Method akka/cluster/ClusterReadView.akka$cluster$ClusterReadView$$_state:()Lakka/cluster/ClusterEvent$CurrentClusterState;
     987: invokevirtual #145                // Method akka/cluster/ClusterEvent$CurrentClusterState.roleLeaderMap:()Lscala/collection/immutable/Map;
     990: getstatic     #151                // Field scala/Predef$ArrowAssoc$.MODULE$:Lscala/Predef$ArrowAssoc$;
     993: getstatic     #156                // Field scala/Predef$.MODULE$:Lscala/Predef$;
     996: aload         59
     998: invokevirtual #160                // Method scala/Predef$.ArrowAssoc:(Ljava/lang/Object;)Ljava/lang/Object;
    1001: aload         60
    1003: invokevirtual #164                // Method scala/Predef$ArrowAssoc$.$u2192$extension:(Ljava/lang/Object;Ljava/lang/Object;)Lscala/Tuple2;
    1006: invokeinterface #169,  2          // InterfaceMethod scala/collection/immutable/Map.$plus:(Lscala/Tuple2;)Lscala/collection/immutable/Map;
    1011: astore        62
    1013: aload         61
    1015: invokevirtual #53                 // Method akka/cluster/ClusterEvent$CurrentClusterState.copy$default$1:()Lscala/collection/immutable/SortedSet;
    1018: astore        63
    1020: aload         61
    1022: invokevirtual #56                 // Method akka/cluster/ClusterEvent$CurrentClusterState.copy$default$2:()Lscala/collection/immutable/Set;
    1025: astore        64
    1027: aload         61
    1029: invokevirtual #112                // Method akka/cluster/ClusterEvent$CurrentClusterState.copy$default$3:()Lscala/collection/immutable/Set;
    1032: astore        65
    1034: aload         61
    1036: invokevirtual #60                 // Method akka/cluster/ClusterEvent$CurrentClusterState.copy$default$4:()Lscala/Option;
    1039: astore        66
    1041: aload         61
    1043: aload         63
    1045: aload         64
    1047: aload         65
    1049: aload         66
    1051: aload         62
    1053: invokevirtual #68                 // Method akka/cluster/ClusterEvent$CurrentClusterState.copy:(Lscala/collection/immutable/SortedSet;Lscala/collection/immutable/Set;Lscala/collection/immutable/Set;Lscala/Option;Lscala/collection/immutable/Map;)Lakka/cluster/ClusterEvent$CurrentClusterState;
    1056: invokevirtual #72                 // Method akka/cluster/ClusterReadView.akka$cluster$ClusterReadView$$_state_$eq:(Lakka/cluster/ClusterEvent$CurrentClusterState;)V
    1059: getstatic     #78                 // Field scala/runtime/BoxedUnit.UNIT:Lscala/runtime/BoxedUnit;
    1062: astore        9
    1064: goto          1166
    1067: aload         6
    1069: instanceof    #171                // class akka/cluster/ClusterEvent$CurrentInternalStats
    1072: ifeq          1105
    1075: aload         6
    1077: checkcast     #171                // class akka/cluster/ClusterEvent$CurrentInternalStats
    1080: astore        67
    1082: aload_0
    1083: getfield      #31                 // Field $outer:Lakka/cluster/ClusterReadView$$anonfun$1$$anon$1;
    1086: invokevirtual #35                 // Method akka/cluster/ClusterReadView$$anonfun$1$$anon$1.akka$cluster$ClusterReadView$$anonfun$$anon$$$outer:()Lakka/cluster/ClusterReadView$$anonfun$1;
    1089: invokevirtual #41                 // Method akka/cluster/ClusterReadView$$anonfun$1.akka$cluster$ClusterReadView$$anonfun$$$outer:()Lakka/cluster/ClusterReadView;
    1092: aload         67
    1094: invokevirtual #175                // Method akka/cluster/ClusterReadView.akka$cluster$ClusterReadView$$_latestStats_$eq:(Lakka/cluster/ClusterEvent$CurrentInternalStats;)V
    1097: getstatic     #78                 // Field scala/runtime/BoxedUnit.UNIT:Lscala/runtime/BoxedUnit;
    1100: astore        9
    1102: goto          1166
    1105: aload         6
    1107: instanceof    #177                // class akka/cluster/ClusterEvent$ClusterMetricsChanged
    1110: ifeq          1150
    1113: aload         6
    1115: checkcast     #177                // class akka/cluster/ClusterEvent$ClusterMetricsChanged
    1118: astore        68
    1120: aload         68
    1122: invokevirtual #180                // Method akka/cluster/ClusterEvent$ClusterMetricsChanged.nodeMetrics:()Lscala/collection/immutable/Set;
    1125: astore        69
    1127: aload_0
    1128: getfield      #31                 // Field $outer:Lakka/cluster/ClusterReadView$$anonfun$1$$anon$1;
    1131: invokevirtual #35                 // Method akka/cluster/ClusterReadView$$anonfun$1$$anon$1.akka$cluster$ClusterReadView$$anonfun$$anon$$$outer:()Lakka/cluster/ClusterReadView$$anonfun$1;
    1134: invokevirtual #41                 // Method akka/cluster/ClusterReadView$$anonfun$1.akka$cluster$ClusterReadView$$anonfun$$$outer:()Lakka/cluster/ClusterReadView;
    1137: aload         69
    1139: invokevirtual #184                // Method akka/cluster/ClusterReadView.akka$cluster$ClusterReadView$$_clusterMetrics_$eq:(Lscala/collection/immutable/Set;)V
    1142: getstatic     #78                 // Field scala/runtime/BoxedUnit.UNIT:Lscala/runtime/BoxedUnit;
    1145: astore        9
    1147: goto          1166
    1150: getstatic     #189                // Field akka/cluster/ClusterEvent$ClusterShuttingDown$.MODULE$:Lakka/cluster/ClusterEvent$ClusterShuttingDown$;
    1153: aload         6
    1155: invokevirtual #194                // Method java/lang/Object.equals:(Ljava/lang/Object;)Z
    1158: ifeq          1174
    1161: getstatic     #78                 // Field scala/runtime/BoxedUnit.UNIT:Lscala/runtime/BoxedUnit;
    1164: astore        9
    1166: getstatic     #78                 // Field scala/runtime/BoxedUnit.UNIT:Lscala/runtime/BoxedUnit;
    1169: astore        5
    1171: goto          1229
    1174: new           #196                // class scala/MatchError
    1177: dup
    1178: aload         6
    1180: invokespecial #200                // Method scala/MatchError."<init>":(Ljava/lang/Object;)V
    1183: athrow
    1184: aload_3
    1185: instanceof    #49                 // class akka/cluster/ClusterEvent$CurrentClusterState
    1188: ifeq          1220
    1191: aload_3
    1192: checkcast     #49                 // class akka/cluster/ClusterEvent$CurrentClusterState
    1195: astore        70
    1197: aload_0
    1198: getfield      #31                 // Field $outer:Lakka/cluster/ClusterReadView$$anonfun$1$$anon$1;
    1201: invokevirtual #35                 // Method akka/cluster/ClusterReadView$$anonfun$1$$anon$1.akka$cluster$ClusterReadView$$anonfun$$anon$$$outer:()Lakka/cluster/ClusterReadView$$anonfun$1;
    1204: invokevirtual #41                 // Method akka/cluster/ClusterReadView$$anonfun$1.akka$cluster$ClusterReadView$$anonfun$$$outer:()Lakka/cluster/ClusterReadView;
    1207: aload         70
    1209: invokevirtual #72                 // Method akka/cluster/ClusterReadView.akka$cluster$ClusterReadView$$_state_$eq:(Lakka/cluster/ClusterEvent$CurrentClusterState;)V
    1212: getstatic     #78                 // Field scala/runtime/BoxedUnit.UNIT:Lscala/runtime/BoxedUnit;
    1215: astore        5
    1217: goto          1229
    1220: aload_2
    1221: aload_1
    1222: invokeinterface #205,  2          // InterfaceMethod scala/Function1.apply:(Ljava/lang/Object;)Ljava/lang/Object;
    1227: astore        5
    1229: aload         5
    1231: areturn

  public final boolean isDefinedAt(java.lang.Object);
    Code:
       0: aload_1
       1: astore_2
       2: aload_2
       3: instanceof    #23                 // class akka/cluster/ClusterEvent$ClusterDomainEvent
       6: ifeq          14
       9: iconst_1
      10: istore_3
      11: goto          28
      14: aload_2
      15: instanceof    #49                 // class akka/cluster/ClusterEvent$CurrentClusterState
      18: ifeq          26
      21: iconst_1
      22: istore_3
      23: goto          28
      26: iconst_0
      27: istore_3
      28: iload_3
      29: ireturn

  public akka.cluster.ClusterReadView$$anonfun$1$$anon$1$$anonfun$receive$1(akka.cluster.ClusterReadView$$anonfun$1$$anon$1);
    Code:
       0: aload_1
       1: ifnonnull     6
       4: aconst_null
       5: athrow
       6: aload_0
       7: aload_1
       8: putfield      #31                 // Field $outer:Lakka/cluster/ClusterReadView$$anonfun$1$$anon$1;
      11: aload_0
      12: invokespecial #268                // Method scala/runtime/AbstractPartialFunction."<init>":()V
      15: return
}
