Compiled from "Gossip.scala"
public final class akka.cluster.Gossip$$anonfun$leaderOf$2 extends scala.runtime.AbstractFunction0<scala.Some<akka.cluster.Member>> implements scala.Serializable {
  public static final long serialVersionUID;

  private final scala.collection.immutable.SortedSet reachableMembers$1;

  public final scala.Some<akka.cluster.Member> apply();
    Code:
       0: new           #23                 // class scala/Some
       3: dup
       4: aload_0
       5: getfield      #25                 // Field reachableMembers$1:Lscala/collection/immutable/SortedSet;
       8: getstatic     #31                 // Field akka/cluster/Member$.MODULE$:Lakka/cluster/Member$;
      11: invokevirtual #35                 // Method akka/cluster/Member$.leaderStatusOrdering:()Lscala/math/Ordering;
      14: invokeinterface #41,  2           // InterfaceMethod scala/collection/immutable/SortedSet.min:(Lscala/math/Ordering;)Ljava/lang/Object;
      19: invokespecial #45                 // Method scala/Some."<init>":(Ljava/lang/Object;)V
      22: areturn

  public final java.lang.Object apply();
    Code:
       0: aload_0
       1: invokevirtual #50                 // Method apply:()Lscala/Some;
       4: areturn

  public akka.cluster.Gossip$$anonfun$leaderOf$2(akka.cluster.Gossip, scala.collection.immutable.SortedSet);
    Code:
       0: aload_0
       1: aload_2
       2: putfield      #25                 // Field reachableMembers$1:Lscala/collection/immutable/SortedSet;
       5: aload_0
       6: invokespecial #54                 // Method scala/runtime/AbstractFunction0."<init>":()V
       9: return
}
