Compiled from "ClusterMetricsCollector.scala"
public final class akka.cluster.MetricsGossip$ implements scala.Serializable {
  public static final akka.cluster.MetricsGossip$ MODULE$;

  private final akka.cluster.MetricsGossip empty;

  public static {};
    Code:
       0: new           #2                  // class akka/cluster/MetricsGossip$
       3: invokespecial #14                 // Method "<init>":()V
       6: return

  public akka.cluster.MetricsGossip empty();
    Code:
       0: aload_0
       1: getfield      #19                 // Field empty:Lakka/cluster/MetricsGossip;
       4: areturn

  public akka.cluster.MetricsGossip apply(scala.collection.immutable.Set<akka.cluster.NodeMetrics>);
    Code:
       0: new           #24                 // class akka/cluster/MetricsGossip
       3: dup
       4: aload_1
       5: invokespecial #27                 // Method akka/cluster/MetricsGossip."<init>":(Lscala/collection/immutable/Set;)V
       8: areturn

  public scala.Option<scala.collection.immutable.Set<akka.cluster.NodeMetrics>> unapply(akka.cluster.MetricsGossip);
    Code:
       0: aload_1
       1: ifnonnull     10
       4: getstatic     #36                 // Field scala/None$.MODULE$:Lscala/None$;
       7: goto          21
      10: new           #38                 // class scala/Some
      13: dup
      14: aload_1
      15: invokevirtual #41                 // Method akka/cluster/MetricsGossip.nodes:()Lscala/collection/immutable/Set;
      18: invokespecial #44                 // Method scala/Some."<init>":(Ljava/lang/Object;)V
      21: areturn

  private java.lang.Object readResolve();
    Code:
       0: getstatic     #51                 // Field MODULE$:Lakka/cluster/MetricsGossip$;
       3: areturn

  private akka.cluster.MetricsGossip$();
    Code:
       0: aload_0
       1: invokespecial #52                 // Method java/lang/Object."<init>":()V
       4: aload_0
       5: putstatic     #51                 // Field MODULE$:Lakka/cluster/MetricsGossip$;
       8: aload_0
       9: new           #24                 // class akka/cluster/MetricsGossip
      12: dup
      13: getstatic     #57                 // Field scala/Predef$.MODULE$:Lscala/Predef$;
      16: invokevirtual #61                 // Method scala/Predef$.Set:()Lscala/collection/immutable/Set$;
      19: invokevirtual #65                 // Method scala/collection/immutable/Set$.empty:()Lscala/collection/immutable/Set;
      22: invokespecial #27                 // Method akka/cluster/MetricsGossip."<init>":(Lscala/collection/immutable/Set;)V
      25: putfield      #19                 // Field empty:Lakka/cluster/MetricsGossip;
      28: return
}
