Compiled from "SSLConnectionConfigurator.java"
public class org.apache.hadoop.hdfs.web.SSLConnectionConfigurator implements org.apache.hadoop.security.authentication.client.ConnectionConfigurator {
  private final org.apache.hadoop.security.ssl.SSLFactory factory;

  private final javax.net.ssl.SSLSocketFactory sf;

  private final javax.net.ssl.HostnameVerifier hv;

  private final int connectTimeout;

  private final int readTimeout;

  org.apache.hadoop.hdfs.web.SSLConnectionConfigurator(int, int, org.apache.hadoop.conf.Configuration) throws java.io.IOException, java.security.GeneralSecurityException;
    Code:
       0: aload_0
       1: invokespecial #1                  // Method java/lang/Object."<init>":()V
       4: aload_0
       5: new           #2                  // class org/apache/hadoop/security/ssl/SSLFactory
       8: dup
       9: getstatic     #3                  // Field org/apache/hadoop/security/ssl/SSLFactory$Mode.CLIENT:Lorg/apache/hadoop/security/ssl/SSLFactory$Mode;
      12: aload_3
      13: invokespecial #4                  // Method org/apache/hadoop/security/ssl/SSLFactory."<init>":(Lorg/apache/hadoop/security/ssl/SSLFactory$Mode;Lorg/apache/hadoop/conf/Configuration;)V
      16: putfield      #5                  // Field factory:Lorg/apache/hadoop/security/ssl/SSLFactory;
      19: aload_0
      20: getfield      #5                  // Field factory:Lorg/apache/hadoop/security/ssl/SSLFactory;
      23: invokevirtual #6                  // Method org/apache/hadoop/security/ssl/SSLFactory.init:()V
      26: aload_0
      27: aload_0
      28: getfield      #5                  // Field factory:Lorg/apache/hadoop/security/ssl/SSLFactory;
      31: invokevirtual #7                  // Method org/apache/hadoop/security/ssl/SSLFactory.createSSLSocketFactory:()Ljavax/net/ssl/SSLSocketFactory;
      34: putfield      #8                  // Field sf:Ljavax/net/ssl/SSLSocketFactory;
      37: aload_0
      38: aload_0
      39: getfield      #5                  // Field factory:Lorg/apache/hadoop/security/ssl/SSLFactory;
      42: invokevirtual #9                  // Method org/apache/hadoop/security/ssl/SSLFactory.getHostnameVerifier:()Ljavax/net/ssl/HostnameVerifier;
      45: putfield      #10                 // Field hv:Ljavax/net/ssl/HostnameVerifier;
      48: aload_0
      49: iload_1
      50: putfield      #11                 // Field connectTimeout:I
      53: aload_0
      54: iload_2
      55: putfield      #12                 // Field readTimeout:I
      58: return

  public java.net.HttpURLConnection configure(java.net.HttpURLConnection);
    Code:
       0: aload_1
       1: instanceof    #13                 // class javax/net/ssl/HttpsURLConnection
       4: ifeq          28
       7: aload_1
       8: checkcast     #13                 // class javax/net/ssl/HttpsURLConnection
      11: astore_2
      12: aload_2
      13: aload_0
      14: getfield      #8                  // Field sf:Ljavax/net/ssl/SSLSocketFactory;
      17: invokevirtual #14                 // Method javax/net/ssl/HttpsURLConnection.setSSLSocketFactory:(Ljavax/net/ssl/SSLSocketFactory;)V
      20: aload_2
      21: aload_0
      22: getfield      #10                 // Field hv:Ljavax/net/ssl/HostnameVerifier;
      25: invokevirtual #15                 // Method javax/net/ssl/HttpsURLConnection.setHostnameVerifier:(Ljavax/net/ssl/HostnameVerifier;)V
      28: aload_1
      29: aload_0
      30: getfield      #11                 // Field connectTimeout:I
      33: invokevirtual #16                 // Method java/net/HttpURLConnection.setConnectTimeout:(I)V
      36: aload_1
      37: aload_0
      38: getfield      #12                 // Field readTimeout:I
      41: invokevirtual #17                 // Method java/net/HttpURLConnection.setReadTimeout:(I)V
      44: aload_1
      45: areturn

  void destroy();
    Code:
       0: aload_0
       1: getfield      #5                  // Field factory:Lorg/apache/hadoop/security/ssl/SSLFactory;
       4: invokevirtual #18                 // Method org/apache/hadoop/security/ssl/SSLFactory.destroy:()V
       7: return
}
