Compiled from "ConcurrencyThrottleSupport.java"
public abstract class org.springframework.util.ConcurrencyThrottleSupport implements java.io.Serializable {
  public static final int UNBOUNDED_CONCURRENCY;

  public static final int NO_CONCURRENCY;

  protected transient org.apache.commons.logging.Log logger;

  private transient java.lang.Object monitor;

  private int concurrencyLimit;

  private int concurrencyCount;

  public org.springframework.util.ConcurrencyThrottleSupport();
    Code:
       0: aload_0
       1: invokespecial #1                  // Method java/lang/Object."<init>":()V
       4: aload_0
       5: aload_0
       6: invokevirtual #2                  // Method java/lang/Object.getClass:()Ljava/lang/Class;
       9: invokestatic  #3                  // Method org/apache/commons/logging/LogFactory.getLog:(Ljava/lang/Class;)Lorg/apache/commons/logging/Log;
      12: putfield      #4                  // Field logger:Lorg/apache/commons/logging/Log;
      15: aload_0
      16: new           #5                  // class java/lang/Object
      19: dup
      20: invokespecial #1                  // Method java/lang/Object."<init>":()V
      23: putfield      #6                  // Field monitor:Ljava/lang/Object;
      26: aload_0
      27: iconst_m1
      28: putfield      #8                  // Field concurrencyLimit:I
      31: aload_0
      32: iconst_0
      33: putfield      #9                  // Field concurrencyCount:I
      36: return

  public void setConcurrencyLimit(int);
    Code:
       0: aload_0
       1: iload_1
       2: putfield      #8                  // Field concurrencyLimit:I
       5: return

  public int getConcurrencyLimit();
    Code:
       0: aload_0
       1: getfield      #8                  // Field concurrencyLimit:I
       4: ireturn

  public boolean isThrottleActive();
    Code:
       0: aload_0
       1: getfield      #8                  // Field concurrencyLimit:I
       4: ifle          11
       7: iconst_1
       8: goto          12
      11: iconst_0
      12: ireturn

  protected void beforeAccess();
    Code:
       0: aload_0
       1: getfield      #8                  // Field concurrencyLimit:I
       4: ifne          17
       7: new           #10                 // class java/lang/IllegalStateException
      10: dup
      11: ldc           #11                 // String Currently no invocations allowed - concurrency limit set to NO_CONCURRENCY
      13: invokespecial #12                 // Method java/lang/IllegalStateException."<init>":(Ljava/lang/String;)V
      16: athrow
      17: aload_0
      18: getfield      #8                  // Field concurrencyLimit:I
      21: ifle          200
      24: aload_0
      25: getfield      #4                  // Field logger:Lorg/apache/commons/logging/Log;
      28: invokeinterface #13,  1           // InterfaceMethod org/apache/commons/logging/Log.isDebugEnabled:()Z
      33: istore_1
      34: aload_0
      35: getfield      #6                  // Field monitor:Ljava/lang/Object;
      38: dup
      39: astore_2
      40: monitorenter
      41: iconst_0
      42: istore_3
      43: aload_0
      44: getfield      #9                  // Field concurrencyCount:I
      47: aload_0
      48: getfield      #8                  // Field concurrencyLimit:I
      51: if_icmplt     143
      54: iload_3
      55: ifeq          68
      58: new           #10                 // class java/lang/IllegalStateException
      61: dup
      62: ldc           #14                 // String Thread was interrupted while waiting for invocation access, but concurrency limit still does not allow for entering
      64: invokespecial #12                 // Method java/lang/IllegalStateException."<init>":(Ljava/lang/String;)V
      67: athrow
      68: iload_1
      69: ifeq          120
      72: aload_0
      73: getfield      #4                  // Field logger:Lorg/apache/commons/logging/Log;
      76: new           #15                 // class java/lang/StringBuilder
      79: dup
      80: invokespecial #16                 // Method java/lang/StringBuilder."<init>":()V
      83: ldc           #17                 // String Concurrency count
      85: invokevirtual #18                 // Method java/lang/StringBuilder.append:(Ljava/lang/String;)Ljava/lang/StringBuilder;
      88: aload_0
      89: getfield      #9                  // Field concurrencyCount:I
      92: invokevirtual #19                 // Method java/lang/StringBuilder.append:(I)Ljava/lang/StringBuilder;
      95: ldc           #20                 // String  has reached limit
      97: invokevirtual #18                 // Method java/lang/StringBuilder.append:(Ljava/lang/String;)Ljava/lang/StringBuilder;
     100: aload_0
     101: getfield      #8                  // Field concurrencyLimit:I
     104: invokevirtual #19                 // Method java/lang/StringBuilder.append:(I)Ljava/lang/StringBuilder;
     107: ldc           #21                 // String  - blocking
     109: invokevirtual #18                 // Method java/lang/StringBuilder.append:(Ljava/lang/String;)Ljava/lang/StringBuilder;
     112: invokevirtual #22                 // Method java/lang/StringBuilder.toString:()Ljava/lang/String;
     115: invokeinterface #23,  2           // InterfaceMethod org/apache/commons/logging/Log.debug:(Ljava/lang/Object;)V
     120: aload_0
     121: getfield      #6                  // Field monitor:Ljava/lang/Object;
     124: invokevirtual #24                 // Method java/lang/Object.wait:()V
     127: goto          43
     130: astore        4
     132: invokestatic  #26                 // Method java/lang/Thread.currentThread:()Ljava/lang/Thread;
     135: invokevirtual #27                 // Method java/lang/Thread.interrupt:()V
     138: iconst_1
     139: istore_3
     140: goto          43
     143: iload_1
     144: ifeq          178
     147: aload_0
     148: getfield      #4                  // Field logger:Lorg/apache/commons/logging/Log;
     151: new           #15                 // class java/lang/StringBuilder
     154: dup
     155: invokespecial #16                 // Method java/lang/StringBuilder."<init>":()V
     158: ldc           #28                 // String Entering throttle at concurrency count
     160: invokevirtual #18                 // Method java/lang/StringBuilder.append:(Ljava/lang/String;)Ljava/lang/StringBuilder;
     163: aload_0
     164: getfield      #9                  // Field concurrencyCount:I
     167: invokevirtual #19                 // Method java/lang/StringBuilder.append:(I)Ljava/lang/StringBuilder;
     170: invokevirtual #22                 // Method java/lang/StringBuilder.toString:()Ljava/lang/String;
     173: invokeinterface #23,  2           // InterfaceMethod org/apache/commons/logging/Log.debug:(Ljava/lang/Object;)V
     178: aload_0
     179: dup
     180: getfield      #9                  // Field concurrencyCount:I
     183: iconst_1
     184: iadd
     185: putfield      #9                  // Field concurrencyCount:I
     188: aload_2
     189: monitorexit
     190: goto          200
     193: astore        5
     195: aload_2
     196: monitorexit
     197: aload         5
     199: athrow
     200: return
    Exception table:
       from    to  target type
         120   127   130   Class java/lang/InterruptedException
          41   190   193   any
         193   197   193   any

  protected void afterAccess();
    Code:
       0: aload_0
       1: getfield      #8                  // Field concurrencyLimit:I
       4: iflt          84
       7: aload_0
       8: getfield      #6                  // Field monitor:Ljava/lang/Object;
      11: dup
      12: astore_1
      13: monitorenter
      14: aload_0
      15: dup
      16: getfield      #9                  // Field concurrencyCount:I
      19: iconst_1
      20: isub
      21: putfield      #9                  // Field concurrencyCount:I
      24: aload_0
      25: getfield      #4                  // Field logger:Lorg/apache/commons/logging/Log;
      28: invokeinterface #13,  1           // InterfaceMethod org/apache/commons/logging/Log.isDebugEnabled:()Z
      33: ifeq          67
      36: aload_0
      37: getfield      #4                  // Field logger:Lorg/apache/commons/logging/Log;
      40: new           #15                 // class java/lang/StringBuilder
      43: dup
      44: invokespecial #16                 // Method java/lang/StringBuilder."<init>":()V
      47: ldc           #29                 // String Returning from throttle at concurrency count
      49: invokevirtual #18                 // Method java/lang/StringBuilder.append:(Ljava/lang/String;)Ljava/lang/StringBuilder;
      52: aload_0
      53: getfield      #9                  // Field concurrencyCount:I
      56: invokevirtual #19                 // Method java/lang/StringBuilder.append:(I)Ljava/lang/StringBuilder;
      59: invokevirtual #22                 // Method java/lang/StringBuilder.toString:()Ljava/lang/String;
      62: invokeinterface #23,  2           // InterfaceMethod org/apache/commons/logging/Log.debug:(Ljava/lang/Object;)V
      67: aload_0
      68: getfield      #6                  // Field monitor:Ljava/lang/Object;
      71: invokevirtual #30                 // Method java/lang/Object.notify:()V
      74: aload_1
      75: monitorexit
      76: goto          84
      79: astore_2
      80: aload_1
      81: monitorexit
      82: aload_2
      83: athrow
      84: return
    Exception table:
       from    to  target type
          14    76    79   any
          79    82    79   any

  private void readObject(java.io.ObjectInputStream) throws java.io.IOException, java.lang.ClassNotFoundException;
    Code:
       0: aload_1
       1: invokevirtual #31                 // Method java/io/ObjectInputStream.defaultReadObject:()V
       4: aload_0
       5: aload_0
       6: invokevirtual #2                  // Method java/lang/Object.getClass:()Ljava/lang/Class;
       9: invokestatic  #3                  // Method org/apache/commons/logging/LogFactory.getLog:(Ljava/lang/Class;)Lorg/apache/commons/logging/Log;
      12: putfield      #4                  // Field logger:Lorg/apache/commons/logging/Log;
      15: aload_0
      16: new           #5                  // class java/lang/Object
      19: dup
      20: invokespecial #1                  // Method java/lang/Object."<init>":()V
      23: putfield      #6                  // Field monitor:Ljava/lang/Object;
      26: return
}
