Compiled from "ExpressionParsingNode.java"
final class org.thymeleaf.standard.expression.ExpressionParsingNode {
  private final java.lang.String input;

  private final org.thymeleaf.standard.expression.Expression expression;

  org.thymeleaf.standard.expression.ExpressionParsingNode(java.lang.String);
    Code:
       0: aload_0
       1: invokespecial #1                  // Method java/lang/Object."<init>":()V
       4: aload_0
       5: aload_1
       6: invokevirtual #2                  // Method java/lang/String.trim:()Ljava/lang/String;
       9: putfield      #3                  // Field input:Ljava/lang/String;
      12: aload_0
      13: aconst_null
      14: putfield      #4                  // Field expression:Lorg/thymeleaf/standard/expression/Expression;
      17: return

  org.thymeleaf.standard.expression.ExpressionParsingNode(org.thymeleaf.standard.expression.Expression);
    Code:
       0: aload_0
       1: invokespecial #1                  // Method java/lang/Object."<init>":()V
       4: aload_0
       5: aload_1
       6: putfield      #4                  // Field expression:Lorg/thymeleaf/standard/expression/Expression;
       9: aload_0
      10: aconst_null
      11: putfield      #3                  // Field input:Ljava/lang/String;
      14: return

  boolean isInput();
    Code:
       0: aload_0
       1: getfield      #3                  // Field input:Ljava/lang/String;
       4: ifnull        11
       7: iconst_1
       8: goto          12
      11: iconst_0
      12: ireturn

  boolean isExpression();
    Code:
       0: aload_0
       1: getfield      #4                  // Field expression:Lorg/thymeleaf/standard/expression/Expression;
       4: ifnull        11
       7: iconst_1
       8: goto          12
      11: iconst_0
      12: ireturn

  boolean isSimpleExpression();
    Code:
       0: aload_0
       1: getfield      #4                  // Field expression:Lorg/thymeleaf/standard/expression/Expression;
       4: ifnull        21
       7: aload_0
       8: getfield      #4                  // Field expression:Lorg/thymeleaf/standard/expression/Expression;
      11: instanceof    #5                  // class org/thymeleaf/standard/expression/SimpleExpression
      14: ifeq          21
      17: iconst_1
      18: goto          22
      21: iconst_0
      22: ireturn

  boolean ComplexExpression();
    Code:
       0: aload_0
       1: getfield      #4                  // Field expression:Lorg/thymeleaf/standard/expression/Expression;
       4: ifnull        21
       7: aload_0
       8: getfield      #4                  // Field expression:Lorg/thymeleaf/standard/expression/Expression;
      11: instanceof    #6                  // class org/thymeleaf/standard/expression/ComplexExpression
      14: ifeq          21
      17: iconst_1
      18: goto          22
      21: iconst_0
      22: ireturn

  java.lang.String getInput();
    Code:
       0: aload_0
       1: getfield      #3                  // Field input:Ljava/lang/String;
       4: areturn

  org.thymeleaf.standard.expression.Expression getExpression();
    Code:
       0: aload_0
       1: getfield      #4                  // Field expression:Lorg/thymeleaf/standard/expression/Expression;
       4: areturn

  public java.lang.String toString();
    Code:
       0: aload_0
       1: invokevirtual #7                  // Method isExpression:()Z
       4: ifeq          40
       7: new           #8                  // class java/lang/StringBuilder
      10: dup
      11: invokespecial #9                  // Method java/lang/StringBuilder."<init>":()V
      14: ldc           #10                 // String [
      16: invokevirtual #11                 // Method java/lang/StringBuilder.append:(Ljava/lang/String;)Ljava/lang/StringBuilder;
      19: aload_0
      20: getfield      #4                  // Field expression:Lorg/thymeleaf/standard/expression/Expression;
      23: invokevirtual #12                 // Method org/thymeleaf/standard/expression/Expression.getStringRepresentation:()Ljava/lang/String;
      26: invokevirtual #11                 // Method java/lang/StringBuilder.append:(Ljava/lang/String;)Ljava/lang/StringBuilder;
      29: ldc           #13                 // String ]
      31: invokevirtual #11                 // Method java/lang/StringBuilder.append:(Ljava/lang/String;)Ljava/lang/StringBuilder;
      34: invokevirtual #14                 // Method java/lang/StringBuilder.toString:()Ljava/lang/String;
      37: goto          44
      40: aload_0
      41: getfield      #3                  // Field input:Ljava/lang/String;
      44: areturn
}
