Compiled from "OGNLShortcutExpression.java"
final class org.thymeleaf.standard.expression.OGNLShortcutExpression {
  private static final org.slf4j.Logger LOGGER;

  private static final java.lang.String EXPRESSION_CACHE_TYPE_OGNL_SHORTCUT;

  private static final java.lang.Object[] NO_PARAMS;

  private final java.lang.String[] expressionLevels;

  org.thymeleaf.standard.expression.OGNLShortcutExpression(java.lang.String[]);
    Code:
       0: aload_0
       1: invokespecial #1                  // Method java/lang/Object."<init>":()V
       4: aload_0
       5: aload_1
       6: putfield      #2                  // Field expressionLevels:[Ljava/lang/String;
       9: return

  java.lang.Object evaluate(org.thymeleaf.IEngineConfiguration, java.util.Map<java.lang.String, java.lang.Object>, java.lang.Object) throws java.lang.Exception;
    Code:
       0: aload_1
       1: invokeinterface #3,  1            // InterfaceMethod org/thymeleaf/IEngineConfiguration.getCacheManager:()Lorg/thymeleaf/cache/ICacheManager;
       6: astore        4
       8: aload         4
      10: ifnonnull     17
      13: aconst_null
      14: goto          24
      17: aload         4
      19: invokeinterface #4,  1            // InterfaceMethod org/thymeleaf/cache/ICacheManager.getExpressionCache:()Lorg/thymeleaf/cache/ICache;
      24: astore        5
      26: aload_3
      27: astore        6
      29: aload_0
      30: getfield      #2                  // Field expressionLevels:[Ljava/lang/String;
      33: astore        7
      35: aload         7
      37: arraylength
      38: istore        8
      40: iconst_0
      41: istore        9
      43: iload         9
      45: iload         8
      47: if_icmpge     376
      50: aload         7
      52: iload         9
      54: aaload
      55: astore        10
      57: aload         6
      59: ifnonnull     95
      62: new           #5                  // class ognl/OgnlException
      65: dup
      66: new           #6                  // class java/lang/StringBuilder
      69: dup
      70: invokespecial #7                  // Method java/lang/StringBuilder."<init>":()V
      73: ldc           #8                  // String source is null for getProperty(null, \"
      75: invokevirtual #9                  // Method java/lang/StringBuilder.append:(Ljava/lang/String;)Ljava/lang/StringBuilder;
      78: aload         10
      80: invokevirtual #9                  // Method java/lang/StringBuilder.append:(Ljava/lang/String;)Ljava/lang/StringBuilder;
      83: ldc           #10                 // String \")
      85: invokevirtual #9                  // Method java/lang/StringBuilder.append:(Ljava/lang/String;)Ljava/lang/StringBuilder;
      88: invokevirtual #11                 // Method java/lang/StringBuilder.toString:()Ljava/lang/String;
      91: invokespecial #12                 // Method ognl/OgnlException."<init>":(Ljava/lang/String;)V
      94: athrow
      95: aload         6
      97: invokestatic  #13                 // Method ognl/OgnlRuntime.getTargetClass:(Ljava/lang/Object;)Ljava/lang/Class;
     100: astore        11
     102: aload         11
     104: invokestatic  #14                 // Method ognl/OgnlRuntime.getPropertyAccessor:(Ljava/lang/Class;)Lognl/PropertyAccessor;
     107: astore        12
     109: aload         6
     111: instanceof    #15                 // class java/lang/Class
     114: ifeq          131
     117: aload         5
     119: aload         10
     121: aload         6
     123: invokestatic  #16                 // Method getObjectProperty:(Lorg/thymeleaf/cache/ICache;Ljava/lang/String;Ljava/lang/Object;)Ljava/lang/Object;
     126: astore        6
     128: goto          370
     131: ldc           #17                 // class org/thymeleaf/standard/expression/OGNLContextPropertyAccessor
     133: aload         12
     135: invokevirtual #18                 // Method java/lang/Object.getClass:()Ljava/lang/Class;
     138: invokevirtual #19                 // Method java/lang/Object.equals:(Ljava/lang/Object;)Z
     141: ifeq          157
     144: aload         10
     146: aload_2
     147: aload         6
     149: invokestatic  #20                 // Method getContextProperty:(Ljava/lang/String;Ljava/util/Map;Ljava/lang/Object;)Ljava/lang/Object;
     152: astore        6
     154: goto          370
     157: ldc           #21                 // class ognl/ObjectPropertyAccessor
     159: aload         12
     161: invokevirtual #18                 // Method java/lang/Object.getClass:()Ljava/lang/Class;
     164: invokevirtual #19                 // Method java/lang/Object.equals:(Ljava/lang/Object;)Z
     167: ifeq          184
     170: aload         5
     172: aload         10
     174: aload         6
     176: invokestatic  #16                 // Method getObjectProperty:(Lorg/thymeleaf/cache/ICache;Ljava/lang/String;Ljava/lang/Object;)Ljava/lang/Object;
     179: astore        6
     181: goto          370
     184: ldc           #22                 // class ognl/MapPropertyAccessor
     186: aload         12
     188: invokevirtual #18                 // Method java/lang/Object.getClass:()Ljava/lang/Class;
     191: invokevirtual #19                 // Method java/lang/Object.equals:(Ljava/lang/Object;)Z
     194: ifeq          212
     197: aload         10
     199: aload         6
     201: checkcast     #23                 // class java/util/Map
     204: invokestatic  #24                 // Method getMapProperty:(Ljava/lang/String;Ljava/util/Map;)Ljava/lang/Object;
     207: astore        6
     209: goto          370
     212: ldc           #25                 // class ognl/ListPropertyAccessor
     214: aload         12
     216: invokevirtual #18                 // Method java/lang/Object.getClass:()Ljava/lang/Class;
     219: invokevirtual #19                 // Method java/lang/Object.equals:(Ljava/lang/Object;)Z
     222: ifeq          242
     225: aload         5
     227: aload         10
     229: aload         6
     231: checkcast     #26                 // class java/util/List
     234: invokestatic  #27                 // Method getListProperty:(Lorg/thymeleaf/cache/ICache;Ljava/lang/String;Ljava/util/List;)Ljava/lang/Object;
     237: astore        6
     239: goto          370
     242: ldc           #28                 // class ognl/SetPropertyAccessor
     244: aload         12
     246: invokevirtual #18                 // Method java/lang/Object.getClass:()Ljava/lang/Class;
     249: invokevirtual #19                 // Method java/lang/Object.equals:(Ljava/lang/Object;)Z
     252: ifeq          272
     255: aload         5
     257: aload         10
     259: aload         6
     261: checkcast     #29                 // class java/util/Set
     264: invokestatic  #30                 // Method getSetProperty:(Lorg/thymeleaf/cache/ICache;Ljava/lang/String;Ljava/util/Set;)Ljava/lang/Object;
     267: astore        6
     269: goto          370
     272: ldc           #31                 // class ognl/IteratorPropertyAccessor
     274: aload         12
     276: invokevirtual #18                 // Method java/lang/Object.getClass:()Ljava/lang/Class;
     279: invokevirtual #19                 // Method java/lang/Object.equals:(Ljava/lang/Object;)Z
     282: ifeq          302
     285: aload         5
     287: aload         10
     289: aload         6
     291: checkcast     #32                 // class java/util/Iterator
     294: invokestatic  #33                 // Method getIteratorProperty:(Lorg/thymeleaf/cache/ICache;Ljava/lang/String;Ljava/util/Iterator;)Ljava/lang/Object;
     297: astore        6
     299: goto          370
     302: ldc           #34                 // class ognl/EnumerationPropertyAccessor
     304: aload         12
     306: invokevirtual #18                 // Method java/lang/Object.getClass:()Ljava/lang/Class;
     309: invokevirtual #19                 // Method java/lang/Object.equals:(Ljava/lang/Object;)Z
     312: ifeq          332
     315: aload         5
     317: aload         10
     319: aload         6
     321: checkcast     #35                 // class java/util/Enumeration
     324: invokestatic  #36                 // Method getEnumerationProperty:(Lorg/thymeleaf/cache/ICache;Ljava/lang/String;Ljava/util/Enumeration;)Ljava/lang/Object;
     327: astore        6
     329: goto          370
     332: ldc           #37                 // class ognl/ArrayPropertyAccessor
     334: aload         12
     336: invokevirtual #18                 // Method java/lang/Object.getClass:()Ljava/lang/Class;
     339: invokevirtual #19                 // Method java/lang/Object.equals:(Ljava/lang/Object;)Z
     342: ifeq          362
     345: aload         5
     347: aload         10
     349: aload         6
     351: checkcast     #38                 // class "[Ljava/lang/Object;"
     354: invokestatic  #39                 // Method getArrayProperty:(Lorg/thymeleaf/cache/ICache;Ljava/lang/String;[Ljava/lang/Object;)Ljava/lang/Object;
     357: astore        6
     359: goto          370
     362: new           #40                 // class org/thymeleaf/standard/expression/OGNLShortcutExpression$OGNLShortcutExpressionNotApplicableException
     365: dup
     366: invokespecial #41                 // Method org/thymeleaf/standard/expression/OGNLShortcutExpression$OGNLShortcutExpressionNotApplicableException."<init>":()V
     369: athrow
     370: iinc          9, 1
     373: goto          43
     376: aload         6
     378: areturn

  private static java.lang.Object getContextProperty(java.lang.String, java.util.Map<java.lang.String, java.lang.Object>, java.lang.Object) throws ognl.OgnlException;
    Code:
       0: ldc           #42                 // String param
       2: aload_0
       3: invokevirtual #43                 // Method java/lang/String.equals:(Ljava/lang/Object;)Z
       6: ifeq          56
       9: aload_1
      10: ifnull        56
      13: aload_1
      14: ldc           #44                 // String %RESTRICT_REQUEST_PARAMETERS%
      16: invokeinterface #45,  2           // InterfaceMethod java/util/Map.containsKey:(Ljava/lang/Object;)Z
      21: ifeq          56
      24: new           #5                  // class ognl/OgnlException
      27: dup
      28: new           #6                  // class java/lang/StringBuilder
      31: dup
      32: invokespecial #7                  // Method java/lang/StringBuilder."<init>":()V
      35: ldc           #46                 // String Access to variable \"
      37: invokevirtual #9                  // Method java/lang/StringBuilder.append:(Ljava/lang/String;)Ljava/lang/StringBuilder;
      40: aload_0
      41: invokevirtual #9                  // Method java/lang/StringBuilder.append:(Ljava/lang/String;)Ljava/lang/StringBuilder;
      44: ldc           #47                 // String \" is forbidden in this context. Note some restrictions apply to variable access. For example, accessing request parameters is forbidden in preprocessing and unescaped expressions, and also in fragment inclusion specifications.
      46: invokevirtual #9                  // Method java/lang/StringBuilder.append:(Ljava/lang/String;)Ljava/lang/StringBuilder;
      49: invokevirtual #11                 // Method java/lang/StringBuilder.toString:()Ljava/lang/String;
      52: invokespecial #12                 // Method ognl/OgnlException."<init>":(Ljava/lang/String;)V
      55: athrow
      56: ldc           #48                 // String execInfo
      58: aload_0
      59: invokevirtual #43                 // Method java/lang/String.equals:(Ljava/lang/Object;)Z
      62: ifeq          77
      65: aload_0
      66: aload_1
      67: invokestatic  #49                 // Method checkExecInfo:(Ljava/lang/String;Ljava/util/Map;)Ljava/lang/Object;
      70: astore_3
      71: aload_3
      72: ifnull        77
      75: aload_3
      76: areturn
      77: aload_2
      78: checkcast     #50                 // class org/thymeleaf/context/IContext
      81: aload_0
      82: invokeinterface #51,  2           // InterfaceMethod org/thymeleaf/context/IContext.getVariable:(Ljava/lang/String;)Ljava/lang/Object;
      87: areturn

  private static java.lang.Object checkExecInfo(java.lang.String, java.util.Map<java.lang.String, java.lang.Object>);
    Code:
       0: ldc           #48                 // String execInfo
       2: aload_0
       3: invokevirtual #43                 // Method java/lang/String.equals:(Ljava/lang/Object;)Z
       6: ifeq          31
       9: getstatic     #52                 // Field LOGGER:Lorg/slf4j/Logger;
      12: ldc           #53                 // String [THYMELEAF][{}] Found Thymeleaf Standard Expression containing a call to the context variable \"execInfo\" (e.g. \"${execInfo.templateName}\"), which has been deprecated. The Execution Info should be now accessed as an expression object instead (e.g. \"${#execInfo.templateName}\"). Deprecated use is still allowed, but will be removed in future versions of Thymeleaf.
      14: invokestatic  #54                 // Method org/thymeleaf/TemplateEngine.threadIndex:()Ljava/lang/String;
      17: invokeinterface #55,  3           // InterfaceMethod org/slf4j/Logger.warn:(Ljava/lang/String;Ljava/lang/Object;)V
      22: aload_1
      23: ldc           #48                 // String execInfo
      25: invokeinterface #56,  2           // InterfaceMethod java/util/Map.get:(Ljava/lang/Object;)Ljava/lang/Object;
      30: areturn
      31: aconst_null
      32: areturn

  private static java.lang.Object getObjectProperty(org.thymeleaf.cache.ICache<org.thymeleaf.cache.ExpressionCacheKey, java.lang.Object>, java.lang.String, java.lang.Object);
    Code:
       0: aload_2
       1: invokestatic  #13                 // Method ognl/OgnlRuntime.getTargetClass:(Ljava/lang/Object;)Ljava/lang/Class;
       4: astore_3
       5: aload_3
       6: aload_1
       7: invokestatic  #57                 // Method computeMethodCacheKey:(Ljava/lang/Class;Ljava/lang/String;)Lorg/thymeleaf/cache/ExpressionCacheKey;
      10: astore        4
      12: aconst_null
      13: astore        5
      15: aload_0
      16: ifnull        32
      19: aload_0
      20: aload         4
      22: invokeinterface #58,  2           // InterfaceMethod org/thymeleaf/cache/ICache.get:(Ljava/lang/Object;)Ljava/lang/Object;
      27: checkcast     #59                 // class java/lang/reflect/Method
      30: astore        5
      32: aload         5
      34: ifnonnull     143
      37: aload_3
      38: invokestatic  #60                 // Method java/beans/Introspector.getBeanInfo:(Ljava/lang/Class;)Ljava/beans/BeanInfo;
      41: astore        6
      43: goto          56
      46: astore        7
      48: new           #40                 // class org/thymeleaf/standard/expression/OGNLShortcutExpression$OGNLShortcutExpressionNotApplicableException
      51: dup
      52: invokespecial #41                 // Method org/thymeleaf/standard/expression/OGNLShortcutExpression$OGNLShortcutExpressionNotApplicableException."<init>":()V
      55: athrow
      56: aload         6
      58: invokeinterface #62,  1           // InterfaceMethod java/beans/BeanInfo.getPropertyDescriptors:()[Ljava/beans/PropertyDescriptor;
      63: astore        7
      65: aload         7
      67: ifnull        143
      70: aload         7
      72: astore        8
      74: aload         8
      76: arraylength
      77: istore        9
      79: iconst_0
      80: istore        10
      82: iload         10
      84: iload         9
      86: if_icmpge     143
      89: aload         8
      91: iload         10
      93: aaload
      94: astore        11
      96: aload         11
      98: invokevirtual #63                 // Method java/beans/PropertyDescriptor.getName:()Ljava/lang/String;
     101: aload_1
     102: invokevirtual #43                 // Method java/lang/String.equals:(Ljava/lang/Object;)Z
     105: ifeq          137
     108: aload         11
     110: invokevirtual #64                 // Method java/beans/PropertyDescriptor.getReadMethod:()Ljava/lang/reflect/Method;
     113: astore        5
     115: aload         5
     117: ifnull        143
     120: aload_0
     121: ifnull        143
     124: aload_0
     125: aload         4
     127: aload         5
     129: invokeinterface #65,  3           // InterfaceMethod org/thymeleaf/cache/ICache.put:(Ljava/lang/Object;Ljava/lang/Object;)V
     134: goto          143
     137: iinc          10, 1
     140: goto          82
     143: aload         5
     145: ifnonnull     156
     148: new           #40                 // class org/thymeleaf/standard/expression/OGNLShortcutExpression$OGNLShortcutExpressionNotApplicableException
     151: dup
     152: invokespecial #41                 // Method org/thymeleaf/standard/expression/OGNLShortcutExpression$OGNLShortcutExpressionNotApplicableException."<init>":()V
     155: athrow
     156: aload         5
     158: aload_2
     159: getstatic     #66                 // Field NO_PARAMS:[Ljava/lang/Object;
     162: invokevirtual #67                 // Method java/lang/reflect/Method.invoke:(Ljava/lang/Object;[Ljava/lang/Object;)Ljava/lang/Object;
     165: areturn
     166: astore        6
     168: new           #40                 // class org/thymeleaf/standard/expression/OGNLShortcutExpression$OGNLShortcutExpressionNotApplicableException
     171: dup
     172: invokespecial #41                 // Method org/thymeleaf/standard/expression/OGNLShortcutExpression$OGNLShortcutExpressionNotApplicableException."<init>":()V
     175: athrow
     176: astore        6
     178: new           #40                 // class org/thymeleaf/standard/expression/OGNLShortcutExpression$OGNLShortcutExpressionNotApplicableException
     181: dup
     182: invokespecial #41                 // Method org/thymeleaf/standard/expression/OGNLShortcutExpression$OGNLShortcutExpressionNotApplicableException."<init>":()V
     185: athrow
    Exception table:
       from    to  target type
          37    43    46   Class java/beans/IntrospectionException
         156   165   166   Class java/lang/IllegalAccessException
         156   165   176   Class java/lang/reflect/InvocationTargetException

  private static java.lang.Object getMapProperty(java.lang.String, java.util.Map<?, ?>);
    Code:
       0: aload_0
       1: ldc           #70                 // String size
       3: invokevirtual #43                 // Method java/lang/String.equals:(Ljava/lang/Object;)Z
       6: ifeq          19
       9: aload_1
      10: invokeinterface #71,  1           // InterfaceMethod java/util/Map.size:()I
      15: invokestatic  #72                 // Method java/lang/Integer.valueOf:(I)Ljava/lang/Integer;
      18: areturn
      19: aload_0
      20: ldc           #73                 // String keys
      22: invokevirtual #43                 // Method java/lang/String.equals:(Ljava/lang/Object;)Z
      25: ifne          37
      28: aload_0
      29: ldc           #74                 // String keySet
      31: invokevirtual #43                 // Method java/lang/String.equals:(Ljava/lang/Object;)Z
      34: ifeq          44
      37: aload_1
      38: invokeinterface #75,  1           // InterfaceMethod java/util/Map.keySet:()Ljava/util/Set;
      43: areturn
      44: aload_0
      45: ldc           #76                 // String values
      47: invokevirtual #43                 // Method java/lang/String.equals:(Ljava/lang/Object;)Z
      50: ifeq          60
      53: aload_1
      54: invokeinterface #77,  1           // InterfaceMethod java/util/Map.values:()Ljava/util/Collection;
      59: areturn
      60: aload_0
      61: ldc           #78                 // String isEmpty
      63: invokevirtual #43                 // Method java/lang/String.equals:(Ljava/lang/Object;)Z
      66: ifeq          88
      69: aload_1
      70: invokeinterface #79,  1           // InterfaceMethod java/util/Map.isEmpty:()Z
      75: ifeq          84
      78: getstatic     #80                 // Field java/lang/Boolean.TRUE:Ljava/lang/Boolean;
      81: goto          87
      84: getstatic     #81                 // Field java/lang/Boolean.FALSE:Ljava/lang/Boolean;
      87: areturn
      88: aload_1
      89: aload_0
      90: invokeinterface #56,  2           // InterfaceMethod java/util/Map.get:(Ljava/lang/Object;)Ljava/lang/Object;
      95: areturn

  public static java.lang.Object getListProperty(org.thymeleaf.cache.ICache<org.thymeleaf.cache.ExpressionCacheKey, java.lang.Object>, java.lang.String, java.util.List<?>);
    Code:
       0: aload_1
       1: ldc           #70                 // String size
       3: invokevirtual #43                 // Method java/lang/String.equals:(Ljava/lang/Object;)Z
       6: ifeq          19
       9: aload_2
      10: invokeinterface #82,  1           // InterfaceMethod java/util/List.size:()I
      15: invokestatic  #72                 // Method java/lang/Integer.valueOf:(I)Ljava/lang/Integer;
      18: areturn
      19: aload_1
      20: ldc           #83                 // String iterator
      22: invokevirtual #43                 // Method java/lang/String.equals:(Ljava/lang/Object;)Z
      25: ifeq          35
      28: aload_2
      29: invokeinterface #84,  1           // InterfaceMethod java/util/List.iterator:()Ljava/util/Iterator;
      34: areturn
      35: aload_1
      36: ldc           #78                 // String isEmpty
      38: invokevirtual #43                 // Method java/lang/String.equals:(Ljava/lang/Object;)Z
      41: ifne          53
      44: aload_1
      45: ldc           #85                 // String empty
      47: invokevirtual #43                 // Method java/lang/String.equals:(Ljava/lang/Object;)Z
      50: ifeq          72
      53: aload_2
      54: invokeinterface #86,  1           // InterfaceMethod java/util/List.isEmpty:()Z
      59: ifeq          68
      62: getstatic     #80                 // Field java/lang/Boolean.TRUE:Ljava/lang/Boolean;
      65: goto          71
      68: getstatic     #81                 // Field java/lang/Boolean.FALSE:Ljava/lang/Boolean;
      71: areturn
      72: aload_0
      73: aload_1
      74: aload_2
      75: invokestatic  #16                 // Method getObjectProperty:(Lorg/thymeleaf/cache/ICache;Ljava/lang/String;Ljava/lang/Object;)Ljava/lang/Object;
      78: areturn

  public static java.lang.Object getArrayProperty(org.thymeleaf.cache.ICache<org.thymeleaf.cache.ExpressionCacheKey, java.lang.Object>, java.lang.String, java.lang.Object[]);
    Code:
       0: aload_1
       1: ldc           #87                 // String length
       3: invokevirtual #43                 // Method java/lang/String.equals:(Ljava/lang/Object;)Z
       6: ifeq          17
       9: aload_2
      10: invokestatic  #88                 // Method java/lang/reflect/Array.getLength:(Ljava/lang/Object;)I
      13: invokestatic  #72                 // Method java/lang/Integer.valueOf:(I)Ljava/lang/Integer;
      16: areturn
      17: aload_0
      18: aload_1
      19: aload_2
      20: invokestatic  #16                 // Method getObjectProperty:(Lorg/thymeleaf/cache/ICache;Ljava/lang/String;Ljava/lang/Object;)Ljava/lang/Object;
      23: areturn

  public static java.lang.Object getEnumerationProperty(org.thymeleaf.cache.ICache<org.thymeleaf.cache.ExpressionCacheKey, java.lang.Object>, java.lang.String, java.util.Enumeration);
    Code:
       0: aload_1
       1: ldc           #89                 // String next
       3: invokevirtual #43                 // Method java/lang/String.equals:(Ljava/lang/Object;)Z
       6: ifne          18
       9: aload_1
      10: ldc           #90                 // String nextElement
      12: invokevirtual #43                 // Method java/lang/String.equals:(Ljava/lang/Object;)Z
      15: ifeq          25
      18: aload_2
      19: invokeinterface #91,  1           // InterfaceMethod java/util/Enumeration.nextElement:()Ljava/lang/Object;
      24: areturn
      25: aload_1
      26: ldc           #92                 // String hasNext
      28: invokevirtual #43                 // Method java/lang/String.equals:(Ljava/lang/Object;)Z
      31: ifne          43
      34: aload_1
      35: ldc           #93                 // String hasMoreElements
      37: invokevirtual #43                 // Method java/lang/String.equals:(Ljava/lang/Object;)Z
      40: ifeq          62
      43: aload_2
      44: invokeinterface #94,  1           // InterfaceMethod java/util/Enumeration.hasMoreElements:()Z
      49: ifeq          58
      52: getstatic     #80                 // Field java/lang/Boolean.TRUE:Ljava/lang/Boolean;
      55: goto          61
      58: getstatic     #81                 // Field java/lang/Boolean.FALSE:Ljava/lang/Boolean;
      61: areturn
      62: aload_0
      63: aload_1
      64: aload_2
      65: invokestatic  #16                 // Method getObjectProperty:(Lorg/thymeleaf/cache/ICache;Ljava/lang/String;Ljava/lang/Object;)Ljava/lang/Object;
      68: areturn

  public static java.lang.Object getIteratorProperty(org.thymeleaf.cache.ICache<org.thymeleaf.cache.ExpressionCacheKey, java.lang.Object>, java.lang.String, java.util.Iterator<?>);
    Code:
       0: aload_1
       1: ldc           #89                 // String next
       3: invokevirtual #43                 // Method java/lang/String.equals:(Ljava/lang/Object;)Z
       6: ifeq          16
       9: aload_2
      10: invokeinterface #95,  1           // InterfaceMethod java/util/Iterator.next:()Ljava/lang/Object;
      15: areturn
      16: aload_1
      17: ldc           #92                 // String hasNext
      19: invokevirtual #43                 // Method java/lang/String.equals:(Ljava/lang/Object;)Z
      22: ifeq          44
      25: aload_2
      26: invokeinterface #96,  1           // InterfaceMethod java/util/Iterator.hasNext:()Z
      31: ifeq          40
      34: getstatic     #80                 // Field java/lang/Boolean.TRUE:Ljava/lang/Boolean;
      37: goto          43
      40: getstatic     #81                 // Field java/lang/Boolean.FALSE:Ljava/lang/Boolean;
      43: areturn
      44: aload_0
      45: aload_1
      46: aload_2
      47: invokestatic  #16                 // Method getObjectProperty:(Lorg/thymeleaf/cache/ICache;Ljava/lang/String;Ljava/lang/Object;)Ljava/lang/Object;
      50: areturn

  public static java.lang.Object getSetProperty(org.thymeleaf.cache.ICache<org.thymeleaf.cache.ExpressionCacheKey, java.lang.Object>, java.lang.String, java.util.Set<?>);
    Code:
       0: aload_1
       1: ldc           #70                 // String size
       3: invokevirtual #43                 // Method java/lang/String.equals:(Ljava/lang/Object;)Z
       6: ifeq          19
       9: aload_2
      10: invokeinterface #97,  1           // InterfaceMethod java/util/Set.size:()I
      15: invokestatic  #72                 // Method java/lang/Integer.valueOf:(I)Ljava/lang/Integer;
      18: areturn
      19: aload_1
      20: ldc           #83                 // String iterator
      22: invokevirtual #43                 // Method java/lang/String.equals:(Ljava/lang/Object;)Z
      25: ifeq          35
      28: aload_2
      29: invokeinterface #98,  1           // InterfaceMethod java/util/Set.iterator:()Ljava/util/Iterator;
      34: areturn
      35: aload_1
      36: ldc           #78                 // String isEmpty
      38: invokevirtual #43                 // Method java/lang/String.equals:(Ljava/lang/Object;)Z
      41: ifeq          63
      44: aload_2
      45: invokeinterface #99,  1           // InterfaceMethod java/util/Set.isEmpty:()Z
      50: ifeq          59
      53: getstatic     #80                 // Field java/lang/Boolean.TRUE:Ljava/lang/Boolean;
      56: goto          62
      59: getstatic     #81                 // Field java/lang/Boolean.FALSE:Ljava/lang/Boolean;
      62: areturn
      63: aload_0
      64: aload_1
      65: aload_2
      66: invokestatic  #16                 // Method getObjectProperty:(Lorg/thymeleaf/cache/ICache;Ljava/lang/String;Ljava/lang/Object;)Ljava/lang/Object;
      69: areturn

  static java.lang.String[] parse(java.lang.String);
    Code:
       0: aload_0
       1: iconst_0
       2: iconst_0
       3: aload_0
       4: invokevirtual #100                // Method java/lang/String.length:()I
       7: invokestatic  #101                // Method doParseExpr:(Ljava/lang/String;III)[Ljava/lang/String;
      10: areturn

  private static java.lang.String[] doParseExpr(java.lang.String, int, int, int);
    Code:
       0: iload_2
       1: istore        5
       3: iconst_1
       4: istore        6
       6: iload         5
       8: iload_3
       9: if_icmpge     67
      12: aload_0
      13: iload         5
      15: invokestatic  #102                // Method java/lang/Character.codePointAt:(Ljava/lang/CharSequence;I)I
      18: istore        4
      20: iload         4
      22: bipush        46
      24: if_icmpne     30
      27: goto          67
      30: iload         6
      32: ifeq          51
      35: iload         4
      37: invokestatic  #103                // Method java/lang/Character.isJavaIdentifierStart:(I)Z
      40: ifne          45
      43: aconst_null
      44: areturn
      45: iconst_0
      46: istore        6
      48: goto          61
      51: iload         4
      53: invokestatic  #104                // Method java/lang/Character.isJavaIdentifierPart:(I)Z
      56: ifne          61
      59: aconst_null
      60: areturn
      61: iinc          5, 1
      64: goto          6
      67: iload         5
      69: iload_3
      70: if_icmpge     94
      73: aload_0
      74: iload_1
      75: iconst_1
      76: iadd
      77: iload         5
      79: iconst_1
      80: iadd
      81: iload_3
      82: invokestatic  #101                // Method doParseExpr:(Ljava/lang/String;III)[Ljava/lang/String;
      85: astore        7
      87: aload         7
      89: ifnonnull     102
      92: aconst_null
      93: areturn
      94: iload_1
      95: iconst_1
      96: iadd
      97: anewarray     #105                // class java/lang/String
     100: astore        7
     102: aload         7
     104: iload_1
     105: aload_0
     106: iload_2
     107: iload         5
     109: invokevirtual #106                // Method java/lang/String.substring:(II)Ljava/lang/String;
     112: aastore
     113: ldc           #107                // String true
     115: aload         7
     117: iload_1
     118: aaload
     119: invokevirtual #108                // Method java/lang/String.equalsIgnoreCase:(Ljava/lang/String;)Z
     122: ifne          149
     125: ldc           #109                // String false
     127: aload         7
     129: iload_1
     130: aaload
     131: invokevirtual #108                // Method java/lang/String.equalsIgnoreCase:(Ljava/lang/String;)Z
     134: ifne          149
     137: ldc           #110                // String null
     139: aload         7
     141: iload_1
     142: aaload
     143: invokevirtual #108                // Method java/lang/String.equalsIgnoreCase:(Ljava/lang/String;)Z
     146: ifeq          151
     149: aconst_null
     150: areturn
     151: aload         7
     153: areturn

  private static org.thymeleaf.cache.ExpressionCacheKey computeMethodCacheKey(java.lang.Class<?>, java.lang.String);
    Code:
       0: new           #111                // class org/thymeleaf/cache/ExpressionCacheKey
       3: dup
       4: ldc           #113                // String ognlsc
       6: aload_0
       7: invokevirtual #114                // Method java/lang/Class.getName:()Ljava/lang/String;
      10: aload_1
      11: invokespecial #115                // Method org/thymeleaf/cache/ExpressionCacheKey."<init>":(Ljava/lang/String;Ljava/lang/String;Ljava/lang/String;)V
      14: areturn

  static {};
    Code:
       0: ldc           #112                // class org/thymeleaf/standard/expression/OGNLShortcutExpression
       2: invokestatic  #116                // Method org/slf4j/LoggerFactory.getLogger:(Ljava/lang/Class;)Lorg/slf4j/Logger;
       5: putstatic     #52                 // Field LOGGER:Lorg/slf4j/Logger;
       8: iconst_0
       9: anewarray     #117                // class java/lang/Object
      12: putstatic     #66                 // Field NO_PARAMS:[Ljava/lang/Object;
      15: return
}
