Compiled from "JournalStorageManager.java"
class org.apache.activemq.artemis.core.persistence.impl.journal.JournalStorageManager$FinishPageMessageOperation extends org.apache.activemq.artemis.core.transaction.TransactionOperationAbstract implements org.apache.activemq.artemis.core.transaction.TransactionOperation {
  private org.apache.activemq.artemis.core.persistence.impl.journal.JournalStorageManager$FinishPageMessageOperation();
    Code:
       0: aload_0
       1: invokespecial #2                  // Method org/apache/activemq/artemis/core/transaction/TransactionOperationAbstract."<init>":()V
       4: return

  public void afterCommit(org.apache.activemq.artemis.core.transaction.Transaction);
    Code:
       0: aload_1
       1: iconst_5
       2: invokeinterface #4,  2            // InterfaceMethod org/apache/activemq/artemis/core/transaction/Transaction.getProperty:(I)Ljava/lang/Object;
       7: checkcast     #5                  // class org/apache/activemq/artemis/core/paging/PageTransactionInfo
      10: astore_2
      11: aload_2
      12: ifnull        21
      15: aload_2
      16: invokeinterface #6,  1            // InterfaceMethod org/apache/activemq/artemis/core/paging/PageTransactionInfo.commit:()V
      21: return

  public void afterRollback(org.apache.activemq.artemis.core.transaction.Transaction);
    Code:
       0: aload_1
       1: iconst_5
       2: invokeinterface #4,  2            // InterfaceMethod org/apache/activemq/artemis/core/transaction/Transaction.getProperty:(I)Ljava/lang/Object;
       7: checkcast     #5                  // class org/apache/activemq/artemis/core/paging/PageTransactionInfo
      10: astore_2
      11: aload_1
      12: invokeinterface #7,  1            // InterfaceMethod org/apache/activemq/artemis/core/transaction/Transaction.getState:()Lorg/apache/activemq/artemis/core/transaction/Transaction$State;
      17: getstatic     #8                  // Field org/apache/activemq/artemis/core/transaction/Transaction$State.PREPARED:Lorg/apache/activemq/artemis/core/transaction/Transaction$State;
      20: if_acmpne     33
      23: aload_2
      24: ifnull        33
      27: aload_2
      28: invokeinterface #9,  1            // InterfaceMethod org/apache/activemq/artemis/core/paging/PageTransactionInfo.rollback:()V
      33: return

  org.apache.activemq.artemis.core.persistence.impl.journal.JournalStorageManager$FinishPageMessageOperation(org.apache.activemq.artemis.core.persistence.impl.journal.JournalStorageManager$1);
    Code:
       0: aload_0
       1: invokespecial #1                  // Method "<init>":()V
       4: return
}
