Compiled from "JournalStorageManager.java"
public class org.apache.activemq.artemis.core.persistence.impl.journal.JournalStorageManager$DuplicateIDEncoding implements org.apache.activemq.artemis.core.journal.EncodingSupport {
  org.apache.activemq.artemis.api.core.SimpleString address;

  byte[] duplID;

  public org.apache.activemq.artemis.core.persistence.impl.journal.JournalStorageManager$DuplicateIDEncoding(org.apache.activemq.artemis.api.core.SimpleString, byte[]);
    Code:
       0: aload_0
       1: invokespecial #1                  // Method java/lang/Object."<init>":()V
       4: aload_0
       5: aload_1
       6: putfield      #2                  // Field address:Lorg/apache/activemq/artemis/api/core/SimpleString;
       9: aload_0
      10: aload_2
      11: putfield      #3                  // Field duplID:[B
      14: return

  public org.apache.activemq.artemis.core.persistence.impl.journal.JournalStorageManager$DuplicateIDEncoding();
    Code:
       0: aload_0
       1: invokespecial #1                  // Method java/lang/Object."<init>":()V
       4: return

  public void decode(org.apache.activemq.artemis.api.core.ActiveMQBuffer);
    Code:
       0: aload_0
       1: aload_1
       2: invokeinterface #4,  1            // InterfaceMethod org/apache/activemq/artemis/api/core/ActiveMQBuffer.readSimpleString:()Lorg/apache/activemq/artemis/api/core/SimpleString;
       7: putfield      #2                  // Field address:Lorg/apache/activemq/artemis/api/core/SimpleString;
      10: aload_1
      11: invokeinterface #5,  1            // InterfaceMethod org/apache/activemq/artemis/api/core/ActiveMQBuffer.readInt:()I
      16: istore_2
      17: aload_0
      18: iload_2
      19: newarray       byte
      21: putfield      #3                  // Field duplID:[B
      24: aload_1
      25: aload_0
      26: getfield      #3                  // Field duplID:[B
      29: invokeinterface #6,  2            // InterfaceMethod org/apache/activemq/artemis/api/core/ActiveMQBuffer.readBytes:([B)V
      34: return

  public void encode(org.apache.activemq.artemis.api.core.ActiveMQBuffer);
    Code:
       0: aload_1
       1: aload_0
       2: getfield      #2                  // Field address:Lorg/apache/activemq/artemis/api/core/SimpleString;
       5: invokeinterface #7,  2            // InterfaceMethod org/apache/activemq/artemis/api/core/ActiveMQBuffer.writeSimpleString:(Lorg/apache/activemq/artemis/api/core/SimpleString;)V
      10: aload_1
      11: aload_0
      12: getfield      #3                  // Field duplID:[B
      15: arraylength
      16: invokeinterface #8,  2            // InterfaceMethod org/apache/activemq/artemis/api/core/ActiveMQBuffer.writeInt:(I)V
      21: aload_1
      22: aload_0
      23: getfield      #3                  // Field duplID:[B
      26: invokeinterface #9,  2            // InterfaceMethod org/apache/activemq/artemis/api/core/ActiveMQBuffer.writeBytes:([B)V
      31: return

  public int getEncodeSize();
    Code:
       0: aload_0
       1: getfield      #2                  // Field address:Lorg/apache/activemq/artemis/api/core/SimpleString;
       4: invokestatic  #10                 // Method org/apache/activemq/artemis/api/core/SimpleString.sizeofString:(Lorg/apache/activemq/artemis/api/core/SimpleString;)I
       7: iconst_4
       8: iadd
       9: aload_0
      10: getfield      #3                  // Field duplID:[B
      13: arraylength
      14: iadd
      15: ireturn

  public java.lang.String toString();
    Code:
       0: aconst_null
       1: astore_1
       2: aload_0
       3: getfield      #2                  // Field address:Lorg/apache/activemq/artemis/api/core/SimpleString;
       6: invokevirtual #12                 // Method org/apache/activemq/artemis/api/core/SimpleString.toString:()Ljava/lang/String;
       9: ldc           #13                 // String BRIDGE
      11: invokevirtual #14                 // Method java/lang/String.startsWith:(Ljava/lang/String;)Z
      14: ifeq          103
      17: aload_0
      18: getfield      #3                  // Field duplID:[B
      21: arraylength
      22: bipush        24
      24: if_icmpne     103
      27: aload_0
      28: getfield      #3                  // Field duplID:[B
      31: invokestatic  #15                 // Method java/nio/ByteBuffer.wrap:([B)Ljava/nio/ByteBuffer;
      34: astore_2
      35: bipush        16
      37: newarray       byte
      39: astore_3
      40: aload_2
      41: aload_3
      42: invokevirtual #16                 // Method java/nio/ByteBuffer.get:([B)Ljava/nio/ByteBuffer;
      45: pop
      46: new           #17                 // class org/apache/activemq/artemis/utils/UUID
      49: dup
      50: iconst_1
      51: aload_3
      52: invokespecial #18                 // Method org/apache/activemq/artemis/utils/UUID."<init>":(I[B)V
      55: astore        4
      57: aload_2
      58: invokevirtual #19                 // Method java/nio/ByteBuffer.getLong:()J
      61: lstore        5
      63: new           #20                 // class java/lang/StringBuilder
      66: dup
      67: invokespecial #21                 // Method java/lang/StringBuilder."<init>":()V
      70: ldc           #22                 // String nodeUUID=
      72: invokevirtual #23                 // Method java/lang/StringBuilder.append:(Ljava/lang/String;)Ljava/lang/StringBuilder;
      75: aload         4
      77: invokevirtual #24                 // Method org/apache/activemq/artemis/utils/UUID.toString:()Ljava/lang/String;
      80: invokevirtual #23                 // Method java/lang/StringBuilder.append:(Ljava/lang/String;)Ljava/lang/StringBuilder;
      83: ldc           #25                 // String  messageID=
      85: invokevirtual #23                 // Method java/lang/StringBuilder.append:(Ljava/lang/String;)Ljava/lang/StringBuilder;
      88: lload         5
      90: invokevirtual #26                 // Method java/lang/StringBuilder.append:(J)Ljava/lang/StringBuilder;
      93: invokevirtual #27                 // Method java/lang/StringBuilder.toString:()Ljava/lang/String;
      96: astore_1
      97: goto          103
     100: astore_2
     101: aconst_null
     102: astore_1
     103: aload_1
     104: ifnull        160
     107: new           #20                 // class java/lang/StringBuilder
     110: dup
     111: invokespecial #21                 // Method java/lang/StringBuilder."<init>":()V
     114: ldc           #29                 // String DuplicateIDEncoding [address=
     116: invokevirtual #23                 // Method java/lang/StringBuilder.append:(Ljava/lang/String;)Ljava/lang/StringBuilder;
     119: aload_0
     120: getfield      #2                  // Field address:Lorg/apache/activemq/artemis/api/core/SimpleString;
     123: invokevirtual #30                 // Method java/lang/StringBuilder.append:(Ljava/lang/Object;)Ljava/lang/StringBuilder;
     126: ldc           #31                 // String , duplID=
     128: invokevirtual #23                 // Method java/lang/StringBuilder.append:(Ljava/lang/String;)Ljava/lang/StringBuilder;
     131: aload_0
     132: getfield      #3                  // Field duplID:[B
     135: iconst_2
     136: invokestatic  #32                 // Method org/apache/activemq/artemis/utils/ByteUtil.bytesToHex:([BI)Ljava/lang/String;
     139: invokevirtual #23                 // Method java/lang/StringBuilder.append:(Ljava/lang/String;)Ljava/lang/StringBuilder;
     142: ldc           #33                 // String  /
     144: invokevirtual #23                 // Method java/lang/StringBuilder.append:(Ljava/lang/String;)Ljava/lang/StringBuilder;
     147: aload_1
     148: invokevirtual #23                 // Method java/lang/StringBuilder.append:(Ljava/lang/String;)Ljava/lang/StringBuilder;
     151: ldc           #34                 // String ]
     153: invokevirtual #23                 // Method java/lang/StringBuilder.append:(Ljava/lang/String;)Ljava/lang/StringBuilder;
     156: invokevirtual #27                 // Method java/lang/StringBuilder.toString:()Ljava/lang/String;
     159: areturn
     160: new           #20                 // class java/lang/StringBuilder
     163: dup
     164: invokespecial #21                 // Method java/lang/StringBuilder."<init>":()V
     167: ldc           #29                 // String DuplicateIDEncoding [address=
     169: invokevirtual #23                 // Method java/lang/StringBuilder.append:(Ljava/lang/String;)Ljava/lang/StringBuilder;
     172: aload_0
     173: getfield      #2                  // Field address:Lorg/apache/activemq/artemis/api/core/SimpleString;
     176: invokevirtual #30                 // Method java/lang/StringBuilder.append:(Ljava/lang/Object;)Ljava/lang/StringBuilder;
     179: ldc           #35                 // String ,str=
     181: invokevirtual #23                 // Method java/lang/StringBuilder.append:(Ljava/lang/String;)Ljava/lang/StringBuilder;
     184: aload_0
     185: getfield      #3                  // Field duplID:[B
     188: invokestatic  #36                 // Method org/apache/activemq/artemis/utils/ByteUtil.toSimpleString:([B)Ljava/lang/String;
     191: invokevirtual #23                 // Method java/lang/StringBuilder.append:(Ljava/lang/String;)Ljava/lang/StringBuilder;
     194: ldc           #31                 // String , duplID=
     196: invokevirtual #23                 // Method java/lang/StringBuilder.append:(Ljava/lang/String;)Ljava/lang/StringBuilder;
     199: aload_0
     200: getfield      #3                  // Field duplID:[B
     203: iconst_2
     204: invokestatic  #32                 // Method org/apache/activemq/artemis/utils/ByteUtil.bytesToHex:([BI)Ljava/lang/String;
     207: invokevirtual #23                 // Method java/lang/StringBuilder.append:(Ljava/lang/String;)Ljava/lang/StringBuilder;
     210: ldc           #34                 // String ]
     212: invokevirtual #23                 // Method java/lang/StringBuilder.append:(Ljava/lang/String;)Ljava/lang/StringBuilder;
     215: invokevirtual #27                 // Method java/lang/StringBuilder.toString:()Ljava/lang/String;
     218: areturn
    Exception table:
       from    to  target type
          27    97   100   Class java/lang/Throwable
}
