Compiled from "JournalStorageManager.java"
final class org.apache.activemq.artemis.core.persistence.impl.journal.JournalStorageManager$DummyOperationContext implements org.apache.activemq.artemis.core.persistence.OperationContext {
  private static org.apache.activemq.artemis.core.persistence.impl.journal.JournalStorageManager$DummyOperationContext instance;

  private org.apache.activemq.artemis.core.persistence.impl.journal.JournalStorageManager$DummyOperationContext();
    Code:
       0: aload_0
       1: invokespecial #1                  // Method java/lang/Object."<init>":()V
       4: return

  public static org.apache.activemq.artemis.core.persistence.OperationContext getInstance();
    Code:
       0: getstatic     #2                  // Field instance:Lorg/apache/activemq/artemis/core/persistence/impl/journal/JournalStorageManager$DummyOperationContext;
       3: areturn

  public void executeOnCompletion(org.apache.activemq.artemis.core.io.IOCallback);
    Code:
       0: aload_1
       1: invokeinterface #3,  1            // InterfaceMethod org/apache/activemq/artemis/core/io/IOCallback.done:()V
       6: return

  public void replicationDone();
    Code:
       0: return

  public void replicationLineUp();
    Code:
       0: return

  public void storeLineUp();
    Code:
       0: return

  public void done();
    Code:
       0: return

  public void onError(int, java.lang.String);
    Code:
       0: return

  public void waitCompletion();
    Code:
       0: return

  public boolean waitCompletion(long);
    Code:
       0: iconst_1
       1: ireturn

  public void pageSyncLineUp();
    Code:
       0: return

  public void pageSyncDone();
    Code:
       0: return

  static {};
    Code:
       0: new           #4                  // class org/apache/activemq/artemis/core/persistence/impl/journal/JournalStorageManager$DummyOperationContext
       3: dup
       4: invokespecial #5                  // Method "<init>":()V
       7: putstatic     #2                  // Field instance:Lorg/apache/activemq/artemis/core/persistence/impl/journal/JournalStorageManager$DummyOperationContext;
      10: return
}
