Compiled from "DescriptorRendererImpl.kt"
final class kotlin.reflect.jvm.internal.impl.renderer.DescriptorRendererImpl$renderTypeConstructor$1 extends kotlin.jvm.internal.Lambda implements kotlin.jvm.functions.Function1<kotlin.reflect.jvm.internal.impl.types.KotlinType, java.lang.Object> {
  public static final kotlin.reflect.jvm.internal.impl.renderer.DescriptorRendererImpl$renderTypeConstructor$1 INSTANCE;

  kotlin.reflect.jvm.internal.impl.renderer.DescriptorRendererImpl$renderTypeConstructor$1();
    Code:
       0: aload_0
       1: iconst_1
       2: invokespecial #12                 // Method kotlin/jvm/internal/Lambda."<init>":(I)V
       5: return

  public final java.lang.Object invoke(kotlin.reflect.jvm.internal.impl.types.KotlinType);
    Code:
       0: aload_1
       1: ldc           #1                  // String it
       3: invokestatic  #11                 // Method kotlin/jvm/internal/Intrinsics.checkNotNullParameter:(Ljava/lang/Object;Ljava/lang/String;)V
       6: aload_1
       7: instanceof    #9                  // class kotlin/reflect/jvm/internal/impl/types/StubTypeForBuilderInference
      10: ifeq          23
      13: aload_1
      14: checkcast     #9                  // class kotlin/reflect/jvm/internal/impl/types/StubTypeForBuilderInference
      17: invokevirtual #15                 // Method kotlin/reflect/jvm/internal/impl/types/StubTypeForBuilderInference.getOriginalTypeVariable:()Lkotlin/reflect/jvm/internal/impl/types/checker/NewTypeVariableConstructor;
      20: goto          24
      23: aload_1
      24: areturn

  public java.lang.Object invoke(java.lang.Object);
    Code:
       0: aload_0
       1: aload_1
       2: checkcast     #8                  // class kotlin/reflect/jvm/internal/impl/types/KotlinType
       5: invokevirtual #14                 // Method invoke:(Lkotlin/reflect/jvm/internal/impl/types/KotlinType;)Ljava/lang/Object;
       8: areturn

  static {};
    Code:
       0: new           #7                  // class kotlin/reflect/jvm/internal/impl/renderer/DescriptorRendererImpl$renderTypeConstructor$1
       3: dup
       4: invokespecial #13                 // Method "<init>":()V
       7: putstatic     #10                 // Field INSTANCE:Lkotlin/reflect/jvm/internal/impl/renderer/DescriptorRendererImpl$renderTypeConstructor$1;
      10: return
}
