Compiled from "AptWriter.java"
public class io.dekorate.processor.AptWriter extends io.dekorate.processor.SimpleFileWriter implements io.dekorate.SessionWriter,io.dekorate.WithProject {
  protected static final java.lang.String PACKAGE;

  protected static final java.lang.String FILENAME;

  protected static final java.lang.String CONFIG;

  protected static final java.lang.String PROJECT;

  protected static final java.lang.String[] STRIP;

  protected static final java.lang.String JSON;

  protected static final java.lang.String YML;

  protected static final java.lang.String TMP;

  protected static final java.lang.String DOT;

  private final javax.annotation.processing.ProcessingEnvironment processingEnv;

  private final io.dekorate.Logger LOGGER;

  public io.dekorate.processor.AptWriter(io.dekorate.project.Project, javax.annotation.processing.ProcessingEnvironment);
    Code:
       0: aload_0
       1: aload_1
       2: invokespecial #1                  // Method io/dekorate/processor/SimpleFileWriter."<init>":(Lio/dekorate/project/Project;)V
       5: aload_0
       6: invokestatic  #2                  // Method io/dekorate/LoggerFactory.getLogger:()Lio/dekorate/Logger;
       9: putfield      #3                  // Field LOGGER:Lio/dekorate/Logger;
      12: aload_0
      13: aload_2
      14: putfield      #4                  // Field processingEnv:Ljavax/annotation/processing/ProcessingEnvironment;
      17: return

  public java.util.Map<java.lang.String, java.lang.String> write(io.dekorate.Session);
    Code:
       0: aload_1
       1: invokevirtual #5                  // Method io/dekorate/Session.close:()Ljava/util/Map;
       4: pop
       5: aload_1
       6: invokevirtual #6                  // Method io/dekorate/Session.getGeneratedResources:()Ljava/util/Map;
       9: astore_2
      10: aload_1
      11: invokevirtual #7                  // Method io/dekorate/Session.configurators:()Lio/dekorate/Configurators;
      14: invokevirtual #8                  // Method io/dekorate/Configurators.toSet:()Ljava/util/Set;
      17: astore_3
      18: aload_2
      19: aload_0
      20: invokedynamic #9,  0              // InvokeDynamic #0:accept:(Lio/dekorate/processor/AptWriter;)Ljava/util/function/BiConsumer;
      25: invokeinterface #10,  2           // InterfaceMethod java/util/Map.forEach:(Ljava/util/function/BiConsumer;)V
      30: aload_3
      31: aload_0
      32: invokedynamic #11,  0             // InvokeDynamic #1:accept:(Lio/dekorate/processor/AptWriter;)Ljava/util/function/Consumer;
      37: invokeinterface #12,  2           // InterfaceMethod java/util/Set.forEach:(Ljava/util/function/Consumer;)V
      42: aload_0
      43: aload_0
      44: invokevirtual #13                 // Method getProject:()Lio/dekorate/project/Project;
      47: invokevirtual #14                 // Method write:(Lio/dekorate/project/Project;)Ljava/util/Map$Entry;
      50: pop
      51: aconst_null
      52: areturn

  public java.util.Map<java.lang.String, java.lang.String> write(java.lang.String, io.dekorate.deps.kubernetes.api.model.KubernetesList);
    Code:
       0: new           #15                 // class java/util/HashMap
       3: dup
       4: invokespecial #16                 // Method java/util/HashMap."<init>":()V
       7: astore_3
       8: aload_0
       9: getfield      #4                  // Field processingEnv:Ljavax/annotation/processing/ProcessingEnvironment;
      12: invokeinterface #17,  1           // InterfaceMethod javax/annotation/processing/ProcessingEnvironment.getFiler:()Ljavax/annotation/processing/Filer;
      17: getstatic     #18                 // Field javax/tools/StandardLocation.CLASS_OUTPUT:Ljavax/tools/StandardLocation;
      20: ldc           #20                 // String
      22: new           #21                 // class java/lang/StringBuilder
      25: dup
      26: invokespecial #22                 // Method java/lang/StringBuilder."<init>":()V
      29: aload_0
      30: invokevirtual #13                 // Method getProject:()Lio/dekorate/project/Project;
      33: invokevirtual #23                 // Method io/dekorate/project/Project.getDekorateOutputDir:()Ljava/lang/String;
      36: invokevirtual #24                 // Method java/lang/StringBuilder.append:(Ljava/lang/String;)Ljava/lang/StringBuilder;
      39: ldc           #25                 // String /
      41: invokevirtual #24                 // Method java/lang/StringBuilder.append:(Ljava/lang/String;)Ljava/lang/StringBuilder;
      44: ldc           #26                 // String %s.%s
      46: iconst_2
      47: anewarray     #27                 // class java/lang/Object
      50: dup
      51: iconst_0
      52: aload_1
      53: aastore
      54: dup
      55: iconst_1
      56: ldc           #28                 // String json
      58: aastore
      59: invokestatic  #29                 // Method java/lang/String.format:(Ljava/lang/String;[Ljava/lang/Object;)Ljava/lang/String;
      62: invokevirtual #24                 // Method java/lang/StringBuilder.append:(Ljava/lang/String;)Ljava/lang/StringBuilder;
      65: invokevirtual #30                 // Method java/lang/StringBuilder.toString:()Ljava/lang/String;
      68: iconst_0
      69: anewarray     #31                 // class javax/lang/model/element/Element
      72: invokeinterface #32,  5           // InterfaceMethod javax/annotation/processing/Filer.createResource:(Ljavax/tools/JavaFileManager$Location;Ljava/lang/CharSequence;Ljava/lang/CharSequence;[Ljavax/lang/model/element/Element;)Ljavax/tools/FileObject;
      77: astore        4
      79: aload         4
      81: invokeinterface #33,  1           // InterfaceMethod javax/tools/FileObject.openWriter:()Ljava/io/Writer;
      86: astore        5
      88: aconst_null
      89: astore        6
      91: aload_2
      92: invokestatic  #34                 // Method io/dekorate/utils/Serialization.asJson:(Ljava/lang/Object;)Ljava/lang/String;
      95: astore        7
      97: aload_0
      98: getfield      #3                  // Field LOGGER:Lio/dekorate/Logger;
     101: new           #21                 // class java/lang/StringBuilder
     104: dup
     105: invokespecial #22                 // Method java/lang/StringBuilder."<init>":()V
     108: ldc           #35                 // String Writing:
     110: invokevirtual #24                 // Method java/lang/StringBuilder.append:(Ljava/lang/String;)Ljava/lang/StringBuilder;
     113: aload         4
     115: invokeinterface #36,  1           // InterfaceMethod javax/tools/FileObject.toUri:()Ljava/net/URI;
     120: invokevirtual #37                 // Method java/lang/StringBuilder.append:(Ljava/lang/Object;)Ljava/lang/StringBuilder;
     123: invokevirtual #30                 // Method java/lang/StringBuilder.toString:()Ljava/lang/String;
     126: invokeinterface #38,  2           // InterfaceMethod io/dekorate/Logger.info:(Ljava/lang/String;)V
     131: aload         5
     133: aload         7
     135: invokevirtual #39                 // Method java/io/Writer.write:(Ljava/lang/String;)V
     138: aload_3
     139: aload         4
     141: invokeinterface #40,  1           // InterfaceMethod javax/tools/FileObject.getName:()Ljava/lang/String;
     146: aload         7
     148: invokeinterface #41,  3           // InterfaceMethod java/util/Map.put:(Ljava/lang/Object;Ljava/lang/Object;)Ljava/lang/Object;
     153: pop
     154: aload         5
     156: ifnull        241
     159: aload         6
     161: ifnull        184
     164: aload         5
     166: invokevirtual #42                 // Method java/io/Writer.close:()V
     169: goto          241
     172: astore        7
     174: aload         6
     176: aload         7
     178: invokevirtual #44                 // Method java/lang/Throwable.addSuppressed:(Ljava/lang/Throwable;)V
     181: goto          241
     184: aload         5
     186: invokevirtual #42                 // Method java/io/Writer.close:()V
     189: goto          241
     192: astore        7
     194: aload         7
     196: astore        6
     198: aload         7
     200: athrow
     201: astore        8
     203: aload         5
     205: ifnull        238
     208: aload         6
     210: ifnull        233
     213: aload         5
     215: invokevirtual #42                 // Method java/io/Writer.close:()V
     218: goto          238
     221: astore        9
     223: aload         6
     225: aload         9
     227: invokevirtual #44                 // Method java/lang/Throwable.addSuppressed:(Ljava/lang/Throwable;)V
     230: goto          238
     233: aload         5
     235: invokevirtual #42                 // Method java/io/Writer.close:()V
     238: aload         8
     240: athrow
     241: aload_0
     242: getfield      #4                  // Field processingEnv:Ljavax/annotation/processing/ProcessingEnvironment;
     245: invokeinterface #17,  1           // InterfaceMethod javax/annotation/processing/ProcessingEnvironment.getFiler:()Ljavax/annotation/processing/Filer;
     250: getstatic     #18                 // Field javax/tools/StandardLocation.CLASS_OUTPUT:Ljavax/tools/StandardLocation;
     253: ldc           #20                 // String
     255: new           #21                 // class java/lang/StringBuilder
     258: dup
     259: invokespecial #22                 // Method java/lang/StringBuilder."<init>":()V
     262: aload_0
     263: invokevirtual #13                 // Method getProject:()Lio/dekorate/project/Project;
     266: invokevirtual #23                 // Method io/dekorate/project/Project.getDekorateOutputDir:()Ljava/lang/String;
     269: invokevirtual #24                 // Method java/lang/StringBuilder.append:(Ljava/lang/String;)Ljava/lang/StringBuilder;
     272: ldc           #25                 // String /
     274: invokevirtual #24                 // Method java/lang/StringBuilder.append:(Ljava/lang/String;)Ljava/lang/StringBuilder;
     277: ldc           #26                 // String %s.%s
     279: iconst_2
     280: anewarray     #27                 // class java/lang/Object
     283: dup
     284: iconst_0
     285: aload_1
     286: aastore
     287: dup
     288: iconst_1
     289: ldc           #45                 // String yml
     291: aastore
     292: invokestatic  #29                 // Method java/lang/String.format:(Ljava/lang/String;[Ljava/lang/Object;)Ljava/lang/String;
     295: invokevirtual #24                 // Method java/lang/StringBuilder.append:(Ljava/lang/String;)Ljava/lang/StringBuilder;
     298: invokevirtual #30                 // Method java/lang/StringBuilder.toString:()Ljava/lang/String;
     301: iconst_0
     302: anewarray     #31                 // class javax/lang/model/element/Element
     305: invokeinterface #32,  5           // InterfaceMethod javax/annotation/processing/Filer.createResource:(Ljavax/tools/JavaFileManager$Location;Ljava/lang/CharSequence;Ljava/lang/CharSequence;[Ljavax/lang/model/element/Element;)Ljavax/tools/FileObject;
     310: astore        5
     312: aload         5
     314: invokeinterface #33,  1           // InterfaceMethod javax/tools/FileObject.openWriter:()Ljava/io/Writer;
     319: astore        6
     321: aconst_null
     322: astore        7
     324: aload_2
     325: invokestatic  #46                 // Method io/dekorate/utils/Serialization.asYaml:(Ljava/lang/Object;)Ljava/lang/String;
     328: astore        8
     330: aload_0
     331: getfield      #3                  // Field LOGGER:Lio/dekorate/Logger;
     334: new           #21                 // class java/lang/StringBuilder
     337: dup
     338: invokespecial #22                 // Method java/lang/StringBuilder."<init>":()V
     341: ldc           #35                 // String Writing:
     343: invokevirtual #24                 // Method java/lang/StringBuilder.append:(Ljava/lang/String;)Ljava/lang/StringBuilder;
     346: aload         5
     348: invokeinterface #36,  1           // InterfaceMethod javax/tools/FileObject.toUri:()Ljava/net/URI;
     353: invokevirtual #37                 // Method java/lang/StringBuilder.append:(Ljava/lang/Object;)Ljava/lang/StringBuilder;
     356: invokevirtual #30                 // Method java/lang/StringBuilder.toString:()Ljava/lang/String;
     359: invokeinterface #38,  2           // InterfaceMethod io/dekorate/Logger.info:(Ljava/lang/String;)V
     364: aload         6
     366: aload         8
     368: invokevirtual #39                 // Method java/io/Writer.write:(Ljava/lang/String;)V
     371: aload_3
     372: aload         5
     374: invokeinterface #40,  1           // InterfaceMethod javax/tools/FileObject.getName:()Ljava/lang/String;
     379: aload         8
     381: invokeinterface #41,  3           // InterfaceMethod java/util/Map.put:(Ljava/lang/Object;Ljava/lang/Object;)Ljava/lang/Object;
     386: pop
     387: aload         6
     389: ifnull        474
     392: aload         7
     394: ifnull        417
     397: aload         6
     399: invokevirtual #42                 // Method java/io/Writer.close:()V
     402: goto          474
     405: astore        8
     407: aload         7
     409: aload         8
     411: invokevirtual #44                 // Method java/lang/Throwable.addSuppressed:(Ljava/lang/Throwable;)V
     414: goto          474
     417: aload         6
     419: invokevirtual #42                 // Method java/io/Writer.close:()V
     422: goto          474
     425: astore        8
     427: aload         8
     429: astore        7
     431: aload         8
     433: athrow
     434: astore        10
     436: aload         6
     438: ifnull        471
     441: aload         7
     443: ifnull        466
     446: aload         6
     448: invokevirtual #42                 // Method java/io/Writer.close:()V
     451: goto          471
     454: astore        11
     456: aload         7
     458: aload         11
     460: invokevirtual #44                 // Method java/lang/Throwable.addSuppressed:(Ljava/lang/Throwable;)V
     463: goto          471
     466: aload         6
     468: invokevirtual #42                 // Method java/io/Writer.close:()V
     471: aload         10
     473: athrow
     474: goto          489
     477: astore_3
     478: new           #48                 // class java/lang/RuntimeException
     481: dup
     482: ldc           #49                 // String Error writing resources
     484: aload_3
     485: invokespecial #50                 // Method java/lang/RuntimeException."<init>":(Ljava/lang/String;Ljava/lang/Throwable;)V
     488: athrow
     489: aconst_null
     490: areturn
    Exception table:
       from    to  target type
         164   169   172   Class java/lang/Throwable
          91   154   192   Class java/lang/Throwable
          91   154   201   any
         213   218   221   Class java/lang/Throwable
         192   203   201   any
         397   402   405   Class java/lang/Throwable
         324   387   425   Class java/lang/Throwable
         324   387   434   any
         446   451   454   Class java/lang/Throwable
         425   436   434   any
           0   474   477   Class java/io/IOException

  private void lambda$write$1(io.dekorate.kubernetes.config.Configuration);
    Code:
       0: aload_0
       1: aload_1
       2: invokevirtual #51                 // Method write:(Lio/dekorate/kubernetes/config/Configuration;)Ljava/util/Map$Entry;
       5: pop
       6: return

  private void lambda$write$0(java.lang.String, io.dekorate.deps.kubernetes.api.model.KubernetesList);
    Code:
       0: aload_0
       1: aload_1
       2: aload_2
       3: invokevirtual #52                 // Method write:(Ljava/lang/String;Lio/dekorate/deps/kubernetes/api/model/KubernetesList;)Ljava/util/Map;
       6: pop
       7: return

  static {};
    Code:
       0: iconst_3
       1: anewarray     #53                 // class java/lang/String
       4: dup
       5: iconst_0
       6: ldc           #54                 // String ^Editable
       8: aastore
       9: dup
      10: iconst_1
      11: ldc           #55                 // String BuildConfig$
      13: aastore
      14: dup
      15: iconst_2
      16: ldc           #56                 // String Config$
      18: aastore
      19: putstatic     #57                 // Field STRIP:[Ljava/lang/String;
      22: return
}
