Compiled from "PublicationPath.java"
public interface org.opensaml.saml.ext.saml2mdrpi.PublicationPath extends org.opensaml.saml.common.SAMLObject {
  public static final java.lang.String DEFAULT_ELEMENT_LOCAL_NAME;

  public static final javax.xml.namespace.QName DEFAULT_ELEMENT_NAME;

  public static final java.lang.String TYPE_LOCAL_NAME;

  public static final javax.xml.namespace.QName TYPE_NAME;

  public abstract java.util.List<org.opensaml.saml.ext.saml2mdrpi.Publication> getPublications();

  static {};
    Code:
       0: new           #1                  // class javax/xml/namespace/QName
       3: dup
       4: ldc           #2                  // String urn:oasis:names:tc:SAML:metadata:rpi
       6: ldc           #3                  // String PublicationPath
       8: ldc           #4                  // String mdrpi
      10: invokespecial #5                  // Method javax/xml/namespace/QName."<init>":(Ljava/lang/String;Ljava/lang/String;Ljava/lang/String;)V
      13: putstatic     #6                  // Field DEFAULT_ELEMENT_NAME:Ljavax/xml/namespace/QName;
      16: new           #1                  // class javax/xml/namespace/QName
      19: dup
      20: ldc           #2                  // String urn:oasis:names:tc:SAML:metadata:rpi
      22: ldc           #7                  // String PublicationPathType
      24: ldc           #4                  // String mdrpi
      26: invokespecial #5                  // Method javax/xml/namespace/QName."<init>":(Ljava/lang/String;Ljava/lang/String;Ljava/lang/String;)V
      29: putstatic     #8                  // Field TYPE_NAME:Ljavax/xml/namespace/QName;
      32: return
}
