Compiled from "Parameter.java"
public abstract class org.sonarsource.sonarlint.shaded.org.picocontainer.Parameter$DelegateResolver implements org.sonarsource.sonarlint.shaded.org.picocontainer.Parameter$Resolver {
  private final org.sonarsource.sonarlint.shaded.org.picocontainer.Parameter$Resolver delegate;

  public org.sonarsource.sonarlint.shaded.org.picocontainer.Parameter$DelegateResolver(org.sonarsource.sonarlint.shaded.org.picocontainer.Parameter$Resolver);
    Code:
       0: aload_0
       1: invokespecial #18                 // Method java/lang/Object."<init>":()V
       4: aload_0
       5: aload_1
       6: putfield      #20                 // Field delegate:Lorg/sonarsource/sonarlint/shaded/org/picocontainer/Parameter$Resolver;
       9: return

  public boolean isResolved();
    Code:
       0: aload_0
       1: getfield      #20                 // Field delegate:Lorg/sonarsource/sonarlint/shaded/org/picocontainer/Parameter$Resolver;
       4: invokeinterface #26,  1           // InterfaceMethod org/sonarsource/sonarlint/shaded/org/picocontainer/Parameter$Resolver.isResolved:()Z
       9: ireturn

  public java.lang.Object resolveInstance();
    Code:
       0: aload_0
       1: getfield      #20                 // Field delegate:Lorg/sonarsource/sonarlint/shaded/org/picocontainer/Parameter$Resolver;
       4: invokeinterface #30,  1           // InterfaceMethod org/sonarsource/sonarlint/shaded/org/picocontainer/Parameter$Resolver.resolveInstance:()Ljava/lang/Object;
       9: areturn

  public org.sonarsource.sonarlint.shaded.org.picocontainer.ComponentAdapter<?> getComponentAdapter();
    Code:
       0: aload_0
       1: getfield      #20                 // Field delegate:Lorg/sonarsource/sonarlint/shaded/org/picocontainer/Parameter$Resolver;
       4: invokeinterface #35,  1           // InterfaceMethod org/sonarsource/sonarlint/shaded/org/picocontainer/Parameter$Resolver.getComponentAdapter:()Lorg/sonarsource/sonarlint/shaded/org/picocontainer/ComponentAdapter;
       9: areturn
}
