Compiled from "RenameEntitiesPanel.java"
class org.protege.editor.owl.ui.rename.RenameEntitiesPanel$1 implements javax.swing.event.DocumentListener {
  final javax.swing.Timer val$timer;

  final org.protege.editor.owl.ui.rename.RenameEntitiesPanel this$0;

  org.protege.editor.owl.ui.rename.RenameEntitiesPanel$1(org.protege.editor.owl.ui.rename.RenameEntitiesPanel, javax.swing.Timer);
    Code:
       0: aload_0
       1: aload_1
       2: putfield      #1                  // Field this$0:Lorg/protege/editor/owl/ui/rename/RenameEntitiesPanel;
       5: aload_0
       6: aload_2
       7: putfield      #2                  // Field val$timer:Ljavax/swing/Timer;
      10: aload_0
      11: invokespecial #3                  // Method java/lang/Object."<init>":()V
      14: return

  public void insertUpdate(javax.swing.event.DocumentEvent);
    Code:
       0: aload_0
       1: getfield      #2                  // Field val$timer:Ljavax/swing/Timer;
       4: invokevirtual #4                  // Method javax/swing/Timer.restart:()V
       7: return

  public void removeUpdate(javax.swing.event.DocumentEvent);
    Code:
       0: aload_0
       1: getfield      #2                  // Field val$timer:Ljavax/swing/Timer;
       4: invokevirtual #4                  // Method javax/swing/Timer.restart:()V
       7: return

  public void changedUpdate(javax.swing.event.DocumentEvent);
    Code:
       0: return
}
