Compiled from "ContentType.scala"
public final class org.sisioh.trinity.domain.http.ContentType$ implements org.sisioh.scala.toolbox.Enum<org.sisioh.trinity.domain.http.ContentType> {
  public static final org.sisioh.trinity.domain.http.ContentType$ MODULE$;

  private javax.activation.MimetypesFileTypeMap extMap;

  private int org$sisioh$scala$toolbox$Enum$$counter;

  private final scala.collection.mutable.ListBuffer<org.sisioh.scala.toolbox.EnumEntry> org$sisioh$scala$toolbox$Enum$$enums;

  private volatile boolean bitmap$0;

  public static {};
    Code:
       0: new           #2                  // class org/sisioh/trinity/domain/http/ContentType$
       3: invokespecial #15                 // Method "<init>":()V
       6: return

  private javax.activation.MimetypesFileTypeMap extMap$lzycompute();
    Code:
       0: aload_0
       1: dup
       2: astore_1
       3: monitorenter
       4: aload_0
       5: getfield      #28                 // Field bitmap$0:Z
       8: ifne          38
      11: aload_0
      12: new           #30                 // class javax/activation/MimetypesFileTypeMap
      15: dup
      16: getstatic     #35                 // Field org/sisioh/trinity/domain/resource/FileReadFilter$.MODULE$:Lorg/sisioh/trinity/domain/resource/FileReadFilter$;
      19: invokevirtual #39                 // Method java/lang/Object.getClass:()Ljava/lang/Class;
      22: ldc           #41                 // String /META-INF/mime.types
      24: invokevirtual #47                 // Method java/lang/Class.getResourceAsStream:(Ljava/lang/String;)Ljava/io/InputStream;
      27: invokespecial #50                 // Method javax/activation/MimetypesFileTypeMap."<init>":(Ljava/io/InputStream;)V
      30: putfield      #52                 // Field extMap:Ljavax/activation/MimetypesFileTypeMap;
      33: aload_0
      34: iconst_1
      35: putfield      #28                 // Field bitmap$0:Z
      38: getstatic     #58                 // Field scala/runtime/BoxedUnit.UNIT:Lscala/runtime/BoxedUnit;
      41: pop
      42: aload_1
      43: monitorexit
      44: aload_0
      45: getfield      #52                 // Field extMap:Ljavax/activation/MimetypesFileTypeMap;
      48: areturn
      49: aload_1
      50: monitorexit
      51: athrow
    Exception table:
       from    to  target type
           4    44    49   any

  public int org$sisioh$scala$toolbox$Enum$$counter();
    Code:
       0: aload_0
       1: getfield      #64                 // Field org$sisioh$scala$toolbox$Enum$$counter:I
       4: ireturn

  public void org$sisioh$scala$toolbox$Enum$$counter_$eq(int);
    Code:
       0: aload_0
       1: iload_1
       2: putfield      #64                 // Field org$sisioh$scala$toolbox$Enum$$counter:I
       5: return

  public scala.collection.mutable.ListBuffer<org.sisioh.trinity.domain.http.ContentType> org$sisioh$scala$toolbox$Enum$$enums();
    Code:
       0: aload_0
       1: getfield      #70                 // Field org$sisioh$scala$toolbox$Enum$$enums:Lscala/collection/mutable/ListBuffer;
       4: areturn

  public void org$sisioh$scala$toolbox$Enum$_setter_$org$sisioh$scala$toolbox$Enum$$enums_$eq(scala.collection.mutable.ListBuffer);
    Code:
       0: aload_0
       1: aload_1
       2: putfield      #70                 // Field org$sisioh$scala$toolbox$Enum$$enums:Lscala/collection/mutable/ListBuffer;
       5: return

  public org.sisioh.scala.toolbox.DeclareEntry<org.sisioh.trinity.domain.http.ContentType> enumEntryToDeclareEntry(org.sisioh.trinity.domain.http.ContentType);
    Code:
       0: aload_0
       1: aload_1
       2: invokestatic  #79                 // Method org/sisioh/scala/toolbox/Enum$class.enumEntryToDeclareEntry:(Lorg/sisioh/scala/toolbox/Enum;Lorg/sisioh/scala/toolbox/EnumEntry;)Lorg/sisioh/scala/toolbox/DeclareEntry;
       5: areturn

  public scala.collection.mutable.ListBuffer<org.sisioh.trinity.domain.http.ContentType> appendValue(org.sisioh.trinity.domain.http.ContentType);
    Code:
       0: aload_0
       1: aload_1
       2: invokestatic  #86                 // Method org/sisioh/scala/toolbox/Enum$class.appendValue:(Lorg/sisioh/scala/toolbox/Enum;Lorg/sisioh/scala/toolbox/EnumEntry;)Lscala/collection/mutable/ListBuffer;
       5: areturn

  public org.sisioh.scala.toolbox.DeclareEntry<org.sisioh.trinity.domain.http.ContentType> declared(org.sisioh.trinity.domain.http.ContentType);
    Code:
       0: aload_0
       1: aload_1
       2: invokestatic  #90                 // Method org/sisioh/scala/toolbox/Enum$class.declared:(Lorg/sisioh/scala/toolbox/Enum;Lorg/sisioh/scala/toolbox/EnumEntry;)Lorg/sisioh/scala/toolbox/DeclareEntry;
       5: areturn

  public org.sisioh.scala.toolbox.EnumEntry apply(int);
    Code:
       0: aload_0
       1: iload_1
       2: invokestatic  #95                 // Method org/sisioh/scala/toolbox/Enum$class.apply:(Lorg/sisioh/scala/toolbox/Enum;I)Lorg/sisioh/scala/toolbox/EnumEntry;
       5: areturn

  public org.sisioh.scala.toolbox.EnumEntry apply(java.lang.String);
    Code:
       0: aload_0
       1: aload_1
       2: invokestatic  #100                // Method org/sisioh/scala/toolbox/Enum$class.apply:(Lorg/sisioh/scala/toolbox/Enum;Ljava/lang/String;)Lorg/sisioh/scala/toolbox/EnumEntry;
       5: areturn

  public scala.collection.immutable.List<org.sisioh.trinity.domain.http.ContentType> values();
    Code:
       0: aload_0
       1: invokestatic  #107                // Method org/sisioh/scala/toolbox/Enum$class.values:(Lorg/sisioh/scala/toolbox/Enum;)Lscala/collection/immutable/List;
       4: areturn

  public java.lang.String getContentType(java.lang.String);
    Code:
       0: aload_0
       1: invokespecial #111                // Method extMap:()Ljavax/activation/MimetypesFileTypeMap;
       4: aload_1
       5: invokevirtual #113                // Method javax/activation/MimetypesFileTypeMap.getContentType:(Ljava/lang/String;)Ljava/lang/String;
       8: areturn

  public java.lang.String getContentType(java.io.File);
    Code:
       0: aload_0
       1: invokespecial #111                // Method extMap:()Ljavax/activation/MimetypesFileTypeMap;
       4: aload_1
       5: invokevirtual #117                // Method javax/activation/MimetypesFileTypeMap.getContentType:(Ljava/io/File;)Ljava/lang/String;
       8: areturn

  private javax.activation.MimetypesFileTypeMap extMap();
    Code:
       0: aload_0
       1: getfield      #28                 // Field bitmap$0:Z
       4: ifeq          14
       7: aload_0
       8: getfield      #52                 // Field extMap:Ljavax/activation/MimetypesFileTypeMap;
      11: goto          18
      14: aload_0
      15: invokespecial #121                // Method extMap$lzycompute:()Ljavax/activation/MimetypesFileTypeMap;
      18: areturn

  public scala.Option<org.sisioh.trinity.domain.http.ContentType> valueOf(java.lang.String);
    Code:
       0: aload_0
       1: invokevirtual #125                // Method values:()Lscala/collection/immutable/List;
       4: new           #127                // class org/sisioh/trinity/domain/http/ContentType$$anonfun$valueOf$1
       7: dup
       8: aload_1
       9: invokespecial #130                // Method org/sisioh/trinity/domain/http/ContentType$$anonfun$valueOf$1."<init>":(Ljava/lang/String;)V
      12: invokevirtual #136                // Method scala/collection/immutable/List.find:(Lscala/Function1;)Lscala/Option;
      15: areturn

  private java.lang.Object readResolve();
    Code:
       0: getstatic     #140                // Field MODULE$:Lorg/sisioh/trinity/domain/http/ContentType$;
       3: areturn

  private org.sisioh.trinity.domain.http.ContentType$();
    Code:
       0: aload_0
       1: invokespecial #141                // Method java/lang/Object."<init>":()V
       4: aload_0
       5: putstatic     #140                // Field MODULE$:Lorg/sisioh/trinity/domain/http/ContentType$;
       8: aload_0
       9: invokestatic  #145                // Method org/sisioh/scala/toolbox/Enum$class.$init$:(Lorg/sisioh/scala/toolbox/Enum;)V
      12: aload_0
      13: getstatic     #150                // Field org/sisioh/trinity/domain/http/ContentType$TextPlan$.MODULE$:Lorg/sisioh/trinity/domain/http/ContentType$TextPlan$;
      16: invokevirtual #152                // Method enumEntryToDeclareEntry:(Lorg/sisioh/scala/toolbox/EnumEntry;)Lorg/sisioh/scala/toolbox/DeclareEntry;
      19: getstatic     #157                // Field org/sisioh/trinity/domain/http/ContentType$TextHtml$.MODULE$:Lorg/sisioh/trinity/domain/http/ContentType$TextHtml$;
      22: invokevirtual #162                // Method org/sisioh/scala/toolbox/DeclareEntry.$percent:(Lorg/sisioh/scala/toolbox/EnumEntry;)Lorg/sisioh/scala/toolbox/DeclareEntry;
      25: getstatic     #167                // Field org/sisioh/trinity/domain/http/ContentType$AppJson$.MODULE$:Lorg/sisioh/trinity/domain/http/ContentType$AppJson$;
      28: invokevirtual #162                // Method org/sisioh/scala/toolbox/DeclareEntry.$percent:(Lorg/sisioh/scala/toolbox/EnumEntry;)Lorg/sisioh/scala/toolbox/DeclareEntry;
      31: getstatic     #172                // Field org/sisioh/trinity/domain/http/ContentType$AppXml$.MODULE$:Lorg/sisioh/trinity/domain/http/ContentType$AppXml$;
      34: invokevirtual #162                // Method org/sisioh/scala/toolbox/DeclareEntry.$percent:(Lorg/sisioh/scala/toolbox/EnumEntry;)Lorg/sisioh/scala/toolbox/DeclareEntry;
      37: getstatic     #177                // Field org/sisioh/trinity/domain/http/ContentType$AppRss$.MODULE$:Lorg/sisioh/trinity/domain/http/ContentType$AppRss$;
      40: invokevirtual #162                // Method org/sisioh/scala/toolbox/DeclareEntry.$percent:(Lorg/sisioh/scala/toolbox/EnumEntry;)Lorg/sisioh/scala/toolbox/DeclareEntry;
      43: getstatic     #182                // Field org/sisioh/trinity/domain/http/ContentType$AppOctetStream$.MODULE$:Lorg/sisioh/trinity/domain/http/ContentType$AppOctetStream$;
      46: invokevirtual #162                // Method org/sisioh/scala/toolbox/DeclareEntry.$percent:(Lorg/sisioh/scala/toolbox/EnumEntry;)Lorg/sisioh/scala/toolbox/DeclareEntry;
      49: getstatic     #182                // Field org/sisioh/trinity/domain/http/ContentType$AppOctetStream$.MODULE$:Lorg/sisioh/trinity/domain/http/ContentType$AppOctetStream$;
      52: invokevirtual #162                // Method org/sisioh/scala/toolbox/DeclareEntry.$percent:(Lorg/sisioh/scala/toolbox/EnumEntry;)Lorg/sisioh/scala/toolbox/DeclareEntry;
      55: getstatic     #187                // Field org/sisioh/trinity/domain/http/ContentType$All$.MODULE$:Lorg/sisioh/trinity/domain/http/ContentType$All$;
      58: invokevirtual #162                // Method org/sisioh/scala/toolbox/DeclareEntry.$percent:(Lorg/sisioh/scala/toolbox/EnumEntry;)Lorg/sisioh/scala/toolbox/DeclareEntry;
      61: pop
      62: return
}
