Compiled from "ContentType.scala"
public class org.sisioh.trinity.domain.http.ContentType$All$ implements org.sisioh.trinity.domain.http.ContentType,scala.Product {
  public static final org.sisioh.trinity.domain.http.ContentType$All$ MODULE$;

  private final java.lang.String main;

  private final java.lang.String sub;

  private int ordinalNo;

  private final java.lang.String name;

  public static {};
    Code:
       0: new           #2                  // class org/sisioh/trinity/domain/http/ContentType$All$
       3: invokespecial #16                 // Method "<init>":()V
       6: return

  public boolean equals(java.lang.Object);
    Code:
       0: aload_0
       1: aload_1
       2: invokestatic  #29                 // Method org/sisioh/trinity/domain/http/ContentType$class.equals:(Lorg/sisioh/trinity/domain/http/ContentType;Ljava/lang/Object;)Z
       5: ireturn

  public java.lang.String toString();
    Code:
       0: aload_0
       1: invokestatic  #37                 // Method org/sisioh/trinity/domain/http/ContentType$class.toString:(Lorg/sisioh/trinity/domain/http/ContentType;)Ljava/lang/String;
       4: areturn

  public int ordinalNo();
    Code:
       0: aload_0
       1: getfield      #40                 // Field ordinalNo:I
       4: ireturn

  public void ordinalNo_$eq(int);
    Code:
       0: aload_0
       1: iload_1
       2: putfield      #40                 // Field ordinalNo:I
       5: return

  public java.lang.String name();
    Code:
       0: aload_0
       1: getfield      #45                 // Field name:Ljava/lang/String;
       4: areturn

  public void org$sisioh$scala$toolbox$EnumEntry$_setter_$name_$eq(java.lang.String);
    Code:
       0: aload_0
       1: aload_1
       2: putfield      #45                 // Field name:Ljava/lang/String;
       5: return

  public int ordinal();
    Code:
       0: aload_0
       1: invokestatic  #53                 // Method org/sisioh/scala/toolbox/EnumEntry$class.ordinal:(Lorg/sisioh/scala/toolbox/EnumEntry;)I
       4: ireturn

  public int compare(org.sisioh.scala.toolbox.EnumEntry);
    Code:
       0: aload_0
       1: aload_1
       2: invokestatic  #57                 // Method org/sisioh/scala/toolbox/EnumEntry$class.compare:(Lorg/sisioh/scala/toolbox/EnumEntry;Lorg/sisioh/scala/toolbox/EnumEntry;)I
       5: ireturn

  public boolean $less(java.lang.Object);
    Code:
       0: aload_0
       1: aload_1
       2: invokestatic  #65                 // Method scala/math/Ordered$class.$less:(Lscala/math/Ordered;Ljava/lang/Object;)Z
       5: ireturn

  public boolean $greater(java.lang.Object);
    Code:
       0: aload_0
       1: aload_1
       2: invokestatic  #68                 // Method scala/math/Ordered$class.$greater:(Lscala/math/Ordered;Ljava/lang/Object;)Z
       5: ireturn

  public boolean $less$eq(java.lang.Object);
    Code:
       0: aload_0
       1: aload_1
       2: invokestatic  #71                 // Method scala/math/Ordered$class.$less$eq:(Lscala/math/Ordered;Ljava/lang/Object;)Z
       5: ireturn

  public boolean $greater$eq(java.lang.Object);
    Code:
       0: aload_0
       1: aload_1
       2: invokestatic  #74                 // Method scala/math/Ordered$class.$greater$eq:(Lscala/math/Ordered;Ljava/lang/Object;)Z
       5: ireturn

  public int compareTo(java.lang.Object);
    Code:
       0: aload_0
       1: aload_1
       2: invokestatic  #79                 // Method scala/math/Ordered$class.compareTo:(Lscala/math/Ordered;Ljava/lang/Object;)I
       5: ireturn

  public java.lang.String main();
    Code:
       0: aload_0
       1: getfield      #81                 // Field main:Ljava/lang/String;
       4: areturn

  public java.lang.String sub();
    Code:
       0: aload_0
       1: getfield      #83                 // Field sub:Ljava/lang/String;
       4: areturn

  public java.lang.String productPrefix();
    Code:
       0: ldc           #86                 // String All
       2: areturn

  public int productArity();
    Code:
       0: iconst_0
       1: ireturn

  public java.lang.Object productElement(int);
    Code:
       0: iload_1
       1: istore_2
       2: new           #91                 // class java/lang/IndexOutOfBoundsException
       5: dup
       6: iload_1
       7: invokestatic  #97                 // Method scala/runtime/BoxesRunTime.boxToInteger:(I)Ljava/lang/Integer;
      10: invokevirtual #99                 // Method java/lang/Object.toString:()Ljava/lang/String;
      13: invokespecial #101                // Method java/lang/IndexOutOfBoundsException."<init>":(Ljava/lang/String;)V
      16: athrow

  public scala.collection.Iterator<java.lang.Object> productIterator();
    Code:
       0: getstatic     #108                // Field scala/runtime/ScalaRunTime$.MODULE$:Lscala/runtime/ScalaRunTime$;
       3: aload_0
       4: invokevirtual #112                // Method scala/runtime/ScalaRunTime$.typedProductIterator:(Lscala/Product;)Lscala/collection/Iterator;
       7: areturn

  public boolean canEqual(java.lang.Object);
    Code:
       0: aload_1
       1: instanceof    #2                  // class org/sisioh/trinity/domain/http/ContentType$All$
       4: ireturn

  public int hashCode();
    Code:
       0: ldc           #115                // int 65921
       2: ireturn

  private java.lang.Object readResolve();
    Code:
       0: getstatic     #119                // Field MODULE$:Lorg/sisioh/trinity/domain/http/ContentType$All$;
       3: areturn

  public int compare(java.lang.Object);
    Code:
       0: aload_0
       1: aload_1
       2: checkcast     #121                // class org/sisioh/scala/toolbox/EnumEntry
       5: invokevirtual #123                // Method compare:(Lorg/sisioh/scala/toolbox/EnumEntry;)I
       8: ireturn

  public org.sisioh.trinity.domain.http.ContentType$All$();
    Code:
       0: aload_0
       1: invokespecial #124                // Method java/lang/Object."<init>":()V
       4: aload_0
       5: putstatic     #119                // Field MODULE$:Lorg/sisioh/trinity/domain/http/ContentType$All$;
       8: aload_0
       9: invokestatic  #128                // Method scala/math/Ordered$class.$init$:(Lscala/math/Ordered;)V
      12: aload_0
      13: invokestatic  #131                // Method org/sisioh/scala/toolbox/EnumEntry$class.$init$:(Lorg/sisioh/scala/toolbox/EnumEntry;)V
      16: aload_0
      17: invokestatic  #134                // Method org/sisioh/trinity/domain/http/ContentType$class.$init$:(Lorg/sisioh/trinity/domain/http/ContentType;)V
      20: aload_0
      21: invokestatic  #139                // Method scala/Product$class.$init$:(Lscala/Product;)V
      24: aload_0
      25: ldc           #141                // String *
      27: putfield      #81                 // Field main:Ljava/lang/String;
      30: aload_0
      31: ldc           #141                // String *
      33: putfield      #83                 // Field sub:Ljava/lang/String;
      36: return
}
