Compiled from "StatusLine.kt"
public final class okhttp3.internal.http.StatusLine {
  public final okhttp3.Protocol protocol;

  public final int code;

  public final java.lang.String message;

  public static final int HTTP_TEMP_REDIRECT;

  public static final int HTTP_PERM_REDIRECT;

  public static final int HTTP_MISDIRECTED_REQUEST;

  public static final int HTTP_CONTINUE;

  public static final okhttp3.internal.http.StatusLine$Companion Companion;

  public java.lang.String toString();
    Code:
       0: iconst_0
       1: istore_1
       2: iconst_0
       3: istore_2
       4: new           #9                  // class java/lang/StringBuilder
       7: dup
       8: invokespecial #13                 // Method java/lang/StringBuilder."<init>":()V
      11: astore_2
      12: iconst_0
      13: istore_3
      14: iconst_0
      15: istore        4
      17: aload_2
      18: astore        5
      20: iconst_0
      21: istore        6
      23: aload_0
      24: getfield      #17                 // Field protocol:Lokhttp3/Protocol;
      27: getstatic     #22                 // Field okhttp3/Protocol.HTTP_1_0:Lokhttp3/Protocol;
      30: if_acmpne     44
      33: aload         5
      35: ldc           #24                 // String HTTP/1.0
      37: invokevirtual #28                 // Method java/lang/StringBuilder.append:(Ljava/lang/String;)Ljava/lang/StringBuilder;
      40: pop
      41: goto          52
      44: aload         5
      46: ldc           #30                 // String HTTP/1.1
      48: invokevirtual #28                 // Method java/lang/StringBuilder.append:(Ljava/lang/String;)Ljava/lang/StringBuilder;
      51: pop
      52: aload         5
      54: bipush        32
      56: invokevirtual #33                 // Method java/lang/StringBuilder.append:(C)Ljava/lang/StringBuilder;
      59: aload_0
      60: getfield      #37                 // Field code:I
      63: invokevirtual #40                 // Method java/lang/StringBuilder.append:(I)Ljava/lang/StringBuilder;
      66: pop
      67: aload         5
      69: bipush        32
      71: invokevirtual #33                 // Method java/lang/StringBuilder.append:(C)Ljava/lang/StringBuilder;
      74: aload_0
      75: getfield      #44                 // Field message:Ljava/lang/String;
      78: invokevirtual #28                 // Method java/lang/StringBuilder.append:(Ljava/lang/String;)Ljava/lang/StringBuilder;
      81: pop
      82: nop
      83: aload_2
      84: invokevirtual #46                 // Method java/lang/StringBuilder.toString:()Ljava/lang/String;
      87: dup
      88: ldc           #48                 // String StringBuilder().apply(builderAction).toString()
      90: invokestatic  #54                 // Method kotlin/jvm/internal/Intrinsics.checkNotNullExpressionValue:(Ljava/lang/Object;Ljava/lang/String;)V
      93: areturn

  public okhttp3.internal.http.StatusLine(okhttp3.Protocol, int, java.lang.String);
    Code:
       0: aload_1
       1: ldc           #62                 // String protocol
       3: invokestatic  #65                 // Method kotlin/jvm/internal/Intrinsics.checkNotNullParameter:(Ljava/lang/Object;Ljava/lang/String;)V
       6: aload_3
       7: ldc           #66                 // String message
       9: invokestatic  #65                 // Method kotlin/jvm/internal/Intrinsics.checkNotNullParameter:(Ljava/lang/Object;Ljava/lang/String;)V
      12: aload_0
      13: invokespecial #67                 // Method java/lang/Object."<init>":()V
      16: aload_0
      17: aload_1
      18: putfield      #17                 // Field protocol:Lokhttp3/Protocol;
      21: aload_0
      22: iload_2
      23: putfield      #37                 // Field code:I
      26: aload_0
      27: aload_3
      28: putfield      #44                 // Field message:Ljava/lang/String;
      31: return

  static {};
    Code:
       0: new           #93                 // class okhttp3/internal/http/StatusLine$Companion
       3: dup
       4: aconst_null
       5: invokespecial #96                 // Method okhttp3/internal/http/StatusLine$Companion."<init>":(Lkotlin/jvm/internal/DefaultConstructorMarker;)V
       8: putstatic     #98                 // Field Companion:Lokhttp3/internal/http/StatusLine$Companion;
      11: return
}
