Compiled from "EventType.java"
public class fi.foyt.fni.rest.illusion.model.EventType {
  private java.lang.Long id;

  private java.lang.String name;

  public fi.foyt.fni.rest.illusion.model.EventType();
    Code:
       0: aload_0
       1: invokespecial #1                  // Method java/lang/Object."<init>":()V
       4: return

  public fi.foyt.fni.rest.illusion.model.EventType(java.lang.Long, java.lang.String);
    Code:
       0: aload_0
       1: invokespecial #1                  // Method java/lang/Object."<init>":()V
       4: aload_0
       5: aload_1
       6: putfield      #2                  // Field id:Ljava/lang/Long;
       9: aload_0
      10: aload_2
      11: putfield      #3                  // Field name:Ljava/lang/String;
      14: return

  public java.lang.Long getId();
    Code:
       0: aload_0
       1: getfield      #2                  // Field id:Ljava/lang/Long;
       4: areturn

  public void setId(java.lang.Long);
    Code:
       0: aload_0
       1: aload_1
       2: putfield      #2                  // Field id:Ljava/lang/Long;
       5: return

  public java.lang.String getName();
    Code:
       0: aload_0
       1: getfield      #3                  // Field name:Ljava/lang/String;
       4: areturn

  public void setName(java.lang.String);
    Code:
       0: aload_0
       1: aload_1
       2: putfield      #3                  // Field name:Ljava/lang/String;
       5: return
}
