public class org.bouncycastle.cms.jcajce.ZlibCompressor implements org.bouncycastle.operator.OutputCompressor {
  private static final java.lang.String ZLIB;

  public org.bouncycastle.cms.jcajce.ZlibCompressor();
    Code:
       0: aload_0
       1: invokespecial #30                 // Method java/lang/Object."<init>":()V
       4: return

  public org.bouncycastle.asn1.x509.AlgorithmIdentifier getAlgorithmIdentifier();
    Code:
       0: new           #17                 // class org/bouncycastle/asn1/x509/AlgorithmIdentifier
       3: dup
       4: new           #16                 // class org/bouncycastle/asn1/ASN1ObjectIdentifier
       7: dup
       8: ldc           #1                  // String 1.2.840.113549.1.9.16.3.8
      10: invokespecial #32                 // Method org/bouncycastle/asn1/ASN1ObjectIdentifier."<init>":(Ljava/lang/String;)V
      13: invokespecial #33                 // Method org/bouncycastle/asn1/x509/AlgorithmIdentifier."<init>":(Lorg/bouncycastle/asn1/ASN1ObjectIdentifier;)V
      16: areturn

  public java.io.OutputStream getOutputStream(java.io.OutputStream);
    Code:
       0: new           #15                 // class java/util/zip/DeflaterOutputStream
       3: dup
       4: aload_1
       5: invokespecial #31                 // Method java/util/zip/DeflaterOutputStream."<init>":(Ljava/io/OutputStream;)V
       8: areturn
}
