public class org.bouncycastle.jcajce.provider.keystore.util.AdaptingKeyStoreSpi extends java.security.KeyStoreSpi {
  public static final java.lang.String COMPAT_OVERRIDE;

  private final org.bouncycastle.jcajce.provider.keystore.util.JKSKeyStoreSpi jksStore;

  private final java.security.KeyStoreSpi primaryStore;

  private java.security.KeyStoreSpi keyStoreSpi;

  public org.bouncycastle.jcajce.provider.keystore.util.AdaptingKeyStoreSpi(org.bouncycastle.jcajce.util.JcaJceHelper, java.security.KeyStoreSpi);
    Code:
       0: aload_0
       1: invokespecial #120                // Method java/security/KeyStoreSpi."<init>":()V
       4: aload_0
       5: new           #59                 // class org/bouncycastle/jcajce/provider/keystore/util/JKSKeyStoreSpi
       8: dup
       9: aload_1
      10: invokespecial #140                // Method org/bouncycastle/jcajce/provider/keystore/util/JKSKeyStoreSpi."<init>":(Lorg/bouncycastle/jcajce/util/JcaJceHelper;)V
      13: putfield      #114                // Field jksStore:Lorg/bouncycastle/jcajce/provider/keystore/util/JKSKeyStoreSpi;
      16: aload_0
      17: aload_2
      18: putfield      #113                // Field primaryStore:Ljava/security/KeyStoreSpi;
      21: aload_0
      22: aload_2
      23: putfield      #112                // Field keyStoreSpi:Ljava/security/KeyStoreSpi;
      26: return

  public boolean engineProbe(java.io.InputStream) throws java.io.IOException;
    Code:
       0: aload_0
       1: getfield      #112                // Field keyStoreSpi:Ljava/security/KeyStoreSpi;
       4: instanceof    #57                 // class org/bouncycastle/jcajce/provider/keystore/pkcs12/PKCS12KeyStoreSpi
       7: ifeq          22
      10: aload_0
      11: getfield      #112                // Field keyStoreSpi:Ljava/security/KeyStoreSpi;
      14: checkcast     #57                 // class org/bouncycastle/jcajce/provider/keystore/pkcs12/PKCS12KeyStoreSpi
      17: aload_1
      18: invokevirtual #138                // Method org/bouncycastle/jcajce/provider/keystore/pkcs12/PKCS12KeyStoreSpi.engineProbe:(Ljava/io/InputStream;)Z
      21: ireturn
      22: iconst_0
      23: ireturn

  public java.security.Key engineGetKey(java.lang.String, char[]) throws java.security.NoSuchAlgorithmException, java.security.UnrecoverableKeyException;
    Code:
       0: aload_0
       1: getfield      #112                // Field keyStoreSpi:Ljava/security/KeyStoreSpi;
       4: aload_1
       5: aload_2
       6: invokevirtual #131                // Method java/security/KeyStoreSpi.engineGetKey:(Ljava/lang/String;[C)Ljava/security/Key;
       9: areturn

  public java.security.cert.Certificate[] engineGetCertificateChain(java.lang.String);
    Code:
       0: aload_0
       1: getfield      #112                // Field keyStoreSpi:Ljava/security/KeyStoreSpi;
       4: aload_1
       5: invokevirtual #133                // Method java/security/KeyStoreSpi.engineGetCertificateChain:(Ljava/lang/String;)[Ljava/security/cert/Certificate;
       8: areturn

  public java.security.cert.Certificate engineGetCertificate(java.lang.String);
    Code:
       0: aload_0
       1: getfield      #112                // Field keyStoreSpi:Ljava/security/KeyStoreSpi;
       4: aload_1
       5: invokevirtual #132                // Method java/security/KeyStoreSpi.engineGetCertificate:(Ljava/lang/String;)Ljava/security/cert/Certificate;
       8: areturn

  public java.util.Date engineGetCreationDate(java.lang.String);
    Code:
       0: aload_0
       1: getfield      #112                // Field keyStoreSpi:Ljava/security/KeyStoreSpi;
       4: aload_1
       5: invokevirtual #136                // Method java/security/KeyStoreSpi.engineGetCreationDate:(Ljava/lang/String;)Ljava/util/Date;
       8: areturn

  public void engineSetKeyEntry(java.lang.String, java.security.Key, char[], java.security.cert.Certificate[]) throws java.security.KeyStoreException;
    Code:
       0: aload_0
       1: getfield      #112                // Field keyStoreSpi:Ljava/security/KeyStoreSpi;
       4: aload_1
       5: aload_2
       6: aload_3
       7: aload         4
       9: invokevirtual #137                // Method java/security/KeyStoreSpi.engineSetKeyEntry:(Ljava/lang/String;Ljava/security/Key;[C[Ljava/security/cert/Certificate;)V
      12: return

  public void engineSetKeyEntry(java.lang.String, byte[], java.security.cert.Certificate[]) throws java.security.KeyStoreException;
    Code:
       0: aload_0
       1: getfield      #112                // Field keyStoreSpi:Ljava/security/KeyStoreSpi;
       4: aload_1
       5: aload_2
       6: aload_3
       7: invokevirtual #135                // Method java/security/KeyStoreSpi.engineSetKeyEntry:(Ljava/lang/String;[B[Ljava/security/cert/Certificate;)V
      10: return

  public void engineSetCertificateEntry(java.lang.String, java.security.cert.Certificate) throws java.security.KeyStoreException;
    Code:
       0: aload_0
       1: getfield      #112                // Field keyStoreSpi:Ljava/security/KeyStoreSpi;
       4: aload_1
       5: aload_2
       6: invokevirtual #134                // Method java/security/KeyStoreSpi.engineSetCertificateEntry:(Ljava/lang/String;Ljava/security/cert/Certificate;)V
       9: return

  public void engineDeleteEntry(java.lang.String) throws java.security.KeyStoreException;
    Code:
       0: aload_0
       1: getfield      #112                // Field keyStoreSpi:Ljava/security/KeyStoreSpi;
       4: aload_1
       5: invokevirtual #123                // Method java/security/KeyStoreSpi.engineDeleteEntry:(Ljava/lang/String;)V
       8: return

  public java.util.Enumeration<java.lang.String> engineAliases();
    Code:
       0: aload_0
       1: getfield      #112                // Field keyStoreSpi:Ljava/security/KeyStoreSpi;
       4: invokevirtual #129                // Method java/security/KeyStoreSpi.engineAliases:()Ljava/util/Enumeration;
       7: areturn

  public boolean engineContainsAlias(java.lang.String);
    Code:
       0: aload_0
       1: getfield      #112                // Field keyStoreSpi:Ljava/security/KeyStoreSpi;
       4: aload_1
       5: invokevirtual #124                // Method java/security/KeyStoreSpi.engineContainsAlias:(Ljava/lang/String;)Z
       8: ireturn

  public int engineSize();
    Code:
       0: aload_0
       1: getfield      #112                // Field keyStoreSpi:Ljava/security/KeyStoreSpi;
       4: invokevirtual #119                // Method java/security/KeyStoreSpi.engineSize:()I
       7: ireturn

  public boolean engineIsKeyEntry(java.lang.String);
    Code:
       0: aload_0
       1: getfield      #112                // Field keyStoreSpi:Ljava/security/KeyStoreSpi;
       4: aload_1
       5: invokevirtual #126                // Method java/security/KeyStoreSpi.engineIsKeyEntry:(Ljava/lang/String;)Z
       8: ireturn

  public boolean engineIsCertificateEntry(java.lang.String);
    Code:
       0: aload_0
       1: getfield      #112                // Field keyStoreSpi:Ljava/security/KeyStoreSpi;
       4: aload_1
       5: invokevirtual #125                // Method java/security/KeyStoreSpi.engineIsCertificateEntry:(Ljava/lang/String;)Z
       8: ireturn

  public java.lang.String engineGetCertificateAlias(java.security.cert.Certificate);
    Code:
       0: aload_0
       1: getfield      #112                // Field keyStoreSpi:Ljava/security/KeyStoreSpi;
       4: aload_1
       5: invokevirtual #130                // Method java/security/KeyStoreSpi.engineGetCertificateAlias:(Ljava/security/cert/Certificate;)Ljava/lang/String;
       8: areturn

  public void engineStore(java.io.OutputStream, char[]) throws java.io.IOException, java.security.NoSuchAlgorithmException, java.security.cert.CertificateException;
    Code:
       0: aload_0
       1: getfield      #112                // Field keyStoreSpi:Ljava/security/KeyStoreSpi;
       4: aload_1
       5: aload_2
       6: invokevirtual #122                // Method java/security/KeyStoreSpi.engineStore:(Ljava/io/OutputStream;[C)V
       9: return

  public void engineStore(java.security.KeyStore$LoadStoreParameter) throws java.io.IOException, java.security.NoSuchAlgorithmException, java.security.cert.CertificateException;
    Code:
       0: aload_0
       1: getfield      #112                // Field keyStoreSpi:Ljava/security/KeyStoreSpi;
       4: aload_1
       5: invokevirtual #128                // Method java/security/KeyStoreSpi.engineStore:(Ljava/security/KeyStore$LoadStoreParameter;)V
       8: return

  public void engineLoad(java.io.InputStream, char[]) throws java.io.IOException, java.security.NoSuchAlgorithmException, java.security.cert.CertificateException;
    Code:
       0: aload_1
       1: ifnonnull     24
       4: aload_0
       5: aload_0
       6: getfield      #113                // Field primaryStore:Ljava/security/KeyStoreSpi;
       9: putfield      #112                // Field keyStoreSpi:Ljava/security/KeyStoreSpi;
      12: aload_0
      13: getfield      #112                // Field keyStoreSpi:Ljava/security/KeyStoreSpi;
      16: aconst_null
      17: aload_2
      18: invokevirtual #121                // Method java/security/KeyStoreSpi.engineLoad:(Ljava/io/InputStream;[C)V
      21: goto          118
      24: ldc           #1                  // String keystore.type.compat
      26: invokestatic  #141                // Method org/bouncycastle/util/Properties.isOverrideSet:(Ljava/lang/String;)Z
      29: ifne          42
      32: aload_0
      33: getfield      #113                // Field primaryStore:Ljava/security/KeyStoreSpi;
      36: instanceof    #57                 // class org/bouncycastle/jcajce/provider/keystore/pkcs12/PKCS12KeyStoreSpi
      39: ifne          101
      42: aload_1
      43: invokevirtual #117                // Method java/io/InputStream.markSupported:()Z
      46: ifne          58
      49: new           #47                 // class java/io/BufferedInputStream
      52: dup
      53: aload_1
      54: invokespecial #115                // Method java/io/BufferedInputStream."<init>":(Ljava/io/InputStream;)V
      57: astore_1
      58: aload_1
      59: bipush        8
      61: invokevirtual #118                // Method java/io/InputStream.mark:(I)V
      64: aload_0
      65: getfield      #114                // Field jksStore:Lorg/bouncycastle/jcajce/provider/keystore/util/JKSKeyStoreSpi;
      68: aload_1
      69: invokevirtual #139                // Method org/bouncycastle/jcajce/provider/keystore/util/JKSKeyStoreSpi.engineProbe:(Ljava/io/InputStream;)Z
      72: ifeq          86
      75: aload_0
      76: aload_0
      77: getfield      #114                // Field jksStore:Lorg/bouncycastle/jcajce/provider/keystore/util/JKSKeyStoreSpi;
      80: putfield      #112                // Field keyStoreSpi:Ljava/security/KeyStoreSpi;
      83: goto          94
      86: aload_0
      87: aload_0
      88: getfield      #113                // Field primaryStore:Ljava/security/KeyStoreSpi;
      91: putfield      #112                // Field keyStoreSpi:Ljava/security/KeyStoreSpi;
      94: aload_1
      95: invokevirtual #116                // Method java/io/InputStream.reset:()V
      98: goto          109
     101: aload_0
     102: aload_0
     103: getfield      #113                // Field primaryStore:Ljava/security/KeyStoreSpi;
     106: putfield      #112                // Field keyStoreSpi:Ljava/security/KeyStoreSpi;
     109: aload_0
     110: getfield      #112                // Field keyStoreSpi:Ljava/security/KeyStoreSpi;
     113: aload_1
     114: aload_2
     115: invokevirtual #121                // Method java/security/KeyStoreSpi.engineLoad:(Ljava/io/InputStream;[C)V
     118: return

  public void engineLoad(java.security.KeyStore$LoadStoreParameter) throws java.io.IOException, java.security.NoSuchAlgorithmException, java.security.cert.CertificateException;
    Code:
       0: aload_0
       1: getfield      #112                // Field keyStoreSpi:Ljava/security/KeyStoreSpi;
       4: aload_1
       5: invokevirtual #127                // Method java/security/KeyStoreSpi.engineLoad:(Ljava/security/KeyStore$LoadStoreParameter;)V
       8: return
}
