Compiled from "NarayanaConfigurationBean.java"
public class org.springframework.boot.jta.narayana.NarayanaConfigurationBean implements org.springframework.beans.factory.InitializingBean {
  private static final java.lang.String JBOSSTS_PROPERTIES_FILE_NAME;

  private final org.springframework.boot.jta.narayana.NarayanaProperties properties;

  public org.springframework.boot.jta.narayana.NarayanaConfigurationBean(org.springframework.boot.jta.narayana.NarayanaProperties);
    Code:
       0: aload_0
       1: invokespecial #1                  // Method java/lang/Object."<init>":()V
       4: aload_0
       5: aload_1
       6: putfield      #2                  // Field properties:Lorg/springframework/boot/jta/narayana/NarayanaProperties;
       9: return

  public void afterPropertiesSet() throws java.lang.Exception;
    Code:
       0: aload_0
       1: invokespecial #3                  // Method isPropertiesFileAvailable:()Z
       4: ifeq          8
       7: return
       8: aload_0
       9: aload_0
      10: getfield      #2                  // Field properties:Lorg/springframework/boot/jta/narayana/NarayanaProperties;
      13: invokevirtual #4                  // Method org/springframework/boot/jta/narayana/NarayanaProperties.getTransactionManagerId:()Ljava/lang/String;
      16: invokespecial #5                  // Method setNodeIdentifier:(Ljava/lang/String;)V
      19: aload_0
      20: aload_0
      21: getfield      #2                  // Field properties:Lorg/springframework/boot/jta/narayana/NarayanaProperties;
      24: invokevirtual #6                  // Method org/springframework/boot/jta/narayana/NarayanaProperties.getLogDir:()Ljava/lang/String;
      27: invokespecial #7                  // Method setObjectStoreDir:(Ljava/lang/String;)V
      30: aload_0
      31: aload_0
      32: getfield      #2                  // Field properties:Lorg/springframework/boot/jta/narayana/NarayanaProperties;
      35: invokevirtual #8                  // Method org/springframework/boot/jta/narayana/NarayanaProperties.isOnePhaseCommit:()Z
      38: invokespecial #9                  // Method setCommitOnePhase:(Z)V
      41: aload_0
      42: getfield      #2                  // Field properties:Lorg/springframework/boot/jta/narayana/NarayanaProperties;
      45: invokevirtual #10                 // Method org/springframework/boot/jta/narayana/NarayanaProperties.getDefaultTimeout:()Ljava/time/Duration;
      48: ifnull        66
      51: aload_0
      52: aload_0
      53: getfield      #2                  // Field properties:Lorg/springframework/boot/jta/narayana/NarayanaProperties;
      56: invokevirtual #10                 // Method org/springframework/boot/jta/narayana/NarayanaProperties.getDefaultTimeout:()Ljava/time/Duration;
      59: invokevirtual #11                 // Method java/time/Duration.getSeconds:()J
      62: l2i
      63: invokespecial #12                 // Method setDefaultTimeout:(I)V
      66: aload_0
      67: getfield      #2                  // Field properties:Lorg/springframework/boot/jta/narayana/NarayanaProperties;
      70: invokevirtual #13                 // Method org/springframework/boot/jta/narayana/NarayanaProperties.getPeriodicRecoveryPeriod:()Ljava/time/Duration;
      73: ifnull        91
      76: aload_0
      77: aload_0
      78: getfield      #2                  // Field properties:Lorg/springframework/boot/jta/narayana/NarayanaProperties;
      81: invokevirtual #13                 // Method org/springframework/boot/jta/narayana/NarayanaProperties.getPeriodicRecoveryPeriod:()Ljava/time/Duration;
      84: invokevirtual #11                 // Method java/time/Duration.getSeconds:()J
      87: l2i
      88: invokespecial #14                 // Method setPeriodicRecoveryPeriod:(I)V
      91: aload_0
      92: getfield      #2                  // Field properties:Lorg/springframework/boot/jta/narayana/NarayanaProperties;
      95: invokevirtual #15                 // Method org/springframework/boot/jta/narayana/NarayanaProperties.getRecoveryBackoffPeriod:()Ljava/time/Duration;
      98: ifnull        116
     101: aload_0
     102: aload_0
     103: getfield      #2                  // Field properties:Lorg/springframework/boot/jta/narayana/NarayanaProperties;
     106: invokevirtual #15                 // Method org/springframework/boot/jta/narayana/NarayanaProperties.getRecoveryBackoffPeriod:()Ljava/time/Duration;
     109: invokevirtual #11                 // Method java/time/Duration.getSeconds:()J
     112: l2i
     113: invokespecial #16                 // Method setRecoveryBackoffPeriod:(I)V
     116: aload_0
     117: aload_0
     118: getfield      #2                  // Field properties:Lorg/springframework/boot/jta/narayana/NarayanaProperties;
     121: invokevirtual #17                 // Method org/springframework/boot/jta/narayana/NarayanaProperties.getXaResourceOrphanFilters:()Ljava/util/List;
     124: invokespecial #18                 // Method setXaResourceOrphanFilters:(Ljava/util/List;)V
     127: aload_0
     128: aload_0
     129: getfield      #2                  // Field properties:Lorg/springframework/boot/jta/narayana/NarayanaProperties;
     132: invokevirtual #19                 // Method org/springframework/boot/jta/narayana/NarayanaProperties.getRecoveryModules:()Ljava/util/List;
     135: invokespecial #20                 // Method setRecoveryModules:(Ljava/util/List;)V
     138: aload_0
     139: aload_0
     140: getfield      #2                  // Field properties:Lorg/springframework/boot/jta/narayana/NarayanaProperties;
     143: invokevirtual #21                 // Method org/springframework/boot/jta/narayana/NarayanaProperties.getExpiryScanners:()Ljava/util/List;
     146: invokespecial #22                 // Method setExpiryScanners:(Ljava/util/List;)V
     149: return

  private boolean isPropertiesFileAvailable();
    Code:
       0: invokestatic  #23                 // Method java/lang/Thread.currentThread:()Ljava/lang/Thread;
       3: invokevirtual #24                 // Method java/lang/Thread.getContextClassLoader:()Ljava/lang/ClassLoader;
       6: ldc           #26                 // String jbossts-properties.xml
       8: invokevirtual #27                 // Method java/lang/ClassLoader.getResource:(Ljava/lang/String;)Ljava/net/URL;
      11: ifnull        18
      14: iconst_1
      15: goto          19
      18: iconst_0
      19: ireturn

  private void setNodeIdentifier(java.lang.String) throws com.arjuna.ats.arjuna.common.CoreEnvironmentBeanException;
    Code:
       0: aload_0
       1: ldc           #28                 // class com/arjuna/ats/arjuna/common/CoreEnvironmentBean
       3: invokespecial #29                 // Method getPopulator:(Ljava/lang/Class;)Ljava/lang/Object;
       6: checkcast     #28                 // class com/arjuna/ats/arjuna/common/CoreEnvironmentBean
       9: aload_1
      10: invokevirtual #30                 // Method com/arjuna/ats/arjuna/common/CoreEnvironmentBean.setNodeIdentifier:(Ljava/lang/String;)V
      13: return

  private void setObjectStoreDir(java.lang.String);
    Code:
       0: aload_1
       1: ifnull        47
       4: aload_0
       5: ldc           #31                 // class com/arjuna/ats/arjuna/common/ObjectStoreEnvironmentBean
       7: invokespecial #29                 // Method getPopulator:(Ljava/lang/Class;)Ljava/lang/Object;
      10: checkcast     #31                 // class com/arjuna/ats/arjuna/common/ObjectStoreEnvironmentBean
      13: aload_1
      14: invokevirtual #32                 // Method com/arjuna/ats/arjuna/common/ObjectStoreEnvironmentBean.setObjectStoreDir:(Ljava/lang/String;)V
      17: aload_0
      18: ldc           #31                 // class com/arjuna/ats/arjuna/common/ObjectStoreEnvironmentBean
      20: ldc           #33                 // String communicationStore
      22: invokespecial #34                 // Method getPopulator:(Ljava/lang/Class;Ljava/lang/String;)Ljava/lang/Object;
      25: checkcast     #31                 // class com/arjuna/ats/arjuna/common/ObjectStoreEnvironmentBean
      28: aload_1
      29: invokevirtual #32                 // Method com/arjuna/ats/arjuna/common/ObjectStoreEnvironmentBean.setObjectStoreDir:(Ljava/lang/String;)V
      32: aload_0
      33: ldc           #31                 // class com/arjuna/ats/arjuna/common/ObjectStoreEnvironmentBean
      35: ldc           #35                 // String stateStore
      37: invokespecial #34                 // Method getPopulator:(Ljava/lang/Class;Ljava/lang/String;)Ljava/lang/Object;
      40: checkcast     #31                 // class com/arjuna/ats/arjuna/common/ObjectStoreEnvironmentBean
      43: aload_1
      44: invokevirtual #32                 // Method com/arjuna/ats/arjuna/common/ObjectStoreEnvironmentBean.setObjectStoreDir:(Ljava/lang/String;)V
      47: return

  private void setCommitOnePhase(boolean);
    Code:
       0: aload_0
       1: ldc           #36                 // class com/arjuna/ats/arjuna/common/CoordinatorEnvironmentBean
       3: invokespecial #29                 // Method getPopulator:(Ljava/lang/Class;)Ljava/lang/Object;
       6: checkcast     #36                 // class com/arjuna/ats/arjuna/common/CoordinatorEnvironmentBean
       9: iload_1
      10: invokevirtual #37                 // Method com/arjuna/ats/arjuna/common/CoordinatorEnvironmentBean.setCommitOnePhase:(Z)V
      13: return

  private void setDefaultTimeout(int);
    Code:
       0: aload_0
       1: ldc           #36                 // class com/arjuna/ats/arjuna/common/CoordinatorEnvironmentBean
       3: invokespecial #29                 // Method getPopulator:(Ljava/lang/Class;)Ljava/lang/Object;
       6: checkcast     #36                 // class com/arjuna/ats/arjuna/common/CoordinatorEnvironmentBean
       9: iload_1
      10: invokevirtual #38                 // Method com/arjuna/ats/arjuna/common/CoordinatorEnvironmentBean.setDefaultTimeout:(I)V
      13: return

  private void setPeriodicRecoveryPeriod(int);
    Code:
       0: aload_0
       1: ldc           #39                 // class com/arjuna/ats/arjuna/common/RecoveryEnvironmentBean
       3: invokespecial #29                 // Method getPopulator:(Ljava/lang/Class;)Ljava/lang/Object;
       6: checkcast     #39                 // class com/arjuna/ats/arjuna/common/RecoveryEnvironmentBean
       9: iload_1
      10: invokevirtual #40                 // Method com/arjuna/ats/arjuna/common/RecoveryEnvironmentBean.setPeriodicRecoveryPeriod:(I)V
      13: return

  private void setRecoveryBackoffPeriod(int);
    Code:
       0: aload_0
       1: ldc           #39                 // class com/arjuna/ats/arjuna/common/RecoveryEnvironmentBean
       3: invokespecial #29                 // Method getPopulator:(Ljava/lang/Class;)Ljava/lang/Object;
       6: checkcast     #39                 // class com/arjuna/ats/arjuna/common/RecoveryEnvironmentBean
       9: iload_1
      10: invokevirtual #41                 // Method com/arjuna/ats/arjuna/common/RecoveryEnvironmentBean.setRecoveryBackoffPeriod:(I)V
      13: return

  private void setXaResourceOrphanFilters(java.util.List<java.lang.String>);
    Code:
       0: aload_0
       1: ldc           #42                 // class com/arjuna/ats/jta/common/JTAEnvironmentBean
       3: invokespecial #29                 // Method getPopulator:(Ljava/lang/Class;)Ljava/lang/Object;
       6: checkcast     #42                 // class com/arjuna/ats/jta/common/JTAEnvironmentBean
       9: aload_1
      10: invokevirtual #43                 // Method com/arjuna/ats/jta/common/JTAEnvironmentBean.setXaResourceOrphanFilterClassNames:(Ljava/util/List;)V
      13: return

  private void setRecoveryModules(java.util.List<java.lang.String>);
    Code:
       0: aload_0
       1: ldc           #39                 // class com/arjuna/ats/arjuna/common/RecoveryEnvironmentBean
       3: invokespecial #29                 // Method getPopulator:(Ljava/lang/Class;)Ljava/lang/Object;
       6: checkcast     #39                 // class com/arjuna/ats/arjuna/common/RecoveryEnvironmentBean
       9: aload_1
      10: invokevirtual #44                 // Method com/arjuna/ats/arjuna/common/RecoveryEnvironmentBean.setRecoveryModuleClassNames:(Ljava/util/List;)V
      13: return

  private void setExpiryScanners(java.util.List<java.lang.String>);
    Code:
       0: aload_0
       1: ldc           #39                 // class com/arjuna/ats/arjuna/common/RecoveryEnvironmentBean
       3: invokespecial #29                 // Method getPopulator:(Ljava/lang/Class;)Ljava/lang/Object;
       6: checkcast     #39                 // class com/arjuna/ats/arjuna/common/RecoveryEnvironmentBean
       9: aload_1
      10: invokevirtual #45                 // Method com/arjuna/ats/arjuna/common/RecoveryEnvironmentBean.setExpiryScannerClassNames:(Ljava/util/List;)V
      13: return

  private <T> T getPopulator(java.lang.Class<T>);
    Code:
       0: aload_1
       1: invokestatic  #46                 // Method com/arjuna/common/internal/util/propertyservice/BeanPopulator.getDefaultInstance:(Ljava/lang/Class;)Ljava/lang/Object;
       4: areturn

  private <T> T getPopulator(java.lang.Class<T>, java.lang.String);
    Code:
       0: aload_1
       1: aload_2
       2: invokestatic  #47                 // Method com/arjuna/common/internal/util/propertyservice/BeanPopulator.getNamedInstance:(Ljava/lang/Class;Ljava/lang/String;)Ljava/lang/Object;
       5: areturn
}
