Compiled from "Funnels.java"
final class org.apache.jena.ext.com.google.common.hash.Funnels$IntegerFunnel extends java.lang.Enum<org.apache.jena.ext.com.google.common.hash.Funnels$IntegerFunnel> implements org.apache.jena.ext.com.google.common.hash.Funnel<java.lang.Integer> {
  public static final org.apache.jena.ext.com.google.common.hash.Funnels$IntegerFunnel INSTANCE;

  private static final org.apache.jena.ext.com.google.common.hash.Funnels$IntegerFunnel[] $VALUES;

  public static org.apache.jena.ext.com.google.common.hash.Funnels$IntegerFunnel[] values();
    Code:
       0: getstatic     #19                 // Field $VALUES:[Lorg/apache/jena/ext/com/google/common/hash/Funnels$IntegerFunnel;
       3: invokevirtual #24                 // Method "[Lorg/apache/jena/ext/com/google/common/hash/Funnels$IntegerFunnel;".clone:()Ljava/lang/Object;
       6: checkcast     #20                 // class "[Lorg/apache/jena/ext/com/google/common/hash/Funnels$IntegerFunnel;"
       9: areturn

  public static org.apache.jena.ext.com.google.common.hash.Funnels$IntegerFunnel valueOf(java.lang.String);
    Code:
       0: ldc           #2                  // class org/apache/jena/ext/com/google/common/hash/Funnels$IntegerFunnel
       2: aload_0
       3: invokestatic  #29                 // Method java/lang/Enum.valueOf:(Ljava/lang/Class;Ljava/lang/String;)Ljava/lang/Enum;
       6: checkcast     #2                  // class org/apache/jena/ext/com/google/common/hash/Funnels$IntegerFunnel
       9: areturn

  private org.apache.jena.ext.com.google.common.hash.Funnels$IntegerFunnel();
    Code:
       0: aload_0
       1: aload_1
       2: iload_2
       3: invokespecial #35                 // Method java/lang/Enum."<init>":(Ljava/lang/String;I)V
       6: return

  public void funnel(java.lang.Integer, org.apache.jena.ext.com.google.common.hash.PrimitiveSink);
    Code:
       0: aload_2
       1: aload_1
       2: invokevirtual #44                 // Method java/lang/Integer.intValue:()I
       5: invokeinterface #50,  2           // InterfaceMethod org/apache/jena/ext/com/google/common/hash/PrimitiveSink.putInt:(I)Lorg/apache/jena/ext/com/google/common/hash/PrimitiveSink;
      10: pop
      11: return

  public java.lang.String toString();
    Code:
       0: ldc           #58                 // String Funnels.integerFunnel()
       2: areturn

  public void funnel(java.lang.Object, org.apache.jena.ext.com.google.common.hash.PrimitiveSink);
    Code:
       0: aload_0
       1: aload_1
       2: checkcast     #40                 // class java/lang/Integer
       5: aload_2
       6: invokevirtual #61                 // Method funnel:(Ljava/lang/Integer;Lorg/apache/jena/ext/com/google/common/hash/PrimitiveSink;)V
       9: return

  static {};
    Code:
       0: new           #2                  // class org/apache/jena/ext/com/google/common/hash/Funnels$IntegerFunnel
       3: dup
       4: ldc           #64                 // String INSTANCE
       6: iconst_0
       7: invokespecial #65                 // Method "<init>":(Ljava/lang/String;I)V
      10: putstatic     #67                 // Field INSTANCE:Lorg/apache/jena/ext/com/google/common/hash/Funnels$IntegerFunnel;
      13: iconst_1
      14: anewarray     #2                  // class org/apache/jena/ext/com/google/common/hash/Funnels$IntegerFunnel
      17: dup
      18: iconst_0
      19: getstatic     #67                 // Field INSTANCE:Lorg/apache/jena/ext/com/google/common/hash/Funnels$IntegerFunnel;
      22: aastore
      23: putstatic     #19                 // Field $VALUES:[Lorg/apache/jena/ext/com/google/common/hash/Funnels$IntegerFunnel;
      26: return
}
