Compiled from "SingleClusterRouter.java"
class io.manbang.ebatis.core.cluster.SingleClusterRouter extends io.manbang.ebatis.core.cluster.AbstractClusterRouter {
  private final io.manbang.ebatis.core.cluster.Cluster[] clusters;

  public io.manbang.ebatis.core.cluster.SingleClusterRouter(io.manbang.ebatis.core.cluster.Cluster);
    Code:
       0: aload_0
       1: invokespecial #1                  // Method io/manbang/ebatis/core/cluster/AbstractClusterRouter."<init>":()V
       4: aload_0
       5: iconst_1
       6: anewarray     #2                  // class io/manbang/ebatis/core/cluster/Cluster
       9: dup
      10: iconst_0
      11: aload_1
      12: aastore
      13: putfield      #3                  // Field clusters:[Lio/manbang/ebatis/core/cluster/Cluster;
      16: return

  protected io.manbang.ebatis.core.cluster.Cluster[] getClusters();
    Code:
       0: aload_0
       1: getfield      #3                  // Field clusters:[Lio/manbang/ebatis/core/cluster/Cluster;
       4: areturn

  protected io.manbang.ebatis.core.cluster.ClusterLoadBalancer getLoadBalancer(io.manbang.ebatis.core.meta.MethodMeta);
    Code:
       0: getstatic     #4                  // Field io/manbang/ebatis/core/cluster/SingleClusterLoaderBalancer.INSTANCE:Lio/manbang/ebatis/core/cluster/SingleClusterLoaderBalancer;
       3: areturn
}
