Compiled from "KotlinTypeCheckerImpl.java"
public class kotlin.reflect.jvm.internal.impl.types.checker.KotlinTypeCheckerImpl implements kotlin.reflect.jvm.internal.impl.types.checker.KotlinTypeChecker {
  private final kotlin.reflect.jvm.internal.impl.types.checker.TypeCheckingProcedure procedure;

  public static kotlin.reflect.jvm.internal.impl.types.checker.KotlinTypeChecker withAxioms(kotlin.reflect.jvm.internal.impl.types.checker.KotlinTypeChecker$TypeConstructorEquality);
    Code:
       0: new           #4                  // class kotlin/reflect/jvm/internal/impl/types/checker/KotlinTypeCheckerImpl
       3: dup
       4: new           #6                  // class kotlin/reflect/jvm/internal/impl/types/checker/TypeCheckingProcedure
       7: dup
       8: new           #5                  // class kotlin/reflect/jvm/internal/impl/types/checker/KotlinTypeCheckerImpl$1
      11: dup
      12: aload_0
      13: invokespecial #10                 // Method kotlin/reflect/jvm/internal/impl/types/checker/KotlinTypeCheckerImpl$1."<init>":(Lkotlin/reflect/jvm/internal/impl/types/checker/KotlinTypeChecker$TypeConstructorEquality;)V
      16: invokespecial #11                 // Method kotlin/reflect/jvm/internal/impl/types/checker/TypeCheckingProcedure."<init>":(Lkotlin/reflect/jvm/internal/impl/types/checker/TypeCheckingProcedureCallbacks;)V
      19: invokespecial #9                  // Method "<init>":(Lkotlin/reflect/jvm/internal/impl/types/checker/TypeCheckingProcedure;)V
      22: areturn

  protected kotlin.reflect.jvm.internal.impl.types.checker.KotlinTypeCheckerImpl(kotlin.reflect.jvm.internal.impl.types.checker.TypeCheckingProcedure);
    Code:
       0: aload_0
       1: invokespecial #8                  // Method java/lang/Object."<init>":()V
       4: aload_0
       5: aload_1
       6: putfield      #7                  // Field procedure:Lkotlin/reflect/jvm/internal/impl/types/checker/TypeCheckingProcedure;
       9: return

  public boolean isSubtypeOf(kotlin.reflect.jvm.internal.impl.types.KotlinType, kotlin.reflect.jvm.internal.impl.types.KotlinType);
    Code:
       0: aload_0
       1: getfield      #7                  // Field procedure:Lkotlin/reflect/jvm/internal/impl/types/checker/TypeCheckingProcedure;
       4: aload_1
       5: aload_2
       6: invokevirtual #13                 // Method kotlin/reflect/jvm/internal/impl/types/checker/TypeCheckingProcedure.isSubtypeOf:(Lkotlin/reflect/jvm/internal/impl/types/KotlinType;Lkotlin/reflect/jvm/internal/impl/types/KotlinType;)Z
       9: ireturn

  public boolean equalTypes(kotlin.reflect.jvm.internal.impl.types.KotlinType, kotlin.reflect.jvm.internal.impl.types.KotlinType);
    Code:
       0: aload_0
       1: getfield      #7                  // Field procedure:Lkotlin/reflect/jvm/internal/impl/types/checker/TypeCheckingProcedure;
       4: aload_1
       5: aload_2
       6: invokevirtual #12                 // Method kotlin/reflect/jvm/internal/impl/types/checker/TypeCheckingProcedure.equalTypes:(Lkotlin/reflect/jvm/internal/impl/types/KotlinType;Lkotlin/reflect/jvm/internal/impl/types/KotlinType;)Z
       9: ireturn
}
