Compiled from "ParseState.java"
public final class org.springframework.beans.factory.parsing.ParseState {
  private static final char TAB;

  private final java.util.Stack<org.springframework.beans.factory.parsing.ParseState$Entry> state;

  public org.springframework.beans.factory.parsing.ParseState();
    Code:
       0: aload_0
       1: invokespecial #1                  // Method java/lang/Object."<init>":()V
       4: aload_0
       5: new           #2                  // class java/util/Stack
       8: dup
       9: invokespecial #3                  // Method java/util/Stack."<init>":()V
      12: putfield      #4                  // Field state:Ljava/util/Stack;
      15: return

  private org.springframework.beans.factory.parsing.ParseState(org.springframework.beans.factory.parsing.ParseState);
    Code:
       0: aload_0
       1: invokespecial #1                  // Method java/lang/Object."<init>":()V
       4: aload_0
       5: aload_1
       6: getfield      #4                  // Field state:Ljava/util/Stack;
       9: invokevirtual #5                  // Method java/util/Stack.clone:()Ljava/lang/Object;
      12: checkcast     #2                  // class java/util/Stack
      15: putfield      #4                  // Field state:Ljava/util/Stack;
      18: return

  public void push(org.springframework.beans.factory.parsing.ParseState$Entry);
    Code:
       0: aload_0
       1: getfield      #4                  // Field state:Ljava/util/Stack;
       4: aload_1
       5: invokevirtual #6                  // Method java/util/Stack.push:(Ljava/lang/Object;)Ljava/lang/Object;
       8: pop
       9: return

  public void pop();
    Code:
       0: aload_0
       1: getfield      #4                  // Field state:Ljava/util/Stack;
       4: invokevirtual #7                  // Method java/util/Stack.pop:()Ljava/lang/Object;
       7: pop
       8: return

  public org.springframework.beans.factory.parsing.ParseState$Entry peek();
    Code:
       0: aload_0
       1: getfield      #4                  // Field state:Ljava/util/Stack;
       4: invokevirtual #8                  // Method java/util/Stack.empty:()Z
       7: ifeq          14
      10: aconst_null
      11: goto          24
      14: aload_0
      15: getfield      #4                  // Field state:Ljava/util/Stack;
      18: invokevirtual #9                  // Method java/util/Stack.peek:()Ljava/lang/Object;
      21: checkcast     #10                 // class org/springframework/beans/factory/parsing/ParseState$Entry
      24: areturn

  public org.springframework.beans.factory.parsing.ParseState snapshot();
    Code:
       0: new           #11                 // class org/springframework/beans/factory/parsing/ParseState
       3: dup
       4: aload_0
       5: invokespecial #12                 // Method "<init>":(Lorg/springframework/beans/factory/parsing/ParseState;)V
       8: areturn

  public java.lang.String toString();
    Code:
       0: new           #13                 // class java/lang/StringBuilder
       3: dup
       4: invokespecial #14                 // Method java/lang/StringBuilder."<init>":()V
       7: astore_1
       8: iconst_0
       9: istore_2
      10: iload_2
      11: aload_0
      12: getfield      #4                  // Field state:Ljava/util/Stack;
      15: invokevirtual #15                 // Method java/util/Stack.size:()I
      18: if_icmpge     78
      21: iload_2
      22: ifle          59
      25: aload_1
      26: bipush        10
      28: invokevirtual #16                 // Method java/lang/StringBuilder.append:(C)Ljava/lang/StringBuilder;
      31: pop
      32: iconst_0
      33: istore_3
      34: iload_3
      35: iload_2
      36: if_icmpge     52
      39: aload_1
      40: bipush        9
      42: invokevirtual #16                 // Method java/lang/StringBuilder.append:(C)Ljava/lang/StringBuilder;
      45: pop
      46: iinc          3, 1
      49: goto          34
      52: aload_1
      53: ldc           #17                 // String ->
      55: invokevirtual #18                 // Method java/lang/StringBuilder.append:(Ljava/lang/String;)Ljava/lang/StringBuilder;
      58: pop
      59: aload_1
      60: aload_0
      61: getfield      #4                  // Field state:Ljava/util/Stack;
      64: iload_2
      65: invokevirtual #19                 // Method java/util/Stack.get:(I)Ljava/lang/Object;
      68: invokevirtual #20                 // Method java/lang/StringBuilder.append:(Ljava/lang/Object;)Ljava/lang/StringBuilder;
      71: pop
      72: iinc          2, 1
      75: goto          10
      78: aload_1
      79: invokevirtual #21                 // Method java/lang/StringBuilder.toString:()Ljava/lang/String;
      82: areturn
}
