Compiled from "SentenceToUpperCaseBean.java"
public class org.camunda.bpm.engine.spring.test.servicetask.SentenceToUpperCaseBean {
  protected org.camunda.bpm.engine.spring.test.servicetask.SentenceGenerator sentenceGenerator;

  public org.camunda.bpm.engine.spring.test.servicetask.SentenceToUpperCaseBean();
    Code:
       0: aload_0
       1: invokespecial #1                  // Method java/lang/Object."<init>":()V
       4: return

  public void setSentence(org.camunda.bpm.engine.impl.pvm.delegate.ActivityExecution);
    Code:
       0: aload_1
       1: ldc           #2                  // String myVar
       3: aload_0
       4: getfield      #3                  // Field sentenceGenerator:Lorg/camunda/bpm/engine/spring/test/servicetask/SentenceGenerator;
       7: invokevirtual #4                  // Method org/camunda/bpm/engine/spring/test/servicetask/SentenceGenerator.getSentence:()Ljava/lang/String;
      10: invokevirtual #5                  // Method java/lang/String.toUpperCase:()Ljava/lang/String;
      13: invokeinterface #6,  3            // InterfaceMethod org/camunda/bpm/engine/impl/pvm/delegate/ActivityExecution.setVariable:(Ljava/lang/String;Ljava/lang/Object;)V
      18: return

  public void setSentenceGenerator(org.camunda.bpm.engine.spring.test.servicetask.SentenceGenerator);
    Code:
       0: aload_0
       1: aload_1
       2: putfield      #3                  // Field sentenceGenerator:Lorg/camunda/bpm/engine/spring/test/servicetask/SentenceGenerator;
       5: return
}
