Compiled from "AWSApplicationAutoScalingAsyncClientBuilder.java"
public final class com.amazonaws.services.applicationautoscaling.AWSApplicationAutoScalingAsyncClientBuilder extends com.amazonaws.client.builder.AwsAsyncClientBuilder<com.amazonaws.services.applicationautoscaling.AWSApplicationAutoScalingAsyncClientBuilder, com.amazonaws.services.applicationautoscaling.AWSApplicationAutoScalingAsync> {
  private static final com.amazonaws.ClientConfigurationFactory CLIENT_CONFIG_FACTORY;

  public static com.amazonaws.services.applicationautoscaling.AWSApplicationAutoScalingAsyncClientBuilder standard();
    Code:
       0: new           #1                  // class com/amazonaws/services/applicationautoscaling/AWSApplicationAutoScalingAsyncClientBuilder
       3: dup
       4: invokespecial #2                  // Method "<init>":()V
       7: areturn

  public static com.amazonaws.services.applicationautoscaling.AWSApplicationAutoScalingAsync defaultClient();
    Code:
       0: invokestatic  #3                  // Method standard:()Lcom/amazonaws/services/applicationautoscaling/AWSApplicationAutoScalingAsyncClientBuilder;
       3: invokevirtual #4                  // Method build:()Ljava/lang/Object;
       6: checkcast     #5                  // class com/amazonaws/services/applicationautoscaling/AWSApplicationAutoScalingAsync
       9: areturn

  private com.amazonaws.services.applicationautoscaling.AWSApplicationAutoScalingAsyncClientBuilder();
    Code:
       0: aload_0
       1: getstatic     #6                  // Field CLIENT_CONFIG_FACTORY:Lcom/amazonaws/ClientConfigurationFactory;
       4: invokespecial #7                  // Method com/amazonaws/client/builder/AwsAsyncClientBuilder."<init>":(Lcom/amazonaws/ClientConfigurationFactory;)V
       7: return

  protected com.amazonaws.services.applicationautoscaling.AWSApplicationAutoScalingAsync build(com.amazonaws.client.AwsAsyncClientParams);
    Code:
       0: new           #8                  // class com/amazonaws/services/applicationautoscaling/AWSApplicationAutoScalingAsyncClient
       3: dup
       4: aload_1
       5: invokespecial #9                  // Method com/amazonaws/services/applicationautoscaling/AWSApplicationAutoScalingAsyncClient."<init>":(Lcom/amazonaws/client/AwsAsyncClientParams;)V
       8: areturn

  protected java.lang.Object build(com.amazonaws.client.AwsAsyncClientParams);
    Code:
       0: aload_0
       1: aload_1
       2: invokevirtual #10                 // Method build:(Lcom/amazonaws/client/AwsAsyncClientParams;)Lcom/amazonaws/services/applicationautoscaling/AWSApplicationAutoScalingAsync;
       5: areturn

  static {};
    Code:
       0: new           #11                 // class com/amazonaws/ClientConfigurationFactory
       3: dup
       4: invokespecial #12                 // Method com/amazonaws/ClientConfigurationFactory."<init>":()V
       7: putstatic     #6                  // Field CLIENT_CONFIG_FACTORY:Lcom/amazonaws/ClientConfigurationFactory;
      10: return
}
