Compiled from "IncomingBatchService.java"
class org.jumpmind.symmetric.service.impl.IncomingBatchService$IncomingBatchMapper implements org.jumpmind.db.sql.ISqlRowMapper<org.jumpmind.symmetric.model.IncomingBatch> {
  final org.jumpmind.symmetric.service.impl.IncomingBatchService this$0;

  org.jumpmind.symmetric.service.impl.IncomingBatchService$IncomingBatchMapper(org.jumpmind.symmetric.service.impl.IncomingBatchService);
    Code:
       0: aload_0
       1: aload_1
       2: putfield      #1                  // Field this$0:Lorg/jumpmind/symmetric/service/impl/IncomingBatchService;
       5: aload_0
       6: invokespecial #2                  // Method java/lang/Object."<init>":()V
       9: return

  public org.jumpmind.symmetric.model.IncomingBatch mapRow(org.jumpmind.db.sql.Row);
    Code:
       0: new           #3                  // class org/jumpmind/symmetric/model/IncomingBatch
       3: dup
       4: invokespecial #4                  // Method org/jumpmind/symmetric/model/IncomingBatch."<init>":()V
       7: astore_2
       8: aload_2
       9: aload_1
      10: ldc           #5                  // String batch_id
      12: invokevirtual #6                  // Method org/jumpmind/db/sql/Row.getLong:(Ljava/lang/String;)J
      15: invokevirtual #7                  // Method org/jumpmind/symmetric/model/IncomingBatch.setBatchId:(J)V
      18: aload_2
      19: aload_1
      20: ldc           #8                  // String node_id
      22: invokevirtual #9                  // Method org/jumpmind/db/sql/Row.getString:(Ljava/lang/String;)Ljava/lang/String;
      25: invokevirtual #10                 // Method org/jumpmind/symmetric/model/IncomingBatch.setNodeId:(Ljava/lang/String;)V
      28: aload_2
      29: aload_1
      30: ldc           #11                 // String channel_id
      32: invokevirtual #9                  // Method org/jumpmind/db/sql/Row.getString:(Ljava/lang/String;)Ljava/lang/String;
      35: invokevirtual #12                 // Method org/jumpmind/symmetric/model/IncomingBatch.setChannelId:(Ljava/lang/String;)V
      38: aload_2
      39: aload_1
      40: ldc           #13                 // String status
      42: invokevirtual #9                  // Method org/jumpmind/db/sql/Row.getString:(Ljava/lang/String;)Ljava/lang/String;
      45: invokestatic  #14                 // Method org/jumpmind/symmetric/model/IncomingBatch$Status.valueOf:(Ljava/lang/String;)Lorg/jumpmind/symmetric/model/IncomingBatch$Status;
      48: invokevirtual #15                 // Method org/jumpmind/symmetric/model/IncomingBatch.setStatus:(Lorg/jumpmind/symmetric/model/IncomingBatch$Status;)V
      51: aload_2
      52: aload_1
      53: ldc           #16                 // String network_millis
      55: invokevirtual #6                  // Method org/jumpmind/db/sql/Row.getLong:(Ljava/lang/String;)J
      58: invokevirtual #17                 // Method org/jumpmind/symmetric/model/IncomingBatch.setNetworkMillis:(J)V
      61: aload_2
      62: aload_1
      63: ldc           #18                 // String filter_millis
      65: invokevirtual #6                  // Method org/jumpmind/db/sql/Row.getLong:(Ljava/lang/String;)J
      68: invokevirtual #19                 // Method org/jumpmind/symmetric/model/IncomingBatch.setFilterMillis:(J)V
      71: aload_2
      72: aload_1
      73: ldc           #20                 // String database_millis
      75: invokevirtual #6                  // Method org/jumpmind/db/sql/Row.getLong:(Ljava/lang/String;)J
      78: invokevirtual #21                 // Method org/jumpmind/symmetric/model/IncomingBatch.setDatabaseMillis:(J)V
      81: aload_2
      82: aload_1
      83: ldc           #22                 // String failed_row_number
      85: invokevirtual #6                  // Method org/jumpmind/db/sql/Row.getLong:(Ljava/lang/String;)J
      88: invokevirtual #23                 // Method org/jumpmind/symmetric/model/IncomingBatch.setFailedRowNumber:(J)V
      91: aload_2
      92: aload_1
      93: ldc           #24                 // String failed_line_number
      95: invokevirtual #6                  // Method org/jumpmind/db/sql/Row.getLong:(Ljava/lang/String;)J
      98: invokevirtual #25                 // Method org/jumpmind/symmetric/model/IncomingBatch.setFailedLineNumber:(J)V
     101: aload_2
     102: aload_1
     103: ldc           #26                 // String byte_count
     105: invokevirtual #6                  // Method org/jumpmind/db/sql/Row.getLong:(Ljava/lang/String;)J
     108: invokevirtual #27                 // Method org/jumpmind/symmetric/model/IncomingBatch.setByteCount:(J)V
     111: aload_2
     112: aload_1
     113: ldc           #28                 // String statement_count
     115: invokevirtual #6                  // Method org/jumpmind/db/sql/Row.getLong:(Ljava/lang/String;)J
     118: invokevirtual #29                 // Method org/jumpmind/symmetric/model/IncomingBatch.setStatementCount:(J)V
     121: aload_2
     122: aload_1
     123: ldc           #30                 // String fallback_insert_count
     125: invokevirtual #6                  // Method org/jumpmind/db/sql/Row.getLong:(Ljava/lang/String;)J
     128: invokevirtual #31                 // Method org/jumpmind/symmetric/model/IncomingBatch.setFallbackInsertCount:(J)V
     131: aload_2
     132: aload_1
     133: ldc           #32                 // String fallback_update_count
     135: invokevirtual #6                  // Method org/jumpmind/db/sql/Row.getLong:(Ljava/lang/String;)J
     138: invokevirtual #33                 // Method org/jumpmind/symmetric/model/IncomingBatch.setFallbackUpdateCount:(J)V
     141: aload_2
     142: aload_1
     143: ldc           #34                 // String ignore_count
     145: invokevirtual #6                  // Method org/jumpmind/db/sql/Row.getLong:(Ljava/lang/String;)J
     148: invokevirtual #35                 // Method org/jumpmind/symmetric/model/IncomingBatch.setIgnoreCount:(J)V
     151: aload_2
     152: aload_1
     153: ldc           #36                 // String missing_delete_count
     155: invokevirtual #6                  // Method org/jumpmind/db/sql/Row.getLong:(Ljava/lang/String;)J
     158: invokevirtual #37                 // Method org/jumpmind/symmetric/model/IncomingBatch.setMissingDeleteCount:(J)V
     161: aload_2
     162: aload_1
     163: ldc           #38                 // String skip_count
     165: invokevirtual #6                  // Method org/jumpmind/db/sql/Row.getLong:(Ljava/lang/String;)J
     168: invokevirtual #39                 // Method org/jumpmind/symmetric/model/IncomingBatch.setSkipCount:(J)V
     171: aload_2
     172: aload_1
     173: ldc           #40                 // String sql_state
     175: invokevirtual #9                  // Method org/jumpmind/db/sql/Row.getString:(Ljava/lang/String;)Ljava/lang/String;
     178: invokevirtual #41                 // Method org/jumpmind/symmetric/model/IncomingBatch.setSqlState:(Ljava/lang/String;)V
     181: aload_2
     182: aload_1
     183: ldc           #42                 // String sql_code
     185: invokevirtual #43                 // Method org/jumpmind/db/sql/Row.getInt:(Ljava/lang/String;)I
     188: invokevirtual #44                 // Method org/jumpmind/symmetric/model/IncomingBatch.setSqlCode:(I)V
     191: aload_2
     192: aload_1
     193: ldc           #45                 // String sql_message
     195: invokevirtual #9                  // Method org/jumpmind/db/sql/Row.getString:(Ljava/lang/String;)Ljava/lang/String;
     198: invokevirtual #46                 // Method org/jumpmind/symmetric/model/IncomingBatch.setSqlMessage:(Ljava/lang/String;)V
     201: aload_2
     202: aload_1
     203: ldc           #47                 // String last_update_hostname
     205: invokevirtual #9                  // Method org/jumpmind/db/sql/Row.getString:(Ljava/lang/String;)Ljava/lang/String;
     208: invokevirtual #48                 // Method org/jumpmind/symmetric/model/IncomingBatch.setLastUpdatedHostName:(Ljava/lang/String;)V
     211: aload_2
     212: aload_1
     213: ldc           #49                 // String last_update_time
     215: invokevirtual #50                 // Method org/jumpmind/db/sql/Row.getDateTime:(Ljava/lang/String;)Ljava/util/Date;
     218: invokevirtual #51                 // Method org/jumpmind/symmetric/model/IncomingBatch.setLastUpdatedTime:(Ljava/util/Date;)V
     221: aload_2
     222: aload_1
     223: ldc           #52                 // String create_time
     225: invokevirtual #50                 // Method org/jumpmind/db/sql/Row.getDateTime:(Ljava/lang/String;)Ljava/util/Date;
     228: invokevirtual #53                 // Method org/jumpmind/symmetric/model/IncomingBatch.setCreateTime:(Ljava/util/Date;)V
     231: aload_2
     232: aload_1
     233: ldc           #54                 // String error_flag
     235: invokevirtual #55                 // Method org/jumpmind/db/sql/Row.getBoolean:(Ljava/lang/String;)Z
     238: invokevirtual #56                 // Method org/jumpmind/symmetric/model/IncomingBatch.setErrorFlag:(Z)V
     241: aload_2
     242: areturn

  public java.lang.Object mapRow(org.jumpmind.db.sql.Row);
    Code:
       0: aload_0
       1: aload_1
       2: invokevirtual #57                 // Method mapRow:(Lorg/jumpmind/db/sql/Row;)Lorg/jumpmind/symmetric/model/IncomingBatch;
       5: areturn
}
