Compiled from "NodeCommunicationServiceSqlMap.java"
public class org.jumpmind.symmetric.service.impl.NodeCommunicationServiceSqlMap extends org.jumpmind.symmetric.service.impl.AbstractSqlMap {
  public org.jumpmind.symmetric.service.impl.NodeCommunicationServiceSqlMap(org.jumpmind.db.platform.IDatabasePlatform, java.util.Map<java.lang.String, java.lang.String>);
    Code:
       0: aload_0
       1: aload_1
       2: aload_2
       3: invokespecial #1                  // Method org/jumpmind/symmetric/service/impl/AbstractSqlMap."<init>":(Lorg/jumpmind/db/platform/IDatabasePlatform;Ljava/util/Map;)V
       6: aload_0
       7: ldc           #2                  // String clearLocksOnRestartSql
       9: ldc           #3                  // String update $(node_communication) set lock_time=null where locking_server_id=? and lock_time is not null
      11: invokevirtual #4                  // Method putSql:(Ljava/lang/String;Ljava/lang/String;)V
      14: aload_0
      15: ldc           #5                  // String selectNodeCommunicationSql
      17: ldc           #6                  // String select * from $(node_communication) where communication_type=? order by last_lock_time
      19: invokevirtual #4                  // Method putSql:(Ljava/lang/String;Ljava/lang/String;)V
      22: aload_0
      23: ldc           #7                  // String insertNodeCommunicationSql
      25: ldc           #8                  // String insert into $(node_communication) (lock_time,locking_server_id,last_lock_millis,success_count,fail_count,total_success_count,total_fail_count,total_success_millis,total_fail_millis,last_lock_time,node_id,communication_type) values(?,?,?,?,?,?,?,?,?,?,?,?)
      27: invokevirtual #4                  // Method putSql:(Ljava/lang/String;Ljava/lang/String;)V
      30: aload_0
      31: ldc           #9                  // String updateNodeCommunicationSql
      33: ldc           #10                 // String update $(node_communication) set lock_time=?,locking_server_id=?,last_lock_millis=?,success_count=?,fail_count=?,total_success_count=?,total_fail_count=?,total_success_millis=?,total_fail_millis=?, last_lock_time=? where node_id=? and communication_type=?
      35: invokevirtual #4                  // Method putSql:(Ljava/lang/String;Ljava/lang/String;)V
      38: aload_0
      39: ldc           #11                 // String deleteNodeCommunicationSql
      41: ldc           #12                 // String delete from $(node_communication) where node_id=? and communication_type=?
      43: invokevirtual #4                  // Method putSql:(Ljava/lang/String;Ljava/lang/String;)V
      46: aload_0
      47: ldc           #13                 // String aquireLockSql
      49: ldc           #14                 // String update $(node_communication) set locking_server_id=?, lock_time=?, last_lock_time=? where   node_id=? and communication_type=? and  (lock_time is null or lock_time < ? or locking_server_id=?)
      51: invokevirtual #4                  // Method putSql:(Ljava/lang/String;Ljava/lang/String;)V
      54: return
}
