Compiled from "TriggerRouterService.java"
class org.jumpmind.symmetric.service.impl.TriggerRouterService$1 extends org.jumpmind.symmetric.service.impl.TriggerRouterService$TriggerRouterMapper {
  final java.util.Map val$retMap;

  final org.jumpmind.symmetric.service.impl.TriggerRouterService this$0;

  org.jumpmind.symmetric.service.impl.TriggerRouterService$1(org.jumpmind.symmetric.service.impl.TriggerRouterService, java.util.Map);
    Code:
       0: aload_0
       1: aload_1
       2: putfield      #1                  // Field this$0:Lorg/jumpmind/symmetric/service/impl/TriggerRouterService;
       5: aload_0
       6: aload_2
       7: putfield      #2                  // Field val$retMap:Ljava/util/Map;
      10: aload_0
      11: aload_1
      12: invokespecial #3                  // Method org/jumpmind/symmetric/service/impl/TriggerRouterService$TriggerRouterMapper."<init>":(Lorg/jumpmind/symmetric/service/impl/TriggerRouterService;)V
      15: return

  public org.jumpmind.symmetric.model.TriggerRouter mapRow(org.jumpmind.db.sql.Row);
    Code:
       0: aload_0
       1: aload_1
       2: invokespecial #4                  // Method org/jumpmind/symmetric/service/impl/TriggerRouterService$TriggerRouterMapper.mapRow:(Lorg/jumpmind/db/sql/Row;)Lorg/jumpmind/symmetric/model/TriggerRouter;
       5: astore_2
       6: aload_0
       7: getfield      #2                  // Field val$retMap:Ljava/util/Map;
      10: aload_2
      11: invokevirtual #5                  // Method org/jumpmind/symmetric/model/TriggerRouter.getTrigger:()Lorg/jumpmind/symmetric/model/Trigger;
      14: invokevirtual #6                  // Method org/jumpmind/symmetric/model/Trigger.getChannelId:()Ljava/lang/String;
      17: invokeinterface #7,  2            // InterfaceMethod java/util/Map.get:(Ljava/lang/Object;)Ljava/lang/Object;
      22: checkcast     #8                  // class java/util/List
      25: astore_3
      26: aload_3
      27: ifnonnull     56
      30: new           #9                  // class java/util/ArrayList
      33: dup
      34: invokespecial #10                 // Method java/util/ArrayList."<init>":()V
      37: astore_3
      38: aload_0
      39: getfield      #2                  // Field val$retMap:Ljava/util/Map;
      42: aload_2
      43: invokevirtual #5                  // Method org/jumpmind/symmetric/model/TriggerRouter.getTrigger:()Lorg/jumpmind/symmetric/model/Trigger;
      46: invokevirtual #6                  // Method org/jumpmind/symmetric/model/Trigger.getChannelId:()Ljava/lang/String;
      49: aload_3
      50: invokeinterface #11,  3           // InterfaceMethod java/util/Map.put:(Ljava/lang/Object;Ljava/lang/Object;)Ljava/lang/Object;
      55: pop
      56: aload_3
      57: aload_2
      58: invokeinterface #12,  2           // InterfaceMethod java/util/List.add:(Ljava/lang/Object;)Z
      63: pop
      64: aload_2
      65: areturn

  public java.lang.Object mapRow(org.jumpmind.db.sql.Row);
    Code:
       0: aload_0
       1: aload_1
       2: invokevirtual #13                 // Method mapRow:(Lorg/jumpmind/db/sql/Row;)Lorg/jumpmind/symmetric/model/TriggerRouter;
       5: areturn
}
