Compiled from "JPropReadContext.java"
public final class io.dekorate.deps.jackson.dataformat.javaprop.io.JPropReadContext$ObjectContext extends io.dekorate.deps.jackson.dataformat.javaprop.io.JPropReadContext {
  static final int STATE_START;

  static final int STATE_BRANCH_KEY;

  static final int STATE_BRANCH_VALUE;

  static final int STATE_CONTENT_KEY;

  static final int STATE_CONTENT_VALUE;

  static final int STATE_END;

  protected java.util.Iterator<java.util.Map$Entry<java.lang.String, io.dekorate.deps.jackson.dataformat.javaprop.util.JPropNode>> _contents;

  public io.dekorate.deps.jackson.dataformat.javaprop.io.JPropReadContext$ObjectContext(io.dekorate.deps.jackson.dataformat.javaprop.io.JPropReadContext, io.dekorate.deps.jackson.dataformat.javaprop.util.JPropNode);
    Code:
       0: aload_0
       1: iconst_2
       2: aload_1
       3: aload_2
       4: invokespecial #32                 // Method io/dekorate/deps/jackson/dataformat/javaprop/io/JPropReadContext."<init>":(ILio/dekorate/deps/jackson/dataformat/javaprop/io/JPropReadContext;Lio/dekorate/deps/jackson/dataformat/javaprop/util/JPropNode;)V
       7: aload_0
       8: aload_2
       9: invokevirtual #38                 // Method io/dekorate/deps/jackson/dataformat/javaprop/util/JPropNode.objectContents:()Ljava/util/Iterator;
      12: putfield      #40                 // Field _contents:Ljava/util/Iterator;
      15: aload_0
      16: iconst_0
      17: putfield      #43                 // Field _state:I
      20: return

  public io.dekorate.deps.jackson.core.JsonToken nextToken();
    Code:
       0: aload_0
       1: getfield      #43                 // Field _state:I
       4: tableswitch   { // 0 to 5
                     0: 44
                     1: 64
                     2: 79
                     3: 96
                     4: 170
                     5: 207
               default: 207
          }
      44: aload_0
      45: aload_0
      46: getfield      #55                 // Field _branchText:Ljava/lang/String;
      49: ifnonnull     56
      52: iconst_3
      53: goto          57
      56: iconst_1
      57: putfield      #43                 // Field _state:I
      60: getstatic     #61                 // Field io/dekorate/deps/jackson/core/JsonToken.START_OBJECT:Lio/dekorate/deps/jackson/core/JsonToken;
      63: areturn
      64: aload_0
      65: ldc           #63                 // String
      67: putfield      #66                 // Field _currentName:Ljava/lang/String;
      70: aload_0
      71: iconst_2
      72: putfield      #43                 // Field _state:I
      75: getstatic     #69                 // Field io/dekorate/deps/jackson/core/JsonToken.FIELD_NAME:Lio/dekorate/deps/jackson/core/JsonToken;
      78: areturn
      79: aload_0
      80: aload_0
      81: getfield      #55                 // Field _branchText:Ljava/lang/String;
      84: putfield      #72                 // Field _currentText:Ljava/lang/String;
      87: aload_0
      88: iconst_3
      89: putfield      #43                 // Field _state:I
      92: getstatic     #75                 // Field io/dekorate/deps/jackson/core/JsonToken.VALUE_STRING:Lio/dekorate/deps/jackson/core/JsonToken;
      95: areturn
      96: aload_0
      97: getfield      #40                 // Field _contents:Ljava/util/Iterator;
     100: invokeinterface #81,  1           // InterfaceMethod java/util/Iterator.hasNext:()Z
     105: ifne          122
     108: aload_0
     109: iconst_5
     110: putfield      #43                 // Field _state:I
     113: aload_0
     114: aconst_null
     115: putfield      #84                 // Field _nextNode:Lio/dekorate/deps/jackson/dataformat/javaprop/util/JPropNode;
     118: getstatic     #87                 // Field io/dekorate/deps/jackson/core/JsonToken.END_OBJECT:Lio/dekorate/deps/jackson/core/JsonToken;
     121: areturn
     122: aload_0
     123: getfield      #40                 // Field _contents:Ljava/util/Iterator;
     126: invokeinterface #91,  1           // InterfaceMethod java/util/Iterator.next:()Ljava/lang/Object;
     131: checkcast     #7                  // class java/util/Map$Entry
     134: astore_1
     135: aload_0
     136: aload_1
     137: invokeinterface #94,  1           // InterfaceMethod java/util/Map$Entry.getKey:()Ljava/lang/Object;
     142: checkcast     #96                 // class java/lang/String
     145: putfield      #66                 // Field _currentName:Ljava/lang/String;
     148: aload_0
     149: aload_1
     150: invokeinterface #99,  1           // InterfaceMethod java/util/Map$Entry.getValue:()Ljava/lang/Object;
     155: checkcast     #34                 // class io/dekorate/deps/jackson/dataformat/javaprop/util/JPropNode
     158: putfield      #84                 // Field _nextNode:Lio/dekorate/deps/jackson/dataformat/javaprop/util/JPropNode;
     161: aload_0
     162: iconst_4
     163: putfield      #43                 // Field _state:I
     166: getstatic     #69                 // Field io/dekorate/deps/jackson/core/JsonToken.FIELD_NAME:Lio/dekorate/deps/jackson/core/JsonToken;
     169: areturn
     170: aload_0
     171: iconst_3
     172: putfield      #43                 // Field _state:I
     175: aload_0
     176: getfield      #84                 // Field _nextNode:Lio/dekorate/deps/jackson/dataformat/javaprop/util/JPropNode;
     179: invokevirtual #102                // Method io/dekorate/deps/jackson/dataformat/javaprop/util/JPropNode.isLeaf:()Z
     182: ifeq          205
     185: aload_0
     186: aload_0
     187: getfield      #84                 // Field _nextNode:Lio/dekorate/deps/jackson/dataformat/javaprop/util/JPropNode;
     190: invokevirtual #105                // Method io/dekorate/deps/jackson/dataformat/javaprop/util/JPropNode.getValue:()Ljava/lang/String;
     193: putfield      #72                 // Field _currentText:Ljava/lang/String;
     196: aload_0
     197: aconst_null
     198: putfield      #84                 // Field _nextNode:Lio/dekorate/deps/jackson/dataformat/javaprop/util/JPropNode;
     201: getstatic     #75                 // Field io/dekorate/deps/jackson/core/JsonToken.VALUE_STRING:Lio/dekorate/deps/jackson/core/JsonToken;
     204: areturn
     205: aconst_null
     206: areturn
     207: aconst_null
     208: areturn

  public io.dekorate.deps.jackson.core.JsonStreamContext getParent();
    Code:
       0: aload_0
       1: invokespecial #113                // Method io/dekorate/deps/jackson/dataformat/javaprop/io/JPropReadContext.getParent:()Lio/dekorate/deps/jackson/dataformat/javaprop/io/JPropReadContext;
       4: areturn
}
