Compiled from "EndpointPublishService.java"
public final class org.jboss.as.webservices.service.EndpointPublishService implements org.jboss.msc.service.Service<org.jboss.wsf.spi.publish.Context> {
  private final org.jboss.msc.service.ServiceName name;

  private volatile org.jboss.wsf.spi.publish.Context wsctx;

  private final org.jboss.as.server.deployment.DeploymentUnit deploymentUnit;

  private final org.jboss.msc.value.InjectedValue<org.jboss.as.web.host.WebHost> hostInjector;

  private org.jboss.as.webservices.service.EndpointPublishService(java.lang.String, org.jboss.as.server.deployment.DeploymentUnit);
    Code:
       0: aload_0
       1: invokespecial #1                  // Method java/lang/Object."<init>":()V
       4: aload_0
       5: new           #2                  // class org/jboss/msc/value/InjectedValue
       8: dup
       9: invokespecial #3                  // Method org/jboss/msc/value/InjectedValue."<init>":()V
      12: putfield      #4                  // Field hostInjector:Lorg/jboss/msc/value/InjectedValue;
      15: aload_0
      16: getstatic     #5                  // Field org/jboss/as/webservices/util/WSServices.ENDPOINT_PUBLISH_SERVICE:Lorg/jboss/msc/service/ServiceName;
      19: iconst_1
      20: anewarray     #6                  // class java/lang/String
      23: dup
      24: iconst_0
      25: aload_1
      26: aastore
      27: invokevirtual #7                  // Method org/jboss/msc/service/ServiceName.append:([Ljava/lang/String;)Lorg/jboss/msc/service/ServiceName;
      30: putfield      #8                  // Field name:Lorg/jboss/msc/service/ServiceName;
      33: aload_0
      34: aload_2
      35: putfield      #9                  // Field deploymentUnit:Lorg/jboss/as/server/deployment/DeploymentUnit;
      38: return

  public org.jboss.wsf.spi.publish.Context getValue();
    Code:
       0: aload_0
       1: getfield      #10                 // Field wsctx:Lorg/jboss/wsf/spi/publish/Context;
       4: areturn

  public org.jboss.msc.service.ServiceName getName();
    Code:
       0: aload_0
       1: getfield      #8                  // Field name:Lorg/jboss/msc/service/ServiceName;
       4: areturn

  public org.jboss.msc.value.InjectedValue<org.jboss.as.web.host.WebHost> getHostInjector();
    Code:
       0: aload_0
       1: getfield      #4                  // Field hostInjector:Lorg/jboss/msc/value/InjectedValue;
       4: areturn

  public void start(org.jboss.msc.service.StartContext) throws org.jboss.msc.service.StartException;
    Code:
       0: getstatic     #11                 // Field org/jboss/as/webservices/logging/WSLogger.ROOT_LOGGER:Lorg/jboss/as/webservices/logging/WSLogger;
       3: aload_0
       4: getfield      #8                  // Field name:Lorg/jboss/msc/service/ServiceName;
       7: invokeinterface #12,  2           // InterfaceMethod org/jboss/as/webservices/logging/WSLogger.starting:(Ljava/lang/Object;)V
      12: aload_0
      13: aload_0
      14: getfield      #4                  // Field hostInjector:Lorg/jboss/msc/value/InjectedValue;
      17: invokevirtual #13                 // Method org/jboss/msc/value/InjectedValue.getValue:()Ljava/lang/Object;
      20: checkcast     #14                 // class org/jboss/as/web/host/WebHost
      23: aload_1
      24: invokeinterface #15,  1           // InterfaceMethod org/jboss/msc/service/StartContext.getChildTarget:()Lorg/jboss/msc/service/ServiceTarget;
      29: aload_0
      30: getfield      #9                  // Field deploymentUnit:Lorg/jboss/as/server/deployment/DeploymentUnit;
      33: invokestatic  #16                 // Method org/jboss/as/webservices/publish/EndpointPublisherHelper.doPublishStep:(Lorg/jboss/as/web/host/WebHost;Lorg/jboss/msc/service/ServiceTarget;Lorg/jboss/as/server/deployment/DeploymentUnit;)Lorg/jboss/wsf/spi/publish/Context;
      36: putfield      #10                 // Field wsctx:Lorg/jboss/wsf/spi/publish/Context;
      39: goto          52
      42: astore_2
      43: new           #18                 // class org/jboss/msc/service/StartException
      46: dup
      47: aload_2
      48: invokespecial #19                 // Method org/jboss/msc/service/StartException."<init>":(Ljava/lang/Throwable;)V
      51: athrow
      52: return
    Exception table:
       from    to  target type
          12    39    42   Class java/lang/Exception

  public void stop(org.jboss.msc.service.StopContext);
    Code:
       0: getstatic     #11                 // Field org/jboss/as/webservices/logging/WSLogger.ROOT_LOGGER:Lorg/jboss/as/webservices/logging/WSLogger;
       3: aload_0
       4: getfield      #8                  // Field name:Lorg/jboss/msc/service/ServiceName;
       7: invokeinterface #20,  2           // InterfaceMethod org/jboss/as/webservices/logging/WSLogger.stopping:(Ljava/lang/Object;)V
      12: aload_0
      13: getfield      #10                 // Field wsctx:Lorg/jboss/wsf/spi/publish/Context;
      16: invokevirtual #21                 // Method org/jboss/wsf/spi/publish/Context.getEndpoints:()Ljava/util/List;
      19: astore_2
      20: aload_2
      21: ifnull        33
      24: aload_2
      25: invokeinterface #22,  1           // InterfaceMethod java/util/List.isEmpty:()Z
      30: ifeq          34
      33: return
      34: aload_0
      35: getfield      #4                  // Field hostInjector:Lorg/jboss/msc/value/InjectedValue;
      38: invokevirtual #13                 // Method org/jboss/msc/value/InjectedValue.getValue:()Ljava/lang/Object;
      41: checkcast     #14                 // class org/jboss/as/web/host/WebHost
      44: aload_0
      45: getfield      #10                 // Field wsctx:Lorg/jboss/wsf/spi/publish/Context;
      48: invokestatic  #23                 // Method org/jboss/as/webservices/publish/EndpointPublisherHelper.undoPublishStep:(Lorg/jboss/as/web/host/WebHost;Lorg/jboss/wsf/spi/publish/Context;)V
      51: goto          64
      54: astore_3
      55: new           #24                 // class java/lang/RuntimeException
      58: dup
      59: aload_3
      60: invokespecial #25                 // Method java/lang/RuntimeException."<init>":(Ljava/lang/Throwable;)V
      63: athrow
      64: return
    Exception table:
       from    to  target type
          34    51    54   Class java/lang/Exception

  public static org.jboss.msc.service.ServiceBuilder<org.jboss.wsf.spi.publish.Context> createServiceBuilder(org.jboss.msc.service.ServiceTarget, java.lang.String, java.lang.ClassLoader, java.lang.String, java.util.Map<java.lang.String, java.lang.String>);
    Code:
       0: aload_0
       1: aload_1
       2: aload_2
       3: aload_3
       4: aload         4
       6: aconst_null
       7: aconst_null
       8: aconst_null
       9: invokestatic  #26                 // Method createServiceBuilder:(Lorg/jboss/msc/service/ServiceTarget;Ljava/lang/String;Ljava/lang/ClassLoader;Ljava/lang/String;Ljava/util/Map;Lorg/jboss/metadata/web/jboss/JBossWebMetaData;Lorg/jboss/wsf/spi/metadata/webservices/WebservicesMetaData;Lorg/jboss/wsf/spi/metadata/webservices/JBossWebservicesMetaData;)Lorg/jboss/msc/service/ServiceBuilder;
      12: areturn

  public static org.jboss.msc.service.ServiceBuilder<org.jboss.wsf.spi.publish.Context> createServiceBuilder(org.jboss.msc.service.ServiceTarget, java.lang.String, java.lang.ClassLoader, java.lang.String, java.util.Map<java.lang.String, java.lang.String>, org.jboss.metadata.web.jboss.JBossWebMetaData, org.jboss.wsf.spi.metadata.webservices.WebservicesMetaData, org.jboss.wsf.spi.metadata.webservices.JBossWebservicesMetaData);
    Code:
       0: aload_0
       1: aload_1
       2: aload_2
       3: aload_3
       4: aload         4
       6: aload         5
       8: aload         6
      10: aload         7
      12: invokestatic  #27                 // Method org/jboss/as/webservices/service/EndpointDeployService.install:(Lorg/jboss/msc/service/ServiceTarget;Ljava/lang/String;Ljava/lang/ClassLoader;Ljava/lang/String;Ljava/util/Map;Lorg/jboss/metadata/web/jboss/JBossWebMetaData;Lorg/jboss/wsf/spi/metadata/webservices/WebservicesMetaData;Lorg/jboss/wsf/spi/metadata/webservices/JBossWebservicesMetaData;)Lorg/jboss/as/server/deployment/DeploymentUnit;
      15: astore        8
      17: new           #28                 // class org/jboss/as/webservices/service/EndpointPublishService
      20: dup
      21: aload_1
      22: aload         8
      24: invokespecial #29                 // Method "<init>":(Ljava/lang/String;Lorg/jboss/as/server/deployment/DeploymentUnit;)V
      27: astore        9
      29: aload_0
      30: aload         9
      32: invokevirtual #30                 // Method getName:()Lorg/jboss/msc/service/ServiceName;
      35: aload         9
      37: invokeinterface #31,  3           // InterfaceMethod org/jboss/msc/service/ServiceTarget.addService:(Lorg/jboss/msc/service/ServiceName;Lorg/jboss/msc/service/Service;)Lorg/jboss/msc/service/ServiceBuilder;
      42: astore        10
      44: aload         10
      46: getstatic     #32                 // Field org/jboss/msc/service/ServiceBuilder$DependencyType.REQUIRED:Lorg/jboss/msc/service/ServiceBuilder$DependencyType;
      49: getstatic     #33                 // Field org/jboss/as/webservices/util/WSServices.CONFIG_SERVICE:Lorg/jboss/msc/service/ServiceName;
      52: invokeinterface #34,  3           // InterfaceMethod org/jboss/msc/service/ServiceBuilder.addDependency:(Lorg/jboss/msc/service/ServiceBuilder$DependencyType;Lorg/jboss/msc/service/ServiceName;)Lorg/jboss/msc/service/ServiceBuilder;
      57: pop
      58: aload         10
      60: getstatic     #35                 // Field org/jboss/as/web/host/WebHost.SERVICE_NAME:Lorg/jboss/msc/service/ServiceName;
      63: iconst_1
      64: anewarray     #6                  // class java/lang/String
      67: dup
      68: iconst_0
      69: aload_3
      70: aastore
      71: invokevirtual #7                  // Method org/jboss/msc/service/ServiceName.append:([Ljava/lang/String;)Lorg/jboss/msc/service/ServiceName;
      74: ldc           #14                 // class org/jboss/as/web/host/WebHost
      76: aload         9
      78: invokevirtual #36                 // Method getHostInjector:()Lorg/jboss/msc/value/InjectedValue;
      81: invokeinterface #37,  4           // InterfaceMethod org/jboss/msc/service/ServiceBuilder.addDependency:(Lorg/jboss/msc/service/ServiceName;Ljava/lang/Class;Lorg/jboss/msc/inject/Injector;)Lorg/jboss/msc/service/ServiceBuilder;
      86: pop
      87: aload         8
      89: invokestatic  #38                 // Method org/jboss/as/webservices/service/EndpointService.getServiceNamesFromDeploymentUnit:(Lorg/jboss/as/server/deployment/DeploymentUnit;)Ljava/util/List;
      92: invokeinterface #39,  1           // InterfaceMethod java/util/List.iterator:()Ljava/util/Iterator;
      97: astore        11
      99: aload         11
     101: invokeinterface #40,  1           // InterfaceMethod java/util/Iterator.hasNext:()Z
     106: ifeq          137
     109: aload         11
     111: invokeinterface #41,  1           // InterfaceMethod java/util/Iterator.next:()Ljava/lang/Object;
     116: checkcast     #42                 // class org/jboss/msc/service/ServiceName
     119: astore        12
     121: aload         10
     123: getstatic     #32                 // Field org/jboss/msc/service/ServiceBuilder$DependencyType.REQUIRED:Lorg/jboss/msc/service/ServiceBuilder$DependencyType;
     126: aload         12
     128: invokeinterface #34,  3           // InterfaceMethod org/jboss/msc/service/ServiceBuilder.addDependency:(Lorg/jboss/msc/service/ServiceBuilder$DependencyType;Lorg/jboss/msc/service/ServiceName;)Lorg/jboss/msc/service/ServiceBuilder;
     133: pop
     134: goto          99
     137: aload         10
     139: areturn

  public static void install(org.jboss.msc.service.ServiceTarget, java.lang.String, java.lang.ClassLoader, java.lang.String, java.util.Map<java.lang.String, java.lang.String>);
    Code:
       0: aload_0
       1: aload_1
       2: aload_2
       3: aload_3
       4: aload         4
       6: aconst_null
       7: aconst_null
       8: aconst_null
       9: invokestatic  #43                 // Method install:(Lorg/jboss/msc/service/ServiceTarget;Ljava/lang/String;Ljava/lang/ClassLoader;Ljava/lang/String;Ljava/util/Map;Lorg/jboss/metadata/web/jboss/JBossWebMetaData;Lorg/jboss/wsf/spi/metadata/webservices/WebservicesMetaData;Lorg/jboss/wsf/spi/metadata/webservices/JBossWebservicesMetaData;)V
      12: return

  public static void install(org.jboss.msc.service.ServiceTarget, java.lang.String, java.lang.ClassLoader, java.lang.String, java.util.Map<java.lang.String, java.lang.String>, org.jboss.metadata.web.jboss.JBossWebMetaData, org.jboss.wsf.spi.metadata.webservices.WebservicesMetaData, org.jboss.wsf.spi.metadata.webservices.JBossWebservicesMetaData);
    Code:
       0: aload_0
       1: aload_1
       2: aload_2
       3: aload_3
       4: aload         4
       6: aload         5
       8: aload         6
      10: aload         7
      12: invokestatic  #26                 // Method createServiceBuilder:(Lorg/jboss/msc/service/ServiceTarget;Ljava/lang/String;Ljava/lang/ClassLoader;Ljava/lang/String;Ljava/util/Map;Lorg/jboss/metadata/web/jboss/JBossWebMetaData;Lorg/jboss/wsf/spi/metadata/webservices/WebservicesMetaData;Lorg/jboss/wsf/spi/metadata/webservices/JBossWebservicesMetaData;)Lorg/jboss/msc/service/ServiceBuilder;
      15: astore        8
      17: aload         8
      19: getstatic     #44                 // Field org/jboss/msc/service/ServiceController$Mode.ACTIVE:Lorg/jboss/msc/service/ServiceController$Mode;
      22: invokeinterface #45,  2           // InterfaceMethod org/jboss/msc/service/ServiceBuilder.setInitialMode:(Lorg/jboss/msc/service/ServiceController$Mode;)Lorg/jboss/msc/service/ServiceBuilder;
      27: pop
      28: aload         8
      30: invokeinterface #46,  1           // InterfaceMethod org/jboss/msc/service/ServiceBuilder.install:()Lorg/jboss/msc/service/ServiceController;
      35: pop
      36: return

  public java.lang.Object getValue() throws java.lang.IllegalStateException, java.lang.IllegalArgumentException;
    Code:
       0: aload_0
       1: invokevirtual #47                 // Method getValue:()Lorg/jboss/wsf/spi/publish/Context;
       4: areturn
}
