Compiled from "PolicyBeanDefinitionParser.java"
public class org.apache.cxf.ws.policy.spring.PolicyBeanDefinitionParser extends org.springframework.beans.factory.xml.AbstractSingleBeanDefinitionParser {
  public org.apache.cxf.ws.policy.spring.PolicyBeanDefinitionParser();
    Code:
       0: aload_0
       1: invokespecial #1                  // Method org/springframework/beans/factory/xml/AbstractSingleBeanDefinitionParser."<init>":()V
       4: return

  protected void doParse(org.w3c.dom.Element, org.springframework.beans.factory.xml.ParserContext, org.springframework.beans.factory.support.BeanDefinitionBuilder);
    Code:
       0: aload_3
       1: ldc           #2                  // String element
       3: aload_1
       4: invokevirtual #3                  // Method org/springframework/beans/factory/support/BeanDefinitionBuilder.addPropertyValue:(Ljava/lang/String;Ljava/lang/Object;)Lorg/springframework/beans/factory/support/BeanDefinitionBuilder;
       7: pop
       8: return

  protected java.lang.String resolveId(org.w3c.dom.Element, org.springframework.beans.factory.support.AbstractBeanDefinition, org.springframework.beans.factory.xml.ParserContext) throws org.springframework.beans.factory.BeanDefinitionStoreException;
    Code:
       0: aload_1
       1: ldc           #4                  // String http://docs.oasis-open.org/wss/2004/01/oasis-200401-wss-wssecurity-utility-1.0.xsd
       3: ldc           #5                  // String Id
       5: invokeinterface #6,  3            // InterfaceMethod org/w3c/dom/Element.getAttributeNS:(Ljava/lang/String;Ljava/lang/String;)Ljava/lang/String;
      10: areturn

  protected java.lang.Class<?> getBeanClass(org.w3c.dom.Element);
    Code:
       0: ldc_w         #7                  // class org/apache/cxf/ws/policy/PolicyBean
       3: areturn
}
