Compiled from "CountOptions.java"
public class com.mongodb.client.model.CountOptions {
  private org.bson.conversions.Bson hint;

  private java.lang.String hintString;

  private int limit;

  private int skip;

  private long maxTimeMS;

  private com.mongodb.client.model.Collation collation;

  public com.mongodb.client.model.CountOptions();
    Code:
       0: aload_0
       1: invokespecial #1                  // Method java/lang/Object."<init>":()V
       4: return

  public org.bson.conversions.Bson getHint();
    Code:
       0: aload_0
       1: getfield      #2                  // Field hint:Lorg/bson/conversions/Bson;
       4: areturn

  public java.lang.String getHintString();
    Code:
       0: aload_0
       1: getfield      #3                  // Field hintString:Ljava/lang/String;
       4: areturn

  public com.mongodb.client.model.CountOptions hint(org.bson.conversions.Bson);
    Code:
       0: aload_0
       1: aload_1
       2: putfield      #2                  // Field hint:Lorg/bson/conversions/Bson;
       5: aload_0
       6: areturn

  public com.mongodb.client.model.CountOptions hintString(java.lang.String);
    Code:
       0: aload_0
       1: aload_1
       2: putfield      #3                  // Field hintString:Ljava/lang/String;
       5: aload_0
       6: areturn

  public int getLimit();
    Code:
       0: aload_0
       1: getfield      #4                  // Field limit:I
       4: ireturn

  public com.mongodb.client.model.CountOptions limit(int);
    Code:
       0: aload_0
       1: iload_1
       2: putfield      #4                  // Field limit:I
       5: aload_0
       6: areturn

  public int getSkip();
    Code:
       0: aload_0
       1: getfield      #5                  // Field skip:I
       4: ireturn

  public com.mongodb.client.model.CountOptions skip(int);
    Code:
       0: aload_0
       1: iload_1
       2: putfield      #5                  // Field skip:I
       5: aload_0
       6: areturn

  public long getMaxTime(java.util.concurrent.TimeUnit);
    Code:
       0: ldc           #6                  // String timeUnit
       2: aload_1
       3: invokestatic  #7                  // Method com/mongodb/assertions/Assertions.notNull:(Ljava/lang/String;Ljava/lang/Object;)Ljava/lang/Object;
       6: pop
       7: aload_1
       8: aload_0
       9: getfield      #8                  // Field maxTimeMS:J
      12: getstatic     #9                  // Field java/util/concurrent/TimeUnit.MILLISECONDS:Ljava/util/concurrent/TimeUnit;
      15: invokevirtual #10                 // Method java/util/concurrent/TimeUnit.convert:(JLjava/util/concurrent/TimeUnit;)J
      18: lreturn

  public com.mongodb.client.model.CountOptions maxTime(long, java.util.concurrent.TimeUnit);
    Code:
       0: ldc           #6                  // String timeUnit
       2: aload_3
       3: invokestatic  #7                  // Method com/mongodb/assertions/Assertions.notNull:(Ljava/lang/String;Ljava/lang/Object;)Ljava/lang/Object;
       6: pop
       7: aload_0
       8: getstatic     #9                  // Field java/util/concurrent/TimeUnit.MILLISECONDS:Ljava/util/concurrent/TimeUnit;
      11: lload_1
      12: aload_3
      13: invokevirtual #10                 // Method java/util/concurrent/TimeUnit.convert:(JLjava/util/concurrent/TimeUnit;)J
      16: putfield      #8                  // Field maxTimeMS:J
      19: aload_0
      20: areturn

  public com.mongodb.client.model.Collation getCollation();
    Code:
       0: aload_0
       1: getfield      #11                 // Field collation:Lcom/mongodb/client/model/Collation;
       4: areturn

  public com.mongodb.client.model.CountOptions collation(com.mongodb.client.model.Collation);
    Code:
       0: aload_0
       1: aload_1
       2: putfield      #11                 // Field collation:Lcom/mongodb/client/model/Collation;
       5: aload_0
       6: areturn
}
