Compiled from "CreateViewOptions.java"
public class com.mongodb.client.model.CreateViewOptions {
  private com.mongodb.client.model.Collation collation;

  public com.mongodb.client.model.CreateViewOptions();
    Code:
       0: aload_0
       1: invokespecial #1                  // Method java/lang/Object."<init>":()V
       4: return

  public com.mongodb.client.model.Collation getCollation();
    Code:
       0: aload_0
       1: getfield      #2                  // Field collation:Lcom/mongodb/client/model/Collation;
       4: areturn

  public com.mongodb.client.model.CreateViewOptions collation(com.mongodb.client.model.Collation);
    Code:
       0: aload_0
       1: aload_1
       2: putfield      #2                  // Field collation:Lcom/mongodb/client/model/Collation;
       5: aload_0
       6: areturn
}
