Compiled from "Filters.java"
final class com.mongodb.client.model.Filters$SimpleFilter implements org.bson.conversions.Bson {
  private final java.lang.String fieldName;

  private final org.bson.BsonValue value;

  private com.mongodb.client.model.Filters$SimpleFilter(java.lang.String, org.bson.BsonValue);
    Code:
       0: aload_0
       1: invokespecial #2                  // Method java/lang/Object."<init>":()V
       4: aload_0
       5: ldc           #3                  // String fieldName
       7: aload_1
       8: invokestatic  #4                  // Method com/mongodb/assertions/Assertions.notNull:(Ljava/lang/String;Ljava/lang/Object;)Ljava/lang/Object;
      11: checkcast     #5                  // class java/lang/String
      14: putfield      #6                  // Field fieldName:Ljava/lang/String;
      17: aload_0
      18: ldc           #7                  // String value
      20: aload_2
      21: invokestatic  #4                  // Method com/mongodb/assertions/Assertions.notNull:(Ljava/lang/String;Ljava/lang/Object;)Ljava/lang/Object;
      24: checkcast     #8                  // class org/bson/BsonValue
      27: putfield      #9                  // Field value:Lorg/bson/BsonValue;
      30: return

  public <TDocument> org.bson.BsonDocument toBsonDocument(java.lang.Class<TDocument>, org.bson.codecs.configuration.CodecRegistry);
    Code:
       0: new           #10                 // class org/bson/BsonDocument
       3: dup
       4: aload_0
       5: getfield      #6                  // Field fieldName:Ljava/lang/String;
       8: aload_0
       9: getfield      #9                  // Field value:Lorg/bson/BsonValue;
      12: invokespecial #11                 // Method org/bson/BsonDocument."<init>":(Ljava/lang/String;Lorg/bson/BsonValue;)V
      15: areturn

  public java.lang.String toString();
    Code:
       0: aload_0
       1: getfield      #6                  // Field fieldName:Ljava/lang/String;
       4: ldc           #12                 // String $eq
       6: aload_0
       7: getfield      #9                  // Field value:Lorg/bson/BsonValue;
      10: invokestatic  #13                 // Method com/mongodb/client/model/Filters.access$100:(Ljava/lang/String;Ljava/lang/String;Ljava/lang/Object;)Ljava/lang/String;
      13: areturn

  com.mongodb.client.model.Filters$SimpleFilter(java.lang.String, org.bson.BsonValue, com.mongodb.client.model.Filters$1);
    Code:
       0: aload_0
       1: aload_1
       2: aload_2
       3: invokespecial #1                  // Method "<init>":(Ljava/lang/String;Lorg/bson/BsonValue;)V
       6: return
}
