Compiled from "Updates.java"
class com.mongodb.client.model.Updates$PushUpdate<TItem> extends com.mongodb.client.model.Updates$WithEachUpdate<TItem> {
  private final com.mongodb.client.model.PushOptions options;

  com.mongodb.client.model.Updates$PushUpdate(java.lang.String, java.util.List<TItem>, com.mongodb.client.model.PushOptions);
    Code:
       0: aload_0
       1: aload_1
       2: aload_2
       3: ldc           #1                  // String $push
       5: invokespecial #2                  // Method com/mongodb/client/model/Updates$WithEachUpdate."<init>":(Ljava/lang/String;Ljava/util/List;Ljava/lang/String;)V
       8: aload_0
       9: ldc           #3                  // String options
      11: aload_3
      12: invokestatic  #4                  // Method com/mongodb/assertions/Assertions.notNull:(Ljava/lang/String;Ljava/lang/Object;)Ljava/lang/Object;
      15: checkcast     #5                  // class com/mongodb/client/model/PushOptions
      18: putfield      #6                  // Field options:Lcom/mongodb/client/model/PushOptions;
      21: return

  protected <TDocument> void writeAdditionalFields(org.bson.BsonDocumentWriter, java.lang.Class<TDocument>, org.bson.codecs.configuration.CodecRegistry);
    Code:
       0: aload_0
       1: getfield      #6                  // Field options:Lcom/mongodb/client/model/PushOptions;
       4: invokevirtual #7                  // Method com/mongodb/client/model/PushOptions.getPosition:()Ljava/lang/Integer;
       7: ifnull        26
      10: aload_1
      11: ldc           #8                  // String $position
      13: aload_0
      14: getfield      #6                  // Field options:Lcom/mongodb/client/model/PushOptions;
      17: invokevirtual #7                  // Method com/mongodb/client/model/PushOptions.getPosition:()Ljava/lang/Integer;
      20: invokevirtual #9                  // Method java/lang/Integer.intValue:()I
      23: invokevirtual #10                 // Method org/bson/BsonDocumentWriter.writeInt32:(Ljava/lang/String;I)V
      26: aload_0
      27: getfield      #6                  // Field options:Lcom/mongodb/client/model/PushOptions;
      30: invokevirtual #11                 // Method com/mongodb/client/model/PushOptions.getSlice:()Ljava/lang/Integer;
      33: ifnull        52
      36: aload_1
      37: ldc           #12                 // String $slice
      39: aload_0
      40: getfield      #6                  // Field options:Lcom/mongodb/client/model/PushOptions;
      43: invokevirtual #11                 // Method com/mongodb/client/model/PushOptions.getSlice:()Ljava/lang/Integer;
      46: invokevirtual #9                  // Method java/lang/Integer.intValue:()I
      49: invokevirtual #10                 // Method org/bson/BsonDocumentWriter.writeInt32:(Ljava/lang/String;I)V
      52: aload_0
      53: getfield      #6                  // Field options:Lcom/mongodb/client/model/PushOptions;
      56: invokevirtual #13                 // Method com/mongodb/client/model/PushOptions.getSort:()Ljava/lang/Integer;
      59: ifnull        81
      62: aload_1
      63: ldc           #14                 // String $sort
      65: aload_0
      66: getfield      #6                  // Field options:Lcom/mongodb/client/model/PushOptions;
      69: invokevirtual #13                 // Method com/mongodb/client/model/PushOptions.getSort:()Ljava/lang/Integer;
      72: invokevirtual #9                  // Method java/lang/Integer.intValue:()I
      75: invokevirtual #10                 // Method org/bson/BsonDocumentWriter.writeInt32:(Ljava/lang/String;I)V
      78: goto          109
      81: aload_0
      82: getfield      #6                  // Field options:Lcom/mongodb/client/model/PushOptions;
      85: invokevirtual #15                 // Method com/mongodb/client/model/PushOptions.getSortDocument:()Lorg/bson/conversions/Bson;
      88: ifnull        109
      91: aload_1
      92: ldc           #14                 // String $sort
      94: invokevirtual #16                 // Method org/bson/BsonDocumentWriter.writeName:(Ljava/lang/String;)V
      97: aload_1
      98: aload_0
      99: getfield      #6                  // Field options:Lcom/mongodb/client/model/PushOptions;
     102: invokevirtual #15                 // Method com/mongodb/client/model/PushOptions.getSortDocument:()Lorg/bson/conversions/Bson;
     105: aload_3
     106: invokestatic  #17                 // Method com/mongodb/client/model/BuildersHelper.encodeValue:(Lorg/bson/BsonDocumentWriter;Ljava/lang/Object;Lorg/bson/codecs/configuration/CodecRegistry;)V
     109: return

  protected java.lang.String additionalFieldsToString();
    Code:
       0: new           #18                 // class java/lang/StringBuilder
       3: dup
       4: invokespecial #19                 // Method java/lang/StringBuilder."<init>":()V
       7: ldc           #20                 // String , options=
       9: invokevirtual #21                 // Method java/lang/StringBuilder.append:(Ljava/lang/String;)Ljava/lang/StringBuilder;
      12: aload_0
      13: getfield      #6                  // Field options:Lcom/mongodb/client/model/PushOptions;
      16: invokevirtual #22                 // Method java/lang/StringBuilder.append:(Ljava/lang/Object;)Ljava/lang/StringBuilder;
      19: invokevirtual #23                 // Method java/lang/StringBuilder.toString:()Ljava/lang/String;
      22: areturn
}
