Compiled from "ResourceHandlerRegistration.java"
public class org.springframework.web.servlet.config.annotation.ResourceHandlerRegistration {
  private final java.lang.String[] pathPatterns;

  private final java.util.List<java.lang.String> locationValues;

  private java.lang.Integer cachePeriod;

  private org.springframework.http.CacheControl cacheControl;

  private org.springframework.web.servlet.config.annotation.ResourceChainRegistration resourceChainRegistration;

  public org.springframework.web.servlet.config.annotation.ResourceHandlerRegistration(java.lang.String...);
    Code:
       0: aload_0
       1: invokespecial #1                  // Method java/lang/Object."<init>":()V
       4: aload_0
       5: new           #2                  // class java/util/ArrayList
       8: dup
       9: invokespecial #3                  // Method java/util/ArrayList."<init>":()V
      12: putfield      #4                  // Field locationValues:Ljava/util/List;
      15: aload_1
      16: ldc           #5                  // String At least one path pattern is required for resource handling.
      18: invokestatic  #6                  // Method org/springframework/util/Assert.notEmpty:([Ljava/lang/Object;Ljava/lang/String;)V
      21: aload_0
      22: aload_1
      23: putfield      #7                  // Field pathPatterns:[Ljava/lang/String;
      26: return

  public org.springframework.web.servlet.config.annotation.ResourceHandlerRegistration addResourceLocations(java.lang.String...);
    Code:
       0: aload_0
       1: getfield      #4                  // Field locationValues:Ljava/util/List;
       4: aload_1
       5: invokestatic  #8                  // Method java/util/Arrays.asList:([Ljava/lang/Object;)Ljava/util/List;
       8: invokeinterface #9,  2            // InterfaceMethod java/util/List.addAll:(Ljava/util/Collection;)Z
      13: pop
      14: aload_0
      15: areturn

  public org.springframework.web.servlet.config.annotation.ResourceHandlerRegistration setCachePeriod(java.lang.Integer);
    Code:
       0: aload_0
       1: aload_1
       2: putfield      #10                 // Field cachePeriod:Ljava/lang/Integer;
       5: aload_0
       6: areturn

  public org.springframework.web.servlet.config.annotation.ResourceHandlerRegistration setCacheControl(org.springframework.http.CacheControl);
    Code:
       0: aload_0
       1: aload_1
       2: putfield      #11                 // Field cacheControl:Lorg/springframework/http/CacheControl;
       5: aload_0
       6: areturn

  public org.springframework.web.servlet.config.annotation.ResourceChainRegistration resourceChain(boolean);
    Code:
       0: aload_0
       1: new           #12                 // class org/springframework/web/servlet/config/annotation/ResourceChainRegistration
       4: dup
       5: iload_1
       6: invokespecial #13                 // Method org/springframework/web/servlet/config/annotation/ResourceChainRegistration."<init>":(Z)V
       9: putfield      #14                 // Field resourceChainRegistration:Lorg/springframework/web/servlet/config/annotation/ResourceChainRegistration;
      12: aload_0
      13: getfield      #14                 // Field resourceChainRegistration:Lorg/springframework/web/servlet/config/annotation/ResourceChainRegistration;
      16: areturn

  public org.springframework.web.servlet.config.annotation.ResourceChainRegistration resourceChain(boolean, org.springframework.cache.Cache);
    Code:
       0: aload_0
       1: new           #12                 // class org/springframework/web/servlet/config/annotation/ResourceChainRegistration
       4: dup
       5: iload_1
       6: aload_2
       7: invokespecial #15                 // Method org/springframework/web/servlet/config/annotation/ResourceChainRegistration."<init>":(ZLorg/springframework/cache/Cache;)V
      10: putfield      #14                 // Field resourceChainRegistration:Lorg/springframework/web/servlet/config/annotation/ResourceChainRegistration;
      13: aload_0
      14: getfield      #14                 // Field resourceChainRegistration:Lorg/springframework/web/servlet/config/annotation/ResourceChainRegistration;
      17: areturn

  protected java.lang.String[] getPathPatterns();
    Code:
       0: aload_0
       1: getfield      #7                  // Field pathPatterns:[Ljava/lang/String;
       4: areturn

  protected org.springframework.web.servlet.resource.ResourceHttpRequestHandler getRequestHandler();
    Code:
       0: new           #16                 // class org/springframework/web/servlet/resource/ResourceHttpRequestHandler
       3: dup
       4: invokespecial #17                 // Method org/springframework/web/servlet/resource/ResourceHttpRequestHandler."<init>":()V
       7: astore_1
       8: aload_0
       9: getfield      #14                 // Field resourceChainRegistration:Lorg/springframework/web/servlet/config/annotation/ResourceChainRegistration;
      12: ifnull        37
      15: aload_1
      16: aload_0
      17: getfield      #14                 // Field resourceChainRegistration:Lorg/springframework/web/servlet/config/annotation/ResourceChainRegistration;
      20: invokevirtual #18                 // Method org/springframework/web/servlet/config/annotation/ResourceChainRegistration.getResourceResolvers:()Ljava/util/List;
      23: invokevirtual #19                 // Method org/springframework/web/servlet/resource/ResourceHttpRequestHandler.setResourceResolvers:(Ljava/util/List;)V
      26: aload_1
      27: aload_0
      28: getfield      #14                 // Field resourceChainRegistration:Lorg/springframework/web/servlet/config/annotation/ResourceChainRegistration;
      31: invokevirtual #20                 // Method org/springframework/web/servlet/config/annotation/ResourceChainRegistration.getResourceTransformers:()Ljava/util/List;
      34: invokevirtual #21                 // Method org/springframework/web/servlet/resource/ResourceHttpRequestHandler.setResourceTransformers:(Ljava/util/List;)V
      37: aload_1
      38: aload_0
      39: getfield      #4                  // Field locationValues:Ljava/util/List;
      42: invokevirtual #22                 // Method org/springframework/web/servlet/resource/ResourceHttpRequestHandler.setLocationValues:(Ljava/util/List;)V
      45: aload_0
      46: getfield      #11                 // Field cacheControl:Lorg/springframework/http/CacheControl;
      49: ifnull        63
      52: aload_1
      53: aload_0
      54: getfield      #11                 // Field cacheControl:Lorg/springframework/http/CacheControl;
      57: invokevirtual #23                 // Method org/springframework/web/servlet/resource/ResourceHttpRequestHandler.setCacheControl:(Lorg/springframework/http/CacheControl;)V
      60: goto          81
      63: aload_0
      64: getfield      #10                 // Field cachePeriod:Ljava/lang/Integer;
      67: ifnull        81
      70: aload_1
      71: aload_0
      72: getfield      #10                 // Field cachePeriod:Ljava/lang/Integer;
      75: invokevirtual #24                 // Method java/lang/Integer.intValue:()I
      78: invokevirtual #25                 // Method org/springframework/web/servlet/resource/ResourceHttpRequestHandler.setCacheSeconds:(I)V
      81: aload_1
      82: areturn
}
