Compiled from "RebaseImplementationTarget.java"
public class org.modelmapper.internal.bytebuddy.dynamic.scaffold.inline.RebaseImplementationTarget$RebasedMethodInvocation extends org.modelmapper.internal.bytebuddy.implementation.Implementation$SpecialMethodInvocation$AbstractBase {
  private final org.modelmapper.internal.bytebuddy.description.method.MethodDescription methodDescription;

  private final org.modelmapper.internal.bytebuddy.description.type.TypeDescription instrumentedType;

  private final org.modelmapper.internal.bytebuddy.implementation.bytecode.StackManipulation stackManipulation;

  protected org.modelmapper.internal.bytebuddy.dynamic.scaffold.inline.RebaseImplementationTarget$RebasedMethodInvocation(org.modelmapper.internal.bytebuddy.description.method.MethodDescription, org.modelmapper.internal.bytebuddy.description.type.TypeDescription, org.modelmapper.internal.bytebuddy.implementation.bytecode.StackManipulation);
    Code:
       0: aload_0
       1: invokespecial #44                 // Method org/modelmapper/internal/bytebuddy/implementation/Implementation$SpecialMethodInvocation$AbstractBase."<init>":()V
       4: aload_0
       5: aload_1
       6: putfield      #46                 // Field methodDescription:Lorg/modelmapper/internal/bytebuddy/description/method/MethodDescription;
       9: aload_0
      10: aload_2
      11: putfield      #48                 // Field instrumentedType:Lorg/modelmapper/internal/bytebuddy/description/type/TypeDescription;
      14: aload_0
      15: aload_3
      16: putfield      #50                 // Field stackManipulation:Lorg/modelmapper/internal/bytebuddy/implementation/bytecode/StackManipulation;
      19: return

  protected static org.modelmapper.internal.bytebuddy.implementation.Implementation$SpecialMethodInvocation of(org.modelmapper.internal.bytebuddy.description.method.MethodDescription, org.modelmapper.internal.bytebuddy.description.type.TypeDescription, org.modelmapper.internal.bytebuddy.implementation.bytecode.StackManipulation);
    Code:
       0: aload_0
       1: invokeinterface #60,  1           // InterfaceMethod org/modelmapper/internal/bytebuddy/description/method/MethodDescription.isStatic:()Z
       6: ifeq          16
       9: aload_0
      10: invokestatic  #64                 // Method org/modelmapper/internal/bytebuddy/implementation/bytecode/member/MethodInvocation.invoke:(Lorg/modelmapper/internal/bytebuddy/description/method/MethodDescription;)Lorg/modelmapper/internal/bytebuddy/implementation/bytecode/member/MethodInvocation$WithImplicitInvocationTargetType;
      13: goto          26
      16: aload_0
      17: invokestatic  #64                 // Method org/modelmapper/internal/bytebuddy/implementation/bytecode/member/MethodInvocation.invoke:(Lorg/modelmapper/internal/bytebuddy/description/method/MethodDescription;)Lorg/modelmapper/internal/bytebuddy/implementation/bytecode/member/MethodInvocation$WithImplicitInvocationTargetType;
      20: aload_1
      21: invokeinterface #68,  2           // InterfaceMethod org/modelmapper/internal/bytebuddy/implementation/bytecode/member/MethodInvocation$WithImplicitInvocationTargetType.special:(Lorg/modelmapper/internal/bytebuddy/description/type/TypeDescription;)Lorg/modelmapper/internal/bytebuddy/implementation/bytecode/StackManipulation;
      26: astore_3
      27: aload_3
      28: invokeinterface #71,  1           // InterfaceMethod org/modelmapper/internal/bytebuddy/implementation/bytecode/StackManipulation.isValid:()Z
      33: ifeq          67
      36: new           #2                  // class org/modelmapper/internal/bytebuddy/dynamic/scaffold/inline/RebaseImplementationTarget$RebasedMethodInvocation
      39: dup
      40: aload_0
      41: aload_1
      42: new           #23                 // class org/modelmapper/internal/bytebuddy/implementation/bytecode/StackManipulation$Compound
      45: dup
      46: iconst_2
      47: anewarray     #20                 // class org/modelmapper/internal/bytebuddy/implementation/bytecode/StackManipulation
      50: dup
      51: iconst_0
      52: aload_2
      53: aastore
      54: dup
      55: iconst_1
      56: aload_3
      57: aastore
      58: invokespecial #74                 // Method org/modelmapper/internal/bytebuddy/implementation/bytecode/StackManipulation$Compound."<init>":([Lorg/modelmapper/internal/bytebuddy/implementation/bytecode/StackManipulation;)V
      61: invokespecial #76                 // Method "<init>":(Lorg/modelmapper/internal/bytebuddy/description/method/MethodDescription;Lorg/modelmapper/internal/bytebuddy/description/type/TypeDescription;Lorg/modelmapper/internal/bytebuddy/implementation/bytecode/StackManipulation;)V
      64: goto          70
      67: getstatic     #80                 // Field org/modelmapper/internal/bytebuddy/implementation/Implementation$SpecialMethodInvocation$Illegal.INSTANCE:Lorg/modelmapper/internal/bytebuddy/implementation/Implementation$SpecialMethodInvocation$Illegal;
      70: areturn

  public org.modelmapper.internal.bytebuddy.description.method.MethodDescription getMethodDescription();
    Code:
       0: aload_0
       1: getfield      #46                 // Field methodDescription:Lorg/modelmapper/internal/bytebuddy/description/method/MethodDescription;
       4: areturn

  public org.modelmapper.internal.bytebuddy.description.type.TypeDescription getTypeDescription();
    Code:
       0: aload_0
       1: getfield      #48                 // Field instrumentedType:Lorg/modelmapper/internal/bytebuddy/description/type/TypeDescription;
       4: areturn

  public org.modelmapper.internal.bytebuddy.implementation.bytecode.StackManipulation$Size apply(org.modelmapper.internal.asm.MethodVisitor, org.modelmapper.internal.bytebuddy.implementation.Implementation$Context);
    Code:
       0: aload_0
       1: getfield      #50                 // Field stackManipulation:Lorg/modelmapper/internal/bytebuddy/implementation/bytecode/StackManipulation;
       4: aload_1
       5: aload_2
       6: invokeinterface #90,  3           // InterfaceMethod org/modelmapper/internal/bytebuddy/implementation/bytecode/StackManipulation.apply:(Lorg/modelmapper/internal/asm/MethodVisitor;Lorg/modelmapper/internal/bytebuddy/implementation/Implementation$Context;)Lorg/modelmapper/internal/bytebuddy/implementation/bytecode/StackManipulation$Size;
      11: areturn
}
