Compiled from "Metrics.java"
public class org.apache.pulsar.common.stats.Metrics {
  final java.util.Map<java.lang.String, java.lang.Object> metrics;

  final java.util.Map<java.lang.String, java.lang.String> dimensions;

  public org.apache.pulsar.common.stats.Metrics();
    Code:
       0: aload_0
       1: invokespecial #1                  // Method java/lang/Object."<init>":()V
       4: aload_0
       5: new           #2                  // class java/util/TreeMap
       8: dup
       9: invokespecial #3                  // Method java/util/TreeMap."<init>":()V
      12: putfield      #4                  // Field metrics:Ljava/util/Map;
      15: aload_0
      16: new           #5                  // class java/util/HashMap
      19: dup
      20: invokespecial #6                  // Method java/util/HashMap."<init>":()V
      23: putfield      #7                  // Field dimensions:Ljava/util/Map;
      26: return

  protected org.apache.pulsar.common.stats.Metrics(java.util.Map<java.lang.String, java.lang.String>);
    Code:
       0: aload_0
       1: invokespecial #1                  // Method java/lang/Object."<init>":()V
       4: aload_0
       5: new           #2                  // class java/util/TreeMap
       8: dup
       9: invokespecial #3                  // Method java/util/TreeMap."<init>":()V
      12: putfield      #4                  // Field metrics:Ljava/util/Map;
      15: aload_0
      16: aload_1
      17: putfield      #7                  // Field dimensions:Ljava/util/Map;
      20: return

  public static org.apache.pulsar.common.stats.Metrics create(java.util.Map<java.lang.String, java.lang.String>);
    Code:
       0: new           #2                  // class java/util/TreeMap
       3: dup
       4: invokespecial #3                  // Method java/util/TreeMap."<init>":()V
       7: astore_1
       8: aload_1
       9: aload_0
      10: invokeinterface #8,  2            // InterfaceMethod java/util/Map.putAll:(Ljava/util/Map;)V
      15: new           #9                  // class org/apache/pulsar/common/stats/Metrics
      18: dup
      19: aload_1
      20: invokestatic  #10                 // Method java/util/Collections.unmodifiableMap:(Ljava/util/Map;)Ljava/util/Map;
      23: invokespecial #11                 // Method "<init>":(Ljava/util/Map;)V
      26: areturn

  public void put(java.lang.String, java.lang.Object);
    Code:
       0: aload_0
       1: getfield      #4                  // Field metrics:Ljava/util/Map;
       4: aload_1
       5: aload_2
       6: invokeinterface #12,  3           // InterfaceMethod java/util/Map.put:(Ljava/lang/Object;Ljava/lang/Object;)Ljava/lang/Object;
      11: pop
      12: return

  public java.util.Map<java.lang.String, java.lang.Object> getMetrics();
    Code:
       0: aload_0
       1: getfield      #4                  // Field metrics:Ljava/util/Map;
       4: invokestatic  #10                 // Method java/util/Collections.unmodifiableMap:(Ljava/util/Map;)Ljava/util/Map;
       7: areturn

  public void putAll(java.util.Map<java.lang.String, java.lang.Object>);
    Code:
       0: aload_0
       1: getfield      #4                  // Field metrics:Ljava/util/Map;
       4: aload_1
       5: invokeinterface #8,  2            // InterfaceMethod java/util/Map.putAll:(Ljava/util/Map;)V
      10: return

  public java.util.Map<java.lang.String, java.lang.String> getDimensions();
    Code:
       0: aload_0
       1: getfield      #7                  // Field dimensions:Ljava/util/Map;
       4: areturn

  public java.lang.String getDimension(java.lang.String);
    Code:
       0: aload_0
       1: getfield      #7                  // Field dimensions:Ljava/util/Map;
       4: aload_1
       5: invokeinterface #13,  2           // InterfaceMethod java/util/Map.get:(Ljava/lang/Object;)Ljava/lang/Object;
      10: checkcast     #14                 // class java/lang/String
      13: areturn

  public int hashCode();
    Code:
       0: aload_0
       1: getfield      #7                  // Field dimensions:Ljava/util/Map;
       4: invokestatic  #15                 // Method java/util/Objects.hashCode:(Ljava/lang/Object;)I
       7: ireturn

  public boolean equals(java.lang.Object);
    Code:
       0: aload_1
       1: instanceof    #9                  // class org/apache/pulsar/common/stats/Metrics
       4: ifeq          28
       7: aload_0
       8: getfield      #7                  // Field dimensions:Ljava/util/Map;
      11: aload_1
      12: checkcast     #9                  // class org/apache/pulsar/common/stats/Metrics
      15: getfield      #7                  // Field dimensions:Ljava/util/Map;
      18: invokestatic  #16                 // Method java/util/Objects.equals:(Ljava/lang/Object;Ljava/lang/Object;)Z
      21: ifeq          28
      24: iconst_1
      25: goto          29
      28: iconst_0
      29: ireturn

  public java.lang.String toString();
    Code:
       0: ldc           #17                 // String dimensions=[%s], metrics=[%s]
       2: iconst_2
       3: anewarray     #18                 // class java/lang/Object
       6: dup
       7: iconst_0
       8: aload_0
       9: getfield      #7                  // Field dimensions:Ljava/util/Map;
      12: aastore
      13: dup
      14: iconst_1
      15: aload_0
      16: getfield      #4                  // Field metrics:Ljava/util/Map;
      19: aastore
      20: invokestatic  #19                 // Method java/lang/String.format:(Ljava/lang/String;[Ljava/lang/Object;)Ljava/lang/String;
      23: areturn
}
