Compiled from "BackgroundImage.java"
public final class javafx.scene.layout.BackgroundImage {
  final javafx.scene.image.Image image;

  final javafx.scene.layout.BackgroundRepeat repeatX;

  final javafx.scene.layout.BackgroundRepeat repeatY;

  final javafx.scene.layout.BackgroundPosition position;

  final javafx.scene.layout.BackgroundSize size;

  java.lang.Boolean opaque;

  private final int hash;

  public final javafx.scene.image.Image getImage();
    Code:
       0: aload_0
       1: getfield      #1                  // Field image:Ljavafx/scene/image/Image;
       4: areturn

  public final javafx.scene.layout.BackgroundRepeat getRepeatX();
    Code:
       0: aload_0
       1: getfield      #2                  // Field repeatX:Ljavafx/scene/layout/BackgroundRepeat;
       4: areturn

  public final javafx.scene.layout.BackgroundRepeat getRepeatY();
    Code:
       0: aload_0
       1: getfield      #3                  // Field repeatY:Ljavafx/scene/layout/BackgroundRepeat;
       4: areturn

  public final javafx.scene.layout.BackgroundPosition getPosition();
    Code:
       0: aload_0
       1: getfield      #4                  // Field position:Ljavafx/scene/layout/BackgroundPosition;
       4: areturn

  public final javafx.scene.layout.BackgroundSize getSize();
    Code:
       0: aload_0
       1: getfield      #5                  // Field size:Ljavafx/scene/layout/BackgroundSize;
       4: areturn

  public javafx.scene.layout.BackgroundImage(javafx.scene.image.Image, javafx.scene.layout.BackgroundRepeat, javafx.scene.layout.BackgroundRepeat, javafx.scene.layout.BackgroundPosition, javafx.scene.layout.BackgroundSize);
    Code:
       0: aload_0
       1: invokespecial #6                  // Method java/lang/Object."<init>":()V
       4: aload_0
       5: aconst_null
       6: putfield      #7                  // Field opaque:Ljava/lang/Boolean;
       9: aload_1
      10: ifnonnull     23
      13: new           #8                  // class java/lang/NullPointerException
      16: dup
      17: ldc           #9                  // String Image cannot be null
      19: invokespecial #10                 // Method java/lang/NullPointerException."<init>":(Ljava/lang/String;)V
      22: athrow
      23: aload_0
      24: aload_1
      25: putfield      #1                  // Field image:Ljavafx/scene/image/Image;
      28: aload_0
      29: aload_2
      30: ifnonnull     39
      33: getstatic     #11                 // Field javafx/scene/layout/BackgroundRepeat.REPEAT:Ljavafx/scene/layout/BackgroundRepeat;
      36: goto          40
      39: aload_2
      40: putfield      #2                  // Field repeatX:Ljavafx/scene/layout/BackgroundRepeat;
      43: aload_0
      44: aload_3
      45: ifnonnull     54
      48: getstatic     #11                 // Field javafx/scene/layout/BackgroundRepeat.REPEAT:Ljavafx/scene/layout/BackgroundRepeat;
      51: goto          55
      54: aload_3
      55: putfield      #3                  // Field repeatY:Ljavafx/scene/layout/BackgroundRepeat;
      58: aload_0
      59: aload         4
      61: ifnonnull     70
      64: getstatic     #12                 // Field javafx/scene/layout/BackgroundPosition.DEFAULT:Ljavafx/scene/layout/BackgroundPosition;
      67: goto          72
      70: aload         4
      72: putfield      #4                  // Field position:Ljavafx/scene/layout/BackgroundPosition;
      75: aload_0
      76: aload         5
      78: ifnonnull     87
      81: getstatic     #13                 // Field javafx/scene/layout/BackgroundSize.DEFAULT:Ljavafx/scene/layout/BackgroundSize;
      84: goto          89
      87: aload         5
      89: putfield      #5                  // Field size:Ljavafx/scene/layout/BackgroundSize;
      92: aload_0
      93: getfield      #1                  // Field image:Ljavafx/scene/image/Image;
      96: invokevirtual #14                 // Method java/lang/Object.hashCode:()I
      99: istore        6
     101: bipush        31
     103: iload         6
     105: imul
     106: aload_0
     107: getfield      #2                  // Field repeatX:Ljavafx/scene/layout/BackgroundRepeat;
     110: invokevirtual #15                 // Method javafx/scene/layout/BackgroundRepeat.hashCode:()I
     113: iadd
     114: istore        6
     116: bipush        31
     118: iload         6
     120: imul
     121: aload_0
     122: getfield      #3                  // Field repeatY:Ljavafx/scene/layout/BackgroundRepeat;
     125: invokevirtual #15                 // Method javafx/scene/layout/BackgroundRepeat.hashCode:()I
     128: iadd
     129: istore        6
     131: bipush        31
     133: iload         6
     135: imul
     136: aload_0
     137: getfield      #4                  // Field position:Ljavafx/scene/layout/BackgroundPosition;
     140: invokevirtual #16                 // Method javafx/scene/layout/BackgroundPosition.hashCode:()I
     143: iadd
     144: istore        6
     146: bipush        31
     148: iload         6
     150: imul
     151: aload_0
     152: getfield      #5                  // Field size:Ljavafx/scene/layout/BackgroundSize;
     155: invokevirtual #17                 // Method javafx/scene/layout/BackgroundSize.hashCode:()I
     158: iadd
     159: istore        6
     161: aload_0
     162: iload         6
     164: putfield      #18                 // Field hash:I
     167: return

  public boolean equals(java.lang.Object);
    Code:
       0: aload_0
       1: aload_1
       2: if_acmpne     7
       5: iconst_1
       6: ireturn
       7: aload_1
       8: ifnull        22
      11: aload_0
      12: invokevirtual #19                 // Method java/lang/Object.getClass:()Ljava/lang/Class;
      15: aload_1
      16: invokevirtual #19                 // Method java/lang/Object.getClass:()Ljava/lang/Class;
      19: if_acmpeq     24
      22: iconst_0
      23: ireturn
      24: aload_1
      25: checkcast     #20                 // class javafx/scene/layout/BackgroundImage
      28: astore_2
      29: aload_0
      30: getfield      #18                 // Field hash:I
      33: aload_2
      34: getfield      #18                 // Field hash:I
      37: if_icmpeq     42
      40: iconst_0
      41: ireturn
      42: aload_0
      43: getfield      #1                  // Field image:Ljavafx/scene/image/Image;
      46: aload_2
      47: getfield      #1                  // Field image:Ljavafx/scene/image/Image;
      50: invokevirtual #21                 // Method java/lang/Object.equals:(Ljava/lang/Object;)Z
      53: ifne          58
      56: iconst_0
      57: ireturn
      58: aload_0
      59: getfield      #4                  // Field position:Ljavafx/scene/layout/BackgroundPosition;
      62: aload_2
      63: getfield      #4                  // Field position:Ljavafx/scene/layout/BackgroundPosition;
      66: invokevirtual #22                 // Method javafx/scene/layout/BackgroundPosition.equals:(Ljava/lang/Object;)Z
      69: ifne          74
      72: iconst_0
      73: ireturn
      74: aload_0
      75: getfield      #2                  // Field repeatX:Ljavafx/scene/layout/BackgroundRepeat;
      78: aload_2
      79: getfield      #2                  // Field repeatX:Ljavafx/scene/layout/BackgroundRepeat;
      82: if_acmpeq     87
      85: iconst_0
      86: ireturn
      87: aload_0
      88: getfield      #3                  // Field repeatY:Ljavafx/scene/layout/BackgroundRepeat;
      91: aload_2
      92: getfield      #3                  // Field repeatY:Ljavafx/scene/layout/BackgroundRepeat;
      95: if_acmpeq     100
      98: iconst_0
      99: ireturn
     100: aload_0
     101: getfield      #5                  // Field size:Ljavafx/scene/layout/BackgroundSize;
     104: aload_2
     105: getfield      #5                  // Field size:Ljavafx/scene/layout/BackgroundSize;
     108: invokevirtual #23                 // Method javafx/scene/layout/BackgroundSize.equals:(Ljava/lang/Object;)Z
     111: ifne          116
     114: iconst_0
     115: ireturn
     116: iconst_1
     117: ireturn

  public int hashCode();
    Code:
       0: aload_0
       1: getfield      #18                 // Field hash:I
       4: ireturn
}
