Compiled from "Region.java"
class javafx.scene.layout.Region$12 {
  static final int[] $SwitchMap$javafx$geometry$HPos;

  static final int[] $SwitchMap$javafx$geometry$VPos;

  static {};
    Code:
       0: invokestatic  #1                  // Method javafx/geometry/VPos.values:()[Ljavafx/geometry/VPos;
       3: arraylength
       4: newarray       int
       6: putstatic     #2                  // Field $SwitchMap$javafx$geometry$VPos:[I
       9: getstatic     #2                  // Field $SwitchMap$javafx$geometry$VPos:[I
      12: getstatic     #3                  // Field javafx/geometry/VPos.BASELINE:Ljavafx/geometry/VPos;
      15: invokevirtual #4                  // Method javafx/geometry/VPos.ordinal:()I
      18: iconst_1
      19: iastore
      20: goto          24
      23: astore_0
      24: getstatic     #2                  // Field $SwitchMap$javafx$geometry$VPos:[I
      27: getstatic     #6                  // Field javafx/geometry/VPos.TOP:Ljavafx/geometry/VPos;
      30: invokevirtual #4                  // Method javafx/geometry/VPos.ordinal:()I
      33: iconst_2
      34: iastore
      35: goto          39
      38: astore_0
      39: getstatic     #2                  // Field $SwitchMap$javafx$geometry$VPos:[I
      42: getstatic     #7                  // Field javafx/geometry/VPos.CENTER:Ljavafx/geometry/VPos;
      45: invokevirtual #4                  // Method javafx/geometry/VPos.ordinal:()I
      48: iconst_3
      49: iastore
      50: goto          54
      53: astore_0
      54: getstatic     #2                  // Field $SwitchMap$javafx$geometry$VPos:[I
      57: getstatic     #8                  // Field javafx/geometry/VPos.BOTTOM:Ljavafx/geometry/VPos;
      60: invokevirtual #4                  // Method javafx/geometry/VPos.ordinal:()I
      63: iconst_4
      64: iastore
      65: goto          69
      68: astore_0
      69: invokestatic  #9                  // Method javafx/geometry/HPos.values:()[Ljavafx/geometry/HPos;
      72: arraylength
      73: newarray       int
      75: putstatic     #10                 // Field $SwitchMap$javafx$geometry$HPos:[I
      78: getstatic     #10                 // Field $SwitchMap$javafx$geometry$HPos:[I
      81: getstatic     #11                 // Field javafx/geometry/HPos.LEFT:Ljavafx/geometry/HPos;
      84: invokevirtual #12                 // Method javafx/geometry/HPos.ordinal:()I
      87: iconst_1
      88: iastore
      89: goto          93
      92: astore_0
      93: getstatic     #10                 // Field $SwitchMap$javafx$geometry$HPos:[I
      96: getstatic     #13                 // Field javafx/geometry/HPos.CENTER:Ljavafx/geometry/HPos;
      99: invokevirtual #12                 // Method javafx/geometry/HPos.ordinal:()I
     102: iconst_2
     103: iastore
     104: goto          108
     107: astore_0
     108: getstatic     #10                 // Field $SwitchMap$javafx$geometry$HPos:[I
     111: getstatic     #14                 // Field javafx/geometry/HPos.RIGHT:Ljavafx/geometry/HPos;
     114: invokevirtual #12                 // Method javafx/geometry/HPos.ordinal:()I
     117: iconst_3
     118: iastore
     119: goto          123
     122: astore_0
     123: return
    Exception table:
       from    to  target type
           9    20    23   Class java/lang/NoSuchFieldError
          24    35    38   Class java/lang/NoSuchFieldError
          39    50    53   Class java/lang/NoSuchFieldError
          54    65    68   Class java/lang/NoSuchFieldError
          78    89    92   Class java/lang/NoSuchFieldError
          93   104   107   Class java/lang/NoSuchFieldError
         108   119   122   Class java/lang/NoSuchFieldError
}
