Compiled from "URIBuilder.java"
public class org.apache.http.client.utils.URIBuilder {
  private java.lang.String scheme;

  private java.lang.String encodedSchemeSpecificPart;

  private java.lang.String encodedAuthority;

  private java.lang.String userInfo;

  private java.lang.String encodedUserInfo;

  private java.lang.String host;

  private int port;

  private java.lang.String path;

  private java.lang.String encodedPath;

  private java.lang.String encodedQuery;

  private java.util.List<org.apache.http.NameValuePair> queryParams;

  private java.lang.String query;

  private java.nio.charset.Charset charset;

  private java.lang.String fragment;

  private java.lang.String encodedFragment;

  public org.apache.http.client.utils.URIBuilder();
    Code:
       0: aload_0
       1: invokespecial #1                  // Method java/lang/Object."<init>":()V
       4: aload_0
       5: iconst_m1
       6: putfield      #2                  // Field port:I
       9: return

  public org.apache.http.client.utils.URIBuilder(java.lang.String) throws java.net.URISyntaxException;
    Code:
       0: aload_0
       1: invokespecial #1                  // Method java/lang/Object."<init>":()V
       4: aload_0
       5: new           #3                  // class java/net/URI
       8: dup
       9: aload_1
      10: invokespecial #4                  // Method java/net/URI."<init>":(Ljava/lang/String;)V
      13: invokespecial #5                  // Method digestURI:(Ljava/net/URI;)V
      16: return

  public org.apache.http.client.utils.URIBuilder(java.net.URI);
    Code:
       0: aload_0
       1: invokespecial #1                  // Method java/lang/Object."<init>":()V
       4: aload_0
       5: aload_1
       6: invokespecial #5                  // Method digestURI:(Ljava/net/URI;)V
       9: return

  public org.apache.http.client.utils.URIBuilder setCharset(java.nio.charset.Charset);
    Code:
       0: aload_0
       1: aload_1
       2: putfield      #6                  // Field charset:Ljava/nio/charset/Charset;
       5: aload_0
       6: areturn

  public java.nio.charset.Charset getCharset();
    Code:
       0: aload_0
       1: getfield      #6                  // Field charset:Ljava/nio/charset/Charset;
       4: areturn

  private java.util.List<org.apache.http.NameValuePair> parseQuery(java.lang.String, java.nio.charset.Charset);
    Code:
       0: aload_1
       1: ifnull        17
       4: aload_1
       5: invokevirtual #7                  // Method java/lang/String.isEmpty:()Z
       8: ifne          17
      11: aload_1
      12: aload_2
      13: invokestatic  #8                  // Method org/apache/http/client/utils/URLEncodedUtils.parse:(Ljava/lang/String;Ljava/nio/charset/Charset;)Ljava/util/List;
      16: areturn
      17: aconst_null
      18: areturn

  public java.net.URI build() throws java.net.URISyntaxException;
    Code:
       0: new           #3                  // class java/net/URI
       3: dup
       4: aload_0
       5: invokespecial #9                  // Method buildString:()Ljava/lang/String;
       8: invokespecial #4                  // Method java/net/URI."<init>":(Ljava/lang/String;)V
      11: areturn

  private java.lang.String buildString();
    Code:
       0: new           #10                 // class java/lang/StringBuilder
       3: dup
       4: invokespecial #11                 // Method java/lang/StringBuilder."<init>":()V
       7: astore_1
       8: aload_0
       9: getfield      #12                 // Field scheme:Ljava/lang/String;
      12: ifnull        29
      15: aload_1
      16: aload_0
      17: getfield      #12                 // Field scheme:Ljava/lang/String;
      20: invokevirtual #13                 // Method java/lang/StringBuilder.append:(Ljava/lang/String;)Ljava/lang/StringBuilder;
      23: bipush        58
      25: invokevirtual #14                 // Method java/lang/StringBuilder.append:(C)Ljava/lang/StringBuilder;
      28: pop
      29: aload_0
      30: getfield      #15                 // Field encodedSchemeSpecificPart:Ljava/lang/String;
      33: ifnull        48
      36: aload_1
      37: aload_0
      38: getfield      #15                 // Field encodedSchemeSpecificPart:Ljava/lang/String;
      41: invokevirtual #13                 // Method java/lang/StringBuilder.append:(Ljava/lang/String;)Ljava/lang/StringBuilder;
      44: pop
      45: goto          355
      48: aload_0
      49: getfield      #16                 // Field encodedAuthority:Ljava/lang/String;
      52: ifnull        72
      55: aload_1
      56: ldc           #17                 // String //
      58: invokevirtual #13                 // Method java/lang/StringBuilder.append:(Ljava/lang/String;)Ljava/lang/StringBuilder;
      61: aload_0
      62: getfield      #16                 // Field encodedAuthority:Ljava/lang/String;
      65: invokevirtual #13                 // Method java/lang/StringBuilder.append:(Ljava/lang/String;)Ljava/lang/StringBuilder;
      68: pop
      69: goto          197
      72: aload_0
      73: getfield      #18                 // Field host:Ljava/lang/String;
      76: ifnull        197
      79: aload_1
      80: ldc           #17                 // String //
      82: invokevirtual #13                 // Method java/lang/StringBuilder.append:(Ljava/lang/String;)Ljava/lang/StringBuilder;
      85: pop
      86: aload_0
      87: getfield      #19                 // Field encodedUserInfo:Ljava/lang/String;
      90: ifnull        110
      93: aload_1
      94: aload_0
      95: getfield      #19                 // Field encodedUserInfo:Ljava/lang/String;
      98: invokevirtual #13                 // Method java/lang/StringBuilder.append:(Ljava/lang/String;)Ljava/lang/StringBuilder;
     101: ldc           #20                 // String @
     103: invokevirtual #13                 // Method java/lang/StringBuilder.append:(Ljava/lang/String;)Ljava/lang/StringBuilder;
     106: pop
     107: goto          135
     110: aload_0
     111: getfield      #21                 // Field userInfo:Ljava/lang/String;
     114: ifnull        135
     117: aload_1
     118: aload_0
     119: aload_0
     120: getfield      #21                 // Field userInfo:Ljava/lang/String;
     123: invokespecial #22                 // Method encodeUserInfo:(Ljava/lang/String;)Ljava/lang/String;
     126: invokevirtual #13                 // Method java/lang/StringBuilder.append:(Ljava/lang/String;)Ljava/lang/StringBuilder;
     129: ldc           #20                 // String @
     131: invokevirtual #13                 // Method java/lang/StringBuilder.append:(Ljava/lang/String;)Ljava/lang/StringBuilder;
     134: pop
     135: aload_0
     136: getfield      #18                 // Field host:Ljava/lang/String;
     139: invokestatic  #23                 // Method org/apache/http/conn/util/InetAddressUtils.isIPv6Address:(Ljava/lang/String;)Z
     142: ifeq          167
     145: aload_1
     146: ldc           #24                 // String [
     148: invokevirtual #13                 // Method java/lang/StringBuilder.append:(Ljava/lang/String;)Ljava/lang/StringBuilder;
     151: aload_0
     152: getfield      #18                 // Field host:Ljava/lang/String;
     155: invokevirtual #13                 // Method java/lang/StringBuilder.append:(Ljava/lang/String;)Ljava/lang/StringBuilder;
     158: ldc           #25                 // String ]
     160: invokevirtual #13                 // Method java/lang/StringBuilder.append:(Ljava/lang/String;)Ljava/lang/StringBuilder;
     163: pop
     164: goto          176
     167: aload_1
     168: aload_0
     169: getfield      #18                 // Field host:Ljava/lang/String;
     172: invokevirtual #13                 // Method java/lang/StringBuilder.append:(Ljava/lang/String;)Ljava/lang/StringBuilder;
     175: pop
     176: aload_0
     177: getfield      #2                  // Field port:I
     180: iflt          197
     183: aload_1
     184: ldc           #26                 // String :
     186: invokevirtual #13                 // Method java/lang/StringBuilder.append:(Ljava/lang/String;)Ljava/lang/StringBuilder;
     189: aload_0
     190: getfield      #2                  // Field port:I
     193: invokevirtual #27                 // Method java/lang/StringBuilder.append:(I)Ljava/lang/StringBuilder;
     196: pop
     197: aload_0
     198: getfield      #28                 // Field encodedPath:Ljava/lang/String;
     201: ifnull        231
     204: aload_1
     205: aload_0
     206: getfield      #28                 // Field encodedPath:Ljava/lang/String;
     209: aload_1
     210: invokevirtual #29                 // Method java/lang/StringBuilder.length:()I
     213: ifne          220
     216: iconst_1
     217: goto          221
     220: iconst_0
     221: invokestatic  #30                 // Method normalizePath:(Ljava/lang/String;Z)Ljava/lang/String;
     224: invokevirtual #13                 // Method java/lang/StringBuilder.append:(Ljava/lang/String;)Ljava/lang/StringBuilder;
     227: pop
     228: goto          266
     231: aload_0
     232: getfield      #31                 // Field path:Ljava/lang/String;
     235: ifnull        266
     238: aload_1
     239: aload_0
     240: aload_0
     241: getfield      #31                 // Field path:Ljava/lang/String;
     244: aload_1
     245: invokevirtual #29                 // Method java/lang/StringBuilder.length:()I
     248: ifne          255
     251: iconst_1
     252: goto          256
     255: iconst_0
     256: invokestatic  #30                 // Method normalizePath:(Ljava/lang/String;Z)Ljava/lang/String;
     259: invokespecial #32                 // Method encodePath:(Ljava/lang/String;)Ljava/lang/String;
     262: invokevirtual #13                 // Method java/lang/StringBuilder.append:(Ljava/lang/String;)Ljava/lang/StringBuilder;
     265: pop
     266: aload_0
     267: getfield      #33                 // Field encodedQuery:Ljava/lang/String;
     270: ifnull        290
     273: aload_1
     274: ldc           #34                 // String ?
     276: invokevirtual #13                 // Method java/lang/StringBuilder.append:(Ljava/lang/String;)Ljava/lang/StringBuilder;
     279: aload_0
     280: getfield      #33                 // Field encodedQuery:Ljava/lang/String;
     283: invokevirtual #13                 // Method java/lang/StringBuilder.append:(Ljava/lang/String;)Ljava/lang/StringBuilder;
     286: pop
     287: goto          355
     290: aload_0
     291: getfield      #35                 // Field queryParams:Ljava/util/List;
     294: ifnull        330
     297: aload_0
     298: getfield      #35                 // Field queryParams:Ljava/util/List;
     301: invokeinterface #36,  1           // InterfaceMethod java/util/List.isEmpty:()Z
     306: ifne          330
     309: aload_1
     310: ldc           #34                 // String ?
     312: invokevirtual #13                 // Method java/lang/StringBuilder.append:(Ljava/lang/String;)Ljava/lang/StringBuilder;
     315: aload_0
     316: aload_0
     317: getfield      #35                 // Field queryParams:Ljava/util/List;
     320: invokespecial #37                 // Method encodeUrlForm:(Ljava/util/List;)Ljava/lang/String;
     323: invokevirtual #13                 // Method java/lang/StringBuilder.append:(Ljava/lang/String;)Ljava/lang/StringBuilder;
     326: pop
     327: goto          355
     330: aload_0
     331: getfield      #38                 // Field query:Ljava/lang/String;
     334: ifnull        355
     337: aload_1
     338: ldc           #34                 // String ?
     340: invokevirtual #13                 // Method java/lang/StringBuilder.append:(Ljava/lang/String;)Ljava/lang/StringBuilder;
     343: aload_0
     344: aload_0
     345: getfield      #38                 // Field query:Ljava/lang/String;
     348: invokespecial #39                 // Method encodeUric:(Ljava/lang/String;)Ljava/lang/String;
     351: invokevirtual #13                 // Method java/lang/StringBuilder.append:(Ljava/lang/String;)Ljava/lang/StringBuilder;
     354: pop
     355: aload_0
     356: getfield      #40                 // Field encodedFragment:Ljava/lang/String;
     359: ifnull        379
     362: aload_1
     363: ldc           #41                 // String #
     365: invokevirtual #13                 // Method java/lang/StringBuilder.append:(Ljava/lang/String;)Ljava/lang/StringBuilder;
     368: aload_0
     369: getfield      #40                 // Field encodedFragment:Ljava/lang/String;
     372: invokevirtual #13                 // Method java/lang/StringBuilder.append:(Ljava/lang/String;)Ljava/lang/StringBuilder;
     375: pop
     376: goto          404
     379: aload_0
     380: getfield      #42                 // Field fragment:Ljava/lang/String;
     383: ifnull        404
     386: aload_1
     387: ldc           #41                 // String #
     389: invokevirtual #13                 // Method java/lang/StringBuilder.append:(Ljava/lang/String;)Ljava/lang/StringBuilder;
     392: aload_0
     393: aload_0
     394: getfield      #42                 // Field fragment:Ljava/lang/String;
     397: invokespecial #39                 // Method encodeUric:(Ljava/lang/String;)Ljava/lang/String;
     400: invokevirtual #13                 // Method java/lang/StringBuilder.append:(Ljava/lang/String;)Ljava/lang/StringBuilder;
     403: pop
     404: aload_1
     405: invokevirtual #43                 // Method java/lang/StringBuilder.toString:()Ljava/lang/String;
     408: areturn

  private static java.lang.String normalizePath(java.lang.String, boolean);
    Code:
       0: aload_0
       1: astore_2
       2: aload_2
       3: invokestatic  #44                 // Method org/apache/http/util/TextUtils.isBlank:(Ljava/lang/CharSequence;)Z
       6: ifeq          12
       9: ldc           #45                 // String
      11: areturn
      12: iconst_0
      13: istore_3
      14: iload_3
      15: aload_2
      16: invokevirtual #46                 // Method java/lang/String.length:()I
      19: if_icmpge     41
      22: aload_2
      23: iload_3
      24: invokevirtual #47                 // Method java/lang/String.charAt:(I)C
      27: bipush        47
      29: if_icmpeq     35
      32: goto          41
      35: iinc          3, 1
      38: goto          14
      41: iload_3
      42: iconst_1
      43: if_icmple     54
      46: aload_2
      47: iload_3
      48: iconst_1
      49: isub
      50: invokevirtual #48                 // Method java/lang/String.substring:(I)Ljava/lang/String;
      53: astore_2
      54: iload_1
      55: ifne          87
      58: aload_2
      59: ldc           #49                 // String /
      61: invokevirtual #50                 // Method java/lang/String.startsWith:(Ljava/lang/String;)Z
      64: ifne          87
      67: new           #10                 // class java/lang/StringBuilder
      70: dup
      71: invokespecial #11                 // Method java/lang/StringBuilder."<init>":()V
      74: ldc           #49                 // String /
      76: invokevirtual #13                 // Method java/lang/StringBuilder.append:(Ljava/lang/String;)Ljava/lang/StringBuilder;
      79: aload_2
      80: invokevirtual #13                 // Method java/lang/StringBuilder.append:(Ljava/lang/String;)Ljava/lang/StringBuilder;
      83: invokevirtual #43                 // Method java/lang/StringBuilder.toString:()Ljava/lang/String;
      86: astore_2
      87: aload_2
      88: areturn

  private void digestURI(java.net.URI);
    Code:
       0: aload_0
       1: aload_1
       2: invokevirtual #51                 // Method java/net/URI.getScheme:()Ljava/lang/String;
       5: putfield      #12                 // Field scheme:Ljava/lang/String;
       8: aload_0
       9: aload_1
      10: invokevirtual #52                 // Method java/net/URI.getRawSchemeSpecificPart:()Ljava/lang/String;
      13: putfield      #15                 // Field encodedSchemeSpecificPart:Ljava/lang/String;
      16: aload_0
      17: aload_1
      18: invokevirtual #53                 // Method java/net/URI.getRawAuthority:()Ljava/lang/String;
      21: putfield      #16                 // Field encodedAuthority:Ljava/lang/String;
      24: aload_0
      25: aload_1
      26: invokevirtual #54                 // Method java/net/URI.getHost:()Ljava/lang/String;
      29: putfield      #18                 // Field host:Ljava/lang/String;
      32: aload_0
      33: aload_1
      34: invokevirtual #55                 // Method java/net/URI.getPort:()I
      37: putfield      #2                  // Field port:I
      40: aload_0
      41: aload_1
      42: invokevirtual #56                 // Method java/net/URI.getRawUserInfo:()Ljava/lang/String;
      45: putfield      #19                 // Field encodedUserInfo:Ljava/lang/String;
      48: aload_0
      49: aload_1
      50: invokevirtual #57                 // Method java/net/URI.getUserInfo:()Ljava/lang/String;
      53: putfield      #21                 // Field userInfo:Ljava/lang/String;
      56: aload_0
      57: aload_1
      58: invokevirtual #58                 // Method java/net/URI.getRawPath:()Ljava/lang/String;
      61: putfield      #28                 // Field encodedPath:Ljava/lang/String;
      64: aload_0
      65: aload_1
      66: invokevirtual #59                 // Method java/net/URI.getPath:()Ljava/lang/String;
      69: putfield      #31                 // Field path:Ljava/lang/String;
      72: aload_0
      73: aload_1
      74: invokevirtual #60                 // Method java/net/URI.getRawQuery:()Ljava/lang/String;
      77: putfield      #33                 // Field encodedQuery:Ljava/lang/String;
      80: aload_0
      81: aload_0
      82: aload_1
      83: invokevirtual #60                 // Method java/net/URI.getRawQuery:()Ljava/lang/String;
      86: aload_0
      87: getfield      #6                  // Field charset:Ljava/nio/charset/Charset;
      90: ifnull        100
      93: aload_0
      94: getfield      #6                  // Field charset:Ljava/nio/charset/Charset;
      97: goto          103
     100: getstatic     #61                 // Field org/apache/http/Consts.UTF_8:Ljava/nio/charset/Charset;
     103: invokespecial #62                 // Method parseQuery:(Ljava/lang/String;Ljava/nio/charset/Charset;)Ljava/util/List;
     106: putfield      #35                 // Field queryParams:Ljava/util/List;
     109: aload_0
     110: aload_1
     111: invokevirtual #63                 // Method java/net/URI.getRawFragment:()Ljava/lang/String;
     114: putfield      #40                 // Field encodedFragment:Ljava/lang/String;
     117: aload_0
     118: aload_1
     119: invokevirtual #64                 // Method java/net/URI.getFragment:()Ljava/lang/String;
     122: putfield      #42                 // Field fragment:Ljava/lang/String;
     125: return

  private java.lang.String encodeUserInfo(java.lang.String);
    Code:
       0: aload_1
       1: aload_0
       2: getfield      #6                  // Field charset:Ljava/nio/charset/Charset;
       5: ifnull        15
       8: aload_0
       9: getfield      #6                  // Field charset:Ljava/nio/charset/Charset;
      12: goto          18
      15: getstatic     #61                 // Field org/apache/http/Consts.UTF_8:Ljava/nio/charset/Charset;
      18: invokestatic  #65                 // Method org/apache/http/client/utils/URLEncodedUtils.encUserInfo:(Ljava/lang/String;Ljava/nio/charset/Charset;)Ljava/lang/String;
      21: areturn

  private java.lang.String encodePath(java.lang.String);
    Code:
       0: aload_1
       1: aload_0
       2: getfield      #6                  // Field charset:Ljava/nio/charset/Charset;
       5: ifnull        15
       8: aload_0
       9: getfield      #6                  // Field charset:Ljava/nio/charset/Charset;
      12: goto          18
      15: getstatic     #61                 // Field org/apache/http/Consts.UTF_8:Ljava/nio/charset/Charset;
      18: invokestatic  #66                 // Method org/apache/http/client/utils/URLEncodedUtils.encPath:(Ljava/lang/String;Ljava/nio/charset/Charset;)Ljava/lang/String;
      21: areturn

  private java.lang.String encodeUrlForm(java.util.List<org.apache.http.NameValuePair>);
    Code:
       0: aload_1
       1: aload_0
       2: getfield      #6                  // Field charset:Ljava/nio/charset/Charset;
       5: ifnull        15
       8: aload_0
       9: getfield      #6                  // Field charset:Ljava/nio/charset/Charset;
      12: goto          18
      15: getstatic     #61                 // Field org/apache/http/Consts.UTF_8:Ljava/nio/charset/Charset;
      18: invokestatic  #67                 // Method org/apache/http/client/utils/URLEncodedUtils.format:(Ljava/lang/Iterable;Ljava/nio/charset/Charset;)Ljava/lang/String;
      21: areturn

  private java.lang.String encodeUric(java.lang.String);
    Code:
       0: aload_1
       1: aload_0
       2: getfield      #6                  // Field charset:Ljava/nio/charset/Charset;
       5: ifnull        15
       8: aload_0
       9: getfield      #6                  // Field charset:Ljava/nio/charset/Charset;
      12: goto          18
      15: getstatic     #61                 // Field org/apache/http/Consts.UTF_8:Ljava/nio/charset/Charset;
      18: invokestatic  #68                 // Method org/apache/http/client/utils/URLEncodedUtils.encUric:(Ljava/lang/String;Ljava/nio/charset/Charset;)Ljava/lang/String;
      21: areturn

  public org.apache.http.client.utils.URIBuilder setScheme(java.lang.String);
    Code:
       0: aload_0
       1: aload_1
       2: putfield      #12                 // Field scheme:Ljava/lang/String;
       5: aload_0
       6: areturn

  public org.apache.http.client.utils.URIBuilder setUserInfo(java.lang.String);
    Code:
       0: aload_0
       1: aload_1
       2: putfield      #21                 // Field userInfo:Ljava/lang/String;
       5: aload_0
       6: aconst_null
       7: putfield      #15                 // Field encodedSchemeSpecificPart:Ljava/lang/String;
      10: aload_0
      11: aconst_null
      12: putfield      #16                 // Field encodedAuthority:Ljava/lang/String;
      15: aload_0
      16: aconst_null
      17: putfield      #19                 // Field encodedUserInfo:Ljava/lang/String;
      20: aload_0
      21: areturn

  public org.apache.http.client.utils.URIBuilder setUserInfo(java.lang.String, java.lang.String);
    Code:
       0: aload_0
       1: new           #10                 // class java/lang/StringBuilder
       4: dup
       5: invokespecial #11                 // Method java/lang/StringBuilder."<init>":()V
       8: aload_1
       9: invokevirtual #13                 // Method java/lang/StringBuilder.append:(Ljava/lang/String;)Ljava/lang/StringBuilder;
      12: bipush        58
      14: invokevirtual #14                 // Method java/lang/StringBuilder.append:(C)Ljava/lang/StringBuilder;
      17: aload_2
      18: invokevirtual #13                 // Method java/lang/StringBuilder.append:(Ljava/lang/String;)Ljava/lang/StringBuilder;
      21: invokevirtual #43                 // Method java/lang/StringBuilder.toString:()Ljava/lang/String;
      24: invokevirtual #69                 // Method setUserInfo:(Ljava/lang/String;)Lorg/apache/http/client/utils/URIBuilder;
      27: areturn

  public org.apache.http.client.utils.URIBuilder setHost(java.lang.String);
    Code:
       0: aload_0
       1: aload_1
       2: putfield      #18                 // Field host:Ljava/lang/String;
       5: aload_0
       6: aconst_null
       7: putfield      #15                 // Field encodedSchemeSpecificPart:Ljava/lang/String;
      10: aload_0
      11: aconst_null
      12: putfield      #16                 // Field encodedAuthority:Ljava/lang/String;
      15: aload_0
      16: areturn

  public org.apache.http.client.utils.URIBuilder setPort(int);
    Code:
       0: aload_0
       1: iload_1
       2: ifge          9
       5: iconst_m1
       6: goto          10
       9: iload_1
      10: putfield      #2                  // Field port:I
      13: aload_0
      14: aconst_null
      15: putfield      #15                 // Field encodedSchemeSpecificPart:Ljava/lang/String;
      18: aload_0
      19: aconst_null
      20: putfield      #16                 // Field encodedAuthority:Ljava/lang/String;
      23: aload_0
      24: areturn

  public org.apache.http.client.utils.URIBuilder setPath(java.lang.String);
    Code:
       0: aload_0
       1: aload_1
       2: putfield      #31                 // Field path:Ljava/lang/String;
       5: aload_0
       6: aconst_null
       7: putfield      #15                 // Field encodedSchemeSpecificPart:Ljava/lang/String;
      10: aload_0
      11: aconst_null
      12: putfield      #28                 // Field encodedPath:Ljava/lang/String;
      15: aload_0
      16: areturn

  public org.apache.http.client.utils.URIBuilder removeQuery();
    Code:
       0: aload_0
       1: aconst_null
       2: putfield      #35                 // Field queryParams:Ljava/util/List;
       5: aload_0
       6: aconst_null
       7: putfield      #38                 // Field query:Ljava/lang/String;
      10: aload_0
      11: aconst_null
      12: putfield      #33                 // Field encodedQuery:Ljava/lang/String;
      15: aload_0
      16: aconst_null
      17: putfield      #15                 // Field encodedSchemeSpecificPart:Ljava/lang/String;
      20: aload_0
      21: areturn

  public org.apache.http.client.utils.URIBuilder setQuery(java.lang.String);
    Code:
       0: aload_0
       1: aload_0
       2: aload_1
       3: aload_0
       4: getfield      #6                  // Field charset:Ljava/nio/charset/Charset;
       7: ifnull        17
      10: aload_0
      11: getfield      #6                  // Field charset:Ljava/nio/charset/Charset;
      14: goto          20
      17: getstatic     #61                 // Field org/apache/http/Consts.UTF_8:Ljava/nio/charset/Charset;
      20: invokespecial #62                 // Method parseQuery:(Ljava/lang/String;Ljava/nio/charset/Charset;)Ljava/util/List;
      23: putfield      #35                 // Field queryParams:Ljava/util/List;
      26: aload_0
      27: aconst_null
      28: putfield      #38                 // Field query:Ljava/lang/String;
      31: aload_0
      32: aconst_null
      33: putfield      #33                 // Field encodedQuery:Ljava/lang/String;
      36: aload_0
      37: aconst_null
      38: putfield      #15                 // Field encodedSchemeSpecificPart:Ljava/lang/String;
      41: aload_0
      42: areturn

  public org.apache.http.client.utils.URIBuilder setParameters(java.util.List<org.apache.http.NameValuePair>);
    Code:
       0: aload_0
       1: getfield      #35                 // Field queryParams:Ljava/util/List;
       4: ifnonnull     21
       7: aload_0
       8: new           #70                 // class java/util/ArrayList
      11: dup
      12: invokespecial #71                 // Method java/util/ArrayList."<init>":()V
      15: putfield      #35                 // Field queryParams:Ljava/util/List;
      18: goto          30
      21: aload_0
      22: getfield      #35                 // Field queryParams:Ljava/util/List;
      25: invokeinterface #72,  1           // InterfaceMethod java/util/List.clear:()V
      30: aload_0
      31: getfield      #35                 // Field queryParams:Ljava/util/List;
      34: aload_1
      35: invokeinterface #73,  2           // InterfaceMethod java/util/List.addAll:(Ljava/util/Collection;)Z
      40: pop
      41: aload_0
      42: aconst_null
      43: putfield      #33                 // Field encodedQuery:Ljava/lang/String;
      46: aload_0
      47: aconst_null
      48: putfield      #15                 // Field encodedSchemeSpecificPart:Ljava/lang/String;
      51: aload_0
      52: aconst_null
      53: putfield      #38                 // Field query:Ljava/lang/String;
      56: aload_0
      57: areturn

  public org.apache.http.client.utils.URIBuilder addParameters(java.util.List<org.apache.http.NameValuePair>);
    Code:
       0: aload_0
       1: getfield      #35                 // Field queryParams:Ljava/util/List;
       4: ifnonnull     18
       7: aload_0
       8: new           #70                 // class java/util/ArrayList
      11: dup
      12: invokespecial #71                 // Method java/util/ArrayList."<init>":()V
      15: putfield      #35                 // Field queryParams:Ljava/util/List;
      18: aload_0
      19: getfield      #35                 // Field queryParams:Ljava/util/List;
      22: aload_1
      23: invokeinterface #73,  2           // InterfaceMethod java/util/List.addAll:(Ljava/util/Collection;)Z
      28: pop
      29: aload_0
      30: aconst_null
      31: putfield      #33                 // Field encodedQuery:Ljava/lang/String;
      34: aload_0
      35: aconst_null
      36: putfield      #15                 // Field encodedSchemeSpecificPart:Ljava/lang/String;
      39: aload_0
      40: aconst_null
      41: putfield      #38                 // Field query:Ljava/lang/String;
      44: aload_0
      45: areturn

  public org.apache.http.client.utils.URIBuilder setParameters(org.apache.http.NameValuePair...);
    Code:
       0: aload_0
       1: getfield      #35                 // Field queryParams:Ljava/util/List;
       4: ifnonnull     21
       7: aload_0
       8: new           #70                 // class java/util/ArrayList
      11: dup
      12: invokespecial #71                 // Method java/util/ArrayList."<init>":()V
      15: putfield      #35                 // Field queryParams:Ljava/util/List;
      18: goto          30
      21: aload_0
      22: getfield      #35                 // Field queryParams:Ljava/util/List;
      25: invokeinterface #72,  1           // InterfaceMethod java/util/List.clear:()V
      30: aload_1
      31: astore_2
      32: aload_2
      33: arraylength
      34: istore_3
      35: iconst_0
      36: istore        4
      38: iload         4
      40: iload_3
      41: if_icmpge     68
      44: aload_2
      45: iload         4
      47: aaload
      48: astore        5
      50: aload_0
      51: getfield      #35                 // Field queryParams:Ljava/util/List;
      54: aload         5
      56: invokeinterface #74,  2           // InterfaceMethod java/util/List.add:(Ljava/lang/Object;)Z
      61: pop
      62: iinc          4, 1
      65: goto          38
      68: aload_0
      69: aconst_null
      70: putfield      #33                 // Field encodedQuery:Ljava/lang/String;
      73: aload_0
      74: aconst_null
      75: putfield      #15                 // Field encodedSchemeSpecificPart:Ljava/lang/String;
      78: aload_0
      79: aconst_null
      80: putfield      #38                 // Field query:Ljava/lang/String;
      83: aload_0
      84: areturn

  public org.apache.http.client.utils.URIBuilder addParameter(java.lang.String, java.lang.String);
    Code:
       0: aload_0
       1: getfield      #35                 // Field queryParams:Ljava/util/List;
       4: ifnonnull     18
       7: aload_0
       8: new           #70                 // class java/util/ArrayList
      11: dup
      12: invokespecial #71                 // Method java/util/ArrayList."<init>":()V
      15: putfield      #35                 // Field queryParams:Ljava/util/List;
      18: aload_0
      19: getfield      #35                 // Field queryParams:Ljava/util/List;
      22: new           #75                 // class org/apache/http/message/BasicNameValuePair
      25: dup
      26: aload_1
      27: aload_2
      28: invokespecial #76                 // Method org/apache/http/message/BasicNameValuePair."<init>":(Ljava/lang/String;Ljava/lang/String;)V
      31: invokeinterface #74,  2           // InterfaceMethod java/util/List.add:(Ljava/lang/Object;)Z
      36: pop
      37: aload_0
      38: aconst_null
      39: putfield      #33                 // Field encodedQuery:Ljava/lang/String;
      42: aload_0
      43: aconst_null
      44: putfield      #15                 // Field encodedSchemeSpecificPart:Ljava/lang/String;
      47: aload_0
      48: aconst_null
      49: putfield      #38                 // Field query:Ljava/lang/String;
      52: aload_0
      53: areturn

  public org.apache.http.client.utils.URIBuilder setParameter(java.lang.String, java.lang.String);
    Code:
       0: aload_0
       1: getfield      #35                 // Field queryParams:Ljava/util/List;
       4: ifnonnull     18
       7: aload_0
       8: new           #70                 // class java/util/ArrayList
      11: dup
      12: invokespecial #71                 // Method java/util/ArrayList."<init>":()V
      15: putfield      #35                 // Field queryParams:Ljava/util/List;
      18: aload_0
      19: getfield      #35                 // Field queryParams:Ljava/util/List;
      22: invokeinterface #36,  1           // InterfaceMethod java/util/List.isEmpty:()Z
      27: ifne          83
      30: aload_0
      31: getfield      #35                 // Field queryParams:Ljava/util/List;
      34: invokeinterface #77,  1           // InterfaceMethod java/util/List.iterator:()Ljava/util/Iterator;
      39: astore_3
      40: aload_3
      41: invokeinterface #78,  1           // InterfaceMethod java/util/Iterator.hasNext:()Z
      46: ifeq          83
      49: aload_3
      50: invokeinterface #79,  1           // InterfaceMethod java/util/Iterator.next:()Ljava/lang/Object;
      55: checkcast     #80                 // class org/apache/http/NameValuePair
      58: astore        4
      60: aload         4
      62: invokeinterface #81,  1           // InterfaceMethod org/apache/http/NameValuePair.getName:()Ljava/lang/String;
      67: aload_1
      68: invokevirtual #82                 // Method java/lang/String.equals:(Ljava/lang/Object;)Z
      71: ifeq          80
      74: aload_3
      75: invokeinterface #83,  1           // InterfaceMethod java/util/Iterator.remove:()V
      80: goto          40
      83: aload_0
      84: getfield      #35                 // Field queryParams:Ljava/util/List;
      87: new           #75                 // class org/apache/http/message/BasicNameValuePair
      90: dup
      91: aload_1
      92: aload_2
      93: invokespecial #76                 // Method org/apache/http/message/BasicNameValuePair."<init>":(Ljava/lang/String;Ljava/lang/String;)V
      96: invokeinterface #74,  2           // InterfaceMethod java/util/List.add:(Ljava/lang/Object;)Z
     101: pop
     102: aload_0
     103: aconst_null
     104: putfield      #33                 // Field encodedQuery:Ljava/lang/String;
     107: aload_0
     108: aconst_null
     109: putfield      #15                 // Field encodedSchemeSpecificPart:Ljava/lang/String;
     112: aload_0
     113: aconst_null
     114: putfield      #38                 // Field query:Ljava/lang/String;
     117: aload_0
     118: areturn

  public org.apache.http.client.utils.URIBuilder clearParameters();
    Code:
       0: aload_0
       1: aconst_null
       2: putfield      #35                 // Field queryParams:Ljava/util/List;
       5: aload_0
       6: aconst_null
       7: putfield      #33                 // Field encodedQuery:Ljava/lang/String;
      10: aload_0
      11: aconst_null
      12: putfield      #15                 // Field encodedSchemeSpecificPart:Ljava/lang/String;
      15: aload_0
      16: areturn

  public org.apache.http.client.utils.URIBuilder setCustomQuery(java.lang.String);
    Code:
       0: aload_0
       1: aload_1
       2: putfield      #38                 // Field query:Ljava/lang/String;
       5: aload_0
       6: aconst_null
       7: putfield      #33                 // Field encodedQuery:Ljava/lang/String;
      10: aload_0
      11: aconst_null
      12: putfield      #15                 // Field encodedSchemeSpecificPart:Ljava/lang/String;
      15: aload_0
      16: aconst_null
      17: putfield      #35                 // Field queryParams:Ljava/util/List;
      20: aload_0
      21: areturn

  public org.apache.http.client.utils.URIBuilder setFragment(java.lang.String);
    Code:
       0: aload_0
       1: aload_1
       2: putfield      #42                 // Field fragment:Ljava/lang/String;
       5: aload_0
       6: aconst_null
       7: putfield      #40                 // Field encodedFragment:Ljava/lang/String;
      10: aload_0
      11: areturn

  public boolean isAbsolute();
    Code:
       0: aload_0
       1: getfield      #12                 // Field scheme:Ljava/lang/String;
       4: ifnull        11
       7: iconst_1
       8: goto          12
      11: iconst_0
      12: ireturn

  public boolean isOpaque();
    Code:
       0: aload_0
       1: getfield      #31                 // Field path:Ljava/lang/String;
       4: ifnonnull     11
       7: iconst_1
       8: goto          12
      11: iconst_0
      12: ireturn

  public java.lang.String getScheme();
    Code:
       0: aload_0
       1: getfield      #12                 // Field scheme:Ljava/lang/String;
       4: areturn

  public java.lang.String getUserInfo();
    Code:
       0: aload_0
       1: getfield      #21                 // Field userInfo:Ljava/lang/String;
       4: areturn

  public java.lang.String getHost();
    Code:
       0: aload_0
       1: getfield      #18                 // Field host:Ljava/lang/String;
       4: areturn

  public int getPort();
    Code:
       0: aload_0
       1: getfield      #2                  // Field port:I
       4: ireturn

  public java.lang.String getPath();
    Code:
       0: aload_0
       1: getfield      #31                 // Field path:Ljava/lang/String;
       4: areturn

  public java.util.List<org.apache.http.NameValuePair> getQueryParams();
    Code:
       0: aload_0
       1: getfield      #35                 // Field queryParams:Ljava/util/List;
       4: ifnull        19
       7: new           #70                 // class java/util/ArrayList
      10: dup
      11: aload_0
      12: getfield      #35                 // Field queryParams:Ljava/util/List;
      15: invokespecial #84                 // Method java/util/ArrayList."<init>":(Ljava/util/Collection;)V
      18: areturn
      19: new           #70                 // class java/util/ArrayList
      22: dup
      23: invokespecial #71                 // Method java/util/ArrayList."<init>":()V
      26: areturn

  public java.lang.String getFragment();
    Code:
       0: aload_0
       1: getfield      #42                 // Field fragment:Ljava/lang/String;
       4: areturn

  public java.lang.String toString();
    Code:
       0: aload_0
       1: invokespecial #9                  // Method buildString:()Ljava/lang/String;
       4: areturn
}
