Compiled from "DefaultNamespaceContextSelectorService.java"
class org.jboss.as.naming.service.DefaultNamespaceContextSelectorService$1 extends org.jboss.as.naming.context.NamespaceContextSelector {
  final org.jboss.as.naming.service.DefaultNamespaceContextSelectorService this$0;

  org.jboss.as.naming.service.DefaultNamespaceContextSelectorService$1(org.jboss.as.naming.service.DefaultNamespaceContextSelectorService);
    Code:
       0: aload_0
       1: aload_1
       2: putfield      #1                  // Field this$0:Lorg/jboss/as/naming/service/DefaultNamespaceContextSelectorService;
       5: aload_0
       6: invokespecial #2                  // Method org/jboss/as/naming/context/NamespaceContextSelector."<init>":()V
       9: return

  public javax.naming.Context getContext(java.lang.String);
    Code:
       0: aload_1
       1: ldc           #3                  // String global
       3: invokevirtual #4                  // Method java/lang/String.equals:(Ljava/lang/Object;)Z
       6: ifeq          26
       9: aload_0
      10: getfield      #1                  // Field this$0:Lorg/jboss/as/naming/service/DefaultNamespaceContextSelectorService;
      13: invokestatic  #5                  // Method org/jboss/as/naming/service/DefaultNamespaceContextSelectorService.access$000:(Lorg/jboss/as/naming/service/DefaultNamespaceContextSelectorService;)Lorg/jboss/msc/value/InjectedValue;
      16: invokevirtual #6                  // Method org/jboss/msc/value/InjectedValue.getValue:()Ljava/lang/Object;
      19: checkcast     #7                  // class org/jboss/as/naming/NamingStore
      22: astore_2
      23: goto          80
      26: aload_1
      27: ldc           #8                  // String jboss
      29: invokevirtual #4                  // Method java/lang/String.equals:(Ljava/lang/Object;)Z
      32: ifeq          52
      35: aload_0
      36: getfield      #1                  // Field this$0:Lorg/jboss/as/naming/service/DefaultNamespaceContextSelectorService;
      39: invokestatic  #9                  // Method org/jboss/as/naming/service/DefaultNamespaceContextSelectorService.access$100:(Lorg/jboss/as/naming/service/DefaultNamespaceContextSelectorService;)Lorg/jboss/msc/value/InjectedValue;
      42: invokevirtual #6                  // Method org/jboss/msc/value/InjectedValue.getValue:()Ljava/lang/Object;
      45: checkcast     #7                  // class org/jboss/as/naming/NamingStore
      48: astore_2
      49: goto          80
      52: aload_1
      53: ldc           #10                 // String jboss/exported
      55: invokevirtual #4                  // Method java/lang/String.equals:(Ljava/lang/Object;)Z
      58: ifeq          78
      61: aload_0
      62: getfield      #1                  // Field this$0:Lorg/jboss/as/naming/service/DefaultNamespaceContextSelectorService;
      65: invokestatic  #11                 // Method org/jboss/as/naming/service/DefaultNamespaceContextSelectorService.access$200:(Lorg/jboss/as/naming/service/DefaultNamespaceContextSelectorService;)Lorg/jboss/msc/value/InjectedValue;
      68: invokevirtual #6                  // Method org/jboss/msc/value/InjectedValue.getValue:()Ljava/lang/Object;
      71: checkcast     #7                  // class org/jboss/as/naming/NamingStore
      74: astore_2
      75: goto          80
      78: aconst_null
      79: astore_2
      80: aload_2
      81: ifnull        107
      84: aload_2
      85: invokestatic  #12                 // Method org/jboss/as/naming/service/DefaultNamespaceContextSelectorService.access$300:()Ljavax/naming/CompositeName;
      88: invokeinterface #13,  2           // InterfaceMethod org/jboss/as/naming/NamingStore.lookup:(Ljavax/naming/Name;)Ljava/lang/Object;
      93: checkcast     #14                 // class javax/naming/Context
      96: areturn
      97: astore_3
      98: new           #16                 // class java/lang/IllegalStateException
     101: dup
     102: aload_3
     103: invokespecial #17                 // Method java/lang/IllegalStateException."<init>":(Ljava/lang/Throwable;)V
     106: athrow
     107: aconst_null
     108: areturn
    Exception table:
       from    to  target type
          84    96    97   Class javax/naming/NamingException
}
