Compiled from "AccessAuditResourceDefinition.java"
public class org.jboss.as.domain.management.audit.AccessAuditResourceDefinition extends org.jboss.as.controller.SimpleResourceDefinition {
  public static final org.jboss.as.controller.PathElement PATH_ELEMENT;

  static final java.lang.String DEPRECATED_MESSAGE_CATEGORY;

  private final org.jboss.as.controller.audit.ManagedAuditLogger auditLogger;

  private final org.jboss.as.controller.services.path.PathManagerService pathManager;

  private final org.jboss.as.domain.management.audit.EnvironmentNameReader environmentReader;

  public org.jboss.as.domain.management.audit.AccessAuditResourceDefinition(org.jboss.as.controller.audit.ManagedAuditLogger, org.jboss.as.controller.services.path.PathManagerService, org.jboss.as.domain.management.audit.EnvironmentNameReader);
    Code:
       0: aload_0
       1: getstatic     #1                  // Field PATH_ELEMENT:Lorg/jboss/as/controller/PathElement;
       4: iconst_1
       5: anewarray     #2                  // class java/lang/String
       8: dup
       9: iconst_0
      10: ldc           #4                  // String core.management.audit-log
      12: aastore
      13: invokestatic  #5                  // Method org/jboss/as/domain/management/_private/DomainManagementResolver.getResolver:([Ljava/lang/String;)Lorg/jboss/as/controller/descriptions/ResourceDescriptionResolver;
      16: new           #6                  // class org/jboss/as/domain/management/audit/AccessAuditResourceDefinition$1
      19: dup
      20: invokespecial #7                  // Method org/jboss/as/domain/management/audit/AccessAuditResourceDefinition$1."<init>":()V
      23: new           #8                  // class org/jboss/as/domain/management/audit/AccessAuditResourceDefinition$2
      26: dup
      27: invokespecial #9                  // Method org/jboss/as/domain/management/audit/AccessAuditResourceDefinition$2."<init>":()V
      30: invokespecial #10                 // Method org/jboss/as/controller/SimpleResourceDefinition."<init>":(Lorg/jboss/as/controller/PathElement;Lorg/jboss/as/controller/descriptions/ResourceDescriptionResolver;Lorg/jboss/as/controller/OperationStepHandler;Lorg/jboss/as/controller/OperationStepHandler;)V
      33: aload_0
      34: aload_1
      35: putfield      #11                 // Field auditLogger:Lorg/jboss/as/controller/audit/ManagedAuditLogger;
      38: aload_0
      39: aload_2
      40: putfield      #12                 // Field pathManager:Lorg/jboss/as/controller/services/path/PathManagerService;
      43: aload_0
      44: aload_3
      45: putfield      #13                 // Field environmentReader:Lorg/jboss/as/domain/management/audit/EnvironmentNameReader;
      48: aload_0
      49: iconst_1
      50: bipush        7
      52: invokestatic  #14                 // Method org/jboss/as/controller/ModelVersion.create:(II)Lorg/jboss/as/controller/ModelVersion;
      55: invokevirtual #15                 // Method setDeprecated:(Lorg/jboss/as/controller/ModelVersion;)V
      58: return

  public void registerChildren(org.jboss.as.controller.registry.ManagementResourceRegistration);
    Code:
       0: aload_1
       1: new           #16                 // class org/jboss/as/domain/management/audit/JsonAuditLogFormatterResourceDefinition
       4: dup
       5: aload_0
       6: getfield      #11                 // Field auditLogger:Lorg/jboss/as/controller/audit/ManagedAuditLogger;
       9: invokespecial #17                 // Method org/jboss/as/domain/management/audit/JsonAuditLogFormatterResourceDefinition."<init>":(Lorg/jboss/as/controller/audit/ManagedAuditLogger;)V
      12: invokeinterface #18,  2           // InterfaceMethod org/jboss/as/controller/registry/ManagementResourceRegistration.registerSubModel:(Lorg/jboss/as/controller/ResourceDefinition;)Lorg/jboss/as/controller/registry/ManagementResourceRegistration;
      17: pop
      18: aload_1
      19: new           #19                 // class org/jboss/as/domain/management/audit/FileAuditLogHandlerResourceDefinition
      22: dup
      23: aload_0
      24: getfield      #11                 // Field auditLogger:Lorg/jboss/as/controller/audit/ManagedAuditLogger;
      27: aload_0
      28: getfield      #12                 // Field pathManager:Lorg/jboss/as/controller/services/path/PathManagerService;
      31: invokespecial #20                 // Method org/jboss/as/domain/management/audit/FileAuditLogHandlerResourceDefinition."<init>":(Lorg/jboss/as/controller/audit/ManagedAuditLogger;Lorg/jboss/as/controller/services/path/PathManagerService;)V
      34: invokeinterface #18,  2           // InterfaceMethod org/jboss/as/controller/registry/ManagementResourceRegistration.registerSubModel:(Lorg/jboss/as/controller/ResourceDefinition;)Lorg/jboss/as/controller/registry/ManagementResourceRegistration;
      39: pop
      40: aload_1
      41: new           #21                 // class org/jboss/as/domain/management/audit/PeriodicRotatingFileAuditLogHandlerResourceDefinition
      44: dup
      45: aload_0
      46: getfield      #11                 // Field auditLogger:Lorg/jboss/as/controller/audit/ManagedAuditLogger;
      49: aload_0
      50: getfield      #12                 // Field pathManager:Lorg/jboss/as/controller/services/path/PathManagerService;
      53: invokespecial #22                 // Method org/jboss/as/domain/management/audit/PeriodicRotatingFileAuditLogHandlerResourceDefinition."<init>":(Lorg/jboss/as/controller/audit/ManagedAuditLogger;Lorg/jboss/as/controller/services/path/PathManagerService;)V
      56: invokeinterface #18,  2           // InterfaceMethod org/jboss/as/controller/registry/ManagementResourceRegistration.registerSubModel:(Lorg/jboss/as/controller/ResourceDefinition;)Lorg/jboss/as/controller/registry/ManagementResourceRegistration;
      61: pop
      62: aload_1
      63: new           #23                 // class org/jboss/as/domain/management/audit/SizeRotatingFileAuditLogHandlerResourceDefinition
      66: dup
      67: aload_0
      68: getfield      #11                 // Field auditLogger:Lorg/jboss/as/controller/audit/ManagedAuditLogger;
      71: aload_0
      72: getfield      #12                 // Field pathManager:Lorg/jboss/as/controller/services/path/PathManagerService;
      75: invokespecial #24                 // Method org/jboss/as/domain/management/audit/SizeRotatingFileAuditLogHandlerResourceDefinition."<init>":(Lorg/jboss/as/controller/audit/ManagedAuditLogger;Lorg/jboss/as/controller/services/path/PathManagerService;)V
      78: invokeinterface #18,  2           // InterfaceMethod org/jboss/as/controller/registry/ManagementResourceRegistration.registerSubModel:(Lorg/jboss/as/controller/ResourceDefinition;)Lorg/jboss/as/controller/registry/ManagementResourceRegistration;
      83: pop
      84: aload_1
      85: new           #25                 // class org/jboss/as/domain/management/audit/SyslogAuditLogHandlerResourceDefinition
      88: dup
      89: aload_0
      90: getfield      #11                 // Field auditLogger:Lorg/jboss/as/controller/audit/ManagedAuditLogger;
      93: aload_0
      94: getfield      #12                 // Field pathManager:Lorg/jboss/as/controller/services/path/PathManagerService;
      97: aload_0
      98: getfield      #13                 // Field environmentReader:Lorg/jboss/as/domain/management/audit/EnvironmentNameReader;
     101: invokespecial #26                 // Method org/jboss/as/domain/management/audit/SyslogAuditLogHandlerResourceDefinition."<init>":(Lorg/jboss/as/controller/audit/ManagedAuditLogger;Lorg/jboss/as/controller/services/path/PathManagerService;Lorg/jboss/as/domain/management/audit/EnvironmentNameReader;)V
     104: invokeinterface #18,  2           // InterfaceMethod org/jboss/as/controller/registry/ManagementResourceRegistration.registerSubModel:(Lorg/jboss/as/controller/ResourceDefinition;)Lorg/jboss/as/controller/registry/ManagementResourceRegistration;
     109: pop
     110: aload_1
     111: new           #27                 // class org/jboss/as/domain/management/audit/InMemoryAuditLogHandlerResourceDefinition
     114: dup
     115: aload_0
     116: getfield      #11                 // Field auditLogger:Lorg/jboss/as/controller/audit/ManagedAuditLogger;
     119: invokespecial #28                 // Method org/jboss/as/domain/management/audit/InMemoryAuditLogHandlerResourceDefinition."<init>":(Lorg/jboss/as/controller/audit/ManagedAuditLogger;)V
     122: invokeinterface #18,  2           // InterfaceMethod org/jboss/as/controller/registry/ManagementResourceRegistration.registerSubModel:(Lorg/jboss/as/controller/ResourceDefinition;)Lorg/jboss/as/controller/registry/ManagementResourceRegistration;
     127: pop
     128: aload_1
     129: aload_0
     130: getfield      #11                 // Field auditLogger:Lorg/jboss/as/controller/audit/ManagedAuditLogger;
     133: invokestatic  #29                 // Method org/jboss/as/domain/management/audit/AuditLogLoggerResourceDefinition.createDefinition:(Lorg/jboss/as/controller/audit/ManagedAuditLogger;)Lorg/jboss/as/domain/management/audit/AuditLogLoggerResourceDefinition;
     136: invokeinterface #18,  2           // InterfaceMethod org/jboss/as/controller/registry/ManagementResourceRegistration.registerSubModel:(Lorg/jboss/as/controller/ResourceDefinition;)Lorg/jboss/as/controller/registry/ManagementResourceRegistration;
     141: pop
     142: aload_0
     143: getfield      #13                 // Field environmentReader:Lorg/jboss/as/domain/management/audit/EnvironmentNameReader;
     146: invokeinterface #30,  1           // InterfaceMethod org/jboss/as/domain/management/audit/EnvironmentNameReader.isServer:()Z
     151: ifne          168
     154: aload_1
     155: aload_0
     156: getfield      #11                 // Field auditLogger:Lorg/jboss/as/controller/audit/ManagedAuditLogger;
     159: invokestatic  #31                 // Method org/jboss/as/domain/management/audit/AuditLogLoggerResourceDefinition.createHostServerDefinition:(Lorg/jboss/as/controller/audit/ManagedAuditLogger;)Lorg/jboss/as/domain/management/audit/AuditLogLoggerResourceDefinition;
     162: invokeinterface #18,  2           // InterfaceMethod org/jboss/as/controller/registry/ManagementResourceRegistration.registerSubModel:(Lorg/jboss/as/controller/ResourceDefinition;)Lorg/jboss/as/controller/registry/ManagementResourceRegistration;
     167: pop
     168: return

  static {};
    Code:
       0: ldc           #33                 // String access
       2: ldc           #34                 // String audit
       4: invokestatic  #35                 // Method org/jboss/as/controller/PathElement.pathElement:(Ljava/lang/String;Ljava/lang/String;)Lorg/jboss/as/controller/PathElement;
       7: putstatic     #1                  // Field PATH_ELEMENT:Lorg/jboss/as/controller/PathElement;
      10: return
}
