Compiled from "AuditLogHandlerReferenceResourceDefinition.java"
class org.jboss.as.domain.management.audit.AuditLogHandlerReferenceResourceDefinition$AuditLogHandlerReferenceAddHandler extends org.jboss.as.controller.AbstractAddStepHandler {
  private final org.jboss.as.controller.audit.ManagedAuditLogger auditLogger;

  private final boolean executeRuntime;

  org.jboss.as.domain.management.audit.AuditLogHandlerReferenceResourceDefinition$AuditLogHandlerReferenceAddHandler(org.jboss.as.controller.audit.ManagedAuditLogger, boolean);
    Code:
       0: aload_0
       1: invokespecial #2                  // Method org/jboss/as/controller/AbstractAddStepHandler."<init>":()V
       4: aload_0
       5: aload_1
       6: putfield      #3                  // Field auditLogger:Lorg/jboss/as/controller/audit/ManagedAuditLogger;
       9: aload_0
      10: iload_2
      11: putfield      #4                  // Field executeRuntime:Z
      14: return

  protected void populateModel(org.jboss.as.controller.OperationContext, org.jboss.dmr.ModelNode, org.jboss.as.controller.registry.Resource) throws org.jboss.as.controller.OperationFailedException;
    Code:
       0: aload_2
       1: ldc           #5                  // String address
       3: invokevirtual #6                  // Method org/jboss/dmr/ModelNode.require:(Ljava/lang/String;)Lorg/jboss/dmr/ModelNode;
       6: invokestatic  #7                  // Method org/jboss/as/controller/PathAddress.pathAddress:(Lorg/jboss/dmr/ModelNode;)Lorg/jboss/as/controller/PathAddress;
       9: astore        4
      11: aload         4
      13: invokevirtual #8                  // Method org/jboss/as/controller/PathAddress.getLastElement:()Lorg/jboss/as/controller/PathElement;
      16: invokevirtual #9                  // Method org/jboss/as/controller/PathElement.getValue:()Ljava/lang/String;
      19: astore        5
      21: aload_1
      22: aload         4
      24: aload         5
      26: invokestatic  #10                 // Method org/jboss/as/domain/management/audit/HandlerUtil.lookForHandler:(Lorg/jboss/as/controller/OperationContext;Lorg/jboss/as/controller/PathAddress;Ljava/lang/String;)Z
      29: ifne          43
      32: getstatic     #11                 // Field org/jboss/as/domain/management/logging/DomainManagementLogger.ROOT_LOGGER:Lorg/jboss/as/domain/management/logging/DomainManagementLogger;
      35: aload         5
      37: invokeinterface #12,  2           // InterfaceMethod org/jboss/as/domain/management/logging/DomainManagementLogger.noHandlerCalled:(Ljava/lang/String;)Ljava/lang/IllegalStateException;
      42: athrow
      43: aload_3
      44: invokeinterface #13,  1           // InterfaceMethod org/jboss/as/controller/registry/Resource.getModel:()Lorg/jboss/dmr/ModelNode;
      49: invokevirtual #14                 // Method org/jboss/dmr/ModelNode.setEmptyObject:()Lorg/jboss/dmr/ModelNode;
      52: pop
      53: return

  protected boolean requiresRuntime(org.jboss.as.controller.OperationContext);
    Code:
       0: aload_0
       1: getfield      #4                  // Field executeRuntime:Z
       4: ireturn

  protected void performRuntime(org.jboss.as.controller.OperationContext, org.jboss.dmr.ModelNode, org.jboss.dmr.ModelNode) throws org.jboss.as.controller.OperationFailedException;
    Code:
       0: aload_0
       1: getfield      #3                  // Field auditLogger:Lorg/jboss/as/controller/audit/ManagedAuditLogger;
       4: invokeinterface #15,  1           // InterfaceMethod org/jboss/as/controller/audit/ManagedAuditLogger.getUpdater:()Lorg/jboss/as/controller/audit/ManagedAuditLogger$AuditLogHandlerUpdater;
       9: aload_2
      10: ldc           #5                  // String address
      12: invokevirtual #6                  // Method org/jboss/dmr/ModelNode.require:(Ljava/lang/String;)Lorg/jboss/dmr/ModelNode;
      15: invokestatic  #7                  // Method org/jboss/as/controller/PathAddress.pathAddress:(Lorg/jboss/dmr/ModelNode;)Lorg/jboss/as/controller/PathAddress;
      18: invokeinterface #16,  2           // InterfaceMethod org/jboss/as/controller/audit/ManagedAuditLogger$AuditLogHandlerUpdater.addHandlerReference:(Lorg/jboss/as/controller/PathAddress;)V
      23: return

  protected void rollbackRuntime(org.jboss.as.controller.OperationContext, org.jboss.dmr.ModelNode, org.jboss.as.controller.registry.Resource);
    Code:
       0: aload_0
       1: getfield      #3                  // Field auditLogger:Lorg/jboss/as/controller/audit/ManagedAuditLogger;
       4: invokeinterface #15,  1           // InterfaceMethod org/jboss/as/controller/audit/ManagedAuditLogger.getUpdater:()Lorg/jboss/as/controller/audit/ManagedAuditLogger$AuditLogHandlerUpdater;
       9: invokeinterface #17,  1           // InterfaceMethod org/jboss/as/controller/audit/ManagedAuditLogger$AuditLogHandlerUpdater.rollbackChanges:()V
      14: return
}
