Compiled from "AnnotationConstructorCaller.kt"
public final class kotlin.reflect.jvm.internal.calls.AnnotationConstructorCaller$CallMode extends java.lang.Enum<kotlin.reflect.jvm.internal.calls.AnnotationConstructorCaller$CallMode> {
  public static final kotlin.reflect.jvm.internal.calls.AnnotationConstructorCaller$CallMode CALL_BY_NAME;

  public static final kotlin.reflect.jvm.internal.calls.AnnotationConstructorCaller$CallMode POSITIONAL_CALL;

  private static final kotlin.reflect.jvm.internal.calls.AnnotationConstructorCaller$CallMode[] $VALUES;

  static {};
    Code:
       0: iconst_2
       1: anewarray     #10                 // class kotlin/reflect/jvm/internal/calls/AnnotationConstructorCaller$CallMode
       4: dup
       5: dup
       6: iconst_0
       7: new           #10                 // class kotlin/reflect/jvm/internal/calls/AnnotationConstructorCaller$CallMode
      10: dup
      11: ldc           #5                  // String CALL_BY_NAME
      13: iconst_0
      14: invokespecial #17                 // Method "<init>":(Ljava/lang/String;I)V
      17: dup
      18: putstatic     #12                 // Field CALL_BY_NAME:Lkotlin/reflect/jvm/internal/calls/AnnotationConstructorCaller$CallMode;
      21: aastore
      22: dup
      23: iconst_1
      24: new           #10                 // class kotlin/reflect/jvm/internal/calls/AnnotationConstructorCaller$CallMode
      27: dup
      28: ldc           #6                  // String POSITIONAL_CALL
      30: iconst_1
      31: invokespecial #17                 // Method "<init>":(Ljava/lang/String;I)V
      34: dup
      35: putstatic     #13                 // Field POSITIONAL_CALL:Lkotlin/reflect/jvm/internal/calls/AnnotationConstructorCaller$CallMode;
      38: aastore
      39: putstatic     #11                 // Field $VALUES:[Lkotlin/reflect/jvm/internal/calls/AnnotationConstructorCaller$CallMode;
      42: return

  protected kotlin.reflect.jvm.internal.calls.AnnotationConstructorCaller$CallMode();
    Code:
       0: aload_0
       1: aload_1
       2: iload_2
       3: invokespecial #15                 // Method java/lang/Enum."<init>":(Ljava/lang/String;I)V
       6: return

  public static kotlin.reflect.jvm.internal.calls.AnnotationConstructorCaller$CallMode[] values();
    Code:
       0: getstatic     #11                 // Field $VALUES:[Lkotlin/reflect/jvm/internal/calls/AnnotationConstructorCaller$CallMode;
       3: invokevirtual #14                 // Method "[Lkotlin/reflect/jvm/internal/calls/AnnotationConstructorCaller$CallMode;".clone:()Ljava/lang/Object;
       6: checkcast     #7                  // class "[Lkotlin/reflect/jvm/internal/calls/AnnotationConstructorCaller$CallMode;"
       9: areturn

  public static kotlin.reflect.jvm.internal.calls.AnnotationConstructorCaller$CallMode valueOf(java.lang.String);
    Code:
       0: ldc           #10                 // class kotlin/reflect/jvm/internal/calls/AnnotationConstructorCaller$CallMode
       2: aload_0
       3: invokestatic  #16                 // Method java/lang/Enum.valueOf:(Ljava/lang/Class;Ljava/lang/String;)Ljava/lang/Enum;
       6: checkcast     #10                 // class kotlin/reflect/jvm/internal/calls/AnnotationConstructorCaller$CallMode
       9: areturn
}
