Compiled from "ColumnAliasExtractor.java"
public interface org.hibernate.dialect.ColumnAliasExtractor {
  public static final org.hibernate.dialect.ColumnAliasExtractor COLUMN_LABEL_EXTRACTOR;

  public static final org.hibernate.dialect.ColumnAliasExtractor COLUMN_NAME_EXTRACTOR;

  public abstract java.lang.String extractColumnAlias(java.sql.ResultSetMetaData, int) throws java.sql.SQLException;

  static {};
    Code:
       0: new           #1                  // class org/hibernate/dialect/ColumnAliasExtractor$1
       3: dup
       4: invokespecial #2                  // Method org/hibernate/dialect/ColumnAliasExtractor$1."<init>":()V
       7: putstatic     #3                  // Field COLUMN_LABEL_EXTRACTOR:Lorg/hibernate/dialect/ColumnAliasExtractor;
      10: new           #4                  // class org/hibernate/dialect/ColumnAliasExtractor$2
      13: dup
      14: invokespecial #5                  // Method org/hibernate/dialect/ColumnAliasExtractor$2."<init>":()V
      17: putstatic     #6                  // Field COLUMN_NAME_EXTRACTOR:Lorg/hibernate/dialect/ColumnAliasExtractor;
      20: return
}
