Compiled from "DerbyTenFiveDialect.java"
public class org.hibernate.dialect.DerbyTenFiveDialect extends org.hibernate.dialect.DerbyDialect {
  public org.hibernate.dialect.DerbyTenFiveDialect();
    Code:
       0: aload_0
       1: invokespecial #1                  // Method org/hibernate/dialect/DerbyDialect."<init>":()V
       4: aload_0
       5: ldc           #2                  // String concat
       7: new           #3                  // class org/hibernate/dialect/function/DerbyConcatFunction
      10: dup
      11: invokespecial #4                  // Method org/hibernate/dialect/function/DerbyConcatFunction."<init>":()V
      14: invokevirtual #5                  // Method registerFunction:(Ljava/lang/String;Lorg/hibernate/dialect/function/SQLFunction;)V
      17: aload_0
      18: ldc           #6                  // String trim
      20: new           #7                  // class org/hibernate/dialect/function/AnsiTrimFunction
      23: dup
      24: invokespecial #8                  // Method org/hibernate/dialect/function/AnsiTrimFunction."<init>":()V
      27: invokevirtual #5                  // Method registerFunction:(Ljava/lang/String;Lorg/hibernate/dialect/function/SQLFunction;)V
      30: return

  public boolean supportsSequences();
    Code:
       0: iconst_0
       1: ireturn

  public boolean supportsLimit();
    Code:
       0: iconst_1
       1: ireturn

  public boolean supportsLimitOffset();
    Code:
       0: iconst_1
       1: ireturn
}
