Compiled from "SybaseAnywhereDialect.java"
public class org.hibernate.dialect.SybaseAnywhereDialect extends org.hibernate.dialect.SybaseDialect {
  public org.hibernate.dialect.SybaseAnywhereDialect();
    Code:
       0: aload_0
       1: invokespecial #1                  // Method org/hibernate/dialect/SybaseDialect."<init>":()V
       4: return

  public java.lang.String getNoColumnsInsertString();
    Code:
       0: ldc           #2                  // String values (default)
       2: areturn

  public boolean dropConstraints();
    Code:
       0: iconst_0
       1: ireturn

  public org.hibernate.dialect.identity.IdentityColumnSupport getIdentityColumnSupport();
    Code:
       0: new           #3                  // class org/hibernate/dialect/identity/SybaseAnywhereIdentityColumnSupport
       3: dup
       4: invokespecial #4                  // Method org/hibernate/dialect/identity/SybaseAnywhereIdentityColumnSupport."<init>":()V
       7: areturn
}
