Compiled from "Rule.java"
public final class io.swagger.codegen.v3.ignore.rules.Rule$Operation extends java.lang.Enum<io.swagger.codegen.v3.ignore.rules.Rule$Operation> {
  public static final io.swagger.codegen.v3.ignore.rules.Rule$Operation EXCLUDE;

  public static final io.swagger.codegen.v3.ignore.rules.Rule$Operation INCLUDE;

  public static final io.swagger.codegen.v3.ignore.rules.Rule$Operation NOOP;

  public static final io.swagger.codegen.v3.ignore.rules.Rule$Operation EXCLUDE_AND_TERMINATE;

  private static final io.swagger.codegen.v3.ignore.rules.Rule$Operation[] $VALUES;

  public static io.swagger.codegen.v3.ignore.rules.Rule$Operation[] values();
    Code:
       0: getstatic     #1                  // Field $VALUES:[Lio/swagger/codegen/v3/ignore/rules/Rule$Operation;
       3: invokevirtual #2                  // Method "[Lio/swagger/codegen/v3/ignore/rules/Rule$Operation;".clone:()Ljava/lang/Object;
       6: checkcast     #3                  // class "[Lio/swagger/codegen/v3/ignore/rules/Rule$Operation;"
       9: areturn

  public static io.swagger.codegen.v3.ignore.rules.Rule$Operation valueOf(java.lang.String);
    Code:
       0: ldc           #4                  // class io/swagger/codegen/v3/ignore/rules/Rule$Operation
       2: aload_0
       3: invokestatic  #5                  // Method java/lang/Enum.valueOf:(Ljava/lang/Class;Ljava/lang/String;)Ljava/lang/Enum;
       6: checkcast     #4                  // class io/swagger/codegen/v3/ignore/rules/Rule$Operation
       9: areturn

  private io.swagger.codegen.v3.ignore.rules.Rule$Operation();
    Code:
       0: aload_0
       1: aload_1
       2: iload_2
       3: invokespecial #6                  // Method java/lang/Enum."<init>":(Ljava/lang/String;I)V
       6: return

  static {};
    Code:
       0: new           #4                  // class io/swagger/codegen/v3/ignore/rules/Rule$Operation
       3: dup
       4: ldc           #7                  // String EXCLUDE
       6: iconst_0
       7: invokespecial #8                  // Method "<init>":(Ljava/lang/String;I)V
      10: putstatic     #9                  // Field EXCLUDE:Lio/swagger/codegen/v3/ignore/rules/Rule$Operation;
      13: new           #4                  // class io/swagger/codegen/v3/ignore/rules/Rule$Operation
      16: dup
      17: ldc           #10                 // String INCLUDE
      19: iconst_1
      20: invokespecial #8                  // Method "<init>":(Ljava/lang/String;I)V
      23: putstatic     #11                 // Field INCLUDE:Lio/swagger/codegen/v3/ignore/rules/Rule$Operation;
      26: new           #4                  // class io/swagger/codegen/v3/ignore/rules/Rule$Operation
      29: dup
      30: ldc           #12                 // String NOOP
      32: iconst_2
      33: invokespecial #8                  // Method "<init>":(Ljava/lang/String;I)V
      36: putstatic     #13                 // Field NOOP:Lio/swagger/codegen/v3/ignore/rules/Rule$Operation;
      39: new           #4                  // class io/swagger/codegen/v3/ignore/rules/Rule$Operation
      42: dup
      43: ldc           #14                 // String EXCLUDE_AND_TERMINATE
      45: iconst_3
      46: invokespecial #8                  // Method "<init>":(Ljava/lang/String;I)V
      49: putstatic     #15                 // Field EXCLUDE_AND_TERMINATE:Lio/swagger/codegen/v3/ignore/rules/Rule$Operation;
      52: iconst_4
      53: anewarray     #4                  // class io/swagger/codegen/v3/ignore/rules/Rule$Operation
      56: dup
      57: iconst_0
      58: getstatic     #9                  // Field EXCLUDE:Lio/swagger/codegen/v3/ignore/rules/Rule$Operation;
      61: aastore
      62: dup
      63: iconst_1
      64: getstatic     #11                 // Field INCLUDE:Lio/swagger/codegen/v3/ignore/rules/Rule$Operation;
      67: aastore
      68: dup
      69: iconst_2
      70: getstatic     #13                 // Field NOOP:Lio/swagger/codegen/v3/ignore/rules/Rule$Operation;
      73: aastore
      74: dup
      75: iconst_3
      76: getstatic     #15                 // Field EXCLUDE_AND_TERMINATE:Lio/swagger/codegen/v3/ignore/rules/Rule$Operation;
      79: aastore
      80: putstatic     #1                  // Field $VALUES:[Lio/swagger/codegen/v3/ignore/rules/Rule$Operation;
      83: return
}
