Compiled from "TcpTransport.java"
class org.apache.activemq.transport.tcp.TcpTransport$1 implements java.lang.Runnable {
  final java.util.concurrent.CountDownLatch val$latch;

  final org.apache.activemq.transport.tcp.TcpTransport this$0;

  org.apache.activemq.transport.tcp.TcpTransport$1(org.apache.activemq.transport.tcp.TcpTransport, java.util.concurrent.CountDownLatch);
    Code:
       0: aload_0
       1: aload_1
       2: putfield      #1                  // Field this$0:Lorg/apache/activemq/transport/tcp/TcpTransport;
       5: aload_0
       6: aload_2
       7: putfield      #2                  // Field val$latch:Ljava/util/concurrent/CountDownLatch;
      10: aload_0
      11: invokespecial #3                  // Method java/lang/Object."<init>":()V
      14: return

  public void run();
    Code:
       0: invokestatic  #4                  // Method org/apache/activemq/transport/tcp/TcpTransport.access$000:()Lorg/slf4j/Logger;
       3: ldc           #5                  // String Closing socket {}
       5: aload_0
       6: getfield      #1                  // Field this$0:Lorg/apache/activemq/transport/tcp/TcpTransport;
       9: getfield      #6                  // Field org/apache/activemq/transport/tcp/TcpTransport.socket:Ljava/net/Socket;
      12: invokeinterface #7,  3            // InterfaceMethod org/slf4j/Logger.trace:(Ljava/lang/String;Ljava/lang/Object;)V
      17: aload_0
      18: getfield      #1                  // Field this$0:Lorg/apache/activemq/transport/tcp/TcpTransport;
      21: getfield      #6                  // Field org/apache/activemq/transport/tcp/TcpTransport.socket:Ljava/net/Socket;
      24: invokevirtual #8                  // Method java/net/Socket.close:()V
      27: invokestatic  #4                  // Method org/apache/activemq/transport/tcp/TcpTransport.access$000:()Lorg/slf4j/Logger;
      30: ldc           #9                  // String Closed socket {}
      32: aload_0
      33: getfield      #1                  // Field this$0:Lorg/apache/activemq/transport/tcp/TcpTransport;
      36: getfield      #6                  // Field org/apache/activemq/transport/tcp/TcpTransport.socket:Ljava/net/Socket;
      39: invokeinterface #10,  3           // InterfaceMethod org/slf4j/Logger.debug:(Ljava/lang/String;Ljava/lang/Object;)V
      44: aload_0
      45: getfield      #2                  // Field val$latch:Ljava/util/concurrent/CountDownLatch;
      48: invokevirtual #11                 // Method java/util/concurrent/CountDownLatch.countDown:()V
      51: goto          125
      54: astore_1
      55: invokestatic  #4                  // Method org/apache/activemq/transport/tcp/TcpTransport.access$000:()Lorg/slf4j/Logger;
      58: invokeinterface #13,  1           // InterfaceMethod org/slf4j/Logger.isDebugEnabled:()Z
      63: ifeq          105
      66: invokestatic  #4                  // Method org/apache/activemq/transport/tcp/TcpTransport.access$000:()Lorg/slf4j/Logger;
      69: new           #14                 // class java/lang/StringBuilder
      72: dup
      73: invokespecial #15                 // Method java/lang/StringBuilder."<init>":()V
      76: ldc           #16                 // String Caught exception closing socket
      78: invokevirtual #17                 // Method java/lang/StringBuilder.append:(Ljava/lang/String;)Ljava/lang/StringBuilder;
      81: aload_0
      82: getfield      #1                  // Field this$0:Lorg/apache/activemq/transport/tcp/TcpTransport;
      85: getfield      #6                  // Field org/apache/activemq/transport/tcp/TcpTransport.socket:Ljava/net/Socket;
      88: invokevirtual #18                 // Method java/lang/StringBuilder.append:(Ljava/lang/Object;)Ljava/lang/StringBuilder;
      91: ldc           #19                 // String . This exception will be ignored.
      93: invokevirtual #17                 // Method java/lang/StringBuilder.append:(Ljava/lang/String;)Ljava/lang/StringBuilder;
      96: invokevirtual #20                 // Method java/lang/StringBuilder.toString:()Ljava/lang/String;
      99: aload_1
     100: invokeinterface #21,  3           // InterfaceMethod org/slf4j/Logger.debug:(Ljava/lang/String;Ljava/lang/Throwable;)V
     105: aload_0
     106: getfield      #2                  // Field val$latch:Ljava/util/concurrent/CountDownLatch;
     109: invokevirtual #11                 // Method java/util/concurrent/CountDownLatch.countDown:()V
     112: goto          125
     115: astore_2
     116: aload_0
     117: getfield      #2                  // Field val$latch:Ljava/util/concurrent/CountDownLatch;
     120: invokevirtual #11                 // Method java/util/concurrent/CountDownLatch.countDown:()V
     123: aload_2
     124: athrow
     125: return
    Exception table:
       from    to  target type
          17    44    54   Class java/io/IOException
          17    44   115   any
          54   105   115   any
         115   116   115   any
}
