Compiled from "SyntheticClassBean.java"
public class org.jboss.weld.bean.SyntheticClassBean<T> extends org.jboss.weld.bean.AbstractSyntheticBean<T> {
  protected final javax.enterprise.inject.spi.InjectionTarget<T> producer;

  public org.jboss.weld.bean.SyntheticClassBean(javax.enterprise.inject.spi.BeanAttributes<T>, java.lang.Class<T>, javax.enterprise.inject.spi.InjectionTargetFactory<T>, org.jboss.weld.manager.BeanManagerImpl);
    Code:
       0: aload_0
       1: aload_1
       2: aload         4
       4: aload_2
       5: invokespecial #1                  // Method org/jboss/weld/bean/AbstractSyntheticBean."<init>":(Ljavax/enterprise/inject/spi/BeanAttributes;Lorg/jboss/weld/manager/BeanManagerImpl;Ljava/lang/Class;)V
       8: aload_0
       9: aload_3
      10: aload_0
      11: invokeinterface #2,  2            // InterfaceMethod javax/enterprise/inject/spi/InjectionTargetFactory.createInjectionTarget:(Ljavax/enterprise/inject/spi/Bean;)Ljavax/enterprise/inject/spi/InjectionTarget;
      16: putfield      #3                  // Field producer:Ljavax/enterprise/inject/spi/InjectionTarget;
      19: return

  public T create(javax.enterprise.context.spi.CreationalContext<T>);
    Code:
       0: aload_0
       1: getfield      #3                  // Field producer:Ljavax/enterprise/inject/spi/InjectionTarget;
       4: aload_1
       5: invokeinterface #4,  2            // InterfaceMethod javax/enterprise/inject/spi/InjectionTarget.produce:(Ljavax/enterprise/context/spi/CreationalContext;)Ljava/lang/Object;
      10: astore_2
      11: aload_0
      12: getfield      #3                  // Field producer:Ljavax/enterprise/inject/spi/InjectionTarget;
      15: aload_2
      16: aload_1
      17: invokeinterface #5,  3            // InterfaceMethod javax/enterprise/inject/spi/InjectionTarget.inject:(Ljava/lang/Object;Ljavax/enterprise/context/spi/CreationalContext;)V
      22: aload_0
      23: getfield      #3                  // Field producer:Ljavax/enterprise/inject/spi/InjectionTarget;
      26: aload_2
      27: invokeinterface #6,  2            // InterfaceMethod javax/enterprise/inject/spi/InjectionTarget.postConstruct:(Ljava/lang/Object;)V
      32: aload_2
      33: areturn

  public void destroy(T, javax.enterprise.context.spi.CreationalContext<T>);
    Code:
       0: aload_0
       1: getfield      #3                  // Field producer:Ljavax/enterprise/inject/spi/InjectionTarget;
       4: aload_1
       5: invokeinterface #7,  2            // InterfaceMethod javax/enterprise/inject/spi/InjectionTarget.preDestroy:(Ljava/lang/Object;)V
      10: aload_0
      11: getfield      #3                  // Field producer:Ljavax/enterprise/inject/spi/InjectionTarget;
      14: aload_1
      15: invokeinterface #8,  2            // InterfaceMethod javax/enterprise/inject/spi/InjectionTarget.dispose:(Ljava/lang/Object;)V
      20: aload_2
      21: invokeinterface #9,  1            // InterfaceMethod javax/enterprise/context/spi/CreationalContext.release:()V
      26: goto          38
      29: astore_3
      30: aload_2
      31: invokeinterface #9,  1            // InterfaceMethod javax/enterprise/context/spi/CreationalContext.release:()V
      36: aload_3
      37: athrow
      38: return
    Exception table:
       from    to  target type
           0    20    29   any

  protected javax.enterprise.inject.spi.InjectionTarget<T> getProducer();
    Code:
       0: aload_0
       1: getfield      #3                  // Field producer:Ljavax/enterprise/inject/spi/InjectionTarget;
       4: areturn

  public java.lang.String toString();
    Code:
       0: new           #10                 // class java/lang/StringBuilder
       3: dup
       4: invokespecial #11                 // Method java/lang/StringBuilder."<init>":()V
       7: ldc           #12                 // String SyntheticClassBean [attributes=
       9: invokevirtual #13                 // Method java/lang/StringBuilder.append:(Ljava/lang/String;)Ljava/lang/StringBuilder;
      12: aload_0
      13: invokevirtual #14                 // Method attributes:()Ljavax/enterprise/inject/spi/BeanAttributes;
      16: invokevirtual #15                 // Method java/lang/StringBuilder.append:(Ljava/lang/Object;)Ljava/lang/StringBuilder;
      19: ldc           #16                 // String , injectionTarget=
      21: invokevirtual #13                 // Method java/lang/StringBuilder.append:(Ljava/lang/String;)Ljava/lang/StringBuilder;
      24: aload_0
      25: getfield      #3                  // Field producer:Ljavax/enterprise/inject/spi/InjectionTarget;
      28: invokevirtual #17                 // Method java/lang/Object.getClass:()Ljava/lang/Class;
      31: invokevirtual #15                 // Method java/lang/StringBuilder.append:(Ljava/lang/Object;)Ljava/lang/StringBuilder;
      34: ldc           #18                 // String , beanClass=
      36: invokevirtual #13                 // Method java/lang/StringBuilder.append:(Ljava/lang/String;)Ljava/lang/StringBuilder;
      39: aload_0
      40: invokevirtual #19                 // Method getBeanClass:()Ljava/lang/Class;
      43: invokevirtual #15                 // Method java/lang/StringBuilder.append:(Ljava/lang/Object;)Ljava/lang/StringBuilder;
      46: ldc           #20                 // String ]
      48: invokevirtual #13                 // Method java/lang/StringBuilder.append:(Ljava/lang/String;)Ljava/lang/StringBuilder;
      51: invokevirtual #21                 // Method java/lang/StringBuilder.toString:()Ljava/lang/String;
      54: areturn

  protected javax.enterprise.inject.spi.Producer getProducer();
    Code:
       0: aload_0
       1: invokevirtual #22                 // Method getProducer:()Ljavax/enterprise/inject/spi/InjectionTarget;
       4: areturn
}
