Compiled from "ChildLoadBalancerHelper.java"
final class io.grpc.rls.ChildLoadBalancerHelper$ChildLoadBalancerHelperProvider {
  private final io.grpc.LoadBalancer$Helper helper;

  private final io.grpc.rls.SubchannelStateManager subchannelStateManager;

  private final io.grpc.LoadBalancer$SubchannelPicker picker;

  io.grpc.rls.ChildLoadBalancerHelper$ChildLoadBalancerHelperProvider(io.grpc.LoadBalancer$Helper, io.grpc.rls.SubchannelStateManager, io.grpc.LoadBalancer$SubchannelPicker);
    Code:
       0: aload_0
       1: invokespecial #1                  // Method java/lang/Object."<init>":()V
       4: aload_0
       5: aload_1
       6: ldc           #2                  // String helper
       8: invokestatic  #3                  // Method com/google/common/base/Preconditions.checkNotNull:(Ljava/lang/Object;Ljava/lang/Object;)Ljava/lang/Object;
      11: checkcast     #4                  // class io/grpc/LoadBalancer$Helper
      14: putfield      #5                  // Field helper:Lio/grpc/LoadBalancer$Helper;
      17: aload_0
      18: aload_2
      19: ldc           #6                  // String subchannelStateManager
      21: invokestatic  #3                  // Method com/google/common/base/Preconditions.checkNotNull:(Ljava/lang/Object;Ljava/lang/Object;)Ljava/lang/Object;
      24: checkcast     #7                  // class io/grpc/rls/SubchannelStateManager
      27: putfield      #8                  // Field subchannelStateManager:Lio/grpc/rls/SubchannelStateManager;
      30: aload_0
      31: aload_3
      32: ldc           #9                  // String picker
      34: invokestatic  #3                  // Method com/google/common/base/Preconditions.checkNotNull:(Ljava/lang/Object;Ljava/lang/Object;)Ljava/lang/Object;
      37: checkcast     #10                 // class io/grpc/LoadBalancer$SubchannelPicker
      40: putfield      #11                 // Field picker:Lio/grpc/LoadBalancer$SubchannelPicker;
      43: return

  io.grpc.rls.ChildLoadBalancerHelper forTarget(java.lang.String);
    Code:
       0: new           #12                 // class io/grpc/rls/ChildLoadBalancerHelper
       3: dup
       4: aload_1
       5: aload_0
       6: getfield      #5                  // Field helper:Lio/grpc/LoadBalancer$Helper;
       9: aload_0
      10: getfield      #8                  // Field subchannelStateManager:Lio/grpc/rls/SubchannelStateManager;
      13: aload_0
      14: getfield      #11                 // Field picker:Lio/grpc/LoadBalancer$SubchannelPicker;
      17: aconst_null
      18: invokespecial #13                 // Method io/grpc/rls/ChildLoadBalancerHelper."<init>":(Ljava/lang/String;Lio/grpc/LoadBalancer$Helper;Lio/grpc/rls/SubchannelStateManager;Lio/grpc/LoadBalancer$SubchannelPicker;Lio/grpc/rls/ChildLoadBalancerHelper$1;)V
      21: areturn
}
