Compiled from "LbPolicyConfiguration.java"
final class io.grpc.rls.LbPolicyConfiguration$RefCountedChildPolicyWrapper implements io.grpc.internal.ObjectPool<io.grpc.rls.LbPolicyConfiguration$ChildPolicyWrapper> {
  private final java.util.concurrent.atomic.AtomicLong refCnt;

  private io.grpc.rls.LbPolicyConfiguration$ChildPolicyWrapper childPolicyWrapper;

  private io.grpc.rls.LbPolicyConfiguration$RefCountedChildPolicyWrapper(io.grpc.rls.LbPolicyConfiguration$ChildPolicyWrapper);
    Code:
       0: aload_0
       1: invokespecial #1                  // Method java/lang/Object."<init>":()V
       4: aload_0
       5: new           #2                  // class java/util/concurrent/atomic/AtomicLong
       8: dup
       9: invokespecial #3                  // Method java/util/concurrent/atomic/AtomicLong."<init>":()V
      12: putfield      #4                  // Field refCnt:Ljava/util/concurrent/atomic/AtomicLong;
      15: aload_0
      16: aload_1
      17: ldc           #5                  // String childPolicyWrapper
      19: invokestatic  #6                  // Method com/google/common/base/Preconditions.checkNotNull:(Ljava/lang/Object;Ljava/lang/Object;)Ljava/lang/Object;
      22: checkcast     #7                  // class io/grpc/rls/LbPolicyConfiguration$ChildPolicyWrapper
      25: putfield      #8                  // Field childPolicyWrapper:Lio/grpc/rls/LbPolicyConfiguration$ChildPolicyWrapper;
      28: return

  public io.grpc.rls.LbPolicyConfiguration$ChildPolicyWrapper getObject();
    Code:
       0: aload_0
       1: invokevirtual #9                  // Method isReleased:()Z
       4: ifne          11
       7: iconst_1
       8: goto          12
      11: iconst_0
      12: ldc           #10                 // String ChildPolicyWrapper is already released
      14: invokestatic  #11                 // Method com/google/common/base/Preconditions.checkState:(ZLjava/lang/Object;)V
      17: aload_0
      18: getfield      #4                  // Field refCnt:Ljava/util/concurrent/atomic/AtomicLong;
      21: invokevirtual #12                 // Method java/util/concurrent/atomic/AtomicLong.getAndIncrement:()J
      24: pop2
      25: aload_0
      26: getfield      #8                  // Field childPolicyWrapper:Lio/grpc/rls/LbPolicyConfiguration$ChildPolicyWrapper;
      29: areturn

  public io.grpc.rls.LbPolicyConfiguration$ChildPolicyWrapper returnObject(java.lang.Object);
    Code:
       0: aload_0
       1: invokevirtual #9                  // Method isReleased:()Z
       4: ifne          11
       7: iconst_1
       8: goto          12
      11: iconst_0
      12: ldc           #13                 // String cannot return already released ChildPolicyWrapper, this is possibly a bug.
      14: invokestatic  #11                 // Method com/google/common/base/Preconditions.checkState:(ZLjava/lang/Object;)V
      17: aload_0
      18: getfield      #8                  // Field childPolicyWrapper:Lio/grpc/rls/LbPolicyConfiguration$ChildPolicyWrapper;
      21: aload_1
      22: if_acmpne     29
      25: iconst_1
      26: goto          30
      29: iconst_0
      30: ldc           #14                 // String returned object doesn\'t match the pooled childPolicyWrapper
      32: invokestatic  #11                 // Method com/google/common/base/Preconditions.checkState:(ZLjava/lang/Object;)V
      35: aload_0
      36: getfield      #4                  // Field refCnt:Ljava/util/concurrent/atomic/AtomicLong;
      39: invokevirtual #15                 // Method java/util/concurrent/atomic/AtomicLong.decrementAndGet:()J
      42: lstore_2
      43: lload_2
      44: ldc2_w        #16                 // long -1l
      47: lcmp
      48: ifeq          55
      51: iconst_1
      52: goto          56
      55: iconst_0
      56: ldc           #18                 // String Cannot return never pooled childPolicyWrapper
      58: invokestatic  #11                 // Method com/google/common/base/Preconditions.checkState:(ZLjava/lang/Object;)V
      61: lload_2
      62: lconst_0
      63: lcmp
      64: ifne          72
      67: aload_0
      68: aconst_null
      69: putfield      #8                  // Field childPolicyWrapper:Lio/grpc/rls/LbPolicyConfiguration$ChildPolicyWrapper;
      72: aconst_null
      73: areturn

  boolean isReleased();
    Code:
       0: aload_0
       1: getfield      #8                  // Field childPolicyWrapper:Lio/grpc/rls/LbPolicyConfiguration$ChildPolicyWrapper;
       4: ifnonnull     11
       7: iconst_1
       8: goto          12
      11: iconst_0
      12: ireturn

  static io.grpc.rls.LbPolicyConfiguration$RefCountedChildPolicyWrapper of(io.grpc.rls.LbPolicyConfiguration$ChildPolicyWrapper);
    Code:
       0: new           #19                 // class io/grpc/rls/LbPolicyConfiguration$RefCountedChildPolicyWrapper
       3: dup
       4: aload_0
       5: invokespecial #20                 // Method "<init>":(Lio/grpc/rls/LbPolicyConfiguration$ChildPolicyWrapper;)V
       8: areturn

  public java.lang.String toString();
    Code:
       0: aload_0
       1: invokestatic  #21                 // Method com/google/common/base/MoreObjects.toStringHelper:(Ljava/lang/Object;)Lcom/google/common/base/MoreObjects$ToStringHelper;
       4: ldc           #22                 // String object
       6: aload_0
       7: getfield      #8                  // Field childPolicyWrapper:Lio/grpc/rls/LbPolicyConfiguration$ChildPolicyWrapper;
      10: invokevirtual #23                 // Method com/google/common/base/MoreObjects$ToStringHelper.add:(Ljava/lang/String;Ljava/lang/Object;)Lcom/google/common/base/MoreObjects$ToStringHelper;
      13: ldc           #24                 // String refCnt
      15: aload_0
      16: getfield      #4                  // Field refCnt:Ljava/util/concurrent/atomic/AtomicLong;
      19: invokevirtual #25                 // Method java/util/concurrent/atomic/AtomicLong.get:()J
      22: invokevirtual #26                 // Method com/google/common/base/MoreObjects$ToStringHelper.add:(Ljava/lang/String;J)Lcom/google/common/base/MoreObjects$ToStringHelper;
      25: invokevirtual #27                 // Method com/google/common/base/MoreObjects$ToStringHelper.toString:()Ljava/lang/String;
      28: areturn

  public java.lang.Object returnObject(java.lang.Object);
    Code:
       0: aload_0
       1: aload_1
       2: invokevirtual #28                 // Method returnObject:(Ljava/lang/Object;)Lio/grpc/rls/LbPolicyConfiguration$ChildPolicyWrapper;
       5: areturn

  public java.lang.Object getObject();
    Code:
       0: aload_0
       1: invokevirtual #29                 // Method getObject:()Lio/grpc/rls/LbPolicyConfiguration$ChildPolicyWrapper;
       4: areturn
}
