Compiled from "LinkedHashLruCache.java"
class io.grpc.rls.LinkedHashLruCache$PeriodicCleaner$CleaningTask implements java.lang.Runnable {
  final io.grpc.rls.LinkedHashLruCache$PeriodicCleaner this$1;

  private io.grpc.rls.LinkedHashLruCache$PeriodicCleaner$CleaningTask(io.grpc.rls.LinkedHashLruCache$PeriodicCleaner);
    Code:
       0: aload_0
       1: aload_1
       2: putfield      #2                  // Field this$1:Lio/grpc/rls/LinkedHashLruCache$PeriodicCleaner;
       5: aload_0
       6: invokespecial #3                  // Method java/lang/Object."<init>":()V
       9: return

  public void run();
    Code:
       0: aload_0
       1: getfield      #2                  // Field this$1:Lio/grpc/rls/LinkedHashLruCache$PeriodicCleaner;
       4: getfield      #4                  // Field io/grpc/rls/LinkedHashLruCache$PeriodicCleaner.this$0:Lio/grpc/rls/LinkedHashLruCache;
       7: aload_0
       8: getfield      #2                  // Field this$1:Lio/grpc/rls/LinkedHashLruCache$PeriodicCleaner;
      11: getfield      #4                  // Field io/grpc/rls/LinkedHashLruCache$PeriodicCleaner.this$0:Lio/grpc/rls/LinkedHashLruCache;
      14: invokestatic  #5                  // Method io/grpc/rls/LinkedHashLruCache.access$500:(Lio/grpc/rls/LinkedHashLruCache;)Lio/grpc/internal/TimeProvider;
      17: invokeinterface #6,  1            // InterfaceMethod io/grpc/internal/TimeProvider.currentTimeNanos:()J
      22: invokestatic  #7                  // Method io/grpc/rls/LinkedHashLruCache.access$600:(Lio/grpc/rls/LinkedHashLruCache;J)Z
      25: pop
      26: return

  io.grpc.rls.LinkedHashLruCache$PeriodicCleaner$CleaningTask(io.grpc.rls.LinkedHashLruCache$PeriodicCleaner, io.grpc.rls.LinkedHashLruCache$1);
    Code:
       0: aload_0
       1: aload_1
       2: invokespecial #1                  // Method "<init>":(Lio/grpc/rls/LinkedHashLruCache$PeriodicCleaner;)V
       5: return
}
