Compiled from "SaxHandler.java"
public final class com.arjuna.common.util.propertyservice.SaxHandler extends org.xml.sax.helpers.DefaultHandler {
  private final java.util.Properties properties;

  private boolean isEntry;

  private java.lang.String currentKey;

  private java.lang.StringBuffer currentBuffer;

  public com.arjuna.common.util.propertyservice.SaxHandler();
    Code:
       0: aload_0
       1: invokespecial #1                  // Method org/xml/sax/helpers/DefaultHandler."<init>":()V
       4: aload_0
       5: new           #2                  // class java/util/Properties
       8: dup
       9: invokespecial #3                  // Method java/util/Properties."<init>":()V
      12: putfield      #4                  // Field properties:Ljava/util/Properties;
      15: aload_0
      16: iconst_0
      17: putfield      #5                  // Field isEntry:Z
      20: aload_0
      21: aconst_null
      22: putfield      #6                  // Field currentKey:Ljava/lang/String;
      25: aload_0
      26: aconst_null
      27: putfield      #7                  // Field currentBuffer:Ljava/lang/StringBuffer;
      30: return

  public java.util.Properties getProperties();
    Code:
       0: new           #2                  // class java/util/Properties
       3: dup
       4: invokespecial #3                  // Method java/util/Properties."<init>":()V
       7: astore_1
       8: aload_1
       9: aload_0
      10: getfield      #4                  // Field properties:Ljava/util/Properties;
      13: invokevirtual #8                  // Method java/util/Properties.putAll:(Ljava/util/Map;)V
      16: aload_1
      17: areturn

  public void startElement(java.lang.String, java.lang.String, java.lang.String, org.xml.sax.Attributes) throws org.xml.sax.SAXException;
    Code:
       0: aload_3
       1: invokevirtual #9                  // Method java/lang/String.toLowerCase:()Ljava/lang/String;
       4: ldc           #10                 // String entry
       6: invokevirtual #11                 // Method java/lang/String.equals:(Ljava/lang/Object;)Z
       9: ifeq          57
      12: aload         4
      14: invokeinterface #12,  1           // InterfaceMethod org/xml/sax/Attributes.getLength:()I
      19: ifle          57
      22: aload_0
      23: aload_0
      24: ldc           #13                 // String key
      26: aload         4
      28: invokespecial #14                 // Method getAttributeValue:(Ljava/lang/String;Lorg/xml/sax/Attributes;)Ljava/lang/String;
      31: putfield      #6                  // Field currentKey:Ljava/lang/String;
      34: aload_0
      35: getfield      #6                  // Field currentKey:Ljava/lang/String;
      38: ifnull        57
      41: aload_0
      42: iconst_1
      43: putfield      #5                  // Field isEntry:Z
      46: aload_0
      47: new           #15                 // class java/lang/StringBuffer
      50: dup
      51: invokespecial #16                 // Method java/lang/StringBuffer."<init>":()V
      54: putfield      #7                  // Field currentBuffer:Ljava/lang/StringBuffer;
      57: return

  public void endElement(java.lang.String, java.lang.String, java.lang.String) throws org.xml.sax.SAXException;
    Code:
       0: aload_3
       1: invokevirtual #9                  // Method java/lang/String.toLowerCase:()Ljava/lang/String;
       4: ldc           #10                 // String entry
       6: invokevirtual #11                 // Method java/lang/String.equals:(Ljava/lang/Object;)Z
       9: ifeq          56
      12: aload_0
      13: getfield      #5                  // Field isEntry:Z
      16: ifeq          56
      19: aload_0
      20: getfield      #4                  // Field properties:Ljava/util/Properties;
      23: aload_0
      24: getfield      #6                  // Field currentKey:Ljava/lang/String;
      27: aload_0
      28: getfield      #7                  // Field currentBuffer:Ljava/lang/StringBuffer;
      31: invokevirtual #17                 // Method java/lang/StringBuffer.toString:()Ljava/lang/String;
      34: invokevirtual #18                 // Method java/lang/String.trim:()Ljava/lang/String;
      37: invokevirtual #19                 // Method java/util/Properties.put:(Ljava/lang/Object;Ljava/lang/Object;)Ljava/lang/Object;
      40: pop
      41: aload_0
      42: aconst_null
      43: putfield      #6                  // Field currentKey:Ljava/lang/String;
      46: aload_0
      47: aconst_null
      48: putfield      #7                  // Field currentBuffer:Ljava/lang/StringBuffer;
      51: aload_0
      52: iconst_0
      53: putfield      #5                  // Field isEntry:Z
      56: return

  public void characters(char[], int, int) throws org.xml.sax.SAXException;
    Code:
       0: aload_0
       1: getfield      #5                  // Field isEntry:Z
       4: ifeq          18
       7: aload_0
       8: getfield      #7                  // Field currentBuffer:Ljava/lang/StringBuffer;
      11: aload_1
      12: iload_2
      13: iload_3
      14: invokevirtual #20                 // Method java/lang/StringBuffer.append:([CII)Ljava/lang/StringBuffer;
      17: pop
      18: return

  private java.lang.String getAttributeValue(java.lang.String, org.xml.sax.Attributes);
    Code:
       0: iconst_0
       1: istore_3
       2: iload_3
       3: aload_2
       4: invokeinterface #12,  1           // InterfaceMethod org/xml/sax/Attributes.getLength:()I
       9: if_icmpge     46
      12: aload_2
      13: iload_3
      14: invokeinterface #21,  2           // InterfaceMethod org/xml/sax/Attributes.getQName:(I)Ljava/lang/String;
      19: invokevirtual #9                  // Method java/lang/String.toLowerCase:()Ljava/lang/String;
      22: aload_1
      23: invokevirtual #9                  // Method java/lang/String.toLowerCase:()Ljava/lang/String;
      26: invokevirtual #11                 // Method java/lang/String.equals:(Ljava/lang/Object;)Z
      29: ifeq          40
      32: aload_2
      33: iload_3
      34: invokeinterface #22,  2           // InterfaceMethod org/xml/sax/Attributes.getValue:(I)Ljava/lang/String;
      39: areturn
      40: iinc          3, 1
      43: goto          2
      46: aconst_null
      47: areturn
}
