Compiled from "HardenedObjectInputStream.java"
public class ch.qos.logback.core.net.HardenedObjectInputStream extends java.io.ObjectInputStream {
  final java.util.List<java.lang.String> whitelistedClassNames;

  static final java.lang.String[] JAVA_PACKAGES;

  public ch.qos.logback.core.net.HardenedObjectInputStream(java.io.InputStream, java.lang.String[]) throws java.io.IOException;
    Code:
       0: aload_0
       1: aload_1
       2: invokespecial #1                  // Method java/io/ObjectInputStream."<init>":(Ljava/io/InputStream;)V
       5: aload_0
       6: new           #7                  // class java/util/ArrayList
       9: dup
      10: invokespecial #9                  // Method java/util/ArrayList."<init>":()V
      13: putfield      #12                 // Field whitelistedClassNames:Ljava/util/List;
      16: aload_2
      17: ifnull        47
      20: iconst_0
      21: istore_3
      22: iload_3
      23: aload_2
      24: arraylength
      25: if_icmpge     47
      28: aload_0
      29: getfield      #12                 // Field whitelistedClassNames:Ljava/util/List;
      32: aload_2
      33: iload_3
      34: aaload
      35: invokeinterface #18,  2           // InterfaceMethod java/util/List.add:(Ljava/lang/Object;)Z
      40: pop
      41: iinc          3, 1
      44: goto          22
      47: return

  public ch.qos.logback.core.net.HardenedObjectInputStream(java.io.InputStream, java.util.List<java.lang.String>) throws java.io.IOException;
    Code:
       0: aload_0
       1: aload_1
       2: invokespecial #1                  // Method java/io/ObjectInputStream."<init>":(Ljava/io/InputStream;)V
       5: aload_0
       6: new           #7                  // class java/util/ArrayList
       9: dup
      10: invokespecial #9                  // Method java/util/ArrayList."<init>":()V
      13: putfield      #12                 // Field whitelistedClassNames:Ljava/util/List;
      16: aload_0
      17: getfield      #12                 // Field whitelistedClassNames:Ljava/util/List;
      20: aload_2
      21: invokeinterface #24,  2           // InterfaceMethod java/util/List.addAll:(Ljava/util/Collection;)Z
      26: pop
      27: return

  protected java.lang.Class<?> resolveClass(java.io.ObjectStreamClass) throws java.io.IOException, java.lang.ClassNotFoundException;
    Code:
       0: aload_1
       1: invokevirtual #28                 // Method java/io/ObjectStreamClass.getName:()Ljava/lang/String;
       4: astore_2
       5: aload_0
       6: aload_2
       7: invokevirtual #34                 // Method isWhitelisted:(Ljava/lang/String;)Z
      10: ifne          27
      13: new           #38                 // class java/io/InvalidClassException
      16: dup
      17: ldc           #40                 // String Unauthorized deserialization attempt
      19: aload_1
      20: invokevirtual #28                 // Method java/io/ObjectStreamClass.getName:()Ljava/lang/String;
      23: invokespecial #42                 // Method java/io/InvalidClassException."<init>":(Ljava/lang/String;Ljava/lang/String;)V
      26: athrow
      27: aload_0
      28: aload_1
      29: invokespecial #45                 // Method java/io/ObjectInputStream.resolveClass:(Ljava/io/ObjectStreamClass;)Ljava/lang/Class;
      32: areturn

  private boolean isWhitelisted(java.lang.String);
    Code:
       0: iconst_0
       1: istore_2
       2: iload_2
       3: getstatic     #49                 // Field JAVA_PACKAGES:[Ljava/lang/String;
       6: arraylength
       7: if_icmpge     30
      10: aload_1
      11: getstatic     #49                 // Field JAVA_PACKAGES:[Ljava/lang/String;
      14: iload_2
      15: aaload
      16: invokevirtual #53                 // Method java/lang/String.startsWith:(Ljava/lang/String;)Z
      19: ifeq          24
      22: iconst_1
      23: ireturn
      24: iinc          2, 1
      27: goto          2
      30: aload_0
      31: getfield      #12                 // Field whitelistedClassNames:Ljava/util/List;
      34: invokeinterface #58,  1           // InterfaceMethod java/util/List.iterator:()Ljava/util/Iterator;
      39: astore_2
      40: aload_2
      41: invokeinterface #62,  1           // InterfaceMethod java/util/Iterator.hasNext:()Z
      46: ifeq          72
      49: aload_2
      50: invokeinterface #68,  1           // InterfaceMethod java/util/Iterator.next:()Ljava/lang/Object;
      55: checkcast     #54                 // class java/lang/String
      58: astore_3
      59: aload_1
      60: aload_3
      61: invokevirtual #72                 // Method java/lang/String.equals:(Ljava/lang/Object;)Z
      64: ifeq          69
      67: iconst_1
      68: ireturn
      69: goto          40
      72: iconst_0
      73: ireturn

  protected void addToWhitelist(java.util.List<java.lang.String>);
    Code:
       0: aload_0
       1: getfield      #12                 // Field whitelistedClassNames:Ljava/util/List;
       4: aload_1
       5: invokeinterface #24,  2           // InterfaceMethod java/util/List.addAll:(Ljava/util/Collection;)Z
      10: pop
      11: return

  static {};
    Code:
       0: iconst_2
       1: anewarray     #54                 // class java/lang/String
       4: dup
       5: iconst_0
       6: ldc           #75                 // String java.lang
       8: aastore
       9: dup
      10: iconst_1
      11: ldc           #77                 // String java.util
      13: aastore
      14: putstatic     #49                 // Field JAVA_PACKAGES:[Ljava/lang/String;
      17: return
}
