Compiled from "ConversionUtils.scala"
public final class ai.h2o.sparkling.ml.params.ConversionUtils$ {
  public static ai.h2o.sparkling.ml.params.ConversionUtils$ MODULE$;

  public static {};
    Code:
       0: new           #2                  // class ai/h2o/sparkling/ml/params/ConversionUtils$
       3: invokespecial #17                 // Method "<init>":()V
       6: return

  public double[] toDoubleArray(java.util.ArrayList<java.lang.Object>);
    Code:
       0: getstatic     #26                 // Field scala/collection/JavaConverters$.MODULE$:Lscala/collection/JavaConverters$;
       3: aload_1
       4: invokevirtual #30                 // Method scala/collection/JavaConverters$.asScalaBufferConverter:(Ljava/util/List;)Lscala/collection/convert/Decorators$AsScala;
       7: invokevirtual #34                 // Method scala/collection/convert/Decorators$AsScala.asScala:()Ljava/lang/Object;
      10: checkcast     #36                 // class scala/collection/TraversableOnce
      13: getstatic     #41                 // Field scala/reflect/ClassTag$.MODULE$:Lscala/reflect/ClassTag$;
      16: invokevirtual #45                 // Method scala/reflect/ClassTag$.Double:()Lscala/reflect/ClassTag;
      19: invokeinterface #49,  2           // InterfaceMethod scala/collection/TraversableOnce.toArray:(Lscala/reflect/ClassTag;)Ljava/lang/Object;
      24: checkcast     #51                 // class "[D"
      27: areturn

  private ai.h2o.sparkling.ml.params.ConversionUtils$();
    Code:
       0: aload_0
       1: invokespecial #54                 // Method java/lang/Object."<init>":()V
       4: aload_0
       5: putstatic     #56                 // Field MODULE$:Lai/h2o/sparkling/ml/params/ConversionUtils$;
       8: return
}
