Compiled from "EnumParamValidator.scala"
public final class ai.h2o.sparkling.ml.params.EnumParamValidator$ {
  public static ai.h2o.sparkling.ml.params.EnumParamValidator$ MODULE$;

  public static {};
    Code:
       0: new           #2                  // class ai/h2o/sparkling/ml/params/EnumParamValidator$
       3: invokespecial #22                 // Method "<init>":()V
       6: return

  public <T extends java.lang.Enum<T>> java.lang.String getValidatedEnumValue(java.lang.String, scala.reflect.ClassTag<T>);
    Code:
       0: aload_0
       1: aload_2
       2: invokeinterface #33,  1           // InterfaceMethod scala/reflect/ClassTag.runtimeClass:()Ljava/lang/Class;
       7: aload_1
       8: invokespecial #36                 // Method getValidatedEnumValue:(Ljava/lang/Class;Ljava/lang/String;)Ljava/lang/String;
      11: areturn

  public <T extends java.lang.Enum<T>> java.lang.String[] getValidatedEnumValues(java.lang.String[], boolean, scala.reflect.ClassTag<T>);
    Code:
       0: aload_0
       1: aload_3
       2: invokeinterface #33,  1           // InterfaceMethod scala/reflect/ClassTag.runtimeClass:()Ljava/lang/Class;
       7: aload_1
       8: iload_2
       9: invokespecial #47                 // Method getValidatedEnumValues:(Ljava/lang/Class;[Ljava/lang/String;Z)[Ljava/lang/String;
      12: areturn

  public java.lang.String getValidatedEnumValue(java.lang.String, java.lang.String);
    Code:
       0: aload_0
       1: aload_1
       2: invokestatic  #57                 // Method java/lang/Class.forName:(Ljava/lang/String;)Ljava/lang/Class;
       5: aload_2
       6: invokespecial #36                 // Method getValidatedEnumValue:(Ljava/lang/Class;Ljava/lang/String;)Ljava/lang/String;
       9: areturn

  public java.lang.String[] getValidatedEnumValues(java.lang.String, java.util.ArrayList<java.lang.String>, boolean);
    Code:
       0: aload_2
       1: ifnonnull     8
       4: aconst_null
       5: goto          25
       8: aload_2
       9: aload_2
      10: invokevirtual #65                 // Method java/util/ArrayList.size:()I
      13: anewarray     #67                 // class java/lang/String
      16: checkcast     #69                 // class "[Ljava/lang/Object;"
      19: invokevirtual #73                 // Method java/util/ArrayList.toArray:([Ljava/lang/Object;)[Ljava/lang/Object;
      22: checkcast     #74                 // class "[Ljava/lang/String;"
      25: astore        4
      27: aload_0
      28: aload_1
      29: invokestatic  #57                 // Method java/lang/Class.forName:(Ljava/lang/String;)Ljava/lang/Class;
      32: aload         4
      34: iload_3
      35: invokespecial #47                 // Method getValidatedEnumValues:(Ljava/lang/Class;[Ljava/lang/String;Z)[Ljava/lang/String;
      38: areturn

  private java.lang.String getValidatedEnumValue(java.lang.Class<?>, java.lang.String);
    Code:
       0: aload_0
       1: aload_1
       2: invokespecial #82                 // Method getEnumValues:(Ljava/lang/Class;)[Ljava/lang/String;
       5: astore_3
       6: aload_2
       7: ifnonnull     60
      10: new           #84                 // class java/lang/IllegalArgumentException
      13: dup
      14: new           #86                 // class java/lang/StringBuilder
      17: dup
      18: ldc           #87                 // int 47
      20: invokespecial #90                 // Method java/lang/StringBuilder."<init>":(I)V
      23: ldc           #92                 // String Null is not a valid value. Allowed values are:
      25: invokevirtual #96                 // Method java/lang/StringBuilder.append:(Ljava/lang/String;)Ljava/lang/StringBuilder;
      28: new           #12                 // class scala/collection/mutable/ArrayOps$ofRef
      31: dup
      32: getstatic     #101                // Field scala/Predef$.MODULE$:Lscala/Predef$;
      35: aload_3
      36: checkcast     #69                 // class "[Ljava/lang/Object;"
      39: invokevirtual #104                // Method scala/Predef$.refArrayOps:([Ljava/lang/Object;)[Ljava/lang/Object;
      42: invokespecial #107                // Method scala/collection/mutable/ArrayOps$ofRef."<init>":([Ljava/lang/Object;)V
      45: ldc           #109                // String ,
      47: invokevirtual #113                // Method scala/collection/mutable/ArrayOps$ofRef.mkString:(Ljava/lang/String;)Ljava/lang/String;
      50: invokevirtual #96                 // Method java/lang/StringBuilder.append:(Ljava/lang/String;)Ljava/lang/StringBuilder;
      53: invokevirtual #117                // Method java/lang/StringBuilder.toString:()Ljava/lang/String;
      56: invokespecial #120                // Method java/lang/IllegalArgumentException."<init>":(Ljava/lang/String;)V
      59: athrow
      60: new           #12                 // class scala/collection/mutable/ArrayOps$ofRef
      63: dup
      64: getstatic     #101                // Field scala/Predef$.MODULE$:Lscala/Predef$;
      67: new           #12                 // class scala/collection/mutable/ArrayOps$ofRef
      70: dup
      71: getstatic     #101                // Field scala/Predef$.MODULE$:Lscala/Predef$;
      74: aload_3
      75: checkcast     #69                 // class "[Ljava/lang/Object;"
      78: invokevirtual #104                // Method scala/Predef$.refArrayOps:([Ljava/lang/Object;)[Ljava/lang/Object;
      81: invokespecial #107                // Method scala/collection/mutable/ArrayOps$ofRef."<init>":([Ljava/lang/Object;)V
      84: invokedynamic #142,  0            // InvokeDynamic #0:apply:()Lscala/Function1;
      89: getstatic     #147                // Field scala/Array$.MODULE$:Lscala/Array$;
      92: getstatic     #152                // Field scala/reflect/ClassTag$.MODULE$:Lscala/reflect/ClassTag$;
      95: ldc           #67                 // class java/lang/String
      97: invokevirtual #155                // Method scala/reflect/ClassTag$.apply:(Ljava/lang/Class;)Lscala/reflect/ClassTag;
     100: invokevirtual #159                // Method scala/Array$.canBuildFrom:(Lscala/reflect/ClassTag;)Lscala/collection/generic/CanBuildFrom;
     103: invokevirtual #163                // Method scala/collection/mutable/ArrayOps$ofRef.map:(Lscala/Function1;Lscala/collection/generic/CanBuildFrom;)Ljava/lang/Object;
     106: checkcast     #69                 // class "[Ljava/lang/Object;"
     109: invokevirtual #104                // Method scala/Predef$.refArrayOps:([Ljava/lang/Object;)[Ljava/lang/Object;
     112: invokespecial #107                // Method scala/collection/mutable/ArrayOps$ofRef."<init>":([Ljava/lang/Object;)V
     115: aload_2
     116: invokevirtual #166                // Method java/lang/String.toLowerCase:()Ljava/lang/String;
     119: invokevirtual #170                // Method scala/collection/mutable/ArrayOps$ofRef.contains:(Ljava/lang/Object;)Z
     122: ifne          184
     125: new           #84                 // class java/lang/IllegalArgumentException
     128: dup
     129: new           #86                 // class java/lang/StringBuilder
     132: dup
     133: ldc           #171                // int 45
     135: invokespecial #90                 // Method java/lang/StringBuilder."<init>":(I)V
     138: ldc           #173                // String \'
     140: invokevirtual #96                 // Method java/lang/StringBuilder.append:(Ljava/lang/String;)Ljava/lang/StringBuilder;
     143: aload_2
     144: invokevirtual #96                 // Method java/lang/StringBuilder.append:(Ljava/lang/String;)Ljava/lang/StringBuilder;
     147: ldc           #175                // String \' is not a valid value. Allowed values are:
     149: invokevirtual #96                 // Method java/lang/StringBuilder.append:(Ljava/lang/String;)Ljava/lang/StringBuilder;
     152: new           #12                 // class scala/collection/mutable/ArrayOps$ofRef
     155: dup
     156: getstatic     #101                // Field scala/Predef$.MODULE$:Lscala/Predef$;
     159: aload_3
     160: checkcast     #69                 // class "[Ljava/lang/Object;"
     163: invokevirtual #104                // Method scala/Predef$.refArrayOps:([Ljava/lang/Object;)[Ljava/lang/Object;
     166: invokespecial #107                // Method scala/collection/mutable/ArrayOps$ofRef."<init>":([Ljava/lang/Object;)V
     169: ldc           #109                // String ,
     171: invokevirtual #113                // Method scala/collection/mutable/ArrayOps$ofRef.mkString:(Ljava/lang/String;)Ljava/lang/String;
     174: invokevirtual #96                 // Method java/lang/StringBuilder.append:(Ljava/lang/String;)Ljava/lang/StringBuilder;
     177: invokevirtual #117                // Method java/lang/StringBuilder.toString:()Ljava/lang/String;
     180: invokespecial #120                // Method java/lang/IllegalArgumentException."<init>":(Ljava/lang/String;)V
     183: athrow
     184: new           #12                 // class scala/collection/mutable/ArrayOps$ofRef
     187: dup
     188: getstatic     #101                // Field scala/Predef$.MODULE$:Lscala/Predef$;
     191: aload_3
     192: checkcast     #69                 // class "[Ljava/lang/Object;"
     195: invokevirtual #104                // Method scala/Predef$.refArrayOps:([Ljava/lang/Object;)[Ljava/lang/Object;
     198: invokespecial #107                // Method scala/collection/mutable/ArrayOps$ofRef."<init>":([Ljava/lang/Object;)V
     201: aload_2
     202: invokedynamic #185,  0            // InvokeDynamic #1:apply:(Ljava/lang/String;)Lscala/Function1;
     207: invokevirtual #189                // Method scala/collection/mutable/ArrayOps$ofRef.find:(Lscala/Function1;)Lscala/Option;
     210: invokevirtual #195                // Method scala/Option.get:()Ljava/lang/Object;
     213: checkcast     #67                 // class java/lang/String
     216: areturn

  private java.lang.String[] getValidatedEnumValues(java.lang.Class<?>, java.lang.String[], boolean);
    Code:
       0: aload_0
       1: aload_1
       2: invokespecial #82                 // Method getEnumValues:(Ljava/lang/Class;)[Ljava/lang/String;
       5: astore        4
       7: aload_2
       8: aconst_null
       9: if_acmpne     69
      12: iload_3
      13: ifeq          18
      16: aconst_null
      17: areturn
      18: new           #84                 // class java/lang/IllegalArgumentException
      21: dup
      22: new           #86                 // class java/lang/StringBuilder
      25: dup
      26: ldc           #199                // int 86
      28: invokespecial #90                 // Method java/lang/StringBuilder."<init>":(I)V
      31: ldc           #201                // String Null is not a valid value. Allowed input is array with any of the following elements:
      33: invokevirtual #96                 // Method java/lang/StringBuilder.append:(Ljava/lang/String;)Ljava/lang/StringBuilder;
      36: new           #12                 // class scala/collection/mutable/ArrayOps$ofRef
      39: dup
      40: getstatic     #101                // Field scala/Predef$.MODULE$:Lscala/Predef$;
      43: aload         4
      45: checkcast     #69                 // class "[Ljava/lang/Object;"
      48: invokevirtual #104                // Method scala/Predef$.refArrayOps:([Ljava/lang/Object;)[Ljava/lang/Object;
      51: invokespecial #107                // Method scala/collection/mutable/ArrayOps$ofRef."<init>":([Ljava/lang/Object;)V
      54: ldc           #109                // String ,
      56: invokevirtual #113                // Method scala/collection/mutable/ArrayOps$ofRef.mkString:(Ljava/lang/String;)Ljava/lang/String;
      59: invokevirtual #96                 // Method java/lang/StringBuilder.append:(Ljava/lang/String;)Ljava/lang/StringBuilder;
      62: invokevirtual #117                // Method java/lang/StringBuilder.toString:()Ljava/lang/String;
      65: invokespecial #120                // Method java/lang/IllegalArgumentException."<init>":(Ljava/lang/String;)V
      68: athrow
      69: new           #12                 // class scala/collection/mutable/ArrayOps$ofRef
      72: dup
      73: getstatic     #101                // Field scala/Predef$.MODULE$:Lscala/Predef$;
      76: aload_2
      77: checkcast     #69                 // class "[Ljava/lang/Object;"
      80: invokevirtual #104                // Method scala/Predef$.refArrayOps:([Ljava/lang/Object;)[Ljava/lang/Object;
      83: invokespecial #107                // Method scala/collection/mutable/ArrayOps$ofRef."<init>":([Ljava/lang/Object;)V
      86: iload_3
      87: aload         4
      89: invokedynamic #209,  0            // InvokeDynamic #2:apply:(Z[Ljava/lang/String;)Lscala/Function1;
      94: invokevirtual #213                // Method scala/collection/mutable/ArrayOps$ofRef.foreach:(Lscala/Function1;)V
      97: new           #12                 // class scala/collection/mutable/ArrayOps$ofRef
     100: dup
     101: getstatic     #101                // Field scala/Predef$.MODULE$:Lscala/Predef$;
     104: aload         4
     106: checkcast     #69                 // class "[Ljava/lang/Object;"
     109: invokevirtual #104                // Method scala/Predef$.refArrayOps:([Ljava/lang/Object;)[Ljava/lang/Object;
     112: invokespecial #107                // Method scala/collection/mutable/ArrayOps$ofRef."<init>":([Ljava/lang/Object;)V
     115: aload_2
     116: invokedynamic #221,  0            // InvokeDynamic #3:apply:([Ljava/lang/String;)Lscala/Function1;
     121: invokevirtual #225                // Method scala/collection/mutable/ArrayOps$ofRef.filter:(Lscala/Function1;)Ljava/lang/Object;
     124: checkcast     #74                 // class "[Ljava/lang/String;"
     127: areturn

  public <T extends java.lang.Enum<T>> boolean getValidatedEnumValues$default$2();
    Code:
       0: iconst_0
       1: ireturn

  private java.lang.String[] getEnumValues(java.lang.Class<?>);
    Code:
       0: new           #12                 // class scala/collection/mutable/ArrayOps$ofRef
       3: dup
       4: getstatic     #101                // Field scala/Predef$.MODULE$:Lscala/Predef$;
       7: aload_1
       8: ldc           #231                // String values
      10: iconst_0
      11: anewarray     #53                 // class java/lang/Class
      14: invokevirtual #235                // Method java/lang/Class.getDeclaredMethod:(Ljava/lang/String;[Ljava/lang/Class;)Ljava/lang/reflect/Method;
      17: aconst_null
      18: iconst_0
      19: anewarray     #4                  // class java/lang/Object
      22: invokevirtual #241                // Method java/lang/reflect/Method.invoke:(Ljava/lang/Object;[Ljava/lang/Object;)Ljava/lang/Object;
      25: checkcast     #243                // class "[Ljava/lang/Enum;"
      28: checkcast     #69                 // class "[Ljava/lang/Object;"
      31: invokevirtual #104                // Method scala/Predef$.refArrayOps:([Ljava/lang/Object;)[Ljava/lang/Object;
      34: invokespecial #107                // Method scala/collection/mutable/ArrayOps$ofRef."<init>":([Ljava/lang/Object;)V
      37: invokedynamic #250,  0            // InvokeDynamic #4:apply:()Lscala/Function1;
      42: getstatic     #147                // Field scala/Array$.MODULE$:Lscala/Array$;
      45: getstatic     #152                // Field scala/reflect/ClassTag$.MODULE$:Lscala/reflect/ClassTag$;
      48: ldc           #67                 // class java/lang/String
      50: invokevirtual #155                // Method scala/reflect/ClassTag$.apply:(Ljava/lang/Class;)Lscala/reflect/ClassTag;
      53: invokevirtual #159                // Method scala/Array$.canBuildFrom:(Lscala/reflect/ClassTag;)Lscala/collection/generic/CanBuildFrom;
      56: invokevirtual #163                // Method scala/collection/mutable/ArrayOps$ofRef.map:(Lscala/Function1;Lscala/collection/generic/CanBuildFrom;)Ljava/lang/Object;
      59: checkcast     #74                 // class "[Ljava/lang/String;"
      62: areturn

  public static final java.lang.String $anonfun$getValidatedEnumValue$1(java.lang.String);
    Code:
       0: aload_0
       1: invokevirtual #166                // Method java/lang/String.toLowerCase:()Ljava/lang/String;
       4: areturn

  public static final boolean $anonfun$getValidatedEnumValue$2(java.lang.String, java.lang.String);
    Code:
       0: aload_1
       1: invokevirtual #166                // Method java/lang/String.toLowerCase:()Ljava/lang/String;
       4: aload_0
       5: invokevirtual #166                // Method java/lang/String.toLowerCase:()Ljava/lang/String;
       8: astore_2
       9: dup
      10: ifnonnull     21
      13: pop
      14: aload_2
      15: ifnull        28
      18: goto          32
      21: aload_2
      22: invokevirtual #258                // Method java/lang/Object.equals:(Ljava/lang/Object;)Z
      25: ifeq          32
      28: iconst_1
      29: goto          33
      32: iconst_0
      33: ireturn

  public static final java.lang.String $anonfun$getValidatedEnumValues$2(java.lang.String);
    Code:
       0: aload_0
       1: invokevirtual #166                // Method java/lang/String.toLowerCase:()Ljava/lang/String;
       4: areturn

  public static final void $anonfun$getValidatedEnumValues$1(boolean, java.lang.String[], java.lang.String);
    Code:
       0: iload_0
       1: ifeq          10
       4: ldc_w         #266                // String  null or
       7: goto          13
      10: ldc_w         #268                // String
      13: astore_3
      14: aload_2
      15: ifnonnull     86
      18: new           #84                 // class java/lang/IllegalArgumentException
      21: dup
      22: new           #86                 // class java/lang/StringBuilder
      25: dup
      26: ldc_w         #269                // int 112
      29: invokespecial #90                 // Method java/lang/StringBuilder."<init>":(I)V
      32: ldc_w         #271                // String Null can not be specified as the input array element.
      35: invokevirtual #96                 // Method java/lang/StringBuilder.append:(Ljava/lang/String;)Ljava/lang/StringBuilder;
      38: ldc_w         #273                // String Allowed input is
      41: invokevirtual #96                 // Method java/lang/StringBuilder.append:(Ljava/lang/String;)Ljava/lang/StringBuilder;
      44: aload_3
      45: invokevirtual #96                 // Method java/lang/StringBuilder.append:(Ljava/lang/String;)Ljava/lang/StringBuilder;
      48: ldc_w         #275                // String array with any of the following elements:
      51: invokevirtual #96                 // Method java/lang/StringBuilder.append:(Ljava/lang/String;)Ljava/lang/StringBuilder;
      54: new           #12                 // class scala/collection/mutable/ArrayOps$ofRef
      57: dup
      58: getstatic     #101                // Field scala/Predef$.MODULE$:Lscala/Predef$;
      61: aload_1
      62: checkcast     #69                 // class "[Ljava/lang/Object;"
      65: invokevirtual #104                // Method scala/Predef$.refArrayOps:([Ljava/lang/Object;)[Ljava/lang/Object;
      68: invokespecial #107                // Method scala/collection/mutable/ArrayOps$ofRef."<init>":([Ljava/lang/Object;)V
      71: ldc           #109                // String ,
      73: invokevirtual #113                // Method scala/collection/mutable/ArrayOps$ofRef.mkString:(Ljava/lang/String;)Ljava/lang/String;
      76: invokevirtual #96                 // Method java/lang/StringBuilder.append:(Ljava/lang/String;)Ljava/lang/StringBuilder;
      79: invokevirtual #117                // Method java/lang/StringBuilder.toString:()Ljava/lang/String;
      82: invokespecial #120                // Method java/lang/IllegalArgumentException."<init>":(Ljava/lang/String;)V
      85: athrow
      86: new           #12                 // class scala/collection/mutable/ArrayOps$ofRef
      89: dup
      90: getstatic     #101                // Field scala/Predef$.MODULE$:Lscala/Predef$;
      93: new           #12                 // class scala/collection/mutable/ArrayOps$ofRef
      96: dup
      97: getstatic     #101                // Field scala/Predef$.MODULE$:Lscala/Predef$;
     100: aload_1
     101: checkcast     #69                 // class "[Ljava/lang/Object;"
     104: invokevirtual #104                // Method scala/Predef$.refArrayOps:([Ljava/lang/Object;)[Ljava/lang/Object;
     107: invokespecial #107                // Method scala/collection/mutable/ArrayOps$ofRef."<init>":([Ljava/lang/Object;)V
     110: invokedynamic #279,  0            // InvokeDynamic #5:apply:()Lscala/Function1;
     115: getstatic     #147                // Field scala/Array$.MODULE$:Lscala/Array$;
     118: getstatic     #152                // Field scala/reflect/ClassTag$.MODULE$:Lscala/reflect/ClassTag$;
     121: ldc           #67                 // class java/lang/String
     123: invokevirtual #155                // Method scala/reflect/ClassTag$.apply:(Ljava/lang/Class;)Lscala/reflect/ClassTag;
     126: invokevirtual #159                // Method scala/Array$.canBuildFrom:(Lscala/reflect/ClassTag;)Lscala/collection/generic/CanBuildFrom;
     129: invokevirtual #163                // Method scala/collection/mutable/ArrayOps$ofRef.map:(Lscala/Function1;Lscala/collection/generic/CanBuildFrom;)Ljava/lang/Object;
     132: checkcast     #69                 // class "[Ljava/lang/Object;"
     135: invokevirtual #104                // Method scala/Predef$.refArrayOps:([Ljava/lang/Object;)[Ljava/lang/Object;
     138: invokespecial #107                // Method scala/collection/mutable/ArrayOps$ofRef."<init>":([Ljava/lang/Object;)V
     141: aload_2
     142: invokevirtual #166                // Method java/lang/String.toLowerCase:()Ljava/lang/String;
     145: invokevirtual #170                // Method scala/collection/mutable/ArrayOps$ofRef.contains:(Ljava/lang/Object;)Z
     148: ifne          228
     151: new           #84                 // class java/lang/IllegalArgumentException
     154: dup
     155: new           #86                 // class java/lang/StringBuilder
     158: dup
     159: ldc_w         #280                // int 83
     162: invokespecial #90                 // Method java/lang/StringBuilder."<init>":(I)V
     165: ldc           #173                // String \'
     167: invokevirtual #96                 // Method java/lang/StringBuilder.append:(Ljava/lang/String;)Ljava/lang/StringBuilder;
     170: aload_2
     171: invokevirtual #96                 // Method java/lang/StringBuilder.append:(Ljava/lang/String;)Ljava/lang/StringBuilder;
     174: ldc_w         #282                // String \' is not a valid value. Allowed input is
     177: invokevirtual #96                 // Method java/lang/StringBuilder.append:(Ljava/lang/String;)Ljava/lang/StringBuilder;
     180: aload_3
     181: invokevirtual #96                 // Method java/lang/StringBuilder.append:(Ljava/lang/String;)Ljava/lang/StringBuilder;
     184: ldc_w         #284                // String array with
     187: invokevirtual #96                 // Method java/lang/StringBuilder.append:(Ljava/lang/String;)Ljava/lang/StringBuilder;
     190: ldc_w         #286                // String  any of the following elements:
     193: invokevirtual #96                 // Method java/lang/StringBuilder.append:(Ljava/lang/String;)Ljava/lang/StringBuilder;
     196: new           #12                 // class scala/collection/mutable/ArrayOps$ofRef
     199: dup
     200: getstatic     #101                // Field scala/Predef$.MODULE$:Lscala/Predef$;
     203: aload_1
     204: checkcast     #69                 // class "[Ljava/lang/Object;"
     207: invokevirtual #104                // Method scala/Predef$.refArrayOps:([Ljava/lang/Object;)[Ljava/lang/Object;
     210: invokespecial #107                // Method scala/collection/mutable/ArrayOps$ofRef."<init>":([Ljava/lang/Object;)V
     213: ldc           #109                // String ,
     215: invokevirtual #113                // Method scala/collection/mutable/ArrayOps$ofRef.mkString:(Ljava/lang/String;)Ljava/lang/String;
     218: invokevirtual #96                 // Method java/lang/StringBuilder.append:(Ljava/lang/String;)Ljava/lang/StringBuilder;
     221: invokevirtual #117                // Method java/lang/StringBuilder.toString:()Ljava/lang/String;
     224: invokespecial #120                // Method java/lang/IllegalArgumentException."<init>":(Ljava/lang/String;)V
     227: athrow
     228: return

  public static final java.lang.String $anonfun$getValidatedEnumValues$4(java.lang.String);
    Code:
       0: aload_0
       1: invokevirtual #166                // Method java/lang/String.toLowerCase:()Ljava/lang/String;
       4: areturn

  public static final boolean $anonfun$getValidatedEnumValues$3(java.lang.String[], java.lang.String);
    Code:
       0: new           #12                 // class scala/collection/mutable/ArrayOps$ofRef
       3: dup
       4: getstatic     #101                // Field scala/Predef$.MODULE$:Lscala/Predef$;
       7: new           #12                 // class scala/collection/mutable/ArrayOps$ofRef
      10: dup
      11: getstatic     #101                // Field scala/Predef$.MODULE$:Lscala/Predef$;
      14: aload_0
      15: checkcast     #69                 // class "[Ljava/lang/Object;"
      18: invokevirtual #104                // Method scala/Predef$.refArrayOps:([Ljava/lang/Object;)[Ljava/lang/Object;
      21: invokespecial #107                // Method scala/collection/mutable/ArrayOps$ofRef."<init>":([Ljava/lang/Object;)V
      24: invokedynamic #296,  0            // InvokeDynamic #6:apply:()Lscala/Function1;
      29: getstatic     #147                // Field scala/Array$.MODULE$:Lscala/Array$;
      32: getstatic     #152                // Field scala/reflect/ClassTag$.MODULE$:Lscala/reflect/ClassTag$;
      35: ldc           #67                 // class java/lang/String
      37: invokevirtual #155                // Method scala/reflect/ClassTag$.apply:(Ljava/lang/Class;)Lscala/reflect/ClassTag;
      40: invokevirtual #159                // Method scala/Array$.canBuildFrom:(Lscala/reflect/ClassTag;)Lscala/collection/generic/CanBuildFrom;
      43: invokevirtual #163                // Method scala/collection/mutable/ArrayOps$ofRef.map:(Lscala/Function1;Lscala/collection/generic/CanBuildFrom;)Ljava/lang/Object;
      46: checkcast     #69                 // class "[Ljava/lang/Object;"
      49: invokevirtual #104                // Method scala/Predef$.refArrayOps:([Ljava/lang/Object;)[Ljava/lang/Object;
      52: invokespecial #107                // Method scala/collection/mutable/ArrayOps$ofRef."<init>":([Ljava/lang/Object;)V
      55: aload_1
      56: invokevirtual #166                // Method java/lang/String.toLowerCase:()Ljava/lang/String;
      59: invokevirtual #170                // Method scala/collection/mutable/ArrayOps$ofRef.contains:(Ljava/lang/Object;)Z
      62: ireturn

  public static final java.lang.String $anonfun$getEnumValues$1(java.lang.Enum);
    Code:
       0: aload_0
       1: invokevirtual #301                // Method java/lang/Enum.name:()Ljava/lang/String;
       4: areturn

  private ai.h2o.sparkling.ml.params.EnumParamValidator$();
    Code:
       0: aload_0
       1: invokespecial #303                // Method java/lang/Object."<init>":()V
       4: aload_0
       5: putstatic     #305                // Field MODULE$:Lai/h2o/sparkling/ml/params/EnumParamValidator$;
       8: return

  public static final java.lang.Object $anonfun$getValidatedEnumValue$2$adapted(java.lang.String, java.lang.String);
    Code:
       0: aload_0
       1: aload_1
       2: invokestatic  #307                // Method $anonfun$getValidatedEnumValue$2:(Ljava/lang/String;Ljava/lang/String;)Z
       5: invokestatic  #313                // Method scala/runtime/BoxesRunTime.boxToBoolean:(Z)Ljava/lang/Boolean;
       8: areturn

  public static final java.lang.Object $anonfun$getValidatedEnumValues$1$adapted(boolean, java.lang.String[], java.lang.String);
    Code:
       0: iload_0
       1: aload_1
       2: aload_2
       3: invokestatic  #315                // Method $anonfun$getValidatedEnumValues$1:(Z[Ljava/lang/String;Ljava/lang/String;)V
       6: getstatic     #321                // Field scala/runtime/BoxedUnit.UNIT:Lscala/runtime/BoxedUnit;
       9: areturn

  public static final java.lang.Object $anonfun$getValidatedEnumValues$3$adapted(java.lang.String[], java.lang.String);
    Code:
       0: aload_0
       1: aload_1
       2: invokestatic  #323                // Method $anonfun$getValidatedEnumValues$3:([Ljava/lang/String;Ljava/lang/String;)Z
       5: invokestatic  #313                // Method scala/runtime/BoxesRunTime.boxToBoolean:(Z)Ljava/lang/Boolean;
       8: areturn

  private static java.lang.Object $deserializeLambda$(java.lang.invoke.SerializedLambda);
    Code:
       0: aload_0
       1: invokedynamic #335,  0            // InvokeDynamic #7:lambdaDeserialize:(Ljava/lang/invoke/SerializedLambda;)Ljava/lang/Object;
       6: areturn
}
