Compiled from "SslContextFactory.java"
class org.eclipse.jetty.util.ssl.SslContextFactory$Factory {
  private final java.security.KeyStore _keyStore;

  private final java.security.KeyStore _trustStore;

  private final javax.net.ssl.SSLContext _context;

  org.eclipse.jetty.util.ssl.SslContextFactory$Factory(java.security.KeyStore, java.security.KeyStore, javax.net.ssl.SSLContext);
    Code:
       0: aload_0
       1: invokespecial #4                  // Method java/lang/Object."<init>":()V
       4: aload_0
       5: aload_1
       6: putfield      #2                  // Field _keyStore:Ljava/security/KeyStore;
       9: aload_0
      10: aload_2
      11: putfield      #1                  // Field _trustStore:Ljava/security/KeyStore;
      14: aload_0
      15: aload_3
      16: putfield      #3                  // Field _context:Ljavax/net/ssl/SSLContext;
      19: return

  static javax.net.ssl.SSLContext access$000(org.eclipse.jetty.util.ssl.SslContextFactory$Factory);
    Code:
       0: aload_0
       1: getfield      #3                  // Field _context:Ljavax/net/ssl/SSLContext;
       4: areturn

  static java.security.KeyStore access$100(org.eclipse.jetty.util.ssl.SslContextFactory$Factory);
    Code:
       0: aload_0
       1: getfield      #2                  // Field _keyStore:Ljava/security/KeyStore;
       4: areturn

  static java.security.KeyStore access$200(org.eclipse.jetty.util.ssl.SslContextFactory$Factory);
    Code:
       0: aload_0
       1: getfield      #1                  // Field _trustStore:Ljava/security/KeyStore;
       4: areturn
}
