Compiled from "ObjectDecoderInputStream.java"
public class io.netty.handler.codec.serialization.ObjectDecoderInputStream extends java.io.InputStream implements java.io.ObjectInput {
  private final java.io.DataInputStream in;

  private final int maxObjectSize;

  private final io.netty.handler.codec.serialization.ClassResolver classResolver;

  public io.netty.handler.codec.serialization.ObjectDecoderInputStream(java.io.InputStream);
    Code:
       0: aload_0
       1: aload_1
       2: aconst_null
       3: invokespecial #1                  // Method "<init>":(Ljava/io/InputStream;Ljava/lang/ClassLoader;)V
       6: return

  public io.netty.handler.codec.serialization.ObjectDecoderInputStream(java.io.InputStream, java.lang.ClassLoader);
    Code:
       0: aload_0
       1: aload_1
       2: aload_2
       3: ldc           #2                  // int 1048576
       5: invokespecial #3                  // Method "<init>":(Ljava/io/InputStream;Ljava/lang/ClassLoader;I)V
       8: return

  public io.netty.handler.codec.serialization.ObjectDecoderInputStream(java.io.InputStream, int);
    Code:
       0: aload_0
       1: aload_1
       2: aconst_null
       3: iload_2
       4: invokespecial #3                  // Method "<init>":(Ljava/io/InputStream;Ljava/lang/ClassLoader;I)V
       7: return

  public io.netty.handler.codec.serialization.ObjectDecoderInputStream(java.io.InputStream, java.lang.ClassLoader, int);
    Code:
       0: aload_0
       1: invokespecial #4                  // Method java/io/InputStream."<init>":()V
       4: aload_1
       5: ifnonnull     18
       8: new           #5                  // class java/lang/NullPointerException
      11: dup
      12: ldc           #6                  // String in
      14: invokespecial #7                  // Method java/lang/NullPointerException."<init>":(Ljava/lang/String;)V
      17: athrow
      18: iload_3
      19: ifgt          49
      22: new           #8                  // class java/lang/IllegalArgumentException
      25: dup
      26: new           #9                  // class java/lang/StringBuilder
      29: dup
      30: invokespecial #10                 // Method java/lang/StringBuilder."<init>":()V
      33: ldc           #11                 // String maxObjectSize:
      35: invokevirtual #12                 // Method java/lang/StringBuilder.append:(Ljava/lang/String;)Ljava/lang/StringBuilder;
      38: iload_3
      39: invokevirtual #13                 // Method java/lang/StringBuilder.append:(I)Ljava/lang/StringBuilder;
      42: invokevirtual #14                 // Method java/lang/StringBuilder.toString:()Ljava/lang/String;
      45: invokespecial #15                 // Method java/lang/IllegalArgumentException."<init>":(Ljava/lang/String;)V
      48: athrow
      49: aload_1
      50: instanceof    #16                 // class java/io/DataInputStream
      53: ifeq          67
      56: aload_0
      57: aload_1
      58: checkcast     #16                 // class java/io/DataInputStream
      61: putfield      #17                 // Field in:Ljava/io/DataInputStream;
      64: goto          79
      67: aload_0
      68: new           #16                 // class java/io/DataInputStream
      71: dup
      72: aload_1
      73: invokespecial #18                 // Method java/io/DataInputStream."<init>":(Ljava/io/InputStream;)V
      76: putfield      #17                 // Field in:Ljava/io/DataInputStream;
      79: aload_0
      80: aload_2
      81: invokestatic  #19                 // Method io/netty/handler/codec/serialization/ClassResolvers.weakCachingResolver:(Ljava/lang/ClassLoader;)Lio/netty/handler/codec/serialization/ClassResolver;
      84: putfield      #20                 // Field classResolver:Lio/netty/handler/codec/serialization/ClassResolver;
      87: aload_0
      88: iload_3
      89: putfield      #21                 // Field maxObjectSize:I
      92: return

  public java.lang.Object readObject() throws java.lang.ClassNotFoundException, java.io.IOException;
    Code:
       0: aload_0
       1: invokevirtual #22                 // Method readInt:()I
       4: istore_1
       5: iload_1
       6: ifgt          36
       9: new           #23                 // class java/io/StreamCorruptedException
      12: dup
      13: new           #9                  // class java/lang/StringBuilder
      16: dup
      17: invokespecial #10                 // Method java/lang/StringBuilder."<init>":()V
      20: ldc           #24                 // String invalid data length:
      22: invokevirtual #12                 // Method java/lang/StringBuilder.append:(Ljava/lang/String;)Ljava/lang/StringBuilder;
      25: iload_1
      26: invokevirtual #13                 // Method java/lang/StringBuilder.append:(I)Ljava/lang/StringBuilder;
      29: invokevirtual #14                 // Method java/lang/StringBuilder.toString:()Ljava/lang/String;
      32: invokespecial #25                 // Method java/io/StreamCorruptedException."<init>":(Ljava/lang/String;)V
      35: athrow
      36: iload_1
      37: aload_0
      38: getfield      #21                 // Field maxObjectSize:I
      41: if_icmple     88
      44: new           #23                 // class java/io/StreamCorruptedException
      47: dup
      48: new           #9                  // class java/lang/StringBuilder
      51: dup
      52: invokespecial #10                 // Method java/lang/StringBuilder."<init>":()V
      55: ldc           #26                 // String data length too big:
      57: invokevirtual #12                 // Method java/lang/StringBuilder.append:(Ljava/lang/String;)Ljava/lang/StringBuilder;
      60: iload_1
      61: invokevirtual #13                 // Method java/lang/StringBuilder.append:(I)Ljava/lang/StringBuilder;
      64: ldc           #27                 // String  (max:
      66: invokevirtual #12                 // Method java/lang/StringBuilder.append:(Ljava/lang/String;)Ljava/lang/StringBuilder;
      69: aload_0
      70: getfield      #21                 // Field maxObjectSize:I
      73: invokevirtual #13                 // Method java/lang/StringBuilder.append:(I)Ljava/lang/StringBuilder;
      76: bipush        41
      78: invokevirtual #28                 // Method java/lang/StringBuilder.append:(C)Ljava/lang/StringBuilder;
      81: invokevirtual #14                 // Method java/lang/StringBuilder.toString:()Ljava/lang/String;
      84: invokespecial #25                 // Method java/io/StreamCorruptedException."<init>":(Ljava/lang/String;)V
      87: athrow
      88: new           #29                 // class io/netty/handler/codec/serialization/CompactObjectInputStream
      91: dup
      92: aload_0
      93: getfield      #17                 // Field in:Ljava/io/DataInputStream;
      96: aload_0
      97: getfield      #20                 // Field classResolver:Lio/netty/handler/codec/serialization/ClassResolver;
     100: invokespecial #30                 // Method io/netty/handler/codec/serialization/CompactObjectInputStream."<init>":(Ljava/io/InputStream;Lio/netty/handler/codec/serialization/ClassResolver;)V
     103: invokevirtual #31                 // Method io/netty/handler/codec/serialization/CompactObjectInputStream.readObject:()Ljava/lang/Object;
     106: areturn

  public int available() throws java.io.IOException;
    Code:
       0: aload_0
       1: getfield      #17                 // Field in:Ljava/io/DataInputStream;
       4: invokevirtual #32                 // Method java/io/DataInputStream.available:()I
       7: ireturn

  public void close() throws java.io.IOException;
    Code:
       0: aload_0
       1: getfield      #17                 // Field in:Ljava/io/DataInputStream;
       4: invokevirtual #33                 // Method java/io/DataInputStream.close:()V
       7: return

  public void mark(int);
    Code:
       0: aload_0
       1: getfield      #17                 // Field in:Ljava/io/DataInputStream;
       4: iload_1
       5: invokevirtual #34                 // Method java/io/DataInputStream.mark:(I)V
       8: return

  public boolean markSupported();
    Code:
       0: aload_0
       1: getfield      #17                 // Field in:Ljava/io/DataInputStream;
       4: invokevirtual #35                 // Method java/io/DataInputStream.markSupported:()Z
       7: ireturn

  public int read() throws java.io.IOException;
    Code:
       0: aload_0
       1: getfield      #17                 // Field in:Ljava/io/DataInputStream;
       4: invokevirtual #36                 // Method java/io/DataInputStream.read:()I
       7: ireturn

  public final int read(byte[], int, int) throws java.io.IOException;
    Code:
       0: aload_0
       1: getfield      #17                 // Field in:Ljava/io/DataInputStream;
       4: aload_1
       5: iload_2
       6: iload_3
       7: invokevirtual #37                 // Method java/io/DataInputStream.read:([BII)I
      10: ireturn

  public final int read(byte[]) throws java.io.IOException;
    Code:
       0: aload_0
       1: getfield      #17                 // Field in:Ljava/io/DataInputStream;
       4: aload_1
       5: invokevirtual #38                 // Method java/io/DataInputStream.read:([B)I
       8: ireturn

  public final boolean readBoolean() throws java.io.IOException;
    Code:
       0: aload_0
       1: getfield      #17                 // Field in:Ljava/io/DataInputStream;
       4: invokevirtual #39                 // Method java/io/DataInputStream.readBoolean:()Z
       7: ireturn

  public final byte readByte() throws java.io.IOException;
    Code:
       0: aload_0
       1: getfield      #17                 // Field in:Ljava/io/DataInputStream;
       4: invokevirtual #40                 // Method java/io/DataInputStream.readByte:()B
       7: ireturn

  public final char readChar() throws java.io.IOException;
    Code:
       0: aload_0
       1: getfield      #17                 // Field in:Ljava/io/DataInputStream;
       4: invokevirtual #41                 // Method java/io/DataInputStream.readChar:()C
       7: ireturn

  public final double readDouble() throws java.io.IOException;
    Code:
       0: aload_0
       1: getfield      #17                 // Field in:Ljava/io/DataInputStream;
       4: invokevirtual #42                 // Method java/io/DataInputStream.readDouble:()D
       7: dreturn

  public final float readFloat() throws java.io.IOException;
    Code:
       0: aload_0
       1: getfield      #17                 // Field in:Ljava/io/DataInputStream;
       4: invokevirtual #43                 // Method java/io/DataInputStream.readFloat:()F
       7: freturn

  public final void readFully(byte[], int, int) throws java.io.IOException;
    Code:
       0: aload_0
       1: getfield      #17                 // Field in:Ljava/io/DataInputStream;
       4: aload_1
       5: iload_2
       6: iload_3
       7: invokevirtual #44                 // Method java/io/DataInputStream.readFully:([BII)V
      10: return

  public final void readFully(byte[]) throws java.io.IOException;
    Code:
       0: aload_0
       1: getfield      #17                 // Field in:Ljava/io/DataInputStream;
       4: aload_1
       5: invokevirtual #45                 // Method java/io/DataInputStream.readFully:([B)V
       8: return

  public final int readInt() throws java.io.IOException;
    Code:
       0: aload_0
       1: getfield      #17                 // Field in:Ljava/io/DataInputStream;
       4: invokevirtual #46                 // Method java/io/DataInputStream.readInt:()I
       7: ireturn

  public final java.lang.String readLine() throws java.io.IOException;
    Code:
       0: aload_0
       1: getfield      #17                 // Field in:Ljava/io/DataInputStream;
       4: invokevirtual #47                 // Method java/io/DataInputStream.readLine:()Ljava/lang/String;
       7: areturn

  public final long readLong() throws java.io.IOException;
    Code:
       0: aload_0
       1: getfield      #17                 // Field in:Ljava/io/DataInputStream;
       4: invokevirtual #48                 // Method java/io/DataInputStream.readLong:()J
       7: lreturn

  public final short readShort() throws java.io.IOException;
    Code:
       0: aload_0
       1: getfield      #17                 // Field in:Ljava/io/DataInputStream;
       4: invokevirtual #49                 // Method java/io/DataInputStream.readShort:()S
       7: ireturn

  public final int readUnsignedByte() throws java.io.IOException;
    Code:
       0: aload_0
       1: getfield      #17                 // Field in:Ljava/io/DataInputStream;
       4: invokevirtual #50                 // Method java/io/DataInputStream.readUnsignedByte:()I
       7: ireturn

  public final int readUnsignedShort() throws java.io.IOException;
    Code:
       0: aload_0
       1: getfield      #17                 // Field in:Ljava/io/DataInputStream;
       4: invokevirtual #51                 // Method java/io/DataInputStream.readUnsignedShort:()I
       7: ireturn

  public final java.lang.String readUTF() throws java.io.IOException;
    Code:
       0: aload_0
       1: getfield      #17                 // Field in:Ljava/io/DataInputStream;
       4: invokevirtual #52                 // Method java/io/DataInputStream.readUTF:()Ljava/lang/String;
       7: areturn

  public void reset() throws java.io.IOException;
    Code:
       0: aload_0
       1: getfield      #17                 // Field in:Ljava/io/DataInputStream;
       4: invokevirtual #53                 // Method java/io/DataInputStream.reset:()V
       7: return

  public long skip(long) throws java.io.IOException;
    Code:
       0: aload_0
       1: getfield      #17                 // Field in:Ljava/io/DataInputStream;
       4: lload_1
       5: invokevirtual #54                 // Method java/io/DataInputStream.skip:(J)J
       8: lreturn

  public final int skipBytes(int) throws java.io.IOException;
    Code:
       0: aload_0
       1: getfield      #17                 // Field in:Ljava/io/DataInputStream;
       4: iload_1
       5: invokevirtual #55                 // Method java/io/DataInputStream.skipBytes:(I)I
       8: ireturn
}
