Compiled from "AutoValue_JsonTestRequest.java"
final class org.graylog2.rest.models.tools.requests.AutoValue_JsonTestRequest extends org.graylog2.rest.models.tools.requests.$AutoValue_JsonTestRequest {
  org.graylog2.rest.models.tools.requests.AutoValue_JsonTestRequest(boolean, java.lang.String, java.lang.String, java.lang.String, boolean, java.lang.String, java.lang.String, java.lang.String);
    Code:
       0: aload_0
       1: iload_1
       2: aload_2
       3: aload_3
       4: aload         4
       6: iload         5
       8: aload         6
      10: aload         7
      12: aload         8
      14: invokespecial #1                  // Method org/graylog2/rest/models/tools/requests/$AutoValue_JsonTestRequest."<init>":(ZLjava/lang/String;Ljava/lang/String;Ljava/lang/String;ZLjava/lang/String;Ljava/lang/String;Ljava/lang/String;)V
      17: return

  public final boolean isFlatten();
    Code:
       0: aload_0
       1: invokevirtual #2                  // Method flatten:()Z
       4: ireturn

  public final java.lang.String getListSeparator();
    Code:
       0: aload_0
       1: invokevirtual #3                  // Method listSeparator:()Ljava/lang/String;
       4: areturn

  public final java.lang.String getKeySeparator();
    Code:
       0: aload_0
       1: invokevirtual #4                  // Method keySeparator:()Ljava/lang/String;
       4: areturn

  public final java.lang.String getKvSeparator();
    Code:
       0: aload_0
       1: invokevirtual #5                  // Method kvSeparator:()Ljava/lang/String;
       4: areturn

  public final boolean isReplaceKeyWhitespace();
    Code:
       0: aload_0
       1: invokevirtual #6                  // Method replaceKeyWhitespace:()Z
       4: ireturn

  public final java.lang.String getKeyWhitespaceReplacement();
    Code:
       0: aload_0
       1: invokevirtual #7                  // Method keyWhitespaceReplacement:()Ljava/lang/String;
       4: areturn

  public final java.lang.String getKeyPrefix();
    Code:
       0: aload_0
       1: invokevirtual #8                  // Method keyPrefix:()Ljava/lang/String;
       4: areturn

  public final java.lang.String getString();
    Code:
       0: aload_0
       1: invokevirtual #9                  // Method string:()Ljava/lang/String;
       4: areturn
}
