Compiled from "ConfigBeanImpl.java"
public class com.typesafe.config.impl.ConfigBeanImpl {
  public com.typesafe.config.impl.ConfigBeanImpl();
    Code:
       0: aload_0
       1: invokespecial #1                  // Method java/lang/Object."<init>":()V
       4: return

  public static <T> T createInternal(com.typesafe.config.Config, java.lang.Class<T>);
    Code:
       0: aload_0
       1: checkcast     #2                  // class com/typesafe/config/impl/SimpleConfig
       4: invokevirtual #3                  // Method com/typesafe/config/impl/SimpleConfig.root:()Lcom/typesafe/config/impl/AbstractConfigObject;
       7: invokevirtual #4                  // Method com/typesafe/config/impl/AbstractConfigObject.resolveStatus:()Lcom/typesafe/config/impl/ResolveStatus;
      10: getstatic     #5                  // Field com/typesafe/config/impl/ResolveStatus.RESOLVED:Lcom/typesafe/config/impl/ResolveStatus;
      13: if_acmpeq     26
      16: new           #6                  // class com/typesafe/config/ConfigException$NotResolved
      19: dup
      20: ldc           #7                  // String need to Config#resolve() a config before using it to initialize a bean, see the API docs for Config#resolve()
      22: invokespecial #8                  // Method com/typesafe/config/ConfigException$NotResolved."<init>":(Ljava/lang/String;)V
      25: athrow
      26: new           #9                  // class java/util/HashMap
      29: dup
      30: invokespecial #10                 // Method java/util/HashMap."<init>":()V
      33: astore_2
      34: new           #9                  // class java/util/HashMap
      37: dup
      38: invokespecial #10                 // Method java/util/HashMap."<init>":()V
      41: astore_3
      42: aload_0
      43: invokeinterface #11,  1           // InterfaceMethod com/typesafe/config/Config.root:()Lcom/typesafe/config/ConfigObject;
      48: invokeinterface #12,  1           // InterfaceMethod com/typesafe/config/ConfigObject.entrySet:()Ljava/util/Set;
      53: invokeinterface #13,  1           // InterfaceMethod java/util/Set.iterator:()Ljava/util/Iterator;
      58: astore        4
      60: aload         4
      62: invokeinterface #14,  1           // InterfaceMethod java/util/Iterator.hasNext:()Z
      67: ifeq          158
      70: aload         4
      72: invokeinterface #15,  1           // InterfaceMethod java/util/Iterator.next:()Ljava/lang/Object;
      77: checkcast     #16                 // class java/util/Map$Entry
      80: astore        5
      82: aload         5
      84: invokeinterface #17,  1           // InterfaceMethod java/util/Map$Entry.getKey:()Ljava/lang/Object;
      89: checkcast     #18                 // class java/lang/String
      92: astore        6
      94: aload         6
      96: invokestatic  #19                 // Method com/typesafe/config/impl/ConfigImplUtil.toCamelCase:(Ljava/lang/String;)Ljava/lang/String;
      99: astore        7
     101: aload_3
     102: aload         7
     104: invokeinterface #20,  2           // InterfaceMethod java/util/Map.containsKey:(Ljava/lang/Object;)Z
     109: ifeq          125
     112: aload         6
     114: aload         7
     116: invokevirtual #21                 // Method java/lang/String.equals:(Ljava/lang/Object;)Z
     119: ifne          125
     122: goto          155
     125: aload_2
     126: aload         7
     128: aload         5
     130: invokeinterface #22,  1           // InterfaceMethod java/util/Map$Entry.getValue:()Ljava/lang/Object;
     135: checkcast     #23                 // class com/typesafe/config/impl/AbstractConfigValue
     138: invokeinterface #24,  3           // InterfaceMethod java/util/Map.put:(Ljava/lang/Object;Ljava/lang/Object;)Ljava/lang/Object;
     143: pop
     144: aload_3
     145: aload         7
     147: aload         6
     149: invokeinterface #24,  3           // InterfaceMethod java/util/Map.put:(Ljava/lang/Object;Ljava/lang/Object;)Ljava/lang/Object;
     154: pop
     155: goto          60
     158: aconst_null
     159: astore        4
     161: aload_1
     162: invokestatic  #25                 // Method java/beans/Introspector.getBeanInfo:(Ljava/lang/Class;)Ljava/beans/BeanInfo;
     165: astore        4
     167: goto          204
     170: astore        5
     172: new           #27                 // class com/typesafe/config/ConfigException$BadBean
     175: dup
     176: new           #28                 // class java/lang/StringBuilder
     179: dup
     180: invokespecial #29                 // Method java/lang/StringBuilder."<init>":()V
     183: ldc           #30                 // String Could not get bean information for class
     185: invokevirtual #31                 // Method java/lang/StringBuilder.append:(Ljava/lang/String;)Ljava/lang/StringBuilder;
     188: aload_1
     189: invokevirtual #32                 // Method java/lang/Class.getName:()Ljava/lang/String;
     192: invokevirtual #31                 // Method java/lang/StringBuilder.append:(Ljava/lang/String;)Ljava/lang/StringBuilder;
     195: invokevirtual #33                 // Method java/lang/StringBuilder.toString:()Ljava/lang/String;
     198: aload         5
     200: invokespecial #34                 // Method com/typesafe/config/ConfigException$BadBean."<init>":(Ljava/lang/String;Ljava/lang/Throwable;)V
     203: athrow
     204: new           #35                 // class java/util/ArrayList
     207: dup
     208: invokespecial #36                 // Method java/util/ArrayList."<init>":()V
     211: astore        5
     213: aload         4
     215: invokeinterface #37,  1           // InterfaceMethod java/beans/BeanInfo.getPropertyDescriptors:()[Ljava/beans/PropertyDescriptor;
     220: astore        6
     222: aload         6
     224: arraylength
     225: istore        7
     227: iconst_0
     228: istore        8
     230: iload         8
     232: iload         7
     234: if_icmpge     279
     237: aload         6
     239: iload         8
     241: aaload
     242: astore        9
     244: aload         9
     246: invokevirtual #38                 // Method java/beans/PropertyDescriptor.getReadMethod:()Ljava/lang/reflect/Method;
     249: ifnull        273
     252: aload         9
     254: invokevirtual #39                 // Method java/beans/PropertyDescriptor.getWriteMethod:()Ljava/lang/reflect/Method;
     257: ifnonnull     263
     260: goto          273
     263: aload         5
     265: aload         9
     267: invokeinterface #40,  2           // InterfaceMethod java/util/List.add:(Ljava/lang/Object;)Z
     272: pop
     273: iinc          8, 1
     276: goto          230
     279: new           #35                 // class java/util/ArrayList
     282: dup
     283: invokespecial #36                 // Method java/util/ArrayList."<init>":()V
     286: astore        6
     288: aload         5
     290: invokeinterface #41,  1           // InterfaceMethod java/util/List.iterator:()Ljava/util/Iterator;
     295: astore        7
     297: aload         7
     299: invokeinterface #14,  1           // InterfaceMethod java/util/Iterator.hasNext:()Z
     304: ifeq          435
     307: aload         7
     309: invokeinterface #15,  1           // InterfaceMethod java/util/Iterator.next:()Ljava/lang/Object;
     314: checkcast     #42                 // class java/beans/PropertyDescriptor
     317: astore        8
     319: aload         8
     321: invokevirtual #39                 // Method java/beans/PropertyDescriptor.getWriteMethod:()Ljava/lang/reflect/Method;
     324: astore        9
     326: aload         9
     328: invokevirtual #43                 // Method java/lang/reflect/Method.getParameterTypes:()[Ljava/lang/Class;
     331: iconst_0
     332: aaload
     333: astore        10
     335: aload         10
     337: invokestatic  #44                 // Method getValueTypeOrNull:(Ljava/lang/Class;)Lcom/typesafe/config/ConfigValueType;
     340: astore        11
     342: aload         11
     344: ifnull        432
     347: aload_3
     348: aload         8
     350: invokevirtual #45                 // Method java/beans/PropertyDescriptor.getName:()Ljava/lang/String;
     353: invokeinterface #46,  2           // InterfaceMethod java/util/Map.get:(Ljava/lang/Object;)Ljava/lang/Object;
     358: checkcast     #18                 // class java/lang/String
     361: astore        12
     363: aload         12
     365: ifnonnull     375
     368: aload         8
     370: invokevirtual #45                 // Method java/beans/PropertyDescriptor.getName:()Ljava/lang/String;
     373: astore        12
     375: aload         12
     377: invokestatic  #47                 // Method com/typesafe/config/impl/Path.newKey:(Ljava/lang/String;)Lcom/typesafe/config/impl/Path;
     380: astore        13
     382: aload_2
     383: aload         8
     385: invokevirtual #45                 // Method java/beans/PropertyDescriptor.getName:()Ljava/lang/String;
     388: invokeinterface #46,  2           // InterfaceMethod java/util/Map.get:(Ljava/lang/Object;)Ljava/lang/Object;
     393: checkcast     #23                 // class com/typesafe/config/impl/AbstractConfigValue
     396: astore        14
     398: aload         14
     400: ifnull        417
     403: aload         13
     405: aload         11
     407: aload         14
     409: aload         6
     411: invokestatic  #48                 // Method com/typesafe/config/impl/SimpleConfig.checkValid:(Lcom/typesafe/config/impl/Path;Lcom/typesafe/config/ConfigValueType;Lcom/typesafe/config/impl/AbstractConfigValue;Ljava/util/List;)V
     414: goto          432
     417: aload         6
     419: aload         11
     421: aload         13
     423: aload_0
     424: invokeinterface #49,  1           // InterfaceMethod com/typesafe/config/Config.origin:()Lcom/typesafe/config/ConfigOrigin;
     429: invokestatic  #50                 // Method com/typesafe/config/impl/SimpleConfig.addMissing:(Ljava/util/List;Lcom/typesafe/config/ConfigValueType;Lcom/typesafe/config/impl/Path;Lcom/typesafe/config/ConfigOrigin;)V
     432: goto          297
     435: aload         6
     437: invokeinterface #51,  1           // InterfaceMethod java/util/List.isEmpty:()Z
     442: ifne          455
     445: new           #52                 // class com/typesafe/config/ConfigException$ValidationFailed
     448: dup
     449: aload         6
     451: invokespecial #53                 // Method com/typesafe/config/ConfigException$ValidationFailed."<init>":(Ljava/lang/Iterable;)V
     454: athrow
     455: aload_1
     456: invokevirtual #54                 // Method java/lang/Class.newInstance:()Ljava/lang/Object;
     459: astore        7
     461: aload         5
     463: invokeinterface #41,  1           // InterfaceMethod java/util/List.iterator:()Ljava/util/Iterator;
     468: astore        8
     470: aload         8
     472: invokeinterface #14,  1           // InterfaceMethod java/util/Iterator.hasNext:()Z
     477: ifeq          562
     480: aload         8
     482: invokeinterface #15,  1           // InterfaceMethod java/util/Iterator.next:()Ljava/lang/Object;
     487: checkcast     #42                 // class java/beans/PropertyDescriptor
     490: astore        9
     492: aload         9
     494: invokevirtual #39                 // Method java/beans/PropertyDescriptor.getWriteMethod:()Ljava/lang/reflect/Method;
     497: astore        10
     499: aload         10
     501: invokevirtual #55                 // Method java/lang/reflect/Method.getGenericParameterTypes:()[Ljava/lang/reflect/Type;
     504: iconst_0
     505: aaload
     506: astore        11
     508: aload         10
     510: invokevirtual #43                 // Method java/lang/reflect/Method.getParameterTypes:()[Ljava/lang/Class;
     513: iconst_0
     514: aaload
     515: astore        12
     517: aload_1
     518: aload         11
     520: aload         12
     522: aload_0
     523: aload_3
     524: aload         9
     526: invokevirtual #45                 // Method java/beans/PropertyDescriptor.getName:()Ljava/lang/String;
     529: invokeinterface #46,  2           // InterfaceMethod java/util/Map.get:(Ljava/lang/Object;)Ljava/lang/Object;
     534: checkcast     #18                 // class java/lang/String
     537: invokestatic  #56                 // Method getValue:(Ljava/lang/Class;Ljava/lang/reflect/Type;Ljava/lang/Class;Lcom/typesafe/config/Config;Ljava/lang/String;)Ljava/lang/Object;
     540: astore        13
     542: aload         10
     544: aload         7
     546: iconst_1
     547: anewarray     #57                 // class java/lang/Object
     550: dup
     551: iconst_0
     552: aload         13
     554: aastore
     555: invokevirtual #58                 // Method java/lang/reflect/Method.invoke:(Ljava/lang/Object;[Ljava/lang/Object;)Ljava/lang/Object;
     558: pop
     559: goto          470
     562: aload         7
     564: areturn
     565: astore        5
     567: new           #27                 // class com/typesafe/config/ConfigException$BadBean
     570: dup
     571: new           #28                 // class java/lang/StringBuilder
     574: dup
     575: invokespecial #29                 // Method java/lang/StringBuilder."<init>":()V
     578: aload_1
     579: invokevirtual #32                 // Method java/lang/Class.getName:()Ljava/lang/String;
     582: invokevirtual #31                 // Method java/lang/StringBuilder.append:(Ljava/lang/String;)Ljava/lang/StringBuilder;
     585: ldc           #60                 // String  needs a public no-args constructor to be used as a bean
     587: invokevirtual #31                 // Method java/lang/StringBuilder.append:(Ljava/lang/String;)Ljava/lang/StringBuilder;
     590: invokevirtual #33                 // Method java/lang/StringBuilder.toString:()Ljava/lang/String;
     593: aload         5
     595: invokespecial #34                 // Method com/typesafe/config/ConfigException$BadBean."<init>":(Ljava/lang/String;Ljava/lang/Throwable;)V
     598: athrow
     599: astore        5
     601: new           #27                 // class com/typesafe/config/ConfigException$BadBean
     604: dup
     605: new           #28                 // class java/lang/StringBuilder
     608: dup
     609: invokespecial #29                 // Method java/lang/StringBuilder."<init>":()V
     612: aload_1
     613: invokevirtual #32                 // Method java/lang/Class.getName:()Ljava/lang/String;
     616: invokevirtual #31                 // Method java/lang/StringBuilder.append:(Ljava/lang/String;)Ljava/lang/StringBuilder;
     619: ldc           #62                 // String  getters and setters are not accessible, they must be for use as a bean
     621: invokevirtual #31                 // Method java/lang/StringBuilder.append:(Ljava/lang/String;)Ljava/lang/StringBuilder;
     624: invokevirtual #33                 // Method java/lang/StringBuilder.toString:()Ljava/lang/String;
     627: aload         5
     629: invokespecial #34                 // Method com/typesafe/config/ConfigException$BadBean."<init>":(Ljava/lang/String;Ljava/lang/Throwable;)V
     632: athrow
     633: astore        5
     635: new           #27                 // class com/typesafe/config/ConfigException$BadBean
     638: dup
     639: new           #28                 // class java/lang/StringBuilder
     642: dup
     643: invokespecial #29                 // Method java/lang/StringBuilder."<init>":()V
     646: ldc           #64                 // String Calling bean method on
     648: invokevirtual #31                 // Method java/lang/StringBuilder.append:(Ljava/lang/String;)Ljava/lang/StringBuilder;
     651: aload_1
     652: invokevirtual #32                 // Method java/lang/Class.getName:()Ljava/lang/String;
     655: invokevirtual #31                 // Method java/lang/StringBuilder.append:(Ljava/lang/String;)Ljava/lang/StringBuilder;
     658: ldc           #65                 // String  caused an exception
     660: invokevirtual #31                 // Method java/lang/StringBuilder.append:(Ljava/lang/String;)Ljava/lang/StringBuilder;
     663: invokevirtual #33                 // Method java/lang/StringBuilder.toString:()Ljava/lang/String;
     666: aload         5
     668: invokespecial #34                 // Method com/typesafe/config/ConfigException$BadBean."<init>":(Ljava/lang/String;Ljava/lang/Throwable;)V
     671: athrow
    Exception table:
       from    to  target type
         161   167   170   Class java/beans/IntrospectionException
         204   564   565   Class java/lang/InstantiationException
         204   564   599   Class java/lang/IllegalAccessException
         204   564   633   Class java/lang/reflect/InvocationTargetException

  private static java.lang.Object getValue(java.lang.Class<?>, java.lang.reflect.Type, java.lang.Class<?>, com.typesafe.config.Config, java.lang.String);
    Code:
       0: aload_2
       1: ldc           #66                 // class java/lang/Boolean
       3: if_acmpeq     13
       6: aload_2
       7: getstatic     #67                 // Field java/lang/Boolean.TYPE:Ljava/lang/Class;
      10: if_acmpne     25
      13: aload_3
      14: aload         4
      16: invokeinterface #68,  2           // InterfaceMethod com/typesafe/config/Config.getBoolean:(Ljava/lang/String;)Z
      21: invokestatic  #69                 // Method java/lang/Boolean.valueOf:(Z)Ljava/lang/Boolean;
      24: areturn
      25: aload_2
      26: ldc           #70                 // class java/lang/Integer
      28: if_acmpeq     38
      31: aload_2
      32: getstatic     #71                 // Field java/lang/Integer.TYPE:Ljava/lang/Class;
      35: if_acmpne     50
      38: aload_3
      39: aload         4
      41: invokeinterface #72,  2           // InterfaceMethod com/typesafe/config/Config.getInt:(Ljava/lang/String;)I
      46: invokestatic  #73                 // Method java/lang/Integer.valueOf:(I)Ljava/lang/Integer;
      49: areturn
      50: aload_2
      51: ldc           #74                 // class java/lang/Double
      53: if_acmpeq     63
      56: aload_2
      57: getstatic     #75                 // Field java/lang/Double.TYPE:Ljava/lang/Class;
      60: if_acmpne     75
      63: aload_3
      64: aload         4
      66: invokeinterface #76,  2           // InterfaceMethod com/typesafe/config/Config.getDouble:(Ljava/lang/String;)D
      71: invokestatic  #77                 // Method java/lang/Double.valueOf:(D)Ljava/lang/Double;
      74: areturn
      75: aload_2
      76: ldc           #78                 // class java/lang/Long
      78: if_acmpeq     88
      81: aload_2
      82: getstatic     #79                 // Field java/lang/Long.TYPE:Ljava/lang/Class;
      85: if_acmpne     100
      88: aload_3
      89: aload         4
      91: invokeinterface #80,  2           // InterfaceMethod com/typesafe/config/Config.getLong:(Ljava/lang/String;)J
      96: invokestatic  #81                 // Method java/lang/Long.valueOf:(J)Ljava/lang/Long;
      99: areturn
     100: aload_2
     101: ldc           #18                 // class java/lang/String
     103: if_acmpne     115
     106: aload_3
     107: aload         4
     109: invokeinterface #82,  2           // InterfaceMethod com/typesafe/config/Config.getString:(Ljava/lang/String;)Ljava/lang/String;
     114: areturn
     115: aload_2
     116: ldc           #83                 // class java/time/Duration
     118: if_acmpne     130
     121: aload_3
     122: aload         4
     124: invokeinterface #84,  2           // InterfaceMethod com/typesafe/config/Config.getDuration:(Ljava/lang/String;)Ljava/time/Duration;
     129: areturn
     130: aload_2
     131: ldc           #85                 // class com/typesafe/config/ConfigMemorySize
     133: if_acmpne     145
     136: aload_3
     137: aload         4
     139: invokeinterface #86,  2           // InterfaceMethod com/typesafe/config/Config.getMemorySize:(Ljava/lang/String;)Lcom/typesafe/config/ConfigMemorySize;
     144: areturn
     145: aload_2
     146: ldc           #57                 // class java/lang/Object
     148: if_acmpne     160
     151: aload_3
     152: aload         4
     154: invokeinterface #87,  2           // InterfaceMethod com/typesafe/config/Config.getAnyRef:(Ljava/lang/String;)Ljava/lang/Object;
     159: areturn
     160: aload_2
     161: ldc           #88                 // class java/util/List
     163: if_acmpne     176
     166: aload_0
     167: aload_1
     168: aload_2
     169: aload_3
     170: aload         4
     172: invokestatic  #89                 // Method getListValue:(Ljava/lang/Class;Ljava/lang/reflect/Type;Ljava/lang/Class;Lcom/typesafe/config/Config;Ljava/lang/String;)Ljava/lang/Object;
     175: areturn
     176: aload_2
     177: ldc           #90                 // class java/util/Map
     179: if_acmpne     294
     182: aload_1
     183: checkcast     #91                 // class java/lang/reflect/ParameterizedType
     186: invokeinterface #92,  1           // InterfaceMethod java/lang/reflect/ParameterizedType.getActualTypeArguments:()[Ljava/lang/reflect/Type;
     191: astore        5
     193: aload         5
     195: iconst_0
     196: aaload
     197: ldc           #18                 // class java/lang/String
     199: if_acmpne     211
     202: aload         5
     204: iconst_1
     205: aaload
     206: ldc           #57                 // class java/lang/Object
     208: if_acmpeq     280
     211: new           #27                 // class com/typesafe/config/ConfigException$BadBean
     214: dup
     215: new           #28                 // class java/lang/StringBuilder
     218: dup
     219: invokespecial #29                 // Method java/lang/StringBuilder."<init>":()V
     222: ldc           #93                 // String Bean property \'
     224: invokevirtual #31                 // Method java/lang/StringBuilder.append:(Ljava/lang/String;)Ljava/lang/StringBuilder;
     227: aload         4
     229: invokevirtual #31                 // Method java/lang/StringBuilder.append:(Ljava/lang/String;)Ljava/lang/StringBuilder;
     232: ldc           #94                 // String \' of class
     234: invokevirtual #31                 // Method java/lang/StringBuilder.append:(Ljava/lang/String;)Ljava/lang/StringBuilder;
     237: aload_0
     238: invokevirtual #32                 // Method java/lang/Class.getName:()Ljava/lang/String;
     241: invokevirtual #31                 // Method java/lang/StringBuilder.append:(Ljava/lang/String;)Ljava/lang/StringBuilder;
     244: ldc           #95                 // String  has unsupported Map<
     246: invokevirtual #31                 // Method java/lang/StringBuilder.append:(Ljava/lang/String;)Ljava/lang/StringBuilder;
     249: aload         5
     251: iconst_0
     252: aaload
     253: invokevirtual #96                 // Method java/lang/StringBuilder.append:(Ljava/lang/Object;)Ljava/lang/StringBuilder;
     256: ldc           #97                 // String ,
     258: invokevirtual #31                 // Method java/lang/StringBuilder.append:(Ljava/lang/String;)Ljava/lang/StringBuilder;
     261: aload         5
     263: iconst_1
     264: aaload
     265: invokevirtual #96                 // Method java/lang/StringBuilder.append:(Ljava/lang/Object;)Ljava/lang/StringBuilder;
     268: ldc           #98                 // String >, only Map<String,Object> is supported right now
     270: invokevirtual #31                 // Method java/lang/StringBuilder.append:(Ljava/lang/String;)Ljava/lang/StringBuilder;
     273: invokevirtual #33                 // Method java/lang/StringBuilder.toString:()Ljava/lang/String;
     276: invokespecial #99                 // Method com/typesafe/config/ConfigException$BadBean."<init>":(Ljava/lang/String;)V
     279: athrow
     280: aload_3
     281: aload         4
     283: invokeinterface #100,  2          // InterfaceMethod com/typesafe/config/Config.getObject:(Ljava/lang/String;)Lcom/typesafe/config/ConfigObject;
     288: invokeinterface #101,  1          // InterfaceMethod com/typesafe/config/ConfigObject.unwrapped:()Ljava/util/Map;
     293: areturn
     294: aload_2
     295: ldc           #102                // class com/typesafe/config/Config
     297: if_acmpne     309
     300: aload_3
     301: aload         4
     303: invokeinterface #103,  2          // InterfaceMethod com/typesafe/config/Config.getConfig:(Ljava/lang/String;)Lcom/typesafe/config/Config;
     308: areturn
     309: aload_2
     310: ldc           #104                // class com/typesafe/config/ConfigObject
     312: if_acmpne     324
     315: aload_3
     316: aload         4
     318: invokeinterface #100,  2          // InterfaceMethod com/typesafe/config/Config.getObject:(Ljava/lang/String;)Lcom/typesafe/config/ConfigObject;
     323: areturn
     324: aload_2
     325: ldc           #105                // class com/typesafe/config/ConfigValue
     327: if_acmpne     339
     330: aload_3
     331: aload         4
     333: invokeinterface #106,  2          // InterfaceMethod com/typesafe/config/Config.getValue:(Ljava/lang/String;)Lcom/typesafe/config/ConfigValue;
     338: areturn
     339: aload_2
     340: ldc           #107                // class com/typesafe/config/ConfigList
     342: if_acmpne     354
     345: aload_3
     346: aload         4
     348: invokeinterface #108,  2          // InterfaceMethod com/typesafe/config/Config.getList:(Ljava/lang/String;)Lcom/typesafe/config/ConfigList;
     353: areturn
     354: aload_2
     355: invokestatic  #109                // Method hasAtLeastOneBeanProperty:(Ljava/lang/Class;)Z
     358: ifeq          374
     361: aload_3
     362: aload         4
     364: invokeinterface #103,  2          // InterfaceMethod com/typesafe/config/Config.getConfig:(Ljava/lang/String;)Lcom/typesafe/config/Config;
     369: aload_2
     370: invokestatic  #110                // Method createInternal:(Lcom/typesafe/config/Config;Ljava/lang/Class;)Ljava/lang/Object;
     373: areturn
     374: new           #27                 // class com/typesafe/config/ConfigException$BadBean
     377: dup
     378: new           #28                 // class java/lang/StringBuilder
     381: dup
     382: invokespecial #29                 // Method java/lang/StringBuilder."<init>":()V
     385: ldc           #111                // String Bean property
     387: invokevirtual #31                 // Method java/lang/StringBuilder.append:(Ljava/lang/String;)Ljava/lang/StringBuilder;
     390: aload         4
     392: invokevirtual #31                 // Method java/lang/StringBuilder.append:(Ljava/lang/String;)Ljava/lang/StringBuilder;
     395: ldc           #112                // String  of class
     397: invokevirtual #31                 // Method java/lang/StringBuilder.append:(Ljava/lang/String;)Ljava/lang/StringBuilder;
     400: aload_0
     401: invokevirtual #32                 // Method java/lang/Class.getName:()Ljava/lang/String;
     404: invokevirtual #31                 // Method java/lang/StringBuilder.append:(Ljava/lang/String;)Ljava/lang/StringBuilder;
     407: ldc           #113                // String  has unsupported type
     409: invokevirtual #31                 // Method java/lang/StringBuilder.append:(Ljava/lang/String;)Ljava/lang/StringBuilder;
     412: aload_1
     413: invokevirtual #96                 // Method java/lang/StringBuilder.append:(Ljava/lang/Object;)Ljava/lang/StringBuilder;
     416: invokevirtual #33                 // Method java/lang/StringBuilder.toString:()Ljava/lang/String;
     419: invokespecial #99                 // Method com/typesafe/config/ConfigException$BadBean."<init>":(Ljava/lang/String;)V
     422: athrow

  private static java.lang.Object getListValue(java.lang.Class<?>, java.lang.reflect.Type, java.lang.Class<?>, com.typesafe.config.Config, java.lang.String);
    Code:
       0: aload_1
       1: checkcast     #91                 // class java/lang/reflect/ParameterizedType
       4: invokeinterface #92,  1           // InterfaceMethod java/lang/reflect/ParameterizedType.getActualTypeArguments:()[Ljava/lang/reflect/Type;
       9: iconst_0
      10: aaload
      11: astore        5
      13: aload         5
      15: ldc           #66                 // class java/lang/Boolean
      17: if_acmpne     29
      20: aload_3
      21: aload         4
      23: invokeinterface #114,  2          // InterfaceMethod com/typesafe/config/Config.getBooleanList:(Ljava/lang/String;)Ljava/util/List;
      28: areturn
      29: aload         5
      31: ldc           #70                 // class java/lang/Integer
      33: if_acmpne     45
      36: aload_3
      37: aload         4
      39: invokeinterface #115,  2          // InterfaceMethod com/typesafe/config/Config.getIntList:(Ljava/lang/String;)Ljava/util/List;
      44: areturn
      45: aload         5
      47: ldc           #74                 // class java/lang/Double
      49: if_acmpne     61
      52: aload_3
      53: aload         4
      55: invokeinterface #116,  2          // InterfaceMethod com/typesafe/config/Config.getDoubleList:(Ljava/lang/String;)Ljava/util/List;
      60: areturn
      61: aload         5
      63: ldc           #78                 // class java/lang/Long
      65: if_acmpne     77
      68: aload_3
      69: aload         4
      71: invokeinterface #117,  2          // InterfaceMethod com/typesafe/config/Config.getLongList:(Ljava/lang/String;)Ljava/util/List;
      76: areturn
      77: aload         5
      79: ldc           #18                 // class java/lang/String
      81: if_acmpne     93
      84: aload_3
      85: aload         4
      87: invokeinterface #118,  2          // InterfaceMethod com/typesafe/config/Config.getStringList:(Ljava/lang/String;)Ljava/util/List;
      92: areturn
      93: aload         5
      95: ldc           #83                 // class java/time/Duration
      97: if_acmpne     109
     100: aload_3
     101: aload         4
     103: invokeinterface #119,  2          // InterfaceMethod com/typesafe/config/Config.getDurationList:(Ljava/lang/String;)Ljava/util/List;
     108: areturn
     109: aload         5
     111: ldc           #85                 // class com/typesafe/config/ConfigMemorySize
     113: if_acmpne     125
     116: aload_3
     117: aload         4
     119: invokeinterface #120,  2          // InterfaceMethod com/typesafe/config/Config.getMemorySizeList:(Ljava/lang/String;)Ljava/util/List;
     124: areturn
     125: aload         5
     127: ldc           #57                 // class java/lang/Object
     129: if_acmpne     141
     132: aload_3
     133: aload         4
     135: invokeinterface #121,  2          // InterfaceMethod com/typesafe/config/Config.getAnyRefList:(Ljava/lang/String;)Ljava/util/List;
     140: areturn
     141: aload         5
     143: ldc           #102                // class com/typesafe/config/Config
     145: if_acmpne     157
     148: aload_3
     149: aload         4
     151: invokeinterface #122,  2          // InterfaceMethod com/typesafe/config/Config.getConfigList:(Ljava/lang/String;)Ljava/util/List;
     156: areturn
     157: aload         5
     159: ldc           #104                // class com/typesafe/config/ConfigObject
     161: if_acmpne     173
     164: aload_3
     165: aload         4
     167: invokeinterface #123,  2          // InterfaceMethod com/typesafe/config/Config.getObjectList:(Ljava/lang/String;)Ljava/util/List;
     172: areturn
     173: aload         5
     175: ldc           #105                // class com/typesafe/config/ConfigValue
     177: if_acmpne     189
     180: aload_3
     181: aload         4
     183: invokeinterface #108,  2          // InterfaceMethod com/typesafe/config/Config.getList:(Ljava/lang/String;)Lcom/typesafe/config/ConfigList;
     188: areturn
     189: new           #27                 // class com/typesafe/config/ConfigException$BadBean
     192: dup
     193: new           #28                 // class java/lang/StringBuilder
     196: dup
     197: invokespecial #29                 // Method java/lang/StringBuilder."<init>":()V
     200: ldc           #93                 // String Bean property \'
     202: invokevirtual #31                 // Method java/lang/StringBuilder.append:(Ljava/lang/String;)Ljava/lang/StringBuilder;
     205: aload         4
     207: invokevirtual #31                 // Method java/lang/StringBuilder.append:(Ljava/lang/String;)Ljava/lang/StringBuilder;
     210: ldc           #94                 // String \' of class
     212: invokevirtual #31                 // Method java/lang/StringBuilder.append:(Ljava/lang/String;)Ljava/lang/StringBuilder;
     215: aload_0
     216: invokevirtual #32                 // Method java/lang/Class.getName:()Ljava/lang/String;
     219: invokevirtual #31                 // Method java/lang/StringBuilder.append:(Ljava/lang/String;)Ljava/lang/StringBuilder;
     222: ldc           #124                // String  has unsupported list element type
     224: invokevirtual #31                 // Method java/lang/StringBuilder.append:(Ljava/lang/String;)Ljava/lang/StringBuilder;
     227: aload         5
     229: invokevirtual #96                 // Method java/lang/StringBuilder.append:(Ljava/lang/Object;)Ljava/lang/StringBuilder;
     232: invokevirtual #33                 // Method java/lang/StringBuilder.toString:()Ljava/lang/String;
     235: invokespecial #99                 // Method com/typesafe/config/ConfigException$BadBean."<init>":(Ljava/lang/String;)V
     238: athrow

  private static com.typesafe.config.ConfigValueType getValueTypeOrNull(java.lang.Class<?>);
    Code:
       0: aload_0
       1: ldc           #66                 // class java/lang/Boolean
       3: if_acmpeq     13
       6: aload_0
       7: getstatic     #67                 // Field java/lang/Boolean.TYPE:Ljava/lang/Class;
      10: if_acmpne     17
      13: getstatic     #125                // Field com/typesafe/config/ConfigValueType.BOOLEAN:Lcom/typesafe/config/ConfigValueType;
      16: areturn
      17: aload_0
      18: ldc           #70                 // class java/lang/Integer
      20: if_acmpeq     30
      23: aload_0
      24: getstatic     #71                 // Field java/lang/Integer.TYPE:Ljava/lang/Class;
      27: if_acmpne     34
      30: getstatic     #126                // Field com/typesafe/config/ConfigValueType.NUMBER:Lcom/typesafe/config/ConfigValueType;
      33: areturn
      34: aload_0
      35: ldc           #74                 // class java/lang/Double
      37: if_acmpeq     47
      40: aload_0
      41: getstatic     #75                 // Field java/lang/Double.TYPE:Ljava/lang/Class;
      44: if_acmpne     51
      47: getstatic     #126                // Field com/typesafe/config/ConfigValueType.NUMBER:Lcom/typesafe/config/ConfigValueType;
      50: areturn
      51: aload_0
      52: ldc           #78                 // class java/lang/Long
      54: if_acmpeq     64
      57: aload_0
      58: getstatic     #79                 // Field java/lang/Long.TYPE:Ljava/lang/Class;
      61: if_acmpne     68
      64: getstatic     #126                // Field com/typesafe/config/ConfigValueType.NUMBER:Lcom/typesafe/config/ConfigValueType;
      67: areturn
      68: aload_0
      69: ldc           #18                 // class java/lang/String
      71: if_acmpne     78
      74: getstatic     #127                // Field com/typesafe/config/ConfigValueType.STRING:Lcom/typesafe/config/ConfigValueType;
      77: areturn
      78: aload_0
      79: ldc           #83                 // class java/time/Duration
      81: if_acmpne     86
      84: aconst_null
      85: areturn
      86: aload_0
      87: ldc           #85                 // class com/typesafe/config/ConfigMemorySize
      89: if_acmpne     94
      92: aconst_null
      93: areturn
      94: aload_0
      95: ldc           #88                 // class java/util/List
      97: if_acmpne     104
     100: getstatic     #128                // Field com/typesafe/config/ConfigValueType.LIST:Lcom/typesafe/config/ConfigValueType;
     103: areturn
     104: aload_0
     105: ldc           #90                 // class java/util/Map
     107: if_acmpne     114
     110: getstatic     #129                // Field com/typesafe/config/ConfigValueType.OBJECT:Lcom/typesafe/config/ConfigValueType;
     113: areturn
     114: aload_0
     115: ldc           #102                // class com/typesafe/config/Config
     117: if_acmpne     124
     120: getstatic     #129                // Field com/typesafe/config/ConfigValueType.OBJECT:Lcom/typesafe/config/ConfigValueType;
     123: areturn
     124: aload_0
     125: ldc           #104                // class com/typesafe/config/ConfigObject
     127: if_acmpne     134
     130: getstatic     #129                // Field com/typesafe/config/ConfigValueType.OBJECT:Lcom/typesafe/config/ConfigValueType;
     133: areturn
     134: aload_0
     135: ldc           #107                // class com/typesafe/config/ConfigList
     137: if_acmpne     144
     140: getstatic     #128                // Field com/typesafe/config/ConfigValueType.LIST:Lcom/typesafe/config/ConfigValueType;
     143: areturn
     144: aconst_null
     145: areturn

  private static boolean hasAtLeastOneBeanProperty(java.lang.Class<?>);
    Code:
       0: aconst_null
       1: astore_1
       2: aload_0
       3: invokestatic  #25                 // Method java/beans/Introspector.getBeanInfo:(Ljava/lang/Class;)Ljava/beans/BeanInfo;
       6: astore_1
       7: goto          13
      10: astore_2
      11: iconst_0
      12: ireturn
      13: aload_1
      14: invokeinterface #37,  1           // InterfaceMethod java/beans/BeanInfo.getPropertyDescriptors:()[Ljava/beans/PropertyDescriptor;
      19: astore_2
      20: aload_2
      21: arraylength
      22: istore_3
      23: iconst_0
      24: istore        4
      26: iload         4
      28: iload_3
      29: if_icmpge     62
      32: aload_2
      33: iload         4
      35: aaload
      36: astore        5
      38: aload         5
      40: invokevirtual #38                 // Method java/beans/PropertyDescriptor.getReadMethod:()Ljava/lang/reflect/Method;
      43: ifnull        56
      46: aload         5
      48: invokevirtual #39                 // Method java/beans/PropertyDescriptor.getWriteMethod:()Ljava/lang/reflect/Method;
      51: ifnull        56
      54: iconst_1
      55: ireturn
      56: iinc          4, 1
      59: goto          26
      62: iconst_0
      63: ireturn
    Exception table:
       from    to  target type
           2     7    10   Class java/beans/IntrospectionException
}
