Compiled from "OriginType.java"
final class com.typesafe.config.impl.OriginType extends java.lang.Enum<com.typesafe.config.impl.OriginType> {
  public static final com.typesafe.config.impl.OriginType GENERIC;

  public static final com.typesafe.config.impl.OriginType FILE;

  public static final com.typesafe.config.impl.OriginType URL;

  public static final com.typesafe.config.impl.OriginType RESOURCE;

  private static final com.typesafe.config.impl.OriginType[] $VALUES;

  public static com.typesafe.config.impl.OriginType[] values();
    Code:
       0: getstatic     #1                  // Field $VALUES:[Lcom/typesafe/config/impl/OriginType;
       3: invokevirtual #2                  // Method "[Lcom/typesafe/config/impl/OriginType;".clone:()Ljava/lang/Object;
       6: checkcast     #3                  // class "[Lcom/typesafe/config/impl/OriginType;"
       9: areturn

  public static com.typesafe.config.impl.OriginType valueOf(java.lang.String);
    Code:
       0: ldc           #4                  // class com/typesafe/config/impl/OriginType
       2: aload_0
       3: invokestatic  #5                  // Method java/lang/Enum.valueOf:(Ljava/lang/Class;Ljava/lang/String;)Ljava/lang/Enum;
       6: checkcast     #4                  // class com/typesafe/config/impl/OriginType
       9: areturn

  private com.typesafe.config.impl.OriginType();
    Code:
       0: aload_0
       1: aload_1
       2: iload_2
       3: invokespecial #6                  // Method java/lang/Enum."<init>":(Ljava/lang/String;I)V
       6: return

  static {};
    Code:
       0: new           #4                  // class com/typesafe/config/impl/OriginType
       3: dup
       4: ldc           #7                  // String GENERIC
       6: iconst_0
       7: invokespecial #8                  // Method "<init>":(Ljava/lang/String;I)V
      10: putstatic     #9                  // Field GENERIC:Lcom/typesafe/config/impl/OriginType;
      13: new           #4                  // class com/typesafe/config/impl/OriginType
      16: dup
      17: ldc           #10                 // String FILE
      19: iconst_1
      20: invokespecial #8                  // Method "<init>":(Ljava/lang/String;I)V
      23: putstatic     #11                 // Field FILE:Lcom/typesafe/config/impl/OriginType;
      26: new           #4                  // class com/typesafe/config/impl/OriginType
      29: dup
      30: ldc           #12                 // String URL
      32: iconst_2
      33: invokespecial #8                  // Method "<init>":(Ljava/lang/String;I)V
      36: putstatic     #13                 // Field URL:Lcom/typesafe/config/impl/OriginType;
      39: new           #4                  // class com/typesafe/config/impl/OriginType
      42: dup
      43: ldc           #14                 // String RESOURCE
      45: iconst_3
      46: invokespecial #8                  // Method "<init>":(Ljava/lang/String;I)V
      49: putstatic     #15                 // Field RESOURCE:Lcom/typesafe/config/impl/OriginType;
      52: iconst_4
      53: anewarray     #4                  // class com/typesafe/config/impl/OriginType
      56: dup
      57: iconst_0
      58: getstatic     #9                  // Field GENERIC:Lcom/typesafe/config/impl/OriginType;
      61: aastore
      62: dup
      63: iconst_1
      64: getstatic     #11                 // Field FILE:Lcom/typesafe/config/impl/OriginType;
      67: aastore
      68: dup
      69: iconst_2
      70: getstatic     #13                 // Field URL:Lcom/typesafe/config/impl/OriginType;
      73: aastore
      74: dup
      75: iconst_3
      76: getstatic     #15                 // Field RESOURCE:Lcom/typesafe/config/impl/OriginType;
      79: aastore
      80: putstatic     #1                  // Field $VALUES:[Lcom/typesafe/config/impl/OriginType;
      83: return
}
