Compiled from "Parseable.java"
final class com.typesafe.config.impl.Parseable$ParseableResourceURL extends com.typesafe.config.impl.Parseable$ParseableURL {
  private final com.typesafe.config.impl.Parseable$Relativizer relativizer;

  private final java.lang.String resource;

  com.typesafe.config.impl.Parseable$ParseableResourceURL(java.net.URL, com.typesafe.config.ConfigParseOptions, java.lang.String, com.typesafe.config.impl.Parseable$Relativizer);
    Code:
       0: aload_0
       1: aload_1
       2: invokespecial #1                  // Method com/typesafe/config/impl/Parseable$ParseableURL."<init>":(Ljava/net/URL;)V
       5: aload_0
       6: aload         4
       8: putfield      #2                  // Field relativizer:Lcom/typesafe/config/impl/Parseable$Relativizer;
      11: aload_0
      12: aload_3
      13: putfield      #3                  // Field resource:Ljava/lang/String;
      16: aload_0
      17: aload_2
      18: invokevirtual #4                  // Method postConstruct:(Lcom/typesafe/config/ConfigParseOptions;)V
      21: return

  protected com.typesafe.config.ConfigOrigin createOrigin();
    Code:
       0: aload_0
       1: getfield      #3                  // Field resource:Ljava/lang/String;
       4: aload_0
       5: getfield      #5                  // Field input:Ljava/net/URL;
       8: invokestatic  #6                  // Method com/typesafe/config/impl/SimpleConfigOrigin.newResource:(Ljava/lang/String;Ljava/net/URL;)Lcom/typesafe/config/impl/SimpleConfigOrigin;
      11: areturn

  com.typesafe.config.ConfigParseable relativeTo(java.lang.String);
    Code:
       0: aload_0
       1: getfield      #2                  // Field relativizer:Lcom/typesafe/config/impl/Parseable$Relativizer;
       4: aload_1
       5: invokeinterface #7,  2            // InterfaceMethod com/typesafe/config/impl/Parseable$Relativizer.relativeTo:(Ljava/lang/String;)Lcom/typesafe/config/ConfigParseable;
      10: areturn
}
