Compiled from "Parseable.java"
final class com.typesafe.config.impl.Parseable$ParseableFile extends com.typesafe.config.impl.Parseable {
  private final java.io.File input;

  com.typesafe.config.impl.Parseable$ParseableFile(java.io.File, com.typesafe.config.ConfigParseOptions);
    Code:
       0: aload_0
       1: invokespecial #1                  // Method com/typesafe/config/impl/Parseable."<init>":()V
       4: aload_0
       5: aload_1
       6: putfield      #2                  // Field input:Ljava/io/File;
       9: aload_0
      10: aload_2
      11: invokevirtual #3                  // Method postConstruct:(Lcom/typesafe/config/ConfigParseOptions;)V
      14: return

  protected java.io.Reader reader() throws java.io.IOException;
    Code:
       0: invokestatic  #4                  // Method com/typesafe/config/impl/ConfigImpl.traceLoadsEnabled:()Z
       3: ifeq          31
       6: new           #5                  // class java/lang/StringBuilder
       9: dup
      10: invokespecial #6                  // Method java/lang/StringBuilder."<init>":()V
      13: ldc           #7                  // String Loading config from a file:
      15: invokevirtual #8                  // Method java/lang/StringBuilder.append:(Ljava/lang/String;)Ljava/lang/StringBuilder;
      18: aload_0
      19: getfield      #2                  // Field input:Ljava/io/File;
      22: invokevirtual #9                  // Method java/lang/StringBuilder.append:(Ljava/lang/Object;)Ljava/lang/StringBuilder;
      25: invokevirtual #10                 // Method java/lang/StringBuilder.toString:()Ljava/lang/String;
      28: invokestatic  #11                 // Method trace:(Ljava/lang/String;)V
      31: new           #12                 // class java/io/FileInputStream
      34: dup
      35: aload_0
      36: getfield      #2                  // Field input:Ljava/io/File;
      39: invokespecial #13                 // Method java/io/FileInputStream."<init>":(Ljava/io/File;)V
      42: astore_1
      43: aload_1
      44: invokestatic  #14                 // Method com/typesafe/config/impl/Parseable.access$000:(Ljava/io/InputStream;)Ljava/io/Reader;
      47: areturn

  com.typesafe.config.ConfigSyntax guessSyntax();
    Code:
       0: aload_0
       1: getfield      #2                  // Field input:Ljava/io/File;
       4: invokevirtual #15                 // Method java/io/File.getName:()Ljava/lang/String;
       7: invokestatic  #16                 // Method com/typesafe/config/impl/Parseable.access$100:(Ljava/lang/String;)Lcom/typesafe/config/ConfigSyntax;
      10: areturn

  com.typesafe.config.ConfigParseable relativeTo(java.lang.String);
    Code:
       0: new           #17                 // class java/io/File
       3: dup
       4: aload_1
       5: invokespecial #18                 // Method java/io/File."<init>":(Ljava/lang/String;)V
       8: invokevirtual #19                 // Method java/io/File.isAbsolute:()Z
      11: ifeq          26
      14: new           #17                 // class java/io/File
      17: dup
      18: aload_1
      19: invokespecial #18                 // Method java/io/File."<init>":(Ljava/lang/String;)V
      22: astore_2
      23: goto          35
      26: aload_0
      27: getfield      #2                  // Field input:Ljava/io/File;
      30: aload_1
      31: invokestatic  #20                 // Method relativeTo:(Ljava/io/File;Ljava/lang/String;)Ljava/io/File;
      34: astore_2
      35: aload_2
      36: ifnonnull     41
      39: aconst_null
      40: areturn
      41: aload_2
      42: invokevirtual #21                 // Method java/io/File.exists:()Z
      45: ifeq          83
      48: new           #5                  // class java/lang/StringBuilder
      51: dup
      52: invokespecial #6                  // Method java/lang/StringBuilder."<init>":()V
      55: aload_2
      56: invokevirtual #9                  // Method java/lang/StringBuilder.append:(Ljava/lang/Object;)Ljava/lang/StringBuilder;
      59: ldc           #22                 // String  exists, so loading it as a file
      61: invokevirtual #8                  // Method java/lang/StringBuilder.append:(Ljava/lang/String;)Ljava/lang/StringBuilder;
      64: invokevirtual #10                 // Method java/lang/StringBuilder.toString:()Ljava/lang/String;
      67: invokestatic  #11                 // Method trace:(Ljava/lang/String;)V
      70: aload_2
      71: aload_0
      72: invokevirtual #23                 // Method options:()Lcom/typesafe/config/ConfigParseOptions;
      75: aconst_null
      76: invokevirtual #24                 // Method com/typesafe/config/ConfigParseOptions.setOriginDescription:(Ljava/lang/String;)Lcom/typesafe/config/ConfigParseOptions;
      79: invokestatic  #25                 // Method newFile:(Ljava/io/File;Lcom/typesafe/config/ConfigParseOptions;)Lcom/typesafe/config/impl/Parseable;
      82: areturn
      83: new           #5                  // class java/lang/StringBuilder
      86: dup
      87: invokespecial #6                  // Method java/lang/StringBuilder."<init>":()V
      90: aload_2
      91: invokevirtual #9                  // Method java/lang/StringBuilder.append:(Ljava/lang/Object;)Ljava/lang/StringBuilder;
      94: ldc           #26                 // String  does not exist, so trying it as a classpath resource
      96: invokevirtual #8                  // Method java/lang/StringBuilder.append:(Ljava/lang/String;)Ljava/lang/StringBuilder;
      99: invokevirtual #10                 // Method java/lang/StringBuilder.toString:()Ljava/lang/String;
     102: invokestatic  #11                 // Method trace:(Ljava/lang/String;)V
     105: aload_0
     106: aload_1
     107: invokespecial #27                 // Method com/typesafe/config/impl/Parseable.relativeTo:(Ljava/lang/String;)Lcom/typesafe/config/ConfigParseable;
     110: areturn

  protected com.typesafe.config.ConfigOrigin createOrigin();
    Code:
       0: aload_0
       1: getfield      #2                  // Field input:Ljava/io/File;
       4: invokevirtual #28                 // Method java/io/File.getPath:()Ljava/lang/String;
       7: invokestatic  #29                 // Method com/typesafe/config/impl/SimpleConfigOrigin.newFile:(Ljava/lang/String;)Lcom/typesafe/config/impl/SimpleConfigOrigin;
      10: areturn

  public java.lang.String toString();
    Code:
       0: new           #5                  // class java/lang/StringBuilder
       3: dup
       4: invokespecial #6                  // Method java/lang/StringBuilder."<init>":()V
       7: aload_0
       8: invokevirtual #30                 // Method java/lang/Object.getClass:()Ljava/lang/Class;
      11: invokevirtual #31                 // Method java/lang/Class.getSimpleName:()Ljava/lang/String;
      14: invokevirtual #8                  // Method java/lang/StringBuilder.append:(Ljava/lang/String;)Ljava/lang/StringBuilder;
      17: ldc           #32                 // String (
      19: invokevirtual #8                  // Method java/lang/StringBuilder.append:(Ljava/lang/String;)Ljava/lang/StringBuilder;
      22: aload_0
      23: getfield      #2                  // Field input:Ljava/io/File;
      26: invokevirtual #28                 // Method java/io/File.getPath:()Ljava/lang/String;
      29: invokevirtual #8                  // Method java/lang/StringBuilder.append:(Ljava/lang/String;)Ljava/lang/StringBuilder;
      32: ldc           #33                 // String )
      34: invokevirtual #8                  // Method java/lang/StringBuilder.append:(Ljava/lang/String;)Ljava/lang/StringBuilder;
      37: invokevirtual #10                 // Method java/lang/StringBuilder.toString:()Ljava/lang/String;
      40: areturn
}
