Compiled from "Parseable.java"
final class com.typesafe.config.impl.Parseable$ParseableNotFound extends com.typesafe.config.impl.Parseable {
  private final java.lang.String what;

  private final java.lang.String message;

  com.typesafe.config.impl.Parseable$ParseableNotFound(java.lang.String, java.lang.String, com.typesafe.config.ConfigParseOptions);
    Code:
       0: aload_0
       1: invokespecial #1                  // Method com/typesafe/config/impl/Parseable."<init>":()V
       4: aload_0
       5: aload_1
       6: putfield      #2                  // Field what:Ljava/lang/String;
       9: aload_0
      10: aload_2
      11: putfield      #3                  // Field message:Ljava/lang/String;
      14: aload_0
      15: aload_3
      16: invokevirtual #4                  // Method postConstruct:(Lcom/typesafe/config/ConfigParseOptions;)V
      19: return

  protected java.io.Reader reader() throws java.io.IOException;
    Code:
       0: new           #5                  // class java/io/FileNotFoundException
       3: dup
       4: aload_0
       5: getfield      #3                  // Field message:Ljava/lang/String;
       8: invokespecial #6                  // Method java/io/FileNotFoundException."<init>":(Ljava/lang/String;)V
      11: athrow

  protected com.typesafe.config.ConfigOrigin createOrigin();
    Code:
       0: aload_0
       1: getfield      #2                  // Field what:Ljava/lang/String;
       4: invokestatic  #7                  // Method com/typesafe/config/impl/SimpleConfigOrigin.newSimple:(Ljava/lang/String;)Lcom/typesafe/config/impl/SimpleConfigOrigin;
       7: areturn
}
