Compiled from "SimpleConfigList.java"
final class com.typesafe.config.impl.SimpleConfigList$3 implements java.util.ListIterator<com.typesafe.config.ConfigValue> {
  final java.util.ListIterator val$i;

  com.typesafe.config.impl.SimpleConfigList$3(java.util.ListIterator);
    Code:
       0: aload_0
       1: aload_1
       2: putfield      #1                  // Field val$i:Ljava/util/ListIterator;
       5: aload_0
       6: invokespecial #2                  // Method java/lang/Object."<init>":()V
       9: return

  public boolean hasNext();
    Code:
       0: aload_0
       1: getfield      #1                  // Field val$i:Ljava/util/ListIterator;
       4: invokeinterface #3,  1            // InterfaceMethod java/util/ListIterator.hasNext:()Z
       9: ireturn

  public com.typesafe.config.ConfigValue next();
    Code:
       0: aload_0
       1: getfield      #1                  // Field val$i:Ljava/util/ListIterator;
       4: invokeinterface #4,  1            // InterfaceMethod java/util/ListIterator.next:()Ljava/lang/Object;
       9: checkcast     #5                  // class com/typesafe/config/ConfigValue
      12: areturn

  public void remove();
    Code:
       0: ldc           #6                  // String listIterator().remove
       2: invokestatic  #7                  // Method com/typesafe/config/impl/SimpleConfigList.access$000:(Ljava/lang/String;)Ljava/lang/UnsupportedOperationException;
       5: athrow

  public void add(com.typesafe.config.ConfigValue);
    Code:
       0: ldc           #8                  // String listIterator().add
       2: invokestatic  #7                  // Method com/typesafe/config/impl/SimpleConfigList.access$000:(Ljava/lang/String;)Ljava/lang/UnsupportedOperationException;
       5: athrow

  public boolean hasPrevious();
    Code:
       0: aload_0
       1: getfield      #1                  // Field val$i:Ljava/util/ListIterator;
       4: invokeinterface #9,  1            // InterfaceMethod java/util/ListIterator.hasPrevious:()Z
       9: ireturn

  public int nextIndex();
    Code:
       0: aload_0
       1: getfield      #1                  // Field val$i:Ljava/util/ListIterator;
       4: invokeinterface #10,  1           // InterfaceMethod java/util/ListIterator.nextIndex:()I
       9: ireturn

  public com.typesafe.config.ConfigValue previous();
    Code:
       0: aload_0
       1: getfield      #1                  // Field val$i:Ljava/util/ListIterator;
       4: invokeinterface #11,  1           // InterfaceMethod java/util/ListIterator.previous:()Ljava/lang/Object;
       9: checkcast     #5                  // class com/typesafe/config/ConfigValue
      12: areturn

  public int previousIndex();
    Code:
       0: aload_0
       1: getfield      #1                  // Field val$i:Ljava/util/ListIterator;
       4: invokeinterface #12,  1           // InterfaceMethod java/util/ListIterator.previousIndex:()I
       9: ireturn

  public void set(com.typesafe.config.ConfigValue);
    Code:
       0: ldc           #13                 // String listIterator().set
       2: invokestatic  #7                  // Method com/typesafe/config/impl/SimpleConfigList.access$000:(Ljava/lang/String;)Ljava/lang/UnsupportedOperationException;
       5: athrow

  public void add(java.lang.Object);
    Code:
       0: aload_0
       1: aload_1
       2: checkcast     #5                  // class com/typesafe/config/ConfigValue
       5: invokevirtual #14                 // Method add:(Lcom/typesafe/config/ConfigValue;)V
       8: return

  public void set(java.lang.Object);
    Code:
       0: aload_0
       1: aload_1
       2: checkcast     #5                  // class com/typesafe/config/ConfigValue
       5: invokevirtual #15                 // Method set:(Lcom/typesafe/config/ConfigValue;)V
       8: return

  public java.lang.Object previous();
    Code:
       0: aload_0
       1: invokevirtual #16                 // Method previous:()Lcom/typesafe/config/ConfigValue;
       4: areturn

  public java.lang.Object next();
    Code:
       0: aload_0
       1: invokevirtual #17                 // Method next:()Lcom/typesafe/config/ConfigValue;
       4: areturn
}
