Compiled from "Tokens.java"
final class com.typesafe.config.impl.Tokens$Comment$HashComment extends com.typesafe.config.impl.Tokens$Comment {
  com.typesafe.config.impl.Tokens$Comment$HashComment(com.typesafe.config.ConfigOrigin, java.lang.String);
    Code:
       0: aload_0
       1: aload_1
       2: aload_2
       3: invokespecial #1                  // Method com/typesafe/config/impl/Tokens$Comment."<init>":(Lcom/typesafe/config/ConfigOrigin;Ljava/lang/String;)V
       6: return

  public java.lang.String tokenText();
    Code:
       0: new           #2                  // class java/lang/StringBuilder
       3: dup
       4: invokespecial #3                  // Method java/lang/StringBuilder."<init>":()V
       7: ldc           #4                  // String #
       9: invokevirtual #5                  // Method java/lang/StringBuilder.append:(Ljava/lang/String;)Ljava/lang/StringBuilder;
      12: aload_0
      13: invokestatic  #6                  // Method com/typesafe/config/impl/Tokens$Comment.access$000:(Lcom/typesafe/config/impl/Tokens$Comment;)Ljava/lang/String;
      16: invokevirtual #5                  // Method java/lang/StringBuilder.append:(Ljava/lang/String;)Ljava/lang/StringBuilder;
      19: invokevirtual #7                  // Method java/lang/StringBuilder.toString:()Ljava/lang/String;
      22: areturn
}
