Compiled from "PS.java"
class com.github.benmanes.caffeine.cache.PS<K, V> extends com.github.benmanes.caffeine.cache.Node<K, V> implements com.github.benmanes.caffeine.cache.NodeFactory<K, V> {
  protected static final long KEY_OFFSET;

  protected static final long VALUE_OFFSET;

  volatile K key;

  volatile V value;

  com.github.benmanes.caffeine.cache.PS();
    Code:
       0: aload_0
       1: invokespecial #1                  // Method com/github/benmanes/caffeine/cache/Node."<init>":()V
       4: return

  com.github.benmanes.caffeine.cache.PS(K, java.lang.ref.ReferenceQueue<K>, V, java.lang.ref.ReferenceQueue<V>, int, long);
    Code:
       0: aload_0
       1: aload_1
       2: aload_3
       3: aload         4
       5: iload         5
       7: lload         6
       9: invokespecial #2                  // Method "<init>":(Ljava/lang/Object;Ljava/lang/Object;Ljava/lang/ref/ReferenceQueue;IJ)V
      12: return

  com.github.benmanes.caffeine.cache.PS(java.lang.Object, V, java.lang.ref.ReferenceQueue<V>, int, long);
    Code:
       0: aload_0
       1: invokespecial #1                  // Method com/github/benmanes/caffeine/cache/Node."<init>":()V
       4: getstatic     #3                  // Field com/github/benmanes/caffeine/cache/UnsafeAccess.UNSAFE:Lsun/misc/Unsafe;
       7: aload_0
       8: getstatic     #4                  // Field KEY_OFFSET:J
      11: aload_1
      12: invokevirtual #5                  // Method sun/misc/Unsafe.putObject:(Ljava/lang/Object;JLjava/lang/Object;)V
      15: getstatic     #3                  // Field com/github/benmanes/caffeine/cache/UnsafeAccess.UNSAFE:Lsun/misc/Unsafe;
      18: aload_0
      19: getstatic     #6                  // Field VALUE_OFFSET:J
      22: aload_2
      23: invokevirtual #5                  // Method sun/misc/Unsafe.putObject:(Ljava/lang/Object;JLjava/lang/Object;)V
      26: return

  public final K getKey();
    Code:
       0: getstatic     #3                  // Field com/github/benmanes/caffeine/cache/UnsafeAccess.UNSAFE:Lsun/misc/Unsafe;
       3: aload_0
       4: getstatic     #4                  // Field KEY_OFFSET:J
       7: invokevirtual #7                  // Method sun/misc/Unsafe.getObject:(Ljava/lang/Object;J)Ljava/lang/Object;
      10: areturn

  public final java.lang.Object getKeyReference();
    Code:
       0: getstatic     #3                  // Field com/github/benmanes/caffeine/cache/UnsafeAccess.UNSAFE:Lsun/misc/Unsafe;
       3: aload_0
       4: getstatic     #4                  // Field KEY_OFFSET:J
       7: invokevirtual #7                  // Method sun/misc/Unsafe.getObject:(Ljava/lang/Object;J)Ljava/lang/Object;
      10: areturn

  public final V getValue();
    Code:
       0: getstatic     #3                  // Field com/github/benmanes/caffeine/cache/UnsafeAccess.UNSAFE:Lsun/misc/Unsafe;
       3: aload_0
       4: getstatic     #6                  // Field VALUE_OFFSET:J
       7: invokevirtual #7                  // Method sun/misc/Unsafe.getObject:(Ljava/lang/Object;J)Ljava/lang/Object;
      10: areturn

  public final java.lang.Object getValueReference();
    Code:
       0: getstatic     #3                  // Field com/github/benmanes/caffeine/cache/UnsafeAccess.UNSAFE:Lsun/misc/Unsafe;
       3: aload_0
       4: getstatic     #6                  // Field VALUE_OFFSET:J
       7: invokevirtual #7                  // Method sun/misc/Unsafe.getObject:(Ljava/lang/Object;J)Ljava/lang/Object;
      10: areturn

  public final void setValue(V, java.lang.ref.ReferenceQueue<V>);
    Code:
       0: getstatic     #3                  // Field com/github/benmanes/caffeine/cache/UnsafeAccess.UNSAFE:Lsun/misc/Unsafe;
       3: aload_0
       4: getstatic     #6                  // Field VALUE_OFFSET:J
       7: aload_1
       8: invokevirtual #5                  // Method sun/misc/Unsafe.putObject:(Ljava/lang/Object;JLjava/lang/Object;)V
      11: return

  public final boolean containsValue(java.lang.Object);
    Code:
       0: aload_1
       1: aload_0
       2: invokevirtual #8                  // Method getValue:()Ljava/lang/Object;
       5: invokestatic  #9                  // Method java/util/Objects.equals:(Ljava/lang/Object;Ljava/lang/Object;)Z
       8: ireturn

  public com.github.benmanes.caffeine.cache.Node<K, V> newNode(K, java.lang.ref.ReferenceQueue<K>, V, java.lang.ref.ReferenceQueue<V>, int, long);
    Code:
       0: new           #10                 // class com/github/benmanes/caffeine/cache/PS
       3: dup
       4: aload_1
       5: aload_2
       6: aload_3
       7: aload         4
       9: iload         5
      11: lload         6
      13: invokespecial #11                 // Method "<init>":(Ljava/lang/Object;Ljava/lang/ref/ReferenceQueue;Ljava/lang/Object;Ljava/lang/ref/ReferenceQueue;IJ)V
      16: areturn

  public com.github.benmanes.caffeine.cache.Node<K, V> newNode(java.lang.Object, V, java.lang.ref.ReferenceQueue<V>, int, long);
    Code:
       0: new           #10                 // class com/github/benmanes/caffeine/cache/PS
       3: dup
       4: aload_1
       5: aload_2
       6: aload_3
       7: iload         4
       9: lload         5
      11: invokespecial #2                  // Method "<init>":(Ljava/lang/Object;Ljava/lang/Object;Ljava/lang/ref/ReferenceQueue;IJ)V
      14: areturn

  public final boolean isAlive();
    Code:
       0: aload_0
       1: invokevirtual #12                 // Method getKeyReference:()Ljava/lang/Object;
       4: astore_1
       5: aload_1
       6: getstatic     #13                 // Field RETIRED_STRONG_KEY:Ljava/lang/Object;
       9: if_acmpeq     23
      12: aload_1
      13: getstatic     #14                 // Field DEAD_STRONG_KEY:Ljava/lang/Object;
      16: if_acmpeq     23
      19: iconst_1
      20: goto          24
      23: iconst_0
      24: ireturn

  public final boolean isRetired();
    Code:
       0: aload_0
       1: invokevirtual #12                 // Method getKeyReference:()Ljava/lang/Object;
       4: getstatic     #13                 // Field RETIRED_STRONG_KEY:Ljava/lang/Object;
       7: if_acmpne     14
      10: iconst_1
      11: goto          15
      14: iconst_0
      15: ireturn

  public final void retire();
    Code:
       0: getstatic     #3                  // Field com/github/benmanes/caffeine/cache/UnsafeAccess.UNSAFE:Lsun/misc/Unsafe;
       3: aload_0
       4: getstatic     #4                  // Field KEY_OFFSET:J
       7: getstatic     #13                 // Field RETIRED_STRONG_KEY:Ljava/lang/Object;
      10: invokevirtual #5                  // Method sun/misc/Unsafe.putObject:(Ljava/lang/Object;JLjava/lang/Object;)V
      13: return

  public final boolean isDead();
    Code:
       0: aload_0
       1: invokevirtual #12                 // Method getKeyReference:()Ljava/lang/Object;
       4: getstatic     #14                 // Field DEAD_STRONG_KEY:Ljava/lang/Object;
       7: if_acmpne     14
      10: iconst_1
      11: goto          15
      14: iconst_0
      15: ireturn

  public final void die();
    Code:
       0: getstatic     #3                  // Field com/github/benmanes/caffeine/cache/UnsafeAccess.UNSAFE:Lsun/misc/Unsafe;
       3: aload_0
       4: getstatic     #6                  // Field VALUE_OFFSET:J
       7: aconst_null
       8: invokevirtual #5                  // Method sun/misc/Unsafe.putObject:(Ljava/lang/Object;JLjava/lang/Object;)V
      11: getstatic     #3                  // Field com/github/benmanes/caffeine/cache/UnsafeAccess.UNSAFE:Lsun/misc/Unsafe;
      14: aload_0
      15: getstatic     #4                  // Field KEY_OFFSET:J
      18: getstatic     #14                 // Field DEAD_STRONG_KEY:Ljava/lang/Object;
      21: invokevirtual #5                  // Method sun/misc/Unsafe.putObject:(Ljava/lang/Object;JLjava/lang/Object;)V
      24: return

  static {};
    Code:
       0: ldc           #10                 // class com/github/benmanes/caffeine/cache/PS
       2: ldc           #16                 // String key
       4: invokestatic  #17                 // Method com/github/benmanes/caffeine/cache/UnsafeAccess.objectFieldOffset:(Ljava/lang/Class;Ljava/lang/String;)J
       7: putstatic     #4                  // Field KEY_OFFSET:J
      10: ldc           #10                 // class com/github/benmanes/caffeine/cache/PS
      12: ldc           #18                 // String value
      14: invokestatic  #17                 // Method com/github/benmanes/caffeine/cache/UnsafeAccess.objectFieldOffset:(Ljava/lang/Class;Ljava/lang/String;)J
      17: putstatic     #6                  // Field VALUE_OFFSET:J
      20: return
}
