Compiled from "Scheduler.java"
final class com.github.benmanes.caffeine.cache.SystemScheduler extends java.lang.Enum<com.github.benmanes.caffeine.cache.SystemScheduler> implements com.github.benmanes.caffeine.cache.Scheduler {
  public static final com.github.benmanes.caffeine.cache.SystemScheduler INSTANCE;

  static final java.lang.reflect.Method delayedExecutor;

  private static final com.github.benmanes.caffeine.cache.SystemScheduler[] $VALUES;

  public static com.github.benmanes.caffeine.cache.SystemScheduler[] values();
    Code:
       0: getstatic     #1                  // Field $VALUES:[Lcom/github/benmanes/caffeine/cache/SystemScheduler;
       3: invokevirtual #2                  // Method "[Lcom/github/benmanes/caffeine/cache/SystemScheduler;".clone:()Ljava/lang/Object;
       6: checkcast     #3                  // class "[Lcom/github/benmanes/caffeine/cache/SystemScheduler;"
       9: areturn

  public static com.github.benmanes.caffeine.cache.SystemScheduler valueOf(java.lang.String);
    Code:
       0: ldc           #4                  // class com/github/benmanes/caffeine/cache/SystemScheduler
       2: aload_0
       3: invokestatic  #5                  // Method java/lang/Enum.valueOf:(Ljava/lang/Class;Ljava/lang/String;)Ljava/lang/Enum;
       6: checkcast     #4                  // class com/github/benmanes/caffeine/cache/SystemScheduler
       9: areturn

  private com.github.benmanes.caffeine.cache.SystemScheduler();
    Code:
       0: aload_0
       1: aload_1
       2: iload_2
       3: invokespecial #6                  // Method java/lang/Enum."<init>":(Ljava/lang/String;I)V
       6: return

  public java.util.concurrent.Future<?> schedule(java.util.concurrent.Executor, java.lang.Runnable, long, java.util.concurrent.TimeUnit);
    Code:
       0: aload_1
       1: invokestatic  #7                  // Method java/util/Objects.requireNonNull:(Ljava/lang/Object;)Ljava/lang/Object;
       4: pop
       5: aload_2
       6: invokestatic  #7                  // Method java/util/Objects.requireNonNull:(Ljava/lang/Object;)Ljava/lang/Object;
       9: pop
      10: aload         5
      12: invokestatic  #7                  // Method java/util/Objects.requireNonNull:(Ljava/lang/Object;)Ljava/lang/Object;
      15: pop
      16: getstatic     #8                  // Field delayedExecutor:Ljava/lang/reflect/Method;
      19: ldc           #9                  // class java/util/concurrent/CompletableFuture
      21: iconst_3
      22: anewarray     #10                 // class java/lang/Object
      25: dup
      26: iconst_0
      27: lload_3
      28: invokestatic  #11                 // Method java/lang/Long.valueOf:(J)Ljava/lang/Long;
      31: aastore
      32: dup
      33: iconst_1
      34: aload         5
      36: aastore
      37: dup
      38: iconst_2
      39: aload_1
      40: aastore
      41: invokevirtual #12                 // Method java/lang/reflect/Method.invoke:(Ljava/lang/Object;[Ljava/lang/Object;)Ljava/lang/Object;
      44: checkcast     #13                 // class java/util/concurrent/Executor
      47: astore        6
      49: aload_2
      50: aload         6
      52: invokestatic  #14                 // Method java/util/concurrent/CompletableFuture.runAsync:(Ljava/lang/Runnable;Ljava/util/concurrent/Executor;)Ljava/util/concurrent/CompletableFuture;
      55: areturn
      56: astore        6
      58: new           #17                 // class java/lang/RuntimeException
      61: dup
      62: aload         6
      64: invokespecial #18                 // Method java/lang/RuntimeException."<init>":(Ljava/lang/Throwable;)V
      67: athrow
    Exception table:
       from    to  target type
          16    55    56   Class java/lang/IllegalAccessException
          16    55    56   Class java/lang/reflect/InvocationTargetException

  static java.lang.reflect.Method getDelayedExecutorMethod();
    Code:
       0: ldc           #9                  // class java/util/concurrent/CompletableFuture
       2: ldc           #19                 // String delayedExecutor
       4: iconst_3
       5: anewarray     #20                 // class java/lang/Class
       8: dup
       9: iconst_0
      10: getstatic     #21                 // Field java/lang/Long.TYPE:Ljava/lang/Class;
      13: aastore
      14: dup
      15: iconst_1
      16: ldc           #22                 // class java/util/concurrent/TimeUnit
      18: aastore
      19: dup
      20: iconst_2
      21: ldc           #13                 // class java/util/concurrent/Executor
      23: aastore
      24: invokevirtual #23                 // Method java/lang/Class.getMethod:(Ljava/lang/String;[Ljava/lang/Class;)Ljava/lang/reflect/Method;
      27: areturn
      28: astore_0
      29: aconst_null
      30: areturn
    Exception table:
       from    to  target type
           0    27    28   Class java/lang/NoSuchMethodException
           0    27    28   Class java/lang/SecurityException

  static boolean isPresent();
    Code:
       0: getstatic     #8                  // Field delayedExecutor:Ljava/lang/reflect/Method;
       3: ifnull        10
       6: iconst_1
       7: goto          11
      10: iconst_0
      11: ireturn

  static {};
    Code:
       0: new           #4                  // class com/github/benmanes/caffeine/cache/SystemScheduler
       3: dup
       4: ldc           #26                 // String INSTANCE
       6: iconst_0
       7: invokespecial #27                 // Method "<init>":(Ljava/lang/String;I)V
      10: putstatic     #28                 // Field INSTANCE:Lcom/github/benmanes/caffeine/cache/SystemScheduler;
      13: iconst_1
      14: anewarray     #4                  // class com/github/benmanes/caffeine/cache/SystemScheduler
      17: dup
      18: iconst_0
      19: getstatic     #28                 // Field INSTANCE:Lcom/github/benmanes/caffeine/cache/SystemScheduler;
      22: aastore
      23: putstatic     #1                  // Field $VALUES:[Lcom/github/benmanes/caffeine/cache/SystemScheduler;
      26: invokestatic  #29                 // Method getDelayedExecutorMethod:()Ljava/lang/reflect/Method;
      29: putstatic     #8                  // Field delayedExecutor:Ljava/lang/reflect/Method;
      32: return
}
