Compiled from "ComponentTuplizerFactory.java"
public class org.hibernate.tuple.component.ComponentTuplizerFactory implements java.io.Serializable {
  private static final java.lang.Class[] COMPONENT_TUP_CTOR_SIG;

  private java.util.Map<org.hibernate.EntityMode, java.lang.Class<? extends org.hibernate.tuple.component.ComponentTuplizer>> defaultImplClassByMode;

  private final org.hibernate.boot.spi.ClassLoaderAccess classLoaderAccess;

  static final boolean $assertionsDisabled;

  public org.hibernate.tuple.component.ComponentTuplizerFactory(org.hibernate.boot.spi.MetadataBuildingOptions);
    Code:
       0: aload_0
       1: invokespecial #1                  // Method java/lang/Object."<init>":()V
       4: aload_0
       5: invokestatic  #2                  // Method buildBaseMapping:()Ljava/util/Map;
       8: putfield      #3                  // Field defaultImplClassByMode:Ljava/util/Map;
      11: aload_0
      12: new           #4                  // class org/hibernate/boot/internal/ClassLoaderAccessImpl
      15: dup
      16: aload_1
      17: invokeinterface #5,  1            // InterfaceMethod org/hibernate/boot/spi/MetadataBuildingOptions.getTempClassLoader:()Ljava/lang/ClassLoader;
      22: aload_1
      23: invokeinterface #6,  1            // InterfaceMethod org/hibernate/boot/spi/MetadataBuildingOptions.getServiceRegistry:()Lorg/hibernate/boot/registry/StandardServiceRegistry;
      28: ldc           #7                  // class org/hibernate/boot/registry/classloading/spi/ClassLoaderService
      30: invokeinterface #8,  2            // InterfaceMethod org/hibernate/boot/registry/StandardServiceRegistry.getService:(Ljava/lang/Class;)Lorg/hibernate/service/Service;
      35: checkcast     #7                  // class org/hibernate/boot/registry/classloading/spi/ClassLoaderService
      38: invokespecial #9                  // Method org/hibernate/boot/internal/ClassLoaderAccessImpl."<init>":(Ljava/lang/ClassLoader;Lorg/hibernate/boot/registry/classloading/spi/ClassLoaderService;)V
      41: putfield      #10                 // Field classLoaderAccess:Lorg/hibernate/boot/spi/ClassLoaderAccess;
      44: return

  public org.hibernate.tuple.component.ComponentTuplizerFactory(org.hibernate.boot.spi.BootstrapContext);
    Code:
       0: aload_0
       1: invokespecial #1                  // Method java/lang/Object."<init>":()V
       4: aload_0
       5: invokestatic  #2                  // Method buildBaseMapping:()Ljava/util/Map;
       8: putfield      #3                  // Field defaultImplClassByMode:Ljava/util/Map;
      11: aload_0
      12: aload_1
      13: invokeinterface #11,  1           // InterfaceMethod org/hibernate/boot/spi/BootstrapContext.getClassLoaderAccess:()Lorg/hibernate/boot/spi/ClassLoaderAccess;
      18: putfield      #10                 // Field classLoaderAccess:Lorg/hibernate/boot/spi/ClassLoaderAccess;
      21: return

  public void registerDefaultTuplizerClass(org.hibernate.EntityMode, java.lang.Class<? extends org.hibernate.tuple.component.ComponentTuplizer>);
    Code:
       0: getstatic     #12                 // Field $assertionsDisabled:Z
       3: ifne          57
       6: aload_0
       7: aload_2
       8: invokespecial #13                 // Method isComponentTuplizerImplementor:(Ljava/lang/Class;)Z
      11: ifne          57
      14: new           #14                 // class java/lang/AssertionError
      17: dup
      18: new           #15                 // class java/lang/StringBuilder
      21: dup
      22: invokespecial #16                 // Method java/lang/StringBuilder."<init>":()V
      25: ldc           #17                 // String Specified tuplizer class [
      27: invokevirtual #18                 // Method java/lang/StringBuilder.append:(Ljava/lang/String;)Ljava/lang/StringBuilder;
      30: aload_2
      31: invokevirtual #19                 // Method java/lang/Class.getName:()Ljava/lang/String;
      34: invokevirtual #18                 // Method java/lang/StringBuilder.append:(Ljava/lang/String;)Ljava/lang/StringBuilder;
      37: ldc           #20                 // String ] does not implement
      39: invokevirtual #18                 // Method java/lang/StringBuilder.append:(Ljava/lang/String;)Ljava/lang/StringBuilder;
      42: ldc           #21                 // class org/hibernate/tuple/component/ComponentTuplizer
      44: invokevirtual #19                 // Method java/lang/Class.getName:()Ljava/lang/String;
      47: invokevirtual #18                 // Method java/lang/StringBuilder.append:(Ljava/lang/String;)Ljava/lang/StringBuilder;
      50: invokevirtual #22                 // Method java/lang/StringBuilder.toString:()Ljava/lang/String;
      53: invokespecial #23                 // Method java/lang/AssertionError."<init>":(Ljava/lang/Object;)V
      56: athrow
      57: getstatic     #12                 // Field $assertionsDisabled:Z
      60: ifne          106
      63: aload_0
      64: aload_2
      65: invokespecial #24                 // Method hasProperConstructor:(Ljava/lang/Class;)Z
      68: ifne          106
      71: new           #14                 // class java/lang/AssertionError
      74: dup
      75: new           #15                 // class java/lang/StringBuilder
      78: dup
      79: invokespecial #16                 // Method java/lang/StringBuilder."<init>":()V
      82: ldc           #17                 // String Specified tuplizer class [
      84: invokevirtual #18                 // Method java/lang/StringBuilder.append:(Ljava/lang/String;)Ljava/lang/StringBuilder;
      87: aload_2
      88: invokevirtual #19                 // Method java/lang/Class.getName:()Ljava/lang/String;
      91: invokevirtual #18                 // Method java/lang/StringBuilder.append:(Ljava/lang/String;)Ljava/lang/StringBuilder;
      94: ldc           #25                 // String ] is not properly instantiatable
      96: invokevirtual #18                 // Method java/lang/StringBuilder.append:(Ljava/lang/String;)Ljava/lang/StringBuilder;
      99: invokevirtual #22                 // Method java/lang/StringBuilder.toString:()Ljava/lang/String;
     102: invokespecial #23                 // Method java/lang/AssertionError."<init>":(Ljava/lang/Object;)V
     105: athrow
     106: aload_0
     107: getfield      #3                  // Field defaultImplClassByMode:Ljava/util/Map;
     110: aload_1
     111: aload_2
     112: invokeinterface #26,  3           // InterfaceMethod java/util/Map.put:(Ljava/lang/Object;Ljava/lang/Object;)Ljava/lang/Object;
     117: pop
     118: return

  public org.hibernate.tuple.component.ComponentTuplizer constructTuplizer(java.lang.String, org.hibernate.mapping.Component);
    Code:
       0: aload_0
       1: getfield      #10                 // Field classLoaderAccess:Lorg/hibernate/boot/spi/ClassLoaderAccess;
       4: aload_1
       5: invokeinterface #27,  2           // InterfaceMethod org/hibernate/boot/spi/ClassLoaderAccess.classForName:(Ljava/lang/String;)Ljava/lang/Class;
      10: astore_3
      11: aload_0
      12: aload_3
      13: aload_2
      14: invokevirtual #28                 // Method constructTuplizer:(Ljava/lang/Class;Lorg/hibernate/mapping/Component;)Lorg/hibernate/tuple/component/ComponentTuplizer;
      17: areturn
      18: astore_3
      19: new           #30                 // class org/hibernate/HibernateException
      22: dup
      23: new           #15                 // class java/lang/StringBuilder
      26: dup
      27: invokespecial #16                 // Method java/lang/StringBuilder."<init>":()V
      30: ldc           #31                 // String Could not locate specified tuplizer class [
      32: invokevirtual #18                 // Method java/lang/StringBuilder.append:(Ljava/lang/String;)Ljava/lang/StringBuilder;
      35: aload_1
      36: invokevirtual #18                 // Method java/lang/StringBuilder.append:(Ljava/lang/String;)Ljava/lang/StringBuilder;
      39: ldc           #32                 // String ]
      41: invokevirtual #18                 // Method java/lang/StringBuilder.append:(Ljava/lang/String;)Ljava/lang/StringBuilder;
      44: invokevirtual #22                 // Method java/lang/StringBuilder.toString:()Ljava/lang/String;
      47: invokespecial #33                 // Method org/hibernate/HibernateException."<init>":(Ljava/lang/String;)V
      50: athrow
    Exception table:
       from    to  target type
           0    17    18   Class org/hibernate/boot/registry/classloading/spi/ClassLoadingException

  public org.hibernate.tuple.component.ComponentTuplizer constructTuplizer(java.lang.Class<? extends org.hibernate.tuple.component.ComponentTuplizer>, org.hibernate.mapping.Component);
    Code:
       0: aload_0
       1: aload_1
       2: invokespecial #34                 // Method getProperConstructor:(Ljava/lang/Class;)Ljava/lang/reflect/Constructor;
       5: astore_3
       6: getstatic     #12                 // Field $assertionsDisabled:Z
       9: ifne          51
      12: aload_3
      13: ifnonnull     51
      16: new           #14                 // class java/lang/AssertionError
      19: dup
      20: new           #15                 // class java/lang/StringBuilder
      23: dup
      24: invokespecial #16                 // Method java/lang/StringBuilder."<init>":()V
      27: ldc           #35                 // String Unable to locate proper constructor for tuplizer [
      29: invokevirtual #18                 // Method java/lang/StringBuilder.append:(Ljava/lang/String;)Ljava/lang/StringBuilder;
      32: aload_1
      33: invokevirtual #19                 // Method java/lang/Class.getName:()Ljava/lang/String;
      36: invokevirtual #18                 // Method java/lang/StringBuilder.append:(Ljava/lang/String;)Ljava/lang/StringBuilder;
      39: ldc           #32                 // String ]
      41: invokevirtual #18                 // Method java/lang/StringBuilder.append:(Ljava/lang/String;)Ljava/lang/StringBuilder;
      44: invokevirtual #22                 // Method java/lang/StringBuilder.toString:()Ljava/lang/String;
      47: invokespecial #23                 // Method java/lang/AssertionError."<init>":(Ljava/lang/Object;)V
      50: athrow
      51: aload_3
      52: iconst_1
      53: anewarray     #36                 // class java/lang/Object
      56: dup
      57: iconst_0
      58: aload_2
      59: aastore
      60: invokevirtual #37                 // Method java/lang/reflect/Constructor.newInstance:([Ljava/lang/Object;)Ljava/lang/Object;
      63: checkcast     #21                 // class org/hibernate/tuple/component/ComponentTuplizer
      66: areturn
      67: astore        4
      69: new           #30                 // class org/hibernate/HibernateException
      72: dup
      73: new           #15                 // class java/lang/StringBuilder
      76: dup
      77: invokespecial #16                 // Method java/lang/StringBuilder."<init>":()V
      80: ldc           #39                 // String Unable to instantiate default tuplizer [
      82: invokevirtual #18                 // Method java/lang/StringBuilder.append:(Ljava/lang/String;)Ljava/lang/StringBuilder;
      85: aload_1
      86: invokevirtual #19                 // Method java/lang/Class.getName:()Ljava/lang/String;
      89: invokevirtual #18                 // Method java/lang/StringBuilder.append:(Ljava/lang/String;)Ljava/lang/StringBuilder;
      92: ldc           #32                 // String ]
      94: invokevirtual #18                 // Method java/lang/StringBuilder.append:(Ljava/lang/String;)Ljava/lang/StringBuilder;
      97: invokevirtual #22                 // Method java/lang/StringBuilder.toString:()Ljava/lang/String;
     100: aload         4
     102: invokespecial #40                 // Method org/hibernate/HibernateException."<init>":(Ljava/lang/String;Ljava/lang/Throwable;)V
     105: athrow
    Exception table:
       from    to  target type
          51    66    67   Class java/lang/Throwable

  public org.hibernate.tuple.component.ComponentTuplizer constructDefaultTuplizer(org.hibernate.EntityMode, org.hibernate.mapping.Component);
    Code:
       0: aload_0
       1: getfield      #3                  // Field defaultImplClassByMode:Ljava/util/Map;
       4: aload_1
       5: invokeinterface #41,  2           // InterfaceMethod java/util/Map.get:(Ljava/lang/Object;)Ljava/lang/Object;
      10: checkcast     #42                 // class java/lang/Class
      13: astore_3
      14: aload_3
      15: ifnonnull     50
      18: new           #30                 // class org/hibernate/HibernateException
      21: dup
      22: new           #15                 // class java/lang/StringBuilder
      25: dup
      26: invokespecial #16                 // Method java/lang/StringBuilder."<init>":()V
      29: ldc           #43                 // String could not determine default tuplizer class to use [
      31: invokevirtual #18                 // Method java/lang/StringBuilder.append:(Ljava/lang/String;)Ljava/lang/StringBuilder;
      34: aload_1
      35: invokevirtual #44                 // Method java/lang/StringBuilder.append:(Ljava/lang/Object;)Ljava/lang/StringBuilder;
      38: ldc           #32                 // String ]
      40: invokevirtual #18                 // Method java/lang/StringBuilder.append:(Ljava/lang/String;)Ljava/lang/StringBuilder;
      43: invokevirtual #22                 // Method java/lang/StringBuilder.toString:()Ljava/lang/String;
      46: invokespecial #33                 // Method org/hibernate/HibernateException."<init>":(Ljava/lang/String;)V
      49: athrow
      50: aload_0
      51: aload_3
      52: aload_2
      53: invokevirtual #28                 // Method constructTuplizer:(Ljava/lang/Class;Lorg/hibernate/mapping/Component;)Lorg/hibernate/tuple/component/ComponentTuplizer;
      56: areturn

  private boolean isComponentTuplizerImplementor(java.lang.Class);
    Code:
       0: aload_1
       1: ldc           #21                 // class org/hibernate/tuple/component/ComponentTuplizer
       3: invokestatic  #45                 // Method org/hibernate/internal/util/ReflectHelper.implementsInterface:(Ljava/lang/Class;Ljava/lang/Class;)Z
       6: ireturn

  private boolean hasProperConstructor(java.lang.Class);
    Code:
       0: aload_0
       1: aload_1
       2: invokespecial #34                 // Method getProperConstructor:(Ljava/lang/Class;)Ljava/lang/reflect/Constructor;
       5: ifnull        12
       8: iconst_1
       9: goto          13
      12: iconst_0
      13: ireturn

  private java.lang.reflect.Constructor<? extends org.hibernate.tuple.component.ComponentTuplizer> getProperConstructor(java.lang.Class<? extends org.hibernate.tuple.component.ComponentTuplizer>);
    Code:
       0: aconst_null
       1: astore_2
       2: aload_1
       3: getstatic     #46                 // Field COMPONENT_TUP_CTOR_SIG:[Ljava/lang/Class;
       6: invokevirtual #47                 // Method java/lang/Class.getDeclaredConstructor:([Ljava/lang/Class;)Ljava/lang/reflect/Constructor;
       9: astore_2
      10: aload_2
      11: invokestatic  #48                 // Method org/hibernate/internal/util/ReflectHelper.ensureAccessibility:(Ljava/lang/reflect/AccessibleObject;)V
      14: goto          20
      17: astore_3
      18: aconst_null
      19: astore_2
      20: goto          24
      23: astore_3
      24: aload_2
      25: areturn
    Exception table:
       from    to  target type
          10    14    17   Class java/lang/SecurityException
           2    20    23   Class java/lang/NoSuchMethodException

  private static java.util.Map<org.hibernate.EntityMode, java.lang.Class<? extends org.hibernate.tuple.component.ComponentTuplizer>> buildBaseMapping();
    Code:
       0: new           #51                 // class java/util/concurrent/ConcurrentHashMap
       3: dup
       4: invokespecial #52                 // Method java/util/concurrent/ConcurrentHashMap."<init>":()V
       7: astore_0
       8: aload_0
       9: getstatic     #53                 // Field org/hibernate/EntityMode.POJO:Lorg/hibernate/EntityMode;
      12: ldc           #54                 // class org/hibernate/tuple/component/PojoComponentTuplizer
      14: invokeinterface #26,  3           // InterfaceMethod java/util/Map.put:(Ljava/lang/Object;Ljava/lang/Object;)Ljava/lang/Object;
      19: pop
      20: aload_0
      21: getstatic     #55                 // Field org/hibernate/EntityMode.MAP:Lorg/hibernate/EntityMode;
      24: ldc           #56                 // class org/hibernate/tuple/component/DynamicMapComponentTuplizer
      26: invokeinterface #26,  3           // InterfaceMethod java/util/Map.put:(Ljava/lang/Object;Ljava/lang/Object;)Ljava/lang/Object;
      31: pop
      32: aload_0
      33: areturn

  static {};
    Code:
       0: ldc           #57                 // class org/hibernate/tuple/component/ComponentTuplizerFactory
       2: invokevirtual #58                 // Method java/lang/Class.desiredAssertionStatus:()Z
       5: ifne          12
       8: iconst_1
       9: goto          13
      12: iconst_0
      13: putstatic     #12                 // Field $assertionsDisabled:Z
      16: iconst_1
      17: anewarray     #42                 // class java/lang/Class
      20: dup
      21: iconst_0
      22: ldc           #59                 // class org/hibernate/mapping/Component
      24: aastore
      25: putstatic     #46                 // Field COMPONENT_TUP_CTOR_SIG:[Ljava/lang/Class;
      28: return
}
