Compiled from "PlatformImplementations.kt"
final class kotlin.internal.PlatformImplementations$ReflectThrowable {
  public static final java.lang.reflect.Method addSuppressed;

  public static final java.lang.reflect.Method getSuppressed;

  public static final kotlin.internal.PlatformImplementations$ReflectThrowable INSTANCE;

  private kotlin.internal.PlatformImplementations$ReflectThrowable();
    Code:
       0: aload_0
       1: invokespecial #13                 // Method java/lang/Object."<init>":()V
       4: return

  static {};
    Code:
       0: new           #2                  // class kotlin/internal/PlatformImplementations$ReflectThrowable
       3: dup
       4: invokespecial #32                 // Method "<init>":()V
       7: astore_0
       8: aload_0
       9: putstatic     #34                 // Field INSTANCE:Lkotlin/internal/PlatformImplementations$ReflectThrowable;
      12: nop
      13: ldc           #36                 // class java/lang/Throwable
      15: astore_1
      16: aload_1
      17: invokevirtual #42                 // Method java/lang/Class.getMethods:()[Ljava/lang/reflect/Method;
      20: astore_2
      21: aload_2
      22: dup
      23: ldc           #44                 // String throwableMethods
      25: invokestatic  #50                 // Method kotlin/jvm/internal/Intrinsics.checkNotNullExpressionValue:(Ljava/lang/Object;Ljava/lang/String;)V
      28: astore_3
      29: iconst_0
      30: istore        4
      32: aload_3
      33: astore        5
      35: iconst_0
      36: istore        6
      38: aload         5
      40: astore        7
      42: aload         7
      44: arraylength
      45: istore        8
      47: iconst_0
      48: istore        9
      50: iload         9
      52: iload         8
      54: if_icmpge     133
      57: aload         7
      59: iload         9
      61: aaload
      62: astore        10
      64: aload         10
      66: astore        11
      68: iconst_0
      69: istore        12
      71: aload         11
      73: dup
      74: ldc           #52                 // String it
      76: invokestatic  #50                 // Method kotlin/jvm/internal/Intrinsics.checkNotNullExpressionValue:(Ljava/lang/Object;Ljava/lang/String;)V
      79: invokevirtual #58                 // Method java/lang/reflect/Method.getName:()Ljava/lang/String;
      82: ldc           #59                 // String addSuppressed
      84: invokestatic  #63                 // Method kotlin/jvm/internal/Intrinsics.areEqual:(Ljava/lang/Object;Ljava/lang/Object;)Z
      87: ifeq          118
      90: aload         11
      92: invokevirtual #67                 // Method java/lang/reflect/Method.getParameterTypes:()[Ljava/lang/Class;
      95: dup
      96: ldc           #69                 // String it.parameterTypes
      98: invokestatic  #50                 // Method kotlin/jvm/internal/Intrinsics.checkNotNullExpressionValue:(Ljava/lang/Object;Ljava/lang/String;)V
     101: invokestatic  #75                 // Method kotlin/collections/ArraysKt.singleOrNull:([Ljava/lang/Object;)Ljava/lang/Object;
     104: checkcast     #38                 // class java/lang/Class
     107: aload_1
     108: invokestatic  #63                 // Method kotlin/jvm/internal/Intrinsics.areEqual:(Ljava/lang/Object;Ljava/lang/Object;)Z
     111: ifeq          118
     114: iconst_1
     115: goto          119
     118: iconst_0
     119: ifeq          127
     122: aload         10
     124: goto          134
     127: iinc          9, 1
     130: goto          50
     133: aconst_null
     134: putstatic     #77                 // Field addSuppressed:Ljava/lang/reflect/Method;
     137: aload_2
     138: astore_3
     139: iconst_0
     140: istore        4
     142: aload_3
     143: astore        5
     145: iconst_0
     146: istore        6
     148: aload         5
     150: astore        7
     152: aload         7
     154: arraylength
     155: istore        8
     157: iconst_0
     158: istore        9
     160: iload         9
     162: iload         8
     164: if_icmpge     211
     167: aload         7
     169: iload         9
     171: aaload
     172: astore        10
     174: aload         10
     176: astore        11
     178: iconst_0
     179: istore        12
     181: aload         11
     183: dup
     184: ldc           #52                 // String it
     186: invokestatic  #50                 // Method kotlin/jvm/internal/Intrinsics.checkNotNullExpressionValue:(Ljava/lang/Object;Ljava/lang/String;)V
     189: invokevirtual #58                 // Method java/lang/reflect/Method.getName:()Ljava/lang/String;
     192: ldc           #78                 // String getSuppressed
     194: invokestatic  #63                 // Method kotlin/jvm/internal/Intrinsics.areEqual:(Ljava/lang/Object;Ljava/lang/Object;)Z
     197: ifeq          205
     200: aload         10
     202: goto          212
     205: iinc          9, 1
     208: goto          160
     211: aconst_null
     212: putstatic     #80                 // Field getSuppressed:Ljava/lang/reflect/Method;
     215: return
}
