Compiled from "SproutConfigurationProperties.java"
public class net.savantly.sprout.autoconfigure.properties.SproutConfigurationProperties$Jwt {
  private java.lang.String secret;

  private java.lang.String base64Secret;

  private long tokenValidityInSeconds;

  private long tokenValidityInSecondsForRememberMe;

  public net.savantly.sprout.autoconfigure.properties.SproutConfigurationProperties$Jwt();
    Code:
       0: aload_0
       1: invokespecial #1                  // Method java/lang/Object."<init>":()V
       4: aload_0
       5: ldc           #2                  // String UseThebAse64SecreTformOreSecurity!
       7: putfield      #3                  // Field secret:Ljava/lang/String;
      10: aload_0
      11: ldc           #4                  // String NDkxYWFlYzJkMDk4Mjk4OTdkMGU5MWQ5MTEwZGZkMjQxYTdkNGYzNGQ3OWI5YzQ2OTA2OGQwYWQxNWVjZWUwMDk3NDA1NjU1YWIxMjE2MTc5YWFjMmVjZGY0NTJhOGZlOTg4ODgwYjBlM2Y5ZTE5NDY2MDZkMGE5Y2Y5MmVlOTY
      13: putfield      #5                  // Field base64Secret:Ljava/lang/String;
      16: aload_0
      17: ldc2_w        #6                  // long 86400l
      20: putfield      #8                  // Field tokenValidityInSeconds:J
      23: aload_0
      24: ldc2_w        #9                  // long 2592000l
      27: putfield      #11                 // Field tokenValidityInSecondsForRememberMe:J
      30: return

  public java.lang.String getSecret();
    Code:
       0: aload_0
       1: getfield      #3                  // Field secret:Ljava/lang/String;
       4: areturn

  public java.lang.String getBase64Secret();
    Code:
       0: aload_0
       1: getfield      #5                  // Field base64Secret:Ljava/lang/String;
       4: areturn

  public long getTokenValidityInSeconds();
    Code:
       0: aload_0
       1: getfield      #8                  // Field tokenValidityInSeconds:J
       4: lreturn

  public long getTokenValidityInSecondsForRememberMe();
    Code:
       0: aload_0
       1: getfield      #11                 // Field tokenValidityInSecondsForRememberMe:J
       4: lreturn

  public void setSecret(java.lang.String);
    Code:
       0: aload_0
       1: aload_1
       2: putfield      #3                  // Field secret:Ljava/lang/String;
       5: return

  public void setBase64Secret(java.lang.String);
    Code:
       0: aload_0
       1: aload_1
       2: putfield      #5                  // Field base64Secret:Ljava/lang/String;
       5: return

  public void setTokenValidityInSeconds(long);
    Code:
       0: aload_0
       1: lload_1
       2: putfield      #8                  // Field tokenValidityInSeconds:J
       5: return

  public void setTokenValidityInSecondsForRememberMe(long);
    Code:
       0: aload_0
       1: lload_1
       2: putfield      #11                 // Field tokenValidityInSecondsForRememberMe:J
       5: return
}
