Compiled from "SproutConfigurationProperties.java"
public class net.savantly.sprout.autoconfigure.properties.SproutConfigurationProperties {
  private net.savantly.sprout.autoconfigure.properties.SproutConfigurationProperties$Security security;

  private net.savantly.sprout.autoconfigure.properties.SproutConfigurationProperties$Jpa jpa;

  private net.savantly.sprout.autoconfigure.properties.SproutConfigurationProperties$Cors cors;

  private net.savantly.sprout.autoconfigure.properties.SproutConfigurationProperties$Mvc mvc;

  public net.savantly.sprout.autoconfigure.properties.SproutConfigurationProperties();
    Code:
       0: aload_0
       1: invokespecial #1                  // Method java/lang/Object."<init>":()V
       4: aload_0
       5: new           #2                  // class net/savantly/sprout/autoconfigure/properties/SproutConfigurationProperties$Security
       8: dup
       9: invokespecial #3                  // Method net/savantly/sprout/autoconfigure/properties/SproutConfigurationProperties$Security."<init>":()V
      12: putfield      #4                  // Field security:Lnet/savantly/sprout/autoconfigure/properties/SproutConfigurationProperties$Security;
      15: aload_0
      16: new           #5                  // class net/savantly/sprout/autoconfigure/properties/SproutConfigurationProperties$Jpa
      19: dup
      20: invokespecial #6                  // Method net/savantly/sprout/autoconfigure/properties/SproutConfigurationProperties$Jpa."<init>":()V
      23: putfield      #7                  // Field jpa:Lnet/savantly/sprout/autoconfigure/properties/SproutConfigurationProperties$Jpa;
      26: aload_0
      27: new           #8                  // class net/savantly/sprout/autoconfigure/properties/SproutConfigurationProperties$Cors
      30: dup
      31: invokespecial #9                  // Method net/savantly/sprout/autoconfigure/properties/SproutConfigurationProperties$Cors."<init>":()V
      34: putfield      #10                 // Field cors:Lnet/savantly/sprout/autoconfigure/properties/SproutConfigurationProperties$Cors;
      37: aload_0
      38: new           #11                 // class net/savantly/sprout/autoconfigure/properties/SproutConfigurationProperties$Mvc
      41: dup
      42: invokespecial #12                 // Method net/savantly/sprout/autoconfigure/properties/SproutConfigurationProperties$Mvc."<init>":()V
      45: putfield      #13                 // Field mvc:Lnet/savantly/sprout/autoconfigure/properties/SproutConfigurationProperties$Mvc;
      48: return

  public net.savantly.sprout.autoconfigure.properties.SproutConfigurationProperties$Security getSecurity();
    Code:
       0: aload_0
       1: getfield      #4                  // Field security:Lnet/savantly/sprout/autoconfigure/properties/SproutConfigurationProperties$Security;
       4: areturn

  public net.savantly.sprout.autoconfigure.properties.SproutConfigurationProperties$Jpa getJpa();
    Code:
       0: aload_0
       1: getfield      #7                  // Field jpa:Lnet/savantly/sprout/autoconfigure/properties/SproutConfigurationProperties$Jpa;
       4: areturn

  public net.savantly.sprout.autoconfigure.properties.SproutConfigurationProperties$Cors getCors();
    Code:
       0: aload_0
       1: getfield      #10                 // Field cors:Lnet/savantly/sprout/autoconfigure/properties/SproutConfigurationProperties$Cors;
       4: areturn

  public net.savantly.sprout.autoconfigure.properties.SproutConfigurationProperties$Mvc getMvc();
    Code:
       0: aload_0
       1: getfield      #13                 // Field mvc:Lnet/savantly/sprout/autoconfigure/properties/SproutConfigurationProperties$Mvc;
       4: areturn

  public void setSecurity(net.savantly.sprout.autoconfigure.properties.SproutConfigurationProperties$Security);
    Code:
       0: aload_0
       1: aload_1
       2: putfield      #4                  // Field security:Lnet/savantly/sprout/autoconfigure/properties/SproutConfigurationProperties$Security;
       5: return

  public void setJpa(net.savantly.sprout.autoconfigure.properties.SproutConfigurationProperties$Jpa);
    Code:
       0: aload_0
       1: aload_1
       2: putfield      #7                  // Field jpa:Lnet/savantly/sprout/autoconfigure/properties/SproutConfigurationProperties$Jpa;
       5: return

  public void setCors(net.savantly.sprout.autoconfigure.properties.SproutConfigurationProperties$Cors);
    Code:
       0: aload_0
       1: aload_1
       2: putfield      #10                 // Field cors:Lnet/savantly/sprout/autoconfigure/properties/SproutConfigurationProperties$Cors;
       5: return

  public void setMvc(net.savantly.sprout.autoconfigure.properties.SproutConfigurationProperties$Mvc);
    Code:
       0: aload_0
       1: aload_1
       2: putfield      #13                 // Field mvc:Lnet/savantly/sprout/autoconfigure/properties/SproutConfigurationProperties$Mvc;
       5: return
}
