Compiled from "EntityContext.java"
public class de.flapdoodle.mongoom.mapping.entities.EntityContext<EntityBean> extends de.flapdoodle.mongoom.mapping.entities.AbstractBeanContext<EntityBean> implements de.flapdoodle.mongoom.mapping.IEntityContext<EntityBean>, de.flapdoodle.mongoom.mapping.entities.IBeanContext<EntityBean> {
  private final de.flapdoodle.mongoom.annotations.Entity _entityAnnotation;

  private final de.flapdoodle.mongoom.annotations.Views _viewsAnnotation;

  private final java.util.Map<java.lang.String, de.flapdoodle.mongoom.mapping.index.EntityIndexDef> _indexGroupMap;

  private final java.util.Map<java.lang.String, de.flapdoodle.mongoom.mapping.index.IndexDef> _indexDef;

  private final java.util.Map<java.lang.Class<?>, de.flapdoodle.mongoom.mapping.IViewTransformation<?, com.mongodb.DBObject>> _viewTransformation;

  private de.flapdoodle.mongoom.mapping.properties.IPropertyField<?> _versionProperty;

  private de.flapdoodle.mongoom.mapping.versions.IVersionFactory<?> _versionFactory;

  private de.flapdoodle.mongoom.mapping.properties.IPropertyField<?> _idProperty;

  private de.flapdoodle.mongoom.mapping.ITransformation<?, ?> _idTransformation;

  private de.flapdoodle.mongoom.mapping.callbacks.IEntityWriteCallback<EntityBean> _writeCallback;

  private de.flapdoodle.mongoom.mapping.callbacks.IEntityReadCallback<EntityBean> _readCallback;

  public de.flapdoodle.mongoom.mapping.entities.EntityContext(java.lang.Class<EntityBean>, de.flapdoodle.mongoom.annotations.Entity, de.flapdoodle.mongoom.annotations.Views, java.util.Map<java.lang.String, de.flapdoodle.mongoom.mapping.index.EntityIndexDef>);
    Code:
       0: aload_0
       1: aload_1
       2: invokespecial #3                  // Method de/flapdoodle/mongoom/mapping/entities/AbstractBeanContext."<init>":(Ljava/lang/Class;)V
       5: aload_0
       6: invokestatic  #4                  // Method com/google/common/collect/Maps.newHashMap:()Ljava/util/HashMap;
       9: putfield      #5                  // Field _viewTransformation:Ljava/util/Map;
      12: aload_0
      13: aload_2
      14: putfield      #6                  // Field _entityAnnotation:Lde/flapdoodle/mongoom/annotations/Entity;
      17: aload_0
      18: aload_3
      19: putfield      #7                  // Field _viewsAnnotation:Lde/flapdoodle/mongoom/annotations/Views;
      22: aload_0
      23: aload         4
      25: putfield      #1                  // Field _indexGroupMap:Ljava/util/Map;
      28: aload_0
      29: invokestatic  #8                  // Method com/google/common/collect/Maps.newLinkedHashMap:()Ljava/util/LinkedHashMap;
      32: putfield      #2                  // Field _indexDef:Ljava/util/Map;
      35: return

  public <S> de.flapdoodle.mongoom.mapping.context.IPropertyContext<S> contextFor(de.flapdoodle.mongoom.mapping.properties.IProperty<S>);
    Code:
       0: new           #9                  // class de/flapdoodle/mongoom/mapping/context/PropertyContext
       3: dup
       4: aload_0
       5: aload_1
       6: invokespecial #10                 // Method de/flapdoodle/mongoom/mapping/context/PropertyContext."<init>":(Lde/flapdoodle/mongoom/mapping/context/IPropertyContext;Lde/flapdoodle/mongoom/mapping/properties/IProperty;)V
       9: areturn

  public java.lang.Class<EntityBean> getEntityClass();
    Code:
       0: aload_0
       1: invokespecial #11                 // Method de/flapdoodle/mongoom/mapping/entities/AbstractBeanContext.getViewClass:()Ljava/lang/Class;
       4: areturn

  public de.flapdoodle.mongoom.annotations.Entity getEntityAnnotation();
    Code:
       0: aload_0
       1: getfield      #6                  // Field _entityAnnotation:Lde/flapdoodle/mongoom/annotations/Entity;
       4: areturn

  public void setVersionFactory(de.flapdoodle.mongoom.mapping.properties.IPropertyField<?>, de.flapdoodle.mongoom.mapping.versions.IVersionFactory<?>);
    Code:
       0: aload_0
       1: aload_1
       2: putfield      #12                 // Field _versionProperty:Lde/flapdoodle/mongoom/mapping/properties/IPropertyField;
       5: aload_0
       6: aload_2
       7: putfield      #13                 // Field _versionFactory:Lde/flapdoodle/mongoom/mapping/versions/IVersionFactory;
      10: return

  public de.flapdoodle.mongoom.mapping.properties.IPropertyField<?> getVersionProperty();
    Code:
       0: aload_0
       1: getfield      #12                 // Field _versionProperty:Lde/flapdoodle/mongoom/mapping/properties/IPropertyField;
       4: areturn

  public de.flapdoodle.mongoom.mapping.versions.IVersionFactory<?> getVersionFactory();
    Code:
       0: aload_0
       1: getfield      #13                 // Field _versionFactory:Lde/flapdoodle/mongoom/mapping/versions/IVersionFactory;
       4: areturn

  public <Source> de.flapdoodle.mongoom.mapping.IViewTransformation<Source, com.mongodb.DBObject> viewTransformation(java.lang.Class<Source>);
    Code:
       0: aload_0
       1: getfield      #5                  // Field _viewTransformation:Ljava/util/Map;
       4: aload_1
       5: invokeinterface #14,  2           // InterfaceMethod java/util/Map.get:(Ljava/lang/Object;)Ljava/lang/Object;
      10: checkcast     #15                 // class de/flapdoodle/mongoom/mapping/IViewTransformation
      13: astore_2
      14: aload_2
      15: ifnonnull     49
      18: new           #16                 // class de/flapdoodle/mongoom/exceptions/MappingException
      21: dup
      22: aload_0
      23: invokevirtual #17                 // Method getEntityClass:()Ljava/lang/Class;
      26: new           #18                 // class java/lang/StringBuilder
      29: dup
      30: invokespecial #19                 // Method java/lang/StringBuilder."<init>":()V
      33: ldc           #20                 // String ViewTransformation for
      35: invokevirtual #21                 // Method java/lang/StringBuilder.append:(Ljava/lang/String;)Ljava/lang/StringBuilder;
      38: aload_1
      39: invokevirtual #22                 // Method java/lang/StringBuilder.append:(Ljava/lang/Object;)Ljava/lang/StringBuilder;
      42: invokevirtual #23                 // Method java/lang/StringBuilder.toString:()Ljava/lang/String;
      45: invokespecial #24                 // Method de/flapdoodle/mongoom/exceptions/MappingException."<init>":(Ljava/lang/Class;Ljava/lang/String;)V
      48: athrow
      49: aload_2
      50: areturn

  protected <Source> void setViewTransformation(java.lang.Class<Source>, de.flapdoodle.mongoom.mapping.IViewTransformation<Source, com.mongodb.DBObject>);
    Code:
       0: aload_2
       1: invokeinterface #25,  1           // InterfaceMethod de/flapdoodle/mongoom/mapping/IViewTransformation.properties:()Ljava/util/Set;
       6: ifnonnull     40
       9: new           #16                 // class de/flapdoodle/mongoom/exceptions/MappingException
      12: dup
      13: aload_0
      14: invokevirtual #17                 // Method getEntityClass:()Ljava/lang/Class;
      17: new           #18                 // class java/lang/StringBuilder
      20: dup
      21: invokespecial #19                 // Method java/lang/StringBuilder."<init>":()V
      24: ldc           #26                 // String View has no properties:
      26: invokevirtual #21                 // Method java/lang/StringBuilder.append:(Ljava/lang/String;)Ljava/lang/StringBuilder;
      29: aload_1
      30: invokevirtual #22                 // Method java/lang/StringBuilder.append:(Ljava/lang/Object;)Ljava/lang/StringBuilder;
      33: invokevirtual #23                 // Method java/lang/StringBuilder.toString:()Ljava/lang/String;
      36: invokespecial #24                 // Method de/flapdoodle/mongoom/exceptions/MappingException."<init>":(Ljava/lang/Class;Ljava/lang/String;)V
      39: athrow
      40: aload_0
      41: getfield      #5                  // Field _viewTransformation:Ljava/util/Map;
      44: aload_1
      45: aload_2
      46: invokeinterface #27,  3           // InterfaceMethod java/util/Map.put:(Ljava/lang/Object;Ljava/lang/Object;)Ljava/lang/Object;
      51: pop
      52: return

  public void setId(de.flapdoodle.mongoom.mapping.properties.IPropertyField<?>, de.flapdoodle.mongoom.mapping.ITransformation<?, ?>);
    Code:
       0: aload_0
       1: getfield      #28                 // Field _idProperty:Lde/flapdoodle/mongoom/mapping/properties/IPropertyField;
       4: ifnull        21
       7: new           #16                 // class de/flapdoodle/mongoom/exceptions/MappingException
      10: dup
      11: aload_0
      12: invokevirtual #17                 // Method getEntityClass:()Ljava/lang/Class;
      15: ldc           #29                 // String Id allready set
      17: invokespecial #24                 // Method de/flapdoodle/mongoom/exceptions/MappingException."<init>":(Ljava/lang/Class;Ljava/lang/String;)V
      20: athrow
      21: aload_0
      22: aload_1
      23: putfield      #28                 // Field _idProperty:Lde/flapdoodle/mongoom/mapping/properties/IPropertyField;
      26: aload_0
      27: aload_2
      28: putfield      #30                 // Field _idTransformation:Lde/flapdoodle/mongoom/mapping/ITransformation;
      31: return

  public de.flapdoodle.mongoom.mapping.properties.IPropertyField<?> getIdProperty();
    Code:
       0: aload_0
       1: getfield      #28                 // Field _idProperty:Lde/flapdoodle/mongoom/mapping/properties/IPropertyField;
       4: areturn

  public de.flapdoodle.mongoom.mapping.ITransformation<?, ?> getIdTransformation();
    Code:
       0: aload_0
       1: getfield      #30                 // Field _idTransformation:Lde/flapdoodle/mongoom/mapping/ITransformation;
       4: areturn

  public void setWriteCallback(de.flapdoodle.mongoom.mapping.callbacks.IEntityWriteCallback<EntityBean>);
    Code:
       0: aload_0
       1: aload_1
       2: putfield      #31                 // Field _writeCallback:Lde/flapdoodle/mongoom/mapping/callbacks/IEntityWriteCallback;
       5: return

  public void setReadCallback(de.flapdoodle.mongoom.mapping.callbacks.IEntityReadCallback<EntityBean>);
    Code:
       0: aload_0
       1: aload_1
       2: putfield      #32                 // Field _readCallback:Lde/flapdoodle/mongoom/mapping/callbacks/IEntityReadCallback;
       5: return

  public de.flapdoodle.mongoom.mapping.callbacks.IEntityWriteCallback<EntityBean> getWriteCallback();
    Code:
       0: aload_0
       1: getfield      #31                 // Field _writeCallback:Lde/flapdoodle/mongoom/mapping/callbacks/IEntityWriteCallback;
       4: areturn

  public de.flapdoodle.mongoom.mapping.callbacks.IEntityReadCallback<EntityBean> getReadCallback();
    Code:
       0: aload_0
       1: getfield      #32                 // Field _readCallback:Lde/flapdoodle/mongoom/mapping/callbacks/IEntityReadCallback;
       4: areturn

  public de.flapdoodle.mongoom.datastore.index.IIndex index();
    Code:
       0: new           #33                 // class de/flapdoodle/mongoom/mapping/entities/EntityContext$Index
       3: dup
       4: aload_0
       5: invokespecial #34                 // Method de/flapdoodle/mongoom/mapping/entities/EntityContext$Index."<init>":(Lde/flapdoodle/mongoom/mapping/entities/EntityContext;)V
       8: areturn

  public de.flapdoodle.mongoom.datastore.index.IPropertyIndex propertyIndex();
    Code:
       0: new           #16                 // class de/flapdoodle/mongoom/exceptions/MappingException
       3: dup
       4: aload_0
       5: invokevirtual #35                 // Method getViewClass:()Ljava/lang/Class;
       8: ldc           #36                 // String should not be called
      10: invokespecial #24                 // Method de/flapdoodle/mongoom/exceptions/MappingException."<init>":(Ljava/lang/Class;Ljava/lang/String;)V
      13: athrow

  public void addIndexedInGroup(de.flapdoodle.mongoom.mapping.properties.IPropertyMappedName, de.flapdoodle.mongoom.annotations.index.IndexedInGroup);
    Code:
       0: aload_0
       1: getfield      #1                  // Field _indexGroupMap:Ljava/util/Map;
       4: aload_2
       5: invokeinterface #37,  1           // InterfaceMethod de/flapdoodle/mongoom/annotations/index/IndexedInGroup.group:()Ljava/lang/String;
      10: invokeinterface #14,  2           // InterfaceMethod java/util/Map.get:(Ljava/lang/Object;)Ljava/lang/Object;
      15: checkcast     #38                 // class de/flapdoodle/mongoom/mapping/index/EntityIndexDef
      18: astore_3
      19: aload_3
      20: ifnonnull     54
      23: new           #16                 // class de/flapdoodle/mongoom/exceptions/MappingException
      26: dup
      27: aload_0
      28: invokevirtual #17                 // Method getEntityClass:()Ljava/lang/Class;
      31: new           #18                 // class java/lang/StringBuilder
      34: dup
      35: invokespecial #19                 // Method java/lang/StringBuilder."<init>":()V
      38: ldc           #39                 // String IndexGroup not found:
      40: invokevirtual #21                 // Method java/lang/StringBuilder.append:(Ljava/lang/String;)Ljava/lang/StringBuilder;
      43: aload_2
      44: invokevirtual #22                 // Method java/lang/StringBuilder.append:(Ljava/lang/Object;)Ljava/lang/StringBuilder;
      47: invokevirtual #23                 // Method java/lang/StringBuilder.toString:()Ljava/lang/String;
      50: invokespecial #24                 // Method de/flapdoodle/mongoom/exceptions/MappingException."<init>":(Ljava/lang/Class;Ljava/lang/String;)V
      53: athrow
      54: aload_3
      55: new           #40                 // class de/flapdoodle/mongoom/mapping/index/FieldIndex
      58: dup
      59: aload_1
      60: invokeinterface #41,  1           // InterfaceMethod de/flapdoodle/mongoom/mapping/properties/IPropertyMappedName.getMapped:()Ljava/lang/String;
      65: aload_2
      66: invokeinterface #42,  1           // InterfaceMethod de/flapdoodle/mongoom/annotations/index/IndexedInGroup.direction:()Lde/flapdoodle/mongoom/annotations/Direction;
      71: aload_2
      72: invokeinterface #43,  1           // InterfaceMethod de/flapdoodle/mongoom/annotations/index/IndexedInGroup.priority:()I
      77: invokespecial #44                 // Method de/flapdoodle/mongoom/mapping/index/FieldIndex."<init>":(Ljava/lang/String;Lde/flapdoodle/mongoom/annotations/Direction;I)V
      80: invokevirtual #45                 // Method de/flapdoodle/mongoom/mapping/index/EntityIndexDef.addField:(Lde/flapdoodle/mongoom/mapping/index/FieldIndex;)V
      83: return

  public void setIndexed(de.flapdoodle.mongoom.mapping.properties.IPropertyMappedName, de.flapdoodle.mongoom.annotations.index.Indexed);
    Code:
       0: aload_2
       1: invokeinterface #46,  1           // InterfaceMethod de/flapdoodle/mongoom/annotations/index/Indexed.options:()Lde/flapdoodle/mongoom/annotations/index/IndexOption;
       6: astore_3
       7: aload_1
       8: invokeinterface #41,  1           // InterfaceMethod de/flapdoodle/mongoom/mapping/properties/IPropertyMappedName.getMapped:()Ljava/lang/String;
      13: astore        4
      15: aload_0
      16: getfield      #2                  // Field _indexDef:Ljava/util/Map;
      19: aload         4
      21: new           #47                 // class de/flapdoodle/mongoom/mapping/index/IndexDef
      24: dup
      25: aload         4
      27: iconst_1
      28: anewarray     #40                 // class de/flapdoodle/mongoom/mapping/index/FieldIndex
      31: dup
      32: iconst_0
      33: new           #40                 // class de/flapdoodle/mongoom/mapping/index/FieldIndex
      36: dup
      37: aload         4
      39: aload_2
      40: invokeinterface #48,  1           // InterfaceMethod de/flapdoodle/mongoom/annotations/index/Indexed.direction:()Lde/flapdoodle/mongoom/annotations/Direction;
      45: iconst_0
      46: invokespecial #44                 // Method de/flapdoodle/mongoom/mapping/index/FieldIndex."<init>":(Ljava/lang/String;Lde/flapdoodle/mongoom/annotations/Direction;I)V
      49: aastore
      50: invokestatic  #49                 // Method com/google/common/collect/Lists.newArrayList:([Ljava/lang/Object;)Ljava/util/ArrayList;
      53: aload_3
      54: invokeinterface #50,  1           // InterfaceMethod de/flapdoodle/mongoom/annotations/index/IndexOption.unique:()Z
      59: aload_3
      60: invokeinterface #51,  1           // InterfaceMethod de/flapdoodle/mongoom/annotations/index/IndexOption.dropDups:()Z
      65: aload_3
      66: invokeinterface #52,  1           // InterfaceMethod de/flapdoodle/mongoom/annotations/index/IndexOption.sparse:()Z
      71: invokespecial #53                 // Method de/flapdoodle/mongoom/mapping/index/IndexDef."<init>":(Ljava/lang/String;Ljava/util/List;ZZZ)V
      74: invokeinterface #27,  3           // InterfaceMethod java/util/Map.put:(Ljava/lang/Object;Ljava/lang/Object;)Ljava/lang/Object;
      79: pop
      80: return

  static java.util.Map access$000(de.flapdoodle.mongoom.mapping.entities.EntityContext);
    Code:
       0: aload_0
       1: getfield      #2                  // Field _indexDef:Ljava/util/Map;
       4: areturn

  static java.util.Map access$100(de.flapdoodle.mongoom.mapping.entities.EntityContext);
    Code:
       0: aload_0
       1: getfield      #1                  // Field _indexGroupMap:Ljava/util/Map;
       4: areturn
}
