Compiled from "PropertyTransformationMap.java"
class de.flapdoodle.mongoom.mapping.entities.PropertyTransformationMap$1 implements de.flapdoodle.mongoom.mapping.entities.IPropertyTransformations {
  final de.flapdoodle.mongoom.mapping.entities.PropertyTransformationMap this$0;

  de.flapdoodle.mongoom.mapping.entities.PropertyTransformationMap$1(de.flapdoodle.mongoom.mapping.entities.PropertyTransformationMap);
    Code:
       0: aload_0
       1: aload_1
       2: putfield      #1                  // Field this$0:Lde/flapdoodle/mongoom/mapping/entities/PropertyTransformationMap;
       5: aload_0
       6: invokespecial #2                  // Method java/lang/Object."<init>":()V
       9: return

  public <Source> de.flapdoodle.mongoom.mapping.ITransformation<Source, ?> get(de.flapdoodle.mongoom.mapping.naming.PropertyName<Source>);
    Code:
       0: aload_0
       1: getfield      #1                  // Field this$0:Lde/flapdoodle/mongoom/mapping/entities/PropertyTransformationMap;
       4: invokestatic  #3                  // Method de/flapdoodle/mongoom/mapping/entities/PropertyTransformationMap.access$000:(Lde/flapdoodle/mongoom/mapping/entities/PropertyTransformationMap;)Ljava/util/Map;
       7: aload_1
       8: invokeinterface #4,  2            // InterfaceMethod java/util/Map.get:(Ljava/lang/Object;)Ljava/lang/Object;
      13: checkcast     #5                  // class de/flapdoodle/mongoom/mapping/ITransformation
      16: areturn

  public de.flapdoodle.mongoom.mapping.naming.PropertyName get(java.lang.String);
    Code:
       0: aload_0
       1: getfield      #1                  // Field this$0:Lde/flapdoodle/mongoom/mapping/entities/PropertyTransformationMap;
       4: invokestatic  #6                  // Method de/flapdoodle/mongoom/mapping/entities/PropertyTransformationMap.access$100:(Lde/flapdoodle/mongoom/mapping/entities/PropertyTransformationMap;)Ljava/util/Map;
       7: aload_1
       8: invokeinterface #4,  2            // InterfaceMethod java/util/Map.get:(Ljava/lang/Object;)Ljava/lang/Object;
      13: checkcast     #7                  // class de/flapdoodle/mongoom/mapping/naming/PropertyName
      16: areturn

  public <Source> de.flapdoodle.mongoom.mapping.naming.PropertyName get(de.flapdoodle.mongoom.mapping.properties.PropertyReference<Source>);
    Code:
       0: aload_0
       1: getfield      #1                  // Field this$0:Lde/flapdoodle/mongoom/mapping/entities/PropertyTransformationMap;
       4: invokestatic  #8                  // Method de/flapdoodle/mongoom/mapping/entities/PropertyTransformationMap.access$200:(Lde/flapdoodle/mongoom/mapping/entities/PropertyTransformationMap;)Ljava/util/Map;
       7: aload_1
       8: invokeinterface #4,  2            // InterfaceMethod java/util/Map.get:(Ljava/lang/Object;)Ljava/lang/Object;
      13: checkcast     #7                  // class de/flapdoodle/mongoom/mapping/naming/PropertyName
      16: areturn

  public <Source> de.flapdoodle.mongoom.mapping.properties.IProperty<Source> getProperty(de.flapdoodle.mongoom.mapping.naming.PropertyName<Source>);
    Code:
       0: aload_0
       1: getfield      #1                  // Field this$0:Lde/flapdoodle/mongoom/mapping/entities/PropertyTransformationMap;
       4: invokestatic  #9                  // Method de/flapdoodle/mongoom/mapping/entities/PropertyTransformationMap.access$300:(Lde/flapdoodle/mongoom/mapping/entities/PropertyTransformationMap;)Ljava/util/Map;
       7: aload_1
       8: invokeinterface #4,  2            // InterfaceMethod java/util/Map.get:(Ljava/lang/Object;)Ljava/lang/Object;
      13: checkcast     #10                 // class de/flapdoodle/mongoom/mapping/properties/IProperty
      16: areturn

  public java.util.Set<de.flapdoodle.mongoom.mapping.naming.PropertyName<?>> propertyNames();
    Code:
       0: aload_0
       1: getfield      #1                  // Field this$0:Lde/flapdoodle/mongoom/mapping/entities/PropertyTransformationMap;
       4: invokestatic  #9                  // Method de/flapdoodle/mongoom/mapping/entities/PropertyTransformationMap.access$300:(Lde/flapdoodle/mongoom/mapping/entities/PropertyTransformationMap;)Ljava/util/Map;
       7: invokeinterface #11,  1           // InterfaceMethod java/util/Map.keySet:()Ljava/util/Set;
      12: areturn
}
