Compiled from "TCBeginIndicationImpl.java"
public class org.mobicents.protocols.ss7.tcap.tc.dialog.events.TCBeginIndicationImpl extends org.mobicents.protocols.ss7.tcap.tc.dialog.events.DialogIndicationImpl implements org.mobicents.protocols.ss7.tcap.api.tc.dialog.events.TCBeginIndication {
  private org.mobicents.protocols.ss7.sccp.parameter.SccpAddress originatingAddress;

  private org.mobicents.protocols.ss7.sccp.parameter.SccpAddress destinationAddress;

  private org.mobicents.protocols.ss7.tcap.asn.ApplicationContextName applicationContextName;

  private org.mobicents.protocols.ss7.tcap.asn.UserInformation userInformation;

  org.mobicents.protocols.ss7.tcap.tc.dialog.events.TCBeginIndicationImpl();
    Code:
       0: aload_0
       1: getstatic     #1                  // Field org/mobicents/protocols/ss7/tcap/api/tc/dialog/events/EventType.Begin:Lorg/mobicents/protocols/ss7/tcap/api/tc/dialog/events/EventType;
       4: invokespecial #2                  // Method org/mobicents/protocols/ss7/tcap/tc/dialog/events/DialogIndicationImpl."<init>":(Lorg/mobicents/protocols/ss7/tcap/api/tc/dialog/events/EventType;)V
       7: return

  public org.mobicents.protocols.ss7.tcap.asn.ApplicationContextName getApplicationContextName();
    Code:
       0: aload_0
       1: getfield      #3                  // Field applicationContextName:Lorg/mobicents/protocols/ss7/tcap/asn/ApplicationContextName;
       4: areturn

  public org.mobicents.protocols.ss7.sccp.parameter.SccpAddress getDestinationAddress();
    Code:
       0: aload_0
       1: getfield      #4                  // Field destinationAddress:Lorg/mobicents/protocols/ss7/sccp/parameter/SccpAddress;
       4: areturn

  public org.mobicents.protocols.ss7.sccp.parameter.SccpAddress getOriginatingAddress();
    Code:
       0: aload_0
       1: getfield      #5                  // Field originatingAddress:Lorg/mobicents/protocols/ss7/sccp/parameter/SccpAddress;
       4: areturn

  public org.mobicents.protocols.ss7.tcap.asn.UserInformation getUserInformation();
    Code:
       0: aload_0
       1: getfield      #6                  // Field userInformation:Lorg/mobicents/protocols/ss7/tcap/asn/UserInformation;
       4: areturn

  public void setApplicationContextName(org.mobicents.protocols.ss7.tcap.asn.ApplicationContextName);
    Code:
       0: aload_0
       1: aload_1
       2: putfield      #3                  // Field applicationContextName:Lorg/mobicents/protocols/ss7/tcap/asn/ApplicationContextName;
       5: return

  public void setDestinationAddress(org.mobicents.protocols.ss7.sccp.parameter.SccpAddress);
    Code:
       0: aload_0
       1: aload_1
       2: putfield      #4                  // Field destinationAddress:Lorg/mobicents/protocols/ss7/sccp/parameter/SccpAddress;
       5: return

  public void setOriginatingAddress(org.mobicents.protocols.ss7.sccp.parameter.SccpAddress);
    Code:
       0: aload_0
       1: aload_1
       2: putfield      #5                  // Field originatingAddress:Lorg/mobicents/protocols/ss7/sccp/parameter/SccpAddress;
       5: return

  public void setUserInformation(org.mobicents.protocols.ss7.tcap.asn.UserInformation);
    Code:
       0: aload_0
       1: aload_1
       2: putfield      #6                  // Field userInformation:Lorg/mobicents/protocols/ss7/tcap/asn/UserInformation;
       5: return
}
