Compiled from "FinderFromFile.java"
public class org.apache.commons.digester.plugins.strategies.FinderFromFile extends org.apache.commons.digester.plugins.RuleFinder {
  public static java.lang.String DFLT_FILENAME_ATTR;

  private java.lang.String filenameAttr;

  public org.apache.commons.digester.plugins.strategies.FinderFromFile();
    Code:
       0: aload_0
       1: getstatic     #1                  // Field DFLT_FILENAME_ATTR:Ljava/lang/String;
       4: invokespecial #2                  // Method "<init>":(Ljava/lang/String;)V
       7: return

  public org.apache.commons.digester.plugins.strategies.FinderFromFile(java.lang.String);
    Code:
       0: aload_0
       1: invokespecial #3                  // Method org/apache/commons/digester/plugins/RuleFinder."<init>":()V
       4: aload_0
       5: aload_1
       6: putfield      #4                  // Field filenameAttr:Ljava/lang/String;
       9: return

  public org.apache.commons.digester.plugins.RuleLoader findLoader(org.apache.commons.digester.Digester, java.lang.Class, java.util.Properties) throws org.apache.commons.digester.plugins.PluginException;
    Code:
       0: aload_3
       1: aload_0
       2: getfield      #4                  // Field filenameAttr:Ljava/lang/String;
       5: invokevirtual #5                  // Method java/util/Properties.getProperty:(Ljava/lang/String;)Ljava/lang/String;
       8: astore        4
      10: aload         4
      12: ifnonnull     17
      15: aconst_null
      16: areturn
      17: aconst_null
      18: astore        5
      20: new           #6                  // class java/io/FileInputStream
      23: dup
      24: aload         4
      26: invokespecial #7                  // Method java/io/FileInputStream."<init>":(Ljava/lang/String;)V
      29: astore        5
      31: goto          71
      34: astore        6
      36: new           #9                  // class org/apache/commons/digester/plugins/PluginException
      39: dup
      40: new           #10                 // class java/lang/StringBuffer
      43: dup
      44: invokespecial #11                 // Method java/lang/StringBuffer."<init>":()V
      47: ldc           #12                 // String Unable to process file [
      49: invokevirtual #13                 // Method java/lang/StringBuffer.append:(Ljava/lang/String;)Ljava/lang/StringBuffer;
      52: aload         4
      54: invokevirtual #13                 // Method java/lang/StringBuffer.append:(Ljava/lang/String;)Ljava/lang/StringBuffer;
      57: ldc           #14                 // String ]
      59: invokevirtual #13                 // Method java/lang/StringBuffer.append:(Ljava/lang/String;)Ljava/lang/StringBuffer;
      62: invokevirtual #15                 // Method java/lang/StringBuffer.toString:()Ljava/lang/String;
      65: aload         6
      67: invokespecial #16                 // Method org/apache/commons/digester/plugins/PluginException."<init>":(Ljava/lang/String;Ljava/lang/Throwable;)V
      70: athrow
      71: new           #17                 // class org/apache/commons/digester/plugins/strategies/LoaderFromStream
      74: dup
      75: aload         5
      77: invokespecial #18                 // Method org/apache/commons/digester/plugins/strategies/LoaderFromStream."<init>":(Ljava/io/InputStream;)V
      80: astore        6
      82: aload         6
      84: astore        7
      86: jsr           137
      89: aload         7
      91: areturn
      92: astore        6
      94: new           #9                  // class org/apache/commons/digester/plugins/PluginException
      97: dup
      98: new           #10                 // class java/lang/StringBuffer
     101: dup
     102: invokespecial #11                 // Method java/lang/StringBuffer."<init>":()V
     105: ldc           #20                 // String Unable to load xmlrules from file [
     107: invokevirtual #13                 // Method java/lang/StringBuffer.append:(Ljava/lang/String;)Ljava/lang/StringBuffer;
     110: aload         4
     112: invokevirtual #13                 // Method java/lang/StringBuffer.append:(Ljava/lang/String;)Ljava/lang/StringBuffer;
     115: ldc           #14                 // String ]
     117: invokevirtual #13                 // Method java/lang/StringBuffer.append:(Ljava/lang/String;)Ljava/lang/StringBuffer;
     120: invokevirtual #15                 // Method java/lang/StringBuffer.toString:()Ljava/lang/String;
     123: aload         6
     125: invokespecial #16                 // Method org/apache/commons/digester/plugins/PluginException."<init>":(Ljava/lang/String;Ljava/lang/Throwable;)V
     128: athrow
     129: astore        8
     131: jsr           137
     134: aload         8
     136: athrow
     137: astore        9
     139: aload         5
     141: invokevirtual #21                 // Method java/io/InputStream.close:()V
     144: goto          184
     147: astore        10
     149: new           #9                  // class org/apache/commons/digester/plugins/PluginException
     152: dup
     153: new           #10                 // class java/lang/StringBuffer
     156: dup
     157: invokespecial #11                 // Method java/lang/StringBuffer."<init>":()V
     160: ldc           #22                 // String Unable to close stream for file [
     162: invokevirtual #13                 // Method java/lang/StringBuffer.append:(Ljava/lang/String;)Ljava/lang/StringBuffer;
     165: aload         4
     167: invokevirtual #13                 // Method java/lang/StringBuffer.append:(Ljava/lang/String;)Ljava/lang/StringBuffer;
     170: ldc           #14                 // String ]
     172: invokevirtual #13                 // Method java/lang/StringBuffer.append:(Ljava/lang/String;)Ljava/lang/StringBuffer;
     175: invokevirtual #15                 // Method java/lang/StringBuffer.toString:()Ljava/lang/String;
     178: aload         10
     180: invokespecial #16                 // Method org/apache/commons/digester/plugins/PluginException."<init>":(Ljava/lang/String;Ljava/lang/Throwable;)V
     183: athrow
     184: ret           9
    Exception table:
       from    to  target type
          20    31    34   Class java/io/IOException
          71    89    92   Class java/lang/Exception
          71    89   129   any
          92   134   129   any
         139   144   147   Class java/io/IOException

  static {};
    Code:
       0: ldc           #23                 // String file
       2: putstatic     #1                  // Field DFLT_FILENAME_ATTR:Ljava/lang/String;
       5: return
}
