Compiled from "DOMOutputter.java"
public class org.jdom2.output.DOMOutputter {
  private static final org.jdom2.adapters.DOMAdapter DEFAULT_ADAPTER;

  private static final org.jdom2.output.support.DOMOutputProcessor DEFAULT_PROCESSOR;

  private org.jdom2.adapters.DOMAdapter adapter;

  private org.jdom2.output.Format format;

  private org.jdom2.output.support.DOMOutputProcessor processor;

  public org.jdom2.output.DOMOutputter();
    Code:
       0: aload_0
       1: aconst_null
       2: aconst_null
       3: aconst_null
       4: invokespecial #1                  // Method "<init>":(Lorg/jdom2/adapters/DOMAdapter;Lorg/jdom2/output/Format;Lorg/jdom2/output/support/DOMOutputProcessor;)V
       7: return

  public org.jdom2.output.DOMOutputter(org.jdom2.output.support.DOMOutputProcessor);
    Code:
       0: aload_0
       1: aconst_null
       2: aconst_null
       3: aload_1
       4: invokespecial #1                  // Method "<init>":(Lorg/jdom2/adapters/DOMAdapter;Lorg/jdom2/output/Format;Lorg/jdom2/output/support/DOMOutputProcessor;)V
       7: return

  public org.jdom2.output.DOMOutputter(org.jdom2.adapters.DOMAdapter, org.jdom2.output.Format, org.jdom2.output.support.DOMOutputProcessor);
    Code:
       0: aload_0
       1: invokespecial #2                  // Method java/lang/Object."<init>":()V
       4: aload_0
       5: aload_1
       6: ifnonnull     15
       9: getstatic     #3                  // Field DEFAULT_ADAPTER:Lorg/jdom2/adapters/DOMAdapter;
      12: goto          16
      15: aload_1
      16: putfield      #4                  // Field adapter:Lorg/jdom2/adapters/DOMAdapter;
      19: aload_0
      20: aload_2
      21: ifnonnull     30
      24: invokestatic  #5                  // Method org/jdom2/output/Format.getRawFormat:()Lorg/jdom2/output/Format;
      27: goto          31
      30: aload_2
      31: putfield      #6                  // Field format:Lorg/jdom2/output/Format;
      34: aload_0
      35: aload_3
      36: ifnonnull     45
      39: getstatic     #7                  // Field DEFAULT_PROCESSOR:Lorg/jdom2/output/support/DOMOutputProcessor;
      42: goto          46
      45: aload_3
      46: putfield      #8                  // Field processor:Lorg/jdom2/output/support/DOMOutputProcessor;
      49: return

  public org.jdom2.output.DOMOutputter(java.lang.String);
    Code:
       0: aload_0
       1: invokespecial #2                  // Method java/lang/Object."<init>":()V
       4: aload_1
       5: ifnonnull     18
       8: aload_0
       9: getstatic     #3                  // Field DEFAULT_ADAPTER:Lorg/jdom2/adapters/DOMAdapter;
      12: putfield      #4                  // Field adapter:Lorg/jdom2/adapters/DOMAdapter;
      15: goto          32
      18: aload_0
      19: aload_1
      20: ldc_w         #9                  // class org/jdom2/adapters/DOMAdapter
      23: invokestatic  #10                 // Method org/jdom2/internal/ReflectionConstructor.construct:(Ljava/lang/String;Ljava/lang/Class;)Ljava/lang/Object;
      26: checkcast     #9                  // class org/jdom2/adapters/DOMAdapter
      29: putfield      #4                  // Field adapter:Lorg/jdom2/adapters/DOMAdapter;
      32: return

  public org.jdom2.output.DOMOutputter(org.jdom2.adapters.DOMAdapter);
    Code:
       0: aload_0
       1: invokespecial #2                  // Method java/lang/Object."<init>":()V
       4: aload_0
       5: aload_1
       6: ifnonnull     15
       9: getstatic     #3                  // Field DEFAULT_ADAPTER:Lorg/jdom2/adapters/DOMAdapter;
      12: goto          16
      15: aload_1
      16: putfield      #4                  // Field adapter:Lorg/jdom2/adapters/DOMAdapter;
      19: return

  public org.jdom2.adapters.DOMAdapter getDOMAdapter();
    Code:
       0: aload_0
       1: getfield      #4                  // Field adapter:Lorg/jdom2/adapters/DOMAdapter;
       4: areturn

  public void setDOMAdapter(org.jdom2.adapters.DOMAdapter);
    Code:
       0: aload_0
       1: aload_1
       2: ifnonnull     11
       5: getstatic     #3                  // Field DEFAULT_ADAPTER:Lorg/jdom2/adapters/DOMAdapter;
       8: goto          12
      11: aload_1
      12: putfield      #4                  // Field adapter:Lorg/jdom2/adapters/DOMAdapter;
      15: return

  public org.jdom2.output.Format getFormat();
    Code:
       0: aload_0
       1: getfield      #6                  // Field format:Lorg/jdom2/output/Format;
       4: areturn

  public void setFormat(org.jdom2.output.Format);
    Code:
       0: aload_0
       1: aload_1
       2: ifnonnull     11
       5: invokestatic  #5                  // Method org/jdom2/output/Format.getRawFormat:()Lorg/jdom2/output/Format;
       8: goto          12
      11: aload_1
      12: putfield      #6                  // Field format:Lorg/jdom2/output/Format;
      15: return

  public org.jdom2.output.support.DOMOutputProcessor getDOMOutputProcessor();
    Code:
       0: aload_0
       1: getfield      #8                  // Field processor:Lorg/jdom2/output/support/DOMOutputProcessor;
       4: areturn

  public void setDOMOutputProcessor(org.jdom2.output.support.DOMOutputProcessor);
    Code:
       0: aload_0
       1: aload_1
       2: ifnonnull     11
       5: getstatic     #7                  // Field DEFAULT_PROCESSOR:Lorg/jdom2/output/support/DOMOutputProcessor;
       8: goto          12
      11: aload_1
      12: putfield      #8                  // Field processor:Lorg/jdom2/output/support/DOMOutputProcessor;
      15: return

  public void setForceNamespaceAware(boolean);
    Code:
       0: return

  public boolean getForceNamespaceAware();
    Code:
       0: iconst_1
       1: ireturn

  public org.w3c.dom.Document output(org.jdom2.Document) throws org.jdom2.JDOMException;
    Code:
       0: aload_0
       1: getfield      #8                  // Field processor:Lorg/jdom2/output/support/DOMOutputProcessor;
       4: aload_0
       5: getfield      #4                  // Field adapter:Lorg/jdom2/adapters/DOMAdapter;
       8: aload_1
       9: invokevirtual #11                 // Method org/jdom2/Document.getDocType:()Lorg/jdom2/DocType;
      12: invokeinterface #12,  2           // InterfaceMethod org/jdom2/adapters/DOMAdapter.createDocument:(Lorg/jdom2/DocType;)Lorg/w3c/dom/Document;
      17: aload_0
      18: getfield      #6                  // Field format:Lorg/jdom2/output/Format;
      21: aload_1
      22: invokeinterface #13,  4           // InterfaceMethod org/jdom2/output/support/DOMOutputProcessor.process:(Lorg/w3c/dom/Document;Lorg/jdom2/output/Format;Lorg/jdom2/Document;)Lorg/w3c/dom/Document;
      27: areturn

  public org.w3c.dom.DocumentType output(org.jdom2.DocType) throws org.jdom2.JDOMException;
    Code:
       0: aload_0
       1: getfield      #4                  // Field adapter:Lorg/jdom2/adapters/DOMAdapter;
       4: aload_1
       5: invokeinterface #12,  2           // InterfaceMethod org/jdom2/adapters/DOMAdapter.createDocument:(Lorg/jdom2/DocType;)Lorg/w3c/dom/Document;
      10: invokeinterface #14,  1           // InterfaceMethod org/w3c/dom/Document.getDoctype:()Lorg/w3c/dom/DocumentType;
      15: areturn

  public org.w3c.dom.Element output(org.jdom2.Element) throws org.jdom2.JDOMException;
    Code:
       0: aload_0
       1: getfield      #8                  // Field processor:Lorg/jdom2/output/support/DOMOutputProcessor;
       4: aload_0
       5: getfield      #4                  // Field adapter:Lorg/jdom2/adapters/DOMAdapter;
       8: invokeinterface #15,  1           // InterfaceMethod org/jdom2/adapters/DOMAdapter.createDocument:()Lorg/w3c/dom/Document;
      13: aload_0
      14: getfield      #6                  // Field format:Lorg/jdom2/output/Format;
      17: aload_1
      18: invokeinterface #16,  4           // InterfaceMethod org/jdom2/output/support/DOMOutputProcessor.process:(Lorg/w3c/dom/Document;Lorg/jdom2/output/Format;Lorg/jdom2/Element;)Lorg/w3c/dom/Element;
      23: areturn

  public org.w3c.dom.Text output(org.jdom2.Text) throws org.jdom2.JDOMException;
    Code:
       0: aload_0
       1: getfield      #8                  // Field processor:Lorg/jdom2/output/support/DOMOutputProcessor;
       4: aload_0
       5: getfield      #4                  // Field adapter:Lorg/jdom2/adapters/DOMAdapter;
       8: invokeinterface #15,  1           // InterfaceMethod org/jdom2/adapters/DOMAdapter.createDocument:()Lorg/w3c/dom/Document;
      13: aload_0
      14: getfield      #6                  // Field format:Lorg/jdom2/output/Format;
      17: aload_1
      18: invokeinterface #17,  4           // InterfaceMethod org/jdom2/output/support/DOMOutputProcessor.process:(Lorg/w3c/dom/Document;Lorg/jdom2/output/Format;Lorg/jdom2/Text;)Lorg/w3c/dom/Text;
      23: areturn

  public org.w3c.dom.CDATASection output(org.jdom2.CDATA) throws org.jdom2.JDOMException;
    Code:
       0: aload_0
       1: getfield      #8                  // Field processor:Lorg/jdom2/output/support/DOMOutputProcessor;
       4: aload_0
       5: getfield      #4                  // Field adapter:Lorg/jdom2/adapters/DOMAdapter;
       8: invokeinterface #15,  1           // InterfaceMethod org/jdom2/adapters/DOMAdapter.createDocument:()Lorg/w3c/dom/Document;
      13: aload_0
      14: getfield      #6                  // Field format:Lorg/jdom2/output/Format;
      17: aload_1
      18: invokeinterface #18,  4           // InterfaceMethod org/jdom2/output/support/DOMOutputProcessor.process:(Lorg/w3c/dom/Document;Lorg/jdom2/output/Format;Lorg/jdom2/CDATA;)Lorg/w3c/dom/CDATASection;
      23: areturn

  public org.w3c.dom.ProcessingInstruction output(org.jdom2.ProcessingInstruction) throws org.jdom2.JDOMException;
    Code:
       0: aload_0
       1: getfield      #8                  // Field processor:Lorg/jdom2/output/support/DOMOutputProcessor;
       4: aload_0
       5: getfield      #4                  // Field adapter:Lorg/jdom2/adapters/DOMAdapter;
       8: invokeinterface #15,  1           // InterfaceMethod org/jdom2/adapters/DOMAdapter.createDocument:()Lorg/w3c/dom/Document;
      13: aload_0
      14: getfield      #6                  // Field format:Lorg/jdom2/output/Format;
      17: aload_1
      18: invokeinterface #19,  4           // InterfaceMethod org/jdom2/output/support/DOMOutputProcessor.process:(Lorg/w3c/dom/Document;Lorg/jdom2/output/Format;Lorg/jdom2/ProcessingInstruction;)Lorg/w3c/dom/ProcessingInstruction;
      23: areturn

  public org.w3c.dom.Comment output(org.jdom2.Comment) throws org.jdom2.JDOMException;
    Code:
       0: aload_0
       1: getfield      #8                  // Field processor:Lorg/jdom2/output/support/DOMOutputProcessor;
       4: aload_0
       5: getfield      #4                  // Field adapter:Lorg/jdom2/adapters/DOMAdapter;
       8: invokeinterface #15,  1           // InterfaceMethod org/jdom2/adapters/DOMAdapter.createDocument:()Lorg/w3c/dom/Document;
      13: aload_0
      14: getfield      #6                  // Field format:Lorg/jdom2/output/Format;
      17: aload_1
      18: invokeinterface #20,  4           // InterfaceMethod org/jdom2/output/support/DOMOutputProcessor.process:(Lorg/w3c/dom/Document;Lorg/jdom2/output/Format;Lorg/jdom2/Comment;)Lorg/w3c/dom/Comment;
      23: areturn

  public org.w3c.dom.EntityReference output(org.jdom2.EntityRef) throws org.jdom2.JDOMException;
    Code:
       0: aload_0
       1: getfield      #8                  // Field processor:Lorg/jdom2/output/support/DOMOutputProcessor;
       4: aload_0
       5: getfield      #4                  // Field adapter:Lorg/jdom2/adapters/DOMAdapter;
       8: invokeinterface #15,  1           // InterfaceMethod org/jdom2/adapters/DOMAdapter.createDocument:()Lorg/w3c/dom/Document;
      13: aload_0
      14: getfield      #6                  // Field format:Lorg/jdom2/output/Format;
      17: aload_1
      18: invokeinterface #21,  4           // InterfaceMethod org/jdom2/output/support/DOMOutputProcessor.process:(Lorg/w3c/dom/Document;Lorg/jdom2/output/Format;Lorg/jdom2/EntityRef;)Lorg/w3c/dom/EntityReference;
      23: areturn

  public org.w3c.dom.Attr output(org.jdom2.Attribute) throws org.jdom2.JDOMException;
    Code:
       0: aload_0
       1: getfield      #8                  // Field processor:Lorg/jdom2/output/support/DOMOutputProcessor;
       4: aload_0
       5: getfield      #4                  // Field adapter:Lorg/jdom2/adapters/DOMAdapter;
       8: invokeinterface #15,  1           // InterfaceMethod org/jdom2/adapters/DOMAdapter.createDocument:()Lorg/w3c/dom/Document;
      13: aload_0
      14: getfield      #6                  // Field format:Lorg/jdom2/output/Format;
      17: aload_1
      18: invokeinterface #22,  4           // InterfaceMethod org/jdom2/output/support/DOMOutputProcessor.process:(Lorg/w3c/dom/Document;Lorg/jdom2/output/Format;Lorg/jdom2/Attribute;)Lorg/w3c/dom/Attr;
      23: areturn

  public java.util.List<org.w3c.dom.Node> output(java.util.List<? extends org.jdom2.Content>) throws org.jdom2.JDOMException;
    Code:
       0: aload_0
       1: getfield      #8                  // Field processor:Lorg/jdom2/output/support/DOMOutputProcessor;
       4: aload_0
       5: getfield      #4                  // Field adapter:Lorg/jdom2/adapters/DOMAdapter;
       8: invokeinterface #15,  1           // InterfaceMethod org/jdom2/adapters/DOMAdapter.createDocument:()Lorg/w3c/dom/Document;
      13: aload_0
      14: getfield      #6                  // Field format:Lorg/jdom2/output/Format;
      17: aload_1
      18: invokeinterface #23,  4           // InterfaceMethod org/jdom2/output/support/DOMOutputProcessor.process:(Lorg/w3c/dom/Document;Lorg/jdom2/output/Format;Ljava/util/List;)Ljava/util/List;
      23: areturn

  public org.w3c.dom.Element output(org.w3c.dom.Document, org.jdom2.Element) throws org.jdom2.JDOMException;
    Code:
       0: aload_0
       1: getfield      #8                  // Field processor:Lorg/jdom2/output/support/DOMOutputProcessor;
       4: aload_1
       5: aload_0
       6: getfield      #6                  // Field format:Lorg/jdom2/output/Format;
       9: aload_2
      10: invokeinterface #16,  4           // InterfaceMethod org/jdom2/output/support/DOMOutputProcessor.process:(Lorg/w3c/dom/Document;Lorg/jdom2/output/Format;Lorg/jdom2/Element;)Lorg/w3c/dom/Element;
      15: areturn

  public org.w3c.dom.Text output(org.w3c.dom.Document, org.jdom2.Text) throws org.jdom2.JDOMException;
    Code:
       0: aload_0
       1: getfield      #8                  // Field processor:Lorg/jdom2/output/support/DOMOutputProcessor;
       4: aload_1
       5: aload_0
       6: getfield      #6                  // Field format:Lorg/jdom2/output/Format;
       9: aload_2
      10: invokeinterface #17,  4           // InterfaceMethod org/jdom2/output/support/DOMOutputProcessor.process:(Lorg/w3c/dom/Document;Lorg/jdom2/output/Format;Lorg/jdom2/Text;)Lorg/w3c/dom/Text;
      15: areturn

  public org.w3c.dom.CDATASection output(org.w3c.dom.Document, org.jdom2.CDATA) throws org.jdom2.JDOMException;
    Code:
       0: aload_0
       1: getfield      #8                  // Field processor:Lorg/jdom2/output/support/DOMOutputProcessor;
       4: aload_1
       5: aload_0
       6: getfield      #6                  // Field format:Lorg/jdom2/output/Format;
       9: aload_2
      10: invokeinterface #18,  4           // InterfaceMethod org/jdom2/output/support/DOMOutputProcessor.process:(Lorg/w3c/dom/Document;Lorg/jdom2/output/Format;Lorg/jdom2/CDATA;)Lorg/w3c/dom/CDATASection;
      15: areturn

  public org.w3c.dom.ProcessingInstruction output(org.w3c.dom.Document, org.jdom2.ProcessingInstruction) throws org.jdom2.JDOMException;
    Code:
       0: aload_0
       1: getfield      #8                  // Field processor:Lorg/jdom2/output/support/DOMOutputProcessor;
       4: aload_1
       5: aload_0
       6: getfield      #6                  // Field format:Lorg/jdom2/output/Format;
       9: aload_2
      10: invokeinterface #19,  4           // InterfaceMethod org/jdom2/output/support/DOMOutputProcessor.process:(Lorg/w3c/dom/Document;Lorg/jdom2/output/Format;Lorg/jdom2/ProcessingInstruction;)Lorg/w3c/dom/ProcessingInstruction;
      15: areturn

  public org.w3c.dom.Comment output(org.w3c.dom.Document, org.jdom2.Comment) throws org.jdom2.JDOMException;
    Code:
       0: aload_0
       1: getfield      #8                  // Field processor:Lorg/jdom2/output/support/DOMOutputProcessor;
       4: aload_1
       5: aload_0
       6: getfield      #6                  // Field format:Lorg/jdom2/output/Format;
       9: aload_2
      10: invokeinterface #20,  4           // InterfaceMethod org/jdom2/output/support/DOMOutputProcessor.process:(Lorg/w3c/dom/Document;Lorg/jdom2/output/Format;Lorg/jdom2/Comment;)Lorg/w3c/dom/Comment;
      15: areturn

  public org.w3c.dom.EntityReference output(org.w3c.dom.Document, org.jdom2.EntityRef) throws org.jdom2.JDOMException;
    Code:
       0: aload_0
       1: getfield      #8                  // Field processor:Lorg/jdom2/output/support/DOMOutputProcessor;
       4: aload_1
       5: aload_0
       6: getfield      #6                  // Field format:Lorg/jdom2/output/Format;
       9: aload_2
      10: invokeinterface #21,  4           // InterfaceMethod org/jdom2/output/support/DOMOutputProcessor.process:(Lorg/w3c/dom/Document;Lorg/jdom2/output/Format;Lorg/jdom2/EntityRef;)Lorg/w3c/dom/EntityReference;
      15: areturn

  public org.w3c.dom.Attr output(org.w3c.dom.Document, org.jdom2.Attribute) throws org.jdom2.JDOMException;
    Code:
       0: aload_0
       1: getfield      #8                  // Field processor:Lorg/jdom2/output/support/DOMOutputProcessor;
       4: aload_1
       5: aload_0
       6: getfield      #6                  // Field format:Lorg/jdom2/output/Format;
       9: aload_2
      10: invokeinterface #22,  4           // InterfaceMethod org/jdom2/output/support/DOMOutputProcessor.process:(Lorg/w3c/dom/Document;Lorg/jdom2/output/Format;Lorg/jdom2/Attribute;)Lorg/w3c/dom/Attr;
      15: areturn

  public java.util.List<org.w3c.dom.Node> output(org.w3c.dom.Document, java.util.List<? extends org.jdom2.Content>) throws org.jdom2.JDOMException;
    Code:
       0: aload_0
       1: getfield      #8                  // Field processor:Lorg/jdom2/output/support/DOMOutputProcessor;
       4: aload_1
       5: aload_0
       6: getfield      #6                  // Field format:Lorg/jdom2/output/Format;
       9: aload_2
      10: invokeinterface #23,  4           // InterfaceMethod org/jdom2/output/support/DOMOutputProcessor.process:(Lorg/w3c/dom/Document;Lorg/jdom2/output/Format;Ljava/util/List;)Ljava/util/List;
      15: areturn

  static {};
    Code:
       0: new           #24                 // class org/jdom2/adapters/JAXPDOMAdapter
       3: dup
       4: invokespecial #25                 // Method org/jdom2/adapters/JAXPDOMAdapter."<init>":()V
       7: putstatic     #3                  // Field DEFAULT_ADAPTER:Lorg/jdom2/adapters/DOMAdapter;
      10: new           #26                 // class org/jdom2/output/DOMOutputter$DefaultDOMOutputProcessor
      13: dup
      14: aconst_null
      15: invokespecial #27                 // Method org/jdom2/output/DOMOutputter$DefaultDOMOutputProcessor."<init>":(Lorg/jdom2/output/DOMOutputter$1;)V
      18: putstatic     #7                  // Field DEFAULT_PROCESSOR:Lorg/jdom2/output/support/DOMOutputProcessor;
      21: return
}
