Compiled from "Format.java"
final class org.jdom2.output.Format$EscapeStrategy8Bits implements org.jdom2.output.EscapeStrategy {
  private org.jdom2.output.Format$EscapeStrategy8Bits();
    Code:
       0: aload_0
       1: invokespecial #2                  // Method java/lang/Object."<init>":()V
       4: return

  public boolean shouldEscape(char);
    Code:
       0: iload_1
       1: bipush        8
       3: iushr
       4: ifeq          11
       7: iconst_1
       8: goto          12
      11: iconst_0
      12: ireturn

  org.jdom2.output.Format$EscapeStrategy8Bits(org.jdom2.output.Format$1);
    Code:
       0: aload_0
       1: invokespecial #1                  // Method "<init>":()V
       4: return
}
