Compiled from "StAXEventOutputter.java"
public final class org.jdom2.output.StAXEventOutputter implements java.lang.Cloneable {
  private static final org.jdom2.output.StAXEventOutputter$DefaultStAXEventProcessor DEFAULTPROCESSOR;

  private static final javax.xml.stream.XMLEventFactory DEFAULTEVENTFACTORY;

  private org.jdom2.output.Format myFormat;

  private org.jdom2.output.support.StAXEventProcessor myProcessor;

  private javax.xml.stream.XMLEventFactory myEventFactory;

  public org.jdom2.output.StAXEventOutputter(org.jdom2.output.Format, org.jdom2.output.support.StAXEventProcessor, javax.xml.stream.XMLEventFactory);
    Code:
       0: aload_0
       1: invokespecial #1                  // Method java/lang/Object."<init>":()V
       4: aload_0
       5: aconst_null
       6: putfield      #2                  // Field myFormat:Lorg/jdom2/output/Format;
       9: aload_0
      10: aconst_null
      11: putfield      #3                  // Field myProcessor:Lorg/jdom2/output/support/StAXEventProcessor;
      14: aload_0
      15: aconst_null
      16: putfield      #4                  // Field myEventFactory:Ljavax/xml/stream/XMLEventFactory;
      19: aload_0
      20: aload_1
      21: ifnonnull     30
      24: invokestatic  #5                  // Method org/jdom2/output/Format.getRawFormat:()Lorg/jdom2/output/Format;
      27: goto          34
      30: aload_1
      31: invokevirtual #6                  // Method org/jdom2/output/Format.clone:()Lorg/jdom2/output/Format;
      34: putfield      #2                  // Field myFormat:Lorg/jdom2/output/Format;
      37: aload_0
      38: aload_2
      39: ifnonnull     48
      42: getstatic     #7                  // Field DEFAULTPROCESSOR:Lorg/jdom2/output/StAXEventOutputter$DefaultStAXEventProcessor;
      45: goto          49
      48: aload_2
      49: putfield      #3                  // Field myProcessor:Lorg/jdom2/output/support/StAXEventProcessor;
      52: aload_0
      53: aload_3
      54: ifnonnull     63
      57: getstatic     #8                  // Field DEFAULTEVENTFACTORY:Ljavax/xml/stream/XMLEventFactory;
      60: goto          64
      63: aload_3
      64: putfield      #4                  // Field myEventFactory:Ljavax/xml/stream/XMLEventFactory;
      67: return

  public org.jdom2.output.StAXEventOutputter();
    Code:
       0: aload_0
       1: aconst_null
       2: aconst_null
       3: aconst_null
       4: invokespecial #9                  // Method "<init>":(Lorg/jdom2/output/Format;Lorg/jdom2/output/support/StAXEventProcessor;Ljavax/xml/stream/XMLEventFactory;)V
       7: return

  public org.jdom2.output.StAXEventOutputter(org.jdom2.output.Format);
    Code:
       0: aload_0
       1: aload_1
       2: aconst_null
       3: aconst_null
       4: invokespecial #9                  // Method "<init>":(Lorg/jdom2/output/Format;Lorg/jdom2/output/support/StAXEventProcessor;Ljavax/xml/stream/XMLEventFactory;)V
       7: return

  public org.jdom2.output.StAXEventOutputter(org.jdom2.output.support.StAXEventProcessor);
    Code:
       0: aload_0
       1: aconst_null
       2: aload_1
       3: aconst_null
       4: invokespecial #9                  // Method "<init>":(Lorg/jdom2/output/Format;Lorg/jdom2/output/support/StAXEventProcessor;Ljavax/xml/stream/XMLEventFactory;)V
       7: return

  public org.jdom2.output.StAXEventOutputter(javax.xml.stream.XMLEventFactory);
    Code:
       0: aload_0
       1: aconst_null
       2: aconst_null
       3: aload_1
       4: invokespecial #9                  // Method "<init>":(Lorg/jdom2/output/Format;Lorg/jdom2/output/support/StAXEventProcessor;Ljavax/xml/stream/XMLEventFactory;)V
       7: return

  public void setFormat(org.jdom2.output.Format);
    Code:
       0: aload_0
       1: aload_1
       2: invokevirtual #6                  // Method org/jdom2/output/Format.clone:()Lorg/jdom2/output/Format;
       5: putfield      #2                  // Field myFormat:Lorg/jdom2/output/Format;
       8: return

  public org.jdom2.output.Format getFormat();
    Code:
       0: aload_0
       1: getfield      #2                  // Field myFormat:Lorg/jdom2/output/Format;
       4: areturn

  public org.jdom2.output.support.StAXEventProcessor getStAXStream();
    Code:
       0: aload_0
       1: getfield      #3                  // Field myProcessor:Lorg/jdom2/output/support/StAXEventProcessor;
       4: areturn

  public void setStAXEventProcessor(org.jdom2.output.support.StAXEventProcessor);
    Code:
       0: aload_0
       1: aload_1
       2: putfield      #3                  // Field myProcessor:Lorg/jdom2/output/support/StAXEventProcessor;
       5: return

  public javax.xml.stream.XMLEventFactory getEventFactory();
    Code:
       0: aload_0
       1: getfield      #4                  // Field myEventFactory:Ljavax/xml/stream/XMLEventFactory;
       4: areturn

  public void setEventFactory(javax.xml.stream.XMLEventFactory);
    Code:
       0: aload_0
       1: aload_1
       2: putfield      #4                  // Field myEventFactory:Ljavax/xml/stream/XMLEventFactory;
       5: return

  public final void output(org.jdom2.Document, javax.xml.stream.util.XMLEventConsumer) throws javax.xml.stream.XMLStreamException;
    Code:
       0: aload_0
       1: getfield      #3                  // Field myProcessor:Lorg/jdom2/output/support/StAXEventProcessor;
       4: aload_2
       5: aload_0
       6: getfield      #2                  // Field myFormat:Lorg/jdom2/output/Format;
       9: aload_0
      10: getfield      #4                  // Field myEventFactory:Ljavax/xml/stream/XMLEventFactory;
      13: aload_1
      14: invokeinterface #10,  5           // InterfaceMethod org/jdom2/output/support/StAXEventProcessor.process:(Ljavax/xml/stream/util/XMLEventConsumer;Lorg/jdom2/output/Format;Ljavax/xml/stream/XMLEventFactory;Lorg/jdom2/Document;)V
      19: return

  public final void output(org.jdom2.DocType, javax.xml.stream.util.XMLEventConsumer) throws javax.xml.stream.XMLStreamException;
    Code:
       0: aload_0
       1: getfield      #3                  // Field myProcessor:Lorg/jdom2/output/support/StAXEventProcessor;
       4: aload_2
       5: aload_0
       6: getfield      #2                  // Field myFormat:Lorg/jdom2/output/Format;
       9: aload_0
      10: getfield      #4                  // Field myEventFactory:Ljavax/xml/stream/XMLEventFactory;
      13: aload_1
      14: invokeinterface #11,  5           // InterfaceMethod org/jdom2/output/support/StAXEventProcessor.process:(Ljavax/xml/stream/util/XMLEventConsumer;Lorg/jdom2/output/Format;Ljavax/xml/stream/XMLEventFactory;Lorg/jdom2/DocType;)V
      19: return

  public final void output(org.jdom2.Element, javax.xml.stream.util.XMLEventConsumer) throws javax.xml.stream.XMLStreamException;
    Code:
       0: aload_0
       1: getfield      #3                  // Field myProcessor:Lorg/jdom2/output/support/StAXEventProcessor;
       4: aload_2
       5: aload_0
       6: getfield      #2                  // Field myFormat:Lorg/jdom2/output/Format;
       9: aload_0
      10: getfield      #4                  // Field myEventFactory:Ljavax/xml/stream/XMLEventFactory;
      13: aload_1
      14: invokeinterface #12,  5           // InterfaceMethod org/jdom2/output/support/StAXEventProcessor.process:(Ljavax/xml/stream/util/XMLEventConsumer;Lorg/jdom2/output/Format;Ljavax/xml/stream/XMLEventFactory;Lorg/jdom2/Element;)V
      19: return

  public final void outputElementContent(org.jdom2.Element, javax.xml.stream.util.XMLEventConsumer) throws javax.xml.stream.XMLStreamException;
    Code:
       0: aload_0
       1: getfield      #3                  // Field myProcessor:Lorg/jdom2/output/support/StAXEventProcessor;
       4: aload_2
       5: aload_0
       6: getfield      #2                  // Field myFormat:Lorg/jdom2/output/Format;
       9: aload_0
      10: getfield      #4                  // Field myEventFactory:Ljavax/xml/stream/XMLEventFactory;
      13: aload_1
      14: invokevirtual #13                 // Method org/jdom2/Element.getContent:()Ljava/util/List;
      17: invokeinterface #14,  5           // InterfaceMethod org/jdom2/output/support/StAXEventProcessor.process:(Ljavax/xml/stream/util/XMLEventConsumer;Lorg/jdom2/output/Format;Ljavax/xml/stream/XMLEventFactory;Ljava/util/List;)V
      22: return

  public final void output(java.util.List<? extends org.jdom2.Content>, javax.xml.stream.util.XMLEventConsumer) throws javax.xml.stream.XMLStreamException;
    Code:
       0: aload_0
       1: getfield      #3                  // Field myProcessor:Lorg/jdom2/output/support/StAXEventProcessor;
       4: aload_2
       5: aload_0
       6: getfield      #2                  // Field myFormat:Lorg/jdom2/output/Format;
       9: aload_0
      10: getfield      #4                  // Field myEventFactory:Ljavax/xml/stream/XMLEventFactory;
      13: aload_1
      14: invokeinterface #14,  5           // InterfaceMethod org/jdom2/output/support/StAXEventProcessor.process:(Ljavax/xml/stream/util/XMLEventConsumer;Lorg/jdom2/output/Format;Ljavax/xml/stream/XMLEventFactory;Ljava/util/List;)V
      19: return

  public final void output(org.jdom2.CDATA, javax.xml.stream.util.XMLEventConsumer) throws javax.xml.stream.XMLStreamException;
    Code:
       0: aload_0
       1: getfield      #3                  // Field myProcessor:Lorg/jdom2/output/support/StAXEventProcessor;
       4: aload_2
       5: aload_0
       6: getfield      #2                  // Field myFormat:Lorg/jdom2/output/Format;
       9: aload_0
      10: getfield      #4                  // Field myEventFactory:Ljavax/xml/stream/XMLEventFactory;
      13: aload_1
      14: invokeinterface #15,  5           // InterfaceMethod org/jdom2/output/support/StAXEventProcessor.process:(Ljavax/xml/stream/util/XMLEventConsumer;Lorg/jdom2/output/Format;Ljavax/xml/stream/XMLEventFactory;Lorg/jdom2/CDATA;)V
      19: return

  public final void output(org.jdom2.Text, javax.xml.stream.util.XMLEventConsumer) throws javax.xml.stream.XMLStreamException;
    Code:
       0: aload_0
       1: getfield      #3                  // Field myProcessor:Lorg/jdom2/output/support/StAXEventProcessor;
       4: aload_2
       5: aload_0
       6: getfield      #2                  // Field myFormat:Lorg/jdom2/output/Format;
       9: aload_0
      10: getfield      #4                  // Field myEventFactory:Ljavax/xml/stream/XMLEventFactory;
      13: aload_1
      14: invokeinterface #16,  5           // InterfaceMethod org/jdom2/output/support/StAXEventProcessor.process:(Ljavax/xml/stream/util/XMLEventConsumer;Lorg/jdom2/output/Format;Ljavax/xml/stream/XMLEventFactory;Lorg/jdom2/Text;)V
      19: return

  public final void output(org.jdom2.Comment, javax.xml.stream.util.XMLEventConsumer) throws javax.xml.stream.XMLStreamException;
    Code:
       0: aload_0
       1: getfield      #3                  // Field myProcessor:Lorg/jdom2/output/support/StAXEventProcessor;
       4: aload_2
       5: aload_0
       6: getfield      #2                  // Field myFormat:Lorg/jdom2/output/Format;
       9: aload_0
      10: getfield      #4                  // Field myEventFactory:Ljavax/xml/stream/XMLEventFactory;
      13: aload_1
      14: invokeinterface #17,  5           // InterfaceMethod org/jdom2/output/support/StAXEventProcessor.process:(Ljavax/xml/stream/util/XMLEventConsumer;Lorg/jdom2/output/Format;Ljavax/xml/stream/XMLEventFactory;Lorg/jdom2/Comment;)V
      19: return

  public final void output(org.jdom2.ProcessingInstruction, javax.xml.stream.util.XMLEventConsumer) throws javax.xml.stream.XMLStreamException;
    Code:
       0: aload_0
       1: getfield      #3                  // Field myProcessor:Lorg/jdom2/output/support/StAXEventProcessor;
       4: aload_2
       5: aload_0
       6: getfield      #2                  // Field myFormat:Lorg/jdom2/output/Format;
       9: aload_0
      10: getfield      #4                  // Field myEventFactory:Ljavax/xml/stream/XMLEventFactory;
      13: aload_1
      14: invokeinterface #18,  5           // InterfaceMethod org/jdom2/output/support/StAXEventProcessor.process:(Ljavax/xml/stream/util/XMLEventConsumer;Lorg/jdom2/output/Format;Ljavax/xml/stream/XMLEventFactory;Lorg/jdom2/ProcessingInstruction;)V
      19: return

  public final void output(org.jdom2.EntityRef, javax.xml.stream.util.XMLEventConsumer) throws javax.xml.stream.XMLStreamException;
    Code:
       0: aload_0
       1: getfield      #3                  // Field myProcessor:Lorg/jdom2/output/support/StAXEventProcessor;
       4: aload_2
       5: aload_0
       6: getfield      #2                  // Field myFormat:Lorg/jdom2/output/Format;
       9: aload_0
      10: getfield      #4                  // Field myEventFactory:Ljavax/xml/stream/XMLEventFactory;
      13: aload_1
      14: invokeinterface #19,  5           // InterfaceMethod org/jdom2/output/support/StAXEventProcessor.process:(Ljavax/xml/stream/util/XMLEventConsumer;Lorg/jdom2/output/Format;Ljavax/xml/stream/XMLEventFactory;Lorg/jdom2/EntityRef;)V
      19: return

  public org.jdom2.output.StAXEventOutputter clone();
    Code:
       0: aload_0
       1: invokespecial #20                 // Method java/lang/Object.clone:()Ljava/lang/Object;
       4: checkcast     #21                 // class org/jdom2/output/StAXEventOutputter
       7: areturn
       8: astore_1
       9: new           #23                 // class java/lang/RuntimeException
      12: dup
      13: aload_1
      14: invokevirtual #24                 // Method java/lang/CloneNotSupportedException.toString:()Ljava/lang/String;
      17: invokespecial #25                 // Method java/lang/RuntimeException."<init>":(Ljava/lang/String;)V
      20: athrow
    Exception table:
       from    to  target type
           0     7     8   Class java/lang/CloneNotSupportedException

  public java.lang.String toString();
    Code:
       0: new           #26                 // class java/lang/StringBuilder
       3: dup
       4: invokespecial #27                 // Method java/lang/StringBuilder."<init>":()V
       7: astore_1
       8: aload_1
       9: ldc           #28                 // String StAXStreamOutputter[omitDeclaration =
      11: invokevirtual #29                 // Method java/lang/StringBuilder.append:(Ljava/lang/String;)Ljava/lang/StringBuilder;
      14: pop
      15: aload_1
      16: aload_0
      17: getfield      #2                  // Field myFormat:Lorg/jdom2/output/Format;
      20: getfield      #30                 // Field org/jdom2/output/Format.omitDeclaration:Z
      23: invokevirtual #31                 // Method java/lang/StringBuilder.append:(Z)Ljava/lang/StringBuilder;
      26: pop
      27: aload_1
      28: ldc           #32                 // String ,
      30: invokevirtual #29                 // Method java/lang/StringBuilder.append:(Ljava/lang/String;)Ljava/lang/StringBuilder;
      33: pop
      34: aload_1
      35: ldc           #33                 // String encoding =
      37: invokevirtual #29                 // Method java/lang/StringBuilder.append:(Ljava/lang/String;)Ljava/lang/StringBuilder;
      40: pop
      41: aload_1
      42: aload_0
      43: getfield      #2                  // Field myFormat:Lorg/jdom2/output/Format;
      46: getfield      #34                 // Field org/jdom2/output/Format.encoding:Ljava/lang/String;
      49: invokevirtual #29                 // Method java/lang/StringBuilder.append:(Ljava/lang/String;)Ljava/lang/StringBuilder;
      52: pop
      53: aload_1
      54: ldc           #32                 // String ,
      56: invokevirtual #29                 // Method java/lang/StringBuilder.append:(Ljava/lang/String;)Ljava/lang/StringBuilder;
      59: pop
      60: aload_1
      61: ldc           #35                 // String omitEncoding =
      63: invokevirtual #29                 // Method java/lang/StringBuilder.append:(Ljava/lang/String;)Ljava/lang/StringBuilder;
      66: pop
      67: aload_1
      68: aload_0
      69: getfield      #2                  // Field myFormat:Lorg/jdom2/output/Format;
      72: getfield      #36                 // Field org/jdom2/output/Format.omitEncoding:Z
      75: invokevirtual #31                 // Method java/lang/StringBuilder.append:(Z)Ljava/lang/StringBuilder;
      78: pop
      79: aload_1
      80: ldc           #32                 // String ,
      82: invokevirtual #29                 // Method java/lang/StringBuilder.append:(Ljava/lang/String;)Ljava/lang/StringBuilder;
      85: pop
      86: aload_1
      87: ldc           #37                 // String indent = \'
      89: invokevirtual #29                 // Method java/lang/StringBuilder.append:(Ljava/lang/String;)Ljava/lang/StringBuilder;
      92: pop
      93: aload_1
      94: aload_0
      95: getfield      #2                  // Field myFormat:Lorg/jdom2/output/Format;
      98: getfield      #38                 // Field org/jdom2/output/Format.indent:Ljava/lang/String;
     101: invokevirtual #29                 // Method java/lang/StringBuilder.append:(Ljava/lang/String;)Ljava/lang/StringBuilder;
     104: pop
     105: aload_1
     106: ldc           #39                 // String \'
     108: invokevirtual #29                 // Method java/lang/StringBuilder.append:(Ljava/lang/String;)Ljava/lang/StringBuilder;
     111: pop
     112: aload_1
     113: ldc           #32                 // String ,
     115: invokevirtual #29                 // Method java/lang/StringBuilder.append:(Ljava/lang/String;)Ljava/lang/StringBuilder;
     118: pop
     119: aload_1
     120: ldc           #40                 // String expandEmptyElements =
     122: invokevirtual #29                 // Method java/lang/StringBuilder.append:(Ljava/lang/String;)Ljava/lang/StringBuilder;
     125: pop
     126: aload_1
     127: aload_0
     128: getfield      #2                  // Field myFormat:Lorg/jdom2/output/Format;
     131: getfield      #41                 // Field org/jdom2/output/Format.expandEmptyElements:Z
     134: invokevirtual #31                 // Method java/lang/StringBuilder.append:(Z)Ljava/lang/StringBuilder;
     137: pop
     138: aload_1
     139: ldc           #32                 // String ,
     141: invokevirtual #29                 // Method java/lang/StringBuilder.append:(Ljava/lang/String;)Ljava/lang/StringBuilder;
     144: pop
     145: aload_1
     146: ldc           #42                 // String lineSeparator = \'
     148: invokevirtual #29                 // Method java/lang/StringBuilder.append:(Ljava/lang/String;)Ljava/lang/StringBuilder;
     151: pop
     152: aload_0
     153: getfield      #2                  // Field myFormat:Lorg/jdom2/output/Format;
     156: getfield      #43                 // Field org/jdom2/output/Format.lineSeparator:Ljava/lang/String;
     159: invokevirtual #44                 // Method java/lang/String.toCharArray:()[C
     162: astore_2
     163: aload_2
     164: arraylength
     165: istore_3
     166: iconst_0
     167: istore        4
     169: iload         4
     171: iload_3
     172: if_icmpge     282
     175: aload_2
     176: iload         4
     178: caload
     179: istore        5
     181: iload         5
     183: tableswitch   { // 9 to 13
                     9: 236
                    10: 226
                    11: 246
                    12: 246
                    13: 216
               default: 246
          }
     216: aload_1
     217: ldc           #45                 // String \\r
     219: invokevirtual #29                 // Method java/lang/StringBuilder.append:(Ljava/lang/String;)Ljava/lang/StringBuilder;
     222: pop
     223: goto          276
     226: aload_1
     227: ldc           #46                 // String \\n
     229: invokevirtual #29                 // Method java/lang/StringBuilder.append:(Ljava/lang/String;)Ljava/lang/StringBuilder;
     232: pop
     233: goto          276
     236: aload_1
     237: ldc           #47                 // String \\t
     239: invokevirtual #29                 // Method java/lang/StringBuilder.append:(Ljava/lang/String;)Ljava/lang/StringBuilder;
     242: pop
     243: goto          276
     246: aload_1
     247: new           #26                 // class java/lang/StringBuilder
     250: dup
     251: invokespecial #27                 // Method java/lang/StringBuilder."<init>":()V
     254: ldc           #48                 // String [
     256: invokevirtual #29                 // Method java/lang/StringBuilder.append:(Ljava/lang/String;)Ljava/lang/StringBuilder;
     259: iload         5
     261: invokevirtual #49                 // Method java/lang/StringBuilder.append:(I)Ljava/lang/StringBuilder;
     264: ldc           #50                 // String ]
     266: invokevirtual #29                 // Method java/lang/StringBuilder.append:(Ljava/lang/String;)Ljava/lang/StringBuilder;
     269: invokevirtual #51                 // Method java/lang/StringBuilder.toString:()Ljava/lang/String;
     272: invokevirtual #29                 // Method java/lang/StringBuilder.append:(Ljava/lang/String;)Ljava/lang/StringBuilder;
     275: pop
     276: iinc          4, 1
     279: goto          169
     282: aload_1
     283: ldc           #52                 // String \',
     285: invokevirtual #29                 // Method java/lang/StringBuilder.append:(Ljava/lang/String;)Ljava/lang/StringBuilder;
     288: pop
     289: aload_1
     290: ldc           #53                 // String textMode =
     292: invokevirtual #29                 // Method java/lang/StringBuilder.append:(Ljava/lang/String;)Ljava/lang/StringBuilder;
     295: pop
     296: aload_1
     297: new           #26                 // class java/lang/StringBuilder
     300: dup
     301: invokespecial #27                 // Method java/lang/StringBuilder."<init>":()V
     304: aload_0
     305: getfield      #2                  // Field myFormat:Lorg/jdom2/output/Format;
     308: getfield      #54                 // Field org/jdom2/output/Format.mode:Lorg/jdom2/output/Format$TextMode;
     311: invokevirtual #55                 // Method java/lang/StringBuilder.append:(Ljava/lang/Object;)Ljava/lang/StringBuilder;
     314: ldc           #50                 // String ]
     316: invokevirtual #29                 // Method java/lang/StringBuilder.append:(Ljava/lang/String;)Ljava/lang/StringBuilder;
     319: invokevirtual #51                 // Method java/lang/StringBuilder.toString:()Ljava/lang/String;
     322: invokevirtual #29                 // Method java/lang/StringBuilder.append:(Ljava/lang/String;)Ljava/lang/StringBuilder;
     325: pop
     326: aload_1
     327: invokevirtual #51                 // Method java/lang/StringBuilder.toString:()Ljava/lang/String;
     330: areturn

  public java.lang.Object clone() throws java.lang.CloneNotSupportedException;
    Code:
       0: aload_0
       1: invokevirtual #56                 // Method clone:()Lorg/jdom2/output/StAXEventOutputter;
       4: areturn

  static {};
    Code:
       0: new           #57                 // class org/jdom2/output/StAXEventOutputter$DefaultStAXEventProcessor
       3: dup
       4: aconst_null
       5: invokespecial #58                 // Method org/jdom2/output/StAXEventOutputter$DefaultStAXEventProcessor."<init>":(Lorg/jdom2/output/StAXEventOutputter$1;)V
       8: putstatic     #7                  // Field DEFAULTPROCESSOR:Lorg/jdom2/output/StAXEventOutputter$DefaultStAXEventProcessor;
      11: invokestatic  #59                 // Method javax/xml/stream/XMLEventFactory.newInstance:()Ljavax/xml/stream/XMLEventFactory;
      14: putstatic     #8                  // Field DEFAULTEVENTFACTORY:Ljavax/xml/stream/XMLEventFactory;
      17: return
}
