Compiled from "ActionMarshaller.java"
public class org.opensaml.saml1.core.impl.ActionMarshaller extends org.opensaml.common.impl.AbstractSAMLObjectMarshaller {
  public org.opensaml.saml1.core.impl.ActionMarshaller();
    Code:
       0: aload_0
       1: invokespecial #1                  // Method org/opensaml/common/impl/AbstractSAMLObjectMarshaller."<init>":()V
       4: return

  protected void marshallAttributes(org.opensaml.xml.XMLObject, org.w3c.dom.Element) throws org.opensaml.xml.io.MarshallingException;
    Code:
       0: aload_1
       1: checkcast     #2                  // class org/opensaml/saml1/core/Action
       4: astore_3
       5: aload_3
       6: invokeinterface #3,  1            // InterfaceMethod org/opensaml/saml1/core/Action.getNamespace:()Ljava/lang/String;
      11: ifnull        29
      14: aload_2
      15: aconst_null
      16: ldc           #4                  // String Namespace
      18: aload_3
      19: invokeinterface #3,  1            // InterfaceMethod org/opensaml/saml1/core/Action.getNamespace:()Ljava/lang/String;
      24: invokeinterface #5,  4            // InterfaceMethod org/w3c/dom/Element.setAttributeNS:(Ljava/lang/String;Ljava/lang/String;Ljava/lang/String;)V
      29: return

  protected void marshallElementContent(org.opensaml.xml.XMLObject, org.w3c.dom.Element) throws org.opensaml.xml.io.MarshallingException;
    Code:
       0: aload_1
       1: checkcast     #2                  // class org/opensaml/saml1/core/Action
       4: astore_3
       5: aload_3
       6: invokeinterface #6,  1            // InterfaceMethod org/opensaml/saml1/core/Action.getContents:()Ljava/lang/String;
      11: ifnull        24
      14: aload_2
      15: aload_3
      16: invokeinterface #6,  1            // InterfaceMethod org/opensaml/saml1/core/Action.getContents:()Ljava/lang/String;
      21: invokestatic  #7                  // Method org/opensaml/xml/util/XMLHelper.appendTextContent:(Lorg/w3c/dom/Element;Ljava/lang/String;)V
      24: return
}
