Compiled from "AuthorizationDecisionStatementImpl.java"
public class org.opensaml.saml1.core.impl.AuthorizationDecisionStatementImpl extends org.opensaml.saml1.core.impl.SubjectStatementImpl implements org.opensaml.saml1.core.AuthorizationDecisionStatement {
  private java.lang.String resource;

  private org.opensaml.saml1.core.DecisionTypeEnumeration decision;

  private final org.opensaml.xml.util.XMLObjectChildrenList<org.opensaml.saml1.core.Action> actions;

  private org.opensaml.saml1.core.Evidence evidence;

  protected org.opensaml.saml1.core.impl.AuthorizationDecisionStatementImpl(java.lang.String, java.lang.String, java.lang.String);
    Code:
       0: aload_0
       1: aload_1
       2: aload_2
       3: aload_3
       4: invokespecial #1                  // Method org/opensaml/saml1/core/impl/SubjectStatementImpl."<init>":(Ljava/lang/String;Ljava/lang/String;Ljava/lang/String;)V
       7: aload_0
       8: new           #2                  // class org/opensaml/xml/util/XMLObjectChildrenList
      11: dup
      12: aload_0
      13: invokespecial #3                  // Method org/opensaml/xml/util/XMLObjectChildrenList."<init>":(Lorg/opensaml/xml/XMLObject;)V
      16: putfield      #4                  // Field actions:Lorg/opensaml/xml/util/XMLObjectChildrenList;
      19: return

  public java.lang.String getResource();
    Code:
       0: aload_0
       1: getfield      #5                  // Field resource:Ljava/lang/String;
       4: areturn

  public void setResource(java.lang.String);
    Code:
       0: aload_0
       1: aload_0
       2: aload_0
       3: getfield      #5                  // Field resource:Ljava/lang/String;
       6: aload_1
       7: invokevirtual #6                  // Method prepareForAssignment:(Ljava/lang/String;Ljava/lang/String;)Ljava/lang/String;
      10: putfield      #5                  // Field resource:Ljava/lang/String;
      13: return

  public org.opensaml.saml1.core.DecisionTypeEnumeration getDecision();
    Code:
       0: aload_0
       1: getfield      #7                  // Field decision:Lorg/opensaml/saml1/core/DecisionTypeEnumeration;
       4: areturn

  public void setDecision(org.opensaml.saml1.core.DecisionTypeEnumeration);
    Code:
       0: aload_0
       1: aload_0
       2: aload_0
       3: getfield      #7                  // Field decision:Lorg/opensaml/saml1/core/DecisionTypeEnumeration;
       6: aload_1
       7: invokevirtual #8                  // Method prepareForAssignment:(Ljava/lang/Object;Ljava/lang/Object;)Ljava/lang/Object;
      10: checkcast     #9                  // class org/opensaml/saml1/core/DecisionTypeEnumeration
      13: putfield      #7                  // Field decision:Lorg/opensaml/saml1/core/DecisionTypeEnumeration;
      16: return

  public java.util.List<org.opensaml.saml1.core.Action> getActions();
    Code:
       0: aload_0
       1: getfield      #4                  // Field actions:Lorg/opensaml/xml/util/XMLObjectChildrenList;
       4: areturn

  public org.opensaml.saml1.core.Evidence getEvidence();
    Code:
       0: aload_0
       1: getfield      #10                 // Field evidence:Lorg/opensaml/saml1/core/Evidence;
       4: areturn

  public void setEvidence(org.opensaml.saml1.core.Evidence) throws java.lang.IllegalArgumentException;
    Code:
       0: aload_0
       1: aload_0
       2: aload_0
       3: getfield      #10                 // Field evidence:Lorg/opensaml/saml1/core/Evidence;
       6: aload_1
       7: invokevirtual #11                 // Method prepareForAssignment:(Lorg/opensaml/xml/XMLObject;Lorg/opensaml/xml/XMLObject;)Lorg/opensaml/xml/XMLObject;
      10: checkcast     #12                 // class org/opensaml/saml1/core/Evidence
      13: putfield      #10                 // Field evidence:Lorg/opensaml/saml1/core/Evidence;
      16: return

  public java.util.List<org.opensaml.xml.XMLObject> getOrderedChildren();
    Code:
       0: new           #13                 // class java/util/ArrayList
       3: dup
       4: aload_0
       5: getfield      #4                  // Field actions:Lorg/opensaml/xml/util/XMLObjectChildrenList;
       8: invokevirtual #14                 // Method org/opensaml/xml/util/XMLObjectChildrenList.size:()I
      11: iconst_2
      12: iadd
      13: invokespecial #15                 // Method java/util/ArrayList."<init>":(I)V
      16: astore_1
      17: aload_0
      18: invokespecial #16                 // Method org/opensaml/saml1/core/impl/SubjectStatementImpl.getOrderedChildren:()Ljava/util/List;
      21: ifnull        35
      24: aload_1
      25: aload_0
      26: invokespecial #16                 // Method org/opensaml/saml1/core/impl/SubjectStatementImpl.getOrderedChildren:()Ljava/util/List;
      29: invokeinterface #17,  2           // InterfaceMethod java/util/List.addAll:(Ljava/util/Collection;)Z
      34: pop
      35: aload_1
      36: aload_0
      37: getfield      #4                  // Field actions:Lorg/opensaml/xml/util/XMLObjectChildrenList;
      40: invokeinterface #17,  2           // InterfaceMethod java/util/List.addAll:(Ljava/util/Collection;)Z
      45: pop
      46: aload_0
      47: getfield      #10                 // Field evidence:Lorg/opensaml/saml1/core/Evidence;
      50: ifnull        64
      53: aload_1
      54: aload_0
      55: getfield      #10                 // Field evidence:Lorg/opensaml/saml1/core/Evidence;
      58: invokeinterface #18,  2           // InterfaceMethod java/util/List.add:(Ljava/lang/Object;)Z
      63: pop
      64: aload_1
      65: invokeinterface #19,  1           // InterfaceMethod java/util/List.size:()I
      70: ifne          75
      73: aconst_null
      74: areturn
      75: aload_1
      76: invokestatic  #20                 // Method java/util/Collections.unmodifiableList:(Ljava/util/List;)Ljava/util/List;
      79: areturn
}
