Compiled from "WalkerVisitorSkipService.java"
public class org.apache.jena.sparql.algebra.walker.WalkerVisitorSkipService extends org.apache.jena.sparql.algebra.walker.WalkerVisitor {
  public org.apache.jena.sparql.algebra.walker.WalkerVisitorSkipService(org.apache.jena.sparql.algebra.OpVisitor, org.apache.jena.sparql.expr.ExprVisitor, org.apache.jena.sparql.algebra.OpVisitor, org.apache.jena.sparql.algebra.OpVisitor);
    Code:
       0: aload_0
       1: aload_1
       2: aload_2
       3: aload_3
       4: aload         4
       6: invokespecial #1                  // Method org/apache/jena/sparql/algebra/walker/WalkerVisitor."<init>":(Lorg/apache/jena/sparql/algebra/OpVisitor;Lorg/apache/jena/sparql/expr/ExprVisitor;Lorg/apache/jena/sparql/algebra/OpVisitor;Lorg/apache/jena/sparql/algebra/OpVisitor;)V
       9: return

  public void visit(org.apache.jena.sparql.algebra.op.OpService);
    Code:
       0: aload_0
       1: getfield      #2                  // Field opVisitor:Lorg/apache/jena/sparql/algebra/OpVisitor;
       4: ifnull        15
       7: aload_1
       8: aload_0
       9: getfield      #2                  // Field opVisitor:Lorg/apache/jena/sparql/algebra/OpVisitor;
      12: invokevirtual #3                  // Method org/apache/jena/sparql/algebra/op/OpService.visit:(Lorg/apache/jena/sparql/algebra/OpVisitor;)V
      15: return
}
