Compiled from "MeterPartition.java"
public class io.micrometer.core.instrument.util.MeterPartition extends java.util.AbstractList<java.util.List<io.micrometer.core.instrument.Meter>> {
  private final java.util.List<io.micrometer.core.instrument.Meter> list;

  private final int partitionSize;

  private final int partitionCount;

  public io.micrometer.core.instrument.util.MeterPartition(io.micrometer.core.instrument.MeterRegistry, int);
    Code:
       0: aload_0
       1: invokespecial #17                 // Method java/util/AbstractList."<init>":()V
       4: aload_0
       5: aload_1
       6: invokevirtual #23                 // Method io/micrometer/core/instrument/MeterRegistry.getMeters:()Ljava/util/List;
       9: putfield      #25                 // Field list:Ljava/util/List;
      12: aload_0
      13: iload_2
      14: putfield      #27                 // Field partitionSize:I
      17: aload_0
      18: aload_0
      19: getfield      #25                 // Field list:Ljava/util/List;
      22: invokeinterface #33,  1           // InterfaceMethod java/util/List.size:()I
      27: iload_2
      28: invokestatic  #39                 // Method io/micrometer/core/instrument/util/MathUtils.divideWithCeilingRoundingMode:(II)I
      31: putfield      #41                 // Field partitionCount:I
      34: return

  public static java.util.List<java.util.List<io.micrometer.core.instrument.Meter>> partition(io.micrometer.core.instrument.MeterRegistry, int);
    Code:
       0: new           #2                  // class io/micrometer/core/instrument/util/MeterPartition
       3: dup
       4: aload_0
       5: iload_1
       6: invokespecial #50                 // Method "<init>":(Lio/micrometer/core/instrument/MeterRegistry;I)V
       9: areturn

  public java.util.List<io.micrometer.core.instrument.Meter> get(int);
    Code:
       0: iload_1
       1: aload_0
       2: getfield      #27                 // Field partitionSize:I
       5: imul
       6: istore_2
       7: iload_2
       8: aload_0
       9: getfield      #27                 // Field partitionSize:I
      12: iadd
      13: aload_0
      14: getfield      #25                 // Field list:Ljava/util/List;
      17: invokeinterface #33,  1           // InterfaceMethod java/util/List.size:()I
      22: invokestatic  #58                 // Method java/lang/Math.min:(II)I
      25: istore_3
      26: aload_0
      27: getfield      #25                 // Field list:Ljava/util/List;
      30: iload_2
      31: iload_3
      32: invokeinterface #62,  3           // InterfaceMethod java/util/List.subList:(II)Ljava/util/List;
      37: areturn

  public int size();
    Code:
       0: aload_0
       1: getfield      #41                 // Field partitionCount:I
       4: ireturn

  public boolean isEmpty();
    Code:
       0: aload_0
       1: getfield      #25                 // Field list:Ljava/util/List;
       4: invokeinterface #69,  1           // InterfaceMethod java/util/List.isEmpty:()Z
       9: ireturn

  public java.lang.Object get(int);
    Code:
       0: aload_0
       1: iload_1
       2: invokevirtual #72                 // Method get:(I)Ljava/util/List;
       5: areturn
}
