public class org.bouncycastle.crypto.tls.TlsRSAKeyExchange extends org.bouncycastle.crypto.tls.AbstractTlsKeyExchange {
  protected org.bouncycastle.crypto.params.AsymmetricKeyParameter serverPublicKey;

  protected org.bouncycastle.crypto.params.RSAKeyParameters rsaServerPublicKey;

  protected org.bouncycastle.crypto.tls.TlsEncryptionCredentials serverCredentials;

  protected byte[] premasterSecret;

  public org.bouncycastle.crypto.tls.TlsRSAKeyExchange(java.util.Vector);
    Code:
       0: aload_0
       1: iconst_1
       2: aload_1
       3: invokespecial #131                // Method org/bouncycastle/crypto/tls/AbstractTlsKeyExchange."<init>":(ILjava/util/Vector;)V
       6: aload_0
       7: aconst_null
       8: putfield      #123                // Field serverPublicKey:Lorg/bouncycastle/crypto/params/AsymmetricKeyParameter;
      11: aload_0
      12: aconst_null
      13: putfield      #124                // Field rsaServerPublicKey:Lorg/bouncycastle/crypto/params/RSAKeyParameters;
      16: aload_0
      17: aconst_null
      18: putfield      #126                // Field serverCredentials:Lorg/bouncycastle/crypto/tls/TlsEncryptionCredentials;
      21: return

  public void skipServerCredentials() throws java.io.IOException;
    Code:
       0: new           #68                 // class org/bouncycastle/crypto/tls/TlsFatalAlert
       3: dup
       4: bipush        10
       6: invokespecial #136                // Method org/bouncycastle/crypto/tls/TlsFatalAlert."<init>":(S)V
       9: athrow

  public void processServerCredentials(org.bouncycastle.crypto.tls.TlsCredentials) throws java.io.IOException;
    Code:
       0: aload_1
       1: instanceof    #67                 // class org/bouncycastle/crypto/tls/TlsEncryptionCredentials
       4: ifne          17
       7: new           #68                 // class org/bouncycastle/crypto/tls/TlsFatalAlert
      10: dup
      11: bipush        80
      13: invokespecial #136                // Method org/bouncycastle/crypto/tls/TlsFatalAlert."<init>":(S)V
      16: athrow
      17: aload_0
      18: aload_1
      19: invokeinterface #146,  1          // InterfaceMethod org/bouncycastle/crypto/tls/TlsCredentials.getCertificate:()Lorg/bouncycastle/crypto/tls/Certificate;
      24: invokevirtual #138                // Method processServerCertificate:(Lorg/bouncycastle/crypto/tls/Certificate;)V
      27: aload_0
      28: aload_1
      29: checkcast     #67                 // class org/bouncycastle/crypto/tls/TlsEncryptionCredentials
      32: putfield      #126                // Field serverCredentials:Lorg/bouncycastle/crypto/tls/TlsEncryptionCredentials;
      35: return

  public void processServerCertificate(org.bouncycastle.crypto.tls.Certificate) throws java.io.IOException;
    Code:
       0: aload_1
       1: invokevirtual #133                // Method org/bouncycastle/crypto/tls/Certificate.isEmpty:()Z
       4: ifeq          17
       7: new           #68                 // class org/bouncycastle/crypto/tls/TlsFatalAlert
      10: dup
      11: bipush        42
      13: invokespecial #136                // Method org/bouncycastle/crypto/tls/TlsFatalAlert."<init>":(S)V
      16: athrow
      17: aload_1
      18: iconst_0
      19: invokevirtual #134                // Method org/bouncycastle/crypto/tls/Certificate.getCertificateAt:(I)Lorg/bouncycastle/asn1/x509/Certificate;
      22: astore_2
      23: aload_2
      24: invokevirtual #128                // Method org/bouncycastle/asn1/x509/Certificate.getSubjectPublicKeyInfo:()Lorg/bouncycastle/asn1/x509/SubjectPublicKeyInfo;
      27: astore_3
      28: aload_0
      29: aload_3
      30: invokestatic  #144                // Method org/bouncycastle/crypto/util/PublicKeyFactory.createKey:(Lorg/bouncycastle/asn1/x509/SubjectPublicKeyInfo;)Lorg/bouncycastle/crypto/params/AsymmetricKeyParameter;
      33: putfield      #123                // Field serverPublicKey:Lorg/bouncycastle/crypto/params/AsymmetricKeyParameter;
      36: goto          53
      39: astore        4
      41: new           #68                 // class org/bouncycastle/crypto/tls/TlsFatalAlert
      44: dup
      45: bipush        43
      47: aload         4
      49: invokespecial #137                // Method org/bouncycastle/crypto/tls/TlsFatalAlert."<init>":(SLjava/lang/Throwable;)V
      52: athrow
      53: aload_0
      54: getfield      #123                // Field serverPublicKey:Lorg/bouncycastle/crypto/params/AsymmetricKeyParameter;
      57: invokevirtual #129                // Method org/bouncycastle/crypto/params/AsymmetricKeyParameter.isPrivate:()Z
      60: ifeq          73
      63: new           #68                 // class org/bouncycastle/crypto/tls/TlsFatalAlert
      66: dup
      67: bipush        80
      69: invokespecial #136                // Method org/bouncycastle/crypto/tls/TlsFatalAlert."<init>":(S)V
      72: athrow
      73: aload_0
      74: aload_0
      75: aload_0
      76: getfield      #123                // Field serverPublicKey:Lorg/bouncycastle/crypto/params/AsymmetricKeyParameter;
      79: checkcast     #62                 // class org/bouncycastle/crypto/params/RSAKeyParameters
      82: invokevirtual #139                // Method validateRSAPublicKey:(Lorg/bouncycastle/crypto/params/RSAKeyParameters;)Lorg/bouncycastle/crypto/params/RSAKeyParameters;
      85: putfield      #124                // Field rsaServerPublicKey:Lorg/bouncycastle/crypto/params/RSAKeyParameters;
      88: aload_2
      89: bipush        32
      91: invokestatic  #142                // Method org/bouncycastle/crypto/tls/TlsUtils.validateKeyUsage:(Lorg/bouncycastle/asn1/x509/Certificate;I)V
      94: aload_0
      95: aload_1
      96: invokespecial #132                // Method org/bouncycastle/crypto/tls/AbstractTlsKeyExchange.processServerCertificate:(Lorg/bouncycastle/crypto/tls/Certificate;)V
      99: return
    Exception table:
       from    to  target type
          28    36    39   Class java/lang/RuntimeException

  public void validateCertificateRequest(org.bouncycastle.crypto.tls.CertificateRequest) throws java.io.IOException;
    Code:
       0: aload_1
       1: invokevirtual #135                // Method org/bouncycastle/crypto/tls/CertificateRequest.getCertificateTypes:()[S
       4: astore_2
       5: iconst_0
       6: istore_3
       7: iload_3
       8: aload_2
       9: arraylength
      10: if_icmpge     71
      13: aload_2
      14: iload_3
      15: saload
      16: lookupswitch  { // 3
                     1: 52
                     2: 52
                    64: 52
               default: 55
          }
      52: goto          65
      55: new           #68                 // class org/bouncycastle/crypto/tls/TlsFatalAlert
      58: dup
      59: bipush        47
      61: invokespecial #136                // Method org/bouncycastle/crypto/tls/TlsFatalAlert."<init>":(S)V
      64: athrow
      65: iinc          3, 1
      68: goto          7
      71: return

  public void processClientCredentials(org.bouncycastle.crypto.tls.TlsCredentials) throws java.io.IOException;
    Code:
       0: aload_1
       1: instanceof    #71                 // class org/bouncycastle/crypto/tls/TlsSignerCredentials
       4: ifne          17
       7: new           #68                 // class org/bouncycastle/crypto/tls/TlsFatalAlert
      10: dup
      11: bipush        80
      13: invokespecial #136                // Method org/bouncycastle/crypto/tls/TlsFatalAlert."<init>":(S)V
      16: athrow
      17: return

  public void generateClientKeyExchange(java.io.OutputStream) throws java.io.IOException;
    Code:
       0: aload_0
       1: aload_0
       2: getfield      #125                // Field context:Lorg/bouncycastle/crypto/tls/TlsContext;
       5: aload_0
       6: getfield      #124                // Field rsaServerPublicKey:Lorg/bouncycastle/crypto/params/RSAKeyParameters;
       9: aload_1
      10: invokestatic  #140                // Method org/bouncycastle/crypto/tls/TlsRSAUtils.generateEncryptedPreMasterSecret:(Lorg/bouncycastle/crypto/tls/TlsContext;Lorg/bouncycastle/crypto/params/RSAKeyParameters;Ljava/io/OutputStream;)[B
      13: putfield      #122                // Field premasterSecret:[B
      16: return

  public void processClientKeyExchange(java.io.InputStream) throws java.io.IOException;
    Code:
       0: aload_0
       1: getfield      #125                // Field context:Lorg/bouncycastle/crypto/tls/TlsContext;
       4: invokestatic  #143                // Method org/bouncycastle/crypto/tls/TlsUtils.isSSL:(Lorg/bouncycastle/crypto/tls/TlsContext;)Z
       7: ifeq          18
      10: aload_1
      11: invokestatic  #145                // Method org/bouncycastle/util/io/Streams.readAll:(Ljava/io/InputStream;)[B
      14: astore_2
      15: goto          23
      18: aload_1
      19: invokestatic  #141                // Method org/bouncycastle/crypto/tls/TlsUtils.readOpaque16:(Ljava/io/InputStream;)[B
      22: astore_2
      23: aload_0
      24: aload_0
      25: getfield      #126                // Field serverCredentials:Lorg/bouncycastle/crypto/tls/TlsEncryptionCredentials;
      28: aload_2
      29: invokeinterface #147,  2          // InterfaceMethod org/bouncycastle/crypto/tls/TlsEncryptionCredentials.decryptPreMasterSecret:([B)[B
      34: putfield      #122                // Field premasterSecret:[B
      37: return

  public byte[] generatePremasterSecret() throws java.io.IOException;
    Code:
       0: aload_0
       1: getfield      #122                // Field premasterSecret:[B
       4: ifnonnull     17
       7: new           #68                 // class org/bouncycastle/crypto/tls/TlsFatalAlert
      10: dup
      11: bipush        80
      13: invokespecial #136                // Method org/bouncycastle/crypto/tls/TlsFatalAlert."<init>":(S)V
      16: athrow
      17: aload_0
      18: getfield      #122                // Field premasterSecret:[B
      21: astore_1
      22: aload_0
      23: aconst_null
      24: putfield      #122                // Field premasterSecret:[B
      27: aload_1
      28: areturn

  protected org.bouncycastle.crypto.params.RSAKeyParameters validateRSAPublicKey(org.bouncycastle.crypto.params.RSAKeyParameters) throws java.io.IOException;
    Code:
       0: aload_1
       1: invokevirtual #130                // Method org/bouncycastle/crypto/params/RSAKeyParameters.getExponent:()Ljava/math/BigInteger;
       4: iconst_2
       5: invokevirtual #127                // Method java/math/BigInteger.isProbablePrime:(I)Z
       8: ifne          21
      11: new           #68                 // class org/bouncycastle/crypto/tls/TlsFatalAlert
      14: dup
      15: bipush        47
      17: invokespecial #136                // Method org/bouncycastle/crypto/tls/TlsFatalAlert."<init>":(S)V
      20: athrow
      21: aload_1
      22: areturn
}
