Compiled from "SchemaInfoImpl.java"
public class org.apache.pulsar.client.impl.schema.SchemaInfoImpl$SchemaInfoImplBuilder {
  private java.lang.String name;

  private byte[] schema;

  private org.apache.pulsar.common.schema.SchemaType type;

  private boolean properties$set;

  private java.util.Map<java.lang.String, java.lang.String> properties$value;

  org.apache.pulsar.client.impl.schema.SchemaInfoImpl$SchemaInfoImplBuilder();
    Code:
       0: aload_0
       1: invokespecial #1                  // Method java/lang/Object."<init>":()V
       4: return

  public org.apache.pulsar.client.impl.schema.SchemaInfoImpl$SchemaInfoImplBuilder name(java.lang.String);
    Code:
       0: aload_0
       1: aload_1
       2: putfield      #2                  // Field name:Ljava/lang/String;
       5: aload_0
       6: areturn

  public org.apache.pulsar.client.impl.schema.SchemaInfoImpl$SchemaInfoImplBuilder schema(byte[]);
    Code:
       0: aload_0
       1: aload_1
       2: putfield      #3                  // Field schema:[B
       5: aload_0
       6: areturn

  public org.apache.pulsar.client.impl.schema.SchemaInfoImpl$SchemaInfoImplBuilder type(org.apache.pulsar.common.schema.SchemaType);
    Code:
       0: aload_0
       1: aload_1
       2: putfield      #4                  // Field type:Lorg/apache/pulsar/common/schema/SchemaType;
       5: aload_0
       6: areturn

  public org.apache.pulsar.client.impl.schema.SchemaInfoImpl$SchemaInfoImplBuilder properties(java.util.Map<java.lang.String, java.lang.String>);
    Code:
       0: aload_0
       1: aload_1
       2: putfield      #5                  // Field properties$value:Ljava/util/Map;
       5: aload_0
       6: iconst_1
       7: putfield      #6                  // Field properties$set:Z
      10: aload_0
      11: areturn

  public org.apache.pulsar.client.impl.schema.SchemaInfoImpl build();
    Code:
       0: aload_0
       1: getfield      #5                  // Field properties$value:Ljava/util/Map;
       4: astore_1
       5: aload_0
       6: getfield      #6                  // Field properties$set:Z
       9: ifne          16
      12: invokestatic  #7                  // Method org/apache/pulsar/client/impl/schema/SchemaInfoImpl.access$000:()Ljava/util/Map;
      15: astore_1
      16: new           #8                  // class org/apache/pulsar/client/impl/schema/SchemaInfoImpl
      19: dup
      20: aload_0
      21: getfield      #2                  // Field name:Ljava/lang/String;
      24: aload_0
      25: getfield      #3                  // Field schema:[B
      28: aload_0
      29: getfield      #4                  // Field type:Lorg/apache/pulsar/common/schema/SchemaType;
      32: aload_1
      33: invokespecial #9                  // Method org/apache/pulsar/client/impl/schema/SchemaInfoImpl."<init>":(Ljava/lang/String;[BLorg/apache/pulsar/common/schema/SchemaType;Ljava/util/Map;)V
      36: areturn

  public java.lang.String toString();
    Code:
       0: new           #10                 // class java/lang/StringBuilder
       3: dup
       4: invokespecial #11                 // Method java/lang/StringBuilder."<init>":()V
       7: ldc           #12                 // String SchemaInfoImpl.SchemaInfoImplBuilder(name=
       9: invokevirtual #13                 // Method java/lang/StringBuilder.append:(Ljava/lang/String;)Ljava/lang/StringBuilder;
      12: aload_0
      13: getfield      #2                  // Field name:Ljava/lang/String;
      16: invokevirtual #13                 // Method java/lang/StringBuilder.append:(Ljava/lang/String;)Ljava/lang/StringBuilder;
      19: ldc           #14                 // String , schema=
      21: invokevirtual #13                 // Method java/lang/StringBuilder.append:(Ljava/lang/String;)Ljava/lang/StringBuilder;
      24: aload_0
      25: getfield      #3                  // Field schema:[B
      28: invokestatic  #15                 // Method java/util/Arrays.toString:([B)Ljava/lang/String;
      31: invokevirtual #13                 // Method java/lang/StringBuilder.append:(Ljava/lang/String;)Ljava/lang/StringBuilder;
      34: ldc           #16                 // String , type=
      36: invokevirtual #13                 // Method java/lang/StringBuilder.append:(Ljava/lang/String;)Ljava/lang/StringBuilder;
      39: aload_0
      40: getfield      #4                  // Field type:Lorg/apache/pulsar/common/schema/SchemaType;
      43: invokevirtual #17                 // Method java/lang/StringBuilder.append:(Ljava/lang/Object;)Ljava/lang/StringBuilder;
      46: ldc           #18                 // String , properties$value=
      48: invokevirtual #13                 // Method java/lang/StringBuilder.append:(Ljava/lang/String;)Ljava/lang/StringBuilder;
      51: aload_0
      52: getfield      #5                  // Field properties$value:Ljava/util/Map;
      55: invokevirtual #17                 // Method java/lang/StringBuilder.append:(Ljava/lang/Object;)Ljava/lang/StringBuilder;
      58: ldc           #19                 // String )
      60: invokevirtual #13                 // Method java/lang/StringBuilder.append:(Ljava/lang/String;)Ljava/lang/StringBuilder;
      63: invokevirtual #20                 // Method java/lang/StringBuilder.toString:()Ljava/lang/String;
      66: areturn
}
