Compiled from "AxiomListFrameSection.java"
public class org.protege.editor.owl.ui.frame.AxiomListFrameSection extends org.protege.editor.owl.ui.frame.AbstractOWLFrameSection<java.util.Set<org.semanticweb.owlapi.model.OWLAxiom>, org.semanticweb.owlapi.model.OWLAxiom, org.semanticweb.owlapi.model.OWLAxiom> {
  private org.protege.editor.owl.ui.frame.AxiomListFrameSection$RowComparator rowComparator;

  private java.util.Set<org.semanticweb.owlapi.model.OWLAxiom> added;

  public org.protege.editor.owl.ui.frame.AxiomListFrameSection(org.protege.editor.owl.OWLEditorKit, org.protege.editor.owl.ui.frame.OWLFrame<java.util.Set<org.semanticweb.owlapi.model.OWLAxiom>>);
    Code:
       0: aload_0
       1: aload_1
       2: ldc           #1                  // String Axioms
       4: ldc           #2                  // String Axiom
       6: aload_2
       7: invokespecial #3                  // Method org/protege/editor/owl/ui/frame/AbstractOWLFrameSection."<init>":(Lorg/protege/editor/owl/OWLEditorKit;Ljava/lang/String;Ljava/lang/String;Lorg/protege/editor/owl/ui/frame/OWLFrame;)V
      10: aload_0
      11: new           #4                  // class org/protege/editor/owl/ui/frame/AxiomListFrameSection$RowComparator
      14: dup
      15: aload_0
      16: invokespecial #5                  // Method org/protege/editor/owl/ui/frame/AxiomListFrameSection$RowComparator."<init>":(Lorg/protege/editor/owl/ui/frame/AxiomListFrameSection;)V
      19: putfield      #6                  // Field rowComparator:Lorg/protege/editor/owl/ui/frame/AxiomListFrameSection$RowComparator;
      22: aload_0
      23: new           #7                  // class java/util/HashSet
      26: dup
      27: invokespecial #8                  // Method java/util/HashSet."<init>":()V
      30: putfield      #9                  // Field added:Ljava/util/Set;
      33: return

  protected org.semanticweb.owlapi.model.OWLAxiom createAxiom(org.semanticweb.owlapi.model.OWLAxiom);
    Code:
       0: aconst_null
       1: areturn

  public org.protege.editor.owl.ui.editor.OWLObjectEditor<org.semanticweb.owlapi.model.OWLAxiom> getObjectEditor();
    Code:
       0: aconst_null
       1: areturn

  protected void refill(org.semanticweb.owlapi.model.OWLOntology);
    Code:
       0: aload_0
       1: invokevirtual #10                 // Method getRootObject:()Ljava/lang/Object;
       4: checkcast     #11                 // class java/util/Set
       7: astore_2
       8: aload_2
       9: invokeinterface #12,  1           // InterfaceMethod java/util/Set.iterator:()Ljava/util/Iterator;
      14: astore_3
      15: aload_3
      16: invokeinterface #13,  1           // InterfaceMethod java/util/Iterator.hasNext:()Z
      21: ifeq          87
      24: aload_3
      25: invokeinterface #14,  1           // InterfaceMethod java/util/Iterator.next:()Ljava/lang/Object;
      30: checkcast     #15                 // class org/semanticweb/owlapi/model/OWLAxiom
      33: astore        4
      35: aload_1
      36: aload         4
      38: invokeinterface #16,  2           // InterfaceMethod org/semanticweb/owlapi/model/OWLOntology.containsAxiom:(Lorg/semanticweb/owlapi/model/OWLAxiom;)Z
      43: ifeq          84
      46: aload_0
      47: new           #17                 // class org/protege/editor/owl/ui/frame/AxiomListFrameSectionRow
      50: dup
      51: aload_0
      52: invokevirtual #18                 // Method getOWLEditorKit:()Lorg/protege/editor/owl/OWLEditorKit;
      55: aload_0
      56: aload_1
      57: aload_0
      58: invokevirtual #10                 // Method getRootObject:()Ljava/lang/Object;
      61: checkcast     #11                 // class java/util/Set
      64: aload         4
      66: invokespecial #19                 // Method org/protege/editor/owl/ui/frame/AxiomListFrameSectionRow."<init>":(Lorg/protege/editor/owl/OWLEditorKit;Lorg/protege/editor/owl/ui/frame/OWLFrameSection;Lorg/semanticweb/owlapi/model/OWLOntology;Ljava/util/Set;Lorg/semanticweb/owlapi/model/OWLAxiom;)V
      69: invokevirtual #20                 // Method addRow:(Lorg/protege/editor/owl/ui/frame/OWLFrameSectionRow;)V
      72: aload_0
      73: getfield      #9                  // Field added:Ljava/util/Set;
      76: aload         4
      78: invokeinterface #21,  2           // InterfaceMethod java/util/Set.add:(Ljava/lang/Object;)Z
      83: pop
      84: goto          15
      87: return

  protected void refillInferred();
    Code:
       0: aload_0
       1: invokevirtual #10                 // Method getRootObject:()Ljava/lang/Object;
       4: checkcast     #11                 // class java/util/Set
       7: astore_1
       8: aload_1
       9: invokeinterface #12,  1           // InterfaceMethod java/util/Set.iterator:()Ljava/util/Iterator;
      14: astore_2
      15: aload_2
      16: invokeinterface #13,  1           // InterfaceMethod java/util/Iterator.hasNext:()Z
      21: ifeq          75
      24: aload_2
      25: invokeinterface #14,  1           // InterfaceMethod java/util/Iterator.next:()Ljava/lang/Object;
      30: checkcast     #15                 // class org/semanticweb/owlapi/model/OWLAxiom
      33: astore_3
      34: aload_0
      35: getfield      #9                  // Field added:Ljava/util/Set;
      38: aload_3
      39: invokeinterface #22,  2           // InterfaceMethod java/util/Set.contains:(Ljava/lang/Object;)Z
      44: ifne          72
      47: aload_0
      48: new           #17                 // class org/protege/editor/owl/ui/frame/AxiomListFrameSectionRow
      51: dup
      52: aload_0
      53: invokevirtual #18                 // Method getOWLEditorKit:()Lorg/protege/editor/owl/OWLEditorKit;
      56: aload_0
      57: aconst_null
      58: aload_0
      59: invokevirtual #10                 // Method getRootObject:()Ljava/lang/Object;
      62: checkcast     #11                 // class java/util/Set
      65: aload_3
      66: invokespecial #19                 // Method org/protege/editor/owl/ui/frame/AxiomListFrameSectionRow."<init>":(Lorg/protege/editor/owl/OWLEditorKit;Lorg/protege/editor/owl/ui/frame/OWLFrameSection;Lorg/semanticweb/owlapi/model/OWLOntology;Ljava/util/Set;Lorg/semanticweb/owlapi/model/OWLAxiom;)V
      69: invokevirtual #20                 // Method addRow:(Lorg/protege/editor/owl/ui/frame/OWLFrameSectionRow;)V
      72: goto          15
      75: return

  protected void clear();
    Code:
       0: aload_0
       1: getfield      #9                  // Field added:Ljava/util/Set;
       4: invokeinterface #23,  1           // InterfaceMethod java/util/Set.clear:()V
       9: return

  public java.util.Comparator<org.protege.editor.owl.ui.frame.OWLFrameSectionRow<java.util.Set<org.semanticweb.owlapi.model.OWLAxiom>, org.semanticweb.owlapi.model.OWLAxiom, org.semanticweb.owlapi.model.OWLAxiom>> getRowComparator();
    Code:
       0: aload_0
       1: getfield      #6                  // Field rowComparator:Lorg/protege/editor/owl/ui/frame/AxiomListFrameSection$RowComparator;
       4: areturn

  public boolean canAdd();
    Code:
       0: iconst_0
       1: ireturn

  protected boolean isResettingChange(org.semanticweb.owlapi.model.OWLOntologyChange);
    Code:
       0: aload_1
       1: invokevirtual #24                 // Method org/semanticweb/owlapi/model/OWLOntologyChange.isAxiomChange:()Z
       4: ireturn

  protected org.semanticweb.owlapi.model.OWLAxiom createAxiom(java.lang.Object);
    Code:
       0: aload_0
       1: aload_1
       2: checkcast     #15                 // class org/semanticweb/owlapi/model/OWLAxiom
       5: invokevirtual #25                 // Method createAxiom:(Lorg/semanticweb/owlapi/model/OWLAxiom;)Lorg/semanticweb/owlapi/model/OWLAxiom;
       8: areturn
}
