Compiled from "ImplementationVisitor.java"
final class org.sonatype.guice.bean.locators.ImplementationVisitor extends com.google.inject.spi.DefaultBindingTargetVisitor<java.lang.Object, java.lang.Class<?>> {
  static final org.sonatype.guice.bean.locators.ImplementationVisitor THIS;

  org.sonatype.guice.bean.locators.ImplementationVisitor();
    Code:
       0: aload_0
       1: invokespecial #1                  // Method com/google/inject/spi/DefaultBindingTargetVisitor."<init>":()V
       4: return

  public java.lang.Class<?> visit(com.google.inject.spi.UntargettedBinding<?>);
    Code:
       0: aload_1
       1: invokeinterface #2,  1            // InterfaceMethod com/google/inject/spi/UntargettedBinding.getKey:()Lcom/google/inject/Key;
       6: invokevirtual #3                  // Method com/google/inject/Key.getTypeLiteral:()Lcom/google/inject/TypeLiteral;
       9: invokevirtual #4                  // Method com/google/inject/TypeLiteral.getRawType:()Ljava/lang/Class;
      12: areturn

  public java.lang.Class<?> visit(com.google.inject.spi.LinkedKeyBinding<?>);
    Code:
       0: aload_1
       1: invokeinterface #5,  1            // InterfaceMethod com/google/inject/spi/LinkedKeyBinding.getLinkedKey:()Lcom/google/inject/Key;
       6: invokevirtual #3                  // Method com/google/inject/Key.getTypeLiteral:()Lcom/google/inject/TypeLiteral;
       9: invokevirtual #4                  // Method com/google/inject/TypeLiteral.getRawType:()Ljava/lang/Class;
      12: areturn

  public java.lang.Class<?> visit(com.google.inject.spi.ConstructorBinding<?>);
    Code:
       0: aload_1
       1: invokeinterface #6,  1            // InterfaceMethod com/google/inject/spi/ConstructorBinding.getConstructor:()Lcom/google/inject/spi/InjectionPoint;
       6: invokevirtual #7                  // Method com/google/inject/spi/InjectionPoint.getDeclaringType:()Lcom/google/inject/TypeLiteral;
       9: invokevirtual #4                  // Method com/google/inject/TypeLiteral.getRawType:()Ljava/lang/Class;
      12: areturn

  public java.lang.Class<?> visit(com.google.inject.spi.InstanceBinding<?>);
    Code:
       0: aload_1
       1: invokeinterface #8,  1            // InterfaceMethod com/google/inject/spi/InstanceBinding.getInstance:()Ljava/lang/Object;
       6: invokevirtual #9                  // Method java/lang/Object.getClass:()Ljava/lang/Class;
       9: areturn

  public java.lang.Class<?> visit(com.google.inject.spi.ProviderInstanceBinding<?>);
    Code:
       0: aload_1
       1: invokeinterface #10,  1           // InterfaceMethod com/google/inject/spi/ProviderInstanceBinding.getProviderInstance:()Lcom/google/inject/Provider;
       6: astore_2
       7: aload_2
       8: instanceof    #11                 // class org/sonatype/guice/bean/reflect/DeferredProvider
      11: ifeq          30
      14: aload_2
      15: checkcast     #11                 // class org/sonatype/guice/bean/reflect/DeferredProvider
      18: invokeinterface #12,  1           // InterfaceMethod org/sonatype/guice/bean/reflect/DeferredProvider.getImplementationClass:()Lorg/sonatype/guice/bean/reflect/DeferredClass;
      23: invokeinterface #13,  1           // InterfaceMethod org/sonatype/guice/bean/reflect/DeferredClass.load:()Ljava/lang/Class;
      28: areturn
      29: astore_3
      30: aconst_null
      31: areturn
    Exception table:
       from    to  target type
          14    28    29   Class java/lang/TypeNotPresentException

  public java.lang.Class<?> visit(com.google.inject.spi.ExposedBinding<?>);
    Code:
       0: aload_1
       1: invokeinterface #15,  1           // InterfaceMethod com/google/inject/spi/ExposedBinding.getPrivateElements:()Lcom/google/inject/spi/PrivateElements;
       6: invokeinterface #16,  1           // InterfaceMethod com/google/inject/spi/PrivateElements.getInjector:()Lcom/google/inject/Injector;
      11: aload_1
      12: invokeinterface #17,  1           // InterfaceMethod com/google/inject/spi/ExposedBinding.getKey:()Lcom/google/inject/Key;
      17: invokeinterface #18,  2           // InterfaceMethod com/google/inject/Injector.getBinding:(Lcom/google/inject/Key;)Lcom/google/inject/Binding;
      22: aload_0
      23: invokeinterface #19,  2           // InterfaceMethod com/google/inject/Binding.acceptTargetVisitor:(Lcom/google/inject/spi/BindingTargetVisitor;)Ljava/lang/Object;
      28: checkcast     #20                 // class java/lang/Class
      31: areturn

  public java.lang.Object visit(com.google.inject.spi.ConstructorBinding);
    Code:
       0: aload_0
       1: aload_1
       2: invokevirtual #21                 // Method visit:(Lcom/google/inject/spi/ConstructorBinding;)Ljava/lang/Class;
       5: areturn

  public java.lang.Object visit(com.google.inject.spi.UntargettedBinding);
    Code:
       0: aload_0
       1: aload_1
       2: invokevirtual #22                 // Method visit:(Lcom/google/inject/spi/UntargettedBinding;)Ljava/lang/Class;
       5: areturn

  public java.lang.Object visit(com.google.inject.spi.ExposedBinding);
    Code:
       0: aload_0
       1: aload_1
       2: invokevirtual #23                 // Method visit:(Lcom/google/inject/spi/ExposedBinding;)Ljava/lang/Class;
       5: areturn

  public java.lang.Object visit(com.google.inject.spi.LinkedKeyBinding);
    Code:
       0: aload_0
       1: aload_1
       2: invokevirtual #24                 // Method visit:(Lcom/google/inject/spi/LinkedKeyBinding;)Ljava/lang/Class;
       5: areturn

  public java.lang.Object visit(com.google.inject.spi.ProviderInstanceBinding);
    Code:
       0: aload_0
       1: aload_1
       2: invokevirtual #25                 // Method visit:(Lcom/google/inject/spi/ProviderInstanceBinding;)Ljava/lang/Class;
       5: areturn

  public java.lang.Object visit(com.google.inject.spi.InstanceBinding);
    Code:
       0: aload_0
       1: aload_1
       2: invokevirtual #26                 // Method visit:(Lcom/google/inject/spi/InstanceBinding;)Ljava/lang/Class;
       5: areturn

  static {};
    Code:
       0: new           #27                 // class org/sonatype/guice/bean/locators/ImplementationVisitor
       3: dup
       4: invokespecial #28                 // Method "<init>":()V
       7: putstatic     #29                 // Field THIS:Lorg/sonatype/guice/bean/locators/ImplementationVisitor;
      10: return
}
