Compiled from "QuartzAutoConfiguration.java"
public class org.springframework.boot.autoconfigure.quartz.QuartzAutoConfiguration$JdbcStoreTypeConfiguration {
  protected org.springframework.boot.autoconfigure.quartz.QuartzAutoConfiguration$JdbcStoreTypeConfiguration();
    Code:
       0: aload_0
       1: invokespecial #1                  // Method java/lang/Object."<init>":()V
       4: return

  public org.springframework.boot.autoconfigure.quartz.SchedulerFactoryBeanCustomizer dataSourceCustomizer(org.springframework.boot.autoconfigure.quartz.QuartzProperties, javax.sql.DataSource, org.springframework.beans.factory.ObjectProvider<javax.sql.DataSource>, org.springframework.beans.factory.ObjectProvider<org.springframework.transaction.PlatformTransactionManager>);
    Code:
       0: aload_0
       1: aload_1
       2: aload_2
       3: aload_3
       4: aload         4
       6: invokedynamic #2,  0              // InvokeDynamic #0:customize:(Lorg/springframework/boot/autoconfigure/quartz/QuartzAutoConfiguration$JdbcStoreTypeConfiguration;Lorg/springframework/boot/autoconfigure/quartz/QuartzProperties;Ljavax/sql/DataSource;Lorg/springframework/beans/factory/ObjectProvider;Lorg/springframework/beans/factory/ObjectProvider;)Lorg/springframework/boot/autoconfigure/quartz/SchedulerFactoryBeanCustomizer;
      11: areturn

  private javax.sql.DataSource getDataSource(javax.sql.DataSource, org.springframework.beans.factory.ObjectProvider<javax.sql.DataSource>);
    Code:
       0: aload_2
       1: invokeinterface #3,  1            // InterfaceMethod org/springframework/beans/factory/ObjectProvider.getIfAvailable:()Ljava/lang/Object;
       6: checkcast     #4                  // class javax/sql/DataSource
       9: astore_3
      10: aload_3
      11: ifnull        18
      14: aload_3
      15: goto          19
      18: aload_1
      19: areturn

  public org.springframework.boot.autoconfigure.quartz.QuartzDataSourceInitializer quartzDataSourceInitializer(javax.sql.DataSource, org.springframework.beans.factory.ObjectProvider<javax.sql.DataSource>, org.springframework.core.io.ResourceLoader, org.springframework.boot.autoconfigure.quartz.QuartzProperties);
    Code:
       0: aload_0
       1: aload_1
       2: aload_2
       3: invokespecial #5                  // Method getDataSource:(Ljavax/sql/DataSource;Lorg/springframework/beans/factory/ObjectProvider;)Ljavax/sql/DataSource;
       6: astore        5
       8: new           #6                  // class org/springframework/boot/autoconfigure/quartz/QuartzDataSourceInitializer
      11: dup
      12: aload         5
      14: aload_3
      15: aload         4
      17: invokespecial #7                  // Method org/springframework/boot/autoconfigure/quartz/QuartzDataSourceInitializer."<init>":(Ljavax/sql/DataSource;Lorg/springframework/core/io/ResourceLoader;Lorg/springframework/boot/autoconfigure/quartz/QuartzProperties;)V
      20: areturn

  public static org.springframework.boot.autoconfigure.quartz.QuartzAutoConfiguration$JdbcStoreTypeConfiguration$DataSourceInitializerSchedulerDependencyPostProcessor dataSourceInitializerSchedulerDependencyPostProcessor();
    Code:
       0: new           #8                  // class org/springframework/boot/autoconfigure/quartz/QuartzAutoConfiguration$JdbcStoreTypeConfiguration$DataSourceInitializerSchedulerDependencyPostProcessor
       3: dup
       4: invokespecial #9                  // Method org/springframework/boot/autoconfigure/quartz/QuartzAutoConfiguration$JdbcStoreTypeConfiguration$DataSourceInitializerSchedulerDependencyPostProcessor."<init>":()V
       7: areturn

  private void lambda$dataSourceCustomizer$0(org.springframework.boot.autoconfigure.quartz.QuartzProperties, javax.sql.DataSource, org.springframework.beans.factory.ObjectProvider, org.springframework.beans.factory.ObjectProvider, org.springframework.scheduling.quartz.SchedulerFactoryBean);
    Code:
       0: aload_1
       1: invokevirtual #10                 // Method org/springframework/boot/autoconfigure/quartz/QuartzProperties.getJobStoreType:()Lorg/springframework/boot/autoconfigure/quartz/JobStoreType;
       4: getstatic     #11                 // Field org/springframework/boot/autoconfigure/quartz/JobStoreType.JDBC:Lorg/springframework/boot/autoconfigure/quartz/JobStoreType;
       7: if_acmpne     49
      10: aload_0
      11: aload_2
      12: aload_3
      13: invokespecial #5                  // Method getDataSource:(Ljavax/sql/DataSource;Lorg/springframework/beans/factory/ObjectProvider;)Ljavax/sql/DataSource;
      16: astore        6
      18: aload         5
      20: aload         6
      22: invokevirtual #12                 // Method org/springframework/scheduling/quartz/SchedulerFactoryBean.setDataSource:(Ljavax/sql/DataSource;)V
      25: aload         4
      27: invokeinterface #13,  1           // InterfaceMethod org/springframework/beans/factory/ObjectProvider.getIfUnique:()Ljava/lang/Object;
      32: checkcast     #14                 // class org/springframework/transaction/PlatformTransactionManager
      35: astore        7
      37: aload         7
      39: ifnull        49
      42: aload         5
      44: aload         7
      46: invokevirtual #15                 // Method org/springframework/scheduling/quartz/SchedulerFactoryBean.setTransactionManager:(Lorg/springframework/transaction/PlatformTransactionManager;)V
      49: return
}
