Compiled from "BodyEvent.java"
public class ch.qos.logback.core.joran.event.BodyEvent extends ch.qos.logback.core.joran.event.SaxEvent {
  private java.lang.String text;

  ch.qos.logback.core.joran.event.BodyEvent(java.lang.String, org.xml.sax.Locator);
    Code:
       0: aload_0
       1: aconst_null
       2: aconst_null
       3: aconst_null
       4: aload_2
       5: invokespecial #1                  // Method ch/qos/logback/core/joran/event/SaxEvent."<init>":(Ljava/lang/String;Ljava/lang/String;Ljava/lang/String;Lorg/xml/sax/Locator;)V
       8: aload_0
       9: aload_1
      10: putfield      #2                  // Field text:Ljava/lang/String;
      13: return

  public java.lang.String getText();
    Code:
       0: aload_0
       1: getfield      #2                  // Field text:Ljava/lang/String;
       4: ifnull        15
       7: aload_0
       8: getfield      #2                  // Field text:Ljava/lang/String;
      11: invokevirtual #3                  // Method java/lang/String.trim:()Ljava/lang/String;
      14: areturn
      15: aload_0
      16: getfield      #2                  // Field text:Ljava/lang/String;
      19: areturn

  public java.lang.String toString();
    Code:
       0: new           #4                  // class java/lang/StringBuilder
       3: dup
       4: invokespecial #5                  // Method java/lang/StringBuilder."<init>":()V
       7: ldc           #6                  // String BodyEvent(
       9: invokevirtual #7                  // Method java/lang/StringBuilder.append:(Ljava/lang/String;)Ljava/lang/StringBuilder;
      12: aload_0
      13: invokevirtual #8                  // Method getText:()Ljava/lang/String;
      16: invokevirtual #7                  // Method java/lang/StringBuilder.append:(Ljava/lang/String;)Ljava/lang/StringBuilder;
      19: ldc           #9                  // String )
      21: invokevirtual #7                  // Method java/lang/StringBuilder.append:(Ljava/lang/String;)Ljava/lang/StringBuilder;
      24: aload_0
      25: getfield      #10                 // Field locator:Lorg/xml/sax/Locator;
      28: invokeinterface #11,  1           // InterfaceMethod org/xml/sax/Locator.getLineNumber:()I
      33: invokevirtual #12                 // Method java/lang/StringBuilder.append:(I)Ljava/lang/StringBuilder;
      36: ldc           #13                 // String ,
      38: invokevirtual #7                  // Method java/lang/StringBuilder.append:(Ljava/lang/String;)Ljava/lang/StringBuilder;
      41: aload_0
      42: getfield      #10                 // Field locator:Lorg/xml/sax/Locator;
      45: invokeinterface #14,  1           // InterfaceMethod org/xml/sax/Locator.getColumnNumber:()I
      50: invokevirtual #12                 // Method java/lang/StringBuilder.append:(I)Ljava/lang/StringBuilder;
      53: invokevirtual #15                 // Method java/lang/StringBuilder.toString:()Ljava/lang/String;
      56: areturn

  public void append(java.lang.String);
    Code:
       0: new           #4                  // class java/lang/StringBuilder
       3: dup
       4: invokespecial #5                  // Method java/lang/StringBuilder."<init>":()V
       7: aload_0
       8: dup_x1
       9: getfield      #2                  // Field text:Ljava/lang/String;
      12: invokevirtual #7                  // Method java/lang/StringBuilder.append:(Ljava/lang/String;)Ljava/lang/StringBuilder;
      15: aload_1
      16: invokevirtual #7                  // Method java/lang/StringBuilder.append:(Ljava/lang/String;)Ljava/lang/StringBuilder;
      19: invokevirtual #15                 // Method java/lang/StringBuilder.toString:()Ljava/lang/String;
      22: putfield      #2                  // Field text:Ljava/lang/String;
      25: return
}
