Compiled from "TestManifest.java"
public class org.apache.jena.sparql.vocabulary.TestManifest {
  private static org.apache.jena.rdf.model.Model m_model;

  public static final java.lang.String NS;

  public static final org.apache.jena.rdf.model.Resource NAMESPACE;

  public static final org.apache.jena.rdf.model.Property notable;

  public static final org.apache.jena.rdf.model.Property requires;

  public static final org.apache.jena.rdf.model.Property result;

  public static final org.apache.jena.rdf.model.Property action;

  public static final org.apache.jena.rdf.model.Property name;

  public static final org.apache.jena.rdf.model.Property entries;

  public static final org.apache.jena.rdf.model.Property include;

  public static final org.apache.jena.rdf.model.Resource Notable;

  public static final org.apache.jena.rdf.model.Resource Requirement;

  public static final org.apache.jena.rdf.model.Resource TestStatus;

  public static final org.apache.jena.rdf.model.Resource ReducedCardinalityTest;

  public static final org.apache.jena.rdf.model.Resource QueryEvaluationTest;

  public static final org.apache.jena.rdf.model.Resource NegativeSyntaxTest;

  public static final org.apache.jena.rdf.model.Resource PositiveSyntaxTest;

  public static final org.apache.jena.rdf.model.Resource ManifestEntry;

  public static final org.apache.jena.rdf.model.Resource Manifest;

  public static final org.apache.jena.rdf.model.Resource accepted;

  public static final org.apache.jena.rdf.model.Resource XsdDateOperations;

  public static final org.apache.jena.rdf.model.Resource proposed;

  public static final org.apache.jena.rdf.model.Resource LangTagAwareness;

  public static final org.apache.jena.rdf.model.Resource rejected;

  public static final org.apache.jena.rdf.model.Resource KnownTypesDefault2Neq;

  public static final org.apache.jena.rdf.model.Resource StringSimpleLiteralCmp;

  public static final org.apache.jena.rdf.model.Resource IllFormedLiterals;

  public org.apache.jena.sparql.vocabulary.TestManifest();
    Code:
       0: aload_0
       1: invokespecial #1                  // Method java/lang/Object."<init>":()V
       4: return

  public static java.lang.String getURI();
    Code:
       0: ldc           #3                  // String http://www.w3.org/2001/sw/DataAccess/tests/test-manifest#
       2: areturn

  static {};
    Code:
       0: invokestatic  #4                  // Method org/apache/jena/rdf/model/ModelFactory.createDefaultModel:()Lorg/apache/jena/rdf/model/Model;
       3: putstatic     #5                  // Field m_model:Lorg/apache/jena/rdf/model/Model;
       6: getstatic     #5                  // Field m_model:Lorg/apache/jena/rdf/model/Model;
       9: ldc           #3                  // String http://www.w3.org/2001/sw/DataAccess/tests/test-manifest#
      11: invokeinterface #6,  2            // InterfaceMethod org/apache/jena/rdf/model/Model.createResource:(Ljava/lang/String;)Lorg/apache/jena/rdf/model/Resource;
      16: putstatic     #7                  // Field NAMESPACE:Lorg/apache/jena/rdf/model/Resource;
      19: getstatic     #5                  // Field m_model:Lorg/apache/jena/rdf/model/Model;
      22: ldc           #8                  // String http://www.w3.org/2001/sw/DataAccess/tests/test-manifest#notable
      24: invokeinterface #9,  2            // InterfaceMethod org/apache/jena/rdf/model/Model.createProperty:(Ljava/lang/String;)Lorg/apache/jena/rdf/model/Property;
      29: putstatic     #10                 // Field notable:Lorg/apache/jena/rdf/model/Property;
      32: getstatic     #5                  // Field m_model:Lorg/apache/jena/rdf/model/Model;
      35: ldc           #11                 // String http://www.w3.org/2001/sw/DataAccess/tests/test-manifest#requires
      37: invokeinterface #9,  2            // InterfaceMethod org/apache/jena/rdf/model/Model.createProperty:(Ljava/lang/String;)Lorg/apache/jena/rdf/model/Property;
      42: putstatic     #12                 // Field requires:Lorg/apache/jena/rdf/model/Property;
      45: getstatic     #5                  // Field m_model:Lorg/apache/jena/rdf/model/Model;
      48: ldc           #13                 // String http://www.w3.org/2001/sw/DataAccess/tests/test-manifest#result
      50: invokeinterface #9,  2            // InterfaceMethod org/apache/jena/rdf/model/Model.createProperty:(Ljava/lang/String;)Lorg/apache/jena/rdf/model/Property;
      55: putstatic     #14                 // Field result:Lorg/apache/jena/rdf/model/Property;
      58: getstatic     #5                  // Field m_model:Lorg/apache/jena/rdf/model/Model;
      61: ldc           #15                 // String http://www.w3.org/2001/sw/DataAccess/tests/test-manifest#action
      63: invokeinterface #9,  2            // InterfaceMethod org/apache/jena/rdf/model/Model.createProperty:(Ljava/lang/String;)Lorg/apache/jena/rdf/model/Property;
      68: putstatic     #16                 // Field action:Lorg/apache/jena/rdf/model/Property;
      71: getstatic     #5                  // Field m_model:Lorg/apache/jena/rdf/model/Model;
      74: ldc           #17                 // String http://www.w3.org/2001/sw/DataAccess/tests/test-manifest#name
      76: invokeinterface #9,  2            // InterfaceMethod org/apache/jena/rdf/model/Model.createProperty:(Ljava/lang/String;)Lorg/apache/jena/rdf/model/Property;
      81: putstatic     #18                 // Field name:Lorg/apache/jena/rdf/model/Property;
      84: getstatic     #5                  // Field m_model:Lorg/apache/jena/rdf/model/Model;
      87: ldc           #19                 // String http://www.w3.org/2001/sw/DataAccess/tests/test-manifest#entries
      89: invokeinterface #9,  2            // InterfaceMethod org/apache/jena/rdf/model/Model.createProperty:(Ljava/lang/String;)Lorg/apache/jena/rdf/model/Property;
      94: putstatic     #20                 // Field entries:Lorg/apache/jena/rdf/model/Property;
      97: getstatic     #5                  // Field m_model:Lorg/apache/jena/rdf/model/Model;
     100: ldc           #21                 // String http://www.w3.org/2001/sw/DataAccess/tests/test-manifest#include
     102: invokeinterface #9,  2            // InterfaceMethod org/apache/jena/rdf/model/Model.createProperty:(Ljava/lang/String;)Lorg/apache/jena/rdf/model/Property;
     107: putstatic     #22                 // Field include:Lorg/apache/jena/rdf/model/Property;
     110: getstatic     #5                  // Field m_model:Lorg/apache/jena/rdf/model/Model;
     113: ldc           #23                 // String http://www.w3.org/2001/sw/DataAccess/tests/test-manifest#Notable
     115: invokeinterface #6,  2            // InterfaceMethod org/apache/jena/rdf/model/Model.createResource:(Ljava/lang/String;)Lorg/apache/jena/rdf/model/Resource;
     120: putstatic     #24                 // Field Notable:Lorg/apache/jena/rdf/model/Resource;
     123: getstatic     #5                  // Field m_model:Lorg/apache/jena/rdf/model/Model;
     126: ldc           #25                 // String http://www.w3.org/2001/sw/DataAccess/tests/test-manifest#Requirement
     128: invokeinterface #6,  2            // InterfaceMethod org/apache/jena/rdf/model/Model.createResource:(Ljava/lang/String;)Lorg/apache/jena/rdf/model/Resource;
     133: putstatic     #26                 // Field Requirement:Lorg/apache/jena/rdf/model/Resource;
     136: getstatic     #5                  // Field m_model:Lorg/apache/jena/rdf/model/Model;
     139: ldc           #27                 // String http://www.w3.org/2001/sw/DataAccess/tests/test-manifest#TestStatus
     141: invokeinterface #6,  2            // InterfaceMethod org/apache/jena/rdf/model/Model.createResource:(Ljava/lang/String;)Lorg/apache/jena/rdf/model/Resource;
     146: putstatic     #28                 // Field TestStatus:Lorg/apache/jena/rdf/model/Resource;
     149: getstatic     #5                  // Field m_model:Lorg/apache/jena/rdf/model/Model;
     152: ldc           #29                 // String http://www.w3.org/2001/sw/DataAccess/tests/test-manifest#ReducedCardinalityTest
     154: invokeinterface #6,  2            // InterfaceMethod org/apache/jena/rdf/model/Model.createResource:(Ljava/lang/String;)Lorg/apache/jena/rdf/model/Resource;
     159: putstatic     #30                 // Field ReducedCardinalityTest:Lorg/apache/jena/rdf/model/Resource;
     162: getstatic     #5                  // Field m_model:Lorg/apache/jena/rdf/model/Model;
     165: ldc           #31                 // String http://www.w3.org/2001/sw/DataAccess/tests/test-manifest#QueryEvaluationTest
     167: invokeinterface #6,  2            // InterfaceMethod org/apache/jena/rdf/model/Model.createResource:(Ljava/lang/String;)Lorg/apache/jena/rdf/model/Resource;
     172: putstatic     #32                 // Field QueryEvaluationTest:Lorg/apache/jena/rdf/model/Resource;
     175: getstatic     #5                  // Field m_model:Lorg/apache/jena/rdf/model/Model;
     178: ldc           #33                 // String http://www.w3.org/2001/sw/DataAccess/tests/test-manifest#NegativeSyntaxTest
     180: invokeinterface #6,  2            // InterfaceMethod org/apache/jena/rdf/model/Model.createResource:(Ljava/lang/String;)Lorg/apache/jena/rdf/model/Resource;
     185: putstatic     #34                 // Field NegativeSyntaxTest:Lorg/apache/jena/rdf/model/Resource;
     188: getstatic     #5                  // Field m_model:Lorg/apache/jena/rdf/model/Model;
     191: ldc           #35                 // String http://www.w3.org/2001/sw/DataAccess/tests/test-manifest#PositiveSyntaxTest
     193: invokeinterface #6,  2            // InterfaceMethod org/apache/jena/rdf/model/Model.createResource:(Ljava/lang/String;)Lorg/apache/jena/rdf/model/Resource;
     198: putstatic     #36                 // Field PositiveSyntaxTest:Lorg/apache/jena/rdf/model/Resource;
     201: getstatic     #5                  // Field m_model:Lorg/apache/jena/rdf/model/Model;
     204: ldc           #37                 // String http://www.w3.org/2001/sw/DataAccess/tests/test-manifest#ManifestEntry
     206: invokeinterface #6,  2            // InterfaceMethod org/apache/jena/rdf/model/Model.createResource:(Ljava/lang/String;)Lorg/apache/jena/rdf/model/Resource;
     211: putstatic     #38                 // Field ManifestEntry:Lorg/apache/jena/rdf/model/Resource;
     214: getstatic     #5                  // Field m_model:Lorg/apache/jena/rdf/model/Model;
     217: ldc           #39                 // String http://www.w3.org/2001/sw/DataAccess/tests/test-manifest#Manifest
     219: invokeinterface #6,  2            // InterfaceMethod org/apache/jena/rdf/model/Model.createResource:(Ljava/lang/String;)Lorg/apache/jena/rdf/model/Resource;
     224: putstatic     #40                 // Field Manifest:Lorg/apache/jena/rdf/model/Resource;
     227: getstatic     #5                  // Field m_model:Lorg/apache/jena/rdf/model/Model;
     230: ldc           #41                 // String http://www.w3.org/2001/sw/DataAccess/tests/test-manifest#accepted
     232: invokeinterface #6,  2            // InterfaceMethod org/apache/jena/rdf/model/Model.createResource:(Ljava/lang/String;)Lorg/apache/jena/rdf/model/Resource;
     237: putstatic     #42                 // Field accepted:Lorg/apache/jena/rdf/model/Resource;
     240: getstatic     #5                  // Field m_model:Lorg/apache/jena/rdf/model/Model;
     243: ldc           #43                 // String http://www.w3.org/2001/sw/DataAccess/tests/test-manifest#XsdDateOperations
     245: invokeinterface #6,  2            // InterfaceMethod org/apache/jena/rdf/model/Model.createResource:(Ljava/lang/String;)Lorg/apache/jena/rdf/model/Resource;
     250: putstatic     #44                 // Field XsdDateOperations:Lorg/apache/jena/rdf/model/Resource;
     253: getstatic     #5                  // Field m_model:Lorg/apache/jena/rdf/model/Model;
     256: ldc           #45                 // String http://www.w3.org/2001/sw/DataAccess/tests/test-manifest#proposed
     258: invokeinterface #6,  2            // InterfaceMethod org/apache/jena/rdf/model/Model.createResource:(Ljava/lang/String;)Lorg/apache/jena/rdf/model/Resource;
     263: putstatic     #46                 // Field proposed:Lorg/apache/jena/rdf/model/Resource;
     266: getstatic     #5                  // Field m_model:Lorg/apache/jena/rdf/model/Model;
     269: ldc           #47                 // String http://www.w3.org/2001/sw/DataAccess/tests/test-manifest#LangTagAwareness
     271: invokeinterface #6,  2            // InterfaceMethod org/apache/jena/rdf/model/Model.createResource:(Ljava/lang/String;)Lorg/apache/jena/rdf/model/Resource;
     276: putstatic     #48                 // Field LangTagAwareness:Lorg/apache/jena/rdf/model/Resource;
     279: getstatic     #5                  // Field m_model:Lorg/apache/jena/rdf/model/Model;
     282: ldc           #49                 // String http://www.w3.org/2001/sw/DataAccess/tests/test-manifest#rejected
     284: invokeinterface #6,  2            // InterfaceMethod org/apache/jena/rdf/model/Model.createResource:(Ljava/lang/String;)Lorg/apache/jena/rdf/model/Resource;
     289: putstatic     #50                 // Field rejected:Lorg/apache/jena/rdf/model/Resource;
     292: getstatic     #5                  // Field m_model:Lorg/apache/jena/rdf/model/Model;
     295: ldc           #51                 // String http://www.w3.org/2001/sw/DataAccess/tests/test-manifest#KnownTypesDefault2Neq
     297: invokeinterface #6,  2            // InterfaceMethod org/apache/jena/rdf/model/Model.createResource:(Ljava/lang/String;)Lorg/apache/jena/rdf/model/Resource;
     302: putstatic     #52                 // Field KnownTypesDefault2Neq:Lorg/apache/jena/rdf/model/Resource;
     305: getstatic     #5                  // Field m_model:Lorg/apache/jena/rdf/model/Model;
     308: ldc           #53                 // String http://www.w3.org/2001/sw/DataAccess/tests/test-manifest#StringSimpleLiteralCmp
     310: invokeinterface #6,  2            // InterfaceMethod org/apache/jena/rdf/model/Model.createResource:(Ljava/lang/String;)Lorg/apache/jena/rdf/model/Resource;
     315: putstatic     #54                 // Field StringSimpleLiteralCmp:Lorg/apache/jena/rdf/model/Resource;
     318: getstatic     #5                  // Field m_model:Lorg/apache/jena/rdf/model/Model;
     321: ldc           #55                 // String http://www.w3.org/2001/sw/DataAccess/tests/test-manifest#IllFormedLiterals
     323: invokeinterface #6,  2            // InterfaceMethod org/apache/jena/rdf/model/Model.createResource:(Ljava/lang/String;)Lorg/apache/jena/rdf/model/Resource;
     328: putstatic     #56                 // Field IllFormedLiterals:Lorg/apache/jena/rdf/model/Resource;
     331: return
}
