Compiled from "RSAKey.java"
public class com.nimbusds.jose.jwk.RSAKey$OtherPrimesInfo implements java.io.Serializable {
  private static final long serialVersionUID;

  private final com.nimbusds.jose.util.Base64URL r;

  private final com.nimbusds.jose.util.Base64URL d;

  private final com.nimbusds.jose.util.Base64URL t;

  public com.nimbusds.jose.jwk.RSAKey$OtherPrimesInfo(com.nimbusds.jose.util.Base64URL, com.nimbusds.jose.util.Base64URL, com.nimbusds.jose.util.Base64URL);
    Code:
       0: aload_0
       1: invokespecial #24                 // Method java/lang/Object."<init>":()V
       4: aload_1
       5: ifnonnull     18
       8: new           #26                 // class java/lang/IllegalArgumentException
      11: dup
      12: ldc           #28                 // String The prime factor must not be null
      14: invokespecial #31                 // Method java/lang/IllegalArgumentException."<init>":(Ljava/lang/String;)V
      17: athrow
      18: aload_0
      19: aload_1
      20: putfield      #35                 // Field r:Lcom/nimbusds/jose/util/Base64URL;
      23: aload_2
      24: ifnonnull     37
      27: new           #26                 // class java/lang/IllegalArgumentException
      30: dup
      31: ldc           #37                 // String The factor CRT exponent must not be null
      33: invokespecial #31                 // Method java/lang/IllegalArgumentException."<init>":(Ljava/lang/String;)V
      36: athrow
      37: aload_0
      38: aload_2
      39: putfield      #39                 // Field d:Lcom/nimbusds/jose/util/Base64URL;
      42: aload_3
      43: ifnonnull     56
      46: new           #26                 // class java/lang/IllegalArgumentException
      49: dup
      50: ldc           #41                 // String The factor CRT coefficient must not be null
      52: invokespecial #31                 // Method java/lang/IllegalArgumentException."<init>":(Ljava/lang/String;)V
      55: athrow
      56: aload_0
      57: aload_3
      58: putfield      #43                 // Field t:Lcom/nimbusds/jose/util/Base64URL;
      61: return

  public com.nimbusds.jose.jwk.RSAKey$OtherPrimesInfo(java.security.spec.RSAOtherPrimeInfo);
    Code:
       0: aload_0
       1: invokespecial #24                 // Method java/lang/Object."<init>":()V
       4: aload_0
       5: aload_1
       6: invokevirtual #52                 // Method java/security/spec/RSAOtherPrimeInfo.getPrime:()Ljava/math/BigInteger;
       9: invokestatic  #56                 // Method com/nimbusds/jose/util/Base64URL.encode:(Ljava/math/BigInteger;)Lcom/nimbusds/jose/util/Base64URL;
      12: putfield      #35                 // Field r:Lcom/nimbusds/jose/util/Base64URL;
      15: aload_0
      16: aload_1
      17: invokevirtual #59                 // Method java/security/spec/RSAOtherPrimeInfo.getExponent:()Ljava/math/BigInteger;
      20: invokestatic  #56                 // Method com/nimbusds/jose/util/Base64URL.encode:(Ljava/math/BigInteger;)Lcom/nimbusds/jose/util/Base64URL;
      23: putfield      #39                 // Field d:Lcom/nimbusds/jose/util/Base64URL;
      26: aload_0
      27: aload_1
      28: invokevirtual #62                 // Method java/security/spec/RSAOtherPrimeInfo.getCrtCoefficient:()Ljava/math/BigInteger;
      31: invokestatic  #56                 // Method com/nimbusds/jose/util/Base64URL.encode:(Ljava/math/BigInteger;)Lcom/nimbusds/jose/util/Base64URL;
      34: putfield      #43                 // Field t:Lcom/nimbusds/jose/util/Base64URL;
      37: return

  public com.nimbusds.jose.util.Base64URL getPrimeFactor();
    Code:
       0: aload_0
       1: getfield      #35                 // Field r:Lcom/nimbusds/jose/util/Base64URL;
       4: areturn

  public com.nimbusds.jose.util.Base64URL getFactorCRTExponent();
    Code:
       0: aload_0
       1: getfield      #39                 // Field d:Lcom/nimbusds/jose/util/Base64URL;
       4: areturn

  public com.nimbusds.jose.util.Base64URL getFactorCRTCoefficient();
    Code:
       0: aload_0
       1: getfield      #43                 // Field t:Lcom/nimbusds/jose/util/Base64URL;
       4: areturn

  public static java.util.List<com.nimbusds.jose.jwk.RSAKey$OtherPrimesInfo> toList(java.security.spec.RSAOtherPrimeInfo[]);
    Code:
       0: new           #73                 // class java/util/ArrayList
       3: dup
       4: invokespecial #74                 // Method java/util/ArrayList."<init>":()V
       7: astore_1
       8: aload_0
       9: ifnonnull     14
      12: aload_1
      13: areturn
      14: aload_0
      15: astore_2
      16: aload_2
      17: arraylength
      18: istore_3
      19: iconst_0
      20: istore        4
      22: iload         4
      24: iload_3
      25: if_icmpge     56
      28: aload_2
      29: iload         4
      31: aaload
      32: astore        5
      34: aload_1
      35: new           #2                  // class com/nimbusds/jose/jwk/RSAKey$OtherPrimesInfo
      38: dup
      39: aload         5
      41: invokespecial #80                 // Method "<init>":(Ljava/security/spec/RSAOtherPrimeInfo;)V
      44: invokeinterface #84,  2           // InterfaceMethod java/util/List.add:(Ljava/lang/Object;)Z
      49: pop
      50: iinc          4, 1
      53: goto          22
      56: aload_1
      57: areturn

  static com.nimbusds.jose.util.Base64URL access$1000(com.nimbusds.jose.jwk.RSAKey$OtherPrimesInfo);
    Code:
       0: aload_0
       1: getfield      #35                 // Field r:Lcom/nimbusds/jose/util/Base64URL;
       4: areturn

  static com.nimbusds.jose.util.Base64URL access$1100(com.nimbusds.jose.jwk.RSAKey$OtherPrimesInfo);
    Code:
       0: aload_0
       1: getfield      #39                 // Field d:Lcom/nimbusds/jose/util/Base64URL;
       4: areturn

  static com.nimbusds.jose.util.Base64URL access$1200(com.nimbusds.jose.jwk.RSAKey$OtherPrimesInfo);
    Code:
       0: aload_0
       1: getfield      #43                 // Field t:Lcom/nimbusds/jose/util/Base64URL;
       4: areturn
}
