Compiled from "StompCommand.java"
public final class io.netty.handler.codec.stomp.StompCommand extends java.lang.Enum<io.netty.handler.codec.stomp.StompCommand> {
  public static final io.netty.handler.codec.stomp.StompCommand STOMP;

  public static final io.netty.handler.codec.stomp.StompCommand CONNECT;

  public static final io.netty.handler.codec.stomp.StompCommand CONNECTED;

  public static final io.netty.handler.codec.stomp.StompCommand SEND;

  public static final io.netty.handler.codec.stomp.StompCommand SUBSCRIBE;

  public static final io.netty.handler.codec.stomp.StompCommand UNSUBSCRIBE;

  public static final io.netty.handler.codec.stomp.StompCommand ACK;

  public static final io.netty.handler.codec.stomp.StompCommand NACK;

  public static final io.netty.handler.codec.stomp.StompCommand BEGIN;

  public static final io.netty.handler.codec.stomp.StompCommand DISCONNECT;

  public static final io.netty.handler.codec.stomp.StompCommand MESSAGE;

  public static final io.netty.handler.codec.stomp.StompCommand RECEIPT;

  public static final io.netty.handler.codec.stomp.StompCommand ERROR;

  public static final io.netty.handler.codec.stomp.StompCommand UNKNOWN;

  private static final io.netty.handler.codec.stomp.StompCommand[] $VALUES;

  public static io.netty.handler.codec.stomp.StompCommand[] values();
    Code:
       0: getstatic     #1                  // Field $VALUES:[Lio/netty/handler/codec/stomp/StompCommand;
       3: invokevirtual #2                  // Method "[Lio/netty/handler/codec/stomp/StompCommand;".clone:()Ljava/lang/Object;
       6: checkcast     #3                  // class "[Lio/netty/handler/codec/stomp/StompCommand;"
       9: areturn

  public static io.netty.handler.codec.stomp.StompCommand valueOf(java.lang.String);
    Code:
       0: ldc           #4                  // class io/netty/handler/codec/stomp/StompCommand
       2: aload_0
       3: invokestatic  #5                  // Method java/lang/Enum.valueOf:(Ljava/lang/Class;Ljava/lang/String;)Ljava/lang/Enum;
       6: checkcast     #4                  // class io/netty/handler/codec/stomp/StompCommand
       9: areturn

  private io.netty.handler.codec.stomp.StompCommand();
    Code:
       0: aload_0
       1: aload_1
       2: iload_2
       3: invokespecial #6                  // Method java/lang/Enum."<init>":(Ljava/lang/String;I)V
       6: return

  static {};
    Code:
       0: new           #4                  // class io/netty/handler/codec/stomp/StompCommand
       3: dup
       4: ldc           #7                  // String STOMP
       6: iconst_0
       7: invokespecial #8                  // Method "<init>":(Ljava/lang/String;I)V
      10: putstatic     #9                  // Field STOMP:Lio/netty/handler/codec/stomp/StompCommand;
      13: new           #4                  // class io/netty/handler/codec/stomp/StompCommand
      16: dup
      17: ldc           #10                 // String CONNECT
      19: iconst_1
      20: invokespecial #8                  // Method "<init>":(Ljava/lang/String;I)V
      23: putstatic     #11                 // Field CONNECT:Lio/netty/handler/codec/stomp/StompCommand;
      26: new           #4                  // class io/netty/handler/codec/stomp/StompCommand
      29: dup
      30: ldc           #12                 // String CONNECTED
      32: iconst_2
      33: invokespecial #8                  // Method "<init>":(Ljava/lang/String;I)V
      36: putstatic     #13                 // Field CONNECTED:Lio/netty/handler/codec/stomp/StompCommand;
      39: new           #4                  // class io/netty/handler/codec/stomp/StompCommand
      42: dup
      43: ldc           #14                 // String SEND
      45: iconst_3
      46: invokespecial #8                  // Method "<init>":(Ljava/lang/String;I)V
      49: putstatic     #15                 // Field SEND:Lio/netty/handler/codec/stomp/StompCommand;
      52: new           #4                  // class io/netty/handler/codec/stomp/StompCommand
      55: dup
      56: ldc           #16                 // String SUBSCRIBE
      58: iconst_4
      59: invokespecial #8                  // Method "<init>":(Ljava/lang/String;I)V
      62: putstatic     #17                 // Field SUBSCRIBE:Lio/netty/handler/codec/stomp/StompCommand;
      65: new           #4                  // class io/netty/handler/codec/stomp/StompCommand
      68: dup
      69: ldc           #18                 // String UNSUBSCRIBE
      71: iconst_5
      72: invokespecial #8                  // Method "<init>":(Ljava/lang/String;I)V
      75: putstatic     #19                 // Field UNSUBSCRIBE:Lio/netty/handler/codec/stomp/StompCommand;
      78: new           #4                  // class io/netty/handler/codec/stomp/StompCommand
      81: dup
      82: ldc           #20                 // String ACK
      84: bipush        6
      86: invokespecial #8                  // Method "<init>":(Ljava/lang/String;I)V
      89: putstatic     #21                 // Field ACK:Lio/netty/handler/codec/stomp/StompCommand;
      92: new           #4                  // class io/netty/handler/codec/stomp/StompCommand
      95: dup
      96: ldc           #22                 // String NACK
      98: bipush        7
     100: invokespecial #8                  // Method "<init>":(Ljava/lang/String;I)V
     103: putstatic     #23                 // Field NACK:Lio/netty/handler/codec/stomp/StompCommand;
     106: new           #4                  // class io/netty/handler/codec/stomp/StompCommand
     109: dup
     110: ldc           #24                 // String BEGIN
     112: bipush        8
     114: invokespecial #8                  // Method "<init>":(Ljava/lang/String;I)V
     117: putstatic     #25                 // Field BEGIN:Lio/netty/handler/codec/stomp/StompCommand;
     120: new           #4                  // class io/netty/handler/codec/stomp/StompCommand
     123: dup
     124: ldc           #26                 // String DISCONNECT
     126: bipush        9
     128: invokespecial #8                  // Method "<init>":(Ljava/lang/String;I)V
     131: putstatic     #27                 // Field DISCONNECT:Lio/netty/handler/codec/stomp/StompCommand;
     134: new           #4                  // class io/netty/handler/codec/stomp/StompCommand
     137: dup
     138: ldc           #28                 // String MESSAGE
     140: bipush        10
     142: invokespecial #8                  // Method "<init>":(Ljava/lang/String;I)V
     145: putstatic     #29                 // Field MESSAGE:Lio/netty/handler/codec/stomp/StompCommand;
     148: new           #4                  // class io/netty/handler/codec/stomp/StompCommand
     151: dup
     152: ldc           #30                 // String RECEIPT
     154: bipush        11
     156: invokespecial #8                  // Method "<init>":(Ljava/lang/String;I)V
     159: putstatic     #31                 // Field RECEIPT:Lio/netty/handler/codec/stomp/StompCommand;
     162: new           #4                  // class io/netty/handler/codec/stomp/StompCommand
     165: dup
     166: ldc           #32                 // String ERROR
     168: bipush        12
     170: invokespecial #8                  // Method "<init>":(Ljava/lang/String;I)V
     173: putstatic     #33                 // Field ERROR:Lio/netty/handler/codec/stomp/StompCommand;
     176: new           #4                  // class io/netty/handler/codec/stomp/StompCommand
     179: dup
     180: ldc           #34                 // String UNKNOWN
     182: bipush        13
     184: invokespecial #8                  // Method "<init>":(Ljava/lang/String;I)V
     187: putstatic     #35                 // Field UNKNOWN:Lio/netty/handler/codec/stomp/StompCommand;
     190: bipush        14
     192: anewarray     #4                  // class io/netty/handler/codec/stomp/StompCommand
     195: dup
     196: iconst_0
     197: getstatic     #9                  // Field STOMP:Lio/netty/handler/codec/stomp/StompCommand;
     200: aastore
     201: dup
     202: iconst_1
     203: getstatic     #11                 // Field CONNECT:Lio/netty/handler/codec/stomp/StompCommand;
     206: aastore
     207: dup
     208: iconst_2
     209: getstatic     #13                 // Field CONNECTED:Lio/netty/handler/codec/stomp/StompCommand;
     212: aastore
     213: dup
     214: iconst_3
     215: getstatic     #15                 // Field SEND:Lio/netty/handler/codec/stomp/StompCommand;
     218: aastore
     219: dup
     220: iconst_4
     221: getstatic     #17                 // Field SUBSCRIBE:Lio/netty/handler/codec/stomp/StompCommand;
     224: aastore
     225: dup
     226: iconst_5
     227: getstatic     #19                 // Field UNSUBSCRIBE:Lio/netty/handler/codec/stomp/StompCommand;
     230: aastore
     231: dup
     232: bipush        6
     234: getstatic     #21                 // Field ACK:Lio/netty/handler/codec/stomp/StompCommand;
     237: aastore
     238: dup
     239: bipush        7
     241: getstatic     #23                 // Field NACK:Lio/netty/handler/codec/stomp/StompCommand;
     244: aastore
     245: dup
     246: bipush        8
     248: getstatic     #25                 // Field BEGIN:Lio/netty/handler/codec/stomp/StompCommand;
     251: aastore
     252: dup
     253: bipush        9
     255: getstatic     #27                 // Field DISCONNECT:Lio/netty/handler/codec/stomp/StompCommand;
     258: aastore
     259: dup
     260: bipush        10
     262: getstatic     #29                 // Field MESSAGE:Lio/netty/handler/codec/stomp/StompCommand;
     265: aastore
     266: dup
     267: bipush        11
     269: getstatic     #31                 // Field RECEIPT:Lio/netty/handler/codec/stomp/StompCommand;
     272: aastore
     273: dup
     274: bipush        12
     276: getstatic     #33                 // Field ERROR:Lio/netty/handler/codec/stomp/StompCommand;
     279: aastore
     280: dup
     281: bipush        13
     283: getstatic     #35                 // Field UNKNOWN:Lio/netty/handler/codec/stomp/StompCommand;
     286: aastore
     287: putstatic     #1                  // Field $VALUES:[Lio/netty/handler/codec/stomp/StompCommand;
     290: return
}
