Compiled from "FinalizableReferenceQueue.java"
class com.google.common.base.FinalizableReferenceQueue$SystemLoader implements com.google.common.base.FinalizableReferenceQueue$FinalizerLoader {
  static boolean disabled;

  com.google.common.base.FinalizableReferenceQueue$SystemLoader();
    Code:
       0: aload_0
       1: invokespecial #1                  // Method java/lang/Object."<init>":()V
       4: return

  public java.lang.Class<?> loadFinalizer();
    Code:
       0: getstatic     #2                  // Field disabled:Z
       3: ifeq          8
       6: aconst_null
       7: areturn
       8: invokestatic  #3                  // Method java/lang/ClassLoader.getSystemClassLoader:()Ljava/lang/ClassLoader;
      11: astore_1
      12: goto          26
      15: astore_2
      16: invokestatic  #5                  // Method com/google/common/base/FinalizableReferenceQueue.access$000:()Ljava/util/logging/Logger;
      19: ldc           #6                  // String Not allowed to access system class loader.
      21: invokevirtual #7                  // Method java/util/logging/Logger.info:(Ljava/lang/String;)V
      24: aconst_null
      25: areturn
      26: aload_1
      27: ifnull        40
      30: aload_1
      31: ldc           #8                  // String com.google.common.base.internal.Finalizer
      33: invokevirtual #9                  // Method java/lang/ClassLoader.loadClass:(Ljava/lang/String;)Ljava/lang/Class;
      36: areturn
      37: astore_2
      38: aconst_null
      39: areturn
      40: aconst_null
      41: areturn
    Exception table:
       from    to  target type
           8    12    15   Class java/lang/SecurityException
          30    36    37   Class java/lang/ClassNotFoundException
}
