Compiled from "MethodCallExpression.java"
public class org.apache.camel.model.language.MethodCallExpression extends org.apache.camel.model.language.ExpressionDefinition {
  private java.lang.String bean;

  private java.lang.String ref;

  private java.lang.String method;

  private java.lang.String beanTypeName;

  private java.lang.Class<?> beanType;

  private java.lang.Object instance;

  public org.apache.camel.model.language.MethodCallExpression();
    Code:
       0: aload_0
       1: invokespecial #33                 // Method org/apache/camel/model/language/ExpressionDefinition."<init>":()V
       4: return

  public org.apache.camel.model.language.MethodCallExpression(java.lang.String);
    Code:
       0: aload_0
       1: aload_1
       2: aconst_null
       3: invokespecial #39                 // Method "<init>":(Ljava/lang/String;Ljava/lang/String;)V
       6: return

  public org.apache.camel.model.language.MethodCallExpression(java.lang.String, java.lang.String);
    Code:
       0: aload_0
       1: aload_1
       2: invokespecial #42                 // Method org/apache/camel/model/language/ExpressionDefinition."<init>":(Ljava/lang/String;)V
       5: aload_0
       6: aload_2
       7: putfield      #44                 // Field method:Ljava/lang/String;
      10: return

  public org.apache.camel.model.language.MethodCallExpression(java.lang.Object);
    Code:
       0: aload_0
       1: aload_1
       2: aconst_null
       3: invokespecial #48                 // Method "<init>":(Ljava/lang/Object;Ljava/lang/String;)V
       6: return

  public org.apache.camel.model.language.MethodCallExpression(java.lang.Object, java.lang.String);
    Code:
       0: aload_0
       1: aload_1
       2: invokestatic  #54                 // Method org/apache/camel/util/ObjectHelper.className:(Ljava/lang/Object;)Ljava/lang/String;
       5: invokespecial #42                 // Method org/apache/camel/model/language/ExpressionDefinition."<init>":(Ljava/lang/String;)V
       8: aload_0
       9: aload_1
      10: invokevirtual #57                 // Method setInstance:(Ljava/lang/Object;)V
      13: aload_0
      14: aload_2
      15: invokevirtual #60                 // Method setMethod:(Ljava/lang/String;)V
      18: return

  public org.apache.camel.model.language.MethodCallExpression(java.lang.Class<?>);
    Code:
       0: aload_0
       1: aload_1
       2: aconst_null
       3: invokespecial #64                 // Method "<init>":(Ljava/lang/Class;Ljava/lang/String;)V
       6: return

  public org.apache.camel.model.language.MethodCallExpression(java.lang.Class<?>, java.lang.String);
    Code:
       0: aload_0
       1: aload_1
       2: invokevirtual #71                 // Method java/lang/Class.getName:()Ljava/lang/String;
       5: invokespecial #42                 // Method org/apache/camel/model/language/ExpressionDefinition."<init>":(Ljava/lang/String;)V
       8: aload_0
       9: aload_1
      10: putfield      #73                 // Field beanType:Ljava/lang/Class;
      13: aload_0
      14: aload_2
      15: putfield      #44                 // Field method:Ljava/lang/String;
      18: return

  public java.lang.String getLanguage();
    Code:
       0: ldc           #75                 // String bean
       2: areturn

  public java.lang.String getBean();
    Code:
       0: aload_0
       1: getfield      #78                 // Field bean:Ljava/lang/String;
       4: areturn

  public void setBean(java.lang.String);
    Code:
       0: aload_0
       1: aload_1
       2: putfield      #78                 // Field bean:Ljava/lang/String;
       5: return

  public java.lang.String getRef();
    Code:
       0: aload_0
       1: getfield      #82                 // Field ref:Ljava/lang/String;
       4: areturn

  public void setRef(java.lang.String);
    Code:
       0: aload_0
       1: aload_1
       2: putfield      #82                 // Field ref:Ljava/lang/String;
       5: return

  public java.lang.String getMethod();
    Code:
       0: aload_0
       1: getfield      #44                 // Field method:Ljava/lang/String;
       4: areturn

  public void setMethod(java.lang.String);
    Code:
       0: aload_0
       1: aload_1
       2: putfield      #44                 // Field method:Ljava/lang/String;
       5: return

  public java.lang.Class<?> getBeanType();
    Code:
       0: aload_0
       1: getfield      #73                 // Field beanType:Ljava/lang/Class;
       4: areturn

  public void setBeanType(java.lang.Class<?>);
    Code:
       0: aload_0
       1: aload_1
       2: putfield      #73                 // Field beanType:Ljava/lang/Class;
       5: aload_0
       6: aconst_null
       7: putfield      #89                 // Field instance:Ljava/lang/Object;
      10: return

  public java.lang.String getBeanTypeName();
    Code:
       0: aload_0
       1: getfield      #92                 // Field beanTypeName:Ljava/lang/String;
       4: areturn

  public void setBeanTypeName(java.lang.String);
    Code:
       0: aload_0
       1: aload_1
       2: putfield      #92                 // Field beanTypeName:Ljava/lang/String;
       5: return

  public java.lang.Object getInstance();
    Code:
       0: aload_0
       1: getfield      #89                 // Field instance:Ljava/lang/Object;
       4: areturn

  public void setInstance(java.lang.Object);
    Code:
       0: aload_1
       1: instanceof    #67                 // class java/lang/Class
       4: ifeq          23
       7: aload_0
       8: aload_1
       9: checkcast     #67                 // class java/lang/Class
      12: putfield      #73                 // Field beanType:Ljava/lang/Class;
      15: aload_0
      16: aconst_null
      17: putfield      #89                 // Field instance:Ljava/lang/Object;
      20: goto          33
      23: aload_0
      24: aconst_null
      25: putfield      #73                 // Field beanType:Ljava/lang/Class;
      28: aload_0
      29: aload_1
      30: putfield      #89                 // Field instance:Ljava/lang/Object;
      33: return

  public org.apache.camel.Expression createExpression(org.apache.camel.CamelContext);
    Code:
       0: aload_0
       1: getfield      #73                 // Field beanType:Ljava/lang/Class;
       4: ifnonnull     42
       7: aload_0
       8: getfield      #92                 // Field beanTypeName:Ljava/lang/String;
      11: ifnull        42
      14: aload_0
      15: aload_1
      16: invokeinterface #105,  1          // InterfaceMethod org/apache/camel/CamelContext.getClassResolver:()Lorg/apache/camel/spi/ClassResolver;
      21: aload_0
      22: getfield      #92                 // Field beanTypeName:Ljava/lang/String;
      25: invokeinterface #111,  2          // InterfaceMethod org/apache/camel/spi/ClassResolver.resolveMandatoryClass:(Ljava/lang/String;)Ljava/lang/Class;
      30: putfield      #73                 // Field beanType:Ljava/lang/Class;
      33: goto          42
      36: astore_2
      37: aload_2
      38: invokestatic  #115                // Method org/apache/camel/util/ObjectHelper.wrapRuntimeCamelException:(Ljava/lang/Throwable;)Lorg/apache/camel/RuntimeCamelException;
      41: athrow
      42: aload_0
      43: getfield      #73                 // Field beanType:Ljava/lang/Class;
      46: ifnull        110
      49: aload_0
      50: getfield      #73                 // Field beanType:Ljava/lang/Class;
      53: invokestatic  #119                // Method org/apache/camel/util/ObjectHelper.hasDefaultPublicNoArgConstructor:(Ljava/lang/Class;)Z
      56: ifeq          94
      59: aload_0
      60: aload_1
      61: invokeinterface #123,  1          // InterfaceMethod org/apache/camel/CamelContext.getInjector:()Lorg/apache/camel/spi/Injector;
      66: aload_0
      67: getfield      #73                 // Field beanType:Ljava/lang/Class;
      70: invokeinterface #129,  2          // InterfaceMethod org/apache/camel/spi/Injector.newInstance:(Ljava/lang/Class;)Ljava/lang/Object;
      75: putfield      #89                 // Field instance:Ljava/lang/Object;
      78: new           #131                // class org/apache/camel/component/bean/ConstantBeanHolder
      81: dup
      82: aload_0
      83: getfield      #89                 // Field instance:Ljava/lang/Object;
      86: aload_1
      87: invokespecial #134                // Method org/apache/camel/component/bean/ConstantBeanHolder."<init>":(Ljava/lang/Object;Lorg/apache/camel/CamelContext;)V
      90: astore_2
      91: goto          173
      94: new           #136                // class org/apache/camel/component/bean/ConstantStaticTypeBeanHolder
      97: dup
      98: aload_0
      99: getfield      #73                 // Field beanType:Ljava/lang/Class;
     102: aload_1
     103: invokespecial #139                // Method org/apache/camel/component/bean/ConstantStaticTypeBeanHolder."<init>":(Ljava/lang/Class;Lorg/apache/camel/CamelContext;)V
     106: astore_2
     107: goto          173
     110: aload_0
     111: getfield      #89                 // Field instance:Ljava/lang/Object;
     114: ifnull        133
     117: new           #131                // class org/apache/camel/component/bean/ConstantBeanHolder
     120: dup
     121: aload_0
     122: getfield      #89                 // Field instance:Ljava/lang/Object;
     125: aload_1
     126: invokespecial #134                // Method org/apache/camel/component/bean/ConstantBeanHolder."<init>":(Ljava/lang/Object;Lorg/apache/camel/CamelContext;)V
     129: astore_2
     130: goto          173
     133: aload_0
     134: invokevirtual #141                // Method beanName:()Ljava/lang/String;
     137: astore_3
     138: new           #143                // class org/apache/camel/component/bean/RegistryBean
     141: dup
     142: aload_1
     143: aload_3
     144: invokespecial #146                // Method org/apache/camel/component/bean/RegistryBean."<init>":(Lorg/apache/camel/CamelContext;Ljava/lang/String;)V
     147: astore        4
     149: aload_0
     150: aload         4
     152: invokeinterface #150,  1          // InterfaceMethod org/apache/camel/component/bean/BeanHolder.getBean:()Ljava/lang/Object;
     157: putfield      #89                 // Field instance:Ljava/lang/Object;
     160: new           #131                // class org/apache/camel/component/bean/ConstantBeanHolder
     163: dup
     164: aload_0
     165: getfield      #89                 // Field instance:Ljava/lang/Object;
     168: aload_1
     169: invokespecial #134                // Method org/apache/camel/component/bean/ConstantBeanHolder."<init>":(Ljava/lang/Object;Lorg/apache/camel/CamelContext;)V
     172: astore_2
     173: new           #152                // class org/apache/camel/language/bean/BeanExpression
     176: dup
     177: aload_2
     178: aload_0
     179: invokevirtual #154                // Method getMethod:()Ljava/lang/String;
     182: invokespecial #157                // Method org/apache/camel/language/bean/BeanExpression."<init>":(Lorg/apache/camel/component/bean/BeanHolder;Ljava/lang/String;)V
     185: astore        5
     187: aload_0
     188: aload_1
     189: aload_0
     190: getfield      #89                 // Field instance:Ljava/lang/Object;
     193: aload_0
     194: getfield      #73                 // Field beanType:Ljava/lang/Class;
     197: aload_0
     198: invokevirtual #154                // Method getMethod:()Ljava/lang/String;
     201: invokevirtual #161                // Method validateHasMethod:(Lorg/apache/camel/CamelContext;Ljava/lang/Object;Ljava/lang/Class;Ljava/lang/String;)V
     204: aload         5
     206: areturn
    Exception table:
       from    to  target type
          14    33    36   Class java/lang/ClassNotFoundException

  public org.apache.camel.Predicate createPredicate(org.apache.camel.CamelContext);
    Code:
       0: aload_0
       1: aload_1
       2: invokevirtual #174                // Method createExpression:(Lorg/apache/camel/CamelContext;)Lorg/apache/camel/Expression;
       5: checkcast     #152                // class org/apache/camel/language/bean/BeanExpression
       8: areturn

  protected void validateHasMethod(org.apache.camel.CamelContext, java.lang.Object, java.lang.Class<?>, java.lang.String);
    Code:
       0: aload         4
       2: ifnonnull     6
       5: return
       6: aload_2
       7: ifnonnull     41
      10: aload_3
      11: ifnonnull     41
      14: new           #176                // class java/lang/IllegalArgumentException
      17: dup
      18: new           #178                // class java/lang/StringBuilder
      21: dup
      22: invokespecial #179                // Method java/lang/StringBuilder."<init>":()V
      25: ldc           #181                // String Either bean or type should be provided on
      27: invokevirtual #185                // Method java/lang/StringBuilder.append:(Ljava/lang/String;)Ljava/lang/StringBuilder;
      30: aload_0
      31: invokevirtual #188                // Method java/lang/StringBuilder.append:(Ljava/lang/Object;)Ljava/lang/StringBuilder;
      34: invokevirtual #191                // Method java/lang/StringBuilder.toString:()Ljava/lang/String;
      37: invokespecial #192                // Method java/lang/IllegalArgumentException."<init>":(Ljava/lang/String;)V
      40: athrow
      41: aload         4
      43: invokestatic  #198                // Method org/apache/camel/util/OgnlHelper.isValidOgnlExpression:(Ljava/lang/String;)Z
      46: ifeq          50
      49: return
      50: aload         4
      52: invokestatic  #201                // Method org/apache/camel/util/OgnlHelper.isInvalidValidOgnlExpression:(Ljava/lang/String;)Z
      55: ifeq          93
      58: new           #203                // class org/apache/camel/ExpressionIllegalSyntaxException
      61: dup
      62: aload         4
      64: invokespecial #204                // Method org/apache/camel/ExpressionIllegalSyntaxException."<init>":(Ljava/lang/String;)V
      67: astore        5
      69: new           #206                // class org/apache/camel/component/bean/MethodNotFoundException
      72: dup
      73: aload_2
      74: ifnull        81
      77: aload_2
      78: goto          82
      81: aload_3
      82: aload         4
      84: aload         5
      86: invokespecial #213                // Method org/apache/camel/component/bean/MethodNotFoundException."<init>":(Ljava/lang/Object;Ljava/lang/String;Ljava/lang/Throwable;)V
      89: invokestatic  #115                // Method org/apache/camel/util/ObjectHelper.wrapRuntimeCamelException:(Ljava/lang/Throwable;)Lorg/apache/camel/RuntimeCamelException;
      92: athrow
      93: aload_2
      94: ifnull        139
      97: new           #215                // class org/apache/camel/component/bean/BeanInfo
     100: dup
     101: aload_1
     102: aload_2
     103: invokevirtual #218                // Method java/lang/Object.getClass:()Ljava/lang/Class;
     106: invokespecial #221                // Method org/apache/camel/component/bean/BeanInfo."<init>":(Lorg/apache/camel/CamelContext;Ljava/lang/Class;)V
     109: astore        5
     111: aload         5
     113: aload         4
     115: invokevirtual #224                // Method org/apache/camel/component/bean/BeanInfo.hasMethod:(Ljava/lang/String;)Z
     118: ifne          136
     121: new           #206                // class org/apache/camel/component/bean/MethodNotFoundException
     124: dup
     125: aconst_null
     126: aload_2
     127: aload         4
     129: invokespecial #227                // Method org/apache/camel/component/bean/MethodNotFoundException."<init>":(Lorg/apache/camel/Exchange;Ljava/lang/Object;Ljava/lang/String;)V
     132: invokestatic  #115                // Method org/apache/camel/util/ObjectHelper.wrapRuntimeCamelException:(Ljava/lang/Throwable;)Lorg/apache/camel/RuntimeCamelException;
     135: athrow
     136: goto          176
     139: new           #215                // class org/apache/camel/component/bean/BeanInfo
     142: dup
     143: aload_1
     144: aload_3
     145: invokespecial #221                // Method org/apache/camel/component/bean/BeanInfo."<init>":(Lorg/apache/camel/CamelContext;Ljava/lang/Class;)V
     148: astore        5
     150: aload         5
     152: aload         4
     154: invokevirtual #230                // Method org/apache/camel/component/bean/BeanInfo.hasStaticMethod:(Ljava/lang/String;)Z
     157: ifne          176
     160: new           #206                // class org/apache/camel/component/bean/MethodNotFoundException
     163: dup
     164: aconst_null
     165: aload_3
     166: aload         4
     168: iconst_1
     169: invokespecial #233                // Method org/apache/camel/component/bean/MethodNotFoundException."<init>":(Lorg/apache/camel/Exchange;Ljava/lang/Class;Ljava/lang/String;Z)V
     172: invokestatic  #115                // Method org/apache/camel/util/ObjectHelper.wrapRuntimeCamelException:(Ljava/lang/Throwable;)Lorg/apache/camel/RuntimeCamelException;
     175: athrow
     176: return

  protected java.lang.String beanName();
    Code:
       0: aload_0
       1: getfield      #78                 // Field bean:Ljava/lang/String;
       4: ifnull        12
       7: aload_0
       8: getfield      #78                 // Field bean:Ljava/lang/String;
      11: areturn
      12: aload_0
      13: getfield      #82                 // Field ref:Ljava/lang/String;
      16: ifnull        24
      19: aload_0
      20: getfield      #82                 // Field ref:Ljava/lang/String;
      23: areturn
      24: aload_0
      25: getfield      #89                 // Field instance:Ljava/lang/Object;
      28: ifnull        39
      31: aload_0
      32: getfield      #89                 // Field instance:Ljava/lang/Object;
      35: invokestatic  #54                 // Method org/apache/camel/util/ObjectHelper.className:(Ljava/lang/Object;)Ljava/lang/String;
      38: areturn
      39: aload_0
      40: invokevirtual #241                // Method getExpression:()Ljava/lang/String;
      43: areturn

  public java.lang.String toString();
    Code:
       0: aload_0
       1: getfield      #78                 // Field bean:Ljava/lang/String;
       4: ifnonnull     14
       7: aload_0
       8: getfield      #82                 // Field ref:Ljava/lang/String;
      11: ifnull        18
      14: iconst_1
      15: goto          19
      18: iconst_0
      19: istore_1
      20: new           #178                // class java/lang/StringBuilder
      23: dup
      24: invokespecial #179                // Method java/lang/StringBuilder."<init>":()V
      27: ldc           #243                // String bean[
      29: invokevirtual #185                // Method java/lang/StringBuilder.append:(Ljava/lang/String;)Ljava/lang/StringBuilder;
      32: iload_1
      33: ifeq          41
      36: ldc           #245                // String ref:
      38: goto          43
      41: ldc           #247                // String
      43: invokevirtual #185                // Method java/lang/StringBuilder.append:(Ljava/lang/String;)Ljava/lang/StringBuilder;
      46: aload_0
      47: invokevirtual #141                // Method beanName:()Ljava/lang/String;
      50: invokevirtual #185                // Method java/lang/StringBuilder.append:(Ljava/lang/String;)Ljava/lang/StringBuilder;
      53: aload_0
      54: getfield      #44                 // Field method:Ljava/lang/String;
      57: ifnull        85
      60: new           #178                // class java/lang/StringBuilder
      63: dup
      64: invokespecial #179                // Method java/lang/StringBuilder."<init>":()V
      67: ldc           #249                // String  method:
      69: invokevirtual #185                // Method java/lang/StringBuilder.append:(Ljava/lang/String;)Ljava/lang/StringBuilder;
      72: aload_0
      73: getfield      #44                 // Field method:Ljava/lang/String;
      76: invokevirtual #185                // Method java/lang/StringBuilder.append:(Ljava/lang/String;)Ljava/lang/StringBuilder;
      79: invokevirtual #191                // Method java/lang/StringBuilder.toString:()Ljava/lang/String;
      82: goto          87
      85: ldc           #247                // String
      87: invokevirtual #185                // Method java/lang/StringBuilder.append:(Ljava/lang/String;)Ljava/lang/StringBuilder;
      90: ldc           #251                // String ]
      92: invokevirtual #185                // Method java/lang/StringBuilder.append:(Ljava/lang/String;)Ljava/lang/StringBuilder;
      95: invokevirtual #191                // Method java/lang/StringBuilder.toString:()Ljava/lang/String;
      98: areturn
}
