Compiled from "CommonProxiedMethodFilters.java"
final class org.jboss.weld.bean.proxy.CommonProxiedMethodFilters {
  static final org.jboss.weld.bean.proxy.ProxiedMethodFilter NON_STATIC;

  static final org.jboss.weld.bean.proxy.ProxiedMethodFilter NON_FINAL;

  static final org.jboss.weld.bean.proxy.ProxiedMethodFilter OBJECT_TO_STRING;

  private org.jboss.weld.bean.proxy.CommonProxiedMethodFilters();
    Code:
       0: aload_0
       1: invokespecial #1                  // Method java/lang/Object."<init>":()V
       4: return

  static {};
    Code:
       0: new           #2                  // class org/jboss/weld/bean/proxy/CommonProxiedMethodFilters$1
       3: dup
       4: invokespecial #3                  // Method org/jboss/weld/bean/proxy/CommonProxiedMethodFilters$1."<init>":()V
       7: putstatic     #4                  // Field NON_STATIC:Lorg/jboss/weld/bean/proxy/ProxiedMethodFilter;
      10: new           #5                  // class org/jboss/weld/bean/proxy/CommonProxiedMethodFilters$2
      13: dup
      14: invokespecial #6                  // Method org/jboss/weld/bean/proxy/CommonProxiedMethodFilters$2."<init>":()V
      17: putstatic     #7                  // Field NON_FINAL:Lorg/jboss/weld/bean/proxy/ProxiedMethodFilter;
      20: new           #8                  // class org/jboss/weld/bean/proxy/CommonProxiedMethodFilters$3
      23: dup
      24: invokespecial #9                  // Method org/jboss/weld/bean/proxy/CommonProxiedMethodFilters$3."<init>":()V
      27: putstatic     #10                 // Field OBJECT_TO_STRING:Lorg/jboss/weld/bean/proxy/ProxiedMethodFilter;
      30: return
}
