Compiled from "AudioCodecSettings.java"
final class software.amazon.awssdk.services.mediaconvert.model.AudioCodecSettings$BuilderImpl implements software.amazon.awssdk.services.mediaconvert.model.AudioCodecSettings$Builder {
  private software.amazon.awssdk.services.mediaconvert.model.AacSettings aacSettings;

  private software.amazon.awssdk.services.mediaconvert.model.Ac3Settings ac3Settings;

  private software.amazon.awssdk.services.mediaconvert.model.AiffSettings aiffSettings;

  private java.lang.String codec;

  private software.amazon.awssdk.services.mediaconvert.model.Eac3AtmosSettings eac3AtmosSettings;

  private software.amazon.awssdk.services.mediaconvert.model.Eac3Settings eac3Settings;

  private software.amazon.awssdk.services.mediaconvert.model.Mp2Settings mp2Settings;

  private software.amazon.awssdk.services.mediaconvert.model.Mp3Settings mp3Settings;

  private software.amazon.awssdk.services.mediaconvert.model.OpusSettings opusSettings;

  private software.amazon.awssdk.services.mediaconvert.model.VorbisSettings vorbisSettings;

  private software.amazon.awssdk.services.mediaconvert.model.WavSettings wavSettings;

  private software.amazon.awssdk.services.mediaconvert.model.AudioCodecSettings$BuilderImpl();
    Code:
       0: aload_0
       1: invokespecial #14                 // Method java/lang/Object."<init>":()V
       4: return

  private software.amazon.awssdk.services.mediaconvert.model.AudioCodecSettings$BuilderImpl(software.amazon.awssdk.services.mediaconvert.model.AudioCodecSettings);
    Code:
       0: aload_0
       1: invokespecial #14                 // Method java/lang/Object."<init>":()V
       4: aload_0
       5: aload_1
       6: invokestatic  #15                 // Method software/amazon/awssdk/services/mediaconvert/model/AudioCodecSettings.access$1300:(Lsoftware/amazon/awssdk/services/mediaconvert/model/AudioCodecSettings;)Lsoftware/amazon/awssdk/services/mediaconvert/model/AacSettings;
       9: invokevirtual #16                 // Method aacSettings:(Lsoftware/amazon/awssdk/services/mediaconvert/model/AacSettings;)Lsoftware/amazon/awssdk/services/mediaconvert/model/AudioCodecSettings$Builder;
      12: pop
      13: aload_0
      14: aload_1
      15: invokestatic  #17                 // Method software/amazon/awssdk/services/mediaconvert/model/AudioCodecSettings.access$1400:(Lsoftware/amazon/awssdk/services/mediaconvert/model/AudioCodecSettings;)Lsoftware/amazon/awssdk/services/mediaconvert/model/Ac3Settings;
      18: invokevirtual #18                 // Method ac3Settings:(Lsoftware/amazon/awssdk/services/mediaconvert/model/Ac3Settings;)Lsoftware/amazon/awssdk/services/mediaconvert/model/AudioCodecSettings$Builder;
      21: pop
      22: aload_0
      23: aload_1
      24: invokestatic  #19                 // Method software/amazon/awssdk/services/mediaconvert/model/AudioCodecSettings.access$1500:(Lsoftware/amazon/awssdk/services/mediaconvert/model/AudioCodecSettings;)Lsoftware/amazon/awssdk/services/mediaconvert/model/AiffSettings;
      27: invokevirtual #20                 // Method aiffSettings:(Lsoftware/amazon/awssdk/services/mediaconvert/model/AiffSettings;)Lsoftware/amazon/awssdk/services/mediaconvert/model/AudioCodecSettings$Builder;
      30: pop
      31: aload_0
      32: aload_1
      33: invokestatic  #21                 // Method software/amazon/awssdk/services/mediaconvert/model/AudioCodecSettings.access$1600:(Lsoftware/amazon/awssdk/services/mediaconvert/model/AudioCodecSettings;)Ljava/lang/String;
      36: invokevirtual #22                 // Method codec:(Ljava/lang/String;)Lsoftware/amazon/awssdk/services/mediaconvert/model/AudioCodecSettings$Builder;
      39: pop
      40: aload_0
      41: aload_1
      42: invokestatic  #23                 // Method software/amazon/awssdk/services/mediaconvert/model/AudioCodecSettings.access$1700:(Lsoftware/amazon/awssdk/services/mediaconvert/model/AudioCodecSettings;)Lsoftware/amazon/awssdk/services/mediaconvert/model/Eac3AtmosSettings;
      45: invokevirtual #24                 // Method eac3AtmosSettings:(Lsoftware/amazon/awssdk/services/mediaconvert/model/Eac3AtmosSettings;)Lsoftware/amazon/awssdk/services/mediaconvert/model/AudioCodecSettings$Builder;
      48: pop
      49: aload_0
      50: aload_1
      51: invokestatic  #25                 // Method software/amazon/awssdk/services/mediaconvert/model/AudioCodecSettings.access$1800:(Lsoftware/amazon/awssdk/services/mediaconvert/model/AudioCodecSettings;)Lsoftware/amazon/awssdk/services/mediaconvert/model/Eac3Settings;
      54: invokevirtual #26                 // Method eac3Settings:(Lsoftware/amazon/awssdk/services/mediaconvert/model/Eac3Settings;)Lsoftware/amazon/awssdk/services/mediaconvert/model/AudioCodecSettings$Builder;
      57: pop
      58: aload_0
      59: aload_1
      60: invokestatic  #27                 // Method software/amazon/awssdk/services/mediaconvert/model/AudioCodecSettings.access$1900:(Lsoftware/amazon/awssdk/services/mediaconvert/model/AudioCodecSettings;)Lsoftware/amazon/awssdk/services/mediaconvert/model/Mp2Settings;
      63: invokevirtual #28                 // Method mp2Settings:(Lsoftware/amazon/awssdk/services/mediaconvert/model/Mp2Settings;)Lsoftware/amazon/awssdk/services/mediaconvert/model/AudioCodecSettings$Builder;
      66: pop
      67: aload_0
      68: aload_1
      69: invokestatic  #29                 // Method software/amazon/awssdk/services/mediaconvert/model/AudioCodecSettings.access$2000:(Lsoftware/amazon/awssdk/services/mediaconvert/model/AudioCodecSettings;)Lsoftware/amazon/awssdk/services/mediaconvert/model/Mp3Settings;
      72: invokevirtual #30                 // Method mp3Settings:(Lsoftware/amazon/awssdk/services/mediaconvert/model/Mp3Settings;)Lsoftware/amazon/awssdk/services/mediaconvert/model/AudioCodecSettings$Builder;
      75: pop
      76: aload_0
      77: aload_1
      78: invokestatic  #31                 // Method software/amazon/awssdk/services/mediaconvert/model/AudioCodecSettings.access$2100:(Lsoftware/amazon/awssdk/services/mediaconvert/model/AudioCodecSettings;)Lsoftware/amazon/awssdk/services/mediaconvert/model/OpusSettings;
      81: invokevirtual #32                 // Method opusSettings:(Lsoftware/amazon/awssdk/services/mediaconvert/model/OpusSettings;)Lsoftware/amazon/awssdk/services/mediaconvert/model/AudioCodecSettings$Builder;
      84: pop
      85: aload_0
      86: aload_1
      87: invokestatic  #33                 // Method software/amazon/awssdk/services/mediaconvert/model/AudioCodecSettings.access$2200:(Lsoftware/amazon/awssdk/services/mediaconvert/model/AudioCodecSettings;)Lsoftware/amazon/awssdk/services/mediaconvert/model/VorbisSettings;
      90: invokevirtual #34                 // Method vorbisSettings:(Lsoftware/amazon/awssdk/services/mediaconvert/model/VorbisSettings;)Lsoftware/amazon/awssdk/services/mediaconvert/model/AudioCodecSettings$Builder;
      93: pop
      94: aload_0
      95: aload_1
      96: invokestatic  #35                 // Method software/amazon/awssdk/services/mediaconvert/model/AudioCodecSettings.access$2300:(Lsoftware/amazon/awssdk/services/mediaconvert/model/AudioCodecSettings;)Lsoftware/amazon/awssdk/services/mediaconvert/model/WavSettings;
      99: invokevirtual #36                 // Method wavSettings:(Lsoftware/amazon/awssdk/services/mediaconvert/model/WavSettings;)Lsoftware/amazon/awssdk/services/mediaconvert/model/AudioCodecSettings$Builder;
     102: pop
     103: return

  public final software.amazon.awssdk.services.mediaconvert.model.AacSettings$Builder getAacSettings();
    Code:
       0: aload_0
       1: getfield      #13                 // Field aacSettings:Lsoftware/amazon/awssdk/services/mediaconvert/model/AacSettings;
       4: ifnull        17
       7: aload_0
       8: getfield      #13                 // Field aacSettings:Lsoftware/amazon/awssdk/services/mediaconvert/model/AacSettings;
      11: invokevirtual #37                 // Method software/amazon/awssdk/services/mediaconvert/model/AacSettings.toBuilder:()Lsoftware/amazon/awssdk/services/mediaconvert/model/AacSettings$Builder;
      14: goto          18
      17: aconst_null
      18: areturn

  public final void setAacSettings(software.amazon.awssdk.services.mediaconvert.model.AacSettings$BuilderImpl);
    Code:
       0: aload_0
       1: aload_1
       2: ifnull        12
       5: aload_1
       6: invokevirtual #38                 // Method software/amazon/awssdk/services/mediaconvert/model/AacSettings$BuilderImpl.build:()Lsoftware/amazon/awssdk/services/mediaconvert/model/AacSettings;
       9: goto          13
      12: aconst_null
      13: putfield      #13                 // Field aacSettings:Lsoftware/amazon/awssdk/services/mediaconvert/model/AacSettings;
      16: return

  public final software.amazon.awssdk.services.mediaconvert.model.AudioCodecSettings$Builder aacSettings(software.amazon.awssdk.services.mediaconvert.model.AacSettings);
    Code:
       0: aload_0
       1: aload_1
       2: putfield      #13                 // Field aacSettings:Lsoftware/amazon/awssdk/services/mediaconvert/model/AacSettings;
       5: aload_0
       6: areturn

  public final software.amazon.awssdk.services.mediaconvert.model.Ac3Settings$Builder getAc3Settings();
    Code:
       0: aload_0
       1: getfield      #12                 // Field ac3Settings:Lsoftware/amazon/awssdk/services/mediaconvert/model/Ac3Settings;
       4: ifnull        17
       7: aload_0
       8: getfield      #12                 // Field ac3Settings:Lsoftware/amazon/awssdk/services/mediaconvert/model/Ac3Settings;
      11: invokevirtual #39                 // Method software/amazon/awssdk/services/mediaconvert/model/Ac3Settings.toBuilder:()Lsoftware/amazon/awssdk/services/mediaconvert/model/Ac3Settings$Builder;
      14: goto          18
      17: aconst_null
      18: areturn

  public final void setAc3Settings(software.amazon.awssdk.services.mediaconvert.model.Ac3Settings$BuilderImpl);
    Code:
       0: aload_0
       1: aload_1
       2: ifnull        12
       5: aload_1
       6: invokevirtual #40                 // Method software/amazon/awssdk/services/mediaconvert/model/Ac3Settings$BuilderImpl.build:()Lsoftware/amazon/awssdk/services/mediaconvert/model/Ac3Settings;
       9: goto          13
      12: aconst_null
      13: putfield      #12                 // Field ac3Settings:Lsoftware/amazon/awssdk/services/mediaconvert/model/Ac3Settings;
      16: return

  public final software.amazon.awssdk.services.mediaconvert.model.AudioCodecSettings$Builder ac3Settings(software.amazon.awssdk.services.mediaconvert.model.Ac3Settings);
    Code:
       0: aload_0
       1: aload_1
       2: putfield      #12                 // Field ac3Settings:Lsoftware/amazon/awssdk/services/mediaconvert/model/Ac3Settings;
       5: aload_0
       6: areturn

  public final software.amazon.awssdk.services.mediaconvert.model.AiffSettings$Builder getAiffSettings();
    Code:
       0: aload_0
       1: getfield      #11                 // Field aiffSettings:Lsoftware/amazon/awssdk/services/mediaconvert/model/AiffSettings;
       4: ifnull        17
       7: aload_0
       8: getfield      #11                 // Field aiffSettings:Lsoftware/amazon/awssdk/services/mediaconvert/model/AiffSettings;
      11: invokevirtual #41                 // Method software/amazon/awssdk/services/mediaconvert/model/AiffSettings.toBuilder:()Lsoftware/amazon/awssdk/services/mediaconvert/model/AiffSettings$Builder;
      14: goto          18
      17: aconst_null
      18: areturn

  public final void setAiffSettings(software.amazon.awssdk.services.mediaconvert.model.AiffSettings$BuilderImpl);
    Code:
       0: aload_0
       1: aload_1
       2: ifnull        12
       5: aload_1
       6: invokevirtual #42                 // Method software/amazon/awssdk/services/mediaconvert/model/AiffSettings$BuilderImpl.build:()Lsoftware/amazon/awssdk/services/mediaconvert/model/AiffSettings;
       9: goto          13
      12: aconst_null
      13: putfield      #11                 // Field aiffSettings:Lsoftware/amazon/awssdk/services/mediaconvert/model/AiffSettings;
      16: return

  public final software.amazon.awssdk.services.mediaconvert.model.AudioCodecSettings$Builder aiffSettings(software.amazon.awssdk.services.mediaconvert.model.AiffSettings);
    Code:
       0: aload_0
       1: aload_1
       2: putfield      #11                 // Field aiffSettings:Lsoftware/amazon/awssdk/services/mediaconvert/model/AiffSettings;
       5: aload_0
       6: areturn

  public final java.lang.String getCodec();
    Code:
       0: aload_0
       1: getfield      #10                 // Field codec:Ljava/lang/String;
       4: areturn

  public final void setCodec(java.lang.String);
    Code:
       0: aload_0
       1: aload_1
       2: putfield      #10                 // Field codec:Ljava/lang/String;
       5: return

  public final software.amazon.awssdk.services.mediaconvert.model.AudioCodecSettings$Builder codec(java.lang.String);
    Code:
       0: aload_0
       1: aload_1
       2: putfield      #10                 // Field codec:Ljava/lang/String;
       5: aload_0
       6: areturn

  public final software.amazon.awssdk.services.mediaconvert.model.AudioCodecSettings$Builder codec(software.amazon.awssdk.services.mediaconvert.model.AudioCodec);
    Code:
       0: aload_0
       1: aload_1
       2: ifnonnull     9
       5: aconst_null
       6: goto          13
       9: aload_1
      10: invokevirtual #43                 // Method software/amazon/awssdk/services/mediaconvert/model/AudioCodec.toString:()Ljava/lang/String;
      13: invokevirtual #22                 // Method codec:(Ljava/lang/String;)Lsoftware/amazon/awssdk/services/mediaconvert/model/AudioCodecSettings$Builder;
      16: pop
      17: aload_0
      18: areturn

  public final software.amazon.awssdk.services.mediaconvert.model.Eac3AtmosSettings$Builder getEac3AtmosSettings();
    Code:
       0: aload_0
       1: getfield      #9                  // Field eac3AtmosSettings:Lsoftware/amazon/awssdk/services/mediaconvert/model/Eac3AtmosSettings;
       4: ifnull        17
       7: aload_0
       8: getfield      #9                  // Field eac3AtmosSettings:Lsoftware/amazon/awssdk/services/mediaconvert/model/Eac3AtmosSettings;
      11: invokevirtual #44                 // Method software/amazon/awssdk/services/mediaconvert/model/Eac3AtmosSettings.toBuilder:()Lsoftware/amazon/awssdk/services/mediaconvert/model/Eac3AtmosSettings$Builder;
      14: goto          18
      17: aconst_null
      18: areturn

  public final void setEac3AtmosSettings(software.amazon.awssdk.services.mediaconvert.model.Eac3AtmosSettings$BuilderImpl);
    Code:
       0: aload_0
       1: aload_1
       2: ifnull        12
       5: aload_1
       6: invokevirtual #45                 // Method software/amazon/awssdk/services/mediaconvert/model/Eac3AtmosSettings$BuilderImpl.build:()Lsoftware/amazon/awssdk/services/mediaconvert/model/Eac3AtmosSettings;
       9: goto          13
      12: aconst_null
      13: putfield      #9                  // Field eac3AtmosSettings:Lsoftware/amazon/awssdk/services/mediaconvert/model/Eac3AtmosSettings;
      16: return

  public final software.amazon.awssdk.services.mediaconvert.model.AudioCodecSettings$Builder eac3AtmosSettings(software.amazon.awssdk.services.mediaconvert.model.Eac3AtmosSettings);
    Code:
       0: aload_0
       1: aload_1
       2: putfield      #9                  // Field eac3AtmosSettings:Lsoftware/amazon/awssdk/services/mediaconvert/model/Eac3AtmosSettings;
       5: aload_0
       6: areturn

  public final software.amazon.awssdk.services.mediaconvert.model.Eac3Settings$Builder getEac3Settings();
    Code:
       0: aload_0
       1: getfield      #8                  // Field eac3Settings:Lsoftware/amazon/awssdk/services/mediaconvert/model/Eac3Settings;
       4: ifnull        17
       7: aload_0
       8: getfield      #8                  // Field eac3Settings:Lsoftware/amazon/awssdk/services/mediaconvert/model/Eac3Settings;
      11: invokevirtual #46                 // Method software/amazon/awssdk/services/mediaconvert/model/Eac3Settings.toBuilder:()Lsoftware/amazon/awssdk/services/mediaconvert/model/Eac3Settings$Builder;
      14: goto          18
      17: aconst_null
      18: areturn

  public final void setEac3Settings(software.amazon.awssdk.services.mediaconvert.model.Eac3Settings$BuilderImpl);
    Code:
       0: aload_0
       1: aload_1
       2: ifnull        12
       5: aload_1
       6: invokevirtual #47                 // Method software/amazon/awssdk/services/mediaconvert/model/Eac3Settings$BuilderImpl.build:()Lsoftware/amazon/awssdk/services/mediaconvert/model/Eac3Settings;
       9: goto          13
      12: aconst_null
      13: putfield      #8                  // Field eac3Settings:Lsoftware/amazon/awssdk/services/mediaconvert/model/Eac3Settings;
      16: return

  public final software.amazon.awssdk.services.mediaconvert.model.AudioCodecSettings$Builder eac3Settings(software.amazon.awssdk.services.mediaconvert.model.Eac3Settings);
    Code:
       0: aload_0
       1: aload_1
       2: putfield      #8                  // Field eac3Settings:Lsoftware/amazon/awssdk/services/mediaconvert/model/Eac3Settings;
       5: aload_0
       6: areturn

  public final software.amazon.awssdk.services.mediaconvert.model.Mp2Settings$Builder getMp2Settings();
    Code:
       0: aload_0
       1: getfield      #7                  // Field mp2Settings:Lsoftware/amazon/awssdk/services/mediaconvert/model/Mp2Settings;
       4: ifnull        17
       7: aload_0
       8: getfield      #7                  // Field mp2Settings:Lsoftware/amazon/awssdk/services/mediaconvert/model/Mp2Settings;
      11: invokevirtual #48                 // Method software/amazon/awssdk/services/mediaconvert/model/Mp2Settings.toBuilder:()Lsoftware/amazon/awssdk/services/mediaconvert/model/Mp2Settings$Builder;
      14: goto          18
      17: aconst_null
      18: areturn

  public final void setMp2Settings(software.amazon.awssdk.services.mediaconvert.model.Mp2Settings$BuilderImpl);
    Code:
       0: aload_0
       1: aload_1
       2: ifnull        12
       5: aload_1
       6: invokevirtual #49                 // Method software/amazon/awssdk/services/mediaconvert/model/Mp2Settings$BuilderImpl.build:()Lsoftware/amazon/awssdk/services/mediaconvert/model/Mp2Settings;
       9: goto          13
      12: aconst_null
      13: putfield      #7                  // Field mp2Settings:Lsoftware/amazon/awssdk/services/mediaconvert/model/Mp2Settings;
      16: return

  public final software.amazon.awssdk.services.mediaconvert.model.AudioCodecSettings$Builder mp2Settings(software.amazon.awssdk.services.mediaconvert.model.Mp2Settings);
    Code:
       0: aload_0
       1: aload_1
       2: putfield      #7                  // Field mp2Settings:Lsoftware/amazon/awssdk/services/mediaconvert/model/Mp2Settings;
       5: aload_0
       6: areturn

  public final software.amazon.awssdk.services.mediaconvert.model.Mp3Settings$Builder getMp3Settings();
    Code:
       0: aload_0
       1: getfield      #6                  // Field mp3Settings:Lsoftware/amazon/awssdk/services/mediaconvert/model/Mp3Settings;
       4: ifnull        17
       7: aload_0
       8: getfield      #6                  // Field mp3Settings:Lsoftware/amazon/awssdk/services/mediaconvert/model/Mp3Settings;
      11: invokevirtual #50                 // Method software/amazon/awssdk/services/mediaconvert/model/Mp3Settings.toBuilder:()Lsoftware/amazon/awssdk/services/mediaconvert/model/Mp3Settings$Builder;
      14: goto          18
      17: aconst_null
      18: areturn

  public final void setMp3Settings(software.amazon.awssdk.services.mediaconvert.model.Mp3Settings$BuilderImpl);
    Code:
       0: aload_0
       1: aload_1
       2: ifnull        12
       5: aload_1
       6: invokevirtual #51                 // Method software/amazon/awssdk/services/mediaconvert/model/Mp3Settings$BuilderImpl.build:()Lsoftware/amazon/awssdk/services/mediaconvert/model/Mp3Settings;
       9: goto          13
      12: aconst_null
      13: putfield      #6                  // Field mp3Settings:Lsoftware/amazon/awssdk/services/mediaconvert/model/Mp3Settings;
      16: return

  public final software.amazon.awssdk.services.mediaconvert.model.AudioCodecSettings$Builder mp3Settings(software.amazon.awssdk.services.mediaconvert.model.Mp3Settings);
    Code:
       0: aload_0
       1: aload_1
       2: putfield      #6                  // Field mp3Settings:Lsoftware/amazon/awssdk/services/mediaconvert/model/Mp3Settings;
       5: aload_0
       6: areturn

  public final software.amazon.awssdk.services.mediaconvert.model.OpusSettings$Builder getOpusSettings();
    Code:
       0: aload_0
       1: getfield      #5                  // Field opusSettings:Lsoftware/amazon/awssdk/services/mediaconvert/model/OpusSettings;
       4: ifnull        17
       7: aload_0
       8: getfield      #5                  // Field opusSettings:Lsoftware/amazon/awssdk/services/mediaconvert/model/OpusSettings;
      11: invokevirtual #52                 // Method software/amazon/awssdk/services/mediaconvert/model/OpusSettings.toBuilder:()Lsoftware/amazon/awssdk/services/mediaconvert/model/OpusSettings$Builder;
      14: goto          18
      17: aconst_null
      18: areturn

  public final void setOpusSettings(software.amazon.awssdk.services.mediaconvert.model.OpusSettings$BuilderImpl);
    Code:
       0: aload_0
       1: aload_1
       2: ifnull        12
       5: aload_1
       6: invokevirtual #53                 // Method software/amazon/awssdk/services/mediaconvert/model/OpusSettings$BuilderImpl.build:()Lsoftware/amazon/awssdk/services/mediaconvert/model/OpusSettings;
       9: goto          13
      12: aconst_null
      13: putfield      #5                  // Field opusSettings:Lsoftware/amazon/awssdk/services/mediaconvert/model/OpusSettings;
      16: return

  public final software.amazon.awssdk.services.mediaconvert.model.AudioCodecSettings$Builder opusSettings(software.amazon.awssdk.services.mediaconvert.model.OpusSettings);
    Code:
       0: aload_0
       1: aload_1
       2: putfield      #5                  // Field opusSettings:Lsoftware/amazon/awssdk/services/mediaconvert/model/OpusSettings;
       5: aload_0
       6: areturn

  public final software.amazon.awssdk.services.mediaconvert.model.VorbisSettings$Builder getVorbisSettings();
    Code:
       0: aload_0
       1: getfield      #4                  // Field vorbisSettings:Lsoftware/amazon/awssdk/services/mediaconvert/model/VorbisSettings;
       4: ifnull        17
       7: aload_0
       8: getfield      #4                  // Field vorbisSettings:Lsoftware/amazon/awssdk/services/mediaconvert/model/VorbisSettings;
      11: invokevirtual #54                 // Method software/amazon/awssdk/services/mediaconvert/model/VorbisSettings.toBuilder:()Lsoftware/amazon/awssdk/services/mediaconvert/model/VorbisSettings$Builder;
      14: goto          18
      17: aconst_null
      18: areturn

  public final void setVorbisSettings(software.amazon.awssdk.services.mediaconvert.model.VorbisSettings$BuilderImpl);
    Code:
       0: aload_0
       1: aload_1
       2: ifnull        12
       5: aload_1
       6: invokevirtual #55                 // Method software/amazon/awssdk/services/mediaconvert/model/VorbisSettings$BuilderImpl.build:()Lsoftware/amazon/awssdk/services/mediaconvert/model/VorbisSettings;
       9: goto          13
      12: aconst_null
      13: putfield      #4                  // Field vorbisSettings:Lsoftware/amazon/awssdk/services/mediaconvert/model/VorbisSettings;
      16: return

  public final software.amazon.awssdk.services.mediaconvert.model.AudioCodecSettings$Builder vorbisSettings(software.amazon.awssdk.services.mediaconvert.model.VorbisSettings);
    Code:
       0: aload_0
       1: aload_1
       2: putfield      #4                  // Field vorbisSettings:Lsoftware/amazon/awssdk/services/mediaconvert/model/VorbisSettings;
       5: aload_0
       6: areturn

  public final software.amazon.awssdk.services.mediaconvert.model.WavSettings$Builder getWavSettings();
    Code:
       0: aload_0
       1: getfield      #3                  // Field wavSettings:Lsoftware/amazon/awssdk/services/mediaconvert/model/WavSettings;
       4: ifnull        17
       7: aload_0
       8: getfield      #3                  // Field wavSettings:Lsoftware/amazon/awssdk/services/mediaconvert/model/WavSettings;
      11: invokevirtual #56                 // Method software/amazon/awssdk/services/mediaconvert/model/WavSettings.toBuilder:()Lsoftware/amazon/awssdk/services/mediaconvert/model/WavSettings$Builder;
      14: goto          18
      17: aconst_null
      18: areturn

  public final void setWavSettings(software.amazon.awssdk.services.mediaconvert.model.WavSettings$BuilderImpl);
    Code:
       0: aload_0
       1: aload_1
       2: ifnull        12
       5: aload_1
       6: invokevirtual #57                 // Method software/amazon/awssdk/services/mediaconvert/model/WavSettings$BuilderImpl.build:()Lsoftware/amazon/awssdk/services/mediaconvert/model/WavSettings;
       9: goto          13
      12: aconst_null
      13: putfield      #3                  // Field wavSettings:Lsoftware/amazon/awssdk/services/mediaconvert/model/WavSettings;
      16: return

  public final software.amazon.awssdk.services.mediaconvert.model.AudioCodecSettings$Builder wavSettings(software.amazon.awssdk.services.mediaconvert.model.WavSettings);
    Code:
       0: aload_0
       1: aload_1
       2: putfield      #3                  // Field wavSettings:Lsoftware/amazon/awssdk/services/mediaconvert/model/WavSettings;
       5: aload_0
       6: areturn

  public software.amazon.awssdk.services.mediaconvert.model.AudioCodecSettings build();
    Code:
       0: new           #58                 // class software/amazon/awssdk/services/mediaconvert/model/AudioCodecSettings
       3: dup
       4: aload_0
       5: aconst_null
       6: invokespecial #59                 // Method software/amazon/awssdk/services/mediaconvert/model/AudioCodecSettings."<init>":(Lsoftware/amazon/awssdk/services/mediaconvert/model/AudioCodecSettings$BuilderImpl;Lsoftware/amazon/awssdk/services/mediaconvert/model/AudioCodecSettings$1;)V
       9: areturn

  public java.util.List<software.amazon.awssdk.core.SdkField<?>> sdkFields();
    Code:
       0: invokestatic  #60                 // Method software/amazon/awssdk/services/mediaconvert/model/AudioCodecSettings.access$2500:()Ljava/util/List;
       3: areturn

  public java.lang.Object build();
    Code:
       0: aload_0
       1: invokevirtual #61                 // Method build:()Lsoftware/amazon/awssdk/services/mediaconvert/model/AudioCodecSettings;
       4: areturn

  static software.amazon.awssdk.services.mediaconvert.model.AacSettings access$000(software.amazon.awssdk.services.mediaconvert.model.AudioCodecSettings$BuilderImpl);
    Code:
       0: aload_0
       1: getfield      #13                 // Field aacSettings:Lsoftware/amazon/awssdk/services/mediaconvert/model/AacSettings;
       4: areturn

  static software.amazon.awssdk.services.mediaconvert.model.Ac3Settings access$100(software.amazon.awssdk.services.mediaconvert.model.AudioCodecSettings$BuilderImpl);
    Code:
       0: aload_0
       1: getfield      #12                 // Field ac3Settings:Lsoftware/amazon/awssdk/services/mediaconvert/model/Ac3Settings;
       4: areturn

  static software.amazon.awssdk.services.mediaconvert.model.AiffSettings access$200(software.amazon.awssdk.services.mediaconvert.model.AudioCodecSettings$BuilderImpl);
    Code:
       0: aload_0
       1: getfield      #11                 // Field aiffSettings:Lsoftware/amazon/awssdk/services/mediaconvert/model/AiffSettings;
       4: areturn

  static java.lang.String access$300(software.amazon.awssdk.services.mediaconvert.model.AudioCodecSettings$BuilderImpl);
    Code:
       0: aload_0
       1: getfield      #10                 // Field codec:Ljava/lang/String;
       4: areturn

  static software.amazon.awssdk.services.mediaconvert.model.Eac3AtmosSettings access$400(software.amazon.awssdk.services.mediaconvert.model.AudioCodecSettings$BuilderImpl);
    Code:
       0: aload_0
       1: getfield      #9                  // Field eac3AtmosSettings:Lsoftware/amazon/awssdk/services/mediaconvert/model/Eac3AtmosSettings;
       4: areturn

  static software.amazon.awssdk.services.mediaconvert.model.Eac3Settings access$500(software.amazon.awssdk.services.mediaconvert.model.AudioCodecSettings$BuilderImpl);
    Code:
       0: aload_0
       1: getfield      #8                  // Field eac3Settings:Lsoftware/amazon/awssdk/services/mediaconvert/model/Eac3Settings;
       4: areturn

  static software.amazon.awssdk.services.mediaconvert.model.Mp2Settings access$600(software.amazon.awssdk.services.mediaconvert.model.AudioCodecSettings$BuilderImpl);
    Code:
       0: aload_0
       1: getfield      #7                  // Field mp2Settings:Lsoftware/amazon/awssdk/services/mediaconvert/model/Mp2Settings;
       4: areturn

  static software.amazon.awssdk.services.mediaconvert.model.Mp3Settings access$700(software.amazon.awssdk.services.mediaconvert.model.AudioCodecSettings$BuilderImpl);
    Code:
       0: aload_0
       1: getfield      #6                  // Field mp3Settings:Lsoftware/amazon/awssdk/services/mediaconvert/model/Mp3Settings;
       4: areturn

  static software.amazon.awssdk.services.mediaconvert.model.OpusSettings access$800(software.amazon.awssdk.services.mediaconvert.model.AudioCodecSettings$BuilderImpl);
    Code:
       0: aload_0
       1: getfield      #5                  // Field opusSettings:Lsoftware/amazon/awssdk/services/mediaconvert/model/OpusSettings;
       4: areturn

  static software.amazon.awssdk.services.mediaconvert.model.VorbisSettings access$900(software.amazon.awssdk.services.mediaconvert.model.AudioCodecSettings$BuilderImpl);
    Code:
       0: aload_0
       1: getfield      #4                  // Field vorbisSettings:Lsoftware/amazon/awssdk/services/mediaconvert/model/VorbisSettings;
       4: areturn

  static software.amazon.awssdk.services.mediaconvert.model.WavSettings access$1000(software.amazon.awssdk.services.mediaconvert.model.AudioCodecSettings$BuilderImpl);
    Code:
       0: aload_0
       1: getfield      #3                  // Field wavSettings:Lsoftware/amazon/awssdk/services/mediaconvert/model/WavSettings;
       4: areturn

  software.amazon.awssdk.services.mediaconvert.model.AudioCodecSettings$BuilderImpl(software.amazon.awssdk.services.mediaconvert.model.AudioCodecSettings, software.amazon.awssdk.services.mediaconvert.model.AudioCodecSettings$1);
    Code:
       0: aload_0
       1: aload_1
       2: invokespecial #2                  // Method "<init>":(Lsoftware/amazon/awssdk/services/mediaconvert/model/AudioCodecSettings;)V
       5: return

  software.amazon.awssdk.services.mediaconvert.model.AudioCodecSettings$BuilderImpl(software.amazon.awssdk.services.mediaconvert.model.AudioCodecSettings$1);
    Code:
       0: aload_0
       1: invokespecial #1                  // Method "<init>":()V
       4: return
}
