Compiled from "AvcIntraUhdSettings.java"
final class software.amazon.awssdk.services.mediaconvert.model.AvcIntraUhdSettings$BuilderImpl implements software.amazon.awssdk.services.mediaconvert.model.AvcIntraUhdSettings$Builder {
  private java.lang.String qualityTuningLevel;

  private software.amazon.awssdk.services.mediaconvert.model.AvcIntraUhdSettings$BuilderImpl();
    Code:
       0: aload_0
       1: invokespecial #4                  // Method java/lang/Object."<init>":()V
       4: return

  private software.amazon.awssdk.services.mediaconvert.model.AvcIntraUhdSettings$BuilderImpl(software.amazon.awssdk.services.mediaconvert.model.AvcIntraUhdSettings);
    Code:
       0: aload_0
       1: invokespecial #4                  // Method java/lang/Object."<init>":()V
       4: aload_0
       5: aload_1
       6: invokestatic  #5                  // Method software/amazon/awssdk/services/mediaconvert/model/AvcIntraUhdSettings.access$300:(Lsoftware/amazon/awssdk/services/mediaconvert/model/AvcIntraUhdSettings;)Ljava/lang/String;
       9: invokevirtual #6                  // Method qualityTuningLevel:(Ljava/lang/String;)Lsoftware/amazon/awssdk/services/mediaconvert/model/AvcIntraUhdSettings$Builder;
      12: pop
      13: return

  public final java.lang.String getQualityTuningLevel();
    Code:
       0: aload_0
       1: getfield      #3                  // Field qualityTuningLevel:Ljava/lang/String;
       4: areturn

  public final void setQualityTuningLevel(java.lang.String);
    Code:
       0: aload_0
       1: aload_1
       2: putfield      #3                  // Field qualityTuningLevel:Ljava/lang/String;
       5: return

  public final software.amazon.awssdk.services.mediaconvert.model.AvcIntraUhdSettings$Builder qualityTuningLevel(java.lang.String);
    Code:
       0: aload_0
       1: aload_1
       2: putfield      #3                  // Field qualityTuningLevel:Ljava/lang/String;
       5: aload_0
       6: areturn

  public final software.amazon.awssdk.services.mediaconvert.model.AvcIntraUhdSettings$Builder qualityTuningLevel(software.amazon.awssdk.services.mediaconvert.model.AvcIntraUhdQualityTuningLevel);
    Code:
       0: aload_0
       1: aload_1
       2: ifnonnull     9
       5: aconst_null
       6: goto          13
       9: aload_1
      10: invokevirtual #7                  // Method software/amazon/awssdk/services/mediaconvert/model/AvcIntraUhdQualityTuningLevel.toString:()Ljava/lang/String;
      13: invokevirtual #6                  // Method qualityTuningLevel:(Ljava/lang/String;)Lsoftware/amazon/awssdk/services/mediaconvert/model/AvcIntraUhdSettings$Builder;
      16: pop
      17: aload_0
      18: areturn

  public software.amazon.awssdk.services.mediaconvert.model.AvcIntraUhdSettings build();
    Code:
       0: new           #8                  // class software/amazon/awssdk/services/mediaconvert/model/AvcIntraUhdSettings
       3: dup
       4: aload_0
       5: aconst_null
       6: invokespecial #9                  // Method software/amazon/awssdk/services/mediaconvert/model/AvcIntraUhdSettings."<init>":(Lsoftware/amazon/awssdk/services/mediaconvert/model/AvcIntraUhdSettings$BuilderImpl;Lsoftware/amazon/awssdk/services/mediaconvert/model/AvcIntraUhdSettings$1;)V
       9: areturn

  public java.util.List<software.amazon.awssdk.core.SdkField<?>> sdkFields();
    Code:
       0: invokestatic  #10                 // Method software/amazon/awssdk/services/mediaconvert/model/AvcIntraUhdSettings.access$500:()Ljava/util/List;
       3: areturn

  public java.lang.Object build();
    Code:
       0: aload_0
       1: invokevirtual #11                 // Method build:()Lsoftware/amazon/awssdk/services/mediaconvert/model/AvcIntraUhdSettings;
       4: areturn

  static java.lang.String access$000(software.amazon.awssdk.services.mediaconvert.model.AvcIntraUhdSettings$BuilderImpl);
    Code:
       0: aload_0
       1: getfield      #3                  // Field qualityTuningLevel:Ljava/lang/String;
       4: areturn

  software.amazon.awssdk.services.mediaconvert.model.AvcIntraUhdSettings$BuilderImpl(software.amazon.awssdk.services.mediaconvert.model.AvcIntraUhdSettings, software.amazon.awssdk.services.mediaconvert.model.AvcIntraUhdSettings$1);
    Code:
       0: aload_0
       1: aload_1
       2: invokespecial #2                  // Method "<init>":(Lsoftware/amazon/awssdk/services/mediaconvert/model/AvcIntraUhdSettings;)V
       5: return

  software.amazon.awssdk.services.mediaconvert.model.AvcIntraUhdSettings$BuilderImpl(software.amazon.awssdk.services.mediaconvert.model.AvcIntraUhdSettings$1);
    Code:
       0: aload_0
       1: invokespecial #1                  // Method "<init>":()V
       4: return
}
