Compiled from "HlsGroupSettings.java"
public final class software.amazon.awssdk.services.mediaconvert.model.HlsGroupSettings implements software.amazon.awssdk.core.SdkPojo, java.io.Serializable, software.amazon.awssdk.utils.builder.ToCopyableBuilder<software.amazon.awssdk.services.mediaconvert.model.HlsGroupSettings$Builder, software.amazon.awssdk.services.mediaconvert.model.HlsGroupSettings> {
  private static final software.amazon.awssdk.core.SdkField<java.util.List<java.lang.String>> AD_MARKERS_FIELD;

  private static final software.amazon.awssdk.core.SdkField<java.util.List<software.amazon.awssdk.services.mediaconvert.model.HlsAdditionalManifest>> ADDITIONAL_MANIFESTS_FIELD;

  private static final software.amazon.awssdk.core.SdkField<java.lang.String> AUDIO_ONLY_HEADER_FIELD;

  private static final software.amazon.awssdk.core.SdkField<java.lang.String> BASE_URL_FIELD;

  private static final software.amazon.awssdk.core.SdkField<java.util.List<software.amazon.awssdk.services.mediaconvert.model.HlsCaptionLanguageMapping>> CAPTION_LANGUAGE_MAPPINGS_FIELD;

  private static final software.amazon.awssdk.core.SdkField<java.lang.String> CAPTION_LANGUAGE_SETTING_FIELD;

  private static final software.amazon.awssdk.core.SdkField<java.lang.String> CAPTION_SEGMENT_LENGTH_CONTROL_FIELD;

  private static final software.amazon.awssdk.core.SdkField<java.lang.String> CLIENT_CACHE_FIELD;

  private static final software.amazon.awssdk.core.SdkField<java.lang.String> CODEC_SPECIFICATION_FIELD;

  private static final software.amazon.awssdk.core.SdkField<java.lang.String> DESTINATION_FIELD;

  private static final software.amazon.awssdk.core.SdkField<software.amazon.awssdk.services.mediaconvert.model.DestinationSettings> DESTINATION_SETTINGS_FIELD;

  private static final software.amazon.awssdk.core.SdkField<java.lang.String> DIRECTORY_STRUCTURE_FIELD;

  private static final software.amazon.awssdk.core.SdkField<software.amazon.awssdk.services.mediaconvert.model.HlsEncryptionSettings> ENCRYPTION_FIELD;

  private static final software.amazon.awssdk.core.SdkField<java.lang.String> IMAGE_BASED_TRICK_PLAY_FIELD;

  private static final software.amazon.awssdk.core.SdkField<software.amazon.awssdk.services.mediaconvert.model.HlsImageBasedTrickPlaySettings> IMAGE_BASED_TRICK_PLAY_SETTINGS_FIELD;

  private static final software.amazon.awssdk.core.SdkField<java.lang.String> MANIFEST_COMPRESSION_FIELD;

  private static final software.amazon.awssdk.core.SdkField<java.lang.String> MANIFEST_DURATION_FORMAT_FIELD;

  private static final software.amazon.awssdk.core.SdkField<java.lang.Double> MIN_FINAL_SEGMENT_LENGTH_FIELD;

  private static final software.amazon.awssdk.core.SdkField<java.lang.Integer> MIN_SEGMENT_LENGTH_FIELD;

  private static final software.amazon.awssdk.core.SdkField<java.lang.String> OUTPUT_SELECTION_FIELD;

  private static final software.amazon.awssdk.core.SdkField<java.lang.String> PROGRAM_DATE_TIME_FIELD;

  private static final software.amazon.awssdk.core.SdkField<java.lang.Integer> PROGRAM_DATE_TIME_PERIOD_FIELD;

  private static final software.amazon.awssdk.core.SdkField<java.lang.String> SEGMENT_CONTROL_FIELD;

  private static final software.amazon.awssdk.core.SdkField<java.lang.Integer> SEGMENT_LENGTH_FIELD;

  private static final software.amazon.awssdk.core.SdkField<java.lang.String> SEGMENT_LENGTH_CONTROL_FIELD;

  private static final software.amazon.awssdk.core.SdkField<java.lang.Integer> SEGMENTS_PER_SUBDIRECTORY_FIELD;

  private static final software.amazon.awssdk.core.SdkField<java.lang.String> STREAM_INF_RESOLUTION_FIELD;

  private static final software.amazon.awssdk.core.SdkField<java.lang.String> TARGET_DURATION_COMPATIBILITY_MODE_FIELD;

  private static final software.amazon.awssdk.core.SdkField<java.lang.String> TIMED_METADATA_ID3_FRAME_FIELD;

  private static final software.amazon.awssdk.core.SdkField<java.lang.Integer> TIMED_METADATA_ID3_PERIOD_FIELD;

  private static final software.amazon.awssdk.core.SdkField<java.lang.Integer> TIMESTAMP_DELTA_MILLISECONDS_FIELD;

  private static final java.util.List<software.amazon.awssdk.core.SdkField<?>> SDK_FIELDS;

  private static final long serialVersionUID;

  private final java.util.List<java.lang.String> adMarkers;

  private final java.util.List<software.amazon.awssdk.services.mediaconvert.model.HlsAdditionalManifest> additionalManifests;

  private final java.lang.String audioOnlyHeader;

  private final java.lang.String baseUrl;

  private final java.util.List<software.amazon.awssdk.services.mediaconvert.model.HlsCaptionLanguageMapping> captionLanguageMappings;

  private final java.lang.String captionLanguageSetting;

  private final java.lang.String captionSegmentLengthControl;

  private final java.lang.String clientCache;

  private final java.lang.String codecSpecification;

  private final java.lang.String destination;

  private final software.amazon.awssdk.services.mediaconvert.model.DestinationSettings destinationSettings;

  private final java.lang.String directoryStructure;

  private final software.amazon.awssdk.services.mediaconvert.model.HlsEncryptionSettings encryption;

  private final java.lang.String imageBasedTrickPlay;

  private final software.amazon.awssdk.services.mediaconvert.model.HlsImageBasedTrickPlaySettings imageBasedTrickPlaySettings;

  private final java.lang.String manifestCompression;

  private final java.lang.String manifestDurationFormat;

  private final java.lang.Double minFinalSegmentLength;

  private final java.lang.Integer minSegmentLength;

  private final java.lang.String outputSelection;

  private final java.lang.String programDateTime;

  private final java.lang.Integer programDateTimePeriod;

  private final java.lang.String segmentControl;

  private final java.lang.Integer segmentLength;

  private final java.lang.String segmentLengthControl;

  private final java.lang.Integer segmentsPerSubdirectory;

  private final java.lang.String streamInfResolution;

  private final java.lang.String targetDurationCompatibilityMode;

  private final java.lang.String timedMetadataId3Frame;

  private final java.lang.Integer timedMetadataId3Period;

  private final java.lang.Integer timestampDeltaMilliseconds;

  private software.amazon.awssdk.services.mediaconvert.model.HlsGroupSettings(software.amazon.awssdk.services.mediaconvert.model.HlsGroupSettings$BuilderImpl);
    Code:
       0: aload_0
       1: invokespecial #34                 // Method java/lang/Object."<init>":()V
       4: aload_0
       5: aload_1
       6: invokestatic  #35                 // Method software/amazon/awssdk/services/mediaconvert/model/HlsGroupSettings$BuilderImpl.access$000:(Lsoftware/amazon/awssdk/services/mediaconvert/model/HlsGroupSettings$BuilderImpl;)Ljava/util/List;
       9: putfield      #33                 // Field adMarkers:Ljava/util/List;
      12: aload_0
      13: aload_1
      14: invokestatic  #36                 // Method software/amazon/awssdk/services/mediaconvert/model/HlsGroupSettings$BuilderImpl.access$100:(Lsoftware/amazon/awssdk/services/mediaconvert/model/HlsGroupSettings$BuilderImpl;)Ljava/util/List;
      17: putfield      #32                 // Field additionalManifests:Ljava/util/List;
      20: aload_0
      21: aload_1
      22: invokestatic  #37                 // Method software/amazon/awssdk/services/mediaconvert/model/HlsGroupSettings$BuilderImpl.access$200:(Lsoftware/amazon/awssdk/services/mediaconvert/model/HlsGroupSettings$BuilderImpl;)Ljava/lang/String;
      25: putfield      #31                 // Field audioOnlyHeader:Ljava/lang/String;
      28: aload_0
      29: aload_1
      30: invokestatic  #38                 // Method software/amazon/awssdk/services/mediaconvert/model/HlsGroupSettings$BuilderImpl.access$300:(Lsoftware/amazon/awssdk/services/mediaconvert/model/HlsGroupSettings$BuilderImpl;)Ljava/lang/String;
      33: putfield      #30                 // Field baseUrl:Ljava/lang/String;
      36: aload_0
      37: aload_1
      38: invokestatic  #39                 // Method software/amazon/awssdk/services/mediaconvert/model/HlsGroupSettings$BuilderImpl.access$400:(Lsoftware/amazon/awssdk/services/mediaconvert/model/HlsGroupSettings$BuilderImpl;)Ljava/util/List;
      41: putfield      #29                 // Field captionLanguageMappings:Ljava/util/List;
      44: aload_0
      45: aload_1
      46: invokestatic  #40                 // Method software/amazon/awssdk/services/mediaconvert/model/HlsGroupSettings$BuilderImpl.access$500:(Lsoftware/amazon/awssdk/services/mediaconvert/model/HlsGroupSettings$BuilderImpl;)Ljava/lang/String;
      49: putfield      #28                 // Field captionLanguageSetting:Ljava/lang/String;
      52: aload_0
      53: aload_1
      54: invokestatic  #41                 // Method software/amazon/awssdk/services/mediaconvert/model/HlsGroupSettings$BuilderImpl.access$600:(Lsoftware/amazon/awssdk/services/mediaconvert/model/HlsGroupSettings$BuilderImpl;)Ljava/lang/String;
      57: putfield      #27                 // Field captionSegmentLengthControl:Ljava/lang/String;
      60: aload_0
      61: aload_1
      62: invokestatic  #42                 // Method software/amazon/awssdk/services/mediaconvert/model/HlsGroupSettings$BuilderImpl.access$700:(Lsoftware/amazon/awssdk/services/mediaconvert/model/HlsGroupSettings$BuilderImpl;)Ljava/lang/String;
      65: putfield      #26                 // Field clientCache:Ljava/lang/String;
      68: aload_0
      69: aload_1
      70: invokestatic  #43                 // Method software/amazon/awssdk/services/mediaconvert/model/HlsGroupSettings$BuilderImpl.access$800:(Lsoftware/amazon/awssdk/services/mediaconvert/model/HlsGroupSettings$BuilderImpl;)Ljava/lang/String;
      73: putfield      #25                 // Field codecSpecification:Ljava/lang/String;
      76: aload_0
      77: aload_1
      78: invokestatic  #44                 // Method software/amazon/awssdk/services/mediaconvert/model/HlsGroupSettings$BuilderImpl.access$900:(Lsoftware/amazon/awssdk/services/mediaconvert/model/HlsGroupSettings$BuilderImpl;)Ljava/lang/String;
      81: putfield      #24                 // Field destination:Ljava/lang/String;
      84: aload_0
      85: aload_1
      86: invokestatic  #45                 // Method software/amazon/awssdk/services/mediaconvert/model/HlsGroupSettings$BuilderImpl.access$1000:(Lsoftware/amazon/awssdk/services/mediaconvert/model/HlsGroupSettings$BuilderImpl;)Lsoftware/amazon/awssdk/services/mediaconvert/model/DestinationSettings;
      89: putfield      #23                 // Field destinationSettings:Lsoftware/amazon/awssdk/services/mediaconvert/model/DestinationSettings;
      92: aload_0
      93: aload_1
      94: invokestatic  #46                 // Method software/amazon/awssdk/services/mediaconvert/model/HlsGroupSettings$BuilderImpl.access$1100:(Lsoftware/amazon/awssdk/services/mediaconvert/model/HlsGroupSettings$BuilderImpl;)Ljava/lang/String;
      97: putfield      #22                 // Field directoryStructure:Ljava/lang/String;
     100: aload_0
     101: aload_1
     102: invokestatic  #47                 // Method software/amazon/awssdk/services/mediaconvert/model/HlsGroupSettings$BuilderImpl.access$1200:(Lsoftware/amazon/awssdk/services/mediaconvert/model/HlsGroupSettings$BuilderImpl;)Lsoftware/amazon/awssdk/services/mediaconvert/model/HlsEncryptionSettings;
     105: putfield      #21                 // Field encryption:Lsoftware/amazon/awssdk/services/mediaconvert/model/HlsEncryptionSettings;
     108: aload_0
     109: aload_1
     110: invokestatic  #48                 // Method software/amazon/awssdk/services/mediaconvert/model/HlsGroupSettings$BuilderImpl.access$1300:(Lsoftware/amazon/awssdk/services/mediaconvert/model/HlsGroupSettings$BuilderImpl;)Ljava/lang/String;
     113: putfield      #20                 // Field imageBasedTrickPlay:Ljava/lang/String;
     116: aload_0
     117: aload_1
     118: invokestatic  #49                 // Method software/amazon/awssdk/services/mediaconvert/model/HlsGroupSettings$BuilderImpl.access$1400:(Lsoftware/amazon/awssdk/services/mediaconvert/model/HlsGroupSettings$BuilderImpl;)Lsoftware/amazon/awssdk/services/mediaconvert/model/HlsImageBasedTrickPlaySettings;
     121: putfield      #19                 // Field imageBasedTrickPlaySettings:Lsoftware/amazon/awssdk/services/mediaconvert/model/HlsImageBasedTrickPlaySettings;
     124: aload_0
     125: aload_1
     126: invokestatic  #50                 // Method software/amazon/awssdk/services/mediaconvert/model/HlsGroupSettings$BuilderImpl.access$1500:(Lsoftware/amazon/awssdk/services/mediaconvert/model/HlsGroupSettings$BuilderImpl;)Ljava/lang/String;
     129: putfield      #18                 // Field manifestCompression:Ljava/lang/String;
     132: aload_0
     133: aload_1
     134: invokestatic  #51                 // Method software/amazon/awssdk/services/mediaconvert/model/HlsGroupSettings$BuilderImpl.access$1600:(Lsoftware/amazon/awssdk/services/mediaconvert/model/HlsGroupSettings$BuilderImpl;)Ljava/lang/String;
     137: putfield      #17                 // Field manifestDurationFormat:Ljava/lang/String;
     140: aload_0
     141: aload_1
     142: invokestatic  #52                 // Method software/amazon/awssdk/services/mediaconvert/model/HlsGroupSettings$BuilderImpl.access$1700:(Lsoftware/amazon/awssdk/services/mediaconvert/model/HlsGroupSettings$BuilderImpl;)Ljava/lang/Double;
     145: putfield      #16                 // Field minFinalSegmentLength:Ljava/lang/Double;
     148: aload_0
     149: aload_1
     150: invokestatic  #53                 // Method software/amazon/awssdk/services/mediaconvert/model/HlsGroupSettings$BuilderImpl.access$1800:(Lsoftware/amazon/awssdk/services/mediaconvert/model/HlsGroupSettings$BuilderImpl;)Ljava/lang/Integer;
     153: putfield      #15                 // Field minSegmentLength:Ljava/lang/Integer;
     156: aload_0
     157: aload_1
     158: invokestatic  #54                 // Method software/amazon/awssdk/services/mediaconvert/model/HlsGroupSettings$BuilderImpl.access$1900:(Lsoftware/amazon/awssdk/services/mediaconvert/model/HlsGroupSettings$BuilderImpl;)Ljava/lang/String;
     161: putfield      #14                 // Field outputSelection:Ljava/lang/String;
     164: aload_0
     165: aload_1
     166: invokestatic  #55                 // Method software/amazon/awssdk/services/mediaconvert/model/HlsGroupSettings$BuilderImpl.access$2000:(Lsoftware/amazon/awssdk/services/mediaconvert/model/HlsGroupSettings$BuilderImpl;)Ljava/lang/String;
     169: putfield      #13                 // Field programDateTime:Ljava/lang/String;
     172: aload_0
     173: aload_1
     174: invokestatic  #56                 // Method software/amazon/awssdk/services/mediaconvert/model/HlsGroupSettings$BuilderImpl.access$2100:(Lsoftware/amazon/awssdk/services/mediaconvert/model/HlsGroupSettings$BuilderImpl;)Ljava/lang/Integer;
     177: putfield      #12                 // Field programDateTimePeriod:Ljava/lang/Integer;
     180: aload_0
     181: aload_1
     182: invokestatic  #57                 // Method software/amazon/awssdk/services/mediaconvert/model/HlsGroupSettings$BuilderImpl.access$2200:(Lsoftware/amazon/awssdk/services/mediaconvert/model/HlsGroupSettings$BuilderImpl;)Ljava/lang/String;
     185: putfield      #11                 // Field segmentControl:Ljava/lang/String;
     188: aload_0
     189: aload_1
     190: invokestatic  #58                 // Method software/amazon/awssdk/services/mediaconvert/model/HlsGroupSettings$BuilderImpl.access$2300:(Lsoftware/amazon/awssdk/services/mediaconvert/model/HlsGroupSettings$BuilderImpl;)Ljava/lang/Integer;
     193: putfield      #10                 // Field segmentLength:Ljava/lang/Integer;
     196: aload_0
     197: aload_1
     198: invokestatic  #59                 // Method software/amazon/awssdk/services/mediaconvert/model/HlsGroupSettings$BuilderImpl.access$2400:(Lsoftware/amazon/awssdk/services/mediaconvert/model/HlsGroupSettings$BuilderImpl;)Ljava/lang/String;
     201: putfield      #9                  // Field segmentLengthControl:Ljava/lang/String;
     204: aload_0
     205: aload_1
     206: invokestatic  #60                 // Method software/amazon/awssdk/services/mediaconvert/model/HlsGroupSettings$BuilderImpl.access$2500:(Lsoftware/amazon/awssdk/services/mediaconvert/model/HlsGroupSettings$BuilderImpl;)Ljava/lang/Integer;
     209: putfield      #8                  // Field segmentsPerSubdirectory:Ljava/lang/Integer;
     212: aload_0
     213: aload_1
     214: invokestatic  #61                 // Method software/amazon/awssdk/services/mediaconvert/model/HlsGroupSettings$BuilderImpl.access$2600:(Lsoftware/amazon/awssdk/services/mediaconvert/model/HlsGroupSettings$BuilderImpl;)Ljava/lang/String;
     217: putfield      #7                  // Field streamInfResolution:Ljava/lang/String;
     220: aload_0
     221: aload_1
     222: invokestatic  #62                 // Method software/amazon/awssdk/services/mediaconvert/model/HlsGroupSettings$BuilderImpl.access$2700:(Lsoftware/amazon/awssdk/services/mediaconvert/model/HlsGroupSettings$BuilderImpl;)Ljava/lang/String;
     225: putfield      #6                  // Field targetDurationCompatibilityMode:Ljava/lang/String;
     228: aload_0
     229: aload_1
     230: invokestatic  #63                 // Method software/amazon/awssdk/services/mediaconvert/model/HlsGroupSettings$BuilderImpl.access$2800:(Lsoftware/amazon/awssdk/services/mediaconvert/model/HlsGroupSettings$BuilderImpl;)Ljava/lang/String;
     233: putfield      #5                  // Field timedMetadataId3Frame:Ljava/lang/String;
     236: aload_0
     237: aload_1
     238: invokestatic  #64                 // Method software/amazon/awssdk/services/mediaconvert/model/HlsGroupSettings$BuilderImpl.access$2900:(Lsoftware/amazon/awssdk/services/mediaconvert/model/HlsGroupSettings$BuilderImpl;)Ljava/lang/Integer;
     241: putfield      #4                  // Field timedMetadataId3Period:Ljava/lang/Integer;
     244: aload_0
     245: aload_1
     246: invokestatic  #65                 // Method software/amazon/awssdk/services/mediaconvert/model/HlsGroupSettings$BuilderImpl.access$3000:(Lsoftware/amazon/awssdk/services/mediaconvert/model/HlsGroupSettings$BuilderImpl;)Ljava/lang/Integer;
     249: putfield      #3                  // Field timestampDeltaMilliseconds:Ljava/lang/Integer;
     252: return

  public final java.util.List<software.amazon.awssdk.services.mediaconvert.model.HlsAdMarkers> adMarkers();
    Code:
       0: aload_0
       1: getfield      #33                 // Field adMarkers:Ljava/util/List;
       4: invokestatic  #66                 // Method software/amazon/awssdk/services/mediaconvert/model/___listOfHlsAdMarkersCopier.copyStringToEnum:(Ljava/util/Collection;)Ljava/util/List;
       7: areturn

  public final boolean hasAdMarkers();
    Code:
       0: aload_0
       1: getfield      #33                 // Field adMarkers:Ljava/util/List;
       4: ifnull        21
       7: aload_0
       8: getfield      #33                 // Field adMarkers:Ljava/util/List;
      11: instanceof    #67                 // class software/amazon/awssdk/core/util/SdkAutoConstructList
      14: ifne          21
      17: iconst_1
      18: goto          22
      21: iconst_0
      22: ireturn

  public final java.util.List<java.lang.String> adMarkersAsStrings();
    Code:
       0: aload_0
       1: getfield      #33                 // Field adMarkers:Ljava/util/List;
       4: areturn

  public final boolean hasAdditionalManifests();
    Code:
       0: aload_0
       1: getfield      #32                 // Field additionalManifests:Ljava/util/List;
       4: ifnull        21
       7: aload_0
       8: getfield      #32                 // Field additionalManifests:Ljava/util/List;
      11: instanceof    #67                 // class software/amazon/awssdk/core/util/SdkAutoConstructList
      14: ifne          21
      17: iconst_1
      18: goto          22
      21: iconst_0
      22: ireturn

  public final java.util.List<software.amazon.awssdk.services.mediaconvert.model.HlsAdditionalManifest> additionalManifests();
    Code:
       0: aload_0
       1: getfield      #32                 // Field additionalManifests:Ljava/util/List;
       4: areturn

  public final software.amazon.awssdk.services.mediaconvert.model.HlsAudioOnlyHeader audioOnlyHeader();
    Code:
       0: aload_0
       1: getfield      #31                 // Field audioOnlyHeader:Ljava/lang/String;
       4: invokestatic  #68                 // Method software/amazon/awssdk/services/mediaconvert/model/HlsAudioOnlyHeader.fromValue:(Ljava/lang/String;)Lsoftware/amazon/awssdk/services/mediaconvert/model/HlsAudioOnlyHeader;
       7: areturn

  public final java.lang.String audioOnlyHeaderAsString();
    Code:
       0: aload_0
       1: getfield      #31                 // Field audioOnlyHeader:Ljava/lang/String;
       4: areturn

  public final java.lang.String baseUrl();
    Code:
       0: aload_0
       1: getfield      #30                 // Field baseUrl:Ljava/lang/String;
       4: areturn

  public final boolean hasCaptionLanguageMappings();
    Code:
       0: aload_0
       1: getfield      #29                 // Field captionLanguageMappings:Ljava/util/List;
       4: ifnull        21
       7: aload_0
       8: getfield      #29                 // Field captionLanguageMappings:Ljava/util/List;
      11: instanceof    #67                 // class software/amazon/awssdk/core/util/SdkAutoConstructList
      14: ifne          21
      17: iconst_1
      18: goto          22
      21: iconst_0
      22: ireturn

  public final java.util.List<software.amazon.awssdk.services.mediaconvert.model.HlsCaptionLanguageMapping> captionLanguageMappings();
    Code:
       0: aload_0
       1: getfield      #29                 // Field captionLanguageMappings:Ljava/util/List;
       4: areturn

  public final software.amazon.awssdk.services.mediaconvert.model.HlsCaptionLanguageSetting captionLanguageSetting();
    Code:
       0: aload_0
       1: getfield      #28                 // Field captionLanguageSetting:Ljava/lang/String;
       4: invokestatic  #69                 // Method software/amazon/awssdk/services/mediaconvert/model/HlsCaptionLanguageSetting.fromValue:(Ljava/lang/String;)Lsoftware/amazon/awssdk/services/mediaconvert/model/HlsCaptionLanguageSetting;
       7: areturn

  public final java.lang.String captionLanguageSettingAsString();
    Code:
       0: aload_0
       1: getfield      #28                 // Field captionLanguageSetting:Ljava/lang/String;
       4: areturn

  public final software.amazon.awssdk.services.mediaconvert.model.HlsCaptionSegmentLengthControl captionSegmentLengthControl();
    Code:
       0: aload_0
       1: getfield      #27                 // Field captionSegmentLengthControl:Ljava/lang/String;
       4: invokestatic  #70                 // Method software/amazon/awssdk/services/mediaconvert/model/HlsCaptionSegmentLengthControl.fromValue:(Ljava/lang/String;)Lsoftware/amazon/awssdk/services/mediaconvert/model/HlsCaptionSegmentLengthControl;
       7: areturn

  public final java.lang.String captionSegmentLengthControlAsString();
    Code:
       0: aload_0
       1: getfield      #27                 // Field captionSegmentLengthControl:Ljava/lang/String;
       4: areturn

  public final software.amazon.awssdk.services.mediaconvert.model.HlsClientCache clientCache();
    Code:
       0: aload_0
       1: getfield      #26                 // Field clientCache:Ljava/lang/String;
       4: invokestatic  #71                 // Method software/amazon/awssdk/services/mediaconvert/model/HlsClientCache.fromValue:(Ljava/lang/String;)Lsoftware/amazon/awssdk/services/mediaconvert/model/HlsClientCache;
       7: areturn

  public final java.lang.String clientCacheAsString();
    Code:
       0: aload_0
       1: getfield      #26                 // Field clientCache:Ljava/lang/String;
       4: areturn

  public final software.amazon.awssdk.services.mediaconvert.model.HlsCodecSpecification codecSpecification();
    Code:
       0: aload_0
       1: getfield      #25                 // Field codecSpecification:Ljava/lang/String;
       4: invokestatic  #72                 // Method software/amazon/awssdk/services/mediaconvert/model/HlsCodecSpecification.fromValue:(Ljava/lang/String;)Lsoftware/amazon/awssdk/services/mediaconvert/model/HlsCodecSpecification;
       7: areturn

  public final java.lang.String codecSpecificationAsString();
    Code:
       0: aload_0
       1: getfield      #25                 // Field codecSpecification:Ljava/lang/String;
       4: areturn

  public final java.lang.String destination();
    Code:
       0: aload_0
       1: getfield      #24                 // Field destination:Ljava/lang/String;
       4: areturn

  public final software.amazon.awssdk.services.mediaconvert.model.DestinationSettings destinationSettings();
    Code:
       0: aload_0
       1: getfield      #23                 // Field destinationSettings:Lsoftware/amazon/awssdk/services/mediaconvert/model/DestinationSettings;
       4: areturn

  public final software.amazon.awssdk.services.mediaconvert.model.HlsDirectoryStructure directoryStructure();
    Code:
       0: aload_0
       1: getfield      #22                 // Field directoryStructure:Ljava/lang/String;
       4: invokestatic  #73                 // Method software/amazon/awssdk/services/mediaconvert/model/HlsDirectoryStructure.fromValue:(Ljava/lang/String;)Lsoftware/amazon/awssdk/services/mediaconvert/model/HlsDirectoryStructure;
       7: areturn

  public final java.lang.String directoryStructureAsString();
    Code:
       0: aload_0
       1: getfield      #22                 // Field directoryStructure:Ljava/lang/String;
       4: areturn

  public final software.amazon.awssdk.services.mediaconvert.model.HlsEncryptionSettings encryption();
    Code:
       0: aload_0
       1: getfield      #21                 // Field encryption:Lsoftware/amazon/awssdk/services/mediaconvert/model/HlsEncryptionSettings;
       4: areturn

  public final software.amazon.awssdk.services.mediaconvert.model.HlsImageBasedTrickPlay imageBasedTrickPlay();
    Code:
       0: aload_0
       1: getfield      #20                 // Field imageBasedTrickPlay:Ljava/lang/String;
       4: invokestatic  #74                 // Method software/amazon/awssdk/services/mediaconvert/model/HlsImageBasedTrickPlay.fromValue:(Ljava/lang/String;)Lsoftware/amazon/awssdk/services/mediaconvert/model/HlsImageBasedTrickPlay;
       7: areturn

  public final java.lang.String imageBasedTrickPlayAsString();
    Code:
       0: aload_0
       1: getfield      #20                 // Field imageBasedTrickPlay:Ljava/lang/String;
       4: areturn

  public final software.amazon.awssdk.services.mediaconvert.model.HlsImageBasedTrickPlaySettings imageBasedTrickPlaySettings();
    Code:
       0: aload_0
       1: getfield      #19                 // Field imageBasedTrickPlaySettings:Lsoftware/amazon/awssdk/services/mediaconvert/model/HlsImageBasedTrickPlaySettings;
       4: areturn

  public final software.amazon.awssdk.services.mediaconvert.model.HlsManifestCompression manifestCompression();
    Code:
       0: aload_0
       1: getfield      #18                 // Field manifestCompression:Ljava/lang/String;
       4: invokestatic  #75                 // Method software/amazon/awssdk/services/mediaconvert/model/HlsManifestCompression.fromValue:(Ljava/lang/String;)Lsoftware/amazon/awssdk/services/mediaconvert/model/HlsManifestCompression;
       7: areturn

  public final java.lang.String manifestCompressionAsString();
    Code:
       0: aload_0
       1: getfield      #18                 // Field manifestCompression:Ljava/lang/String;
       4: areturn

  public final software.amazon.awssdk.services.mediaconvert.model.HlsManifestDurationFormat manifestDurationFormat();
    Code:
       0: aload_0
       1: getfield      #17                 // Field manifestDurationFormat:Ljava/lang/String;
       4: invokestatic  #76                 // Method software/amazon/awssdk/services/mediaconvert/model/HlsManifestDurationFormat.fromValue:(Ljava/lang/String;)Lsoftware/amazon/awssdk/services/mediaconvert/model/HlsManifestDurationFormat;
       7: areturn

  public final java.lang.String manifestDurationFormatAsString();
    Code:
       0: aload_0
       1: getfield      #17                 // Field manifestDurationFormat:Ljava/lang/String;
       4: areturn

  public final java.lang.Double minFinalSegmentLength();
    Code:
       0: aload_0
       1: getfield      #16                 // Field minFinalSegmentLength:Ljava/lang/Double;
       4: areturn

  public final java.lang.Integer minSegmentLength();
    Code:
       0: aload_0
       1: getfield      #15                 // Field minSegmentLength:Ljava/lang/Integer;
       4: areturn

  public final software.amazon.awssdk.services.mediaconvert.model.HlsOutputSelection outputSelection();
    Code:
       0: aload_0
       1: getfield      #14                 // Field outputSelection:Ljava/lang/String;
       4: invokestatic  #77                 // Method software/amazon/awssdk/services/mediaconvert/model/HlsOutputSelection.fromValue:(Ljava/lang/String;)Lsoftware/amazon/awssdk/services/mediaconvert/model/HlsOutputSelection;
       7: areturn

  public final java.lang.String outputSelectionAsString();
    Code:
       0: aload_0
       1: getfield      #14                 // Field outputSelection:Ljava/lang/String;
       4: areturn

  public final software.amazon.awssdk.services.mediaconvert.model.HlsProgramDateTime programDateTime();
    Code:
       0: aload_0
       1: getfield      #13                 // Field programDateTime:Ljava/lang/String;
       4: invokestatic  #78                 // Method software/amazon/awssdk/services/mediaconvert/model/HlsProgramDateTime.fromValue:(Ljava/lang/String;)Lsoftware/amazon/awssdk/services/mediaconvert/model/HlsProgramDateTime;
       7: areturn

  public final java.lang.String programDateTimeAsString();
    Code:
       0: aload_0
       1: getfield      #13                 // Field programDateTime:Ljava/lang/String;
       4: areturn

  public final java.lang.Integer programDateTimePeriod();
    Code:
       0: aload_0
       1: getfield      #12                 // Field programDateTimePeriod:Ljava/lang/Integer;
       4: areturn

  public final software.amazon.awssdk.services.mediaconvert.model.HlsSegmentControl segmentControl();
    Code:
       0: aload_0
       1: getfield      #11                 // Field segmentControl:Ljava/lang/String;
       4: invokestatic  #79                 // Method software/amazon/awssdk/services/mediaconvert/model/HlsSegmentControl.fromValue:(Ljava/lang/String;)Lsoftware/amazon/awssdk/services/mediaconvert/model/HlsSegmentControl;
       7: areturn

  public final java.lang.String segmentControlAsString();
    Code:
       0: aload_0
       1: getfield      #11                 // Field segmentControl:Ljava/lang/String;
       4: areturn

  public final java.lang.Integer segmentLength();
    Code:
       0: aload_0
       1: getfield      #10                 // Field segmentLength:Ljava/lang/Integer;
       4: areturn

  public final software.amazon.awssdk.services.mediaconvert.model.HlsSegmentLengthControl segmentLengthControl();
    Code:
       0: aload_0
       1: getfield      #9                  // Field segmentLengthControl:Ljava/lang/String;
       4: invokestatic  #80                 // Method software/amazon/awssdk/services/mediaconvert/model/HlsSegmentLengthControl.fromValue:(Ljava/lang/String;)Lsoftware/amazon/awssdk/services/mediaconvert/model/HlsSegmentLengthControl;
       7: areturn

  public final java.lang.String segmentLengthControlAsString();
    Code:
       0: aload_0
       1: getfield      #9                  // Field segmentLengthControl:Ljava/lang/String;
       4: areturn

  public final java.lang.Integer segmentsPerSubdirectory();
    Code:
       0: aload_0
       1: getfield      #8                  // Field segmentsPerSubdirectory:Ljava/lang/Integer;
       4: areturn

  public final software.amazon.awssdk.services.mediaconvert.model.HlsStreamInfResolution streamInfResolution();
    Code:
       0: aload_0
       1: getfield      #7                  // Field streamInfResolution:Ljava/lang/String;
       4: invokestatic  #81                 // Method software/amazon/awssdk/services/mediaconvert/model/HlsStreamInfResolution.fromValue:(Ljava/lang/String;)Lsoftware/amazon/awssdk/services/mediaconvert/model/HlsStreamInfResolution;
       7: areturn

  public final java.lang.String streamInfResolutionAsString();
    Code:
       0: aload_0
       1: getfield      #7                  // Field streamInfResolution:Ljava/lang/String;
       4: areturn

  public final software.amazon.awssdk.services.mediaconvert.model.HlsTargetDurationCompatibilityMode targetDurationCompatibilityMode();
    Code:
       0: aload_0
       1: getfield      #6                  // Field targetDurationCompatibilityMode:Ljava/lang/String;
       4: invokestatic  #82                 // Method software/amazon/awssdk/services/mediaconvert/model/HlsTargetDurationCompatibilityMode.fromValue:(Ljava/lang/String;)Lsoftware/amazon/awssdk/services/mediaconvert/model/HlsTargetDurationCompatibilityMode;
       7: areturn

  public final java.lang.String targetDurationCompatibilityModeAsString();
    Code:
       0: aload_0
       1: getfield      #6                  // Field targetDurationCompatibilityMode:Ljava/lang/String;
       4: areturn

  public final software.amazon.awssdk.services.mediaconvert.model.HlsTimedMetadataId3Frame timedMetadataId3Frame();
    Code:
       0: aload_0
       1: getfield      #5                  // Field timedMetadataId3Frame:Ljava/lang/String;
       4: invokestatic  #83                 // Method software/amazon/awssdk/services/mediaconvert/model/HlsTimedMetadataId3Frame.fromValue:(Ljava/lang/String;)Lsoftware/amazon/awssdk/services/mediaconvert/model/HlsTimedMetadataId3Frame;
       7: areturn

  public final java.lang.String timedMetadataId3FrameAsString();
    Code:
       0: aload_0
       1: getfield      #5                  // Field timedMetadataId3Frame:Ljava/lang/String;
       4: areturn

  public final java.lang.Integer timedMetadataId3Period();
    Code:
       0: aload_0
       1: getfield      #4                  // Field timedMetadataId3Period:Ljava/lang/Integer;
       4: areturn

  public final java.lang.Integer timestampDeltaMilliseconds();
    Code:
       0: aload_0
       1: getfield      #3                  // Field timestampDeltaMilliseconds:Ljava/lang/Integer;
       4: areturn

  public software.amazon.awssdk.services.mediaconvert.model.HlsGroupSettings$Builder toBuilder();
    Code:
       0: new           #84                 // class software/amazon/awssdk/services/mediaconvert/model/HlsGroupSettings$BuilderImpl
       3: dup
       4: aload_0
       5: aconst_null
       6: invokespecial #85                 // Method software/amazon/awssdk/services/mediaconvert/model/HlsGroupSettings$BuilderImpl."<init>":(Lsoftware/amazon/awssdk/services/mediaconvert/model/HlsGroupSettings;Lsoftware/amazon/awssdk/services/mediaconvert/model/HlsGroupSettings$1;)V
       9: areturn

  public static software.amazon.awssdk.services.mediaconvert.model.HlsGroupSettings$Builder builder();
    Code:
       0: new           #84                 // class software/amazon/awssdk/services/mediaconvert/model/HlsGroupSettings$BuilderImpl
       3: dup
       4: aconst_null
       5: invokespecial #86                 // Method software/amazon/awssdk/services/mediaconvert/model/HlsGroupSettings$BuilderImpl."<init>":(Lsoftware/amazon/awssdk/services/mediaconvert/model/HlsGroupSettings$1;)V
       8: areturn

  public static java.lang.Class<? extends software.amazon.awssdk.services.mediaconvert.model.HlsGroupSettings$Builder> serializableBuilderClass();
    Code:
       0: ldc           #84                 // class software/amazon/awssdk/services/mediaconvert/model/HlsGroupSettings$BuilderImpl
       2: areturn

  public final int hashCode();
    Code:
       0: iconst_1
       1: istore_1
       2: bipush        31
       4: iload_1
       5: imul
       6: aload_0
       7: invokevirtual #87                 // Method hasAdMarkers:()Z
      10: ifeq          20
      13: aload_0
      14: invokevirtual #88                 // Method adMarkersAsStrings:()Ljava/util/List;
      17: goto          21
      20: aconst_null
      21: invokestatic  #89                 // Method java/util/Objects.hashCode:(Ljava/lang/Object;)I
      24: iadd
      25: istore_1
      26: bipush        31
      28: iload_1
      29: imul
      30: aload_0
      31: invokevirtual #90                 // Method hasAdditionalManifests:()Z
      34: ifeq          44
      37: aload_0
      38: invokevirtual #91                 // Method additionalManifests:()Ljava/util/List;
      41: goto          45
      44: aconst_null
      45: invokestatic  #89                 // Method java/util/Objects.hashCode:(Ljava/lang/Object;)I
      48: iadd
      49: istore_1
      50: bipush        31
      52: iload_1
      53: imul
      54: aload_0
      55: invokevirtual #92                 // Method audioOnlyHeaderAsString:()Ljava/lang/String;
      58: invokestatic  #89                 // Method java/util/Objects.hashCode:(Ljava/lang/Object;)I
      61: iadd
      62: istore_1
      63: bipush        31
      65: iload_1
      66: imul
      67: aload_0
      68: invokevirtual #93                 // Method baseUrl:()Ljava/lang/String;
      71: invokestatic  #89                 // Method java/util/Objects.hashCode:(Ljava/lang/Object;)I
      74: iadd
      75: istore_1
      76: bipush        31
      78: iload_1
      79: imul
      80: aload_0
      81: invokevirtual #94                 // Method hasCaptionLanguageMappings:()Z
      84: ifeq          94
      87: aload_0
      88: invokevirtual #95                 // Method captionLanguageMappings:()Ljava/util/List;
      91: goto          95
      94: aconst_null
      95: invokestatic  #89                 // Method java/util/Objects.hashCode:(Ljava/lang/Object;)I
      98: iadd
      99: istore_1
     100: bipush        31
     102: iload_1
     103: imul
     104: aload_0
     105: invokevirtual #96                 // Method captionLanguageSettingAsString:()Ljava/lang/String;
     108: invokestatic  #89                 // Method java/util/Objects.hashCode:(Ljava/lang/Object;)I
     111: iadd
     112: istore_1
     113: bipush        31
     115: iload_1
     116: imul
     117: aload_0
     118: invokevirtual #97                 // Method captionSegmentLengthControlAsString:()Ljava/lang/String;
     121: invokestatic  #89                 // Method java/util/Objects.hashCode:(Ljava/lang/Object;)I
     124: iadd
     125: istore_1
     126: bipush        31
     128: iload_1
     129: imul
     130: aload_0
     131: invokevirtual #98                 // Method clientCacheAsString:()Ljava/lang/String;
     134: invokestatic  #89                 // Method java/util/Objects.hashCode:(Ljava/lang/Object;)I
     137: iadd
     138: istore_1
     139: bipush        31
     141: iload_1
     142: imul
     143: aload_0
     144: invokevirtual #99                 // Method codecSpecificationAsString:()Ljava/lang/String;
     147: invokestatic  #89                 // Method java/util/Objects.hashCode:(Ljava/lang/Object;)I
     150: iadd
     151: istore_1
     152: bipush        31
     154: iload_1
     155: imul
     156: aload_0
     157: invokevirtual #100                // Method destination:()Ljava/lang/String;
     160: invokestatic  #89                 // Method java/util/Objects.hashCode:(Ljava/lang/Object;)I
     163: iadd
     164: istore_1
     165: bipush        31
     167: iload_1
     168: imul
     169: aload_0
     170: invokevirtual #101                // Method destinationSettings:()Lsoftware/amazon/awssdk/services/mediaconvert/model/DestinationSettings;
     173: invokestatic  #89                 // Method java/util/Objects.hashCode:(Ljava/lang/Object;)I
     176: iadd
     177: istore_1
     178: bipush        31
     180: iload_1
     181: imul
     182: aload_0
     183: invokevirtual #102                // Method directoryStructureAsString:()Ljava/lang/String;
     186: invokestatic  #89                 // Method java/util/Objects.hashCode:(Ljava/lang/Object;)I
     189: iadd
     190: istore_1
     191: bipush        31
     193: iload_1
     194: imul
     195: aload_0
     196: invokevirtual #103                // Method encryption:()Lsoftware/amazon/awssdk/services/mediaconvert/model/HlsEncryptionSettings;
     199: invokestatic  #89                 // Method java/util/Objects.hashCode:(Ljava/lang/Object;)I
     202: iadd
     203: istore_1
     204: bipush        31
     206: iload_1
     207: imul
     208: aload_0
     209: invokevirtual #104                // Method imageBasedTrickPlayAsString:()Ljava/lang/String;
     212: invokestatic  #89                 // Method java/util/Objects.hashCode:(Ljava/lang/Object;)I
     215: iadd
     216: istore_1
     217: bipush        31
     219: iload_1
     220: imul
     221: aload_0
     222: invokevirtual #105                // Method imageBasedTrickPlaySettings:()Lsoftware/amazon/awssdk/services/mediaconvert/model/HlsImageBasedTrickPlaySettings;
     225: invokestatic  #89                 // Method java/util/Objects.hashCode:(Ljava/lang/Object;)I
     228: iadd
     229: istore_1
     230: bipush        31
     232: iload_1
     233: imul
     234: aload_0
     235: invokevirtual #106                // Method manifestCompressionAsString:()Ljava/lang/String;
     238: invokestatic  #89                 // Method java/util/Objects.hashCode:(Ljava/lang/Object;)I
     241: iadd
     242: istore_1
     243: bipush        31
     245: iload_1
     246: imul
     247: aload_0
     248: invokevirtual #107                // Method manifestDurationFormatAsString:()Ljava/lang/String;
     251: invokestatic  #89                 // Method java/util/Objects.hashCode:(Ljava/lang/Object;)I
     254: iadd
     255: istore_1
     256: bipush        31
     258: iload_1
     259: imul
     260: aload_0
     261: invokevirtual #108                // Method minFinalSegmentLength:()Ljava/lang/Double;
     264: invokestatic  #89                 // Method java/util/Objects.hashCode:(Ljava/lang/Object;)I
     267: iadd
     268: istore_1
     269: bipush        31
     271: iload_1
     272: imul
     273: aload_0
     274: invokevirtual #109                // Method minSegmentLength:()Ljava/lang/Integer;
     277: invokestatic  #89                 // Method java/util/Objects.hashCode:(Ljava/lang/Object;)I
     280: iadd
     281: istore_1
     282: bipush        31
     284: iload_1
     285: imul
     286: aload_0
     287: invokevirtual #110                // Method outputSelectionAsString:()Ljava/lang/String;
     290: invokestatic  #89                 // Method java/util/Objects.hashCode:(Ljava/lang/Object;)I
     293: iadd
     294: istore_1
     295: bipush        31
     297: iload_1
     298: imul
     299: aload_0
     300: invokevirtual #111                // Method programDateTimeAsString:()Ljava/lang/String;
     303: invokestatic  #89                 // Method java/util/Objects.hashCode:(Ljava/lang/Object;)I
     306: iadd
     307: istore_1
     308: bipush        31
     310: iload_1
     311: imul
     312: aload_0
     313: invokevirtual #112                // Method programDateTimePeriod:()Ljava/lang/Integer;
     316: invokestatic  #89                 // Method java/util/Objects.hashCode:(Ljava/lang/Object;)I
     319: iadd
     320: istore_1
     321: bipush        31
     323: iload_1
     324: imul
     325: aload_0
     326: invokevirtual #113                // Method segmentControlAsString:()Ljava/lang/String;
     329: invokestatic  #89                 // Method java/util/Objects.hashCode:(Ljava/lang/Object;)I
     332: iadd
     333: istore_1
     334: bipush        31
     336: iload_1
     337: imul
     338: aload_0
     339: invokevirtual #114                // Method segmentLength:()Ljava/lang/Integer;
     342: invokestatic  #89                 // Method java/util/Objects.hashCode:(Ljava/lang/Object;)I
     345: iadd
     346: istore_1
     347: bipush        31
     349: iload_1
     350: imul
     351: aload_0
     352: invokevirtual #115                // Method segmentLengthControlAsString:()Ljava/lang/String;
     355: invokestatic  #89                 // Method java/util/Objects.hashCode:(Ljava/lang/Object;)I
     358: iadd
     359: istore_1
     360: bipush        31
     362: iload_1
     363: imul
     364: aload_0
     365: invokevirtual #116                // Method segmentsPerSubdirectory:()Ljava/lang/Integer;
     368: invokestatic  #89                 // Method java/util/Objects.hashCode:(Ljava/lang/Object;)I
     371: iadd
     372: istore_1
     373: bipush        31
     375: iload_1
     376: imul
     377: aload_0
     378: invokevirtual #117                // Method streamInfResolutionAsString:()Ljava/lang/String;
     381: invokestatic  #89                 // Method java/util/Objects.hashCode:(Ljava/lang/Object;)I
     384: iadd
     385: istore_1
     386: bipush        31
     388: iload_1
     389: imul
     390: aload_0
     391: invokevirtual #118                // Method targetDurationCompatibilityModeAsString:()Ljava/lang/String;
     394: invokestatic  #89                 // Method java/util/Objects.hashCode:(Ljava/lang/Object;)I
     397: iadd
     398: istore_1
     399: bipush        31
     401: iload_1
     402: imul
     403: aload_0
     404: invokevirtual #119                // Method timedMetadataId3FrameAsString:()Ljava/lang/String;
     407: invokestatic  #89                 // Method java/util/Objects.hashCode:(Ljava/lang/Object;)I
     410: iadd
     411: istore_1
     412: bipush        31
     414: iload_1
     415: imul
     416: aload_0
     417: invokevirtual #120                // Method timedMetadataId3Period:()Ljava/lang/Integer;
     420: invokestatic  #89                 // Method java/util/Objects.hashCode:(Ljava/lang/Object;)I
     423: iadd
     424: istore_1
     425: bipush        31
     427: iload_1
     428: imul
     429: aload_0
     430: invokevirtual #121                // Method timestampDeltaMilliseconds:()Ljava/lang/Integer;
     433: invokestatic  #89                 // Method java/util/Objects.hashCode:(Ljava/lang/Object;)I
     436: iadd
     437: istore_1
     438: iload_1
     439: ireturn

  public final boolean equals(java.lang.Object);
    Code:
       0: aload_0
       1: aload_1
       2: invokevirtual #122                // Method equalsBySdkFields:(Ljava/lang/Object;)Z
       5: ireturn

  public final boolean equalsBySdkFields(java.lang.Object);
    Code:
       0: aload_0
       1: aload_1
       2: if_acmpne     7
       5: iconst_1
       6: ireturn
       7: aload_1
       8: ifnonnull     13
      11: iconst_0
      12: ireturn
      13: aload_1
      14: instanceof    #123                // class software/amazon/awssdk/services/mediaconvert/model/HlsGroupSettings
      17: ifne          22
      20: iconst_0
      21: ireturn
      22: aload_1
      23: checkcast     #123                // class software/amazon/awssdk/services/mediaconvert/model/HlsGroupSettings
      26: astore_2
      27: aload_0
      28: invokevirtual #87                 // Method hasAdMarkers:()Z
      31: aload_2
      32: invokevirtual #87                 // Method hasAdMarkers:()Z
      35: if_icmpne     498
      38: aload_0
      39: invokevirtual #88                 // Method adMarkersAsStrings:()Ljava/util/List;
      42: aload_2
      43: invokevirtual #88                 // Method adMarkersAsStrings:()Ljava/util/List;
      46: invokestatic  #124                // Method java/util/Objects.equals:(Ljava/lang/Object;Ljava/lang/Object;)Z
      49: ifeq          498
      52: aload_0
      53: invokevirtual #90                 // Method hasAdditionalManifests:()Z
      56: aload_2
      57: invokevirtual #90                 // Method hasAdditionalManifests:()Z
      60: if_icmpne     498
      63: aload_0
      64: invokevirtual #91                 // Method additionalManifests:()Ljava/util/List;
      67: aload_2
      68: invokevirtual #91                 // Method additionalManifests:()Ljava/util/List;
      71: invokestatic  #124                // Method java/util/Objects.equals:(Ljava/lang/Object;Ljava/lang/Object;)Z
      74: ifeq          498
      77: aload_0
      78: invokevirtual #92                 // Method audioOnlyHeaderAsString:()Ljava/lang/String;
      81: aload_2
      82: invokevirtual #92                 // Method audioOnlyHeaderAsString:()Ljava/lang/String;
      85: invokestatic  #124                // Method java/util/Objects.equals:(Ljava/lang/Object;Ljava/lang/Object;)Z
      88: ifeq          498
      91: aload_0
      92: invokevirtual #93                 // Method baseUrl:()Ljava/lang/String;
      95: aload_2
      96: invokevirtual #93                 // Method baseUrl:()Ljava/lang/String;
      99: invokestatic  #124                // Method java/util/Objects.equals:(Ljava/lang/Object;Ljava/lang/Object;)Z
     102: ifeq          498
     105: aload_0
     106: invokevirtual #94                 // Method hasCaptionLanguageMappings:()Z
     109: aload_2
     110: invokevirtual #94                 // Method hasCaptionLanguageMappings:()Z
     113: if_icmpne     498
     116: aload_0
     117: invokevirtual #95                 // Method captionLanguageMappings:()Ljava/util/List;
     120: aload_2
     121: invokevirtual #95                 // Method captionLanguageMappings:()Ljava/util/List;
     124: invokestatic  #124                // Method java/util/Objects.equals:(Ljava/lang/Object;Ljava/lang/Object;)Z
     127: ifeq          498
     130: aload_0
     131: invokevirtual #96                 // Method captionLanguageSettingAsString:()Ljava/lang/String;
     134: aload_2
     135: invokevirtual #96                 // Method captionLanguageSettingAsString:()Ljava/lang/String;
     138: invokestatic  #124                // Method java/util/Objects.equals:(Ljava/lang/Object;Ljava/lang/Object;)Z
     141: ifeq          498
     144: aload_0
     145: invokevirtual #97                 // Method captionSegmentLengthControlAsString:()Ljava/lang/String;
     148: aload_2
     149: invokevirtual #97                 // Method captionSegmentLengthControlAsString:()Ljava/lang/String;
     152: invokestatic  #124                // Method java/util/Objects.equals:(Ljava/lang/Object;Ljava/lang/Object;)Z
     155: ifeq          498
     158: aload_0
     159: invokevirtual #98                 // Method clientCacheAsString:()Ljava/lang/String;
     162: aload_2
     163: invokevirtual #98                 // Method clientCacheAsString:()Ljava/lang/String;
     166: invokestatic  #124                // Method java/util/Objects.equals:(Ljava/lang/Object;Ljava/lang/Object;)Z
     169: ifeq          498
     172: aload_0
     173: invokevirtual #99                 // Method codecSpecificationAsString:()Ljava/lang/String;
     176: aload_2
     177: invokevirtual #99                 // Method codecSpecificationAsString:()Ljava/lang/String;
     180: invokestatic  #124                // Method java/util/Objects.equals:(Ljava/lang/Object;Ljava/lang/Object;)Z
     183: ifeq          498
     186: aload_0
     187: invokevirtual #100                // Method destination:()Ljava/lang/String;
     190: aload_2
     191: invokevirtual #100                // Method destination:()Ljava/lang/String;
     194: invokestatic  #124                // Method java/util/Objects.equals:(Ljava/lang/Object;Ljava/lang/Object;)Z
     197: ifeq          498
     200: aload_0
     201: invokevirtual #101                // Method destinationSettings:()Lsoftware/amazon/awssdk/services/mediaconvert/model/DestinationSettings;
     204: aload_2
     205: invokevirtual #101                // Method destinationSettings:()Lsoftware/amazon/awssdk/services/mediaconvert/model/DestinationSettings;
     208: invokestatic  #124                // Method java/util/Objects.equals:(Ljava/lang/Object;Ljava/lang/Object;)Z
     211: ifeq          498
     214: aload_0
     215: invokevirtual #102                // Method directoryStructureAsString:()Ljava/lang/String;
     218: aload_2
     219: invokevirtual #102                // Method directoryStructureAsString:()Ljava/lang/String;
     222: invokestatic  #124                // Method java/util/Objects.equals:(Ljava/lang/Object;Ljava/lang/Object;)Z
     225: ifeq          498
     228: aload_0
     229: invokevirtual #103                // Method encryption:()Lsoftware/amazon/awssdk/services/mediaconvert/model/HlsEncryptionSettings;
     232: aload_2
     233: invokevirtual #103                // Method encryption:()Lsoftware/amazon/awssdk/services/mediaconvert/model/HlsEncryptionSettings;
     236: invokestatic  #124                // Method java/util/Objects.equals:(Ljava/lang/Object;Ljava/lang/Object;)Z
     239: ifeq          498
     242: aload_0
     243: invokevirtual #104                // Method imageBasedTrickPlayAsString:()Ljava/lang/String;
     246: aload_2
     247: invokevirtual #104                // Method imageBasedTrickPlayAsString:()Ljava/lang/String;
     250: invokestatic  #124                // Method java/util/Objects.equals:(Ljava/lang/Object;Ljava/lang/Object;)Z
     253: ifeq          498
     256: aload_0
     257: invokevirtual #105                // Method imageBasedTrickPlaySettings:()Lsoftware/amazon/awssdk/services/mediaconvert/model/HlsImageBasedTrickPlaySettings;
     260: aload_2
     261: invokevirtual #105                // Method imageBasedTrickPlaySettings:()Lsoftware/amazon/awssdk/services/mediaconvert/model/HlsImageBasedTrickPlaySettings;
     264: invokestatic  #124                // Method java/util/Objects.equals:(Ljava/lang/Object;Ljava/lang/Object;)Z
     267: ifeq          498
     270: aload_0
     271: invokevirtual #106                // Method manifestCompressionAsString:()Ljava/lang/String;
     274: aload_2
     275: invokevirtual #106                // Method manifestCompressionAsString:()Ljava/lang/String;
     278: invokestatic  #124                // Method java/util/Objects.equals:(Ljava/lang/Object;Ljava/lang/Object;)Z
     281: ifeq          498
     284: aload_0
     285: invokevirtual #107                // Method manifestDurationFormatAsString:()Ljava/lang/String;
     288: aload_2
     289: invokevirtual #107                // Method manifestDurationFormatAsString:()Ljava/lang/String;
     292: invokestatic  #124                // Method java/util/Objects.equals:(Ljava/lang/Object;Ljava/lang/Object;)Z
     295: ifeq          498
     298: aload_0
     299: invokevirtual #108                // Method minFinalSegmentLength:()Ljava/lang/Double;
     302: aload_2
     303: invokevirtual #108                // Method minFinalSegmentLength:()Ljava/lang/Double;
     306: invokestatic  #124                // Method java/util/Objects.equals:(Ljava/lang/Object;Ljava/lang/Object;)Z
     309: ifeq          498
     312: aload_0
     313: invokevirtual #109                // Method minSegmentLength:()Ljava/lang/Integer;
     316: aload_2
     317: invokevirtual #109                // Method minSegmentLength:()Ljava/lang/Integer;
     320: invokestatic  #124                // Method java/util/Objects.equals:(Ljava/lang/Object;Ljava/lang/Object;)Z
     323: ifeq          498
     326: aload_0
     327: invokevirtual #110                // Method outputSelectionAsString:()Ljava/lang/String;
     330: aload_2
     331: invokevirtual #110                // Method outputSelectionAsString:()Ljava/lang/String;
     334: invokestatic  #124                // Method java/util/Objects.equals:(Ljava/lang/Object;Ljava/lang/Object;)Z
     337: ifeq          498
     340: aload_0
     341: invokevirtual #111                // Method programDateTimeAsString:()Ljava/lang/String;
     344: aload_2
     345: invokevirtual #111                // Method programDateTimeAsString:()Ljava/lang/String;
     348: invokestatic  #124                // Method java/util/Objects.equals:(Ljava/lang/Object;Ljava/lang/Object;)Z
     351: ifeq          498
     354: aload_0
     355: invokevirtual #112                // Method programDateTimePeriod:()Ljava/lang/Integer;
     358: aload_2
     359: invokevirtual #112                // Method programDateTimePeriod:()Ljava/lang/Integer;
     362: invokestatic  #124                // Method java/util/Objects.equals:(Ljava/lang/Object;Ljava/lang/Object;)Z
     365: ifeq          498
     368: aload_0
     369: invokevirtual #113                // Method segmentControlAsString:()Ljava/lang/String;
     372: aload_2
     373: invokevirtual #113                // Method segmentControlAsString:()Ljava/lang/String;
     376: invokestatic  #124                // Method java/util/Objects.equals:(Ljava/lang/Object;Ljava/lang/Object;)Z
     379: ifeq          498
     382: aload_0
     383: invokevirtual #114                // Method segmentLength:()Ljava/lang/Integer;
     386: aload_2
     387: invokevirtual #114                // Method segmentLength:()Ljava/lang/Integer;
     390: invokestatic  #124                // Method java/util/Objects.equals:(Ljava/lang/Object;Ljava/lang/Object;)Z
     393: ifeq          498
     396: aload_0
     397: invokevirtual #115                // Method segmentLengthControlAsString:()Ljava/lang/String;
     400: aload_2
     401: invokevirtual #115                // Method segmentLengthControlAsString:()Ljava/lang/String;
     404: invokestatic  #124                // Method java/util/Objects.equals:(Ljava/lang/Object;Ljava/lang/Object;)Z
     407: ifeq          498
     410: aload_0
     411: invokevirtual #116                // Method segmentsPerSubdirectory:()Ljava/lang/Integer;
     414: aload_2
     415: invokevirtual #116                // Method segmentsPerSubdirectory:()Ljava/lang/Integer;
     418: invokestatic  #124                // Method java/util/Objects.equals:(Ljava/lang/Object;Ljava/lang/Object;)Z
     421: ifeq          498
     424: aload_0
     425: invokevirtual #117                // Method streamInfResolutionAsString:()Ljava/lang/String;
     428: aload_2
     429: invokevirtual #117                // Method streamInfResolutionAsString:()Ljava/lang/String;
     432: invokestatic  #124                // Method java/util/Objects.equals:(Ljava/lang/Object;Ljava/lang/Object;)Z
     435: ifeq          498
     438: aload_0
     439: invokevirtual #118                // Method targetDurationCompatibilityModeAsString:()Ljava/lang/String;
     442: aload_2
     443: invokevirtual #118                // Method targetDurationCompatibilityModeAsString:()Ljava/lang/String;
     446: invokestatic  #124                // Method java/util/Objects.equals:(Ljava/lang/Object;Ljava/lang/Object;)Z
     449: ifeq          498
     452: aload_0
     453: invokevirtual #119                // Method timedMetadataId3FrameAsString:()Ljava/lang/String;
     456: aload_2
     457: invokevirtual #119                // Method timedMetadataId3FrameAsString:()Ljava/lang/String;
     460: invokestatic  #124                // Method java/util/Objects.equals:(Ljava/lang/Object;Ljava/lang/Object;)Z
     463: ifeq          498
     466: aload_0
     467: invokevirtual #120                // Method timedMetadataId3Period:()Ljava/lang/Integer;
     470: aload_2
     471: invokevirtual #120                // Method timedMetadataId3Period:()Ljava/lang/Integer;
     474: invokestatic  #124                // Method java/util/Objects.equals:(Ljava/lang/Object;Ljava/lang/Object;)Z
     477: ifeq          498
     480: aload_0
     481: invokevirtual #121                // Method timestampDeltaMilliseconds:()Ljava/lang/Integer;
     484: aload_2
     485: invokevirtual #121                // Method timestampDeltaMilliseconds:()Ljava/lang/Integer;
     488: invokestatic  #124                // Method java/util/Objects.equals:(Ljava/lang/Object;Ljava/lang/Object;)Z
     491: ifeq          498
     494: iconst_1
     495: goto          499
     498: iconst_0
     499: ireturn

  public final java.lang.String toString();
    Code:
       0: ldc           #125                // String HlsGroupSettings
       2: invokestatic  #126                // Method software/amazon/awssdk/utils/ToString.builder:(Ljava/lang/String;)Lsoftware/amazon/awssdk/utils/ToString;
       5: ldc           #127                // String AdMarkers
       7: aload_0
       8: invokevirtual #87                 // Method hasAdMarkers:()Z
      11: ifeq          21
      14: aload_0
      15: invokevirtual #88                 // Method adMarkersAsStrings:()Ljava/util/List;
      18: goto          22
      21: aconst_null
      22: invokevirtual #128                // Method software/amazon/awssdk/utils/ToString.add:(Ljava/lang/String;Ljava/lang/Object;)Lsoftware/amazon/awssdk/utils/ToString;
      25: ldc           #129                // String AdditionalManifests
      27: aload_0
      28: invokevirtual #90                 // Method hasAdditionalManifests:()Z
      31: ifeq          41
      34: aload_0
      35: invokevirtual #91                 // Method additionalManifests:()Ljava/util/List;
      38: goto          42
      41: aconst_null
      42: invokevirtual #128                // Method software/amazon/awssdk/utils/ToString.add:(Ljava/lang/String;Ljava/lang/Object;)Lsoftware/amazon/awssdk/utils/ToString;
      45: ldc           #130                // String AudioOnlyHeader
      47: aload_0
      48: invokevirtual #92                 // Method audioOnlyHeaderAsString:()Ljava/lang/String;
      51: invokevirtual #128                // Method software/amazon/awssdk/utils/ToString.add:(Ljava/lang/String;Ljava/lang/Object;)Lsoftware/amazon/awssdk/utils/ToString;
      54: ldc           #131                // String BaseUrl
      56: aload_0
      57: invokevirtual #93                 // Method baseUrl:()Ljava/lang/String;
      60: invokevirtual #128                // Method software/amazon/awssdk/utils/ToString.add:(Ljava/lang/String;Ljava/lang/Object;)Lsoftware/amazon/awssdk/utils/ToString;
      63: ldc           #132                // String CaptionLanguageMappings
      65: aload_0
      66: invokevirtual #94                 // Method hasCaptionLanguageMappings:()Z
      69: ifeq          79
      72: aload_0
      73: invokevirtual #95                 // Method captionLanguageMappings:()Ljava/util/List;
      76: goto          80
      79: aconst_null
      80: invokevirtual #128                // Method software/amazon/awssdk/utils/ToString.add:(Ljava/lang/String;Ljava/lang/Object;)Lsoftware/amazon/awssdk/utils/ToString;
      83: ldc           #133                // String CaptionLanguageSetting
      85: aload_0
      86: invokevirtual #96                 // Method captionLanguageSettingAsString:()Ljava/lang/String;
      89: invokevirtual #128                // Method software/amazon/awssdk/utils/ToString.add:(Ljava/lang/String;Ljava/lang/Object;)Lsoftware/amazon/awssdk/utils/ToString;
      92: ldc           #134                // String CaptionSegmentLengthControl
      94: aload_0
      95: invokevirtual #97                 // Method captionSegmentLengthControlAsString:()Ljava/lang/String;
      98: invokevirtual #128                // Method software/amazon/awssdk/utils/ToString.add:(Ljava/lang/String;Ljava/lang/Object;)Lsoftware/amazon/awssdk/utils/ToString;
     101: ldc           #135                // String ClientCache
     103: aload_0
     104: invokevirtual #98                 // Method clientCacheAsString:()Ljava/lang/String;
     107: invokevirtual #128                // Method software/amazon/awssdk/utils/ToString.add:(Ljava/lang/String;Ljava/lang/Object;)Lsoftware/amazon/awssdk/utils/ToString;
     110: ldc           #136                // String CodecSpecification
     112: aload_0
     113: invokevirtual #99                 // Method codecSpecificationAsString:()Ljava/lang/String;
     116: invokevirtual #128                // Method software/amazon/awssdk/utils/ToString.add:(Ljava/lang/String;Ljava/lang/Object;)Lsoftware/amazon/awssdk/utils/ToString;
     119: ldc           #137                // String Destination
     121: aload_0
     122: invokevirtual #100                // Method destination:()Ljava/lang/String;
     125: invokevirtual #128                // Method software/amazon/awssdk/utils/ToString.add:(Ljava/lang/String;Ljava/lang/Object;)Lsoftware/amazon/awssdk/utils/ToString;
     128: ldc           #138                // String DestinationSettings
     130: aload_0
     131: invokevirtual #101                // Method destinationSettings:()Lsoftware/amazon/awssdk/services/mediaconvert/model/DestinationSettings;
     134: invokevirtual #128                // Method software/amazon/awssdk/utils/ToString.add:(Ljava/lang/String;Ljava/lang/Object;)Lsoftware/amazon/awssdk/utils/ToString;
     137: ldc           #139                // String DirectoryStructure
     139: aload_0
     140: invokevirtual #102                // Method directoryStructureAsString:()Ljava/lang/String;
     143: invokevirtual #128                // Method software/amazon/awssdk/utils/ToString.add:(Ljava/lang/String;Ljava/lang/Object;)Lsoftware/amazon/awssdk/utils/ToString;
     146: ldc           #140                // String Encryption
     148: aload_0
     149: invokevirtual #103                // Method encryption:()Lsoftware/amazon/awssdk/services/mediaconvert/model/HlsEncryptionSettings;
     152: invokevirtual #128                // Method software/amazon/awssdk/utils/ToString.add:(Ljava/lang/String;Ljava/lang/Object;)Lsoftware/amazon/awssdk/utils/ToString;
     155: ldc           #141                // String ImageBasedTrickPlay
     157: aload_0
     158: invokevirtual #104                // Method imageBasedTrickPlayAsString:()Ljava/lang/String;
     161: invokevirtual #128                // Method software/amazon/awssdk/utils/ToString.add:(Ljava/lang/String;Ljava/lang/Object;)Lsoftware/amazon/awssdk/utils/ToString;
     164: ldc           #142                // String ImageBasedTrickPlaySettings
     166: aload_0
     167: invokevirtual #105                // Method imageBasedTrickPlaySettings:()Lsoftware/amazon/awssdk/services/mediaconvert/model/HlsImageBasedTrickPlaySettings;
     170: invokevirtual #128                // Method software/amazon/awssdk/utils/ToString.add:(Ljava/lang/String;Ljava/lang/Object;)Lsoftware/amazon/awssdk/utils/ToString;
     173: ldc           #143                // String ManifestCompression
     175: aload_0
     176: invokevirtual #106                // Method manifestCompressionAsString:()Ljava/lang/String;
     179: invokevirtual #128                // Method software/amazon/awssdk/utils/ToString.add:(Ljava/lang/String;Ljava/lang/Object;)Lsoftware/amazon/awssdk/utils/ToString;
     182: ldc           #144                // String ManifestDurationFormat
     184: aload_0
     185: invokevirtual #107                // Method manifestDurationFormatAsString:()Ljava/lang/String;
     188: invokevirtual #128                // Method software/amazon/awssdk/utils/ToString.add:(Ljava/lang/String;Ljava/lang/Object;)Lsoftware/amazon/awssdk/utils/ToString;
     191: ldc           #145                // String MinFinalSegmentLength
     193: aload_0
     194: invokevirtual #108                // Method minFinalSegmentLength:()Ljava/lang/Double;
     197: invokevirtual #128                // Method software/amazon/awssdk/utils/ToString.add:(Ljava/lang/String;Ljava/lang/Object;)Lsoftware/amazon/awssdk/utils/ToString;
     200: ldc           #146                // String MinSegmentLength
     202: aload_0
     203: invokevirtual #109                // Method minSegmentLength:()Ljava/lang/Integer;
     206: invokevirtual #128                // Method software/amazon/awssdk/utils/ToString.add:(Ljava/lang/String;Ljava/lang/Object;)Lsoftware/amazon/awssdk/utils/ToString;
     209: ldc           #147                // String OutputSelection
     211: aload_0
     212: invokevirtual #110                // Method outputSelectionAsString:()Ljava/lang/String;
     215: invokevirtual #128                // Method software/amazon/awssdk/utils/ToString.add:(Ljava/lang/String;Ljava/lang/Object;)Lsoftware/amazon/awssdk/utils/ToString;
     218: ldc           #148                // String ProgramDateTime
     220: aload_0
     221: invokevirtual #111                // Method programDateTimeAsString:()Ljava/lang/String;
     224: invokevirtual #128                // Method software/amazon/awssdk/utils/ToString.add:(Ljava/lang/String;Ljava/lang/Object;)Lsoftware/amazon/awssdk/utils/ToString;
     227: ldc           #149                // String ProgramDateTimePeriod
     229: aload_0
     230: invokevirtual #112                // Method programDateTimePeriod:()Ljava/lang/Integer;
     233: invokevirtual #128                // Method software/amazon/awssdk/utils/ToString.add:(Ljava/lang/String;Ljava/lang/Object;)Lsoftware/amazon/awssdk/utils/ToString;
     236: ldc           #150                // String SegmentControl
     238: aload_0
     239: invokevirtual #113                // Method segmentControlAsString:()Ljava/lang/String;
     242: invokevirtual #128                // Method software/amazon/awssdk/utils/ToString.add:(Ljava/lang/String;Ljava/lang/Object;)Lsoftware/amazon/awssdk/utils/ToString;
     245: ldc           #151                // String SegmentLength
     247: aload_0
     248: invokevirtual #114                // Method segmentLength:()Ljava/lang/Integer;
     251: invokevirtual #128                // Method software/amazon/awssdk/utils/ToString.add:(Ljava/lang/String;Ljava/lang/Object;)Lsoftware/amazon/awssdk/utils/ToString;
     254: ldc           #152                // String SegmentLengthControl
     256: aload_0
     257: invokevirtual #115                // Method segmentLengthControlAsString:()Ljava/lang/String;
     260: invokevirtual #128                // Method software/amazon/awssdk/utils/ToString.add:(Ljava/lang/String;Ljava/lang/Object;)Lsoftware/amazon/awssdk/utils/ToString;
     263: ldc           #153                // String SegmentsPerSubdirectory
     265: aload_0
     266: invokevirtual #116                // Method segmentsPerSubdirectory:()Ljava/lang/Integer;
     269: invokevirtual #128                // Method software/amazon/awssdk/utils/ToString.add:(Ljava/lang/String;Ljava/lang/Object;)Lsoftware/amazon/awssdk/utils/ToString;
     272: ldc           #154                // String StreamInfResolution
     274: aload_0
     275: invokevirtual #117                // Method streamInfResolutionAsString:()Ljava/lang/String;
     278: invokevirtual #128                // Method software/amazon/awssdk/utils/ToString.add:(Ljava/lang/String;Ljava/lang/Object;)Lsoftware/amazon/awssdk/utils/ToString;
     281: ldc           #155                // String TargetDurationCompatibilityMode
     283: aload_0
     284: invokevirtual #118                // Method targetDurationCompatibilityModeAsString:()Ljava/lang/String;
     287: invokevirtual #128                // Method software/amazon/awssdk/utils/ToString.add:(Ljava/lang/String;Ljava/lang/Object;)Lsoftware/amazon/awssdk/utils/ToString;
     290: ldc           #156                // String TimedMetadataId3Frame
     292: aload_0
     293: invokevirtual #119                // Method timedMetadataId3FrameAsString:()Ljava/lang/String;
     296: invokevirtual #128                // Method software/amazon/awssdk/utils/ToString.add:(Ljava/lang/String;Ljava/lang/Object;)Lsoftware/amazon/awssdk/utils/ToString;
     299: ldc           #157                // String TimedMetadataId3Period
     301: aload_0
     302: invokevirtual #120                // Method timedMetadataId3Period:()Ljava/lang/Integer;
     305: invokevirtual #128                // Method software/amazon/awssdk/utils/ToString.add:(Ljava/lang/String;Ljava/lang/Object;)Lsoftware/amazon/awssdk/utils/ToString;
     308: ldc           #158                // String TimestampDeltaMilliseconds
     310: aload_0
     311: invokevirtual #121                // Method timestampDeltaMilliseconds:()Ljava/lang/Integer;
     314: invokevirtual #128                // Method software/amazon/awssdk/utils/ToString.add:(Ljava/lang/String;Ljava/lang/Object;)Lsoftware/amazon/awssdk/utils/ToString;
     317: invokevirtual #159                // Method software/amazon/awssdk/utils/ToString.build:()Ljava/lang/String;
     320: areturn

  public final <T> java.util.Optional<T> getValueForField(java.lang.String, java.lang.Class<T>);
    Code:
       0: aload_1
       1: astore_3
       2: iconst_m1
       3: istore        4
       5: aload_3
       6: invokevirtual #160                // Method java/lang/String.hashCode:()I
       9: lookupswitch  { // 31
           -1946698230: 662
           -1764934966: 614
           -1709005281: 582
           -1637867603: 678
           -1615350262: 358
           -1577110321: 470
           -1416857881: 550
           -1189545125: 710
           -1169939644: 646
            -916244585: 502
            -829144650: 268
            -760254291: 390
            -380417341: 328
            -362708007: 630
            -319923494: 518
            -110812878: 343
            -106072172: 742
              -9911395: 283
             238021614: 406
             334799694: 694
             480832419: 454
             753652725: 534
             891404651: 566
             959952064: 598
             968480166: 438
            1332027582: 313
            1446909458: 486
            1467750999: 374
            1506040239: 298
            1913732657: 422
            2053595539: 726
               default: 755
          }
     268: aload_3
     269: ldc           #127                // String AdMarkers
     271: invokevirtual #161                // Method java/lang/String.equals:(Ljava/lang/Object;)Z
     274: ifeq          755
     277: iconst_0
     278: istore        4
     280: goto          755
     283: aload_3
     284: ldc           #129                // String AdditionalManifests
     286: invokevirtual #161                // Method java/lang/String.equals:(Ljava/lang/Object;)Z
     289: ifeq          755
     292: iconst_1
     293: istore        4
     295: goto          755
     298: aload_3
     299: ldc           #130                // String AudioOnlyHeader
     301: invokevirtual #161                // Method java/lang/String.equals:(Ljava/lang/Object;)Z
     304: ifeq          755
     307: iconst_2
     308: istore        4
     310: goto          755
     313: aload_3
     314: ldc           #131                // String BaseUrl
     316: invokevirtual #161                // Method java/lang/String.equals:(Ljava/lang/Object;)Z
     319: ifeq          755
     322: iconst_3
     323: istore        4
     325: goto          755
     328: aload_3
     329: ldc           #132                // String CaptionLanguageMappings
     331: invokevirtual #161                // Method java/lang/String.equals:(Ljava/lang/Object;)Z
     334: ifeq          755
     337: iconst_4
     338: istore        4
     340: goto          755
     343: aload_3
     344: ldc           #133                // String CaptionLanguageSetting
     346: invokevirtual #161                // Method java/lang/String.equals:(Ljava/lang/Object;)Z
     349: ifeq          755
     352: iconst_5
     353: istore        4
     355: goto          755
     358: aload_3
     359: ldc           #134                // String CaptionSegmentLengthControl
     361: invokevirtual #161                // Method java/lang/String.equals:(Ljava/lang/Object;)Z
     364: ifeq          755
     367: bipush        6
     369: istore        4
     371: goto          755
     374: aload_3
     375: ldc           #135                // String ClientCache
     377: invokevirtual #161                // Method java/lang/String.equals:(Ljava/lang/Object;)Z
     380: ifeq          755
     383: bipush        7
     385: istore        4
     387: goto          755
     390: aload_3
     391: ldc           #136                // String CodecSpecification
     393: invokevirtual #161                // Method java/lang/String.equals:(Ljava/lang/Object;)Z
     396: ifeq          755
     399: bipush        8
     401: istore        4
     403: goto          755
     406: aload_3
     407: ldc           #137                // String Destination
     409: invokevirtual #161                // Method java/lang/String.equals:(Ljava/lang/Object;)Z
     412: ifeq          755
     415: bipush        9
     417: istore        4
     419: goto          755
     422: aload_3
     423: ldc           #138                // String DestinationSettings
     425: invokevirtual #161                // Method java/lang/String.equals:(Ljava/lang/Object;)Z
     428: ifeq          755
     431: bipush        10
     433: istore        4
     435: goto          755
     438: aload_3
     439: ldc           #139                // String DirectoryStructure
     441: invokevirtual #161                // Method java/lang/String.equals:(Ljava/lang/Object;)Z
     444: ifeq          755
     447: bipush        11
     449: istore        4
     451: goto          755
     454: aload_3
     455: ldc           #140                // String Encryption
     457: invokevirtual #161                // Method java/lang/String.equals:(Ljava/lang/Object;)Z
     460: ifeq          755
     463: bipush        12
     465: istore        4
     467: goto          755
     470: aload_3
     471: ldc           #141                // String ImageBasedTrickPlay
     473: invokevirtual #161                // Method java/lang/String.equals:(Ljava/lang/Object;)Z
     476: ifeq          755
     479: bipush        13
     481: istore        4
     483: goto          755
     486: aload_3
     487: ldc           #142                // String ImageBasedTrickPlaySettings
     489: invokevirtual #161                // Method java/lang/String.equals:(Ljava/lang/Object;)Z
     492: ifeq          755
     495: bipush        14
     497: istore        4
     499: goto          755
     502: aload_3
     503: ldc           #143                // String ManifestCompression
     505: invokevirtual #161                // Method java/lang/String.equals:(Ljava/lang/Object;)Z
     508: ifeq          755
     511: bipush        15
     513: istore        4
     515: goto          755
     518: aload_3
     519: ldc           #144                // String ManifestDurationFormat
     521: invokevirtual #161                // Method java/lang/String.equals:(Ljava/lang/Object;)Z
     524: ifeq          755
     527: bipush        16
     529: istore        4
     531: goto          755
     534: aload_3
     535: ldc           #145                // String MinFinalSegmentLength
     537: invokevirtual #161                // Method java/lang/String.equals:(Ljava/lang/Object;)Z
     540: ifeq          755
     543: bipush        17
     545: istore        4
     547: goto          755
     550: aload_3
     551: ldc           #146                // String MinSegmentLength
     553: invokevirtual #161                // Method java/lang/String.equals:(Ljava/lang/Object;)Z
     556: ifeq          755
     559: bipush        18
     561: istore        4
     563: goto          755
     566: aload_3
     567: ldc           #147                // String OutputSelection
     569: invokevirtual #161                // Method java/lang/String.equals:(Ljava/lang/Object;)Z
     572: ifeq          755
     575: bipush        19
     577: istore        4
     579: goto          755
     582: aload_3
     583: ldc           #148                // String ProgramDateTime
     585: invokevirtual #161                // Method java/lang/String.equals:(Ljava/lang/Object;)Z
     588: ifeq          755
     591: bipush        20
     593: istore        4
     595: goto          755
     598: aload_3
     599: ldc           #149                // String ProgramDateTimePeriod
     601: invokevirtual #161                // Method java/lang/String.equals:(Ljava/lang/Object;)Z
     604: ifeq          755
     607: bipush        21
     609: istore        4
     611: goto          755
     614: aload_3
     615: ldc           #150                // String SegmentControl
     617: invokevirtual #161                // Method java/lang/String.equals:(Ljava/lang/Object;)Z
     620: ifeq          755
     623: bipush        22
     625: istore        4
     627: goto          755
     630: aload_3
     631: ldc           #151                // String SegmentLength
     633: invokevirtual #161                // Method java/lang/String.equals:(Ljava/lang/Object;)Z
     636: ifeq          755
     639: bipush        23
     641: istore        4
     643: goto          755
     646: aload_3
     647: ldc           #152                // String SegmentLengthControl
     649: invokevirtual #161                // Method java/lang/String.equals:(Ljava/lang/Object;)Z
     652: ifeq          755
     655: bipush        24
     657: istore        4
     659: goto          755
     662: aload_3
     663: ldc           #153                // String SegmentsPerSubdirectory
     665: invokevirtual #161                // Method java/lang/String.equals:(Ljava/lang/Object;)Z
     668: ifeq          755
     671: bipush        25
     673: istore        4
     675: goto          755
     678: aload_3
     679: ldc           #154                // String StreamInfResolution
     681: invokevirtual #161                // Method java/lang/String.equals:(Ljava/lang/Object;)Z
     684: ifeq          755
     687: bipush        26
     689: istore        4
     691: goto          755
     694: aload_3
     695: ldc           #155                // String TargetDurationCompatibilityMode
     697: invokevirtual #161                // Method java/lang/String.equals:(Ljava/lang/Object;)Z
     700: ifeq          755
     703: bipush        27
     705: istore        4
     707: goto          755
     710: aload_3
     711: ldc           #156                // String TimedMetadataId3Frame
     713: invokevirtual #161                // Method java/lang/String.equals:(Ljava/lang/Object;)Z
     716: ifeq          755
     719: bipush        28
     721: istore        4
     723: goto          755
     726: aload_3
     727: ldc           #157                // String TimedMetadataId3Period
     729: invokevirtual #161                // Method java/lang/String.equals:(Ljava/lang/Object;)Z
     732: ifeq          755
     735: bipush        29
     737: istore        4
     739: goto          755
     742: aload_3
     743: ldc           #158                // String TimestampDeltaMilliseconds
     745: invokevirtual #161                // Method java/lang/String.equals:(Ljava/lang/Object;)Z
     748: ifeq          755
     751: bipush        30
     753: istore        4
     755: iload         4
     757: tableswitch   { // 0 to 30
                     0: 896
                     1: 908
                     2: 920
                     3: 932
                     4: 944
                     5: 956
                     6: 968
                     7: 980
                     8: 992
                     9: 1004
                    10: 1016
                    11: 1028
                    12: 1040
                    13: 1052
                    14: 1064
                    15: 1076
                    16: 1088
                    17: 1100
                    18: 1112
                    19: 1124
                    20: 1136
                    21: 1148
                    22: 1160
                    23: 1172
                    24: 1184
                    25: 1196
                    26: 1208
                    27: 1220
                    28: 1232
                    29: 1244
                    30: 1256
               default: 1268
          }
     896: aload_2
     897: aload_0
     898: invokevirtual #88                 // Method adMarkersAsStrings:()Ljava/util/List;
     901: invokevirtual #162                // Method java/lang/Class.cast:(Ljava/lang/Object;)Ljava/lang/Object;
     904: invokestatic  #163                // Method java/util/Optional.ofNullable:(Ljava/lang/Object;)Ljava/util/Optional;
     907: areturn
     908: aload_2
     909: aload_0
     910: invokevirtual #91                 // Method additionalManifests:()Ljava/util/List;
     913: invokevirtual #162                // Method java/lang/Class.cast:(Ljava/lang/Object;)Ljava/lang/Object;
     916: invokestatic  #163                // Method java/util/Optional.ofNullable:(Ljava/lang/Object;)Ljava/util/Optional;
     919: areturn
     920: aload_2
     921: aload_0
     922: invokevirtual #92                 // Method audioOnlyHeaderAsString:()Ljava/lang/String;
     925: invokevirtual #162                // Method java/lang/Class.cast:(Ljava/lang/Object;)Ljava/lang/Object;
     928: invokestatic  #163                // Method java/util/Optional.ofNullable:(Ljava/lang/Object;)Ljava/util/Optional;
     931: areturn
     932: aload_2
     933: aload_0
     934: invokevirtual #93                 // Method baseUrl:()Ljava/lang/String;
     937: invokevirtual #162                // Method java/lang/Class.cast:(Ljava/lang/Object;)Ljava/lang/Object;
     940: invokestatic  #163                // Method java/util/Optional.ofNullable:(Ljava/lang/Object;)Ljava/util/Optional;
     943: areturn
     944: aload_2
     945: aload_0
     946: invokevirtual #95                 // Method captionLanguageMappings:()Ljava/util/List;
     949: invokevirtual #162                // Method java/lang/Class.cast:(Ljava/lang/Object;)Ljava/lang/Object;
     952: invokestatic  #163                // Method java/util/Optional.ofNullable:(Ljava/lang/Object;)Ljava/util/Optional;
     955: areturn
     956: aload_2
     957: aload_0
     958: invokevirtual #96                 // Method captionLanguageSettingAsString:()Ljava/lang/String;
     961: invokevirtual #162                // Method java/lang/Class.cast:(Ljava/lang/Object;)Ljava/lang/Object;
     964: invokestatic  #163                // Method java/util/Optional.ofNullable:(Ljava/lang/Object;)Ljava/util/Optional;
     967: areturn
     968: aload_2
     969: aload_0
     970: invokevirtual #97                 // Method captionSegmentLengthControlAsString:()Ljava/lang/String;
     973: invokevirtual #162                // Method java/lang/Class.cast:(Ljava/lang/Object;)Ljava/lang/Object;
     976: invokestatic  #163                // Method java/util/Optional.ofNullable:(Ljava/lang/Object;)Ljava/util/Optional;
     979: areturn
     980: aload_2
     981: aload_0
     982: invokevirtual #98                 // Method clientCacheAsString:()Ljava/lang/String;
     985: invokevirtual #162                // Method java/lang/Class.cast:(Ljava/lang/Object;)Ljava/lang/Object;
     988: invokestatic  #163                // Method java/util/Optional.ofNullable:(Ljava/lang/Object;)Ljava/util/Optional;
     991: areturn
     992: aload_2
     993: aload_0
     994: invokevirtual #99                 // Method codecSpecificationAsString:()Ljava/lang/String;
     997: invokevirtual #162                // Method java/lang/Class.cast:(Ljava/lang/Object;)Ljava/lang/Object;
    1000: invokestatic  #163                // Method java/util/Optional.ofNullable:(Ljava/lang/Object;)Ljava/util/Optional;
    1003: areturn
    1004: aload_2
    1005: aload_0
    1006: invokevirtual #100                // Method destination:()Ljava/lang/String;
    1009: invokevirtual #162                // Method java/lang/Class.cast:(Ljava/lang/Object;)Ljava/lang/Object;
    1012: invokestatic  #163                // Method java/util/Optional.ofNullable:(Ljava/lang/Object;)Ljava/util/Optional;
    1015: areturn
    1016: aload_2
    1017: aload_0
    1018: invokevirtual #101                // Method destinationSettings:()Lsoftware/amazon/awssdk/services/mediaconvert/model/DestinationSettings;
    1021: invokevirtual #162                // Method java/lang/Class.cast:(Ljava/lang/Object;)Ljava/lang/Object;
    1024: invokestatic  #163                // Method java/util/Optional.ofNullable:(Ljava/lang/Object;)Ljava/util/Optional;
    1027: areturn
    1028: aload_2
    1029: aload_0
    1030: invokevirtual #102                // Method directoryStructureAsString:()Ljava/lang/String;
    1033: invokevirtual #162                // Method java/lang/Class.cast:(Ljava/lang/Object;)Ljava/lang/Object;
    1036: invokestatic  #163                // Method java/util/Optional.ofNullable:(Ljava/lang/Object;)Ljava/util/Optional;
    1039: areturn
    1040: aload_2
    1041: aload_0
    1042: invokevirtual #103                // Method encryption:()Lsoftware/amazon/awssdk/services/mediaconvert/model/HlsEncryptionSettings;
    1045: invokevirtual #162                // Method java/lang/Class.cast:(Ljava/lang/Object;)Ljava/lang/Object;
    1048: invokestatic  #163                // Method java/util/Optional.ofNullable:(Ljava/lang/Object;)Ljava/util/Optional;
    1051: areturn
    1052: aload_2
    1053: aload_0
    1054: invokevirtual #104                // Method imageBasedTrickPlayAsString:()Ljava/lang/String;
    1057: invokevirtual #162                // Method java/lang/Class.cast:(Ljava/lang/Object;)Ljava/lang/Object;
    1060: invokestatic  #163                // Method java/util/Optional.ofNullable:(Ljava/lang/Object;)Ljava/util/Optional;
    1063: areturn
    1064: aload_2
    1065: aload_0
    1066: invokevirtual #105                // Method imageBasedTrickPlaySettings:()Lsoftware/amazon/awssdk/services/mediaconvert/model/HlsImageBasedTrickPlaySettings;
    1069: invokevirtual #162                // Method java/lang/Class.cast:(Ljava/lang/Object;)Ljava/lang/Object;
    1072: invokestatic  #163                // Method java/util/Optional.ofNullable:(Ljava/lang/Object;)Ljava/util/Optional;
    1075: areturn
    1076: aload_2
    1077: aload_0
    1078: invokevirtual #106                // Method manifestCompressionAsString:()Ljava/lang/String;
    1081: invokevirtual #162                // Method java/lang/Class.cast:(Ljava/lang/Object;)Ljava/lang/Object;
    1084: invokestatic  #163                // Method java/util/Optional.ofNullable:(Ljava/lang/Object;)Ljava/util/Optional;
    1087: areturn
    1088: aload_2
    1089: aload_0
    1090: invokevirtual #107                // Method manifestDurationFormatAsString:()Ljava/lang/String;
    1093: invokevirtual #162                // Method java/lang/Class.cast:(Ljava/lang/Object;)Ljava/lang/Object;
    1096: invokestatic  #163                // Method java/util/Optional.ofNullable:(Ljava/lang/Object;)Ljava/util/Optional;
    1099: areturn
    1100: aload_2
    1101: aload_0
    1102: invokevirtual #108                // Method minFinalSegmentLength:()Ljava/lang/Double;
    1105: invokevirtual #162                // Method java/lang/Class.cast:(Ljava/lang/Object;)Ljava/lang/Object;
    1108: invokestatic  #163                // Method java/util/Optional.ofNullable:(Ljava/lang/Object;)Ljava/util/Optional;
    1111: areturn
    1112: aload_2
    1113: aload_0
    1114: invokevirtual #109                // Method minSegmentLength:()Ljava/lang/Integer;
    1117: invokevirtual #162                // Method java/lang/Class.cast:(Ljava/lang/Object;)Ljava/lang/Object;
    1120: invokestatic  #163                // Method java/util/Optional.ofNullable:(Ljava/lang/Object;)Ljava/util/Optional;
    1123: areturn
    1124: aload_2
    1125: aload_0
    1126: invokevirtual #110                // Method outputSelectionAsString:()Ljava/lang/String;
    1129: invokevirtual #162                // Method java/lang/Class.cast:(Ljava/lang/Object;)Ljava/lang/Object;
    1132: invokestatic  #163                // Method java/util/Optional.ofNullable:(Ljava/lang/Object;)Ljava/util/Optional;
    1135: areturn
    1136: aload_2
    1137: aload_0
    1138: invokevirtual #111                // Method programDateTimeAsString:()Ljava/lang/String;
    1141: invokevirtual #162                // Method java/lang/Class.cast:(Ljava/lang/Object;)Ljava/lang/Object;
    1144: invokestatic  #163                // Method java/util/Optional.ofNullable:(Ljava/lang/Object;)Ljava/util/Optional;
    1147: areturn
    1148: aload_2
    1149: aload_0
    1150: invokevirtual #112                // Method programDateTimePeriod:()Ljava/lang/Integer;
    1153: invokevirtual #162                // Method java/lang/Class.cast:(Ljava/lang/Object;)Ljava/lang/Object;
    1156: invokestatic  #163                // Method java/util/Optional.ofNullable:(Ljava/lang/Object;)Ljava/util/Optional;
    1159: areturn
    1160: aload_2
    1161: aload_0
    1162: invokevirtual #113                // Method segmentControlAsString:()Ljava/lang/String;
    1165: invokevirtual #162                // Method java/lang/Class.cast:(Ljava/lang/Object;)Ljava/lang/Object;
    1168: invokestatic  #163                // Method java/util/Optional.ofNullable:(Ljava/lang/Object;)Ljava/util/Optional;
    1171: areturn
    1172: aload_2
    1173: aload_0
    1174: invokevirtual #114                // Method segmentLength:()Ljava/lang/Integer;
    1177: invokevirtual #162                // Method java/lang/Class.cast:(Ljava/lang/Object;)Ljava/lang/Object;
    1180: invokestatic  #163                // Method java/util/Optional.ofNullable:(Ljava/lang/Object;)Ljava/util/Optional;
    1183: areturn
    1184: aload_2
    1185: aload_0
    1186: invokevirtual #115                // Method segmentLengthControlAsString:()Ljava/lang/String;
    1189: invokevirtual #162                // Method java/lang/Class.cast:(Ljava/lang/Object;)Ljava/lang/Object;
    1192: invokestatic  #163                // Method java/util/Optional.ofNullable:(Ljava/lang/Object;)Ljava/util/Optional;
    1195: areturn
    1196: aload_2
    1197: aload_0
    1198: invokevirtual #116                // Method segmentsPerSubdirectory:()Ljava/lang/Integer;
    1201: invokevirtual #162                // Method java/lang/Class.cast:(Ljava/lang/Object;)Ljava/lang/Object;
    1204: invokestatic  #163                // Method java/util/Optional.ofNullable:(Ljava/lang/Object;)Ljava/util/Optional;
    1207: areturn
    1208: aload_2
    1209: aload_0
    1210: invokevirtual #117                // Method streamInfResolutionAsString:()Ljava/lang/String;
    1213: invokevirtual #162                // Method java/lang/Class.cast:(Ljava/lang/Object;)Ljava/lang/Object;
    1216: invokestatic  #163                // Method java/util/Optional.ofNullable:(Ljava/lang/Object;)Ljava/util/Optional;
    1219: areturn
    1220: aload_2
    1221: aload_0
    1222: invokevirtual #118                // Method targetDurationCompatibilityModeAsString:()Ljava/lang/String;
    1225: invokevirtual #162                // Method java/lang/Class.cast:(Ljava/lang/Object;)Ljava/lang/Object;
    1228: invokestatic  #163                // Method java/util/Optional.ofNullable:(Ljava/lang/Object;)Ljava/util/Optional;
    1231: areturn
    1232: aload_2
    1233: aload_0
    1234: invokevirtual #119                // Method timedMetadataId3FrameAsString:()Ljava/lang/String;
    1237: invokevirtual #162                // Method java/lang/Class.cast:(Ljava/lang/Object;)Ljava/lang/Object;
    1240: invokestatic  #163                // Method java/util/Optional.ofNullable:(Ljava/lang/Object;)Ljava/util/Optional;
    1243: areturn
    1244: aload_2
    1245: aload_0
    1246: invokevirtual #120                // Method timedMetadataId3Period:()Ljava/lang/Integer;
    1249: invokevirtual #162                // Method java/lang/Class.cast:(Ljava/lang/Object;)Ljava/lang/Object;
    1252: invokestatic  #163                // Method java/util/Optional.ofNullable:(Ljava/lang/Object;)Ljava/util/Optional;
    1255: areturn
    1256: aload_2
    1257: aload_0
    1258: invokevirtual #121                // Method timestampDeltaMilliseconds:()Ljava/lang/Integer;
    1261: invokevirtual #162                // Method java/lang/Class.cast:(Ljava/lang/Object;)Ljava/lang/Object;
    1264: invokestatic  #163                // Method java/util/Optional.ofNullable:(Ljava/lang/Object;)Ljava/util/Optional;
    1267: areturn
    1268: invokestatic  #164                // Method java/util/Optional.empty:()Ljava/util/Optional;
    1271: areturn

  public final java.util.List<software.amazon.awssdk.core.SdkField<?>> sdkFields();
    Code:
       0: getstatic     #1                  // Field SDK_FIELDS:Ljava/util/List;
       3: areturn

  private static <T> java.util.function.Function<java.lang.Object, T> getter(java.util.function.Function<software.amazon.awssdk.services.mediaconvert.model.HlsGroupSettings, T>);
    Code:
       0: aload_0
       1: invokedynamic #165,  0            // InvokeDynamic #0:apply:(Ljava/util/function/Function;)Ljava/util/function/Function;
       6: areturn

  private static <T> java.util.function.BiConsumer<java.lang.Object, T> setter(java.util.function.BiConsumer<software.amazon.awssdk.services.mediaconvert.model.HlsGroupSettings$Builder, T>);
    Code:
       0: aload_0
       1: invokedynamic #166,  0            // InvokeDynamic #1:accept:(Ljava/util/function/BiConsumer;)Ljava/util/function/BiConsumer;
       6: areturn

  public software.amazon.awssdk.utils.builder.CopyableBuilder toBuilder();
    Code:
       0: aload_0
       1: invokevirtual #167                // Method toBuilder:()Lsoftware/amazon/awssdk/services/mediaconvert/model/HlsGroupSettings$Builder;
       4: areturn

  private static void lambda$setter$1(java.util.function.BiConsumer, java.lang.Object, java.lang.Object);
    Code:
       0: aload_0
       1: aload_1
       2: checkcast     #168                // class software/amazon/awssdk/services/mediaconvert/model/HlsGroupSettings$Builder
       5: aload_2
       6: invokeinterface #169,  3          // InterfaceMethod java/util/function/BiConsumer.accept:(Ljava/lang/Object;Ljava/lang/Object;)V
      11: return

  private static java.lang.Object lambda$getter$0(java.util.function.Function, java.lang.Object);
    Code:
       0: aload_0
       1: aload_1
       2: checkcast     #123                // class software/amazon/awssdk/services/mediaconvert/model/HlsGroupSettings
       5: invokeinterface #170,  2          // InterfaceMethod java/util/function/Function.apply:(Ljava/lang/Object;)Ljava/lang/Object;
      10: areturn

  static java.util.List access$3300(software.amazon.awssdk.services.mediaconvert.model.HlsGroupSettings);
    Code:
       0: aload_0
       1: getfield      #33                 // Field adMarkers:Ljava/util/List;
       4: areturn

  static java.util.List access$3400(software.amazon.awssdk.services.mediaconvert.model.HlsGroupSettings);
    Code:
       0: aload_0
       1: getfield      #32                 // Field additionalManifests:Ljava/util/List;
       4: areturn

  static java.lang.String access$3500(software.amazon.awssdk.services.mediaconvert.model.HlsGroupSettings);
    Code:
       0: aload_0
       1: getfield      #31                 // Field audioOnlyHeader:Ljava/lang/String;
       4: areturn

  static java.lang.String access$3600(software.amazon.awssdk.services.mediaconvert.model.HlsGroupSettings);
    Code:
       0: aload_0
       1: getfield      #30                 // Field baseUrl:Ljava/lang/String;
       4: areturn

  static java.util.List access$3700(software.amazon.awssdk.services.mediaconvert.model.HlsGroupSettings);
    Code:
       0: aload_0
       1: getfield      #29                 // Field captionLanguageMappings:Ljava/util/List;
       4: areturn

  static java.lang.String access$3800(software.amazon.awssdk.services.mediaconvert.model.HlsGroupSettings);
    Code:
       0: aload_0
       1: getfield      #28                 // Field captionLanguageSetting:Ljava/lang/String;
       4: areturn

  static java.lang.String access$3900(software.amazon.awssdk.services.mediaconvert.model.HlsGroupSettings);
    Code:
       0: aload_0
       1: getfield      #27                 // Field captionSegmentLengthControl:Ljava/lang/String;
       4: areturn

  static java.lang.String access$4000(software.amazon.awssdk.services.mediaconvert.model.HlsGroupSettings);
    Code:
       0: aload_0
       1: getfield      #26                 // Field clientCache:Ljava/lang/String;
       4: areturn

  static java.lang.String access$4100(software.amazon.awssdk.services.mediaconvert.model.HlsGroupSettings);
    Code:
       0: aload_0
       1: getfield      #25                 // Field codecSpecification:Ljava/lang/String;
       4: areturn

  static java.lang.String access$4200(software.amazon.awssdk.services.mediaconvert.model.HlsGroupSettings);
    Code:
       0: aload_0
       1: getfield      #24                 // Field destination:Ljava/lang/String;
       4: areturn

  static software.amazon.awssdk.services.mediaconvert.model.DestinationSettings access$4300(software.amazon.awssdk.services.mediaconvert.model.HlsGroupSettings);
    Code:
       0: aload_0
       1: getfield      #23                 // Field destinationSettings:Lsoftware/amazon/awssdk/services/mediaconvert/model/DestinationSettings;
       4: areturn

  static java.lang.String access$4400(software.amazon.awssdk.services.mediaconvert.model.HlsGroupSettings);
    Code:
       0: aload_0
       1: getfield      #22                 // Field directoryStructure:Ljava/lang/String;
       4: areturn

  static software.amazon.awssdk.services.mediaconvert.model.HlsEncryptionSettings access$4500(software.amazon.awssdk.services.mediaconvert.model.HlsGroupSettings);
    Code:
       0: aload_0
       1: getfield      #21                 // Field encryption:Lsoftware/amazon/awssdk/services/mediaconvert/model/HlsEncryptionSettings;
       4: areturn

  static java.lang.String access$4600(software.amazon.awssdk.services.mediaconvert.model.HlsGroupSettings);
    Code:
       0: aload_0
       1: getfield      #20                 // Field imageBasedTrickPlay:Ljava/lang/String;
       4: areturn

  static software.amazon.awssdk.services.mediaconvert.model.HlsImageBasedTrickPlaySettings access$4700(software.amazon.awssdk.services.mediaconvert.model.HlsGroupSettings);
    Code:
       0: aload_0
       1: getfield      #19                 // Field imageBasedTrickPlaySettings:Lsoftware/amazon/awssdk/services/mediaconvert/model/HlsImageBasedTrickPlaySettings;
       4: areturn

  static java.lang.String access$4800(software.amazon.awssdk.services.mediaconvert.model.HlsGroupSettings);
    Code:
       0: aload_0
       1: getfield      #18                 // Field manifestCompression:Ljava/lang/String;
       4: areturn

  static java.lang.String access$4900(software.amazon.awssdk.services.mediaconvert.model.HlsGroupSettings);
    Code:
       0: aload_0
       1: getfield      #17                 // Field manifestDurationFormat:Ljava/lang/String;
       4: areturn

  static java.lang.Double access$5000(software.amazon.awssdk.services.mediaconvert.model.HlsGroupSettings);
    Code:
       0: aload_0
       1: getfield      #16                 // Field minFinalSegmentLength:Ljava/lang/Double;
       4: areturn

  static java.lang.Integer access$5100(software.amazon.awssdk.services.mediaconvert.model.HlsGroupSettings);
    Code:
       0: aload_0
       1: getfield      #15                 // Field minSegmentLength:Ljava/lang/Integer;
       4: areturn

  static java.lang.String access$5200(software.amazon.awssdk.services.mediaconvert.model.HlsGroupSettings);
    Code:
       0: aload_0
       1: getfield      #14                 // Field outputSelection:Ljava/lang/String;
       4: areturn

  static java.lang.String access$5300(software.amazon.awssdk.services.mediaconvert.model.HlsGroupSettings);
    Code:
       0: aload_0
       1: getfield      #13                 // Field programDateTime:Ljava/lang/String;
       4: areturn

  static java.lang.Integer access$5400(software.amazon.awssdk.services.mediaconvert.model.HlsGroupSettings);
    Code:
       0: aload_0
       1: getfield      #12                 // Field programDateTimePeriod:Ljava/lang/Integer;
       4: areturn

  static java.lang.String access$5500(software.amazon.awssdk.services.mediaconvert.model.HlsGroupSettings);
    Code:
       0: aload_0
       1: getfield      #11                 // Field segmentControl:Ljava/lang/String;
       4: areturn

  static java.lang.Integer access$5600(software.amazon.awssdk.services.mediaconvert.model.HlsGroupSettings);
    Code:
       0: aload_0
       1: getfield      #10                 // Field segmentLength:Ljava/lang/Integer;
       4: areturn

  static java.lang.String access$5700(software.amazon.awssdk.services.mediaconvert.model.HlsGroupSettings);
    Code:
       0: aload_0
       1: getfield      #9                  // Field segmentLengthControl:Ljava/lang/String;
       4: areturn

  static java.lang.Integer access$5800(software.amazon.awssdk.services.mediaconvert.model.HlsGroupSettings);
    Code:
       0: aload_0
       1: getfield      #8                  // Field segmentsPerSubdirectory:Ljava/lang/Integer;
       4: areturn

  static java.lang.String access$5900(software.amazon.awssdk.services.mediaconvert.model.HlsGroupSettings);
    Code:
       0: aload_0
       1: getfield      #7                  // Field streamInfResolution:Ljava/lang/String;
       4: areturn

  static java.lang.String access$6000(software.amazon.awssdk.services.mediaconvert.model.HlsGroupSettings);
    Code:
       0: aload_0
       1: getfield      #6                  // Field targetDurationCompatibilityMode:Ljava/lang/String;
       4: areturn

  static java.lang.String access$6100(software.amazon.awssdk.services.mediaconvert.model.HlsGroupSettings);
    Code:
       0: aload_0
       1: getfield      #5                  // Field timedMetadataId3Frame:Ljava/lang/String;
       4: areturn

  static java.lang.Integer access$6200(software.amazon.awssdk.services.mediaconvert.model.HlsGroupSettings);
    Code:
       0: aload_0
       1: getfield      #4                  // Field timedMetadataId3Period:Ljava/lang/Integer;
       4: areturn

  static java.lang.Integer access$6300(software.amazon.awssdk.services.mediaconvert.model.HlsGroupSettings);
    Code:
       0: aload_0
       1: getfield      #3                  // Field timestampDeltaMilliseconds:Ljava/lang/Integer;
       4: areturn

  software.amazon.awssdk.services.mediaconvert.model.HlsGroupSettings(software.amazon.awssdk.services.mediaconvert.model.HlsGroupSettings$BuilderImpl, software.amazon.awssdk.services.mediaconvert.model.HlsGroupSettings$1);
    Code:
       0: aload_0
       1: aload_1
       2: invokespecial #2                  // Method "<init>":(Lsoftware/amazon/awssdk/services/mediaconvert/model/HlsGroupSettings$BuilderImpl;)V
       5: return

  static java.util.List access$6500();
    Code:
       0: getstatic     #1                  // Field SDK_FIELDS:Ljava/util/List;
       3: areturn

  static {};
    Code:
       0: getstatic     #171                // Field software/amazon/awssdk/core/protocol/MarshallingType.LIST:Lsoftware/amazon/awssdk/core/protocol/MarshallingType;
       3: invokestatic  #172                // Method software/amazon/awssdk/core/SdkField.builder:(Lsoftware/amazon/awssdk/core/protocol/MarshallingType;)Lsoftware/amazon/awssdk/core/SdkField$Builder;
       6: ldc           #127                // String AdMarkers
       8: invokevirtual #173                // Method software/amazon/awssdk/core/SdkField$Builder.memberName:(Ljava/lang/String;)Lsoftware/amazon/awssdk/core/SdkField$Builder;
      11: invokedynamic #174,  0            // InvokeDynamic #2:apply:()Ljava/util/function/Function;
      16: invokestatic  #175                // Method getter:(Ljava/util/function/Function;)Ljava/util/function/Function;
      19: invokevirtual #176                // Method software/amazon/awssdk/core/SdkField$Builder.getter:(Ljava/util/function/Function;)Lsoftware/amazon/awssdk/core/SdkField$Builder;
      22: invokedynamic #177,  0            // InvokeDynamic #3:accept:()Ljava/util/function/BiConsumer;
      27: invokestatic  #178                // Method setter:(Ljava/util/function/BiConsumer;)Ljava/util/function/BiConsumer;
      30: invokevirtual #179                // Method software/amazon/awssdk/core/SdkField$Builder.setter:(Ljava/util/function/BiConsumer;)Lsoftware/amazon/awssdk/core/SdkField$Builder;
      33: iconst_2
      34: anewarray     #180                // class software/amazon/awssdk/core/traits/Trait
      37: dup
      38: iconst_0
      39: invokestatic  #181                // Method software/amazon/awssdk/core/traits/LocationTrait.builder:()Lsoftware/amazon/awssdk/core/traits/LocationTrait$Builder;
      42: getstatic     #182                // Field software/amazon/awssdk/core/protocol/MarshallLocation.PAYLOAD:Lsoftware/amazon/awssdk/core/protocol/MarshallLocation;
      45: invokevirtual #183                // Method software/amazon/awssdk/core/traits/LocationTrait$Builder.location:(Lsoftware/amazon/awssdk/core/protocol/MarshallLocation;)Lsoftware/amazon/awssdk/core/traits/LocationTrait$Builder;
      48: ldc           #184                // String adMarkers
      50: invokevirtual #185                // Method software/amazon/awssdk/core/traits/LocationTrait$Builder.locationName:(Ljava/lang/String;)Lsoftware/amazon/awssdk/core/traits/LocationTrait$Builder;
      53: invokevirtual #186                // Method software/amazon/awssdk/core/traits/LocationTrait$Builder.build:()Lsoftware/amazon/awssdk/core/traits/LocationTrait;
      56: aastore
      57: dup
      58: iconst_1
      59: invokestatic  #187                // Method software/amazon/awssdk/core/traits/ListTrait.builder:()Lsoftware/amazon/awssdk/core/traits/ListTrait$Builder;
      62: aconst_null
      63: invokevirtual #188                // Method software/amazon/awssdk/core/traits/ListTrait$Builder.memberLocationName:(Ljava/lang/String;)Lsoftware/amazon/awssdk/core/traits/ListTrait$Builder;
      66: getstatic     #189                // Field software/amazon/awssdk/core/protocol/MarshallingType.STRING:Lsoftware/amazon/awssdk/core/protocol/MarshallingType;
      69: invokestatic  #172                // Method software/amazon/awssdk/core/SdkField.builder:(Lsoftware/amazon/awssdk/core/protocol/MarshallingType;)Lsoftware/amazon/awssdk/core/SdkField$Builder;
      72: iconst_1
      73: anewarray     #180                // class software/amazon/awssdk/core/traits/Trait
      76: dup
      77: iconst_0
      78: invokestatic  #181                // Method software/amazon/awssdk/core/traits/LocationTrait.builder:()Lsoftware/amazon/awssdk/core/traits/LocationTrait$Builder;
      81: getstatic     #182                // Field software/amazon/awssdk/core/protocol/MarshallLocation.PAYLOAD:Lsoftware/amazon/awssdk/core/protocol/MarshallLocation;
      84: invokevirtual #183                // Method software/amazon/awssdk/core/traits/LocationTrait$Builder.location:(Lsoftware/amazon/awssdk/core/protocol/MarshallLocation;)Lsoftware/amazon/awssdk/core/traits/LocationTrait$Builder;
      87: ldc           #190                // String member
      89: invokevirtual #185                // Method software/amazon/awssdk/core/traits/LocationTrait$Builder.locationName:(Ljava/lang/String;)Lsoftware/amazon/awssdk/core/traits/LocationTrait$Builder;
      92: invokevirtual #186                // Method software/amazon/awssdk/core/traits/LocationTrait$Builder.build:()Lsoftware/amazon/awssdk/core/traits/LocationTrait;
      95: aastore
      96: invokevirtual #191                // Method software/amazon/awssdk/core/SdkField$Builder.traits:([Lsoftware/amazon/awssdk/core/traits/Trait;)Lsoftware/amazon/awssdk/core/SdkField$Builder;
      99: invokevirtual #192                // Method software/amazon/awssdk/core/SdkField$Builder.build:()Lsoftware/amazon/awssdk/core/SdkField;
     102: invokevirtual #193                // Method software/amazon/awssdk/core/traits/ListTrait$Builder.memberFieldInfo:(Lsoftware/amazon/awssdk/core/SdkField;)Lsoftware/amazon/awssdk/core/traits/ListTrait$Builder;
     105: invokevirtual #194                // Method software/amazon/awssdk/core/traits/ListTrait$Builder.build:()Lsoftware/amazon/awssdk/core/traits/ListTrait;
     108: aastore
     109: invokevirtual #191                // Method software/amazon/awssdk/core/SdkField$Builder.traits:([Lsoftware/amazon/awssdk/core/traits/Trait;)Lsoftware/amazon/awssdk/core/SdkField$Builder;
     112: invokevirtual #192                // Method software/amazon/awssdk/core/SdkField$Builder.build:()Lsoftware/amazon/awssdk/core/SdkField;
     115: putstatic     #195                // Field AD_MARKERS_FIELD:Lsoftware/amazon/awssdk/core/SdkField;
     118: getstatic     #171                // Field software/amazon/awssdk/core/protocol/MarshallingType.LIST:Lsoftware/amazon/awssdk/core/protocol/MarshallingType;
     121: invokestatic  #172                // Method software/amazon/awssdk/core/SdkField.builder:(Lsoftware/amazon/awssdk/core/protocol/MarshallingType;)Lsoftware/amazon/awssdk/core/SdkField$Builder;
     124: ldc           #129                // String AdditionalManifests
     126: invokevirtual #173                // Method software/amazon/awssdk/core/SdkField$Builder.memberName:(Ljava/lang/String;)Lsoftware/amazon/awssdk/core/SdkField$Builder;
     129: invokedynamic #196,  0            // InvokeDynamic #4:apply:()Ljava/util/function/Function;
     134: invokestatic  #175                // Method getter:(Ljava/util/function/Function;)Ljava/util/function/Function;
     137: invokevirtual #176                // Method software/amazon/awssdk/core/SdkField$Builder.getter:(Ljava/util/function/Function;)Lsoftware/amazon/awssdk/core/SdkField$Builder;
     140: invokedynamic #197,  0            // InvokeDynamic #5:accept:()Ljava/util/function/BiConsumer;
     145: invokestatic  #178                // Method setter:(Ljava/util/function/BiConsumer;)Ljava/util/function/BiConsumer;
     148: invokevirtual #179                // Method software/amazon/awssdk/core/SdkField$Builder.setter:(Ljava/util/function/BiConsumer;)Lsoftware/amazon/awssdk/core/SdkField$Builder;
     151: iconst_2
     152: anewarray     #180                // class software/amazon/awssdk/core/traits/Trait
     155: dup
     156: iconst_0
     157: invokestatic  #181                // Method software/amazon/awssdk/core/traits/LocationTrait.builder:()Lsoftware/amazon/awssdk/core/traits/LocationTrait$Builder;
     160: getstatic     #182                // Field software/amazon/awssdk/core/protocol/MarshallLocation.PAYLOAD:Lsoftware/amazon/awssdk/core/protocol/MarshallLocation;
     163: invokevirtual #183                // Method software/amazon/awssdk/core/traits/LocationTrait$Builder.location:(Lsoftware/amazon/awssdk/core/protocol/MarshallLocation;)Lsoftware/amazon/awssdk/core/traits/LocationTrait$Builder;
     166: ldc           #198                // String additionalManifests
     168: invokevirtual #185                // Method software/amazon/awssdk/core/traits/LocationTrait$Builder.locationName:(Ljava/lang/String;)Lsoftware/amazon/awssdk/core/traits/LocationTrait$Builder;
     171: invokevirtual #186                // Method software/amazon/awssdk/core/traits/LocationTrait$Builder.build:()Lsoftware/amazon/awssdk/core/traits/LocationTrait;
     174: aastore
     175: dup
     176: iconst_1
     177: invokestatic  #187                // Method software/amazon/awssdk/core/traits/ListTrait.builder:()Lsoftware/amazon/awssdk/core/traits/ListTrait$Builder;
     180: aconst_null
     181: invokevirtual #188                // Method software/amazon/awssdk/core/traits/ListTrait$Builder.memberLocationName:(Ljava/lang/String;)Lsoftware/amazon/awssdk/core/traits/ListTrait$Builder;
     184: getstatic     #199                // Field software/amazon/awssdk/core/protocol/MarshallingType.SDK_POJO:Lsoftware/amazon/awssdk/core/protocol/MarshallingType;
     187: invokestatic  #172                // Method software/amazon/awssdk/core/SdkField.builder:(Lsoftware/amazon/awssdk/core/protocol/MarshallingType;)Lsoftware/amazon/awssdk/core/SdkField$Builder;
     190: invokedynamic #200,  0            // InvokeDynamic #6:get:()Ljava/util/function/Supplier;
     195: invokevirtual #201                // Method software/amazon/awssdk/core/SdkField$Builder.constructor:(Ljava/util/function/Supplier;)Lsoftware/amazon/awssdk/core/SdkField$Builder;
     198: iconst_1
     199: anewarray     #180                // class software/amazon/awssdk/core/traits/Trait
     202: dup
     203: iconst_0
     204: invokestatic  #181                // Method software/amazon/awssdk/core/traits/LocationTrait.builder:()Lsoftware/amazon/awssdk/core/traits/LocationTrait$Builder;
     207: getstatic     #182                // Field software/amazon/awssdk/core/protocol/MarshallLocation.PAYLOAD:Lsoftware/amazon/awssdk/core/protocol/MarshallLocation;
     210: invokevirtual #183                // Method software/amazon/awssdk/core/traits/LocationTrait$Builder.location:(Lsoftware/amazon/awssdk/core/protocol/MarshallLocation;)Lsoftware/amazon/awssdk/core/traits/LocationTrait$Builder;
     213: ldc           #190                // String member
     215: invokevirtual #185                // Method software/amazon/awssdk/core/traits/LocationTrait$Builder.locationName:(Ljava/lang/String;)Lsoftware/amazon/awssdk/core/traits/LocationTrait$Builder;
     218: invokevirtual #186                // Method software/amazon/awssdk/core/traits/LocationTrait$Builder.build:()Lsoftware/amazon/awssdk/core/traits/LocationTrait;
     221: aastore
     222: invokevirtual #191                // Method software/amazon/awssdk/core/SdkField$Builder.traits:([Lsoftware/amazon/awssdk/core/traits/Trait;)Lsoftware/amazon/awssdk/core/SdkField$Builder;
     225: invokevirtual #192                // Method software/amazon/awssdk/core/SdkField$Builder.build:()Lsoftware/amazon/awssdk/core/SdkField;
     228: invokevirtual #193                // Method software/amazon/awssdk/core/traits/ListTrait$Builder.memberFieldInfo:(Lsoftware/amazon/awssdk/core/SdkField;)Lsoftware/amazon/awssdk/core/traits/ListTrait$Builder;
     231: invokevirtual #194                // Method software/amazon/awssdk/core/traits/ListTrait$Builder.build:()Lsoftware/amazon/awssdk/core/traits/ListTrait;
     234: aastore
     235: invokevirtual #191                // Method software/amazon/awssdk/core/SdkField$Builder.traits:([Lsoftware/amazon/awssdk/core/traits/Trait;)Lsoftware/amazon/awssdk/core/SdkField$Builder;
     238: invokevirtual #192                // Method software/amazon/awssdk/core/SdkField$Builder.build:()Lsoftware/amazon/awssdk/core/SdkField;
     241: putstatic     #202                // Field ADDITIONAL_MANIFESTS_FIELD:Lsoftware/amazon/awssdk/core/SdkField;
     244: getstatic     #189                // Field software/amazon/awssdk/core/protocol/MarshallingType.STRING:Lsoftware/amazon/awssdk/core/protocol/MarshallingType;
     247: invokestatic  #172                // Method software/amazon/awssdk/core/SdkField.builder:(Lsoftware/amazon/awssdk/core/protocol/MarshallingType;)Lsoftware/amazon/awssdk/core/SdkField$Builder;
     250: ldc           #130                // String AudioOnlyHeader
     252: invokevirtual #173                // Method software/amazon/awssdk/core/SdkField$Builder.memberName:(Ljava/lang/String;)Lsoftware/amazon/awssdk/core/SdkField$Builder;
     255: invokedynamic #203,  0            // InvokeDynamic #7:apply:()Ljava/util/function/Function;
     260: invokestatic  #175                // Method getter:(Ljava/util/function/Function;)Ljava/util/function/Function;
     263: invokevirtual #176                // Method software/amazon/awssdk/core/SdkField$Builder.getter:(Ljava/util/function/Function;)Lsoftware/amazon/awssdk/core/SdkField$Builder;
     266: invokedynamic #204,  0            // InvokeDynamic #8:accept:()Ljava/util/function/BiConsumer;
     271: invokestatic  #178                // Method setter:(Ljava/util/function/BiConsumer;)Ljava/util/function/BiConsumer;
     274: invokevirtual #179                // Method software/amazon/awssdk/core/SdkField$Builder.setter:(Ljava/util/function/BiConsumer;)Lsoftware/amazon/awssdk/core/SdkField$Builder;
     277: iconst_1
     278: anewarray     #180                // class software/amazon/awssdk/core/traits/Trait
     281: dup
     282: iconst_0
     283: invokestatic  #181                // Method software/amazon/awssdk/core/traits/LocationTrait.builder:()Lsoftware/amazon/awssdk/core/traits/LocationTrait$Builder;
     286: getstatic     #182                // Field software/amazon/awssdk/core/protocol/MarshallLocation.PAYLOAD:Lsoftware/amazon/awssdk/core/protocol/MarshallLocation;
     289: invokevirtual #183                // Method software/amazon/awssdk/core/traits/LocationTrait$Builder.location:(Lsoftware/amazon/awssdk/core/protocol/MarshallLocation;)Lsoftware/amazon/awssdk/core/traits/LocationTrait$Builder;
     292: ldc           #205                // String audioOnlyHeader
     294: invokevirtual #185                // Method software/amazon/awssdk/core/traits/LocationTrait$Builder.locationName:(Ljava/lang/String;)Lsoftware/amazon/awssdk/core/traits/LocationTrait$Builder;
     297: invokevirtual #186                // Method software/amazon/awssdk/core/traits/LocationTrait$Builder.build:()Lsoftware/amazon/awssdk/core/traits/LocationTrait;
     300: aastore
     301: invokevirtual #191                // Method software/amazon/awssdk/core/SdkField$Builder.traits:([Lsoftware/amazon/awssdk/core/traits/Trait;)Lsoftware/amazon/awssdk/core/SdkField$Builder;
     304: invokevirtual #192                // Method software/amazon/awssdk/core/SdkField$Builder.build:()Lsoftware/amazon/awssdk/core/SdkField;
     307: putstatic     #206                // Field AUDIO_ONLY_HEADER_FIELD:Lsoftware/amazon/awssdk/core/SdkField;
     310: getstatic     #189                // Field software/amazon/awssdk/core/protocol/MarshallingType.STRING:Lsoftware/amazon/awssdk/core/protocol/MarshallingType;
     313: invokestatic  #172                // Method software/amazon/awssdk/core/SdkField.builder:(Lsoftware/amazon/awssdk/core/protocol/MarshallingType;)Lsoftware/amazon/awssdk/core/SdkField$Builder;
     316: ldc           #131                // String BaseUrl
     318: invokevirtual #173                // Method software/amazon/awssdk/core/SdkField$Builder.memberName:(Ljava/lang/String;)Lsoftware/amazon/awssdk/core/SdkField$Builder;
     321: invokedynamic #207,  0            // InvokeDynamic #9:apply:()Ljava/util/function/Function;
     326: invokestatic  #175                // Method getter:(Ljava/util/function/Function;)Ljava/util/function/Function;
     329: invokevirtual #176                // Method software/amazon/awssdk/core/SdkField$Builder.getter:(Ljava/util/function/Function;)Lsoftware/amazon/awssdk/core/SdkField$Builder;
     332: invokedynamic #208,  0            // InvokeDynamic #10:accept:()Ljava/util/function/BiConsumer;
     337: invokestatic  #178                // Method setter:(Ljava/util/function/BiConsumer;)Ljava/util/function/BiConsumer;
     340: invokevirtual #179                // Method software/amazon/awssdk/core/SdkField$Builder.setter:(Ljava/util/function/BiConsumer;)Lsoftware/amazon/awssdk/core/SdkField$Builder;
     343: iconst_1
     344: anewarray     #180                // class software/amazon/awssdk/core/traits/Trait
     347: dup
     348: iconst_0
     349: invokestatic  #181                // Method software/amazon/awssdk/core/traits/LocationTrait.builder:()Lsoftware/amazon/awssdk/core/traits/LocationTrait$Builder;
     352: getstatic     #182                // Field software/amazon/awssdk/core/protocol/MarshallLocation.PAYLOAD:Lsoftware/amazon/awssdk/core/protocol/MarshallLocation;
     355: invokevirtual #183                // Method software/amazon/awssdk/core/traits/LocationTrait$Builder.location:(Lsoftware/amazon/awssdk/core/protocol/MarshallLocation;)Lsoftware/amazon/awssdk/core/traits/LocationTrait$Builder;
     358: ldc           #209                // String baseUrl
     360: invokevirtual #185                // Method software/amazon/awssdk/core/traits/LocationTrait$Builder.locationName:(Ljava/lang/String;)Lsoftware/amazon/awssdk/core/traits/LocationTrait$Builder;
     363: invokevirtual #186                // Method software/amazon/awssdk/core/traits/LocationTrait$Builder.build:()Lsoftware/amazon/awssdk/core/traits/LocationTrait;
     366: aastore
     367: invokevirtual #191                // Method software/amazon/awssdk/core/SdkField$Builder.traits:([Lsoftware/amazon/awssdk/core/traits/Trait;)Lsoftware/amazon/awssdk/core/SdkField$Builder;
     370: invokevirtual #192                // Method software/amazon/awssdk/core/SdkField$Builder.build:()Lsoftware/amazon/awssdk/core/SdkField;
     373: putstatic     #210                // Field BASE_URL_FIELD:Lsoftware/amazon/awssdk/core/SdkField;
     376: getstatic     #171                // Field software/amazon/awssdk/core/protocol/MarshallingType.LIST:Lsoftware/amazon/awssdk/core/protocol/MarshallingType;
     379: invokestatic  #172                // Method software/amazon/awssdk/core/SdkField.builder:(Lsoftware/amazon/awssdk/core/protocol/MarshallingType;)Lsoftware/amazon/awssdk/core/SdkField$Builder;
     382: ldc           #132                // String CaptionLanguageMappings
     384: invokevirtual #173                // Method software/amazon/awssdk/core/SdkField$Builder.memberName:(Ljava/lang/String;)Lsoftware/amazon/awssdk/core/SdkField$Builder;
     387: invokedynamic #211,  0            // InvokeDynamic #11:apply:()Ljava/util/function/Function;
     392: invokestatic  #175                // Method getter:(Ljava/util/function/Function;)Ljava/util/function/Function;
     395: invokevirtual #176                // Method software/amazon/awssdk/core/SdkField$Builder.getter:(Ljava/util/function/Function;)Lsoftware/amazon/awssdk/core/SdkField$Builder;
     398: invokedynamic #212,  0            // InvokeDynamic #12:accept:()Ljava/util/function/BiConsumer;
     403: invokestatic  #178                // Method setter:(Ljava/util/function/BiConsumer;)Ljava/util/function/BiConsumer;
     406: invokevirtual #179                // Method software/amazon/awssdk/core/SdkField$Builder.setter:(Ljava/util/function/BiConsumer;)Lsoftware/amazon/awssdk/core/SdkField$Builder;
     409: iconst_2
     410: anewarray     #180                // class software/amazon/awssdk/core/traits/Trait
     413: dup
     414: iconst_0
     415: invokestatic  #181                // Method software/amazon/awssdk/core/traits/LocationTrait.builder:()Lsoftware/amazon/awssdk/core/traits/LocationTrait$Builder;
     418: getstatic     #182                // Field software/amazon/awssdk/core/protocol/MarshallLocation.PAYLOAD:Lsoftware/amazon/awssdk/core/protocol/MarshallLocation;
     421: invokevirtual #183                // Method software/amazon/awssdk/core/traits/LocationTrait$Builder.location:(Lsoftware/amazon/awssdk/core/protocol/MarshallLocation;)Lsoftware/amazon/awssdk/core/traits/LocationTrait$Builder;
     424: ldc           #213                // String captionLanguageMappings
     426: invokevirtual #185                // Method software/amazon/awssdk/core/traits/LocationTrait$Builder.locationName:(Ljava/lang/String;)Lsoftware/amazon/awssdk/core/traits/LocationTrait$Builder;
     429: invokevirtual #186                // Method software/amazon/awssdk/core/traits/LocationTrait$Builder.build:()Lsoftware/amazon/awssdk/core/traits/LocationTrait;
     432: aastore
     433: dup
     434: iconst_1
     435: invokestatic  #187                // Method software/amazon/awssdk/core/traits/ListTrait.builder:()Lsoftware/amazon/awssdk/core/traits/ListTrait$Builder;
     438: aconst_null
     439: invokevirtual #188                // Method software/amazon/awssdk/core/traits/ListTrait$Builder.memberLocationName:(Ljava/lang/String;)Lsoftware/amazon/awssdk/core/traits/ListTrait$Builder;
     442: getstatic     #199                // Field software/amazon/awssdk/core/protocol/MarshallingType.SDK_POJO:Lsoftware/amazon/awssdk/core/protocol/MarshallingType;
     445: invokestatic  #172                // Method software/amazon/awssdk/core/SdkField.builder:(Lsoftware/amazon/awssdk/core/protocol/MarshallingType;)Lsoftware/amazon/awssdk/core/SdkField$Builder;
     448: invokedynamic #214,  0            // InvokeDynamic #13:get:()Ljava/util/function/Supplier;
     453: invokevirtual #201                // Method software/amazon/awssdk/core/SdkField$Builder.constructor:(Ljava/util/function/Supplier;)Lsoftware/amazon/awssdk/core/SdkField$Builder;
     456: iconst_1
     457: anewarray     #180                // class software/amazon/awssdk/core/traits/Trait
     460: dup
     461: iconst_0
     462: invokestatic  #181                // Method software/amazon/awssdk/core/traits/LocationTrait.builder:()Lsoftware/amazon/awssdk/core/traits/LocationTrait$Builder;
     465: getstatic     #182                // Field software/amazon/awssdk/core/protocol/MarshallLocation.PAYLOAD:Lsoftware/amazon/awssdk/core/protocol/MarshallLocation;
     468: invokevirtual #183                // Method software/amazon/awssdk/core/traits/LocationTrait$Builder.location:(Lsoftware/amazon/awssdk/core/protocol/MarshallLocation;)Lsoftware/amazon/awssdk/core/traits/LocationTrait$Builder;
     471: ldc           #190                // String member
     473: invokevirtual #185                // Method software/amazon/awssdk/core/traits/LocationTrait$Builder.locationName:(Ljava/lang/String;)Lsoftware/amazon/awssdk/core/traits/LocationTrait$Builder;
     476: invokevirtual #186                // Method software/amazon/awssdk/core/traits/LocationTrait$Builder.build:()Lsoftware/amazon/awssdk/core/traits/LocationTrait;
     479: aastore
     480: invokevirtual #191                // Method software/amazon/awssdk/core/SdkField$Builder.traits:([Lsoftware/amazon/awssdk/core/traits/Trait;)Lsoftware/amazon/awssdk/core/SdkField$Builder;
     483: invokevirtual #192                // Method software/amazon/awssdk/core/SdkField$Builder.build:()Lsoftware/amazon/awssdk/core/SdkField;
     486: invokevirtual #193                // Method software/amazon/awssdk/core/traits/ListTrait$Builder.memberFieldInfo:(Lsoftware/amazon/awssdk/core/SdkField;)Lsoftware/amazon/awssdk/core/traits/ListTrait$Builder;
     489: invokevirtual #194                // Method software/amazon/awssdk/core/traits/ListTrait$Builder.build:()Lsoftware/amazon/awssdk/core/traits/ListTrait;
     492: aastore
     493: invokevirtual #191                // Method software/amazon/awssdk/core/SdkField$Builder.traits:([Lsoftware/amazon/awssdk/core/traits/Trait;)Lsoftware/amazon/awssdk/core/SdkField$Builder;
     496: invokevirtual #192                // Method software/amazon/awssdk/core/SdkField$Builder.build:()Lsoftware/amazon/awssdk/core/SdkField;
     499: putstatic     #215                // Field CAPTION_LANGUAGE_MAPPINGS_FIELD:Lsoftware/amazon/awssdk/core/SdkField;
     502: getstatic     #189                // Field software/amazon/awssdk/core/protocol/MarshallingType.STRING:Lsoftware/amazon/awssdk/core/protocol/MarshallingType;
     505: invokestatic  #172                // Method software/amazon/awssdk/core/SdkField.builder:(Lsoftware/amazon/awssdk/core/protocol/MarshallingType;)Lsoftware/amazon/awssdk/core/SdkField$Builder;
     508: ldc           #133                // String CaptionLanguageSetting
     510: invokevirtual #173                // Method software/amazon/awssdk/core/SdkField$Builder.memberName:(Ljava/lang/String;)Lsoftware/amazon/awssdk/core/SdkField$Builder;
     513: invokedynamic #216,  0            // InvokeDynamic #14:apply:()Ljava/util/function/Function;
     518: invokestatic  #175                // Method getter:(Ljava/util/function/Function;)Ljava/util/function/Function;
     521: invokevirtual #176                // Method software/amazon/awssdk/core/SdkField$Builder.getter:(Ljava/util/function/Function;)Lsoftware/amazon/awssdk/core/SdkField$Builder;
     524: invokedynamic #217,  0            // InvokeDynamic #15:accept:()Ljava/util/function/BiConsumer;
     529: invokestatic  #178                // Method setter:(Ljava/util/function/BiConsumer;)Ljava/util/function/BiConsumer;
     532: invokevirtual #179                // Method software/amazon/awssdk/core/SdkField$Builder.setter:(Ljava/util/function/BiConsumer;)Lsoftware/amazon/awssdk/core/SdkField$Builder;
     535: iconst_1
     536: anewarray     #180                // class software/amazon/awssdk/core/traits/Trait
     539: dup
     540: iconst_0
     541: invokestatic  #181                // Method software/amazon/awssdk/core/traits/LocationTrait.builder:()Lsoftware/amazon/awssdk/core/traits/LocationTrait$Builder;
     544: getstatic     #182                // Field software/amazon/awssdk/core/protocol/MarshallLocation.PAYLOAD:Lsoftware/amazon/awssdk/core/protocol/MarshallLocation;
     547: invokevirtual #183                // Method software/amazon/awssdk/core/traits/LocationTrait$Builder.location:(Lsoftware/amazon/awssdk/core/protocol/MarshallLocation;)Lsoftware/amazon/awssdk/core/traits/LocationTrait$Builder;
     550: ldc           #218                // String captionLanguageSetting
     552: invokevirtual #185                // Method software/amazon/awssdk/core/traits/LocationTrait$Builder.locationName:(Ljava/lang/String;)Lsoftware/amazon/awssdk/core/traits/LocationTrait$Builder;
     555: invokevirtual #186                // Method software/amazon/awssdk/core/traits/LocationTrait$Builder.build:()Lsoftware/amazon/awssdk/core/traits/LocationTrait;
     558: aastore
     559: invokevirtual #191                // Method software/amazon/awssdk/core/SdkField$Builder.traits:([Lsoftware/amazon/awssdk/core/traits/Trait;)Lsoftware/amazon/awssdk/core/SdkField$Builder;
     562: invokevirtual #192                // Method software/amazon/awssdk/core/SdkField$Builder.build:()Lsoftware/amazon/awssdk/core/SdkField;
     565: putstatic     #219                // Field CAPTION_LANGUAGE_SETTING_FIELD:Lsoftware/amazon/awssdk/core/SdkField;
     568: getstatic     #189                // Field software/amazon/awssdk/core/protocol/MarshallingType.STRING:Lsoftware/amazon/awssdk/core/protocol/MarshallingType;
     571: invokestatic  #172                // Method software/amazon/awssdk/core/SdkField.builder:(Lsoftware/amazon/awssdk/core/protocol/MarshallingType;)Lsoftware/amazon/awssdk/core/SdkField$Builder;
     574: ldc           #134                // String CaptionSegmentLengthControl
     576: invokevirtual #173                // Method software/amazon/awssdk/core/SdkField$Builder.memberName:(Ljava/lang/String;)Lsoftware/amazon/awssdk/core/SdkField$Builder;
     579: invokedynamic #220,  0            // InvokeDynamic #16:apply:()Ljava/util/function/Function;
     584: invokestatic  #175                // Method getter:(Ljava/util/function/Function;)Ljava/util/function/Function;
     587: invokevirtual #176                // Method software/amazon/awssdk/core/SdkField$Builder.getter:(Ljava/util/function/Function;)Lsoftware/amazon/awssdk/core/SdkField$Builder;
     590: invokedynamic #221,  0            // InvokeDynamic #17:accept:()Ljava/util/function/BiConsumer;
     595: invokestatic  #178                // Method setter:(Ljava/util/function/BiConsumer;)Ljava/util/function/BiConsumer;
     598: invokevirtual #179                // Method software/amazon/awssdk/core/SdkField$Builder.setter:(Ljava/util/function/BiConsumer;)Lsoftware/amazon/awssdk/core/SdkField$Builder;
     601: iconst_1
     602: anewarray     #180                // class software/amazon/awssdk/core/traits/Trait
     605: dup
     606: iconst_0
     607: invokestatic  #181                // Method software/amazon/awssdk/core/traits/LocationTrait.builder:()Lsoftware/amazon/awssdk/core/traits/LocationTrait$Builder;
     610: getstatic     #182                // Field software/amazon/awssdk/core/protocol/MarshallLocation.PAYLOAD:Lsoftware/amazon/awssdk/core/protocol/MarshallLocation;
     613: invokevirtual #183                // Method software/amazon/awssdk/core/traits/LocationTrait$Builder.location:(Lsoftware/amazon/awssdk/core/protocol/MarshallLocation;)Lsoftware/amazon/awssdk/core/traits/LocationTrait$Builder;
     616: ldc           #222                // String captionSegmentLengthControl
     618: invokevirtual #185                // Method software/amazon/awssdk/core/traits/LocationTrait$Builder.locationName:(Ljava/lang/String;)Lsoftware/amazon/awssdk/core/traits/LocationTrait$Builder;
     621: invokevirtual #186                // Method software/amazon/awssdk/core/traits/LocationTrait$Builder.build:()Lsoftware/amazon/awssdk/core/traits/LocationTrait;
     624: aastore
     625: invokevirtual #191                // Method software/amazon/awssdk/core/SdkField$Builder.traits:([Lsoftware/amazon/awssdk/core/traits/Trait;)Lsoftware/amazon/awssdk/core/SdkField$Builder;
     628: invokevirtual #192                // Method software/amazon/awssdk/core/SdkField$Builder.build:()Lsoftware/amazon/awssdk/core/SdkField;
     631: putstatic     #223                // Field CAPTION_SEGMENT_LENGTH_CONTROL_FIELD:Lsoftware/amazon/awssdk/core/SdkField;
     634: getstatic     #189                // Field software/amazon/awssdk/core/protocol/MarshallingType.STRING:Lsoftware/amazon/awssdk/core/protocol/MarshallingType;
     637: invokestatic  #172                // Method software/amazon/awssdk/core/SdkField.builder:(Lsoftware/amazon/awssdk/core/protocol/MarshallingType;)Lsoftware/amazon/awssdk/core/SdkField$Builder;
     640: ldc           #135                // String ClientCache
     642: invokevirtual #173                // Method software/amazon/awssdk/core/SdkField$Builder.memberName:(Ljava/lang/String;)Lsoftware/amazon/awssdk/core/SdkField$Builder;
     645: invokedynamic #224,  0            // InvokeDynamic #18:apply:()Ljava/util/function/Function;
     650: invokestatic  #175                // Method getter:(Ljava/util/function/Function;)Ljava/util/function/Function;
     653: invokevirtual #176                // Method software/amazon/awssdk/core/SdkField$Builder.getter:(Ljava/util/function/Function;)Lsoftware/amazon/awssdk/core/SdkField$Builder;
     656: invokedynamic #225,  0            // InvokeDynamic #19:accept:()Ljava/util/function/BiConsumer;
     661: invokestatic  #178                // Method setter:(Ljava/util/function/BiConsumer;)Ljava/util/function/BiConsumer;
     664: invokevirtual #179                // Method software/amazon/awssdk/core/SdkField$Builder.setter:(Ljava/util/function/BiConsumer;)Lsoftware/amazon/awssdk/core/SdkField$Builder;
     667: iconst_1
     668: anewarray     #180                // class software/amazon/awssdk/core/traits/Trait
     671: dup
     672: iconst_0
     673: invokestatic  #181                // Method software/amazon/awssdk/core/traits/LocationTrait.builder:()Lsoftware/amazon/awssdk/core/traits/LocationTrait$Builder;
     676: getstatic     #182                // Field software/amazon/awssdk/core/protocol/MarshallLocation.PAYLOAD:Lsoftware/amazon/awssdk/core/protocol/MarshallLocation;
     679: invokevirtual #183                // Method software/amazon/awssdk/core/traits/LocationTrait$Builder.location:(Lsoftware/amazon/awssdk/core/protocol/MarshallLocation;)Lsoftware/amazon/awssdk/core/traits/LocationTrait$Builder;
     682: ldc           #226                // String clientCache
     684: invokevirtual #185                // Method software/amazon/awssdk/core/traits/LocationTrait$Builder.locationName:(Ljava/lang/String;)Lsoftware/amazon/awssdk/core/traits/LocationTrait$Builder;
     687: invokevirtual #186                // Method software/amazon/awssdk/core/traits/LocationTrait$Builder.build:()Lsoftware/amazon/awssdk/core/traits/LocationTrait;
     690: aastore
     691: invokevirtual #191                // Method software/amazon/awssdk/core/SdkField$Builder.traits:([Lsoftware/amazon/awssdk/core/traits/Trait;)Lsoftware/amazon/awssdk/core/SdkField$Builder;
     694: invokevirtual #192                // Method software/amazon/awssdk/core/SdkField$Builder.build:()Lsoftware/amazon/awssdk/core/SdkField;
     697: putstatic     #227                // Field CLIENT_CACHE_FIELD:Lsoftware/amazon/awssdk/core/SdkField;
     700: getstatic     #189                // Field software/amazon/awssdk/core/protocol/MarshallingType.STRING:Lsoftware/amazon/awssdk/core/protocol/MarshallingType;
     703: invokestatic  #172                // Method software/amazon/awssdk/core/SdkField.builder:(Lsoftware/amazon/awssdk/core/protocol/MarshallingType;)Lsoftware/amazon/awssdk/core/SdkField$Builder;
     706: ldc           #136                // String CodecSpecification
     708: invokevirtual #173                // Method software/amazon/awssdk/core/SdkField$Builder.memberName:(Ljava/lang/String;)Lsoftware/amazon/awssdk/core/SdkField$Builder;
     711: invokedynamic #228,  0            // InvokeDynamic #20:apply:()Ljava/util/function/Function;
     716: invokestatic  #175                // Method getter:(Ljava/util/function/Function;)Ljava/util/function/Function;
     719: invokevirtual #176                // Method software/amazon/awssdk/core/SdkField$Builder.getter:(Ljava/util/function/Function;)Lsoftware/amazon/awssdk/core/SdkField$Builder;
     722: invokedynamic #229,  0            // InvokeDynamic #21:accept:()Ljava/util/function/BiConsumer;
     727: invokestatic  #178                // Method setter:(Ljava/util/function/BiConsumer;)Ljava/util/function/BiConsumer;
     730: invokevirtual #179                // Method software/amazon/awssdk/core/SdkField$Builder.setter:(Ljava/util/function/BiConsumer;)Lsoftware/amazon/awssdk/core/SdkField$Builder;
     733: iconst_1
     734: anewarray     #180                // class software/amazon/awssdk/core/traits/Trait
     737: dup
     738: iconst_0
     739: invokestatic  #181                // Method software/amazon/awssdk/core/traits/LocationTrait.builder:()Lsoftware/amazon/awssdk/core/traits/LocationTrait$Builder;
     742: getstatic     #182                // Field software/amazon/awssdk/core/protocol/MarshallLocation.PAYLOAD:Lsoftware/amazon/awssdk/core/protocol/MarshallLocation;
     745: invokevirtual #183                // Method software/amazon/awssdk/core/traits/LocationTrait$Builder.location:(Lsoftware/amazon/awssdk/core/protocol/MarshallLocation;)Lsoftware/amazon/awssdk/core/traits/LocationTrait$Builder;
     748: ldc           #230                // String codecSpecification
     750: invokevirtual #185                // Method software/amazon/awssdk/core/traits/LocationTrait$Builder.locationName:(Ljava/lang/String;)Lsoftware/amazon/awssdk/core/traits/LocationTrait$Builder;
     753: invokevirtual #186                // Method software/amazon/awssdk/core/traits/LocationTrait$Builder.build:()Lsoftware/amazon/awssdk/core/traits/LocationTrait;
     756: aastore
     757: invokevirtual #191                // Method software/amazon/awssdk/core/SdkField$Builder.traits:([Lsoftware/amazon/awssdk/core/traits/Trait;)Lsoftware/amazon/awssdk/core/SdkField$Builder;
     760: invokevirtual #192                // Method software/amazon/awssdk/core/SdkField$Builder.build:()Lsoftware/amazon/awssdk/core/SdkField;
     763: putstatic     #231                // Field CODEC_SPECIFICATION_FIELD:Lsoftware/amazon/awssdk/core/SdkField;
     766: getstatic     #189                // Field software/amazon/awssdk/core/protocol/MarshallingType.STRING:Lsoftware/amazon/awssdk/core/protocol/MarshallingType;
     769: invokestatic  #172                // Method software/amazon/awssdk/core/SdkField.builder:(Lsoftware/amazon/awssdk/core/protocol/MarshallingType;)Lsoftware/amazon/awssdk/core/SdkField$Builder;
     772: ldc           #137                // String Destination
     774: invokevirtual #173                // Method software/amazon/awssdk/core/SdkField$Builder.memberName:(Ljava/lang/String;)Lsoftware/amazon/awssdk/core/SdkField$Builder;
     777: invokedynamic #232,  0            // InvokeDynamic #22:apply:()Ljava/util/function/Function;
     782: invokestatic  #175                // Method getter:(Ljava/util/function/Function;)Ljava/util/function/Function;
     785: invokevirtual #176                // Method software/amazon/awssdk/core/SdkField$Builder.getter:(Ljava/util/function/Function;)Lsoftware/amazon/awssdk/core/SdkField$Builder;
     788: invokedynamic #233,  0            // InvokeDynamic #23:accept:()Ljava/util/function/BiConsumer;
     793: invokestatic  #178                // Method setter:(Ljava/util/function/BiConsumer;)Ljava/util/function/BiConsumer;
     796: invokevirtual #179                // Method software/amazon/awssdk/core/SdkField$Builder.setter:(Ljava/util/function/BiConsumer;)Lsoftware/amazon/awssdk/core/SdkField$Builder;
     799: iconst_1
     800: anewarray     #180                // class software/amazon/awssdk/core/traits/Trait
     803: dup
     804: iconst_0
     805: invokestatic  #181                // Method software/amazon/awssdk/core/traits/LocationTrait.builder:()Lsoftware/amazon/awssdk/core/traits/LocationTrait$Builder;
     808: getstatic     #182                // Field software/amazon/awssdk/core/protocol/MarshallLocation.PAYLOAD:Lsoftware/amazon/awssdk/core/protocol/MarshallLocation;
     811: invokevirtual #183                // Method software/amazon/awssdk/core/traits/LocationTrait$Builder.location:(Lsoftware/amazon/awssdk/core/protocol/MarshallLocation;)Lsoftware/amazon/awssdk/core/traits/LocationTrait$Builder;
     814: ldc           #234                // String destination
     816: invokevirtual #185                // Method software/amazon/awssdk/core/traits/LocationTrait$Builder.locationName:(Ljava/lang/String;)Lsoftware/amazon/awssdk/core/traits/LocationTrait$Builder;
     819: invokevirtual #186                // Method software/amazon/awssdk/core/traits/LocationTrait$Builder.build:()Lsoftware/amazon/awssdk/core/traits/LocationTrait;
     822: aastore
     823: invokevirtual #191                // Method software/amazon/awssdk/core/SdkField$Builder.traits:([Lsoftware/amazon/awssdk/core/traits/Trait;)Lsoftware/amazon/awssdk/core/SdkField$Builder;
     826: invokevirtual #192                // Method software/amazon/awssdk/core/SdkField$Builder.build:()Lsoftware/amazon/awssdk/core/SdkField;
     829: putstatic     #235                // Field DESTINATION_FIELD:Lsoftware/amazon/awssdk/core/SdkField;
     832: getstatic     #199                // Field software/amazon/awssdk/core/protocol/MarshallingType.SDK_POJO:Lsoftware/amazon/awssdk/core/protocol/MarshallingType;
     835: invokestatic  #172                // Method software/amazon/awssdk/core/SdkField.builder:(Lsoftware/amazon/awssdk/core/protocol/MarshallingType;)Lsoftware/amazon/awssdk/core/SdkField$Builder;
     838: ldc           #138                // String DestinationSettings
     840: invokevirtual #173                // Method software/amazon/awssdk/core/SdkField$Builder.memberName:(Ljava/lang/String;)Lsoftware/amazon/awssdk/core/SdkField$Builder;
     843: invokedynamic #236,  0            // InvokeDynamic #24:apply:()Ljava/util/function/Function;
     848: invokestatic  #175                // Method getter:(Ljava/util/function/Function;)Ljava/util/function/Function;
     851: invokevirtual #176                // Method software/amazon/awssdk/core/SdkField$Builder.getter:(Ljava/util/function/Function;)Lsoftware/amazon/awssdk/core/SdkField$Builder;
     854: invokedynamic #237,  0            // InvokeDynamic #25:accept:()Ljava/util/function/BiConsumer;
     859: invokestatic  #178                // Method setter:(Ljava/util/function/BiConsumer;)Ljava/util/function/BiConsumer;
     862: invokevirtual #179                // Method software/amazon/awssdk/core/SdkField$Builder.setter:(Ljava/util/function/BiConsumer;)Lsoftware/amazon/awssdk/core/SdkField$Builder;
     865: invokedynamic #238,  0            // InvokeDynamic #26:get:()Ljava/util/function/Supplier;
     870: invokevirtual #201                // Method software/amazon/awssdk/core/SdkField$Builder.constructor:(Ljava/util/function/Supplier;)Lsoftware/amazon/awssdk/core/SdkField$Builder;
     873: iconst_1
     874: anewarray     #180                // class software/amazon/awssdk/core/traits/Trait
     877: dup
     878: iconst_0
     879: invokestatic  #181                // Method software/amazon/awssdk/core/traits/LocationTrait.builder:()Lsoftware/amazon/awssdk/core/traits/LocationTrait$Builder;
     882: getstatic     #182                // Field software/amazon/awssdk/core/protocol/MarshallLocation.PAYLOAD:Lsoftware/amazon/awssdk/core/protocol/MarshallLocation;
     885: invokevirtual #183                // Method software/amazon/awssdk/core/traits/LocationTrait$Builder.location:(Lsoftware/amazon/awssdk/core/protocol/MarshallLocation;)Lsoftware/amazon/awssdk/core/traits/LocationTrait$Builder;
     888: ldc           #239                // String destinationSettings
     890: invokevirtual #185                // Method software/amazon/awssdk/core/traits/LocationTrait$Builder.locationName:(Ljava/lang/String;)Lsoftware/amazon/awssdk/core/traits/LocationTrait$Builder;
     893: invokevirtual #186                // Method software/amazon/awssdk/core/traits/LocationTrait$Builder.build:()Lsoftware/amazon/awssdk/core/traits/LocationTrait;
     896: aastore
     897: invokevirtual #191                // Method software/amazon/awssdk/core/SdkField$Builder.traits:([Lsoftware/amazon/awssdk/core/traits/Trait;)Lsoftware/amazon/awssdk/core/SdkField$Builder;
     900: invokevirtual #192                // Method software/amazon/awssdk/core/SdkField$Builder.build:()Lsoftware/amazon/awssdk/core/SdkField;
     903: putstatic     #240                // Field DESTINATION_SETTINGS_FIELD:Lsoftware/amazon/awssdk/core/SdkField;
     906: getstatic     #189                // Field software/amazon/awssdk/core/protocol/MarshallingType.STRING:Lsoftware/amazon/awssdk/core/protocol/MarshallingType;
     909: invokestatic  #172                // Method software/amazon/awssdk/core/SdkField.builder:(Lsoftware/amazon/awssdk/core/protocol/MarshallingType;)Lsoftware/amazon/awssdk/core/SdkField$Builder;
     912: ldc           #139                // String DirectoryStructure
     914: invokevirtual #173                // Method software/amazon/awssdk/core/SdkField$Builder.memberName:(Ljava/lang/String;)Lsoftware/amazon/awssdk/core/SdkField$Builder;
     917: invokedynamic #241,  0            // InvokeDynamic #27:apply:()Ljava/util/function/Function;
     922: invokestatic  #175                // Method getter:(Ljava/util/function/Function;)Ljava/util/function/Function;
     925: invokevirtual #176                // Method software/amazon/awssdk/core/SdkField$Builder.getter:(Ljava/util/function/Function;)Lsoftware/amazon/awssdk/core/SdkField$Builder;
     928: invokedynamic #242,  0            // InvokeDynamic #28:accept:()Ljava/util/function/BiConsumer;
     933: invokestatic  #178                // Method setter:(Ljava/util/function/BiConsumer;)Ljava/util/function/BiConsumer;
     936: invokevirtual #179                // Method software/amazon/awssdk/core/SdkField$Builder.setter:(Ljava/util/function/BiConsumer;)Lsoftware/amazon/awssdk/core/SdkField$Builder;
     939: iconst_1
     940: anewarray     #180                // class software/amazon/awssdk/core/traits/Trait
     943: dup
     944: iconst_0
     945: invokestatic  #181                // Method software/amazon/awssdk/core/traits/LocationTrait.builder:()Lsoftware/amazon/awssdk/core/traits/LocationTrait$Builder;
     948: getstatic     #182                // Field software/amazon/awssdk/core/protocol/MarshallLocation.PAYLOAD:Lsoftware/amazon/awssdk/core/protocol/MarshallLocation;
     951: invokevirtual #183                // Method software/amazon/awssdk/core/traits/LocationTrait$Builder.location:(Lsoftware/amazon/awssdk/core/protocol/MarshallLocation;)Lsoftware/amazon/awssdk/core/traits/LocationTrait$Builder;
     954: ldc           #243                // String directoryStructure
     956: invokevirtual #185                // Method software/amazon/awssdk/core/traits/LocationTrait$Builder.locationName:(Ljava/lang/String;)Lsoftware/amazon/awssdk/core/traits/LocationTrait$Builder;
     959: invokevirtual #186                // Method software/amazon/awssdk/core/traits/LocationTrait$Builder.build:()Lsoftware/amazon/awssdk/core/traits/LocationTrait;
     962: aastore
     963: invokevirtual #191                // Method software/amazon/awssdk/core/SdkField$Builder.traits:([Lsoftware/amazon/awssdk/core/traits/Trait;)Lsoftware/amazon/awssdk/core/SdkField$Builder;
     966: invokevirtual #192                // Method software/amazon/awssdk/core/SdkField$Builder.build:()Lsoftware/amazon/awssdk/core/SdkField;
     969: putstatic     #244                // Field DIRECTORY_STRUCTURE_FIELD:Lsoftware/amazon/awssdk/core/SdkField;
     972: getstatic     #199                // Field software/amazon/awssdk/core/protocol/MarshallingType.SDK_POJO:Lsoftware/amazon/awssdk/core/protocol/MarshallingType;
     975: invokestatic  #172                // Method software/amazon/awssdk/core/SdkField.builder:(Lsoftware/amazon/awssdk/core/protocol/MarshallingType;)Lsoftware/amazon/awssdk/core/SdkField$Builder;
     978: ldc           #140                // String Encryption
     980: invokevirtual #173                // Method software/amazon/awssdk/core/SdkField$Builder.memberName:(Ljava/lang/String;)Lsoftware/amazon/awssdk/core/SdkField$Builder;
     983: invokedynamic #245,  0            // InvokeDynamic #29:apply:()Ljava/util/function/Function;
     988: invokestatic  #175                // Method getter:(Ljava/util/function/Function;)Ljava/util/function/Function;
     991: invokevirtual #176                // Method software/amazon/awssdk/core/SdkField$Builder.getter:(Ljava/util/function/Function;)Lsoftware/amazon/awssdk/core/SdkField$Builder;
     994: invokedynamic #246,  0            // InvokeDynamic #30:accept:()Ljava/util/function/BiConsumer;
     999: invokestatic  #178                // Method setter:(Ljava/util/function/BiConsumer;)Ljava/util/function/BiConsumer;
    1002: invokevirtual #179                // Method software/amazon/awssdk/core/SdkField$Builder.setter:(Ljava/util/function/BiConsumer;)Lsoftware/amazon/awssdk/core/SdkField$Builder;
    1005: invokedynamic #247,  0            // InvokeDynamic #31:get:()Ljava/util/function/Supplier;
    1010: invokevirtual #201                // Method software/amazon/awssdk/core/SdkField$Builder.constructor:(Ljava/util/function/Supplier;)Lsoftware/amazon/awssdk/core/SdkField$Builder;
    1013: iconst_1
    1014: anewarray     #180                // class software/amazon/awssdk/core/traits/Trait
    1017: dup
    1018: iconst_0
    1019: invokestatic  #181                // Method software/amazon/awssdk/core/traits/LocationTrait.builder:()Lsoftware/amazon/awssdk/core/traits/LocationTrait$Builder;
    1022: getstatic     #182                // Field software/amazon/awssdk/core/protocol/MarshallLocation.PAYLOAD:Lsoftware/amazon/awssdk/core/protocol/MarshallLocation;
    1025: invokevirtual #183                // Method software/amazon/awssdk/core/traits/LocationTrait$Builder.location:(Lsoftware/amazon/awssdk/core/protocol/MarshallLocation;)Lsoftware/amazon/awssdk/core/traits/LocationTrait$Builder;
    1028: ldc           #248                // String encryption
    1030: invokevirtual #185                // Method software/amazon/awssdk/core/traits/LocationTrait$Builder.locationName:(Ljava/lang/String;)Lsoftware/amazon/awssdk/core/traits/LocationTrait$Builder;
    1033: invokevirtual #186                // Method software/amazon/awssdk/core/traits/LocationTrait$Builder.build:()Lsoftware/amazon/awssdk/core/traits/LocationTrait;
    1036: aastore
    1037: invokevirtual #191                // Method software/amazon/awssdk/core/SdkField$Builder.traits:([Lsoftware/amazon/awssdk/core/traits/Trait;)Lsoftware/amazon/awssdk/core/SdkField$Builder;
    1040: invokevirtual #192                // Method software/amazon/awssdk/core/SdkField$Builder.build:()Lsoftware/amazon/awssdk/core/SdkField;
    1043: putstatic     #249                // Field ENCRYPTION_FIELD:Lsoftware/amazon/awssdk/core/SdkField;
    1046: getstatic     #189                // Field software/amazon/awssdk/core/protocol/MarshallingType.STRING:Lsoftware/amazon/awssdk/core/protocol/MarshallingType;
    1049: invokestatic  #172                // Method software/amazon/awssdk/core/SdkField.builder:(Lsoftware/amazon/awssdk/core/protocol/MarshallingType;)Lsoftware/amazon/awssdk/core/SdkField$Builder;
    1052: ldc           #141                // String ImageBasedTrickPlay
    1054: invokevirtual #173                // Method software/amazon/awssdk/core/SdkField$Builder.memberName:(Ljava/lang/String;)Lsoftware/amazon/awssdk/core/SdkField$Builder;
    1057: invokedynamic #250,  0            // InvokeDynamic #32:apply:()Ljava/util/function/Function;
    1062: invokestatic  #175                // Method getter:(Ljava/util/function/Function;)Ljava/util/function/Function;
    1065: invokevirtual #176                // Method software/amazon/awssdk/core/SdkField$Builder.getter:(Ljava/util/function/Function;)Lsoftware/amazon/awssdk/core/SdkField$Builder;
    1068: invokedynamic #251,  0            // InvokeDynamic #33:accept:()Ljava/util/function/BiConsumer;
    1073: invokestatic  #178                // Method setter:(Ljava/util/function/BiConsumer;)Ljava/util/function/BiConsumer;
    1076: invokevirtual #179                // Method software/amazon/awssdk/core/SdkField$Builder.setter:(Ljava/util/function/BiConsumer;)Lsoftware/amazon/awssdk/core/SdkField$Builder;
    1079: iconst_1
    1080: anewarray     #180                // class software/amazon/awssdk/core/traits/Trait
    1083: dup
    1084: iconst_0
    1085: invokestatic  #181                // Method software/amazon/awssdk/core/traits/LocationTrait.builder:()Lsoftware/amazon/awssdk/core/traits/LocationTrait$Builder;
    1088: getstatic     #182                // Field software/amazon/awssdk/core/protocol/MarshallLocation.PAYLOAD:Lsoftware/amazon/awssdk/core/protocol/MarshallLocation;
    1091: invokevirtual #183                // Method software/amazon/awssdk/core/traits/LocationTrait$Builder.location:(Lsoftware/amazon/awssdk/core/protocol/MarshallLocation;)Lsoftware/amazon/awssdk/core/traits/LocationTrait$Builder;
    1094: ldc           #252                // String imageBasedTrickPlay
    1096: invokevirtual #185                // Method software/amazon/awssdk/core/traits/LocationTrait$Builder.locationName:(Ljava/lang/String;)Lsoftware/amazon/awssdk/core/traits/LocationTrait$Builder;
    1099: invokevirtual #186                // Method software/amazon/awssdk/core/traits/LocationTrait$Builder.build:()Lsoftware/amazon/awssdk/core/traits/LocationTrait;
    1102: aastore
    1103: invokevirtual #191                // Method software/amazon/awssdk/core/SdkField$Builder.traits:([Lsoftware/amazon/awssdk/core/traits/Trait;)Lsoftware/amazon/awssdk/core/SdkField$Builder;
    1106: invokevirtual #192                // Method software/amazon/awssdk/core/SdkField$Builder.build:()Lsoftware/amazon/awssdk/core/SdkField;
    1109: putstatic     #253                // Field IMAGE_BASED_TRICK_PLAY_FIELD:Lsoftware/amazon/awssdk/core/SdkField;
    1112: getstatic     #199                // Field software/amazon/awssdk/core/protocol/MarshallingType.SDK_POJO:Lsoftware/amazon/awssdk/core/protocol/MarshallingType;
    1115: invokestatic  #172                // Method software/amazon/awssdk/core/SdkField.builder:(Lsoftware/amazon/awssdk/core/protocol/MarshallingType;)Lsoftware/amazon/awssdk/core/SdkField$Builder;
    1118: ldc           #142                // String ImageBasedTrickPlaySettings
    1120: invokevirtual #173                // Method software/amazon/awssdk/core/SdkField$Builder.memberName:(Ljava/lang/String;)Lsoftware/amazon/awssdk/core/SdkField$Builder;
    1123: invokedynamic #254,  0            // InvokeDynamic #34:apply:()Ljava/util/function/Function;
    1128: invokestatic  #175                // Method getter:(Ljava/util/function/Function;)Ljava/util/function/Function;
    1131: invokevirtual #176                // Method software/amazon/awssdk/core/SdkField$Builder.getter:(Ljava/util/function/Function;)Lsoftware/amazon/awssdk/core/SdkField$Builder;
    1134: invokedynamic #255,  0            // InvokeDynamic #35:accept:()Ljava/util/function/BiConsumer;
    1139: invokestatic  #178                // Method setter:(Ljava/util/function/BiConsumer;)Ljava/util/function/BiConsumer;
    1142: invokevirtual #179                // Method software/amazon/awssdk/core/SdkField$Builder.setter:(Ljava/util/function/BiConsumer;)Lsoftware/amazon/awssdk/core/SdkField$Builder;
    1145: invokedynamic #256,  0            // InvokeDynamic #36:get:()Ljava/util/function/Supplier;
    1150: invokevirtual #201                // Method software/amazon/awssdk/core/SdkField$Builder.constructor:(Ljava/util/function/Supplier;)Lsoftware/amazon/awssdk/core/SdkField$Builder;
    1153: iconst_1
    1154: anewarray     #180                // class software/amazon/awssdk/core/traits/Trait
    1157: dup
    1158: iconst_0
    1159: invokestatic  #181                // Method software/amazon/awssdk/core/traits/LocationTrait.builder:()Lsoftware/amazon/awssdk/core/traits/LocationTrait$Builder;
    1162: getstatic     #182                // Field software/amazon/awssdk/core/protocol/MarshallLocation.PAYLOAD:Lsoftware/amazon/awssdk/core/protocol/MarshallLocation;
    1165: invokevirtual #183                // Method software/amazon/awssdk/core/traits/LocationTrait$Builder.location:(Lsoftware/amazon/awssdk/core/protocol/MarshallLocation;)Lsoftware/amazon/awssdk/core/traits/LocationTrait$Builder;
    1168: ldc_w         #257                // String imageBasedTrickPlaySettings
    1171: invokevirtual #185                // Method software/amazon/awssdk/core/traits/LocationTrait$Builder.locationName:(Ljava/lang/String;)Lsoftware/amazon/awssdk/core/traits/LocationTrait$Builder;
    1174: invokevirtual #186                // Method software/amazon/awssdk/core/traits/LocationTrait$Builder.build:()Lsoftware/amazon/awssdk/core/traits/LocationTrait;
    1177: aastore
    1178: invokevirtual #191                // Method software/amazon/awssdk/core/SdkField$Builder.traits:([Lsoftware/amazon/awssdk/core/traits/Trait;)Lsoftware/amazon/awssdk/core/SdkField$Builder;
    1181: invokevirtual #192                // Method software/amazon/awssdk/core/SdkField$Builder.build:()Lsoftware/amazon/awssdk/core/SdkField;
    1184: putstatic     #258                // Field IMAGE_BASED_TRICK_PLAY_SETTINGS_FIELD:Lsoftware/amazon/awssdk/core/SdkField;
    1187: getstatic     #189                // Field software/amazon/awssdk/core/protocol/MarshallingType.STRING:Lsoftware/amazon/awssdk/core/protocol/MarshallingType;
    1190: invokestatic  #172                // Method software/amazon/awssdk/core/SdkField.builder:(Lsoftware/amazon/awssdk/core/protocol/MarshallingType;)Lsoftware/amazon/awssdk/core/SdkField$Builder;
    1193: ldc           #143                // String ManifestCompression
    1195: invokevirtual #173                // Method software/amazon/awssdk/core/SdkField$Builder.memberName:(Ljava/lang/String;)Lsoftware/amazon/awssdk/core/SdkField$Builder;
    1198: invokedynamic #259,  0            // InvokeDynamic #37:apply:()Ljava/util/function/Function;
    1203: invokestatic  #175                // Method getter:(Ljava/util/function/Function;)Ljava/util/function/Function;
    1206: invokevirtual #176                // Method software/amazon/awssdk/core/SdkField$Builder.getter:(Ljava/util/function/Function;)Lsoftware/amazon/awssdk/core/SdkField$Builder;
    1209: invokedynamic #260,  0            // InvokeDynamic #38:accept:()Ljava/util/function/BiConsumer;
    1214: invokestatic  #178                // Method setter:(Ljava/util/function/BiConsumer;)Ljava/util/function/BiConsumer;
    1217: invokevirtual #179                // Method software/amazon/awssdk/core/SdkField$Builder.setter:(Ljava/util/function/BiConsumer;)Lsoftware/amazon/awssdk/core/SdkField$Builder;
    1220: iconst_1
    1221: anewarray     #180                // class software/amazon/awssdk/core/traits/Trait
    1224: dup
    1225: iconst_0
    1226: invokestatic  #181                // Method software/amazon/awssdk/core/traits/LocationTrait.builder:()Lsoftware/amazon/awssdk/core/traits/LocationTrait$Builder;
    1229: getstatic     #182                // Field software/amazon/awssdk/core/protocol/MarshallLocation.PAYLOAD:Lsoftware/amazon/awssdk/core/protocol/MarshallLocation;
    1232: invokevirtual #183                // Method software/amazon/awssdk/core/traits/LocationTrait$Builder.location:(Lsoftware/amazon/awssdk/core/protocol/MarshallLocation;)Lsoftware/amazon/awssdk/core/traits/LocationTrait$Builder;
    1235: ldc_w         #261                // String manifestCompression
    1238: invokevirtual #185                // Method software/amazon/awssdk/core/traits/LocationTrait$Builder.locationName:(Ljava/lang/String;)Lsoftware/amazon/awssdk/core/traits/LocationTrait$Builder;
    1241: invokevirtual #186                // Method software/amazon/awssdk/core/traits/LocationTrait$Builder.build:()Lsoftware/amazon/awssdk/core/traits/LocationTrait;
    1244: aastore
    1245: invokevirtual #191                // Method software/amazon/awssdk/core/SdkField$Builder.traits:([Lsoftware/amazon/awssdk/core/traits/Trait;)Lsoftware/amazon/awssdk/core/SdkField$Builder;
    1248: invokevirtual #192                // Method software/amazon/awssdk/core/SdkField$Builder.build:()Lsoftware/amazon/awssdk/core/SdkField;
    1251: putstatic     #262                // Field MANIFEST_COMPRESSION_FIELD:Lsoftware/amazon/awssdk/core/SdkField;
    1254: getstatic     #189                // Field software/amazon/awssdk/core/protocol/MarshallingType.STRING:Lsoftware/amazon/awssdk/core/protocol/MarshallingType;
    1257: invokestatic  #172                // Method software/amazon/awssdk/core/SdkField.builder:(Lsoftware/amazon/awssdk/core/protocol/MarshallingType;)Lsoftware/amazon/awssdk/core/SdkField$Builder;
    1260: ldc           #144                // String ManifestDurationFormat
    1262: invokevirtual #173                // Method software/amazon/awssdk/core/SdkField$Builder.memberName:(Ljava/lang/String;)Lsoftware/amazon/awssdk/core/SdkField$Builder;
    1265: invokedynamic #263,  0            // InvokeDynamic #39:apply:()Ljava/util/function/Function;
    1270: invokestatic  #175                // Method getter:(Ljava/util/function/Function;)Ljava/util/function/Function;
    1273: invokevirtual #176                // Method software/amazon/awssdk/core/SdkField$Builder.getter:(Ljava/util/function/Function;)Lsoftware/amazon/awssdk/core/SdkField$Builder;
    1276: invokedynamic #264,  0            // InvokeDynamic #40:accept:()Ljava/util/function/BiConsumer;
    1281: invokestatic  #178                // Method setter:(Ljava/util/function/BiConsumer;)Ljava/util/function/BiConsumer;
    1284: invokevirtual #179                // Method software/amazon/awssdk/core/SdkField$Builder.setter:(Ljava/util/function/BiConsumer;)Lsoftware/amazon/awssdk/core/SdkField$Builder;
    1287: iconst_1
    1288: anewarray     #180                // class software/amazon/awssdk/core/traits/Trait
    1291: dup
    1292: iconst_0
    1293: invokestatic  #181                // Method software/amazon/awssdk/core/traits/LocationTrait.builder:()Lsoftware/amazon/awssdk/core/traits/LocationTrait$Builder;
    1296: getstatic     #182                // Field software/amazon/awssdk/core/protocol/MarshallLocation.PAYLOAD:Lsoftware/amazon/awssdk/core/protocol/MarshallLocation;
    1299: invokevirtual #183                // Method software/amazon/awssdk/core/traits/LocationTrait$Builder.location:(Lsoftware/amazon/awssdk/core/protocol/MarshallLocation;)Lsoftware/amazon/awssdk/core/traits/LocationTrait$Builder;
    1302: ldc_w         #265                // String manifestDurationFormat
    1305: invokevirtual #185                // Method software/amazon/awssdk/core/traits/LocationTrait$Builder.locationName:(Ljava/lang/String;)Lsoftware/amazon/awssdk/core/traits/LocationTrait$Builder;
    1308: invokevirtual #186                // Method software/amazon/awssdk/core/traits/LocationTrait$Builder.build:()Lsoftware/amazon/awssdk/core/traits/LocationTrait;
    1311: aastore
    1312: invokevirtual #191                // Method software/amazon/awssdk/core/SdkField$Builder.traits:([Lsoftware/amazon/awssdk/core/traits/Trait;)Lsoftware/amazon/awssdk/core/SdkField$Builder;
    1315: invokevirtual #192                // Method software/amazon/awssdk/core/SdkField$Builder.build:()Lsoftware/amazon/awssdk/core/SdkField;
    1318: putstatic     #266                // Field MANIFEST_DURATION_FORMAT_FIELD:Lsoftware/amazon/awssdk/core/SdkField;
    1321: getstatic     #267                // Field software/amazon/awssdk/core/protocol/MarshallingType.DOUBLE:Lsoftware/amazon/awssdk/core/protocol/MarshallingType;
    1324: invokestatic  #172                // Method software/amazon/awssdk/core/SdkField.builder:(Lsoftware/amazon/awssdk/core/protocol/MarshallingType;)Lsoftware/amazon/awssdk/core/SdkField$Builder;
    1327: ldc           #145                // String MinFinalSegmentLength
    1329: invokevirtual #173                // Method software/amazon/awssdk/core/SdkField$Builder.memberName:(Ljava/lang/String;)Lsoftware/amazon/awssdk/core/SdkField$Builder;
    1332: invokedynamic #268,  0            // InvokeDynamic #41:apply:()Ljava/util/function/Function;
    1337: invokestatic  #175                // Method getter:(Ljava/util/function/Function;)Ljava/util/function/Function;
    1340: invokevirtual #176                // Method software/amazon/awssdk/core/SdkField$Builder.getter:(Ljava/util/function/Function;)Lsoftware/amazon/awssdk/core/SdkField$Builder;
    1343: invokedynamic #269,  0            // InvokeDynamic #42:accept:()Ljava/util/function/BiConsumer;
    1348: invokestatic  #178                // Method setter:(Ljava/util/function/BiConsumer;)Ljava/util/function/BiConsumer;
    1351: invokevirtual #179                // Method software/amazon/awssdk/core/SdkField$Builder.setter:(Ljava/util/function/BiConsumer;)Lsoftware/amazon/awssdk/core/SdkField$Builder;
    1354: iconst_1
    1355: anewarray     #180                // class software/amazon/awssdk/core/traits/Trait
    1358: dup
    1359: iconst_0
    1360: invokestatic  #181                // Method software/amazon/awssdk/core/traits/LocationTrait.builder:()Lsoftware/amazon/awssdk/core/traits/LocationTrait$Builder;
    1363: getstatic     #182                // Field software/amazon/awssdk/core/protocol/MarshallLocation.PAYLOAD:Lsoftware/amazon/awssdk/core/protocol/MarshallLocation;
    1366: invokevirtual #183                // Method software/amazon/awssdk/core/traits/LocationTrait$Builder.location:(Lsoftware/amazon/awssdk/core/protocol/MarshallLocation;)Lsoftware/amazon/awssdk/core/traits/LocationTrait$Builder;
    1369: ldc_w         #270                // String minFinalSegmentLength
    1372: invokevirtual #185                // Method software/amazon/awssdk/core/traits/LocationTrait$Builder.locationName:(Ljava/lang/String;)Lsoftware/amazon/awssdk/core/traits/LocationTrait$Builder;
    1375: invokevirtual #186                // Method software/amazon/awssdk/core/traits/LocationTrait$Builder.build:()Lsoftware/amazon/awssdk/core/traits/LocationTrait;
    1378: aastore
    1379: invokevirtual #191                // Method software/amazon/awssdk/core/SdkField$Builder.traits:([Lsoftware/amazon/awssdk/core/traits/Trait;)Lsoftware/amazon/awssdk/core/SdkField$Builder;
    1382: invokevirtual #192                // Method software/amazon/awssdk/core/SdkField$Builder.build:()Lsoftware/amazon/awssdk/core/SdkField;
    1385: putstatic     #271                // Field MIN_FINAL_SEGMENT_LENGTH_FIELD:Lsoftware/amazon/awssdk/core/SdkField;
    1388: getstatic     #272                // Field software/amazon/awssdk/core/protocol/MarshallingType.INTEGER:Lsoftware/amazon/awssdk/core/protocol/MarshallingType;
    1391: invokestatic  #172                // Method software/amazon/awssdk/core/SdkField.builder:(Lsoftware/amazon/awssdk/core/protocol/MarshallingType;)Lsoftware/amazon/awssdk/core/SdkField$Builder;
    1394: ldc           #146                // String MinSegmentLength
    1396: invokevirtual #173                // Method software/amazon/awssdk/core/SdkField$Builder.memberName:(Ljava/lang/String;)Lsoftware/amazon/awssdk/core/SdkField$Builder;
    1399: invokedynamic #273,  0            // InvokeDynamic #43:apply:()Ljava/util/function/Function;
    1404: invokestatic  #175                // Method getter:(Ljava/util/function/Function;)Ljava/util/function/Function;
    1407: invokevirtual #176                // Method software/amazon/awssdk/core/SdkField$Builder.getter:(Ljava/util/function/Function;)Lsoftware/amazon/awssdk/core/SdkField$Builder;
    1410: invokedynamic #274,  0            // InvokeDynamic #44:accept:()Ljava/util/function/BiConsumer;
    1415: invokestatic  #178                // Method setter:(Ljava/util/function/BiConsumer;)Ljava/util/function/BiConsumer;
    1418: invokevirtual #179                // Method software/amazon/awssdk/core/SdkField$Builder.setter:(Ljava/util/function/BiConsumer;)Lsoftware/amazon/awssdk/core/SdkField$Builder;
    1421: iconst_1
    1422: anewarray     #180                // class software/amazon/awssdk/core/traits/Trait
    1425: dup
    1426: iconst_0
    1427: invokestatic  #181                // Method software/amazon/awssdk/core/traits/LocationTrait.builder:()Lsoftware/amazon/awssdk/core/traits/LocationTrait$Builder;
    1430: getstatic     #182                // Field software/amazon/awssdk/core/protocol/MarshallLocation.PAYLOAD:Lsoftware/amazon/awssdk/core/protocol/MarshallLocation;
    1433: invokevirtual #183                // Method software/amazon/awssdk/core/traits/LocationTrait$Builder.location:(Lsoftware/amazon/awssdk/core/protocol/MarshallLocation;)Lsoftware/amazon/awssdk/core/traits/LocationTrait$Builder;
    1436: ldc_w         #275                // String minSegmentLength
    1439: invokevirtual #185                // Method software/amazon/awssdk/core/traits/LocationTrait$Builder.locationName:(Ljava/lang/String;)Lsoftware/amazon/awssdk/core/traits/LocationTrait$Builder;
    1442: invokevirtual #186                // Method software/amazon/awssdk/core/traits/LocationTrait$Builder.build:()Lsoftware/amazon/awssdk/core/traits/LocationTrait;
    1445: aastore
    1446: invokevirtual #191                // Method software/amazon/awssdk/core/SdkField$Builder.traits:([Lsoftware/amazon/awssdk/core/traits/Trait;)Lsoftware/amazon/awssdk/core/SdkField$Builder;
    1449: invokevirtual #192                // Method software/amazon/awssdk/core/SdkField$Builder.build:()Lsoftware/amazon/awssdk/core/SdkField;
    1452: putstatic     #276                // Field MIN_SEGMENT_LENGTH_FIELD:Lsoftware/amazon/awssdk/core/SdkField;
    1455: getstatic     #189                // Field software/amazon/awssdk/core/protocol/MarshallingType.STRING:Lsoftware/amazon/awssdk/core/protocol/MarshallingType;
    1458: invokestatic  #172                // Method software/amazon/awssdk/core/SdkField.builder:(Lsoftware/amazon/awssdk/core/protocol/MarshallingType;)Lsoftware/amazon/awssdk/core/SdkField$Builder;
    1461: ldc           #147                // String OutputSelection
    1463: invokevirtual #173                // Method software/amazon/awssdk/core/SdkField$Builder.memberName:(Ljava/lang/String;)Lsoftware/amazon/awssdk/core/SdkField$Builder;
    1466: invokedynamic #277,  0            // InvokeDynamic #45:apply:()Ljava/util/function/Function;
    1471: invokestatic  #175                // Method getter:(Ljava/util/function/Function;)Ljava/util/function/Function;
    1474: invokevirtual #176                // Method software/amazon/awssdk/core/SdkField$Builder.getter:(Ljava/util/function/Function;)Lsoftware/amazon/awssdk/core/SdkField$Builder;
    1477: invokedynamic #278,  0            // InvokeDynamic #46:accept:()Ljava/util/function/BiConsumer;
    1482: invokestatic  #178                // Method setter:(Ljava/util/function/BiConsumer;)Ljava/util/function/BiConsumer;
    1485: invokevirtual #179                // Method software/amazon/awssdk/core/SdkField$Builder.setter:(Ljava/util/function/BiConsumer;)Lsoftware/amazon/awssdk/core/SdkField$Builder;
    1488: iconst_1
    1489: anewarray     #180                // class software/amazon/awssdk/core/traits/Trait
    1492: dup
    1493: iconst_0
    1494: invokestatic  #181                // Method software/amazon/awssdk/core/traits/LocationTrait.builder:()Lsoftware/amazon/awssdk/core/traits/LocationTrait$Builder;
    1497: getstatic     #182                // Field software/amazon/awssdk/core/protocol/MarshallLocation.PAYLOAD:Lsoftware/amazon/awssdk/core/protocol/MarshallLocation;
    1500: invokevirtual #183                // Method software/amazon/awssdk/core/traits/LocationTrait$Builder.location:(Lsoftware/amazon/awssdk/core/protocol/MarshallLocation;)Lsoftware/amazon/awssdk/core/traits/LocationTrait$Builder;
    1503: ldc_w         #279                // String outputSelection
    1506: invokevirtual #185                // Method software/amazon/awssdk/core/traits/LocationTrait$Builder.locationName:(Ljava/lang/String;)Lsoftware/amazon/awssdk/core/traits/LocationTrait$Builder;
    1509: invokevirtual #186                // Method software/amazon/awssdk/core/traits/LocationTrait$Builder.build:()Lsoftware/amazon/awssdk/core/traits/LocationTrait;
    1512: aastore
    1513: invokevirtual #191                // Method software/amazon/awssdk/core/SdkField$Builder.traits:([Lsoftware/amazon/awssdk/core/traits/Trait;)Lsoftware/amazon/awssdk/core/SdkField$Builder;
    1516: invokevirtual #192                // Method software/amazon/awssdk/core/SdkField$Builder.build:()Lsoftware/amazon/awssdk/core/SdkField;
    1519: putstatic     #280                // Field OUTPUT_SELECTION_FIELD:Lsoftware/amazon/awssdk/core/SdkField;
    1522: getstatic     #189                // Field software/amazon/awssdk/core/protocol/MarshallingType.STRING:Lsoftware/amazon/awssdk/core/protocol/MarshallingType;
    1525: invokestatic  #172                // Method software/amazon/awssdk/core/SdkField.builder:(Lsoftware/amazon/awssdk/core/protocol/MarshallingType;)Lsoftware/amazon/awssdk/core/SdkField$Builder;
    1528: ldc           #148                // String ProgramDateTime
    1530: invokevirtual #173                // Method software/amazon/awssdk/core/SdkField$Builder.memberName:(Ljava/lang/String;)Lsoftware/amazon/awssdk/core/SdkField$Builder;
    1533: invokedynamic #281,  0            // InvokeDynamic #47:apply:()Ljava/util/function/Function;
    1538: invokestatic  #175                // Method getter:(Ljava/util/function/Function;)Ljava/util/function/Function;
    1541: invokevirtual #176                // Method software/amazon/awssdk/core/SdkField$Builder.getter:(Ljava/util/function/Function;)Lsoftware/amazon/awssdk/core/SdkField$Builder;
    1544: invokedynamic #282,  0            // InvokeDynamic #48:accept:()Ljava/util/function/BiConsumer;
    1549: invokestatic  #178                // Method setter:(Ljava/util/function/BiConsumer;)Ljava/util/function/BiConsumer;
    1552: invokevirtual #179                // Method software/amazon/awssdk/core/SdkField$Builder.setter:(Ljava/util/function/BiConsumer;)Lsoftware/amazon/awssdk/core/SdkField$Builder;
    1555: iconst_1
    1556: anewarray     #180                // class software/amazon/awssdk/core/traits/Trait
    1559: dup
    1560: iconst_0
    1561: invokestatic  #181                // Method software/amazon/awssdk/core/traits/LocationTrait.builder:()Lsoftware/amazon/awssdk/core/traits/LocationTrait$Builder;
    1564: getstatic     #182                // Field software/amazon/awssdk/core/protocol/MarshallLocation.PAYLOAD:Lsoftware/amazon/awssdk/core/protocol/MarshallLocation;
    1567: invokevirtual #183                // Method software/amazon/awssdk/core/traits/LocationTrait$Builder.location:(Lsoftware/amazon/awssdk/core/protocol/MarshallLocation;)Lsoftware/amazon/awssdk/core/traits/LocationTrait$Builder;
    1570: ldc_w         #283                // String programDateTime
    1573: invokevirtual #185                // Method software/amazon/awssdk/core/traits/LocationTrait$Builder.locationName:(Ljava/lang/String;)Lsoftware/amazon/awssdk/core/traits/LocationTrait$Builder;
    1576: invokevirtual #186                // Method software/amazon/awssdk/core/traits/LocationTrait$Builder.build:()Lsoftware/amazon/awssdk/core/traits/LocationTrait;
    1579: aastore
    1580: invokevirtual #191                // Method software/amazon/awssdk/core/SdkField$Builder.traits:([Lsoftware/amazon/awssdk/core/traits/Trait;)Lsoftware/amazon/awssdk/core/SdkField$Builder;
    1583: invokevirtual #192                // Method software/amazon/awssdk/core/SdkField$Builder.build:()Lsoftware/amazon/awssdk/core/SdkField;
    1586: putstatic     #284                // Field PROGRAM_DATE_TIME_FIELD:Lsoftware/amazon/awssdk/core/SdkField;
    1589: getstatic     #272                // Field software/amazon/awssdk/core/protocol/MarshallingType.INTEGER:Lsoftware/amazon/awssdk/core/protocol/MarshallingType;
    1592: invokestatic  #172                // Method software/amazon/awssdk/core/SdkField.builder:(Lsoftware/amazon/awssdk/core/protocol/MarshallingType;)Lsoftware/amazon/awssdk/core/SdkField$Builder;
    1595: ldc           #149                // String ProgramDateTimePeriod
    1597: invokevirtual #173                // Method software/amazon/awssdk/core/SdkField$Builder.memberName:(Ljava/lang/String;)Lsoftware/amazon/awssdk/core/SdkField$Builder;
    1600: invokedynamic #285,  0            // InvokeDynamic #49:apply:()Ljava/util/function/Function;
    1605: invokestatic  #175                // Method getter:(Ljava/util/function/Function;)Ljava/util/function/Function;
    1608: invokevirtual #176                // Method software/amazon/awssdk/core/SdkField$Builder.getter:(Ljava/util/function/Function;)Lsoftware/amazon/awssdk/core/SdkField$Builder;
    1611: invokedynamic #286,  0            // InvokeDynamic #50:accept:()Ljava/util/function/BiConsumer;
    1616: invokestatic  #178                // Method setter:(Ljava/util/function/BiConsumer;)Ljava/util/function/BiConsumer;
    1619: invokevirtual #179                // Method software/amazon/awssdk/core/SdkField$Builder.setter:(Ljava/util/function/BiConsumer;)Lsoftware/amazon/awssdk/core/SdkField$Builder;
    1622: iconst_1
    1623: anewarray     #180                // class software/amazon/awssdk/core/traits/Trait
    1626: dup
    1627: iconst_0
    1628: invokestatic  #181                // Method software/amazon/awssdk/core/traits/LocationTrait.builder:()Lsoftware/amazon/awssdk/core/traits/LocationTrait$Builder;
    1631: getstatic     #182                // Field software/amazon/awssdk/core/protocol/MarshallLocation.PAYLOAD:Lsoftware/amazon/awssdk/core/protocol/MarshallLocation;
    1634: invokevirtual #183                // Method software/amazon/awssdk/core/traits/LocationTrait$Builder.location:(Lsoftware/amazon/awssdk/core/protocol/MarshallLocation;)Lsoftware/amazon/awssdk/core/traits/LocationTrait$Builder;
    1637: ldc_w         #287                // String programDateTimePeriod
    1640: invokevirtual #185                // Method software/amazon/awssdk/core/traits/LocationTrait$Builder.locationName:(Ljava/lang/String;)Lsoftware/amazon/awssdk/core/traits/LocationTrait$Builder;
    1643: invokevirtual #186                // Method software/amazon/awssdk/core/traits/LocationTrait$Builder.build:()Lsoftware/amazon/awssdk/core/traits/LocationTrait;
    1646: aastore
    1647: invokevirtual #191                // Method software/amazon/awssdk/core/SdkField$Builder.traits:([Lsoftware/amazon/awssdk/core/traits/Trait;)Lsoftware/amazon/awssdk/core/SdkField$Builder;
    1650: invokevirtual #192                // Method software/amazon/awssdk/core/SdkField$Builder.build:()Lsoftware/amazon/awssdk/core/SdkField;
    1653: putstatic     #288                // Field PROGRAM_DATE_TIME_PERIOD_FIELD:Lsoftware/amazon/awssdk/core/SdkField;
    1656: getstatic     #189                // Field software/amazon/awssdk/core/protocol/MarshallingType.STRING:Lsoftware/amazon/awssdk/core/protocol/MarshallingType;
    1659: invokestatic  #172                // Method software/amazon/awssdk/core/SdkField.builder:(Lsoftware/amazon/awssdk/core/protocol/MarshallingType;)Lsoftware/amazon/awssdk/core/SdkField$Builder;
    1662: ldc           #150                // String SegmentControl
    1664: invokevirtual #173                // Method software/amazon/awssdk/core/SdkField$Builder.memberName:(Ljava/lang/String;)Lsoftware/amazon/awssdk/core/SdkField$Builder;
    1667: invokedynamic #289,  0            // InvokeDynamic #51:apply:()Ljava/util/function/Function;
    1672: invokestatic  #175                // Method getter:(Ljava/util/function/Function;)Ljava/util/function/Function;
    1675: invokevirtual #176                // Method software/amazon/awssdk/core/SdkField$Builder.getter:(Ljava/util/function/Function;)Lsoftware/amazon/awssdk/core/SdkField$Builder;
    1678: invokedynamic #290,  0            // InvokeDynamic #52:accept:()Ljava/util/function/BiConsumer;
    1683: invokestatic  #178                // Method setter:(Ljava/util/function/BiConsumer;)Ljava/util/function/BiConsumer;
    1686: invokevirtual #179                // Method software/amazon/awssdk/core/SdkField$Builder.setter:(Ljava/util/function/BiConsumer;)Lsoftware/amazon/awssdk/core/SdkField$Builder;
    1689: iconst_1
    1690: anewarray     #180                // class software/amazon/awssdk/core/traits/Trait
    1693: dup
    1694: iconst_0
    1695: invokestatic  #181                // Method software/amazon/awssdk/core/traits/LocationTrait.builder:()Lsoftware/amazon/awssdk/core/traits/LocationTrait$Builder;
    1698: getstatic     #182                // Field software/amazon/awssdk/core/protocol/MarshallLocation.PAYLOAD:Lsoftware/amazon/awssdk/core/protocol/MarshallLocation;
    1701: invokevirtual #183                // Method software/amazon/awssdk/core/traits/LocationTrait$Builder.location:(Lsoftware/amazon/awssdk/core/protocol/MarshallLocation;)Lsoftware/amazon/awssdk/core/traits/LocationTrait$Builder;
    1704: ldc_w         #291                // String segmentControl
    1707: invokevirtual #185                // Method software/amazon/awssdk/core/traits/LocationTrait$Builder.locationName:(Ljava/lang/String;)Lsoftware/amazon/awssdk/core/traits/LocationTrait$Builder;
    1710: invokevirtual #186                // Method software/amazon/awssdk/core/traits/LocationTrait$Builder.build:()Lsoftware/amazon/awssdk/core/traits/LocationTrait;
    1713: aastore
    1714: invokevirtual #191                // Method software/amazon/awssdk/core/SdkField$Builder.traits:([Lsoftware/amazon/awssdk/core/traits/Trait;)Lsoftware/amazon/awssdk/core/SdkField$Builder;
    1717: invokevirtual #192                // Method software/amazon/awssdk/core/SdkField$Builder.build:()Lsoftware/amazon/awssdk/core/SdkField;
    1720: putstatic     #292                // Field SEGMENT_CONTROL_FIELD:Lsoftware/amazon/awssdk/core/SdkField;
    1723: getstatic     #272                // Field software/amazon/awssdk/core/protocol/MarshallingType.INTEGER:Lsoftware/amazon/awssdk/core/protocol/MarshallingType;
    1726: invokestatic  #172                // Method software/amazon/awssdk/core/SdkField.builder:(Lsoftware/amazon/awssdk/core/protocol/MarshallingType;)Lsoftware/amazon/awssdk/core/SdkField$Builder;
    1729: ldc           #151                // String SegmentLength
    1731: invokevirtual #173                // Method software/amazon/awssdk/core/SdkField$Builder.memberName:(Ljava/lang/String;)Lsoftware/amazon/awssdk/core/SdkField$Builder;
    1734: invokedynamic #293,  0            // InvokeDynamic #53:apply:()Ljava/util/function/Function;
    1739: invokestatic  #175                // Method getter:(Ljava/util/function/Function;)Ljava/util/function/Function;
    1742: invokevirtual #176                // Method software/amazon/awssdk/core/SdkField$Builder.getter:(Ljava/util/function/Function;)Lsoftware/amazon/awssdk/core/SdkField$Builder;
    1745: invokedynamic #294,  0            // InvokeDynamic #54:accept:()Ljava/util/function/BiConsumer;
    1750: invokestatic  #178                // Method setter:(Ljava/util/function/BiConsumer;)Ljava/util/function/BiConsumer;
    1753: invokevirtual #179                // Method software/amazon/awssdk/core/SdkField$Builder.setter:(Ljava/util/function/BiConsumer;)Lsoftware/amazon/awssdk/core/SdkField$Builder;
    1756: iconst_1
    1757: anewarray     #180                // class software/amazon/awssdk/core/traits/Trait
    1760: dup
    1761: iconst_0
    1762: invokestatic  #181                // Method software/amazon/awssdk/core/traits/LocationTrait.builder:()Lsoftware/amazon/awssdk/core/traits/LocationTrait$Builder;
    1765: getstatic     #182                // Field software/amazon/awssdk/core/protocol/MarshallLocation.PAYLOAD:Lsoftware/amazon/awssdk/core/protocol/MarshallLocation;
    1768: invokevirtual #183                // Method software/amazon/awssdk/core/traits/LocationTrait$Builder.location:(Lsoftware/amazon/awssdk/core/protocol/MarshallLocation;)Lsoftware/amazon/awssdk/core/traits/LocationTrait$Builder;
    1771: ldc_w         #295                // String segmentLength
    1774: invokevirtual #185                // Method software/amazon/awssdk/core/traits/LocationTrait$Builder.locationName:(Ljava/lang/String;)Lsoftware/amazon/awssdk/core/traits/LocationTrait$Builder;
    1777: invokevirtual #186                // Method software/amazon/awssdk/core/traits/LocationTrait$Builder.build:()Lsoftware/amazon/awssdk/core/traits/LocationTrait;
    1780: aastore
    1781: invokevirtual #191                // Method software/amazon/awssdk/core/SdkField$Builder.traits:([Lsoftware/amazon/awssdk/core/traits/Trait;)Lsoftware/amazon/awssdk/core/SdkField$Builder;
    1784: invokevirtual #192                // Method software/amazon/awssdk/core/SdkField$Builder.build:()Lsoftware/amazon/awssdk/core/SdkField;
    1787: putstatic     #296                // Field SEGMENT_LENGTH_FIELD:Lsoftware/amazon/awssdk/core/SdkField;
    1790: getstatic     #189                // Field software/amazon/awssdk/core/protocol/MarshallingType.STRING:Lsoftware/amazon/awssdk/core/protocol/MarshallingType;
    1793: invokestatic  #172                // Method software/amazon/awssdk/core/SdkField.builder:(Lsoftware/amazon/awssdk/core/protocol/MarshallingType;)Lsoftware/amazon/awssdk/core/SdkField$Builder;
    1796: ldc           #152                // String SegmentLengthControl
    1798: invokevirtual #173                // Method software/amazon/awssdk/core/SdkField$Builder.memberName:(Ljava/lang/String;)Lsoftware/amazon/awssdk/core/SdkField$Builder;
    1801: invokedynamic #297,  0            // InvokeDynamic #55:apply:()Ljava/util/function/Function;
    1806: invokestatic  #175                // Method getter:(Ljava/util/function/Function;)Ljava/util/function/Function;
    1809: invokevirtual #176                // Method software/amazon/awssdk/core/SdkField$Builder.getter:(Ljava/util/function/Function;)Lsoftware/amazon/awssdk/core/SdkField$Builder;
    1812: invokedynamic #298,  0            // InvokeDynamic #56:accept:()Ljava/util/function/BiConsumer;
    1817: invokestatic  #178                // Method setter:(Ljava/util/function/BiConsumer;)Ljava/util/function/BiConsumer;
    1820: invokevirtual #179                // Method software/amazon/awssdk/core/SdkField$Builder.setter:(Ljava/util/function/BiConsumer;)Lsoftware/amazon/awssdk/core/SdkField$Builder;
    1823: iconst_1
    1824: anewarray     #180                // class software/amazon/awssdk/core/traits/Trait
    1827: dup
    1828: iconst_0
    1829: invokestatic  #181                // Method software/amazon/awssdk/core/traits/LocationTrait.builder:()Lsoftware/amazon/awssdk/core/traits/LocationTrait$Builder;
    1832: getstatic     #182                // Field software/amazon/awssdk/core/protocol/MarshallLocation.PAYLOAD:Lsoftware/amazon/awssdk/core/protocol/MarshallLocation;
    1835: invokevirtual #183                // Method software/amazon/awssdk/core/traits/LocationTrait$Builder.location:(Lsoftware/amazon/awssdk/core/protocol/MarshallLocation;)Lsoftware/amazon/awssdk/core/traits/LocationTrait$Builder;
    1838: ldc_w         #299                // String segmentLengthControl
    1841: invokevirtual #185                // Method software/amazon/awssdk/core/traits/LocationTrait$Builder.locationName:(Ljava/lang/String;)Lsoftware/amazon/awssdk/core/traits/LocationTrait$Builder;
    1844: invokevirtual #186                // Method software/amazon/awssdk/core/traits/LocationTrait$Builder.build:()Lsoftware/amazon/awssdk/core/traits/LocationTrait;
    1847: aastore
    1848: invokevirtual #191                // Method software/amazon/awssdk/core/SdkField$Builder.traits:([Lsoftware/amazon/awssdk/core/traits/Trait;)Lsoftware/amazon/awssdk/core/SdkField$Builder;
    1851: invokevirtual #192                // Method software/amazon/awssdk/core/SdkField$Builder.build:()Lsoftware/amazon/awssdk/core/SdkField;
    1854: putstatic     #300                // Field SEGMENT_LENGTH_CONTROL_FIELD:Lsoftware/amazon/awssdk/core/SdkField;
    1857: getstatic     #272                // Field software/amazon/awssdk/core/protocol/MarshallingType.INTEGER:Lsoftware/amazon/awssdk/core/protocol/MarshallingType;
    1860: invokestatic  #172                // Method software/amazon/awssdk/core/SdkField.builder:(Lsoftware/amazon/awssdk/core/protocol/MarshallingType;)Lsoftware/amazon/awssdk/core/SdkField$Builder;
    1863: ldc           #153                // String SegmentsPerSubdirectory
    1865: invokevirtual #173                // Method software/amazon/awssdk/core/SdkField$Builder.memberName:(Ljava/lang/String;)Lsoftware/amazon/awssdk/core/SdkField$Builder;
    1868: invokedynamic #301,  0            // InvokeDynamic #57:apply:()Ljava/util/function/Function;
    1873: invokestatic  #175                // Method getter:(Ljava/util/function/Function;)Ljava/util/function/Function;
    1876: invokevirtual #176                // Method software/amazon/awssdk/core/SdkField$Builder.getter:(Ljava/util/function/Function;)Lsoftware/amazon/awssdk/core/SdkField$Builder;
    1879: invokedynamic #302,  0            // InvokeDynamic #58:accept:()Ljava/util/function/BiConsumer;
    1884: invokestatic  #178                // Method setter:(Ljava/util/function/BiConsumer;)Ljava/util/function/BiConsumer;
    1887: invokevirtual #179                // Method software/amazon/awssdk/core/SdkField$Builder.setter:(Ljava/util/function/BiConsumer;)Lsoftware/amazon/awssdk/core/SdkField$Builder;
    1890: iconst_1
    1891: anewarray     #180                // class software/amazon/awssdk/core/traits/Trait
    1894: dup
    1895: iconst_0
    1896: invokestatic  #181                // Method software/amazon/awssdk/core/traits/LocationTrait.builder:()Lsoftware/amazon/awssdk/core/traits/LocationTrait$Builder;
    1899: getstatic     #182                // Field software/amazon/awssdk/core/protocol/MarshallLocation.PAYLOAD:Lsoftware/amazon/awssdk/core/protocol/MarshallLocation;
    1902: invokevirtual #183                // Method software/amazon/awssdk/core/traits/LocationTrait$Builder.location:(Lsoftware/amazon/awssdk/core/protocol/MarshallLocation;)Lsoftware/amazon/awssdk/core/traits/LocationTrait$Builder;
    1905: ldc_w         #303                // String segmentsPerSubdirectory
    1908: invokevirtual #185                // Method software/amazon/awssdk/core/traits/LocationTrait$Builder.locationName:(Ljava/lang/String;)Lsoftware/amazon/awssdk/core/traits/LocationTrait$Builder;
    1911: invokevirtual #186                // Method software/amazon/awssdk/core/traits/LocationTrait$Builder.build:()Lsoftware/amazon/awssdk/core/traits/LocationTrait;
    1914: aastore
    1915: invokevirtual #191                // Method software/amazon/awssdk/core/SdkField$Builder.traits:([Lsoftware/amazon/awssdk/core/traits/Trait;)Lsoftware/amazon/awssdk/core/SdkField$Builder;
    1918: invokevirtual #192                // Method software/amazon/awssdk/core/SdkField$Builder.build:()Lsoftware/amazon/awssdk/core/SdkField;
    1921: putstatic     #304                // Field SEGMENTS_PER_SUBDIRECTORY_FIELD:Lsoftware/amazon/awssdk/core/SdkField;
    1924: getstatic     #189                // Field software/amazon/awssdk/core/protocol/MarshallingType.STRING:Lsoftware/amazon/awssdk/core/protocol/MarshallingType;
    1927: invokestatic  #172                // Method software/amazon/awssdk/core/SdkField.builder:(Lsoftware/amazon/awssdk/core/protocol/MarshallingType;)Lsoftware/amazon/awssdk/core/SdkField$Builder;
    1930: ldc           #154                // String StreamInfResolution
    1932: invokevirtual #173                // Method software/amazon/awssdk/core/SdkField$Builder.memberName:(Ljava/lang/String;)Lsoftware/amazon/awssdk/core/SdkField$Builder;
    1935: invokedynamic #305,  0            // InvokeDynamic #59:apply:()Ljava/util/function/Function;
    1940: invokestatic  #175                // Method getter:(Ljava/util/function/Function;)Ljava/util/function/Function;
    1943: invokevirtual #176                // Method software/amazon/awssdk/core/SdkField$Builder.getter:(Ljava/util/function/Function;)Lsoftware/amazon/awssdk/core/SdkField$Builder;
    1946: invokedynamic #306,  0            // InvokeDynamic #60:accept:()Ljava/util/function/BiConsumer;
    1951: invokestatic  #178                // Method setter:(Ljava/util/function/BiConsumer;)Ljava/util/function/BiConsumer;
    1954: invokevirtual #179                // Method software/amazon/awssdk/core/SdkField$Builder.setter:(Ljava/util/function/BiConsumer;)Lsoftware/amazon/awssdk/core/SdkField$Builder;
    1957: iconst_1
    1958: anewarray     #180                // class software/amazon/awssdk/core/traits/Trait
    1961: dup
    1962: iconst_0
    1963: invokestatic  #181                // Method software/amazon/awssdk/core/traits/LocationTrait.builder:()Lsoftware/amazon/awssdk/core/traits/LocationTrait$Builder;
    1966: getstatic     #182                // Field software/amazon/awssdk/core/protocol/MarshallLocation.PAYLOAD:Lsoftware/amazon/awssdk/core/protocol/MarshallLocation;
    1969: invokevirtual #183                // Method software/amazon/awssdk/core/traits/LocationTrait$Builder.location:(Lsoftware/amazon/awssdk/core/protocol/MarshallLocation;)Lsoftware/amazon/awssdk/core/traits/LocationTrait$Builder;
    1972: ldc_w         #307                // String streamInfResolution
    1975: invokevirtual #185                // Method software/amazon/awssdk/core/traits/LocationTrait$Builder.locationName:(Ljava/lang/String;)Lsoftware/amazon/awssdk/core/traits/LocationTrait$Builder;
    1978: invokevirtual #186                // Method software/amazon/awssdk/core/traits/LocationTrait$Builder.build:()Lsoftware/amazon/awssdk/core/traits/LocationTrait;
    1981: aastore
    1982: invokevirtual #191                // Method software/amazon/awssdk/core/SdkField$Builder.traits:([Lsoftware/amazon/awssdk/core/traits/Trait;)Lsoftware/amazon/awssdk/core/SdkField$Builder;
    1985: invokevirtual #192                // Method software/amazon/awssdk/core/SdkField$Builder.build:()Lsoftware/amazon/awssdk/core/SdkField;
    1988: putstatic     #308                // Field STREAM_INF_RESOLUTION_FIELD:Lsoftware/amazon/awssdk/core/SdkField;
    1991: getstatic     #189                // Field software/amazon/awssdk/core/protocol/MarshallingType.STRING:Lsoftware/amazon/awssdk/core/protocol/MarshallingType;
    1994: invokestatic  #172                // Method software/amazon/awssdk/core/SdkField.builder:(Lsoftware/amazon/awssdk/core/protocol/MarshallingType;)Lsoftware/amazon/awssdk/core/SdkField$Builder;
    1997: ldc           #155                // String TargetDurationCompatibilityMode
    1999: invokevirtual #173                // Method software/amazon/awssdk/core/SdkField$Builder.memberName:(Ljava/lang/String;)Lsoftware/amazon/awssdk/core/SdkField$Builder;
    2002: invokedynamic #309,  0            // InvokeDynamic #61:apply:()Ljava/util/function/Function;
    2007: invokestatic  #175                // Method getter:(Ljava/util/function/Function;)Ljava/util/function/Function;
    2010: invokevirtual #176                // Method software/amazon/awssdk/core/SdkField$Builder.getter:(Ljava/util/function/Function;)Lsoftware/amazon/awssdk/core/SdkField$Builder;
    2013: invokedynamic #310,  0            // InvokeDynamic #62:accept:()Ljava/util/function/BiConsumer;
    2018: invokestatic  #178                // Method setter:(Ljava/util/function/BiConsumer;)Ljava/util/function/BiConsumer;
    2021: invokevirtual #179                // Method software/amazon/awssdk/core/SdkField$Builder.setter:(Ljava/util/function/BiConsumer;)Lsoftware/amazon/awssdk/core/SdkField$Builder;
    2024: iconst_1
    2025: anewarray     #180                // class software/amazon/awssdk/core/traits/Trait
    2028: dup
    2029: iconst_0
    2030: invokestatic  #181                // Method software/amazon/awssdk/core/traits/LocationTrait.builder:()Lsoftware/amazon/awssdk/core/traits/LocationTrait$Builder;
    2033: getstatic     #182                // Field software/amazon/awssdk/core/protocol/MarshallLocation.PAYLOAD:Lsoftware/amazon/awssdk/core/protocol/MarshallLocation;
    2036: invokevirtual #183                // Method software/amazon/awssdk/core/traits/LocationTrait$Builder.location:(Lsoftware/amazon/awssdk/core/protocol/MarshallLocation;)Lsoftware/amazon/awssdk/core/traits/LocationTrait$Builder;
    2039: ldc_w         #311                // String targetDurationCompatibilityMode
    2042: invokevirtual #185                // Method software/amazon/awssdk/core/traits/LocationTrait$Builder.locationName:(Ljava/lang/String;)Lsoftware/amazon/awssdk/core/traits/LocationTrait$Builder;
    2045: invokevirtual #186                // Method software/amazon/awssdk/core/traits/LocationTrait$Builder.build:()Lsoftware/amazon/awssdk/core/traits/LocationTrait;
    2048: aastore
    2049: invokevirtual #191                // Method software/amazon/awssdk/core/SdkField$Builder.traits:([Lsoftware/amazon/awssdk/core/traits/Trait;)Lsoftware/amazon/awssdk/core/SdkField$Builder;
    2052: invokevirtual #192                // Method software/amazon/awssdk/core/SdkField$Builder.build:()Lsoftware/amazon/awssdk/core/SdkField;
    2055: putstatic     #312                // Field TARGET_DURATION_COMPATIBILITY_MODE_FIELD:Lsoftware/amazon/awssdk/core/SdkField;
    2058: getstatic     #189                // Field software/amazon/awssdk/core/protocol/MarshallingType.STRING:Lsoftware/amazon/awssdk/core/protocol/MarshallingType;
    2061: invokestatic  #172                // Method software/amazon/awssdk/core/SdkField.builder:(Lsoftware/amazon/awssdk/core/protocol/MarshallingType;)Lsoftware/amazon/awssdk/core/SdkField$Builder;
    2064: ldc           #156                // String TimedMetadataId3Frame
    2066: invokevirtual #173                // Method software/amazon/awssdk/core/SdkField$Builder.memberName:(Ljava/lang/String;)Lsoftware/amazon/awssdk/core/SdkField$Builder;
    2069: invokedynamic #313,  0            // InvokeDynamic #63:apply:()Ljava/util/function/Function;
    2074: invokestatic  #175                // Method getter:(Ljava/util/function/Function;)Ljava/util/function/Function;
    2077: invokevirtual #176                // Method software/amazon/awssdk/core/SdkField$Builder.getter:(Ljava/util/function/Function;)Lsoftware/amazon/awssdk/core/SdkField$Builder;
    2080: invokedynamic #314,  0            // InvokeDynamic #64:accept:()Ljava/util/function/BiConsumer;
    2085: invokestatic  #178                // Method setter:(Ljava/util/function/BiConsumer;)Ljava/util/function/BiConsumer;
    2088: invokevirtual #179                // Method software/amazon/awssdk/core/SdkField$Builder.setter:(Ljava/util/function/BiConsumer;)Lsoftware/amazon/awssdk/core/SdkField$Builder;
    2091: iconst_1
    2092: anewarray     #180                // class software/amazon/awssdk/core/traits/Trait
    2095: dup
    2096: iconst_0
    2097: invokestatic  #181                // Method software/amazon/awssdk/core/traits/LocationTrait.builder:()Lsoftware/amazon/awssdk/core/traits/LocationTrait$Builder;
    2100: getstatic     #182                // Field software/amazon/awssdk/core/protocol/MarshallLocation.PAYLOAD:Lsoftware/amazon/awssdk/core/protocol/MarshallLocation;
    2103: invokevirtual #183                // Method software/amazon/awssdk/core/traits/LocationTrait$Builder.location:(Lsoftware/amazon/awssdk/core/protocol/MarshallLocation;)Lsoftware/amazon/awssdk/core/traits/LocationTrait$Builder;
    2106: ldc_w         #315                // String timedMetadataId3Frame
    2109: invokevirtual #185                // Method software/amazon/awssdk/core/traits/LocationTrait$Builder.locationName:(Ljava/lang/String;)Lsoftware/amazon/awssdk/core/traits/LocationTrait$Builder;
    2112: invokevirtual #186                // Method software/amazon/awssdk/core/traits/LocationTrait$Builder.build:()Lsoftware/amazon/awssdk/core/traits/LocationTrait;
    2115: aastore
    2116: invokevirtual #191                // Method software/amazon/awssdk/core/SdkField$Builder.traits:([Lsoftware/amazon/awssdk/core/traits/Trait;)Lsoftware/amazon/awssdk/core/SdkField$Builder;
    2119: invokevirtual #192                // Method software/amazon/awssdk/core/SdkField$Builder.build:()Lsoftware/amazon/awssdk/core/SdkField;
    2122: putstatic     #316                // Field TIMED_METADATA_ID3_FRAME_FIELD:Lsoftware/amazon/awssdk/core/SdkField;
    2125: getstatic     #272                // Field software/amazon/awssdk/core/protocol/MarshallingType.INTEGER:Lsoftware/amazon/awssdk/core/protocol/MarshallingType;
    2128: invokestatic  #172                // Method software/amazon/awssdk/core/SdkField.builder:(Lsoftware/amazon/awssdk/core/protocol/MarshallingType;)Lsoftware/amazon/awssdk/core/SdkField$Builder;
    2131: ldc           #157                // String TimedMetadataId3Period
    2133: invokevirtual #173                // Method software/amazon/awssdk/core/SdkField$Builder.memberName:(Ljava/lang/String;)Lsoftware/amazon/awssdk/core/SdkField$Builder;
    2136: invokedynamic #317,  0            // InvokeDynamic #65:apply:()Ljava/util/function/Function;
    2141: invokestatic  #175                // Method getter:(Ljava/util/function/Function;)Ljava/util/function/Function;
    2144: invokevirtual #176                // Method software/amazon/awssdk/core/SdkField$Builder.getter:(Ljava/util/function/Function;)Lsoftware/amazon/awssdk/core/SdkField$Builder;
    2147: invokedynamic #318,  0            // InvokeDynamic #66:accept:()Ljava/util/function/BiConsumer;
    2152: invokestatic  #178                // Method setter:(Ljava/util/function/BiConsumer;)Ljava/util/function/BiConsumer;
    2155: invokevirtual #179                // Method software/amazon/awssdk/core/SdkField$Builder.setter:(Ljava/util/function/BiConsumer;)Lsoftware/amazon/awssdk/core/SdkField$Builder;
    2158: iconst_1
    2159: anewarray     #180                // class software/amazon/awssdk/core/traits/Trait
    2162: dup
    2163: iconst_0
    2164: invokestatic  #181                // Method software/amazon/awssdk/core/traits/LocationTrait.builder:()Lsoftware/amazon/awssdk/core/traits/LocationTrait$Builder;
    2167: getstatic     #182                // Field software/amazon/awssdk/core/protocol/MarshallLocation.PAYLOAD:Lsoftware/amazon/awssdk/core/protocol/MarshallLocation;
    2170: invokevirtual #183                // Method software/amazon/awssdk/core/traits/LocationTrait$Builder.location:(Lsoftware/amazon/awssdk/core/protocol/MarshallLocation;)Lsoftware/amazon/awssdk/core/traits/LocationTrait$Builder;
    2173: ldc_w         #319                // String timedMetadataId3Period
    2176: invokevirtual #185                // Method software/amazon/awssdk/core/traits/LocationTrait$Builder.locationName:(Ljava/lang/String;)Lsoftware/amazon/awssdk/core/traits/LocationTrait$Builder;
    2179: invokevirtual #186                // Method software/amazon/awssdk/core/traits/LocationTrait$Builder.build:()Lsoftware/amazon/awssdk/core/traits/LocationTrait;
    2182: aastore
    2183: invokevirtual #191                // Method software/amazon/awssdk/core/SdkField$Builder.traits:([Lsoftware/amazon/awssdk/core/traits/Trait;)Lsoftware/amazon/awssdk/core/SdkField$Builder;
    2186: invokevirtual #192                // Method software/amazon/awssdk/core/SdkField$Builder.build:()Lsoftware/amazon/awssdk/core/SdkField;
    2189: putstatic     #320                // Field TIMED_METADATA_ID3_PERIOD_FIELD:Lsoftware/amazon/awssdk/core/SdkField;
    2192: getstatic     #272                // Field software/amazon/awssdk/core/protocol/MarshallingType.INTEGER:Lsoftware/amazon/awssdk/core/protocol/MarshallingType;
    2195: invokestatic  #172                // Method software/amazon/awssdk/core/SdkField.builder:(Lsoftware/amazon/awssdk/core/protocol/MarshallingType;)Lsoftware/amazon/awssdk/core/SdkField$Builder;
    2198: ldc           #158                // String TimestampDeltaMilliseconds
    2200: invokevirtual #173                // Method software/amazon/awssdk/core/SdkField$Builder.memberName:(Ljava/lang/String;)Lsoftware/amazon/awssdk/core/SdkField$Builder;
    2203: invokedynamic #321,  0            // InvokeDynamic #67:apply:()Ljava/util/function/Function;
    2208: invokestatic  #175                // Method getter:(Ljava/util/function/Function;)Ljava/util/function/Function;
    2211: invokevirtual #176                // Method software/amazon/awssdk/core/SdkField$Builder.getter:(Ljava/util/function/Function;)Lsoftware/amazon/awssdk/core/SdkField$Builder;
    2214: invokedynamic #322,  0            // InvokeDynamic #68:accept:()Ljava/util/function/BiConsumer;
    2219: invokestatic  #178                // Method setter:(Ljava/util/function/BiConsumer;)Ljava/util/function/BiConsumer;
    2222: invokevirtual #179                // Method software/amazon/awssdk/core/SdkField$Builder.setter:(Ljava/util/function/BiConsumer;)Lsoftware/amazon/awssdk/core/SdkField$Builder;
    2225: iconst_1
    2226: anewarray     #180                // class software/amazon/awssdk/core/traits/Trait
    2229: dup
    2230: iconst_0
    2231: invokestatic  #181                // Method software/amazon/awssdk/core/traits/LocationTrait.builder:()Lsoftware/amazon/awssdk/core/traits/LocationTrait$Builder;
    2234: getstatic     #182                // Field software/amazon/awssdk/core/protocol/MarshallLocation.PAYLOAD:Lsoftware/amazon/awssdk/core/protocol/MarshallLocation;
    2237: invokevirtual #183                // Method software/amazon/awssdk/core/traits/LocationTrait$Builder.location:(Lsoftware/amazon/awssdk/core/protocol/MarshallLocation;)Lsoftware/amazon/awssdk/core/traits/LocationTrait$Builder;
    2240: ldc_w         #323                // String timestampDeltaMilliseconds
    2243: invokevirtual #185                // Method software/amazon/awssdk/core/traits/LocationTrait$Builder.locationName:(Ljava/lang/String;)Lsoftware/amazon/awssdk/core/traits/LocationTrait$Builder;
    2246: invokevirtual #186                // Method software/amazon/awssdk/core/traits/LocationTrait$Builder.build:()Lsoftware/amazon/awssdk/core/traits/LocationTrait;
    2249: aastore
    2250: invokevirtual #191                // Method software/amazon/awssdk/core/SdkField$Builder.traits:([Lsoftware/amazon/awssdk/core/traits/Trait;)Lsoftware/amazon/awssdk/core/SdkField$Builder;
    2253: invokevirtual #192                // Method software/amazon/awssdk/core/SdkField$Builder.build:()Lsoftware/amazon/awssdk/core/SdkField;
    2256: putstatic     #324                // Field TIMESTAMP_DELTA_MILLISECONDS_FIELD:Lsoftware/amazon/awssdk/core/SdkField;
    2259: bipush        31
    2261: anewarray     #325                // class software/amazon/awssdk/core/SdkField
    2264: dup
    2265: iconst_0
    2266: getstatic     #195                // Field AD_MARKERS_FIELD:Lsoftware/amazon/awssdk/core/SdkField;
    2269: aastore
    2270: dup
    2271: iconst_1
    2272: getstatic     #202                // Field ADDITIONAL_MANIFESTS_FIELD:Lsoftware/amazon/awssdk/core/SdkField;
    2275: aastore
    2276: dup
    2277: iconst_2
    2278: getstatic     #206                // Field AUDIO_ONLY_HEADER_FIELD:Lsoftware/amazon/awssdk/core/SdkField;
    2281: aastore
    2282: dup
    2283: iconst_3
    2284: getstatic     #210                // Field BASE_URL_FIELD:Lsoftware/amazon/awssdk/core/SdkField;
    2287: aastore
    2288: dup
    2289: iconst_4
    2290: getstatic     #215                // Field CAPTION_LANGUAGE_MAPPINGS_FIELD:Lsoftware/amazon/awssdk/core/SdkField;
    2293: aastore
    2294: dup
    2295: iconst_5
    2296: getstatic     #219                // Field CAPTION_LANGUAGE_SETTING_FIELD:Lsoftware/amazon/awssdk/core/SdkField;
    2299: aastore
    2300: dup
    2301: bipush        6
    2303: getstatic     #223                // Field CAPTION_SEGMENT_LENGTH_CONTROL_FIELD:Lsoftware/amazon/awssdk/core/SdkField;
    2306: aastore
    2307: dup
    2308: bipush        7
    2310: getstatic     #227                // Field CLIENT_CACHE_FIELD:Lsoftware/amazon/awssdk/core/SdkField;
    2313: aastore
    2314: dup
    2315: bipush        8
    2317: getstatic     #231                // Field CODEC_SPECIFICATION_FIELD:Lsoftware/amazon/awssdk/core/SdkField;
    2320: aastore
    2321: dup
    2322: bipush        9
    2324: getstatic     #235                // Field DESTINATION_FIELD:Lsoftware/amazon/awssdk/core/SdkField;
    2327: aastore
    2328: dup
    2329: bipush        10
    2331: getstatic     #240                // Field DESTINATION_SETTINGS_FIELD:Lsoftware/amazon/awssdk/core/SdkField;
    2334: aastore
    2335: dup
    2336: bipush        11
    2338: getstatic     #244                // Field DIRECTORY_STRUCTURE_FIELD:Lsoftware/amazon/awssdk/core/SdkField;
    2341: aastore
    2342: dup
    2343: bipush        12
    2345: getstatic     #249                // Field ENCRYPTION_FIELD:Lsoftware/amazon/awssdk/core/SdkField;
    2348: aastore
    2349: dup
    2350: bipush        13
    2352: getstatic     #253                // Field IMAGE_BASED_TRICK_PLAY_FIELD:Lsoftware/amazon/awssdk/core/SdkField;
    2355: aastore
    2356: dup
    2357: bipush        14
    2359: getstatic     #258                // Field IMAGE_BASED_TRICK_PLAY_SETTINGS_FIELD:Lsoftware/amazon/awssdk/core/SdkField;
    2362: aastore
    2363: dup
    2364: bipush        15
    2366: getstatic     #262                // Field MANIFEST_COMPRESSION_FIELD:Lsoftware/amazon/awssdk/core/SdkField;
    2369: aastore
    2370: dup
    2371: bipush        16
    2373: getstatic     #266                // Field MANIFEST_DURATION_FORMAT_FIELD:Lsoftware/amazon/awssdk/core/SdkField;
    2376: aastore
    2377: dup
    2378: bipush        17
    2380: getstatic     #271                // Field MIN_FINAL_SEGMENT_LENGTH_FIELD:Lsoftware/amazon/awssdk/core/SdkField;
    2383: aastore
    2384: dup
    2385: bipush        18
    2387: getstatic     #276                // Field MIN_SEGMENT_LENGTH_FIELD:Lsoftware/amazon/awssdk/core/SdkField;
    2390: aastore
    2391: dup
    2392: bipush        19
    2394: getstatic     #280                // Field OUTPUT_SELECTION_FIELD:Lsoftware/amazon/awssdk/core/SdkField;
    2397: aastore
    2398: dup
    2399: bipush        20
    2401: getstatic     #284                // Field PROGRAM_DATE_TIME_FIELD:Lsoftware/amazon/awssdk/core/SdkField;
    2404: aastore
    2405: dup
    2406: bipush        21
    2408: getstatic     #288                // Field PROGRAM_DATE_TIME_PERIOD_FIELD:Lsoftware/amazon/awssdk/core/SdkField;
    2411: aastore
    2412: dup
    2413: bipush        22
    2415: getstatic     #292                // Field SEGMENT_CONTROL_FIELD:Lsoftware/amazon/awssdk/core/SdkField;
    2418: aastore
    2419: dup
    2420: bipush        23
    2422: getstatic     #296                // Field SEGMENT_LENGTH_FIELD:Lsoftware/amazon/awssdk/core/SdkField;
    2425: aastore
    2426: dup
    2427: bipush        24
    2429: getstatic     #300                // Field SEGMENT_LENGTH_CONTROL_FIELD:Lsoftware/amazon/awssdk/core/SdkField;
    2432: aastore
    2433: dup
    2434: bipush        25
    2436: getstatic     #304                // Field SEGMENTS_PER_SUBDIRECTORY_FIELD:Lsoftware/amazon/awssdk/core/SdkField;
    2439: aastore
    2440: dup
    2441: bipush        26
    2443: getstatic     #308                // Field STREAM_INF_RESOLUTION_FIELD:Lsoftware/amazon/awssdk/core/SdkField;
    2446: aastore
    2447: dup
    2448: bipush        27
    2450: getstatic     #312                // Field TARGET_DURATION_COMPATIBILITY_MODE_FIELD:Lsoftware/amazon/awssdk/core/SdkField;
    2453: aastore
    2454: dup
    2455: bipush        28
    2457: getstatic     #316                // Field TIMED_METADATA_ID3_FRAME_FIELD:Lsoftware/amazon/awssdk/core/SdkField;
    2460: aastore
    2461: dup
    2462: bipush        29
    2464: getstatic     #320                // Field TIMED_METADATA_ID3_PERIOD_FIELD:Lsoftware/amazon/awssdk/core/SdkField;
    2467: aastore
    2468: dup
    2469: bipush        30
    2471: getstatic     #324                // Field TIMESTAMP_DELTA_MILLISECONDS_FIELD:Lsoftware/amazon/awssdk/core/SdkField;
    2474: aastore
    2475: invokestatic  #326                // Method java/util/Arrays.asList:([Ljava/lang/Object;)Ljava/util/List;
    2478: invokestatic  #327                // Method java/util/Collections.unmodifiableList:(Ljava/util/List;)Ljava/util/List;
    2481: putstatic     #1                  // Field SDK_FIELDS:Ljava/util/List;
    2484: return
}
