Compiled from "InputVideoGenerator.java"
final class software.amazon.awssdk.services.mediaconvert.model.InputVideoGenerator$BuilderImpl implements software.amazon.awssdk.services.mediaconvert.model.InputVideoGenerator$Builder {
  private java.lang.Integer duration;

  private software.amazon.awssdk.services.mediaconvert.model.InputVideoGenerator$BuilderImpl();
    Code:
       0: aload_0
       1: invokespecial #4                  // Method java/lang/Object."<init>":()V
       4: return

  private software.amazon.awssdk.services.mediaconvert.model.InputVideoGenerator$BuilderImpl(software.amazon.awssdk.services.mediaconvert.model.InputVideoGenerator);
    Code:
       0: aload_0
       1: invokespecial #4                  // Method java/lang/Object."<init>":()V
       4: aload_0
       5: aload_1
       6: invokestatic  #5                  // Method software/amazon/awssdk/services/mediaconvert/model/InputVideoGenerator.access$300:(Lsoftware/amazon/awssdk/services/mediaconvert/model/InputVideoGenerator;)Ljava/lang/Integer;
       9: invokevirtual #6                  // Method duration:(Ljava/lang/Integer;)Lsoftware/amazon/awssdk/services/mediaconvert/model/InputVideoGenerator$Builder;
      12: pop
      13: return

  public final java.lang.Integer getDuration();
    Code:
       0: aload_0
       1: getfield      #3                  // Field duration:Ljava/lang/Integer;
       4: areturn

  public final void setDuration(java.lang.Integer);
    Code:
       0: aload_0
       1: aload_1
       2: putfield      #3                  // Field duration:Ljava/lang/Integer;
       5: return

  public final software.amazon.awssdk.services.mediaconvert.model.InputVideoGenerator$Builder duration(java.lang.Integer);
    Code:
       0: aload_0
       1: aload_1
       2: putfield      #3                  // Field duration:Ljava/lang/Integer;
       5: aload_0
       6: areturn

  public software.amazon.awssdk.services.mediaconvert.model.InputVideoGenerator build();
    Code:
       0: new           #7                  // class software/amazon/awssdk/services/mediaconvert/model/InputVideoGenerator
       3: dup
       4: aload_0
       5: aconst_null
       6: invokespecial #8                  // Method software/amazon/awssdk/services/mediaconvert/model/InputVideoGenerator."<init>":(Lsoftware/amazon/awssdk/services/mediaconvert/model/InputVideoGenerator$BuilderImpl;Lsoftware/amazon/awssdk/services/mediaconvert/model/InputVideoGenerator$1;)V
       9: areturn

  public java.util.List<software.amazon.awssdk.core.SdkField<?>> sdkFields();
    Code:
       0: invokestatic  #9                  // Method software/amazon/awssdk/services/mediaconvert/model/InputVideoGenerator.access$500:()Ljava/util/List;
       3: areturn

  public java.lang.Object build();
    Code:
       0: aload_0
       1: invokevirtual #10                 // Method build:()Lsoftware/amazon/awssdk/services/mediaconvert/model/InputVideoGenerator;
       4: areturn

  static java.lang.Integer access$000(software.amazon.awssdk.services.mediaconvert.model.InputVideoGenerator$BuilderImpl);
    Code:
       0: aload_0
       1: getfield      #3                  // Field duration:Ljava/lang/Integer;
       4: areturn

  software.amazon.awssdk.services.mediaconvert.model.InputVideoGenerator$BuilderImpl(software.amazon.awssdk.services.mediaconvert.model.InputVideoGenerator, software.amazon.awssdk.services.mediaconvert.model.InputVideoGenerator$1);
    Code:
       0: aload_0
       1: aload_1
       2: invokespecial #2                  // Method "<init>":(Lsoftware/amazon/awssdk/services/mediaconvert/model/InputVideoGenerator;)V
       5: return

  software.amazon.awssdk.services.mediaconvert.model.InputVideoGenerator$BuilderImpl(software.amazon.awssdk.services.mediaconvert.model.InputVideoGenerator$1);
    Code:
       0: aload_0
       1: invokespecial #1                  // Method "<init>":()V
       4: return
}
