Compiled from "Xavc4kProfileSettings.java"
final class software.amazon.awssdk.services.mediaconvert.model.Xavc4kProfileSettings$BuilderImpl implements software.amazon.awssdk.services.mediaconvert.model.Xavc4kProfileSettings$Builder {
  private java.lang.String bitrateClass;

  private java.lang.String codecProfile;

  private java.lang.String flickerAdaptiveQuantization;

  private java.lang.String gopBReference;

  private java.lang.Integer gopClosedCadence;

  private java.lang.Integer hrdBufferSize;

  private java.lang.String qualityTuningLevel;

  private java.lang.Integer slices;

  private software.amazon.awssdk.services.mediaconvert.model.Xavc4kProfileSettings$BuilderImpl();
    Code:
       0: aload_0
       1: invokespecial #11                 // Method java/lang/Object."<init>":()V
       4: return

  private software.amazon.awssdk.services.mediaconvert.model.Xavc4kProfileSettings$BuilderImpl(software.amazon.awssdk.services.mediaconvert.model.Xavc4kProfileSettings);
    Code:
       0: aload_0
       1: invokespecial #11                 // Method java/lang/Object."<init>":()V
       4: aload_0
       5: aload_1
       6: invokestatic  #12                 // Method software/amazon/awssdk/services/mediaconvert/model/Xavc4kProfileSettings.access$1000:(Lsoftware/amazon/awssdk/services/mediaconvert/model/Xavc4kProfileSettings;)Ljava/lang/String;
       9: invokevirtual #13                 // Method bitrateClass:(Ljava/lang/String;)Lsoftware/amazon/awssdk/services/mediaconvert/model/Xavc4kProfileSettings$Builder;
      12: pop
      13: aload_0
      14: aload_1
      15: invokestatic  #14                 // Method software/amazon/awssdk/services/mediaconvert/model/Xavc4kProfileSettings.access$1100:(Lsoftware/amazon/awssdk/services/mediaconvert/model/Xavc4kProfileSettings;)Ljava/lang/String;
      18: invokevirtual #15                 // Method codecProfile:(Ljava/lang/String;)Lsoftware/amazon/awssdk/services/mediaconvert/model/Xavc4kProfileSettings$Builder;
      21: pop
      22: aload_0
      23: aload_1
      24: invokestatic  #16                 // Method software/amazon/awssdk/services/mediaconvert/model/Xavc4kProfileSettings.access$1200:(Lsoftware/amazon/awssdk/services/mediaconvert/model/Xavc4kProfileSettings;)Ljava/lang/String;
      27: invokevirtual #17                 // Method flickerAdaptiveQuantization:(Ljava/lang/String;)Lsoftware/amazon/awssdk/services/mediaconvert/model/Xavc4kProfileSettings$Builder;
      30: pop
      31: aload_0
      32: aload_1
      33: invokestatic  #18                 // Method software/amazon/awssdk/services/mediaconvert/model/Xavc4kProfileSettings.access$1300:(Lsoftware/amazon/awssdk/services/mediaconvert/model/Xavc4kProfileSettings;)Ljava/lang/String;
      36: invokevirtual #19                 // Method gopBReference:(Ljava/lang/String;)Lsoftware/amazon/awssdk/services/mediaconvert/model/Xavc4kProfileSettings$Builder;
      39: pop
      40: aload_0
      41: aload_1
      42: invokestatic  #20                 // Method software/amazon/awssdk/services/mediaconvert/model/Xavc4kProfileSettings.access$1400:(Lsoftware/amazon/awssdk/services/mediaconvert/model/Xavc4kProfileSettings;)Ljava/lang/Integer;
      45: invokevirtual #21                 // Method gopClosedCadence:(Ljava/lang/Integer;)Lsoftware/amazon/awssdk/services/mediaconvert/model/Xavc4kProfileSettings$Builder;
      48: pop
      49: aload_0
      50: aload_1
      51: invokestatic  #22                 // Method software/amazon/awssdk/services/mediaconvert/model/Xavc4kProfileSettings.access$1500:(Lsoftware/amazon/awssdk/services/mediaconvert/model/Xavc4kProfileSettings;)Ljava/lang/Integer;
      54: invokevirtual #23                 // Method hrdBufferSize:(Ljava/lang/Integer;)Lsoftware/amazon/awssdk/services/mediaconvert/model/Xavc4kProfileSettings$Builder;
      57: pop
      58: aload_0
      59: aload_1
      60: invokestatic  #24                 // Method software/amazon/awssdk/services/mediaconvert/model/Xavc4kProfileSettings.access$1600:(Lsoftware/amazon/awssdk/services/mediaconvert/model/Xavc4kProfileSettings;)Ljava/lang/String;
      63: invokevirtual #25                 // Method qualityTuningLevel:(Ljava/lang/String;)Lsoftware/amazon/awssdk/services/mediaconvert/model/Xavc4kProfileSettings$Builder;
      66: pop
      67: aload_0
      68: aload_1
      69: invokestatic  #26                 // Method software/amazon/awssdk/services/mediaconvert/model/Xavc4kProfileSettings.access$1700:(Lsoftware/amazon/awssdk/services/mediaconvert/model/Xavc4kProfileSettings;)Ljava/lang/Integer;
      72: invokevirtual #27                 // Method slices:(Ljava/lang/Integer;)Lsoftware/amazon/awssdk/services/mediaconvert/model/Xavc4kProfileSettings$Builder;
      75: pop
      76: return

  public final java.lang.String getBitrateClass();
    Code:
       0: aload_0
       1: getfield      #10                 // Field bitrateClass:Ljava/lang/String;
       4: areturn

  public final void setBitrateClass(java.lang.String);
    Code:
       0: aload_0
       1: aload_1
       2: putfield      #10                 // Field bitrateClass:Ljava/lang/String;
       5: return

  public final software.amazon.awssdk.services.mediaconvert.model.Xavc4kProfileSettings$Builder bitrateClass(java.lang.String);
    Code:
       0: aload_0
       1: aload_1
       2: putfield      #10                 // Field bitrateClass:Ljava/lang/String;
       5: aload_0
       6: areturn

  public final software.amazon.awssdk.services.mediaconvert.model.Xavc4kProfileSettings$Builder bitrateClass(software.amazon.awssdk.services.mediaconvert.model.Xavc4kProfileBitrateClass);
    Code:
       0: aload_0
       1: aload_1
       2: ifnonnull     9
       5: aconst_null
       6: goto          13
       9: aload_1
      10: invokevirtual #28                 // Method software/amazon/awssdk/services/mediaconvert/model/Xavc4kProfileBitrateClass.toString:()Ljava/lang/String;
      13: invokevirtual #13                 // Method bitrateClass:(Ljava/lang/String;)Lsoftware/amazon/awssdk/services/mediaconvert/model/Xavc4kProfileSettings$Builder;
      16: pop
      17: aload_0
      18: areturn

  public final java.lang.String getCodecProfile();
    Code:
       0: aload_0
       1: getfield      #9                  // Field codecProfile:Ljava/lang/String;
       4: areturn

  public final void setCodecProfile(java.lang.String);
    Code:
       0: aload_0
       1: aload_1
       2: putfield      #9                  // Field codecProfile:Ljava/lang/String;
       5: return

  public final software.amazon.awssdk.services.mediaconvert.model.Xavc4kProfileSettings$Builder codecProfile(java.lang.String);
    Code:
       0: aload_0
       1: aload_1
       2: putfield      #9                  // Field codecProfile:Ljava/lang/String;
       5: aload_0
       6: areturn

  public final software.amazon.awssdk.services.mediaconvert.model.Xavc4kProfileSettings$Builder codecProfile(software.amazon.awssdk.services.mediaconvert.model.Xavc4kProfileCodecProfile);
    Code:
       0: aload_0
       1: aload_1
       2: ifnonnull     9
       5: aconst_null
       6: goto          13
       9: aload_1
      10: invokevirtual #29                 // Method software/amazon/awssdk/services/mediaconvert/model/Xavc4kProfileCodecProfile.toString:()Ljava/lang/String;
      13: invokevirtual #15                 // Method codecProfile:(Ljava/lang/String;)Lsoftware/amazon/awssdk/services/mediaconvert/model/Xavc4kProfileSettings$Builder;
      16: pop
      17: aload_0
      18: areturn

  public final java.lang.String getFlickerAdaptiveQuantization();
    Code:
       0: aload_0
       1: getfield      #8                  // Field flickerAdaptiveQuantization:Ljava/lang/String;
       4: areturn

  public final void setFlickerAdaptiveQuantization(java.lang.String);
    Code:
       0: aload_0
       1: aload_1
       2: putfield      #8                  // Field flickerAdaptiveQuantization:Ljava/lang/String;
       5: return

  public final software.amazon.awssdk.services.mediaconvert.model.Xavc4kProfileSettings$Builder flickerAdaptiveQuantization(java.lang.String);
    Code:
       0: aload_0
       1: aload_1
       2: putfield      #8                  // Field flickerAdaptiveQuantization:Ljava/lang/String;
       5: aload_0
       6: areturn

  public final software.amazon.awssdk.services.mediaconvert.model.Xavc4kProfileSettings$Builder flickerAdaptiveQuantization(software.amazon.awssdk.services.mediaconvert.model.XavcFlickerAdaptiveQuantization);
    Code:
       0: aload_0
       1: aload_1
       2: ifnonnull     9
       5: aconst_null
       6: goto          13
       9: aload_1
      10: invokevirtual #30                 // Method software/amazon/awssdk/services/mediaconvert/model/XavcFlickerAdaptiveQuantization.toString:()Ljava/lang/String;
      13: invokevirtual #17                 // Method flickerAdaptiveQuantization:(Ljava/lang/String;)Lsoftware/amazon/awssdk/services/mediaconvert/model/Xavc4kProfileSettings$Builder;
      16: pop
      17: aload_0
      18: areturn

  public final java.lang.String getGopBReference();
    Code:
       0: aload_0
       1: getfield      #7                  // Field gopBReference:Ljava/lang/String;
       4: areturn

  public final void setGopBReference(java.lang.String);
    Code:
       0: aload_0
       1: aload_1
       2: putfield      #7                  // Field gopBReference:Ljava/lang/String;
       5: return

  public final software.amazon.awssdk.services.mediaconvert.model.Xavc4kProfileSettings$Builder gopBReference(java.lang.String);
    Code:
       0: aload_0
       1: aload_1
       2: putfield      #7                  // Field gopBReference:Ljava/lang/String;
       5: aload_0
       6: areturn

  public final software.amazon.awssdk.services.mediaconvert.model.Xavc4kProfileSettings$Builder gopBReference(software.amazon.awssdk.services.mediaconvert.model.XavcGopBReference);
    Code:
       0: aload_0
       1: aload_1
       2: ifnonnull     9
       5: aconst_null
       6: goto          13
       9: aload_1
      10: invokevirtual #31                 // Method software/amazon/awssdk/services/mediaconvert/model/XavcGopBReference.toString:()Ljava/lang/String;
      13: invokevirtual #19                 // Method gopBReference:(Ljava/lang/String;)Lsoftware/amazon/awssdk/services/mediaconvert/model/Xavc4kProfileSettings$Builder;
      16: pop
      17: aload_0
      18: areturn

  public final java.lang.Integer getGopClosedCadence();
    Code:
       0: aload_0
       1: getfield      #6                  // Field gopClosedCadence:Ljava/lang/Integer;
       4: areturn

  public final void setGopClosedCadence(java.lang.Integer);
    Code:
       0: aload_0
       1: aload_1
       2: putfield      #6                  // Field gopClosedCadence:Ljava/lang/Integer;
       5: return

  public final software.amazon.awssdk.services.mediaconvert.model.Xavc4kProfileSettings$Builder gopClosedCadence(java.lang.Integer);
    Code:
       0: aload_0
       1: aload_1
       2: putfield      #6                  // Field gopClosedCadence:Ljava/lang/Integer;
       5: aload_0
       6: areturn

  public final java.lang.Integer getHrdBufferSize();
    Code:
       0: aload_0
       1: getfield      #5                  // Field hrdBufferSize:Ljava/lang/Integer;
       4: areturn

  public final void setHrdBufferSize(java.lang.Integer);
    Code:
       0: aload_0
       1: aload_1
       2: putfield      #5                  // Field hrdBufferSize:Ljava/lang/Integer;
       5: return

  public final software.amazon.awssdk.services.mediaconvert.model.Xavc4kProfileSettings$Builder hrdBufferSize(java.lang.Integer);
    Code:
       0: aload_0
       1: aload_1
       2: putfield      #5                  // Field hrdBufferSize:Ljava/lang/Integer;
       5: aload_0
       6: areturn

  public final java.lang.String getQualityTuningLevel();
    Code:
       0: aload_0
       1: getfield      #4                  // Field qualityTuningLevel:Ljava/lang/String;
       4: areturn

  public final void setQualityTuningLevel(java.lang.String);
    Code:
       0: aload_0
       1: aload_1
       2: putfield      #4                  // Field qualityTuningLevel:Ljava/lang/String;
       5: return

  public final software.amazon.awssdk.services.mediaconvert.model.Xavc4kProfileSettings$Builder qualityTuningLevel(java.lang.String);
    Code:
       0: aload_0
       1: aload_1
       2: putfield      #4                  // Field qualityTuningLevel:Ljava/lang/String;
       5: aload_0
       6: areturn

  public final software.amazon.awssdk.services.mediaconvert.model.Xavc4kProfileSettings$Builder qualityTuningLevel(software.amazon.awssdk.services.mediaconvert.model.Xavc4kProfileQualityTuningLevel);
    Code:
       0: aload_0
       1: aload_1
       2: ifnonnull     9
       5: aconst_null
       6: goto          13
       9: aload_1
      10: invokevirtual #32                 // Method software/amazon/awssdk/services/mediaconvert/model/Xavc4kProfileQualityTuningLevel.toString:()Ljava/lang/String;
      13: invokevirtual #25                 // Method qualityTuningLevel:(Ljava/lang/String;)Lsoftware/amazon/awssdk/services/mediaconvert/model/Xavc4kProfileSettings$Builder;
      16: pop
      17: aload_0
      18: areturn

  public final java.lang.Integer getSlices();
    Code:
       0: aload_0
       1: getfield      #3                  // Field slices:Ljava/lang/Integer;
       4: areturn

  public final void setSlices(java.lang.Integer);
    Code:
       0: aload_0
       1: aload_1
       2: putfield      #3                  // Field slices:Ljava/lang/Integer;
       5: return

  public final software.amazon.awssdk.services.mediaconvert.model.Xavc4kProfileSettings$Builder slices(java.lang.Integer);
    Code:
       0: aload_0
       1: aload_1
       2: putfield      #3                  // Field slices:Ljava/lang/Integer;
       5: aload_0
       6: areturn

  public software.amazon.awssdk.services.mediaconvert.model.Xavc4kProfileSettings build();
    Code:
       0: new           #33                 // class software/amazon/awssdk/services/mediaconvert/model/Xavc4kProfileSettings
       3: dup
       4: aload_0
       5: aconst_null
       6: invokespecial #34                 // Method software/amazon/awssdk/services/mediaconvert/model/Xavc4kProfileSettings."<init>":(Lsoftware/amazon/awssdk/services/mediaconvert/model/Xavc4kProfileSettings$BuilderImpl;Lsoftware/amazon/awssdk/services/mediaconvert/model/Xavc4kProfileSettings$1;)V
       9: areturn

  public java.util.List<software.amazon.awssdk.core.SdkField<?>> sdkFields();
    Code:
       0: invokestatic  #35                 // Method software/amazon/awssdk/services/mediaconvert/model/Xavc4kProfileSettings.access$1900:()Ljava/util/List;
       3: areturn

  public java.lang.Object build();
    Code:
       0: aload_0
       1: invokevirtual #36                 // Method build:()Lsoftware/amazon/awssdk/services/mediaconvert/model/Xavc4kProfileSettings;
       4: areturn

  static java.lang.String access$000(software.amazon.awssdk.services.mediaconvert.model.Xavc4kProfileSettings$BuilderImpl);
    Code:
       0: aload_0
       1: getfield      #10                 // Field bitrateClass:Ljava/lang/String;
       4: areturn

  static java.lang.String access$100(software.amazon.awssdk.services.mediaconvert.model.Xavc4kProfileSettings$BuilderImpl);
    Code:
       0: aload_0
       1: getfield      #9                  // Field codecProfile:Ljava/lang/String;
       4: areturn

  static java.lang.String access$200(software.amazon.awssdk.services.mediaconvert.model.Xavc4kProfileSettings$BuilderImpl);
    Code:
       0: aload_0
       1: getfield      #8                  // Field flickerAdaptiveQuantization:Ljava/lang/String;
       4: areturn

  static java.lang.String access$300(software.amazon.awssdk.services.mediaconvert.model.Xavc4kProfileSettings$BuilderImpl);
    Code:
       0: aload_0
       1: getfield      #7                  // Field gopBReference:Ljava/lang/String;
       4: areturn

  static java.lang.Integer access$400(software.amazon.awssdk.services.mediaconvert.model.Xavc4kProfileSettings$BuilderImpl);
    Code:
       0: aload_0
       1: getfield      #6                  // Field gopClosedCadence:Ljava/lang/Integer;
       4: areturn

  static java.lang.Integer access$500(software.amazon.awssdk.services.mediaconvert.model.Xavc4kProfileSettings$BuilderImpl);
    Code:
       0: aload_0
       1: getfield      #5                  // Field hrdBufferSize:Ljava/lang/Integer;
       4: areturn

  static java.lang.String access$600(software.amazon.awssdk.services.mediaconvert.model.Xavc4kProfileSettings$BuilderImpl);
    Code:
       0: aload_0
       1: getfield      #4                  // Field qualityTuningLevel:Ljava/lang/String;
       4: areturn

  static java.lang.Integer access$700(software.amazon.awssdk.services.mediaconvert.model.Xavc4kProfileSettings$BuilderImpl);
    Code:
       0: aload_0
       1: getfield      #3                  // Field slices:Ljava/lang/Integer;
       4: areturn

  software.amazon.awssdk.services.mediaconvert.model.Xavc4kProfileSettings$BuilderImpl(software.amazon.awssdk.services.mediaconvert.model.Xavc4kProfileSettings, software.amazon.awssdk.services.mediaconvert.model.Xavc4kProfileSettings$1);
    Code:
       0: aload_0
       1: aload_1
       2: invokespecial #2                  // Method "<init>":(Lsoftware/amazon/awssdk/services/mediaconvert/model/Xavc4kProfileSettings;)V
       5: return

  software.amazon.awssdk.services.mediaconvert.model.Xavc4kProfileSettings$BuilderImpl(software.amazon.awssdk.services.mediaconvert.model.Xavc4kProfileSettings$1);
    Code:
       0: aload_0
       1: invokespecial #1                  // Method "<init>":()V
       4: return
}
