Compiled from "DefaultPathExpr.java"
class org.jaxen.expr.DefaultPathExpr extends org.jaxen.expr.DefaultExpr implements org.jaxen.expr.PathExpr {
  private static final long serialVersionUID;

  private org.jaxen.expr.Expr filterExpr;

  private org.jaxen.expr.LocationPath locationPath;

  org.jaxen.expr.DefaultPathExpr(org.jaxen.expr.Expr, org.jaxen.expr.LocationPath);
    Code:
       0: aload_0
       1: invokespecial #1                  // Method org/jaxen/expr/DefaultExpr."<init>":()V
       4: aload_0
       5: aload_1
       6: putfield      #2                  // Field filterExpr:Lorg/jaxen/expr/Expr;
       9: aload_0
      10: aload_2
      11: putfield      #3                  // Field locationPath:Lorg/jaxen/expr/LocationPath;
      14: return

  public org.jaxen.expr.Expr getFilterExpr();
    Code:
       0: aload_0
       1: getfield      #2                  // Field filterExpr:Lorg/jaxen/expr/Expr;
       4: areturn

  public void setFilterExpr(org.jaxen.expr.Expr);
    Code:
       0: aload_0
       1: aload_1
       2: putfield      #2                  // Field filterExpr:Lorg/jaxen/expr/Expr;
       5: return

  public org.jaxen.expr.LocationPath getLocationPath();
    Code:
       0: aload_0
       1: getfield      #3                  // Field locationPath:Lorg/jaxen/expr/LocationPath;
       4: areturn

  public java.lang.String toString();
    Code:
       0: aload_0
       1: invokevirtual #4                  // Method getLocationPath:()Lorg/jaxen/expr/LocationPath;
       4: ifnull        47
       7: new           #5                  // class java/lang/StringBuffer
      10: dup
      11: invokespecial #6                  // Method java/lang/StringBuffer."<init>":()V
      14: ldc           #7                  // String [(DefaultPathExpr):
      16: invokevirtual #8                  // Method java/lang/StringBuffer.append:(Ljava/lang/String;)Ljava/lang/StringBuffer;
      19: aload_0
      20: invokevirtual #9                  // Method getFilterExpr:()Lorg/jaxen/expr/Expr;
      23: invokevirtual #10                 // Method java/lang/StringBuffer.append:(Ljava/lang/Object;)Ljava/lang/StringBuffer;
      26: ldc           #11                 // String ,
      28: invokevirtual #8                  // Method java/lang/StringBuffer.append:(Ljava/lang/String;)Ljava/lang/StringBuffer;
      31: aload_0
      32: invokevirtual #4                  // Method getLocationPath:()Lorg/jaxen/expr/LocationPath;
      35: invokevirtual #10                 // Method java/lang/StringBuffer.append:(Ljava/lang/Object;)Ljava/lang/StringBuffer;
      38: ldc           #12                 // String ]
      40: invokevirtual #8                  // Method java/lang/StringBuffer.append:(Ljava/lang/String;)Ljava/lang/StringBuffer;
      43: invokevirtual #13                 // Method java/lang/StringBuffer.toString:()Ljava/lang/String;
      46: areturn
      47: new           #5                  // class java/lang/StringBuffer
      50: dup
      51: invokespecial #6                  // Method java/lang/StringBuffer."<init>":()V
      54: ldc           #7                  // String [(DefaultPathExpr):
      56: invokevirtual #8                  // Method java/lang/StringBuffer.append:(Ljava/lang/String;)Ljava/lang/StringBuffer;
      59: aload_0
      60: invokevirtual #9                  // Method getFilterExpr:()Lorg/jaxen/expr/Expr;
      63: invokevirtual #10                 // Method java/lang/StringBuffer.append:(Ljava/lang/Object;)Ljava/lang/StringBuffer;
      66: ldc           #12                 // String ]
      68: invokevirtual #8                  // Method java/lang/StringBuffer.append:(Ljava/lang/String;)Ljava/lang/StringBuffer;
      71: invokevirtual #13                 // Method java/lang/StringBuffer.toString:()Ljava/lang/String;
      74: areturn

  public java.lang.String getText();
    Code:
       0: new           #5                  // class java/lang/StringBuffer
       3: dup
       4: invokespecial #6                  // Method java/lang/StringBuffer."<init>":()V
       7: astore_1
       8: aload_0
       9: invokevirtual #9                  // Method getFilterExpr:()Lorg/jaxen/expr/Expr;
      12: ifnull        29
      15: aload_1
      16: aload_0
      17: invokevirtual #9                  // Method getFilterExpr:()Lorg/jaxen/expr/Expr;
      20: invokeinterface #14,  1           // InterfaceMethod org/jaxen/expr/Expr.getText:()Ljava/lang/String;
      25: invokevirtual #8                  // Method java/lang/StringBuffer.append:(Ljava/lang/String;)Ljava/lang/StringBuffer;
      28: pop
      29: aload_0
      30: invokevirtual #4                  // Method getLocationPath:()Lorg/jaxen/expr/LocationPath;
      33: ifnull        74
      36: aload_0
      37: invokevirtual #4                  // Method getLocationPath:()Lorg/jaxen/expr/LocationPath;
      40: invokeinterface #15,  1           // InterfaceMethod org/jaxen/expr/LocationPath.getSteps:()Ljava/util/List;
      45: invokeinterface #16,  1           // InterfaceMethod java/util/List.isEmpty:()Z
      50: ifne          60
      53: aload_1
      54: ldc           #17                 // String /
      56: invokevirtual #8                  // Method java/lang/StringBuffer.append:(Ljava/lang/String;)Ljava/lang/StringBuffer;
      59: pop
      60: aload_1
      61: aload_0
      62: invokevirtual #4                  // Method getLocationPath:()Lorg/jaxen/expr/LocationPath;
      65: invokeinterface #18,  1           // InterfaceMethod org/jaxen/expr/LocationPath.getText:()Ljava/lang/String;
      70: invokevirtual #8                  // Method java/lang/StringBuffer.append:(Ljava/lang/String;)Ljava/lang/StringBuffer;
      73: pop
      74: aload_1
      75: invokevirtual #13                 // Method java/lang/StringBuffer.toString:()Ljava/lang/String;
      78: areturn

  public org.jaxen.expr.Expr simplify();
    Code:
       0: aload_0
       1: invokevirtual #9                  // Method getFilterExpr:()Lorg/jaxen/expr/Expr;
       4: ifnull        20
       7: aload_0
       8: aload_0
       9: invokevirtual #9                  // Method getFilterExpr:()Lorg/jaxen/expr/Expr;
      12: invokeinterface #19,  1           // InterfaceMethod org/jaxen/expr/Expr.simplify:()Lorg/jaxen/expr/Expr;
      17: invokevirtual #20                 // Method setFilterExpr:(Lorg/jaxen/expr/Expr;)V
      20: aload_0
      21: invokevirtual #4                  // Method getLocationPath:()Lorg/jaxen/expr/LocationPath;
      24: ifnull        37
      27: aload_0
      28: invokevirtual #4                  // Method getLocationPath:()Lorg/jaxen/expr/LocationPath;
      31: invokeinterface #21,  1           // InterfaceMethod org/jaxen/expr/LocationPath.simplify:()Lorg/jaxen/expr/Expr;
      36: pop
      37: aload_0
      38: invokevirtual #9                  // Method getFilterExpr:()Lorg/jaxen/expr/Expr;
      41: ifnonnull     53
      44: aload_0
      45: invokevirtual #4                  // Method getLocationPath:()Lorg/jaxen/expr/LocationPath;
      48: ifnonnull     53
      51: aconst_null
      52: areturn
      53: aload_0
      54: invokevirtual #4                  // Method getLocationPath:()Lorg/jaxen/expr/LocationPath;
      57: ifnonnull     65
      60: aload_0
      61: invokevirtual #9                  // Method getFilterExpr:()Lorg/jaxen/expr/Expr;
      64: areturn
      65: aload_0
      66: invokevirtual #9                  // Method getFilterExpr:()Lorg/jaxen/expr/Expr;
      69: ifnonnull     77
      72: aload_0
      73: invokevirtual #4                  // Method getLocationPath:()Lorg/jaxen/expr/LocationPath;
      76: areturn
      77: aload_0
      78: areturn

  public java.lang.Object evaluate(org.jaxen.Context) throws org.jaxen.JaxenException;
    Code:
       0: aconst_null
       1: astore_2
       2: aconst_null
       3: astore_3
       4: aload_0
       5: invokevirtual #9                  // Method getFilterExpr:()Lorg/jaxen/expr/Expr;
       8: ifnull        42
      11: aload_0
      12: invokevirtual #9                  // Method getFilterExpr:()Lorg/jaxen/expr/Expr;
      15: aload_1
      16: invokeinterface #22,  2           // InterfaceMethod org/jaxen/expr/Expr.evaluate:(Lorg/jaxen/Context;)Ljava/lang/Object;
      21: astore_2
      22: new           #23                 // class org/jaxen/Context
      25: dup
      26: aload_1
      27: invokevirtual #24                 // Method org/jaxen/Context.getContextSupport:()Lorg/jaxen/ContextSupport;
      30: invokespecial #25                 // Method org/jaxen/Context."<init>":(Lorg/jaxen/ContextSupport;)V
      33: astore_3
      34: aload_3
      35: aload_2
      36: invokestatic  #26                 // Method convertToList:(Ljava/lang/Object;)Ljava/util/List;
      39: invokevirtual #27                 // Method org/jaxen/Context.setNodeSet:(Ljava/util/List;)V
      42: aload_0
      43: invokevirtual #4                  // Method getLocationPath:()Lorg/jaxen/expr/LocationPath;
      46: ifnull        60
      49: aload_0
      50: invokevirtual #4                  // Method getLocationPath:()Lorg/jaxen/expr/LocationPath;
      53: aload_3
      54: invokeinterface #28,  2           // InterfaceMethod org/jaxen/expr/LocationPath.evaluate:(Lorg/jaxen/Context;)Ljava/lang/Object;
      59: areturn
      60: aload_2
      61: areturn
}
