Compiled from "DefaultAdditiveExpr.java"
abstract class org.jaxen.expr.DefaultAdditiveExpr extends org.jaxen.expr.DefaultArithExpr implements org.jaxen.expr.AdditiveExpr {
  org.jaxen.expr.DefaultAdditiveExpr(org.jaxen.expr.Expr, org.jaxen.expr.Expr);
    Code:
       0: aload_0
       1: aload_1
       2: aload_2
       3: invokespecial #1                  // Method org/jaxen/expr/DefaultArithExpr."<init>":(Lorg/jaxen/expr/Expr;Lorg/jaxen/expr/Expr;)V
       6: return

  public java.lang.String toString();
    Code:
       0: new           #2                  // class java/lang/StringBuffer
       3: dup
       4: invokespecial #3                  // Method java/lang/StringBuffer."<init>":()V
       7: ldc           #4                  // String [(
       9: invokevirtual #5                  // Method java/lang/StringBuffer.append:(Ljava/lang/String;)Ljava/lang/StringBuffer;
      12: aload_0
      13: invokevirtual #6                  // Method java/lang/Object.getClass:()Ljava/lang/Class;
      16: invokevirtual #7                  // Method java/lang/Class.getName:()Ljava/lang/String;
      19: invokevirtual #5                  // Method java/lang/StringBuffer.append:(Ljava/lang/String;)Ljava/lang/StringBuffer;
      22: ldc           #8                  // String ):
      24: invokevirtual #5                  // Method java/lang/StringBuffer.append:(Ljava/lang/String;)Ljava/lang/StringBuffer;
      27: aload_0
      28: invokevirtual #9                  // Method getLHS:()Lorg/jaxen/expr/Expr;
      31: invokevirtual #10                 // Method java/lang/StringBuffer.append:(Ljava/lang/Object;)Ljava/lang/StringBuffer;
      34: ldc           #11                 // String ,
      36: invokevirtual #5                  // Method java/lang/StringBuffer.append:(Ljava/lang/String;)Ljava/lang/StringBuffer;
      39: aload_0
      40: invokevirtual #12                 // Method getRHS:()Lorg/jaxen/expr/Expr;
      43: invokevirtual #10                 // Method java/lang/StringBuffer.append:(Ljava/lang/Object;)Ljava/lang/StringBuffer;
      46: ldc           #13                 // String ]
      48: invokevirtual #5                  // Method java/lang/StringBuffer.append:(Ljava/lang/String;)Ljava/lang/StringBuffer;
      51: invokevirtual #14                 // Method java/lang/StringBuffer.toString:()Ljava/lang/String;
      54: areturn
}
