Compiled from "MustacheNotFoundException.java"
public class com.github.mustachejava.MustacheNotFoundException extends com.github.mustachejava.MustacheException {
  private final java.lang.String name;

  public com.github.mustachejava.MustacheNotFoundException(java.lang.String);
    Code:
       0: aload_0
       1: new           #1                  // class java/lang/StringBuilder
       4: dup
       5: invokespecial #2                  // Method java/lang/StringBuilder."<init>":()V
       8: ldc           #3                  // String Template
      10: invokevirtual #4                  // Method java/lang/StringBuilder.append:(Ljava/lang/String;)Ljava/lang/StringBuilder;
      13: aload_1
      14: invokevirtual #4                  // Method java/lang/StringBuilder.append:(Ljava/lang/String;)Ljava/lang/StringBuilder;
      17: ldc           #5                  // String  not found
      19: invokevirtual #4                  // Method java/lang/StringBuilder.append:(Ljava/lang/String;)Ljava/lang/StringBuilder;
      22: invokevirtual #6                  // Method java/lang/StringBuilder.toString:()Ljava/lang/String;
      25: invokespecial #7                  // Method com/github/mustachejava/MustacheException."<init>":(Ljava/lang/String;)V
      28: aload_0
      29: aload_1
      30: putfield      #8                  // Field name:Ljava/lang/String;
      33: return

  public com.github.mustachejava.MustacheNotFoundException(java.lang.String, java.lang.Throwable);
    Code:
       0: aload_0
       1: new           #1                  // class java/lang/StringBuilder
       4: dup
       5: invokespecial #2                  // Method java/lang/StringBuilder."<init>":()V
       8: ldc           #3                  // String Template
      10: invokevirtual #4                  // Method java/lang/StringBuilder.append:(Ljava/lang/String;)Ljava/lang/StringBuilder;
      13: aload_1
      14: invokevirtual #4                  // Method java/lang/StringBuilder.append:(Ljava/lang/String;)Ljava/lang/StringBuilder;
      17: ldc           #5                  // String  not found
      19: invokevirtual #4                  // Method java/lang/StringBuilder.append:(Ljava/lang/String;)Ljava/lang/StringBuilder;
      22: invokevirtual #6                  // Method java/lang/StringBuilder.toString:()Ljava/lang/String;
      25: aload_2
      26: invokespecial #9                  // Method com/github/mustachejava/MustacheException."<init>":(Ljava/lang/String;Ljava/lang/Throwable;)V
      29: aload_0
      30: aload_1
      31: putfield      #8                  // Field name:Ljava/lang/String;
      34: return

  public java.lang.String getName();
    Code:
       0: aload_0
       1: getfield      #8                  // Field name:Ljava/lang/String;
       4: areturn
}
