Compiled from "QueueUnlockMain.java"
public class net.openhft.chronicle.queue.QueueUnlockMain {
  public net.openhft.chronicle.queue.QueueUnlockMain();
    Code:
       0: aload_0
       1: invokespecial #2                  // Method java/lang/Object."<init>":()V
       4: return

  public static void main(java.lang.String[]);
    Code:
       0: aload_0
       1: iconst_0
       2: aaload
       3: invokestatic  #3                  // Method unlock:(Ljava/lang/String;)V
       6: return

  private static void unlock(java.lang.String);
    Code:
       0: new           #4                  // class java/io/File
       3: dup
       4: aload_0
       5: invokespecial #5                  // Method java/io/File."<init>":(Ljava/lang/String;)V
       8: astore_1
       9: aload_1
      10: invokevirtual #6                  // Method java/io/File.isDirectory:()Z
      13: ifne          28
      16: getstatic     #7                  // Field java/lang/System.err:Ljava/io/PrintStream;
      19: ldc           #8                  // String Path argument must be a queue directory
      21: invokevirtual #9                  // Method java/io/PrintStream.println:(Ljava/lang/String;)V
      24: iconst_1
      25: invokestatic  #10                 // Method java/lang/System.exit:(I)V
      28: new           #4                  // class java/io/File
      31: dup
      32: aload_1
      33: ldc           #11                 // String metadata.cq4t
      35: invokespecial #12                 // Method java/io/File."<init>":(Ljava/io/File;Ljava/lang/String;)V
      38: astore_2
      39: aload_2
      40: invokevirtual #13                 // Method java/io/File.exists:()Z
      43: ifne          58
      46: getstatic     #7                  // Field java/lang/System.err:Ljava/io/PrintStream;
      49: ldc           #14                 // String Metadata file not found, nothing to unlock
      51: invokevirtual #9                  // Method java/io/PrintStream.println:(Ljava/lang/String;)V
      54: iconst_1
      55: invokestatic  #10                 // Method java/lang/System.exit:(I)V
      58: aload_2
      59: getstatic     #15                 // Field net/openhft/chronicle/queue/impl/table/Metadata$NoMeta.INSTANCE:Lnet/openhft/chronicle/queue/impl/table/Metadata$NoMeta;
      62: invokestatic  #16                 // Method net/openhft/chronicle/queue/impl/table/SingleTableBuilder.binary:(Ljava/io/File;Lnet/openhft/chronicle/queue/impl/table/Metadata;)Lnet/openhft/chronicle/queue/impl/table/SingleTableBuilder;
      65: iconst_0
      66: invokevirtual #17                 // Method net/openhft/chronicle/queue/impl/table/SingleTableBuilder.readOnly:(Z)Lnet/openhft/chronicle/queue/impl/table/SingleTableBuilder;
      69: invokevirtual #18                 // Method net/openhft/chronicle/queue/impl/table/SingleTableBuilder.build:()Lnet/openhft/chronicle/queue/impl/TableStore;
      72: astore_3
      73: new           #19                 // class net/openhft/chronicle/queue/impl/single/TableStoreWriteLock
      76: dup
      77: aload_3
      78: invokedynamic #20,  0             // InvokeDynamic #0:get:()Ljava/util/function/Supplier;
      83: lconst_0
      84: invokestatic  #21                 // Method java/lang/Long.valueOf:(J)Ljava/lang/Long;
      87: ldc           #22                 // String chronicle.append.lock
      89: invokespecial #23                 // Method net/openhft/chronicle/queue/impl/single/TableStoreWriteLock."<init>":(Lnet/openhft/chronicle/queue/impl/TableStore;Ljava/util/function/Supplier;Ljava/lang/Long;Ljava/lang/String;)V
      92: invokevirtual #24                 // Method net/openhft/chronicle/queue/impl/single/TableStoreWriteLock.forceUnlock:()V
      95: new           #19                 // class net/openhft/chronicle/queue/impl/single/TableStoreWriteLock
      98: dup
      99: aload_3
     100: invokedynamic #20,  0             // InvokeDynamic #0:get:()Ljava/util/function/Supplier;
     105: lconst_0
     106: invokestatic  #21                 // Method java/lang/Long.valueOf:(J)Ljava/lang/Long;
     109: invokespecial #25                 // Method net/openhft/chronicle/queue/impl/single/TableStoreWriteLock."<init>":(Lnet/openhft/chronicle/queue/impl/TableStore;Ljava/util/function/Supplier;Ljava/lang/Long;)V
     112: invokevirtual #24                 // Method net/openhft/chronicle/queue/impl/single/TableStoreWriteLock.forceUnlock:()V
     115: getstatic     #26                 // Field java/lang/System.out:Ljava/io/PrintStream;
     118: ldc           #27                 // String Done
     120: invokevirtual #9                  // Method java/io/PrintStream.println:(Ljava/lang/String;)V
     123: return

  static {};
    Code:
       0: invokestatic  #28                 // Method net/openhft/chronicle/queue/impl/single/SingleChronicleQueueBuilder.addAliases:()V
       3: return
}
