Compiled from "RollCycles.java"
public final class net.openhft.chronicle.queue.RollCycles extends java.lang.Enum<net.openhft.chronicle.queue.RollCycles> implements net.openhft.chronicle.queue.RollCycle {
  public static final net.openhft.chronicle.queue.RollCycles FIVE_MINUTELY;

  public static final net.openhft.chronicle.queue.RollCycles TEN_MINUTELY;

  public static final net.openhft.chronicle.queue.RollCycles TWENTY_MINUTELY;

  public static final net.openhft.chronicle.queue.RollCycles HALF_HOURLY;

  public static final net.openhft.chronicle.queue.RollCycles FAST_HOURLY;

  public static final net.openhft.chronicle.queue.RollCycles TWO_HOURLY;

  public static final net.openhft.chronicle.queue.RollCycles FOUR_HOURLY;

  public static final net.openhft.chronicle.queue.RollCycles SIX_HOURLY;

  public static final net.openhft.chronicle.queue.RollCycles FAST_DAILY;

  public static final net.openhft.chronicle.queue.RollCycles MINUTELY;

  public static final net.openhft.chronicle.queue.RollCycles HOURLY;

  public static final net.openhft.chronicle.queue.RollCycles DAILY;

  public static final net.openhft.chronicle.queue.RollCycles LARGE_HOURLY;

  public static final net.openhft.chronicle.queue.RollCycles LARGE_DAILY;

  public static final net.openhft.chronicle.queue.RollCycles XLARGE_DAILY;

  public static final net.openhft.chronicle.queue.RollCycles HUGE_DAILY;

  public static final net.openhft.chronicle.queue.RollCycles SMALL_DAILY;

  public static final net.openhft.chronicle.queue.RollCycles LARGE_HOURLY_SPARSE;

  public static final net.openhft.chronicle.queue.RollCycles LARGE_HOURLY_XSPARSE;

  public static final net.openhft.chronicle.queue.RollCycles HUGE_DAILY_XSPARSE;

  public static final net.openhft.chronicle.queue.RollCycles TEST_SECONDLY;

  public static final net.openhft.chronicle.queue.RollCycles TEST4_SECONDLY;

  public static final net.openhft.chronicle.queue.RollCycles TEST_HOURLY;

  public static final net.openhft.chronicle.queue.RollCycles TEST_DAILY;

  public static final net.openhft.chronicle.queue.RollCycles TEST2_DAILY;

  public static final net.openhft.chronicle.queue.RollCycles TEST4_DAILY;

  public static final net.openhft.chronicle.queue.RollCycles TEST8_DAILY;

  public static final net.openhft.chronicle.queue.RollCycles DEFAULT;

  private static final java.lang.Iterable<net.openhft.chronicle.queue.RollCycles> VALUES;

  private final java.lang.String format;

  private final int lengthInMillis;

  private final int cycleShift;

  private final int indexCount;

  private final int indexSpacing;

  private final long sequenceMask;

  private static final net.openhft.chronicle.queue.RollCycles[] $VALUES;

  public static net.openhft.chronicle.queue.RollCycles[] values();
    Code:
       0: getstatic     #1                  // Field $VALUES:[Lnet/openhft/chronicle/queue/RollCycles;
       3: invokevirtual #2                  // Method "[Lnet/openhft/chronicle/queue/RollCycles;".clone:()Ljava/lang/Object;
       6: checkcast     #3                  // class "[Lnet/openhft/chronicle/queue/RollCycles;"
       9: areturn

  public static net.openhft.chronicle.queue.RollCycles valueOf(java.lang.String);
    Code:
       0: ldc           #4                  // class net/openhft/chronicle/queue/RollCycles
       2: aload_0
       3: invokestatic  #5                  // Method java/lang/Enum.valueOf:(Ljava/lang/Class;Ljava/lang/String;)Ljava/lang/Enum;
       6: checkcast     #4                  // class net/openhft/chronicle/queue/RollCycles
       9: areturn

  private net.openhft.chronicle.queue.RollCycles(java.lang.String, int, int, int);
    Code:
       0: aload_0
       1: aload_1
       2: iload_2
       3: invokespecial #6                  // Method java/lang/Enum."<init>":(Ljava/lang/String;I)V
       6: aload_0
       7: aload_3
       8: putfield      #7                  // Field format:Ljava/lang/String;
      11: aload_0
      12: iload         4
      14: putfield      #8                  // Field lengthInMillis:I
      17: aload_0
      18: iload         5
      20: bipush        8
      22: invokestatic  #9                  // Method net/openhft/chronicle/core/Maths.nextPower2:(II)I
      25: putfield      #10                 // Field indexCount:I
      28: aload_0
      29: iload         6
      31: iconst_1
      32: invokestatic  #9                  // Method net/openhft/chronicle/core/Maths.nextPower2:(II)I
      35: putfield      #11                 // Field indexSpacing:I
      38: aload_0
      39: bipush        32
      41: iload         5
      43: i2l
      44: invokestatic  #12                 // Method net/openhft/chronicle/core/Maths.intLog2:(J)I
      47: iconst_2
      48: imul
      49: iload         6
      51: i2l
      52: invokestatic  #12                 // Method net/openhft/chronicle/core/Maths.intLog2:(J)I
      55: iadd
      56: invokestatic  #13                 // Method java/lang/Math.max:(II)I
      59: putfield      #14                 // Field cycleShift:I
      62: aload_0
      63: lconst_1
      64: aload_0
      65: getfield      #14                 // Field cycleShift:I
      68: lshl
      69: lconst_1
      70: lsub
      71: putfield      #15                 // Field sequenceMask:J
      74: return

  public long maxMessagesPerCycle();
    Code:
       0: aload_0
       1: getfield      #10                 // Field indexCount:I
       4: i2l
       5: aload_0
       6: getfield      #11                 // Field indexSpacing:I
       9: invokestatic  #16                 // Method maxMessagesPerCycle:(JI)J
      12: lreturn

  public static java.lang.Iterable<net.openhft.chronicle.queue.RollCycles> all();
    Code:
       0: getstatic     #17                 // Field VALUES:Ljava/lang/Iterable;
       3: areturn

  public java.lang.String format();
    Code:
       0: aload_0
       1: getfield      #7                  // Field format:Ljava/lang/String;
       4: areturn

  public int lengthInMillis();
    Code:
       0: aload_0
       1: getfield      #8                  // Field lengthInMillis:I
       4: ireturn

  public int defaultIndexCount();
    Code:
       0: aload_0
       1: getfield      #10                 // Field indexCount:I
       4: ireturn

  public int defaultIndexSpacing();
    Code:
       0: aload_0
       1: getfield      #11                 // Field indexSpacing:I
       4: ireturn

  public int current(net.openhft.chronicle.core.time.TimeProvider, long);
    Code:
       0: aload_1
       1: invokeinterface #18,  1           // InterfaceMethod net/openhft/chronicle/core/time/TimeProvider.currentTimeMillis:()J
       6: lload_2
       7: lsub
       8: aload_0
       9: invokevirtual #19                 // Method lengthInMillis:()I
      12: i2l
      13: ldiv
      14: l2i
      15: ireturn

  public long toIndex(int, long);
    Code:
       0: iload_1
       1: i2l
       2: aload_0
       3: getfield      #14                 // Field cycleShift:I
       6: lshl
       7: lload_2
       8: aload_0
       9: getfield      #15                 // Field sequenceMask:J
      12: land
      13: ladd
      14: lreturn

  public long toSequenceNumber(long);
    Code:
       0: lload_1
       1: aload_0
       2: getfield      #15                 // Field sequenceMask:J
       5: land
       6: lreturn

  public int toCycle(long);
    Code:
       0: lload_1
       1: aload_0
       2: getfield      #14                 // Field cycleShift:I
       5: lshr
       6: invokestatic  #20                 // Method net/openhft/chronicle/core/Maths.toUInt31:(J)I
       9: ireturn

  public static long maxMessagesPerCycle(long, int);
    Code:
       0: lload_0
       1: ldc2_w        #21                 // long 8l
       4: invokestatic  #23                 // Method net/openhft/chronicle/core/Maths.nextPower2:(JJ)J
       7: lstore_3
       8: iload_2
       9: iconst_1
      10: invokestatic  #9                  // Method net/openhft/chronicle/core/Maths.nextPower2:(II)I
      13: istore        5
      15: bipush        32
      17: lload_3
      18: invokestatic  #12                 // Method net/openhft/chronicle/core/Maths.intLog2:(J)I
      21: iconst_2
      22: imul
      23: iload         5
      25: i2l
      26: invokestatic  #12                 // Method net/openhft/chronicle/core/Maths.intLog2:(J)I
      29: iadd
      30: invokestatic  #13                 // Method java/lang/Math.max:(II)I
      33: istore        6
      35: lconst_1
      36: iload         6
      38: lshl
      39: lconst_1
      40: lsub
      41: lstore        7
      43: lload         7
      45: lload_3
      46: lload_3
      47: lmul
      48: iload         5
      50: i2l
      51: lmul
      52: invokestatic  #24                 // Method java/lang/Math.min:(JJ)J
      55: lreturn

  static {};
    Code:
       0: new           #4                  // class net/openhft/chronicle/queue/RollCycles
       3: dup
       4: ldc           #25                 // String FIVE_MINUTELY
       6: iconst_0
       7: ldc           #26                 // String yyyyMMdd-HHmm\'V\'
       9: ldc           #27                 // int 300000
      11: sipush        2048
      14: sipush        256
      17: invokespecial #28                 // Method "<init>":(Ljava/lang/String;ILjava/lang/String;III)V
      20: putstatic     #29                 // Field FIVE_MINUTELY:Lnet/openhft/chronicle/queue/RollCycles;
      23: new           #4                  // class net/openhft/chronicle/queue/RollCycles
      26: dup
      27: ldc           #30                 // String TEN_MINUTELY
      29: iconst_1
      30: ldc           #31                 // String yyyyMMdd-HHmm\'X\'
      32: ldc           #32                 // int 600000
      34: sipush        2048
      37: sipush        256
      40: invokespecial #28                 // Method "<init>":(Ljava/lang/String;ILjava/lang/String;III)V
      43: putstatic     #33                 // Field TEN_MINUTELY:Lnet/openhft/chronicle/queue/RollCycles;
      46: new           #4                  // class net/openhft/chronicle/queue/RollCycles
      49: dup
      50: ldc           #34                 // String TWENTY_MINUTELY
      52: iconst_2
      53: ldc           #35                 // String yyyyMMdd-HHmm\'XX\'
      55: ldc           #36                 // int 1200000
      57: sipush        2048
      60: sipush        256
      63: invokespecial #28                 // Method "<init>":(Ljava/lang/String;ILjava/lang/String;III)V
      66: putstatic     #37                 // Field TWENTY_MINUTELY:Lnet/openhft/chronicle/queue/RollCycles;
      69: new           #4                  // class net/openhft/chronicle/queue/RollCycles
      72: dup
      73: ldc           #38                 // String HALF_HOURLY
      75: iconst_3
      76: ldc           #39                 // String yyyyMMdd-HHmm\'H\'
      78: ldc           #40                 // int 1800000
      80: sipush        2048
      83: sipush        256
      86: invokespecial #28                 // Method "<init>":(Ljava/lang/String;ILjava/lang/String;III)V
      89: putstatic     #41                 // Field HALF_HOURLY:Lnet/openhft/chronicle/queue/RollCycles;
      92: new           #4                  // class net/openhft/chronicle/queue/RollCycles
      95: dup
      96: ldc           #42                 // String FAST_HOURLY
      98: iconst_4
      99: ldc           #43                 // String yyyyMMdd-HH\'F\'
     101: ldc           #44                 // int 3600000
     103: sipush        4096
     106: sipush        256
     109: invokespecial #28                 // Method "<init>":(Ljava/lang/String;ILjava/lang/String;III)V
     112: putstatic     #45                 // Field FAST_HOURLY:Lnet/openhft/chronicle/queue/RollCycles;
     115: new           #4                  // class net/openhft/chronicle/queue/RollCycles
     118: dup
     119: ldc           #46                 // String TWO_HOURLY
     121: iconst_5
     122: ldc           #47                 // String yyyyMMdd-HH\'II\'
     124: ldc           #48                 // int 7200000
     126: sipush        4096
     129: sipush        256
     132: invokespecial #28                 // Method "<init>":(Ljava/lang/String;ILjava/lang/String;III)V
     135: putstatic     #49                 // Field TWO_HOURLY:Lnet/openhft/chronicle/queue/RollCycles;
     138: new           #4                  // class net/openhft/chronicle/queue/RollCycles
     141: dup
     142: ldc           #50                 // String FOUR_HOURLY
     144: bipush        6
     146: ldc           #51                 // String yyyyMMdd-HH\'IV\'
     148: ldc           #52                 // int 14400000
     150: sipush        4096
     153: sipush        256
     156: invokespecial #28                 // Method "<init>":(Ljava/lang/String;ILjava/lang/String;III)V
     159: putstatic     #53                 // Field FOUR_HOURLY:Lnet/openhft/chronicle/queue/RollCycles;
     162: new           #4                  // class net/openhft/chronicle/queue/RollCycles
     165: dup
     166: ldc           #54                 // String SIX_HOURLY
     168: bipush        7
     170: ldc           #55                 // String yyyyMMdd-HH\'VI\'
     172: ldc           #56                 // int 21600000
     174: sipush        4096
     177: sipush        256
     180: invokespecial #28                 // Method "<init>":(Ljava/lang/String;ILjava/lang/String;III)V
     183: putstatic     #57                 // Field SIX_HOURLY:Lnet/openhft/chronicle/queue/RollCycles;
     186: new           #4                  // class net/openhft/chronicle/queue/RollCycles
     189: dup
     190: ldc           #58                 // String FAST_DAILY
     192: bipush        8
     194: ldc           #59                 // String yyyyMMdd\'F\'
     196: ldc           #60                 // int 86400000
     198: sipush        4096
     201: sipush        256
     204: invokespecial #28                 // Method "<init>":(Ljava/lang/String;ILjava/lang/String;III)V
     207: putstatic     #61                 // Field FAST_DAILY:Lnet/openhft/chronicle/queue/RollCycles;
     210: new           #4                  // class net/openhft/chronicle/queue/RollCycles
     213: dup
     214: ldc           #62                 // String MINUTELY
     216: bipush        9
     218: ldc           #63                 // String yyyyMMdd-HHmm
     220: ldc           #64                 // int 60000
     222: sipush        2048
     225: bipush        16
     227: invokespecial #28                 // Method "<init>":(Ljava/lang/String;ILjava/lang/String;III)V
     230: putstatic     #65                 // Field MINUTELY:Lnet/openhft/chronicle/queue/RollCycles;
     233: new           #4                  // class net/openhft/chronicle/queue/RollCycles
     236: dup
     237: ldc           #66                 // String HOURLY
     239: bipush        10
     241: ldc           #67                 // String yyyyMMdd-HH
     243: ldc           #44                 // int 3600000
     245: sipush        4096
     248: bipush        16
     250: invokespecial #28                 // Method "<init>":(Ljava/lang/String;ILjava/lang/String;III)V
     253: putstatic     #68                 // Field HOURLY:Lnet/openhft/chronicle/queue/RollCycles;
     256: new           #4                  // class net/openhft/chronicle/queue/RollCycles
     259: dup
     260: ldc           #69                 // String DAILY
     262: bipush        11
     264: ldc           #70                 // String yyyyMMdd
     266: ldc           #60                 // int 86400000
     268: sipush        8192
     271: bipush        64
     273: invokespecial #28                 // Method "<init>":(Ljava/lang/String;ILjava/lang/String;III)V
     276: putstatic     #71                 // Field DAILY:Lnet/openhft/chronicle/queue/RollCycles;
     279: new           #4                  // class net/openhft/chronicle/queue/RollCycles
     282: dup
     283: ldc           #72                 // String LARGE_HOURLY
     285: bipush        12
     287: ldc           #73                 // String yyyyMMdd-HH\'L\'
     289: ldc           #44                 // int 3600000
     291: sipush        8192
     294: bipush        64
     296: invokespecial #28                 // Method "<init>":(Ljava/lang/String;ILjava/lang/String;III)V
     299: putstatic     #74                 // Field LARGE_HOURLY:Lnet/openhft/chronicle/queue/RollCycles;
     302: new           #4                  // class net/openhft/chronicle/queue/RollCycles
     305: dup
     306: ldc           #75                 // String LARGE_DAILY
     308: bipush        13
     310: ldc           #76                 // String yyyyMMdd\'L\'
     312: ldc           #60                 // int 86400000
     314: ldc           #77                 // int 32768
     316: sipush        128
     319: invokespecial #28                 // Method "<init>":(Ljava/lang/String;ILjava/lang/String;III)V
     322: putstatic     #78                 // Field LARGE_DAILY:Lnet/openhft/chronicle/queue/RollCycles;
     325: new           #4                  // class net/openhft/chronicle/queue/RollCycles
     328: dup
     329: ldc           #79                 // String XLARGE_DAILY
     331: bipush        14
     333: ldc           #80                 // String yyyyMMdd\'X\'
     335: ldc           #60                 // int 86400000
     337: ldc           #81                 // int 131072
     339: sipush        256
     342: invokespecial #28                 // Method "<init>":(Ljava/lang/String;ILjava/lang/String;III)V
     345: putstatic     #82                 // Field XLARGE_DAILY:Lnet/openhft/chronicle/queue/RollCycles;
     348: new           #4                  // class net/openhft/chronicle/queue/RollCycles
     351: dup
     352: ldc           #83                 // String HUGE_DAILY
     354: bipush        15
     356: ldc           #84                 // String yyyyMMdd\'H\'
     358: ldc           #60                 // int 86400000
     360: ldc           #85                 // int 524288
     362: sipush        1024
     365: invokespecial #28                 // Method "<init>":(Ljava/lang/String;ILjava/lang/String;III)V
     368: putstatic     #86                 // Field HUGE_DAILY:Lnet/openhft/chronicle/queue/RollCycles;
     371: new           #4                  // class net/openhft/chronicle/queue/RollCycles
     374: dup
     375: ldc           #87                 // String SMALL_DAILY
     377: bipush        16
     379: ldc           #88                 // String yyyyMMdd\'S\'
     381: ldc           #60                 // int 86400000
     383: sipush        8192
     386: bipush        8
     388: invokespecial #28                 // Method "<init>":(Ljava/lang/String;ILjava/lang/String;III)V
     391: putstatic     #89                 // Field SMALL_DAILY:Lnet/openhft/chronicle/queue/RollCycles;
     394: new           #4                  // class net/openhft/chronicle/queue/RollCycles
     397: dup
     398: ldc           #90                 // String LARGE_HOURLY_SPARSE
     400: bipush        17
     402: ldc           #91                 // String yyyyMMdd-HH\'LS\'
     404: ldc           #44                 // int 3600000
     406: sipush        4096
     409: sipush        1024
     412: invokespecial #28                 // Method "<init>":(Ljava/lang/String;ILjava/lang/String;III)V
     415: putstatic     #92                 // Field LARGE_HOURLY_SPARSE:Lnet/openhft/chronicle/queue/RollCycles;
     418: new           #4                  // class net/openhft/chronicle/queue/RollCycles
     421: dup
     422: ldc           #93                 // String LARGE_HOURLY_XSPARSE
     424: bipush        18
     426: ldc           #94                 // String yyyyMMdd-HH\'LX\'
     428: ldc           #44                 // int 3600000
     430: sipush        2048
     433: ldc           #95                 // int 1048576
     435: invokespecial #28                 // Method "<init>":(Ljava/lang/String;ILjava/lang/String;III)V
     438: putstatic     #96                 // Field LARGE_HOURLY_XSPARSE:Lnet/openhft/chronicle/queue/RollCycles;
     441: new           #4                  // class net/openhft/chronicle/queue/RollCycles
     444: dup
     445: ldc           #97                 // String HUGE_DAILY_XSPARSE
     447: bipush        19
     449: ldc           #98                 // String yyyyMMdd\'HX\'
     451: ldc           #60                 // int 86400000
     453: sipush        16384
     456: ldc           #95                 // int 1048576
     458: invokespecial #28                 // Method "<init>":(Ljava/lang/String;ILjava/lang/String;III)V
     461: putstatic     #99                 // Field HUGE_DAILY_XSPARSE:Lnet/openhft/chronicle/queue/RollCycles;
     464: new           #4                  // class net/openhft/chronicle/queue/RollCycles
     467: dup
     468: ldc           #100                // String TEST_SECONDLY
     470: bipush        20
     472: ldc           #101                // String yyyyMMdd-HHmmss\'T\'
     474: sipush        1000
     477: ldc           #77                 // int 32768
     479: iconst_4
     480: invokespecial #28                 // Method "<init>":(Ljava/lang/String;ILjava/lang/String;III)V
     483: putstatic     #102                // Field TEST_SECONDLY:Lnet/openhft/chronicle/queue/RollCycles;
     486: new           #4                  // class net/openhft/chronicle/queue/RollCycles
     489: dup
     490: ldc           #103                // String TEST4_SECONDLY
     492: bipush        21
     494: ldc           #104                // String yyyyMMdd-HHmmss\'T4\'
     496: sipush        1000
     499: bipush        32
     501: iconst_4
     502: invokespecial #28                 // Method "<init>":(Ljava/lang/String;ILjava/lang/String;III)V
     505: putstatic     #105                // Field TEST4_SECONDLY:Lnet/openhft/chronicle/queue/RollCycles;
     508: new           #4                  // class net/openhft/chronicle/queue/RollCycles
     511: dup
     512: ldc           #106                // String TEST_HOURLY
     514: bipush        22
     516: ldc           #107                // String yyyyMMdd-HH\'T\'
     518: ldc           #44                 // int 3600000
     520: bipush        16
     522: iconst_4
     523: invokespecial #28                 // Method "<init>":(Ljava/lang/String;ILjava/lang/String;III)V
     526: putstatic     #108                // Field TEST_HOURLY:Lnet/openhft/chronicle/queue/RollCycles;
     529: new           #4                  // class net/openhft/chronicle/queue/RollCycles
     532: dup
     533: ldc           #109                // String TEST_DAILY
     535: bipush        23
     537: ldc           #110                // String yyyyMMdd\'T1\'
     539: ldc           #60                 // int 86400000
     541: bipush        8
     543: iconst_1
     544: invokespecial #28                 // Method "<init>":(Ljava/lang/String;ILjava/lang/String;III)V
     547: putstatic     #111                // Field TEST_DAILY:Lnet/openhft/chronicle/queue/RollCycles;
     550: new           #4                  // class net/openhft/chronicle/queue/RollCycles
     553: dup
     554: ldc           #112                // String TEST2_DAILY
     556: bipush        24
     558: ldc           #113                // String yyyyMMdd\'T2\'
     560: ldc           #60                 // int 86400000
     562: bipush        16
     564: iconst_2
     565: invokespecial #28                 // Method "<init>":(Ljava/lang/String;ILjava/lang/String;III)V
     568: putstatic     #114                // Field TEST2_DAILY:Lnet/openhft/chronicle/queue/RollCycles;
     571: new           #4                  // class net/openhft/chronicle/queue/RollCycles
     574: dup
     575: ldc           #115                // String TEST4_DAILY
     577: bipush        25
     579: ldc           #116                // String yyyyMMdd\'T4\'
     581: ldc           #60                 // int 86400000
     583: bipush        32
     585: iconst_4
     586: invokespecial #28                 // Method "<init>":(Ljava/lang/String;ILjava/lang/String;III)V
     589: putstatic     #117                // Field TEST4_DAILY:Lnet/openhft/chronicle/queue/RollCycles;
     592: new           #4                  // class net/openhft/chronicle/queue/RollCycles
     595: dup
     596: ldc           #118                // String TEST8_DAILY
     598: bipush        26
     600: ldc           #119                // String yyyyMMdd\'T8\'
     602: ldc           #60                 // int 86400000
     604: sipush        128
     607: bipush        8
     609: invokespecial #28                 // Method "<init>":(Ljava/lang/String;ILjava/lang/String;III)V
     612: putstatic     #120                // Field TEST8_DAILY:Lnet/openhft/chronicle/queue/RollCycles;
     615: bipush        27
     617: anewarray     #4                  // class net/openhft/chronicle/queue/RollCycles
     620: dup
     621: iconst_0
     622: getstatic     #29                 // Field FIVE_MINUTELY:Lnet/openhft/chronicle/queue/RollCycles;
     625: aastore
     626: dup
     627: iconst_1
     628: getstatic     #33                 // Field TEN_MINUTELY:Lnet/openhft/chronicle/queue/RollCycles;
     631: aastore
     632: dup
     633: iconst_2
     634: getstatic     #37                 // Field TWENTY_MINUTELY:Lnet/openhft/chronicle/queue/RollCycles;
     637: aastore
     638: dup
     639: iconst_3
     640: getstatic     #41                 // Field HALF_HOURLY:Lnet/openhft/chronicle/queue/RollCycles;
     643: aastore
     644: dup
     645: iconst_4
     646: getstatic     #45                 // Field FAST_HOURLY:Lnet/openhft/chronicle/queue/RollCycles;
     649: aastore
     650: dup
     651: iconst_5
     652: getstatic     #49                 // Field TWO_HOURLY:Lnet/openhft/chronicle/queue/RollCycles;
     655: aastore
     656: dup
     657: bipush        6
     659: getstatic     #53                 // Field FOUR_HOURLY:Lnet/openhft/chronicle/queue/RollCycles;
     662: aastore
     663: dup
     664: bipush        7
     666: getstatic     #57                 // Field SIX_HOURLY:Lnet/openhft/chronicle/queue/RollCycles;
     669: aastore
     670: dup
     671: bipush        8
     673: getstatic     #61                 // Field FAST_DAILY:Lnet/openhft/chronicle/queue/RollCycles;
     676: aastore
     677: dup
     678: bipush        9
     680: getstatic     #65                 // Field MINUTELY:Lnet/openhft/chronicle/queue/RollCycles;
     683: aastore
     684: dup
     685: bipush        10
     687: getstatic     #68                 // Field HOURLY:Lnet/openhft/chronicle/queue/RollCycles;
     690: aastore
     691: dup
     692: bipush        11
     694: getstatic     #71                 // Field DAILY:Lnet/openhft/chronicle/queue/RollCycles;
     697: aastore
     698: dup
     699: bipush        12
     701: getstatic     #74                 // Field LARGE_HOURLY:Lnet/openhft/chronicle/queue/RollCycles;
     704: aastore
     705: dup
     706: bipush        13
     708: getstatic     #78                 // Field LARGE_DAILY:Lnet/openhft/chronicle/queue/RollCycles;
     711: aastore
     712: dup
     713: bipush        14
     715: getstatic     #82                 // Field XLARGE_DAILY:Lnet/openhft/chronicle/queue/RollCycles;
     718: aastore
     719: dup
     720: bipush        15
     722: getstatic     #86                 // Field HUGE_DAILY:Lnet/openhft/chronicle/queue/RollCycles;
     725: aastore
     726: dup
     727: bipush        16
     729: getstatic     #89                 // Field SMALL_DAILY:Lnet/openhft/chronicle/queue/RollCycles;
     732: aastore
     733: dup
     734: bipush        17
     736: getstatic     #92                 // Field LARGE_HOURLY_SPARSE:Lnet/openhft/chronicle/queue/RollCycles;
     739: aastore
     740: dup
     741: bipush        18
     743: getstatic     #96                 // Field LARGE_HOURLY_XSPARSE:Lnet/openhft/chronicle/queue/RollCycles;
     746: aastore
     747: dup
     748: bipush        19
     750: getstatic     #99                 // Field HUGE_DAILY_XSPARSE:Lnet/openhft/chronicle/queue/RollCycles;
     753: aastore
     754: dup
     755: bipush        20
     757: getstatic     #102                // Field TEST_SECONDLY:Lnet/openhft/chronicle/queue/RollCycles;
     760: aastore
     761: dup
     762: bipush        21
     764: getstatic     #105                // Field TEST4_SECONDLY:Lnet/openhft/chronicle/queue/RollCycles;
     767: aastore
     768: dup
     769: bipush        22
     771: getstatic     #108                // Field TEST_HOURLY:Lnet/openhft/chronicle/queue/RollCycles;
     774: aastore
     775: dup
     776: bipush        23
     778: getstatic     #111                // Field TEST_DAILY:Lnet/openhft/chronicle/queue/RollCycles;
     781: aastore
     782: dup
     783: bipush        24
     785: getstatic     #114                // Field TEST2_DAILY:Lnet/openhft/chronicle/queue/RollCycles;
     788: aastore
     789: dup
     790: bipush        25
     792: getstatic     #117                // Field TEST4_DAILY:Lnet/openhft/chronicle/queue/RollCycles;
     795: aastore
     796: dup
     797: bipush        26
     799: getstatic     #120                // Field TEST8_DAILY:Lnet/openhft/chronicle/queue/RollCycles;
     802: aastore
     803: putstatic     #1                  // Field $VALUES:[Lnet/openhft/chronicle/queue/RollCycles;
     806: getstatic     #61                 // Field FAST_DAILY:Lnet/openhft/chronicle/queue/RollCycles;
     809: putstatic     #121                // Field DEFAULT:Lnet/openhft/chronicle/queue/RollCycles;
     812: invokestatic  #122                // Method values:()[Lnet/openhft/chronicle/queue/RollCycles;
     815: invokestatic  #123                // Method java/util/Arrays.asList:([Ljava/lang/Object;)Ljava/util/List;
     818: putstatic     #17                 // Field VALUES:Ljava/lang/Iterable;
     821: return
}
