public abstract class org.bouncycastle.cms.bc.BcKeyTransRecipient implements org.bouncycastle.cms.KeyTransRecipient {
  private org.bouncycastle.crypto.params.AsymmetricKeyParameter recipientKey;

  public org.bouncycastle.cms.bc.BcKeyTransRecipient(org.bouncycastle.crypto.params.AsymmetricKeyParameter);
    Code:
       0: aload_0
       1: invokespecial #49                 // Method java/lang/Object."<init>":()V
       4: aload_0
       5: aload_1
       6: putfield      #48                 // Field recipientKey:Lorg/bouncycastle/crypto/params/AsymmetricKeyParameter;
       9: return

  protected org.bouncycastle.crypto.CipherParameters extractSecretKey(org.bouncycastle.asn1.x509.AlgorithmIdentifier, org.bouncycastle.asn1.x509.AlgorithmIdentifier, byte[]) throws org.bouncycastle.cms.CMSException;
    Code:
       0: new           #29                 // class org/bouncycastle/operator/bc/BcRSAAsymmetricKeyUnwrapper
       3: dup
       4: aload_1
       5: aload_0
       6: getfield      #48                 // Field recipientKey:Lorg/bouncycastle/crypto/params/AsymmetricKeyParameter;
       9: invokespecial #57                 // Method org/bouncycastle/operator/bc/BcRSAAsymmetricKeyUnwrapper."<init>":(Lorg/bouncycastle/asn1/x509/AlgorithmIdentifier;Lorg/bouncycastle/crypto/params/AsymmetricKeyParameter;)V
      12: astore        4
      14: aload         4
      16: aload_2
      17: aload_3
      18: invokevirtual #55                 // Method org/bouncycastle/operator/AsymmetricKeyUnwrapper.generateUnwrappedKey:(Lorg/bouncycastle/asn1/x509/AlgorithmIdentifier;[B)Lorg/bouncycastle/operator/GenericKey;
      21: invokestatic  #54                 // Method org/bouncycastle/cms/bc/CMSUtils.getBcKey:(Lorg/bouncycastle/operator/GenericKey;)Lorg/bouncycastle/crypto/CipherParameters;
      24: areturn
      25: astore        5
      27: new           #23                 // class org/bouncycastle/cms/CMSException
      30: dup
      31: new           #22                 // class java/lang/StringBuilder
      34: dup
      35: invokespecial #50                 // Method java/lang/StringBuilder."<init>":()V
      38: ldc           #1                  // String exception unwrapping key:
      40: invokevirtual #52                 // Method java/lang/StringBuilder.append:(Ljava/lang/String;)Ljava/lang/StringBuilder;
      43: aload         5
      45: invokevirtual #56                 // Method org/bouncycastle/operator/OperatorException.getMessage:()Ljava/lang/String;
      48: invokevirtual #52                 // Method java/lang/StringBuilder.append:(Ljava/lang/String;)Ljava/lang/StringBuilder;
      51: invokevirtual #51                 // Method java/lang/StringBuilder.toString:()Ljava/lang/String;
      54: aload         5
      56: invokespecial #53                 // Method org/bouncycastle/cms/CMSException."<init>":(Ljava/lang/String;Ljava/lang/Exception;)V
      59: athrow
    Exception table:
       from    to  target type
          14    24    25   Class org/bouncycastle/operator/OperatorException
}
