Compiled from "BrokerConfigurationFailedException.java"
public class won.protocol.exception.BrokerConfigurationFailedException extends won.protocol.exception.WonProtocolException {
  private java.net.URI wonNodeURI;

  public won.protocol.exception.BrokerConfigurationFailedException(java.net.URI);
    Code:
       0: aload_0
       1: ldc           #1                  // String setting up broker for won node URI {0} failed
       3: iconst_1
       4: anewarray     #2                  // class java/lang/Object
       7: dup
       8: iconst_0
       9: aload_1
      10: invokevirtual #3                  // Method java/net/URI.toString:()Ljava/lang/String;
      13: aastore
      14: invokestatic  #4                  // Method java/text/MessageFormat.format:(Ljava/lang/String;[Ljava/lang/Object;)Ljava/lang/String;
      17: invokespecial #5                  // Method won/protocol/exception/WonProtocolException."<init>":(Ljava/lang/String;)V
      20: aload_0
      21: aload_1
      22: putfield      #6                  // Field wonNodeURI:Ljava/net/URI;
      25: return
}
