Compiled from "Element.java"
public final class org.jboss.metadata.parser.jboss.Element extends java.lang.Enum<org.jboss.metadata.parser.jboss.Element> {
  public static final org.jboss.metadata.parser.jboss.Element UNKNOWN;

  public static final org.jboss.metadata.parser.jboss.Element CONTEXT_ROOT;

  public static final org.jboss.metadata.parser.jboss.Element DISTINCT_NAME;

  public static final org.jboss.metadata.parser.jboss.Element HAR;

  public static final org.jboss.metadata.parser.jboss.Element JMX_NAME;

  public static final org.jboss.metadata.parser.jboss.Element LIBRARY_DIRECTORY;

  public static final org.jboss.metadata.parser.jboss.Element LOADER_REPOSITORY;

  public static final org.jboss.metadata.parser.jboss.Element LOADER_REPOSITORY_CONFIG;

  public static final org.jboss.metadata.parser.jboss.Element MODULE;

  public static final org.jboss.metadata.parser.jboss.Element MODULE_ORDER;

  public static final org.jboss.metadata.parser.jboss.Element PRINCIPAL_NAME;

  public static final org.jboss.metadata.parser.jboss.Element ROLE_NAME;

  public static final org.jboss.metadata.parser.jboss.Element SECURITY_DOMAIN;

  public static final org.jboss.metadata.parser.jboss.Element SECURITY_ROLE;

  public static final org.jboss.metadata.parser.jboss.Element SERVICE;

  public static final org.jboss.metadata.parser.jboss.Element UNAUTHENTICATED_PRINCIPAL;

  public static final org.jboss.metadata.parser.jboss.Element WEB;

  public static final org.jboss.metadata.parser.jboss.Element WEB_URI;

  private final java.lang.String name;

  private static final java.util.Map<java.lang.String, org.jboss.metadata.parser.jboss.Element> MAP;

  private static final org.jboss.metadata.parser.jboss.Element[] $VALUES;

  public static org.jboss.metadata.parser.jboss.Element[] values();
    Code:
       0: getstatic     #1                  // Field $VALUES:[Lorg/jboss/metadata/parser/jboss/Element;
       3: invokevirtual #2                  // Method "[Lorg/jboss/metadata/parser/jboss/Element;".clone:()Ljava/lang/Object;
       6: checkcast     #3                  // class "[Lorg/jboss/metadata/parser/jboss/Element;"
       9: areturn

  public static org.jboss.metadata.parser.jboss.Element valueOf(java.lang.String);
    Code:
       0: ldc           #4                  // class org/jboss/metadata/parser/jboss/Element
       2: aload_0
       3: invokestatic  #5                  // Method java/lang/Enum.valueOf:(Ljava/lang/Class;Ljava/lang/String;)Ljava/lang/Enum;
       6: checkcast     #4                  // class org/jboss/metadata/parser/jboss/Element
       9: areturn

  private org.jboss.metadata.parser.jboss.Element(java.lang.String);
    Code:
       0: aload_0
       1: aload_1
       2: iload_2
       3: invokespecial #6                  // Method java/lang/Enum."<init>":(Ljava/lang/String;I)V
       6: aload_0
       7: aload_3
       8: putfield      #7                  // Field name:Ljava/lang/String;
      11: return

  public java.lang.String getLocalName();
    Code:
       0: aload_0
       1: getfield      #7                  // Field name:Ljava/lang/String;
       4: areturn

  public static org.jboss.metadata.parser.jboss.Element forName(java.lang.String);
    Code:
       0: getstatic     #8                  // Field MAP:Ljava/util/Map;
       3: aload_0
       4: invokeinterface #9,  2            // InterfaceMethod java/util/Map.get:(Ljava/lang/Object;)Ljava/lang/Object;
       9: checkcast     #4                  // class org/jboss/metadata/parser/jboss/Element
      12: astore_1
      13: aload_1
      14: ifnonnull     23
      17: getstatic     #10                 // Field UNKNOWN:Lorg/jboss/metadata/parser/jboss/Element;
      20: goto          24
      23: aload_1
      24: areturn

  static {};
    Code:
       0: new           #4                  // class org/jboss/metadata/parser/jboss/Element
       3: dup
       4: ldc           #11                 // String UNKNOWN
       6: iconst_0
       7: aconst_null
       8: invokespecial #12                 // Method "<init>":(Ljava/lang/String;ILjava/lang/String;)V
      11: putstatic     #10                 // Field UNKNOWN:Lorg/jboss/metadata/parser/jboss/Element;
      14: new           #4                  // class org/jboss/metadata/parser/jboss/Element
      17: dup
      18: ldc           #13                 // String CONTEXT_ROOT
      20: iconst_1
      21: ldc           #14                 // String context-root
      23: invokespecial #12                 // Method "<init>":(Ljava/lang/String;ILjava/lang/String;)V
      26: putstatic     #15                 // Field CONTEXT_ROOT:Lorg/jboss/metadata/parser/jboss/Element;
      29: new           #4                  // class org/jboss/metadata/parser/jboss/Element
      32: dup
      33: ldc           #16                 // String DISTINCT_NAME
      35: iconst_2
      36: ldc           #17                 // String distinct-name
      38: invokespecial #12                 // Method "<init>":(Ljava/lang/String;ILjava/lang/String;)V
      41: putstatic     #18                 // Field DISTINCT_NAME:Lorg/jboss/metadata/parser/jboss/Element;
      44: new           #4                  // class org/jboss/metadata/parser/jboss/Element
      47: dup
      48: ldc           #19                 // String HAR
      50: iconst_3
      51: ldc           #20                 // String har
      53: invokespecial #12                 // Method "<init>":(Ljava/lang/String;ILjava/lang/String;)V
      56: putstatic     #21                 // Field HAR:Lorg/jboss/metadata/parser/jboss/Element;
      59: new           #4                  // class org/jboss/metadata/parser/jboss/Element
      62: dup
      63: ldc           #22                 // String JMX_NAME
      65: iconst_4
      66: ldc           #23                 // String jmx-name
      68: invokespecial #12                 // Method "<init>":(Ljava/lang/String;ILjava/lang/String;)V
      71: putstatic     #24                 // Field JMX_NAME:Lorg/jboss/metadata/parser/jboss/Element;
      74: new           #4                  // class org/jboss/metadata/parser/jboss/Element
      77: dup
      78: ldc           #25                 // String LIBRARY_DIRECTORY
      80: iconst_5
      81: ldc           #26                 // String library-directory
      83: invokespecial #12                 // Method "<init>":(Ljava/lang/String;ILjava/lang/String;)V
      86: putstatic     #27                 // Field LIBRARY_DIRECTORY:Lorg/jboss/metadata/parser/jboss/Element;
      89: new           #4                  // class org/jboss/metadata/parser/jboss/Element
      92: dup
      93: ldc           #28                 // String LOADER_REPOSITORY
      95: bipush        6
      97: ldc           #29                 // String loader-repository
      99: invokespecial #12                 // Method "<init>":(Ljava/lang/String;ILjava/lang/String;)V
     102: putstatic     #30                 // Field LOADER_REPOSITORY:Lorg/jboss/metadata/parser/jboss/Element;
     105: new           #4                  // class org/jboss/metadata/parser/jboss/Element
     108: dup
     109: ldc           #31                 // String LOADER_REPOSITORY_CONFIG
     111: bipush        7
     113: ldc           #32                 // String loader-repository-config
     115: invokespecial #12                 // Method "<init>":(Ljava/lang/String;ILjava/lang/String;)V
     118: putstatic     #33                 // Field LOADER_REPOSITORY_CONFIG:Lorg/jboss/metadata/parser/jboss/Element;
     121: new           #4                  // class org/jboss/metadata/parser/jboss/Element
     124: dup
     125: ldc           #34                 // String MODULE
     127: bipush        8
     129: ldc           #35                 // String module
     131: invokespecial #12                 // Method "<init>":(Ljava/lang/String;ILjava/lang/String;)V
     134: putstatic     #36                 // Field MODULE:Lorg/jboss/metadata/parser/jboss/Element;
     137: new           #4                  // class org/jboss/metadata/parser/jboss/Element
     140: dup
     141: ldc           #37                 // String MODULE_ORDER
     143: bipush        9
     145: ldc           #38                 // String module-order
     147: invokespecial #12                 // Method "<init>":(Ljava/lang/String;ILjava/lang/String;)V
     150: putstatic     #39                 // Field MODULE_ORDER:Lorg/jboss/metadata/parser/jboss/Element;
     153: new           #4                  // class org/jboss/metadata/parser/jboss/Element
     156: dup
     157: ldc           #40                 // String PRINCIPAL_NAME
     159: bipush        10
     161: ldc           #41                 // String principal-name
     163: invokespecial #12                 // Method "<init>":(Ljava/lang/String;ILjava/lang/String;)V
     166: putstatic     #42                 // Field PRINCIPAL_NAME:Lorg/jboss/metadata/parser/jboss/Element;
     169: new           #4                  // class org/jboss/metadata/parser/jboss/Element
     172: dup
     173: ldc           #43                 // String ROLE_NAME
     175: bipush        11
     177: ldc           #44                 // String role-name
     179: invokespecial #12                 // Method "<init>":(Ljava/lang/String;ILjava/lang/String;)V
     182: putstatic     #45                 // Field ROLE_NAME:Lorg/jboss/metadata/parser/jboss/Element;
     185: new           #4                  // class org/jboss/metadata/parser/jboss/Element
     188: dup
     189: ldc           #46                 // String SECURITY_DOMAIN
     191: bipush        12
     193: ldc           #47                 // String security-domain
     195: invokespecial #12                 // Method "<init>":(Ljava/lang/String;ILjava/lang/String;)V
     198: putstatic     #48                 // Field SECURITY_DOMAIN:Lorg/jboss/metadata/parser/jboss/Element;
     201: new           #4                  // class org/jboss/metadata/parser/jboss/Element
     204: dup
     205: ldc           #49                 // String SECURITY_ROLE
     207: bipush        13
     209: ldc           #50                 // String security-role
     211: invokespecial #12                 // Method "<init>":(Ljava/lang/String;ILjava/lang/String;)V
     214: putstatic     #51                 // Field SECURITY_ROLE:Lorg/jboss/metadata/parser/jboss/Element;
     217: new           #4                  // class org/jboss/metadata/parser/jboss/Element
     220: dup
     221: ldc           #52                 // String SERVICE
     223: bipush        14
     225: ldc           #53                 // String service
     227: invokespecial #12                 // Method "<init>":(Ljava/lang/String;ILjava/lang/String;)V
     230: putstatic     #54                 // Field SERVICE:Lorg/jboss/metadata/parser/jboss/Element;
     233: new           #4                  // class org/jboss/metadata/parser/jboss/Element
     236: dup
     237: ldc           #55                 // String UNAUTHENTICATED_PRINCIPAL
     239: bipush        15
     241: ldc           #56                 // String unauthenticated-principal
     243: invokespecial #12                 // Method "<init>":(Ljava/lang/String;ILjava/lang/String;)V
     246: putstatic     #57                 // Field UNAUTHENTICATED_PRINCIPAL:Lorg/jboss/metadata/parser/jboss/Element;
     249: new           #4                  // class org/jboss/metadata/parser/jboss/Element
     252: dup
     253: ldc           #58                 // String WEB
     255: bipush        16
     257: ldc           #59                 // String web
     259: invokespecial #12                 // Method "<init>":(Ljava/lang/String;ILjava/lang/String;)V
     262: putstatic     #60                 // Field WEB:Lorg/jboss/metadata/parser/jboss/Element;
     265: new           #4                  // class org/jboss/metadata/parser/jboss/Element
     268: dup
     269: ldc           #61                 // String WEB_URI
     271: bipush        17
     273: ldc           #62                 // String web-uri
     275: invokespecial #12                 // Method "<init>":(Ljava/lang/String;ILjava/lang/String;)V
     278: putstatic     #63                 // Field WEB_URI:Lorg/jboss/metadata/parser/jboss/Element;
     281: bipush        18
     283: anewarray     #4                  // class org/jboss/metadata/parser/jboss/Element
     286: dup
     287: iconst_0
     288: getstatic     #10                 // Field UNKNOWN:Lorg/jboss/metadata/parser/jboss/Element;
     291: aastore
     292: dup
     293: iconst_1
     294: getstatic     #15                 // Field CONTEXT_ROOT:Lorg/jboss/metadata/parser/jboss/Element;
     297: aastore
     298: dup
     299: iconst_2
     300: getstatic     #18                 // Field DISTINCT_NAME:Lorg/jboss/metadata/parser/jboss/Element;
     303: aastore
     304: dup
     305: iconst_3
     306: getstatic     #21                 // Field HAR:Lorg/jboss/metadata/parser/jboss/Element;
     309: aastore
     310: dup
     311: iconst_4
     312: getstatic     #24                 // Field JMX_NAME:Lorg/jboss/metadata/parser/jboss/Element;
     315: aastore
     316: dup
     317: iconst_5
     318: getstatic     #27                 // Field LIBRARY_DIRECTORY:Lorg/jboss/metadata/parser/jboss/Element;
     321: aastore
     322: dup
     323: bipush        6
     325: getstatic     #30                 // Field LOADER_REPOSITORY:Lorg/jboss/metadata/parser/jboss/Element;
     328: aastore
     329: dup
     330: bipush        7
     332: getstatic     #33                 // Field LOADER_REPOSITORY_CONFIG:Lorg/jboss/metadata/parser/jboss/Element;
     335: aastore
     336: dup
     337: bipush        8
     339: getstatic     #36                 // Field MODULE:Lorg/jboss/metadata/parser/jboss/Element;
     342: aastore
     343: dup
     344: bipush        9
     346: getstatic     #39                 // Field MODULE_ORDER:Lorg/jboss/metadata/parser/jboss/Element;
     349: aastore
     350: dup
     351: bipush        10
     353: getstatic     #42                 // Field PRINCIPAL_NAME:Lorg/jboss/metadata/parser/jboss/Element;
     356: aastore
     357: dup
     358: bipush        11
     360: getstatic     #45                 // Field ROLE_NAME:Lorg/jboss/metadata/parser/jboss/Element;
     363: aastore
     364: dup
     365: bipush        12
     367: getstatic     #48                 // Field SECURITY_DOMAIN:Lorg/jboss/metadata/parser/jboss/Element;
     370: aastore
     371: dup
     372: bipush        13
     374: getstatic     #51                 // Field SECURITY_ROLE:Lorg/jboss/metadata/parser/jboss/Element;
     377: aastore
     378: dup
     379: bipush        14
     381: getstatic     #54                 // Field SERVICE:Lorg/jboss/metadata/parser/jboss/Element;
     384: aastore
     385: dup
     386: bipush        15
     388: getstatic     #57                 // Field UNAUTHENTICATED_PRINCIPAL:Lorg/jboss/metadata/parser/jboss/Element;
     391: aastore
     392: dup
     393: bipush        16
     395: getstatic     #60                 // Field WEB:Lorg/jboss/metadata/parser/jboss/Element;
     398: aastore
     399: dup
     400: bipush        17
     402: getstatic     #63                 // Field WEB_URI:Lorg/jboss/metadata/parser/jboss/Element;
     405: aastore
     406: putstatic     #1                  // Field $VALUES:[Lorg/jboss/metadata/parser/jboss/Element;
     409: new           #64                 // class java/util/HashMap
     412: dup
     413: invokespecial #65                 // Method java/util/HashMap."<init>":()V
     416: astore_0
     417: invokestatic  #66                 // Method values:()[Lorg/jboss/metadata/parser/jboss/Element;
     420: astore_1
     421: aload_1
     422: arraylength
     423: istore_2
     424: iconst_0
     425: istore_3
     426: iload_3
     427: iload_2
     428: if_icmpge     465
     431: aload_1
     432: iload_3
     433: aaload
     434: astore        4
     436: aload         4
     438: invokevirtual #67                 // Method getLocalName:()Ljava/lang/String;
     441: astore        5
     443: aload         5
     445: ifnull        459
     448: aload_0
     449: aload         5
     451: aload         4
     453: invokeinterface #68,  3           // InterfaceMethod java/util/Map.put:(Ljava/lang/Object;Ljava/lang/Object;)Ljava/lang/Object;
     458: pop
     459: iinc          3, 1
     462: goto          426
     465: aload_0
     466: putstatic     #8                  // Field MAP:Ljava/util/Map;
     469: return
}
