Compiled from "ToggleCommand.java"
public class org.apache.bookkeeper.tools.cli.commands.autorecovery.ToggleCommand$AutoRecoveryFlags extends org.apache.bookkeeper.tools.framework.CliFlags {
  private boolean enable;

  private boolean status;

  public org.apache.bookkeeper.tools.cli.commands.autorecovery.ToggleCommand$AutoRecoveryFlags();
    Code:
       0: aload_0
       1: invokespecial #3                  // Method org/apache/bookkeeper/tools/framework/CliFlags."<init>":()V
       4: return

  public org.apache.bookkeeper.tools.cli.commands.autorecovery.ToggleCommand$AutoRecoveryFlags enable(boolean);
    Code:
       0: aload_0
       1: iload_1
       2: putfield      #1                  // Field enable:Z
       5: aload_0
       6: areturn

  public org.apache.bookkeeper.tools.cli.commands.autorecovery.ToggleCommand$AutoRecoveryFlags status(boolean);
    Code:
       0: aload_0
       1: iload_1
       2: putfield      #2                  // Field status:Z
       5: aload_0
       6: areturn

  static boolean access$000(org.apache.bookkeeper.tools.cli.commands.autorecovery.ToggleCommand$AutoRecoveryFlags);
    Code:
       0: aload_0
       1: getfield      #2                  // Field status:Z
       4: ireturn

  static boolean access$100(org.apache.bookkeeper.tools.cli.commands.autorecovery.ToggleCommand$AutoRecoveryFlags);
    Code:
       0: aload_0
       1: getfield      #1                  // Field enable:Z
       4: ireturn
}
