Compiled from "ApplicationExceptionMetaDataParser.java"
public class org.jboss.metadata.ejb.parser.spec.ApplicationExceptionMetaDataParser extends org.jboss.metadata.ejb.parser.spec.AbstractIdMetaDataParser<org.jboss.metadata.ejb.spec.ApplicationExceptionMetaData> {
  public static final org.jboss.metadata.ejb.parser.spec.ApplicationExceptionMetaDataParser INSTANCE;

  public org.jboss.metadata.ejb.parser.spec.ApplicationExceptionMetaDataParser();
    Code:
       0: aload_0
       1: invokespecial #1                  // Method org/jboss/metadata/ejb/parser/spec/AbstractIdMetaDataParser."<init>":()V
       4: return

  public org.jboss.metadata.ejb.spec.ApplicationExceptionMetaData parse(javax.xml.stream.XMLStreamReader, org.jboss.metadata.property.PropertyReplacer) throws javax.xml.stream.XMLStreamException;
    Code:
       0: new           #2                  // class org/jboss/metadata/ejb/spec/ApplicationExceptionMetaData
       3: dup
       4: invokespecial #3                  // Method org/jboss/metadata/ejb/spec/ApplicationExceptionMetaData."<init>":()V
       7: astore_3
       8: aload_3
       9: aload_1
      10: aload_0
      11: invokestatic  #4                  // Method org/jboss/metadata/ejb/parser/spec/AttributeProcessorHelper.processAttributes:(Ljava/lang/Object;Ljavax/xml/stream/XMLStreamReader;Lorg/jboss/metadata/ejb/parser/spec/AttributeProcessor;)V
      14: aload_0
      15: aload_3
      16: aload_1
      17: aload_2
      18: invokevirtual #5                  // Method processElements:(Ljava/lang/Object;Ljavax/xml/stream/XMLStreamReader;Lorg/jboss/metadata/property/PropertyReplacer;)V
      21: aload_3
      22: areturn

  protected void processElement(org.jboss.metadata.ejb.spec.ApplicationExceptionMetaData, javax.xml.stream.XMLStreamReader, org.jboss.metadata.property.PropertyReplacer) throws javax.xml.stream.XMLStreamException;
    Code:
       0: aload_2
       1: invokeinterface #6,  1            // InterfaceMethod javax/xml/stream/XMLStreamReader.getLocalName:()Ljava/lang/String;
       6: invokestatic  #7                  // Method org/jboss/metadata/ejb/parser/spec/EjbJarElement.forName:(Ljava/lang/String;)Lorg/jboss/metadata/ejb/parser/spec/EjbJarElement;
       9: astore        4
      11: getstatic     #8                  // Field org/jboss/metadata/ejb/parser/spec/ApplicationExceptionMetaDataParser$1.$SwitchMap$org$jboss$metadata$ejb$parser$spec$EjbJarElement:[I
      14: aload         4
      16: invokevirtual #9                  // Method org/jboss/metadata/ejb/parser/spec/EjbJarElement.ordinal:()I
      19: iaload
      20: tableswitch   { // 1 to 3
                     1: 48
                     2: 60
                     3: 75
               default: 93
          }
      48: aload_1
      49: aload_2
      50: aload_3
      51: invokestatic  #10                 // Method org/jboss/metadata/ejb/parser/spec/AbstractIdMetaDataParser.getElementText:(Ljavax/xml/stream/XMLStreamReader;Lorg/jboss/metadata/property/PropertyReplacer;)Ljava/lang/String;
      54: invokevirtual #11                 // Method org/jboss/metadata/ejb/spec/ApplicationExceptionMetaData.setExceptionClass:(Ljava/lang/String;)V
      57: goto          98
      60: aload_1
      61: aload_2
      62: aload_3
      63: invokestatic  #10                 // Method org/jboss/metadata/ejb/parser/spec/AbstractIdMetaDataParser.getElementText:(Ljavax/xml/stream/XMLStreamReader;Lorg/jboss/metadata/property/PropertyReplacer;)Ljava/lang/String;
      66: invokestatic  #12                 // Method java/lang/Boolean.valueOf:(Ljava/lang/String;)Ljava/lang/Boolean;
      69: invokevirtual #13                 // Method org/jboss/metadata/ejb/spec/ApplicationExceptionMetaData.setInherited:(Ljava/lang/Boolean;)V
      72: goto          98
      75: aload_1
      76: aload_2
      77: aload_3
      78: invokestatic  #10                 // Method org/jboss/metadata/ejb/parser/spec/AbstractIdMetaDataParser.getElementText:(Ljavax/xml/stream/XMLStreamReader;Lorg/jboss/metadata/property/PropertyReplacer;)Ljava/lang/String;
      81: invokestatic  #12                 // Method java/lang/Boolean.valueOf:(Ljava/lang/String;)Ljava/lang/Boolean;
      84: invokevirtual #14                 // Method java/lang/Boolean.booleanValue:()Z
      87: invokevirtual #15                 // Method org/jboss/metadata/ejb/spec/ApplicationExceptionMetaData.setRollback:(Z)V
      90: goto          98
      93: aload_2
      94: invokestatic  #16                 // Method unexpectedElement:(Ljavax/xml/stream/XMLStreamReader;)Ljavax/xml/stream/XMLStreamException;
      97: athrow
      98: return

  protected void processElement(java.lang.Object, javax.xml.stream.XMLStreamReader, org.jboss.metadata.property.PropertyReplacer) throws javax.xml.stream.XMLStreamException;
    Code:
       0: aload_0
       1: aload_1
       2: checkcast     #2                  // class org/jboss/metadata/ejb/spec/ApplicationExceptionMetaData
       5: aload_2
       6: aload_3
       7: invokevirtual #17                 // Method processElement:(Lorg/jboss/metadata/ejb/spec/ApplicationExceptionMetaData;Ljavax/xml/stream/XMLStreamReader;Lorg/jboss/metadata/property/PropertyReplacer;)V
      10: return

  public java.lang.Object parse(javax.xml.stream.XMLStreamReader, org.jboss.metadata.property.PropertyReplacer) throws javax.xml.stream.XMLStreamException;
    Code:
       0: aload_0
       1: aload_1
       2: aload_2
       3: invokevirtual #18                 // Method parse:(Ljavax/xml/stream/XMLStreamReader;Lorg/jboss/metadata/property/PropertyReplacer;)Lorg/jboss/metadata/ejb/spec/ApplicationExceptionMetaData;
       6: areturn

  static {};
    Code:
       0: new           #19                 // class org/jboss/metadata/ejb/parser/spec/ApplicationExceptionMetaDataParser
       3: dup
       4: invokespecial #20                 // Method "<init>":()V
       7: putstatic     #21                 // Field INSTANCE:Lorg/jboss/metadata/ejb/parser/spec/ApplicationExceptionMetaDataParser;
      10: return
}
