Compiled from "factorial.java"
public class org.apache.jena.sparql.function.library.leviathan.factorial extends org.apache.jena.sparql.function.FunctionBase1 {
  public org.apache.jena.sparql.function.library.leviathan.factorial();
    Code:
       0: aload_0
       1: invokespecial #1                  // Method org/apache/jena/sparql/function/FunctionBase1."<init>":()V
       4: return

  public org.apache.jena.sparql.expr.NodeValue exec(org.apache.jena.sparql.expr.NodeValue);
    Code:
       0: aload_1
       1: invokevirtual #2                  // Method org/apache/jena/sparql/expr/NodeValue.getInteger:()Ljava/math/BigInteger;
       4: astore_2
       5: aload_2
       6: getstatic     #3                  // Field java/math/BigInteger.ZERO:Ljava/math/BigInteger;
       9: invokevirtual #4                  // Method java/math/BigInteger.compareTo:(Ljava/math/BigInteger;)I
      12: tableswitch   { // -1 to 1
                    -1: 47
                     0: 40
                     1: 57
               default: 105
          }
      40: getstatic     #5                  // Field java/math/BigInteger.ONE:Ljava/math/BigInteger;
      43: invokestatic  #6                  // Method org/apache/jena/sparql/expr/NodeValue.makeInteger:(Ljava/math/BigInteger;)Lorg/apache/jena/sparql/expr/NodeValue;
      46: areturn
      47: new           #7                  // class org/apache/jena/sparql/expr/ExprEvalException
      50: dup
      51: ldc           #8                  // String Cannot evaluate a negative factorial
      53: invokespecial #9                  // Method org/apache/jena/sparql/expr/ExprEvalException."<init>":(Ljava/lang/String;)V
      56: athrow
      57: aload_2
      58: getstatic     #3                  // Field java/math/BigInteger.ZERO:Ljava/math/BigInteger;
      61: invokevirtual #10                 // Method java/math/BigInteger.add:(Ljava/math/BigInteger;)Ljava/math/BigInteger;
      64: astore_3
      65: aload_2
      66: getstatic     #5                  // Field java/math/BigInteger.ONE:Ljava/math/BigInteger;
      69: invokevirtual #11                 // Method java/math/BigInteger.subtract:(Ljava/math/BigInteger;)Ljava/math/BigInteger;
      72: astore_2
      73: aload_2
      74: getstatic     #3                  // Field java/math/BigInteger.ZERO:Ljava/math/BigInteger;
      77: invokevirtual #4                  // Method java/math/BigInteger.compareTo:(Ljava/math/BigInteger;)I
      80: ifeq          100
      83: aload_3
      84: aload_2
      85: invokevirtual #12                 // Method java/math/BigInteger.multiply:(Ljava/math/BigInteger;)Ljava/math/BigInteger;
      88: astore_3
      89: aload_2
      90: getstatic     #5                  // Field java/math/BigInteger.ONE:Ljava/math/BigInteger;
      93: invokevirtual #11                 // Method java/math/BigInteger.subtract:(Ljava/math/BigInteger;)Ljava/math/BigInteger;
      96: astore_2
      97: goto          73
     100: aload_3
     101: invokestatic  #6                  // Method org/apache/jena/sparql/expr/NodeValue.makeInteger:(Ljava/math/BigInteger;)Lorg/apache/jena/sparql/expr/NodeValue;
     104: areturn
     105: new           #7                  // class org/apache/jena/sparql/expr/ExprEvalException
     108: dup
     109: ldc           #13                 // String Unexpecte comparison result
     111: invokespecial #9                  // Method org/apache/jena/sparql/expr/ExprEvalException."<init>":(Ljava/lang/String;)V
     114: athrow
}
