Compiled from "ServletManagementContextFactory.java"
class org.springframework.boot.actuate.autoconfigure.web.servlet.ServletManagementContextFactory implements org.springframework.boot.actuate.autoconfigure.web.ManagementContextFactory {
  org.springframework.boot.actuate.autoconfigure.web.servlet.ServletManagementContextFactory();
    Code:
       0: aload_0
       1: invokespecial #1                  // Method java/lang/Object."<init>":()V
       4: return

  public org.springframework.boot.web.context.ConfigurableWebServerApplicationContext createManagementContext(org.springframework.context.ApplicationContext, java.lang.Class<?>...);
    Code:
       0: new           #2                  // class org/springframework/boot/web/servlet/context/AnnotationConfigServletWebServerApplicationContext
       3: dup
       4: invokespecial #3                  // Method org/springframework/boot/web/servlet/context/AnnotationConfigServletWebServerApplicationContext."<init>":()V
       7: astore_3
       8: aload_3
       9: aload_1
      10: invokevirtual #4                  // Method org/springframework/boot/web/servlet/context/AnnotationConfigServletWebServerApplicationContext.setParent:(Lorg/springframework/context/ApplicationContext;)V
      13: new           #5                  // class java/util/ArrayList
      16: dup
      17: aload_2
      18: invokestatic  #6                  // Method java/util/Arrays.asList:([Ljava/lang/Object;)Ljava/util/List;
      21: invokespecial #7                  // Method java/util/ArrayList."<init>":(Ljava/util/Collection;)V
      24: astore        4
      26: aload         4
      28: ldc           #8                  // class org/springframework/boot/autoconfigure/web/servlet/ServletWebServerFactoryAutoConfiguration
      30: invokeinterface #9,  2            // InterfaceMethod java/util/List.add:(Ljava/lang/Object;)Z
      35: pop
      36: aload_3
      37: aload         4
      39: invokestatic  #10                 // Method org/springframework/util/ClassUtils.toClassArray:(Ljava/util/Collection;)[Ljava/lang/Class;
      42: invokevirtual #11                 // Method org/springframework/boot/web/servlet/context/AnnotationConfigServletWebServerApplicationContext.register:([Ljava/lang/Class;)V
      45: aload_0
      46: aload_1
      47: aload_3
      48: invokespecial #12                 // Method registerServletWebServerFactory:(Lorg/springframework/context/ApplicationContext;Lorg/springframework/boot/web/servlet/context/AnnotationConfigServletWebServerApplicationContext;)V
      51: aload_3
      52: areturn

  private void registerServletWebServerFactory(org.springframework.context.ApplicationContext, org.springframework.boot.web.servlet.context.AnnotationConfigServletWebServerApplicationContext);
    Code:
       0: aload_2
       1: invokevirtual #13                 // Method org/springframework/boot/web/servlet/context/AnnotationConfigServletWebServerApplicationContext.getBeanFactory:()Lorg/springframework/beans/factory/config/ConfigurableListableBeanFactory;
       4: astore_3
       5: aload_3
       6: instanceof    #14                 // class org/springframework/beans/factory/support/BeanDefinitionRegistry
       9: ifeq          39
      12: aload_3
      13: checkcast     #14                 // class org/springframework/beans/factory/support/BeanDefinitionRegistry
      16: astore        4
      18: aload         4
      20: ldc           #15                 // String ServletWebServerFactory
      22: new           #16                 // class org/springframework/beans/factory/support/RootBeanDefinition
      25: dup
      26: aload_0
      27: aload_1
      28: invokespecial #17                 // Method determineServletWebServerFactoryClass:(Lorg/springframework/context/ApplicationContext;)Ljava/lang/Class;
      31: invokespecial #18                 // Method org/springframework/beans/factory/support/RootBeanDefinition."<init>":(Ljava/lang/Class;)V
      34: invokeinterface #19,  3           // InterfaceMethod org/springframework/beans/factory/support/BeanDefinitionRegistry.registerBeanDefinition:(Ljava/lang/String;Lorg/springframework/beans/factory/config/BeanDefinition;)V
      39: goto          43
      42: astore_3
      43: return
    Exception table:
       from    to  target type
           0    39    42   Class org/springframework/beans/factory/NoSuchBeanDefinitionException

  private java.lang.Class<?> determineServletWebServerFactoryClass(org.springframework.context.ApplicationContext) throws org.springframework.beans.factory.NoSuchBeanDefinitionException;
    Code:
       0: aload_1
       1: ldc           #21                 // class org/springframework/boot/web/servlet/server/ServletWebServerFactory
       3: invokeinterface #22,  2           // InterfaceMethod org/springframework/context/ApplicationContext.getBean:(Ljava/lang/Class;)Ljava/lang/Object;
       8: checkcast     #21                 // class org/springframework/boot/web/servlet/server/ServletWebServerFactory
      11: invokevirtual #23                 // Method java/lang/Object.getClass:()Ljava/lang/Class;
      14: astore_2
      15: aload_0
      16: aload_2
      17: invokespecial #24                 // Method cannotBeInstantiated:(Ljava/lang/Class;)Z
      20: ifeq          58
      23: new           #25                 // class org/springframework/beans/FatalBeanException
      26: dup
      27: new           #26                 // class java/lang/StringBuilder
      30: dup
      31: invokespecial #27                 // Method java/lang/StringBuilder."<init>":()V
      34: ldc           #28                 // String ServletWebServerFactory implementation
      36: invokevirtual #29                 // Method java/lang/StringBuilder.append:(Ljava/lang/String;)Ljava/lang/StringBuilder;
      39: aload_2
      40: invokevirtual #30                 // Method java/lang/Class.getName:()Ljava/lang/String;
      43: invokevirtual #29                 // Method java/lang/StringBuilder.append:(Ljava/lang/String;)Ljava/lang/StringBuilder;
      46: ldc           #31                 // String  cannot be instantiated. To allow a separate management port to be used, a top-level class or static inner class should be used instead
      48: invokevirtual #29                 // Method java/lang/StringBuilder.append:(Ljava/lang/String;)Ljava/lang/StringBuilder;
      51: invokevirtual #32                 // Method java/lang/StringBuilder.toString:()Ljava/lang/String;
      54: invokespecial #33                 // Method org/springframework/beans/FatalBeanException."<init>":(Ljava/lang/String;)V
      57: athrow
      58: aload_2
      59: areturn

  private boolean cannotBeInstantiated(java.lang.Class<?>);
    Code:
       0: aload_1
       1: invokevirtual #34                 // Method java/lang/Class.isLocalClass:()Z
       4: ifne          31
       7: aload_1
       8: invokevirtual #35                 // Method java/lang/Class.isMemberClass:()Z
      11: ifeq          24
      14: aload_1
      15: invokevirtual #36                 // Method java/lang/Class.getModifiers:()I
      18: invokestatic  #37                 // Method java/lang/reflect/Modifier.isStatic:(I)Z
      21: ifeq          31
      24: aload_1
      25: invokevirtual #38                 // Method java/lang/Class.isAnonymousClass:()Z
      28: ifeq          35
      31: iconst_1
      32: goto          36
      35: iconst_0
      36: ireturn
}
