Compiled from "GroovyRootDocBuilder.java"
public class org.codehaus.groovy.tools.groovydoc.GroovyRootDocBuilder {
  private final org.codehaus.groovy.tools.shell.util.Logger log;

  private static final char FS;

  private java.util.List<org.codehaus.groovy.tools.groovydoc.LinkArgument> links;

  private final org.codehaus.groovy.tools.groovydoc.GroovyDocTool tool;

  private final java.lang.String[] sourcepaths;

  private final org.codehaus.groovy.tools.groovydoc.SimpleGroovyRootDoc rootDoc;

  private final java.util.Properties properties;

  public org.codehaus.groovy.tools.groovydoc.GroovyRootDocBuilder(org.codehaus.groovy.tools.groovydoc.GroovyDocTool, java.lang.String[], java.util.List<org.codehaus.groovy.tools.groovydoc.LinkArgument>, java.util.Properties);
    Code:
       0: aload_0
       1: invokespecial #31                 // Method java/lang/Object."<init>":()V
       4: aload_0
       5: ldc           #2                  // class org/codehaus/groovy/tools/groovydoc/GroovyRootDocBuilder
       7: invokestatic  #37                 // Method org/codehaus/groovy/tools/shell/util/Logger.create:(Ljava/lang/Class;)Lorg/codehaus/groovy/tools/shell/util/Logger;
      10: putfield      #39                 // Field log:Lorg/codehaus/groovy/tools/shell/util/Logger;
      13: aload_0
      14: aload_1
      15: putfield      #41                 // Field tool:Lorg/codehaus/groovy/tools/groovydoc/GroovyDocTool;
      18: aload_0
      19: aload_2
      20: putfield      #43                 // Field sourcepaths:[Ljava/lang/String;
      23: aload_0
      24: aload_3
      25: putfield      #45                 // Field links:Ljava/util/List;
      28: aload_0
      29: new           #47                 // class org/codehaus/groovy/tools/groovydoc/SimpleGroovyRootDoc
      32: dup
      33: ldc           #49                 // String root
      35: invokespecial #52                 // Method org/codehaus/groovy/tools/groovydoc/SimpleGroovyRootDoc."<init>":(Ljava/lang/String;)V
      38: putfield      #54                 // Field rootDoc:Lorg/codehaus/groovy/tools/groovydoc/SimpleGroovyRootDoc;
      41: aload_0
      42: aload         4
      44: putfield      #56                 // Field properties:Ljava/util/Properties;
      47: return

  public java.util.Map<java.lang.String, org.codehaus.groovy.groovydoc.GroovyClassDoc> getClassDocsFromSingleSource(java.lang.String, java.lang.String, java.lang.String) throws groovyjarjarantlr.RecognitionException, groovyjarjarantlr.TokenStreamException;
    Code:
       0: aload_2
       1: ldc           #66                 // String .java
       3: invokevirtual #72                 // Method java/lang/String.indexOf:(Ljava/lang/String;)I
       6: ifle          17
       9: aload_0
      10: aload_1
      11: aload_2
      12: aload_3
      13: invokespecial #75                 // Method parseJava:(Ljava/lang/String;Ljava/lang/String;Ljava/lang/String;)Ljava/util/Map;
      16: areturn
      17: aload_2
      18: ldc           #77                 // String .sourcefile
      20: invokevirtual #72                 // Method java/lang/String.indexOf:(Ljava/lang/String;)I
      23: ifle          34
      26: aload_0
      27: aload_1
      28: aload_2
      29: aload_3
      30: invokespecial #75                 // Method parseJava:(Ljava/lang/String;Ljava/lang/String;Ljava/lang/String;)Ljava/util/Map;
      33: areturn
      34: aload_0
      35: aload_1
      36: aload_2
      37: aload_3
      38: invokespecial #80                 // Method parseGroovy:(Ljava/lang/String;Ljava/lang/String;Ljava/lang/String;)Ljava/util/Map;
      41: areturn

  private java.util.Map<java.lang.String, org.codehaus.groovy.groovydoc.GroovyClassDoc> parseJava(java.lang.String, java.lang.String, java.lang.String) throws groovyjarjarantlr.RecognitionException, groovyjarjarantlr.TokenStreamException;
    Code:
       0: new           #88                 // class org/codehaus/groovy/antlr/SourceBuffer
       3: dup
       4: invokespecial #89                 // Method org/codehaus/groovy/antlr/SourceBuffer."<init>":()V
       7: astore        4
       9: aload_3
      10: aload         4
      12: invokestatic  #93                 // Method getJavaParser:(Ljava/lang/String;Lorg/codehaus/groovy/antlr/SourceBuffer;)Lorg/codehaus/groovy/antlr/java/JavaRecognizer;
      15: astore        5
      17: aload         5
      19: invokevirtual #99                 // Method org/codehaus/groovy/antlr/java/JavaRecognizer.getTokenNames:()[Ljava/lang/String;
      22: astore        6
      24: aload         5
      26: invokevirtual #102                // Method org/codehaus/groovy/antlr/java/JavaRecognizer.compilationUnit:()V
      29: goto          72
      32: astore        7
      34: aload_0
      35: getfield      #39                 // Field log:Lorg/codehaus/groovy/tools/shell/util/Logger;
      38: new           #105                // class java/lang/StringBuilder
      41: dup
      42: invokespecial #106                // Method java/lang/StringBuilder."<init>":()V
      45: ldc           #108                // String Out of memory while processing:
      47: invokevirtual #112                // Method java/lang/StringBuilder.append:(Ljava/lang/String;)Ljava/lang/StringBuilder;
      50: aload_1
      51: invokevirtual #112                // Method java/lang/StringBuilder.append:(Ljava/lang/String;)Ljava/lang/StringBuilder;
      54: ldc           #114                // String /
      56: invokevirtual #112                // Method java/lang/StringBuilder.append:(Ljava/lang/String;)Ljava/lang/StringBuilder;
      59: aload_2
      60: invokevirtual #112                // Method java/lang/StringBuilder.append:(Ljava/lang/String;)Ljava/lang/StringBuilder;
      63: invokevirtual #118                // Method java/lang/StringBuilder.toString:()Ljava/lang/String;
      66: invokevirtual #122                // Method org/codehaus/groovy/tools/shell/util/Logger.error:(Ljava/lang/Object;)V
      69: aload         7
      71: athrow
      72: aload         5
      74: invokevirtual #126                // Method org/codehaus/groovy/antlr/java/JavaRecognizer.getAST:()Lgroovyjarjarantlr/collections/AST;
      77: astore        7
      79: new           #128                // class org/codehaus/groovy/antlr/java/Java2GroovyConverter
      82: dup
      83: aload         6
      85: invokespecial #131                // Method org/codehaus/groovy/antlr/java/Java2GroovyConverter."<init>":([Ljava/lang/String;)V
      88: astore        8
      90: new           #133                // class org/codehaus/groovy/antlr/treewalker/PreOrderTraversal
      93: dup
      94: aload         8
      96: invokespecial #136                // Method org/codehaus/groovy/antlr/treewalker/PreOrderTraversal."<init>":(Lorg/codehaus/groovy/antlr/treewalker/Visitor;)V
      99: astore        9
     101: aload         9
     103: aload         7
     105: invokeinterface #142,  2          // InterfaceMethod org/codehaus/groovy/antlr/AntlrASTProcessor.process:(Lgroovyjarjarantlr/collections/AST;)Lgroovyjarjarantlr/collections/AST;
     110: pop
     111: new           #144                // class org/codehaus/groovy/antlr/java/Groovifier
     114: dup
     115: aload         6
     117: iconst_0
     118: invokespecial #147                // Method org/codehaus/groovy/antlr/java/Groovifier."<init>":([Ljava/lang/String;Z)V
     121: astore        10
     123: new           #133                // class org/codehaus/groovy/antlr/treewalker/PreOrderTraversal
     126: dup
     127: aload         10
     129: invokespecial #136                // Method org/codehaus/groovy/antlr/treewalker/PreOrderTraversal."<init>":(Lorg/codehaus/groovy/antlr/treewalker/Visitor;)V
     132: astore        11
     134: aload         11
     136: aload         7
     138: invokeinterface #142,  2          // InterfaceMethod org/codehaus/groovy/antlr/AntlrASTProcessor.process:(Lgroovyjarjarantlr/collections/AST;)Lgroovyjarjarantlr/collections/AST;
     143: pop
     144: new           #149                // class org/codehaus/groovy/tools/groovydoc/SimpleGroovyClassDocAssembler
     147: dup
     148: aload_1
     149: aload_2
     150: aload         4
     152: aload_0
     153: getfield      #45                 // Field links:Ljava/util/List;
     156: aload_0
     157: getfield      #56                 // Field properties:Ljava/util/Properties;
     160: iconst_0
     161: invokespecial #152                // Method org/codehaus/groovy/tools/groovydoc/SimpleGroovyClassDocAssembler."<init>":(Ljava/lang/String;Ljava/lang/String;Lorg/codehaus/groovy/antlr/SourceBuffer;Ljava/util/List;Ljava/util/Properties;Z)V
     164: astore        12
     166: new           #154                // class org/codehaus/groovy/antlr/treewalker/SourceCodeTraversal
     169: dup
     170: aload         12
     172: invokespecial #155                // Method org/codehaus/groovy/antlr/treewalker/SourceCodeTraversal."<init>":(Lorg/codehaus/groovy/antlr/treewalker/Visitor;)V
     175: astore        13
     177: aload         13
     179: aload         7
     181: invokeinterface #142,  2          // InterfaceMethod org/codehaus/groovy/antlr/AntlrASTProcessor.process:(Lgroovyjarjarantlr/collections/AST;)Lgroovyjarjarantlr/collections/AST;
     186: pop
     187: aload         12
     189: checkcast     #149                // class org/codehaus/groovy/tools/groovydoc/SimpleGroovyClassDocAssembler
     192: invokevirtual #159                // Method org/codehaus/groovy/tools/groovydoc/SimpleGroovyClassDocAssembler.getGroovyClassDocs:()Ljava/util/Map;
     195: areturn
    Exception table:
       from    to  target type
          24    29    32   Class java/lang/OutOfMemoryError

  private java.util.Map<java.lang.String, org.codehaus.groovy.groovydoc.GroovyClassDoc> parseGroovy(java.lang.String, java.lang.String, java.lang.String) throws groovyjarjarantlr.RecognitionException, groovyjarjarantlr.TokenStreamException;
    Code:
       0: new           #88                 // class org/codehaus/groovy/antlr/SourceBuffer
       3: dup
       4: invokespecial #89                 // Method org/codehaus/groovy/antlr/SourceBuffer."<init>":()V
       7: astore        4
       9: aload_3
      10: aload         4
      12: invokestatic  #180                // Method getGroovyParser:(Ljava/lang/String;Lorg/codehaus/groovy/antlr/SourceBuffer;)Lorg/codehaus/groovy/antlr/parser/GroovyRecognizer;
      15: astore        5
      17: aload         5
      19: invokevirtual #183                // Method org/codehaus/groovy/antlr/parser/GroovyRecognizer.compilationUnit:()V
      22: goto          65
      25: astore        6
      27: aload_0
      28: getfield      #39                 // Field log:Lorg/codehaus/groovy/tools/shell/util/Logger;
      31: new           #105                // class java/lang/StringBuilder
      34: dup
      35: invokespecial #106                // Method java/lang/StringBuilder."<init>":()V
      38: ldc           #108                // String Out of memory while processing:
      40: invokevirtual #112                // Method java/lang/StringBuilder.append:(Ljava/lang/String;)Ljava/lang/StringBuilder;
      43: aload_1
      44: invokevirtual #112                // Method java/lang/StringBuilder.append:(Ljava/lang/String;)Ljava/lang/StringBuilder;
      47: ldc           #114                // String /
      49: invokevirtual #112                // Method java/lang/StringBuilder.append:(Ljava/lang/String;)Ljava/lang/StringBuilder;
      52: aload_2
      53: invokevirtual #112                // Method java/lang/StringBuilder.append:(Ljava/lang/String;)Ljava/lang/StringBuilder;
      56: invokevirtual #118                // Method java/lang/StringBuilder.toString:()Ljava/lang/String;
      59: invokevirtual #122                // Method org/codehaus/groovy/tools/shell/util/Logger.error:(Ljava/lang/Object;)V
      62: aload         6
      64: athrow
      65: aload         5
      67: invokevirtual #184                // Method org/codehaus/groovy/antlr/parser/GroovyRecognizer.getAST:()Lgroovyjarjarantlr/collections/AST;
      70: astore        6
      72: new           #149                // class org/codehaus/groovy/tools/groovydoc/SimpleGroovyClassDocAssembler
      75: dup
      76: aload_1
      77: aload_2
      78: aload         4
      80: aload_0
      81: getfield      #45                 // Field links:Ljava/util/List;
      84: aload_0
      85: getfield      #56                 // Field properties:Ljava/util/Properties;
      88: iconst_1
      89: invokespecial #152                // Method org/codehaus/groovy/tools/groovydoc/SimpleGroovyClassDocAssembler."<init>":(Ljava/lang/String;Ljava/lang/String;Lorg/codehaus/groovy/antlr/SourceBuffer;Ljava/util/List;Ljava/util/Properties;Z)V
      92: astore        7
      94: new           #154                // class org/codehaus/groovy/antlr/treewalker/SourceCodeTraversal
      97: dup
      98: aload         7
     100: invokespecial #155                // Method org/codehaus/groovy/antlr/treewalker/SourceCodeTraversal."<init>":(Lorg/codehaus/groovy/antlr/treewalker/Visitor;)V
     103: astore        8
     105: aload         8
     107: aload         6
     109: invokeinterface #142,  2          // InterfaceMethod org/codehaus/groovy/antlr/AntlrASTProcessor.process:(Lgroovyjarjarantlr/collections/AST;)Lgroovyjarjarantlr/collections/AST;
     114: pop
     115: aload         7
     117: checkcast     #149                // class org/codehaus/groovy/tools/groovydoc/SimpleGroovyClassDocAssembler
     120: invokevirtual #159                // Method org/codehaus/groovy/tools/groovydoc/SimpleGroovyClassDocAssembler.getGroovyClassDocs:()Ljava/util/Map;
     123: areturn
    Exception table:
       from    to  target type
          17    22    25   Class java/lang/OutOfMemoryError

  private static org.codehaus.groovy.antlr.java.JavaRecognizer getJavaParser(java.lang.String, org.codehaus.groovy.antlr.SourceBuffer);
    Code:
       0: new           #187                // class org/codehaus/groovy/antlr/UnicodeEscapingReader
       3: dup
       4: new           #189                // class java/io/StringReader
       7: dup
       8: aload_0
       9: invokespecial #190                // Method java/io/StringReader."<init>":(Ljava/lang/String;)V
      12: aload_1
      13: invokespecial #193                // Method org/codehaus/groovy/antlr/UnicodeEscapingReader."<init>":(Ljava/io/Reader;Lorg/codehaus/groovy/antlr/SourceBuffer;)V
      16: astore_2
      17: new           #195                // class org/codehaus/groovy/antlr/java/JavaLexer
      20: dup
      21: aload_2
      22: invokespecial #198                // Method org/codehaus/groovy/antlr/java/JavaLexer."<init>":(Ljava/io/Reader;)V
      25: astore_3
      26: aload_2
      27: aload_3
      28: invokevirtual #202                // Method org/codehaus/groovy/antlr/UnicodeEscapingReader.setLexer:(Lgroovyjarjarantlr/CharScanner;)V
      31: aload_3
      32: invokestatic  #206                // Method org/codehaus/groovy/antlr/java/JavaRecognizer.make:(Lorg/codehaus/groovy/antlr/java/JavaLexer;)Lorg/codehaus/groovy/antlr/java/JavaRecognizer;
      35: astore        4
      37: aload         4
      39: aload_1
      40: invokevirtual #210                // Method org/codehaus/groovy/antlr/java/JavaRecognizer.setSourceBuffer:(Lorg/codehaus/groovy/antlr/SourceBuffer;)V
      43: aload         4
      45: areturn

  private static org.codehaus.groovy.antlr.parser.GroovyRecognizer getGroovyParser(java.lang.String, org.codehaus.groovy.antlr.SourceBuffer);
    Code:
       0: new           #187                // class org/codehaus/groovy/antlr/UnicodeEscapingReader
       3: dup
       4: new           #189                // class java/io/StringReader
       7: dup
       8: aload_0
       9: invokespecial #190                // Method java/io/StringReader."<init>":(Ljava/lang/String;)V
      12: aload_1
      13: invokespecial #193                // Method org/codehaus/groovy/antlr/UnicodeEscapingReader."<init>":(Ljava/io/Reader;Lorg/codehaus/groovy/antlr/SourceBuffer;)V
      16: astore_2
      17: new           #217                // class org/codehaus/groovy/antlr/parser/GroovyLexer
      20: dup
      21: aload_2
      22: invokespecial #218                // Method org/codehaus/groovy/antlr/parser/GroovyLexer."<init>":(Ljava/io/Reader;)V
      25: astore_3
      26: aload_2
      27: aload_3
      28: invokevirtual #202                // Method org/codehaus/groovy/antlr/UnicodeEscapingReader.setLexer:(Lgroovyjarjarantlr/CharScanner;)V
      31: aload_3
      32: invokestatic  #221                // Method org/codehaus/groovy/antlr/parser/GroovyRecognizer.make:(Lorg/codehaus/groovy/antlr/parser/GroovyLexer;)Lorg/codehaus/groovy/antlr/parser/GroovyRecognizer;
      35: astore        4
      37: aload         4
      39: aload_1
      40: invokevirtual #222                // Method org/codehaus/groovy/antlr/parser/GroovyRecognizer.setSourceBuffer:(Lorg/codehaus/groovy/antlr/SourceBuffer;)V
      43: aload         4
      45: areturn

  public void buildTree(java.util.List<java.lang.String>) throws java.io.IOException;
    Code:
       0: aload_0
       1: invokespecial #230                // Method setOverview:()V
       4: new           #232                // class java/util/ArrayList
       7: dup
       8: invokespecial #233                // Method java/util/ArrayList."<init>":()V
      11: astore_2
      12: aload_0
      13: getfield      #43                 // Field sourcepaths:[Ljava/lang/String;
      16: ifnull        69
      19: aload_0
      20: getfield      #43                 // Field sourcepaths:[Ljava/lang/String;
      23: astore_3
      24: aload_3
      25: arraylength
      26: istore        4
      28: iconst_0
      29: istore        5
      31: iload         5
      33: iload         4
      35: if_icmpge     69
      38: aload_3
      39: iload         5
      41: aaload
      42: astore        6
      44: aload_2
      45: new           #237                // class java/io/File
      48: dup
      49: aload         6
      51: invokespecial #238                // Method java/io/File."<init>":(Ljava/lang/String;)V
      54: invokevirtual #242                // Method java/io/File.getAbsoluteFile:()Ljava/io/File;
      57: invokeinterface #246,  2          // InterfaceMethod java/util/List.add:(Ljava/lang/Object;)Z
      62: pop
      63: iinc          5, 1
      66: goto          31
      69: aload_1
      70: invokeinterface #250,  1          // InterfaceMethod java/util/List.iterator:()Ljava/util/Iterator;
      75: astore_3
      76: aload_3
      77: invokeinterface #256,  1          // InterfaceMethod java/util/Iterator.hasNext:()Z
      82: ifeq          196
      85: aload_3
      86: invokeinterface #260,  1          // InterfaceMethod java/util/Iterator.next:()Ljava/lang/Object;
      91: checkcast     #68                 // class java/lang/String
      94: astore        4
      96: new           #237                // class java/io/File
      99: dup
     100: aload         4
     102: invokespecial #238                // Method java/io/File."<init>":(Ljava/lang/String;)V
     105: astore        5
     107: aload         5
     109: invokevirtual #263                // Method java/io/File.exists:()Z
     112: ifeq          127
     115: aload_0
     116: aload         4
     118: aload         5
     120: iconst_1
     121: invokespecial #267                // Method processFile:(Ljava/lang/String;Ljava/io/File;Z)V
     124: goto          76
     127: aload_2
     128: invokeinterface #250,  1          // InterfaceMethod java/util/List.iterator:()Ljava/util/Iterator;
     133: astore        6
     135: aload         6
     137: invokeinterface #256,  1          // InterfaceMethod java/util/Iterator.hasNext:()Z
     142: ifeq          193
     145: aload         6
     147: invokeinterface #260,  1          // InterfaceMethod java/util/Iterator.next:()Ljava/lang/Object;
     152: checkcast     #237                // class java/io/File
     155: astore        7
     157: new           #237                // class java/io/File
     160: dup
     161: aload         7
     163: aload         4
     165: invokespecial #270                // Method java/io/File."<init>":(Ljava/io/File;Ljava/lang/String;)V
     168: astore        5
     170: aload         5
     172: invokevirtual #263                // Method java/io/File.exists:()Z
     175: ifeq          190
     178: aload_0
     179: aload         4
     181: aload         5
     183: iconst_0
     184: invokespecial #267                // Method processFile:(Ljava/lang/String;Ljava/io/File;Z)V
     187: goto          193
     190: goto          135
     193: goto          76
     196: return

  private void setOverview();
    Code:
       0: aload_0
       1: getfield      #56                 // Field properties:Ljava/util/Properties;
       4: ldc_w         #281                // String overviewFile
       7: invokevirtual #287                // Method java/util/Properties.getProperty:(Ljava/lang/String;)Ljava/lang/String;
      10: astore_1
      11: aload_1
      12: ifnull        72
      15: aload_1
      16: invokevirtual #291                // Method java/lang/String.length:()I
      19: ifle          72
      22: new           #237                // class java/io/File
      25: dup
      26: aload_1
      27: invokespecial #238                // Method java/io/File."<init>":(Ljava/lang/String;)V
      30: invokestatic  #297                // Method org/codehaus/groovy/runtime/ResourceGroovyMethods.getText:(Ljava/io/File;)Ljava/lang/String;
      33: astore_2
      34: aload_0
      35: aload_2
      36: invokespecial #300                // Method calcThenSetOverviewDescription:(Ljava/lang/String;)V
      39: goto          72
      42: astore_2
      43: getstatic     #306                // Field java/lang/System.err:Ljava/io/PrintStream;
      46: new           #105                // class java/lang/StringBuilder
      49: dup
      50: invokespecial #106                // Method java/lang/StringBuilder."<init>":()V
      53: ldc_w         #308                // String Unable to load overview file:
      56: invokevirtual #112                // Method java/lang/StringBuilder.append:(Ljava/lang/String;)Ljava/lang/StringBuilder;
      59: aload_2
      60: invokevirtual #311                // Method java/io/IOException.getMessage:()Ljava/lang/String;
      63: invokevirtual #112                // Method java/lang/StringBuilder.append:(Ljava/lang/String;)Ljava/lang/StringBuilder;
      66: invokevirtual #118                // Method java/lang/StringBuilder.toString:()Ljava/lang/String;
      69: invokevirtual #316                // Method java/io/PrintStream.println:(Ljava/lang/String;)V
      72: return
    Exception table:
       from    to  target type
          22    39    42   Class java/io/IOException

  private void processFile(java.lang.String, java.io.File, boolean) throws java.io.IOException;
    Code:
       0: aload_2
       1: invokestatic  #297                // Method org/codehaus/groovy/runtime/ResourceGroovyMethods.getText:(Ljava/io/File;)Ljava/lang/String;
       4: astore        4
       6: aload_0
       7: getfield      #41                 // Field tool:Lorg/codehaus/groovy/tools/groovydoc/GroovyDocTool;
      10: pop
      11: aload_1
      12: invokestatic  #324                // Method org/codehaus/groovy/tools/groovydoc/GroovyDocTool.getPath:(Ljava/lang/String;)Ljava/lang/String;
      15: bipush        92
      17: bipush        47
      19: invokevirtual #328                // Method java/lang/String.replace:(CC)Ljava/lang/String;
      22: astore        5
      24: iload_3
      25: ifeq          34
      28: ldc_w         #330                // String DefaultPackage
      31: goto          36
      34: aload         5
      36: astore        6
      38: aload_0
      39: getfield      #41                 // Field tool:Lorg/codehaus/groovy/tools/groovydoc/GroovyDocTool;
      42: pop
      43: aload_1
      44: invokestatic  #333                // Method org/codehaus/groovy/tools/groovydoc/GroovyDocTool.getFile:(Ljava/lang/String;)Ljava/lang/String;
      47: astore        7
      49: aconst_null
      50: astore        8
      52: iload_3
      53: ifne          70
      56: aload_0
      57: getfield      #54                 // Field rootDoc:Lorg/codehaus/groovy/tools/groovydoc/SimpleGroovyRootDoc;
      60: aload         6
      62: invokevirtual #337                // Method org/codehaus/groovy/tools/groovydoc/SimpleGroovyRootDoc.packageNamed:(Ljava/lang/String;)Lorg/codehaus/groovy/groovydoc/GroovyPackageDoc;
      65: checkcast     #339                // class org/codehaus/groovy/tools/groovydoc/SimpleGroovyPackageDoc
      68: astore        8
      70: aload_1
      71: ldc_w         #341                // String package.html
      74: invokevirtual #345                // Method java/lang/String.endsWith:(Ljava/lang/String;)Z
      77: ifne          100
      80: aload_1
      81: ldc_w         #347                // String package-info.java
      84: invokevirtual #345                // Method java/lang/String.endsWith:(Ljava/lang/String;)Z
      87: ifne          100
      90: aload_1
      91: ldc_w         #349                // String package-info.groovy
      94: invokevirtual #345                // Method java/lang/String.endsWith:(Ljava/lang/String;)Z
      97: ifeq          141
     100: aload         8
     102: ifnonnull     120
     105: new           #339                // class org/codehaus/groovy/tools/groovydoc/SimpleGroovyPackageDoc
     108: dup
     109: aload         5
     111: invokespecial #350                // Method org/codehaus/groovy/tools/groovydoc/SimpleGroovyPackageDoc."<init>":(Ljava/lang/String;)V
     114: astore        8
     116: aload         5
     118: astore        6
     120: aload_0
     121: aload         4
     123: aload_1
     124: aload         8
     126: invokevirtual #354                // Method processPackageInfo:(Ljava/lang/String;Ljava/lang/String;Lorg/codehaus/groovy/tools/groovydoc/SimpleGroovyPackageDoc;)V
     129: aload_0
     130: getfield      #54                 // Field rootDoc:Lorg/codehaus/groovy/tools/groovydoc/SimpleGroovyRootDoc;
     133: aload         6
     135: aload         8
     137: invokevirtual #358                // Method org/codehaus/groovy/tools/groovydoc/SimpleGroovyRootDoc.put:(Ljava/lang/String;Lorg/codehaus/groovy/groovydoc/GroovyPackageDoc;)V
     140: return
     141: aload_0
     142: aload         6
     144: aload         7
     146: aload         4
     148: invokevirtual #360                // Method getClassDocsFromSingleSource:(Ljava/lang/String;Ljava/lang/String;Ljava/lang/String;)Ljava/util/Map;
     151: astore        9
     153: aload_0
     154: getfield      #54                 // Field rootDoc:Lorg/codehaus/groovy/tools/groovydoc/SimpleGroovyRootDoc;
     157: aload         9
     159: invokevirtual #364                // Method org/codehaus/groovy/tools/groovydoc/SimpleGroovyRootDoc.putAllClasses:(Ljava/util/Map;)V
     162: iload_3
     163: ifeq          257
     166: aload         9
     168: invokeinterface #368,  1          // InterfaceMethod java/util/Map.entrySet:()Ljava/util/Set;
     173: invokeinterface #371,  1          // InterfaceMethod java/util/Set.iterator:()Ljava/util/Iterator;
     178: astore        10
     180: aload         10
     182: invokeinterface #256,  1          // InterfaceMethod java/util/Iterator.hasNext:()Z
     187: ifeq          257
     190: aload         10
     192: invokeinterface #260,  1          // InterfaceMethod java/util/Iterator.next:()Ljava/lang/Object;
     197: checkcast     #7                  // class java/util/Map$Entry
     200: astore        11
     202: aload         11
     204: invokeinterface #374,  1          // InterfaceMethod java/util/Map$Entry.getValue:()Ljava/lang/Object;
     209: checkcast     #376                // class org/codehaus/groovy/groovydoc/GroovyClassDoc
     212: invokeinterface #379,  1          // InterfaceMethod org/codehaus/groovy/groovydoc/GroovyClassDoc.getFullPathName:()Ljava/lang/String;
     217: astore        12
     219: aload         12
     221: bipush        47
     223: invokevirtual #383                // Method java/lang/String.lastIndexOf:(I)I
     226: istore        13
     228: iload         13
     230: ifle          243
     233: aload         12
     235: iconst_0
     236: iload         13
     238: invokevirtual #387                // Method java/lang/String.substring:(II)Ljava/lang/String;
     241: astore        6
     243: aload_0
     244: getfield      #54                 // Field rootDoc:Lorg/codehaus/groovy/tools/groovydoc/SimpleGroovyRootDoc;
     247: aload         6
     249: invokevirtual #337                // Method org/codehaus/groovy/tools/groovydoc/SimpleGroovyRootDoc.packageNamed:(Ljava/lang/String;)Lorg/codehaus/groovy/groovydoc/GroovyPackageDoc;
     252: checkcast     #339                // class org/codehaus/groovy/tools/groovydoc/SimpleGroovyPackageDoc
     255: astore        8
     257: aload         8
     259: ifnonnull     273
     262: new           #339                // class org/codehaus/groovy/tools/groovydoc/SimpleGroovyPackageDoc
     265: dup
     266: aload         6
     268: invokespecial #350                // Method org/codehaus/groovy/tools/groovydoc/SimpleGroovyPackageDoc."<init>":(Ljava/lang/String;)V
     271: astore        8
     273: aload         8
     275: aload         9
     277: invokevirtual #390                // Method org/codehaus/groovy/tools/groovydoc/SimpleGroovyPackageDoc.putAll:(Ljava/util/Map;)V
     280: aload_0
     281: getfield      #54                 // Field rootDoc:Lorg/codehaus/groovy/tools/groovydoc/SimpleGroovyRootDoc;
     284: aload         6
     286: aload         8
     288: invokevirtual #358                // Method org/codehaus/groovy/tools/groovydoc/SimpleGroovyRootDoc.put:(Ljava/lang/String;Lorg/codehaus/groovy/groovydoc/GroovyPackageDoc;)V
     291: goto          493
     294: astore        9
     296: aload_0
     297: getfield      #39                 // Field log:Lorg/codehaus/groovy/tools/shell/util/Logger;
     300: new           #105                // class java/lang/StringBuilder
     303: dup
     304: invokespecial #106                // Method java/lang/StringBuilder."<init>":()V
     307: ldc_w         #392                // String ignored due to RecognitionException:
     310: invokevirtual #112                // Method java/lang/StringBuilder.append:(Ljava/lang/String;)Ljava/lang/StringBuilder;
     313: aload_1
     314: invokevirtual #112                // Method java/lang/StringBuilder.append:(Ljava/lang/String;)Ljava/lang/StringBuilder;
     317: ldc_w         #394                // String  [
     320: invokevirtual #112                // Method java/lang/StringBuilder.append:(Ljava/lang/String;)Ljava/lang/StringBuilder;
     323: aload         9
     325: invokevirtual #395                // Method groovyjarjarantlr/RecognitionException.getMessage:()Ljava/lang/String;
     328: invokevirtual #112                // Method java/lang/StringBuilder.append:(Ljava/lang/String;)Ljava/lang/StringBuilder;
     331: ldc_w         #397                // String ]
     334: invokevirtual #112                // Method java/lang/StringBuilder.append:(Ljava/lang/String;)Ljava/lang/StringBuilder;
     337: invokevirtual #118                // Method java/lang/StringBuilder.toString:()Ljava/lang/String;
     340: invokevirtual #122                // Method org/codehaus/groovy/tools/shell/util/Logger.error:(Ljava/lang/Object;)V
     343: aload_0
     344: getfield      #39                 // Field log:Lorg/codehaus/groovy/tools/shell/util/Logger;
     347: new           #105                // class java/lang/StringBuilder
     350: dup
     351: invokespecial #106                // Method java/lang/StringBuilder."<init>":()V
     354: ldc_w         #392                // String ignored due to RecognitionException:
     357: invokevirtual #112                // Method java/lang/StringBuilder.append:(Ljava/lang/String;)Ljava/lang/StringBuilder;
     360: aload_1
     361: invokevirtual #112                // Method java/lang/StringBuilder.append:(Ljava/lang/String;)Ljava/lang/StringBuilder;
     364: ldc_w         #394                // String  [
     367: invokevirtual #112                // Method java/lang/StringBuilder.append:(Ljava/lang/String;)Ljava/lang/StringBuilder;
     370: aload         9
     372: invokevirtual #395                // Method groovyjarjarantlr/RecognitionException.getMessage:()Ljava/lang/String;
     375: invokevirtual #112                // Method java/lang/StringBuilder.append:(Ljava/lang/String;)Ljava/lang/StringBuilder;
     378: ldc_w         #397                // String ]
     381: invokevirtual #112                // Method java/lang/StringBuilder.append:(Ljava/lang/String;)Ljava/lang/StringBuilder;
     384: invokevirtual #118                // Method java/lang/StringBuilder.toString:()Ljava/lang/String;
     387: aload         9
     389: invokevirtual #401                // Method org/codehaus/groovy/tools/shell/util/Logger.debug:(Ljava/lang/Object;Ljava/lang/Throwable;)V
     392: goto          493
     395: astore        9
     397: aload_0
     398: getfield      #39                 // Field log:Lorg/codehaus/groovy/tools/shell/util/Logger;
     401: new           #105                // class java/lang/StringBuilder
     404: dup
     405: invokespecial #106                // Method java/lang/StringBuilder."<init>":()V
     408: ldc_w         #403                // String ignored due to TokenStreamException:
     411: invokevirtual #112                // Method java/lang/StringBuilder.append:(Ljava/lang/String;)Ljava/lang/StringBuilder;
     414: aload_1
     415: invokevirtual #112                // Method java/lang/StringBuilder.append:(Ljava/lang/String;)Ljava/lang/StringBuilder;
     418: ldc_w         #394                // String  [
     421: invokevirtual #112                // Method java/lang/StringBuilder.append:(Ljava/lang/String;)Ljava/lang/StringBuilder;
     424: aload         9
     426: invokevirtual #404                // Method groovyjarjarantlr/TokenStreamException.getMessage:()Ljava/lang/String;
     429: invokevirtual #112                // Method java/lang/StringBuilder.append:(Ljava/lang/String;)Ljava/lang/StringBuilder;
     432: ldc_w         #397                // String ]
     435: invokevirtual #112                // Method java/lang/StringBuilder.append:(Ljava/lang/String;)Ljava/lang/StringBuilder;
     438: invokevirtual #118                // Method java/lang/StringBuilder.toString:()Ljava/lang/String;
     441: invokevirtual #122                // Method org/codehaus/groovy/tools/shell/util/Logger.error:(Ljava/lang/Object;)V
     444: aload_0
     445: getfield      #39                 // Field log:Lorg/codehaus/groovy/tools/shell/util/Logger;
     448: new           #105                // class java/lang/StringBuilder
     451: dup
     452: invokespecial #106                // Method java/lang/StringBuilder."<init>":()V
     455: ldc_w         #403                // String ignored due to TokenStreamException:
     458: invokevirtual #112                // Method java/lang/StringBuilder.append:(Ljava/lang/String;)Ljava/lang/StringBuilder;
     461: aload_1
     462: invokevirtual #112                // Method java/lang/StringBuilder.append:(Ljava/lang/String;)Ljava/lang/StringBuilder;
     465: ldc_w         #394                // String  [
     468: invokevirtual #112                // Method java/lang/StringBuilder.append:(Ljava/lang/String;)Ljava/lang/StringBuilder;
     471: aload         9
     473: invokevirtual #404                // Method groovyjarjarantlr/TokenStreamException.getMessage:()Ljava/lang/String;
     476: invokevirtual #112                // Method java/lang/StringBuilder.append:(Ljava/lang/String;)Ljava/lang/StringBuilder;
     479: ldc_w         #397                // String ]
     482: invokevirtual #112                // Method java/lang/StringBuilder.append:(Ljava/lang/String;)Ljava/lang/StringBuilder;
     485: invokevirtual #118                // Method java/lang/StringBuilder.toString:()Ljava/lang/String;
     488: aload         9
     490: invokevirtual #401                // Method org/codehaus/groovy/tools/shell/util/Logger.debug:(Ljava/lang/Object;Ljava/lang/Throwable;)V
     493: return
    Exception table:
       from    to  target type
         141   291   294   Class groovyjarjarantlr/RecognitionException
         141   291   395   Class groovyjarjarantlr/TokenStreamException

  void processPackageInfo(java.lang.String, java.lang.String, org.codehaus.groovy.tools.groovydoc.SimpleGroovyPackageDoc);
    Code:
       0: aload_3
       1: invokevirtual #425                // Method org/codehaus/groovy/tools/groovydoc/SimpleGroovyPackageDoc.getRelativeRootPath:()Ljava/lang/String;
       4: astore        4
       6: aload_0
       7: aload_1
       8: aload_2
       9: aload         4
      11: invokespecial #429                // Method calcThenSetPackageDescription:(Ljava/lang/String;Ljava/lang/String;Ljava/lang/String;)Ljava/lang/String;
      14: astore        5
      16: aload_3
      17: aload         5
      19: invokevirtual #432                // Method org/codehaus/groovy/tools/groovydoc/SimpleGroovyPackageDoc.setDescription:(Ljava/lang/String;)V
      22: aload_0
      23: aload_1
      24: aload_2
      25: ldc_w         #434                // String
      28: invokespecial #429                // Method calcThenSetPackageDescription:(Ljava/lang/String;Ljava/lang/String;Ljava/lang/String;)Ljava/lang/String;
      31: astore        6
      33: aload         6
      35: aload_3
      36: invokestatic  #438                // Method calcThenSetSummary:(Ljava/lang/String;Lorg/codehaus/groovy/tools/groovydoc/SimpleGroovyPackageDoc;)V
      39: return

  private java.lang.String calcThenSetPackageDescription(java.lang.String, java.lang.String, java.lang.String);
    Code:
       0: aload_2
       1: ldc_w         #443                // String .html
       4: invokevirtual #345                // Method java/lang/String.endsWith:(Ljava/lang/String;)Z
       7: ifeq          39
      10: aload_1
      11: invokestatic  #446                // Method scrubOffExcessiveTags:(Ljava/lang/String;)Ljava/lang/String;
      14: astore        4
      16: aload         4
      18: ldc_w         #448                // String p
      21: invokestatic  #452                // Method pruneTagFromFront:(Ljava/lang/String;Ljava/lang/String;)Ljava/lang/String;
      24: astore        4
      26: aload         4
      28: ldc_w         #454                // String /p
      31: invokestatic  #457                // Method pruneTagFromEnd:(Ljava/lang/String;Ljava/lang/String;)Ljava/lang/String;
      34: astore        4
      36: goto          45
      39: aload_1
      40: invokestatic  #460                // Method trimPackageAndComments:(Ljava/lang/String;)Ljava/lang/String;
      43: astore        4
      45: aload_0
      46: aload         4
      48: aload_3
      49: invokespecial #463                // Method replaceTags:(Ljava/lang/String;Ljava/lang/String;)Ljava/lang/String;
      52: astore        4
      54: aload         4
      56: areturn

  private java.lang.String replaceTags(java.lang.String, java.lang.String);
    Code:
       0: aload_1
       1: ldc_w         #465                // String (?m)^\\s*\\*
       4: ldc_w         #434                // String
       7: invokevirtual #468                // Method java/lang/String.replaceAll:(Ljava/lang/String;Ljava/lang/String;)Ljava/lang/String;
      10: astore_3
      11: aload_0
      12: aload_3
      13: ldc_w         #434                // String
      16: ldc_w         #434                // String
      19: getstatic     #474                // Field org/codehaus/groovy/tools/groovydoc/SimpleGroovyClassDoc.LINK_REGEX:Ljava/util/regex/Pattern;
      22: aload_2
      23: invokespecial #478                // Method replaceAllTags:(Ljava/lang/String;Ljava/lang/String;Ljava/lang/String;Ljava/util/regex/Pattern;Ljava/lang/String;)Ljava/lang/String;
      26: astore_3
      27: aload_0
      28: aload_3
      29: ldc_w         #480                // String <TT>
      32: ldc_w         #482                // String </TT>
      35: getstatic     #485                // Field org/codehaus/groovy/tools/groovydoc/SimpleGroovyClassDoc.CODE_REGEX:Ljava/util/regex/Pattern;
      38: aload_2
      39: invokespecial #478                // Method replaceAllTags:(Ljava/lang/String;Ljava/lang/String;Ljava/lang/String;Ljava/util/regex/Pattern;Ljava/lang/String;)Ljava/lang/String;
      42: astore_3
      43: aload_0
      44: new           #105                // class java/lang/StringBuilder
      47: dup
      48: invokespecial #106                // Method java/lang/StringBuilder."<init>":()V
      51: aload_3
      52: invokevirtual #112                // Method java/lang/StringBuilder.append:(Ljava/lang/String;)Ljava/lang/StringBuilder;
      55: ldc_w         #487                // String @endMarker
      58: invokevirtual #112                // Method java/lang/StringBuilder.append:(Ljava/lang/String;)Ljava/lang/StringBuilder;
      61: invokevirtual #118                // Method java/lang/StringBuilder.toString:()Ljava/lang/String;
      64: ldc_w         #489                // String <DL><DT><B>$1:</B></DT><DD>
      67: ldc_w         #491                // String </DD></DL>
      70: getstatic     #494                // Field org/codehaus/groovy/tools/groovydoc/SimpleGroovyClassDoc.TAG_REGEX:Ljava/util/regex/Pattern;
      73: aload_2
      74: invokespecial #478                // Method replaceAllTags:(Ljava/lang/String;Ljava/lang/String;Ljava/lang/String;Ljava/util/regex/Pattern;Ljava/lang/String;)Ljava/lang/String;
      77: astore_3
      78: aload_3
      79: iconst_0
      80: aload_3
      81: invokevirtual #291                // Method java/lang/String.length:()I
      84: bipush        10
      86: isub
      87: invokevirtual #387                // Method java/lang/String.substring:(II)Ljava/lang/String;
      90: astore_3
      91: aload_3
      92: invokestatic  #497                // Method org/codehaus/groovy/tools/groovydoc/SimpleGroovyClassDoc.decodeSpecialSymbols:(Ljava/lang/String;)Ljava/lang/String;
      95: areturn

  private java.lang.String replaceAllTags(java.lang.String, java.lang.String, java.lang.String, java.util.regex.Pattern, java.lang.String);
    Code:
       0: aload_1
       1: aload_2
       2: aload_3
       3: aload         4
       5: aload_0
       6: getfield      #45                 // Field links:Ljava/util/List;
       9: aload         5
      11: aload_0
      12: getfield      #54                 // Field rootDoc:Lorg/codehaus/groovy/tools/groovydoc/SimpleGroovyRootDoc;
      15: aconst_null
      16: invokestatic  #502                // Method org/codehaus/groovy/tools/groovydoc/SimpleGroovyClassDoc.replaceAllTags:(Ljava/lang/String;Ljava/lang/String;Ljava/lang/String;Ljava/util/regex/Pattern;Ljava/util/List;Ljava/lang/String;Lorg/codehaus/groovy/groovydoc/GroovyRootDoc;Lorg/codehaus/groovy/tools/groovydoc/SimpleGroovyClassDoc;)Ljava/lang/String;
      19: areturn

  private static void calcThenSetSummary(java.lang.String, org.codehaus.groovy.tools.groovydoc.SimpleGroovyPackageDoc);
    Code:
       0: aload_1
       1: aload_0
       2: invokestatic  #511                // Method org/codehaus/groovy/tools/groovydoc/SimpleGroovyDoc.calculateFirstSentence:(Ljava/lang/String;)Ljava/lang/String;
       5: invokevirtual #514                // Method org/codehaus/groovy/tools/groovydoc/SimpleGroovyPackageDoc.setSummary:(Ljava/lang/String;)V
       8: return

  private void calcThenSetOverviewDescription(java.lang.String);
    Code:
       0: aload_1
       1: invokestatic  #446                // Method scrubOffExcessiveTags:(Ljava/lang/String;)Ljava/lang/String;
       4: astore_2
       5: aload_0
       6: getfield      #54                 // Field rootDoc:Lorg/codehaus/groovy/tools/groovydoc/SimpleGroovyRootDoc;
       9: aload_2
      10: invokevirtual #515                // Method org/codehaus/groovy/tools/groovydoc/SimpleGroovyRootDoc.setDescription:(Ljava/lang/String;)V
      13: return

  private static java.lang.String trimPackageAndComments(java.lang.String);
    Code:
       0: aload_0
       1: ldc_w         #517                // String (?sm)^package.*
       4: ldc_w         #434                // String
       7: invokevirtual #520                // Method java/lang/String.replaceFirst:(Ljava/lang/String;Ljava/lang/String;)Ljava/lang/String;
      10: ldc_w         #522                // String (?sm)/.*\\*\\*(.*)\\*/
      13: ldc_w         #524                // String $1
      16: invokevirtual #520                // Method java/lang/String.replaceFirst:(Ljava/lang/String;Ljava/lang/String;)Ljava/lang/String;
      19: ldc_w         #465                // String (?m)^\\s*\\*
      22: ldc_w         #434                // String
      25: invokevirtual #468                // Method java/lang/String.replaceAll:(Ljava/lang/String;Ljava/lang/String;)Ljava/lang/String;
      28: areturn

  private static java.lang.String scrubOffExcessiveTags(java.lang.String);
    Code:
       0: aload_0
       1: ldc_w         #526                // String html
       4: invokestatic  #452                // Method pruneTagFromFront:(Ljava/lang/String;Ljava/lang/String;)Ljava/lang/String;
       7: astore_1
       8: aload_1
       9: ldc_w         #528                // String /head
      12: invokestatic  #452                // Method pruneTagFromFront:(Ljava/lang/String;Ljava/lang/String;)Ljava/lang/String;
      15: astore_1
      16: aload_1
      17: ldc_w         #530                // String body
      20: invokestatic  #452                // Method pruneTagFromFront:(Ljava/lang/String;Ljava/lang/String;)Ljava/lang/String;
      23: astore_1
      24: aload_1
      25: ldc_w         #532                // String /html
      28: invokestatic  #457                // Method pruneTagFromEnd:(Ljava/lang/String;Ljava/lang/String;)Ljava/lang/String;
      31: astore_1
      32: aload_1
      33: ldc_w         #534                // String /body
      36: invokestatic  #457                // Method pruneTagFromEnd:(Ljava/lang/String;Ljava/lang/String;)Ljava/lang/String;
      39: areturn

  private static java.lang.String pruneTagFromFront(java.lang.String, java.lang.String);
    Code:
       0: aload_0
       1: aload_1
       2: invokevirtual #537                // Method java/lang/String.toLowerCase:()Ljava/lang/String;
       5: invokestatic  #541                // Method indexOfTag:(Ljava/lang/String;Ljava/lang/String;)I
       8: aload_0
       9: aload_1
      10: invokevirtual #544                // Method java/lang/String.toUpperCase:()Ljava/lang/String;
      13: invokestatic  #541                // Method indexOfTag:(Ljava/lang/String;Ljava/lang/String;)I
      16: invokestatic  #550                // Method java/lang/Math.max:(II)I
      19: istore_2
      20: iload_2
      21: ifge          26
      24: aload_0
      25: areturn
      26: aload_0
      27: iload_2
      28: invokevirtual #553                // Method java/lang/String.substring:(I)Ljava/lang/String;
      31: areturn

  private static java.lang.String pruneTagFromEnd(java.lang.String, java.lang.String);
    Code:
       0: aload_0
       1: new           #105                // class java/lang/StringBuilder
       4: dup
       5: invokespecial #106                // Method java/lang/StringBuilder."<init>":()V
       8: ldc_w         #557                // String <
      11: invokevirtual #112                // Method java/lang/StringBuilder.append:(Ljava/lang/String;)Ljava/lang/StringBuilder;
      14: aload_1
      15: invokevirtual #537                // Method java/lang/String.toLowerCase:()Ljava/lang/String;
      18: invokevirtual #112                // Method java/lang/StringBuilder.append:(Ljava/lang/String;)Ljava/lang/StringBuilder;
      21: ldc_w         #559                // String >
      24: invokevirtual #112                // Method java/lang/StringBuilder.append:(Ljava/lang/String;)Ljava/lang/StringBuilder;
      27: invokevirtual #118                // Method java/lang/StringBuilder.toString:()Ljava/lang/String;
      30: invokevirtual #561                // Method java/lang/String.lastIndexOf:(Ljava/lang/String;)I
      33: aload_0
      34: new           #105                // class java/lang/StringBuilder
      37: dup
      38: invokespecial #106                // Method java/lang/StringBuilder."<init>":()V
      41: ldc_w         #557                // String <
      44: invokevirtual #112                // Method java/lang/StringBuilder.append:(Ljava/lang/String;)Ljava/lang/StringBuilder;
      47: aload_1
      48: invokevirtual #544                // Method java/lang/String.toUpperCase:()Ljava/lang/String;
      51: invokevirtual #112                // Method java/lang/StringBuilder.append:(Ljava/lang/String;)Ljava/lang/StringBuilder;
      54: ldc_w         #559                // String >
      57: invokevirtual #112                // Method java/lang/StringBuilder.append:(Ljava/lang/String;)Ljava/lang/StringBuilder;
      60: invokevirtual #118                // Method java/lang/StringBuilder.toString:()Ljava/lang/String;
      63: invokevirtual #561                // Method java/lang/String.lastIndexOf:(Ljava/lang/String;)I
      66: invokestatic  #550                // Method java/lang/Math.max:(II)I
      69: istore_2
      70: iload_2
      71: ifge          76
      74: aload_0
      75: areturn
      76: aload_0
      77: iconst_0
      78: iload_2
      79: invokevirtual #387                // Method java/lang/String.substring:(II)Ljava/lang/String;
      82: areturn

  private static int indexOfTag(java.lang.String, java.lang.String);
    Code:
       0: aload_0
       1: new           #105                // class java/lang/StringBuilder
       4: dup
       5: invokespecial #106                // Method java/lang/StringBuilder."<init>":()V
       8: ldc_w         #557                // String <
      11: invokevirtual #112                // Method java/lang/StringBuilder.append:(Ljava/lang/String;)Ljava/lang/StringBuilder;
      14: aload_1
      15: invokevirtual #112                // Method java/lang/StringBuilder.append:(Ljava/lang/String;)Ljava/lang/StringBuilder;
      18: ldc_w         #559                // String >
      21: invokevirtual #112                // Method java/lang/StringBuilder.append:(Ljava/lang/String;)Ljava/lang/StringBuilder;
      24: invokevirtual #118                // Method java/lang/StringBuilder.toString:()Ljava/lang/String;
      27: invokevirtual #72                 // Method java/lang/String.indexOf:(Ljava/lang/String;)I
      30: istore_2
      31: iload_2
      32: ifle          44
      35: iload_2
      36: aload_1
      37: invokevirtual #291                // Method java/lang/String.length:()I
      40: iconst_2
      41: iadd
      42: iadd
      43: istore_2
      44: iload_2
      45: ireturn

  public org.codehaus.groovy.groovydoc.GroovyRootDoc getRootDoc();
    Code:
       0: aload_0
       1: getfield      #54                 // Field rootDoc:Lorg/codehaus/groovy/tools/groovydoc/SimpleGroovyRootDoc;
       4: invokevirtual #568                // Method org/codehaus/groovy/tools/groovydoc/SimpleGroovyRootDoc.resolve:()V
       7: aload_0
       8: getfield      #54                 // Field rootDoc:Lorg/codehaus/groovy/tools/groovydoc/SimpleGroovyRootDoc;
      11: areturn
}
