Compiled from "SimpleGroovyClassDocAssembler.java"
public class org.codehaus.groovy.tools.groovydoc.SimpleGroovyClassDocAssembler extends org.codehaus.groovy.antlr.treewalker.VisitorAdapter implements org.codehaus.groovy.antlr.parser.GroovyTokenTypes {
  private static final java.lang.String FS;

  private static final java.util.regex.Pattern PREV_JAVADOC_COMMENT_PATTERN;

  private final java.util.Stack<org.codehaus.groovy.antlr.GroovySourceAST> stack;

  private java.util.Map<java.lang.String, org.codehaus.groovy.groovydoc.GroovyClassDoc> classDocs;

  private java.util.List<java.lang.String> importedClassesAndPackages;

  private java.util.Map<java.lang.String, java.lang.String> aliases;

  private java.util.List<org.codehaus.groovy.tools.groovydoc.LinkArgument> links;

  private java.util.Properties properties;

  private org.codehaus.groovy.tools.groovydoc.SimpleGroovyFieldDoc currentFieldDoc;

  private org.codehaus.groovy.antlr.SourceBuffer sourceBuffer;

  private java.lang.String packagePath;

  private org.codehaus.groovy.antlr.LineColumn lastLineCol;

  private boolean insideEnum;

  private java.util.Map<java.lang.String, org.codehaus.groovy.tools.groovydoc.SimpleGroovyClassDoc> foundClasses;

  private boolean isGroovy;

  private boolean deferSetup;

  private java.lang.String className;

  public org.codehaus.groovy.tools.groovydoc.SimpleGroovyClassDocAssembler(java.lang.String, java.lang.String, org.codehaus.groovy.antlr.SourceBuffer, java.util.List<org.codehaus.groovy.tools.groovydoc.LinkArgument>, java.util.Properties, boolean);
    Code:
       0: aload_0
       1: invokespecial #47                 // Method org/codehaus/groovy/antlr/treewalker/VisitorAdapter."<init>":()V
       4: aload_0
       5: aload_3
       6: putfield      #49                 // Field sourceBuffer:Lorg/codehaus/groovy/antlr/SourceBuffer;
       9: aload_0
      10: aload_1
      11: putfield      #51                 // Field packagePath:Ljava/lang/String;
      14: aload_0
      15: aload         4
      17: putfield      #53                 // Field links:Ljava/util/List;
      20: aload_0
      21: aload         5
      23: putfield      #55                 // Field properties:Ljava/util/Properties;
      26: aload_0
      27: iload         6
      29: putfield      #57                 // Field isGroovy:Z
      32: aload_0
      33: new           #59                 // class java/util/Stack
      36: dup
      37: invokespecial #60                 // Method java/util/Stack."<init>":()V
      40: putfield      #62                 // Field stack:Ljava/util/Stack;
      43: aload_0
      44: aload_2
      45: putfield      #64                 // Field className:Ljava/lang/String;
      48: aload_0
      49: new           #66                 // class java/util/LinkedHashMap
      52: dup
      53: invokespecial #67                 // Method java/util/LinkedHashMap."<init>":()V
      56: putfield      #69                 // Field classDocs:Ljava/util/Map;
      59: aload_2
      60: ifnull        82
      63: aload_2
      64: ldc           #71                 // String .
      66: invokevirtual #77                 // Method java/lang/String.lastIndexOf:(Ljava/lang/String;)I
      69: istore        7
      71: aload_0
      72: aload_2
      73: iconst_0
      74: iload         7
      76: invokevirtual #81                 // Method java/lang/String.substring:(II)Ljava/lang/String;
      79: putfield      #64                 // Field className:Ljava/lang/String;
      82: aload_0
      83: aload_1
      84: ldc           #89                 // String DefaultPackage
      86: invokevirtual #93                 // Method java/lang/String.equals:(Ljava/lang/Object;)Z
      89: putfield      #95                 // Field deferSetup:Z
      92: aload_0
      93: new           #97                 // class java/util/ArrayList
      96: dup
      97: invokespecial #98                 // Method java/util/ArrayList."<init>":()V
     100: putfield      #100                // Field importedClassesAndPackages:Ljava/util/List;
     103: aload_0
     104: new           #66                 // class java/util/LinkedHashMap
     107: dup
     108: invokespecial #67                 // Method java/util/LinkedHashMap."<init>":()V
     111: putfield      #102                // Field aliases:Ljava/util/Map;
     114: aload_0
     115: getfield      #95                 // Field deferSetup:Z
     118: ifne          134
     121: aload_0
     122: aload_1
     123: aload         4
     125: iload         6
     127: aload_0
     128: getfield      #64                 // Field className:Ljava/lang/String;
     131: invokespecial #106                // Method setUpImports:(Ljava/lang/String;Ljava/util/List;ZLjava/lang/String;)V
     134: aload_0
     135: new           #108                // class org/codehaus/groovy/antlr/LineColumn
     138: dup
     139: iconst_1
     140: iconst_1
     141: invokespecial #111                // Method org/codehaus/groovy/antlr/LineColumn."<init>":(II)V
     144: putfield      #113                // Field lastLineCol:Lorg/codehaus/groovy/antlr/LineColumn;
     147: return

  private void setUpImports(java.lang.String, java.util.List<org.codehaus.groovy.tools.groovydoc.LinkArgument>, boolean, java.lang.String);
    Code:
       0: aload_0
       1: getfield      #100                // Field importedClassesAndPackages:Ljava/util/List;
       4: new           #120                // class java/lang/StringBuilder
       7: dup
       8: invokespecial #121                // Method java/lang/StringBuilder."<init>":()V
      11: aload_1
      12: invokevirtual #125                // Method java/lang/StringBuilder.append:(Ljava/lang/String;)Ljava/lang/StringBuilder;
      15: ldc           #127                // String /*
      17: invokevirtual #125                // Method java/lang/StringBuilder.append:(Ljava/lang/String;)Ljava/lang/StringBuilder;
      20: invokevirtual #131                // Method java/lang/StringBuilder.toString:()Ljava/lang/String;
      23: invokeinterface #134,  2          // InterfaceMethod java/util/List.add:(Ljava/lang/Object;)Z
      28: pop
      29: iload_3
      30: ifeq          106
      33: getstatic     #140                // Field org/codehaus/groovy/control/ResolveVisitor.DEFAULT_IMPORTS:[Ljava/lang/String;
      36: astore        5
      38: aload         5
      40: arraylength
      41: istore        6
      43: iconst_0
      44: istore        7
      46: iload         7
      48: iload         6
      50: if_icmpge     103
      53: aload         5
      55: iload         7
      57: aaload
      58: astore        8
      60: aload_0
      61: getfield      #100                // Field importedClassesAndPackages:Ljava/util/List;
      64: new           #120                // class java/lang/StringBuilder
      67: dup
      68: invokespecial #121                // Method java/lang/StringBuilder."<init>":()V
      71: aload         8
      73: bipush        46
      75: bipush        47
      77: invokevirtual #145                // Method java/lang/String.replace:(CC)Ljava/lang/String;
      80: invokevirtual #125                // Method java/lang/StringBuilder.append:(Ljava/lang/String;)Ljava/lang/StringBuilder;
      83: ldc           #147                // String *
      85: invokevirtual #125                // Method java/lang/StringBuilder.append:(Ljava/lang/String;)Ljava/lang/StringBuilder;
      88: invokevirtual #131                // Method java/lang/StringBuilder.toString:()Ljava/lang/String;
      91: invokeinterface #134,  2          // InterfaceMethod java/util/List.add:(Ljava/lang/Object;)Z
      96: pop
      97: iinc          7, 1
     100: goto          46
     103: goto          118
     106: aload_0
     107: getfield      #100                // Field importedClassesAndPackages:Ljava/util/List;
     110: ldc           #149                // String java/lang/*
     112: invokeinterface #134,  2          // InterfaceMethod java/util/List.add:(Ljava/lang/Object;)Z
     117: pop
     118: new           #151                // class org/codehaus/groovy/tools/groovydoc/SimpleGroovyClassDoc
     121: dup
     122: aload_0
     123: getfield      #100                // Field importedClassesAndPackages:Ljava/util/List;
     126: aload_0
     127: getfield      #102                // Field aliases:Ljava/util/Map;
     130: aload         4
     132: aload_2
     133: invokespecial #154                // Method org/codehaus/groovy/tools/groovydoc/SimpleGroovyClassDoc."<init>":(Ljava/util/List;Ljava/util/Map;Ljava/lang/String;Ljava/util/List;)V
     136: astore        5
     138: aload         5
     140: new           #120                // class java/lang/StringBuilder
     143: dup
     144: invokespecial #121                // Method java/lang/StringBuilder."<init>":()V
     147: aload_1
     148: invokevirtual #125                // Method java/lang/StringBuilder.append:(Ljava/lang/String;)Ljava/lang/StringBuilder;
     151: ldc           #11                 // String /
     153: invokevirtual #125                // Method java/lang/StringBuilder.append:(Ljava/lang/String;)Ljava/lang/StringBuilder;
     156: aload         4
     158: invokevirtual #125                // Method java/lang/StringBuilder.append:(Ljava/lang/String;)Ljava/lang/StringBuilder;
     161: invokevirtual #131                // Method java/lang/StringBuilder.toString:()Ljava/lang/String;
     164: invokevirtual #158                // Method org/codehaus/groovy/tools/groovydoc/SimpleGroovyClassDoc.setFullPathName:(Ljava/lang/String;)V
     167: aload         5
     169: iload_3
     170: invokevirtual #162                // Method org/codehaus/groovy/tools/groovydoc/SimpleGroovyClassDoc.setGroovy:(Z)V
     173: aload_0
     174: getfield      #69                 // Field classDocs:Ljava/util/Map;
     177: aload         5
     179: invokevirtual #165                // Method org/codehaus/groovy/tools/groovydoc/SimpleGroovyClassDoc.getFullPathName:()Ljava/lang/String;
     182: aload         5
     184: invokeinterface #171,  3          // InterfaceMethod java/util/Map.put:(Ljava/lang/Object;Ljava/lang/Object;)Ljava/lang/Object;
     189: pop
     190: return

  public java.util.Map<java.lang.String, org.codehaus.groovy.groovydoc.GroovyClassDoc> getGroovyClassDocs();
    Code:
       0: aload_0
       1: invokespecial #179                // Method postProcessClassDocs:()V
       4: aload_0
       5: getfield      #69                 // Field classDocs:Ljava/util/Map;
       8: areturn

  public void visitInterfaceDef(org.codehaus.groovy.antlr.GroovySourceAST, int);
    Code:
       0: aload_0
       1: aload_1
       2: iload_2
       3: invokevirtual #184                // Method visitClassDef:(Lorg/codehaus/groovy/antlr/GroovySourceAST;I)V
       6: return

  public void visitTraitDef(org.codehaus.groovy.antlr.GroovySourceAST, int);
    Code:
       0: aload_0
       1: aload_1
       2: iload_2
       3: invokevirtual #184                // Method visitClassDef:(Lorg/codehaus/groovy/antlr/GroovySourceAST;I)V
       6: return

  public void visitEnumDef(org.codehaus.groovy.antlr.GroovySourceAST, int);
    Code:
       0: aload_0
       1: aload_1
       2: iload_2
       3: invokevirtual #184                // Method visitClassDef:(Lorg/codehaus/groovy/antlr/GroovySourceAST;I)V
       6: aload_0
       7: aload_1
       8: invokespecial #193                // Method getCurrentOrTopLevelClassDoc:(Lorg/codehaus/groovy/antlr/GroovySourceAST;)Lorg/codehaus/groovy/tools/groovydoc/SimpleGroovyClassDoc;
      11: astore_3
      12: iload_2
      13: iconst_4
      14: if_icmpne     25
      17: aload_3
      18: ifnull        25
      21: aload_3
      22: invokestatic  #197                // Method adjustForAutomaticEnumMethods:(Lorg/codehaus/groovy/tools/groovydoc/SimpleGroovyClassDoc;)V
      25: return

  public void visitAnnotationDef(org.codehaus.groovy.antlr.GroovySourceAST, int);
    Code:
       0: aload_0
       1: aload_1
       2: iload_2
       3: invokevirtual #184                // Method visitClassDef:(Lorg/codehaus/groovy/antlr/GroovySourceAST;I)V
       6: return

  public void visitClassDef(org.codehaus.groovy.antlr.GroovySourceAST, int);
    Code:
       0: iload_2
       1: iconst_1
       2: if_icmpne     286
       5: aload_0
       6: invokespecial #202                // Method getCurrentClassDoc:()Lorg/codehaus/groovy/tools/groovydoc/SimpleGroovyClassDoc;
       9: astore_3
      10: aload_1
      11: invokestatic  #206                // Method getIdentFor:(Lorg/codehaus/groovy/antlr/GroovySourceAST;)Ljava/lang/String;
      14: astore        4
      16: aload         4
      18: astore        5
      20: aload_3
      21: ifnull        70
      24: aload_0
      25: invokespecial #210                // Method isNested:()Z
      28: ifeq          70
      31: aload_0
      32: invokespecial #213                // Method insideAnonymousInnerClass:()Z
      35: ifne          70
      38: new           #120                // class java/lang/StringBuilder
      41: dup
      42: invokespecial #121                // Method java/lang/StringBuilder."<init>":()V
      45: aload_3
      46: invokevirtual #216                // Method org/codehaus/groovy/tools/groovydoc/SimpleGroovyClassDoc.name:()Ljava/lang/String;
      49: invokevirtual #125                // Method java/lang/StringBuilder.append:(Ljava/lang/String;)Ljava/lang/StringBuilder;
      52: ldc           #71                 // String .
      54: invokevirtual #125                // Method java/lang/StringBuilder.append:(Ljava/lang/String;)Ljava/lang/StringBuilder;
      57: aload         5
      59: invokevirtual #125                // Method java/lang/StringBuilder.append:(Ljava/lang/String;)Ljava/lang/StringBuilder;
      62: invokevirtual #131                // Method java/lang/StringBuilder.toString:()Ljava/lang/String;
      65: astore        5
      67: goto          81
      70: aload_0
      71: new           #66                 // class java/util/LinkedHashMap
      74: dup
      75: invokespecial #67                 // Method java/util/LinkedHashMap."<init>":()V
      78: putfield      #218                // Field foundClasses:Ljava/util/Map;
      81: aload_0
      82: getfield      #69                 // Field classDocs:Ljava/util/Map;
      85: new           #120                // class java/lang/StringBuilder
      88: dup
      89: invokespecial #121                // Method java/lang/StringBuilder."<init>":()V
      92: aload_0
      93: getfield      #51                 // Field packagePath:Ljava/lang/String;
      96: invokevirtual #125                // Method java/lang/StringBuilder.append:(Ljava/lang/String;)Ljava/lang/StringBuilder;
      99: ldc           #11                 // String /
     101: invokevirtual #125                // Method java/lang/StringBuilder.append:(Ljava/lang/String;)Ljava/lang/StringBuilder;
     104: aload         5
     106: invokevirtual #125                // Method java/lang/StringBuilder.append:(Ljava/lang/String;)Ljava/lang/StringBuilder;
     109: invokevirtual #131                // Method java/lang/StringBuilder.toString:()Ljava/lang/String;
     112: invokeinterface #222,  2          // InterfaceMethod java/util/Map.get:(Ljava/lang/Object;)Ljava/lang/Object;
     117: checkcast     #151                // class org/codehaus/groovy/tools/groovydoc/SimpleGroovyClassDoc
     120: astore        6
     122: aload         6
     124: ifnonnull     159
     127: new           #151                // class org/codehaus/groovy/tools/groovydoc/SimpleGroovyClassDoc
     130: dup
     131: aload_0
     132: getfield      #100                // Field importedClassesAndPackages:Ljava/util/List;
     135: aload_0
     136: getfield      #102                // Field aliases:Ljava/util/Map;
     139: aload         5
     141: aload_0
     142: getfield      #53                 // Field links:Ljava/util/List;
     145: invokespecial #154                // Method org/codehaus/groovy/tools/groovydoc/SimpleGroovyClassDoc."<init>":(Ljava/util/List;Ljava/util/Map;Ljava/lang/String;Ljava/util/List;)V
     148: astore        6
     150: aload         6
     152: aload_0
     153: getfield      #57                 // Field isGroovy:Z
     156: invokevirtual #162                // Method org/codehaus/groovy/tools/groovydoc/SimpleGroovyClassDoc.setGroovy:(Z)V
     159: aload         6
     161: aload_0
     162: aload_1
     163: invokespecial #225                // Method getJavaDocCommentsBeforeNode:(Lorg/codehaus/groovy/antlr/GroovySourceAST;)Ljava/lang/String;
     166: invokevirtual #228                // Method org/codehaus/groovy/tools/groovydoc/SimpleGroovyClassDoc.setRawCommentText:(Ljava/lang/String;)V
     169: aload         6
     171: new           #120                // class java/lang/StringBuilder
     174: dup
     175: invokespecial #121                // Method java/lang/StringBuilder."<init>":()V
     178: aload_0
     179: getfield      #51                 // Field packagePath:Ljava/lang/String;
     182: invokevirtual #125                // Method java/lang/StringBuilder.append:(Ljava/lang/String;)Ljava/lang/StringBuilder;
     185: ldc           #11                 // String /
     187: invokevirtual #125                // Method java/lang/StringBuilder.append:(Ljava/lang/String;)Ljava/lang/StringBuilder;
     190: aload         6
     192: invokevirtual #216                // Method org/codehaus/groovy/tools/groovydoc/SimpleGroovyClassDoc.name:()Ljava/lang/String;
     195: invokevirtual #125                // Method java/lang/StringBuilder.append:(Ljava/lang/String;)Ljava/lang/StringBuilder;
     198: invokevirtual #131                // Method java/lang/StringBuilder.toString:()Ljava/lang/String;
     201: invokevirtual #158                // Method org/codehaus/groovy/tools/groovydoc/SimpleGroovyClassDoc.setFullPathName:(Ljava/lang/String;)V
     204: aload         6
     206: aload_1
     207: invokevirtual #234                // Method org/codehaus/groovy/antlr/GroovySourceAST.getType:()I
     210: invokevirtual #238                // Method org/codehaus/groovy/tools/groovydoc/SimpleGroovyClassDoc.setTokenType:(I)V
     213: aload         6
     215: aload_0
     216: aload_1
     217: invokespecial #241                // Method getIdentPlusTypeArgsFor:(Lorg/codehaus/groovy/antlr/GroovySourceAST;)Ljava/lang/String;
     220: invokevirtual #244                // Method org/codehaus/groovy/tools/groovydoc/SimpleGroovyClassDoc.setNameWithTypeArgs:(Ljava/lang/String;)V
     223: aload_0
     224: aload_1
     225: aload         6
     227: invokespecial #248                // Method processAnnotations:(Lorg/codehaus/groovy/antlr/GroovySourceAST;Lorg/codehaus/groovy/tools/groovydoc/SimpleGroovyProgramElementDoc;)V
     230: aload_0
     231: aload_1
     232: aload         6
     234: invokespecial #252                // Method processModifiers:(Lorg/codehaus/groovy/antlr/GroovySourceAST;Lorg/codehaus/groovy/tools/groovydoc/SimpleGroovyAbstractableElementDoc;)Z
     237: pop
     238: aload_0
     239: getfield      #69                 // Field classDocs:Ljava/util/Map;
     242: aload         6
     244: invokevirtual #165                // Method org/codehaus/groovy/tools/groovydoc/SimpleGroovyClassDoc.getFullPathName:()Ljava/lang/String;
     247: aload         6
     249: invokeinterface #171,  3          // InterfaceMethod java/util/Map.put:(Ljava/lang/Object;Ljava/lang/Object;)Ljava/lang/Object;
     254: pop
     255: aload_0
     256: getfield      #218                // Field foundClasses:Ljava/util/Map;
     259: aload         4
     261: aload         6
     263: invokeinterface #171,  3          // InterfaceMethod java/util/Map.put:(Ljava/lang/Object;Ljava/lang/Object;)Ljava/lang/Object;
     268: pop
     269: aload_3
     270: ifnull        286
     273: aload_3
     274: aload         6
     276: invokevirtual #256                // Method org/codehaus/groovy/tools/groovydoc/SimpleGroovyClassDoc.addNested:(Lorg/codehaus/groovy/groovydoc/GroovyClassDoc;)Z
     279: pop
     280: aload         6
     282: aload_3
     283: invokevirtual #260                // Method org/codehaus/groovy/tools/groovydoc/SimpleGroovyClassDoc.setOuter:(Lorg/codehaus/groovy/groovydoc/GroovyClassDoc;)V
     286: return

  public void visitPackageDef(org.codehaus.groovy.antlr.GroovySourceAST, int);
    Code:
       0: iload_2
       1: iconst_1
       2: if_icmpne     35
       5: aload_0
       6: getfield      #95                 // Field deferSetup:Z
       9: ifeq          35
      12: aload_0
      13: aload_1
      14: invokespecial #267                // Method extractImportPath:(Lorg/codehaus/groovy/antlr/GroovySourceAST;)Ljava/lang/String;
      17: astore_3
      18: aload_0
      19: aload_3
      20: aload_0
      21: getfield      #53                 // Field links:Ljava/util/List;
      24: aload_0
      25: getfield      #57                 // Field isGroovy:Z
      28: aload_0
      29: getfield      #64                 // Field className:Ljava/lang/String;
      32: invokespecial #106                // Method setUpImports:(Ljava/lang/String;Ljava/util/List;ZLjava/lang/String;)V
      35: return

  public void visitImport(org.codehaus.groovy.antlr.GroovySourceAST, int);
    Code:
       0: iload_2
       1: iconst_1
       2: if_icmpne     81
       5: aload_0
       6: aload_1
       7: invokespecial #267                // Method extractImportPath:(Lorg/codehaus/groovy/antlr/GroovySourceAST;)Ljava/lang/String;
      10: astore_3
      11: aload_1
      12: bipush        114
      14: invokevirtual #273                // Method org/codehaus/groovy/antlr/GroovySourceAST.childOfType:(I)Lorg/codehaus/groovy/antlr/GroovySourceAST;
      17: astore        4
      19: aload         4
      21: ifnull        70
      24: aload         4
      26: bipush        90
      28: invokevirtual #273                // Method org/codehaus/groovy/antlr/GroovySourceAST.childOfType:(I)Lorg/codehaus/groovy/antlr/GroovySourceAST;
      31: invokevirtual #277                // Method org/codehaus/groovy/antlr/GroovySourceAST.getNextSibling:()Lgroovyjarjarantlr/collections/AST;
      34: invokeinterface #282,  1          // InterfaceMethod groovyjarjarantlr/collections/AST.getText:()Ljava/lang/String;
      39: astore        5
      41: aload         4
      43: bipush        90
      45: invokevirtual #273                // Method org/codehaus/groovy/antlr/GroovySourceAST.childOfType:(I)Lorg/codehaus/groovy/antlr/GroovySourceAST;
      48: astore        4
      50: aload_0
      51: aload         4
      53: invokespecial #285                // Method recurseDownImportBranch:(Lorg/codehaus/groovy/antlr/GroovySourceAST;)Ljava/lang/String;
      56: astore_3
      57: aload_0
      58: getfield      #102                // Field aliases:Ljava/util/Map;
      61: aload         5
      63: aload_3
      64: invokeinterface #171,  3          // InterfaceMethod java/util/Map.put:(Ljava/lang/Object;Ljava/lang/Object;)Ljava/lang/Object;
      69: pop
      70: aload_0
      71: getfield      #100                // Field importedClassesAndPackages:Ljava/util/List;
      74: aload_3
      75: invokeinterface #134,  2          // InterfaceMethod java/util/List.add:(Ljava/lang/Object;)Z
      80: pop
      81: return

  public void visitExtendsClause(org.codehaus.groovy.antlr.GroovySourceAST, int);
    Code:
       0: aload_0
       1: invokespecial #202                // Method getCurrentClassDoc:()Lorg/codehaus/groovy/tools/groovydoc/SimpleGroovyClassDoc;
       4: astore_3
       5: iload_2
       6: iconst_1
       7: if_icmpne     76
      10: aload_1
      11: invokestatic  #293                // Method findTypeNames:(Lorg/codehaus/groovy/antlr/GroovySourceAST;)Ljava/util/List;
      14: invokeinterface #297,  1          // InterfaceMethod java/util/List.iterator:()Ljava/util/Iterator;
      19: astore        4
      21: aload         4
      23: invokeinterface #302,  1          // InterfaceMethod java/util/Iterator.hasNext:()Z
      28: ifeq          76
      31: aload         4
      33: invokeinterface #306,  1          // InterfaceMethod java/util/Iterator.next:()Ljava/lang/Object;
      38: checkcast     #230                // class org/codehaus/groovy/antlr/GroovySourceAST
      41: astore        5
      43: aload_0
      44: aload         5
      46: invokespecial #309                // Method extractName:(Lorg/codehaus/groovy/antlr/GroovySourceAST;)Ljava/lang/String;
      49: astore        6
      51: aload_3
      52: invokevirtual #312                // Method org/codehaus/groovy/tools/groovydoc/SimpleGroovyClassDoc.isInterface:()Z
      55: ifeq          67
      58: aload_3
      59: aload         6
      61: invokevirtual #315                // Method org/codehaus/groovy/tools/groovydoc/SimpleGroovyClassDoc.addInterfaceName:(Ljava/lang/String;)V
      64: goto          73
      67: aload_3
      68: aload         6
      70: invokevirtual #318                // Method org/codehaus/groovy/tools/groovydoc/SimpleGroovyClassDoc.setSuperClassName:(Ljava/lang/String;)V
      73: goto          21
      76: return

  public void visitImplementsClause(org.codehaus.groovy.antlr.GroovySourceAST, int);
    Code:
       0: iload_2
       1: iconst_1
       2: if_icmpne     51
       5: aload_1
       6: invokestatic  #293                // Method findTypeNames:(Lorg/codehaus/groovy/antlr/GroovySourceAST;)Ljava/util/List;
       9: invokeinterface #297,  1          // InterfaceMethod java/util/List.iterator:()Ljava/util/Iterator;
      14: astore_3
      15: aload_3
      16: invokeinterface #302,  1          // InterfaceMethod java/util/Iterator.hasNext:()Z
      21: ifeq          51
      24: aload_3
      25: invokeinterface #306,  1          // InterfaceMethod java/util/Iterator.next:()Ljava/lang/Object;
      30: checkcast     #230                // class org/codehaus/groovy/antlr/GroovySourceAST
      33: astore        4
      35: aload_0
      36: invokespecial #202                // Method getCurrentClassDoc:()Lorg/codehaus/groovy/tools/groovydoc/SimpleGroovyClassDoc;
      39: aload_0
      40: aload         4
      42: invokespecial #309                // Method extractName:(Lorg/codehaus/groovy/antlr/GroovySourceAST;)Ljava/lang/String;
      45: invokevirtual #315                // Method org/codehaus/groovy/tools/groovydoc/SimpleGroovyClassDoc.addInterfaceName:(Ljava/lang/String;)V
      48: goto          15
      51: return

  private static java.util.List<org.codehaus.groovy.antlr.GroovySourceAST> findTypeNames(org.codehaus.groovy.antlr.GroovySourceAST);
    Code:
       0: new           #97                 // class java/util/ArrayList
       3: dup
       4: invokespecial #98                 // Method java/util/ArrayList."<init>":()V
       7: astore_1
       8: aload_0
       9: invokevirtual #325                // Method org/codehaus/groovy/antlr/GroovySourceAST.getFirstChild:()Lgroovyjarjarantlr/collections/AST;
      12: astore_2
      13: aload_2
      14: ifnull        66
      17: aload_2
      18: checkcast     #230                // class org/codehaus/groovy/antlr/GroovySourceAST
      21: astore_3
      22: aload_3
      23: invokevirtual #234                // Method org/codehaus/groovy/antlr/GroovySourceAST.getType:()I
      26: bipush        12
      28: if_icmpne     48
      31: aload_1
      32: aload_3
      33: invokevirtual #325                // Method org/codehaus/groovy/antlr/GroovySourceAST.getFirstChild:()Lgroovyjarjarantlr/collections/AST;
      36: checkcast     #230                // class org/codehaus/groovy/antlr/GroovySourceAST
      39: invokeinterface #134,  2          // InterfaceMethod java/util/List.add:(Ljava/lang/Object;)Z
      44: pop
      45: goto          56
      48: aload_1
      49: aload_3
      50: invokeinterface #134,  2          // InterfaceMethod java/util/List.add:(Ljava/lang/Object;)Z
      55: pop
      56: aload_2
      57: invokeinterface #326,  1          // InterfaceMethod groovyjarjarantlr/collections/AST.getNextSibling:()Lgroovyjarjarantlr/collections/AST;
      62: astore_2
      63: goto          13
      66: aload_1
      67: areturn

  public void visitCtorIdent(org.codehaus.groovy.antlr.GroovySourceAST, int);
    Code:
       0: iload_2
       1: iconst_1
       2: if_icmpne     77
       5: aload_0
       6: getfield      #333                // Field insideEnum:Z
       9: ifne          77
      12: aload_0
      13: invokespecial #213                // Method insideAnonymousInnerClass:()Z
      16: ifne          77
      19: aload_0
      20: invokespecial #202                // Method getCurrentClassDoc:()Lorg/codehaus/groovy/tools/groovydoc/SimpleGroovyClassDoc;
      23: astore_3
      24: new           #335                // class org/codehaus/groovy/tools/groovydoc/SimpleGroovyConstructorDoc
      27: dup
      28: aload_3
      29: invokevirtual #216                // Method org/codehaus/groovy/tools/groovydoc/SimpleGroovyClassDoc.name:()Ljava/lang/String;
      32: aload_3
      33: invokespecial #338                // Method org/codehaus/groovy/tools/groovydoc/SimpleGroovyConstructorDoc."<init>":(Ljava/lang/String;Lorg/codehaus/groovy/groovydoc/GroovyClassDoc;)V
      36: astore        4
      38: aload         4
      40: aload_0
      41: aload_1
      42: invokespecial #225                // Method getJavaDocCommentsBeforeNode:(Lorg/codehaus/groovy/antlr/GroovySourceAST;)Ljava/lang/String;
      45: invokevirtual #339                // Method org/codehaus/groovy/tools/groovydoc/SimpleGroovyConstructorDoc.setRawCommentText:(Ljava/lang/String;)V
      48: aload_0
      49: aload_1
      50: aload         4
      52: invokespecial #252                // Method processModifiers:(Lorg/codehaus/groovy/antlr/GroovySourceAST;Lorg/codehaus/groovy/tools/groovydoc/SimpleGroovyAbstractableElementDoc;)Z
      55: pop
      56: aload_0
      57: aload_1
      58: aload         4
      60: invokespecial #343                // Method addParametersTo:(Lorg/codehaus/groovy/antlr/GroovySourceAST;Lorg/codehaus/groovy/tools/groovydoc/SimpleGroovyExecutableMemberDoc;)V
      63: aload_0
      64: aload_1
      65: aload         4
      67: invokespecial #248                // Method processAnnotations:(Lorg/codehaus/groovy/antlr/GroovySourceAST;Lorg/codehaus/groovy/tools/groovydoc/SimpleGroovyProgramElementDoc;)V
      70: aload_3
      71: aload         4
      73: invokevirtual #346                // Method org/codehaus/groovy/tools/groovydoc/SimpleGroovyClassDoc.add:(Lorg/codehaus/groovy/groovydoc/GroovyConstructorDoc;)Z
      76: pop
      77: return

  public void visitMethodDef(org.codehaus.groovy.antlr.GroovySourceAST, int);
    Code:
       0: iload_2
       1: iconst_1
       2: if_icmpne     108
       5: aload_0
       6: getfield      #333                // Field insideEnum:Z
       9: ifne          108
      12: aload_0
      13: invokespecial #213                // Method insideAnonymousInnerClass:()Z
      16: ifne          108
      19: aload_0
      20: invokespecial #202                // Method getCurrentClassDoc:()Lorg/codehaus/groovy/tools/groovydoc/SimpleGroovyClassDoc;
      23: astore_3
      24: aload_3
      25: ifnonnull     59
      28: ldc_w         #351                // String true
      31: aload_0
      32: getfield      #55                 // Field properties:Ljava/util/Properties;
      35: ldc_w         #353                // String processScripts
      38: ldc_w         #351                // String true
      41: invokevirtual #357                // Method java/util/Properties.getProperty:(Ljava/lang/String;Ljava/lang/String;)Ljava/lang/String;
      44: invokevirtual #93                 // Method java/lang/String.equals:(Ljava/lang/Object;)Z
      47: ifeq          58
      50: aload_0
      51: invokespecial #360                // Method getOrMakeScriptClassDoc:()Lorg/codehaus/groovy/tools/groovydoc/SimpleGroovyClassDoc;
      54: astore_3
      55: goto          59
      58: return
      59: aload_0
      60: aload_1
      61: aload_3
      62: invokespecial #364                // Method createMethod:(Lorg/codehaus/groovy/antlr/GroovySourceAST;Lorg/codehaus/groovy/tools/groovydoc/SimpleGroovyClassDoc;)Lorg/codehaus/groovy/tools/groovydoc/SimpleGroovyMethodDoc;
      65: astore        4
      67: new           #120                // class java/lang/StringBuilder
      70: dup
      71: invokespecial #121                // Method java/lang/StringBuilder."<init>":()V
      74: astore        5
      76: aload_0
      77: aload_1
      78: bipush        72
      80: invokevirtual #273                // Method org/codehaus/groovy/antlr/GroovySourceAST.childOfType:(I)Lorg/codehaus/groovy/antlr/GroovySourceAST;
      83: aload         5
      85: ldc_w         #366                // String def
      88: invokespecial #370                // Method getTypeParameters:(Lorg/codehaus/groovy/antlr/GroovySourceAST;Ljava/lang/StringBuilder;Ljava/lang/String;)V
      91: aload         4
      93: aload         5
      95: invokevirtual #131                // Method java/lang/StringBuilder.toString:()Ljava/lang/String;
      98: invokevirtual #375                // Method org/codehaus/groovy/tools/groovydoc/SimpleGroovyMethodDoc.setTypeParameters:(Ljava/lang/String;)V
     101: aload_3
     102: aload         4
     104: invokevirtual #378                // Method org/codehaus/groovy/tools/groovydoc/SimpleGroovyClassDoc.add:(Lorg/codehaus/groovy/groovydoc/GroovyMethodDoc;)Z
     107: pop
     108: return

  private org.codehaus.groovy.tools.groovydoc.SimpleGroovyClassDoc getOrMakeScriptClassDoc();
    Code:
       0: aload_0
       1: getfield      #218                // Field foundClasses:Ljava/util/Map;
       4: ifnull        43
       7: aload_0
       8: getfield      #218                // Field foundClasses:Ljava/util/Map;
      11: aload_0
      12: getfield      #64                 // Field className:Ljava/lang/String;
      15: invokeinterface #385,  2          // InterfaceMethod java/util/Map.containsKey:(Ljava/lang/Object;)Z
      20: ifeq          43
      23: aload_0
      24: getfield      #218                // Field foundClasses:Ljava/util/Map;
      27: aload_0
      28: getfield      #64                 // Field className:Ljava/lang/String;
      31: invokeinterface #222,  2          // InterfaceMethod java/util/Map.get:(Ljava/lang/Object;)Ljava/lang/Object;
      36: checkcast     #151                // class org/codehaus/groovy/tools/groovydoc/SimpleGroovyClassDoc
      39: astore_1
      40: goto          204
      43: new           #151                // class org/codehaus/groovy/tools/groovydoc/SimpleGroovyClassDoc
      46: dup
      47: aload_0
      48: getfield      #100                // Field importedClassesAndPackages:Ljava/util/List;
      51: aload_0
      52: getfield      #102                // Field aliases:Ljava/util/Map;
      55: aload_0
      56: getfield      #64                 // Field className:Ljava/lang/String;
      59: aload_0
      60: getfield      #53                 // Field links:Ljava/util/List;
      63: invokespecial #154                // Method org/codehaus/groovy/tools/groovydoc/SimpleGroovyClassDoc."<init>":(Ljava/util/List;Ljava/util/Map;Ljava/lang/String;Ljava/util/List;)V
      66: astore_1
      67: aload_1
      68: new           #120                // class java/lang/StringBuilder
      71: dup
      72: invokespecial #121                // Method java/lang/StringBuilder."<init>":()V
      75: aload_0
      76: getfield      #51                 // Field packagePath:Ljava/lang/String;
      79: invokevirtual #125                // Method java/lang/StringBuilder.append:(Ljava/lang/String;)Ljava/lang/StringBuilder;
      82: ldc           #11                 // String /
      84: invokevirtual #125                // Method java/lang/StringBuilder.append:(Ljava/lang/String;)Ljava/lang/StringBuilder;
      87: aload_0
      88: getfield      #64                 // Field className:Ljava/lang/String;
      91: invokevirtual #125                // Method java/lang/StringBuilder.append:(Ljava/lang/String;)Ljava/lang/StringBuilder;
      94: invokevirtual #131                // Method java/lang/StringBuilder.toString:()Ljava/lang/String;
      97: invokevirtual #158                // Method org/codehaus/groovy/tools/groovydoc/SimpleGroovyClassDoc.setFullPathName:(Ljava/lang/String;)V
     100: aload_1
     101: iconst_1
     102: invokevirtual #388                // Method org/codehaus/groovy/tools/groovydoc/SimpleGroovyClassDoc.setPublic:(Z)V
     105: aload_1
     106: iconst_1
     107: invokevirtual #391                // Method org/codehaus/groovy/tools/groovydoc/SimpleGroovyClassDoc.setScript:(Z)V
     110: aload_1
     111: aload_0
     112: getfield      #57                 // Field isGroovy:Z
     115: invokevirtual #162                // Method org/codehaus/groovy/tools/groovydoc/SimpleGroovyClassDoc.setGroovy:(Z)V
     118: aload_1
     119: ldc_w         #393                // String groovy/lang/Script
     122: invokevirtual #318                // Method org/codehaus/groovy/tools/groovydoc/SimpleGroovyClassDoc.setSuperClassName:(Ljava/lang/String;)V
     125: ldc_w         #351                // String true
     128: aload_0
     129: getfield      #55                 // Field properties:Ljava/util/Properties;
     132: ldc_w         #395                // String includeMainForScripts
     135: ldc_w         #351                // String true
     138: invokevirtual #357                // Method java/util/Properties.getProperty:(Ljava/lang/String;Ljava/lang/String;)Ljava/lang/String;
     141: invokevirtual #93                 // Method java/lang/String.equals:(Ljava/lang/Object;)Z
     144: ifeq          156
     147: aload_1
     148: aload_1
     149: invokestatic  #399                // Method createMainMethod:(Lorg/codehaus/groovy/tools/groovydoc/SimpleGroovyClassDoc;)Lorg/codehaus/groovy/groovydoc/GroovyMethodDoc;
     152: invokevirtual #378                // Method org/codehaus/groovy/tools/groovydoc/SimpleGroovyClassDoc.add:(Lorg/codehaus/groovy/groovydoc/GroovyMethodDoc;)Z
     155: pop
     156: aload_0
     157: getfield      #69                 // Field classDocs:Ljava/util/Map;
     160: aload_1
     161: invokevirtual #165                // Method org/codehaus/groovy/tools/groovydoc/SimpleGroovyClassDoc.getFullPathName:()Ljava/lang/String;
     164: aload_1
     165: invokeinterface #171,  3          // InterfaceMethod java/util/Map.put:(Ljava/lang/Object;Ljava/lang/Object;)Ljava/lang/Object;
     170: pop
     171: aload_0
     172: getfield      #218                // Field foundClasses:Ljava/util/Map;
     175: ifnonnull     189
     178: aload_0
     179: new           #66                 // class java/util/LinkedHashMap
     182: dup
     183: invokespecial #67                 // Method java/util/LinkedHashMap."<init>":()V
     186: putfield      #218                // Field foundClasses:Ljava/util/Map;
     189: aload_0
     190: getfield      #218                // Field foundClasses:Ljava/util/Map;
     193: aload_0
     194: getfield      #64                 // Field className:Ljava/lang/String;
     197: aload_1
     198: invokeinterface #171,  3          // InterfaceMethod java/util/Map.put:(Ljava/lang/Object;Ljava/lang/Object;)Ljava/lang/Object;
     203: pop
     204: aload_1
     205: areturn

  private org.codehaus.groovy.tools.groovydoc.SimpleGroovyMethodDoc createMethod(org.codehaus.groovy.antlr.GroovySourceAST, org.codehaus.groovy.tools.groovydoc.SimpleGroovyClassDoc);
    Code:
       0: aload_1
       1: invokestatic  #206                // Method getIdentFor:(Lorg/codehaus/groovy/antlr/GroovySourceAST;)Ljava/lang/String;
       4: astore_3
       5: new           #372                // class org/codehaus/groovy/tools/groovydoc/SimpleGroovyMethodDoc
       8: dup
       9: aload_3
      10: aload_2
      11: invokespecial #400                // Method org/codehaus/groovy/tools/groovydoc/SimpleGroovyMethodDoc."<init>":(Ljava/lang/String;Lorg/codehaus/groovy/groovydoc/GroovyClassDoc;)V
      14: astore        4
      16: aload         4
      18: aload_0
      19: aload_1
      20: invokespecial #225                // Method getJavaDocCommentsBeforeNode:(Lorg/codehaus/groovy/antlr/GroovySourceAST;)Ljava/lang/String;
      23: invokevirtual #401                // Method org/codehaus/groovy/tools/groovydoc/SimpleGroovyMethodDoc.setRawCommentText:(Ljava/lang/String;)V
      26: aload_0
      27: aload_1
      28: aload         4
      30: invokespecial #252                // Method processModifiers:(Lorg/codehaus/groovy/antlr/GroovySourceAST;Lorg/codehaus/groovy/tools/groovydoc/SimpleGroovyAbstractableElementDoc;)Z
      33: pop
      34: aload         4
      36: new           #403                // class org/codehaus/groovy/tools/groovydoc/SimpleGroovyType
      39: dup
      40: aload_0
      41: aload_1
      42: invokespecial #406                // Method getTypeOrDefault:(Lorg/codehaus/groovy/antlr/GroovySourceAST;)Ljava/lang/String;
      45: invokespecial #408                // Method org/codehaus/groovy/tools/groovydoc/SimpleGroovyType."<init>":(Ljava/lang/String;)V
      48: invokevirtual #412                // Method org/codehaus/groovy/tools/groovydoc/SimpleGroovyMethodDoc.setReturnType:(Lorg/codehaus/groovy/groovydoc/GroovyType;)V
      51: aload_0
      52: aload_1
      53: aload         4
      55: invokespecial #343                // Method addParametersTo:(Lorg/codehaus/groovy/antlr/GroovySourceAST;Lorg/codehaus/groovy/tools/groovydoc/SimpleGroovyExecutableMemberDoc;)V
      58: aload_0
      59: aload_1
      60: aload         4
      62: invokespecial #248                // Method processAnnotations:(Lorg/codehaus/groovy/antlr/GroovySourceAST;Lorg/codehaus/groovy/tools/groovydoc/SimpleGroovyProgramElementDoc;)V
      65: aload         4
      67: areturn

  private static org.codehaus.groovy.groovydoc.GroovyMethodDoc createMainMethod(org.codehaus.groovy.tools.groovydoc.SimpleGroovyClassDoc);
    Code:
       0: new           #372                // class org/codehaus/groovy/tools/groovydoc/SimpleGroovyMethodDoc
       3: dup
       4: ldc_w         #415                // String main
       7: aload_0
       8: invokespecial #400                // Method org/codehaus/groovy/tools/groovydoc/SimpleGroovyMethodDoc."<init>":(Ljava/lang/String;Lorg/codehaus/groovy/groovydoc/GroovyClassDoc;)V
      11: astore_1
      12: aload_1
      13: iconst_1
      14: invokevirtual #416                // Method org/codehaus/groovy/tools/groovydoc/SimpleGroovyMethodDoc.setPublic:(Z)V
      17: aload_1
      18: iconst_1
      19: invokevirtual #419                // Method org/codehaus/groovy/tools/groovydoc/SimpleGroovyMethodDoc.setStatic:(Z)V
      22: aload_1
      23: ldc_w         #421                // String Implicit main method for Groovy Scripts
      26: invokevirtual #424                // Method org/codehaus/groovy/tools/groovydoc/SimpleGroovyMethodDoc.setCommentText:(Ljava/lang/String;)V
      29: aload_1
      30: aload_1
      31: invokevirtual #427                // Method org/codehaus/groovy/tools/groovydoc/SimpleGroovyMethodDoc.commentText:()Ljava/lang/String;
      34: invokevirtual #430                // Method org/codehaus/groovy/tools/groovydoc/SimpleGroovyMethodDoc.setFirstSentenceCommentText:(Ljava/lang/String;)V
      37: new           #432                // class org/codehaus/groovy/tools/groovydoc/SimpleGroovyParameter
      40: dup
      41: ldc_w         #434                // String args
      44: invokespecial #435                // Method org/codehaus/groovy/tools/groovydoc/SimpleGroovyParameter."<init>":(Ljava/lang/String;)V
      47: astore_2
      48: new           #403                // class org/codehaus/groovy/tools/groovydoc/SimpleGroovyType
      51: dup
      52: ldc_w         #437                // String java.lang.String[]
      55: invokespecial #408                // Method org/codehaus/groovy/tools/groovydoc/SimpleGroovyType."<init>":(Ljava/lang/String;)V
      58: astore_3
      59: aload_2
      60: aload_3
      61: invokevirtual #440                // Method org/codehaus/groovy/tools/groovydoc/SimpleGroovyParameter.setType:(Lorg/codehaus/groovy/groovydoc/GroovyType;)V
      64: aload_1
      65: aload_2
      66: invokevirtual #443                // Method org/codehaus/groovy/tools/groovydoc/SimpleGroovyMethodDoc.add:(Lorg/codehaus/groovy/groovydoc/GroovyParameter;)V
      69: new           #403                // class org/codehaus/groovy/tools/groovydoc/SimpleGroovyType
      72: dup
      73: ldc_w         #445                // String void
      76: invokespecial #408                // Method org/codehaus/groovy/tools/groovydoc/SimpleGroovyType."<init>":(Ljava/lang/String;)V
      79: astore        4
      81: aload_1
      82: aload         4
      84: invokevirtual #412                // Method org/codehaus/groovy/tools/groovydoc/SimpleGroovyMethodDoc.setReturnType:(Lorg/codehaus/groovy/groovydoc/GroovyType;)V
      87: aload_1
      88: areturn

  public void visitAnnotationFieldDef(org.codehaus.groovy.antlr.GroovySourceAST, int);
    Code:
       0: aload_0
       1: getfield      #57                 // Field isGroovy:Z
       4: ifeq          85
       7: iload_2
       8: iconst_1
       9: if_icmpne     85
      12: aload_0
      13: invokespecial #202                // Method getCurrentClassDoc:()Lorg/codehaus/groovy/tools/groovydoc/SimpleGroovyClassDoc;
      16: astore_3
      17: aload_0
      18: aload_1
      19: aload_3
      20: invokespecial #364                // Method createMethod:(Lorg/codehaus/groovy/antlr/GroovySourceAST;Lorg/codehaus/groovy/tools/groovydoc/SimpleGroovyClassDoc;)Lorg/codehaus/groovy/tools/groovydoc/SimpleGroovyMethodDoc;
      23: astore        4
      25: aload_0
      26: aload_1
      27: invokespecial #454                // Method getDefaultValue:(Lorg/codehaus/groovy/antlr/GroovySourceAST;)Ljava/lang/String;
      30: astore        5
      32: aload         5
      34: ifnull        75
      37: aload         4
      39: invokevirtual #457                // Method org/codehaus/groovy/tools/groovydoc/SimpleGroovyMethodDoc.getRawCommentText:()Ljava/lang/String;
      42: astore        6
      44: aload         4
      46: new           #120                // class java/lang/StringBuilder
      49: dup
      50: invokespecial #121                // Method java/lang/StringBuilder."<init>":()V
      53: aload         6
      55: invokevirtual #125                // Method java/lang/StringBuilder.append:(Ljava/lang/String;)Ljava/lang/StringBuilder;
      58: ldc_w         #459                // String \n* @default
      61: invokevirtual #125                // Method java/lang/StringBuilder.append:(Ljava/lang/String;)Ljava/lang/StringBuilder;
      64: aload         5
      66: invokevirtual #125                // Method java/lang/StringBuilder.append:(Ljava/lang/String;)Ljava/lang/StringBuilder;
      69: invokevirtual #131                // Method java/lang/StringBuilder.toString:()Ljava/lang/String;
      72: invokevirtual #401                // Method org/codehaus/groovy/tools/groovydoc/SimpleGroovyMethodDoc.setRawCommentText:(Ljava/lang/String;)V
      75: aload_3
      76: aload         4
      78: invokevirtual #378                // Method org/codehaus/groovy/tools/groovydoc/SimpleGroovyClassDoc.add:(Lorg/codehaus/groovy/groovydoc/GroovyMethodDoc;)Z
      81: pop
      82: goto          170
      85: iload_2
      86: iconst_1
      87: if_icmpne     170
      90: aload_0
      91: aload_1
      92: iload_2
      93: invokevirtual #462                // Method visitVariableDef:(Lorg/codehaus/groovy/antlr/GroovySourceAST;I)V
      96: aload_0
      97: aload_1
      98: invokespecial #454                // Method getDefaultValue:(Lorg/codehaus/groovy/antlr/GroovySourceAST;)Ljava/lang/String;
     101: astore_3
     102: aload_0
     103: getfield      #57                 // Field isGroovy:Z
     106: ifeq          117
     109: aload_0
     110: getfield      #464                // Field currentFieldDoc:Lorg/codehaus/groovy/tools/groovydoc/SimpleGroovyFieldDoc;
     113: iconst_1
     114: invokevirtual #467                // Method org/codehaus/groovy/tools/groovydoc/SimpleGroovyFieldDoc.setPublic:(Z)V
     117: aload_3
     118: ifnull        170
     121: aload_0
     122: getfield      #464                // Field currentFieldDoc:Lorg/codehaus/groovy/tools/groovydoc/SimpleGroovyFieldDoc;
     125: aload_3
     126: invokevirtual #470                // Method org/codehaus/groovy/tools/groovydoc/SimpleGroovyFieldDoc.setConstantValueExpression:(Ljava/lang/String;)V
     129: aload_0
     130: getfield      #464                // Field currentFieldDoc:Lorg/codehaus/groovy/tools/groovydoc/SimpleGroovyFieldDoc;
     133: invokevirtual #471                // Method org/codehaus/groovy/tools/groovydoc/SimpleGroovyFieldDoc.getRawCommentText:()Ljava/lang/String;
     136: astore        4
     138: aload_0
     139: getfield      #464                // Field currentFieldDoc:Lorg/codehaus/groovy/tools/groovydoc/SimpleGroovyFieldDoc;
     142: new           #120                // class java/lang/StringBuilder
     145: dup
     146: invokespecial #121                // Method java/lang/StringBuilder."<init>":()V
     149: aload         4
     151: invokevirtual #125                // Method java/lang/StringBuilder.append:(Ljava/lang/String;)Ljava/lang/StringBuilder;
     154: ldc_w         #459                // String \n* @default
     157: invokevirtual #125                // Method java/lang/StringBuilder.append:(Ljava/lang/String;)Ljava/lang/StringBuilder;
     160: aload_3
     161: invokevirtual #125                // Method java/lang/StringBuilder.append:(Ljava/lang/String;)Ljava/lang/StringBuilder;
     164: invokevirtual #131                // Method java/lang/StringBuilder.toString:()Ljava/lang/String;
     167: invokevirtual #472                // Method org/codehaus/groovy/tools/groovydoc/SimpleGroovyFieldDoc.setRawCommentText:(Ljava/lang/String;)V
     170: return

  public void visitEnumConstantDef(org.codehaus.groovy.antlr.GroovySourceAST, int);
    Code:
       0: iload_2
       1: iconst_1
       2: if_icmpne     91
       5: aload_0
       6: invokespecial #202                // Method getCurrentClassDoc:()Lorg/codehaus/groovy/tools/groovydoc/SimpleGroovyClassDoc;
       9: astore_3
      10: aload_0
      11: iconst_1
      12: putfield      #333                // Field insideEnum:Z
      15: aload_1
      16: invokestatic  #206                // Method getIdentFor:(Lorg/codehaus/groovy/antlr/GroovySourceAST;)Ljava/lang/String;
      19: astore        4
      21: new           #466                // class org/codehaus/groovy/tools/groovydoc/SimpleGroovyFieldDoc
      24: dup
      25: aload         4
      27: aload_3
      28: invokespecial #476                // Method org/codehaus/groovy/tools/groovydoc/SimpleGroovyFieldDoc."<init>":(Ljava/lang/String;Lorg/codehaus/groovy/groovydoc/GroovyClassDoc;)V
      31: astore        5
      33: aload         5
      35: aload_0
      36: aload_1
      37: invokespecial #225                // Method getJavaDocCommentsBeforeNode:(Lorg/codehaus/groovy/antlr/GroovySourceAST;)Ljava/lang/String;
      40: invokevirtual #472                // Method org/codehaus/groovy/tools/groovydoc/SimpleGroovyFieldDoc.setRawCommentText:(Ljava/lang/String;)V
      43: aload_0
      44: aload_1
      45: aload         5
      47: invokespecial #252                // Method processModifiers:(Lorg/codehaus/groovy/antlr/GroovySourceAST;Lorg/codehaus/groovy/tools/groovydoc/SimpleGroovyAbstractableElementDoc;)Z
      50: pop
      51: aload_0
      52: aload_1
      53: bipush        12
      55: invokevirtual #273                // Method org/codehaus/groovy/antlr/GroovySourceAST.childOfType:(I)Lorg/codehaus/groovy/antlr/GroovySourceAST;
      58: aload_3
      59: invokevirtual #479                // Method org/codehaus/groovy/tools/groovydoc/SimpleGroovyClassDoc.getTypeDescription:()Ljava/lang/String;
      62: invokespecial #483                // Method getTypeNodeAsText:(Lorg/codehaus/groovy/antlr/GroovySourceAST;Ljava/lang/String;)Ljava/lang/String;
      65: astore        6
      67: aload         5
      69: new           #403                // class org/codehaus/groovy/tools/groovydoc/SimpleGroovyType
      72: dup
      73: aload         6
      75: invokespecial #408                // Method org/codehaus/groovy/tools/groovydoc/SimpleGroovyType."<init>":(Ljava/lang/String;)V
      78: invokevirtual #484                // Method org/codehaus/groovy/tools/groovydoc/SimpleGroovyFieldDoc.setType:(Lorg/codehaus/groovy/groovydoc/GroovyType;)V
      81: aload_3
      82: aload         5
      84: invokevirtual #488                // Method org/codehaus/groovy/tools/groovydoc/SimpleGroovyClassDoc.addEnumConstant:(Lorg/codehaus/groovy/groovydoc/GroovyFieldDoc;)Z
      87: pop
      88: goto          101
      91: iload_2
      92: iconst_4
      93: if_icmpne     101
      96: aload_0
      97: iconst_0
      98: putfield      #333                // Field insideEnum:Z
     101: return

  public void visitVariableDef(org.codehaus.groovy.antlr.GroovySourceAST, int);
    Code:
       0: iload_2
       1: iconst_1
       2: if_icmpne     259
       5: aload_0
       6: invokespecial #213                // Method insideAnonymousInnerClass:()Z
       9: ifne          259
      12: iconst_1
      13: istore_3
      14: aload_0
      15: invokespecial #202                // Method getCurrentClassDoc:()Lorg/codehaus/groovy/tools/groovydoc/SimpleGroovyClassDoc;
      18: astore        4
      20: aload         4
      22: ifnonnull     59
      25: ldc_w         #351                // String true
      28: aload_0
      29: getfield      #55                 // Field properties:Ljava/util/Properties;
      32: ldc_w         #353                // String processScripts
      35: ldc_w         #351                // String true
      38: invokevirtual #357                // Method java/util/Properties.getProperty:(Ljava/lang/String;Ljava/lang/String;)Ljava/lang/String;
      41: invokevirtual #93                 // Method java/lang/String.equals:(Ljava/lang/Object;)Z
      44: ifeq          58
      47: aload_0
      48: invokespecial #360                // Method getOrMakeScriptClassDoc:()Lorg/codehaus/groovy/tools/groovydoc/SimpleGroovyClassDoc;
      51: astore        4
      53: iconst_0
      54: istore_3
      55: goto          67
      58: return
      59: aload_0
      60: invokespecial #494                // Method isFieldDefinition:()Z
      63: ifne          67
      66: return
      67: aload_1
      68: invokestatic  #206                // Method getIdentFor:(Lorg/codehaus/groovy/antlr/GroovySourceAST;)Ljava/lang/String;
      71: astore        5
      73: aload         5
      75: invokevirtual #497                // Method java/lang/String.isEmpty:()Z
      78: ifeq          82
      81: return
      82: aload_0
      83: new           #466                // class org/codehaus/groovy/tools/groovydoc/SimpleGroovyFieldDoc
      86: dup
      87: aload         5
      89: aload         4
      91: invokespecial #476                // Method org/codehaus/groovy/tools/groovydoc/SimpleGroovyFieldDoc."<init>":(Ljava/lang/String;Lorg/codehaus/groovy/groovydoc/GroovyClassDoc;)V
      94: putfield      #464                // Field currentFieldDoc:Lorg/codehaus/groovy/tools/groovydoc/SimpleGroovyFieldDoc;
      97: aload_0
      98: getfield      #464                // Field currentFieldDoc:Lorg/codehaus/groovy/tools/groovydoc/SimpleGroovyFieldDoc;
     101: aload_0
     102: aload_1
     103: invokespecial #225                // Method getJavaDocCommentsBeforeNode:(Lorg/codehaus/groovy/antlr/GroovySourceAST;)Ljava/lang/String;
     106: invokevirtual #472                // Method org/codehaus/groovy/tools/groovydoc/SimpleGroovyFieldDoc.setRawCommentText:(Ljava/lang/String;)V
     109: aload_0
     110: aload_1
     111: aload_0
     112: getfield      #464                // Field currentFieldDoc:Lorg/codehaus/groovy/tools/groovydoc/SimpleGroovyFieldDoc;
     115: invokespecial #252                // Method processModifiers:(Lorg/codehaus/groovy/antlr/GroovySourceAST;Lorg/codehaus/groovy/tools/groovydoc/SimpleGroovyAbstractableElementDoc;)Z
     118: istore        6
     120: aload_0
     121: getfield      #464                // Field currentFieldDoc:Lorg/codehaus/groovy/tools/groovydoc/SimpleGroovyFieldDoc;
     124: new           #403                // class org/codehaus/groovy/tools/groovydoc/SimpleGroovyType
     127: dup
     128: aload_0
     129: aload_1
     130: invokespecial #406                // Method getTypeOrDefault:(Lorg/codehaus/groovy/antlr/GroovySourceAST;)Ljava/lang/String;
     133: invokespecial #408                // Method org/codehaus/groovy/tools/groovydoc/SimpleGroovyType."<init>":(Ljava/lang/String;)V
     136: invokevirtual #484                // Method org/codehaus/groovy/tools/groovydoc/SimpleGroovyFieldDoc.setType:(Lorg/codehaus/groovy/groovydoc/GroovyType;)V
     139: aload_0
     140: aload_1
     141: aload_0
     142: getfield      #464                // Field currentFieldDoc:Lorg/codehaus/groovy/tools/groovydoc/SimpleGroovyFieldDoc;
     145: invokespecial #248                // Method processAnnotations:(Lorg/codehaus/groovy/antlr/GroovySourceAST;Lorg/codehaus/groovy/tools/groovydoc/SimpleGroovyProgramElementDoc;)V
     148: iload_3
     149: ifne          226
     152: aload_0
     153: getfield      #464                // Field currentFieldDoc:Lorg/codehaus/groovy/tools/groovydoc/SimpleGroovyFieldDoc;
     156: invokevirtual #501                // Method org/codehaus/groovy/tools/groovydoc/SimpleGroovyFieldDoc.annotations:()[Lorg/codehaus/groovy/groovydoc/GroovyAnnotationRef;
     159: astore        7
     161: aload         7
     163: arraylength
     164: istore        8
     166: iconst_0
     167: istore        9
     169: iload         9
     171: iload         8
     173: if_icmpge     226
     176: aload         7
     178: iload         9
     180: aaload
     181: astore        10
     183: ldc_w         #505                // String Field
     186: aload         10
     188: invokeinterface #508,  1          // InterfaceMethod org/codehaus/groovy/groovydoc/GroovyAnnotationRef.name:()Ljava/lang/String;
     193: invokevirtual #93                 // Method java/lang/String.equals:(Ljava/lang/Object;)Z
     196: ifne          215
     199: ldc_w         #510                // String groovy/transform/Field
     202: aload         10
     204: invokeinterface #508,  1          // InterfaceMethod org/codehaus/groovy/groovydoc/GroovyAnnotationRef.name:()Ljava/lang/String;
     209: invokevirtual #93                 // Method java/lang/String.equals:(Ljava/lang/Object;)Z
     212: ifeq          220
     215: iconst_1
     216: istore_3
     217: goto          226
     220: iinc          9, 1
     223: goto          169
     226: iload_3
     227: ifne          231
     230: return
     231: iload         6
     233: ifeq          249
     236: aload         4
     238: aload_0
     239: getfield      #464                // Field currentFieldDoc:Lorg/codehaus/groovy/tools/groovydoc/SimpleGroovyFieldDoc;
     242: invokevirtual #513                // Method org/codehaus/groovy/tools/groovydoc/SimpleGroovyClassDoc.addProperty:(Lorg/codehaus/groovy/groovydoc/GroovyFieldDoc;)Z
     245: pop
     246: goto          259
     249: aload         4
     251: aload_0
     252: getfield      #464                // Field currentFieldDoc:Lorg/codehaus/groovy/tools/groovydoc/SimpleGroovyFieldDoc;
     255: invokevirtual #515                // Method org/codehaus/groovy/tools/groovydoc/SimpleGroovyClassDoc.add:(Lorg/codehaus/groovy/groovydoc/GroovyFieldDoc;)Z
     258: pop
     259: return

  public void visitAssign(org.codehaus.groovy.antlr.GroovySourceAST, int);
    Code:
       0: aload_0
       1: aload_1
       2: iload_2
       3: invokespecial #524                // Method gobbleComments:(Lorg/codehaus/groovy/antlr/GroovySourceAST;I)V
       6: return

  public void visitMethodCall(org.codehaus.groovy.antlr.GroovySourceAST, int);
    Code:
       0: aload_0
       1: aload_1
       2: iload_2
       3: invokespecial #524                // Method gobbleComments:(Lorg/codehaus/groovy/antlr/GroovySourceAST;I)V
       6: return

  private void gobbleComments(org.codehaus.groovy.antlr.GroovySourceAST, int);
    Code:
       0: iload_2
       1: iconst_1
       2: if_icmpne     88
       5: aload_0
       6: invokespecial #202                // Method getCurrentClassDoc:()Lorg/codehaus/groovy/tools/groovydoc/SimpleGroovyClassDoc;
       9: astore_3
      10: aload_3
      11: ifnull        21
      14: aload_3
      15: invokevirtual #528                // Method org/codehaus/groovy/tools/groovydoc/SimpleGroovyClassDoc.isScript:()Z
      18: ifeq          88
      21: aload_1
      22: invokevirtual #531                // Method org/codehaus/groovy/antlr/GroovySourceAST.getLine:()I
      25: aload_0
      26: getfield      #113                // Field lastLineCol:Lorg/codehaus/groovy/antlr/LineColumn;
      29: invokevirtual #532                // Method org/codehaus/groovy/antlr/LineColumn.getLine:()I
      32: if_icmpgt     63
      35: aload_1
      36: invokevirtual #531                // Method org/codehaus/groovy/antlr/GroovySourceAST.getLine:()I
      39: aload_0
      40: getfield      #113                // Field lastLineCol:Lorg/codehaus/groovy/antlr/LineColumn;
      43: invokevirtual #532                // Method org/codehaus/groovy/antlr/LineColumn.getLine:()I
      46: if_icmpne     88
      49: aload_1
      50: invokevirtual #535                // Method org/codehaus/groovy/antlr/GroovySourceAST.getColumn:()I
      53: aload_0
      54: getfield      #113                // Field lastLineCol:Lorg/codehaus/groovy/antlr/LineColumn;
      57: invokevirtual #536                // Method org/codehaus/groovy/antlr/LineColumn.getColumn:()I
      60: if_icmple     88
      63: aload_0
      64: aload_1
      65: invokespecial #225                // Method getJavaDocCommentsBeforeNode:(Lorg/codehaus/groovy/antlr/GroovySourceAST;)Ljava/lang/String;
      68: pop
      69: aload_0
      70: new           #108                // class org/codehaus/groovy/antlr/LineColumn
      73: dup
      74: aload_1
      75: invokevirtual #531                // Method org/codehaus/groovy/antlr/GroovySourceAST.getLine:()I
      78: aload_1
      79: invokevirtual #535                // Method org/codehaus/groovy/antlr/GroovySourceAST.getColumn:()I
      82: invokespecial #111                // Method org/codehaus/groovy/antlr/LineColumn."<init>":(II)V
      85: putfield      #113                // Field lastLineCol:Lorg/codehaus/groovy/antlr/LineColumn;
      88: return

  private void postProcessClassDocs();
    Code:
       0: aload_0
       1: getfield      #69                 // Field classDocs:Ljava/util/Map;
       4: invokeinterface #540,  1          // InterfaceMethod java/util/Map.values:()Ljava/util/Collection;
       9: invokeinterface #543,  1          // InterfaceMethod java/util/Collection.iterator:()Ljava/util/Iterator;
      14: astore_1
      15: aload_1
      16: invokeinterface #302,  1          // InterfaceMethod java/util/Iterator.hasNext:()Z
      21: ifeq          87
      24: aload_1
      25: invokeinterface #306,  1          // InterfaceMethod java/util/Iterator.next:()Ljava/lang/Object;
      30: checkcast     #545                // class org/codehaus/groovy/groovydoc/GroovyClassDoc
      33: astore_2
      34: aload_2
      35: checkcast     #151                // class org/codehaus/groovy/tools/groovydoc/SimpleGroovyClassDoc
      38: astore_3
      39: aload_3
      40: invokevirtual #548                // Method org/codehaus/groovy/tools/groovydoc/SimpleGroovyClassDoc.isClass:()Z
      43: ifeq          84
      46: aload_3
      47: invokevirtual #552                // Method org/codehaus/groovy/tools/groovydoc/SimpleGroovyClassDoc.constructors:()[Lorg/codehaus/groovy/groovydoc/GroovyConstructorDoc;
      50: astore        4
      52: aload         4
      54: ifnull        84
      57: aload         4
      59: arraylength
      60: ifne          84
      63: new           #335                // class org/codehaus/groovy/tools/groovydoc/SimpleGroovyConstructorDoc
      66: dup
      67: aload_3
      68: invokevirtual #216                // Method org/codehaus/groovy/tools/groovydoc/SimpleGroovyClassDoc.name:()Ljava/lang/String;
      71: aload_3
      72: invokespecial #338                // Method org/codehaus/groovy/tools/groovydoc/SimpleGroovyConstructorDoc."<init>":(Ljava/lang/String;Lorg/codehaus/groovy/groovydoc/GroovyClassDoc;)V
      75: astore        5
      77: aload_3
      78: aload         5
      80: invokevirtual #346                // Method org/codehaus/groovy/tools/groovydoc/SimpleGroovyClassDoc.add:(Lorg/codehaus/groovy/groovydoc/GroovyConstructorDoc;)Z
      83: pop
      84: goto          15
      87: return

  private boolean isNested();
    Code:
       0: aload_0
       1: invokespecial #202                // Method getCurrentClassDoc:()Lorg/codehaus/groovy/tools/groovydoc/SimpleGroovyClassDoc;
       4: ifnull        11
       7: iconst_1
       8: goto          12
      11: iconst_0
      12: ireturn

  private static boolean isTopLevelConstruct(org.codehaus.groovy.antlr.GroovySourceAST);
    Code:
       0: aload_0
       1: ifnonnull     6
       4: iconst_0
       5: ireturn
       6: aload_0
       7: invokevirtual #234                // Method org/codehaus/groovy/antlr/GroovySourceAST.getType:()I
      10: istore_1
      11: iload_1
      12: bipush        13
      14: if_icmpeq     41
      17: iload_1
      18: bipush        14
      20: if_icmpeq     41
      23: iload_1
      24: bipush        15
      26: if_icmpeq     41
      29: iload_1
      30: bipush        64
      32: if_icmpeq     41
      35: iload_1
      36: bipush        61
      38: if_icmpne     45
      41: iconst_1
      42: goto          46
      45: iconst_0
      46: ireturn

  private static void adjustForAutomaticEnumMethods(org.codehaus.groovy.tools.groovydoc.SimpleGroovyClassDoc);
    Code:
       0: new           #372                // class org/codehaus/groovy/tools/groovydoc/SimpleGroovyMethodDoc
       3: dup
       4: ldc_w         #564                // String valueOf
       7: aload_0
       8: invokespecial #400                // Method org/codehaus/groovy/tools/groovydoc/SimpleGroovyMethodDoc."<init>":(Ljava/lang/String;Lorg/codehaus/groovy/groovydoc/GroovyClassDoc;)V
      11: astore_1
      12: aload_1
      13: ldc_w         #566                // String Returns the enum constant of this type with the specified name.
      16: invokevirtual #401                // Method org/codehaus/groovy/tools/groovydoc/SimpleGroovyMethodDoc.setRawCommentText:(Ljava/lang/String;)V
      19: new           #432                // class org/codehaus/groovy/tools/groovydoc/SimpleGroovyParameter
      22: dup
      23: ldc_w         #567                // String name
      26: invokespecial #435                // Method org/codehaus/groovy/tools/groovydoc/SimpleGroovyParameter."<init>":(Ljava/lang/String;)V
      29: astore_2
      30: aload_2
      31: ldc_w         #569                // String String
      34: invokevirtual #572                // Method org/codehaus/groovy/tools/groovydoc/SimpleGroovyParameter.setTypeName:(Ljava/lang/String;)V
      37: aload_1
      38: aload_2
      39: invokevirtual #443                // Method org/codehaus/groovy/tools/groovydoc/SimpleGroovyMethodDoc.add:(Lorg/codehaus/groovy/groovydoc/GroovyParameter;)V
      42: aload_1
      43: new           #403                // class org/codehaus/groovy/tools/groovydoc/SimpleGroovyType
      46: dup
      47: aload_0
      48: invokevirtual #216                // Method org/codehaus/groovy/tools/groovydoc/SimpleGroovyClassDoc.name:()Ljava/lang/String;
      51: invokespecial #408                // Method org/codehaus/groovy/tools/groovydoc/SimpleGroovyType."<init>":(Ljava/lang/String;)V
      54: invokevirtual #412                // Method org/codehaus/groovy/tools/groovydoc/SimpleGroovyMethodDoc.setReturnType:(Lorg/codehaus/groovy/groovydoc/GroovyType;)V
      57: aload_0
      58: aload_1
      59: invokevirtual #378                // Method org/codehaus/groovy/tools/groovydoc/SimpleGroovyClassDoc.add:(Lorg/codehaus/groovy/groovydoc/GroovyMethodDoc;)Z
      62: pop
      63: new           #372                // class org/codehaus/groovy/tools/groovydoc/SimpleGroovyMethodDoc
      66: dup
      67: ldc_w         #573                // String values
      70: aload_0
      71: invokespecial #400                // Method org/codehaus/groovy/tools/groovydoc/SimpleGroovyMethodDoc."<init>":(Ljava/lang/String;Lorg/codehaus/groovy/groovydoc/GroovyClassDoc;)V
      74: astore_3
      75: aload_3
      76: ldc_w         #575                // String Returns an array containing the constants of this enum type, in the order they are declared.
      79: invokevirtual #401                // Method org/codehaus/groovy/tools/groovydoc/SimpleGroovyMethodDoc.setRawCommentText:(Ljava/lang/String;)V
      82: aload_3
      83: new           #403                // class org/codehaus/groovy/tools/groovydoc/SimpleGroovyType
      86: dup
      87: new           #120                // class java/lang/StringBuilder
      90: dup
      91: invokespecial #121                // Method java/lang/StringBuilder."<init>":()V
      94: aload_0
      95: invokevirtual #216                // Method org/codehaus/groovy/tools/groovydoc/SimpleGroovyClassDoc.name:()Ljava/lang/String;
      98: invokevirtual #125                // Method java/lang/StringBuilder.append:(Ljava/lang/String;)Ljava/lang/StringBuilder;
     101: ldc_w         #577                // String []
     104: invokevirtual #125                // Method java/lang/StringBuilder.append:(Ljava/lang/String;)Ljava/lang/StringBuilder;
     107: invokevirtual #131                // Method java/lang/StringBuilder.toString:()Ljava/lang/String;
     110: invokespecial #408                // Method org/codehaus/groovy/tools/groovydoc/SimpleGroovyType."<init>":(Ljava/lang/String;)V
     113: invokevirtual #412                // Method org/codehaus/groovy/tools/groovydoc/SimpleGroovyMethodDoc.setReturnType:(Lorg/codehaus/groovy/groovydoc/GroovyType;)V
     116: aload_0
     117: aload_3
     118: invokevirtual #378                // Method org/codehaus/groovy/tools/groovydoc/SimpleGroovyClassDoc.add:(Lorg/codehaus/groovy/groovydoc/GroovyMethodDoc;)Z
     121: pop
     122: return

  private java.lang.String extractImportPath(org.codehaus.groovy.antlr.GroovySourceAST);
    Code:
       0: aload_0
       1: aload_1
       2: invokestatic  #582                // Method getPackageDotType:(Lorg/codehaus/groovy/antlr/GroovySourceAST;)Lorg/codehaus/groovy/antlr/GroovySourceAST;
       5: invokespecial #285                // Method recurseDownImportBranch:(Lorg/codehaus/groovy/antlr/GroovySourceAST;)Ljava/lang/String;
       8: areturn

  private static org.codehaus.groovy.antlr.GroovySourceAST getPackageDotType(org.codehaus.groovy.antlr.GroovySourceAST);
    Code:
       0: aload_0
       1: bipush        90
       3: invokevirtual #273                // Method org/codehaus/groovy/antlr/GroovySourceAST.childOfType:(I)Lorg/codehaus/groovy/antlr/GroovySourceAST;
       6: astore_1
       7: aload_1
       8: ifnonnull     18
      11: aload_0
      12: bipush        87
      14: invokevirtual #273                // Method org/codehaus/groovy/antlr/GroovySourceAST.childOfType:(I)Lorg/codehaus/groovy/antlr/GroovySourceAST;
      17: astore_1
      18: aload_1
      19: areturn

  private java.lang.String recurseDownImportBranch(org.codehaus.groovy.antlr.GroovySourceAST);
    Code:
       0: aload_1
       1: ifnull        89
       4: aload_1
       5: invokevirtual #234                // Method org/codehaus/groovy/antlr/GroovySourceAST.getType:()I
       8: bipush        90
      10: if_icmpne     61
      13: aload_1
      14: invokevirtual #325                // Method org/codehaus/groovy/antlr/GroovySourceAST.getFirstChild:()Lgroovyjarjarantlr/collections/AST;
      17: checkcast     #230                // class org/codehaus/groovy/antlr/GroovySourceAST
      20: astore_2
      21: aload_2
      22: invokevirtual #277                // Method org/codehaus/groovy/antlr/GroovySourceAST.getNextSibling:()Lgroovyjarjarantlr/collections/AST;
      25: checkcast     #230                // class org/codehaus/groovy/antlr/GroovySourceAST
      28: astore_3
      29: new           #120                // class java/lang/StringBuilder
      32: dup
      33: invokespecial #121                // Method java/lang/StringBuilder."<init>":()V
      36: aload_0
      37: aload_2
      38: invokespecial #285                // Method recurseDownImportBranch:(Lorg/codehaus/groovy/antlr/GroovySourceAST;)Ljava/lang/String;
      41: invokevirtual #125                // Method java/lang/StringBuilder.append:(Ljava/lang/String;)Ljava/lang/StringBuilder;
      44: ldc           #11                 // String /
      46: invokevirtual #125                // Method java/lang/StringBuilder.append:(Ljava/lang/String;)Ljava/lang/StringBuilder;
      49: aload_0
      50: aload_3
      51: invokespecial #285                // Method recurseDownImportBranch:(Lorg/codehaus/groovy/antlr/GroovySourceAST;)Ljava/lang/String;
      54: invokevirtual #125                // Method java/lang/StringBuilder.append:(Ljava/lang/String;)Ljava/lang/StringBuilder;
      57: invokevirtual #131                // Method java/lang/StringBuilder.toString:()Ljava/lang/String;
      60: areturn
      61: aload_1
      62: invokevirtual #234                // Method org/codehaus/groovy/antlr/GroovySourceAST.getType:()I
      65: bipush        87
      67: if_icmpne     75
      70: aload_1
      71: invokevirtual #583                // Method org/codehaus/groovy/antlr/GroovySourceAST.getText:()Ljava/lang/String;
      74: areturn
      75: aload_1
      76: invokevirtual #234                // Method org/codehaus/groovy/antlr/GroovySourceAST.getType:()I
      79: bipush        113
      81: if_icmpne     89
      84: aload_1
      85: invokevirtual #583                // Method org/codehaus/groovy/antlr/GroovySourceAST.getText:()Ljava/lang/String;
      88: areturn
      89: ldc_w         #585                // String
      92: areturn

  private void addAnnotationRef(org.codehaus.groovy.tools.groovydoc.SimpleGroovyProgramElementDoc, org.codehaus.groovy.antlr.GroovySourceAST);
    Code:
       0: aload_2
       1: invokestatic  #582                // Method getPackageDotType:(Lorg/codehaus/groovy/antlr/GroovySourceAST;)Lorg/codehaus/groovy/antlr/GroovySourceAST;
       4: astore_3
       5: aload_3
       6: ifnull        33
       9: aload_1
      10: new           #591                // class org/codehaus/groovy/tools/groovydoc/SimpleGroovyAnnotationRef
      13: dup
      14: aload_0
      15: aload_3
      16: invokespecial #309                // Method extractName:(Lorg/codehaus/groovy/antlr/GroovySourceAST;)Ljava/lang/String;
      19: aload_0
      20: aload_2
      21: invokespecial #594                // Method getChildTextFromSource:(Lorg/codehaus/groovy/antlr/GroovySourceAST;)Ljava/lang/String;
      24: invokevirtual #597                // Method java/lang/String.trim:()Ljava/lang/String;
      27: invokespecial #600                // Method org/codehaus/groovy/tools/groovydoc/SimpleGroovyAnnotationRef."<init>":(Ljava/lang/String;Ljava/lang/String;)V
      30: invokevirtual #605                // Method org/codehaus/groovy/tools/groovydoc/SimpleGroovyProgramElementDoc.addAnnotationRef:(Lorg/codehaus/groovy/groovydoc/GroovyAnnotationRef;)V
      33: return

  private void addAnnotationRef(org.codehaus.groovy.tools.groovydoc.SimpleGroovyParameter, org.codehaus.groovy.antlr.GroovySourceAST);
    Code:
       0: aload_2
       1: invokestatic  #582                // Method getPackageDotType:(Lorg/codehaus/groovy/antlr/GroovySourceAST;)Lorg/codehaus/groovy/antlr/GroovySourceAST;
       4: astore_3
       5: aload_3
       6: ifnull        33
       9: aload_1
      10: new           #591                // class org/codehaus/groovy/tools/groovydoc/SimpleGroovyAnnotationRef
      13: dup
      14: aload_0
      15: aload_3
      16: invokespecial #309                // Method extractName:(Lorg/codehaus/groovy/antlr/GroovySourceAST;)Ljava/lang/String;
      19: aload_0
      20: aload_2
      21: invokespecial #594                // Method getChildTextFromSource:(Lorg/codehaus/groovy/antlr/GroovySourceAST;)Ljava/lang/String;
      24: invokevirtual #597                // Method java/lang/String.trim:()Ljava/lang/String;
      27: invokespecial #600                // Method org/codehaus/groovy/tools/groovydoc/SimpleGroovyAnnotationRef."<init>":(Ljava/lang/String;Ljava/lang/String;)V
      30: invokevirtual #608                // Method org/codehaus/groovy/tools/groovydoc/SimpleGroovyParameter.addAnnotationRef:(Lorg/codehaus/groovy/groovydoc/GroovyAnnotationRef;)V
      33: return

  private void addAnnotationRefs(org.codehaus.groovy.tools.groovydoc.SimpleGroovyProgramElementDoc, java.util.List<org.codehaus.groovy.antlr.GroovySourceAST>);
    Code:
       0: aload_2
       1: invokeinterface #297,  1          // InterfaceMethod java/util/List.iterator:()Ljava/util/Iterator;
       6: astore_3
       7: aload_3
       8: invokeinterface #302,  1          // InterfaceMethod java/util/Iterator.hasNext:()Z
      13: ifeq          37
      16: aload_3
      17: invokeinterface #306,  1          // InterfaceMethod java/util/Iterator.next:()Ljava/lang/Object;
      22: checkcast     #230                // class org/codehaus/groovy/antlr/GroovySourceAST
      25: astore        4
      27: aload_0
      28: aload_1
      29: aload         4
      31: invokespecial #612                // Method addAnnotationRef:(Lorg/codehaus/groovy/tools/groovydoc/SimpleGroovyProgramElementDoc;Lorg/codehaus/groovy/antlr/GroovySourceAST;)V
      34: goto          7
      37: return

  private void processAnnotations(org.codehaus.groovy.antlr.GroovySourceAST, org.codehaus.groovy.tools.groovydoc.SimpleGroovyProgramElementDoc);
    Code:
       0: aload_1
       1: iconst_5
       2: invokevirtual #273                // Method org/codehaus/groovy/antlr/GroovySourceAST.childOfType:(I)Lorg/codehaus/groovy/antlr/GroovySourceAST;
       5: astore_3
       6: aload_3
       7: ifnull        21
      10: aload_0
      11: aload_2
      12: aload_3
      13: bipush        66
      15: invokevirtual #617                // Method org/codehaus/groovy/antlr/GroovySourceAST.childrenOfType:(I)Ljava/util/List;
      18: invokespecial #619                // Method addAnnotationRefs:(Lorg/codehaus/groovy/tools/groovydoc/SimpleGroovyProgramElementDoc;Ljava/util/List;)V
      21: return

  private java.lang.String getDefaultValue(org.codehaus.groovy.antlr.GroovySourceAST);
    Code:
       0: aload_1
       1: invokevirtual #325                // Method org/codehaus/groovy/antlr/GroovySourceAST.getFirstChild:()Lgroovyjarjarantlr/collections/AST;
       4: checkcast     #230                // class org/codehaus/groovy/antlr/GroovySourceAST
       7: astore_2
       8: aload_1
       9: invokevirtual #623                // Method org/codehaus/groovy/antlr/GroovySourceAST.getNumberOfChildren:()I
      12: iconst_4
      13: if_icmpeq     18
      16: aconst_null
      17: areturn
      18: iconst_1
      19: istore_3
      20: iload_3
      21: aload_1
      22: invokevirtual #623                // Method org/codehaus/groovy/antlr/GroovySourceAST.getNumberOfChildren:()I
      25: if_icmpge     42
      28: aload_2
      29: invokevirtual #277                // Method org/codehaus/groovy/antlr/GroovySourceAST.getNextSibling:()Lgroovyjarjarantlr/collections/AST;
      32: checkcast     #230                // class org/codehaus/groovy/antlr/GroovySourceAST
      35: astore_2
      36: iinc          3, 1
      39: goto          20
      42: aload_2
      43: astore_3
      44: aload_2
      45: invokevirtual #234                // Method org/codehaus/groovy/antlr/GroovySourceAST.getType:()I
      48: bipush        69
      50: if_icmpeq     68
      53: aload_2
      54: invokevirtual #623                // Method org/codehaus/groovy/antlr/GroovySourceAST.getNumberOfChildren:()I
      57: ifle          68
      60: aload_2
      61: invokevirtual #325                // Method org/codehaus/groovy/antlr/GroovySourceAST.getFirstChild:()Lgroovyjarjarantlr/collections/AST;
      64: checkcast     #230                // class org/codehaus/groovy/antlr/GroovySourceAST
      67: astore_3
      68: aload_0
      69: aload_3
      70: ldc_w         #625                // String ;
      73: invokespecial #627                // Method getChildTextFromSource:(Lorg/codehaus/groovy/antlr/GroovySourceAST;Ljava/lang/String;)Ljava/lang/String;
      76: areturn

  private java.lang.String getChildTextFromSource(org.codehaus.groovy.antlr.GroovySourceAST);
    Code:
       0: aload_0
       1: getfield      #49                 // Field sourceBuffer:Lorg/codehaus/groovy/antlr/SourceBuffer;
       4: new           #108                // class org/codehaus/groovy/antlr/LineColumn
       7: dup
       8: aload_1
       9: invokevirtual #531                // Method org/codehaus/groovy/antlr/GroovySourceAST.getLine:()I
      12: aload_1
      13: invokevirtual #535                // Method org/codehaus/groovy/antlr/GroovySourceAST.getColumn:()I
      16: invokespecial #111                // Method org/codehaus/groovy/antlr/LineColumn."<init>":(II)V
      19: new           #108                // class org/codehaus/groovy/antlr/LineColumn
      22: dup
      23: aload_1
      24: invokevirtual #632                // Method org/codehaus/groovy/antlr/GroovySourceAST.getLineLast:()I
      27: aload_1
      28: invokevirtual #635                // Method org/codehaus/groovy/antlr/GroovySourceAST.getColumnLast:()I
      31: invokespecial #111                // Method org/codehaus/groovy/antlr/LineColumn."<init>":(II)V
      34: invokevirtual #639                // Method org/codehaus/groovy/antlr/SourceBuffer.getSnippet:(Lorg/codehaus/groovy/antlr/LineColumn;Lorg/codehaus/groovy/antlr/LineColumn;)Ljava/lang/String;
      37: areturn

  private java.lang.String getChildTextFromSource(org.codehaus.groovy.antlr.GroovySourceAST, java.lang.String);
    Code:
       0: aload_0
       1: getfield      #49                 // Field sourceBuffer:Lorg/codehaus/groovy/antlr/SourceBuffer;
       4: new           #108                // class org/codehaus/groovy/antlr/LineColumn
       7: dup
       8: aload_1
       9: invokevirtual #531                // Method org/codehaus/groovy/antlr/GroovySourceAST.getLine:()I
      12: aload_1
      13: invokevirtual #535                // Method org/codehaus/groovy/antlr/GroovySourceAST.getColumn:()I
      16: invokespecial #111                // Method org/codehaus/groovy/antlr/LineColumn."<init>":(II)V
      19: new           #108                // class org/codehaus/groovy/antlr/LineColumn
      22: dup
      23: aload_1
      24: invokevirtual #531                // Method org/codehaus/groovy/antlr/GroovySourceAST.getLine:()I
      27: iconst_1
      28: iadd
      29: iconst_0
      30: invokespecial #111                // Method org/codehaus/groovy/antlr/LineColumn."<init>":(II)V
      33: invokevirtual #639                // Method org/codehaus/groovy/antlr/SourceBuffer.getSnippet:(Lorg/codehaus/groovy/antlr/LineColumn;Lorg/codehaus/groovy/antlr/LineColumn;)Ljava/lang/String;
      36: astore_3
      37: new           #641                // class java/util/StringTokenizer
      40: dup
      41: aload_3
      42: aload_2
      43: invokespecial #642                // Method java/util/StringTokenizer."<init>":(Ljava/lang/String;Ljava/lang/String;)V
      46: astore        4
      48: aload         4
      50: invokevirtual #645                // Method java/util/StringTokenizer.nextToken:()Ljava/lang/String;
      53: areturn

  private boolean isFieldDefinition();
    Code:
       0: aload_0
       1: invokespecial #653                // Method getParentNode:()Lorg/codehaus/groovy/antlr/GroovySourceAST;
       4: astore_1
       5: aload_1
       6: ifnull        22
       9: aload_1
      10: invokevirtual #234                // Method org/codehaus/groovy/antlr/GroovySourceAST.getType:()I
      13: bipush        6
      15: if_icmpne     22
      18: iconst_1
      19: goto          23
      22: iconst_0
      23: ireturn

  private boolean insideAnonymousInnerClass();
    Code:
       0: aload_0
       1: invokespecial #657                // Method getGrandParentNode:()Lorg/codehaus/groovy/antlr/GroovySourceAST;
       4: astore_1
       5: aload_1
       6: ifnull        23
       9: aload_1
      10: invokevirtual #234                // Method org/codehaus/groovy/antlr/GroovySourceAST.getType:()I
      13: sipush        159
      16: if_icmpne     23
      19: iconst_1
      20: goto          24
      23: iconst_0
      24: ireturn

  private boolean processModifiers(org.codehaus.groovy.antlr.GroovySourceAST, org.codehaus.groovy.tools.groovydoc.SimpleGroovyAbstractableElementDoc);
    Code:
       0: aload_1
       1: iconst_5
       2: invokevirtual #273                // Method org/codehaus/groovy/antlr/GroovySourceAST.childOfType:(I)Lorg/codehaus/groovy/antlr/GroovySourceAST;
       5: astore_3
       6: iconst_0
       7: istore        4
       9: iconst_0
      10: istore        5
      12: aload_3
      13: ifnull        337
      16: aload_3
      17: invokevirtual #325                // Method org/codehaus/groovy/antlr/GroovySourceAST.getFirstChild:()Lgroovyjarjarantlr/collections/AST;
      20: astore        6
      22: aload         6
      24: ifnull        162
      27: aload         6
      29: invokeinterface #661,  1          // InterfaceMethod groovyjarjarantlr/collections/AST.getType:()I
      34: istore        7
      36: iload         7
      38: lookupswitch  { // 6
                    38: 137
                    39: 145
                    83: 129
                   115: 118
                   116: 96
                   117: 107
               default: 150
          }
      96: aload_2
      97: iconst_1
      98: invokevirtual #662                // Method org/codehaus/groovy/tools/groovydoc/SimpleGroovyAbstractableElementDoc.setPublic:(Z)V
     101: iconst_1
     102: istore        5
     104: goto          150
     107: aload_2
     108: iconst_1
     109: invokevirtual #665                // Method org/codehaus/groovy/tools/groovydoc/SimpleGroovyAbstractableElementDoc.setProtected:(Z)V
     112: iconst_1
     113: istore        4
     115: goto          150
     118: aload_2
     119: iconst_1
     120: invokevirtual #668                // Method org/codehaus/groovy/tools/groovydoc/SimpleGroovyAbstractableElementDoc.setPrivate:(Z)V
     123: iconst_1
     124: istore        4
     126: goto          150
     129: aload_2
     130: iconst_1
     131: invokevirtual #669                // Method org/codehaus/groovy/tools/groovydoc/SimpleGroovyAbstractableElementDoc.setStatic:(Z)V
     134: goto          150
     137: aload_2
     138: iconst_1
     139: invokevirtual #672                // Method org/codehaus/groovy/tools/groovydoc/SimpleGroovyAbstractableElementDoc.setFinal:(Z)V
     142: goto          150
     145: aload_2
     146: iconst_1
     147: invokevirtual #675                // Method org/codehaus/groovy/tools/groovydoc/SimpleGroovyAbstractableElementDoc.setAbstract:(Z)V
     150: aload         6
     152: invokeinterface #326,  1          // InterfaceMethod groovyjarjarantlr/collections/AST.getNextSibling:()Lgroovyjarjarantlr/collections/AST;
     157: astore        6
     159: goto          22
     162: iload         4
     164: ifne          208
     167: aload_0
     168: getfield      #57                 // Field isGroovy:Z
     171: ifeq          208
     174: aload_2
     175: instanceof    #677                // class org/codehaus/groovy/groovydoc/GroovyFieldDoc
     178: ifne          208
     181: aload_0
     182: aload_3
     183: invokespecial #680                // Method isPackageScope:(Lorg/codehaus/groovy/antlr/GroovySourceAST;)Z
     186: ifeq          200
     189: aload_2
     190: iconst_1
     191: invokevirtual #683                // Method org/codehaus/groovy/tools/groovydoc/SimpleGroovyAbstractableElementDoc.setPackagePrivate:(Z)V
     194: iconst_1
     195: istore        4
     197: goto          254
     200: aload_2
     201: iconst_1
     202: invokevirtual #662                // Method org/codehaus/groovy/tools/groovydoc/SimpleGroovyAbstractableElementDoc.setPublic:(Z)V
     205: goto          254
     208: iload         4
     210: ifne          254
     213: iload         5
     215: ifne          254
     218: aload_0
     219: getfield      #57                 // Field isGroovy:Z
     222: ifne          254
     225: aload_0
     226: aload_2
     227: invokespecial #687                // Method insideInterface:(Lorg/codehaus/groovy/tools/groovydoc/SimpleGroovyAbstractableElementDoc;)Z
     230: ifne          241
     233: aload_0
     234: aload_2
     235: invokespecial #690                // Method insideAnnotationDef:(Lorg/codehaus/groovy/tools/groovydoc/SimpleGroovyAbstractableElementDoc;)Z
     238: ifeq          249
     241: aload_2
     242: iconst_1
     243: invokevirtual #662                // Method org/codehaus/groovy/tools/groovydoc/SimpleGroovyAbstractableElementDoc.setPublic:(Z)V
     246: goto          254
     249: aload_2
     250: iconst_1
     251: invokevirtual #683                // Method org/codehaus/groovy/tools/groovydoc/SimpleGroovyAbstractableElementDoc.setPackagePrivate:(Z)V
     254: aload_2
     255: instanceof    #677                // class org/codehaus/groovy/groovydoc/GroovyFieldDoc
     258: ifeq          308
     261: aload_0
     262: getfield      #57                 // Field isGroovy:Z
     265: ifeq          308
     268: iload         4
     270: ifne          277
     273: iconst_1
     274: goto          278
     277: iconst_0
     278: iload         5
     280: ifne          287
     283: iconst_1
     284: goto          288
     287: iconst_0
     288: iand
     289: ifeq          308
     292: aload_0
     293: aload_3
     294: invokespecial #680                // Method isPackageScope:(Lorg/codehaus/groovy/antlr/GroovySourceAST;)Z
     297: ifeq          308
     300: aload_2
     301: iconst_1
     302: invokevirtual #683                // Method org/codehaus/groovy/tools/groovydoc/SimpleGroovyAbstractableElementDoc.setPackagePrivate:(Z)V
     305: iconst_1
     306: istore        4
     308: aload_2
     309: instanceof    #677                // class org/codehaus/groovy/groovydoc/GroovyFieldDoc
     312: ifeq          334
     315: iload         4
     317: ifne          334
     320: iload         5
     322: ifne          334
     325: aload_0
     326: getfield      #57                 // Field isGroovy:Z
     329: ifeq          334
     332: iconst_1
     333: ireturn
     334: goto          395
     337: aload_0
     338: getfield      #57                 // Field isGroovy:Z
     341: ifeq          359
     344: aload_2
     345: instanceof    #677                // class org/codehaus/groovy/groovydoc/GroovyFieldDoc
     348: ifne          359
     351: aload_2
     352: iconst_1
     353: invokevirtual #662                // Method org/codehaus/groovy/tools/groovydoc/SimpleGroovyAbstractableElementDoc.setPublic:(Z)V
     356: goto          395
     359: aload_0
     360: getfield      #57                 // Field isGroovy:Z
     363: ifne          395
     366: aload_0
     367: aload_2
     368: invokespecial #687                // Method insideInterface:(Lorg/codehaus/groovy/tools/groovydoc/SimpleGroovyAbstractableElementDoc;)Z
     371: ifne          382
     374: aload_0
     375: aload_2
     376: invokespecial #690                // Method insideAnnotationDef:(Lorg/codehaus/groovy/tools/groovydoc/SimpleGroovyAbstractableElementDoc;)Z
     379: ifeq          390
     382: aload_2
     383: iconst_1
     384: invokevirtual #662                // Method org/codehaus/groovy/tools/groovydoc/SimpleGroovyAbstractableElementDoc.setPublic:(Z)V
     387: goto          395
     390: aload_2
     391: iconst_1
     392: invokevirtual #683                // Method org/codehaus/groovy/tools/groovydoc/SimpleGroovyAbstractableElementDoc.setPackagePrivate:(Z)V
     395: aload_2
     396: instanceof    #677                // class org/codehaus/groovy/groovydoc/GroovyFieldDoc
     399: ifeq          437
     402: aload_0
     403: getfield      #57                 // Field isGroovy:Z
     406: ifeq          437
     409: iload         4
     411: ifne          418
     414: iconst_1
     415: goto          419
     418: iconst_0
     419: iload         5
     421: ifne          428
     424: iconst_1
     425: goto          429
     428: iconst_0
     429: iand
     430: ifeq          437
     433: iconst_1
     434: goto          438
     437: iconst_0
     438: ireturn

  private boolean isPackageScope(org.codehaus.groovy.antlr.GroovySourceAST);
    Code:
       0: aload_0
       1: aload_1
       2: invokespecial #698                // Method getAnnotationNames:(Lorg/codehaus/groovy/antlr/GroovySourceAST;)Ljava/util/List;
       5: astore_2
       6: aload_2
       7: ldc_w         #700                // String groovy/transform/PackageScope
      10: invokeinterface #703,  2          // InterfaceMethod java/util/List.contains:(Ljava/lang/Object;)Z
      15: ifne          30
      18: aload_2
      19: ldc_w         #705                // String PackageScope
      22: invokeinterface #703,  2          // InterfaceMethod java/util/List.contains:(Ljava/lang/Object;)Z
      27: ifeq          34
      30: iconst_1
      31: goto          35
      34: iconst_0
      35: ireturn

  private java.util.List<java.lang.String> getAnnotationNames(org.codehaus.groovy.antlr.GroovySourceAST);
    Code:
       0: new           #97                 // class java/util/ArrayList
       3: dup
       4: invokespecial #98                 // Method java/util/ArrayList."<init>":()V
       7: astore_2
       8: aload_1
       9: bipush        66
      11: invokevirtual #617                // Method org/codehaus/groovy/antlr/GroovySourceAST.childrenOfType:(I)Ljava/util/List;
      14: astore_3
      15: aload_3
      16: invokeinterface #297,  1          // InterfaceMethod java/util/List.iterator:()Ljava/util/Iterator;
      21: astore        4
      23: aload         4
      25: invokeinterface #302,  1          // InterfaceMethod java/util/Iterator.hasNext:()Z
      30: ifeq          67
      33: aload         4
      35: invokeinterface #306,  1          // InterfaceMethod java/util/Iterator.next:()Ljava/lang/Object;
      40: checkcast     #230                // class org/codehaus/groovy/antlr/GroovySourceAST
      43: astore        5
      45: aload_2
      46: aload_0
      47: aload         5
      49: invokevirtual #325                // Method org/codehaus/groovy/antlr/GroovySourceAST.getFirstChild:()Lgroovyjarjarantlr/collections/AST;
      52: checkcast     #230                // class org/codehaus/groovy/antlr/GroovySourceAST
      55: invokespecial #709                // Method buildName:(Lorg/codehaus/groovy/antlr/GroovySourceAST;)Ljava/lang/String;
      58: invokeinterface #134,  2          // InterfaceMethod java/util/List.add:(Ljava/lang/Object;)Z
      63: pop
      64: goto          23
      67: aload_2
      68: areturn

  private boolean insideInterface(org.codehaus.groovy.tools.groovydoc.SimpleGroovyAbstractableElementDoc);
    Code:
       0: aload_0
       1: invokespecial #202                // Method getCurrentClassDoc:()Lorg/codehaus/groovy/tools/groovydoc/SimpleGroovyClassDoc;
       4: astore_2
       5: aload_2
       6: ifnull        14
       9: aload_2
      10: aload_1
      11: if_acmpne     16
      14: iconst_0
      15: ireturn
      16: aload_2
      17: invokevirtual #312                // Method org/codehaus/groovy/tools/groovydoc/SimpleGroovyClassDoc.isInterface:()Z
      20: ireturn

  private boolean insideAnnotationDef(org.codehaus.groovy.tools.groovydoc.SimpleGroovyAbstractableElementDoc);
    Code:
       0: aload_0
       1: invokespecial #202                // Method getCurrentClassDoc:()Lorg/codehaus/groovy/tools/groovydoc/SimpleGroovyClassDoc;
       4: astore_2
       5: aload_2
       6: ifnull        14
       9: aload_2
      10: aload_1
      11: if_acmpne     16
      14: iconst_0
      15: ireturn
      16: aload_2
      17: invokevirtual #714                // Method org/codehaus/groovy/tools/groovydoc/SimpleGroovyClassDoc.isAnnotationType:()Z
      20: ireturn

  private java.lang.String getJavaDocCommentsBeforeNode(org.codehaus.groovy.antlr.GroovySourceAST);
    Code:
       0: ldc_w         #585                // String
       3: astore_2
       4: new           #108                // class org/codehaus/groovy/antlr/LineColumn
       7: dup
       8: aload_1
       9: invokevirtual #531                // Method org/codehaus/groovy/antlr/GroovySourceAST.getLine:()I
      12: aload_1
      13: invokevirtual #535                // Method org/codehaus/groovy/antlr/GroovySourceAST.getColumn:()I
      16: invokespecial #111                // Method org/codehaus/groovy/antlr/LineColumn."<init>":(II)V
      19: astore_3
      20: aload_0
      21: getfield      #49                 // Field sourceBuffer:Lorg/codehaus/groovy/antlr/SourceBuffer;
      24: aload_0
      25: getfield      #113                // Field lastLineCol:Lorg/codehaus/groovy/antlr/LineColumn;
      28: aload_3
      29: invokevirtual #639                // Method org/codehaus/groovy/antlr/SourceBuffer.getSnippet:(Lorg/codehaus/groovy/antlr/LineColumn;Lorg/codehaus/groovy/antlr/LineColumn;)Ljava/lang/String;
      32: astore        4
      34: aload         4
      36: ifnull        64
      39: getstatic     #716                // Field PREV_JAVADOC_COMMENT_PATTERN:Ljava/util/regex/Pattern;
      42: aload         4
      44: invokevirtual #722                // Method java/util/regex/Pattern.matcher:(Ljava/lang/CharSequence;)Ljava/util/regex/Matcher;
      47: astore        5
      49: aload         5
      51: invokevirtual #727                // Method java/util/regex/Matcher.find:()Z
      54: ifeq          64
      57: aload         5
      59: iconst_1
      60: invokevirtual #731                // Method java/util/regex/Matcher.group:(I)Ljava/lang/String;
      63: astore_2
      64: aload_1
      65: invokestatic  #734                // Method isMajorType:(Lorg/codehaus/groovy/antlr/GroovySourceAST;)Z
      68: ifeq          76
      71: aload_0
      72: aload_3
      73: putfield      #113                // Field lastLineCol:Lorg/codehaus/groovy/antlr/LineColumn;
      76: aload_2
      77: areturn

  private static boolean isMajorType(org.codehaus.groovy.antlr.GroovySourceAST);
    Code:
       0: aload_0
       1: ifnonnull     6
       4: iconst_0
       5: ireturn
       6: aload_0
       7: invokevirtual #234                // Method org/codehaus/groovy/antlr/GroovySourceAST.getType:()I
      10: istore_1
      11: iload_1
      12: bipush        13
      14: if_icmpeq     71
      17: iload_1
      18: bipush        15
      20: if_icmpeq     71
      23: iload_1
      24: bipush        14
      26: if_icmpeq     71
      29: iload_1
      30: bipush        8
      32: if_icmpeq     71
      35: iload_1
      36: bipush        64
      38: if_icmpeq     71
      41: iload_1
      42: bipush        61
      44: if_icmpeq     71
      47: iload_1
      48: bipush        9
      50: if_icmpeq     71
      53: iload_1
      54: bipush        68
      56: if_icmpeq     71
      59: iload_1
      60: bipush        62
      62: if_icmpeq     71
      65: iload_1
      66: bipush        46
      68: if_icmpne     75
      71: iconst_1
      72: goto          76
      75: iconst_0
      76: ireturn

  private static java.lang.String getText(org.codehaus.groovy.antlr.GroovySourceAST);
    Code:
       0: aconst_null
       1: astore_1
       2: aload_0
       3: ifnull        11
       6: aload_0
       7: invokevirtual #583                // Method org/codehaus/groovy/antlr/GroovySourceAST.getText:()Ljava/lang/String;
      10: astore_1
      11: aload_1
      12: areturn

  private java.lang.String extractName(org.codehaus.groovy.antlr.GroovySourceAST);
    Code:
       0: aload_0
       1: aload_1
       2: invokespecial #709                // Method buildName:(Lorg/codehaus/groovy/antlr/GroovySourceAST;)Ljava/lang/String;
       5: astore_2
       6: aload_2
       7: ldc           #11                 // String /
       9: invokevirtual #743                // Method java/lang/String.contains:(Ljava/lang/CharSequence;)Z
      12: ifne          104
      15: new           #120                // class java/lang/StringBuilder
      18: dup
      19: invokespecial #121                // Method java/lang/StringBuilder."<init>":()V
      22: ldc           #11                 // String /
      24: invokevirtual #125                // Method java/lang/StringBuilder.append:(Ljava/lang/String;)Ljava/lang/StringBuilder;
      27: aload_2
      28: invokevirtual #125                // Method java/lang/StringBuilder.append:(Ljava/lang/String;)Ljava/lang/StringBuilder;
      31: invokevirtual #131                // Method java/lang/StringBuilder.toString:()Ljava/lang/String;
      34: astore_3
      35: aload_0
      36: getfield      #100                // Field importedClassesAndPackages:Ljava/util/List;
      39: invokeinterface #746,  1          // InterfaceMethod java/util/List.size:()I
      44: iconst_1
      45: isub
      46: istore        4
      48: iload         4
      50: iflt          104
      53: aload_0
      54: getfield      #100                // Field importedClassesAndPackages:Ljava/util/List;
      57: iload         4
      59: invokeinterface #749,  2          // InterfaceMethod java/util/List.get:(I)Ljava/lang/Object;
      64: checkcast     #73                 // class java/lang/String
      67: astore        5
      69: aload_0
      70: getfield      #102                // Field aliases:Ljava/util/Map;
      73: aload         5
      75: invokeinterface #752,  2          // InterfaceMethod java/util/Map.containsValue:(Ljava/lang/Object;)Z
      80: ifne          98
      83: aload         5
      85: aload_3
      86: invokevirtual #756                // Method java/lang/String.endsWith:(Ljava/lang/String;)Z
      89: ifeq          98
      92: aload         5
      94: astore_2
      95: goto          104
      98: iinc          4, -1
     101: goto          48
     104: aload_2
     105: areturn

  private java.lang.String buildName(org.codehaus.groovy.antlr.GroovySourceAST);
    Code:
       0: aload_1
       1: ifnull        75
       4: aload_1
       5: invokevirtual #234                // Method org/codehaus/groovy/antlr/GroovySourceAST.getType:()I
       8: bipush        90
      10: if_icmpne     61
      13: aload_1
      14: invokevirtual #325                // Method org/codehaus/groovy/antlr/GroovySourceAST.getFirstChild:()Lgroovyjarjarantlr/collections/AST;
      17: checkcast     #230                // class org/codehaus/groovy/antlr/GroovySourceAST
      20: astore_2
      21: aload_2
      22: invokevirtual #277                // Method org/codehaus/groovy/antlr/GroovySourceAST.getNextSibling:()Lgroovyjarjarantlr/collections/AST;
      25: checkcast     #230                // class org/codehaus/groovy/antlr/GroovySourceAST
      28: astore_3
      29: new           #120                // class java/lang/StringBuilder
      32: dup
      33: invokespecial #121                // Method java/lang/StringBuilder."<init>":()V
      36: aload_0
      37: aload_2
      38: invokespecial #709                // Method buildName:(Lorg/codehaus/groovy/antlr/GroovySourceAST;)Ljava/lang/String;
      41: invokevirtual #125                // Method java/lang/StringBuilder.append:(Ljava/lang/String;)Ljava/lang/StringBuilder;
      44: ldc           #11                 // String /
      46: invokevirtual #125                // Method java/lang/StringBuilder.append:(Ljava/lang/String;)Ljava/lang/StringBuilder;
      49: aload_0
      50: aload_3
      51: invokespecial #709                // Method buildName:(Lorg/codehaus/groovy/antlr/GroovySourceAST;)Ljava/lang/String;
      54: invokevirtual #125                // Method java/lang/StringBuilder.append:(Ljava/lang/String;)Ljava/lang/StringBuilder;
      57: invokevirtual #131                // Method java/lang/StringBuilder.toString:()Ljava/lang/String;
      60: areturn
      61: aload_1
      62: invokevirtual #234                // Method org/codehaus/groovy/antlr/GroovySourceAST.getType:()I
      65: bipush        87
      67: if_icmpne     75
      70: aload_1
      71: invokevirtual #583                // Method org/codehaus/groovy/antlr/GroovySourceAST.getText:()Ljava/lang/String;
      74: areturn
      75: ldc_w         #585                // String
      78: areturn

  private java.lang.String getTypeOrDefault(org.codehaus.groovy.antlr.GroovySourceAST);
    Code:
       0: aload_1
       1: bipush        12
       3: invokevirtual #273                // Method org/codehaus/groovy/antlr/GroovySourceAST.childOfType:(I)Lorg/codehaus/groovy/antlr/GroovySourceAST;
       6: astore_2
       7: aload_0
       8: aload_2
       9: ldc_w         #366                // String def
      12: invokespecial #483                // Method getTypeNodeAsText:(Lorg/codehaus/groovy/antlr/GroovySourceAST;Ljava/lang/String;)Ljava/lang/String;
      15: areturn

  private java.lang.String getTypeNodeAsText(org.codehaus.groovy.antlr.GroovySourceAST, java.lang.String);
    Code:
       0: aload_1
       1: ifnonnull     6
       4: aload_2
       5: areturn
       6: aload_1
       7: invokevirtual #234                // Method org/codehaus/groovy/antlr/GroovySourceAST.getType:()I
      10: bipush        12
      12: if_icmpne     22
      15: aload_0
      16: aload_1
      17: aload_2
      18: invokespecial #761                // Method getAsText:(Lorg/codehaus/groovy/antlr/GroovySourceAST;Ljava/lang/String;)Ljava/lang/String;
      21: areturn
      22: aload_1
      23: invokevirtual #234                // Method org/codehaus/groovy/antlr/GroovySourceAST.getType:()I
      26: bipush        71
      28: if_icmpne     44
      31: aload_0
      32: aload_1
      33: invokevirtual #325                // Method org/codehaus/groovy/antlr/GroovySourceAST.getFirstChild:()Lgroovyjarjarantlr/collections/AST;
      36: checkcast     #230                // class org/codehaus/groovy/antlr/GroovySourceAST
      39: aload_2
      40: invokespecial #483                // Method getTypeNodeAsText:(Lorg/codehaus/groovy/antlr/GroovySourceAST;Ljava/lang/String;)Ljava/lang/String;
      43: areturn
      44: aload_1
      45: invokevirtual #234                // Method org/codehaus/groovy/antlr/GroovySourceAST.getType:()I
      48: bipush        74
      50: if_icmpne     167
      53: aload_1
      54: invokevirtual #277                // Method org/codehaus/groovy/antlr/GroovySourceAST.getNextSibling:()Lgroovyjarjarantlr/collections/AST;
      57: astore_3
      58: aload_3
      59: ifnonnull     74
      62: aload_1
      63: invokevirtual #325                // Method org/codehaus/groovy/antlr/GroovySourceAST.getFirstChild:()Lgroovyjarjarantlr/collections/AST;
      66: ifnull        74
      69: aload_1
      70: invokevirtual #325                // Method org/codehaus/groovy/antlr/GroovySourceAST.getFirstChild:()Lgroovyjarjarantlr/collections/AST;
      73: astore_3
      74: aload_3
      75: ifnonnull     82
      78: ldc_w         #763                // String ?
      81: areturn
      82: aload_0
      83: aload_3
      84: invokeinterface #764,  1          // InterfaceMethod groovyjarjarantlr/collections/AST.getFirstChild:()Lgroovyjarjarantlr/collections/AST;
      89: checkcast     #230                // class org/codehaus/groovy/antlr/GroovySourceAST
      92: aload_2
      93: invokespecial #483                // Method getTypeNodeAsText:(Lorg/codehaus/groovy/antlr/GroovySourceAST;Ljava/lang/String;)Ljava/lang/String;
      96: astore        4
      98: aload_3
      99: invokeinterface #661,  1          // InterfaceMethod groovyjarjarantlr/collections/AST.getType:()I
     104: bipush        75
     106: if_icmpne     131
     109: new           #120                // class java/lang/StringBuilder
     112: dup
     113: invokespecial #121                // Method java/lang/StringBuilder."<init>":()V
     116: ldc_w         #766                // String ? extends
     119: invokevirtual #125                // Method java/lang/StringBuilder.append:(Ljava/lang/String;)Ljava/lang/StringBuilder;
     122: aload         4
     124: invokevirtual #125                // Method java/lang/StringBuilder.append:(Ljava/lang/String;)Ljava/lang/StringBuilder;
     127: invokevirtual #131                // Method java/lang/StringBuilder.toString:()Ljava/lang/String;
     130: areturn
     131: aload_3
     132: invokeinterface #661,  1          // InterfaceMethod groovyjarjarantlr/collections/AST.getType:()I
     137: bipush        76
     139: if_icmpne     164
     142: new           #120                // class java/lang/StringBuilder
     145: dup
     146: invokespecial #121                // Method java/lang/StringBuilder."<init>":()V
     149: ldc_w         #768                // String ? super
     152: invokevirtual #125                // Method java/lang/StringBuilder.append:(Ljava/lang/String;)Ljava/lang/StringBuilder;
     155: aload         4
     157: invokevirtual #125                // Method java/lang/StringBuilder.append:(Ljava/lang/String;)Ljava/lang/StringBuilder;
     160: invokevirtual #131                // Method java/lang/StringBuilder.toString:()Ljava/lang/String;
     163: areturn
     164: goto          307
     167: aload_1
     168: invokevirtual #234                // Method org/codehaus/groovy/antlr/GroovySourceAST.getType:()I
     171: bipush        87
     173: if_icmpne     307
     176: aload_0
     177: aload_1
     178: aload_2
     179: invokespecial #771                // Method getAsTextCurrent:(Lorg/codehaus/groovy/antlr/GroovySourceAST;Ljava/lang/String;)Ljava/lang/String;
     182: astore_3
     183: aload_1
     184: invokevirtual #277                // Method org/codehaus/groovy/antlr/GroovySourceAST.getNextSibling:()Lgroovyjarjarantlr/collections/AST;
     187: astore        4
     189: aload         4
     191: ifnonnull     207
     194: aload_1
     195: invokevirtual #325                // Method org/codehaus/groovy/antlr/GroovySourceAST.getFirstChild:()Lgroovyjarjarantlr/collections/AST;
     198: ifnull        207
     201: aload_1
     202: invokevirtual #325                // Method org/codehaus/groovy/antlr/GroovySourceAST.getFirstChild:()Lgroovyjarjarantlr/collections/AST;
     205: astore        4
     207: aload         4
     209: ifnonnull     214
     212: aload_3
     213: areturn
     214: aload_0
     215: aload         4
     217: invokeinterface #764,  1          // InterfaceMethod groovyjarjarantlr/collections/AST.getFirstChild:()Lgroovyjarjarantlr/collections/AST;
     222: checkcast     #230                // class org/codehaus/groovy/antlr/GroovySourceAST
     225: aload_2
     226: invokespecial #483                // Method getTypeNodeAsText:(Lorg/codehaus/groovy/antlr/GroovySourceAST;Ljava/lang/String;)Ljava/lang/String;
     229: astore        5
     231: aload         4
     233: invokeinterface #661,  1          // InterfaceMethod groovyjarjarantlr/collections/AST.getType:()I
     238: bipush        75
     240: if_icmpne     269
     243: new           #120                // class java/lang/StringBuilder
     246: dup
     247: invokespecial #121                // Method java/lang/StringBuilder."<init>":()V
     250: aload_3
     251: invokevirtual #125                // Method java/lang/StringBuilder.append:(Ljava/lang/String;)Ljava/lang/StringBuilder;
     254: ldc_w         #773                // String  extends
     257: invokevirtual #125                // Method java/lang/StringBuilder.append:(Ljava/lang/String;)Ljava/lang/StringBuilder;
     260: aload         5
     262: invokevirtual #125                // Method java/lang/StringBuilder.append:(Ljava/lang/String;)Ljava/lang/StringBuilder;
     265: invokevirtual #131                // Method java/lang/StringBuilder.toString:()Ljava/lang/String;
     268: areturn
     269: aload         4
     271: invokeinterface #661,  1          // InterfaceMethod groovyjarjarantlr/collections/AST.getType:()I
     276: bipush        76
     278: if_icmpne     307
     281: new           #120                // class java/lang/StringBuilder
     284: dup
     285: invokespecial #121                // Method java/lang/StringBuilder."<init>":()V
     288: aload_3
     289: invokevirtual #125                // Method java/lang/StringBuilder.append:(Ljava/lang/String;)Ljava/lang/StringBuilder;
     292: ldc_w         #775                // String  super
     295: invokevirtual #125                // Method java/lang/StringBuilder.append:(Ljava/lang/String;)Ljava/lang/StringBuilder;
     298: aload         5
     300: invokevirtual #125                // Method java/lang/StringBuilder.append:(Ljava/lang/String;)Ljava/lang/StringBuilder;
     303: invokevirtual #131                // Method java/lang/StringBuilder.toString:()Ljava/lang/String;
     306: areturn
     307: aload_2
     308: areturn

  private java.lang.String getAsText(org.codehaus.groovy.antlr.GroovySourceAST, java.lang.String);
    Code:
       0: aload_1
       1: invokevirtual #325                // Method org/codehaus/groovy/antlr/GroovySourceAST.getFirstChild:()Lgroovyjarjarantlr/collections/AST;
       4: checkcast     #230                // class org/codehaus/groovy/antlr/GroovySourceAST
       7: astore_3
       8: aload_0
       9: aload_3
      10: aload_2
      11: invokespecial #771                // Method getAsTextCurrent:(Lorg/codehaus/groovy/antlr/GroovySourceAST;Ljava/lang/String;)Ljava/lang/String;
      14: areturn

  private java.lang.String getAsTextCurrent(org.codehaus.groovy.antlr.GroovySourceAST, java.lang.String);
    Code:
       0: aload_1
       1: ifnonnull     6
       4: aload_2
       5: areturn
       6: aload_1
       7: invokevirtual #234                // Method org/codehaus/groovy/antlr/GroovySourceAST.getType:()I
      10: lookupswitch  { // 12
                    17: 152
                    87: 194
                    90: 237
                   104: 148
                   105: 116
                   106: 120
                   107: 124
                   108: 144
                   109: 136
                   110: 132
                   111: 140
                   112: 128
               default: 350
          }
     116: ldc_w         #779                // String boolean
     119: areturn
     120: ldc_w         #781                // String byte
     123: areturn
     124: ldc_w         #783                // String char
     127: areturn
     128: ldc_w         #785                // String double
     131: areturn
     132: ldc_w         #787                // String float
     135: areturn
     136: ldc_w         #789                // String int
     139: areturn
     140: ldc_w         #791                // String long
     143: areturn
     144: ldc_w         #793                // String short
     147: areturn
     148: ldc_w         #445                // String void
     151: areturn
     152: aload_0
     153: aload_1
     154: aload_2
     155: invokespecial #761                // Method getAsText:(Lorg/codehaus/groovy/antlr/GroovySourceAST;Ljava/lang/String;)Ljava/lang/String;
     158: astore_3
     159: aload_3
     160: ldc_w         #366                // String def
     163: invokevirtual #93                 // Method java/lang/String.equals:(Ljava/lang/Object;)Z
     166: ifne          190
     169: new           #120                // class java/lang/StringBuilder
     172: dup
     173: invokespecial #121                // Method java/lang/StringBuilder."<init>":()V
     176: aload_3
     177: invokevirtual #125                // Method java/lang/StringBuilder.append:(Ljava/lang/String;)Ljava/lang/StringBuilder;
     180: ldc_w         #577                // String []
     183: invokevirtual #125                // Method java/lang/StringBuilder.append:(Ljava/lang/String;)Ljava/lang/StringBuilder;
     186: invokevirtual #131                // Method java/lang/StringBuilder.toString:()Ljava/lang/String;
     189: areturn
     190: ldc_w         #795                // String java/lang/Object[]
     193: areturn
     194: new           #120                // class java/lang/StringBuilder
     197: dup
     198: invokespecial #121                // Method java/lang/StringBuilder."<init>":()V
     201: astore        4
     203: aload         4
     205: aload_1
     206: invokevirtual #583                // Method org/codehaus/groovy/antlr/GroovySourceAST.getText:()Ljava/lang/String;
     209: invokevirtual #125                // Method java/lang/StringBuilder.append:(Ljava/lang/String;)Ljava/lang/StringBuilder;
     212: pop
     213: aload_1
     214: invokevirtual #325                // Method org/codehaus/groovy/antlr/GroovySourceAST.getFirstChild:()Lgroovyjarjarantlr/collections/AST;
     217: checkcast     #230                // class org/codehaus/groovy/antlr/GroovySourceAST
     220: astore        5
     222: aload_0
     223: aload         5
     225: aload         4
     227: aload_2
     228: invokespecial #798                // Method getTypeArguments:(Lorg/codehaus/groovy/antlr/GroovySourceAST;Ljava/lang/StringBuilder;Ljava/lang/String;)V
     231: aload         4
     233: invokevirtual #131                // Method java/lang/StringBuilder.toString:()Ljava/lang/String;
     236: areturn
     237: new           #120                // class java/lang/StringBuilder
     240: dup
     241: invokespecial #121                // Method java/lang/StringBuilder."<init>":()V
     244: astore        6
     246: aload_1
     247: invokevirtual #325                // Method org/codehaus/groovy/antlr/GroovySourceAST.getFirstChild:()Lgroovyjarjarantlr/collections/AST;
     250: checkcast     #230                // class org/codehaus/groovy/antlr/GroovySourceAST
     253: astore        7
     255: aload         7
     257: ifnull        344
     260: aload         7
     262: invokevirtual #234                // Method org/codehaus/groovy/antlr/GroovySourceAST.getType:()I
     265: bipush        87
     267: if_icmpeq     280
     270: aload         7
     272: invokevirtual #234                // Method org/codehaus/groovy/antlr/GroovySourceAST.getType:()I
     275: bipush        90
     277: if_icmpne     312
     280: aload         6
     282: invokevirtual #801                // Method java/lang/StringBuilder.length:()I
     285: ifle          296
     288: aload         6
     290: ldc           #11                 // String /
     292: invokevirtual #125                // Method java/lang/StringBuilder.append:(Ljava/lang/String;)Ljava/lang/StringBuilder;
     295: pop
     296: aload         6
     298: aload_0
     299: aload         7
     301: aload_2
     302: invokespecial #771                // Method getAsTextCurrent:(Lorg/codehaus/groovy/antlr/GroovySourceAST;Ljava/lang/String;)Ljava/lang/String;
     305: invokevirtual #125                // Method java/lang/StringBuilder.append:(Ljava/lang/String;)Ljava/lang/StringBuilder;
     308: pop
     309: goto          331
     312: aload         7
     314: invokevirtual #234                // Method org/codehaus/groovy/antlr/GroovySourceAST.getType:()I
     317: bipush        70
     319: if_icmpne     331
     322: aload_0
     323: aload         7
     325: aload         6
     327: aload_2
     328: invokespecial #798                // Method getTypeArguments:(Lorg/codehaus/groovy/antlr/GroovySourceAST;Ljava/lang/StringBuilder;Ljava/lang/String;)V
     331: aload         7
     333: invokevirtual #277                // Method org/codehaus/groovy/antlr/GroovySourceAST.getNextSibling:()Lgroovyjarjarantlr/collections/AST;
     336: checkcast     #230                // class org/codehaus/groovy/antlr/GroovySourceAST
     339: astore        7
     341: goto          255
     344: aload         6
     346: invokevirtual #131                // Method java/lang/StringBuilder.toString:()Ljava/lang/String;
     349: areturn
     350: aload_2
     351: areturn

  private void getTypeArguments(org.codehaus.groovy.antlr.GroovySourceAST, java.lang.StringBuilder, java.lang.String);
    Code:
       0: aload_1
       1: ifnull        124
       4: aload_1
       5: invokevirtual #234                // Method org/codehaus/groovy/antlr/GroovySourceAST.getType:()I
       8: bipush        70
      10: if_icmpne     124
      13: aload_1
      14: invokevirtual #623                // Method org/codehaus/groovy/antlr/GroovySourceAST.getNumberOfChildren:()I
      17: ifle          124
      20: aload_2
      21: ldc_w         #807                // String <
      24: invokevirtual #125                // Method java/lang/StringBuilder.append:(Ljava/lang/String;)Ljava/lang/StringBuilder;
      27: pop
      28: aload_1
      29: invokevirtual #325                // Method org/codehaus/groovy/antlr/GroovySourceAST.getFirstChild:()Lgroovyjarjarantlr/collections/AST;
      32: checkcast     #230                // class org/codehaus/groovy/antlr/GroovySourceAST
      35: astore        4
      37: new           #97                 // class java/util/ArrayList
      40: dup
      41: invokespecial #98                 // Method java/util/ArrayList."<init>":()V
      44: astore        5
      46: aload         4
      48: ifnull        103
      51: aload         4
      53: invokevirtual #234                // Method org/codehaus/groovy/antlr/GroovySourceAST.getType:()I
      56: bipush        71
      58: if_icmpne     90
      61: aload         4
      63: invokevirtual #623                // Method org/codehaus/groovy/antlr/GroovySourceAST.getNumberOfChildren:()I
      66: ifle          90
      69: aload         5
      71: aload_0
      72: aload         4
      74: invokevirtual #325                // Method org/codehaus/groovy/antlr/GroovySourceAST.getFirstChild:()Lgroovyjarjarantlr/collections/AST;
      77: checkcast     #230                // class org/codehaus/groovy/antlr/GroovySourceAST
      80: aload_3
      81: invokespecial #483                // Method getTypeNodeAsText:(Lorg/codehaus/groovy/antlr/GroovySourceAST;Ljava/lang/String;)Ljava/lang/String;
      84: invokeinterface #134,  2          // InterfaceMethod java/util/List.add:(Ljava/lang/Object;)Z
      89: pop
      90: aload         4
      92: invokevirtual #277                // Method org/codehaus/groovy/antlr/GroovySourceAST.getNextSibling:()Lgroovyjarjarantlr/collections/AST;
      95: checkcast     #230                // class org/codehaus/groovy/antlr/GroovySourceAST
      98: astore        4
     100: goto          46
     103: aload_2
     104: aload         5
     106: ldc_w         #809                // String ,
     109: invokestatic  #815                // Method org/codehaus/groovy/runtime/DefaultGroovyMethods.join:(Ljava/util/Collection;Ljava/lang/String;)Ljava/lang/String;
     112: invokevirtual #125                // Method java/lang/StringBuilder.append:(Ljava/lang/String;)Ljava/lang/StringBuilder;
     115: pop
     116: aload_2
     117: ldc_w         #817                // String >
     120: invokevirtual #125                // Method java/lang/StringBuilder.append:(Ljava/lang/String;)Ljava/lang/StringBuilder;
     123: pop
     124: return

  private void getTypeParameters(org.codehaus.groovy.antlr.GroovySourceAST, java.lang.StringBuilder, java.lang.String);
    Code:
       0: aload_1
       1: ifnull        124
       4: aload_1
       5: invokevirtual #234                // Method org/codehaus/groovy/antlr/GroovySourceAST.getType:()I
       8: bipush        72
      10: if_icmpne     124
      13: aload_1
      14: invokevirtual #623                // Method org/codehaus/groovy/antlr/GroovySourceAST.getNumberOfChildren:()I
      17: ifle          124
      20: aload_2
      21: ldc_w         #807                // String <
      24: invokevirtual #125                // Method java/lang/StringBuilder.append:(Ljava/lang/String;)Ljava/lang/StringBuilder;
      27: pop
      28: aload_1
      29: invokevirtual #325                // Method org/codehaus/groovy/antlr/GroovySourceAST.getFirstChild:()Lgroovyjarjarantlr/collections/AST;
      32: checkcast     #230                // class org/codehaus/groovy/antlr/GroovySourceAST
      35: astore        4
      37: new           #97                 // class java/util/ArrayList
      40: dup
      41: invokespecial #98                 // Method java/util/ArrayList."<init>":()V
      44: astore        5
      46: aload         4
      48: ifnull        103
      51: aload         4
      53: invokevirtual #234                // Method org/codehaus/groovy/antlr/GroovySourceAST.getType:()I
      56: bipush        73
      58: if_icmpne     90
      61: aload         4
      63: invokevirtual #623                // Method org/codehaus/groovy/antlr/GroovySourceAST.getNumberOfChildren:()I
      66: ifle          90
      69: aload         5
      71: aload_0
      72: aload         4
      74: invokevirtual #325                // Method org/codehaus/groovy/antlr/GroovySourceAST.getFirstChild:()Lgroovyjarjarantlr/collections/AST;
      77: checkcast     #230                // class org/codehaus/groovy/antlr/GroovySourceAST
      80: aload_3
      81: invokespecial #483                // Method getTypeNodeAsText:(Lorg/codehaus/groovy/antlr/GroovySourceAST;Ljava/lang/String;)Ljava/lang/String;
      84: invokeinterface #134,  2          // InterfaceMethod java/util/List.add:(Ljava/lang/Object;)Z
      89: pop
      90: aload         4
      92: invokevirtual #277                // Method org/codehaus/groovy/antlr/GroovySourceAST.getNextSibling:()Lgroovyjarjarantlr/collections/AST;
      95: checkcast     #230                // class org/codehaus/groovy/antlr/GroovySourceAST
      98: astore        4
     100: goto          46
     103: aload_2
     104: aload         5
     106: ldc_w         #809                // String ,
     109: invokestatic  #815                // Method org/codehaus/groovy/runtime/DefaultGroovyMethods.join:(Ljava/util/Collection;Ljava/lang/String;)Ljava/lang/String;
     112: invokevirtual #125                // Method java/lang/StringBuilder.append:(Ljava/lang/String;)Ljava/lang/StringBuilder;
     115: pop
     116: aload_2
     117: ldc_w         #817                // String >
     120: invokevirtual #125                // Method java/lang/StringBuilder.append:(Ljava/lang/String;)Ljava/lang/StringBuilder;
     123: pop
     124: return

  private void addParametersTo(org.codehaus.groovy.antlr.GroovySourceAST, org.codehaus.groovy.tools.groovydoc.SimpleGroovyExecutableMemberDoc);
    Code:
       0: aload_1
       1: bipush        20
       3: invokevirtual #273                // Method org/codehaus/groovy/antlr/GroovySourceAST.childOfType:(I)Lorg/codehaus/groovy/antlr/GroovySourceAST;
       6: astore_3
       7: aload_3
       8: ifnull        190
      11: aload_3
      12: invokevirtual #623                // Method org/codehaus/groovy/antlr/GroovySourceAST.getNumberOfChildren:()I
      15: ifle          190
      18: aload_3
      19: invokevirtual #325                // Method org/codehaus/groovy/antlr/GroovySourceAST.getFirstChild:()Lgroovyjarjarantlr/collections/AST;
      22: checkcast     #230                // class org/codehaus/groovy/antlr/GroovySourceAST
      25: astore        4
      27: aload         4
      29: ifnull        190
      32: aload_0
      33: aload         4
      35: invokespecial #406                // Method getTypeOrDefault:(Lorg/codehaus/groovy/antlr/GroovySourceAST;)Ljava/lang/String;
      38: astore        5
      40: aload         4
      42: bipush        87
      44: invokevirtual #273                // Method org/codehaus/groovy/antlr/GroovySourceAST.childOfType:(I)Lorg/codehaus/groovy/antlr/GroovySourceAST;
      47: invokestatic  #823                // Method getText:(Lorg/codehaus/groovy/antlr/GroovySourceAST;)Ljava/lang/String;
      50: astore        6
      52: new           #432                // class org/codehaus/groovy/tools/groovydoc/SimpleGroovyParameter
      55: dup
      56: aload         6
      58: invokespecial #435                // Method org/codehaus/groovy/tools/groovydoc/SimpleGroovyParameter."<init>":(Ljava/lang/String;)V
      61: astore        7
      63: aload         7
      65: aload         4
      67: invokevirtual #234                // Method org/codehaus/groovy/antlr/GroovySourceAST.getType:()I
      70: bipush        47
      72: if_icmpne     79
      75: iconst_1
      76: goto          80
      79: iconst_0
      80: invokevirtual #828                // Method org/codehaus/groovy/tools/groovydoc/SimpleGroovyParameter.setVararg:(Z)V
      83: aload         7
      85: aload         5
      87: invokevirtual #572                // Method org/codehaus/groovy/tools/groovydoc/SimpleGroovyParameter.setTypeName:(Ljava/lang/String;)V
      90: aload         4
      92: iconst_5
      93: invokevirtual #273                // Method org/codehaus/groovy/antlr/GroovySourceAST.childOfType:(I)Lorg/codehaus/groovy/antlr/GroovySourceAST;
      96: astore        8
      98: aload         8
     100: ifnull        154
     103: aload         8
     105: bipush        66
     107: invokevirtual #617                // Method org/codehaus/groovy/antlr/GroovySourceAST.childrenOfType:(I)Ljava/util/List;
     110: astore        9
     112: aload         9
     114: invokeinterface #297,  1          // InterfaceMethod java/util/List.iterator:()Ljava/util/Iterator;
     119: astore        10
     121: aload         10
     123: invokeinterface #302,  1          // InterfaceMethod java/util/Iterator.hasNext:()Z
     128: ifeq          154
     131: aload         10
     133: invokeinterface #306,  1          // InterfaceMethod java/util/Iterator.next:()Ljava/lang/Object;
     138: checkcast     #230                // class org/codehaus/groovy/antlr/GroovySourceAST
     141: astore        11
     143: aload_0
     144: aload         7
     146: aload         11
     148: invokespecial #830                // Method addAnnotationRef:(Lorg/codehaus/groovy/tools/groovydoc/SimpleGroovyParameter;Lorg/codehaus/groovy/antlr/GroovySourceAST;)V
     151: goto          121
     154: aload_2
     155: aload         7
     157: invokevirtual #831                // Method org/codehaus/groovy/tools/groovydoc/SimpleGroovyExecutableMemberDoc.add:(Lorg/codehaus/groovy/groovydoc/GroovyParameter;)V
     160: aload         4
     162: invokevirtual #623                // Method org/codehaus/groovy/antlr/GroovySourceAST.getNumberOfChildren:()I
     165: iconst_4
     166: if_icmpne     177
     169: aload_0
     170: aload         4
     172: aload         7
     174: invokespecial #835                // Method handleDefaultValue:(Lorg/codehaus/groovy/antlr/GroovySourceAST;Lorg/codehaus/groovy/tools/groovydoc/SimpleGroovyParameter;)V
     177: aload         4
     179: invokevirtual #277                // Method org/codehaus/groovy/antlr/GroovySourceAST.getNextSibling:()Lgroovyjarjarantlr/collections/AST;
     182: checkcast     #230                // class org/codehaus/groovy/antlr/GroovySourceAST
     185: astore        4
     187: goto          27
     190: return

  private void handleDefaultValue(org.codehaus.groovy.antlr.GroovySourceAST, org.codehaus.groovy.tools.groovydoc.SimpleGroovyParameter);
    Code:
       0: aload_1
       1: invokevirtual #325                // Method org/codehaus/groovy/antlr/GroovySourceAST.getFirstChild:()Lgroovyjarjarantlr/collections/AST;
       4: checkcast     #230                // class org/codehaus/groovy/antlr/GroovySourceAST
       7: astore_3
       8: iconst_1
       9: istore        4
      11: iload         4
      13: aload_1
      14: invokevirtual #623                // Method org/codehaus/groovy/antlr/GroovySourceAST.getNumberOfChildren:()I
      17: if_icmpge     34
      20: aload_3
      21: invokevirtual #277                // Method org/codehaus/groovy/antlr/GroovySourceAST.getNextSibling:()Lgroovyjarjarantlr/collections/AST;
      24: checkcast     #230                // class org/codehaus/groovy/antlr/GroovySourceAST
      27: astore_3
      28: iinc          4, 1
      31: goto          11
      34: aload_3
      35: astore        4
      37: aload_3
      38: invokevirtual #623                // Method org/codehaus/groovy/antlr/GroovySourceAST.getNumberOfChildren:()I
      41: ifle          53
      44: aload_3
      45: invokevirtual #325                // Method org/codehaus/groovy/antlr/GroovySourceAST.getFirstChild:()Lgroovyjarjarantlr/collections/AST;
      48: checkcast     #230                // class org/codehaus/groovy/antlr/GroovySourceAST
      51: astore        4
      53: aload_2
      54: aload_0
      55: aload         4
      57: ldc_w         #844                // String ,)
      60: invokespecial #627                // Method getChildTextFromSource:(Lorg/codehaus/groovy/antlr/GroovySourceAST;Ljava/lang/String;)Ljava/lang/String;
      63: invokevirtual #847                // Method org/codehaus/groovy/tools/groovydoc/SimpleGroovyParameter.setDefaultValue:(Ljava/lang/String;)V
      66: return

  public void push(org.codehaus.groovy.antlr.GroovySourceAST);
    Code:
       0: aload_0
       1: getfield      #62                 // Field stack:Ljava/util/Stack;
       4: aload_1
       5: invokevirtual #852                // Method java/util/Stack.push:(Ljava/lang/Object;)Ljava/lang/Object;
       8: pop
       9: return

  public org.codehaus.groovy.antlr.GroovySourceAST pop();
    Code:
       0: aload_0
       1: getfield      #62                 // Field stack:Ljava/util/Stack;
       4: invokevirtual #856                // Method java/util/Stack.empty:()Z
       7: ifne          21
      10: aload_0
      11: getfield      #62                 // Field stack:Ljava/util/Stack;
      14: invokevirtual #858                // Method java/util/Stack.pop:()Ljava/lang/Object;
      17: checkcast     #230                // class org/codehaus/groovy/antlr/GroovySourceAST
      20: areturn
      21: aconst_null
      22: areturn

  private org.codehaus.groovy.antlr.GroovySourceAST getParentNode();
    Code:
       0: aconst_null
       1: astore_1
       2: aload_0
       3: getfield      #62                 // Field stack:Ljava/util/Stack;
       6: invokevirtual #858                // Method java/util/Stack.pop:()Ljava/lang/Object;
       9: checkcast     #230                // class org/codehaus/groovy/antlr/GroovySourceAST
      12: astore_2
      13: aload_0
      14: getfield      #62                 // Field stack:Ljava/util/Stack;
      17: invokevirtual #856                // Method java/util/Stack.empty:()Z
      20: ifne          34
      23: aload_0
      24: getfield      #62                 // Field stack:Ljava/util/Stack;
      27: invokevirtual #861                // Method java/util/Stack.peek:()Ljava/lang/Object;
      30: checkcast     #230                // class org/codehaus/groovy/antlr/GroovySourceAST
      33: astore_1
      34: aload_0
      35: getfield      #62                 // Field stack:Ljava/util/Stack;
      38: aload_2
      39: invokevirtual #852                // Method java/util/Stack.push:(Ljava/lang/Object;)Ljava/lang/Object;
      42: pop
      43: aload_1
      44: areturn

  private org.codehaus.groovy.antlr.GroovySourceAST getGrandParentNode();
    Code:
       0: aconst_null
       1: astore_1
       2: aload_0
       3: getfield      #62                 // Field stack:Ljava/util/Stack;
       6: invokevirtual #858                // Method java/util/Stack.pop:()Ljava/lang/Object;
       9: checkcast     #230                // class org/codehaus/groovy/antlr/GroovySourceAST
      12: astore_2
      13: aload_0
      14: getfield      #62                 // Field stack:Ljava/util/Stack;
      17: invokevirtual #856                // Method java/util/Stack.empty:()Z
      20: ifne          64
      23: aload_0
      24: getfield      #62                 // Field stack:Ljava/util/Stack;
      27: invokevirtual #858                // Method java/util/Stack.pop:()Ljava/lang/Object;
      30: checkcast     #230                // class org/codehaus/groovy/antlr/GroovySourceAST
      33: astore_3
      34: aload_0
      35: getfield      #62                 // Field stack:Ljava/util/Stack;
      38: invokevirtual #856                // Method java/util/Stack.empty:()Z
      41: ifne          55
      44: aload_0
      45: getfield      #62                 // Field stack:Ljava/util/Stack;
      48: invokevirtual #861                // Method java/util/Stack.peek:()Ljava/lang/Object;
      51: checkcast     #230                // class org/codehaus/groovy/antlr/GroovySourceAST
      54: astore_1
      55: aload_0
      56: getfield      #62                 // Field stack:Ljava/util/Stack;
      59: aload_3
      60: invokevirtual #852                // Method java/util/Stack.push:(Ljava/lang/Object;)Ljava/lang/Object;
      63: pop
      64: aload_0
      65: getfield      #62                 // Field stack:Ljava/util/Stack;
      68: aload_2
      69: invokevirtual #852                // Method java/util/Stack.push:(Ljava/lang/Object;)Ljava/lang/Object;
      72: pop
      73: aload_1
      74: areturn

  private org.codehaus.groovy.tools.groovydoc.SimpleGroovyClassDoc getCurrentOrTopLevelClassDoc(org.codehaus.groovy.antlr.GroovySourceAST);
    Code:
       0: aload_0
       1: invokespecial #202                // Method getCurrentClassDoc:()Lorg/codehaus/groovy/tools/groovydoc/SimpleGroovyClassDoc;
       4: astore_2
       5: aload_2
       6: ifnull        11
       9: aload_2
      10: areturn
      11: aload_0
      12: getfield      #218                // Field foundClasses:Ljava/util/Map;
      15: aload_1
      16: invokestatic  #206                // Method getIdentFor:(Lorg/codehaus/groovy/antlr/GroovySourceAST;)Ljava/lang/String;
      19: invokeinterface #222,  2          // InterfaceMethod java/util/Map.get:(Ljava/lang/Object;)Ljava/lang/Object;
      24: checkcast     #151                // class org/codehaus/groovy/tools/groovydoc/SimpleGroovyClassDoc
      27: areturn

  private org.codehaus.groovy.tools.groovydoc.SimpleGroovyClassDoc getCurrentClassDoc();
    Code:
       0: aload_0
       1: getfield      #62                 // Field stack:Ljava/util/Stack;
       4: invokevirtual #862                // Method java/util/Stack.isEmpty:()Z
       7: ifeq          12
      10: aconst_null
      11: areturn
      12: aload_0
      13: invokespecial #653                // Method getParentNode:()Lorg/codehaus/groovy/antlr/GroovySourceAST;
      16: astore_1
      17: aload_1
      18: invokestatic  #864                // Method isTopLevelConstruct:(Lorg/codehaus/groovy/antlr/GroovySourceAST;)Z
      21: ifeq          48
      24: aload_0
      25: getfield      #218                // Field foundClasses:Ljava/util/Map;
      28: ifnull        48
      31: aload_0
      32: getfield      #218                // Field foundClasses:Ljava/util/Map;
      35: aload_1
      36: invokestatic  #206                // Method getIdentFor:(Lorg/codehaus/groovy/antlr/GroovySourceAST;)Ljava/lang/String;
      39: invokeinterface #222,  2          // InterfaceMethod java/util/Map.get:(Ljava/lang/Object;)Ljava/lang/Object;
      44: checkcast     #151                // class org/codehaus/groovy/tools/groovydoc/SimpleGroovyClassDoc
      47: areturn
      48: aload_0
      49: getfield      #62                 // Field stack:Ljava/util/Stack;
      52: invokevirtual #858                // Method java/util/Stack.pop:()Ljava/lang/Object;
      55: checkcast     #230                // class org/codehaus/groovy/antlr/GroovySourceAST
      58: astore_2
      59: aload_0
      60: invokespecial #202                // Method getCurrentClassDoc:()Lorg/codehaus/groovy/tools/groovydoc/SimpleGroovyClassDoc;
      63: astore_3
      64: aload_0
      65: getfield      #62                 // Field stack:Ljava/util/Stack;
      68: aload_2
      69: invokevirtual #852                // Method java/util/Stack.push:(Ljava/lang/Object;)Ljava/lang/Object;
      72: pop
      73: aload_3
      74: areturn

  private static java.lang.String getIdentFor(org.codehaus.groovy.antlr.GroovySourceAST);
    Code:
       0: aload_0
       1: bipush        87
       3: invokevirtual #273                // Method org/codehaus/groovy/antlr/GroovySourceAST.childOfType:(I)Lorg/codehaus/groovy/antlr/GroovySourceAST;
       6: astore_1
       7: aload_1
       8: ifnonnull     17
      11: ldc_w         #585                // String
      14: goto          21
      17: aload_1
      18: invokevirtual #583                // Method org/codehaus/groovy/antlr/GroovySourceAST.getText:()Ljava/lang/String;
      21: areturn

  private java.lang.String getIdentPlusTypeArgsFor(org.codehaus.groovy.antlr.GroovySourceAST);
    Code:
       0: aload_1
       1: bipush        87
       3: invokevirtual #273                // Method org/codehaus/groovy/antlr/GroovySourceAST.childOfType:(I)Lorg/codehaus/groovy/antlr/GroovySourceAST;
       6: astore_2
       7: new           #120                // class java/lang/StringBuilder
      10: dup
      11: invokespecial #121                // Method java/lang/StringBuilder."<init>":()V
      14: astore_3
      15: aload_3
      16: aload_2
      17: invokevirtual #583                // Method org/codehaus/groovy/antlr/GroovySourceAST.getText:()Ljava/lang/String;
      20: invokevirtual #125                // Method java/lang/StringBuilder.append:(Ljava/lang/String;)Ljava/lang/StringBuilder;
      23: pop
      24: aload_2
      25: invokevirtual #277                // Method org/codehaus/groovy/antlr/GroovySourceAST.getNextSibling:()Lgroovyjarjarantlr/collections/AST;
      28: checkcast     #230                // class org/codehaus/groovy/antlr/GroovySourceAST
      31: astore        4
      33: aload_0
      34: aload         4
      36: aload_3
      37: ldc_w         #366                // String def
      40: invokespecial #370                // Method getTypeParameters:(Lorg/codehaus/groovy/antlr/GroovySourceAST;Ljava/lang/StringBuilder;Ljava/lang/String;)V
      43: aload_3
      44: invokevirtual #131                // Method java/lang/StringBuilder.toString:()Ljava/lang/String;
      47: areturn

  static {};
    Code:
       0: ldc_w         #870                // String (?s)/\\*\\*(.*?)\\*/
       3: invokestatic  #874                // Method java/util/regex/Pattern.compile:(Ljava/lang/String;)Ljava/util/regex/Pattern;
       6: putstatic     #716                // Field PREV_JAVADOC_COMMENT_PATTERN:Ljava/util/regex/Pattern;
       9: return
}
