Compiled from "ChannelOutboundBuffer.java"
final class io.netty.channel.ChannelOutboundBuffer$Entry$1 extends io.netty.util.Recycler<io.netty.channel.ChannelOutboundBuffer$Entry> {
  io.netty.channel.ChannelOutboundBuffer$Entry$1();
    Code:
       0: aload_0
       1: invokespecial #1                  // Method io/netty/util/Recycler."<init>":()V
       4: return

  protected io.netty.channel.ChannelOutboundBuffer$Entry newObject(io.netty.util.Recycler$Handle<io.netty.channel.ChannelOutboundBuffer$Entry>);
    Code:
       0: new           #2                  // class io/netty/channel/ChannelOutboundBuffer$Entry
       3: dup
       4: aload_1
       5: aconst_null
       6: invokespecial #3                  // Method io/netty/channel/ChannelOutboundBuffer$Entry."<init>":(Lio/netty/util/Recycler$Handle;Lio/netty/channel/ChannelOutboundBuffer$1;)V
       9: areturn

  protected java.lang.Object newObject(io.netty.util.Recycler$Handle);
    Code:
       0: aload_0
       1: aload_1
       2: invokevirtual #4                  // Method newObject:(Lio/netty/util/Recycler$Handle;)Lio/netty/channel/ChannelOutboundBuffer$Entry;
       5: areturn
}
