Compiled from "JsonFraming.scala"
public final class akka.stream.javadsl.JsonFraming$ {
  public static final akka.stream.javadsl.JsonFraming$ MODULE$;

  public static {};
    Code:
       0: new           #2                  // class akka/stream/javadsl/JsonFraming$
       3: invokespecial #12                 // Method "<init>":()V
       6: return

  public akka.stream.javadsl.Flow<akka.util.ByteString, akka.util.ByteString, akka.NotUsed> objectScanner(int);
    Code:
       0: getstatic     #19                 // Field akka/stream/scaladsl/JsonFraming$.MODULE$:Lakka/stream/scaladsl/JsonFraming$;
       3: iload_1
       4: invokevirtual #22                 // Method akka/stream/scaladsl/JsonFraming$.objectScanner:(I)Lakka/stream/scaladsl/Flow;
       7: invokevirtual #28                 // Method akka/stream/scaladsl/Flow.asJava:()Lakka/stream/javadsl/Flow;
      10: areturn

  private akka.stream.javadsl.JsonFraming$();
    Code:
       0: aload_0
       1: invokespecial #32                 // Method java/lang/Object."<init>":()V
       4: aload_0
       5: putstatic     #34                 // Field MODULE$:Lakka/stream/javadsl/JsonFraming$;
       8: return
}
