Compiled from "DictionaryEntityTypeEvaluator.kt"
final class ai.tock.nlp.core.service.entity.DictionaryEntityTypeEvaluator$findValue$$inlined$mapNotNull$lambda$1 extends kotlin.jvm.internal.Lambda implements kotlin.jvm.functions.Function1<java.lang.String, java.lang.Float> {
  final java.lang.String $textToCompare$inlined;

  final double $minDistance$inlined;

  final boolean $textSearch$inlined;

  ai.tock.nlp.core.service.entity.DictionaryEntityTypeEvaluator$findValue$$inlined$mapNotNull$lambda$1(java.lang.String, double, boolean);
    Code:
       0: aload_0
       1: aload_1
       2: putfield      #18                 // Field $textToCompare$inlined:Ljava/lang/String;
       5: aload_0
       6: dload_2
       7: putfield      #22                 // Field $minDistance$inlined:D
      10: aload_0
      11: iload         4
      13: putfield      #26                 // Field $textSearch$inlined:Z
      16: aload_0
      17: iconst_1
      18: invokespecial #29                 // Method kotlin/jvm/internal/Lambda."<init>":(I)V
      21: return

  public java.lang.Object invoke(java.lang.Object);
    Code:
       0: aload_0
       1: aload_1
       2: checkcast     #33                 // class java/lang/String
       5: invokevirtual #36                 // Method invoke:(Ljava/lang/String;)F
       8: invokestatic  #42                 // Method java/lang/Float.valueOf:(F)Ljava/lang/Float;
      11: areturn

  public final float invoke(java.lang.String);
    Code:
       0: aload_1
       1: ldc           #45                 // String it
       3: invokestatic  #51                 // Method kotlin/jvm/internal/Intrinsics.checkParameterIsNotNull:(Ljava/lang/Object;Ljava/lang/String;)V
       6: getstatic     #55                 // Field ai/tock/nlp/core/service/entity/DictionaryEntityTypeEvaluator.INSTANCE:Lai/tock/nlp/core/service/entity/DictionaryEntityTypeEvaluator;
       9: invokestatic  #59                 // Method ai/tock/nlp/core/service/entity/DictionaryEntityTypeEvaluator.access$getLevenshtein$p:(Lai/tock/nlp/core/service/entity/DictionaryEntityTypeEvaluator;)Lorg/simmetrics/StringMetric;
      12: aload_0
      13: getfield      #18                 // Field $textToCompare$inlined:Ljava/lang/String;
      16: aload_1
      17: invokeinterface #65,  3           // InterfaceMethod org/simmetrics/StringMetric.compare:(Ljava/lang/String;Ljava/lang/String;)F
      22: freturn
}
