Compiled from "MetamodelGraphWalker.java"
public class org.hibernate.persister.walking.spi.MetamodelGraphWalker {
  private static final org.jboss.logging.Logger log;

  private final org.hibernate.persister.walking.spi.AssociationVisitationStrategy strategy;

  private final org.hibernate.engine.spi.SessionFactoryImplementor factory;

  private org.hibernate.loader.PropertyPath currentPropertyPath;

  private final java.util.Set<org.hibernate.persister.walking.spi.AssociationKey> visitedAssociationKeys;

  public static void visitEntity(org.hibernate.persister.walking.spi.AssociationVisitationStrategy, org.hibernate.persister.entity.EntityPersister);
    Code:
       0: aload_0
       1: invokeinterface #1,  1            // InterfaceMethod org/hibernate/persister/walking/spi/AssociationVisitationStrategy.start:()V
       6: new           #2                  // class org/hibernate/persister/walking/spi/MetamodelGraphWalker
       9: dup
      10: aload_0
      11: aload_1
      12: invokeinterface #3,  1            // InterfaceMethod org/hibernate/persister/entity/EntityPersister.getFactory:()Lorg/hibernate/engine/spi/SessionFactoryImplementor;
      17: invokespecial #4                  // Method "<init>":(Lorg/hibernate/persister/walking/spi/AssociationVisitationStrategy;Lorg/hibernate/engine/spi/SessionFactoryImplementor;)V
      20: aload_1
      21: invokespecial #5                  // Method visitEntityDefinition:(Lorg/hibernate/persister/walking/spi/EntityDefinition;)V
      24: aload_0
      25: invokeinterface #6,  1            // InterfaceMethod org/hibernate/persister/walking/spi/AssociationVisitationStrategy.finish:()V
      30: goto          42
      33: astore_2
      34: aload_0
      35: invokeinterface #6,  1            // InterfaceMethod org/hibernate/persister/walking/spi/AssociationVisitationStrategy.finish:()V
      40: aload_2
      41: athrow
      42: return
    Exception table:
       from    to  target type
           6    24    33   any

  public static void visitCollection(org.hibernate.persister.walking.spi.AssociationVisitationStrategy, org.hibernate.persister.collection.CollectionPersister);
    Code:
       0: aload_0
       1: invokeinterface #1,  1            // InterfaceMethod org/hibernate/persister/walking/spi/AssociationVisitationStrategy.start:()V
       6: new           #2                  // class org/hibernate/persister/walking/spi/MetamodelGraphWalker
       9: dup
      10: aload_0
      11: aload_1
      12: invokeinterface #7,  1            // InterfaceMethod org/hibernate/persister/collection/CollectionPersister.getFactory:()Lorg/hibernate/engine/spi/SessionFactoryImplementor;
      17: invokespecial #4                  // Method "<init>":(Lorg/hibernate/persister/walking/spi/AssociationVisitationStrategy;Lorg/hibernate/engine/spi/SessionFactoryImplementor;)V
      20: aload_1
      21: invokespecial #8                  // Method visitCollectionDefinition:(Lorg/hibernate/persister/walking/spi/CollectionDefinition;)V
      24: aload_0
      25: invokeinterface #6,  1            // InterfaceMethod org/hibernate/persister/walking/spi/AssociationVisitationStrategy.finish:()V
      30: goto          42
      33: astore_2
      34: aload_0
      35: invokeinterface #6,  1            // InterfaceMethod org/hibernate/persister/walking/spi/AssociationVisitationStrategy.finish:()V
      40: aload_2
      41: athrow
      42: return
    Exception table:
       from    to  target type
           6    24    33   any

  public org.hibernate.persister.walking.spi.MetamodelGraphWalker(org.hibernate.persister.walking.spi.AssociationVisitationStrategy, org.hibernate.engine.spi.SessionFactoryImplementor);
    Code:
       0: aload_0
       1: invokespecial #9                  // Method java/lang/Object."<init>":()V
       4: aload_0
       5: new           #10                 // class org/hibernate/loader/PropertyPath
       8: dup
       9: invokespecial #11                 // Method org/hibernate/loader/PropertyPath."<init>":()V
      12: putfield      #12                 // Field currentPropertyPath:Lorg/hibernate/loader/PropertyPath;
      15: aload_0
      16: new           #13                 // class java/util/HashSet
      19: dup
      20: invokespecial #14                 // Method java/util/HashSet."<init>":()V
      23: putfield      #15                 // Field visitedAssociationKeys:Ljava/util/Set;
      26: aload_0
      27: aload_1
      28: putfield      #16                 // Field strategy:Lorg/hibernate/persister/walking/spi/AssociationVisitationStrategy;
      31: aload_0
      32: aload_2
      33: putfield      #17                 // Field factory:Lorg/hibernate/engine/spi/SessionFactoryImplementor;
      36: return

  private void visitEntityDefinition(org.hibernate.persister.walking.spi.EntityDefinition);
    Code:
       0: aload_0
       1: getfield      #16                 // Field strategy:Lorg/hibernate/persister/walking/spi/AssociationVisitationStrategy;
       4: aload_1
       5: invokeinterface #18,  2           // InterfaceMethod org/hibernate/persister/walking/spi/AssociationVisitationStrategy.startingEntity:(Lorg/hibernate/persister/walking/spi/EntityDefinition;)V
      10: aload_0
      11: aload_1
      12: invokeinterface #19,  1           // InterfaceMethod org/hibernate/persister/walking/spi/EntityDefinition.getEntityKeyDefinition:()Lorg/hibernate/persister/walking/spi/EntityIdentifierDefinition;
      17: invokespecial #20                 // Method visitIdentifierDefinition:(Lorg/hibernate/persister/walking/spi/EntityIdentifierDefinition;)V
      20: aload_0
      21: aload_1
      22: invokespecial #21                 // Method visitAttributes:(Lorg/hibernate/persister/walking/spi/AttributeSource;)V
      25: aload_0
      26: getfield      #16                 // Field strategy:Lorg/hibernate/persister/walking/spi/AssociationVisitationStrategy;
      29: aload_1
      30: invokeinterface #22,  2           // InterfaceMethod org/hibernate/persister/walking/spi/AssociationVisitationStrategy.finishingEntity:(Lorg/hibernate/persister/walking/spi/EntityDefinition;)V
      35: return

  private void visitIdentifierDefinition(org.hibernate.persister.walking.spi.EntityIdentifierDefinition);
    Code:
       0: aload_0
       1: getfield      #16                 // Field strategy:Lorg/hibernate/persister/walking/spi/AssociationVisitationStrategy;
       4: aload_1
       5: invokeinterface #23,  2           // InterfaceMethod org/hibernate/persister/walking/spi/AssociationVisitationStrategy.startingEntityIdentifier:(Lorg/hibernate/persister/walking/spi/EntityIdentifierDefinition;)V
      10: aload_1
      11: invokeinterface #24,  1           // InterfaceMethod org/hibernate/persister/walking/spi/EntityIdentifierDefinition.isEncapsulated:()Z
      16: ifeq          51
      19: aload_1
      20: checkcast     #25                 // class org/hibernate/persister/walking/spi/EncapsulatedEntityIdentifierDefinition
      23: astore_2
      24: aload_2
      25: invokeinterface #26,  1           // InterfaceMethod org/hibernate/persister/walking/spi/EncapsulatedEntityIdentifierDefinition.getAttributeDefinition:()Lorg/hibernate/persister/walking/spi/AttributeDefinition;
      30: astore_3
      31: ldc           #27                 // class org/hibernate/persister/walking/spi/CompositionDefinition
      33: aload_3
      34: invokevirtual #28                 // Method java/lang/Class.isInstance:(Ljava/lang/Object;)Z
      37: ifeq          48
      40: aload_0
      41: aload_3
      42: checkcast     #27                 // class org/hibernate/persister/walking/spi/CompositionDefinition
      45: invokespecial #29                 // Method visitCompositeDefinition:(Lorg/hibernate/persister/walking/spi/CompositionDefinition;)V
      48: goto          59
      51: aload_0
      52: aload_1
      53: checkcast     #30                 // class org/hibernate/persister/walking/spi/NonEncapsulatedEntityIdentifierDefinition
      56: invokespecial #29                 // Method visitCompositeDefinition:(Lorg/hibernate/persister/walking/spi/CompositionDefinition;)V
      59: aload_0
      60: getfield      #16                 // Field strategy:Lorg/hibernate/persister/walking/spi/AssociationVisitationStrategy;
      63: aload_1
      64: invokeinterface #31,  2           // InterfaceMethod org/hibernate/persister/walking/spi/AssociationVisitationStrategy.finishingEntityIdentifier:(Lorg/hibernate/persister/walking/spi/EntityIdentifierDefinition;)V
      69: return

  private void visitAttributes(org.hibernate.persister.walking.spi.AttributeSource);
    Code:
       0: aload_1
       1: invokeinterface #32,  1           // InterfaceMethod org/hibernate/persister/walking/spi/AttributeSource.getAttributes:()Ljava/lang/Iterable;
       6: astore_2
       7: aload_2
       8: ifnonnull     12
      11: return
      12: aload_2
      13: invokeinterface #33,  1           // InterfaceMethod java/lang/Iterable.iterator:()Ljava/util/Iterator;
      18: astore_3
      19: aload_3
      20: invokeinterface #34,  1           // InterfaceMethod java/util/Iterator.hasNext:()Z
      25: ifeq          48
      28: aload_3
      29: invokeinterface #35,  1           // InterfaceMethod java/util/Iterator.next:()Ljava/lang/Object;
      34: checkcast     #36                 // class org/hibernate/persister/walking/spi/AttributeDefinition
      37: astore        4
      39: aload_0
      40: aload         4
      42: invokespecial #37                 // Method visitAttributeDefinition:(Lorg/hibernate/persister/walking/spi/AttributeDefinition;)V
      45: goto          19
      48: return

  private void visitAttributeDefinition(org.hibernate.persister.walking.spi.AttributeDefinition);
    Code:
       0: aload_0
       1: getfield      #12                 // Field currentPropertyPath:Lorg/hibernate/loader/PropertyPath;
       4: aload_1
       5: invokeinterface #38,  1           // InterfaceMethod org/hibernate/persister/walking/spi/AttributeDefinition.getName:()Ljava/lang/String;
      10: invokevirtual #39                 // Method org/hibernate/loader/PropertyPath.append:(Ljava/lang/String;)Lorg/hibernate/loader/PropertyPath;
      13: astore_2
      14: getstatic     #40                 // Field log:Lorg/jboss/logging/Logger;
      17: new           #41                 // class java/lang/StringBuilder
      20: dup
      21: invokespecial #42                 // Method java/lang/StringBuilder."<init>":()V
      24: ldc           #43                 // String Visiting attribute path :
      26: invokevirtual #44                 // Method java/lang/StringBuilder.append:(Ljava/lang/String;)Ljava/lang/StringBuilder;
      29: aload_2
      30: invokevirtual #45                 // Method org/hibernate/loader/PropertyPath.getFullPath:()Ljava/lang/String;
      33: invokevirtual #44                 // Method java/lang/StringBuilder.append:(Ljava/lang/String;)Ljava/lang/StringBuilder;
      36: invokevirtual #46                 // Method java/lang/StringBuilder.toString:()Ljava/lang/String;
      39: invokevirtual #47                 // Method org/jboss/logging/Logger.debug:(Ljava/lang/Object;)V
      42: aload_1
      43: invokeinterface #48,  1           // InterfaceMethod org/hibernate/persister/walking/spi/AttributeDefinition.getType:()Lorg/hibernate/type/Type;
      48: invokeinterface #49,  1           // InterfaceMethod org/hibernate/type/Type.isAssociationType:()Z
      53: ifeq          117
      56: aload_1
      57: checkcast     #50                 // class org/hibernate/persister/walking/spi/AssociationAttributeDefinition
      60: astore_3
      61: aload_3
      62: invokeinterface #51,  1           // InterfaceMethod org/hibernate/persister/walking/spi/AssociationAttributeDefinition.getAssociationKey:()Lorg/hibernate/persister/walking/spi/AssociationKey;
      67: astore        4
      69: aload_0
      70: aload         4
      72: invokevirtual #52                 // Method isDuplicateAssociationKey:(Lorg/hibernate/persister/walking/spi/AssociationKey;)Z
      75: ifeq          117
      78: getstatic     #40                 // Field log:Lorg/jboss/logging/Logger;
      81: new           #41                 // class java/lang/StringBuilder
      84: dup
      85: invokespecial #42                 // Method java/lang/StringBuilder."<init>":()V
      88: ldc           #53                 // String Property path deemed to be circular :
      90: invokevirtual #44                 // Method java/lang/StringBuilder.append:(Ljava/lang/String;)Ljava/lang/StringBuilder;
      93: aload_2
      94: invokevirtual #45                 // Method org/hibernate/loader/PropertyPath.getFullPath:()Ljava/lang/String;
      97: invokevirtual #44                 // Method java/lang/StringBuilder.append:(Ljava/lang/String;)Ljava/lang/StringBuilder;
     100: invokevirtual #46                 // Method java/lang/StringBuilder.toString:()Ljava/lang/String;
     103: invokevirtual #47                 // Method org/jboss/logging/Logger.debug:(Ljava/lang/Object;)V
     106: aload_0
     107: getfield      #16                 // Field strategy:Lorg/hibernate/persister/walking/spi/AssociationVisitationStrategy;
     110: aload_3
     111: invokeinterface #54,  2           // InterfaceMethod org/hibernate/persister/walking/spi/AssociationVisitationStrategy.foundCircularAssociation:(Lorg/hibernate/persister/walking/spi/AssociationAttributeDefinition;)V
     116: return
     117: aload_0
     118: getfield      #16                 // Field strategy:Lorg/hibernate/persister/walking/spi/AssociationVisitationStrategy;
     121: aload_1
     122: invokeinterface #55,  2           // InterfaceMethod org/hibernate/persister/walking/spi/AssociationVisitationStrategy.startingAttribute:(Lorg/hibernate/persister/walking/spi/AttributeDefinition;)Z
     127: istore_3
     128: iload_3
     129: ifeq          210
     132: aload_0
     133: getfield      #12                 // Field currentPropertyPath:Lorg/hibernate/loader/PropertyPath;
     136: astore        4
     138: aload_0
     139: aload_2
     140: putfield      #12                 // Field currentPropertyPath:Lorg/hibernate/loader/PropertyPath;
     143: aload_1
     144: invokeinterface #48,  1           // InterfaceMethod org/hibernate/persister/walking/spi/AttributeDefinition.getType:()Lorg/hibernate/type/Type;
     149: astore        5
     151: aload         5
     153: invokeinterface #49,  1           // InterfaceMethod org/hibernate/type/Type.isAssociationType:()Z
     158: ifeq          172
     161: aload_0
     162: aload_1
     163: checkcast     #50                 // class org/hibernate/persister/walking/spi/AssociationAttributeDefinition
     166: invokespecial #56                 // Method visitAssociation:(Lorg/hibernate/persister/walking/spi/AssociationAttributeDefinition;)V
     169: goto          190
     172: aload         5
     174: invokeinterface #57,  1           // InterfaceMethod org/hibernate/type/Type.isComponentType:()Z
     179: ifeq          190
     182: aload_0
     183: aload_1
     184: checkcast     #27                 // class org/hibernate/persister/walking/spi/CompositionDefinition
     187: invokespecial #29                 // Method visitCompositeDefinition:(Lorg/hibernate/persister/walking/spi/CompositionDefinition;)V
     190: aload_0
     191: aload         4
     193: putfield      #12                 // Field currentPropertyPath:Lorg/hibernate/loader/PropertyPath;
     196: goto          210
     199: astore        6
     201: aload_0
     202: aload         4
     204: putfield      #12                 // Field currentPropertyPath:Lorg/hibernate/loader/PropertyPath;
     207: aload         6
     209: athrow
     210: aload_0
     211: getfield      #16                 // Field strategy:Lorg/hibernate/persister/walking/spi/AssociationVisitationStrategy;
     214: aload_1
     215: invokeinterface #58,  2           // InterfaceMethod org/hibernate/persister/walking/spi/AssociationVisitationStrategy.finishingAttribute:(Lorg/hibernate/persister/walking/spi/AttributeDefinition;)V
     220: return
    Exception table:
       from    to  target type
         143   190   199   any
         199   201   199   any

  private void visitAssociation(org.hibernate.persister.walking.spi.AssociationAttributeDefinition);
    Code:
       0: aload_0
       1: aload_1
       2: invokeinterface #51,  1           // InterfaceMethod org/hibernate/persister/walking/spi/AssociationAttributeDefinition.getAssociationKey:()Lorg/hibernate/persister/walking/spi/AssociationKey;
       7: invokevirtual #59                 // Method addAssociationKey:(Lorg/hibernate/persister/walking/spi/AssociationKey;)V
      10: aload_1
      11: invokeinterface #60,  1           // InterfaceMethod org/hibernate/persister/walking/spi/AssociationAttributeDefinition.getAssociationNature:()Lorg/hibernate/persister/walking/spi/AssociationAttributeDefinition$AssociationNature;
      16: astore_2
      17: aload_2
      18: getstatic     #61                 // Field org/hibernate/persister/walking/spi/AssociationAttributeDefinition$AssociationNature.ANY:Lorg/hibernate/persister/walking/spi/AssociationAttributeDefinition$AssociationNature;
      21: if_acmpne     37
      24: aload_0
      25: aload_1
      26: invokeinterface #62,  1           // InterfaceMethod org/hibernate/persister/walking/spi/AssociationAttributeDefinition.toAnyDefinition:()Lorg/hibernate/persister/walking/spi/AnyMappingDefinition;
      31: invokespecial #63                 // Method visitAnyDefinition:(Lorg/hibernate/persister/walking/spi/AnyMappingDefinition;)V
      34: goto          67
      37: aload_2
      38: getstatic     #64                 // Field org/hibernate/persister/walking/spi/AssociationAttributeDefinition$AssociationNature.COLLECTION:Lorg/hibernate/persister/walking/spi/AssociationAttributeDefinition$AssociationNature;
      41: if_acmpne     57
      44: aload_0
      45: aload_1
      46: invokeinterface #65,  1           // InterfaceMethod org/hibernate/persister/walking/spi/AssociationAttributeDefinition.toCollectionDefinition:()Lorg/hibernate/persister/walking/spi/CollectionDefinition;
      51: invokespecial #8                  // Method visitCollectionDefinition:(Lorg/hibernate/persister/walking/spi/CollectionDefinition;)V
      54: goto          67
      57: aload_0
      58: aload_1
      59: invokeinterface #66,  1           // InterfaceMethod org/hibernate/persister/walking/spi/AssociationAttributeDefinition.toEntityDefinition:()Lorg/hibernate/persister/walking/spi/EntityDefinition;
      64: invokespecial #5                  // Method visitEntityDefinition:(Lorg/hibernate/persister/walking/spi/EntityDefinition;)V
      67: return

  private void visitAnyDefinition(org.hibernate.persister.walking.spi.AnyMappingDefinition);
    Code:
       0: aload_0
       1: getfield      #16                 // Field strategy:Lorg/hibernate/persister/walking/spi/AssociationVisitationStrategy;
       4: aload_1
       5: invokeinterface #67,  2           // InterfaceMethod org/hibernate/persister/walking/spi/AssociationVisitationStrategy.foundAny:(Lorg/hibernate/persister/walking/spi/AnyMappingDefinition;)V
      10: return

  private void visitCompositeDefinition(org.hibernate.persister.walking.spi.CompositionDefinition);
    Code:
       0: aload_0
       1: getfield      #16                 // Field strategy:Lorg/hibernate/persister/walking/spi/AssociationVisitationStrategy;
       4: aload_1
       5: invokeinterface #68,  2           // InterfaceMethod org/hibernate/persister/walking/spi/AssociationVisitationStrategy.startingComposite:(Lorg/hibernate/persister/walking/spi/CompositionDefinition;)V
      10: aload_0
      11: aload_1
      12: invokespecial #21                 // Method visitAttributes:(Lorg/hibernate/persister/walking/spi/AttributeSource;)V
      15: aload_0
      16: getfield      #16                 // Field strategy:Lorg/hibernate/persister/walking/spi/AssociationVisitationStrategy;
      19: aload_1
      20: invokeinterface #69,  2           // InterfaceMethod org/hibernate/persister/walking/spi/AssociationVisitationStrategy.finishingComposite:(Lorg/hibernate/persister/walking/spi/CompositionDefinition;)V
      25: return

  private void visitCollectionDefinition(org.hibernate.persister.walking.spi.CollectionDefinition);
    Code:
       0: aload_0
       1: getfield      #16                 // Field strategy:Lorg/hibernate/persister/walking/spi/AssociationVisitationStrategy;
       4: aload_1
       5: invokeinterface #70,  2           // InterfaceMethod org/hibernate/persister/walking/spi/AssociationVisitationStrategy.startingCollection:(Lorg/hibernate/persister/walking/spi/CollectionDefinition;)V
      10: aload_0
      11: aload_1
      12: invokespecial #71                 // Method visitCollectionIndex:(Lorg/hibernate/persister/walking/spi/CollectionDefinition;)V
      15: aload_0
      16: aload_1
      17: invokespecial #72                 // Method visitCollectionElements:(Lorg/hibernate/persister/walking/spi/CollectionDefinition;)V
      20: aload_0
      21: getfield      #16                 // Field strategy:Lorg/hibernate/persister/walking/spi/AssociationVisitationStrategy;
      24: aload_1
      25: invokeinterface #73,  2           // InterfaceMethod org/hibernate/persister/walking/spi/AssociationVisitationStrategy.finishingCollection:(Lorg/hibernate/persister/walking/spi/CollectionDefinition;)V
      30: return

  private void visitCollectionIndex(org.hibernate.persister.walking.spi.CollectionDefinition);
    Code:
       0: aload_1
       1: invokeinterface #74,  1           // InterfaceMethod org/hibernate/persister/walking/spi/CollectionDefinition.getIndexDefinition:()Lorg/hibernate/persister/walking/spi/CollectionIndexDefinition;
       6: astore_2
       7: aload_2
       8: ifnonnull     12
      11: return
      12: aload_0
      13: getfield      #16                 // Field strategy:Lorg/hibernate/persister/walking/spi/AssociationVisitationStrategy;
      16: aload_2
      17: invokeinterface #75,  2           // InterfaceMethod org/hibernate/persister/walking/spi/AssociationVisitationStrategy.startingCollectionIndex:(Lorg/hibernate/persister/walking/spi/CollectionIndexDefinition;)V
      22: getstatic     #40                 // Field log:Lorg/jboss/logging/Logger;
      25: new           #41                 // class java/lang/StringBuilder
      28: dup
      29: invokespecial #42                 // Method java/lang/StringBuilder."<init>":()V
      32: ldc           #76                 // String Visiting index for collection :
      34: invokevirtual #44                 // Method java/lang/StringBuilder.append:(Ljava/lang/String;)Ljava/lang/StringBuilder;
      37: aload_0
      38: getfield      #12                 // Field currentPropertyPath:Lorg/hibernate/loader/PropertyPath;
      41: invokevirtual #45                 // Method org/hibernate/loader/PropertyPath.getFullPath:()Ljava/lang/String;
      44: invokevirtual #44                 // Method java/lang/StringBuilder.append:(Ljava/lang/String;)Ljava/lang/StringBuilder;
      47: invokevirtual #46                 // Method java/lang/StringBuilder.toString:()Ljava/lang/String;
      50: invokevirtual #47                 // Method org/jboss/logging/Logger.debug:(Ljava/lang/Object;)V
      53: aload_0
      54: aload_0
      55: getfield      #12                 // Field currentPropertyPath:Lorg/hibernate/loader/PropertyPath;
      58: ldc           #77                 // String <index>
      60: invokevirtual #39                 // Method org/hibernate/loader/PropertyPath.append:(Ljava/lang/String;)Lorg/hibernate/loader/PropertyPath;
      63: putfield      #12                 // Field currentPropertyPath:Lorg/hibernate/loader/PropertyPath;
      66: aload_2
      67: invokeinterface #78,  1           // InterfaceMethod org/hibernate/persister/walking/spi/CollectionIndexDefinition.getType:()Lorg/hibernate/type/Type;
      72: astore_3
      73: aload_3
      74: invokeinterface #79,  1           // InterfaceMethod org/hibernate/type/Type.isAnyType:()Z
      79: ifeq          95
      82: aload_0
      83: aload_2
      84: invokeinterface #80,  1           // InterfaceMethod org/hibernate/persister/walking/spi/CollectionIndexDefinition.toAnyMappingDefinition:()Lorg/hibernate/persister/walking/spi/AnyMappingDefinition;
      89: invokespecial #63                 // Method visitAnyDefinition:(Lorg/hibernate/persister/walking/spi/AnyMappingDefinition;)V
      92: goto          136
      95: aload_3
      96: invokeinterface #57,  1           // InterfaceMethod org/hibernate/type/Type.isComponentType:()Z
     101: ifeq          117
     104: aload_0
     105: aload_2
     106: invokeinterface #81,  1           // InterfaceMethod org/hibernate/persister/walking/spi/CollectionIndexDefinition.toCompositeDefinition:()Lorg/hibernate/persister/walking/spi/CompositionDefinition;
     111: invokespecial #29                 // Method visitCompositeDefinition:(Lorg/hibernate/persister/walking/spi/CompositionDefinition;)V
     114: goto          136
     117: aload_3
     118: invokeinterface #49,  1           // InterfaceMethod org/hibernate/type/Type.isAssociationType:()Z
     123: ifeq          136
     126: aload_0
     127: aload_2
     128: invokeinterface #82,  1           // InterfaceMethod org/hibernate/persister/walking/spi/CollectionIndexDefinition.toEntityDefinition:()Lorg/hibernate/persister/walking/spi/EntityDefinition;
     133: invokespecial #5                  // Method visitEntityDefinition:(Lorg/hibernate/persister/walking/spi/EntityDefinition;)V
     136: aload_0
     137: aload_0
     138: getfield      #12                 // Field currentPropertyPath:Lorg/hibernate/loader/PropertyPath;
     141: invokevirtual #83                 // Method org/hibernate/loader/PropertyPath.getParent:()Lorg/hibernate/loader/PropertyPath;
     144: putfield      #12                 // Field currentPropertyPath:Lorg/hibernate/loader/PropertyPath;
     147: goto          166
     150: astore        4
     152: aload_0
     153: aload_0
     154: getfield      #12                 // Field currentPropertyPath:Lorg/hibernate/loader/PropertyPath;
     157: invokevirtual #83                 // Method org/hibernate/loader/PropertyPath.getParent:()Lorg/hibernate/loader/PropertyPath;
     160: putfield      #12                 // Field currentPropertyPath:Lorg/hibernate/loader/PropertyPath;
     163: aload         4
     165: athrow
     166: aload_0
     167: getfield      #16                 // Field strategy:Lorg/hibernate/persister/walking/spi/AssociationVisitationStrategy;
     170: aload_2
     171: invokeinterface #84,  2           // InterfaceMethod org/hibernate/persister/walking/spi/AssociationVisitationStrategy.finishingCollectionIndex:(Lorg/hibernate/persister/walking/spi/CollectionIndexDefinition;)V
     176: return
    Exception table:
       from    to  target type
          66   136   150   any
         150   152   150   any

  private void visitCollectionElements(org.hibernate.persister.walking.spi.CollectionDefinition);
    Code:
       0: aload_1
       1: invokeinterface #85,  1           // InterfaceMethod org/hibernate/persister/walking/spi/CollectionDefinition.getElementDefinition:()Lorg/hibernate/persister/walking/spi/CollectionElementDefinition;
       6: astore_2
       7: aload_0
       8: getfield      #16                 // Field strategy:Lorg/hibernate/persister/walking/spi/AssociationVisitationStrategy;
      11: aload_2
      12: invokeinterface #86,  2           // InterfaceMethod org/hibernate/persister/walking/spi/AssociationVisitationStrategy.startingCollectionElements:(Lorg/hibernate/persister/walking/spi/CollectionElementDefinition;)V
      17: aload_2
      18: invokeinterface #87,  1           // InterfaceMethod org/hibernate/persister/walking/spi/CollectionElementDefinition.getType:()Lorg/hibernate/type/Type;
      23: astore_3
      24: aload_3
      25: invokeinterface #79,  1           // InterfaceMethod org/hibernate/type/Type.isAnyType:()Z
      30: ifeq          46
      33: aload_0
      34: aload_2
      35: invokeinterface #88,  1           // InterfaceMethod org/hibernate/persister/walking/spi/CollectionElementDefinition.toAnyMappingDefinition:()Lorg/hibernate/persister/walking/spi/AnyMappingDefinition;
      40: invokespecial #63                 // Method visitAnyDefinition:(Lorg/hibernate/persister/walking/spi/AnyMappingDefinition;)V
      43: goto          137
      46: aload_3
      47: invokeinterface #57,  1           // InterfaceMethod org/hibernate/type/Type.isComponentType:()Z
      52: ifeq          68
      55: aload_0
      56: aload_2
      57: invokeinterface #89,  1           // InterfaceMethod org/hibernate/persister/walking/spi/CollectionElementDefinition.toCompositeElementDefinition:()Lorg/hibernate/persister/walking/spi/CompositeCollectionElementDefinition;
      62: invokespecial #29                 // Method visitCompositeDefinition:(Lorg/hibernate/persister/walking/spi/CompositionDefinition;)V
      65: goto          137
      68: aload_3
      69: invokeinterface #90,  1           // InterfaceMethod org/hibernate/type/Type.isEntityType:()Z
      74: ifeq          137
      77: aload_1
      78: invokeinterface #91,  1           // InterfaceMethod org/hibernate/persister/walking/spi/CollectionDefinition.getCollectionPersister:()Lorg/hibernate/persister/collection/CollectionPersister;
      83: invokeinterface #92,  1           // InterfaceMethod org/hibernate/persister/collection/CollectionPersister.isOneToMany:()Z
      88: ifne          127
      91: aload_1
      92: invokeinterface #91,  1           // InterfaceMethod org/hibernate/persister/walking/spi/CollectionDefinition.getCollectionPersister:()Lorg/hibernate/persister/collection/CollectionPersister;
      97: checkcast     #93                 // class org/hibernate/persister/collection/QueryableCollection
     100: astore        4
     102: aload_0
     103: new           #94                 // class org/hibernate/persister/walking/spi/AssociationKey
     106: dup
     107: aload         4
     109: invokeinterface #95,  1           // InterfaceMethod org/hibernate/persister/collection/QueryableCollection.getTableName:()Ljava/lang/String;
     114: aload         4
     116: invokeinterface #96,  1           // InterfaceMethod org/hibernate/persister/collection/QueryableCollection.getElementColumnNames:()[Ljava/lang/String;
     121: invokespecial #97                 // Method org/hibernate/persister/walking/spi/AssociationKey."<init>":(Ljava/lang/String;[Ljava/lang/String;)V
     124: invokevirtual #59                 // Method addAssociationKey:(Lorg/hibernate/persister/walking/spi/AssociationKey;)V
     127: aload_0
     128: aload_2
     129: invokeinterface #98,  1           // InterfaceMethod org/hibernate/persister/walking/spi/CollectionElementDefinition.toEntityDefinition:()Lorg/hibernate/persister/walking/spi/EntityDefinition;
     134: invokespecial #5                  // Method visitEntityDefinition:(Lorg/hibernate/persister/walking/spi/EntityDefinition;)V
     137: aload_0
     138: getfield      #16                 // Field strategy:Lorg/hibernate/persister/walking/spi/AssociationVisitationStrategy;
     141: aload_2
     142: invokeinterface #99,  2           // InterfaceMethod org/hibernate/persister/walking/spi/AssociationVisitationStrategy.finishingCollectionElements:(Lorg/hibernate/persister/walking/spi/CollectionElementDefinition;)V
     147: return

  protected void addAssociationKey(org.hibernate.persister.walking.spi.AssociationKey);
    Code:
       0: aload_0
       1: getfield      #15                 // Field visitedAssociationKeys:Ljava/util/Set;
       4: aload_1
       5: invokeinterface #100,  2          // InterfaceMethod java/util/Set.add:(Ljava/lang/Object;)Z
      10: ifne          34
      13: new           #101                // class org/hibernate/persister/walking/spi/WalkingException
      16: dup
      17: ldc           #102                // String Association has already been visited: %s
      19: iconst_1
      20: anewarray     #103                // class java/lang/Object
      23: dup
      24: iconst_0
      25: aload_1
      26: aastore
      27: invokestatic  #104                // Method java/lang/String.format:(Ljava/lang/String;[Ljava/lang/Object;)Ljava/lang/String;
      30: invokespecial #105                // Method org/hibernate/persister/walking/spi/WalkingException."<init>":(Ljava/lang/String;)V
      33: athrow
      34: aload_0
      35: getfield      #16                 // Field strategy:Lorg/hibernate/persister/walking/spi/AssociationVisitationStrategy;
      38: aload_1
      39: invokeinterface #106,  2          // InterfaceMethod org/hibernate/persister/walking/spi/AssociationVisitationStrategy.associationKeyRegistered:(Lorg/hibernate/persister/walking/spi/AssociationKey;)V
      44: return

  protected boolean isDuplicateAssociationKey(org.hibernate.persister.walking.spi.AssociationKey);
    Code:
       0: aload_0
       1: getfield      #15                 // Field visitedAssociationKeys:Ljava/util/Set;
       4: aload_1
       5: invokeinterface #107,  2          // InterfaceMethod java/util/Set.contains:(Ljava/lang/Object;)Z
      10: ifne          26
      13: aload_0
      14: getfield      #16                 // Field strategy:Lorg/hibernate/persister/walking/spi/AssociationVisitationStrategy;
      17: aload_1
      18: invokeinterface #108,  2          // InterfaceMethod org/hibernate/persister/walking/spi/AssociationVisitationStrategy.isDuplicateAssociationKey:(Lorg/hibernate/persister/walking/spi/AssociationKey;)Z
      23: ifeq          30
      26: iconst_1
      27: goto          31
      30: iconst_0
      31: ireturn

  static {};
    Code:
       0: ldc           #2                  // class org/hibernate/persister/walking/spi/MetamodelGraphWalker
       2: invokestatic  #109                // Method org/jboss/logging/Logger.getLogger:(Ljava/lang/Class;)Lorg/jboss/logging/Logger;
       5: putstatic     #40                 // Field log:Lorg/jboss/logging/Logger;
       8: return
}
