Compiled from "NetworkMessages_$bundle.java"
public class org.jboss.as.network.logging.NetworkMessages_$bundle implements org.jboss.as.network.logging.NetworkMessages,java.io.Serializable {
  private static final long serialVersionUID;

  public static final org.jboss.as.network.logging.NetworkMessages_$bundle INSTANCE;

  private static final java.lang.String cannotChangeWhileBound;

  private static final java.lang.String noMulticastBinding;

  private static final java.lang.String nullOrEmptyVar;

  private static final java.lang.String nullOutboundSocketBindingParam;

  private static final java.lang.String nullDestinationAddress;

  private static final java.lang.String negativeDestinationPort;

  protected org.jboss.as.network.logging.NetworkMessages_$bundle();
    Code:
       0: aload_0
       1: invokespecial #1                  // Method java/lang/Object."<init>":()V
       4: return

  protected java.lang.Object readResolve();
    Code:
       0: getstatic     #2                  // Field INSTANCE:Lorg/jboss/as/network/logging/NetworkMessages_$bundle;
       3: areturn

  protected java.lang.String cannotChangeWhileBound$str();
    Code:
       0: ldc           #4                  // String WFLYNET0001: cannot change value while the socket is bound.
       2: areturn

  public final java.lang.IllegalStateException cannotChangeWhileBound();
    Code:
       0: new           #5                  // class java/lang/IllegalStateException
       3: dup
       4: aload_0
       5: invokevirtual #6                  // Method cannotChangeWhileBound$str:()Ljava/lang/String;
       8: iconst_0
       9: anewarray     #7                  // class java/lang/Object
      12: invokestatic  #8                  // Method java/lang/String.format:(Ljava/lang/String;[Ljava/lang/Object;)Ljava/lang/String;
      15: invokespecial #9                  // Method java/lang/IllegalStateException."<init>":(Ljava/lang/String;)V
      18: astore_1
      19: aload_1
      20: invokevirtual #10                 // Method java/lang/IllegalStateException.getStackTrace:()[Ljava/lang/StackTraceElement;
      23: astore_2
      24: aload_1
      25: aload_2
      26: iconst_1
      27: aload_2
      28: arraylength
      29: invokestatic  #11                 // Method java/util/Arrays.copyOfRange:([Ljava/lang/Object;II)[Ljava/lang/Object;
      32: checkcast     #12                 // class "[Ljava/lang/StackTraceElement;"
      35: invokevirtual #13                 // Method java/lang/IllegalStateException.setStackTrace:([Ljava/lang/StackTraceElement;)V
      38: aload_1
      39: areturn

  protected java.lang.String noMulticastBinding$str();
    Code:
       0: ldc           #14                 // String WFLYNET0002: no multicast binding: %s
       2: areturn

  public final java.lang.IllegalStateException noMulticastBinding(java.lang.String);
    Code:
       0: new           #5                  // class java/lang/IllegalStateException
       3: dup
       4: aload_0
       5: invokevirtual #15                 // Method noMulticastBinding$str:()Ljava/lang/String;
       8: iconst_1
       9: anewarray     #7                  // class java/lang/Object
      12: dup
      13: iconst_0
      14: aload_1
      15: aastore
      16: invokestatic  #8                  // Method java/lang/String.format:(Ljava/lang/String;[Ljava/lang/Object;)Ljava/lang/String;
      19: invokespecial #9                  // Method java/lang/IllegalStateException."<init>":(Ljava/lang/String;)V
      22: astore_2
      23: aload_2
      24: invokevirtual #10                 // Method java/lang/IllegalStateException.getStackTrace:()[Ljava/lang/StackTraceElement;
      27: astore_3
      28: aload_2
      29: aload_3
      30: iconst_1
      31: aload_3
      32: arraylength
      33: invokestatic  #11                 // Method java/util/Arrays.copyOfRange:([Ljava/lang/Object;II)[Ljava/lang/Object;
      36: checkcast     #12                 // class "[Ljava/lang/StackTraceElement;"
      39: invokevirtual #13                 // Method java/lang/IllegalStateException.setStackTrace:([Ljava/lang/StackTraceElement;)V
      42: aload_2
      43: areturn

  protected java.lang.String nullOrEmptyVar$str();
    Code:
       0: ldc           #16                 // String WFLYNET0003: %s cannot be null or an empty string
       2: areturn

  public final java.lang.IllegalArgumentException nullOrEmptyVar(java.lang.String);
    Code:
       0: new           #17                 // class java/lang/IllegalArgumentException
       3: dup
       4: aload_0
       5: invokevirtual #18                 // Method nullOrEmptyVar$str:()Ljava/lang/String;
       8: iconst_1
       9: anewarray     #7                  // class java/lang/Object
      12: dup
      13: iconst_0
      14: aload_1
      15: aastore
      16: invokestatic  #8                  // Method java/lang/String.format:(Ljava/lang/String;[Ljava/lang/Object;)Ljava/lang/String;
      19: invokespecial #19                 // Method java/lang/IllegalArgumentException."<init>":(Ljava/lang/String;)V
      22: astore_2
      23: aload_2
      24: invokevirtual #20                 // Method java/lang/IllegalArgumentException.getStackTrace:()[Ljava/lang/StackTraceElement;
      27: astore_3
      28: aload_2
      29: aload_3
      30: iconst_1
      31: aload_3
      32: arraylength
      33: invokestatic  #11                 // Method java/util/Arrays.copyOfRange:([Ljava/lang/Object;II)[Ljava/lang/Object;
      36: checkcast     #12                 // class "[Ljava/lang/StackTraceElement;"
      39: invokevirtual #21                 // Method java/lang/IllegalArgumentException.setStackTrace:([Ljava/lang/StackTraceElement;)V
      42: aload_2
      43: areturn

  protected java.lang.String nullOutboundSocketBindingParam$str();
    Code:
       0: ldc           #22                 // String WFLYNET0004: %s cannot be null for outbound socket binding \'%s\'
       2: areturn

  public final java.lang.IllegalArgumentException nullOutboundSocketBindingParam(java.lang.String, java.lang.String);
    Code:
       0: new           #17                 // class java/lang/IllegalArgumentException
       3: dup
       4: aload_0
       5: invokevirtual #23                 // Method nullOutboundSocketBindingParam$str:()Ljava/lang/String;
       8: iconst_2
       9: anewarray     #7                  // class java/lang/Object
      12: dup
      13: iconst_0
      14: aload_1
      15: aastore
      16: dup
      17: iconst_1
      18: aload_2
      19: aastore
      20: invokestatic  #8                  // Method java/lang/String.format:(Ljava/lang/String;[Ljava/lang/Object;)Ljava/lang/String;
      23: invokespecial #19                 // Method java/lang/IllegalArgumentException."<init>":(Ljava/lang/String;)V
      26: astore_3
      27: aload_3
      28: invokevirtual #20                 // Method java/lang/IllegalArgumentException.getStackTrace:()[Ljava/lang/StackTraceElement;
      31: astore        4
      33: aload_3
      34: aload         4
      36: iconst_1
      37: aload         4
      39: arraylength
      40: invokestatic  #11                 // Method java/util/Arrays.copyOfRange:([Ljava/lang/Object;II)[Ljava/lang/Object;
      43: checkcast     #12                 // class "[Ljava/lang/StackTraceElement;"
      46: invokevirtual #21                 // Method java/lang/IllegalArgumentException.setStackTrace:([Ljava/lang/StackTraceElement;)V
      49: aload_3
      50: areturn

  protected java.lang.String nullDestinationAddress$str();
    Code:
       0: ldc           #24                 // String WFLYNET0005: Destination address cannot be null or empty for outbound socket binding \'%s\'
       2: areturn

  public final java.lang.IllegalArgumentException nullDestinationAddress(java.lang.String);
    Code:
       0: new           #17                 // class java/lang/IllegalArgumentException
       3: dup
       4: aload_0
       5: invokevirtual #25                 // Method nullDestinationAddress$str:()Ljava/lang/String;
       8: iconst_1
       9: anewarray     #7                  // class java/lang/Object
      12: dup
      13: iconst_0
      14: aload_1
      15: aastore
      16: invokestatic  #8                  // Method java/lang/String.format:(Ljava/lang/String;[Ljava/lang/Object;)Ljava/lang/String;
      19: invokespecial #19                 // Method java/lang/IllegalArgumentException."<init>":(Ljava/lang/String;)V
      22: astore_2
      23: aload_2
      24: invokevirtual #20                 // Method java/lang/IllegalArgumentException.getStackTrace:()[Ljava/lang/StackTraceElement;
      27: astore_3
      28: aload_2
      29: aload_3
      30: iconst_1
      31: aload_3
      32: arraylength
      33: invokestatic  #11                 // Method java/util/Arrays.copyOfRange:([Ljava/lang/Object;II)[Ljava/lang/Object;
      36: checkcast     #12                 // class "[Ljava/lang/StackTraceElement;"
      39: invokevirtual #21                 // Method java/lang/IllegalArgumentException.setStackTrace:([Ljava/lang/StackTraceElement;)V
      42: aload_2
      43: areturn

  protected java.lang.String negativeDestinationPort$str();
    Code:
       0: ldc           #26                 // String WFLYNET0006: Destination port cannot be a negative value: [%d] for outbound socket binding \'%s\'
       2: areturn

  public final java.lang.IllegalArgumentException negativeDestinationPort(int, java.lang.String);
    Code:
       0: new           #17                 // class java/lang/IllegalArgumentException
       3: dup
       4: aload_0
       5: invokevirtual #27                 // Method negativeDestinationPort$str:()Ljava/lang/String;
       8: iconst_2
       9: anewarray     #7                  // class java/lang/Object
      12: dup
      13: iconst_0
      14: iload_1
      15: invokestatic  #28                 // Method java/lang/Integer.valueOf:(I)Ljava/lang/Integer;
      18: aastore
      19: dup
      20: iconst_1
      21: aload_2
      22: aastore
      23: invokestatic  #8                  // Method java/lang/String.format:(Ljava/lang/String;[Ljava/lang/Object;)Ljava/lang/String;
      26: invokespecial #19                 // Method java/lang/IllegalArgumentException."<init>":(Ljava/lang/String;)V
      29: astore_3
      30: aload_3
      31: invokevirtual #20                 // Method java/lang/IllegalArgumentException.getStackTrace:()[Ljava/lang/StackTraceElement;
      34: astore        4
      36: aload_3
      37: aload         4
      39: iconst_1
      40: aload         4
      42: arraylength
      43: invokestatic  #11                 // Method java/util/Arrays.copyOfRange:([Ljava/lang/Object;II)[Ljava/lang/Object;
      46: checkcast     #12                 // class "[Ljava/lang/StackTraceElement;"
      49: invokevirtual #21                 // Method java/lang/IllegalArgumentException.setStackTrace:([Ljava/lang/StackTraceElement;)V
      52: aload_3
      53: areturn

  static {};
    Code:
       0: new           #3                  // class org/jboss/as/network/logging/NetworkMessages_$bundle
       3: dup
       4: invokespecial #29                 // Method "<init>":()V
       7: putstatic     #2                  // Field INSTANCE:Lorg/jboss/as/network/logging/NetworkMessages_$bundle;
      10: return
}
