Compiled from "CreateCanaryRequest.java"
public final class software.amazon.awssdk.services.synthetics.model.CreateCanaryRequest extends software.amazon.awssdk.services.synthetics.model.SyntheticsRequest implements software.amazon.awssdk.utils.builder.ToCopyableBuilder<software.amazon.awssdk.services.synthetics.model.CreateCanaryRequest$Builder, software.amazon.awssdk.services.synthetics.model.CreateCanaryRequest> {
  private static final software.amazon.awssdk.core.SdkField<java.lang.String> NAME_FIELD;

  private static final software.amazon.awssdk.core.SdkField<software.amazon.awssdk.services.synthetics.model.CanaryCodeInput> CODE_FIELD;

  private static final software.amazon.awssdk.core.SdkField<java.lang.String> ARTIFACT_S3_LOCATION_FIELD;

  private static final software.amazon.awssdk.core.SdkField<java.lang.String> EXECUTION_ROLE_ARN_FIELD;

  private static final software.amazon.awssdk.core.SdkField<software.amazon.awssdk.services.synthetics.model.CanaryScheduleInput> SCHEDULE_FIELD;

  private static final software.amazon.awssdk.core.SdkField<software.amazon.awssdk.services.synthetics.model.CanaryRunConfigInput> RUN_CONFIG_FIELD;

  private static final software.amazon.awssdk.core.SdkField<java.lang.Integer> SUCCESS_RETENTION_PERIOD_IN_DAYS_FIELD;

  private static final software.amazon.awssdk.core.SdkField<java.lang.Integer> FAILURE_RETENTION_PERIOD_IN_DAYS_FIELD;

  private static final software.amazon.awssdk.core.SdkField<java.lang.String> RUNTIME_VERSION_FIELD;

  private static final software.amazon.awssdk.core.SdkField<software.amazon.awssdk.services.synthetics.model.VpcConfigInput> VPC_CONFIG_FIELD;

  private static final software.amazon.awssdk.core.SdkField<java.util.Map<java.lang.String, java.lang.String>> TAGS_FIELD;

  private static final software.amazon.awssdk.core.SdkField<software.amazon.awssdk.services.synthetics.model.ArtifactConfigInput> ARTIFACT_CONFIG_FIELD;

  private static final java.util.List<software.amazon.awssdk.core.SdkField<?>> SDK_FIELDS;

  private final java.lang.String name;

  private final software.amazon.awssdk.services.synthetics.model.CanaryCodeInput code;

  private final java.lang.String artifactS3Location;

  private final java.lang.String executionRoleArn;

  private final software.amazon.awssdk.services.synthetics.model.CanaryScheduleInput schedule;

  private final software.amazon.awssdk.services.synthetics.model.CanaryRunConfigInput runConfig;

  private final java.lang.Integer successRetentionPeriodInDays;

  private final java.lang.Integer failureRetentionPeriodInDays;

  private final java.lang.String runtimeVersion;

  private final software.amazon.awssdk.services.synthetics.model.VpcConfigInput vpcConfig;

  private final java.util.Map<java.lang.String, java.lang.String> tags;

  private final software.amazon.awssdk.services.synthetics.model.ArtifactConfigInput artifactConfig;

  private software.amazon.awssdk.services.synthetics.model.CreateCanaryRequest(software.amazon.awssdk.services.synthetics.model.CreateCanaryRequest$BuilderImpl);
    Code:
       0: aload_0
       1: aload_1
       2: invokespecial #15                 // Method software/amazon/awssdk/services/synthetics/model/SyntheticsRequest."<init>":(Lsoftware/amazon/awssdk/services/synthetics/model/SyntheticsRequest$Builder;)V
       5: aload_0
       6: aload_1
       7: invokestatic  #16                 // Method software/amazon/awssdk/services/synthetics/model/CreateCanaryRequest$BuilderImpl.access$000:(Lsoftware/amazon/awssdk/services/synthetics/model/CreateCanaryRequest$BuilderImpl;)Ljava/lang/String;
      10: putfield      #14                 // Field name:Ljava/lang/String;
      13: aload_0
      14: aload_1
      15: invokestatic  #17                 // Method software/amazon/awssdk/services/synthetics/model/CreateCanaryRequest$BuilderImpl.access$100:(Lsoftware/amazon/awssdk/services/synthetics/model/CreateCanaryRequest$BuilderImpl;)Lsoftware/amazon/awssdk/services/synthetics/model/CanaryCodeInput;
      18: putfield      #13                 // Field code:Lsoftware/amazon/awssdk/services/synthetics/model/CanaryCodeInput;
      21: aload_0
      22: aload_1
      23: invokestatic  #18                 // Method software/amazon/awssdk/services/synthetics/model/CreateCanaryRequest$BuilderImpl.access$200:(Lsoftware/amazon/awssdk/services/synthetics/model/CreateCanaryRequest$BuilderImpl;)Ljava/lang/String;
      26: putfield      #12                 // Field artifactS3Location:Ljava/lang/String;
      29: aload_0
      30: aload_1
      31: invokestatic  #19                 // Method software/amazon/awssdk/services/synthetics/model/CreateCanaryRequest$BuilderImpl.access$300:(Lsoftware/amazon/awssdk/services/synthetics/model/CreateCanaryRequest$BuilderImpl;)Ljava/lang/String;
      34: putfield      #11                 // Field executionRoleArn:Ljava/lang/String;
      37: aload_0
      38: aload_1
      39: invokestatic  #20                 // Method software/amazon/awssdk/services/synthetics/model/CreateCanaryRequest$BuilderImpl.access$400:(Lsoftware/amazon/awssdk/services/synthetics/model/CreateCanaryRequest$BuilderImpl;)Lsoftware/amazon/awssdk/services/synthetics/model/CanaryScheduleInput;
      42: putfield      #10                 // Field schedule:Lsoftware/amazon/awssdk/services/synthetics/model/CanaryScheduleInput;
      45: aload_0
      46: aload_1
      47: invokestatic  #21                 // Method software/amazon/awssdk/services/synthetics/model/CreateCanaryRequest$BuilderImpl.access$500:(Lsoftware/amazon/awssdk/services/synthetics/model/CreateCanaryRequest$BuilderImpl;)Lsoftware/amazon/awssdk/services/synthetics/model/CanaryRunConfigInput;
      50: putfield      #9                  // Field runConfig:Lsoftware/amazon/awssdk/services/synthetics/model/CanaryRunConfigInput;
      53: aload_0
      54: aload_1
      55: invokestatic  #22                 // Method software/amazon/awssdk/services/synthetics/model/CreateCanaryRequest$BuilderImpl.access$600:(Lsoftware/amazon/awssdk/services/synthetics/model/CreateCanaryRequest$BuilderImpl;)Ljava/lang/Integer;
      58: putfield      #8                  // Field successRetentionPeriodInDays:Ljava/lang/Integer;
      61: aload_0
      62: aload_1
      63: invokestatic  #23                 // Method software/amazon/awssdk/services/synthetics/model/CreateCanaryRequest$BuilderImpl.access$700:(Lsoftware/amazon/awssdk/services/synthetics/model/CreateCanaryRequest$BuilderImpl;)Ljava/lang/Integer;
      66: putfield      #7                  // Field failureRetentionPeriodInDays:Ljava/lang/Integer;
      69: aload_0
      70: aload_1
      71: invokestatic  #24                 // Method software/amazon/awssdk/services/synthetics/model/CreateCanaryRequest$BuilderImpl.access$800:(Lsoftware/amazon/awssdk/services/synthetics/model/CreateCanaryRequest$BuilderImpl;)Ljava/lang/String;
      74: putfield      #6                  // Field runtimeVersion:Ljava/lang/String;
      77: aload_0
      78: aload_1
      79: invokestatic  #25                 // Method software/amazon/awssdk/services/synthetics/model/CreateCanaryRequest$BuilderImpl.access$900:(Lsoftware/amazon/awssdk/services/synthetics/model/CreateCanaryRequest$BuilderImpl;)Lsoftware/amazon/awssdk/services/synthetics/model/VpcConfigInput;
      82: putfield      #5                  // Field vpcConfig:Lsoftware/amazon/awssdk/services/synthetics/model/VpcConfigInput;
      85: aload_0
      86: aload_1
      87: invokestatic  #26                 // Method software/amazon/awssdk/services/synthetics/model/CreateCanaryRequest$BuilderImpl.access$1000:(Lsoftware/amazon/awssdk/services/synthetics/model/CreateCanaryRequest$BuilderImpl;)Ljava/util/Map;
      90: putfield      #4                  // Field tags:Ljava/util/Map;
      93: aload_0
      94: aload_1
      95: invokestatic  #27                 // Method software/amazon/awssdk/services/synthetics/model/CreateCanaryRequest$BuilderImpl.access$1100:(Lsoftware/amazon/awssdk/services/synthetics/model/CreateCanaryRequest$BuilderImpl;)Lsoftware/amazon/awssdk/services/synthetics/model/ArtifactConfigInput;
      98: putfield      #3                  // Field artifactConfig:Lsoftware/amazon/awssdk/services/synthetics/model/ArtifactConfigInput;
     101: return

  public final java.lang.String name();
    Code:
       0: aload_0
       1: getfield      #14                 // Field name:Ljava/lang/String;
       4: areturn

  public final software.amazon.awssdk.services.synthetics.model.CanaryCodeInput code();
    Code:
       0: aload_0
       1: getfield      #13                 // Field code:Lsoftware/amazon/awssdk/services/synthetics/model/CanaryCodeInput;
       4: areturn

  public final java.lang.String artifactS3Location();
    Code:
       0: aload_0
       1: getfield      #12                 // Field artifactS3Location:Ljava/lang/String;
       4: areturn

  public final java.lang.String executionRoleArn();
    Code:
       0: aload_0
       1: getfield      #11                 // Field executionRoleArn:Ljava/lang/String;
       4: areturn

  public final software.amazon.awssdk.services.synthetics.model.CanaryScheduleInput schedule();
    Code:
       0: aload_0
       1: getfield      #10                 // Field schedule:Lsoftware/amazon/awssdk/services/synthetics/model/CanaryScheduleInput;
       4: areturn

  public final software.amazon.awssdk.services.synthetics.model.CanaryRunConfigInput runConfig();
    Code:
       0: aload_0
       1: getfield      #9                  // Field runConfig:Lsoftware/amazon/awssdk/services/synthetics/model/CanaryRunConfigInput;
       4: areturn

  public final java.lang.Integer successRetentionPeriodInDays();
    Code:
       0: aload_0
       1: getfield      #8                  // Field successRetentionPeriodInDays:Ljava/lang/Integer;
       4: areturn

  public final java.lang.Integer failureRetentionPeriodInDays();
    Code:
       0: aload_0
       1: getfield      #7                  // Field failureRetentionPeriodInDays:Ljava/lang/Integer;
       4: areturn

  public final java.lang.String runtimeVersion();
    Code:
       0: aload_0
       1: getfield      #6                  // Field runtimeVersion:Ljava/lang/String;
       4: areturn

  public final software.amazon.awssdk.services.synthetics.model.VpcConfigInput vpcConfig();
    Code:
       0: aload_0
       1: getfield      #5                  // Field vpcConfig:Lsoftware/amazon/awssdk/services/synthetics/model/VpcConfigInput;
       4: areturn

  public final boolean hasTags();
    Code:
       0: aload_0
       1: getfield      #4                  // Field tags:Ljava/util/Map;
       4: ifnull        21
       7: aload_0
       8: getfield      #4                  // Field tags:Ljava/util/Map;
      11: instanceof    #28                 // class software/amazon/awssdk/core/util/SdkAutoConstructMap
      14: ifne          21
      17: iconst_1
      18: goto          22
      21: iconst_0
      22: ireturn

  public final java.util.Map<java.lang.String, java.lang.String> tags();
    Code:
       0: aload_0
       1: getfield      #4                  // Field tags:Ljava/util/Map;
       4: areturn

  public final software.amazon.awssdk.services.synthetics.model.ArtifactConfigInput artifactConfig();
    Code:
       0: aload_0
       1: getfield      #3                  // Field artifactConfig:Lsoftware/amazon/awssdk/services/synthetics/model/ArtifactConfigInput;
       4: areturn

  public software.amazon.awssdk.services.synthetics.model.CreateCanaryRequest$Builder toBuilder();
    Code:
       0: new           #29                 // class software/amazon/awssdk/services/synthetics/model/CreateCanaryRequest$BuilderImpl
       3: dup
       4: aload_0
       5: aconst_null
       6: invokespecial #30                 // Method software/amazon/awssdk/services/synthetics/model/CreateCanaryRequest$BuilderImpl."<init>":(Lsoftware/amazon/awssdk/services/synthetics/model/CreateCanaryRequest;Lsoftware/amazon/awssdk/services/synthetics/model/CreateCanaryRequest$1;)V
       9: areturn

  public static software.amazon.awssdk.services.synthetics.model.CreateCanaryRequest$Builder builder();
    Code:
       0: new           #29                 // class software/amazon/awssdk/services/synthetics/model/CreateCanaryRequest$BuilderImpl
       3: dup
       4: aconst_null
       5: invokespecial #31                 // Method software/amazon/awssdk/services/synthetics/model/CreateCanaryRequest$BuilderImpl."<init>":(Lsoftware/amazon/awssdk/services/synthetics/model/CreateCanaryRequest$1;)V
       8: areturn

  public static java.lang.Class<? extends software.amazon.awssdk.services.synthetics.model.CreateCanaryRequest$Builder> serializableBuilderClass();
    Code:
       0: ldc           #29                 // class software/amazon/awssdk/services/synthetics/model/CreateCanaryRequest$BuilderImpl
       2: areturn

  public final int hashCode();
    Code:
       0: iconst_1
       1: istore_1
       2: bipush        31
       4: iload_1
       5: imul
       6: aload_0
       7: invokespecial #32                 // Method software/amazon/awssdk/services/synthetics/model/SyntheticsRequest.hashCode:()I
      10: iadd
      11: istore_1
      12: bipush        31
      14: iload_1
      15: imul
      16: aload_0
      17: invokevirtual #33                 // Method name:()Ljava/lang/String;
      20: invokestatic  #34                 // Method java/util/Objects.hashCode:(Ljava/lang/Object;)I
      23: iadd
      24: istore_1
      25: bipush        31
      27: iload_1
      28: imul
      29: aload_0
      30: invokevirtual #35                 // Method code:()Lsoftware/amazon/awssdk/services/synthetics/model/CanaryCodeInput;
      33: invokestatic  #34                 // Method java/util/Objects.hashCode:(Ljava/lang/Object;)I
      36: iadd
      37: istore_1
      38: bipush        31
      40: iload_1
      41: imul
      42: aload_0
      43: invokevirtual #36                 // Method artifactS3Location:()Ljava/lang/String;
      46: invokestatic  #34                 // Method java/util/Objects.hashCode:(Ljava/lang/Object;)I
      49: iadd
      50: istore_1
      51: bipush        31
      53: iload_1
      54: imul
      55: aload_0
      56: invokevirtual #37                 // Method executionRoleArn:()Ljava/lang/String;
      59: invokestatic  #34                 // Method java/util/Objects.hashCode:(Ljava/lang/Object;)I
      62: iadd
      63: istore_1
      64: bipush        31
      66: iload_1
      67: imul
      68: aload_0
      69: invokevirtual #38                 // Method schedule:()Lsoftware/amazon/awssdk/services/synthetics/model/CanaryScheduleInput;
      72: invokestatic  #34                 // Method java/util/Objects.hashCode:(Ljava/lang/Object;)I
      75: iadd
      76: istore_1
      77: bipush        31
      79: iload_1
      80: imul
      81: aload_0
      82: invokevirtual #39                 // Method runConfig:()Lsoftware/amazon/awssdk/services/synthetics/model/CanaryRunConfigInput;
      85: invokestatic  #34                 // Method java/util/Objects.hashCode:(Ljava/lang/Object;)I
      88: iadd
      89: istore_1
      90: bipush        31
      92: iload_1
      93: imul
      94: aload_0
      95: invokevirtual #40                 // Method successRetentionPeriodInDays:()Ljava/lang/Integer;
      98: invokestatic  #34                 // Method java/util/Objects.hashCode:(Ljava/lang/Object;)I
     101: iadd
     102: istore_1
     103: bipush        31
     105: iload_1
     106: imul
     107: aload_0
     108: invokevirtual #41                 // Method failureRetentionPeriodInDays:()Ljava/lang/Integer;
     111: invokestatic  #34                 // Method java/util/Objects.hashCode:(Ljava/lang/Object;)I
     114: iadd
     115: istore_1
     116: bipush        31
     118: iload_1
     119: imul
     120: aload_0
     121: invokevirtual #42                 // Method runtimeVersion:()Ljava/lang/String;
     124: invokestatic  #34                 // Method java/util/Objects.hashCode:(Ljava/lang/Object;)I
     127: iadd
     128: istore_1
     129: bipush        31
     131: iload_1
     132: imul
     133: aload_0
     134: invokevirtual #43                 // Method vpcConfig:()Lsoftware/amazon/awssdk/services/synthetics/model/VpcConfigInput;
     137: invokestatic  #34                 // Method java/util/Objects.hashCode:(Ljava/lang/Object;)I
     140: iadd
     141: istore_1
     142: bipush        31
     144: iload_1
     145: imul
     146: aload_0
     147: invokevirtual #44                 // Method hasTags:()Z
     150: ifeq          160
     153: aload_0
     154: invokevirtual #45                 // Method tags:()Ljava/util/Map;
     157: goto          161
     160: aconst_null
     161: invokestatic  #34                 // Method java/util/Objects.hashCode:(Ljava/lang/Object;)I
     164: iadd
     165: istore_1
     166: bipush        31
     168: iload_1
     169: imul
     170: aload_0
     171: invokevirtual #46                 // Method artifactConfig:()Lsoftware/amazon/awssdk/services/synthetics/model/ArtifactConfigInput;
     174: invokestatic  #34                 // Method java/util/Objects.hashCode:(Ljava/lang/Object;)I
     177: iadd
     178: istore_1
     179: iload_1
     180: ireturn

  public final boolean equals(java.lang.Object);
    Code:
       0: aload_0
       1: aload_1
       2: invokespecial #47                 // Method software/amazon/awssdk/services/synthetics/model/SyntheticsRequest.equals:(Ljava/lang/Object;)Z
       5: ifeq          20
       8: aload_0
       9: aload_1
      10: invokevirtual #48                 // Method equalsBySdkFields:(Ljava/lang/Object;)Z
      13: ifeq          20
      16: iconst_1
      17: goto          21
      20: iconst_0
      21: ireturn

  public final boolean equalsBySdkFields(java.lang.Object);
    Code:
       0: aload_0
       1: aload_1
       2: if_acmpne     7
       5: iconst_1
       6: ireturn
       7: aload_1
       8: ifnonnull     13
      11: iconst_0
      12: ireturn
      13: aload_1
      14: instanceof    #49                 // class software/amazon/awssdk/services/synthetics/model/CreateCanaryRequest
      17: ifne          22
      20: iconst_0
      21: ireturn
      22: aload_1
      23: checkcast     #49                 // class software/amazon/awssdk/services/synthetics/model/CreateCanaryRequest
      26: astore_2
      27: aload_0
      28: invokevirtual #33                 // Method name:()Ljava/lang/String;
      31: aload_2
      32: invokevirtual #33                 // Method name:()Ljava/lang/String;
      35: invokestatic  #50                 // Method java/util/Objects.equals:(Ljava/lang/Object;Ljava/lang/Object;)Z
      38: ifeq          210
      41: aload_0
      42: invokevirtual #35                 // Method code:()Lsoftware/amazon/awssdk/services/synthetics/model/CanaryCodeInput;
      45: aload_2
      46: invokevirtual #35                 // Method code:()Lsoftware/amazon/awssdk/services/synthetics/model/CanaryCodeInput;
      49: invokestatic  #50                 // Method java/util/Objects.equals:(Ljava/lang/Object;Ljava/lang/Object;)Z
      52: ifeq          210
      55: aload_0
      56: invokevirtual #36                 // Method artifactS3Location:()Ljava/lang/String;
      59: aload_2
      60: invokevirtual #36                 // Method artifactS3Location:()Ljava/lang/String;
      63: invokestatic  #50                 // Method java/util/Objects.equals:(Ljava/lang/Object;Ljava/lang/Object;)Z
      66: ifeq          210
      69: aload_0
      70: invokevirtual #37                 // Method executionRoleArn:()Ljava/lang/String;
      73: aload_2
      74: invokevirtual #37                 // Method executionRoleArn:()Ljava/lang/String;
      77: invokestatic  #50                 // Method java/util/Objects.equals:(Ljava/lang/Object;Ljava/lang/Object;)Z
      80: ifeq          210
      83: aload_0
      84: invokevirtual #38                 // Method schedule:()Lsoftware/amazon/awssdk/services/synthetics/model/CanaryScheduleInput;
      87: aload_2
      88: invokevirtual #38                 // Method schedule:()Lsoftware/amazon/awssdk/services/synthetics/model/CanaryScheduleInput;
      91: invokestatic  #50                 // Method java/util/Objects.equals:(Ljava/lang/Object;Ljava/lang/Object;)Z
      94: ifeq          210
      97: aload_0
      98: invokevirtual #39                 // Method runConfig:()Lsoftware/amazon/awssdk/services/synthetics/model/CanaryRunConfigInput;
     101: aload_2
     102: invokevirtual #39                 // Method runConfig:()Lsoftware/amazon/awssdk/services/synthetics/model/CanaryRunConfigInput;
     105: invokestatic  #50                 // Method java/util/Objects.equals:(Ljava/lang/Object;Ljava/lang/Object;)Z
     108: ifeq          210
     111: aload_0
     112: invokevirtual #40                 // Method successRetentionPeriodInDays:()Ljava/lang/Integer;
     115: aload_2
     116: invokevirtual #40                 // Method successRetentionPeriodInDays:()Ljava/lang/Integer;
     119: invokestatic  #50                 // Method java/util/Objects.equals:(Ljava/lang/Object;Ljava/lang/Object;)Z
     122: ifeq          210
     125: aload_0
     126: invokevirtual #41                 // Method failureRetentionPeriodInDays:()Ljava/lang/Integer;
     129: aload_2
     130: invokevirtual #41                 // Method failureRetentionPeriodInDays:()Ljava/lang/Integer;
     133: invokestatic  #50                 // Method java/util/Objects.equals:(Ljava/lang/Object;Ljava/lang/Object;)Z
     136: ifeq          210
     139: aload_0
     140: invokevirtual #42                 // Method runtimeVersion:()Ljava/lang/String;
     143: aload_2
     144: invokevirtual #42                 // Method runtimeVersion:()Ljava/lang/String;
     147: invokestatic  #50                 // Method java/util/Objects.equals:(Ljava/lang/Object;Ljava/lang/Object;)Z
     150: ifeq          210
     153: aload_0
     154: invokevirtual #43                 // Method vpcConfig:()Lsoftware/amazon/awssdk/services/synthetics/model/VpcConfigInput;
     157: aload_2
     158: invokevirtual #43                 // Method vpcConfig:()Lsoftware/amazon/awssdk/services/synthetics/model/VpcConfigInput;
     161: invokestatic  #50                 // Method java/util/Objects.equals:(Ljava/lang/Object;Ljava/lang/Object;)Z
     164: ifeq          210
     167: aload_0
     168: invokevirtual #44                 // Method hasTags:()Z
     171: aload_2
     172: invokevirtual #44                 // Method hasTags:()Z
     175: if_icmpne     210
     178: aload_0
     179: invokevirtual #45                 // Method tags:()Ljava/util/Map;
     182: aload_2
     183: invokevirtual #45                 // Method tags:()Ljava/util/Map;
     186: invokestatic  #50                 // Method java/util/Objects.equals:(Ljava/lang/Object;Ljava/lang/Object;)Z
     189: ifeq          210
     192: aload_0
     193: invokevirtual #46                 // Method artifactConfig:()Lsoftware/amazon/awssdk/services/synthetics/model/ArtifactConfigInput;
     196: aload_2
     197: invokevirtual #46                 // Method artifactConfig:()Lsoftware/amazon/awssdk/services/synthetics/model/ArtifactConfigInput;
     200: invokestatic  #50                 // Method java/util/Objects.equals:(Ljava/lang/Object;Ljava/lang/Object;)Z
     203: ifeq          210
     206: iconst_1
     207: goto          211
     210: iconst_0
     211: ireturn

  public final java.lang.String toString();
    Code:
       0: ldc           #51                 // String CreateCanaryRequest
       2: invokestatic  #52                 // Method software/amazon/awssdk/utils/ToString.builder:(Ljava/lang/String;)Lsoftware/amazon/awssdk/utils/ToString;
       5: ldc           #53                 // String Name
       7: aload_0
       8: invokevirtual #33                 // Method name:()Ljava/lang/String;
      11: invokevirtual #54                 // Method software/amazon/awssdk/utils/ToString.add:(Ljava/lang/String;Ljava/lang/Object;)Lsoftware/amazon/awssdk/utils/ToString;
      14: ldc           #55                 // String Code
      16: aload_0
      17: invokevirtual #35                 // Method code:()Lsoftware/amazon/awssdk/services/synthetics/model/CanaryCodeInput;
      20: invokevirtual #54                 // Method software/amazon/awssdk/utils/ToString.add:(Ljava/lang/String;Ljava/lang/Object;)Lsoftware/amazon/awssdk/utils/ToString;
      23: ldc           #56                 // String ArtifactS3Location
      25: aload_0
      26: invokevirtual #36                 // Method artifactS3Location:()Ljava/lang/String;
      29: invokevirtual #54                 // Method software/amazon/awssdk/utils/ToString.add:(Ljava/lang/String;Ljava/lang/Object;)Lsoftware/amazon/awssdk/utils/ToString;
      32: ldc           #57                 // String ExecutionRoleArn
      34: aload_0
      35: invokevirtual #37                 // Method executionRoleArn:()Ljava/lang/String;
      38: invokevirtual #54                 // Method software/amazon/awssdk/utils/ToString.add:(Ljava/lang/String;Ljava/lang/Object;)Lsoftware/amazon/awssdk/utils/ToString;
      41: ldc           #58                 // String Schedule
      43: aload_0
      44: invokevirtual #38                 // Method schedule:()Lsoftware/amazon/awssdk/services/synthetics/model/CanaryScheduleInput;
      47: invokevirtual #54                 // Method software/amazon/awssdk/utils/ToString.add:(Ljava/lang/String;Ljava/lang/Object;)Lsoftware/amazon/awssdk/utils/ToString;
      50: ldc           #59                 // String RunConfig
      52: aload_0
      53: invokevirtual #39                 // Method runConfig:()Lsoftware/amazon/awssdk/services/synthetics/model/CanaryRunConfigInput;
      56: invokevirtual #54                 // Method software/amazon/awssdk/utils/ToString.add:(Ljava/lang/String;Ljava/lang/Object;)Lsoftware/amazon/awssdk/utils/ToString;
      59: ldc           #60                 // String SuccessRetentionPeriodInDays
      61: aload_0
      62: invokevirtual #40                 // Method successRetentionPeriodInDays:()Ljava/lang/Integer;
      65: invokevirtual #54                 // Method software/amazon/awssdk/utils/ToString.add:(Ljava/lang/String;Ljava/lang/Object;)Lsoftware/amazon/awssdk/utils/ToString;
      68: ldc           #61                 // String FailureRetentionPeriodInDays
      70: aload_0
      71: invokevirtual #41                 // Method failureRetentionPeriodInDays:()Ljava/lang/Integer;
      74: invokevirtual #54                 // Method software/amazon/awssdk/utils/ToString.add:(Ljava/lang/String;Ljava/lang/Object;)Lsoftware/amazon/awssdk/utils/ToString;
      77: ldc           #62                 // String RuntimeVersion
      79: aload_0
      80: invokevirtual #42                 // Method runtimeVersion:()Ljava/lang/String;
      83: invokevirtual #54                 // Method software/amazon/awssdk/utils/ToString.add:(Ljava/lang/String;Ljava/lang/Object;)Lsoftware/amazon/awssdk/utils/ToString;
      86: ldc           #63                 // String VpcConfig
      88: aload_0
      89: invokevirtual #43                 // Method vpcConfig:()Lsoftware/amazon/awssdk/services/synthetics/model/VpcConfigInput;
      92: invokevirtual #54                 // Method software/amazon/awssdk/utils/ToString.add:(Ljava/lang/String;Ljava/lang/Object;)Lsoftware/amazon/awssdk/utils/ToString;
      95: ldc           #64                 // String Tags
      97: aload_0
      98: invokevirtual #44                 // Method hasTags:()Z
     101: ifeq          111
     104: aload_0
     105: invokevirtual #45                 // Method tags:()Ljava/util/Map;
     108: goto          112
     111: aconst_null
     112: invokevirtual #54                 // Method software/amazon/awssdk/utils/ToString.add:(Ljava/lang/String;Ljava/lang/Object;)Lsoftware/amazon/awssdk/utils/ToString;
     115: ldc           #65                 // String ArtifactConfig
     117: aload_0
     118: invokevirtual #46                 // Method artifactConfig:()Lsoftware/amazon/awssdk/services/synthetics/model/ArtifactConfigInput;
     121: invokevirtual #54                 // Method software/amazon/awssdk/utils/ToString.add:(Ljava/lang/String;Ljava/lang/Object;)Lsoftware/amazon/awssdk/utils/ToString;
     124: invokevirtual #66                 // Method software/amazon/awssdk/utils/ToString.build:()Ljava/lang/String;
     127: areturn

  public final <T> java.util.Optional<T> getValueForField(java.lang.String, java.lang.Class<T>);
    Code:
       0: aload_1
       1: astore_3
       2: iconst_m1
       3: istore        4
       5: aload_3
       6: invokevirtual #67                 // Method java/lang/String.hashCode:()I
       9: lookupswitch  { // 12
           -1870696872: 206
           -1494317263: 222
            -633276745: 176
            -407244409: 146
            -399921664: 238
               2105869: 131
               2420395: 116
               2598969: 270
             335465455: 161
             728167821: 191
             791561579: 254
            1043471316: 286
               default: 299
          }
     116: aload_3
     117: ldc           #53                 // String Name
     119: invokevirtual #68                 // Method java/lang/String.equals:(Ljava/lang/Object;)Z
     122: ifeq          299
     125: iconst_0
     126: istore        4
     128: goto          299
     131: aload_3
     132: ldc           #55                 // String Code
     134: invokevirtual #68                 // Method java/lang/String.equals:(Ljava/lang/Object;)Z
     137: ifeq          299
     140: iconst_1
     141: istore        4
     143: goto          299
     146: aload_3
     147: ldc           #56                 // String ArtifactS3Location
     149: invokevirtual #68                 // Method java/lang/String.equals:(Ljava/lang/Object;)Z
     152: ifeq          299
     155: iconst_2
     156: istore        4
     158: goto          299
     161: aload_3
     162: ldc           #57                 // String ExecutionRoleArn
     164: invokevirtual #68                 // Method java/lang/String.equals:(Ljava/lang/Object;)Z
     167: ifeq          299
     170: iconst_3
     171: istore        4
     173: goto          299
     176: aload_3
     177: ldc           #58                 // String Schedule
     179: invokevirtual #68                 // Method java/lang/String.equals:(Ljava/lang/Object;)Z
     182: ifeq          299
     185: iconst_4
     186: istore        4
     188: goto          299
     191: aload_3
     192: ldc           #59                 // String RunConfig
     194: invokevirtual #68                 // Method java/lang/String.equals:(Ljava/lang/Object;)Z
     197: ifeq          299
     200: iconst_5
     201: istore        4
     203: goto          299
     206: aload_3
     207: ldc           #60                 // String SuccessRetentionPeriodInDays
     209: invokevirtual #68                 // Method java/lang/String.equals:(Ljava/lang/Object;)Z
     212: ifeq          299
     215: bipush        6
     217: istore        4
     219: goto          299
     222: aload_3
     223: ldc           #61                 // String FailureRetentionPeriodInDays
     225: invokevirtual #68                 // Method java/lang/String.equals:(Ljava/lang/Object;)Z
     228: ifeq          299
     231: bipush        7
     233: istore        4
     235: goto          299
     238: aload_3
     239: ldc           #62                 // String RuntimeVersion
     241: invokevirtual #68                 // Method java/lang/String.equals:(Ljava/lang/Object;)Z
     244: ifeq          299
     247: bipush        8
     249: istore        4
     251: goto          299
     254: aload_3
     255: ldc           #63                 // String VpcConfig
     257: invokevirtual #68                 // Method java/lang/String.equals:(Ljava/lang/Object;)Z
     260: ifeq          299
     263: bipush        9
     265: istore        4
     267: goto          299
     270: aload_3
     271: ldc           #64                 // String Tags
     273: invokevirtual #68                 // Method java/lang/String.equals:(Ljava/lang/Object;)Z
     276: ifeq          299
     279: bipush        10
     281: istore        4
     283: goto          299
     286: aload_3
     287: ldc           #65                 // String ArtifactConfig
     289: invokevirtual #68                 // Method java/lang/String.equals:(Ljava/lang/Object;)Z
     292: ifeq          299
     295: bipush        11
     297: istore        4
     299: iload         4
     301: tableswitch   { // 0 to 11
                     0: 364
                     1: 376
                     2: 388
                     3: 400
                     4: 412
                     5: 424
                     6: 436
                     7: 448
                     8: 460
                     9: 472
                    10: 484
                    11: 496
               default: 508
          }
     364: aload_2
     365: aload_0
     366: invokevirtual #33                 // Method name:()Ljava/lang/String;
     369: invokevirtual #69                 // Method java/lang/Class.cast:(Ljava/lang/Object;)Ljava/lang/Object;
     372: invokestatic  #70                 // Method java/util/Optional.ofNullable:(Ljava/lang/Object;)Ljava/util/Optional;
     375: areturn
     376: aload_2
     377: aload_0
     378: invokevirtual #35                 // Method code:()Lsoftware/amazon/awssdk/services/synthetics/model/CanaryCodeInput;
     381: invokevirtual #69                 // Method java/lang/Class.cast:(Ljava/lang/Object;)Ljava/lang/Object;
     384: invokestatic  #70                 // Method java/util/Optional.ofNullable:(Ljava/lang/Object;)Ljava/util/Optional;
     387: areturn
     388: aload_2
     389: aload_0
     390: invokevirtual #36                 // Method artifactS3Location:()Ljava/lang/String;
     393: invokevirtual #69                 // Method java/lang/Class.cast:(Ljava/lang/Object;)Ljava/lang/Object;
     396: invokestatic  #70                 // Method java/util/Optional.ofNullable:(Ljava/lang/Object;)Ljava/util/Optional;
     399: areturn
     400: aload_2
     401: aload_0
     402: invokevirtual #37                 // Method executionRoleArn:()Ljava/lang/String;
     405: invokevirtual #69                 // Method java/lang/Class.cast:(Ljava/lang/Object;)Ljava/lang/Object;
     408: invokestatic  #70                 // Method java/util/Optional.ofNullable:(Ljava/lang/Object;)Ljava/util/Optional;
     411: areturn
     412: aload_2
     413: aload_0
     414: invokevirtual #38                 // Method schedule:()Lsoftware/amazon/awssdk/services/synthetics/model/CanaryScheduleInput;
     417: invokevirtual #69                 // Method java/lang/Class.cast:(Ljava/lang/Object;)Ljava/lang/Object;
     420: invokestatic  #70                 // Method java/util/Optional.ofNullable:(Ljava/lang/Object;)Ljava/util/Optional;
     423: areturn
     424: aload_2
     425: aload_0
     426: invokevirtual #39                 // Method runConfig:()Lsoftware/amazon/awssdk/services/synthetics/model/CanaryRunConfigInput;
     429: invokevirtual #69                 // Method java/lang/Class.cast:(Ljava/lang/Object;)Ljava/lang/Object;
     432: invokestatic  #70                 // Method java/util/Optional.ofNullable:(Ljava/lang/Object;)Ljava/util/Optional;
     435: areturn
     436: aload_2
     437: aload_0
     438: invokevirtual #40                 // Method successRetentionPeriodInDays:()Ljava/lang/Integer;
     441: invokevirtual #69                 // Method java/lang/Class.cast:(Ljava/lang/Object;)Ljava/lang/Object;
     444: invokestatic  #70                 // Method java/util/Optional.ofNullable:(Ljava/lang/Object;)Ljava/util/Optional;
     447: areturn
     448: aload_2
     449: aload_0
     450: invokevirtual #41                 // Method failureRetentionPeriodInDays:()Ljava/lang/Integer;
     453: invokevirtual #69                 // Method java/lang/Class.cast:(Ljava/lang/Object;)Ljava/lang/Object;
     456: invokestatic  #70                 // Method java/util/Optional.ofNullable:(Ljava/lang/Object;)Ljava/util/Optional;
     459: areturn
     460: aload_2
     461: aload_0
     462: invokevirtual #42                 // Method runtimeVersion:()Ljava/lang/String;
     465: invokevirtual #69                 // Method java/lang/Class.cast:(Ljava/lang/Object;)Ljava/lang/Object;
     468: invokestatic  #70                 // Method java/util/Optional.ofNullable:(Ljava/lang/Object;)Ljava/util/Optional;
     471: areturn
     472: aload_2
     473: aload_0
     474: invokevirtual #43                 // Method vpcConfig:()Lsoftware/amazon/awssdk/services/synthetics/model/VpcConfigInput;
     477: invokevirtual #69                 // Method java/lang/Class.cast:(Ljava/lang/Object;)Ljava/lang/Object;
     480: invokestatic  #70                 // Method java/util/Optional.ofNullable:(Ljava/lang/Object;)Ljava/util/Optional;
     483: areturn
     484: aload_2
     485: aload_0
     486: invokevirtual #45                 // Method tags:()Ljava/util/Map;
     489: invokevirtual #69                 // Method java/lang/Class.cast:(Ljava/lang/Object;)Ljava/lang/Object;
     492: invokestatic  #70                 // Method java/util/Optional.ofNullable:(Ljava/lang/Object;)Ljava/util/Optional;
     495: areturn
     496: aload_2
     497: aload_0
     498: invokevirtual #46                 // Method artifactConfig:()Lsoftware/amazon/awssdk/services/synthetics/model/ArtifactConfigInput;
     501: invokevirtual #69                 // Method java/lang/Class.cast:(Ljava/lang/Object;)Ljava/lang/Object;
     504: invokestatic  #70                 // Method java/util/Optional.ofNullable:(Ljava/lang/Object;)Ljava/util/Optional;
     507: areturn
     508: invokestatic  #71                 // Method java/util/Optional.empty:()Ljava/util/Optional;
     511: areturn

  public final java.util.List<software.amazon.awssdk.core.SdkField<?>> sdkFields();
    Code:
       0: getstatic     #1                  // Field SDK_FIELDS:Ljava/util/List;
       3: areturn

  private static <T> java.util.function.Function<java.lang.Object, T> getter(java.util.function.Function<software.amazon.awssdk.services.synthetics.model.CreateCanaryRequest, T>);
    Code:
       0: aload_0
       1: invokedynamic #72,  0             // InvokeDynamic #0:apply:(Ljava/util/function/Function;)Ljava/util/function/Function;
       6: areturn

  private static <T> java.util.function.BiConsumer<java.lang.Object, T> setter(java.util.function.BiConsumer<software.amazon.awssdk.services.synthetics.model.CreateCanaryRequest$Builder, T>);
    Code:
       0: aload_0
       1: invokedynamic #73,  0             // InvokeDynamic #1:accept:(Ljava/util/function/BiConsumer;)Ljava/util/function/BiConsumer;
       6: areturn

  public software.amazon.awssdk.services.synthetics.model.SyntheticsRequest$Builder toBuilder();
    Code:
       0: aload_0
       1: invokevirtual #74                 // Method toBuilder:()Lsoftware/amazon/awssdk/services/synthetics/model/CreateCanaryRequest$Builder;
       4: areturn

  public software.amazon.awssdk.awscore.AwsRequest$Builder toBuilder();
    Code:
       0: aload_0
       1: invokevirtual #74                 // Method toBuilder:()Lsoftware/amazon/awssdk/services/synthetics/model/CreateCanaryRequest$Builder;
       4: areturn

  public software.amazon.awssdk.core.SdkRequest$Builder toBuilder();
    Code:
       0: aload_0
       1: invokevirtual #74                 // Method toBuilder:()Lsoftware/amazon/awssdk/services/synthetics/model/CreateCanaryRequest$Builder;
       4: areturn

  public software.amazon.awssdk.utils.builder.CopyableBuilder toBuilder();
    Code:
       0: aload_0
       1: invokevirtual #74                 // Method toBuilder:()Lsoftware/amazon/awssdk/services/synthetics/model/CreateCanaryRequest$Builder;
       4: areturn

  private static void lambda$setter$1(java.util.function.BiConsumer, java.lang.Object, java.lang.Object);
    Code:
       0: aload_0
       1: aload_1
       2: checkcast     #75                 // class software/amazon/awssdk/services/synthetics/model/CreateCanaryRequest$Builder
       5: aload_2
       6: invokeinterface #76,  3           // InterfaceMethod java/util/function/BiConsumer.accept:(Ljava/lang/Object;Ljava/lang/Object;)V
      11: return

  private static java.lang.Object lambda$getter$0(java.util.function.Function, java.lang.Object);
    Code:
       0: aload_0
       1: aload_1
       2: checkcast     #49                 // class software/amazon/awssdk/services/synthetics/model/CreateCanaryRequest
       5: invokeinterface #77,  2           // InterfaceMethod java/util/function/Function.apply:(Ljava/lang/Object;)Ljava/lang/Object;
      10: areturn

  static java.lang.String access$1400(software.amazon.awssdk.services.synthetics.model.CreateCanaryRequest);
    Code:
       0: aload_0
       1: getfield      #14                 // Field name:Ljava/lang/String;
       4: areturn

  static software.amazon.awssdk.services.synthetics.model.CanaryCodeInput access$1500(software.amazon.awssdk.services.synthetics.model.CreateCanaryRequest);
    Code:
       0: aload_0
       1: getfield      #13                 // Field code:Lsoftware/amazon/awssdk/services/synthetics/model/CanaryCodeInput;
       4: areturn

  static java.lang.String access$1600(software.amazon.awssdk.services.synthetics.model.CreateCanaryRequest);
    Code:
       0: aload_0
       1: getfield      #12                 // Field artifactS3Location:Ljava/lang/String;
       4: areturn

  static java.lang.String access$1700(software.amazon.awssdk.services.synthetics.model.CreateCanaryRequest);
    Code:
       0: aload_0
       1: getfield      #11                 // Field executionRoleArn:Ljava/lang/String;
       4: areturn

  static software.amazon.awssdk.services.synthetics.model.CanaryScheduleInput access$1800(software.amazon.awssdk.services.synthetics.model.CreateCanaryRequest);
    Code:
       0: aload_0
       1: getfield      #10                 // Field schedule:Lsoftware/amazon/awssdk/services/synthetics/model/CanaryScheduleInput;
       4: areturn

  static software.amazon.awssdk.services.synthetics.model.CanaryRunConfigInput access$1900(software.amazon.awssdk.services.synthetics.model.CreateCanaryRequest);
    Code:
       0: aload_0
       1: getfield      #9                  // Field runConfig:Lsoftware/amazon/awssdk/services/synthetics/model/CanaryRunConfigInput;
       4: areturn

  static java.lang.Integer access$2000(software.amazon.awssdk.services.synthetics.model.CreateCanaryRequest);
    Code:
       0: aload_0
       1: getfield      #8                  // Field successRetentionPeriodInDays:Ljava/lang/Integer;
       4: areturn

  static java.lang.Integer access$2100(software.amazon.awssdk.services.synthetics.model.CreateCanaryRequest);
    Code:
       0: aload_0
       1: getfield      #7                  // Field failureRetentionPeriodInDays:Ljava/lang/Integer;
       4: areturn

  static java.lang.String access$2200(software.amazon.awssdk.services.synthetics.model.CreateCanaryRequest);
    Code:
       0: aload_0
       1: getfield      #6                  // Field runtimeVersion:Ljava/lang/String;
       4: areturn

  static software.amazon.awssdk.services.synthetics.model.VpcConfigInput access$2300(software.amazon.awssdk.services.synthetics.model.CreateCanaryRequest);
    Code:
       0: aload_0
       1: getfield      #5                  // Field vpcConfig:Lsoftware/amazon/awssdk/services/synthetics/model/VpcConfigInput;
       4: areturn

  static java.util.Map access$2400(software.amazon.awssdk.services.synthetics.model.CreateCanaryRequest);
    Code:
       0: aload_0
       1: getfield      #4                  // Field tags:Ljava/util/Map;
       4: areturn

  static software.amazon.awssdk.services.synthetics.model.ArtifactConfigInput access$2500(software.amazon.awssdk.services.synthetics.model.CreateCanaryRequest);
    Code:
       0: aload_0
       1: getfield      #3                  // Field artifactConfig:Lsoftware/amazon/awssdk/services/synthetics/model/ArtifactConfigInput;
       4: areturn

  software.amazon.awssdk.services.synthetics.model.CreateCanaryRequest(software.amazon.awssdk.services.synthetics.model.CreateCanaryRequest$BuilderImpl, software.amazon.awssdk.services.synthetics.model.CreateCanaryRequest$1);
    Code:
       0: aload_0
       1: aload_1
       2: invokespecial #2                  // Method "<init>":(Lsoftware/amazon/awssdk/services/synthetics/model/CreateCanaryRequest$BuilderImpl;)V
       5: return

  static java.util.List access$2700();
    Code:
       0: getstatic     #1                  // Field SDK_FIELDS:Ljava/util/List;
       3: areturn

  static {};
    Code:
       0: getstatic     #78                 // Field software/amazon/awssdk/core/protocol/MarshallingType.STRING:Lsoftware/amazon/awssdk/core/protocol/MarshallingType;
       3: invokestatic  #79                 // Method software/amazon/awssdk/core/SdkField.builder:(Lsoftware/amazon/awssdk/core/protocol/MarshallingType;)Lsoftware/amazon/awssdk/core/SdkField$Builder;
       6: ldc           #53                 // String Name
       8: invokevirtual #80                 // Method software/amazon/awssdk/core/SdkField$Builder.memberName:(Ljava/lang/String;)Lsoftware/amazon/awssdk/core/SdkField$Builder;
      11: invokedynamic #81,  0             // InvokeDynamic #2:apply:()Ljava/util/function/Function;
      16: invokestatic  #82                 // Method getter:(Ljava/util/function/Function;)Ljava/util/function/Function;
      19: invokevirtual #83                 // Method software/amazon/awssdk/core/SdkField$Builder.getter:(Ljava/util/function/Function;)Lsoftware/amazon/awssdk/core/SdkField$Builder;
      22: invokedynamic #84,  0             // InvokeDynamic #3:accept:()Ljava/util/function/BiConsumer;
      27: invokestatic  #85                 // Method setter:(Ljava/util/function/BiConsumer;)Ljava/util/function/BiConsumer;
      30: invokevirtual #86                 // Method software/amazon/awssdk/core/SdkField$Builder.setter:(Ljava/util/function/BiConsumer;)Lsoftware/amazon/awssdk/core/SdkField$Builder;
      33: iconst_1
      34: anewarray     #87                 // class software/amazon/awssdk/core/traits/Trait
      37: dup
      38: iconst_0
      39: invokestatic  #88                 // Method software/amazon/awssdk/core/traits/LocationTrait.builder:()Lsoftware/amazon/awssdk/core/traits/LocationTrait$Builder;
      42: getstatic     #89                 // Field software/amazon/awssdk/core/protocol/MarshallLocation.PAYLOAD:Lsoftware/amazon/awssdk/core/protocol/MarshallLocation;
      45: invokevirtual #90                 // Method software/amazon/awssdk/core/traits/LocationTrait$Builder.location:(Lsoftware/amazon/awssdk/core/protocol/MarshallLocation;)Lsoftware/amazon/awssdk/core/traits/LocationTrait$Builder;
      48: ldc           #53                 // String Name
      50: invokevirtual #91                 // Method software/amazon/awssdk/core/traits/LocationTrait$Builder.locationName:(Ljava/lang/String;)Lsoftware/amazon/awssdk/core/traits/LocationTrait$Builder;
      53: invokevirtual #92                 // Method software/amazon/awssdk/core/traits/LocationTrait$Builder.build:()Lsoftware/amazon/awssdk/core/traits/LocationTrait;
      56: aastore
      57: invokevirtual #93                 // Method software/amazon/awssdk/core/SdkField$Builder.traits:([Lsoftware/amazon/awssdk/core/traits/Trait;)Lsoftware/amazon/awssdk/core/SdkField$Builder;
      60: invokevirtual #94                 // Method software/amazon/awssdk/core/SdkField$Builder.build:()Lsoftware/amazon/awssdk/core/SdkField;
      63: putstatic     #95                 // Field NAME_FIELD:Lsoftware/amazon/awssdk/core/SdkField;
      66: getstatic     #96                 // Field software/amazon/awssdk/core/protocol/MarshallingType.SDK_POJO:Lsoftware/amazon/awssdk/core/protocol/MarshallingType;
      69: invokestatic  #79                 // Method software/amazon/awssdk/core/SdkField.builder:(Lsoftware/amazon/awssdk/core/protocol/MarshallingType;)Lsoftware/amazon/awssdk/core/SdkField$Builder;
      72: ldc           #55                 // String Code
      74: invokevirtual #80                 // Method software/amazon/awssdk/core/SdkField$Builder.memberName:(Ljava/lang/String;)Lsoftware/amazon/awssdk/core/SdkField$Builder;
      77: invokedynamic #97,  0             // InvokeDynamic #4:apply:()Ljava/util/function/Function;
      82: invokestatic  #82                 // Method getter:(Ljava/util/function/Function;)Ljava/util/function/Function;
      85: invokevirtual #83                 // Method software/amazon/awssdk/core/SdkField$Builder.getter:(Ljava/util/function/Function;)Lsoftware/amazon/awssdk/core/SdkField$Builder;
      88: invokedynamic #98,  0             // InvokeDynamic #5:accept:()Ljava/util/function/BiConsumer;
      93: invokestatic  #85                 // Method setter:(Ljava/util/function/BiConsumer;)Ljava/util/function/BiConsumer;
      96: invokevirtual #86                 // Method software/amazon/awssdk/core/SdkField$Builder.setter:(Ljava/util/function/BiConsumer;)Lsoftware/amazon/awssdk/core/SdkField$Builder;
      99: invokedynamic #99,  0             // InvokeDynamic #6:get:()Ljava/util/function/Supplier;
     104: invokevirtual #100                // Method software/amazon/awssdk/core/SdkField$Builder.constructor:(Ljava/util/function/Supplier;)Lsoftware/amazon/awssdk/core/SdkField$Builder;
     107: iconst_1
     108: anewarray     #87                 // class software/amazon/awssdk/core/traits/Trait
     111: dup
     112: iconst_0
     113: invokestatic  #88                 // Method software/amazon/awssdk/core/traits/LocationTrait.builder:()Lsoftware/amazon/awssdk/core/traits/LocationTrait$Builder;
     116: getstatic     #89                 // Field software/amazon/awssdk/core/protocol/MarshallLocation.PAYLOAD:Lsoftware/amazon/awssdk/core/protocol/MarshallLocation;
     119: invokevirtual #90                 // Method software/amazon/awssdk/core/traits/LocationTrait$Builder.location:(Lsoftware/amazon/awssdk/core/protocol/MarshallLocation;)Lsoftware/amazon/awssdk/core/traits/LocationTrait$Builder;
     122: ldc           #55                 // String Code
     124: invokevirtual #91                 // Method software/amazon/awssdk/core/traits/LocationTrait$Builder.locationName:(Ljava/lang/String;)Lsoftware/amazon/awssdk/core/traits/LocationTrait$Builder;
     127: invokevirtual #92                 // Method software/amazon/awssdk/core/traits/LocationTrait$Builder.build:()Lsoftware/amazon/awssdk/core/traits/LocationTrait;
     130: aastore
     131: invokevirtual #93                 // Method software/amazon/awssdk/core/SdkField$Builder.traits:([Lsoftware/amazon/awssdk/core/traits/Trait;)Lsoftware/amazon/awssdk/core/SdkField$Builder;
     134: invokevirtual #94                 // Method software/amazon/awssdk/core/SdkField$Builder.build:()Lsoftware/amazon/awssdk/core/SdkField;
     137: putstatic     #101                // Field CODE_FIELD:Lsoftware/amazon/awssdk/core/SdkField;
     140: getstatic     #78                 // Field software/amazon/awssdk/core/protocol/MarshallingType.STRING:Lsoftware/amazon/awssdk/core/protocol/MarshallingType;
     143: invokestatic  #79                 // Method software/amazon/awssdk/core/SdkField.builder:(Lsoftware/amazon/awssdk/core/protocol/MarshallingType;)Lsoftware/amazon/awssdk/core/SdkField$Builder;
     146: ldc           #56                 // String ArtifactS3Location
     148: invokevirtual #80                 // Method software/amazon/awssdk/core/SdkField$Builder.memberName:(Ljava/lang/String;)Lsoftware/amazon/awssdk/core/SdkField$Builder;
     151: invokedynamic #102,  0            // InvokeDynamic #7:apply:()Ljava/util/function/Function;
     156: invokestatic  #82                 // Method getter:(Ljava/util/function/Function;)Ljava/util/function/Function;
     159: invokevirtual #83                 // Method software/amazon/awssdk/core/SdkField$Builder.getter:(Ljava/util/function/Function;)Lsoftware/amazon/awssdk/core/SdkField$Builder;
     162: invokedynamic #103,  0            // InvokeDynamic #8:accept:()Ljava/util/function/BiConsumer;
     167: invokestatic  #85                 // Method setter:(Ljava/util/function/BiConsumer;)Ljava/util/function/BiConsumer;
     170: invokevirtual #86                 // Method software/amazon/awssdk/core/SdkField$Builder.setter:(Ljava/util/function/BiConsumer;)Lsoftware/amazon/awssdk/core/SdkField$Builder;
     173: iconst_1
     174: anewarray     #87                 // class software/amazon/awssdk/core/traits/Trait
     177: dup
     178: iconst_0
     179: invokestatic  #88                 // Method software/amazon/awssdk/core/traits/LocationTrait.builder:()Lsoftware/amazon/awssdk/core/traits/LocationTrait$Builder;
     182: getstatic     #89                 // Field software/amazon/awssdk/core/protocol/MarshallLocation.PAYLOAD:Lsoftware/amazon/awssdk/core/protocol/MarshallLocation;
     185: invokevirtual #90                 // Method software/amazon/awssdk/core/traits/LocationTrait$Builder.location:(Lsoftware/amazon/awssdk/core/protocol/MarshallLocation;)Lsoftware/amazon/awssdk/core/traits/LocationTrait$Builder;
     188: ldc           #56                 // String ArtifactS3Location
     190: invokevirtual #91                 // Method software/amazon/awssdk/core/traits/LocationTrait$Builder.locationName:(Ljava/lang/String;)Lsoftware/amazon/awssdk/core/traits/LocationTrait$Builder;
     193: invokevirtual #92                 // Method software/amazon/awssdk/core/traits/LocationTrait$Builder.build:()Lsoftware/amazon/awssdk/core/traits/LocationTrait;
     196: aastore
     197: invokevirtual #93                 // Method software/amazon/awssdk/core/SdkField$Builder.traits:([Lsoftware/amazon/awssdk/core/traits/Trait;)Lsoftware/amazon/awssdk/core/SdkField$Builder;
     200: invokevirtual #94                 // Method software/amazon/awssdk/core/SdkField$Builder.build:()Lsoftware/amazon/awssdk/core/SdkField;
     203: putstatic     #104                // Field ARTIFACT_S3_LOCATION_FIELD:Lsoftware/amazon/awssdk/core/SdkField;
     206: getstatic     #78                 // Field software/amazon/awssdk/core/protocol/MarshallingType.STRING:Lsoftware/amazon/awssdk/core/protocol/MarshallingType;
     209: invokestatic  #79                 // Method software/amazon/awssdk/core/SdkField.builder:(Lsoftware/amazon/awssdk/core/protocol/MarshallingType;)Lsoftware/amazon/awssdk/core/SdkField$Builder;
     212: ldc           #57                 // String ExecutionRoleArn
     214: invokevirtual #80                 // Method software/amazon/awssdk/core/SdkField$Builder.memberName:(Ljava/lang/String;)Lsoftware/amazon/awssdk/core/SdkField$Builder;
     217: invokedynamic #105,  0            // InvokeDynamic #9:apply:()Ljava/util/function/Function;
     222: invokestatic  #82                 // Method getter:(Ljava/util/function/Function;)Ljava/util/function/Function;
     225: invokevirtual #83                 // Method software/amazon/awssdk/core/SdkField$Builder.getter:(Ljava/util/function/Function;)Lsoftware/amazon/awssdk/core/SdkField$Builder;
     228: invokedynamic #106,  0            // InvokeDynamic #10:accept:()Ljava/util/function/BiConsumer;
     233: invokestatic  #85                 // Method setter:(Ljava/util/function/BiConsumer;)Ljava/util/function/BiConsumer;
     236: invokevirtual #86                 // Method software/amazon/awssdk/core/SdkField$Builder.setter:(Ljava/util/function/BiConsumer;)Lsoftware/amazon/awssdk/core/SdkField$Builder;
     239: iconst_1
     240: anewarray     #87                 // class software/amazon/awssdk/core/traits/Trait
     243: dup
     244: iconst_0
     245: invokestatic  #88                 // Method software/amazon/awssdk/core/traits/LocationTrait.builder:()Lsoftware/amazon/awssdk/core/traits/LocationTrait$Builder;
     248: getstatic     #89                 // Field software/amazon/awssdk/core/protocol/MarshallLocation.PAYLOAD:Lsoftware/amazon/awssdk/core/protocol/MarshallLocation;
     251: invokevirtual #90                 // Method software/amazon/awssdk/core/traits/LocationTrait$Builder.location:(Lsoftware/amazon/awssdk/core/protocol/MarshallLocation;)Lsoftware/amazon/awssdk/core/traits/LocationTrait$Builder;
     254: ldc           #57                 // String ExecutionRoleArn
     256: invokevirtual #91                 // Method software/amazon/awssdk/core/traits/LocationTrait$Builder.locationName:(Ljava/lang/String;)Lsoftware/amazon/awssdk/core/traits/LocationTrait$Builder;
     259: invokevirtual #92                 // Method software/amazon/awssdk/core/traits/LocationTrait$Builder.build:()Lsoftware/amazon/awssdk/core/traits/LocationTrait;
     262: aastore
     263: invokevirtual #93                 // Method software/amazon/awssdk/core/SdkField$Builder.traits:([Lsoftware/amazon/awssdk/core/traits/Trait;)Lsoftware/amazon/awssdk/core/SdkField$Builder;
     266: invokevirtual #94                 // Method software/amazon/awssdk/core/SdkField$Builder.build:()Lsoftware/amazon/awssdk/core/SdkField;
     269: putstatic     #107                // Field EXECUTION_ROLE_ARN_FIELD:Lsoftware/amazon/awssdk/core/SdkField;
     272: getstatic     #96                 // Field software/amazon/awssdk/core/protocol/MarshallingType.SDK_POJO:Lsoftware/amazon/awssdk/core/protocol/MarshallingType;
     275: invokestatic  #79                 // Method software/amazon/awssdk/core/SdkField.builder:(Lsoftware/amazon/awssdk/core/protocol/MarshallingType;)Lsoftware/amazon/awssdk/core/SdkField$Builder;
     278: ldc           #58                 // String Schedule
     280: invokevirtual #80                 // Method software/amazon/awssdk/core/SdkField$Builder.memberName:(Ljava/lang/String;)Lsoftware/amazon/awssdk/core/SdkField$Builder;
     283: invokedynamic #108,  0            // InvokeDynamic #11:apply:()Ljava/util/function/Function;
     288: invokestatic  #82                 // Method getter:(Ljava/util/function/Function;)Ljava/util/function/Function;
     291: invokevirtual #83                 // Method software/amazon/awssdk/core/SdkField$Builder.getter:(Ljava/util/function/Function;)Lsoftware/amazon/awssdk/core/SdkField$Builder;
     294: invokedynamic #109,  0            // InvokeDynamic #12:accept:()Ljava/util/function/BiConsumer;
     299: invokestatic  #85                 // Method setter:(Ljava/util/function/BiConsumer;)Ljava/util/function/BiConsumer;
     302: invokevirtual #86                 // Method software/amazon/awssdk/core/SdkField$Builder.setter:(Ljava/util/function/BiConsumer;)Lsoftware/amazon/awssdk/core/SdkField$Builder;
     305: invokedynamic #110,  0            // InvokeDynamic #13:get:()Ljava/util/function/Supplier;
     310: invokevirtual #100                // Method software/amazon/awssdk/core/SdkField$Builder.constructor:(Ljava/util/function/Supplier;)Lsoftware/amazon/awssdk/core/SdkField$Builder;
     313: iconst_1
     314: anewarray     #87                 // class software/amazon/awssdk/core/traits/Trait
     317: dup
     318: iconst_0
     319: invokestatic  #88                 // Method software/amazon/awssdk/core/traits/LocationTrait.builder:()Lsoftware/amazon/awssdk/core/traits/LocationTrait$Builder;
     322: getstatic     #89                 // Field software/amazon/awssdk/core/protocol/MarshallLocation.PAYLOAD:Lsoftware/amazon/awssdk/core/protocol/MarshallLocation;
     325: invokevirtual #90                 // Method software/amazon/awssdk/core/traits/LocationTrait$Builder.location:(Lsoftware/amazon/awssdk/core/protocol/MarshallLocation;)Lsoftware/amazon/awssdk/core/traits/LocationTrait$Builder;
     328: ldc           #58                 // String Schedule
     330: invokevirtual #91                 // Method software/amazon/awssdk/core/traits/LocationTrait$Builder.locationName:(Ljava/lang/String;)Lsoftware/amazon/awssdk/core/traits/LocationTrait$Builder;
     333: invokevirtual #92                 // Method software/amazon/awssdk/core/traits/LocationTrait$Builder.build:()Lsoftware/amazon/awssdk/core/traits/LocationTrait;
     336: aastore
     337: invokevirtual #93                 // Method software/amazon/awssdk/core/SdkField$Builder.traits:([Lsoftware/amazon/awssdk/core/traits/Trait;)Lsoftware/amazon/awssdk/core/SdkField$Builder;
     340: invokevirtual #94                 // Method software/amazon/awssdk/core/SdkField$Builder.build:()Lsoftware/amazon/awssdk/core/SdkField;
     343: putstatic     #111                // Field SCHEDULE_FIELD:Lsoftware/amazon/awssdk/core/SdkField;
     346: getstatic     #96                 // Field software/amazon/awssdk/core/protocol/MarshallingType.SDK_POJO:Lsoftware/amazon/awssdk/core/protocol/MarshallingType;
     349: invokestatic  #79                 // Method software/amazon/awssdk/core/SdkField.builder:(Lsoftware/amazon/awssdk/core/protocol/MarshallingType;)Lsoftware/amazon/awssdk/core/SdkField$Builder;
     352: ldc           #59                 // String RunConfig
     354: invokevirtual #80                 // Method software/amazon/awssdk/core/SdkField$Builder.memberName:(Ljava/lang/String;)Lsoftware/amazon/awssdk/core/SdkField$Builder;
     357: invokedynamic #112,  0            // InvokeDynamic #14:apply:()Ljava/util/function/Function;
     362: invokestatic  #82                 // Method getter:(Ljava/util/function/Function;)Ljava/util/function/Function;
     365: invokevirtual #83                 // Method software/amazon/awssdk/core/SdkField$Builder.getter:(Ljava/util/function/Function;)Lsoftware/amazon/awssdk/core/SdkField$Builder;
     368: invokedynamic #113,  0            // InvokeDynamic #15:accept:()Ljava/util/function/BiConsumer;
     373: invokestatic  #85                 // Method setter:(Ljava/util/function/BiConsumer;)Ljava/util/function/BiConsumer;
     376: invokevirtual #86                 // Method software/amazon/awssdk/core/SdkField$Builder.setter:(Ljava/util/function/BiConsumer;)Lsoftware/amazon/awssdk/core/SdkField$Builder;
     379: invokedynamic #114,  0            // InvokeDynamic #16:get:()Ljava/util/function/Supplier;
     384: invokevirtual #100                // Method software/amazon/awssdk/core/SdkField$Builder.constructor:(Ljava/util/function/Supplier;)Lsoftware/amazon/awssdk/core/SdkField$Builder;
     387: iconst_1
     388: anewarray     #87                 // class software/amazon/awssdk/core/traits/Trait
     391: dup
     392: iconst_0
     393: invokestatic  #88                 // Method software/amazon/awssdk/core/traits/LocationTrait.builder:()Lsoftware/amazon/awssdk/core/traits/LocationTrait$Builder;
     396: getstatic     #89                 // Field software/amazon/awssdk/core/protocol/MarshallLocation.PAYLOAD:Lsoftware/amazon/awssdk/core/protocol/MarshallLocation;
     399: invokevirtual #90                 // Method software/amazon/awssdk/core/traits/LocationTrait$Builder.location:(Lsoftware/amazon/awssdk/core/protocol/MarshallLocation;)Lsoftware/amazon/awssdk/core/traits/LocationTrait$Builder;
     402: ldc           #59                 // String RunConfig
     404: invokevirtual #91                 // Method software/amazon/awssdk/core/traits/LocationTrait$Builder.locationName:(Ljava/lang/String;)Lsoftware/amazon/awssdk/core/traits/LocationTrait$Builder;
     407: invokevirtual #92                 // Method software/amazon/awssdk/core/traits/LocationTrait$Builder.build:()Lsoftware/amazon/awssdk/core/traits/LocationTrait;
     410: aastore
     411: invokevirtual #93                 // Method software/amazon/awssdk/core/SdkField$Builder.traits:([Lsoftware/amazon/awssdk/core/traits/Trait;)Lsoftware/amazon/awssdk/core/SdkField$Builder;
     414: invokevirtual #94                 // Method software/amazon/awssdk/core/SdkField$Builder.build:()Lsoftware/amazon/awssdk/core/SdkField;
     417: putstatic     #115                // Field RUN_CONFIG_FIELD:Lsoftware/amazon/awssdk/core/SdkField;
     420: getstatic     #116                // Field software/amazon/awssdk/core/protocol/MarshallingType.INTEGER:Lsoftware/amazon/awssdk/core/protocol/MarshallingType;
     423: invokestatic  #79                 // Method software/amazon/awssdk/core/SdkField.builder:(Lsoftware/amazon/awssdk/core/protocol/MarshallingType;)Lsoftware/amazon/awssdk/core/SdkField$Builder;
     426: ldc           #60                 // String SuccessRetentionPeriodInDays
     428: invokevirtual #80                 // Method software/amazon/awssdk/core/SdkField$Builder.memberName:(Ljava/lang/String;)Lsoftware/amazon/awssdk/core/SdkField$Builder;
     431: invokedynamic #117,  0            // InvokeDynamic #17:apply:()Ljava/util/function/Function;
     436: invokestatic  #82                 // Method getter:(Ljava/util/function/Function;)Ljava/util/function/Function;
     439: invokevirtual #83                 // Method software/amazon/awssdk/core/SdkField$Builder.getter:(Ljava/util/function/Function;)Lsoftware/amazon/awssdk/core/SdkField$Builder;
     442: invokedynamic #118,  0            // InvokeDynamic #18:accept:()Ljava/util/function/BiConsumer;
     447: invokestatic  #85                 // Method setter:(Ljava/util/function/BiConsumer;)Ljava/util/function/BiConsumer;
     450: invokevirtual #86                 // Method software/amazon/awssdk/core/SdkField$Builder.setter:(Ljava/util/function/BiConsumer;)Lsoftware/amazon/awssdk/core/SdkField$Builder;
     453: iconst_1
     454: anewarray     #87                 // class software/amazon/awssdk/core/traits/Trait
     457: dup
     458: iconst_0
     459: invokestatic  #88                 // Method software/amazon/awssdk/core/traits/LocationTrait.builder:()Lsoftware/amazon/awssdk/core/traits/LocationTrait$Builder;
     462: getstatic     #89                 // Field software/amazon/awssdk/core/protocol/MarshallLocation.PAYLOAD:Lsoftware/amazon/awssdk/core/protocol/MarshallLocation;
     465: invokevirtual #90                 // Method software/amazon/awssdk/core/traits/LocationTrait$Builder.location:(Lsoftware/amazon/awssdk/core/protocol/MarshallLocation;)Lsoftware/amazon/awssdk/core/traits/LocationTrait$Builder;
     468: ldc           #60                 // String SuccessRetentionPeriodInDays
     470: invokevirtual #91                 // Method software/amazon/awssdk/core/traits/LocationTrait$Builder.locationName:(Ljava/lang/String;)Lsoftware/amazon/awssdk/core/traits/LocationTrait$Builder;
     473: invokevirtual #92                 // Method software/amazon/awssdk/core/traits/LocationTrait$Builder.build:()Lsoftware/amazon/awssdk/core/traits/LocationTrait;
     476: aastore
     477: invokevirtual #93                 // Method software/amazon/awssdk/core/SdkField$Builder.traits:([Lsoftware/amazon/awssdk/core/traits/Trait;)Lsoftware/amazon/awssdk/core/SdkField$Builder;
     480: invokevirtual #94                 // Method software/amazon/awssdk/core/SdkField$Builder.build:()Lsoftware/amazon/awssdk/core/SdkField;
     483: putstatic     #119                // Field SUCCESS_RETENTION_PERIOD_IN_DAYS_FIELD:Lsoftware/amazon/awssdk/core/SdkField;
     486: getstatic     #116                // Field software/amazon/awssdk/core/protocol/MarshallingType.INTEGER:Lsoftware/amazon/awssdk/core/protocol/MarshallingType;
     489: invokestatic  #79                 // Method software/amazon/awssdk/core/SdkField.builder:(Lsoftware/amazon/awssdk/core/protocol/MarshallingType;)Lsoftware/amazon/awssdk/core/SdkField$Builder;
     492: ldc           #61                 // String FailureRetentionPeriodInDays
     494: invokevirtual #80                 // Method software/amazon/awssdk/core/SdkField$Builder.memberName:(Ljava/lang/String;)Lsoftware/amazon/awssdk/core/SdkField$Builder;
     497: invokedynamic #120,  0            // InvokeDynamic #19:apply:()Ljava/util/function/Function;
     502: invokestatic  #82                 // Method getter:(Ljava/util/function/Function;)Ljava/util/function/Function;
     505: invokevirtual #83                 // Method software/amazon/awssdk/core/SdkField$Builder.getter:(Ljava/util/function/Function;)Lsoftware/amazon/awssdk/core/SdkField$Builder;
     508: invokedynamic #121,  0            // InvokeDynamic #20:accept:()Ljava/util/function/BiConsumer;
     513: invokestatic  #85                 // Method setter:(Ljava/util/function/BiConsumer;)Ljava/util/function/BiConsumer;
     516: invokevirtual #86                 // Method software/amazon/awssdk/core/SdkField$Builder.setter:(Ljava/util/function/BiConsumer;)Lsoftware/amazon/awssdk/core/SdkField$Builder;
     519: iconst_1
     520: anewarray     #87                 // class software/amazon/awssdk/core/traits/Trait
     523: dup
     524: iconst_0
     525: invokestatic  #88                 // Method software/amazon/awssdk/core/traits/LocationTrait.builder:()Lsoftware/amazon/awssdk/core/traits/LocationTrait$Builder;
     528: getstatic     #89                 // Field software/amazon/awssdk/core/protocol/MarshallLocation.PAYLOAD:Lsoftware/amazon/awssdk/core/protocol/MarshallLocation;
     531: invokevirtual #90                 // Method software/amazon/awssdk/core/traits/LocationTrait$Builder.location:(Lsoftware/amazon/awssdk/core/protocol/MarshallLocation;)Lsoftware/amazon/awssdk/core/traits/LocationTrait$Builder;
     534: ldc           #61                 // String FailureRetentionPeriodInDays
     536: invokevirtual #91                 // Method software/amazon/awssdk/core/traits/LocationTrait$Builder.locationName:(Ljava/lang/String;)Lsoftware/amazon/awssdk/core/traits/LocationTrait$Builder;
     539: invokevirtual #92                 // Method software/amazon/awssdk/core/traits/LocationTrait$Builder.build:()Lsoftware/amazon/awssdk/core/traits/LocationTrait;
     542: aastore
     543: invokevirtual #93                 // Method software/amazon/awssdk/core/SdkField$Builder.traits:([Lsoftware/amazon/awssdk/core/traits/Trait;)Lsoftware/amazon/awssdk/core/SdkField$Builder;
     546: invokevirtual #94                 // Method software/amazon/awssdk/core/SdkField$Builder.build:()Lsoftware/amazon/awssdk/core/SdkField;
     549: putstatic     #122                // Field FAILURE_RETENTION_PERIOD_IN_DAYS_FIELD:Lsoftware/amazon/awssdk/core/SdkField;
     552: getstatic     #78                 // Field software/amazon/awssdk/core/protocol/MarshallingType.STRING:Lsoftware/amazon/awssdk/core/protocol/MarshallingType;
     555: invokestatic  #79                 // Method software/amazon/awssdk/core/SdkField.builder:(Lsoftware/amazon/awssdk/core/protocol/MarshallingType;)Lsoftware/amazon/awssdk/core/SdkField$Builder;
     558: ldc           #62                 // String RuntimeVersion
     560: invokevirtual #80                 // Method software/amazon/awssdk/core/SdkField$Builder.memberName:(Ljava/lang/String;)Lsoftware/amazon/awssdk/core/SdkField$Builder;
     563: invokedynamic #123,  0            // InvokeDynamic #21:apply:()Ljava/util/function/Function;
     568: invokestatic  #82                 // Method getter:(Ljava/util/function/Function;)Ljava/util/function/Function;
     571: invokevirtual #83                 // Method software/amazon/awssdk/core/SdkField$Builder.getter:(Ljava/util/function/Function;)Lsoftware/amazon/awssdk/core/SdkField$Builder;
     574: invokedynamic #124,  0            // InvokeDynamic #22:accept:()Ljava/util/function/BiConsumer;
     579: invokestatic  #85                 // Method setter:(Ljava/util/function/BiConsumer;)Ljava/util/function/BiConsumer;
     582: invokevirtual #86                 // Method software/amazon/awssdk/core/SdkField$Builder.setter:(Ljava/util/function/BiConsumer;)Lsoftware/amazon/awssdk/core/SdkField$Builder;
     585: iconst_1
     586: anewarray     #87                 // class software/amazon/awssdk/core/traits/Trait
     589: dup
     590: iconst_0
     591: invokestatic  #88                 // Method software/amazon/awssdk/core/traits/LocationTrait.builder:()Lsoftware/amazon/awssdk/core/traits/LocationTrait$Builder;
     594: getstatic     #89                 // Field software/amazon/awssdk/core/protocol/MarshallLocation.PAYLOAD:Lsoftware/amazon/awssdk/core/protocol/MarshallLocation;
     597: invokevirtual #90                 // Method software/amazon/awssdk/core/traits/LocationTrait$Builder.location:(Lsoftware/amazon/awssdk/core/protocol/MarshallLocation;)Lsoftware/amazon/awssdk/core/traits/LocationTrait$Builder;
     600: ldc           #62                 // String RuntimeVersion
     602: invokevirtual #91                 // Method software/amazon/awssdk/core/traits/LocationTrait$Builder.locationName:(Ljava/lang/String;)Lsoftware/amazon/awssdk/core/traits/LocationTrait$Builder;
     605: invokevirtual #92                 // Method software/amazon/awssdk/core/traits/LocationTrait$Builder.build:()Lsoftware/amazon/awssdk/core/traits/LocationTrait;
     608: aastore
     609: invokevirtual #93                 // Method software/amazon/awssdk/core/SdkField$Builder.traits:([Lsoftware/amazon/awssdk/core/traits/Trait;)Lsoftware/amazon/awssdk/core/SdkField$Builder;
     612: invokevirtual #94                 // Method software/amazon/awssdk/core/SdkField$Builder.build:()Lsoftware/amazon/awssdk/core/SdkField;
     615: putstatic     #125                // Field RUNTIME_VERSION_FIELD:Lsoftware/amazon/awssdk/core/SdkField;
     618: getstatic     #96                 // Field software/amazon/awssdk/core/protocol/MarshallingType.SDK_POJO:Lsoftware/amazon/awssdk/core/protocol/MarshallingType;
     621: invokestatic  #79                 // Method software/amazon/awssdk/core/SdkField.builder:(Lsoftware/amazon/awssdk/core/protocol/MarshallingType;)Lsoftware/amazon/awssdk/core/SdkField$Builder;
     624: ldc           #63                 // String VpcConfig
     626: invokevirtual #80                 // Method software/amazon/awssdk/core/SdkField$Builder.memberName:(Ljava/lang/String;)Lsoftware/amazon/awssdk/core/SdkField$Builder;
     629: invokedynamic #126,  0            // InvokeDynamic #23:apply:()Ljava/util/function/Function;
     634: invokestatic  #82                 // Method getter:(Ljava/util/function/Function;)Ljava/util/function/Function;
     637: invokevirtual #83                 // Method software/amazon/awssdk/core/SdkField$Builder.getter:(Ljava/util/function/Function;)Lsoftware/amazon/awssdk/core/SdkField$Builder;
     640: invokedynamic #127,  0            // InvokeDynamic #24:accept:()Ljava/util/function/BiConsumer;
     645: invokestatic  #85                 // Method setter:(Ljava/util/function/BiConsumer;)Ljava/util/function/BiConsumer;
     648: invokevirtual #86                 // Method software/amazon/awssdk/core/SdkField$Builder.setter:(Ljava/util/function/BiConsumer;)Lsoftware/amazon/awssdk/core/SdkField$Builder;
     651: invokedynamic #128,  0            // InvokeDynamic #25:get:()Ljava/util/function/Supplier;
     656: invokevirtual #100                // Method software/amazon/awssdk/core/SdkField$Builder.constructor:(Ljava/util/function/Supplier;)Lsoftware/amazon/awssdk/core/SdkField$Builder;
     659: iconst_1
     660: anewarray     #87                 // class software/amazon/awssdk/core/traits/Trait
     663: dup
     664: iconst_0
     665: invokestatic  #88                 // Method software/amazon/awssdk/core/traits/LocationTrait.builder:()Lsoftware/amazon/awssdk/core/traits/LocationTrait$Builder;
     668: getstatic     #89                 // Field software/amazon/awssdk/core/protocol/MarshallLocation.PAYLOAD:Lsoftware/amazon/awssdk/core/protocol/MarshallLocation;
     671: invokevirtual #90                 // Method software/amazon/awssdk/core/traits/LocationTrait$Builder.location:(Lsoftware/amazon/awssdk/core/protocol/MarshallLocation;)Lsoftware/amazon/awssdk/core/traits/LocationTrait$Builder;
     674: ldc           #63                 // String VpcConfig
     676: invokevirtual #91                 // Method software/amazon/awssdk/core/traits/LocationTrait$Builder.locationName:(Ljava/lang/String;)Lsoftware/amazon/awssdk/core/traits/LocationTrait$Builder;
     679: invokevirtual #92                 // Method software/amazon/awssdk/core/traits/LocationTrait$Builder.build:()Lsoftware/amazon/awssdk/core/traits/LocationTrait;
     682: aastore
     683: invokevirtual #93                 // Method software/amazon/awssdk/core/SdkField$Builder.traits:([Lsoftware/amazon/awssdk/core/traits/Trait;)Lsoftware/amazon/awssdk/core/SdkField$Builder;
     686: invokevirtual #94                 // Method software/amazon/awssdk/core/SdkField$Builder.build:()Lsoftware/amazon/awssdk/core/SdkField;
     689: putstatic     #129                // Field VPC_CONFIG_FIELD:Lsoftware/amazon/awssdk/core/SdkField;
     692: getstatic     #130                // Field software/amazon/awssdk/core/protocol/MarshallingType.MAP:Lsoftware/amazon/awssdk/core/protocol/MarshallingType;
     695: invokestatic  #79                 // Method software/amazon/awssdk/core/SdkField.builder:(Lsoftware/amazon/awssdk/core/protocol/MarshallingType;)Lsoftware/amazon/awssdk/core/SdkField$Builder;
     698: ldc           #64                 // String Tags
     700: invokevirtual #80                 // Method software/amazon/awssdk/core/SdkField$Builder.memberName:(Ljava/lang/String;)Lsoftware/amazon/awssdk/core/SdkField$Builder;
     703: invokedynamic #131,  0            // InvokeDynamic #26:apply:()Ljava/util/function/Function;
     708: invokestatic  #82                 // Method getter:(Ljava/util/function/Function;)Ljava/util/function/Function;
     711: invokevirtual #83                 // Method software/amazon/awssdk/core/SdkField$Builder.getter:(Ljava/util/function/Function;)Lsoftware/amazon/awssdk/core/SdkField$Builder;
     714: invokedynamic #132,  0            // InvokeDynamic #27:accept:()Ljava/util/function/BiConsumer;
     719: invokestatic  #85                 // Method setter:(Ljava/util/function/BiConsumer;)Ljava/util/function/BiConsumer;
     722: invokevirtual #86                 // Method software/amazon/awssdk/core/SdkField$Builder.setter:(Ljava/util/function/BiConsumer;)Lsoftware/amazon/awssdk/core/SdkField$Builder;
     725: iconst_2
     726: anewarray     #87                 // class software/amazon/awssdk/core/traits/Trait
     729: dup
     730: iconst_0
     731: invokestatic  #88                 // Method software/amazon/awssdk/core/traits/LocationTrait.builder:()Lsoftware/amazon/awssdk/core/traits/LocationTrait$Builder;
     734: getstatic     #89                 // Field software/amazon/awssdk/core/protocol/MarshallLocation.PAYLOAD:Lsoftware/amazon/awssdk/core/protocol/MarshallLocation;
     737: invokevirtual #90                 // Method software/amazon/awssdk/core/traits/LocationTrait$Builder.location:(Lsoftware/amazon/awssdk/core/protocol/MarshallLocation;)Lsoftware/amazon/awssdk/core/traits/LocationTrait$Builder;
     740: ldc           #64                 // String Tags
     742: invokevirtual #91                 // Method software/amazon/awssdk/core/traits/LocationTrait$Builder.locationName:(Ljava/lang/String;)Lsoftware/amazon/awssdk/core/traits/LocationTrait$Builder;
     745: invokevirtual #92                 // Method software/amazon/awssdk/core/traits/LocationTrait$Builder.build:()Lsoftware/amazon/awssdk/core/traits/LocationTrait;
     748: aastore
     749: dup
     750: iconst_1
     751: invokestatic  #133                // Method software/amazon/awssdk/core/traits/MapTrait.builder:()Lsoftware/amazon/awssdk/core/traits/MapTrait$Builder;
     754: ldc           #134                // String key
     756: invokevirtual #135                // Method software/amazon/awssdk/core/traits/MapTrait$Builder.keyLocationName:(Ljava/lang/String;)Lsoftware/amazon/awssdk/core/traits/MapTrait$Builder;
     759: ldc           #136                // String value
     761: invokevirtual #137                // Method software/amazon/awssdk/core/traits/MapTrait$Builder.valueLocationName:(Ljava/lang/String;)Lsoftware/amazon/awssdk/core/traits/MapTrait$Builder;
     764: getstatic     #78                 // Field software/amazon/awssdk/core/protocol/MarshallingType.STRING:Lsoftware/amazon/awssdk/core/protocol/MarshallingType;
     767: invokestatic  #79                 // Method software/amazon/awssdk/core/SdkField.builder:(Lsoftware/amazon/awssdk/core/protocol/MarshallingType;)Lsoftware/amazon/awssdk/core/SdkField$Builder;
     770: iconst_1
     771: anewarray     #87                 // class software/amazon/awssdk/core/traits/Trait
     774: dup
     775: iconst_0
     776: invokestatic  #88                 // Method software/amazon/awssdk/core/traits/LocationTrait.builder:()Lsoftware/amazon/awssdk/core/traits/LocationTrait$Builder;
     779: getstatic     #89                 // Field software/amazon/awssdk/core/protocol/MarshallLocation.PAYLOAD:Lsoftware/amazon/awssdk/core/protocol/MarshallLocation;
     782: invokevirtual #90                 // Method software/amazon/awssdk/core/traits/LocationTrait$Builder.location:(Lsoftware/amazon/awssdk/core/protocol/MarshallLocation;)Lsoftware/amazon/awssdk/core/traits/LocationTrait$Builder;
     785: ldc           #136                // String value
     787: invokevirtual #91                 // Method software/amazon/awssdk/core/traits/LocationTrait$Builder.locationName:(Ljava/lang/String;)Lsoftware/amazon/awssdk/core/traits/LocationTrait$Builder;
     790: invokevirtual #92                 // Method software/amazon/awssdk/core/traits/LocationTrait$Builder.build:()Lsoftware/amazon/awssdk/core/traits/LocationTrait;
     793: aastore
     794: invokevirtual #93                 // Method software/amazon/awssdk/core/SdkField$Builder.traits:([Lsoftware/amazon/awssdk/core/traits/Trait;)Lsoftware/amazon/awssdk/core/SdkField$Builder;
     797: invokevirtual #94                 // Method software/amazon/awssdk/core/SdkField$Builder.build:()Lsoftware/amazon/awssdk/core/SdkField;
     800: invokevirtual #138                // Method software/amazon/awssdk/core/traits/MapTrait$Builder.valueFieldInfo:(Lsoftware/amazon/awssdk/core/SdkField;)Lsoftware/amazon/awssdk/core/traits/MapTrait$Builder;
     803: invokevirtual #139                // Method software/amazon/awssdk/core/traits/MapTrait$Builder.build:()Lsoftware/amazon/awssdk/core/traits/MapTrait;
     806: aastore
     807: invokevirtual #93                 // Method software/amazon/awssdk/core/SdkField$Builder.traits:([Lsoftware/amazon/awssdk/core/traits/Trait;)Lsoftware/amazon/awssdk/core/SdkField$Builder;
     810: invokevirtual #94                 // Method software/amazon/awssdk/core/SdkField$Builder.build:()Lsoftware/amazon/awssdk/core/SdkField;
     813: putstatic     #140                // Field TAGS_FIELD:Lsoftware/amazon/awssdk/core/SdkField;
     816: getstatic     #96                 // Field software/amazon/awssdk/core/protocol/MarshallingType.SDK_POJO:Lsoftware/amazon/awssdk/core/protocol/MarshallingType;
     819: invokestatic  #79                 // Method software/amazon/awssdk/core/SdkField.builder:(Lsoftware/amazon/awssdk/core/protocol/MarshallingType;)Lsoftware/amazon/awssdk/core/SdkField$Builder;
     822: ldc           #65                 // String ArtifactConfig
     824: invokevirtual #80                 // Method software/amazon/awssdk/core/SdkField$Builder.memberName:(Ljava/lang/String;)Lsoftware/amazon/awssdk/core/SdkField$Builder;
     827: invokedynamic #141,  0            // InvokeDynamic #28:apply:()Ljava/util/function/Function;
     832: invokestatic  #82                 // Method getter:(Ljava/util/function/Function;)Ljava/util/function/Function;
     835: invokevirtual #83                 // Method software/amazon/awssdk/core/SdkField$Builder.getter:(Ljava/util/function/Function;)Lsoftware/amazon/awssdk/core/SdkField$Builder;
     838: invokedynamic #142,  0            // InvokeDynamic #29:accept:()Ljava/util/function/BiConsumer;
     843: invokestatic  #85                 // Method setter:(Ljava/util/function/BiConsumer;)Ljava/util/function/BiConsumer;
     846: invokevirtual #86                 // Method software/amazon/awssdk/core/SdkField$Builder.setter:(Ljava/util/function/BiConsumer;)Lsoftware/amazon/awssdk/core/SdkField$Builder;
     849: invokedynamic #143,  0            // InvokeDynamic #30:get:()Ljava/util/function/Supplier;
     854: invokevirtual #100                // Method software/amazon/awssdk/core/SdkField$Builder.constructor:(Ljava/util/function/Supplier;)Lsoftware/amazon/awssdk/core/SdkField$Builder;
     857: iconst_1
     858: anewarray     #87                 // class software/amazon/awssdk/core/traits/Trait
     861: dup
     862: iconst_0
     863: invokestatic  #88                 // Method software/amazon/awssdk/core/traits/LocationTrait.builder:()Lsoftware/amazon/awssdk/core/traits/LocationTrait$Builder;
     866: getstatic     #89                 // Field software/amazon/awssdk/core/protocol/MarshallLocation.PAYLOAD:Lsoftware/amazon/awssdk/core/protocol/MarshallLocation;
     869: invokevirtual #90                 // Method software/amazon/awssdk/core/traits/LocationTrait$Builder.location:(Lsoftware/amazon/awssdk/core/protocol/MarshallLocation;)Lsoftware/amazon/awssdk/core/traits/LocationTrait$Builder;
     872: ldc           #65                 // String ArtifactConfig
     874: invokevirtual #91                 // Method software/amazon/awssdk/core/traits/LocationTrait$Builder.locationName:(Ljava/lang/String;)Lsoftware/amazon/awssdk/core/traits/LocationTrait$Builder;
     877: invokevirtual #92                 // Method software/amazon/awssdk/core/traits/LocationTrait$Builder.build:()Lsoftware/amazon/awssdk/core/traits/LocationTrait;
     880: aastore
     881: invokevirtual #93                 // Method software/amazon/awssdk/core/SdkField$Builder.traits:([Lsoftware/amazon/awssdk/core/traits/Trait;)Lsoftware/amazon/awssdk/core/SdkField$Builder;
     884: invokevirtual #94                 // Method software/amazon/awssdk/core/SdkField$Builder.build:()Lsoftware/amazon/awssdk/core/SdkField;
     887: putstatic     #144                // Field ARTIFACT_CONFIG_FIELD:Lsoftware/amazon/awssdk/core/SdkField;
     890: bipush        12
     892: anewarray     #145                // class software/amazon/awssdk/core/SdkField
     895: dup
     896: iconst_0
     897: getstatic     #95                 // Field NAME_FIELD:Lsoftware/amazon/awssdk/core/SdkField;
     900: aastore
     901: dup
     902: iconst_1
     903: getstatic     #101                // Field CODE_FIELD:Lsoftware/amazon/awssdk/core/SdkField;
     906: aastore
     907: dup
     908: iconst_2
     909: getstatic     #104                // Field ARTIFACT_S3_LOCATION_FIELD:Lsoftware/amazon/awssdk/core/SdkField;
     912: aastore
     913: dup
     914: iconst_3
     915: getstatic     #107                // Field EXECUTION_ROLE_ARN_FIELD:Lsoftware/amazon/awssdk/core/SdkField;
     918: aastore
     919: dup
     920: iconst_4
     921: getstatic     #111                // Field SCHEDULE_FIELD:Lsoftware/amazon/awssdk/core/SdkField;
     924: aastore
     925: dup
     926: iconst_5
     927: getstatic     #115                // Field RUN_CONFIG_FIELD:Lsoftware/amazon/awssdk/core/SdkField;
     930: aastore
     931: dup
     932: bipush        6
     934: getstatic     #119                // Field SUCCESS_RETENTION_PERIOD_IN_DAYS_FIELD:Lsoftware/amazon/awssdk/core/SdkField;
     937: aastore
     938: dup
     939: bipush        7
     941: getstatic     #122                // Field FAILURE_RETENTION_PERIOD_IN_DAYS_FIELD:Lsoftware/amazon/awssdk/core/SdkField;
     944: aastore
     945: dup
     946: bipush        8
     948: getstatic     #125                // Field RUNTIME_VERSION_FIELD:Lsoftware/amazon/awssdk/core/SdkField;
     951: aastore
     952: dup
     953: bipush        9
     955: getstatic     #129                // Field VPC_CONFIG_FIELD:Lsoftware/amazon/awssdk/core/SdkField;
     958: aastore
     959: dup
     960: bipush        10
     962: getstatic     #140                // Field TAGS_FIELD:Lsoftware/amazon/awssdk/core/SdkField;
     965: aastore
     966: dup
     967: bipush        11
     969: getstatic     #144                // Field ARTIFACT_CONFIG_FIELD:Lsoftware/amazon/awssdk/core/SdkField;
     972: aastore
     973: invokestatic  #146                // Method java/util/Arrays.asList:([Ljava/lang/Object;)Ljava/util/List;
     976: invokestatic  #147                // Method java/util/Collections.unmodifiableList:(Ljava/util/List;)Ljava/util/List;
     979: putstatic     #1                  // Field SDK_FIELDS:Ljava/util/List;
     982: return
}
