Compiled from "CatCountRequest.java"
public class io.manbang.ebatis.core.request.CatCountRequest extends io.manbang.ebatis.core.request.CatRequest {
  private java.lang.String index;

  private java.lang.String format;

  public io.manbang.ebatis.core.request.CatCountRequest();
    Code:
       0: aload_0
       1: invokespecial #1                  // Method io/manbang/ebatis/core/request/CatRequest."<init>":()V
       4: return

  protected java.lang.String getSubEndpoint();
    Code:
       0: aload_0
       1: getfield      #2                  // Field index:Ljava/lang/String;
       4: invokestatic  #3                  // Method org/apache/commons/lang3/StringUtils.isNotBlank:(Ljava/lang/CharSequence;)Z
       7: ifeq          33
      10: new           #4                  // class java/lang/StringBuilder
      13: dup
      14: invokespecial #5                  // Method java/lang/StringBuilder."<init>":()V
      17: ldc           #6                  // String /count/
      19: invokevirtual #7                  // Method java/lang/StringBuilder.append:(Ljava/lang/String;)Ljava/lang/StringBuilder;
      22: aload_0
      23: getfield      #2                  // Field index:Ljava/lang/String;
      26: invokevirtual #7                  // Method java/lang/StringBuilder.append:(Ljava/lang/String;)Ljava/lang/StringBuilder;
      29: invokevirtual #8                  // Method java/lang/StringBuilder.toString:()Ljava/lang/String;
      32: areturn
      33: ldc           #9                  // String /count
      35: areturn

  protected void customize(org.elasticsearch.client.Request);
    Code:
       0: aload_0
       1: getfield      #10                 // Field format:Ljava/lang/String;
       4: invokestatic  #3                  // Method org/apache/commons/lang3/StringUtils.isNotBlank:(Ljava/lang/CharSequence;)Z
       7: ifeq          20
      10: aload_1
      11: ldc           #11                 // String format
      13: aload_0
      14: getfield      #10                 // Field format:Ljava/lang/String;
      17: invokevirtual #12                 // Method org/elasticsearch/client/Request.addParameter:(Ljava/lang/String;Ljava/lang/String;)V
      20: return

  public io.manbang.ebatis.core.request.CatCountRequest index(java.lang.String);
    Code:
       0: aload_0
       1: aload_1
       2: putfield      #2                  // Field index:Ljava/lang/String;
       5: aload_0
       6: areturn

  public io.manbang.ebatis.core.request.CatCountRequest format(java.lang.String);
    Code:
       0: aload_0
       1: aload_1
       2: putfield      #10                 // Field format:Ljava/lang/String;
       5: aload_0
       6: areturn

  public java.lang.String index();
    Code:
       0: aload_0
       1: getfield      #2                  // Field index:Ljava/lang/String;
       4: areturn

  public java.lang.String format();
    Code:
       0: aload_0
       1: getfield      #10                 // Field format:Ljava/lang/String;
       4: areturn
}
