Compiled from "JSONSerializers.java"
class com.mongodb.util.JSONSerializers$DBRefBaseSerializer extends com.mongodb.util.JSONSerializers$CompoundObjectSerializer {
  com.mongodb.util.JSONSerializers$DBRefBaseSerializer(com.mongodb.util.ObjectSerializer);
    Code:
       0: aload_0
       1: aload_1
       2: invokespecial #1                  // Method com/mongodb/util/JSONSerializers$CompoundObjectSerializer."<init>":(Lcom/mongodb/util/ObjectSerializer;)V
       5: return

  public void serialize(java.lang.Object, java.lang.StringBuilder);
    Code:
       0: aload_1
       1: checkcast     #2                  // class com/mongodb/DBRef
       4: astore_3
       5: new           #3                  // class com/mongodb/BasicDBObject
       8: dup
       9: invokespecial #4                  // Method com/mongodb/BasicDBObject."<init>":()V
      12: astore        4
      14: aload         4
      16: ldc           #5                  // String $ref
      18: aload_3
      19: invokevirtual #6                  // Method com/mongodb/DBRef.getCollectionName:()Ljava/lang/String;
      22: invokevirtual #7                  // Method com/mongodb/BasicDBObject.put:(Ljava/lang/Object;Ljava/lang/Object;)Ljava/lang/Object;
      25: pop
      26: aload         4
      28: ldc           #8                  // String $id
      30: aload_3
      31: invokevirtual #9                  // Method com/mongodb/DBRef.getId:()Ljava/lang/Object;
      34: invokevirtual #7                  // Method com/mongodb/BasicDBObject.put:(Ljava/lang/Object;Ljava/lang/Object;)Ljava/lang/Object;
      37: pop
      38: aload_3
      39: invokevirtual #10                 // Method com/mongodb/DBRef.getDatabaseName:()Ljava/lang/String;
      42: ifnull        57
      45: aload         4
      47: ldc           #11                 // String $db
      49: aload_3
      50: invokevirtual #10                 // Method com/mongodb/DBRef.getDatabaseName:()Ljava/lang/String;
      53: invokevirtual #7                  // Method com/mongodb/BasicDBObject.put:(Ljava/lang/Object;Ljava/lang/Object;)Ljava/lang/Object;
      56: pop
      57: aload_0
      58: getfield      #12                 // Field serializer:Lcom/mongodb/util/ObjectSerializer;
      61: aload         4
      63: aload_2
      64: invokeinterface #13,  3           // InterfaceMethod com/mongodb/util/ObjectSerializer.serialize:(Ljava/lang/Object;Ljava/lang/StringBuilder;)V
      69: return
}
