Compiled from "HibernateBundle.java"
public class org.sdase.commons.server.hibernate.HibernateBundle<C extends io.dropwizard.Configuration> implements io.dropwizard.ConfiguredBundle<C> {
  private static final java.lang.String POSTGRES_DRIVER_CLASS;

  private static final java.util.Map<java.lang.String, java.lang.String> DEFAULT_PROPERTIES;

  private io.dropwizard.hibernate.HibernateBundle<C> delegate;

  private static java.util.Map<java.lang.String, java.lang.String> initDefaultProperties();
    Code:
       0: new           #4                  // class java/util/HashMap
       3: dup
       4: invokespecial #5                  // Method java/util/HashMap."<init>":()V
       7: astore_0
       8: aload_0
       9: ldc           #6                  // String charSet
      11: ldc           #7                  // String UTF-8
      13: invokeinterface #8,  3            // InterfaceMethod java/util/Map.put:(Ljava/lang/Object;Ljava/lang/Object;)Ljava/lang/Object;
      18: pop
      19: aload_0
      20: ldc           #9                  // String hibernate.dialect
      22: ldc           #10                 // String org.hibernate.dialect.PostgreSQLDialect
      24: invokeinterface #8,  3            // InterfaceMethod java/util/Map.put:(Ljava/lang/Object;Ljava/lang/Object;)Ljava/lang/Object;
      29: pop
      30: aload_0
      31: ldc           #11                 // String currentSchema
      33: ldc           #12                 // String public
      35: invokeinterface #8,  3            // InterfaceMethod java/util/Map.put:(Ljava/lang/Object;Ljava/lang/Object;)Ljava/lang/Object;
      40: pop
      41: aload_0
      42: areturn

  private org.sdase.commons.server.hibernate.HibernateBundle(java.util.Set<java.lang.String>, org.sdase.commons.server.hibernate.DatabaseConfigurationProvider<C>);
    Code:
       0: aload_0
       1: invokespecial #13                 // Method java/lang/Object."<init>":()V
       4: aload_1
       5: iconst_0
       6: anewarray     #14                 // class java/lang/String
       9: invokeinterface #15,  2           // InterfaceMethod java/util/Set.toArray:([Ljava/lang/Object;)[Ljava/lang/Object;
      14: checkcast     #16                 // class "[Ljava/lang/String;"
      17: astore_3
      18: aload_0
      19: new           #17                 // class org/sdase/commons/server/hibernate/HibernateBundle$1
      22: dup
      23: aload_0
      24: aload_3
      25: new           #18                 // class io/dropwizard/hibernate/SessionFactoryFactory
      28: dup
      29: invokespecial #19                 // Method io/dropwizard/hibernate/SessionFactoryFactory."<init>":()V
      32: aload_2
      33: invokespecial #20                 // Method org/sdase/commons/server/hibernate/HibernateBundle$1."<init>":(Lorg/sdase/commons/server/hibernate/HibernateBundle;[Ljava/lang/String;Lio/dropwizard/hibernate/SessionFactoryFactory;Lorg/sdase/commons/server/hibernate/DatabaseConfigurationProvider;)V
      36: putfield      #21                 // Field delegate:Lio/dropwizard/hibernate/HibernateBundle;
      39: return

  private org.sdase.commons.server.hibernate.HibernateBundle(java.util.List<java.lang.Class<?>>, org.sdase.commons.server.hibernate.DatabaseConfigurationProvider<C>);
    Code:
       0: aload_0
       1: invokespecial #13                 // Method java/lang/Object."<init>":()V
       4: aload_0
       5: new           #22                 // class org/sdase/commons/server/hibernate/HibernateBundle$2
       8: dup
       9: aload_0
      10: aload_1
      11: new           #18                 // class io/dropwizard/hibernate/SessionFactoryFactory
      14: dup
      15: invokespecial #19                 // Method io/dropwizard/hibernate/SessionFactoryFactory."<init>":()V
      18: aload_2
      19: invokespecial #23                 // Method org/sdase/commons/server/hibernate/HibernateBundle$2."<init>":(Lorg/sdase/commons/server/hibernate/HibernateBundle;Ljava/util/List;Lio/dropwizard/hibernate/SessionFactoryFactory;Lorg/sdase/commons/server/hibernate/DatabaseConfigurationProvider;)V
      22: putfield      #21                 // Field delegate:Lio/dropwizard/hibernate/HibernateBundle;
      25: return

  private void applyDefaultSettings(io.dropwizard.db.DataSourceFactory);
    Code:
       0: aload_1
       1: invokevirtual #24                 // Method io/dropwizard/db/DataSourceFactory.getDriverClass:()Ljava/lang/String;
       4: ifnonnull     13
       7: aload_1
       8: ldc           #26                 // String org.postgresql.Driver
      10: invokevirtual #27                 // Method io/dropwizard/db/DataSourceFactory.setDriverClass:(Ljava/lang/String;)V
      13: aload_1
      14: invokevirtual #28                 // Method io/dropwizard/db/DataSourceFactory.getProperties:()Ljava/util/Map;
      17: ifnonnull     31
      20: aload_1
      21: new           #29                 // class java/util/LinkedHashMap
      24: dup
      25: invokespecial #30                 // Method java/util/LinkedHashMap."<init>":()V
      28: invokevirtual #31                 // Method io/dropwizard/db/DataSourceFactory.setProperties:(Ljava/util/Map;)V
      31: getstatic     #32                 // Field DEFAULT_PROPERTIES:Ljava/util/Map;
      34: invokeinterface #33,  1           // InterfaceMethod java/util/Map.entrySet:()Ljava/util/Set;
      39: invokeinterface #34,  1           // InterfaceMethod java/util/Set.stream:()Ljava/util/stream/Stream;
      44: aload_1
      45: invokedynamic #35,  0             // InvokeDynamic #0:test:(Lio/dropwizard/db/DataSourceFactory;)Ljava/util/function/Predicate;
      50: invokeinterface #36,  2           // InterfaceMethod java/util/stream/Stream.filter:(Ljava/util/function/Predicate;)Ljava/util/stream/Stream;
      55: aload_1
      56: invokedynamic #37,  0             // InvokeDynamic #1:accept:(Lio/dropwizard/db/DataSourceFactory;)Ljava/util/function/Consumer;
      61: invokeinterface #38,  2           // InterfaceMethod java/util/stream/Stream.forEach:(Ljava/util/function/Consumer;)V
      66: return

  public static org.sdase.commons.server.hibernate.HibernateBundle$InitialBuilder builder();
    Code:
       0: new           #39                 // class org/sdase/commons/server/hibernate/HibernateBundle$Builder
       3: dup
       4: aconst_null
       5: invokespecial #40                 // Method org/sdase/commons/server/hibernate/HibernateBundle$Builder."<init>":(Lorg/sdase/commons/server/hibernate/HibernateBundle$1;)V
       8: areturn

  public org.hibernate.SessionFactory sessionFactory();
    Code:
       0: aload_0
       1: getfield      #21                 // Field delegate:Lio/dropwizard/hibernate/HibernateBundle;
       4: invokevirtual #41                 // Method io/dropwizard/hibernate/HibernateBundle.getSessionFactory:()Lorg/hibernate/SessionFactory;
       7: areturn

  public void initialize(io.dropwizard.setup.Bootstrap<?>);
    Code:
       0: aload_0
       1: getfield      #21                 // Field delegate:Lio/dropwizard/hibernate/HibernateBundle;
       4: aload_1
       5: invokevirtual #42                 // Method io/dropwizard/hibernate/HibernateBundle.initialize:(Lio/dropwizard/setup/Bootstrap;)V
       8: return

  public void run(C, io.dropwizard.setup.Environment) throws java.lang.Exception;
    Code:
       0: aload_0
       1: getfield      #21                 // Field delegate:Lio/dropwizard/hibernate/HibernateBundle;
       4: aload_1
       5: aload_2
       6: invokevirtual #43                 // Method io/dropwizard/hibernate/HibernateBundle.run:(Ljava/lang/Object;Lio/dropwizard/setup/Environment;)V
       9: return

  public void run(java.lang.Object, io.dropwizard.setup.Environment) throws java.lang.Exception;
    Code:
       0: aload_0
       1: aload_1
       2: checkcast     #44                 // class io/dropwizard/Configuration
       5: aload_2
       6: invokevirtual #45                 // Method run:(Lio/dropwizard/Configuration;Lio/dropwizard/setup/Environment;)V
       9: return

  private static void lambda$applyDefaultSettings$1(io.dropwizard.db.DataSourceFactory, java.util.Map$Entry);
    Code:
       0: aload_0
       1: invokevirtual #28                 // Method io/dropwizard/db/DataSourceFactory.getProperties:()Ljava/util/Map;
       4: aload_1
       5: invokeinterface #46,  1           // InterfaceMethod java/util/Map$Entry.getKey:()Ljava/lang/Object;
      10: aload_1
      11: invokeinterface #47,  1           // InterfaceMethod java/util/Map$Entry.getValue:()Ljava/lang/Object;
      16: invokeinterface #8,  3            // InterfaceMethod java/util/Map.put:(Ljava/lang/Object;Ljava/lang/Object;)Ljava/lang/Object;
      21: checkcast     #14                 // class java/lang/String
      24: pop
      25: return

  private static boolean lambda$applyDefaultSettings$0(io.dropwizard.db.DataSourceFactory, java.util.Map$Entry);
    Code:
       0: aload_0
       1: invokevirtual #28                 // Method io/dropwizard/db/DataSourceFactory.getProperties:()Ljava/util/Map;
       4: aload_1
       5: invokeinterface #46,  1           // InterfaceMethod java/util/Map$Entry.getKey:()Ljava/lang/Object;
      10: invokeinterface #48,  2           // InterfaceMethod java/util/Map.containsKey:(Ljava/lang/Object;)Z
      15: ifne          22
      18: iconst_1
      19: goto          23
      22: iconst_0
      23: ireturn

  static void access$000(org.sdase.commons.server.hibernate.HibernateBundle, io.dropwizard.db.DataSourceFactory);
    Code:
       0: aload_0
       1: aload_1
       2: invokespecial #3                  // Method applyDefaultSettings:(Lio/dropwizard/db/DataSourceFactory;)V
       5: return

  org.sdase.commons.server.hibernate.HibernateBundle(java.util.Set, org.sdase.commons.server.hibernate.DatabaseConfigurationProvider, org.sdase.commons.server.hibernate.HibernateBundle$1);
    Code:
       0: aload_0
       1: aload_1
       2: aload_2
       3: invokespecial #2                  // Method "<init>":(Ljava/util/Set;Lorg/sdase/commons/server/hibernate/DatabaseConfigurationProvider;)V
       6: return

  org.sdase.commons.server.hibernate.HibernateBundle(java.util.List, org.sdase.commons.server.hibernate.DatabaseConfigurationProvider, org.sdase.commons.server.hibernate.HibernateBundle$1);
    Code:
       0: aload_0
       1: aload_1
       2: aload_2
       3: invokespecial #1                  // Method "<init>":(Ljava/util/List;Lorg/sdase/commons/server/hibernate/DatabaseConfigurationProvider;)V
       6: return

  static {};
    Code:
       0: invokestatic  #49                 // Method initDefaultProperties:()Ljava/util/Map;
       3: putstatic     #32                 // Field DEFAULT_PROPERTIES:Ljava/util/Map;
       6: return
}
