Compiled from "ClasspathLocationStrategy.java"
public class org.apache.commons.configuration2.io.ClasspathLocationStrategy implements org.apache.commons.configuration2.io.FileLocationStrategy {
  public org.apache.commons.configuration2.io.ClasspathLocationStrategy();
    Code:
       0: aload_0
       1: invokespecial #1                  // Method java/lang/Object."<init>":()V
       4: return

  public java.net.URL locate(org.apache.commons.configuration2.io.FileSystem, org.apache.commons.configuration2.io.FileLocator);
    Code:
       0: aload_2
       1: invokevirtual #2                  // Method org/apache/commons/configuration2/io/FileLocator.getFileName:()Ljava/lang/String;
       4: invokestatic  #3                  // Method org/apache/commons/lang3/StringUtils.isEmpty:(Ljava/lang/CharSequence;)Z
       7: ifeq          14
      10: aconst_null
      11: goto          21
      14: aload_2
      15: invokevirtual #2                  // Method org/apache/commons/configuration2/io/FileLocator.getFileName:()Ljava/lang/String;
      18: invokestatic  #4                  // Method org/apache/commons/configuration2/io/FileLocatorUtils.locateFromClasspath:(Ljava/lang/String;)Ljava/net/URL;
      21: areturn
}
