Compiled from "ServerSessionPacketHandler.java"
class org.apache.activemq.artemis.core.protocol.core.ServerSessionPacketHandler$1 implements org.apache.activemq.artemis.core.io.IOCallback {
  final org.apache.activemq.artemis.core.protocol.core.Packet val$confirmPacket;

  final boolean val$flush;

  final boolean val$closeChannel;

  final org.apache.activemq.artemis.core.protocol.core.Packet val$response;

  final org.apache.activemq.artemis.core.protocol.core.ServerSessionPacketHandler this$0;

  org.apache.activemq.artemis.core.protocol.core.ServerSessionPacketHandler$1(org.apache.activemq.artemis.core.protocol.core.ServerSessionPacketHandler, org.apache.activemq.artemis.core.protocol.core.Packet, boolean, boolean, org.apache.activemq.artemis.core.protocol.core.Packet);
    Code:
       0: aload_0
       1: aload_1
       2: putfield      #1                  // Field this$0:Lorg/apache/activemq/artemis/core/protocol/core/ServerSessionPacketHandler;
       5: aload_0
       6: aload_2
       7: putfield      #2                  // Field val$confirmPacket:Lorg/apache/activemq/artemis/core/protocol/core/Packet;
      10: aload_0
      11: iload_3
      12: putfield      #3                  // Field val$flush:Z
      15: aload_0
      16: iload         4
      18: putfield      #4                  // Field val$closeChannel:Z
      21: aload_0
      22: aload         5
      24: putfield      #5                  // Field val$response:Lorg/apache/activemq/artemis/core/protocol/core/Packet;
      27: aload_0
      28: invokespecial #6                  // Method java/lang/Object."<init>":()V
      31: return

  public void onError(int, java.lang.String);
    Code:
       0: getstatic     #7                  // Field org/apache/activemq/artemis/core/server/ActiveMQServerLogger.LOGGER:Lorg/apache/activemq/artemis/core/server/ActiveMQServerLogger;
       3: iload_1
       4: invokestatic  #8                  // Method java/lang/Integer.valueOf:(I)Ljava/lang/Integer;
       7: aload_2
       8: invokeinterface #9,  3            // InterfaceMethod org/apache/activemq/artemis/core/server/ActiveMQServerLogger.errorProcessingIOCallback:(Ljava/lang/Integer;Ljava/lang/String;)V
      13: new           #10                 // class org/apache/activemq/artemis/core/protocol/core/impl/wireformat/ActiveMQExceptionMessage
      16: dup
      17: iload_1
      18: aload_2
      19: invokestatic  #11                 // Method org/apache/activemq/artemis/api/core/ActiveMQExceptionType.createException:(ILjava/lang/String;)Lorg/apache/activemq/artemis/api/core/ActiveMQException;
      22: invokespecial #12                 // Method org/apache/activemq/artemis/core/protocol/core/impl/wireformat/ActiveMQExceptionMessage."<init>":(Lorg/apache/activemq/artemis/api/core/ActiveMQException;)V
      25: astore_3
      26: aload_0
      27: getfield      #1                  // Field this$0:Lorg/apache/activemq/artemis/core/protocol/core/ServerSessionPacketHandler;
      30: aload_0
      31: getfield      #2                  // Field val$confirmPacket:Lorg/apache/activemq/artemis/core/protocol/core/Packet;
      34: aload_3
      35: aload_0
      36: getfield      #3                  // Field val$flush:Z
      39: aload_0
      40: getfield      #4                  // Field val$closeChannel:Z
      43: invokestatic  #13                 // Method org/apache/activemq/artemis/core/protocol/core/ServerSessionPacketHandler.access$000:(Lorg/apache/activemq/artemis/core/protocol/core/ServerSessionPacketHandler;Lorg/apache/activemq/artemis/core/protocol/core/Packet;Lorg/apache/activemq/artemis/core/protocol/core/Packet;ZZ)V
      46: aload_0
      47: getfield      #1                  // Field this$0:Lorg/apache/activemq/artemis/core/protocol/core/ServerSessionPacketHandler;
      50: invokestatic  #14                 // Method org/apache/activemq/artemis/core/protocol/core/ServerSessionPacketHandler.access$100:(Lorg/apache/activemq/artemis/core/protocol/core/ServerSessionPacketHandler;)Z
      53: ifeq          86
      56: getstatic     #7                  // Field org/apache/activemq/artemis/core/server/ActiveMQServerLogger.LOGGER:Lorg/apache/activemq/artemis/core/server/ActiveMQServerLogger;
      59: new           #15                 // class java/lang/StringBuilder
      62: dup
      63: invokespecial #16                 // Method java/lang/StringBuilder."<init>":()V
      66: ldc           #17                 // String ServerSessionPacketHandler::response sent::
      68: invokevirtual #18                 // Method java/lang/StringBuilder.append:(Ljava/lang/String;)Ljava/lang/StringBuilder;
      71: aload_0
      72: getfield      #5                  // Field val$response:Lorg/apache/activemq/artemis/core/protocol/core/Packet;
      75: invokevirtual #19                 // Method java/lang/StringBuilder.append:(Ljava/lang/Object;)Ljava/lang/StringBuilder;
      78: invokevirtual #20                 // Method java/lang/StringBuilder.toString:()Ljava/lang/String;
      81: invokeinterface #21,  2           // InterfaceMethod org/apache/activemq/artemis/core/server/ActiveMQServerLogger.trace:(Ljava/lang/Object;)V
      86: return

  public void done();
    Code:
       0: aload_0
       1: getfield      #1                  // Field this$0:Lorg/apache/activemq/artemis/core/protocol/core/ServerSessionPacketHandler;
       4: aload_0
       5: getfield      #2                  // Field val$confirmPacket:Lorg/apache/activemq/artemis/core/protocol/core/Packet;
       8: aload_0
       9: getfield      #5                  // Field val$response:Lorg/apache/activemq/artemis/core/protocol/core/Packet;
      12: aload_0
      13: getfield      #3                  // Field val$flush:Z
      16: aload_0
      17: getfield      #4                  // Field val$closeChannel:Z
      20: invokestatic  #13                 // Method org/apache/activemq/artemis/core/protocol/core/ServerSessionPacketHandler.access$000:(Lorg/apache/activemq/artemis/core/protocol/core/ServerSessionPacketHandler;Lorg/apache/activemq/artemis/core/protocol/core/Packet;Lorg/apache/activemq/artemis/core/protocol/core/Packet;ZZ)V
      23: return
}
