Compiled from "HqlBaseLexer.java"
public class org.hibernate.hql.internal.antlr.HqlBaseLexer extends antlr.CharScanner implements org.hibernate.hql.internal.antlr.HqlTokenTypes,antlr.TokenStream {
  public static final antlr.collections.impl.BitSet _tokenSet_0;

  public static final antlr.collections.impl.BitSet _tokenSet_1;

  public static final antlr.collections.impl.BitSet _tokenSet_2;

  public static final antlr.collections.impl.BitSet _tokenSet_3;

  public static final antlr.collections.impl.BitSet _tokenSet_4;

  protected void setPossibleID(boolean);
    Code:
       0: return

  public org.hibernate.hql.internal.antlr.HqlBaseLexer(java.io.InputStream);
    Code:
       0: aload_0
       1: new           #1                  // class antlr/ByteBuffer
       4: dup
       5: aload_1
       6: invokespecial #2                  // Method antlr/ByteBuffer."<init>":(Ljava/io/InputStream;)V
       9: invokespecial #3                  // Method "<init>":(Lantlr/InputBuffer;)V
      12: return

  public org.hibernate.hql.internal.antlr.HqlBaseLexer(java.io.Reader);
    Code:
       0: aload_0
       1: new           #4                  // class antlr/CharBuffer
       4: dup
       5: aload_1
       6: invokespecial #5                  // Method antlr/CharBuffer."<init>":(Ljava/io/Reader;)V
       9: invokespecial #3                  // Method "<init>":(Lantlr/InputBuffer;)V
      12: return

  public org.hibernate.hql.internal.antlr.HqlBaseLexer(antlr.InputBuffer);
    Code:
       0: aload_0
       1: new           #6                  // class antlr/LexerSharedInputState
       4: dup
       5: aload_1
       6: invokespecial #7                  // Method antlr/LexerSharedInputState."<init>":(Lantlr/InputBuffer;)V
       9: invokespecial #8                  // Method "<init>":(Lantlr/LexerSharedInputState;)V
      12: return

  public org.hibernate.hql.internal.antlr.HqlBaseLexer(antlr.LexerSharedInputState);
    Code:
       0: aload_0
       1: aload_1
       2: invokespecial #9                  // Method antlr/CharScanner."<init>":(Lantlr/LexerSharedInputState;)V
       5: aload_0
       6: iconst_0
       7: putfield      #10                 // Field caseSensitiveLiterals:Z
      10: aload_0
      11: iconst_0
      12: invokevirtual #11                 // Method setCaseSensitive:(Z)V
      15: aload_0
      16: new           #12                 // class java/util/Hashtable
      19: dup
      20: invokespecial #13                 // Method java/util/Hashtable."<init>":()V
      23: putfield      #14                 // Field literals:Ljava/util/Hashtable;
      26: aload_0
      27: getfield      #14                 // Field literals:Ljava/util/Hashtable;
      30: new           #15                 // class antlr/ANTLRHashString
      33: dup
      34: ldc           #16                 // String between
      36: aload_0
      37: invokespecial #17                 // Method antlr/ANTLRHashString."<init>":(Ljava/lang/String;Lantlr/CharScanner;)V
      40: new           #18                 // class java/lang/Integer
      43: dup
      44: bipush        10
      46: invokespecial #19                 // Method java/lang/Integer."<init>":(I)V
      49: invokevirtual #20                 // Method java/util/Hashtable.put:(Ljava/lang/Object;Ljava/lang/Object;)Ljava/lang/Object;
      52: pop
      53: aload_0
      54: getfield      #14                 // Field literals:Ljava/util/Hashtable;
      57: new           #15                 // class antlr/ANTLRHashString
      60: dup
      61: ldc           #21                 // String case
      63: aload_0
      64: invokespecial #17                 // Method antlr/ANTLRHashString."<init>":(Ljava/lang/String;Lantlr/CharScanner;)V
      67: new           #18                 // class java/lang/Integer
      70: dup
      71: bipush        56
      73: invokespecial #19                 // Method java/lang/Integer."<init>":(I)V
      76: invokevirtual #20                 // Method java/util/Hashtable.put:(Ljava/lang/Object;Ljava/lang/Object;)Ljava/lang/Object;
      79: pop
      80: aload_0
      81: getfield      #14                 // Field literals:Ljava/util/Hashtable;
      84: new           #15                 // class antlr/ANTLRHashString
      87: dup
      88: ldc           #22                 // String delete
      90: aload_0
      91: invokespecial #17                 // Method antlr/ANTLRHashString."<init>":(Ljava/lang/String;Lantlr/CharScanner;)V
      94: new           #18                 // class java/lang/Integer
      97: dup
      98: bipush        13
     100: invokespecial #19                 // Method java/lang/Integer."<init>":(I)V
     103: invokevirtual #20                 // Method java/util/Hashtable.put:(Ljava/lang/Object;Ljava/lang/Object;)Ljava/lang/Object;
     106: pop
     107: aload_0
     108: getfield      #14                 // Field literals:Ljava/util/Hashtable;
     111: new           #15                 // class antlr/ANTLRHashString
     114: dup
     115: ldc           #23                 // String new
     117: aload_0
     118: invokespecial #17                 // Method antlr/ANTLRHashString."<init>":(Ljava/lang/String;Lantlr/CharScanner;)V
     121: new           #18                 // class java/lang/Integer
     124: dup
     125: bipush        37
     127: invokespecial #19                 // Method java/lang/Integer."<init>":(I)V
     130: invokevirtual #20                 // Method java/util/Hashtable.put:(Ljava/lang/Object;Ljava/lang/Object;)Ljava/lang/Object;
     133: pop
     134: aload_0
     135: getfield      #14                 // Field literals:Ljava/util/Hashtable;
     138: new           #15                 // class antlr/ANTLRHashString
     141: dup
     142: ldc           #24                 // String end
     144: aload_0
     145: invokespecial #17                 // Method antlr/ANTLRHashString."<init>":(Ljava/lang/String;Lantlr/CharScanner;)V
     148: new           #18                 // class java/lang/Integer
     151: dup
     152: bipush        57
     154: invokespecial #19                 // Method java/lang/Integer."<init>":(I)V
     157: invokevirtual #20                 // Method java/util/Hashtable.put:(Ljava/lang/Object;Ljava/lang/Object;)Ljava/lang/Object;
     160: pop
     161: aload_0
     162: getfield      #14                 // Field literals:Ljava/util/Hashtable;
     165: new           #15                 // class antlr/ANTLRHashString
     168: dup
     169: ldc           #25                 // String object
     171: aload_0
     172: invokespecial #17                 // Method antlr/ANTLRHashString."<init>":(Ljava/lang/String;Lantlr/CharScanner;)V
     175: new           #18                 // class java/lang/Integer
     178: dup
     179: bipush        67
     181: invokespecial #19                 // Method java/lang/Integer."<init>":(I)V
     184: invokevirtual #20                 // Method java/util/Hashtable.put:(Ljava/lang/Object;Ljava/lang/Object;)Ljava/lang/Object;
     187: pop
     188: aload_0
     189: getfield      #14                 // Field literals:Ljava/util/Hashtable;
     192: new           #15                 // class antlr/ANTLRHashString
     195: dup
     196: ldc           #26                 // String insert
     198: aload_0
     199: invokespecial #17                 // Method antlr/ANTLRHashString."<init>":(Ljava/lang/String;Lantlr/CharScanner;)V
     202: new           #18                 // class java/lang/Integer
     205: dup
     206: bipush        29
     208: invokespecial #19                 // Method java/lang/Integer."<init>":(I)V
     211: invokevirtual #20                 // Method java/util/Hashtable.put:(Ljava/lang/Object;Ljava/lang/Object;)Ljava/lang/Object;
     214: pop
     215: aload_0
     216: getfield      #14                 // Field literals:Ljava/util/Hashtable;
     219: new           #15                 // class antlr/ANTLRHashString
     222: dup
     223: ldc           #27                 // String distinct
     225: aload_0
     226: invokespecial #17                 // Method antlr/ANTLRHashString."<init>":(Ljava/lang/String;Lantlr/CharScanner;)V
     229: new           #18                 // class java/lang/Integer
     232: dup
     233: bipush        16
     235: invokespecial #19                 // Method java/lang/Integer."<init>":(I)V
     238: invokevirtual #20                 // Method java/util/Hashtable.put:(Ljava/lang/Object;Ljava/lang/Object;)Ljava/lang/Object;
     241: pop
     242: aload_0
     243: getfield      #14                 // Field literals:Ljava/util/Hashtable;
     246: new           #15                 // class antlr/ANTLRHashString
     249: dup
     250: ldc           #28                 // String where
     252: aload_0
     253: invokespecial #17                 // Method antlr/ANTLRHashString."<init>":(Ljava/lang/String;Lantlr/CharScanner;)V
     256: new           #18                 // class java/lang/Integer
     259: dup
     260: bipush        52
     262: invokespecial #19                 // Method java/lang/Integer."<init>":(I)V
     265: invokevirtual #20                 // Method java/util/Hashtable.put:(Ljava/lang/Object;Ljava/lang/Object;)Ljava/lang/Object;
     268: pop
     269: aload_0
     270: getfield      #14                 // Field literals:Ljava/util/Hashtable;
     273: new           #15                 // class antlr/ANTLRHashString
     276: dup
     277: ldc           #29                 // String trailing
     279: aload_0
     280: invokespecial #17                 // Method antlr/ANTLRHashString."<init>":(Ljava/lang/String;Lantlr/CharScanner;)V
     283: new           #18                 // class java/lang/Integer
     286: dup
     287: bipush        69
     289: invokespecial #19                 // Method java/lang/Integer."<init>":(I)V
     292: invokevirtual #20                 // Method java/util/Hashtable.put:(Ljava/lang/Object;Ljava/lang/Object;)Ljava/lang/Object;
     295: pop
     296: aload_0
     297: getfield      #14                 // Field literals:Ljava/util/Hashtable;
     300: new           #15                 // class antlr/ANTLRHashString
     303: dup
     304: ldc           #30                 // String then
     306: aload_0
     307: invokespecial #17                 // Method antlr/ANTLRHashString."<init>":(Ljava/lang/String;Lantlr/CharScanner;)V
     310: new           #18                 // class java/lang/Integer
     313: dup
     314: bipush        59
     316: invokespecial #19                 // Method java/lang/Integer."<init>":(I)V
     319: invokevirtual #20                 // Method java/util/Hashtable.put:(Ljava/lang/Object;Ljava/lang/Object;)Ljava/lang/Object;
     322: pop
     323: aload_0
     324: getfield      #14                 // Field literals:Ljava/util/Hashtable;
     327: new           #15                 // class antlr/ANTLRHashString
     330: dup
     331: ldc           #31                 // String select
     333: aload_0
     334: invokespecial #17                 // Method antlr/ANTLRHashString."<init>":(Ljava/lang/String;Lantlr/CharScanner;)V
     337: new           #18                 // class java/lang/Integer
     340: dup
     341: bipush        45
     343: invokespecial #19                 // Method java/lang/Integer."<init>":(I)V
     346: invokevirtual #20                 // Method java/util/Hashtable.put:(Ljava/lang/Object;Ljava/lang/Object;)Ljava/lang/Object;
     349: pop
     350: aload_0
     351: getfield      #14                 // Field literals:Ljava/util/Hashtable;
     354: new           #15                 // class antlr/ANTLRHashString
     357: dup
     358: ldc           #32                 // String and
     360: aload_0
     361: invokespecial #17                 // Method antlr/ANTLRHashString."<init>":(Ljava/lang/String;Lantlr/CharScanner;)V
     364: new           #18                 // class java/lang/Integer
     367: dup
     368: bipush        6
     370: invokespecial #19                 // Method java/lang/Integer."<init>":(I)V
     373: invokevirtual #20                 // Method java/util/Hashtable.put:(Ljava/lang/Object;Ljava/lang/Object;)Ljava/lang/Object;
     376: pop
     377: aload_0
     378: getfield      #14                 // Field literals:Ljava/util/Hashtable;
     381: new           #15                 // class antlr/ANTLRHashString
     384: dup
     385: ldc           #33                 // String outer
     387: aload_0
     388: invokespecial #17                 // Method antlr/ANTLRHashString."<init>":(Ljava/lang/String;Lantlr/CharScanner;)V
     391: new           #18                 // class java/lang/Integer
     394: dup
     395: bipush        42
     397: invokespecial #19                 // Method java/lang/Integer."<init>":(I)V
     400: invokevirtual #20                 // Method java/util/Hashtable.put:(Ljava/lang/Object;Ljava/lang/Object;)Ljava/lang/Object;
     403: pop
     404: aload_0
     405: getfield      #14                 // Field literals:Ljava/util/Hashtable;
     408: new           #15                 // class antlr/ANTLRHashString
     411: dup
     412: ldc           #34                 // String not
     414: aload_0
     415: invokespecial #17                 // Method antlr/ANTLRHashString."<init>":(Ljava/lang/String;Lantlr/CharScanner;)V
     418: new           #18                 // class java/lang/Integer
     421: dup
     422: bipush        38
     424: invokespecial #19                 // Method java/lang/Integer."<init>":(I)V
     427: invokevirtual #20                 // Method java/util/Hashtable.put:(Ljava/lang/Object;Ljava/lang/Object;)Ljava/lang/Object;
     430: pop
     431: aload_0
     432: getfield      #14                 // Field literals:Ljava/util/Hashtable;
     435: new           #15                 // class antlr/ANTLRHashString
     438: dup
     439: ldc           #35                 // String fetch
     441: aload_0
     442: invokespecial #17                 // Method antlr/ANTLRHashString."<init>":(Ljava/lang/String;Lantlr/CharScanner;)V
     445: new           #18                 // class java/lang/Integer
     448: dup
     449: bipush        21
     451: invokespecial #19                 // Method java/lang/Integer."<init>":(I)V
     454: invokevirtual #20                 // Method java/util/Hashtable.put:(Ljava/lang/Object;Ljava/lang/Object;)Ljava/lang/Object;
     457: pop
     458: aload_0
     459: getfield      #14                 // Field literals:Ljava/util/Hashtable;
     462: new           #15                 // class antlr/ANTLRHashString
     465: dup
     466: ldc           #36                 // String from
     468: aload_0
     469: invokespecial #17                 // Method antlr/ANTLRHashString."<init>":(Ljava/lang/String;Lantlr/CharScanner;)V
     472: new           #18                 // class java/lang/Integer
     475: dup
     476: bipush        22
     478: invokespecial #19                 // Method java/lang/Integer."<init>":(I)V
     481: invokevirtual #20                 // Method java/util/Hashtable.put:(Ljava/lang/Object;Ljava/lang/Object;)Ljava/lang/Object;
     484: pop
     485: aload_0
     486: getfield      #14                 // Field literals:Ljava/util/Hashtable;
     489: new           #15                 // class antlr/ANTLRHashString
     492: dup
     493: ldc           #37                 // String null
     495: aload_0
     496: invokespecial #17                 // Method antlr/ANTLRHashString."<init>":(Ljava/lang/String;Lantlr/CharScanner;)V
     499: new           #18                 // class java/lang/Integer
     502: dup
     503: bipush        39
     505: invokespecial #19                 // Method java/lang/Integer."<init>":(I)V
     508: invokevirtual #20                 // Method java/util/Hashtable.put:(Ljava/lang/Object;Ljava/lang/Object;)Ljava/lang/Object;
     511: pop
     512: aload_0
     513: getfield      #14                 // Field literals:Ljava/util/Hashtable;
     516: new           #15                 // class antlr/ANTLRHashString
     519: dup
     520: ldc           #38                 // String count
     522: aload_0
     523: invokespecial #17                 // Method antlr/ANTLRHashString."<init>":(Ljava/lang/String;Lantlr/CharScanner;)V
     526: new           #18                 // class java/lang/Integer
     529: dup
     530: bipush        12
     532: invokespecial #19                 // Method java/lang/Integer."<init>":(I)V
     535: invokevirtual #20                 // Method java/util/Hashtable.put:(Ljava/lang/Object;Ljava/lang/Object;)Ljava/lang/Object;
     538: pop
     539: aload_0
     540: getfield      #14                 // Field literals:Ljava/util/Hashtable;
     543: new           #15                 // class antlr/ANTLRHashString
     546: dup
     547: ldc           #39                 // String like
     549: aload_0
     550: invokespecial #17                 // Method antlr/ANTLRHashString."<init>":(Ljava/lang/String;Lantlr/CharScanner;)V
     553: new           #18                 // class java/lang/Integer
     556: dup
     557: bipush        34
     559: invokespecial #19                 // Method java/lang/Integer."<init>":(I)V
     562: invokevirtual #20                 // Method java/util/Hashtable.put:(Ljava/lang/Object;Ljava/lang/Object;)Ljava/lang/Object;
     565: pop
     566: aload_0
     567: getfield      #14                 // Field literals:Ljava/util/Hashtable;
     570: new           #15                 // class antlr/ANTLRHashString
     573: dup
     574: ldc           #40                 // String when
     576: aload_0
     577: invokespecial #17                 // Method antlr/ANTLRHashString."<init>":(Ljava/lang/String;Lantlr/CharScanner;)V
     580: new           #18                 // class java/lang/Integer
     583: dup
     584: bipush        60
     586: invokespecial #19                 // Method java/lang/Integer."<init>":(I)V
     589: invokevirtual #20                 // Method java/util/Hashtable.put:(Ljava/lang/Object;Ljava/lang/Object;)Ljava/lang/Object;
     592: pop
     593: aload_0
     594: getfield      #14                 // Field literals:Ljava/util/Hashtable;
     597: new           #15                 // class antlr/ANTLRHashString
     600: dup
     601: ldc           #41                 // String class
     603: aload_0
     604: invokespecial #17                 // Method antlr/ANTLRHashString."<init>":(Ljava/lang/String;Lantlr/CharScanner;)V
     607: new           #18                 // class java/lang/Integer
     610: dup
     611: bipush        11
     613: invokespecial #19                 // Method java/lang/Integer."<init>":(I)V
     616: invokevirtual #20                 // Method java/util/Hashtable.put:(Ljava/lang/Object;Ljava/lang/Object;)Ljava/lang/Object;
     619: pop
     620: aload_0
     621: getfield      #14                 // Field literals:Ljava/util/Hashtable;
     624: new           #15                 // class antlr/ANTLRHashString
     627: dup
     628: ldc           #42                 // String inner
     630: aload_0
     631: invokespecial #17                 // Method antlr/ANTLRHashString."<init>":(Ljava/lang/String;Lantlr/CharScanner;)V
     634: new           #18                 // class java/lang/Integer
     637: dup
     638: bipush        28
     640: invokespecial #19                 // Method java/lang/Integer."<init>":(I)V
     643: invokevirtual #20                 // Method java/util/Hashtable.put:(Ljava/lang/Object;Ljava/lang/Object;)Ljava/lang/Object;
     646: pop
     647: aload_0
     648: getfield      #14                 // Field literals:Ljava/util/Hashtable;
     651: new           #15                 // class antlr/ANTLRHashString
     654: dup
     655: ldc           #43                 // String leading
     657: aload_0
     658: invokespecial #17                 // Method antlr/ANTLRHashString."<init>":(Ljava/lang/String;Lantlr/CharScanner;)V
     661: new           #18                 // class java/lang/Integer
     664: dup
     665: bipush        65
     667: invokespecial #19                 // Method java/lang/Integer."<init>":(I)V
     670: invokevirtual #20                 // Method java/util/Hashtable.put:(Ljava/lang/Object;Ljava/lang/Object;)Ljava/lang/Object;
     673: pop
     674: aload_0
     675: getfield      #14                 // Field literals:Ljava/util/Hashtable;
     678: new           #15                 // class antlr/ANTLRHashString
     681: dup
     682: ldc           #44                 // String with
     684: aload_0
     685: invokespecial #17                 // Method antlr/ANTLRHashString."<init>":(Ljava/lang/String;Lantlr/CharScanner;)V
     688: new           #18                 // class java/lang/Integer
     691: dup
     692: bipush        62
     694: invokespecial #19                 // Method java/lang/Integer."<init>":(I)V
     697: invokevirtual #20                 // Method java/util/Hashtable.put:(Ljava/lang/Object;Ljava/lang/Object;)Ljava/lang/Object;
     700: pop
     701: aload_0
     702: getfield      #14                 // Field literals:Ljava/util/Hashtable;
     705: new           #15                 // class antlr/ANTLRHashString
     708: dup
     709: ldc           #45                 // String set
     711: aload_0
     712: invokespecial #17                 // Method antlr/ANTLRHashString."<init>":(Ljava/lang/String;Lantlr/CharScanner;)V
     715: new           #18                 // class java/lang/Integer
     718: dup
     719: bipush        46
     721: invokespecial #19                 // Method java/lang/Integer."<init>":(I)V
     724: invokevirtual #20                 // Method java/util/Hashtable.put:(Ljava/lang/Object;Ljava/lang/Object;)Ljava/lang/Object;
     727: pop
     728: aload_0
     729: getfield      #14                 // Field literals:Ljava/util/Hashtable;
     732: new           #15                 // class antlr/ANTLRHashString
     735: dup
     736: ldc           #46                 // String escape
     738: aload_0
     739: invokespecial #17                 // Method antlr/ANTLRHashString."<init>":(Ljava/lang/String;Lantlr/CharScanner;)V
     742: new           #18                 // class java/lang/Integer
     745: dup
     746: bipush        18
     748: invokespecial #19                 // Method java/lang/Integer."<init>":(I)V
     751: invokevirtual #20                 // Method java/util/Hashtable.put:(Ljava/lang/Object;Ljava/lang/Object;)Ljava/lang/Object;
     754: pop
     755: aload_0
     756: getfield      #14                 // Field literals:Ljava/util/Hashtable;
     759: new           #15                 // class antlr/ANTLRHashString
     762: dup
     763: ldc           #47                 // String join
     765: aload_0
     766: invokespecial #17                 // Method antlr/ANTLRHashString."<init>":(Ljava/lang/String;Lantlr/CharScanner;)V
     769: new           #18                 // class java/lang/Integer
     772: dup
     773: bipush        32
     775: invokespecial #19                 // Method java/lang/Integer."<init>":(I)V
     778: invokevirtual #20                 // Method java/util/Hashtable.put:(Ljava/lang/Object;Ljava/lang/Object;)Ljava/lang/Object;
     781: pop
     782: aload_0
     783: getfield      #14                 // Field literals:Ljava/util/Hashtable;
     786: new           #15                 // class antlr/ANTLRHashString
     789: dup
     790: ldc           #48                 // String elements
     792: aload_0
     793: invokespecial #17                 // Method antlr/ANTLRHashString."<init>":(Ljava/lang/String;Lantlr/CharScanner;)V
     796: new           #18                 // class java/lang/Integer
     799: dup
     800: bipush        17
     802: invokespecial #19                 // Method java/lang/Integer."<init>":(I)V
     805: invokevirtual #20                 // Method java/util/Hashtable.put:(Ljava/lang/Object;Ljava/lang/Object;)Ljava/lang/Object;
     808: pop
     809: aload_0
     810: getfield      #14                 // Field literals:Ljava/util/Hashtable;
     813: new           #15                 // class antlr/ANTLRHashString
     816: dup
     817: ldc           #49                 // String of
     819: aload_0
     820: invokespecial #17                 // Method antlr/ANTLRHashString."<init>":(Ljava/lang/String;Lantlr/CharScanner;)V
     823: new           #18                 // class java/lang/Integer
     826: dup
     827: bipush        68
     829: invokespecial #19                 // Method java/lang/Integer."<init>":(I)V
     832: invokevirtual #20                 // Method java/util/Hashtable.put:(Ljava/lang/Object;Ljava/lang/Object;)Ljava/lang/Object;
     835: pop
     836: aload_0
     837: getfield      #14                 // Field literals:Ljava/util/Hashtable;
     840: new           #15                 // class antlr/ANTLRHashString
     843: dup
     844: ldc           #50                 // String is
     846: aload_0
     847: invokespecial #17                 // Method antlr/ANTLRHashString."<init>":(Ljava/lang/String;Lantlr/CharScanner;)V
     850: new           #18                 // class java/lang/Integer
     853: dup
     854: bipush        31
     856: invokespecial #19                 // Method java/lang/Integer."<init>":(I)V
     859: invokevirtual #20                 // Method java/util/Hashtable.put:(Ljava/lang/Object;Ljava/lang/Object;)Ljava/lang/Object;
     862: pop
     863: aload_0
     864: getfield      #14                 // Field literals:Ljava/util/Hashtable;
     867: new           #15                 // class antlr/ANTLRHashString
     870: dup
     871: ldc           #51                 // String member
     873: aload_0
     874: invokespecial #17                 // Method antlr/ANTLRHashString."<init>":(Ljava/lang/String;Lantlr/CharScanner;)V
     877: new           #18                 // class java/lang/Integer
     880: dup
     881: bipush        66
     883: invokespecial #19                 // Method java/lang/Integer."<init>":(I)V
     886: invokevirtual #20                 // Method java/util/Hashtable.put:(Ljava/lang/Object;Ljava/lang/Object;)Ljava/lang/Object;
     889: pop
     890: aload_0
     891: getfield      #14                 // Field literals:Ljava/util/Hashtable;
     894: new           #15                 // class antlr/ANTLRHashString
     897: dup
     898: ldc           #52                 // String or
     900: aload_0
     901: invokespecial #17                 // Method antlr/ANTLRHashString."<init>":(Ljava/lang/String;Lantlr/CharScanner;)V
     904: new           #18                 // class java/lang/Integer
     907: dup
     908: bipush        40
     910: invokespecial #19                 // Method java/lang/Integer."<init>":(I)V
     913: invokevirtual #20                 // Method java/util/Hashtable.put:(Ljava/lang/Object;Ljava/lang/Object;)Ljava/lang/Object;
     916: pop
     917: aload_0
     918: getfield      #14                 // Field literals:Ljava/util/Hashtable;
     921: new           #15                 // class antlr/ANTLRHashString
     924: dup
     925: ldc           #53                 // String any
     927: aload_0
     928: invokespecial #17                 // Method antlr/ANTLRHashString."<init>":(Ljava/lang/String;Lantlr/CharScanner;)V
     931: new           #18                 // class java/lang/Integer
     934: dup
     935: iconst_5
     936: invokespecial #19                 // Method java/lang/Integer."<init>":(I)V
     939: invokevirtual #20                 // Method java/util/Hashtable.put:(Ljava/lang/Object;Ljava/lang/Object;)Ljava/lang/Object;
     942: pop
     943: aload_0
     944: getfield      #14                 // Field literals:Ljava/util/Hashtable;
     947: new           #15                 // class antlr/ANTLRHashString
     950: dup
     951: ldc           #54                 // String full
     953: aload_0
     954: invokespecial #17                 // Method antlr/ANTLRHashString."<init>":(Ljava/lang/String;Lantlr/CharScanner;)V
     957: new           #18                 // class java/lang/Integer
     960: dup
     961: bipush        23
     963: invokespecial #19                 // Method java/lang/Integer."<init>":(I)V
     966: invokevirtual #20                 // Method java/util/Hashtable.put:(Ljava/lang/Object;Ljava/lang/Object;)Ljava/lang/Object;
     969: pop
     970: aload_0
     971: getfield      #14                 // Field literals:Ljava/util/Hashtable;
     974: new           #15                 // class antlr/ANTLRHashString
     977: dup
     978: ldc           #55                 // String min
     980: aload_0
     981: invokespecial #17                 // Method antlr/ANTLRHashString."<init>":(Ljava/lang/String;Lantlr/CharScanner;)V
     984: new           #18                 // class java/lang/Integer
     987: dup
     988: bipush        36
     990: invokespecial #19                 // Method java/lang/Integer."<init>":(I)V
     993: invokevirtual #20                 // Method java/util/Hashtable.put:(Ljava/lang/Object;Ljava/lang/Object;)Ljava/lang/Object;
     996: pop
     997: aload_0
     998: getfield      #14                 // Field literals:Ljava/util/Hashtable;
    1001: new           #15                 // class antlr/ANTLRHashString
    1004: dup
    1005: ldc           #56                 // String as
    1007: aload_0
    1008: invokespecial #17                 // Method antlr/ANTLRHashString."<init>":(Ljava/lang/String;Lantlr/CharScanner;)V
    1011: new           #18                 // class java/lang/Integer
    1014: dup
    1015: bipush        7
    1017: invokespecial #19                 // Method java/lang/Integer."<init>":(I)V
    1020: invokevirtual #20                 // Method java/util/Hashtable.put:(Ljava/lang/Object;Ljava/lang/Object;)Ljava/lang/Object;
    1023: pop
    1024: aload_0
    1025: getfield      #14                 // Field literals:Ljava/util/Hashtable;
    1028: new           #15                 // class antlr/ANTLRHashString
    1031: dup
    1032: ldc           #57                 // String by
    1034: aload_0
    1035: invokespecial #17                 // Method antlr/ANTLRHashString."<init>":(Ljava/lang/String;Lantlr/CharScanner;)V
    1038: new           #18                 // class java/lang/Integer
    1041: dup
    1042: bipush        109
    1044: invokespecial #19                 // Method java/lang/Integer."<init>":(I)V
    1047: invokevirtual #20                 // Method java/util/Hashtable.put:(Ljava/lang/Object;Ljava/lang/Object;)Ljava/lang/Object;
    1050: pop
    1051: aload_0
    1052: getfield      #14                 // Field literals:Ljava/util/Hashtable;
    1055: new           #15                 // class antlr/ANTLRHashString
    1058: dup
    1059: ldc           #58                 // String nulls
    1061: aload_0
    1062: invokespecial #17                 // Method antlr/ANTLRHashString."<init>":(Ljava/lang/String;Lantlr/CharScanner;)V
    1065: new           #18                 // class java/lang/Integer
    1068: dup
    1069: bipush        53
    1071: invokespecial #19                 // Method java/lang/Integer."<init>":(I)V
    1074: invokevirtual #20                 // Method java/util/Hashtable.put:(Ljava/lang/Object;Ljava/lang/Object;)Ljava/lang/Object;
    1077: pop
    1078: aload_0
    1079: getfield      #14                 // Field literals:Ljava/util/Hashtable;
    1082: new           #15                 // class antlr/ANTLRHashString
    1085: dup
    1086: ldc           #59                 // String all
    1088: aload_0
    1089: invokespecial #17                 // Method antlr/ANTLRHashString."<init>":(Ljava/lang/String;Lantlr/CharScanner;)V
    1092: new           #18                 // class java/lang/Integer
    1095: dup
    1096: iconst_4
    1097: invokespecial #19                 // Method java/lang/Integer."<init>":(I)V
    1100: invokevirtual #20                 // Method java/util/Hashtable.put:(Ljava/lang/Object;Ljava/lang/Object;)Ljava/lang/Object;
    1103: pop
    1104: aload_0
    1105: getfield      #14                 // Field literals:Ljava/util/Hashtable;
    1108: new           #15                 // class antlr/ANTLRHashString
    1111: dup
    1112: ldc           #60                 // String order
    1114: aload_0
    1115: invokespecial #17                 // Method antlr/ANTLRHashString."<init>":(Ljava/lang/String;Lantlr/CharScanner;)V
    1118: new           #18                 // class java/lang/Integer
    1121: dup
    1122: bipush        41
    1124: invokespecial #19                 // Method java/lang/Integer."<init>":(I)V
    1127: invokevirtual #20                 // Method java/util/Hashtable.put:(Ljava/lang/Object;Ljava/lang/Object;)Ljava/lang/Object;
    1130: pop
    1131: aload_0
    1132: getfield      #14                 // Field literals:Ljava/util/Hashtable;
    1135: new           #15                 // class antlr/ANTLRHashString
    1138: dup
    1139: ldc           #61                 // String both
    1141: aload_0
    1142: invokespecial #17                 // Method antlr/ANTLRHashString."<init>":(Ljava/lang/String;Lantlr/CharScanner;)V
    1145: new           #18                 // class java/lang/Integer
    1148: dup
    1149: bipush        63
    1151: invokespecial #19                 // Method java/lang/Integer."<init>":(I)V
    1154: invokevirtual #20                 // Method java/util/Hashtable.put:(Ljava/lang/Object;Ljava/lang/Object;)Ljava/lang/Object;
    1157: pop
    1158: aload_0
    1159: getfield      #14                 // Field literals:Ljava/util/Hashtable;
    1162: new           #15                 // class antlr/ANTLRHashString
    1165: dup
    1166: ldc           #62                 // String some
    1168: aload_0
    1169: invokespecial #17                 // Method antlr/ANTLRHashString."<init>":(Ljava/lang/String;Lantlr/CharScanner;)V
    1172: new           #18                 // class java/lang/Integer
    1175: dup
    1176: bipush        47
    1178: invokespecial #19                 // Method java/lang/Integer."<init>":(I)V
    1181: invokevirtual #20                 // Method java/util/Hashtable.put:(Ljava/lang/Object;Ljava/lang/Object;)Ljava/lang/Object;
    1184: pop
    1185: aload_0
    1186: getfield      #14                 // Field literals:Ljava/util/Hashtable;
    1189: new           #15                 // class antlr/ANTLRHashString
    1192: dup
    1193: ldc           #63                 // String properties
    1195: aload_0
    1196: invokespecial #17                 // Method antlr/ANTLRHashString."<init>":(Ljava/lang/String;Lantlr/CharScanner;)V
    1199: new           #18                 // class java/lang/Integer
    1202: dup
    1203: bipush        43
    1205: invokespecial #19                 // Method java/lang/Integer."<init>":(I)V
    1208: invokevirtual #20                 // Method java/util/Hashtable.put:(Ljava/lang/Object;Ljava/lang/Object;)Ljava/lang/Object;
    1211: pop
    1212: aload_0
    1213: getfield      #14                 // Field literals:Ljava/util/Hashtable;
    1216: new           #15                 // class antlr/ANTLRHashString
    1219: dup
    1220: ldc           #64                 // String ascending
    1222: aload_0
    1223: invokespecial #17                 // Method antlr/ANTLRHashString."<init>":(Ljava/lang/String;Lantlr/CharScanner;)V
    1226: new           #18                 // class java/lang/Integer
    1229: dup
    1230: bipush        110
    1232: invokespecial #19                 // Method java/lang/Integer."<init>":(I)V
    1235: invokevirtual #20                 // Method java/util/Hashtable.put:(Ljava/lang/Object;Ljava/lang/Object;)Ljava/lang/Object;
    1238: pop
    1239: aload_0
    1240: getfield      #14                 // Field literals:Ljava/util/Hashtable;
    1243: new           #15                 // class antlr/ANTLRHashString
    1246: dup
    1247: ldc           #65                 // String descending
    1249: aload_0
    1250: invokespecial #17                 // Method antlr/ANTLRHashString."<init>":(Ljava/lang/String;Lantlr/CharScanner;)V
    1253: new           #18                 // class java/lang/Integer
    1256: dup
    1257: bipush        111
    1259: invokespecial #19                 // Method java/lang/Integer."<init>":(I)V
    1262: invokevirtual #20                 // Method java/util/Hashtable.put:(Ljava/lang/Object;Ljava/lang/Object;)Ljava/lang/Object;
    1265: pop
    1266: aload_0
    1267: getfield      #14                 // Field literals:Ljava/util/Hashtable;
    1270: new           #15                 // class antlr/ANTLRHashString
    1273: dup
    1274: ldc           #66                 // String false
    1276: aload_0
    1277: invokespecial #17                 // Method antlr/ANTLRHashString."<init>":(Ljava/lang/String;Lantlr/CharScanner;)V
    1280: new           #18                 // class java/lang/Integer
    1283: dup
    1284: bipush        20
    1286: invokespecial #19                 // Method java/lang/Integer."<init>":(I)V
    1289: invokevirtual #20                 // Method java/util/Hashtable.put:(Ljava/lang/Object;Ljava/lang/Object;)Ljava/lang/Object;
    1292: pop
    1293: aload_0
    1294: getfield      #14                 // Field literals:Ljava/util/Hashtable;
    1297: new           #15                 // class antlr/ANTLRHashString
    1300: dup
    1301: ldc           #67                 // String exists
    1303: aload_0
    1304: invokespecial #17                 // Method antlr/ANTLRHashString."<init>":(Ljava/lang/String;Lantlr/CharScanner;)V
    1307: new           #18                 // class java/lang/Integer
    1310: dup
    1311: bipush        19
    1313: invokespecial #19                 // Method java/lang/Integer."<init>":(I)V
    1316: invokevirtual #20                 // Method java/util/Hashtable.put:(Ljava/lang/Object;Ljava/lang/Object;)Ljava/lang/Object;
    1319: pop
    1320: aload_0
    1321: getfield      #14                 // Field literals:Ljava/util/Hashtable;
    1324: new           #15                 // class antlr/ANTLRHashString
    1327: dup
    1328: ldc           #68                 // String asc
    1330: aload_0
    1331: invokespecial #17                 // Method antlr/ANTLRHashString."<init>":(Ljava/lang/String;Lantlr/CharScanner;)V
    1334: new           #18                 // class java/lang/Integer
    1337: dup
    1338: bipush        8
    1340: invokespecial #19                 // Method java/lang/Integer."<init>":(I)V
    1343: invokevirtual #20                 // Method java/util/Hashtable.put:(Ljava/lang/Object;Ljava/lang/Object;)Ljava/lang/Object;
    1346: pop
    1347: aload_0
    1348: getfield      #14                 // Field literals:Ljava/util/Hashtable;
    1351: new           #15                 // class antlr/ANTLRHashString
    1354: dup
    1355: ldc           #69                 // String left
    1357: aload_0
    1358: invokespecial #17                 // Method antlr/ANTLRHashString."<init>":(Ljava/lang/String;Lantlr/CharScanner;)V
    1361: new           #18                 // class java/lang/Integer
    1364: dup
    1365: bipush        33
    1367: invokespecial #19                 // Method java/lang/Integer."<init>":(I)V
    1370: invokevirtual #20                 // Method java/util/Hashtable.put:(Ljava/lang/Object;Ljava/lang/Object;)Ljava/lang/Object;
    1373: pop
    1374: aload_0
    1375: getfield      #14                 // Field literals:Ljava/util/Hashtable;
    1378: new           #15                 // class antlr/ANTLRHashString
    1381: dup
    1382: ldc           #70                 // String desc
    1384: aload_0
    1385: invokespecial #17                 // Method antlr/ANTLRHashString."<init>":(Ljava/lang/String;Lantlr/CharScanner;)V
    1388: new           #18                 // class java/lang/Integer
    1391: dup
    1392: bipush        14
    1394: invokespecial #19                 // Method java/lang/Integer."<init>":(I)V
    1397: invokevirtual #20                 // Method java/util/Hashtable.put:(Ljava/lang/Object;Ljava/lang/Object;)Ljava/lang/Object;
    1400: pop
    1401: aload_0
    1402: getfield      #14                 // Field literals:Ljava/util/Hashtable;
    1405: new           #15                 // class antlr/ANTLRHashString
    1408: dup
    1409: ldc           #71                 // String max
    1411: aload_0
    1412: invokespecial #17                 // Method antlr/ANTLRHashString."<init>":(Ljava/lang/String;Lantlr/CharScanner;)V
    1415: new           #18                 // class java/lang/Integer
    1418: dup
    1419: bipush        35
    1421: invokespecial #19                 // Method java/lang/Integer."<init>":(I)V
    1424: invokevirtual #20                 // Method java/util/Hashtable.put:(Ljava/lang/Object;Ljava/lang/Object;)Ljava/lang/Object;
    1427: pop
    1428: aload_0
    1429: getfield      #14                 // Field literals:Ljava/util/Hashtable;
    1432: new           #15                 // class antlr/ANTLRHashString
    1435: dup
    1436: ldc           #72                 // String empty
    1438: aload_0
    1439: invokespecial #17                 // Method antlr/ANTLRHashString."<init>":(Ljava/lang/String;Lantlr/CharScanner;)V
    1442: new           #18                 // class java/lang/Integer
    1445: dup
    1446: bipush        64
    1448: invokespecial #19                 // Method java/lang/Integer."<init>":(I)V
    1451: invokevirtual #20                 // Method java/util/Hashtable.put:(Ljava/lang/Object;Ljava/lang/Object;)Ljava/lang/Object;
    1454: pop
    1455: aload_0
    1456: getfield      #14                 // Field literals:Ljava/util/Hashtable;
    1459: new           #15                 // class antlr/ANTLRHashString
    1462: dup
    1463: ldc           #73                 // String sum
    1465: aload_0
    1466: invokespecial #17                 // Method antlr/ANTLRHashString."<init>":(Ljava/lang/String;Lantlr/CharScanner;)V
    1469: new           #18                 // class java/lang/Integer
    1472: dup
    1473: bipush        48
    1475: invokespecial #19                 // Method java/lang/Integer."<init>":(I)V
    1478: invokevirtual #20                 // Method java/util/Hashtable.put:(Ljava/lang/Object;Ljava/lang/Object;)Ljava/lang/Object;
    1481: pop
    1482: aload_0
    1483: getfield      #14                 // Field literals:Ljava/util/Hashtable;
    1486: new           #15                 // class antlr/ANTLRHashString
    1489: dup
    1490: ldc           #74                 // String on
    1492: aload_0
    1493: invokespecial #17                 // Method antlr/ANTLRHashString."<init>":(Ljava/lang/String;Lantlr/CharScanner;)V
    1496: new           #18                 // class java/lang/Integer
    1499: dup
    1500: bipush        61
    1502: invokespecial #19                 // Method java/lang/Integer."<init>":(I)V
    1505: invokevirtual #20                 // Method java/util/Hashtable.put:(Ljava/lang/Object;Ljava/lang/Object;)Ljava/lang/Object;
    1508: pop
    1509: aload_0
    1510: getfield      #14                 // Field literals:Ljava/util/Hashtable;
    1513: new           #15                 // class antlr/ANTLRHashString
    1516: dup
    1517: ldc           #75                 // String into
    1519: aload_0
    1520: invokespecial #17                 // Method antlr/ANTLRHashString."<init>":(Ljava/lang/String;Lantlr/CharScanner;)V
    1523: new           #18                 // class java/lang/Integer
    1526: dup
    1527: bipush        30
    1529: invokespecial #19                 // Method java/lang/Integer."<init>":(I)V
    1532: invokevirtual #20                 // Method java/util/Hashtable.put:(Ljava/lang/Object;Ljava/lang/Object;)Ljava/lang/Object;
    1535: pop
    1536: aload_0
    1537: getfield      #14                 // Field literals:Ljava/util/Hashtable;
    1540: new           #15                 // class antlr/ANTLRHashString
    1543: dup
    1544: ldc           #76                 // String else
    1546: aload_0
    1547: invokespecial #17                 // Method antlr/ANTLRHashString."<init>":(Ljava/lang/String;Lantlr/CharScanner;)V
    1550: new           #18                 // class java/lang/Integer
    1553: dup
    1554: bipush        58
    1556: invokespecial #19                 // Method java/lang/Integer."<init>":(I)V
    1559: invokevirtual #20                 // Method java/util/Hashtable.put:(Ljava/lang/Object;Ljava/lang/Object;)Ljava/lang/Object;
    1562: pop
    1563: aload_0
    1564: getfield      #14                 // Field literals:Ljava/util/Hashtable;
    1567: new           #15                 // class antlr/ANTLRHashString
    1570: dup
    1571: ldc           #77                 // String right
    1573: aload_0
    1574: invokespecial #17                 // Method antlr/ANTLRHashString."<init>":(Ljava/lang/String;Lantlr/CharScanner;)V
    1577: new           #18                 // class java/lang/Integer
    1580: dup
    1581: bipush        44
    1583: invokespecial #19                 // Method java/lang/Integer."<init>":(I)V
    1586: invokevirtual #20                 // Method java/util/Hashtable.put:(Ljava/lang/Object;Ljava/lang/Object;)Ljava/lang/Object;
    1589: pop
    1590: aload_0
    1591: getfield      #14                 // Field literals:Ljava/util/Hashtable;
    1594: new           #15                 // class antlr/ANTLRHashString
    1597: dup
    1598: ldc           #78                 // String versioned
    1600: aload_0
    1601: invokespecial #17                 // Method antlr/ANTLRHashString."<init>":(Ljava/lang/String;Lantlr/CharScanner;)V
    1604: new           #18                 // class java/lang/Integer
    1607: dup
    1608: bipush        51
    1610: invokespecial #19                 // Method java/lang/Integer."<init>":(I)V
    1613: invokevirtual #20                 // Method java/util/Hashtable.put:(Ljava/lang/Object;Ljava/lang/Object;)Ljava/lang/Object;
    1616: pop
    1617: aload_0
    1618: getfield      #14                 // Field literals:Ljava/util/Hashtable;
    1621: new           #15                 // class antlr/ANTLRHashString
    1624: dup
    1625: ldc           #79                 // String in
    1627: aload_0
    1628: invokespecial #17                 // Method antlr/ANTLRHashString."<init>":(Ljava/lang/String;Lantlr/CharScanner;)V
    1631: new           #18                 // class java/lang/Integer
    1634: dup
    1635: bipush        26
    1637: invokespecial #19                 // Method java/lang/Integer."<init>":(I)V
    1640: invokevirtual #20                 // Method java/util/Hashtable.put:(Ljava/lang/Object;Ljava/lang/Object;)Ljava/lang/Object;
    1643: pop
    1644: aload_0
    1645: getfield      #14                 // Field literals:Ljava/util/Hashtable;
    1648: new           #15                 // class antlr/ANTLRHashString
    1651: dup
    1652: ldc           #80                 // String avg
    1654: aload_0
    1655: invokespecial #17                 // Method antlr/ANTLRHashString."<init>":(Ljava/lang/String;Lantlr/CharScanner;)V
    1658: new           #18                 // class java/lang/Integer
    1661: dup
    1662: bipush        9
    1664: invokespecial #19                 // Method java/lang/Integer."<init>":(I)V
    1667: invokevirtual #20                 // Method java/util/Hashtable.put:(Ljava/lang/Object;Ljava/lang/Object;)Ljava/lang/Object;
    1670: pop
    1671: aload_0
    1672: getfield      #14                 // Field literals:Ljava/util/Hashtable;
    1675: new           #15                 // class antlr/ANTLRHashString
    1678: dup
    1679: ldc           #81                 // String update
    1681: aload_0
    1682: invokespecial #17                 // Method antlr/ANTLRHashString."<init>":(Ljava/lang/String;Lantlr/CharScanner;)V
    1685: new           #18                 // class java/lang/Integer
    1688: dup
    1689: bipush        50
    1691: invokespecial #19                 // Method java/lang/Integer."<init>":(I)V
    1694: invokevirtual #20                 // Method java/util/Hashtable.put:(Ljava/lang/Object;Ljava/lang/Object;)Ljava/lang/Object;
    1697: pop
    1698: aload_0
    1699: getfield      #14                 // Field literals:Ljava/util/Hashtable;
    1702: new           #15                 // class antlr/ANTLRHashString
    1705: dup
    1706: ldc           #82                 // String true
    1708: aload_0
    1709: invokespecial #17                 // Method antlr/ANTLRHashString."<init>":(Ljava/lang/String;Lantlr/CharScanner;)V
    1712: new           #18                 // class java/lang/Integer
    1715: dup
    1716: bipush        49
    1718: invokespecial #19                 // Method java/lang/Integer."<init>":(I)V
    1721: invokevirtual #20                 // Method java/util/Hashtable.put:(Ljava/lang/Object;Ljava/lang/Object;)Ljava/lang/Object;
    1724: pop
    1725: aload_0
    1726: getfield      #14                 // Field literals:Ljava/util/Hashtable;
    1729: new           #15                 // class antlr/ANTLRHashString
    1732: dup
    1733: ldc           #83                 // String group
    1735: aload_0
    1736: invokespecial #17                 // Method antlr/ANTLRHashString."<init>":(Ljava/lang/String;Lantlr/CharScanner;)V
    1739: new           #18                 // class java/lang/Integer
    1742: dup
    1743: bipush        24
    1745: invokespecial #19                 // Method java/lang/Integer."<init>":(I)V
    1748: invokevirtual #20                 // Method java/util/Hashtable.put:(Ljava/lang/Object;Ljava/lang/Object;)Ljava/lang/Object;
    1751: pop
    1752: aload_0
    1753: getfield      #14                 // Field literals:Ljava/util/Hashtable;
    1756: new           #15                 // class antlr/ANTLRHashString
    1759: dup
    1760: ldc           #84                 // String having
    1762: aload_0
    1763: invokespecial #17                 // Method antlr/ANTLRHashString."<init>":(Ljava/lang/String;Lantlr/CharScanner;)V
    1766: new           #18                 // class java/lang/Integer
    1769: dup
    1770: bipush        25
    1772: invokespecial #19                 // Method java/lang/Integer."<init>":(I)V
    1775: invokevirtual #20                 // Method java/util/Hashtable.put:(Ljava/lang/Object;Ljava/lang/Object;)Ljava/lang/Object;
    1778: pop
    1779: aload_0
    1780: getfield      #14                 // Field literals:Ljava/util/Hashtable;
    1783: new           #15                 // class antlr/ANTLRHashString
    1786: dup
    1787: ldc           #85                 // String indices
    1789: aload_0
    1790: invokespecial #17                 // Method antlr/ANTLRHashString."<init>":(Ljava/lang/String;Lantlr/CharScanner;)V
    1793: new           #18                 // class java/lang/Integer
    1796: dup
    1797: bipush        27
    1799: invokespecial #19                 // Method java/lang/Integer."<init>":(I)V
    1802: invokevirtual #20                 // Method java/util/Hashtable.put:(Ljava/lang/Object;Ljava/lang/Object;)Ljava/lang/Object;
    1805: pop
    1806: return

  public antlr.Token nextToken() throws antlr.TokenStreamException;
    Code:
       0: aconst_null
       1: astore_1
       2: aconst_null
       3: astore_2
       4: iconst_0
       5: istore_3
       6: aload_0
       7: invokevirtual #87                 // Method resetText:()V
      10: aload_0
      11: iconst_1
      12: invokevirtual #88                 // Method LA:(I)C
      15: tableswitch   { // 9 to 124
                     9: 700
                    10: 700
                    11: 726
                    12: 726
                    13: 700
                    14: 726
                    15: 726
                    16: 726
                    17: 726
                    18: 726
                    19: 726
                    20: 726
                    21: 726
                    22: 726
                    23: 726
                    24: 726
                    25: 726
                    26: 726
                    27: 726
                    28: 726
                    29: 726
                    30: 726
                    31: 726
                    32: 700
                    33: 505
                    34: 726
                    35: 726
                    36: 726
                    37: 648
                    38: 726
                    39: 687
                    40: 531
                    41: 544
                    42: 622
                    43: 596
                    44: 518
                    45: 609
                    46: 713
                    47: 635
                    48: 713
                    49: 713
                    50: 713
                    51: 713
                    52: 713
                    53: 713
                    54: 713
                    55: 713
                    56: 713
                    57: 713
                    58: 661
                    59: 726
                    60: 726
                    61: 492
                    62: 726
                    63: 674
                    64: 726
                    65: 726
                    66: 726
                    67: 726
                    68: 726
                    69: 726
                    70: 726
                    71: 726
                    72: 726
                    73: 726
                    74: 726
                    75: 726
                    76: 726
                    77: 726
                    78: 726
                    79: 726
                    80: 726
                    81: 726
                    82: 726
                    83: 726
                    84: 726
                    85: 726
                    86: 726
                    87: 726
                    88: 726
                    89: 726
                    90: 726
                    91: 557
                    92: 726
                    93: 570
                    94: 505
                    95: 726
                    96: 726
                    97: 726
                    98: 726
                    99: 726
                   100: 726
                   101: 726
                   102: 726
                   103: 726
                   104: 726
                   105: 726
                   106: 726
                   107: 726
                   108: 726
                   109: 726
                   110: 726
                   111: 726
                   112: 726
                   113: 726
                   114: 726
                   115: 726
                   116: 726
                   117: 726
                   118: 726
                   119: 726
                   120: 726
                   121: 726
                   122: 726
                   123: 726
                   124: 583
               default: 726
          }
     492: aload_0
     493: iconst_1
     494: invokevirtual #89                 // Method mEQ:(Z)V
     497: aload_0
     498: getfield      #90                 // Field _returnToken:Lantlr/Token;
     501: astore_1
     502: goto          949
     505: aload_0
     506: iconst_1
     507: invokevirtual #91                 // Method mNE:(Z)V
     510: aload_0
     511: getfield      #90                 // Field _returnToken:Lantlr/Token;
     514: astore_1
     515: goto          949
     518: aload_0
     519: iconst_1
     520: invokevirtual #92                 // Method mCOMMA:(Z)V
     523: aload_0
     524: getfield      #90                 // Field _returnToken:Lantlr/Token;
     527: astore_1
     528: goto          949
     531: aload_0
     532: iconst_1
     533: invokevirtual #93                 // Method mOPEN:(Z)V
     536: aload_0
     537: getfield      #90                 // Field _returnToken:Lantlr/Token;
     540: astore_1
     541: goto          949
     544: aload_0
     545: iconst_1
     546: invokevirtual #94                 // Method mCLOSE:(Z)V
     549: aload_0
     550: getfield      #90                 // Field _returnToken:Lantlr/Token;
     553: astore_1
     554: goto          949
     557: aload_0
     558: iconst_1
     559: invokevirtual #95                 // Method mOPEN_BRACKET:(Z)V
     562: aload_0
     563: getfield      #90                 // Field _returnToken:Lantlr/Token;
     566: astore_1
     567: goto          949
     570: aload_0
     571: iconst_1
     572: invokevirtual #96                 // Method mCLOSE_BRACKET:(Z)V
     575: aload_0
     576: getfield      #90                 // Field _returnToken:Lantlr/Token;
     579: astore_1
     580: goto          949
     583: aload_0
     584: iconst_1
     585: invokevirtual #97                 // Method mCONCAT:(Z)V
     588: aload_0
     589: getfield      #90                 // Field _returnToken:Lantlr/Token;
     592: astore_1
     593: goto          949
     596: aload_0
     597: iconst_1
     598: invokevirtual #98                 // Method mPLUS:(Z)V
     601: aload_0
     602: getfield      #90                 // Field _returnToken:Lantlr/Token;
     605: astore_1
     606: goto          949
     609: aload_0
     610: iconst_1
     611: invokevirtual #99                 // Method mMINUS:(Z)V
     614: aload_0
     615: getfield      #90                 // Field _returnToken:Lantlr/Token;
     618: astore_1
     619: goto          949
     622: aload_0
     623: iconst_1
     624: invokevirtual #100                // Method mSTAR:(Z)V
     627: aload_0
     628: getfield      #90                 // Field _returnToken:Lantlr/Token;
     631: astore_1
     632: goto          949
     635: aload_0
     636: iconst_1
     637: invokevirtual #101                // Method mDIV:(Z)V
     640: aload_0
     641: getfield      #90                 // Field _returnToken:Lantlr/Token;
     644: astore_1
     645: goto          949
     648: aload_0
     649: iconst_1
     650: invokevirtual #102                // Method mMOD:(Z)V
     653: aload_0
     654: getfield      #90                 // Field _returnToken:Lantlr/Token;
     657: astore_1
     658: goto          949
     661: aload_0
     662: iconst_1
     663: invokevirtual #103                // Method mCOLON:(Z)V
     666: aload_0
     667: getfield      #90                 // Field _returnToken:Lantlr/Token;
     670: astore_1
     671: goto          949
     674: aload_0
     675: iconst_1
     676: invokevirtual #104                // Method mPARAM:(Z)V
     679: aload_0
     680: getfield      #90                 // Field _returnToken:Lantlr/Token;
     683: astore_1
     684: goto          949
     687: aload_0
     688: iconst_1
     689: invokevirtual #105                // Method mQUOTED_STRING:(Z)V
     692: aload_0
     693: getfield      #90                 // Field _returnToken:Lantlr/Token;
     696: astore_1
     697: goto          949
     700: aload_0
     701: iconst_1
     702: invokevirtual #106                // Method mWS:(Z)V
     705: aload_0
     706: getfield      #90                 // Field _returnToken:Lantlr/Token;
     709: astore_1
     710: goto          949
     713: aload_0
     714: iconst_1
     715: invokevirtual #107                // Method mNUM_INT:(Z)V
     718: aload_0
     719: getfield      #90                 // Field _returnToken:Lantlr/Token;
     722: astore_1
     723: goto          949
     726: aload_0
     727: iconst_1
     728: invokevirtual #88                 // Method LA:(I)C
     731: bipush        60
     733: if_icmpne     759
     736: aload_0
     737: iconst_2
     738: invokevirtual #88                 // Method LA:(I)C
     741: bipush        62
     743: if_icmpne     759
     746: aload_0
     747: iconst_1
     748: invokevirtual #108                // Method mSQL_NE:(Z)V
     751: aload_0
     752: getfield      #90                 // Field _returnToken:Lantlr/Token;
     755: astore_1
     756: goto          949
     759: aload_0
     760: iconst_1
     761: invokevirtual #88                 // Method LA:(I)C
     764: bipush        60
     766: if_icmpne     792
     769: aload_0
     770: iconst_2
     771: invokevirtual #88                 // Method LA:(I)C
     774: bipush        61
     776: if_icmpne     792
     779: aload_0
     780: iconst_1
     781: invokevirtual #109                // Method mLE:(Z)V
     784: aload_0
     785: getfield      #90                 // Field _returnToken:Lantlr/Token;
     788: astore_1
     789: goto          949
     792: aload_0
     793: iconst_1
     794: invokevirtual #88                 // Method LA:(I)C
     797: bipush        62
     799: if_icmpne     825
     802: aload_0
     803: iconst_2
     804: invokevirtual #88                 // Method LA:(I)C
     807: bipush        61
     809: if_icmpne     825
     812: aload_0
     813: iconst_1
     814: invokevirtual #110                // Method mGE:(Z)V
     817: aload_0
     818: getfield      #90                 // Field _returnToken:Lantlr/Token;
     821: astore_1
     822: goto          949
     825: aload_0
     826: iconst_1
     827: invokevirtual #88                 // Method LA:(I)C
     830: bipush        60
     832: if_icmpne     848
     835: aload_0
     836: iconst_1
     837: invokevirtual #111                // Method mLT:(Z)V
     840: aload_0
     841: getfield      #90                 // Field _returnToken:Lantlr/Token;
     844: astore_1
     845: goto          949
     848: aload_0
     849: iconst_1
     850: invokevirtual #88                 // Method LA:(I)C
     853: bipush        62
     855: if_icmpne     871
     858: aload_0
     859: iconst_1
     860: invokevirtual #112                // Method mGT:(Z)V
     863: aload_0
     864: getfield      #90                 // Field _returnToken:Lantlr/Token;
     867: astore_1
     868: goto          949
     871: getstatic     #113                // Field _tokenSet_0:Lantlr/collections/impl/BitSet;
     874: aload_0
     875: iconst_1
     876: invokevirtual #88                 // Method LA:(I)C
     879: invokevirtual #114                // Method antlr/collections/impl/BitSet.member:(I)Z
     882: ifeq          898
     885: aload_0
     886: iconst_1
     887: invokevirtual #115                // Method mIDENT:(Z)V
     890: aload_0
     891: getfield      #90                 // Field _returnToken:Lantlr/Token;
     894: astore_1
     895: goto          949
     898: aload_0
     899: iconst_1
     900: invokevirtual #88                 // Method LA:(I)C
     903: ldc           #117                // int 65535
     905: if_icmpne     924
     908: aload_0
     909: invokevirtual #118                // Method uponEOF:()V
     912: aload_0
     913: aload_0
     914: iconst_1
     915: invokevirtual #119                // Method makeToken:(I)Lantlr/Token;
     918: putfield      #90                 // Field _returnToken:Lantlr/Token;
     921: goto          949
     924: new           #120                // class antlr/NoViableAltForCharException
     927: dup
     928: aload_0
     929: iconst_1
     930: invokevirtual #88                 // Method LA:(I)C
     933: aload_0
     934: invokevirtual #121                // Method getFilename:()Ljava/lang/String;
     937: aload_0
     938: invokevirtual #122                // Method getLine:()I
     941: aload_0
     942: invokevirtual #123                // Method getColumn:()I
     945: invokespecial #124                // Method antlr/NoViableAltForCharException."<init>":(CLjava/lang/String;II)V
     948: athrow
     949: aload_0
     950: getfield      #90                 // Field _returnToken:Lantlr/Token;
     953: ifnonnull     959
     956: goto          2
     959: aload_0
     960: getfield      #90                 // Field _returnToken:Lantlr/Token;
     963: invokevirtual #125                // Method antlr/Token.getType:()I
     966: istore_3
     967: aload_0
     968: getfield      #90                 // Field _returnToken:Lantlr/Token;
     971: iload_3
     972: invokevirtual #126                // Method antlr/Token.setType:(I)V
     975: aload_0
     976: getfield      #90                 // Field _returnToken:Lantlr/Token;
     979: areturn
     980: astore        4
     982: new           #128                // class antlr/TokenStreamRecognitionException
     985: dup
     986: aload         4
     988: invokespecial #129                // Method antlr/TokenStreamRecognitionException."<init>":(Lantlr/RecognitionException;)V
     991: athrow
     992: astore        4
     994: aload         4
     996: instanceof    #131                // class antlr/CharStreamIOException
     999: ifeq          1018
    1002: new           #132                // class antlr/TokenStreamIOException
    1005: dup
    1006: aload         4
    1008: checkcast     #131                // class antlr/CharStreamIOException
    1011: getfield      #133                // Field antlr/CharStreamIOException.io:Ljava/io/IOException;
    1014: invokespecial #134                // Method antlr/TokenStreamIOException."<init>":(Ljava/io/IOException;)V
    1017: athrow
    1018: new           #135                // class antlr/TokenStreamException
    1021: dup
    1022: aload         4
    1024: invokevirtual #136                // Method antlr/CharStreamException.getMessage:()Ljava/lang/String;
    1027: invokespecial #137                // Method antlr/TokenStreamException."<init>":(Ljava/lang/String;)V
    1030: athrow
    Exception table:
       from    to  target type
          10   956   980   Class antlr/RecognitionException
         959   979   980   Class antlr/RecognitionException
          10   956   992   Class antlr/CharStreamException
         959   979   992   Class antlr/CharStreamException
         980   992   992   Class antlr/CharStreamException

  public final void mEQ(boolean) throws antlr.RecognitionException, antlr.CharStreamException, antlr.TokenStreamException;
    Code:
       0: aconst_null
       1: astore_3
       2: aload_0
       3: getfield      #138                // Field text:Lantlr/ANTLRStringBuffer;
       6: invokevirtual #139                // Method antlr/ANTLRStringBuffer.length:()I
       9: istore        4
      11: bipush        105
      13: istore_2
      14: aload_0
      15: bipush        61
      17: invokevirtual #141                // Method match:(C)V
      20: iload_1
      21: ifeq          69
      24: aload_3
      25: ifnonnull     69
      28: iload_2
      29: iconst_m1
      30: if_icmpeq     69
      33: aload_0
      34: iload_2
      35: invokevirtual #119                // Method makeToken:(I)Lantlr/Token;
      38: astore_3
      39: aload_3
      40: new           #142                // class java/lang/String
      43: dup
      44: aload_0
      45: getfield      #138                // Field text:Lantlr/ANTLRStringBuffer;
      48: invokevirtual #143                // Method antlr/ANTLRStringBuffer.getBuffer:()[C
      51: iload         4
      53: aload_0
      54: getfield      #138                // Field text:Lantlr/ANTLRStringBuffer;
      57: invokevirtual #139                // Method antlr/ANTLRStringBuffer.length:()I
      60: iload         4
      62: isub
      63: invokespecial #144                // Method java/lang/String."<init>":([CII)V
      66: invokevirtual #145                // Method antlr/Token.setText:(Ljava/lang/String;)V
      69: aload_0
      70: aload_3
      71: putfield      #90                 // Field _returnToken:Lantlr/Token;
      74: return

  public final void mLT(boolean) throws antlr.RecognitionException, antlr.CharStreamException, antlr.TokenStreamException;
    Code:
       0: aconst_null
       1: astore_3
       2: aload_0
       3: getfield      #138                // Field text:Lantlr/ANTLRStringBuffer;
       6: invokevirtual #139                // Method antlr/ANTLRStringBuffer.length:()I
       9: istore        4
      11: bipush        114
      13: istore_2
      14: aload_0
      15: bipush        60
      17: invokevirtual #141                // Method match:(C)V
      20: iload_1
      21: ifeq          69
      24: aload_3
      25: ifnonnull     69
      28: iload_2
      29: iconst_m1
      30: if_icmpeq     69
      33: aload_0
      34: iload_2
      35: invokevirtual #119                // Method makeToken:(I)Lantlr/Token;
      38: astore_3
      39: aload_3
      40: new           #142                // class java/lang/String
      43: dup
      44: aload_0
      45: getfield      #138                // Field text:Lantlr/ANTLRStringBuffer;
      48: invokevirtual #143                // Method antlr/ANTLRStringBuffer.getBuffer:()[C
      51: iload         4
      53: aload_0
      54: getfield      #138                // Field text:Lantlr/ANTLRStringBuffer;
      57: invokevirtual #139                // Method antlr/ANTLRStringBuffer.length:()I
      60: iload         4
      62: isub
      63: invokespecial #144                // Method java/lang/String."<init>":([CII)V
      66: invokevirtual #145                // Method antlr/Token.setText:(Ljava/lang/String;)V
      69: aload_0
      70: aload_3
      71: putfield      #90                 // Field _returnToken:Lantlr/Token;
      74: return

  public final void mGT(boolean) throws antlr.RecognitionException, antlr.CharStreamException, antlr.TokenStreamException;
    Code:
       0: aconst_null
       1: astore_3
       2: aload_0
       3: getfield      #138                // Field text:Lantlr/ANTLRStringBuffer;
       6: invokevirtual #139                // Method antlr/ANTLRStringBuffer.length:()I
       9: istore        4
      11: bipush        115
      13: istore_2
      14: aload_0
      15: bipush        62
      17: invokevirtual #141                // Method match:(C)V
      20: iload_1
      21: ifeq          69
      24: aload_3
      25: ifnonnull     69
      28: iload_2
      29: iconst_m1
      30: if_icmpeq     69
      33: aload_0
      34: iload_2
      35: invokevirtual #119                // Method makeToken:(I)Lantlr/Token;
      38: astore_3
      39: aload_3
      40: new           #142                // class java/lang/String
      43: dup
      44: aload_0
      45: getfield      #138                // Field text:Lantlr/ANTLRStringBuffer;
      48: invokevirtual #143                // Method antlr/ANTLRStringBuffer.getBuffer:()[C
      51: iload         4
      53: aload_0
      54: getfield      #138                // Field text:Lantlr/ANTLRStringBuffer;
      57: invokevirtual #139                // Method antlr/ANTLRStringBuffer.length:()I
      60: iload         4
      62: isub
      63: invokespecial #144                // Method java/lang/String."<init>":([CII)V
      66: invokevirtual #145                // Method antlr/Token.setText:(Ljava/lang/String;)V
      69: aload_0
      70: aload_3
      71: putfield      #90                 // Field _returnToken:Lantlr/Token;
      74: return

  public final void mSQL_NE(boolean) throws antlr.RecognitionException, antlr.CharStreamException, antlr.TokenStreamException;
    Code:
       0: aconst_null
       1: astore_3
       2: aload_0
       3: getfield      #138                // Field text:Lantlr/ANTLRStringBuffer;
       6: invokevirtual #139                // Method antlr/ANTLRStringBuffer.length:()I
       9: istore        4
      11: bipush        113
      13: istore_2
      14: aload_0
      15: ldc           #146                // String <>
      17: invokevirtual #147                // Method match:(Ljava/lang/String;)V
      20: iload_1
      21: ifeq          69
      24: aload_3
      25: ifnonnull     69
      28: iload_2
      29: iconst_m1
      30: if_icmpeq     69
      33: aload_0
      34: iload_2
      35: invokevirtual #119                // Method makeToken:(I)Lantlr/Token;
      38: astore_3
      39: aload_3
      40: new           #142                // class java/lang/String
      43: dup
      44: aload_0
      45: getfield      #138                // Field text:Lantlr/ANTLRStringBuffer;
      48: invokevirtual #143                // Method antlr/ANTLRStringBuffer.getBuffer:()[C
      51: iload         4
      53: aload_0
      54: getfield      #138                // Field text:Lantlr/ANTLRStringBuffer;
      57: invokevirtual #139                // Method antlr/ANTLRStringBuffer.length:()I
      60: iload         4
      62: isub
      63: invokespecial #144                // Method java/lang/String."<init>":([CII)V
      66: invokevirtual #145                // Method antlr/Token.setText:(Ljava/lang/String;)V
      69: aload_0
      70: aload_3
      71: putfield      #90                 // Field _returnToken:Lantlr/Token;
      74: return

  public final void mNE(boolean) throws antlr.RecognitionException, antlr.CharStreamException, antlr.TokenStreamException;
    Code:
       0: aconst_null
       1: astore_3
       2: aload_0
       3: getfield      #138                // Field text:Lantlr/ANTLRStringBuffer;
       6: invokevirtual #139                // Method antlr/ANTLRStringBuffer.length:()I
       9: istore        4
      11: bipush        112
      13: istore_2
      14: aload_0
      15: iconst_1
      16: invokevirtual #88                 // Method LA:(I)C
      19: lookupswitch  { // 2
                    33: 44
                    94: 53
               default: 62
          }
      44: aload_0
      45: ldc           #148                // String !=
      47: invokevirtual #147                // Method match:(Ljava/lang/String;)V
      50: goto          87
      53: aload_0
      54: ldc           #149                // String ^=
      56: invokevirtual #147                // Method match:(Ljava/lang/String;)V
      59: goto          87
      62: new           #120                // class antlr/NoViableAltForCharException
      65: dup
      66: aload_0
      67: iconst_1
      68: invokevirtual #88                 // Method LA:(I)C
      71: aload_0
      72: invokevirtual #121                // Method getFilename:()Ljava/lang/String;
      75: aload_0
      76: invokevirtual #122                // Method getLine:()I
      79: aload_0
      80: invokevirtual #123                // Method getColumn:()I
      83: invokespecial #124                // Method antlr/NoViableAltForCharException."<init>":(CLjava/lang/String;II)V
      86: athrow
      87: iload_1
      88: ifeq          136
      91: aload_3
      92: ifnonnull     136
      95: iload_2
      96: iconst_m1
      97: if_icmpeq     136
     100: aload_0
     101: iload_2
     102: invokevirtual #119                // Method makeToken:(I)Lantlr/Token;
     105: astore_3
     106: aload_3
     107: new           #142                // class java/lang/String
     110: dup
     111: aload_0
     112: getfield      #138                // Field text:Lantlr/ANTLRStringBuffer;
     115: invokevirtual #143                // Method antlr/ANTLRStringBuffer.getBuffer:()[C
     118: iload         4
     120: aload_0
     121: getfield      #138                // Field text:Lantlr/ANTLRStringBuffer;
     124: invokevirtual #139                // Method antlr/ANTLRStringBuffer.length:()I
     127: iload         4
     129: isub
     130: invokespecial #144                // Method java/lang/String."<init>":([CII)V
     133: invokevirtual #145                // Method antlr/Token.setText:(Ljava/lang/String;)V
     136: aload_0
     137: aload_3
     138: putfield      #90                 // Field _returnToken:Lantlr/Token;
     141: return

  public final void mLE(boolean) throws antlr.RecognitionException, antlr.CharStreamException, antlr.TokenStreamException;
    Code:
       0: aconst_null
       1: astore_3
       2: aload_0
       3: getfield      #138                // Field text:Lantlr/ANTLRStringBuffer;
       6: invokevirtual #139                // Method antlr/ANTLRStringBuffer.length:()I
       9: istore        4
      11: bipush        116
      13: istore_2
      14: aload_0
      15: ldc           #150                // String <=
      17: invokevirtual #147                // Method match:(Ljava/lang/String;)V
      20: iload_1
      21: ifeq          69
      24: aload_3
      25: ifnonnull     69
      28: iload_2
      29: iconst_m1
      30: if_icmpeq     69
      33: aload_0
      34: iload_2
      35: invokevirtual #119                // Method makeToken:(I)Lantlr/Token;
      38: astore_3
      39: aload_3
      40: new           #142                // class java/lang/String
      43: dup
      44: aload_0
      45: getfield      #138                // Field text:Lantlr/ANTLRStringBuffer;
      48: invokevirtual #143                // Method antlr/ANTLRStringBuffer.getBuffer:()[C
      51: iload         4
      53: aload_0
      54: getfield      #138                // Field text:Lantlr/ANTLRStringBuffer;
      57: invokevirtual #139                // Method antlr/ANTLRStringBuffer.length:()I
      60: iload         4
      62: isub
      63: invokespecial #144                // Method java/lang/String."<init>":([CII)V
      66: invokevirtual #145                // Method antlr/Token.setText:(Ljava/lang/String;)V
      69: aload_0
      70: aload_3
      71: putfield      #90                 // Field _returnToken:Lantlr/Token;
      74: return

  public final void mGE(boolean) throws antlr.RecognitionException, antlr.CharStreamException, antlr.TokenStreamException;
    Code:
       0: aconst_null
       1: astore_3
       2: aload_0
       3: getfield      #138                // Field text:Lantlr/ANTLRStringBuffer;
       6: invokevirtual #139                // Method antlr/ANTLRStringBuffer.length:()I
       9: istore        4
      11: bipush        117
      13: istore_2
      14: aload_0
      15: ldc           #151                // String >=
      17: invokevirtual #147                // Method match:(Ljava/lang/String;)V
      20: iload_1
      21: ifeq          69
      24: aload_3
      25: ifnonnull     69
      28: iload_2
      29: iconst_m1
      30: if_icmpeq     69
      33: aload_0
      34: iload_2
      35: invokevirtual #119                // Method makeToken:(I)Lantlr/Token;
      38: astore_3
      39: aload_3
      40: new           #142                // class java/lang/String
      43: dup
      44: aload_0
      45: getfield      #138                // Field text:Lantlr/ANTLRStringBuffer;
      48: invokevirtual #143                // Method antlr/ANTLRStringBuffer.getBuffer:()[C
      51: iload         4
      53: aload_0
      54: getfield      #138                // Field text:Lantlr/ANTLRStringBuffer;
      57: invokevirtual #139                // Method antlr/ANTLRStringBuffer.length:()I
      60: iload         4
      62: isub
      63: invokespecial #144                // Method java/lang/String."<init>":([CII)V
      66: invokevirtual #145                // Method antlr/Token.setText:(Ljava/lang/String;)V
      69: aload_0
      70: aload_3
      71: putfield      #90                 // Field _returnToken:Lantlr/Token;
      74: return

  public final void mCOMMA(boolean) throws antlr.RecognitionException, antlr.CharStreamException, antlr.TokenStreamException;
    Code:
       0: aconst_null
       1: astore_3
       2: aload_0
       3: getfield      #138                // Field text:Lantlr/ANTLRStringBuffer;
       6: invokevirtual #139                // Method antlr/ANTLRStringBuffer.length:()I
       9: istore        4
      11: bipush        104
      13: istore_2
      14: aload_0
      15: bipush        44
      17: invokevirtual #141                // Method match:(C)V
      20: iload_1
      21: ifeq          69
      24: aload_3
      25: ifnonnull     69
      28: iload_2
      29: iconst_m1
      30: if_icmpeq     69
      33: aload_0
      34: iload_2
      35: invokevirtual #119                // Method makeToken:(I)Lantlr/Token;
      38: astore_3
      39: aload_3
      40: new           #142                // class java/lang/String
      43: dup
      44: aload_0
      45: getfield      #138                // Field text:Lantlr/ANTLRStringBuffer;
      48: invokevirtual #143                // Method antlr/ANTLRStringBuffer.getBuffer:()[C
      51: iload         4
      53: aload_0
      54: getfield      #138                // Field text:Lantlr/ANTLRStringBuffer;
      57: invokevirtual #139                // Method antlr/ANTLRStringBuffer.length:()I
      60: iload         4
      62: isub
      63: invokespecial #144                // Method java/lang/String."<init>":([CII)V
      66: invokevirtual #145                // Method antlr/Token.setText:(Ljava/lang/String;)V
      69: aload_0
      70: aload_3
      71: putfield      #90                 // Field _returnToken:Lantlr/Token;
      74: return

  public final void mOPEN(boolean) throws antlr.RecognitionException, antlr.CharStreamException, antlr.TokenStreamException;
    Code:
       0: aconst_null
       1: astore_3
       2: aload_0
       3: getfield      #138                // Field text:Lantlr/ANTLRStringBuffer;
       6: invokevirtual #139                // Method antlr/ANTLRStringBuffer.length:()I
       9: istore        4
      11: bipush        106
      13: istore_2
      14: aload_0
      15: bipush        40
      17: invokevirtual #141                // Method match:(C)V
      20: iload_1
      21: ifeq          69
      24: aload_3
      25: ifnonnull     69
      28: iload_2
      29: iconst_m1
      30: if_icmpeq     69
      33: aload_0
      34: iload_2
      35: invokevirtual #119                // Method makeToken:(I)Lantlr/Token;
      38: astore_3
      39: aload_3
      40: new           #142                // class java/lang/String
      43: dup
      44: aload_0
      45: getfield      #138                // Field text:Lantlr/ANTLRStringBuffer;
      48: invokevirtual #143                // Method antlr/ANTLRStringBuffer.getBuffer:()[C
      51: iload         4
      53: aload_0
      54: getfield      #138                // Field text:Lantlr/ANTLRStringBuffer;
      57: invokevirtual #139                // Method antlr/ANTLRStringBuffer.length:()I
      60: iload         4
      62: isub
      63: invokespecial #144                // Method java/lang/String."<init>":([CII)V
      66: invokevirtual #145                // Method antlr/Token.setText:(Ljava/lang/String;)V
      69: aload_0
      70: aload_3
      71: putfield      #90                 // Field _returnToken:Lantlr/Token;
      74: return

  public final void mCLOSE(boolean) throws antlr.RecognitionException, antlr.CharStreamException, antlr.TokenStreamException;
    Code:
       0: aconst_null
       1: astore_3
       2: aload_0
       3: getfield      #138                // Field text:Lantlr/ANTLRStringBuffer;
       6: invokevirtual #139                // Method antlr/ANTLRStringBuffer.length:()I
       9: istore        4
      11: bipush        107
      13: istore_2
      14: aload_0
      15: bipush        41
      17: invokevirtual #141                // Method match:(C)V
      20: iload_1
      21: ifeq          69
      24: aload_3
      25: ifnonnull     69
      28: iload_2
      29: iconst_m1
      30: if_icmpeq     69
      33: aload_0
      34: iload_2
      35: invokevirtual #119                // Method makeToken:(I)Lantlr/Token;
      38: astore_3
      39: aload_3
      40: new           #142                // class java/lang/String
      43: dup
      44: aload_0
      45: getfield      #138                // Field text:Lantlr/ANTLRStringBuffer;
      48: invokevirtual #143                // Method antlr/ANTLRStringBuffer.getBuffer:()[C
      51: iload         4
      53: aload_0
      54: getfield      #138                // Field text:Lantlr/ANTLRStringBuffer;
      57: invokevirtual #139                // Method antlr/ANTLRStringBuffer.length:()I
      60: iload         4
      62: isub
      63: invokespecial #144                // Method java/lang/String."<init>":([CII)V
      66: invokevirtual #145                // Method antlr/Token.setText:(Ljava/lang/String;)V
      69: aload_0
      70: aload_3
      71: putfield      #90                 // Field _returnToken:Lantlr/Token;
      74: return

  public final void mOPEN_BRACKET(boolean) throws antlr.RecognitionException, antlr.CharStreamException, antlr.TokenStreamException;
    Code:
       0: aconst_null
       1: astore_3
       2: aload_0
       3: getfield      #138                // Field text:Lantlr/ANTLRStringBuffer;
       6: invokevirtual #139                // Method antlr/ANTLRStringBuffer.length:()I
       9: istore        4
      11: bipush        124
      13: istore_2
      14: aload_0
      15: bipush        91
      17: invokevirtual #141                // Method match:(C)V
      20: iload_1
      21: ifeq          69
      24: aload_3
      25: ifnonnull     69
      28: iload_2
      29: iconst_m1
      30: if_icmpeq     69
      33: aload_0
      34: iload_2
      35: invokevirtual #119                // Method makeToken:(I)Lantlr/Token;
      38: astore_3
      39: aload_3
      40: new           #142                // class java/lang/String
      43: dup
      44: aload_0
      45: getfield      #138                // Field text:Lantlr/ANTLRStringBuffer;
      48: invokevirtual #143                // Method antlr/ANTLRStringBuffer.getBuffer:()[C
      51: iload         4
      53: aload_0
      54: getfield      #138                // Field text:Lantlr/ANTLRStringBuffer;
      57: invokevirtual #139                // Method antlr/ANTLRStringBuffer.length:()I
      60: iload         4
      62: isub
      63: invokespecial #144                // Method java/lang/String."<init>":([CII)V
      66: invokevirtual #145                // Method antlr/Token.setText:(Ljava/lang/String;)V
      69: aload_0
      70: aload_3
      71: putfield      #90                 // Field _returnToken:Lantlr/Token;
      74: return

  public final void mCLOSE_BRACKET(boolean) throws antlr.RecognitionException, antlr.CharStreamException, antlr.TokenStreamException;
    Code:
       0: aconst_null
       1: astore_3
       2: aload_0
       3: getfield      #138                // Field text:Lantlr/ANTLRStringBuffer;
       6: invokevirtual #139                // Method antlr/ANTLRStringBuffer.length:()I
       9: istore        4
      11: bipush        125
      13: istore_2
      14: aload_0
      15: bipush        93
      17: invokevirtual #141                // Method match:(C)V
      20: iload_1
      21: ifeq          69
      24: aload_3
      25: ifnonnull     69
      28: iload_2
      29: iconst_m1
      30: if_icmpeq     69
      33: aload_0
      34: iload_2
      35: invokevirtual #119                // Method makeToken:(I)Lantlr/Token;
      38: astore_3
      39: aload_3
      40: new           #142                // class java/lang/String
      43: dup
      44: aload_0
      45: getfield      #138                // Field text:Lantlr/ANTLRStringBuffer;
      48: invokevirtual #143                // Method antlr/ANTLRStringBuffer.getBuffer:()[C
      51: iload         4
      53: aload_0
      54: getfield      #138                // Field text:Lantlr/ANTLRStringBuffer;
      57: invokevirtual #139                // Method antlr/ANTLRStringBuffer.length:()I
      60: iload         4
      62: isub
      63: invokespecial #144                // Method java/lang/String."<init>":([CII)V
      66: invokevirtual #145                // Method antlr/Token.setText:(Ljava/lang/String;)V
      69: aload_0
      70: aload_3
      71: putfield      #90                 // Field _returnToken:Lantlr/Token;
      74: return

  public final void mCONCAT(boolean) throws antlr.RecognitionException, antlr.CharStreamException, antlr.TokenStreamException;
    Code:
       0: aconst_null
       1: astore_3
       2: aload_0
       3: getfield      #138                // Field text:Lantlr/ANTLRStringBuffer;
       6: invokevirtual #139                // Method antlr/ANTLRStringBuffer.length:()I
       9: istore        4
      11: bipush        118
      13: istore_2
      14: aload_0
      15: ldc           #152                // String ||
      17: invokevirtual #147                // Method match:(Ljava/lang/String;)V
      20: iload_1
      21: ifeq          69
      24: aload_3
      25: ifnonnull     69
      28: iload_2
      29: iconst_m1
      30: if_icmpeq     69
      33: aload_0
      34: iload_2
      35: invokevirtual #119                // Method makeToken:(I)Lantlr/Token;
      38: astore_3
      39: aload_3
      40: new           #142                // class java/lang/String
      43: dup
      44: aload_0
      45: getfield      #138                // Field text:Lantlr/ANTLRStringBuffer;
      48: invokevirtual #143                // Method antlr/ANTLRStringBuffer.getBuffer:()[C
      51: iload         4
      53: aload_0
      54: getfield      #138                // Field text:Lantlr/ANTLRStringBuffer;
      57: invokevirtual #139                // Method antlr/ANTLRStringBuffer.length:()I
      60: iload         4
      62: isub
      63: invokespecial #144                // Method java/lang/String."<init>":([CII)V
      66: invokevirtual #145                // Method antlr/Token.setText:(Ljava/lang/String;)V
      69: aload_0
      70: aload_3
      71: putfield      #90                 // Field _returnToken:Lantlr/Token;
      74: return

  public final void mPLUS(boolean) throws antlr.RecognitionException, antlr.CharStreamException, antlr.TokenStreamException;
    Code:
       0: aconst_null
       1: astore_3
       2: aload_0
       3: getfield      #138                // Field text:Lantlr/ANTLRStringBuffer;
       6: invokevirtual #139                // Method antlr/ANTLRStringBuffer.length:()I
       9: istore        4
      11: bipush        119
      13: istore_2
      14: aload_0
      15: bipush        43
      17: invokevirtual #141                // Method match:(C)V
      20: iload_1
      21: ifeq          69
      24: aload_3
      25: ifnonnull     69
      28: iload_2
      29: iconst_m1
      30: if_icmpeq     69
      33: aload_0
      34: iload_2
      35: invokevirtual #119                // Method makeToken:(I)Lantlr/Token;
      38: astore_3
      39: aload_3
      40: new           #142                // class java/lang/String
      43: dup
      44: aload_0
      45: getfield      #138                // Field text:Lantlr/ANTLRStringBuffer;
      48: invokevirtual #143                // Method antlr/ANTLRStringBuffer.getBuffer:()[C
      51: iload         4
      53: aload_0
      54: getfield      #138                // Field text:Lantlr/ANTLRStringBuffer;
      57: invokevirtual #139                // Method antlr/ANTLRStringBuffer.length:()I
      60: iload         4
      62: isub
      63: invokespecial #144                // Method java/lang/String."<init>":([CII)V
      66: invokevirtual #145                // Method antlr/Token.setText:(Ljava/lang/String;)V
      69: aload_0
      70: aload_3
      71: putfield      #90                 // Field _returnToken:Lantlr/Token;
      74: return

  public final void mMINUS(boolean) throws antlr.RecognitionException, antlr.CharStreamException, antlr.TokenStreamException;
    Code:
       0: aconst_null
       1: astore_3
       2: aload_0
       3: getfield      #138                // Field text:Lantlr/ANTLRStringBuffer;
       6: invokevirtual #139                // Method antlr/ANTLRStringBuffer.length:()I
       9: istore        4
      11: bipush        120
      13: istore_2
      14: aload_0
      15: bipush        45
      17: invokevirtual #141                // Method match:(C)V
      20: iload_1
      21: ifeq          69
      24: aload_3
      25: ifnonnull     69
      28: iload_2
      29: iconst_m1
      30: if_icmpeq     69
      33: aload_0
      34: iload_2
      35: invokevirtual #119                // Method makeToken:(I)Lantlr/Token;
      38: astore_3
      39: aload_3
      40: new           #142                // class java/lang/String
      43: dup
      44: aload_0
      45: getfield      #138                // Field text:Lantlr/ANTLRStringBuffer;
      48: invokevirtual #143                // Method antlr/ANTLRStringBuffer.getBuffer:()[C
      51: iload         4
      53: aload_0
      54: getfield      #138                // Field text:Lantlr/ANTLRStringBuffer;
      57: invokevirtual #139                // Method antlr/ANTLRStringBuffer.length:()I
      60: iload         4
      62: isub
      63: invokespecial #144                // Method java/lang/String."<init>":([CII)V
      66: invokevirtual #145                // Method antlr/Token.setText:(Ljava/lang/String;)V
      69: aload_0
      70: aload_3
      71: putfield      #90                 // Field _returnToken:Lantlr/Token;
      74: return

  public final void mSTAR(boolean) throws antlr.RecognitionException, antlr.CharStreamException, antlr.TokenStreamException;
    Code:
       0: aconst_null
       1: astore_3
       2: aload_0
       3: getfield      #138                // Field text:Lantlr/ANTLRStringBuffer;
       6: invokevirtual #139                // Method antlr/ANTLRStringBuffer.length:()I
       9: istore        4
      11: bipush        121
      13: istore_2
      14: aload_0
      15: bipush        42
      17: invokevirtual #141                // Method match:(C)V
      20: iload_1
      21: ifeq          69
      24: aload_3
      25: ifnonnull     69
      28: iload_2
      29: iconst_m1
      30: if_icmpeq     69
      33: aload_0
      34: iload_2
      35: invokevirtual #119                // Method makeToken:(I)Lantlr/Token;
      38: astore_3
      39: aload_3
      40: new           #142                // class java/lang/String
      43: dup
      44: aload_0
      45: getfield      #138                // Field text:Lantlr/ANTLRStringBuffer;
      48: invokevirtual #143                // Method antlr/ANTLRStringBuffer.getBuffer:()[C
      51: iload         4
      53: aload_0
      54: getfield      #138                // Field text:Lantlr/ANTLRStringBuffer;
      57: invokevirtual #139                // Method antlr/ANTLRStringBuffer.length:()I
      60: iload         4
      62: isub
      63: invokespecial #144                // Method java/lang/String."<init>":([CII)V
      66: invokevirtual #145                // Method antlr/Token.setText:(Ljava/lang/String;)V
      69: aload_0
      70: aload_3
      71: putfield      #90                 // Field _returnToken:Lantlr/Token;
      74: return

  public final void mDIV(boolean) throws antlr.RecognitionException, antlr.CharStreamException, antlr.TokenStreamException;
    Code:
       0: aconst_null
       1: astore_3
       2: aload_0
       3: getfield      #138                // Field text:Lantlr/ANTLRStringBuffer;
       6: invokevirtual #139                // Method antlr/ANTLRStringBuffer.length:()I
       9: istore        4
      11: bipush        122
      13: istore_2
      14: aload_0
      15: bipush        47
      17: invokevirtual #141                // Method match:(C)V
      20: iload_1
      21: ifeq          69
      24: aload_3
      25: ifnonnull     69
      28: iload_2
      29: iconst_m1
      30: if_icmpeq     69
      33: aload_0
      34: iload_2
      35: invokevirtual #119                // Method makeToken:(I)Lantlr/Token;
      38: astore_3
      39: aload_3
      40: new           #142                // class java/lang/String
      43: dup
      44: aload_0
      45: getfield      #138                // Field text:Lantlr/ANTLRStringBuffer;
      48: invokevirtual #143                // Method antlr/ANTLRStringBuffer.getBuffer:()[C
      51: iload         4
      53: aload_0
      54: getfield      #138                // Field text:Lantlr/ANTLRStringBuffer;
      57: invokevirtual #139                // Method antlr/ANTLRStringBuffer.length:()I
      60: iload         4
      62: isub
      63: invokespecial #144                // Method java/lang/String."<init>":([CII)V
      66: invokevirtual #145                // Method antlr/Token.setText:(Ljava/lang/String;)V
      69: aload_0
      70: aload_3
      71: putfield      #90                 // Field _returnToken:Lantlr/Token;
      74: return

  public final void mMOD(boolean) throws antlr.RecognitionException, antlr.CharStreamException, antlr.TokenStreamException;
    Code:
       0: aconst_null
       1: astore_3
       2: aload_0
       3: getfield      #138                // Field text:Lantlr/ANTLRStringBuffer;
       6: invokevirtual #139                // Method antlr/ANTLRStringBuffer.length:()I
       9: istore        4
      11: bipush        123
      13: istore_2
      14: aload_0
      15: bipush        37
      17: invokevirtual #141                // Method match:(C)V
      20: iload_1
      21: ifeq          69
      24: aload_3
      25: ifnonnull     69
      28: iload_2
      29: iconst_m1
      30: if_icmpeq     69
      33: aload_0
      34: iload_2
      35: invokevirtual #119                // Method makeToken:(I)Lantlr/Token;
      38: astore_3
      39: aload_3
      40: new           #142                // class java/lang/String
      43: dup
      44: aload_0
      45: getfield      #138                // Field text:Lantlr/ANTLRStringBuffer;
      48: invokevirtual #143                // Method antlr/ANTLRStringBuffer.getBuffer:()[C
      51: iload         4
      53: aload_0
      54: getfield      #138                // Field text:Lantlr/ANTLRStringBuffer;
      57: invokevirtual #139                // Method antlr/ANTLRStringBuffer.length:()I
      60: iload         4
      62: isub
      63: invokespecial #144                // Method java/lang/String."<init>":([CII)V
      66: invokevirtual #145                // Method antlr/Token.setText:(Ljava/lang/String;)V
      69: aload_0
      70: aload_3
      71: putfield      #90                 // Field _returnToken:Lantlr/Token;
      74: return

  public final void mCOLON(boolean) throws antlr.RecognitionException, antlr.CharStreamException, antlr.TokenStreamException;
    Code:
       0: aconst_null
       1: astore_3
       2: aload_0
       3: getfield      #138                // Field text:Lantlr/ANTLRStringBuffer;
       6: invokevirtual #139                // Method antlr/ANTLRStringBuffer.length:()I
       9: istore        4
      11: bipush        127
      13: istore_2
      14: aload_0
      15: bipush        58
      17: invokevirtual #141                // Method match:(C)V
      20: iload_1
      21: ifeq          69
      24: aload_3
      25: ifnonnull     69
      28: iload_2
      29: iconst_m1
      30: if_icmpeq     69
      33: aload_0
      34: iload_2
      35: invokevirtual #119                // Method makeToken:(I)Lantlr/Token;
      38: astore_3
      39: aload_3
      40: new           #142                // class java/lang/String
      43: dup
      44: aload_0
      45: getfield      #138                // Field text:Lantlr/ANTLRStringBuffer;
      48: invokevirtual #143                // Method antlr/ANTLRStringBuffer.getBuffer:()[C
      51: iload         4
      53: aload_0
      54: getfield      #138                // Field text:Lantlr/ANTLRStringBuffer;
      57: invokevirtual #139                // Method antlr/ANTLRStringBuffer.length:()I
      60: iload         4
      62: isub
      63: invokespecial #144                // Method java/lang/String."<init>":([CII)V
      66: invokevirtual #145                // Method antlr/Token.setText:(Ljava/lang/String;)V
      69: aload_0
      70: aload_3
      71: putfield      #90                 // Field _returnToken:Lantlr/Token;
      74: return

  public final void mPARAM(boolean) throws antlr.RecognitionException, antlr.CharStreamException, antlr.TokenStreamException;
    Code:
       0: aconst_null
       1: astore_3
       2: aload_0
       3: getfield      #138                // Field text:Lantlr/ANTLRStringBuffer;
       6: invokevirtual #139                // Method antlr/ANTLRStringBuffer.length:()I
       9: istore        4
      11: sipush        128
      14: istore_2
      15: aload_0
      16: bipush        63
      18: invokevirtual #141                // Method match:(C)V
      21: iload_1
      22: ifeq          70
      25: aload_3
      26: ifnonnull     70
      29: iload_2
      30: iconst_m1
      31: if_icmpeq     70
      34: aload_0
      35: iload_2
      36: invokevirtual #119                // Method makeToken:(I)Lantlr/Token;
      39: astore_3
      40: aload_3
      41: new           #142                // class java/lang/String
      44: dup
      45: aload_0
      46: getfield      #138                // Field text:Lantlr/ANTLRStringBuffer;
      49: invokevirtual #143                // Method antlr/ANTLRStringBuffer.getBuffer:()[C
      52: iload         4
      54: aload_0
      55: getfield      #138                // Field text:Lantlr/ANTLRStringBuffer;
      58: invokevirtual #139                // Method antlr/ANTLRStringBuffer.length:()I
      61: iload         4
      63: isub
      64: invokespecial #144                // Method java/lang/String."<init>":([CII)V
      67: invokevirtual #145                // Method antlr/Token.setText:(Ljava/lang/String;)V
      70: aload_0
      71: aload_3
      72: putfield      #90                 // Field _returnToken:Lantlr/Token;
      75: return

  public final void mIDENT(boolean) throws antlr.RecognitionException, antlr.CharStreamException, antlr.TokenStreamException;
    Code:
       0: aconst_null
       1: astore_3
       2: aload_0
       3: getfield      #138                // Field text:Lantlr/ANTLRStringBuffer;
       6: invokevirtual #139                // Method antlr/ANTLRStringBuffer.length:()I
       9: istore        4
      11: bipush        108
      13: istore_2
      14: aload_0
      15: iconst_0
      16: invokevirtual #153                // Method mID_START_LETTER:(Z)V
      19: getstatic     #154                // Field _tokenSet_1:Lantlr/collections/impl/BitSet;
      22: aload_0
      23: iconst_1
      24: invokevirtual #88                 // Method LA:(I)C
      27: invokevirtual #114                // Method antlr/collections/impl/BitSet.member:(I)Z
      30: ifeq          41
      33: aload_0
      34: iconst_0
      35: invokevirtual #155                // Method mID_LETTER:(Z)V
      38: goto          19
      41: aload_0
      42: getfield      #156                // Field inputState:Lantlr/LexerSharedInputState;
      45: getfield      #157                // Field antlr/LexerSharedInputState.guessing:I
      48: ifne          56
      51: aload_0
      52: iconst_1
      53: invokevirtual #158                // Method setPossibleID:(Z)V
      56: aload_0
      57: iload_2
      58: invokevirtual #159                // Method testLiteralsTable:(I)I
      61: istore_2
      62: iload_1
      63: ifeq          111
      66: aload_3
      67: ifnonnull     111
      70: iload_2
      71: iconst_m1
      72: if_icmpeq     111
      75: aload_0
      76: iload_2
      77: invokevirtual #119                // Method makeToken:(I)Lantlr/Token;
      80: astore_3
      81: aload_3
      82: new           #142                // class java/lang/String
      85: dup
      86: aload_0
      87: getfield      #138                // Field text:Lantlr/ANTLRStringBuffer;
      90: invokevirtual #143                // Method antlr/ANTLRStringBuffer.getBuffer:()[C
      93: iload         4
      95: aload_0
      96: getfield      #138                // Field text:Lantlr/ANTLRStringBuffer;
      99: invokevirtual #139                // Method antlr/ANTLRStringBuffer.length:()I
     102: iload         4
     104: isub
     105: invokespecial #144                // Method java/lang/String."<init>":([CII)V
     108: invokevirtual #145                // Method antlr/Token.setText:(Ljava/lang/String;)V
     111: aload_0
     112: aload_3
     113: putfield      #90                 // Field _returnToken:Lantlr/Token;
     116: return

  protected final void mID_START_LETTER(boolean) throws antlr.RecognitionException, antlr.CharStreamException, antlr.TokenStreamException;
    Code:
       0: aconst_null
       1: astore_3
       2: aload_0
       3: getfield      #138                // Field text:Lantlr/ANTLRStringBuffer;
       6: invokevirtual #139                // Method antlr/ANTLRStringBuffer.length:()I
       9: istore        4
      11: sipush        130
      14: istore_2
      15: aload_0
      16: iconst_1
      17: invokevirtual #88                 // Method LA:(I)C
      20: tableswitch   { // 36 to 122
                    36: 393
                    37: 413
                    38: 413
                    39: 413
                    40: 413
                    41: 413
                    42: 413
                    43: 413
                    44: 413
                    45: 413
                    46: 413
                    47: 413
                    48: 413
                    49: 413
                    50: 413
                    51: 413
                    52: 413
                    53: 413
                    54: 413
                    55: 413
                    56: 413
                    57: 413
                    58: 413
                    59: 413
                    60: 413
                    61: 413
                    62: 413
                    63: 413
                    64: 413
                    65: 413
                    66: 413
                    67: 413
                    68: 413
                    69: 413
                    70: 413
                    71: 413
                    72: 413
                    73: 413
                    74: 413
                    75: 413
                    76: 413
                    77: 413
                    78: 413
                    79: 413
                    80: 413
                    81: 413
                    82: 413
                    83: 413
                    84: 413
                    85: 413
                    86: 413
                    87: 413
                    88: 413
                    89: 413
                    90: 413
                    91: 413
                    92: 413
                    93: 413
                    94: 413
                    95: 384
                    96: 413
                    97: 402
                    98: 402
                    99: 402
                   100: 402
                   101: 402
                   102: 402
                   103: 402
                   104: 402
                   105: 402
                   106: 402
                   107: 402
                   108: 402
                   109: 402
                   110: 402
                   111: 402
                   112: 402
                   113: 402
                   114: 402
                   115: 402
                   116: 402
                   117: 402
                   118: 402
                   119: 402
                   120: 402
                   121: 402
                   122: 402
               default: 413
          }
     384: aload_0
     385: bipush        95
     387: invokevirtual #141                // Method match:(C)V
     390: goto          471
     393: aload_0
     394: bipush        36
     396: invokevirtual #141                // Method match:(C)V
     399: goto          471
     402: aload_0
     403: bipush        97
     405: bipush        122
     407: invokevirtual #160                // Method matchRange:(CC)V
     410: goto          471
     413: aload_0
     414: iconst_1
     415: invokevirtual #88                 // Method LA:(I)C
     418: sipush        128
     421: if_icmplt     446
     424: aload_0
     425: iconst_1
     426: invokevirtual #88                 // Method LA:(I)C
     429: ldc           #161                // int 65534
     431: if_icmpgt     446
     434: aload_0
     435: sipush        128
     438: ldc           #161                // int 65534
     440: invokevirtual #160                // Method matchRange:(CC)V
     443: goto          471
     446: new           #120                // class antlr/NoViableAltForCharException
     449: dup
     450: aload_0
     451: iconst_1
     452: invokevirtual #88                 // Method LA:(I)C
     455: aload_0
     456: invokevirtual #121                // Method getFilename:()Ljava/lang/String;
     459: aload_0
     460: invokevirtual #122                // Method getLine:()I
     463: aload_0
     464: invokevirtual #123                // Method getColumn:()I
     467: invokespecial #124                // Method antlr/NoViableAltForCharException."<init>":(CLjava/lang/String;II)V
     470: athrow
     471: iload_1
     472: ifeq          520
     475: aload_3
     476: ifnonnull     520
     479: iload_2
     480: iconst_m1
     481: if_icmpeq     520
     484: aload_0
     485: iload_2
     486: invokevirtual #119                // Method makeToken:(I)Lantlr/Token;
     489: astore_3
     490: aload_3
     491: new           #142                // class java/lang/String
     494: dup
     495: aload_0
     496: getfield      #138                // Field text:Lantlr/ANTLRStringBuffer;
     499: invokevirtual #143                // Method antlr/ANTLRStringBuffer.getBuffer:()[C
     502: iload         4
     504: aload_0
     505: getfield      #138                // Field text:Lantlr/ANTLRStringBuffer;
     508: invokevirtual #139                // Method antlr/ANTLRStringBuffer.length:()I
     511: iload         4
     513: isub
     514: invokespecial #144                // Method java/lang/String."<init>":([CII)V
     517: invokevirtual #145                // Method antlr/Token.setText:(Ljava/lang/String;)V
     520: aload_0
     521: aload_3
     522: putfield      #90                 // Field _returnToken:Lantlr/Token;
     525: return

  protected final void mID_LETTER(boolean) throws antlr.RecognitionException, antlr.CharStreamException, antlr.TokenStreamException;
    Code:
       0: aconst_null
       1: astore_3
       2: aload_0
       3: getfield      #138                // Field text:Lantlr/ANTLRStringBuffer;
       6: invokevirtual #139                // Method antlr/ANTLRStringBuffer.length:()I
       9: istore        4
      11: sipush        131
      14: istore_2
      15: getstatic     #113                // Field _tokenSet_0:Lantlr/collections/impl/BitSet;
      18: aload_0
      19: iconst_1
      20: invokevirtual #88                 // Method LA:(I)C
      23: invokevirtual #114                // Method antlr/collections/impl/BitSet.member:(I)Z
      26: ifeq          37
      29: aload_0
      30: iconst_0
      31: invokevirtual #153                // Method mID_START_LETTER:(Z)V
      34: goto          93
      37: aload_0
      38: iconst_1
      39: invokevirtual #88                 // Method LA:(I)C
      42: bipush        48
      44: if_icmplt     68
      47: aload_0
      48: iconst_1
      49: invokevirtual #88                 // Method LA:(I)C
      52: bipush        57
      54: if_icmpgt     68
      57: aload_0
      58: bipush        48
      60: bipush        57
      62: invokevirtual #160                // Method matchRange:(CC)V
      65: goto          93
      68: new           #120                // class antlr/NoViableAltForCharException
      71: dup
      72: aload_0
      73: iconst_1
      74: invokevirtual #88                 // Method LA:(I)C
      77: aload_0
      78: invokevirtual #121                // Method getFilename:()Ljava/lang/String;
      81: aload_0
      82: invokevirtual #122                // Method getLine:()I
      85: aload_0
      86: invokevirtual #123                // Method getColumn:()I
      89: invokespecial #124                // Method antlr/NoViableAltForCharException."<init>":(CLjava/lang/String;II)V
      92: athrow
      93: iload_1
      94: ifeq          142
      97: aload_3
      98: ifnonnull     142
     101: iload_2
     102: iconst_m1
     103: if_icmpeq     142
     106: aload_0
     107: iload_2
     108: invokevirtual #119                // Method makeToken:(I)Lantlr/Token;
     111: astore_3
     112: aload_3
     113: new           #142                // class java/lang/String
     116: dup
     117: aload_0
     118: getfield      #138                // Field text:Lantlr/ANTLRStringBuffer;
     121: invokevirtual #143                // Method antlr/ANTLRStringBuffer.getBuffer:()[C
     124: iload         4
     126: aload_0
     127: getfield      #138                // Field text:Lantlr/ANTLRStringBuffer;
     130: invokevirtual #139                // Method antlr/ANTLRStringBuffer.length:()I
     133: iload         4
     135: isub
     136: invokespecial #144                // Method java/lang/String."<init>":([CII)V
     139: invokevirtual #145                // Method antlr/Token.setText:(Ljava/lang/String;)V
     142: aload_0
     143: aload_3
     144: putfield      #90                 // Field _returnToken:Lantlr/Token;
     147: return

  public final void mQUOTED_STRING(boolean) throws antlr.RecognitionException, antlr.CharStreamException, antlr.TokenStreamException;
    Code:
       0: aconst_null
       1: astore_3
       2: aload_0
       3: getfield      #138                // Field text:Lantlr/ANTLRStringBuffer;
       6: invokevirtual #139                // Method antlr/ANTLRStringBuffer.length:()I
       9: istore        4
      11: bipush        126
      13: istore_2
      14: aload_0
      15: bipush        39
      17: invokevirtual #141                // Method match:(C)V
      20: iconst_0
      21: istore        6
      23: aload_0
      24: iconst_1
      25: invokevirtual #88                 // Method LA:(I)C
      28: bipush        39
      30: if_icmpne     97
      33: aload_0
      34: iconst_2
      35: invokevirtual #88                 // Method LA:(I)C
      38: bipush        39
      40: if_icmpne     97
      43: aload_0
      44: invokevirtual #162                // Method mark:()I
      47: istore        7
      49: iconst_1
      50: istore        6
      52: aload_0
      53: getfield      #156                // Field inputState:Lantlr/LexerSharedInputState;
      56: dup
      57: getfield      #157                // Field antlr/LexerSharedInputState.guessing:I
      60: iconst_1
      61: iadd
      62: putfield      #157                // Field antlr/LexerSharedInputState.guessing:I
      65: aload_0
      66: iconst_0
      67: invokevirtual #163                // Method mESCqs:(Z)V
      70: goto          78
      73: astore        8
      75: iconst_0
      76: istore        6
      78: aload_0
      79: iload         7
      81: invokevirtual #164                // Method rewind:(I)V
      84: aload_0
      85: getfield      #156                // Field inputState:Lantlr/LexerSharedInputState;
      88: dup
      89: getfield      #157                // Field antlr/LexerSharedInputState.guessing:I
      92: iconst_1
      93: isub
      94: putfield      #157                // Field antlr/LexerSharedInputState.guessing:I
      97: iload         6
      99: ifeq          110
     102: aload_0
     103: iconst_0
     104: invokevirtual #163                // Method mESCqs:(Z)V
     107: goto          130
     110: getstatic     #165                // Field _tokenSet_2:Lantlr/collections/impl/BitSet;
     113: aload_0
     114: iconst_1
     115: invokevirtual #88                 // Method LA:(I)C
     118: invokevirtual #114                // Method antlr/collections/impl/BitSet.member:(I)Z
     121: ifeq          133
     124: aload_0
     125: bipush        39
     127: invokevirtual #166                // Method matchNot:(C)V
     130: goto          20
     133: aload_0
     134: bipush        39
     136: invokevirtual #141                // Method match:(C)V
     139: iload_1
     140: ifeq          188
     143: aload_3
     144: ifnonnull     188
     147: iload_2
     148: iconst_m1
     149: if_icmpeq     188
     152: aload_0
     153: iload_2
     154: invokevirtual #119                // Method makeToken:(I)Lantlr/Token;
     157: astore_3
     158: aload_3
     159: new           #142                // class java/lang/String
     162: dup
     163: aload_0
     164: getfield      #138                // Field text:Lantlr/ANTLRStringBuffer;
     167: invokevirtual #143                // Method antlr/ANTLRStringBuffer.getBuffer:()[C
     170: iload         4
     172: aload_0
     173: getfield      #138                // Field text:Lantlr/ANTLRStringBuffer;
     176: invokevirtual #139                // Method antlr/ANTLRStringBuffer.length:()I
     179: iload         4
     181: isub
     182: invokespecial #144                // Method java/lang/String."<init>":([CII)V
     185: invokevirtual #145                // Method antlr/Token.setText:(Ljava/lang/String;)V
     188: aload_0
     189: aload_3
     190: putfield      #90                 // Field _returnToken:Lantlr/Token;
     193: return
    Exception table:
       from    to  target type
          65    70    73   Class antlr/RecognitionException

  protected final void mESCqs(boolean) throws antlr.RecognitionException, antlr.CharStreamException, antlr.TokenStreamException;
    Code:
       0: aconst_null
       1: astore_3
       2: aload_0
       3: getfield      #138                // Field text:Lantlr/ANTLRStringBuffer;
       6: invokevirtual #139                // Method antlr/ANTLRStringBuffer.length:()I
       9: istore        4
      11: sipush        132
      14: istore_2
      15: aload_0
      16: bipush        39
      18: invokevirtual #141                // Method match:(C)V
      21: aload_0
      22: bipush        39
      24: invokevirtual #141                // Method match:(C)V
      27: iload_1
      28: ifeq          76
      31: aload_3
      32: ifnonnull     76
      35: iload_2
      36: iconst_m1
      37: if_icmpeq     76
      40: aload_0
      41: iload_2
      42: invokevirtual #119                // Method makeToken:(I)Lantlr/Token;
      45: astore_3
      46: aload_3
      47: new           #142                // class java/lang/String
      50: dup
      51: aload_0
      52: getfield      #138                // Field text:Lantlr/ANTLRStringBuffer;
      55: invokevirtual #143                // Method antlr/ANTLRStringBuffer.getBuffer:()[C
      58: iload         4
      60: aload_0
      61: getfield      #138                // Field text:Lantlr/ANTLRStringBuffer;
      64: invokevirtual #139                // Method antlr/ANTLRStringBuffer.length:()I
      67: iload         4
      69: isub
      70: invokespecial #144                // Method java/lang/String."<init>":([CII)V
      73: invokevirtual #145                // Method antlr/Token.setText:(Ljava/lang/String;)V
      76: aload_0
      77: aload_3
      78: putfield      #90                 // Field _returnToken:Lantlr/Token;
      81: return

  public final void mWS(boolean) throws antlr.RecognitionException, antlr.CharStreamException, antlr.TokenStreamException;
    Code:
       0: aconst_null
       1: astore_3
       2: aload_0
       3: getfield      #138                // Field text:Lantlr/ANTLRStringBuffer;
       6: invokevirtual #139                // Method antlr/ANTLRStringBuffer.length:()I
       9: istore        4
      11: sipush        133
      14: istore_2
      15: aload_0
      16: iconst_1
      17: invokevirtual #88                 // Method LA:(I)C
      20: lookupswitch  { // 3
                     9: 65
                    10: 74
                    32: 56
               default: 97
          }
      56: aload_0
      57: bipush        32
      59: invokevirtual #141                // Method match:(C)V
      62: goto          204
      65: aload_0
      66: bipush        9
      68: invokevirtual #141                // Method match:(C)V
      71: goto          204
      74: aload_0
      75: bipush        10
      77: invokevirtual #141                // Method match:(C)V
      80: aload_0
      81: getfield      #156                // Field inputState:Lantlr/LexerSharedInputState;
      84: getfield      #157                // Field antlr/LexerSharedInputState.guessing:I
      87: ifne          204
      90: aload_0
      91: invokevirtual #167                // Method newline:()V
      94: goto          204
      97: aload_0
      98: iconst_1
      99: invokevirtual #88                 // Method LA:(I)C
     102: bipush        13
     104: if_icmpne     146
     107: aload_0
     108: iconst_2
     109: invokevirtual #88                 // Method LA:(I)C
     112: bipush        10
     114: if_icmpne     146
     117: aload_0
     118: bipush        13
     120: invokevirtual #141                // Method match:(C)V
     123: aload_0
     124: bipush        10
     126: invokevirtual #141                // Method match:(C)V
     129: aload_0
     130: getfield      #156                // Field inputState:Lantlr/LexerSharedInputState;
     133: getfield      #157                // Field antlr/LexerSharedInputState.guessing:I
     136: ifne          204
     139: aload_0
     140: invokevirtual #167                // Method newline:()V
     143: goto          204
     146: aload_0
     147: iconst_1
     148: invokevirtual #88                 // Method LA:(I)C
     151: bipush        13
     153: if_icmpne     179
     156: aload_0
     157: bipush        13
     159: invokevirtual #141                // Method match:(C)V
     162: aload_0
     163: getfield      #156                // Field inputState:Lantlr/LexerSharedInputState;
     166: getfield      #157                // Field antlr/LexerSharedInputState.guessing:I
     169: ifne          204
     172: aload_0
     173: invokevirtual #167                // Method newline:()V
     176: goto          204
     179: new           #120                // class antlr/NoViableAltForCharException
     182: dup
     183: aload_0
     184: iconst_1
     185: invokevirtual #88                 // Method LA:(I)C
     188: aload_0
     189: invokevirtual #121                // Method getFilename:()Ljava/lang/String;
     192: aload_0
     193: invokevirtual #122                // Method getLine:()I
     196: aload_0
     197: invokevirtual #123                // Method getColumn:()I
     200: invokespecial #124                // Method antlr/NoViableAltForCharException."<init>":(CLjava/lang/String;II)V
     203: athrow
     204: aload_0
     205: getfield      #156                // Field inputState:Lantlr/LexerSharedInputState;
     208: getfield      #157                // Field antlr/LexerSharedInputState.guessing:I
     211: ifne          216
     214: iconst_m1
     215: istore_2
     216: iload_1
     217: ifeq          265
     220: aload_3
     221: ifnonnull     265
     224: iload_2
     225: iconst_m1
     226: if_icmpeq     265
     229: aload_0
     230: iload_2
     231: invokevirtual #119                // Method makeToken:(I)Lantlr/Token;
     234: astore_3
     235: aload_3
     236: new           #142                // class java/lang/String
     239: dup
     240: aload_0
     241: getfield      #138                // Field text:Lantlr/ANTLRStringBuffer;
     244: invokevirtual #143                // Method antlr/ANTLRStringBuffer.getBuffer:()[C
     247: iload         4
     249: aload_0
     250: getfield      #138                // Field text:Lantlr/ANTLRStringBuffer;
     253: invokevirtual #139                // Method antlr/ANTLRStringBuffer.length:()I
     256: iload         4
     258: isub
     259: invokespecial #144                // Method java/lang/String."<init>":([CII)V
     262: invokevirtual #145                // Method antlr/Token.setText:(Ljava/lang/String;)V
     265: aload_0
     266: aload_3
     267: putfield      #90                 // Field _returnToken:Lantlr/Token;
     270: return

  public final void mNUM_INT(boolean) throws antlr.RecognitionException, antlr.CharStreamException, antlr.TokenStreamException;
    Code:
       0: aconst_null
       1: astore_3
       2: aload_0
       3: getfield      #138                // Field text:Lantlr/ANTLRStringBuffer;
       6: invokevirtual #139                // Method antlr/ANTLRStringBuffer.length:()I
       9: istore        4
      11: sipush        129
      14: istore_2
      15: aconst_null
      16: astore        6
      18: aconst_null
      19: astore        7
      21: aconst_null
      22: astore        8
      24: aconst_null
      25: astore        9
      27: iconst_0
      28: istore        10
      30: aconst_null
      31: astore        11
      33: aload_0
      34: iconst_1
      35: invokevirtual #88                 // Method LA:(I)C
      38: tableswitch   { // 46 to 57
                    46: 100
                    47: 1204
                    48: 353
                    49: 353
                    50: 353
                    51: 353
                    52: 353
                    53: 353
                    54: 353
                    55: 353
                    56: 353
                    57: 353
               default: 1204
          }
     100: aload_0
     101: bipush        46
     103: invokevirtual #141                // Method match:(C)V
     106: aload_0
     107: getfield      #156                // Field inputState:Lantlr/LexerSharedInputState;
     110: getfield      #157                // Field antlr/LexerSharedInputState.guessing:I
     113: ifne          119
     116: bipush        15
     118: istore_2
     119: aload_0
     120: iconst_1
     121: invokevirtual #88                 // Method LA:(I)C
     124: bipush        48
     126: if_icmplt     1229
     129: aload_0
     130: iconst_1
     131: invokevirtual #88                 // Method LA:(I)C
     134: bipush        57
     136: if_icmpgt     1229
     139: iconst_0
     140: istore        12
     142: aload_0
     143: iconst_1
     144: invokevirtual #88                 // Method LA:(I)C
     147: bipush        48
     149: if_icmplt     173
     152: aload_0
     153: iconst_1
     154: invokevirtual #88                 // Method LA:(I)C
     157: bipush        57
     159: if_icmpgt     173
     162: aload_0
     163: bipush        48
     165: bipush        57
     167: invokevirtual #160                // Method matchRange:(CC)V
     170: goto          207
     173: iload         12
     175: iconst_1
     176: if_icmplt     182
     179: goto          213
     182: new           #120                // class antlr/NoViableAltForCharException
     185: dup
     186: aload_0
     187: iconst_1
     188: invokevirtual #88                 // Method LA:(I)C
     191: aload_0
     192: invokevirtual #121                // Method getFilename:()Ljava/lang/String;
     195: aload_0
     196: invokevirtual #122                // Method getLine:()I
     199: aload_0
     200: invokevirtual #123                // Method getColumn:()I
     203: invokespecial #124                // Method antlr/NoViableAltForCharException."<init>":(CLjava/lang/String;II)V
     206: athrow
     207: iinc          12, 1
     210: goto          142
     213: aload_0
     214: iconst_1
     215: invokevirtual #88                 // Method LA:(I)C
     218: bipush        101
     220: if_icmpne     228
     223: aload_0
     224: iconst_0
     225: invokevirtual #168                // Method mEXPONENT:(Z)V
     228: aload_0
     229: iconst_1
     230: invokevirtual #88                 // Method LA:(I)C
     233: bipush        98
     235: if_icmpeq     258
     238: aload_0
     239: iconst_1
     240: invokevirtual #88                 // Method LA:(I)C
     243: bipush        100
     245: if_icmpeq     258
     248: aload_0
     249: iconst_1
     250: invokevirtual #88                 // Method LA:(I)C
     253: bipush        102
     255: if_icmpne     283
     258: aload_0
     259: iconst_1
     260: invokevirtual #169                // Method mFLOAT_SUFFIX:(Z)V
     263: aload_0
     264: getfield      #90                 // Field _returnToken:Lantlr/Token;
     267: astore        6
     269: aload_0
     270: getfield      #156                // Field inputState:Lantlr/LexerSharedInputState;
     273: getfield      #157                // Field antlr/LexerSharedInputState.guessing:I
     276: ifne          283
     279: aload         6
     281: astore        11
     283: aload_0
     284: getfield      #156                // Field inputState:Lantlr/LexerSharedInputState;
     287: getfield      #157                // Field antlr/LexerSharedInputState.guessing:I
     290: ifne          1229
     293: aload         11
     295: ifnull        320
     298: aload         11
     300: invokevirtual #170                // Method antlr/Token.getText:()Ljava/lang/String;
     303: invokevirtual #171                // Method java/lang/String.toUpperCase:()Ljava/lang/String;
     306: ldc           #172                // String BD
     308: invokevirtual #173                // Method java/lang/String.indexOf:(Ljava/lang/String;)I
     311: iflt          320
     314: bipush        102
     316: istore_2
     317: goto          1229
     320: aload         11
     322: ifnull        347
     325: aload         11
     327: invokevirtual #170                // Method antlr/Token.getText:()Ljava/lang/String;
     330: invokevirtual #171                // Method java/lang/String.toUpperCase:()Ljava/lang/String;
     333: bipush        70
     335: invokevirtual #174                // Method java/lang/String.indexOf:(I)I
     338: iflt          347
     341: bipush        99
     343: istore_2
     344: goto          1229
     347: bipush        98
     349: istore_2
     350: goto          1229
     353: aload_0
     354: iconst_1
     355: invokevirtual #88                 // Method LA:(I)C
     358: tableswitch   { // 48 to 57
                    48: 412
                    49: 674
                    50: 674
                    51: 674
                    52: 674
                    53: 674
                    54: 674
                    55: 674
                    56: 674
                    57: 674
               default: 729
          }
     412: aload_0
     413: bipush        48
     415: invokevirtual #141                // Method match:(C)V
     418: aload_0
     419: getfield      #156                // Field inputState:Lantlr/LexerSharedInputState;
     422: getfield      #157                // Field antlr/LexerSharedInputState.guessing:I
     425: ifne          431
     428: iconst_1
     429: istore        10
     431: aload_0
     432: iconst_1
     433: invokevirtual #88                 // Method LA:(I)C
     436: lookupswitch  { // 9
                    48: 594
                    49: 594
                    50: 594
                    51: 594
                    52: 594
                    53: 594
                    54: 594
                    55: 594
                   120: 520
               default: 671
          }
     520: aload_0
     521: bipush        120
     523: invokevirtual #141                // Method match:(C)V
     526: iconst_0
     527: istore        12
     529: getstatic     #175                // Field _tokenSet_3:Lantlr/collections/impl/BitSet;
     532: aload_0
     533: iconst_1
     534: invokevirtual #88                 // Method LA:(I)C
     537: invokevirtual #114                // Method antlr/collections/impl/BitSet.member:(I)Z
     540: ifeq          551
     543: aload_0
     544: iconst_0
     545: invokevirtual #176                // Method mHEX_DIGIT:(Z)V
     548: goto          585
     551: iload         12
     553: iconst_1
     554: if_icmplt     560
     557: goto          591
     560: new           #120                // class antlr/NoViableAltForCharException
     563: dup
     564: aload_0
     565: iconst_1
     566: invokevirtual #88                 // Method LA:(I)C
     569: aload_0
     570: invokevirtual #121                // Method getFilename:()Ljava/lang/String;
     573: aload_0
     574: invokevirtual #122                // Method getLine:()I
     577: aload_0
     578: invokevirtual #123                // Method getColumn:()I
     581: invokespecial #124                // Method antlr/NoViableAltForCharException."<init>":(CLjava/lang/String;II)V
     584: athrow
     585: iinc          12, 1
     588: goto          529
     591: goto          754
     594: iconst_0
     595: istore        12
     597: aload_0
     598: iconst_1
     599: invokevirtual #88                 // Method LA:(I)C
     602: bipush        48
     604: if_icmplt     628
     607: aload_0
     608: iconst_1
     609: invokevirtual #88                 // Method LA:(I)C
     612: bipush        55
     614: if_icmpgt     628
     617: aload_0
     618: bipush        48
     620: bipush        55
     622: invokevirtual #160                // Method matchRange:(CC)V
     625: goto          662
     628: iload         12
     630: iconst_1
     631: if_icmplt     637
     634: goto          668
     637: new           #120                // class antlr/NoViableAltForCharException
     640: dup
     641: aload_0
     642: iconst_1
     643: invokevirtual #88                 // Method LA:(I)C
     646: aload_0
     647: invokevirtual #121                // Method getFilename:()Ljava/lang/String;
     650: aload_0
     651: invokevirtual #122                // Method getLine:()I
     654: aload_0
     655: invokevirtual #123                // Method getColumn:()I
     658: invokespecial #124                // Method antlr/NoViableAltForCharException."<init>":(CLjava/lang/String;II)V
     661: athrow
     662: iinc          12, 1
     665: goto          597
     668: goto          754
     671: goto          754
     674: aload_0
     675: bipush        49
     677: bipush        57
     679: invokevirtual #160                // Method matchRange:(CC)V
     682: aload_0
     683: iconst_1
     684: invokevirtual #88                 // Method LA:(I)C
     687: bipush        48
     689: if_icmplt     713
     692: aload_0
     693: iconst_1
     694: invokevirtual #88                 // Method LA:(I)C
     697: bipush        57
     699: if_icmpgt     713
     702: aload_0
     703: bipush        48
     705: bipush        57
     707: invokevirtual #160                // Method matchRange:(CC)V
     710: goto          682
     713: aload_0
     714: getfield      #156                // Field inputState:Lantlr/LexerSharedInputState;
     717: getfield      #157                // Field antlr/LexerSharedInputState.guessing:I
     720: ifne          754
     723: iconst_1
     724: istore        10
     726: goto          754
     729: new           #120                // class antlr/NoViableAltForCharException
     732: dup
     733: aload_0
     734: iconst_1
     735: invokevirtual #88                 // Method LA:(I)C
     738: aload_0
     739: invokevirtual #121                // Method getFilename:()Ljava/lang/String;
     742: aload_0
     743: invokevirtual #122                // Method getLine:()I
     746: aload_0
     747: invokevirtual #123                // Method getColumn:()I
     750: invokespecial #124                // Method antlr/NoViableAltForCharException."<init>":(CLjava/lang/String;II)V
     753: athrow
     754: aload_0
     755: iconst_1
     756: invokevirtual #88                 // Method LA:(I)C
     759: bipush        98
     761: if_icmpne     802
     764: aload_0
     765: iconst_2
     766: invokevirtual #88                 // Method LA:(I)C
     769: bipush        105
     771: if_icmpne     802
     774: aload_0
     775: bipush        98
     777: invokevirtual #141                // Method match:(C)V
     780: aload_0
     781: bipush        105
     783: invokevirtual #141                // Method match:(C)V
     786: aload_0
     787: getfield      #156                // Field inputState:Lantlr/LexerSharedInputState;
     790: getfield      #157                // Field antlr/LexerSharedInputState.guessing:I
     793: ifne          1229
     796: bipush        101
     798: istore_2
     799: goto          1229
     802: aload_0
     803: iconst_1
     804: invokevirtual #88                 // Method LA:(I)C
     807: bipush        108
     809: if_icmpne     834
     812: aload_0
     813: bipush        108
     815: invokevirtual #141                // Method match:(C)V
     818: aload_0
     819: getfield      #156                // Field inputState:Lantlr/LexerSharedInputState;
     822: getfield      #157                // Field antlr/LexerSharedInputState.guessing:I
     825: ifne          1229
     828: bipush        100
     830: istore_2
     831: goto          1229
     834: getstatic     #177                // Field _tokenSet_4:Lantlr/collections/impl/BitSet;
     837: aload_0
     838: iconst_1
     839: invokevirtual #88                 // Method LA:(I)C
     842: invokevirtual #114                // Method antlr/collections/impl/BitSet.member:(I)Z
     845: ifeq          1229
     848: iload         10
     850: ifeq          1229
     853: aload_0
     854: iconst_1
     855: invokevirtual #88                 // Method LA:(I)C
     858: lookupswitch  { // 5
                    46: 908
                    98: 1081
                   100: 1081
                   101: 1018
                   102: 1081
               default: 1109
          }
     908: aload_0
     909: bipush        46
     911: invokevirtual #141                // Method match:(C)V
     914: aload_0
     915: iconst_1
     916: invokevirtual #88                 // Method LA:(I)C
     919: bipush        48
     921: if_icmplt     945
     924: aload_0
     925: iconst_1
     926: invokevirtual #88                 // Method LA:(I)C
     929: bipush        57
     931: if_icmpgt     945
     934: aload_0
     935: bipush        48
     937: bipush        57
     939: invokevirtual #160                // Method matchRange:(CC)V
     942: goto          914
     945: aload_0
     946: iconst_1
     947: invokevirtual #88                 // Method LA:(I)C
     950: bipush        101
     952: if_icmpne     960
     955: aload_0
     956: iconst_0
     957: invokevirtual #168                // Method mEXPONENT:(Z)V
     960: aload_0
     961: iconst_1
     962: invokevirtual #88                 // Method LA:(I)C
     965: bipush        98
     967: if_icmpeq     990
     970: aload_0
     971: iconst_1
     972: invokevirtual #88                 // Method LA:(I)C
     975: bipush        100
     977: if_icmpeq     990
     980: aload_0
     981: iconst_1
     982: invokevirtual #88                 // Method LA:(I)C
     985: bipush        102
     987: if_icmpne     1134
     990: aload_0
     991: iconst_1
     992: invokevirtual #169                // Method mFLOAT_SUFFIX:(Z)V
     995: aload_0
     996: getfield      #90                 // Field _returnToken:Lantlr/Token;
     999: astore        7
    1001: aload_0
    1002: getfield      #156                // Field inputState:Lantlr/LexerSharedInputState;
    1005: getfield      #157                // Field antlr/LexerSharedInputState.guessing:I
    1008: ifne          1134
    1011: aload         7
    1013: astore        11
    1015: goto          1134
    1018: aload_0
    1019: iconst_0
    1020: invokevirtual #168                // Method mEXPONENT:(Z)V
    1023: aload_0
    1024: iconst_1
    1025: invokevirtual #88                 // Method LA:(I)C
    1028: bipush        98
    1030: if_icmpeq     1053
    1033: aload_0
    1034: iconst_1
    1035: invokevirtual #88                 // Method LA:(I)C
    1038: bipush        100
    1040: if_icmpeq     1053
    1043: aload_0
    1044: iconst_1
    1045: invokevirtual #88                 // Method LA:(I)C
    1048: bipush        102
    1050: if_icmpne     1134
    1053: aload_0
    1054: iconst_1
    1055: invokevirtual #169                // Method mFLOAT_SUFFIX:(Z)V
    1058: aload_0
    1059: getfield      #90                 // Field _returnToken:Lantlr/Token;
    1062: astore        8
    1064: aload_0
    1065: getfield      #156                // Field inputState:Lantlr/LexerSharedInputState;
    1068: getfield      #157                // Field antlr/LexerSharedInputState.guessing:I
    1071: ifne          1134
    1074: aload         8
    1076: astore        11
    1078: goto          1134
    1081: aload_0
    1082: iconst_1
    1083: invokevirtual #169                // Method mFLOAT_SUFFIX:(Z)V
    1086: aload_0
    1087: getfield      #90                 // Field _returnToken:Lantlr/Token;
    1090: astore        9
    1092: aload_0
    1093: getfield      #156                // Field inputState:Lantlr/LexerSharedInputState;
    1096: getfield      #157                // Field antlr/LexerSharedInputState.guessing:I
    1099: ifne          1134
    1102: aload         9
    1104: astore        11
    1106: goto          1134
    1109: new           #120                // class antlr/NoViableAltForCharException
    1112: dup
    1113: aload_0
    1114: iconst_1
    1115: invokevirtual #88                 // Method LA:(I)C
    1118: aload_0
    1119: invokevirtual #121                // Method getFilename:()Ljava/lang/String;
    1122: aload_0
    1123: invokevirtual #122                // Method getLine:()I
    1126: aload_0
    1127: invokevirtual #123                // Method getColumn:()I
    1130: invokespecial #124                // Method antlr/NoViableAltForCharException."<init>":(CLjava/lang/String;II)V
    1133: athrow
    1134: aload_0
    1135: getfield      #156                // Field inputState:Lantlr/LexerSharedInputState;
    1138: getfield      #157                // Field antlr/LexerSharedInputState.guessing:I
    1141: ifne          1229
    1144: aload         11
    1146: ifnull        1171
    1149: aload         11
    1151: invokevirtual #170                // Method antlr/Token.getText:()Ljava/lang/String;
    1154: invokevirtual #171                // Method java/lang/String.toUpperCase:()Ljava/lang/String;
    1157: ldc           #172                // String BD
    1159: invokevirtual #173                // Method java/lang/String.indexOf:(Ljava/lang/String;)I
    1162: iflt          1171
    1165: bipush        102
    1167: istore_2
    1168: goto          1229
    1171: aload         11
    1173: ifnull        1198
    1176: aload         11
    1178: invokevirtual #170                // Method antlr/Token.getText:()Ljava/lang/String;
    1181: invokevirtual #171                // Method java/lang/String.toUpperCase:()Ljava/lang/String;
    1184: bipush        70
    1186: invokevirtual #174                // Method java/lang/String.indexOf:(I)I
    1189: iflt          1198
    1192: bipush        99
    1194: istore_2
    1195: goto          1229
    1198: bipush        98
    1200: istore_2
    1201: goto          1229
    1204: new           #120                // class antlr/NoViableAltForCharException
    1207: dup
    1208: aload_0
    1209: iconst_1
    1210: invokevirtual #88                 // Method LA:(I)C
    1213: aload_0
    1214: invokevirtual #121                // Method getFilename:()Ljava/lang/String;
    1217: aload_0
    1218: invokevirtual #122                // Method getLine:()I
    1221: aload_0
    1222: invokevirtual #123                // Method getColumn:()I
    1225: invokespecial #124                // Method antlr/NoViableAltForCharException."<init>":(CLjava/lang/String;II)V
    1228: athrow
    1229: iload_1
    1230: ifeq          1278
    1233: aload_3
    1234: ifnonnull     1278
    1237: iload_2
    1238: iconst_m1
    1239: if_icmpeq     1278
    1242: aload_0
    1243: iload_2
    1244: invokevirtual #119                // Method makeToken:(I)Lantlr/Token;
    1247: astore_3
    1248: aload_3
    1249: new           #142                // class java/lang/String
    1252: dup
    1253: aload_0
    1254: getfield      #138                // Field text:Lantlr/ANTLRStringBuffer;
    1257: invokevirtual #143                // Method antlr/ANTLRStringBuffer.getBuffer:()[C
    1260: iload         4
    1262: aload_0
    1263: getfield      #138                // Field text:Lantlr/ANTLRStringBuffer;
    1266: invokevirtual #139                // Method antlr/ANTLRStringBuffer.length:()I
    1269: iload         4
    1271: isub
    1272: invokespecial #144                // Method java/lang/String."<init>":([CII)V
    1275: invokevirtual #145                // Method antlr/Token.setText:(Ljava/lang/String;)V
    1278: aload_0
    1279: aload_3
    1280: putfield      #90                 // Field _returnToken:Lantlr/Token;
    1283: return

  protected final void mEXPONENT(boolean) throws antlr.RecognitionException, antlr.CharStreamException, antlr.TokenStreamException;
    Code:
       0: aconst_null
       1: astore_3
       2: aload_0
       3: getfield      #138                // Field text:Lantlr/ANTLRStringBuffer;
       6: invokevirtual #139                // Method antlr/ANTLRStringBuffer.length:()I
       9: istore        4
      11: sipush        135
      14: istore_2
      15: aload_0
      16: bipush        101
      18: invokevirtual #141                // Method match:(C)V
      21: aload_0
      22: iconst_1
      23: invokevirtual #88                 // Method LA:(I)C
      26: tableswitch   { // 43 to 57
                    43: 100
                    44: 121
                    45: 109
                    46: 121
                    47: 121
                    48: 118
                    49: 118
                    50: 118
                    51: 118
                    52: 118
                    53: 118
                    54: 118
                    55: 118
                    56: 118
                    57: 118
               default: 121
          }
     100: aload_0
     101: bipush        43
     103: invokevirtual #141                // Method match:(C)V
     106: goto          146
     109: aload_0
     110: bipush        45
     112: invokevirtual #141                // Method match:(C)V
     115: goto          146
     118: goto          146
     121: new           #120                // class antlr/NoViableAltForCharException
     124: dup
     125: aload_0
     126: iconst_1
     127: invokevirtual #88                 // Method LA:(I)C
     130: aload_0
     131: invokevirtual #121                // Method getFilename:()Ljava/lang/String;
     134: aload_0
     135: invokevirtual #122                // Method getLine:()I
     138: aload_0
     139: invokevirtual #123                // Method getColumn:()I
     142: invokespecial #124                // Method antlr/NoViableAltForCharException."<init>":(CLjava/lang/String;II)V
     145: athrow
     146: iconst_0
     147: istore        6
     149: aload_0
     150: iconst_1
     151: invokevirtual #88                 // Method LA:(I)C
     154: bipush        48
     156: if_icmplt     180
     159: aload_0
     160: iconst_1
     161: invokevirtual #88                 // Method LA:(I)C
     164: bipush        57
     166: if_icmpgt     180
     169: aload_0
     170: bipush        48
     172: bipush        57
     174: invokevirtual #160                // Method matchRange:(CC)V
     177: goto          214
     180: iload         6
     182: iconst_1
     183: if_icmplt     189
     186: goto          220
     189: new           #120                // class antlr/NoViableAltForCharException
     192: dup
     193: aload_0
     194: iconst_1
     195: invokevirtual #88                 // Method LA:(I)C
     198: aload_0
     199: invokevirtual #121                // Method getFilename:()Ljava/lang/String;
     202: aload_0
     203: invokevirtual #122                // Method getLine:()I
     206: aload_0
     207: invokevirtual #123                // Method getColumn:()I
     210: invokespecial #124                // Method antlr/NoViableAltForCharException."<init>":(CLjava/lang/String;II)V
     213: athrow
     214: iinc          6, 1
     217: goto          149
     220: iload_1
     221: ifeq          269
     224: aload_3
     225: ifnonnull     269
     228: iload_2
     229: iconst_m1
     230: if_icmpeq     269
     233: aload_0
     234: iload_2
     235: invokevirtual #119                // Method makeToken:(I)Lantlr/Token;
     238: astore_3
     239: aload_3
     240: new           #142                // class java/lang/String
     243: dup
     244: aload_0
     245: getfield      #138                // Field text:Lantlr/ANTLRStringBuffer;
     248: invokevirtual #143                // Method antlr/ANTLRStringBuffer.getBuffer:()[C
     251: iload         4
     253: aload_0
     254: getfield      #138                // Field text:Lantlr/ANTLRStringBuffer;
     257: invokevirtual #139                // Method antlr/ANTLRStringBuffer.length:()I
     260: iload         4
     262: isub
     263: invokespecial #144                // Method java/lang/String."<init>":([CII)V
     266: invokevirtual #145                // Method antlr/Token.setText:(Ljava/lang/String;)V
     269: aload_0
     270: aload_3
     271: putfield      #90                 // Field _returnToken:Lantlr/Token;
     274: return

  protected final void mFLOAT_SUFFIX(boolean) throws antlr.RecognitionException, antlr.CharStreamException, antlr.TokenStreamException;
    Code:
       0: aconst_null
       1: astore_3
       2: aload_0
       3: getfield      #138                // Field text:Lantlr/ANTLRStringBuffer;
       6: invokevirtual #139                // Method antlr/ANTLRStringBuffer.length:()I
       9: istore        4
      11: sipush        136
      14: istore_2
      15: aload_0
      16: iconst_1
      17: invokevirtual #88                 // Method LA:(I)C
      20: tableswitch   { // 98 to 102
                    98: 74
                    99: 89
                   100: 65
                   101: 89
                   102: 56
               default: 89
          }
      56: aload_0
      57: bipush        102
      59: invokevirtual #141                // Method match:(C)V
      62: goto          114
      65: aload_0
      66: bipush        100
      68: invokevirtual #141                // Method match:(C)V
      71: goto          114
      74: aload_0
      75: bipush        98
      77: invokevirtual #141                // Method match:(C)V
      80: aload_0
      81: bipush        100
      83: invokevirtual #141                // Method match:(C)V
      86: goto          114
      89: new           #120                // class antlr/NoViableAltForCharException
      92: dup
      93: aload_0
      94: iconst_1
      95: invokevirtual #88                 // Method LA:(I)C
      98: aload_0
      99: invokevirtual #121                // Method getFilename:()Ljava/lang/String;
     102: aload_0
     103: invokevirtual #122                // Method getLine:()I
     106: aload_0
     107: invokevirtual #123                // Method getColumn:()I
     110: invokespecial #124                // Method antlr/NoViableAltForCharException."<init>":(CLjava/lang/String;II)V
     113: athrow
     114: iload_1
     115: ifeq          163
     118: aload_3
     119: ifnonnull     163
     122: iload_2
     123: iconst_m1
     124: if_icmpeq     163
     127: aload_0
     128: iload_2
     129: invokevirtual #119                // Method makeToken:(I)Lantlr/Token;
     132: astore_3
     133: aload_3
     134: new           #142                // class java/lang/String
     137: dup
     138: aload_0
     139: getfield      #138                // Field text:Lantlr/ANTLRStringBuffer;
     142: invokevirtual #143                // Method antlr/ANTLRStringBuffer.getBuffer:()[C
     145: iload         4
     147: aload_0
     148: getfield      #138                // Field text:Lantlr/ANTLRStringBuffer;
     151: invokevirtual #139                // Method antlr/ANTLRStringBuffer.length:()I
     154: iload         4
     156: isub
     157: invokespecial #144                // Method java/lang/String."<init>":([CII)V
     160: invokevirtual #145                // Method antlr/Token.setText:(Ljava/lang/String;)V
     163: aload_0
     164: aload_3
     165: putfield      #90                 // Field _returnToken:Lantlr/Token;
     168: return

  protected final void mHEX_DIGIT(boolean) throws antlr.RecognitionException, antlr.CharStreamException, antlr.TokenStreamException;
    Code:
       0: aconst_null
       1: astore_3
       2: aload_0
       3: getfield      #138                // Field text:Lantlr/ANTLRStringBuffer;
       6: invokevirtual #139                // Method antlr/ANTLRStringBuffer.length:()I
       9: istore        4
      11: sipush        134
      14: istore_2
      15: aload_0
      16: iconst_1
      17: invokevirtual #88                 // Method LA:(I)C
      20: tableswitch   { // 48 to 102
                    48: 256
                    49: 256
                    50: 256
                    51: 256
                    52: 256
                    53: 256
                    54: 256
                    55: 256
                    56: 256
                    57: 256
                    58: 278
                    59: 278
                    60: 278
                    61: 278
                    62: 278
                    63: 278
                    64: 278
                    65: 278
                    66: 278
                    67: 278
                    68: 278
                    69: 278
                    70: 278
                    71: 278
                    72: 278
                    73: 278
                    74: 278
                    75: 278
                    76: 278
                    77: 278
                    78: 278
                    79: 278
                    80: 278
                    81: 278
                    82: 278
                    83: 278
                    84: 278
                    85: 278
                    86: 278
                    87: 278
                    88: 278
                    89: 278
                    90: 278
                    91: 278
                    92: 278
                    93: 278
                    94: 278
                    95: 278
                    96: 278
                    97: 267
                    98: 267
                    99: 267
                   100: 267
                   101: 267
                   102: 267
               default: 278
          }
     256: aload_0
     257: bipush        48
     259: bipush        57
     261: invokevirtual #160                // Method matchRange:(CC)V
     264: goto          303
     267: aload_0
     268: bipush        97
     270: bipush        102
     272: invokevirtual #160                // Method matchRange:(CC)V
     275: goto          303
     278: new           #120                // class antlr/NoViableAltForCharException
     281: dup
     282: aload_0
     283: iconst_1
     284: invokevirtual #88                 // Method LA:(I)C
     287: aload_0
     288: invokevirtual #121                // Method getFilename:()Ljava/lang/String;
     291: aload_0
     292: invokevirtual #122                // Method getLine:()I
     295: aload_0
     296: invokevirtual #123                // Method getColumn:()I
     299: invokespecial #124                // Method antlr/NoViableAltForCharException."<init>":(CLjava/lang/String;II)V
     302: athrow
     303: iload_1
     304: ifeq          352
     307: aload_3
     308: ifnonnull     352
     311: iload_2
     312: iconst_m1
     313: if_icmpeq     352
     316: aload_0
     317: iload_2
     318: invokevirtual #119                // Method makeToken:(I)Lantlr/Token;
     321: astore_3
     322: aload_3
     323: new           #142                // class java/lang/String
     326: dup
     327: aload_0
     328: getfield      #138                // Field text:Lantlr/ANTLRStringBuffer;
     331: invokevirtual #143                // Method antlr/ANTLRStringBuffer.getBuffer:()[C
     334: iload         4
     336: aload_0
     337: getfield      #138                // Field text:Lantlr/ANTLRStringBuffer;
     340: invokevirtual #139                // Method antlr/ANTLRStringBuffer.length:()I
     343: iload         4
     345: isub
     346: invokespecial #144                // Method java/lang/String."<init>":([CII)V
     349: invokevirtual #145                // Method antlr/Token.setText:(Ljava/lang/String;)V
     352: aload_0
     353: aload_3
     354: putfield      #90                 // Field _returnToken:Lantlr/Token;
     357: return

  private static final long[] mk_tokenSet_0();
    Code:
       0: sipush        3072
       3: newarray       long
       5: astore_0
       6: aload_0
       7: iconst_0
       8: ldc2_w        #178                // long 68719476736l
      11: lastore
      12: aload_0
      13: iconst_1
      14: ldc2_w        #180                // long 576460745860972544l
      17: lastore
      18: iconst_2
      19: istore_1
      20: iload_1
      21: sipush        1022
      24: if_icmpgt     39
      27: aload_0
      28: iload_1
      29: ldc2_w        #182                // long -1l
      32: lastore
      33: iinc          1, 1
      36: goto          20
      39: aload_0
      40: sipush        1023
      43: ldc2_w        #184                // long 9223372036854775807l
      46: lastore
      47: aload_0
      48: areturn

  private static final long[] mk_tokenSet_1();
    Code:
       0: sipush        3072
       3: newarray       long
       5: astore_0
       6: aload_0
       7: iconst_0
       8: ldc2_w        #186                // long 287948969894477824l
      11: lastore
      12: aload_0
      13: iconst_1
      14: ldc2_w        #180                // long 576460745860972544l
      17: lastore
      18: iconst_2
      19: istore_1
      20: iload_1
      21: sipush        1022
      24: if_icmpgt     39
      27: aload_0
      28: iload_1
      29: ldc2_w        #182                // long -1l
      32: lastore
      33: iinc          1, 1
      36: goto          20
      39: aload_0
      40: sipush        1023
      43: ldc2_w        #184                // long 9223372036854775807l
      46: lastore
      47: aload_0
      48: areturn

  private static final long[] mk_tokenSet_2();
    Code:
       0: sipush        2048
       3: newarray       long
       5: astore_0
       6: aload_0
       7: iconst_0
       8: ldc2_w        #188                // long -549755813889l
      11: lastore
      12: iconst_1
      13: istore_1
      14: iload_1
      15: sipush        1022
      18: if_icmpgt     33
      21: aload_0
      22: iload_1
      23: ldc2_w        #182                // long -1l
      26: lastore
      27: iinc          1, 1
      30: goto          14
      33: aload_0
      34: sipush        1023
      37: ldc2_w        #184                // long 9223372036854775807l
      40: lastore
      41: aload_0
      42: areturn

  private static final long[] mk_tokenSet_3();
    Code:
       0: sipush        1025
       3: newarray       long
       5: astore_0
       6: aload_0
       7: iconst_0
       8: ldc2_w        #190                // long 287948901175001088l
      11: lastore
      12: aload_0
      13: iconst_1
      14: ldc2_w        #192                // long 541165879296l
      17: lastore
      18: aload_0
      19: areturn

  private static final long[] mk_tokenSet_4();
    Code:
       0: sipush        1025
       3: newarray       long
       5: astore_0
       6: aload_0
       7: iconst_0
       8: ldc2_w        #194                // long 70368744177664l
      11: lastore
      12: aload_0
      13: iconst_1
      14: ldc2_w        #196                // long 498216206336l
      17: lastore
      18: aload_0
      19: areturn

  static {};
    Code:
       0: new           #198                // class antlr/collections/impl/BitSet
       3: dup
       4: invokestatic  #199                // Method mk_tokenSet_0:()[J
       7: invokespecial #200                // Method antlr/collections/impl/BitSet."<init>":([J)V
      10: putstatic     #113                // Field _tokenSet_0:Lantlr/collections/impl/BitSet;
      13: new           #198                // class antlr/collections/impl/BitSet
      16: dup
      17: invokestatic  #201                // Method mk_tokenSet_1:()[J
      20: invokespecial #200                // Method antlr/collections/impl/BitSet."<init>":([J)V
      23: putstatic     #154                // Field _tokenSet_1:Lantlr/collections/impl/BitSet;
      26: new           #198                // class antlr/collections/impl/BitSet
      29: dup
      30: invokestatic  #202                // Method mk_tokenSet_2:()[J
      33: invokespecial #200                // Method antlr/collections/impl/BitSet."<init>":([J)V
      36: putstatic     #165                // Field _tokenSet_2:Lantlr/collections/impl/BitSet;
      39: new           #198                // class antlr/collections/impl/BitSet
      42: dup
      43: invokestatic  #203                // Method mk_tokenSet_3:()[J
      46: invokespecial #200                // Method antlr/collections/impl/BitSet."<init>":([J)V
      49: putstatic     #175                // Field _tokenSet_3:Lantlr/collections/impl/BitSet;
      52: new           #198                // class antlr/collections/impl/BitSet
      55: dup
      56: invokestatic  #204                // Method mk_tokenSet_4:()[J
      59: invokespecial #200                // Method antlr/collections/impl/BitSet."<init>":([J)V
      62: putstatic     #177                // Field _tokenSet_4:Lantlr/collections/impl/BitSet;
      65: return
}
