Compiled from "DecisionTypeMarshaller.java"
public class org.opensaml.xacml.ctx.impl.DecisionTypeMarshaller extends org.opensaml.xacml.impl.AbstractXACMLObjectMarshaller {
  public org.opensaml.xacml.ctx.impl.DecisionTypeMarshaller();
    Code:
       0: aload_0
       1: invokespecial #1                  // Method org/opensaml/xacml/impl/AbstractXACMLObjectMarshaller."<init>":()V
       4: return

  protected void marshallElementContent(org.opensaml.core.xml.XMLObject, org.w3c.dom.Element) throws org.opensaml.core.xml.io.MarshallingException;
    Code:
       0: aload_1
       1: checkcast     #2                  // class org/opensaml/xacml/ctx/DecisionType
       4: astore_3
       5: aload_2
       6: aload_3
       7: invokeinterface #3,  1            // InterfaceMethod org/opensaml/xacml/ctx/DecisionType.getDecision:()Lorg/opensaml/xacml/ctx/DecisionType$DECISION;
      12: invokevirtual #4                  // Method org/opensaml/xacml/ctx/DecisionType$DECISION.toString:()Ljava/lang/String;
      15: invokestatic  #5                  // Method net/shibboleth/utilities/java/support/xml/ElementSupport.appendTextContent:(Lorg/w3c/dom/Element;Ljava/lang/String;)V
      18: return
}
