Compiled from "AbstractHTTP2ServerConnectionFactory.java"
public class org.eclipse.jetty.http2.server.AbstractHTTP2ServerConnectionFactory$HTTP2SessionContainer implements org.eclipse.jetty.io.Connection$Listener,org.eclipse.jetty.util.component.Graceful,org.eclipse.jetty.util.component.Dumpable {
  private final java.util.Set<org.eclipse.jetty.http2.internal.HTTP2Session> sessions;

  private final java.util.concurrent.atomic.AtomicReference<java.util.concurrent.CompletableFuture<java.lang.Void>> shutdown;

  public org.eclipse.jetty.http2.server.AbstractHTTP2ServerConnectionFactory$HTTP2SessionContainer();
    Code:
       0: aload_0
       1: invokespecial #1                  // Method java/lang/Object."<init>":()V
       4: aload_0
       5: invokestatic  #7                  // Method java/util/concurrent/ConcurrentHashMap.newKeySet:()Ljava/util/concurrent/ConcurrentHashMap$KeySetView;
       8: putfield      #13                 // Field sessions:Ljava/util/Set;
      11: aload_0
      12: new           #19                 // class java/util/concurrent/atomic/AtomicReference
      15: dup
      16: invokespecial #21                 // Method java/util/concurrent/atomic/AtomicReference."<init>":()V
      19: putfield      #22                 // Field shutdown:Ljava/util/concurrent/atomic/AtomicReference;
      22: return

  public void onOpened(org.eclipse.jetty.io.Connection);
    Code:
       0: aload_1
       1: checkcast     #26                 // class org/eclipse/jetty/http2/internal/HTTP2Connection
       4: invokevirtual #28                 // Method org/eclipse/jetty/http2/internal/HTTP2Connection.getSession:()Lorg/eclipse/jetty/http2/internal/HTTP2Session;
       7: astore_2
       8: aload_0
       9: getfield      #13                 // Field sessions:Ljava/util/Set;
      12: aload_2
      13: invokeinterface #32,  2           // InterfaceMethod java/util/Set.add:(Ljava/lang/Object;)Z
      18: pop
      19: aload_2
      20: invokestatic  #38                 // InterfaceMethod org/eclipse/jetty/util/component/LifeCycle.start:(Ljava/lang/Object;)V
      23: aload_0
      24: invokevirtual #44                 // Method isShutdown:()Z
      27: ifeq          36
      30: aload_0
      31: aload_2
      32: invokevirtual #48                 // Method shutdown:(Lorg/eclipse/jetty/http2/internal/HTTP2Session;)Ljava/util/concurrent/CompletableFuture;
      35: pop
      36: return

  public void onClosed(org.eclipse.jetty.io.Connection);
    Code:
       0: aload_1
       1: checkcast     #26                 // class org/eclipse/jetty/http2/internal/HTTP2Connection
       4: invokevirtual #28                 // Method org/eclipse/jetty/http2/internal/HTTP2Connection.getSession:()Lorg/eclipse/jetty/http2/internal/HTTP2Session;
       7: astore_2
       8: aload_0
       9: getfield      #13                 // Field sessions:Ljava/util/Set;
      12: aload_2
      13: invokeinterface #51,  2           // InterfaceMethod java/util/Set.remove:(Ljava/lang/Object;)Z
      18: ifeq          25
      21: aload_2
      22: invokestatic  #54                 // InterfaceMethod org/eclipse/jetty/util/component/LifeCycle.stop:(Ljava/lang/Object;)V
      25: return

  public java.util.Set<org.eclipse.jetty.http2.api.Session> getSessions();
    Code:
       0: new           #57                 // class java/util/HashSet
       3: dup
       4: aload_0
       5: getfield      #13                 // Field sessions:Ljava/util/Set;
       8: invokespecial #59                 // Method java/util/HashSet."<init>":(Ljava/util/Collection;)V
      11: areturn

  public int getSize();
    Code:
       0: aload_0
       1: getfield      #13                 // Field sessions:Ljava/util/Set;
       4: invokeinterface #62,  1           // InterfaceMethod java/util/Set.size:()I
       9: ireturn

  public java.util.concurrent.CompletableFuture<java.lang.Void> shutdown();
    Code:
       0: new           #66                 // class java/util/concurrent/CompletableFuture
       3: dup
       4: invokespecial #68                 // Method java/util/concurrent/CompletableFuture."<init>":()V
       7: astore_1
       8: aload_0
       9: getfield      #22                 // Field shutdown:Ljava/util/concurrent/atomic/AtomicReference;
      12: aconst_null
      13: aload_1
      14: invokevirtual #69                 // Method java/util/concurrent/atomic/AtomicReference.compareAndSet:(Ljava/lang/Object;Ljava/lang/Object;)Z
      17: ifeq          68
      20: aload_0
      21: getfield      #13                 // Field sessions:Ljava/util/Set;
      24: invokeinterface #73,  1           // InterfaceMethod java/util/Set.stream:()Ljava/util/stream/Stream;
      29: aload_0
      30: invokedynamic #77,  0             // InvokeDynamic #0:apply:(Lorg/eclipse/jetty/http2/server/AbstractHTTP2ServerConnectionFactory$HTTP2SessionContainer;)Ljava/util/function/Function;
      35: invokeinterface #81,  2           // InterfaceMethod java/util/stream/Stream.map:(Ljava/util/function/Function;)Ljava/util/stream/Stream;
      40: invokedynamic #87,  0             // InvokeDynamic #1:apply:()Ljava/util/function/IntFunction;
      45: invokeinterface #90,  2           // InterfaceMethod java/util/stream/Stream.toArray:(Ljava/util/function/IntFunction;)[Ljava/lang/Object;
      50: checkcast     #94                 // class "[Ljava/util/concurrent/CompletableFuture;"
      53: invokestatic  #96                 // Method java/util/concurrent/CompletableFuture.allOf:([Ljava/util/concurrent/CompletableFuture;)Ljava/util/concurrent/CompletableFuture;
      56: aload_1
      57: invokedynamic #100,  0            // InvokeDynamic #2:accept:(Ljava/util/concurrent/CompletableFuture;)Ljava/util/function/BiConsumer;
      62: invokevirtual #104                // Method java/util/concurrent/CompletableFuture.whenComplete:(Ljava/util/function/BiConsumer;)Ljava/util/concurrent/CompletableFuture;
      65: pop
      66: aload_1
      67: areturn
      68: aload_0
      69: getfield      #22                 // Field shutdown:Ljava/util/concurrent/atomic/AtomicReference;
      72: invokevirtual #108                // Method java/util/concurrent/atomic/AtomicReference.get:()Ljava/lang/Object;
      75: checkcast     #66                 // class java/util/concurrent/CompletableFuture
      78: areturn

  public boolean isShutdown();
    Code:
       0: aload_0
       1: getfield      #22                 // Field shutdown:Ljava/util/concurrent/atomic/AtomicReference;
       4: invokevirtual #108                // Method java/util/concurrent/atomic/AtomicReference.get:()Ljava/lang/Object;
       7: ifnull        14
      10: iconst_1
      11: goto          15
      14: iconst_0
      15: ireturn

  private java.util.concurrent.CompletableFuture<java.lang.Void> shutdown(org.eclipse.jetty.http2.internal.HTTP2Session);
    Code:
       0: aload_1
       1: invokevirtual #112                // Method org/eclipse/jetty/http2/internal/HTTP2Session.shutdown:()Ljava/util/concurrent/CompletableFuture;
       4: areturn

  public java.lang.String dump();
    Code:
       0: aload_0
       1: invokestatic  #117                // InterfaceMethod org/eclipse/jetty/util/component/Dumpable.dump:(Lorg/eclipse/jetty/util/component/Dumpable;)Ljava/lang/String;
       4: areturn

  public void dump(java.lang.Appendable, java.lang.String) throws java.io.IOException;
    Code:
       0: aload_1
       1: aload_2
       2: aload_0
       3: iconst_1
       4: anewarray     #2                  // class java/lang/Object
       7: dup
       8: iconst_0
       9: aload_0
      10: getfield      #13                 // Field sessions:Ljava/util/Set;
      13: aastore
      14: invokestatic  #123                // InterfaceMethod org/eclipse/jetty/util/component/Dumpable.dumpObjects:(Ljava/lang/Appendable;Ljava/lang/String;Ljava/lang/Object;[Ljava/lang/Object;)V
      17: return

  public java.lang.String toString();
    Code:
       0: ldc           #127                // String %s@%x[size=%d]
       2: iconst_3
       3: anewarray     #2                  // class java/lang/Object
       6: dup
       7: iconst_0
       8: aload_0
       9: invokevirtual #129                // Method java/lang/Object.getClass:()Ljava/lang/Class;
      12: invokevirtual #133                // Method java/lang/Class.getSimpleName:()Ljava/lang/String;
      15: aastore
      16: dup
      17: iconst_1
      18: aload_0
      19: invokevirtual #139                // Method java/lang/Object.hashCode:()I
      22: invokestatic  #142                // Method java/lang/Integer.valueOf:(I)Ljava/lang/Integer;
      25: aastore
      26: dup
      27: iconst_2
      28: aload_0
      29: invokevirtual #148                // Method getSize:()I
      32: invokestatic  #142                // Method java/lang/Integer.valueOf:(I)Ljava/lang/Integer;
      35: aastore
      36: invokestatic  #151                // Method java/lang/String.format:(Ljava/lang/String;[Ljava/lang/Object;)Ljava/lang/String;
      39: areturn

  private static void lambda$shutdown$1(java.util.concurrent.CompletableFuture, java.lang.Void, java.lang.Throwable);
    Code:
       0: aload_2
       1: ifnonnull     13
       4: aload_0
       5: aload_1
       6: invokevirtual #157                // Method java/util/concurrent/CompletableFuture.complete:(Ljava/lang/Object;)Z
       9: pop
      10: goto          19
      13: aload_0
      14: aload_2
      15: invokevirtual #160                // Method java/util/concurrent/CompletableFuture.completeExceptionally:(Ljava/lang/Throwable;)Z
      18: pop
      19: return

  private static java.util.concurrent.CompletableFuture[] lambda$shutdown$0(int);
    Code:
       0: iload_0
       1: anewarray     #66                 // class java/util/concurrent/CompletableFuture
       4: areturn
}
