Compiled from "ScanPathToken.java"
final class com.jayway.jsonpath.internal.path.ScanPathToken$PropertyPathTokenPredicate implements com.jayway.jsonpath.internal.path.ScanPathToken$Predicate {
  private final com.jayway.jsonpath.internal.path.EvaluationContextImpl ctx;

  private com.jayway.jsonpath.internal.path.PropertyPathToken propertyPathToken;

  private com.jayway.jsonpath.internal.path.ScanPathToken$PropertyPathTokenPredicate(com.jayway.jsonpath.internal.path.PathToken, com.jayway.jsonpath.internal.path.EvaluationContextImpl);
    Code:
       0: aload_0
       1: invokespecial #2                  // Method java/lang/Object."<init>":()V
       4: aload_0
       5: aload_2
       6: putfield      #3                  // Field ctx:Lcom/jayway/jsonpath/internal/path/EvaluationContextImpl;
       9: aload_0
      10: aload_1
      11: checkcast     #4                  // class com/jayway/jsonpath/internal/path/PropertyPathToken
      14: putfield      #5                  // Field propertyPathToken:Lcom/jayway/jsonpath/internal/path/PropertyPathToken;
      17: return

  public boolean matches(java.lang.Object);
    Code:
       0: aload_0
       1: getfield      #3                  // Field ctx:Lcom/jayway/jsonpath/internal/path/EvaluationContextImpl;
       4: invokevirtual #6                  // Method com/jayway/jsonpath/internal/path/EvaluationContextImpl.jsonProvider:()Lcom/jayway/jsonpath/spi/json/JsonProvider;
       7: aload_1
       8: invokeinterface #7,  2            // InterfaceMethod com/jayway/jsonpath/spi/json/JsonProvider.isMap:(Ljava/lang/Object;)Z
      13: ifne          18
      16: iconst_0
      17: ireturn
      18: aload_0
      19: getfield      #5                  // Field propertyPathToken:Lcom/jayway/jsonpath/internal/path/PropertyPathToken;
      22: invokevirtual #8                  // Method com/jayway/jsonpath/internal/path/PropertyPathToken.isTokenDefinite:()Z
      25: ifne          30
      28: iconst_1
      29: ireturn
      30: aload_0
      31: getfield      #5                  // Field propertyPathToken:Lcom/jayway/jsonpath/internal/path/PropertyPathToken;
      34: invokevirtual #9                  // Method com/jayway/jsonpath/internal/path/PropertyPathToken.isLeaf:()Z
      37: ifeq          60
      40: aload_0
      41: getfield      #3                  // Field ctx:Lcom/jayway/jsonpath/internal/path/EvaluationContextImpl;
      44: invokevirtual #10                 // Method com/jayway/jsonpath/internal/path/EvaluationContextImpl.options:()Ljava/util/Set;
      47: getstatic     #11                 // Field com/jayway/jsonpath/Option.DEFAULT_PATH_LEAF_TO_NULL:Lcom/jayway/jsonpath/Option;
      50: invokeinterface #12,  2           // InterfaceMethod java/util/Set.contains:(Ljava/lang/Object;)Z
      55: ifeq          60
      58: iconst_1
      59: ireturn
      60: aload_0
      61: getfield      #3                  // Field ctx:Lcom/jayway/jsonpath/internal/path/EvaluationContextImpl;
      64: invokevirtual #6                  // Method com/jayway/jsonpath/internal/path/EvaluationContextImpl.jsonProvider:()Lcom/jayway/jsonpath/spi/json/JsonProvider;
      67: aload_1
      68: invokeinterface #13,  2           // InterfaceMethod com/jayway/jsonpath/spi/json/JsonProvider.getPropertyKeys:(Ljava/lang/Object;)Ljava/util/Collection;
      73: astore_2
      74: aload_2
      75: aload_0
      76: getfield      #5                  // Field propertyPathToken:Lcom/jayway/jsonpath/internal/path/PropertyPathToken;
      79: invokevirtual #14                 // Method com/jayway/jsonpath/internal/path/PropertyPathToken.getProperties:()Ljava/util/List;
      82: invokeinterface #15,  2           // InterfaceMethod java/util/Collection.containsAll:(Ljava/util/Collection;)Z
      87: ireturn

  com.jayway.jsonpath.internal.path.ScanPathToken$PropertyPathTokenPredicate(com.jayway.jsonpath.internal.path.PathToken, com.jayway.jsonpath.internal.path.EvaluationContextImpl, com.jayway.jsonpath.internal.path.ScanPathToken$1);
    Code:
       0: aload_0
       1: aload_1
       2: aload_2
       3: invokespecial #1                  // Method "<init>":(Lcom/jayway/jsonpath/internal/path/PathToken;Lcom/jayway/jsonpath/internal/path/EvaluationContextImpl;)V
       6: return
}
