Compiled from "SharedProcessor.java"
public class io.dekorate.deps.kubernetes.client.informers.cache.SharedProcessor<T> {
  private java.util.concurrent.locks.ReadWriteLock lock;

  private java.util.List<io.dekorate.deps.kubernetes.client.informers.cache.ProcessorListener<T>> listeners;

  private java.util.List<io.dekorate.deps.kubernetes.client.informers.cache.ProcessorListener<T>> syncingListeners;

  private java.util.concurrent.ExecutorService executorService;

  public io.dekorate.deps.kubernetes.client.informers.cache.SharedProcessor();
    Code:
       0: aload_0
       1: invokestatic  #27                 // Method java/util/concurrent/Executors.newCachedThreadPool:()Ljava/util/concurrent/ExecutorService;
       4: invokespecial #30                 // Method "<init>":(Ljava/util/concurrent/ExecutorService;)V
       7: return

  public io.dekorate.deps.kubernetes.client.informers.cache.SharedProcessor(java.util.concurrent.ExecutorService);
    Code:
       0: aload_0
       1: invokespecial #35                 // Method java/lang/Object."<init>":()V
       4: aload_0
       5: new           #37                 // class java/util/concurrent/locks/ReentrantReadWriteLock
       8: dup
       9: invokespecial #38                 // Method java/util/concurrent/locks/ReentrantReadWriteLock."<init>":()V
      12: putfield      #40                 // Field lock:Ljava/util/concurrent/locks/ReadWriteLock;
      15: aload_0
      16: new           #42                 // class java/util/ArrayList
      19: dup
      20: invokespecial #43                 // Method java/util/ArrayList."<init>":()V
      23: putfield      #45                 // Field listeners:Ljava/util/List;
      26: aload_0
      27: new           #42                 // class java/util/ArrayList
      30: dup
      31: invokespecial #43                 // Method java/util/ArrayList."<init>":()V
      34: putfield      #47                 // Field syncingListeners:Ljava/util/List;
      37: aload_0
      38: aload_1
      39: putfield      #49                 // Field executorService:Ljava/util/concurrent/ExecutorService;
      42: return

  public void addAndStartListener(io.dekorate.deps.kubernetes.client.informers.cache.ProcessorListener<T>);
    Code:
       0: aload_0
       1: getfield      #40                 // Field lock:Ljava/util/concurrent/locks/ReadWriteLock;
       4: invokeinterface #59,  1           // InterfaceMethod java/util/concurrent/locks/ReadWriteLock.writeLock:()Ljava/util/concurrent/locks/Lock;
       9: invokeinterface #63,  1           // InterfaceMethod java/util/concurrent/locks/Lock.lock:()V
      14: aload_0
      15: aload_1
      16: invokespecial #66                 // Method addListenerLocked:(Lio/dekorate/deps/kubernetes/client/informers/cache/ProcessorListener;)V
      19: aload_0
      20: getfield      #49                 // Field executorService:Ljava/util/concurrent/ExecutorService;
      23: aload_1
      24: invokeinterface #72,  2           // InterfaceMethod java/util/concurrent/ExecutorService.execute:(Ljava/lang/Runnable;)V
      29: aload_0
      30: getfield      #40                 // Field lock:Ljava/util/concurrent/locks/ReadWriteLock;
      33: invokeinterface #59,  1           // InterfaceMethod java/util/concurrent/locks/ReadWriteLock.writeLock:()Ljava/util/concurrent/locks/Lock;
      38: invokeinterface #75,  1           // InterfaceMethod java/util/concurrent/locks/Lock.unlock:()V
      43: goto          63
      46: astore_2
      47: aload_0
      48: getfield      #40                 // Field lock:Ljava/util/concurrent/locks/ReadWriteLock;
      51: invokeinterface #59,  1           // InterfaceMethod java/util/concurrent/locks/ReadWriteLock.writeLock:()Ljava/util/concurrent/locks/Lock;
      56: invokeinterface #75,  1           // InterfaceMethod java/util/concurrent/locks/Lock.unlock:()V
      61: aload_2
      62: athrow
      63: return
    Exception table:
       from    to  target type
          14    29    46   any

  public void addListener(io.dekorate.deps.kubernetes.client.informers.cache.ProcessorListener<T>);
    Code:
       0: aload_0
       1: getfield      #40                 // Field lock:Ljava/util/concurrent/locks/ReadWriteLock;
       4: invokeinterface #59,  1           // InterfaceMethod java/util/concurrent/locks/ReadWriteLock.writeLock:()Ljava/util/concurrent/locks/Lock;
       9: invokeinterface #63,  1           // InterfaceMethod java/util/concurrent/locks/Lock.lock:()V
      14: aload_0
      15: aload_1
      16: invokespecial #66                 // Method addListenerLocked:(Lio/dekorate/deps/kubernetes/client/informers/cache/ProcessorListener;)V
      19: aload_0
      20: getfield      #40                 // Field lock:Ljava/util/concurrent/locks/ReadWriteLock;
      23: invokeinterface #59,  1           // InterfaceMethod java/util/concurrent/locks/ReadWriteLock.writeLock:()Ljava/util/concurrent/locks/Lock;
      28: invokeinterface #75,  1           // InterfaceMethod java/util/concurrent/locks/Lock.unlock:()V
      33: goto          53
      36: astore_2
      37: aload_0
      38: getfield      #40                 // Field lock:Ljava/util/concurrent/locks/ReadWriteLock;
      41: invokeinterface #59,  1           // InterfaceMethod java/util/concurrent/locks/ReadWriteLock.writeLock:()Ljava/util/concurrent/locks/Lock;
      46: invokeinterface #75,  1           // InterfaceMethod java/util/concurrent/locks/Lock.unlock:()V
      51: aload_2
      52: athrow
      53: return
    Exception table:
       from    to  target type
          14    19    36   any

  private void addListenerLocked(io.dekorate.deps.kubernetes.client.informers.cache.ProcessorListener<T>);
    Code:
       0: aload_0
       1: getfield      #45                 // Field listeners:Ljava/util/List;
       4: aload_1
       5: invokeinterface #87,  2           // InterfaceMethod java/util/List.add:(Ljava/lang/Object;)Z
      10: pop
      11: aload_0
      12: getfield      #47                 // Field syncingListeners:Ljava/util/List;
      15: aload_1
      16: invokeinterface #87,  2           // InterfaceMethod java/util/List.add:(Ljava/lang/Object;)Z
      21: pop
      22: return

  public void run();
    Code:
       0: aload_0
       1: getfield      #40                 // Field lock:Ljava/util/concurrent/locks/ReadWriteLock;
       4: invokeinterface #91,  1           // InterfaceMethod java/util/concurrent/locks/ReadWriteLock.readLock:()Ljava/util/concurrent/locks/Lock;
       9: invokeinterface #63,  1           // InterfaceMethod java/util/concurrent/locks/Lock.lock:()V
      14: aload_0
      15: getfield      #45                 // Field listeners:Ljava/util/List;
      18: ifnull        33
      21: aload_0
      22: getfield      #45                 // Field listeners:Ljava/util/List;
      25: invokeinterface #95,  1           // InterfaceMethod java/util/List.isEmpty:()Z
      30: ifeq          48
      33: aload_0
      34: getfield      #40                 // Field lock:Ljava/util/concurrent/locks/ReadWriteLock;
      37: invokeinterface #91,  1           // InterfaceMethod java/util/concurrent/locks/ReadWriteLock.readLock:()Ljava/util/concurrent/locks/Lock;
      42: invokeinterface #75,  1           // InterfaceMethod java/util/concurrent/locks/Lock.unlock:()V
      47: return
      48: aload_0
      49: getfield      #45                 // Field listeners:Ljava/util/List;
      52: invokeinterface #99,  1           // InterfaceMethod java/util/List.iterator:()Ljava/util/Iterator;
      57: astore_1
      58: aload_1
      59: invokeinterface #104,  1          // InterfaceMethod java/util/Iterator.hasNext:()Z
      64: ifeq          91
      67: aload_1
      68: invokeinterface #108,  1          // InterfaceMethod java/util/Iterator.next:()Ljava/lang/Object;
      73: checkcast     #10                 // class io/dekorate/deps/kubernetes/client/informers/cache/ProcessorListener
      76: astore_2
      77: aload_0
      78: getfield      #49                 // Field executorService:Ljava/util/concurrent/ExecutorService;
      81: aload_2
      82: invokeinterface #112,  2          // InterfaceMethod java/util/concurrent/ExecutorService.submit:(Ljava/lang/Runnable;)Ljava/util/concurrent/Future;
      87: pop
      88: goto          58
      91: aload_0
      92: getfield      #40                 // Field lock:Ljava/util/concurrent/locks/ReadWriteLock;
      95: invokeinterface #91,  1           // InterfaceMethod java/util/concurrent/locks/ReadWriteLock.readLock:()Ljava/util/concurrent/locks/Lock;
     100: invokeinterface #75,  1           // InterfaceMethod java/util/concurrent/locks/Lock.unlock:()V
     105: goto          125
     108: astore_3
     109: aload_0
     110: getfield      #40                 // Field lock:Ljava/util/concurrent/locks/ReadWriteLock;
     113: invokeinterface #91,  1           // InterfaceMethod java/util/concurrent/locks/ReadWriteLock.readLock:()Ljava/util/concurrent/locks/Lock;
     118: invokeinterface #75,  1           // InterfaceMethod java/util/concurrent/locks/Lock.unlock:()V
     123: aload_3
     124: athrow
     125: return
    Exception table:
       from    to  target type
          14    33   108   any
          48    91   108   any

  public void distribute(io.dekorate.deps.kubernetes.client.informers.cache.ProcessorListener$Notification<T>, boolean);
    Code:
       0: aload_0
       1: getfield      #40                 // Field lock:Ljava/util/concurrent/locks/ReadWriteLock;
       4: invokeinterface #91,  1           // InterfaceMethod java/util/concurrent/locks/ReadWriteLock.readLock:()Ljava/util/concurrent/locks/Lock;
       9: invokeinterface #63,  1           // InterfaceMethod java/util/concurrent/locks/Lock.lock:()V
      14: iload_2
      15: ifeq          60
      18: aload_0
      19: getfield      #47                 // Field syncingListeners:Ljava/util/List;
      22: invokeinterface #99,  1           // InterfaceMethod java/util/List.iterator:()Ljava/util/Iterator;
      27: astore_3
      28: aload_3
      29: invokeinterface #104,  1          // InterfaceMethod java/util/Iterator.hasNext:()Z
      34: ifeq          57
      37: aload_3
      38: invokeinterface #108,  1          // InterfaceMethod java/util/Iterator.next:()Ljava/lang/Object;
      43: checkcast     #10                 // class io/dekorate/deps/kubernetes/client/informers/cache/ProcessorListener
      46: astore        4
      48: aload         4
      50: aload_1
      51: invokevirtual #119                // Method io/dekorate/deps/kubernetes/client/informers/cache/ProcessorListener.add:(Lio/dekorate/deps/kubernetes/client/informers/cache/ProcessorListener$Notification;)V
      54: goto          28
      57: goto          99
      60: aload_0
      61: getfield      #45                 // Field listeners:Ljava/util/List;
      64: invokeinterface #99,  1           // InterfaceMethod java/util/List.iterator:()Ljava/util/Iterator;
      69: astore_3
      70: aload_3
      71: invokeinterface #104,  1          // InterfaceMethod java/util/Iterator.hasNext:()Z
      76: ifeq          99
      79: aload_3
      80: invokeinterface #108,  1          // InterfaceMethod java/util/Iterator.next:()Ljava/lang/Object;
      85: checkcast     #10                 // class io/dekorate/deps/kubernetes/client/informers/cache/ProcessorListener
      88: astore        4
      90: aload         4
      92: aload_1
      93: invokevirtual #119                // Method io/dekorate/deps/kubernetes/client/informers/cache/ProcessorListener.add:(Lio/dekorate/deps/kubernetes/client/informers/cache/ProcessorListener$Notification;)V
      96: goto          70
      99: aload_0
     100: getfield      #40                 // Field lock:Ljava/util/concurrent/locks/ReadWriteLock;
     103: invokeinterface #91,  1           // InterfaceMethod java/util/concurrent/locks/ReadWriteLock.readLock:()Ljava/util/concurrent/locks/Lock;
     108: invokeinterface #75,  1           // InterfaceMethod java/util/concurrent/locks/Lock.unlock:()V
     113: goto          135
     116: astore        5
     118: aload_0
     119: getfield      #40                 // Field lock:Ljava/util/concurrent/locks/ReadWriteLock;
     122: invokeinterface #91,  1           // InterfaceMethod java/util/concurrent/locks/ReadWriteLock.readLock:()Ljava/util/concurrent/locks/Lock;
     127: invokeinterface #75,  1           // InterfaceMethod java/util/concurrent/locks/Lock.unlock:()V
     132: aload         5
     134: athrow
     135: return
    Exception table:
       from    to  target type
          14    99   116   any
         116   118   116   any

  public boolean shouldResync();
    Code:
       0: aload_0
       1: getfield      #40                 // Field lock:Ljava/util/concurrent/locks/ReadWriteLock;
       4: invokeinterface #59,  1           // InterfaceMethod java/util/concurrent/locks/ReadWriteLock.writeLock:()Ljava/util/concurrent/locks/Lock;
       9: invokeinterface #63,  1           // InterfaceMethod java/util/concurrent/locks/Lock.lock:()V
      14: iconst_0
      15: istore_1
      16: aload_0
      17: new           #42                 // class java/util/ArrayList
      20: dup
      21: invokespecial #43                 // Method java/util/ArrayList."<init>":()V
      24: putfield      #47                 // Field syncingListeners:Ljava/util/List;
      27: invokestatic  #131                // Method java/time/ZonedDateTime.now:()Ljava/time/ZonedDateTime;
      30: astore_2
      31: aload_0
      32: getfield      #45                 // Field listeners:Ljava/util/List;
      35: invokeinterface #99,  1           // InterfaceMethod java/util/List.iterator:()Ljava/util/Iterator;
      40: astore_3
      41: aload_3
      42: invokeinterface #104,  1          // InterfaceMethod java/util/Iterator.hasNext:()Z
      47: ifeq          93
      50: aload_3
      51: invokeinterface #108,  1          // InterfaceMethod java/util/Iterator.next:()Ljava/lang/Object;
      56: checkcast     #10                 // class io/dekorate/deps/kubernetes/client/informers/cache/ProcessorListener
      59: astore        4
      61: aload         4
      63: aload_2
      64: invokevirtual #134                // Method io/dekorate/deps/kubernetes/client/informers/cache/ProcessorListener.shouldResync:(Ljava/time/ZonedDateTime;)Z
      67: ifeq          90
      70: iconst_1
      71: istore_1
      72: aload_0
      73: getfield      #47                 // Field syncingListeners:Ljava/util/List;
      76: aload         4
      78: invokeinterface #87,  2           // InterfaceMethod java/util/List.add:(Ljava/lang/Object;)Z
      83: pop
      84: aload         4
      86: aload_2
      87: invokevirtual #138                // Method io/dekorate/deps/kubernetes/client/informers/cache/ProcessorListener.determineNextResync:(Ljava/time/ZonedDateTime;)V
      90: goto          41
      93: aload_0
      94: getfield      #40                 // Field lock:Ljava/util/concurrent/locks/ReadWriteLock;
      97: invokeinterface #59,  1           // InterfaceMethod java/util/concurrent/locks/ReadWriteLock.writeLock:()Ljava/util/concurrent/locks/Lock;
     102: invokeinterface #75,  1           // InterfaceMethod java/util/concurrent/locks/Lock.unlock:()V
     107: goto          129
     110: astore        5
     112: aload_0
     113: getfield      #40                 // Field lock:Ljava/util/concurrent/locks/ReadWriteLock;
     116: invokeinterface #59,  1           // InterfaceMethod java/util/concurrent/locks/ReadWriteLock.writeLock:()Ljava/util/concurrent/locks/Lock;
     121: invokeinterface #75,  1           // InterfaceMethod java/util/concurrent/locks/Lock.unlock:()V
     126: aload         5
     128: athrow
     129: iload_1
     130: ireturn
    Exception table:
       from    to  target type
          16    93   110   any
         110   112   110   any

  public void stop();
    Code:
       0: aload_0
       1: getfield      #40                 // Field lock:Ljava/util/concurrent/locks/ReadWriteLock;
       4: invokeinterface #59,  1           // InterfaceMethod java/util/concurrent/locks/ReadWriteLock.writeLock:()Ljava/util/concurrent/locks/Lock;
       9: invokeinterface #63,  1           // InterfaceMethod java/util/concurrent/locks/Lock.lock:()V
      14: aload_0
      15: aconst_null
      16: putfield      #45                 // Field listeners:Ljava/util/List;
      19: aload_0
      20: getfield      #40                 // Field lock:Ljava/util/concurrent/locks/ReadWriteLock;
      23: invokeinterface #59,  1           // InterfaceMethod java/util/concurrent/locks/ReadWriteLock.writeLock:()Ljava/util/concurrent/locks/Lock;
      28: invokeinterface #75,  1           // InterfaceMethod java/util/concurrent/locks/Lock.unlock:()V
      33: goto          53
      36: astore_1
      37: aload_0
      38: getfield      #40                 // Field lock:Ljava/util/concurrent/locks/ReadWriteLock;
      41: invokeinterface #59,  1           // InterfaceMethod java/util/concurrent/locks/ReadWriteLock.writeLock:()Ljava/util/concurrent/locks/Lock;
      46: invokeinterface #75,  1           // InterfaceMethod java/util/concurrent/locks/Lock.unlock:()V
      51: aload_1
      52: athrow
      53: aload_0
      54: getfield      #49                 // Field executorService:Ljava/util/concurrent/ExecutorService;
      57: invokeinterface #145,  1          // InterfaceMethod java/util/concurrent/ExecutorService.shutdownNow:()Ljava/util/List;
      62: pop
      63: return
    Exception table:
       from    to  target type
          14    19    36   any
}
