Compiled from "INNValidator.java"
public class org.hibernate.validator.internal.constraintvalidators.hv.ru.INNValidator implements jakarta.validation.ConstraintValidator<org.hibernate.validator.constraints.ru.INN, java.lang.CharSequence> {
  private static final java.util.regex.Pattern NUMBERS_ONLY_PATTERN;

  private static final int RADIX;

  private org.hibernate.validator.internal.constraintvalidators.hv.ru.INNValidator$INNValidationAlgorithm innValidationAlgorithm;

  public org.hibernate.validator.internal.constraintvalidators.hv.ru.INNValidator();
    Code:
       0: aload_0
       1: invokespecial #1                  // Method java/lang/Object."<init>":()V
       4: return

  public void initialize(org.hibernate.validator.constraints.ru.INN);
    Code:
       0: aload_0
       1: aload_1
       2: invokeinterface #7,  1            // InterfaceMethod org/hibernate/validator/constraints/ru/INN.type:()Lorg/hibernate/validator/constraints/ru/INN$Type;
       7: invokestatic  #13                 // InterfaceMethod org/hibernate/validator/internal/constraintvalidators/hv/ru/INNValidator$INNValidationAlgorithm.from:(Lorg/hibernate/validator/constraints/ru/INN$Type;)Lorg/hibernate/validator/internal/constraintvalidators/hv/ru/INNValidator$INNValidationAlgorithm;
      10: putfield      #19                 // Field innValidationAlgorithm:Lorg/hibernate/validator/internal/constraintvalidators/hv/ru/INNValidator$INNValidationAlgorithm;
      13: return

  public boolean isValid(java.lang.CharSequence, jakarta.validation.ConstraintValidatorContext);
    Code:
       0: aload_1
       1: ifnonnull     6
       4: iconst_1
       5: ireturn
       6: aload_1
       7: invokeinterface #25,  1           // InterfaceMethod java/lang/CharSequence.toString:()Ljava/lang/String;
      12: astore_3
      13: getstatic     #31                 // Field NUMBERS_ONLY_PATTERN:Ljava/util/regex/Pattern;
      16: aload_3
      17: invokevirtual #35                 // Method java/util/regex/Pattern.matcher:(Ljava/lang/CharSequence;)Ljava/util/regex/Matcher;
      20: invokevirtual #41                 // Method java/util/regex/Matcher.matches:()Z
      23: istore        4
      25: iload         4
      27: ifne          32
      30: iconst_0
      31: ireturn
      32: aload_0
      33: getfield      #19                 // Field innValidationAlgorithm:Lorg/hibernate/validator/internal/constraintvalidators/hv/ru/INNValidator$INNValidationAlgorithm;
      36: aload_3
      37: invokevirtual #47                 // Method java/lang/String.length:()I
      40: invokeinterface #53,  2           // InterfaceMethod org/hibernate/validator/internal/constraintvalidators/hv/ru/INNValidator$INNValidationAlgorithm.isValidLength:(I)Z
      45: ifne          50
      48: iconst_0
      49: ireturn
      50: aload_3
      51: invokevirtual #57                 // Method java/lang/String.codePoints:()Ljava/util/stream/IntStream;
      54: invokedynamic #61,  0             // InvokeDynamic #0:applyAsInt:()Ljava/util/function/IntUnaryOperator;
      59: invokeinterface #65,  2           // InterfaceMethod java/util/stream/IntStream.map:(Ljava/util/function/IntUnaryOperator;)Ljava/util/stream/IntStream;
      64: invokeinterface #71,  1           // InterfaceMethod java/util/stream/IntStream.toArray:()[I
      69: astore        5
      71: aload_0
      72: getfield      #19                 // Field innValidationAlgorithm:Lorg/hibernate/validator/internal/constraintvalidators/hv/ru/INNValidator$INNValidationAlgorithm;
      75: aload         5
      77: invokeinterface #75,  2           // InterfaceMethod org/hibernate/validator/internal/constraintvalidators/hv/ru/INNValidator$INNValidationAlgorithm.isValidChecksum:([I)Z
      82: ireturn

  public boolean isValid(java.lang.Object, jakarta.validation.ConstraintValidatorContext);
    Code:
       0: aload_0
       1: aload_1
       2: checkcast     #26                 // class java/lang/CharSequence
       5: aload_2
       6: invokevirtual #79                 // Method isValid:(Ljava/lang/CharSequence;Ljakarta/validation/ConstraintValidatorContext;)Z
       9: ireturn

  public void initialize(java.lang.annotation.Annotation);
    Code:
       0: aload_0
       1: aload_1
       2: checkcast     #8                  // class org/hibernate/validator/constraints/ru/INN
       5: invokevirtual #83                 // Method initialize:(Lorg/hibernate/validator/constraints/ru/INN;)V
       8: return

  private static int lambda$isValid$0(int);
    Code:
       0: iload_0
       1: bipush        10
       3: invokestatic  #87                 // Method java/lang/Character.digit:(II)I
       6: ireturn

  static {};
    Code:
       0: ldc           #93                 // String [0-9]+
       2: invokestatic  #95                 // Method java/util/regex/Pattern.compile:(Ljava/lang/String;)Ljava/util/regex/Pattern;
       5: putstatic     #31                 // Field NUMBERS_ONLY_PATTERN:Ljava/util/regex/Pattern;
       8: return
}
