Compiled from "ProcessImpl.scala"
public final class scala.sys.process.ProcessImpl$CompoundProcess$$anonfun$3 extends scala.runtime.AbstractFunction0<scala.Option<java.lang.Object>> implements scala.Serializable {
  public static final long serialVersionUID;

  private final scala.concurrent.SyncVar code$1;

  private final java.lang.Thread thread$1;

  public final scala.Option<java.lang.Object> apply();
    Code:
       0: aload_0
       1: getfield      #25                 // Field thread$1:Ljava/lang/Thread;
       4: invokevirtual #31                 // Method java/lang/Thread.join:()V
       7: aload_0
       8: getfield      #33                 // Field code$1:Lscala/concurrent/SyncVar;
      11: invokevirtual #39                 // Method scala/concurrent/SyncVar.get:()Ljava/lang/Object;
      14: checkcast     #41                 // class scala/Option
      17: areturn

  public final java.lang.Object apply();
    Code:
       0: aload_0
       1: invokevirtual #45                 // Method apply:()Lscala/Option;
       4: areturn

  public scala.sys.process.ProcessImpl$CompoundProcess$$anonfun$3(scala.sys.process.ProcessImpl$CompoundProcess, scala.concurrent.SyncVar, java.lang.Thread);
    Code:
       0: aload_0
       1: aload_2
       2: putfield      #33                 // Field code$1:Lscala/concurrent/SyncVar;
       5: aload_0
       6: aload_3
       7: putfield      #25                 // Field thread$1:Ljava/lang/Thread;
      10: aload_0
      11: invokespecial #49                 // Method scala/runtime/AbstractFunction0."<init>":()V
      14: return
}
