Compiled from "ProcessImpl.scala"
public abstract class scala.sys.process.ProcessImpl$BasicProcess implements scala.sys.process.Process {
  public final scala.sys.process.Process$ $outer;

  public abstract void start();

  public scala.sys.process.Process$ scala$sys$process$ProcessImpl$BasicProcess$$$outer();
    Code:
       0: aload_0
       1: getfield      #15                 // Field $outer:Lscala/sys/process/Process$;
       4: areturn

  public scala.sys.process.ProcessImpl$BasicProcess(scala.sys.process.Process$);
    Code:
       0: aload_1
       1: ifnonnull     6
       4: aconst_null
       5: athrow
       6: aload_0
       7: aload_1
       8: putfield      #15                 // Field $outer:Lscala/sys/process/Process$;
      11: aload_0
      12: invokespecial #21                 // Method java/lang/Object."<init>":()V
      15: return
}
