Compiled from "RequestMethod.java"
public final class org.springframework.web.bind.annotation.RequestMethod extends java.lang.Enum<org.springframework.web.bind.annotation.RequestMethod> {
  public static final org.springframework.web.bind.annotation.RequestMethod GET;

  public static final org.springframework.web.bind.annotation.RequestMethod HEAD;

  public static final org.springframework.web.bind.annotation.RequestMethod POST;

  public static final org.springframework.web.bind.annotation.RequestMethod PUT;

  public static final org.springframework.web.bind.annotation.RequestMethod PATCH;

  public static final org.springframework.web.bind.annotation.RequestMethod DELETE;

  public static final org.springframework.web.bind.annotation.RequestMethod OPTIONS;

  public static final org.springframework.web.bind.annotation.RequestMethod TRACE;

  private static final org.springframework.web.bind.annotation.RequestMethod[] $VALUES;

  public static org.springframework.web.bind.annotation.RequestMethod[] values();
    Code:
       0: getstatic     #1                  // Field $VALUES:[Lorg/springframework/web/bind/annotation/RequestMethod;
       3: invokevirtual #2                  // Method "[Lorg/springframework/web/bind/annotation/RequestMethod;".clone:()Ljava/lang/Object;
       6: checkcast     #3                  // class "[Lorg/springframework/web/bind/annotation/RequestMethod;"
       9: areturn

  public static org.springframework.web.bind.annotation.RequestMethod valueOf(java.lang.String);
    Code:
       0: ldc           #4                  // class org/springframework/web/bind/annotation/RequestMethod
       2: aload_0
       3: invokestatic  #5                  // Method java/lang/Enum.valueOf:(Ljava/lang/Class;Ljava/lang/String;)Ljava/lang/Enum;
       6: checkcast     #4                  // class org/springframework/web/bind/annotation/RequestMethod
       9: areturn

  private org.springframework.web.bind.annotation.RequestMethod();
    Code:
       0: aload_0
       1: aload_1
       2: iload_2
       3: invokespecial #6                  // Method java/lang/Enum."<init>":(Ljava/lang/String;I)V
       6: return

  static {};
    Code:
       0: new           #4                  // class org/springframework/web/bind/annotation/RequestMethod
       3: dup
       4: ldc           #7                  // String GET
       6: iconst_0
       7: invokespecial #8                  // Method "<init>":(Ljava/lang/String;I)V
      10: putstatic     #9                  // Field GET:Lorg/springframework/web/bind/annotation/RequestMethod;
      13: new           #4                  // class org/springframework/web/bind/annotation/RequestMethod
      16: dup
      17: ldc           #10                 // String HEAD
      19: iconst_1
      20: invokespecial #8                  // Method "<init>":(Ljava/lang/String;I)V
      23: putstatic     #11                 // Field HEAD:Lorg/springframework/web/bind/annotation/RequestMethod;
      26: new           #4                  // class org/springframework/web/bind/annotation/RequestMethod
      29: dup
      30: ldc           #12                 // String POST
      32: iconst_2
      33: invokespecial #8                  // Method "<init>":(Ljava/lang/String;I)V
      36: putstatic     #13                 // Field POST:Lorg/springframework/web/bind/annotation/RequestMethod;
      39: new           #4                  // class org/springframework/web/bind/annotation/RequestMethod
      42: dup
      43: ldc           #14                 // String PUT
      45: iconst_3
      46: invokespecial #8                  // Method "<init>":(Ljava/lang/String;I)V
      49: putstatic     #15                 // Field PUT:Lorg/springframework/web/bind/annotation/RequestMethod;
      52: new           #4                  // class org/springframework/web/bind/annotation/RequestMethod
      55: dup
      56: ldc           #16                 // String PATCH
      58: iconst_4
      59: invokespecial #8                  // Method "<init>":(Ljava/lang/String;I)V
      62: putstatic     #17                 // Field PATCH:Lorg/springframework/web/bind/annotation/RequestMethod;
      65: new           #4                  // class org/springframework/web/bind/annotation/RequestMethod
      68: dup
      69: ldc           #18                 // String DELETE
      71: iconst_5
      72: invokespecial #8                  // Method "<init>":(Ljava/lang/String;I)V
      75: putstatic     #19                 // Field DELETE:Lorg/springframework/web/bind/annotation/RequestMethod;
      78: new           #4                  // class org/springframework/web/bind/annotation/RequestMethod
      81: dup
      82: ldc           #20                 // String OPTIONS
      84: bipush        6
      86: invokespecial #8                  // Method "<init>":(Ljava/lang/String;I)V
      89: putstatic     #21                 // Field OPTIONS:Lorg/springframework/web/bind/annotation/RequestMethod;
      92: new           #4                  // class org/springframework/web/bind/annotation/RequestMethod
      95: dup
      96: ldc           #22                 // String TRACE
      98: bipush        7
     100: invokespecial #8                  // Method "<init>":(Ljava/lang/String;I)V
     103: putstatic     #23                 // Field TRACE:Lorg/springframework/web/bind/annotation/RequestMethod;
     106: bipush        8
     108: anewarray     #4                  // class org/springframework/web/bind/annotation/RequestMethod
     111: dup
     112: iconst_0
     113: getstatic     #9                  // Field GET:Lorg/springframework/web/bind/annotation/RequestMethod;
     116: aastore
     117: dup
     118: iconst_1
     119: getstatic     #11                 // Field HEAD:Lorg/springframework/web/bind/annotation/RequestMethod;
     122: aastore
     123: dup
     124: iconst_2
     125: getstatic     #13                 // Field POST:Lorg/springframework/web/bind/annotation/RequestMethod;
     128: aastore
     129: dup
     130: iconst_3
     131: getstatic     #15                 // Field PUT:Lorg/springframework/web/bind/annotation/RequestMethod;
     134: aastore
     135: dup
     136: iconst_4
     137: getstatic     #17                 // Field PATCH:Lorg/springframework/web/bind/annotation/RequestMethod;
     140: aastore
     141: dup
     142: iconst_5
     143: getstatic     #19                 // Field DELETE:Lorg/springframework/web/bind/annotation/RequestMethod;
     146: aastore
     147: dup
     148: bipush        6
     150: getstatic     #21                 // Field OPTIONS:Lorg/springframework/web/bind/annotation/RequestMethod;
     153: aastore
     154: dup
     155: bipush        7
     157: getstatic     #23                 // Field TRACE:Lorg/springframework/web/bind/annotation/RequestMethod;
     160: aastore
     161: putstatic     #1                  // Field $VALUES:[Lorg/springframework/web/bind/annotation/RequestMethod;
     164: return
}
