Compiled from "Algorithm.java"
public abstract class com.auth0.jwt.algorithms.Algorithm {
  private final java.lang.String name;

  private final java.lang.String description;

  public static com.auth0.jwt.algorithms.Algorithm RSA256(com.auth0.jwt.interfaces.RSAKeyProvider) throws java.lang.IllegalArgumentException;
    Code:
       0: new           #1                  // class com/auth0/jwt/algorithms/RSAAlgorithm
       3: dup
       4: ldc           #2                  // String RS256
       6: ldc           #3                  // String SHA256withRSA
       8: aload_0
       9: invokespecial #4                  // Method com/auth0/jwt/algorithms/RSAAlgorithm."<init>":(Ljava/lang/String;Ljava/lang/String;Lcom/auth0/jwt/interfaces/RSAKeyProvider;)V
      12: areturn

  public static com.auth0.jwt.algorithms.Algorithm RSA256(java.security.interfaces.RSAPublicKey, java.security.interfaces.RSAPrivateKey) throws java.lang.IllegalArgumentException;
    Code:
       0: aload_0
       1: aload_1
       2: invokestatic  #5                  // Method com/auth0/jwt/algorithms/RSAAlgorithm.providerForKeys:(Ljava/security/interfaces/RSAPublicKey;Ljava/security/interfaces/RSAPrivateKey;)Lcom/auth0/jwt/interfaces/RSAKeyProvider;
       5: invokestatic  #6                  // Method RSA256:(Lcom/auth0/jwt/interfaces/RSAKeyProvider;)Lcom/auth0/jwt/algorithms/Algorithm;
       8: areturn

  public static com.auth0.jwt.algorithms.Algorithm RSA256(java.security.interfaces.RSAKey) throws java.lang.IllegalArgumentException;
    Code:
       0: aload_0
       1: instanceof    #7                  // class java/security/interfaces/RSAPublicKey
       4: ifeq          14
       7: aload_0
       8: checkcast     #7                  // class java/security/interfaces/RSAPublicKey
      11: goto          15
      14: aconst_null
      15: astore_1
      16: aload_0
      17: instanceof    #8                  // class java/security/interfaces/RSAPrivateKey
      20: ifeq          30
      23: aload_0
      24: checkcast     #8                  // class java/security/interfaces/RSAPrivateKey
      27: goto          31
      30: aconst_null
      31: astore_2
      32: aload_1
      33: aload_2
      34: invokestatic  #9                  // Method RSA256:(Ljava/security/interfaces/RSAPublicKey;Ljava/security/interfaces/RSAPrivateKey;)Lcom/auth0/jwt/algorithms/Algorithm;
      37: areturn

  public static com.auth0.jwt.algorithms.Algorithm RSA384(com.auth0.jwt.interfaces.RSAKeyProvider) throws java.lang.IllegalArgumentException;
    Code:
       0: new           #1                  // class com/auth0/jwt/algorithms/RSAAlgorithm
       3: dup
       4: ldc           #10                 // String RS384
       6: ldc           #11                 // String SHA384withRSA
       8: aload_0
       9: invokespecial #4                  // Method com/auth0/jwt/algorithms/RSAAlgorithm."<init>":(Ljava/lang/String;Ljava/lang/String;Lcom/auth0/jwt/interfaces/RSAKeyProvider;)V
      12: areturn

  public static com.auth0.jwt.algorithms.Algorithm RSA384(java.security.interfaces.RSAPublicKey, java.security.interfaces.RSAPrivateKey) throws java.lang.IllegalArgumentException;
    Code:
       0: aload_0
       1: aload_1
       2: invokestatic  #5                  // Method com/auth0/jwt/algorithms/RSAAlgorithm.providerForKeys:(Ljava/security/interfaces/RSAPublicKey;Ljava/security/interfaces/RSAPrivateKey;)Lcom/auth0/jwt/interfaces/RSAKeyProvider;
       5: invokestatic  #12                 // Method RSA384:(Lcom/auth0/jwt/interfaces/RSAKeyProvider;)Lcom/auth0/jwt/algorithms/Algorithm;
       8: areturn

  public static com.auth0.jwt.algorithms.Algorithm RSA384(java.security.interfaces.RSAKey) throws java.lang.IllegalArgumentException;
    Code:
       0: aload_0
       1: instanceof    #7                  // class java/security/interfaces/RSAPublicKey
       4: ifeq          14
       7: aload_0
       8: checkcast     #7                  // class java/security/interfaces/RSAPublicKey
      11: goto          15
      14: aconst_null
      15: astore_1
      16: aload_0
      17: instanceof    #8                  // class java/security/interfaces/RSAPrivateKey
      20: ifeq          30
      23: aload_0
      24: checkcast     #8                  // class java/security/interfaces/RSAPrivateKey
      27: goto          31
      30: aconst_null
      31: astore_2
      32: aload_1
      33: aload_2
      34: invokestatic  #13                 // Method RSA384:(Ljava/security/interfaces/RSAPublicKey;Ljava/security/interfaces/RSAPrivateKey;)Lcom/auth0/jwt/algorithms/Algorithm;
      37: areturn

  public static com.auth0.jwt.algorithms.Algorithm RSA512(com.auth0.jwt.interfaces.RSAKeyProvider) throws java.lang.IllegalArgumentException;
    Code:
       0: new           #1                  // class com/auth0/jwt/algorithms/RSAAlgorithm
       3: dup
       4: ldc           #14                 // String RS512
       6: ldc           #15                 // String SHA512withRSA
       8: aload_0
       9: invokespecial #4                  // Method com/auth0/jwt/algorithms/RSAAlgorithm."<init>":(Ljava/lang/String;Ljava/lang/String;Lcom/auth0/jwt/interfaces/RSAKeyProvider;)V
      12: areturn

  public static com.auth0.jwt.algorithms.Algorithm RSA512(java.security.interfaces.RSAPublicKey, java.security.interfaces.RSAPrivateKey) throws java.lang.IllegalArgumentException;
    Code:
       0: aload_0
       1: aload_1
       2: invokestatic  #5                  // Method com/auth0/jwt/algorithms/RSAAlgorithm.providerForKeys:(Ljava/security/interfaces/RSAPublicKey;Ljava/security/interfaces/RSAPrivateKey;)Lcom/auth0/jwt/interfaces/RSAKeyProvider;
       5: invokestatic  #16                 // Method RSA512:(Lcom/auth0/jwt/interfaces/RSAKeyProvider;)Lcom/auth0/jwt/algorithms/Algorithm;
       8: areturn

  public static com.auth0.jwt.algorithms.Algorithm RSA512(java.security.interfaces.RSAKey) throws java.lang.IllegalArgumentException;
    Code:
       0: aload_0
       1: instanceof    #7                  // class java/security/interfaces/RSAPublicKey
       4: ifeq          14
       7: aload_0
       8: checkcast     #7                  // class java/security/interfaces/RSAPublicKey
      11: goto          15
      14: aconst_null
      15: astore_1
      16: aload_0
      17: instanceof    #8                  // class java/security/interfaces/RSAPrivateKey
      20: ifeq          30
      23: aload_0
      24: checkcast     #8                  // class java/security/interfaces/RSAPrivateKey
      27: goto          31
      30: aconst_null
      31: astore_2
      32: aload_1
      33: aload_2
      34: invokestatic  #17                 // Method RSA512:(Ljava/security/interfaces/RSAPublicKey;Ljava/security/interfaces/RSAPrivateKey;)Lcom/auth0/jwt/algorithms/Algorithm;
      37: areturn

  public static com.auth0.jwt.algorithms.Algorithm HMAC256(java.lang.String) throws java.lang.IllegalArgumentException;
    Code:
       0: new           #18                 // class com/auth0/jwt/algorithms/HMACAlgorithm
       3: dup
       4: ldc           #19                 // String HS256
       6: ldc           #20                 // String HmacSHA256
       8: aload_0
       9: invokespecial #21                 // Method com/auth0/jwt/algorithms/HMACAlgorithm."<init>":(Ljava/lang/String;Ljava/lang/String;Ljava/lang/String;)V
      12: areturn

  public static com.auth0.jwt.algorithms.Algorithm HMAC384(java.lang.String) throws java.lang.IllegalArgumentException;
    Code:
       0: new           #18                 // class com/auth0/jwt/algorithms/HMACAlgorithm
       3: dup
       4: ldc           #22                 // String HS384
       6: ldc           #23                 // String HmacSHA384
       8: aload_0
       9: invokespecial #21                 // Method com/auth0/jwt/algorithms/HMACAlgorithm."<init>":(Ljava/lang/String;Ljava/lang/String;Ljava/lang/String;)V
      12: areturn

  public static com.auth0.jwt.algorithms.Algorithm HMAC512(java.lang.String) throws java.lang.IllegalArgumentException;
    Code:
       0: new           #18                 // class com/auth0/jwt/algorithms/HMACAlgorithm
       3: dup
       4: ldc           #24                 // String HS512
       6: ldc           #25                 // String HmacSHA512
       8: aload_0
       9: invokespecial #21                 // Method com/auth0/jwt/algorithms/HMACAlgorithm."<init>":(Ljava/lang/String;Ljava/lang/String;Ljava/lang/String;)V
      12: areturn

  public static com.auth0.jwt.algorithms.Algorithm HMAC256(byte[]) throws java.lang.IllegalArgumentException;
    Code:
       0: new           #18                 // class com/auth0/jwt/algorithms/HMACAlgorithm
       3: dup
       4: ldc           #19                 // String HS256
       6: ldc           #20                 // String HmacSHA256
       8: aload_0
       9: invokespecial #26                 // Method com/auth0/jwt/algorithms/HMACAlgorithm."<init>":(Ljava/lang/String;Ljava/lang/String;[B)V
      12: areturn

  public static com.auth0.jwt.algorithms.Algorithm HMAC384(byte[]) throws java.lang.IllegalArgumentException;
    Code:
       0: new           #18                 // class com/auth0/jwt/algorithms/HMACAlgorithm
       3: dup
       4: ldc           #22                 // String HS384
       6: ldc           #23                 // String HmacSHA384
       8: aload_0
       9: invokespecial #26                 // Method com/auth0/jwt/algorithms/HMACAlgorithm."<init>":(Ljava/lang/String;Ljava/lang/String;[B)V
      12: areturn

  public static com.auth0.jwt.algorithms.Algorithm HMAC512(byte[]) throws java.lang.IllegalArgumentException;
    Code:
       0: new           #18                 // class com/auth0/jwt/algorithms/HMACAlgorithm
       3: dup
       4: ldc           #24                 // String HS512
       6: ldc           #25                 // String HmacSHA512
       8: aload_0
       9: invokespecial #26                 // Method com/auth0/jwt/algorithms/HMACAlgorithm."<init>":(Ljava/lang/String;Ljava/lang/String;[B)V
      12: areturn

  public static com.auth0.jwt.algorithms.Algorithm ECDSA256(com.auth0.jwt.interfaces.ECDSAKeyProvider) throws java.lang.IllegalArgumentException;
    Code:
       0: new           #27                 // class com/auth0/jwt/algorithms/ECDSAAlgorithm
       3: dup
       4: ldc           #28                 // String ES256
       6: ldc           #29                 // String SHA256withECDSA
       8: bipush        32
      10: aload_0
      11: invokespecial #30                 // Method com/auth0/jwt/algorithms/ECDSAAlgorithm."<init>":(Ljava/lang/String;Ljava/lang/String;ILcom/auth0/jwt/interfaces/ECDSAKeyProvider;)V
      14: areturn

  public static com.auth0.jwt.algorithms.Algorithm ECDSA256(java.security.interfaces.ECPublicKey, java.security.interfaces.ECPrivateKey) throws java.lang.IllegalArgumentException;
    Code:
       0: aload_0
       1: aload_1
       2: invokestatic  #31                 // Method com/auth0/jwt/algorithms/ECDSAAlgorithm.providerForKeys:(Ljava/security/interfaces/ECPublicKey;Ljava/security/interfaces/ECPrivateKey;)Lcom/auth0/jwt/interfaces/ECDSAKeyProvider;
       5: invokestatic  #32                 // Method ECDSA256:(Lcom/auth0/jwt/interfaces/ECDSAKeyProvider;)Lcom/auth0/jwt/algorithms/Algorithm;
       8: areturn

  public static com.auth0.jwt.algorithms.Algorithm ECDSA256(java.security.interfaces.ECKey) throws java.lang.IllegalArgumentException;
    Code:
       0: aload_0
       1: instanceof    #33                 // class java/security/interfaces/ECPublicKey
       4: ifeq          14
       7: aload_0
       8: checkcast     #33                 // class java/security/interfaces/ECPublicKey
      11: goto          15
      14: aconst_null
      15: astore_1
      16: aload_0
      17: instanceof    #34                 // class java/security/interfaces/ECPrivateKey
      20: ifeq          30
      23: aload_0
      24: checkcast     #34                 // class java/security/interfaces/ECPrivateKey
      27: goto          31
      30: aconst_null
      31: astore_2
      32: aload_1
      33: aload_2
      34: invokestatic  #35                 // Method ECDSA256:(Ljava/security/interfaces/ECPublicKey;Ljava/security/interfaces/ECPrivateKey;)Lcom/auth0/jwt/algorithms/Algorithm;
      37: areturn

  public static com.auth0.jwt.algorithms.Algorithm ECDSA384(com.auth0.jwt.interfaces.ECDSAKeyProvider) throws java.lang.IllegalArgumentException;
    Code:
       0: new           #27                 // class com/auth0/jwt/algorithms/ECDSAAlgorithm
       3: dup
       4: ldc           #36                 // String ES384
       6: ldc           #37                 // String SHA384withECDSA
       8: bipush        48
      10: aload_0
      11: invokespecial #30                 // Method com/auth0/jwt/algorithms/ECDSAAlgorithm."<init>":(Ljava/lang/String;Ljava/lang/String;ILcom/auth0/jwt/interfaces/ECDSAKeyProvider;)V
      14: areturn

  public static com.auth0.jwt.algorithms.Algorithm ECDSA384(java.security.interfaces.ECPublicKey, java.security.interfaces.ECPrivateKey) throws java.lang.IllegalArgumentException;
    Code:
       0: aload_0
       1: aload_1
       2: invokestatic  #31                 // Method com/auth0/jwt/algorithms/ECDSAAlgorithm.providerForKeys:(Ljava/security/interfaces/ECPublicKey;Ljava/security/interfaces/ECPrivateKey;)Lcom/auth0/jwt/interfaces/ECDSAKeyProvider;
       5: invokestatic  #38                 // Method ECDSA384:(Lcom/auth0/jwt/interfaces/ECDSAKeyProvider;)Lcom/auth0/jwt/algorithms/Algorithm;
       8: areturn

  public static com.auth0.jwt.algorithms.Algorithm ECDSA384(java.security.interfaces.ECKey) throws java.lang.IllegalArgumentException;
    Code:
       0: aload_0
       1: instanceof    #33                 // class java/security/interfaces/ECPublicKey
       4: ifeq          14
       7: aload_0
       8: checkcast     #33                 // class java/security/interfaces/ECPublicKey
      11: goto          15
      14: aconst_null
      15: astore_1
      16: aload_0
      17: instanceof    #34                 // class java/security/interfaces/ECPrivateKey
      20: ifeq          30
      23: aload_0
      24: checkcast     #34                 // class java/security/interfaces/ECPrivateKey
      27: goto          31
      30: aconst_null
      31: astore_2
      32: aload_1
      33: aload_2
      34: invokestatic  #39                 // Method ECDSA384:(Ljava/security/interfaces/ECPublicKey;Ljava/security/interfaces/ECPrivateKey;)Lcom/auth0/jwt/algorithms/Algorithm;
      37: areturn

  public static com.auth0.jwt.algorithms.Algorithm ECDSA512(com.auth0.jwt.interfaces.ECDSAKeyProvider) throws java.lang.IllegalArgumentException;
    Code:
       0: new           #27                 // class com/auth0/jwt/algorithms/ECDSAAlgorithm
       3: dup
       4: ldc           #40                 // String ES512
       6: ldc           #41                 // String SHA512withECDSA
       8: bipush        66
      10: aload_0
      11: invokespecial #30                 // Method com/auth0/jwt/algorithms/ECDSAAlgorithm."<init>":(Ljava/lang/String;Ljava/lang/String;ILcom/auth0/jwt/interfaces/ECDSAKeyProvider;)V
      14: areturn

  public static com.auth0.jwt.algorithms.Algorithm ECDSA512(java.security.interfaces.ECPublicKey, java.security.interfaces.ECPrivateKey) throws java.lang.IllegalArgumentException;
    Code:
       0: aload_0
       1: aload_1
       2: invokestatic  #31                 // Method com/auth0/jwt/algorithms/ECDSAAlgorithm.providerForKeys:(Ljava/security/interfaces/ECPublicKey;Ljava/security/interfaces/ECPrivateKey;)Lcom/auth0/jwt/interfaces/ECDSAKeyProvider;
       5: invokestatic  #42                 // Method ECDSA512:(Lcom/auth0/jwt/interfaces/ECDSAKeyProvider;)Lcom/auth0/jwt/algorithms/Algorithm;
       8: areturn

  public static com.auth0.jwt.algorithms.Algorithm ECDSA512(java.security.interfaces.ECKey) throws java.lang.IllegalArgumentException;
    Code:
       0: aload_0
       1: instanceof    #33                 // class java/security/interfaces/ECPublicKey
       4: ifeq          14
       7: aload_0
       8: checkcast     #33                 // class java/security/interfaces/ECPublicKey
      11: goto          15
      14: aconst_null
      15: astore_1
      16: aload_0
      17: instanceof    #34                 // class java/security/interfaces/ECPrivateKey
      20: ifeq          30
      23: aload_0
      24: checkcast     #34                 // class java/security/interfaces/ECPrivateKey
      27: goto          31
      30: aconst_null
      31: astore_2
      32: aload_1
      33: aload_2
      34: invokestatic  #43                 // Method ECDSA512:(Ljava/security/interfaces/ECPublicKey;Ljava/security/interfaces/ECPrivateKey;)Lcom/auth0/jwt/algorithms/Algorithm;
      37: areturn

  public static com.auth0.jwt.algorithms.Algorithm none();
    Code:
       0: new           #44                 // class com/auth0/jwt/algorithms/NoneAlgorithm
       3: dup
       4: invokespecial #45                 // Method com/auth0/jwt/algorithms/NoneAlgorithm."<init>":()V
       7: areturn

  protected com.auth0.jwt.algorithms.Algorithm(java.lang.String, java.lang.String);
    Code:
       0: aload_0
       1: invokespecial #46                 // Method java/lang/Object."<init>":()V
       4: aload_0
       5: aload_1
       6: putfield      #47                 // Field name:Ljava/lang/String;
       9: aload_0
      10: aload_2
      11: putfield      #48                 // Field description:Ljava/lang/String;
      14: return

  public java.lang.String getSigningKeyId();
    Code:
       0: aconst_null
       1: areturn

  public java.lang.String getName();
    Code:
       0: aload_0
       1: getfield      #47                 // Field name:Ljava/lang/String;
       4: areturn

  java.lang.String getDescription();
    Code:
       0: aload_0
       1: getfield      #48                 // Field description:Ljava/lang/String;
       4: areturn

  public java.lang.String toString();
    Code:
       0: aload_0
       1: getfield      #48                 // Field description:Ljava/lang/String;
       4: areturn

  public abstract void verify(com.auth0.jwt.interfaces.DecodedJWT) throws com.auth0.jwt.exceptions.SignatureVerificationException;

  public byte[] sign(byte[], byte[]) throws com.auth0.jwt.exceptions.SignatureGenerationException;
    Code:
       0: aload_1
       1: arraylength
       2: iconst_1
       3: iadd
       4: aload_2
       5: arraylength
       6: iadd
       7: newarray       byte
       9: astore_3
      10: aload_1
      11: iconst_0
      12: aload_3
      13: iconst_0
      14: aload_1
      15: arraylength
      16: invokestatic  #49                 // Method java/lang/System.arraycopy:(Ljava/lang/Object;ILjava/lang/Object;II)V
      19: aload_3
      20: aload_1
      21: arraylength
      22: bipush        46
      24: bastore
      25: aload_2
      26: iconst_0
      27: aload_3
      28: aload_1
      29: arraylength
      30: iconst_1
      31: iadd
      32: aload_2
      33: arraylength
      34: invokestatic  #49                 // Method java/lang/System.arraycopy:(Ljava/lang/Object;ILjava/lang/Object;II)V
      37: aload_0
      38: aload_3
      39: invokevirtual #50                 // Method sign:([B)[B
      42: areturn

  public abstract byte[] sign(byte[]) throws com.auth0.jwt.exceptions.SignatureGenerationException;
}
