Compiled from "AsValueReferenceTypeDeserializer.java"
public class org.graylog2.contentpacks.jackson.AsValueReferenceTypeDeserializer extends com.fasterxml.jackson.databind.jsontype.impl.AsWrapperTypeDeserializer {
  public org.graylog2.contentpacks.jackson.AsValueReferenceTypeDeserializer(com.fasterxml.jackson.databind.JavaType, com.fasterxml.jackson.databind.jsontype.TypeIdResolver, java.lang.String, boolean, com.fasterxml.jackson.databind.JavaType);
    Code:
       0: aload_0
       1: aload_1
       2: aload_2
       3: aload_3
       4: iload         4
       6: aload         5
       8: invokespecial #1                  // Method com/fasterxml/jackson/databind/jsontype/impl/AsWrapperTypeDeserializer."<init>":(Lcom/fasterxml/jackson/databind/JavaType;Lcom/fasterxml/jackson/databind/jsontype/TypeIdResolver;Ljava/lang/String;ZLcom/fasterxml/jackson/databind/JavaType;)V
      11: return

  protected org.graylog2.contentpacks.jackson.AsValueReferenceTypeDeserializer(com.fasterxml.jackson.databind.jsontype.impl.AsWrapperTypeDeserializer, com.fasterxml.jackson.databind.BeanProperty);
    Code:
       0: aload_0
       1: aload_1
       2: aload_2
       3: invokespecial #2                  // Method com/fasterxml/jackson/databind/jsontype/impl/AsWrapperTypeDeserializer."<init>":(Lcom/fasterxml/jackson/databind/jsontype/impl/AsWrapperTypeDeserializer;Lcom/fasterxml/jackson/databind/BeanProperty;)V
       6: return

  public com.fasterxml.jackson.databind.jsontype.TypeDeserializer forProperty(com.fasterxml.jackson.databind.BeanProperty);
    Code:
       0: aload_1
       1: aload_0
       2: getfield      #3                  // Field _property:Lcom/fasterxml/jackson/databind/BeanProperty;
       5: if_acmpne     12
       8: aload_0
       9: goto          21
      12: new           #4                  // class org/graylog2/contentpacks/jackson/AsValueReferenceTypeDeserializer
      15: dup
      16: aload_0
      17: aload_1
      18: invokespecial #5                  // Method "<init>":(Lcom/fasterxml/jackson/databind/jsontype/impl/AsWrapperTypeDeserializer;Lcom/fasterxml/jackson/databind/BeanProperty;)V
      21: areturn

  protected java.lang.Object _deserialize(com.fasterxml.jackson.core.JsonParser, com.fasterxml.jackson.databind.DeserializationContext) throws java.io.IOException;
    Code:
       0: aload_1
       1: invokevirtual #6                  // Method com/fasterxml/jackson/core/JsonParser.readValueAsTree:()Lcom/fasterxml/jackson/core/TreeNode;
       4: astore_3
       5: aload_3
       6: ldc           #7                  // String type
       8: invokeinterface #8,  2            // InterfaceMethod com/fasterxml/jackson/core/TreeNode.path:(Ljava/lang/String;)Lcom/fasterxml/jackson/core/TreeNode;
      13: astore        4
      15: aload         4
      17: invokeinterface #9,  1            // InterfaceMethod com/fasterxml/jackson/core/TreeNode.isObject:()Z
      22: ifne          45
      25: aload_2
      26: aload         4
      28: invokeinterface #10,  1           // InterfaceMethod com/fasterxml/jackson/core/TreeNode.traverse:()Lcom/fasterxml/jackson/core/JsonParser;
      33: getstatic     #11                 // Field com/fasterxml/jackson/core/JsonToken.START_OBJECT:Lcom/fasterxml/jackson/core/JsonToken;
      36: ldc           #12                 // String expected START_OBJECT before the type information and deserialized value
      38: iconst_0
      39: anewarray     #13                 // class java/lang/Object
      42: invokevirtual #14                 // Method com/fasterxml/jackson/databind/DeserializationContext.reportWrongTokenException:(Lcom/fasterxml/jackson/core/JsonParser;Lcom/fasterxml/jackson/core/JsonToken;Ljava/lang/String;[Ljava/lang/Object;)V
      45: aload         4
      47: ldc           #15                 // String @value
      49: invokeinterface #8,  2            // InterfaceMethod com/fasterxml/jackson/core/TreeNode.path:(Ljava/lang/String;)Lcom/fasterxml/jackson/core/TreeNode;
      54: astore        5
      56: aload         5
      58: invokeinterface #16,  1           // InterfaceMethod com/fasterxml/jackson/core/TreeNode.isValueNode:()Z
      63: ifne          86
      66: aload_2
      67: aload         4
      69: invokeinterface #10,  1           // InterfaceMethod com/fasterxml/jackson/core/TreeNode.traverse:()Lcom/fasterxml/jackson/core/JsonParser;
      74: getstatic     #17                 // Field com/fasterxml/jackson/core/JsonToken.VALUE_STRING:Lcom/fasterxml/jackson/core/JsonToken;
      77: ldc           #18                 // String expected VALUE_STRING as type information and deserialized value
      79: iconst_0
      80: anewarray     #13                 // class java/lang/Object
      83: invokevirtual #14                 // Method com/fasterxml/jackson/databind/DeserializationContext.reportWrongTokenException:(Lcom/fasterxml/jackson/core/JsonParser;Lcom/fasterxml/jackson/core/JsonToken;Ljava/lang/String;[Ljava/lang/Object;)V
      86: aload         5
      88: invokeinterface #10,  1           // InterfaceMethod com/fasterxml/jackson/core/TreeNode.traverse:()Lcom/fasterxml/jackson/core/JsonParser;
      93: astore        6
      95: aload         6
      97: invokevirtual #19                 // Method com/fasterxml/jackson/core/JsonParser.nextTextValue:()Ljava/lang/String;
     100: astore        7
     102: aload_0
     103: aload_2
     104: aload         7
     106: invokevirtual #20                 // Method _findDeserializer:(Lcom/fasterxml/jackson/databind/DeserializationContext;Ljava/lang/String;)Lcom/fasterxml/jackson/databind/JsonDeserializer;
     109: astore        8
     111: aload_3
     112: invokeinterface #10,  1           // InterfaceMethod com/fasterxml/jackson/core/TreeNode.traverse:()Lcom/fasterxml/jackson/core/JsonParser;
     117: astore        9
     119: aload         9
     121: invokevirtual #21                 // Method com/fasterxml/jackson/core/JsonParser.nextToken:()Lcom/fasterxml/jackson/core/JsonToken;
     124: getstatic     #11                 // Field com/fasterxml/jackson/core/JsonToken.START_OBJECT:Lcom/fasterxml/jackson/core/JsonToken;
     127: if_acmpeq     145
     130: aload_2
     131: aload         9
     133: getstatic     #11                 // Field com/fasterxml/jackson/core/JsonToken.START_OBJECT:Lcom/fasterxml/jackson/core/JsonToken;
     136: ldc           #22                 // String expected START_OBJECT
     138: iconst_0
     139: anewarray     #13                 // class java/lang/Object
     142: invokevirtual #14                 // Method com/fasterxml/jackson/databind/DeserializationContext.reportWrongTokenException:(Lcom/fasterxml/jackson/core/JsonParser;Lcom/fasterxml/jackson/core/JsonToken;Ljava/lang/String;[Ljava/lang/Object;)V
     145: aload         8
     147: aload         9
     149: aload_2
     150: invokevirtual #23                 // Method com/fasterxml/jackson/databind/JsonDeserializer.deserialize:(Lcom/fasterxml/jackson/core/JsonParser;Lcom/fasterxml/jackson/databind/DeserializationContext;)Ljava/lang/Object;
     153: areturn
}
