Compiled from "WorkObjectInputStream.java"
public class org.jboss.jca.core.workmanager.WorkObjectInputStream extends java.io.ObjectInputStream {
  private org.jboss.jca.core.workmanager.WorkClassLoader wcl;

  public org.jboss.jca.core.workmanager.WorkObjectInputStream(java.io.InputStream) throws java.io.StreamCorruptedException, java.io.IOException;
    Code:
       0: aload_0
       1: aload_1
       2: aconst_null
       3: invokespecial #1                  // Method "<init>":(Ljava/io/InputStream;Lorg/jboss/jca/core/workmanager/WorkClassLoader;)V
       6: return

  public org.jboss.jca.core.workmanager.WorkObjectInputStream(java.io.InputStream, org.jboss.jca.core.workmanager.WorkClassLoader) throws java.io.StreamCorruptedException, java.io.IOException;
    Code:
       0: aload_0
       1: aload_1
       2: invokespecial #2                  // Method java/io/ObjectInputStream."<init>":(Ljava/io/InputStream;)V
       5: aload_0
       6: aload_2
       7: putfield      #3                  // Field wcl:Lorg/jboss/jca/core/workmanager/WorkClassLoader;
      10: return

  public void setWorkClassLoader(org.jboss.jca.core.workmanager.WorkClassLoader);
    Code:
       0: aload_0
       1: aload_1
       2: putfield      #3                  // Field wcl:Lorg/jboss/jca/core/workmanager/WorkClassLoader;
       5: return

  public java.lang.Class resolveClass(java.io.ObjectStreamClass) throws java.io.IOException, java.lang.ClassNotFoundException;
    Code:
       0: aload_0
       1: getfield      #3                  // Field wcl:Lorg/jboss/jca/core/workmanager/WorkClassLoader;
       4: ifnull        20
       7: aload_0
       8: getfield      #3                  // Field wcl:Lorg/jboss/jca/core/workmanager/WorkClassLoader;
      11: aload_1
      12: invokevirtual #4                  // Method java/io/ObjectStreamClass.getName:()Ljava/lang/String;
      15: invokevirtual #5                  // Method org/jboss/jca/core/workmanager/WorkClassLoader.loadClass:(Ljava/lang/String;)Ljava/lang/Class;
      18: areturn
      19: astore_2
      20: aload_0
      21: aload_1
      22: invokespecial #7                  // Method java/io/ObjectInputStream.resolveClass:(Ljava/io/ObjectStreamClass;)Ljava/lang/Class;
      25: areturn
    Exception table:
       from    to  target type
           7    18    19   Class java/lang/Throwable
}
