Compiled from "FileEditorMappingLabelProvider.java"
public class org.eclipse.ui.dialogs.FileEditorMappingLabelProvider extends org.eclipse.jface.viewers.LabelProvider implements org.eclipse.jface.viewers.ITableLabelProvider {
  public static final org.eclipse.ui.dialogs.FileEditorMappingLabelProvider INSTANCE;

  private java.util.List<org.eclipse.swt.graphics.Image> imagesToDispose;

  static {};
    Code:
       0: new           #48                 // class org/eclipse/ui/dialogs/FileEditorMappingLabelProvider
       3: dup
       4: invokespecial #88                 // Method "<init>":()V
       7: putstatic     #81                 // Field INSTANCE:Lorg/eclipse/ui/dialogs/FileEditorMappingLabelProvider;
      10: return

  private org.eclipse.ui.dialogs.FileEditorMappingLabelProvider();
    Code:
       0: aload_0
       1: invokespecial #84                 // Method org/eclipse/jface/viewers/LabelProvider."<init>":()V
       4: aload_0
       5: new           #39                 // class java/util/ArrayList
       8: dup
       9: invokespecial #82                 // Method java/util/ArrayList."<init>":()V
      12: putfield      #80                 // Field imagesToDispose:Ljava/util/List;
      15: return

  public void dispose();
    Code:
       0: aload_0
       1: invokespecial #85                 // Method org/eclipse/jface/viewers/LabelProvider.dispose:()V
       4: aload_0
       5: getfield      #80                 // Field imagesToDispose:Ljava/util/List;
       8: invokeinterface #95,  1           // InterfaceMethod java/util/List.iterator:()Ljava/util/Iterator;
      13: astore_2
      14: goto          31
      17: aload_2
      18: invokeinterface #92,  1           // InterfaceMethod java/util/Iterator.next:()Ljava/lang/Object;
      23: checkcast     #46                 // class org/eclipse/swt/graphics/Image
      26: astore_1
      27: aload_1
      28: invokevirtual #87                 // Method org/eclipse/swt/graphics/Image.dispose:()V
      31: aload_2
      32: invokeinterface #91,  1           // InterfaceMethod java/util/Iterator.hasNext:()Z
      37: ifne          17
      40: aload_0
      41: getfield      #80                 // Field imagesToDispose:Ljava/util/List;
      44: invokeinterface #93,  1           // InterfaceMethod java/util/List.clear:()V
      49: return

  public org.eclipse.swt.graphics.Image getColumnImage(java.lang.Object, int);
    Code:
       0: aload_0
       1: aload_1
       2: invokevirtual #90                 // Method getImage:(Ljava/lang/Object;)Lorg/eclipse/swt/graphics/Image;
       5: areturn

  public java.lang.String getColumnText(java.lang.Object, int);
    Code:
       0: aload_0
       1: aload_1
       2: invokevirtual #89                 // Method getText:(Ljava/lang/Object;)Ljava/lang/String;
       5: areturn

  public org.eclipse.swt.graphics.Image getImage(java.lang.Object);
    Code:
       0: aload_1
       1: instanceof    #47                 // class org/eclipse/ui/IFileEditorMapping
       4: ifeq          33
       7: aload_1
       8: checkcast     #47                 // class org/eclipse/ui/IFileEditorMapping
      11: invokeinterface #97,  1           // InterfaceMethod org/eclipse/ui/IFileEditorMapping.getImageDescriptor:()Lorg/eclipse/jface/resource/ImageDescriptor;
      16: invokevirtual #83                 // Method org/eclipse/jface/resource/ImageDescriptor.createImage:()Lorg/eclipse/swt/graphics/Image;
      19: astore_2
      20: aload_0
      21: getfield      #80                 // Field imagesToDispose:Ljava/util/List;
      24: aload_2
      25: invokeinterface #94,  2           // InterfaceMethod java/util/List.add:(Ljava/lang/Object;)Z
      30: pop
      31: aload_2
      32: areturn
      33: aconst_null
      34: areturn

  public java.lang.String getText(java.lang.Object);
    Code:
       0: aload_1
       1: instanceof    #47                 // class org/eclipse/ui/IFileEditorMapping
       4: ifeq          22
       7: aload_1
       8: checkcast     #47                 // class org/eclipse/ui/IFileEditorMapping
      11: invokeinterface #96,  1           // InterfaceMethod org/eclipse/ui/IFileEditorMapping.getLabel:()Ljava/lang/String;
      16: ldc           #1                  // String *.
      18: invokestatic  #86                 // Method org/eclipse/osgi/util/TextProcessor.process:(Ljava/lang/String;Ljava/lang/String;)Ljava/lang/String;
      21: areturn
      22: aconst_null
      23: areturn
}
