Compiled from "FilteredItemsSelectionDialog.java"
public abstract class org.eclipse.ui.dialogs.FilteredItemsSelectionDialog$SelectionHistory {
  private static final java.lang.String DEFAULT_ROOT_NODE_NAME;

  private static final java.lang.String DEFAULT_INFO_NODE_NAME;

  private static final int MAX_HISTORY_SIZE;

  private final java.util.Set<java.lang.Object> historyList;

  private final java.lang.String rootNodeName;

  private final java.lang.String infoNodeName;

  private org.eclipse.ui.dialogs.FilteredItemsSelectionDialog$SelectionHistory(java.lang.String, java.lang.String);
    Code:
       0: aload_0
       1: invokespecial #101                // Method java/lang/Object."<init>":()V
       4: aload_0
       5: new           #61                 // class org/eclipse/ui/dialogs/FilteredItemsSelectionDialog$SelectionHistory$1
       8: dup
       9: aload_0
      10: invokespecial #108                // Method org/eclipse/ui/dialogs/FilteredItemsSelectionDialog$SelectionHistory$1."<init>":(Lorg/eclipse/ui/dialogs/FilteredItemsSelectionDialog$SelectionHistory;)V
      13: invokestatic  #102                // Method java/util/Collections.synchronizedSet:(Ljava/util/Set;)Ljava/util/Set;
      16: putfield      #100                // Field historyList:Ljava/util/Set;
      19: aload_0
      20: aload_1
      21: putfield      #99                 // Field rootNodeName:Ljava/lang/String;
      24: aload_0
      25: aload_2
      26: putfield      #98                 // Field infoNodeName:Ljava/lang/String;
      29: return

  public org.eclipse.ui.dialogs.FilteredItemsSelectionDialog$SelectionHistory();
    Code:
       0: aload_0
       1: ldc           #1                  // String historyRootNode
       3: ldc           #2                  // String infoNode
       5: invokespecial #106                // Method "<init>":(Ljava/lang/String;Ljava/lang/String;)V
       8: return

  public synchronized void accessed(java.lang.Object);
    Code:
       0: aload_0
       1: getfield      #100                // Field historyList:Ljava/util/Set;
       4: aload_1
       5: invokeinterface #113,  2          // InterfaceMethod java/util/Set.remove:(Ljava/lang/Object;)Z
      10: pop
      11: aload_0
      12: getfield      #100                // Field historyList:Ljava/util/Set;
      15: aload_1
      16: invokeinterface #111,  2          // InterfaceMethod java/util/Set.add:(Ljava/lang/Object;)Z
      21: pop
      22: return

  public synchronized boolean contains(java.lang.Object);
    Code:
       0: aload_0
       1: getfield      #100                // Field historyList:Ljava/util/Set;
       4: aload_1
       5: invokeinterface #112,  2          // InterfaceMethod java/util/Set.contains:(Ljava/lang/Object;)Z
      10: ireturn

  public synchronized boolean isEmpty();
    Code:
       0: aload_0
       1: getfield      #100                // Field historyList:Ljava/util/Set;
       4: invokeinterface #109,  1          // InterfaceMethod java/util/Set.isEmpty:()Z
       9: ireturn

  public synchronized boolean remove(java.lang.Object);
    Code:
       0: aload_0
       1: getfield      #100                // Field historyList:Ljava/util/Set;
       4: aload_1
       5: invokeinterface #113,  2          // InterfaceMethod java/util/Set.remove:(Ljava/lang/Object;)Z
      10: ireturn

  public void load(org.eclipse.ui.IMemento);
    Code:
       0: aload_1
       1: aload_0
       2: getfield      #99                 // Field rootNodeName:Ljava/lang/String;
       5: invokeinterface #115,  2          // InterfaceMethod org/eclipse/ui/IMemento.getChild:(Ljava/lang/String;)Lorg/eclipse/ui/IMemento;
      10: checkcast     #58                 // class org/eclipse/ui/XMLMemento
      13: astore_2
      14: aload_2
      15: ifnonnull     19
      18: return
      19: aload_2
      20: aload_0
      21: getfield      #98                 // Field infoNodeName:Ljava/lang/String;
      24: invokevirtual #103                // Method org/eclipse/ui/XMLMemento.getChildren:(Ljava/lang/String;)[Lorg/eclipse/ui/IMemento;
      27: astore_3
      28: aload_3
      29: dup
      30: astore        7
      32: arraylength
      33: istore        6
      35: iconst_0
      36: istore        5
      38: goto          76
      41: aload         7
      43: iload         5
      45: aaload
      46: astore        4
      48: aload_0
      49: aload         4
      51: invokevirtual #105                // Method restoreItemFromMemento:(Lorg/eclipse/ui/IMemento;)Ljava/lang/Object;
      54: astore        8
      56: aload         8
      58: ifnull        73
      61: aload_0
      62: getfield      #100                // Field historyList:Ljava/util/Set;
      65: aload         8
      67: invokeinterface #111,  2          // InterfaceMethod java/util/Set.add:(Ljava/lang/Object;)Z
      72: pop
      73: iinc          5, 1
      76: iload         5
      78: iload         6
      80: if_icmplt     41
      83: return

  public void save(org.eclipse.ui.IMemento);
    Code:
       0: aload_1
       1: aload_0
       2: getfield      #99                 // Field rootNodeName:Ljava/lang/String;
       5: invokeinterface #114,  2          // InterfaceMethod org/eclipse/ui/IMemento.createChild:(Ljava/lang/String;)Lorg/eclipse/ui/IMemento;
      10: astore_2
      11: aload_0
      12: invokevirtual #104                // Method getHistoryItems:()[Ljava/lang/Object;
      15: astore_3
      16: aload_3
      17: dup
      18: astore        7
      20: arraylength
      21: istore        6
      23: iconst_0
      24: istore        5
      26: goto          59
      29: aload         7
      31: iload         5
      33: aaload
      34: astore        4
      36: aload_2
      37: aload_0
      38: getfield      #98                 // Field infoNodeName:Ljava/lang/String;
      41: invokeinterface #114,  2          // InterfaceMethod org/eclipse/ui/IMemento.createChild:(Ljava/lang/String;)Lorg/eclipse/ui/IMemento;
      46: astore        8
      48: aload_0
      49: aload         4
      51: aload         8
      53: invokevirtual #107                // Method storeItemToMemento:(Ljava/lang/Object;Lorg/eclipse/ui/IMemento;)V
      56: iinc          5, 1
      59: iload         5
      61: iload         6
      63: if_icmplt     29
      66: return

  public synchronized java.lang.Object[] getHistoryItems();
    Code:
       0: aload_0
       1: getfield      #100                // Field historyList:Ljava/util/Set;
       4: invokeinterface #110,  1          // InterfaceMethod java/util/Set.toArray:()[Ljava/lang/Object;
       9: areturn

  protected abstract java.lang.Object restoreItemFromMemento(org.eclipse.ui.IMemento);

  protected abstract void storeItemToMemento(java.lang.Object, org.eclipse.ui.IMemento);
}
