Compiled from "FilteredItemsSelectionDialog.java"
public abstract class org.eclipse.ui.dialogs.FilteredItemsSelectionDialog extends org.eclipse.ui.dialogs.SelectionStatusDialog {
  private static final java.lang.String DIALOG_BOUNDS_SETTINGS;

  private static final java.lang.String SHOW_STATUS_LINE;

  private static final java.lang.String HISTORY_SETTINGS;

  private static final java.lang.String DIALOG_HEIGHT;

  private static final java.lang.String DIALOG_WIDTH;

  public static final int NONE;

  public static final int CARET_BEGINNING;

  public static final int FULL_SELECTION;

  private org.eclipse.swt.widgets.Text pattern;

  private org.eclipse.jface.viewers.TableViewer tableViewer;

  private org.eclipse.ui.dialogs.FilteredItemsSelectionDialog$DetailsContentViewer details;

  private org.eclipse.jface.viewers.ILabelProvider detailsLabelProvider;

  private org.eclipse.ui.dialogs.FilteredItemsSelectionDialog$ItemsListLabelProvider itemsListLabelProvider;

  private org.eclipse.jface.action.MenuManager menuManager;

  private org.eclipse.jface.action.MenuManager contextMenuManager;

  private boolean multi;

  private org.eclipse.swt.widgets.ToolBar toolBar;

  private org.eclipse.swt.widgets.ToolItem toolItem;

  private org.eclipse.swt.widgets.Label progressLabel;

  private org.eclipse.ui.dialogs.FilteredItemsSelectionDialog$ToggleStatusLineAction toggleStatusLineAction;

  private org.eclipse.ui.dialogs.FilteredItemsSelectionDialog$RemoveHistoryItemAction removeHistoryItemAction;

  private org.eclipse.jface.action.ActionContributionItem removeHistoryActionContributionItem;

  private org.eclipse.core.runtime.IStatus status;

  private org.eclipse.ui.dialogs.FilteredItemsSelectionDialog$RefreshCacheJob refreshCacheJob;

  private org.eclipse.ui.dialogs.FilteredItemsSelectionDialog$RefreshProgressMessageJob refreshProgressMessageJob;

  private java.lang.Object[] currentSelection;

  private org.eclipse.ui.dialogs.FilteredItemsSelectionDialog$ContentProvider contentProvider;

  private org.eclipse.ui.dialogs.FilteredItemsSelectionDialog$FilterHistoryJob filterHistoryJob;

  private org.eclipse.ui.dialogs.FilteredItemsSelectionDialog$FilterJob filterJob;

  private org.eclipse.ui.dialogs.FilteredItemsSelectionDialog$ItemsFilter filter;

  private org.eclipse.ui.dialogs.FilteredItemsSelectionDialog$ItemsFilter currentlyCompletingFilter;

  private java.util.List<java.lang.Object> lastCompletedResult;

  private org.eclipse.ui.dialogs.FilteredItemsSelectionDialog$ItemsFilter lastCompletedFilter;

  private java.lang.String initialPatternText;

  private int selectionMode;

  private org.eclipse.ui.dialogs.FilteredItemsSelectionDialog$ItemsListSeparator itemsListSeparator;

  private static final java.lang.String EMPTY_STRING;

  private boolean refreshWithLastSelection;

  private org.eclipse.ui.handlers.IHandlerActivation showViewHandler;

  private org.eclipse.ui.dialogs.IStyledStringHighlighter styledStringHighlighter;

  private boolean isShownForTheFirstTime;

  public org.eclipse.ui.dialogs.FilteredItemsSelectionDialog(org.eclipse.swt.widgets.Shell, boolean);
    Code:
       0: aload_0
       1: aload_1
       2: invokespecial #1114               // Method org/eclipse/ui/dialogs/SelectionStatusDialog."<init>":(Lorg/eclipse/swt/widgets/Shell;)V
       5: aload_0
       6: new           #466                // class org/eclipse/ui/dialogs/FilteredItemsSelectionDialog$RefreshProgressMessageJob
       9: dup
      10: aload_0
      11: invokespecial #1102               // Method org/eclipse/ui/dialogs/FilteredItemsSelectionDialog$RefreshProgressMessageJob."<init>":(Lorg/eclipse/ui/dialogs/FilteredItemsSelectionDialog;)V
      14: putfield      #912                // Field refreshProgressMessageJob:Lorg/eclipse/ui/dialogs/FilteredItemsSelectionDialog$RefreshProgressMessageJob;
      17: aload_0
      18: iconst_0
      19: putfield      #891                // Field refreshWithLastSelection:Z
      22: aload_0
      23: iconst_1
      24: putfield      #889                // Field isShownForTheFirstTime:Z
      27: aload_0
      28: iload_2
      29: putfield      #890                // Field multi:Z
      32: aload_0
      33: new           #457                // class org/eclipse/ui/dialogs/FilteredItemsSelectionDialog$FilterHistoryJob
      36: dup
      37: aload_0
      38: invokespecial #1085               // Method org/eclipse/ui/dialogs/FilteredItemsSelectionDialog$FilterHistoryJob."<init>":(Lorg/eclipse/ui/dialogs/FilteredItemsSelectionDialog;)V
      41: putfield      #906                // Field filterHistoryJob:Lorg/eclipse/ui/dialogs/FilteredItemsSelectionDialog$FilterHistoryJob;
      44: aload_0
      45: new           #458                // class org/eclipse/ui/dialogs/FilteredItemsSelectionDialog$FilterJob
      48: dup
      49: aload_0
      50: invokespecial #1088               // Method org/eclipse/ui/dialogs/FilteredItemsSelectionDialog$FilterJob."<init>":(Lorg/eclipse/ui/dialogs/FilteredItemsSelectionDialog;)V
      53: putfield      #907                // Field filterJob:Lorg/eclipse/ui/dialogs/FilteredItemsSelectionDialog$FilterJob;
      56: aload_0
      57: new           #455                // class org/eclipse/ui/dialogs/FilteredItemsSelectionDialog$ContentProvider
      60: dup
      61: aload_0
      62: invokespecial #1074               // Method org/eclipse/ui/dialogs/FilteredItemsSelectionDialog$ContentProvider."<init>":(Lorg/eclipse/ui/dialogs/FilteredItemsSelectionDialog;)V
      65: putfield      #904                // Field contentProvider:Lorg/eclipse/ui/dialogs/FilteredItemsSelectionDialog$ContentProvider;
      68: aload_0
      69: new           #464                // class org/eclipse/ui/dialogs/FilteredItemsSelectionDialog$RefreshCacheJob
      72: dup
      73: aload_0
      74: invokespecial #1099               // Method org/eclipse/ui/dialogs/FilteredItemsSelectionDialog$RefreshCacheJob."<init>":(Lorg/eclipse/ui/dialogs/FilteredItemsSelectionDialog;)V
      77: putfield      #911                // Field refreshCacheJob:Lorg/eclipse/ui/dialogs/FilteredItemsSelectionDialog$RefreshCacheJob;
      80: aload_0
      81: new           #463                // class org/eclipse/ui/dialogs/FilteredItemsSelectionDialog$ItemsListSeparator
      84: dup
      85: getstatic     #923                // Field org/eclipse/ui/internal/WorkbenchMessages.FilteredItemsSelectionDialog_separatorLabel:Ljava/lang/String;
      88: invokespecial #1095               // Method org/eclipse/ui/dialogs/FilteredItemsSelectionDialog$ItemsListSeparator."<init>":(Ljava/lang/String;)V
      91: putfield      #910                // Field itemsListSeparator:Lorg/eclipse/ui/dialogs/FilteredItemsSelectionDialog$ItemsListSeparator;
      94: aload_0
      95: iconst_0
      96: putfield      #888                // Field selectionMode:I
      99: return

  public org.eclipse.ui.dialogs.FilteredItemsSelectionDialog(org.eclipse.swt.widgets.Shell);
    Code:
       0: aload_0
       1: aload_1
       2: iconst_0
       3: invokespecial #1049               // Method "<init>":(Lorg/eclipse/swt/widgets/Shell;Z)V
       6: return

  protected void addListFilter(org.eclipse.jface.viewers.ViewerFilter);
    Code:
       0: aload_0
       1: getfield      #904                // Field contentProvider:Lorg/eclipse/ui/dialogs/FilteredItemsSelectionDialog$ContentProvider;
       4: aload_1
       5: invokevirtual #1071               // Method org/eclipse/ui/dialogs/FilteredItemsSelectionDialog$ContentProvider.addFilter:(Lorg/eclipse/jface/viewers/ViewerFilter;)V
       8: return

  public void setListLabelProvider(org.eclipse.jface.viewers.ILabelProvider);
    Code:
       0: aload_0
       1: invokevirtual #1051               // Method getItemsListLabelProvider:()Lorg/eclipse/ui/dialogs/FilteredItemsSelectionDialog$ItemsListLabelProvider;
       4: aload_1
       5: invokevirtual #1093               // Method org/eclipse/ui/dialogs/FilteredItemsSelectionDialog$ItemsListLabelProvider.setProvider:(Lorg/eclipse/jface/viewers/ILabelProvider;)V
       8: return

  private org.eclipse.jface.viewers.ILabelDecorator getListSelectionLabelDecorator();
    Code:
       0: aload_0
       1: invokevirtual #1051               // Method getItemsListLabelProvider:()Lorg/eclipse/ui/dialogs/FilteredItemsSelectionDialog$ItemsListLabelProvider;
       4: invokevirtual #1091               // Method org/eclipse/ui/dialogs/FilteredItemsSelectionDialog$ItemsListLabelProvider.getSelectionDecorator:()Lorg/eclipse/jface/viewers/ILabelDecorator;
       7: areturn

  public void setListSelectionLabelDecorator(org.eclipse.jface.viewers.ILabelDecorator);
    Code:
       0: aload_0
       1: invokevirtual #1051               // Method getItemsListLabelProvider:()Lorg/eclipse/ui/dialogs/FilteredItemsSelectionDialog$ItemsListLabelProvider;
       4: aload_1
       5: invokevirtual #1092               // Method org/eclipse/ui/dialogs/FilteredItemsSelectionDialog$ItemsListLabelProvider.setSelectionDecorator:(Lorg/eclipse/jface/viewers/ILabelDecorator;)V
       8: return

  private org.eclipse.ui.dialogs.FilteredItemsSelectionDialog$ItemsListLabelProvider getItemsListLabelProvider();
    Code:
       0: aload_0
       1: getfield      #909                // Field itemsListLabelProvider:Lorg/eclipse/ui/dialogs/FilteredItemsSelectionDialog$ItemsListLabelProvider;
       4: ifnonnull     28
       7: aload_0
       8: new           #462                // class org/eclipse/ui/dialogs/FilteredItemsSelectionDialog$ItemsListLabelProvider
      11: dup
      12: aload_0
      13: new           #471                // class org/eclipse/ui/dialogs/FilteredItemsSelectionDialog$TypeItemLabelProvider
      16: dup
      17: aload_0
      18: invokespecial #1109               // Method org/eclipse/ui/dialogs/FilteredItemsSelectionDialog$TypeItemLabelProvider."<init>":(Lorg/eclipse/ui/dialogs/FilteredItemsSelectionDialog;)V
      21: aconst_null
      22: invokespecial #1094               // Method org/eclipse/ui/dialogs/FilteredItemsSelectionDialog$ItemsListLabelProvider."<init>":(Lorg/eclipse/ui/dialogs/FilteredItemsSelectionDialog;Lorg/eclipse/jface/viewers/ILabelProvider;Lorg/eclipse/jface/viewers/ILabelDecorator;)V
      25: putfield      #909                // Field itemsListLabelProvider:Lorg/eclipse/ui/dialogs/FilteredItemsSelectionDialog$ItemsListLabelProvider;
      28: aload_0
      29: getfield      #909                // Field itemsListLabelProvider:Lorg/eclipse/ui/dialogs/FilteredItemsSelectionDialog$ItemsListLabelProvider;
      32: areturn

  public void setDetailsLabelProvider(org.eclipse.jface.viewers.ILabelProvider);
    Code:
       0: aload_0
       1: aload_1
       2: putfield      #898                // Field detailsLabelProvider:Lorg/eclipse/jface/viewers/ILabelProvider;
       5: aload_0
       6: getfield      #905                // Field details:Lorg/eclipse/ui/dialogs/FilteredItemsSelectionDialog$DetailsContentViewer;
       9: ifnull        20
      12: aload_0
      13: getfield      #905                // Field details:Lorg/eclipse/ui/dialogs/FilteredItemsSelectionDialog$DetailsContentViewer;
      16: aload_1
      17: invokevirtual #1080               // Method org/eclipse/ui/dialogs/FilteredItemsSelectionDialog$DetailsContentViewer.setLabelProvider:(Lorg/eclipse/jface/viewers/IBaseLabelProvider;)V
      20: return

  private org.eclipse.jface.viewers.ILabelProvider getDetailsLabelProvider();
    Code:
       0: aload_0
       1: getfield      #898                // Field detailsLabelProvider:Lorg/eclipse/jface/viewers/ILabelProvider;
       4: ifnonnull     18
       7: aload_0
       8: new           #421                // class org/eclipse/jface/viewers/LabelProvider
      11: dup
      12: invokespecial #943                // Method org/eclipse/jface/viewers/LabelProvider."<init>":()V
      15: putfield      #898                // Field detailsLabelProvider:Lorg/eclipse/jface/viewers/ILabelProvider;
      18: aload_0
      19: getfield      #898                // Field detailsLabelProvider:Lorg/eclipse/jface/viewers/ILabelProvider;
      22: areturn

  public void create();
    Code:
       0: aload_0
       1: invokespecial #1110               // Method org/eclipse/ui/dialogs/SelectionStatusDialog.create:()V
       4: aload_0
       5: getfield      #901                // Field pattern:Lorg/eclipse/swt/widgets/Text;
       8: invokevirtual #992                // Method org/eclipse/swt/widgets/Text.setFocus:()Z
      11: pop
      12: return

  protected void restoreDialog(org.eclipse.jface.dialogs.IDialogSettings);
    Code:
       0: iconst_1
       1: istore_2
       2: aload_1
       3: ldc           #6                  // String ShowStatusLine
       5: invokeinterface #1136,  2         // InterfaceMethod org/eclipse/jface/dialogs/IDialogSettings.get:(Ljava/lang/String;)Ljava/lang/String;
      10: ifnull        22
      13: aload_1
      14: ldc           #6                  // String ShowStatusLine
      16: invokeinterface #1133,  2         // InterfaceMethod org/eclipse/jface/dialogs/IDialogSettings.getBoolean:(Ljava/lang/String;)Z
      21: istore_2
      22: aload_0
      23: getfield      #914                // Field toggleStatusLineAction:Lorg/eclipse/ui/dialogs/FilteredItemsSelectionDialog$ToggleStatusLineAction;
      26: iload_2
      27: invokevirtual #1107               // Method org/eclipse/ui/dialogs/FilteredItemsSelectionDialog$ToggleStatusLineAction.setChecked:(Z)V
      30: aload_0
      31: getfield      #905                // Field details:Lorg/eclipse/ui/dialogs/FilteredItemsSelectionDialog$DetailsContentViewer;
      34: iload_2
      35: invokevirtual #1078               // Method org/eclipse/ui/dialogs/FilteredItemsSelectionDialog$DetailsContentViewer.setVisible:(Z)V
      38: aload_1
      39: ldc           #5                  // String History
      41: invokeinterface #1136,  2         // InterfaceMethod org/eclipse/jface/dialogs/IDialogSettings.get:(Ljava/lang/String;)Ljava/lang/String;
      46: astore_3
      47: aload_3
      48: ifnull        101
      51: new           #399                // class java/io/StringReader
      54: dup
      55: aload_3
      56: invokespecial #925                // Method java/io/StringReader."<init>":(Ljava/lang/String;)V
      59: invokestatic  #1013               // Method org/eclipse/ui/XMLMemento.createReadRoot:(Ljava/io/Reader;)Lorg/eclipse/ui/XMLMemento;
      62: astore        4
      64: aload_0
      65: getfield      #904                // Field contentProvider:Lorg/eclipse/ui/dialogs/FilteredItemsSelectionDialog$ContentProvider;
      68: aload         4
      70: invokevirtual #1072               // Method org/eclipse/ui/dialogs/FilteredItemsSelectionDialog$ContentProvider.loadHistory:(Lorg/eclipse/ui/IMemento;)V
      73: goto          101
      76: astore        4
      78: invokestatic  #1119               // Method org/eclipse/ui/statushandlers/StatusManager.getManager:()Lorg/eclipse/ui/statushandlers/StatusManager;
      81: new           #414                // class org/eclipse/core/runtime/Status
      84: dup
      85: iconst_4
      86: ldc_w         #395                // String org.eclipse.ui
      89: iconst_4
      90: getstatic     #922                // Field org/eclipse/ui/internal/WorkbenchMessages.FilteredItemsSelectionDialog_restoreError:Ljava/lang/String;
      93: aload         4
      95: invokespecial #936                // Method org/eclipse/core/runtime/Status."<init>":(ILjava/lang/String;ILjava/lang/String;Ljava/lang/Throwable;)V
      98: invokevirtual #1118               // Method org/eclipse/ui/statushandlers/StatusManager.handle:(Lorg/eclipse/core/runtime/IStatus;)V
     101: return
    Exception table:
       from    to  target type
          51    73    76   Class org/eclipse/ui/WorkbenchException

  public boolean close();
    Code:
       0: aload_0
       1: getfield      #907                // Field filterJob:Lorg/eclipse/ui/dialogs/FilteredItemsSelectionDialog$FilterJob;
       4: invokevirtual #1087               // Method org/eclipse/ui/dialogs/FilteredItemsSelectionDialog$FilterJob.cancel:()Z
       7: pop
       8: aload_0
       9: getfield      #911                // Field refreshCacheJob:Lorg/eclipse/ui/dialogs/FilteredItemsSelectionDialog$RefreshCacheJob;
      12: invokevirtual #1098               // Method org/eclipse/ui/dialogs/FilteredItemsSelectionDialog$RefreshCacheJob.cancel:()Z
      15: pop
      16: aload_0
      17: getfield      #912                // Field refreshProgressMessageJob:Lorg/eclipse/ui/dialogs/FilteredItemsSelectionDialog$RefreshProgressMessageJob;
      20: invokevirtual #1101               // Method org/eclipse/ui/dialogs/FilteredItemsSelectionDialog$RefreshProgressMessageJob.cancel:()Z
      23: pop
      24: aload_0
      25: getfield      #916                // Field showViewHandler:Lorg/eclipse/ui/handlers/IHandlerActivation;
      28: ifnull        75
      31: invokestatic  #1011               // Method org/eclipse/ui/PlatformUI.getWorkbench:()Lorg/eclipse/ui/IWorkbench;
      34: ldc_w         #475                // class org/eclipse/ui/handlers/IHandlerService
      37: invokeinterface #1143,  2         // InterfaceMethod org/eclipse/ui/IWorkbench.getService:(Ljava/lang/Class;)Ljava/lang/Object;
      42: checkcast     #475                // class org/eclipse/ui/handlers/IHandlerService
      45: astore_1
      46: aload_1
      47: aload_0
      48: getfield      #916                // Field showViewHandler:Lorg/eclipse/ui/handlers/IHandlerActivation;
      51: invokeinterface #1145,  2         // InterfaceMethod org/eclipse/ui/handlers/IHandlerService.deactivateHandler:(Lorg/eclipse/ui/handlers/IHandlerActivation;)V
      56: aload_0
      57: getfield      #916                // Field showViewHandler:Lorg/eclipse/ui/handlers/IHandlerActivation;
      60: invokeinterface #1144,  1         // InterfaceMethod org/eclipse/ui/handlers/IHandlerActivation.getHandler:()Lorg/eclipse/core/commands/IHandler;
      65: invokeinterface #1128,  1         // InterfaceMethod org/eclipse/core/commands/IHandler.dispose:()V
      70: aload_0
      71: aconst_null
      72: putfield      #916                // Field showViewHandler:Lorg/eclipse/ui/handlers/IHandlerActivation;
      75: aload_0
      76: getfield      #897                // Field menuManager:Lorg/eclipse/jface/action/MenuManager;
      79: ifnull        89
      82: aload_0
      83: getfield      #897                // Field menuManager:Lorg/eclipse/jface/action/MenuManager;
      86: invokevirtual #939                // Method org/eclipse/jface/action/MenuManager.dispose:()V
      89: aload_0
      90: getfield      #896                // Field contextMenuManager:Lorg/eclipse/jface/action/MenuManager;
      93: ifnull        103
      96: aload_0
      97: getfield      #896                // Field contextMenuManager:Lorg/eclipse/jface/action/MenuManager;
     100: invokevirtual #939                // Method org/eclipse/jface/action/MenuManager.dispose:()V
     103: aload_0
     104: aload_0
     105: invokevirtual #1031               // Method getDialogSettings:()Lorg/eclipse/jface/dialogs/IDialogSettings;
     108: invokevirtual #1033               // Method storeDialog:(Lorg/eclipse/jface/dialogs/IDialogSettings;)V
     111: aload_0
     112: invokespecial #1112               // Method org/eclipse/ui/dialogs/SelectionStatusDialog.close:()Z
     115: ireturn

  protected void storeDialog(org.eclipse.jface.dialogs.IDialogSettings);
    Code:
       0: aload_1
       1: ldc           #6                  // String ShowStatusLine
       3: aload_0
       4: getfield      #914                // Field toggleStatusLineAction:Lorg/eclipse/ui/dialogs/FilteredItemsSelectionDialog$ToggleStatusLineAction;
       7: invokevirtual #1106               // Method org/eclipse/ui/dialogs/FilteredItemsSelectionDialog$ToggleStatusLineAction.isChecked:()Z
      10: invokeinterface #1135,  3         // InterfaceMethod org/eclipse/jface/dialogs/IDialogSettings.put:(Ljava/lang/String;Z)V
      15: ldc           #5                  // String History
      17: invokestatic  #1014               // Method org/eclipse/ui/XMLMemento.createWriteRoot:(Ljava/lang/String;)Lorg/eclipse/ui/XMLMemento;
      20: astore_2
      21: aload_0
      22: getfield      #904                // Field contentProvider:Lorg/eclipse/ui/dialogs/FilteredItemsSelectionDialog$ContentProvider;
      25: aload_2
      26: invokevirtual #1073               // Method org/eclipse/ui/dialogs/FilteredItemsSelectionDialog$ContentProvider.saveHistory:(Lorg/eclipse/ui/IMemento;)V
      29: new           #400                // class java/io/StringWriter
      32: dup
      33: invokespecial #926                // Method java/io/StringWriter."<init>":()V
      36: astore_3
      37: aload_2
      38: aload_3
      39: invokevirtual #1012               // Method org/eclipse/ui/XMLMemento.save:(Ljava/io/Writer;)V
      42: aload_1
      43: ldc           #5                  // String History
      45: aload_3
      46: invokevirtual #927                // Method java/io/StringWriter.getBuffer:()Ljava/lang/StringBuffer;
      49: invokevirtual #931                // Method java/lang/StringBuffer.toString:()Ljava/lang/String;
      52: invokeinterface #1137,  3         // InterfaceMethod org/eclipse/jface/dialogs/IDialogSettings.put:(Ljava/lang/String;Ljava/lang/String;)V
      57: goto          85
      60: astore        4
      62: invokestatic  #1119               // Method org/eclipse/ui/statushandlers/StatusManager.getManager:()Lorg/eclipse/ui/statushandlers/StatusManager;
      65: new           #414                // class org/eclipse/core/runtime/Status
      68: dup
      69: iconst_4
      70: ldc_w         #395                // String org.eclipse.ui
      73: iconst_4
      74: getstatic     #924                // Field org/eclipse/ui/internal/WorkbenchMessages.FilteredItemsSelectionDialog_storeError:Ljava/lang/String;
      77: aload         4
      79: invokespecial #936                // Method org/eclipse/core/runtime/Status."<init>":(ILjava/lang/String;ILjava/lang/String;Ljava/lang/Throwable;)V
      82: invokevirtual #1118               // Method org/eclipse/ui/statushandlers/StatusManager.handle:(Lorg/eclipse/core/runtime/IStatus;)V
      85: return
    Exception table:
       from    to  target type
          37    57    60   Class java/io/IOException

  private org.eclipse.swt.widgets.Label createHeader(org.eclipse.swt.widgets.Composite);
    Code:
       0: new           #433                // class org/eclipse/swt/widgets/Composite
       3: dup
       4: aload_1
       5: iconst_0
       6: invokespecial #972                // Method org/eclipse/swt/widgets/Composite."<init>":(Lorg/eclipse/swt/widgets/Composite;I)V
       9: astore_2
      10: new           #432                // class org/eclipse/swt/layout/GridLayout
      13: dup
      14: invokespecial #970                // Method org/eclipse/swt/layout/GridLayout."<init>":()V
      17: astore_3
      18: aload_3
      19: iconst_2
      20: putfield      #887                // Field org/eclipse/swt/layout/GridLayout.numColumns:I
      23: aload_3
      24: iconst_0
      25: putfield      #886                // Field org/eclipse/swt/layout/GridLayout.marginWidth:I
      28: aload_3
      29: iconst_0
      30: putfield      #885                // Field org/eclipse/swt/layout/GridLayout.marginHeight:I
      33: aload_2
      34: aload_3
      35: invokevirtual #973                // Method org/eclipse/swt/widgets/Composite.setLayout:(Lorg/eclipse/swt/widgets/Layout;)V
      38: new           #435                // class org/eclipse/swt/widgets/Label
      41: dup
      42: aload_2
      43: iconst_0
      44: invokespecial #978                // Method org/eclipse/swt/widgets/Label."<init>":(Lorg/eclipse/swt/widgets/Composite;I)V
      47: astore        4
      49: aload         4
      51: aload_0
      52: invokevirtual #1024               // Method getMessage:()Ljava/lang/String;
      55: ifnull        78
      58: aload_0
      59: invokevirtual #1024               // Method getMessage:()Ljava/lang/String;
      62: invokevirtual #930                // Method java/lang/String.trim:()Ljava/lang/String;
      65: invokevirtual #929                // Method java/lang/String.length:()I
      68: ifle          78
      71: aload_0
      72: invokevirtual #1024               // Method getMessage:()Ljava/lang/String;
      75: goto          81
      78: getstatic     #920                // Field org/eclipse/ui/internal/WorkbenchMessages.FilteredItemsSelectionDialog_patternLabel:Ljava/lang/String;
      81: invokevirtual #976                // Method org/eclipse/swt/widgets/Label.setText:(Ljava/lang/String;)V
      84: aload         4
      86: aload_0
      87: invokedynamic #1167,  0           // InvokeDynamic #5:keyTraversed:(Lorg/eclipse/ui/dialogs/FilteredItemsSelectionDialog;)Lorg/eclipse/swt/events/TraverseListener;
      92: invokevirtual #977                // Method org/eclipse/swt/widgets/Label.addTraverseListener:(Lorg/eclipse/swt/events/TraverseListener;)V
      95: new           #431                // class org/eclipse/swt/layout/GridData
      98: dup
      99: sipush        768
     102: invokespecial #969                // Method org/eclipse/swt/layout/GridData."<init>":(I)V
     105: astore        5
     107: aload         4
     109: aload         5
     111: invokevirtual #975                // Method org/eclipse/swt/widgets/Label.setLayoutData:(Ljava/lang/Object;)V
     114: aload_0
     115: aload_2
     116: invokevirtual #1044               // Method createViewMenu:(Lorg/eclipse/swt/widgets/Composite;)V
     119: aload_2
     120: aload         5
     122: invokevirtual #971                // Method org/eclipse/swt/widgets/Composite.setLayoutData:(Ljava/lang/Object;)V
     125: aload         4
     127: areturn

  private org.eclipse.swt.widgets.Label createLabels(org.eclipse.swt.widgets.Composite);
    Code:
       0: new           #433                // class org/eclipse/swt/widgets/Composite
       3: dup
       4: aload_1
       5: iconst_0
       6: invokespecial #972                // Method org/eclipse/swt/widgets/Composite."<init>":(Lorg/eclipse/swt/widgets/Composite;I)V
       9: astore_2
      10: new           #432                // class org/eclipse/swt/layout/GridLayout
      13: dup
      14: invokespecial #970                // Method org/eclipse/swt/layout/GridLayout."<init>":()V
      17: astore_3
      18: aload_3
      19: iconst_2
      20: putfield      #887                // Field org/eclipse/swt/layout/GridLayout.numColumns:I
      23: aload_3
      24: iconst_0
      25: putfield      #886                // Field org/eclipse/swt/layout/GridLayout.marginWidth:I
      28: aload_3
      29: iconst_0
      30: putfield      #885                // Field org/eclipse/swt/layout/GridLayout.marginHeight:I
      33: aload_2
      34: aload_3
      35: invokevirtual #973                // Method org/eclipse/swt/widgets/Composite.setLayout:(Lorg/eclipse/swt/widgets/Layout;)V
      38: new           #435                // class org/eclipse/swt/widgets/Label
      41: dup
      42: aload_2
      43: iconst_0
      44: invokespecial #978                // Method org/eclipse/swt/widgets/Label."<init>":(Lorg/eclipse/swt/widgets/Composite;I)V
      47: astore        4
      49: aload         4
      51: getstatic     #917                // Field org/eclipse/ui/internal/WorkbenchMessages.FilteredItemsSelectionDialog_listLabel:Ljava/lang/String;
      54: invokevirtual #976                // Method org/eclipse/swt/widgets/Label.setText:(Ljava/lang/String;)V
      57: aload         4
      59: aload_0
      60: invokedynamic #1168,  0           // InvokeDynamic #6:keyTraversed:(Lorg/eclipse/ui/dialogs/FilteredItemsSelectionDialog;)Lorg/eclipse/swt/events/TraverseListener;
      65: invokevirtual #977                // Method org/eclipse/swt/widgets/Label.addTraverseListener:(Lorg/eclipse/swt/events/TraverseListener;)V
      68: new           #431                // class org/eclipse/swt/layout/GridData
      71: dup
      72: sipush        768
      75: invokespecial #969                // Method org/eclipse/swt/layout/GridData."<init>":(I)V
      78: astore        5
      80: aload         4
      82: aload         5
      84: invokevirtual #975                // Method org/eclipse/swt/widgets/Label.setLayoutData:(Ljava/lang/Object;)V
      87: aload_0
      88: new           #435                // class org/eclipse/swt/widgets/Label
      91: dup
      92: aload_2
      93: ldc_w         #389                // int 131072
      96: invokespecial #978                // Method org/eclipse/swt/widgets/Label."<init>":(Lorg/eclipse/swt/widgets/Composite;I)V
      99: putfield      #900                // Field progressLabel:Lorg/eclipse/swt/widgets/Label;
     102: aload_0
     103: getfield      #900                // Field progressLabel:Lorg/eclipse/swt/widgets/Label;
     106: aload         5
     108: invokevirtual #975                // Method org/eclipse/swt/widgets/Label.setLayoutData:(Ljava/lang/Object;)V
     111: aload_2
     112: aload         5
     114: invokevirtual #971                // Method org/eclipse/swt/widgets/Composite.setLayoutData:(Ljava/lang/Object;)V
     117: aload         4
     119: areturn

  private void createViewMenu(org.eclipse.swt.widgets.Composite);
    Code:
       0: aload_0
       1: new           #439                // class org/eclipse/swt/widgets/ToolBar
       4: dup
       5: aload_1
       6: ldc_w         #390                // int 8388608
       9: invokespecial #1002               // Method org/eclipse/swt/widgets/ToolBar."<init>":(Lorg/eclipse/swt/widgets/Composite;I)V
      12: putfield      #902                // Field toolBar:Lorg/eclipse/swt/widgets/ToolBar;
      15: aload_0
      16: new           #440                // class org/eclipse/swt/widgets/ToolItem
      19: dup
      20: aload_0
      21: getfield      #902                // Field toolBar:Lorg/eclipse/swt/widgets/ToolBar;
      24: bipush        8
      26: iconst_0
      27: invokespecial #1008               // Method org/eclipse/swt/widgets/ToolItem."<init>":(Lorg/eclipse/swt/widgets/ToolBar;II)V
      30: putfield      #903                // Field toolItem:Lorg/eclipse/swt/widgets/ToolItem;
      33: new           #431                // class org/eclipse/swt/layout/GridData
      36: dup
      37: invokespecial #968                // Method org/eclipse/swt/layout/GridData."<init>":()V
      40: astore_2
      41: aload_2
      42: iconst_3
      43: putfield      #884                // Field org/eclipse/swt/layout/GridData.horizontalAlignment:I
      46: aload_0
      47: getfield      #902                // Field toolBar:Lorg/eclipse/swt/widgets/ToolBar;
      50: aload_2
      51: invokevirtual #1000               // Method org/eclipse/swt/widgets/ToolBar.setLayoutData:(Ljava/lang/Object;)V
      54: aload_0
      55: getfield      #902                // Field toolBar:Lorg/eclipse/swt/widgets/ToolBar;
      58: new           #447                // class org/eclipse/ui/dialogs/FilteredItemsSelectionDialog$1
      61: dup
      62: aload_0
      63: invokespecial #1058               // Method org/eclipse/ui/dialogs/FilteredItemsSelectionDialog$1."<init>":(Lorg/eclipse/ui/dialogs/FilteredItemsSelectionDialog;)V
      66: invokevirtual #1001               // Method org/eclipse/swt/widgets/ToolBar.addMouseListener:(Lorg/eclipse/swt/events/MouseListener;)V
      69: aload_0
      70: getfield      #903                // Field toolItem:Lorg/eclipse/swt/widgets/ToolItem;
      73: ldc_w         #393                // String IMG_LCL_VIEW_MENU
      76: invokestatic  #1117               // Method org/eclipse/ui/internal/WorkbenchImages.getImage:(Ljava/lang/String;)Lorg/eclipse/swt/graphics/Image;
      79: invokevirtual #1006               // Method org/eclipse/swt/widgets/ToolItem.setImage:(Lorg/eclipse/swt/graphics/Image;)V
      82: aload_0
      83: getfield      #903                // Field toolItem:Lorg/eclipse/swt/widgets/ToolItem;
      86: getstatic     #918                // Field org/eclipse/ui/internal/WorkbenchMessages.FilteredItemsSelectionDialog_menu:Ljava/lang/String;
      89: invokevirtual #1004               // Method org/eclipse/swt/widgets/ToolItem.setToolTipText:(Ljava/lang/String;)V
      92: aload_0
      93: getfield      #903                // Field toolItem:Lorg/eclipse/swt/widgets/ToolItem;
      96: aload_0
      97: invokedynamic #1162,  0           // InvokeDynamic #0:accept:(Lorg/eclipse/ui/dialogs/FilteredItemsSelectionDialog;)Ljava/util/function/Consumer;
     102: invokestatic  #1142               // InterfaceMethod org/eclipse/swt/events/SelectionListener.widgetSelectedAdapter:(Ljava/util/function/Consumer;)Lorg/eclipse/swt/events/SelectionListener;
     105: invokevirtual #1005               // Method org/eclipse/swt/widgets/ToolItem.addSelectionListener:(Lorg/eclipse/swt/events/SelectionListener;)V
     108: aload_0
     109: new           #417                // class org/eclipse/jface/action/MenuManager
     112: dup
     113: invokespecial #938                // Method org/eclipse/jface/action/MenuManager."<init>":()V
     116: putfield      #897                // Field menuManager:Lorg/eclipse/jface/action/MenuManager;
     119: aload_0
     120: aload_0
     121: getfield      #897                // Field menuManager:Lorg/eclipse/jface/action/MenuManager;
     124: invokevirtual #1030               // Method fillViewMenu:(Lorg/eclipse/jface/action/IMenuManager;)V
     127: invokestatic  #1011               // Method org/eclipse/ui/PlatformUI.getWorkbench:()Lorg/eclipse/ui/IWorkbench;
     130: ldc_w         #475                // class org/eclipse/ui/handlers/IHandlerService
     133: invokeinterface #1143,  2         // InterfaceMethod org/eclipse/ui/IWorkbench.getService:(Ljava/lang/Class;)Ljava/lang/Object;
     138: checkcast     #475                // class org/eclipse/ui/handlers/IHandlerService
     141: astore_3
     142: new           #448                // class org/eclipse/ui/dialogs/FilteredItemsSelectionDialog$2
     145: dup
     146: aload_0
     147: invokespecial #1059               // Method org/eclipse/ui/dialogs/FilteredItemsSelectionDialog$2."<init>":(Lorg/eclipse/ui/dialogs/FilteredItemsSelectionDialog;)V
     150: astore        4
     152: aload_0
     153: aload_3
     154: ldc_w         #396                // String org.eclipse.ui.window.showViewMenu
     157: aload         4
     159: new           #441                // class org/eclipse/ui/ActiveShellExpression
     162: dup
     163: aload_0
     164: invokevirtual #1048               // Method getShell:()Lorg/eclipse/swt/widgets/Shell;
     167: invokespecial #1009               // Method org/eclipse/ui/ActiveShellExpression."<init>":(Lorg/eclipse/swt/widgets/Shell;)V
     170: invokeinterface #1146,  4         // InterfaceMethod org/eclipse/ui/handlers/IHandlerService.activateHandler:(Ljava/lang/String;Lorg/eclipse/core/commands/IHandler;Lorg/eclipse/core/expressions/Expression;)Lorg/eclipse/ui/handlers/IHandlerActivation;
     175: putfield      #916                // Field showViewHandler:Lorg/eclipse/ui/handlers/IHandlerActivation;
     178: return

  protected void fillViewMenu(org.eclipse.jface.action.IMenuManager);
    Code:
       0: aload_0
       1: new           #470                // class org/eclipse/ui/dialogs/FilteredItemsSelectionDialog$ToggleStatusLineAction
       4: dup
       5: aload_0
       6: invokespecial #1108               // Method org/eclipse/ui/dialogs/FilteredItemsSelectionDialog$ToggleStatusLineAction."<init>":(Lorg/eclipse/ui/dialogs/FilteredItemsSelectionDialog;)V
       9: putfield      #914                // Field toggleStatusLineAction:Lorg/eclipse/ui/dialogs/FilteredItemsSelectionDialog$ToggleStatusLineAction;
      12: aload_1
      13: aload_0
      14: getfield      #914                // Field toggleStatusLineAction:Lorg/eclipse/ui/dialogs/FilteredItemsSelectionDialog$ToggleStatusLineAction;
      17: invokeinterface #1131,  2         // InterfaceMethod org/eclipse/jface/action/IMenuManager.add:(Lorg/eclipse/jface/action/IAction;)V
      22: return

  private void showViewMenu();
    Code:
       0: aload_0
       1: getfield      #897                // Field menuManager:Lorg/eclipse/jface/action/MenuManager;
       4: aload_0
       5: invokevirtual #1048               // Method getShell:()Lorg/eclipse/swt/widgets/Shell;
       8: invokevirtual #942                // Method org/eclipse/jface/action/MenuManager.createContextMenu:(Lorg/eclipse/swt/widgets/Control;)Lorg/eclipse/swt/widgets/Menu;
      11: astore_1
      12: aload_0
      13: getfield      #903                // Field toolItem:Lorg/eclipse/swt/widgets/ToolItem;
      16: invokevirtual #1007               // Method org/eclipse/swt/widgets/ToolItem.getBounds:()Lorg/eclipse/swt/graphics/Rectangle;
      19: astore_2
      20: new           #429                // class org/eclipse/swt/graphics/Point
      23: dup
      24: aload_2
      25: getfield      #881                // Field org/eclipse/swt/graphics/Rectangle.x:I
      28: aload_2
      29: getfield      #882                // Field org/eclipse/swt/graphics/Rectangle.y:I
      32: aload_2
      33: getfield      #880                // Field org/eclipse/swt/graphics/Rectangle.height:I
      36: iadd
      37: invokespecial #967                // Method org/eclipse/swt/graphics/Point."<init>":(II)V
      40: astore_3
      41: aload_0
      42: getfield      #902                // Field toolBar:Lorg/eclipse/swt/widgets/ToolBar;
      45: aload_3
      46: invokevirtual #1003               // Method org/eclipse/swt/widgets/ToolBar.toDisplay:(Lorg/eclipse/swt/graphics/Point;)Lorg/eclipse/swt/graphics/Point;
      49: astore_3
      50: aload_1
      51: aload_3
      52: getfield      #878                // Field org/eclipse/swt/graphics/Point.x:I
      55: aload_3
      56: getfield      #879                // Field org/eclipse/swt/graphics/Point.y:I
      59: invokevirtual #979                // Method org/eclipse/swt/widgets/Menu.setLocation:(II)V
      62: aload_1
      63: iconst_1
      64: invokevirtual #980                // Method org/eclipse/swt/widgets/Menu.setVisible:(Z)V
      67: return

  protected void fillContextMenu(org.eclipse.jface.action.IMenuManager);
    Code:
       0: aload_0
       1: getfield      #899                // Field tableViewer:Lorg/eclipse/jface/viewers/TableViewer;
       4: invokevirtual #961                // Method org/eclipse/jface/viewers/TableViewer.getStructuredSelection:()Lorg/eclipse/jface/viewers/IStructuredSelection;
       7: invokeinterface #1141,  1         // InterfaceMethod org/eclipse/jface/viewers/IStructuredSelection.toList:()Ljava/util/List;
      12: astore_2
      13: aconst_null
      14: astore_3
      15: aload_2
      16: invokeinterface #1127,  1         // InterfaceMethod java/util/List.iterator:()Ljava/util/Iterator;
      21: astore        4
      23: goto          50
      26: aload         4
      28: invokeinterface #1121,  1         // InterfaceMethod java/util/Iterator.next:()Ljava/lang/Object;
      33: astore_3
      34: aload_3
      35: instanceof    #463                // class org/eclipse/ui/dialogs/FilteredItemsSelectionDialog$ItemsListSeparator
      38: ifne          49
      41: aload_0
      42: aload_3
      43: invokevirtual #1023               // Method isHistoryElement:(Ljava/lang/Object;)Z
      46: ifne          50
      49: return
      50: aload         4
      52: invokeinterface #1120,  1         // InterfaceMethod java/util/Iterator.hasNext:()Z
      57: ifne          26
      60: aload_2
      61: invokeinterface #1122,  1         // InterfaceMethod java/util/List.size:()I
      66: ifle          89
      69: aload_0
      70: getfield      #913                // Field removeHistoryItemAction:Lorg/eclipse/ui/dialogs/FilteredItemsSelectionDialog$RemoveHistoryItemAction;
      73: getstatic     #921                // Field org/eclipse/ui/internal/WorkbenchMessages.FilteredItemsSelectionDialog_removeItemsFromHistoryAction:Ljava/lang/String;
      76: invokevirtual #1104               // Method org/eclipse/ui/dialogs/FilteredItemsSelectionDialog$RemoveHistoryItemAction.setText:(Ljava/lang/String;)V
      79: aload_1
      80: aload_0
      81: getfield      #895                // Field removeHistoryActionContributionItem:Lorg/eclipse/jface/action/ActionContributionItem;
      84: invokeinterface #1132,  2         // InterfaceMethod org/eclipse/jface/action/IMenuManager.add:(Lorg/eclipse/jface/action/IContributionItem;)V
      89: return

  private void createPopupMenu();
    Code:
       0: aload_0
       1: new           #467                // class org/eclipse/ui/dialogs/FilteredItemsSelectionDialog$RemoveHistoryItemAction
       4: dup
       5: aload_0
       6: invokespecial #1105               // Method org/eclipse/ui/dialogs/FilteredItemsSelectionDialog$RemoveHistoryItemAction."<init>":(Lorg/eclipse/ui/dialogs/FilteredItemsSelectionDialog;)V
       9: putfield      #913                // Field removeHistoryItemAction:Lorg/eclipse/ui/dialogs/FilteredItemsSelectionDialog$RemoveHistoryItemAction;
      12: aload_0
      13: new           #415                // class org/eclipse/jface/action/ActionContributionItem
      16: dup
      17: aload_0
      18: getfield      #913                // Field removeHistoryItemAction:Lorg/eclipse/ui/dialogs/FilteredItemsSelectionDialog$RemoveHistoryItemAction;
      21: invokespecial #937                // Method org/eclipse/jface/action/ActionContributionItem."<init>":(Lorg/eclipse/jface/action/IAction;)V
      24: putfield      #895                // Field removeHistoryActionContributionItem:Lorg/eclipse/jface/action/ActionContributionItem;
      27: aload_0
      28: new           #417                // class org/eclipse/jface/action/MenuManager
      31: dup
      32: invokespecial #938                // Method org/eclipse/jface/action/MenuManager."<init>":()V
      35: putfield      #896                // Field contextMenuManager:Lorg/eclipse/jface/action/MenuManager;
      38: aload_0
      39: getfield      #896                // Field contextMenuManager:Lorg/eclipse/jface/action/MenuManager;
      42: iconst_1
      43: invokevirtual #940                // Method org/eclipse/jface/action/MenuManager.setRemoveAllWhenShown:(Z)V
      46: aload_0
      47: getfield      #896                // Field contextMenuManager:Lorg/eclipse/jface/action/MenuManager;
      50: aload_0
      51: invokedynamic #1163,  0           // InvokeDynamic #1:menuAboutToShow:(Lorg/eclipse/ui/dialogs/FilteredItemsSelectionDialog;)Lorg/eclipse/jface/action/IMenuListener;
      56: invokevirtual #941                // Method org/eclipse/jface/action/MenuManager.addMenuListener:(Lorg/eclipse/jface/action/IMenuListener;)V
      59: aload_0
      60: getfield      #899                // Field tableViewer:Lorg/eclipse/jface/viewers/TableViewer;
      63: invokevirtual #963                // Method org/eclipse/jface/viewers/TableViewer.getTable:()Lorg/eclipse/swt/widgets/Table;
      66: astore_2
      67: aload_0
      68: getfield      #896                // Field contextMenuManager:Lorg/eclipse/jface/action/MenuManager;
      71: aload_2
      72: invokevirtual #942                // Method org/eclipse/jface/action/MenuManager.createContextMenu:(Lorg/eclipse/swt/widgets/Control;)Lorg/eclipse/swt/widgets/Menu;
      75: astore_3
      76: aload_2
      77: aload_3
      78: invokevirtual #991                // Method org/eclipse/swt/widgets/Table.setMenu:(Lorg/eclipse/swt/widgets/Menu;)V
      81: return

  protected abstract org.eclipse.swt.widgets.Control createExtendedContentArea(org.eclipse.swt.widgets.Composite);

  protected org.eclipse.swt.widgets.Control createDialogArea(org.eclipse.swt.widgets.Composite);
    Code:
       0: aload_0
       1: aload_1
       2: invokespecial #1115               // Method org/eclipse/ui/dialogs/SelectionStatusDialog.createDialogArea:(Lorg/eclipse/swt/widgets/Composite;)Lorg/eclipse/swt/widgets/Control;
       5: checkcast     #433                // class org/eclipse/swt/widgets/Composite
       8: astore_2
       9: new           #433                // class org/eclipse/swt/widgets/Composite
      12: dup
      13: aload_2
      14: iconst_0
      15: invokespecial #972                // Method org/eclipse/swt/widgets/Composite."<init>":(Lorg/eclipse/swt/widgets/Composite;I)V
      18: astore_3
      19: new           #431                // class org/eclipse/swt/layout/GridData
      22: dup
      23: sipush        1808
      26: invokespecial #969                // Method org/eclipse/swt/layout/GridData."<init>":(I)V
      29: astore        4
      31: aload_3
      32: aload         4
      34: invokevirtual #971                // Method org/eclipse/swt/widgets/Composite.setLayoutData:(Ljava/lang/Object;)V
      37: new           #432                // class org/eclipse/swt/layout/GridLayout
      40: dup
      41: invokespecial #970                // Method org/eclipse/swt/layout/GridLayout."<init>":()V
      44: astore        5
      46: aload         5
      48: iconst_1
      49: putfield      #887                // Field org/eclipse/swt/layout/GridLayout.numColumns:I
      52: aload         5
      54: iconst_0
      55: putfield      #886                // Field org/eclipse/swt/layout/GridLayout.marginWidth:I
      58: aload         5
      60: iconst_0
      61: putfield      #885                // Field org/eclipse/swt/layout/GridLayout.marginHeight:I
      64: aload_3
      65: aload         5
      67: invokevirtual #973                // Method org/eclipse/swt/widgets/Composite.setLayout:(Lorg/eclipse/swt/widgets/Layout;)V
      70: aload_0
      71: aload_3
      72: invokevirtual #1056               // Method createHeader:(Lorg/eclipse/swt/widgets/Composite;)Lorg/eclipse/swt/widgets/Label;
      75: astore        6
      77: aload_0
      78: new           #438                // class org/eclipse/swt/widgets/Text
      81: dup
      82: aload_3
      83: sipush        2436
      86: invokespecial #999                // Method org/eclipse/swt/widgets/Text."<init>":(Lorg/eclipse/swt/widgets/Composite;I)V
      89: putfield      #901                // Field pattern:Lorg/eclipse/swt/widgets/Text;
      92: aload_0
      93: getfield      #901                // Field pattern:Lorg/eclipse/swt/widgets/Text;
      96: invokevirtual #996                // Method org/eclipse/swt/widgets/Text.getAccessible:()Lorg/eclipse/swt/accessibility/Accessible;
      99: new           #449                // class org/eclipse/ui/dialogs/FilteredItemsSelectionDialog$3
     102: dup
     103: aload_0
     104: aload         6
     106: invokespecial #1060               // Method org/eclipse/ui/dialogs/FilteredItemsSelectionDialog$3."<init>":(Lorg/eclipse/ui/dialogs/FilteredItemsSelectionDialog;Lorg/eclipse/swt/widgets/Label;)V
     109: invokevirtual #966                // Method org/eclipse/swt/accessibility/Accessible.addAccessibleListener:(Lorg/eclipse/swt/accessibility/AccessibleListener;)V
     112: new           #431                // class org/eclipse/swt/layout/GridData
     115: dup
     116: sipush        768
     119: invokespecial #969                // Method org/eclipse/swt/layout/GridData."<init>":(I)V
     122: astore        4
     124: aload_0
     125: getfield      #901                // Field pattern:Lorg/eclipse/swt/widgets/Text;
     128: aload         4
     130: invokevirtual #994                // Method org/eclipse/swt/widgets/Text.setLayoutData:(Ljava/lang/Object;)V
     133: aload_0
     134: aload_3
     135: invokevirtual #1057               // Method createLabels:(Lorg/eclipse/swt/widgets/Composite;)Lorg/eclipse/swt/widgets/Label;
     138: astore        7
     140: aload_0
     141: new           #424                // class org/eclipse/jface/viewers/TableViewer
     144: dup
     145: aload_3
     146: aload_0
     147: getfield      #890                // Field multi:Z
     150: ifeq          157
     153: iconst_2
     154: goto          158
     157: iconst_4
     158: sipush        2048
     161: ior
     162: sipush        512
     165: ior
     166: ldc_w         #392                // int 268435456
     169: ior
     170: invokespecial #962                // Method org/eclipse/jface/viewers/TableViewer."<init>":(Lorg/eclipse/swt/widgets/Composite;I)V
     173: putfield      #899                // Field tableViewer:Lorg/eclipse/jface/viewers/TableViewer;
     176: aload_0
     177: getfield      #899                // Field tableViewer:Lorg/eclipse/jface/viewers/TableViewer;
     180: invokevirtual #963                // Method org/eclipse/jface/viewers/TableViewer.getTable:()Lorg/eclipse/swt/widgets/Table;
     183: invokevirtual #988                // Method org/eclipse/swt/widgets/Table.getAccessible:()Lorg/eclipse/swt/accessibility/Accessible;
     186: new           #450                // class org/eclipse/ui/dialogs/FilteredItemsSelectionDialog$4
     189: dup
     190: aload_0
     191: aload         7
     193: invokespecial #1061               // Method org/eclipse/ui/dialogs/FilteredItemsSelectionDialog$4."<init>":(Lorg/eclipse/ui/dialogs/FilteredItemsSelectionDialog;Lorg/eclipse/swt/widgets/Label;)V
     196: invokevirtual #966                // Method org/eclipse/swt/accessibility/Accessible.addAccessibleListener:(Lorg/eclipse/swt/accessibility/AccessibleListener;)V
     199: aload_0
     200: getfield      #899                // Field tableViewer:Lorg/eclipse/jface/viewers/TableViewer;
     203: aload_0
     204: getfield      #904                // Field contentProvider:Lorg/eclipse/ui/dialogs/FilteredItemsSelectionDialog$ContentProvider;
     207: invokevirtual #956                // Method org/eclipse/jface/viewers/TableViewer.setContentProvider:(Lorg/eclipse/jface/viewers/IContentProvider;)V
     210: aload_0
     211: getfield      #899                // Field tableViewer:Lorg/eclipse/jface/viewers/TableViewer;
     214: aload_0
     215: invokevirtual #1051               // Method getItemsListLabelProvider:()Lorg/eclipse/ui/dialogs/FilteredItemsSelectionDialog$ItemsListLabelProvider;
     218: invokevirtual #955                // Method org/eclipse/jface/viewers/TableViewer.setLabelProvider:(Lorg/eclipse/jface/viewers/IBaseLabelProvider;)V
     221: aload_0
     222: getfield      #899                // Field tableViewer:Lorg/eclipse/jface/viewers/TableViewer;
     225: iconst_0
     226: anewarray     #402                // class java/lang/Object
     229: invokevirtual #954                // Method org/eclipse/jface/viewers/TableViewer.setInput:(Ljava/lang/Object;)V
     232: aload_0
     233: getfield      #899                // Field tableViewer:Lorg/eclipse/jface/viewers/TableViewer;
     236: aload_0
     237: getfield      #904                // Field contentProvider:Lorg/eclipse/ui/dialogs/FilteredItemsSelectionDialog$ContentProvider;
     240: invokevirtual #1065               // Method org/eclipse/ui/dialogs/FilteredItemsSelectionDialog$ContentProvider.getNumberOfElements:()I
     243: invokevirtual #953                // Method org/eclipse/jface/viewers/TableViewer.setItemCount:(I)V
     246: new           #431                // class org/eclipse/swt/layout/GridData
     249: dup
     250: sipush        1808
     253: invokespecial #969                // Method org/eclipse/swt/layout/GridData."<init>":(I)V
     256: astore        4
     258: aload_0
     259: getfield      #899                // Field tableViewer:Lorg/eclipse/jface/viewers/TableViewer;
     262: invokevirtual #963                // Method org/eclipse/jface/viewers/TableViewer.getTable:()Lorg/eclipse/swt/widgets/Table;
     265: invokestatic  #1046               // Method applyDialogFont:(Lorg/eclipse/swt/widgets/Control;)V
     268: aload         4
     270: aload_0
     271: getfield      #899                // Field tableViewer:Lorg/eclipse/jface/viewers/TableViewer;
     274: invokevirtual #963                // Method org/eclipse/jface/viewers/TableViewer.getTable:()Lorg/eclipse/swt/widgets/Table;
     277: invokevirtual #982                // Method org/eclipse/swt/widgets/Table.getItemHeight:()I
     280: bipush        15
     282: imul
     283: putfield      #883                // Field org/eclipse/swt/layout/GridData.heightHint:I
     286: aload_0
     287: getfield      #899                // Field tableViewer:Lorg/eclipse/jface/viewers/TableViewer;
     290: invokevirtual #963                // Method org/eclipse/jface/viewers/TableViewer.getTable:()Lorg/eclipse/swt/widgets/Table;
     293: aload         4
     295: invokevirtual #987                // Method org/eclipse/swt/widgets/Table.setLayoutData:(Ljava/lang/Object;)V
     298: aload_0
     299: invokevirtual #1016               // Method createPopupMenu:()V
     302: aload_0
     303: getfield      #901                // Field pattern:Lorg/eclipse/swt/widgets/Text;
     306: aload_0
     307: invokedynamic #1166,  0           // InvokeDynamic #4:modifyText:(Lorg/eclipse/ui/dialogs/FilteredItemsSelectionDialog;)Lorg/eclipse/swt/events/ModifyListener;
     312: invokevirtual #998                // Method org/eclipse/swt/widgets/Text.addModifyListener:(Lorg/eclipse/swt/events/ModifyListener;)V
     315: aload_0
     316: getfield      #901                // Field pattern:Lorg/eclipse/swt/widgets/Text;
     319: new           #451                // class org/eclipse/ui/dialogs/FilteredItemsSelectionDialog$5
     322: dup
     323: aload_0
     324: invokespecial #1062               // Method org/eclipse/ui/dialogs/FilteredItemsSelectionDialog$5."<init>":(Lorg/eclipse/ui/dialogs/FilteredItemsSelectionDialog;)V
     327: invokevirtual #997                // Method org/eclipse/swt/widgets/Text.addKeyListener:(Lorg/eclipse/swt/events/KeyListener;)V
     330: aload_0
     331: getfield      #899                // Field tableViewer:Lorg/eclipse/jface/viewers/TableViewer;
     334: aload_0
     335: invokedynamic #1165,  0           // InvokeDynamic #3:selectionChanged:(Lorg/eclipse/ui/dialogs/FilteredItemsSelectionDialog;)Lorg/eclipse/jface/viewers/ISelectionChangedListener;
     340: invokevirtual #960                // Method org/eclipse/jface/viewers/TableViewer.addSelectionChangedListener:(Lorg/eclipse/jface/viewers/ISelectionChangedListener;)V
     343: aload_0
     344: getfield      #899                // Field tableViewer:Lorg/eclipse/jface/viewers/TableViewer;
     347: aload_0
     348: invokedynamic #1164,  0           // InvokeDynamic #2:doubleClick:(Lorg/eclipse/ui/dialogs/FilteredItemsSelectionDialog;)Lorg/eclipse/jface/viewers/IDoubleClickListener;
     353: invokevirtual #957                // Method org/eclipse/jface/viewers/TableViewer.addDoubleClickListener:(Lorg/eclipse/jface/viewers/IDoubleClickListener;)V
     356: aload_0
     357: getfield      #899                // Field tableViewer:Lorg/eclipse/jface/viewers/TableViewer;
     360: invokevirtual #963                // Method org/eclipse/jface/viewers/TableViewer.getTable:()Lorg/eclipse/swt/widgets/Table;
     363: new           #452                // class org/eclipse/ui/dialogs/FilteredItemsSelectionDialog$6
     366: dup
     367: aload_0
     368: invokespecial #1063               // Method org/eclipse/ui/dialogs/FilteredItemsSelectionDialog$6."<init>":(Lorg/eclipse/ui/dialogs/FilteredItemsSelectionDialog;)V
     371: invokevirtual #989                // Method org/eclipse/swt/widgets/Table.addKeyListener:(Lorg/eclipse/swt/events/KeyListener;)V
     374: aload_0
     375: aload_3
     376: invokevirtual #1055               // Method createExtendedContentArea:(Lorg/eclipse/swt/widgets/Composite;)Lorg/eclipse/swt/widgets/Control;
     379: pop
     380: aload_0
     381: new           #456                // class org/eclipse/ui/dialogs/FilteredItemsSelectionDialog$DetailsContentViewer
     384: dup
     385: aload_0
     386: aload_3
     387: ldc_w         #391                // int 8390656
     390: invokespecial #1082               // Method org/eclipse/ui/dialogs/FilteredItemsSelectionDialog$DetailsContentViewer."<init>":(Lorg/eclipse/ui/dialogs/FilteredItemsSelectionDialog;Lorg/eclipse/swt/widgets/Composite;I)V
     393: putfield      #905                // Field details:Lorg/eclipse/ui/dialogs/FilteredItemsSelectionDialog$DetailsContentViewer;
     396: aload_0
     397: getfield      #905                // Field details:Lorg/eclipse/ui/dialogs/FilteredItemsSelectionDialog$DetailsContentViewer;
     400: aload_0
     401: getfield      #914                // Field toggleStatusLineAction:Lorg/eclipse/ui/dialogs/FilteredItemsSelectionDialog$ToggleStatusLineAction;
     404: invokevirtual #1106               // Method org/eclipse/ui/dialogs/FilteredItemsSelectionDialog$ToggleStatusLineAction.isChecked:()Z
     407: invokevirtual #1078               // Method org/eclipse/ui/dialogs/FilteredItemsSelectionDialog$DetailsContentViewer.setVisible:(Z)V
     410: aload_0
     411: getfield      #905                // Field details:Lorg/eclipse/ui/dialogs/FilteredItemsSelectionDialog$DetailsContentViewer;
     414: new           #453                // class org/eclipse/ui/dialogs/FilteredItemsSelectionDialog$7
     417: dup
     418: aload_0
     419: invokespecial #1064               // Method org/eclipse/ui/dialogs/FilteredItemsSelectionDialog$7."<init>":(Lorg/eclipse/ui/dialogs/FilteredItemsSelectionDialog;)V
     422: invokevirtual #1081               // Method org/eclipse/ui/dialogs/FilteredItemsSelectionDialog$DetailsContentViewer.setContentProvider:(Lorg/eclipse/jface/viewers/IContentProvider;)V
     425: aload_0
     426: getfield      #905                // Field details:Lorg/eclipse/ui/dialogs/FilteredItemsSelectionDialog$DetailsContentViewer;
     429: aload_0
     430: invokevirtual #1036               // Method getDetailsLabelProvider:()Lorg/eclipse/jface/viewers/ILabelProvider;
     433: invokevirtual #1080               // Method org/eclipse/ui/dialogs/FilteredItemsSelectionDialog$DetailsContentViewer.setLabelProvider:(Lorg/eclipse/jface/viewers/IBaseLabelProvider;)V
     436: aload_3
     437: invokestatic  #1046               // Method applyDialogFont:(Lorg/eclipse/swt/widgets/Control;)V
     440: aload_0
     441: aload_0
     442: invokevirtual #1031               // Method getDialogSettings:()Lorg/eclipse/jface/dialogs/IDialogSettings;
     445: invokevirtual #1032               // Method restoreDialog:(Lorg/eclipse/jface/dialogs/IDialogSettings;)V
     448: aload_0
     449: getfield      #893                // Field initialPatternText:Ljava/lang/String;
     452: ifnull        466
     455: aload_0
     456: getfield      #901                // Field pattern:Lorg/eclipse/swt/widgets/Text;
     459: aload_0
     460: getfield      #893                // Field initialPatternText:Ljava/lang/String;
     463: invokevirtual #995                // Method org/eclipse/swt/widgets/Text.setText:(Ljava/lang/String;)V
     466: aload_0
     467: getfield      #888                // Field selectionMode:I
     470: tableswitch   { // 1 to 2
                     1: 492
                     2: 504
               default: 519
          }
     492: aload_0
     493: getfield      #901                // Field pattern:Lorg/eclipse/swt/widgets/Text;
     496: iconst_0
     497: iconst_0
     498: invokevirtual #993                // Method org/eclipse/swt/widgets/Text.setSelection:(II)V
     501: goto          519
     504: aload_0
     505: getfield      #901                // Field pattern:Lorg/eclipse/swt/widgets/Text;
     508: iconst_0
     509: aload_0
     510: getfield      #893                // Field initialPatternText:Ljava/lang/String;
     513: invokevirtual #929                // Method java/lang/String.length:()I
     516: invokevirtual #993                // Method org/eclipse/swt/widgets/Text.setSelection:(II)V
     519: aload_0
     520: invokevirtual #1015               // Method applyFilter:()V
     523: aload_2
     524: areturn

  protected void handleDoubleClick();
    Code:
       0: aload_0
       1: invokevirtual #1018               // Method okPressed:()V
       4: return

  private void refreshDetails();
    Code:
       0: aload_0
       1: invokevirtual #1038               // Method getSelectedItems:()Lorg/eclipse/jface/viewers/StructuredSelection;
       4: astore_1
       5: aload_1
       6: invokevirtual #945                // Method org/eclipse/jface/viewers/StructuredSelection.size:()I
       9: tableswitch   { // 0 to 1
                     0: 32
                     1: 43
               default: 57
          }
      32: aload_0
      33: getfield      #905                // Field details:Lorg/eclipse/ui/dialogs/FilteredItemsSelectionDialog$DetailsContentViewer;
      36: aconst_null
      37: invokevirtual #1079               // Method org/eclipse/ui/dialogs/FilteredItemsSelectionDialog$DetailsContentViewer.setInput:(Ljava/lang/Object;)V
      40: goto          77
      43: aload_0
      44: getfield      #905                // Field details:Lorg/eclipse/ui/dialogs/FilteredItemsSelectionDialog$DetailsContentViewer;
      47: aload_1
      48: invokevirtual #947                // Method org/eclipse/jface/viewers/StructuredSelection.getFirstElement:()Ljava/lang/Object;
      51: invokevirtual #1079               // Method org/eclipse/ui/dialogs/FilteredItemsSelectionDialog$DetailsContentViewer.setInput:(Ljava/lang/Object;)V
      54: goto          77
      57: aload_0
      58: getfield      #905                // Field details:Lorg/eclipse/ui/dialogs/FilteredItemsSelectionDialog$DetailsContentViewer;
      61: getstatic     #919                // Field org/eclipse/ui/internal/WorkbenchMessages.FilteredItemsSelectionDialog_nItemsSelected:Ljava/lang/String;
      64: aload_1
      65: invokevirtual #945                // Method org/eclipse/jface/viewers/StructuredSelection.size:()I
      68: invokestatic  #928                // Method java/lang/Integer.valueOf:(I)Ljava/lang/Integer;
      71: invokestatic  #965                // Method org/eclipse/osgi/util/NLS.bind:(Ljava/lang/String;Ljava/lang/Object;)Ljava/lang/String;
      74: invokevirtual #1079               // Method org/eclipse/ui/dialogs/FilteredItemsSelectionDialog$DetailsContentViewer.setInput:(Ljava/lang/Object;)V
      77: return

  protected void handleSelected(org.eclipse.jface.viewers.StructuredSelection);
    Code:
       0: new           #414                // class org/eclipse/core/runtime/Status
       3: dup
       4: iconst_0
       5: ldc_w         #395                // String org.eclipse.ui
       8: iconst_0
       9: ldc           #1                  // String
      11: aconst_null
      12: invokespecial #936                // Method org/eclipse/core/runtime/Status."<init>":(ILjava/lang/String;ILjava/lang/String;Ljava/lang/Throwable;)V
      15: astore_2
      16: aload_0
      17: getfield      #892                // Field currentSelection:[Ljava/lang/Object;
      20: astore_3
      21: aload_0
      22: aload_1
      23: invokevirtual #948                // Method org/eclipse/jface/viewers/StructuredSelection.toArray:()[Ljava/lang/Object;
      26: putfield      #892                // Field currentSelection:[Ljava/lang/Object;
      29: aload_1
      30: invokevirtual #946                // Method org/eclipse/jface/viewers/StructuredSelection.isEmpty:()Z
      33: ifeq          80
      36: new           #414                // class org/eclipse/core/runtime/Status
      39: dup
      40: iconst_4
      41: ldc_w         #395                // String org.eclipse.ui
      44: iconst_4
      45: ldc           #1                  // String
      47: aconst_null
      48: invokespecial #936                // Method org/eclipse/core/runtime/Status."<init>":(ILjava/lang/String;ILjava/lang/String;Ljava/lang/Throwable;)V
      51: astore_2
      52: aload_3
      53: ifnull        72
      56: aload_0
      57: invokevirtual #1035               // Method getListSelectionLabelDecorator:()Lorg/eclipse/jface/viewers/ILabelDecorator;
      60: ifnull        72
      63: aload_0
      64: getfield      #899                // Field tableViewer:Lorg/eclipse/jface/viewers/TableViewer;
      67: aload_3
      68: aconst_null
      69: invokevirtual #964                // Method org/eclipse/jface/viewers/TableViewer.update:([Ljava/lang/Object;[Ljava/lang/String;)V
      72: aload_0
      73: aconst_null
      74: putfield      #892                // Field currentSelection:[Ljava/lang/Object;
      77: goto          236
      80: new           #414                // class org/eclipse/core/runtime/Status
      83: dup
      84: iconst_4
      85: ldc_w         #395                // String org.eclipse.ui
      88: iconst_4
      89: ldc           #1                  // String
      91: aconst_null
      92: invokespecial #936                // Method org/eclipse/core/runtime/Status."<init>":(ILjava/lang/String;ILjava/lang/String;Ljava/lang/Throwable;)V
      95: astore_2
      96: aload_1
      97: invokevirtual #950                // Method org/eclipse/jface/viewers/StructuredSelection.toList:()Ljava/util/List;
     100: astore        4
     102: aconst_null
     103: astore        5
     105: aconst_null
     106: astore        6
     108: aload         4
     110: invokeinterface #1127,  1         // InterfaceMethod java/util/List.iterator:()Ljava/util/Iterator;
     115: astore        8
     117: goto          187
     120: aload         8
     122: invokeinterface #1121,  1         // InterfaceMethod java/util/Iterator.next:()Ljava/lang/Object;
     127: astore        7
     129: aload         7
     131: instanceof    #463                // class org/eclipse/ui/dialogs/FilteredItemsSelectionDialog$ItemsListSeparator
     134: ifeq          140
     137: goto          187
     140: aload         7
     142: astore        5
     144: aload_0
     145: aload         5
     147: invokevirtual #1054               // Method validateItem:(Ljava/lang/Object;)Lorg/eclipse/core/runtime/IStatus;
     150: astore        6
     152: aload         6
     154: invokeinterface #1130,  1         // InterfaceMethod org/eclipse/core/runtime/IStatus.isOK:()Z
     159: ifeq          181
     162: new           #414                // class org/eclipse/core/runtime/Status
     165: dup
     166: iconst_0
     167: ldc_w         #395                // String org.eclipse.ui
     170: iconst_0
     171: ldc           #1                  // String
     173: aconst_null
     174: invokespecial #936                // Method org/eclipse/core/runtime/Status."<init>":(ILjava/lang/String;ILjava/lang/String;Ljava/lang/Throwable;)V
     177: astore_2
     178: goto          187
     181: aload         6
     183: astore_2
     184: goto          197
     187: aload         8
     189: invokeinterface #1120,  1         // InterfaceMethod java/util/Iterator.hasNext:()Z
     194: ifne          120
     197: aload_3
     198: ifnull        217
     201: aload_0
     202: invokevirtual #1035               // Method getListSelectionLabelDecorator:()Lorg/eclipse/jface/viewers/ILabelDecorator;
     205: ifnull        217
     208: aload_0
     209: getfield      #899                // Field tableViewer:Lorg/eclipse/jface/viewers/TableViewer;
     212: aload_3
     213: aconst_null
     214: invokevirtual #964                // Method org/eclipse/jface/viewers/TableViewer.update:([Ljava/lang/Object;[Ljava/lang/String;)V
     217: aload_0
     218: invokevirtual #1035               // Method getListSelectionLabelDecorator:()Lorg/eclipse/jface/viewers/ILabelDecorator;
     221: ifnull        236
     224: aload_0
     225: getfield      #899                // Field tableViewer:Lorg/eclipse/jface/viewers/TableViewer;
     228: aload_0
     229: getfield      #892                // Field currentSelection:[Ljava/lang/Object;
     232: aconst_null
     233: invokevirtual #964                // Method org/eclipse/jface/viewers/TableViewer.update:([Ljava/lang/Object;[Ljava/lang/String;)V
     236: aload_0
     237: invokevirtual #1019               // Method refreshDetails:()V
     240: aload_0
     241: aload_2
     242: invokevirtual #1028               // Method updateStatus:(Lorg/eclipse/core/runtime/IStatus;)V
     245: return

  protected org.eclipse.jface.dialogs.IDialogSettings getDialogBoundsSettings();
    Code:
       0: aload_0
       1: invokevirtual #1031               // Method getDialogSettings:()Lorg/eclipse/jface/dialogs/IDialogSettings;
       4: astore_1
       5: aload_1
       6: ldc           #4                  // String DialogBoundsSettings
       8: invokeinterface #1139,  2         // InterfaceMethod org/eclipse/jface/dialogs/IDialogSettings.getSection:(Ljava/lang/String;)Lorg/eclipse/jface/dialogs/IDialogSettings;
      13: astore_2
      14: aload_2
      15: ifnonnull     49
      18: aload_1
      19: ldc           #4                  // String DialogBoundsSettings
      21: invokeinterface #1138,  2         // InterfaceMethod org/eclipse/jface/dialogs/IDialogSettings.addNewSection:(Ljava/lang/String;)Lorg/eclipse/jface/dialogs/IDialogSettings;
      26: astore_2
      27: aload_2
      28: ldc           #2                  // String DIALOG_HEIGHT
      30: sipush        500
      33: invokeinterface #1134,  3         // InterfaceMethod org/eclipse/jface/dialogs/IDialogSettings.put:(Ljava/lang/String;I)V
      38: aload_2
      39: ldc           #3                  // String DIALOG_WIDTH
      41: sipush        600
      44: invokeinterface #1134,  3         // InterfaceMethod org/eclipse/jface/dialogs/IDialogSettings.put:(Ljava/lang/String;I)V
      49: aload_2
      50: areturn

  protected abstract org.eclipse.jface.dialogs.IDialogSettings getDialogSettings();

  public void refresh();
    Code:
       0: aload_0
       1: getfield      #899                // Field tableViewer:Lorg/eclipse/jface/viewers/TableViewer;
       4: ifnull        182
       7: aload_0
       8: getfield      #899                // Field tableViewer:Lorg/eclipse/jface/viewers/TableViewer;
      11: invokevirtual #963                // Method org/eclipse/jface/viewers/TableViewer.getTable:()Lorg/eclipse/swt/widgets/Table;
      14: invokevirtual #984                // Method org/eclipse/swt/widgets/Table.isDisposed:()Z
      17: ifne          182
      20: aload_0
      21: getfield      #899                // Field tableViewer:Lorg/eclipse/jface/viewers/TableViewer;
      24: invokevirtual #958                // Method org/eclipse/jface/viewers/TableViewer.getSelection:()Lorg/eclipse/jface/viewers/ISelection;
      27: checkcast     #423                // class org/eclipse/jface/viewers/StructuredSelection
      30: invokevirtual #950                // Method org/eclipse/jface/viewers/StructuredSelection.toList:()Ljava/util/List;
      33: astore_1
      34: aload_0
      35: getfield      #899                // Field tableViewer:Lorg/eclipse/jface/viewers/TableViewer;
      38: invokevirtual #963                // Method org/eclipse/jface/viewers/TableViewer.getTable:()Lorg/eclipse/swt/widgets/Table;
      41: invokevirtual #983                // Method org/eclipse/swt/widgets/Table.deselectAll:()V
      44: aload_0
      45: getfield      #899                // Field tableViewer:Lorg/eclipse/jface/viewers/TableViewer;
      48: aload_0
      49: getfield      #904                // Field contentProvider:Lorg/eclipse/ui/dialogs/FilteredItemsSelectionDialog$ContentProvider;
      52: invokevirtual #1065               // Method org/eclipse/ui/dialogs/FilteredItemsSelectionDialog$ContentProvider.getNumberOfElements:()I
      55: invokevirtual #953                // Method org/eclipse/jface/viewers/TableViewer.setItemCount:(I)V
      58: aload_0
      59: getfield      #899                // Field tableViewer:Lorg/eclipse/jface/viewers/TableViewer;
      62: invokevirtual #952                // Method org/eclipse/jface/viewers/TableViewer.refresh:()V
      65: aload_0
      66: getfield      #899                // Field tableViewer:Lorg/eclipse/jface/viewers/TableViewer;
      69: invokevirtual #963                // Method org/eclipse/jface/viewers/TableViewer.getTable:()Lorg/eclipse/swt/widgets/Table;
      72: invokevirtual #981                // Method org/eclipse/swt/widgets/Table.getItemCount:()I
      75: ifle          172
      78: aload_0
      79: getfield      #889                // Field isShownForTheFirstTime:Z
      82: ifeq          96
      85: aload_0
      86: iconst_0
      87: putfield      #889                // Field isShownForTheFirstTime:Z
      90: aload_0
      91: aload_1
      92: invokevirtual #1053               // Method prepareInitialSelection:(Ljava/util/List;)Ljava/util/List;
      95: astore_1
      96: aload_0
      97: getfield      #891                // Field refreshWithLastSelection:Z
     100: ifeq          134
     103: aload_1
     104: ifnull        134
     107: aload_1
     108: invokeinterface #1122,  1         // InterfaceMethod java/util/List.size:()I
     113: ifle          134
     116: aload_0
     117: getfield      #899                // Field tableViewer:Lorg/eclipse/jface/viewers/TableViewer;
     120: new           #423                // class org/eclipse/jface/viewers/StructuredSelection
     123: dup
     124: aload_1
     125: invokespecial #951                // Method org/eclipse/jface/viewers/StructuredSelection."<init>":(Ljava/util/List;)V
     128: invokevirtual #959                // Method org/eclipse/jface/viewers/TableViewer.setSelection:(Lorg/eclipse/jface/viewers/ISelection;)V
     131: goto          182
     134: aload_0
     135: iconst_1
     136: putfield      #891                // Field refreshWithLastSelection:Z
     139: aload_0
     140: getfield      #899                // Field tableViewer:Lorg/eclipse/jface/viewers/TableViewer;
     143: invokevirtual #963                // Method org/eclipse/jface/viewers/TableViewer.getTable:()Lorg/eclipse/swt/widgets/Table;
     146: iconst_0
     147: invokevirtual #986                // Method org/eclipse/swt/widgets/Table.setSelection:(I)V
     150: aload_0
     151: getfield      #899                // Field tableViewer:Lorg/eclipse/jface/viewers/TableViewer;
     154: invokevirtual #963                // Method org/eclipse/jface/viewers/TableViewer.getTable:()Lorg/eclipse/swt/widgets/Table;
     157: bipush        13
     159: new           #434                // class org/eclipse/swt/widgets/Event
     162: dup
     163: invokespecial #974                // Method org/eclipse/swt/widgets/Event."<init>":()V
     166: invokevirtual #990                // Method org/eclipse/swt/widgets/Table.notifyListeners:(ILorg/eclipse/swt/widgets/Event;)V
     169: goto          182
     172: aload_0
     173: getfield      #899                // Field tableViewer:Lorg/eclipse/jface/viewers/TableViewer;
     176: getstatic     #875                // Field org/eclipse/jface/viewers/StructuredSelection.EMPTY:Lorg/eclipse/jface/viewers/StructuredSelection;
     179: invokevirtual #959                // Method org/eclipse/jface/viewers/TableViewer.setSelection:(Lorg/eclipse/jface/viewers/ISelection;)V
     182: aload_0
     183: invokevirtual #1020               // Method scheduleProgressMessageRefresh:()V
     186: return

  private java.util.List<java.lang.Object> prepareInitialSelection(java.util.List<java.lang.Object>);
    Code:
       0: aload_0
       1: invokevirtual #1026               // Method getInitialElementSelections:()Ljava/util/List;
       4: invokeinterface #1123,  1         // InterfaceMethod java/util/List.isEmpty:()Z
       9: istore_2
      10: iload_2
      11: ifeq          16
      14: aload_1
      15: areturn
      16: aload_0
      17: iconst_1
      18: putfield      #891                // Field refreshWithLastSelection:Z
      21: aload_0
      22: getfield      #890                // Field multi:Z
      25: ifne          44
      28: aload_0
      29: invokevirtual #1026               // Method getInitialElementSelections:()Ljava/util/List;
      32: iconst_0
      33: invokeinterface #1124,  2         // InterfaceMethod java/util/List.get:(I)Ljava/lang/Object;
      38: astore_3
      39: aload_3
      40: invokestatic  #935                // Method java/util/Collections.singletonList:(Ljava/lang/Object;)Ljava/util/List;
      43: areturn
      44: aload_0
      45: invokevirtual #1026               // Method getInitialElementSelections:()Ljava/util/List;
      48: areturn

  public void updateProgressLabel();
    Code:
       0: aload_0
       1: invokevirtual #1020               // Method scheduleProgressMessageRefresh:()V
       4: return

  public void reloadCache(boolean, org.eclipse.core.runtime.IProgressMonitor);
    Code:
       0: aload_0
       1: getfield      #899                // Field tableViewer:Lorg/eclipse/jface/viewers/TableViewer;
       4: ifnull        36
       7: aload_0
       8: getfield      #899                // Field tableViewer:Lorg/eclipse/jface/viewers/TableViewer;
      11: invokevirtual #963                // Method org/eclipse/jface/viewers/TableViewer.getTable:()Lorg/eclipse/swt/widgets/Table;
      14: invokevirtual #984                // Method org/eclipse/swt/widgets/Table.isDisposed:()Z
      17: ifne          36
      20: aload_0
      21: getfield      #904                // Field contentProvider:Lorg/eclipse/ui/dialogs/FilteredItemsSelectionDialog$ContentProvider;
      24: ifnull        36
      27: aload_0
      28: getfield      #904                // Field contentProvider:Lorg/eclipse/ui/dialogs/FilteredItemsSelectionDialog$ContentProvider;
      31: iload_1
      32: aload_2
      33: invokevirtual #1070               // Method org/eclipse/ui/dialogs/FilteredItemsSelectionDialog$ContentProvider.reloadCache:(ZLorg/eclipse/core/runtime/IProgressMonitor;)V
      36: return

  public void scheduleRefresh();
    Code:
       0: aload_0
       1: getfield      #911                // Field refreshCacheJob:Lorg/eclipse/ui/dialogs/FilteredItemsSelectionDialog$RefreshCacheJob;
       4: invokevirtual #1096               // Method org/eclipse/ui/dialogs/FilteredItemsSelectionDialog$RefreshCacheJob.cancelAll:()V
       7: aload_0
       8: getfield      #911                // Field refreshCacheJob:Lorg/eclipse/ui/dialogs/FilteredItemsSelectionDialog$RefreshCacheJob;
      11: invokevirtual #1097               // Method org/eclipse/ui/dialogs/FilteredItemsSelectionDialog$RefreshCacheJob.schedule:()V
      14: return

  public void scheduleProgressMessageRefresh();
    Code:
       0: aload_0
       1: getfield      #907                // Field filterJob:Lorg/eclipse/ui/dialogs/FilteredItemsSelectionDialog$FilterJob;
       4: invokevirtual #1086               // Method org/eclipse/ui/dialogs/FilteredItemsSelectionDialog$FilterJob.getState:()I
       7: iconst_4
       8: if_icmpeq     30
      11: aload_0
      12: getfield      #912                // Field refreshProgressMessageJob:Lorg/eclipse/ui/dialogs/FilteredItemsSelectionDialog$RefreshProgressMessageJob;
      15: invokevirtual #1100               // Method org/eclipse/ui/dialogs/FilteredItemsSelectionDialog$RefreshProgressMessageJob.getState:()I
      18: iconst_4
      19: if_icmpeq     30
      22: aload_0
      23: getfield      #912                // Field refreshProgressMessageJob:Lorg/eclipse/ui/dialogs/FilteredItemsSelectionDialog$RefreshProgressMessageJob;
      26: aconst_null
      27: invokevirtual #1103               // Method org/eclipse/ui/dialogs/FilteredItemsSelectionDialog$RefreshProgressMessageJob.scheduleProgressRefresh:(Lorg/eclipse/ui/dialogs/FilteredItemsSelectionDialog$GranualProgressMonitor;)V
      30: return

  protected void computeResult();
    Code:
       0: aload_0
       1: getfield      #899                // Field tableViewer:Lorg/eclipse/jface/viewers/TableViewer;
       4: invokevirtual #961                // Method org/eclipse/jface/viewers/TableViewer.getStructuredSelection:()Lorg/eclipse/jface/viewers/IStructuredSelection;
       7: invokeinterface #1141,  1         // InterfaceMethod org/eclipse/jface/viewers/IStructuredSelection.toList:()Ljava/util/List;
      12: astore_1
      13: new           #407                // class java/util/ArrayList
      16: dup
      17: invokespecial #933                // Method java/util/ArrayList."<init>":()V
      20: astore_2
      21: aconst_null
      22: astore_3
      23: aload_1
      24: invokeinterface #1127,  1         // InterfaceMethod java/util/List.iterator:()Ljava/util/Iterator;
      29: astore        4
      31: goto          62
      34: aload         4
      36: invokeinterface #1121,  1         // InterfaceMethod java/util/Iterator.next:()Ljava/lang/Object;
      41: astore_3
      42: aload_3
      43: instanceof    #463                // class org/eclipse/ui/dialogs/FilteredItemsSelectionDialog$ItemsListSeparator
      46: ifne          62
      49: aload_0
      50: aload_3
      51: invokevirtual #1022               // Method accessedHistoryItem:(Ljava/lang/Object;)V
      54: aload_2
      55: aload_3
      56: invokeinterface #1125,  2         // InterfaceMethod java/util/List.add:(Ljava/lang/Object;)Z
      61: pop
      62: aload         4
      64: invokeinterface #1120,  1         // InterfaceMethod java/util/Iterator.hasNext:()Z
      69: ifne          34
      72: aload_0
      73: aload_2
      74: invokevirtual #1027               // Method setResult:(Ljava/util/List;)V
      77: return

  protected void updateStatus(org.eclipse.core.runtime.IStatus);
    Code:
       0: aload_0
       1: aload_1
       2: putfield      #894                // Field status:Lorg/eclipse/core/runtime/IStatus;
       5: aload_0
       6: aload_1
       7: invokespecial #1113               // Method org/eclipse/ui/dialogs/SelectionStatusDialog.updateStatus:(Lorg/eclipse/core/runtime/IStatus;)V
      10: return

  protected void okPressed();
    Code:
       0: aload_0
       1: getfield      #894                // Field status:Lorg/eclipse/core/runtime/IStatus;
       4: ifnull        36
       7: aload_0
       8: getfield      #894                // Field status:Lorg/eclipse/core/runtime/IStatus;
      11: invokeinterface #1130,  1         // InterfaceMethod org/eclipse/core/runtime/IStatus.isOK:()Z
      16: ifne          32
      19: aload_0
      20: getfield      #894                // Field status:Lorg/eclipse/core/runtime/IStatus;
      23: invokeinterface #1129,  1         // InterfaceMethod org/eclipse/core/runtime/IStatus.getCode:()I
      28: iconst_1
      29: if_icmpne     36
      32: aload_0
      33: invokespecial #1111               // Method org/eclipse/ui/dialogs/SelectionStatusDialog.okPressed:()V
      36: return

  public void setInitialPattern(java.lang.String);
    Code:
       0: aload_0
       1: aload_1
       2: iconst_2
       3: invokevirtual #1025               // Method setInitialPattern:(Ljava/lang/String;I)V
       6: return

  public void setInitialPattern(java.lang.String, int);
    Code:
       0: aload_0
       1: aload_1
       2: putfield      #893                // Field initialPatternText:Ljava/lang/String;
       5: aload_0
       6: iload_2
       7: putfield      #888                // Field selectionMode:I
      10: return

  protected java.lang.String getInitialPattern();
    Code:
       0: aload_0
       1: getfield      #893                // Field initialPatternText:Ljava/lang/String;
       4: areturn

  protected org.eclipse.jface.viewers.StructuredSelection getSelectedItems();
    Code:
       0: aload_0
       1: getfield      #899                // Field tableViewer:Lorg/eclipse/jface/viewers/TableViewer;
       4: invokevirtual #961                // Method org/eclipse/jface/viewers/TableViewer.getStructuredSelection:()Lorg/eclipse/jface/viewers/IStructuredSelection;
       7: checkcast     #423                // class org/eclipse/jface/viewers/StructuredSelection
      10: astore_1
      11: aload_1
      12: invokevirtual #950                // Method org/eclipse/jface/viewers/StructuredSelection.toList:()Ljava/util/List;
      15: astore_2
      16: aconst_null
      17: astore_3
      18: aload_1
      19: invokevirtual #949                // Method org/eclipse/jface/viewers/StructuredSelection.iterator:()Ljava/util/Iterator;
      22: astore        4
      24: goto          50
      27: aload         4
      29: invokeinterface #1121,  1         // InterfaceMethod java/util/Iterator.next:()Ljava/lang/Object;
      34: astore        5
      36: aload         5
      38: instanceof    #463                // class org/eclipse/ui/dialogs/FilteredItemsSelectionDialog$ItemsListSeparator
      41: ifeq          50
      44: aload         5
      46: astore_3
      47: goto          60
      50: aload         4
      52: invokeinterface #1120,  1         // InterfaceMethod java/util/Iterator.hasNext:()Z
      57: ifne          27
      60: aload_3
      61: ifnonnull     73
      64: new           #423                // class org/eclipse/jface/viewers/StructuredSelection
      67: dup
      68: aload_2
      69: invokespecial #951                // Method org/eclipse/jface/viewers/StructuredSelection."<init>":(Ljava/util/List;)V
      72: areturn
      73: new           #407                // class java/util/ArrayList
      76: dup
      77: aload_2
      78: invokespecial #934                // Method java/util/ArrayList."<init>":(Ljava/util/Collection;)V
      81: astore        4
      83: aload         4
      85: aload_3
      86: invokeinterface #1126,  2         // InterfaceMethod java/util/List.remove:(Ljava/lang/Object;)Z
      91: pop
      92: new           #423                // class org/eclipse/jface/viewers/StructuredSelection
      95: dup
      96: aload         4
      98: invokespecial #951                // Method org/eclipse/jface/viewers/StructuredSelection."<init>":(Ljava/util/List;)V
     101: areturn

  protected abstract org.eclipse.core.runtime.IStatus validateItem(java.lang.Object);

  protected abstract org.eclipse.ui.dialogs.FilteredItemsSelectionDialog$ItemsFilter createFilter();

  protected void applyFilter();
    Code:
       0: aload_0
       1: invokevirtual #1050               // Method createFilter:()Lorg/eclipse/ui/dialogs/FilteredItemsSelectionDialog$ItemsFilter;
       4: astore_1
       5: aload_0
       6: getfield      #908                // Field filter:Lorg/eclipse/ui/dialogs/FilteredItemsSelectionDialog$ItemsFilter;
       9: ifnull        24
      12: aload_0
      13: getfield      #908                // Field filter:Lorg/eclipse/ui/dialogs/FilteredItemsSelectionDialog$ItemsFilter;
      16: aload_1
      17: invokevirtual #1090               // Method org/eclipse/ui/dialogs/FilteredItemsSelectionDialog$ItemsFilter.equalsFilter:(Lorg/eclipse/ui/dialogs/FilteredItemsSelectionDialog$ItemsFilter;)Z
      20: ifeq          24
      23: return
      24: aload_0
      25: getfield      #906                // Field filterHistoryJob:Lorg/eclipse/ui/dialogs/FilteredItemsSelectionDialog$FilterHistoryJob;
      28: invokevirtual #1084               // Method org/eclipse/ui/dialogs/FilteredItemsSelectionDialog$FilterHistoryJob.cancel:()Z
      31: pop
      32: aload_0
      33: getfield      #907                // Field filterJob:Lorg/eclipse/ui/dialogs/FilteredItemsSelectionDialog$FilterJob;
      36: invokevirtual #1087               // Method org/eclipse/ui/dialogs/FilteredItemsSelectionDialog$FilterJob.cancel:()Z
      39: pop
      40: aload_0
      41: aload_1
      42: putfield      #908                // Field filter:Lorg/eclipse/ui/dialogs/FilteredItemsSelectionDialog$ItemsFilter;
      45: aload_0
      46: getfield      #908                // Field filter:Lorg/eclipse/ui/dialogs/FilteredItemsSelectionDialog$ItemsFilter;
      49: ifnull        59
      52: aload_0
      53: getfield      #906                // Field filterHistoryJob:Lorg/eclipse/ui/dialogs/FilteredItemsSelectionDialog$FilterHistoryJob;
      56: invokevirtual #1083               // Method org/eclipse/ui/dialogs/FilteredItemsSelectionDialog$FilterHistoryJob.schedule:()V
      59: return

  protected abstract java.util.Comparator getItemsComparator();

  protected abstract void fillContentProvider(org.eclipse.ui.dialogs.FilteredItemsSelectionDialog$AbstractContentProvider, org.eclipse.ui.dialogs.FilteredItemsSelectionDialog$ItemsFilter, org.eclipse.core.runtime.IProgressMonitor) throws org.eclipse.core.runtime.CoreException;

  private void removeSelectedItems(java.util.List<?>);
    Code:
       0: aload_1
       1: invokeinterface #1127,  1         // InterfaceMethod java/util/List.iterator:()Ljava/util/Iterator;
       6: astore_3
       7: goto          23
      10: aload_3
      11: invokeinterface #1121,  1         // InterfaceMethod java/util/Iterator.next:()Ljava/lang/Object;
      16: astore_2
      17: aload_0
      18: aload_2
      19: invokevirtual #1052               // Method removeHistoryItem:(Ljava/lang/Object;)Ljava/lang/Object;
      22: pop
      23: aload_3
      24: invokeinterface #1120,  1         // InterfaceMethod java/util/Iterator.hasNext:()Z
      29: ifne          10
      32: aload_0
      33: iconst_0
      34: putfield      #891                // Field refreshWithLastSelection:Z
      37: aload_0
      38: getfield      #904                // Field contentProvider:Lorg/eclipse/ui/dialogs/FilteredItemsSelectionDialog$ContentProvider;
      41: invokevirtual #1066               // Method org/eclipse/ui/dialogs/FilteredItemsSelectionDialog$ContentProvider.refresh:()V
      44: return

  protected java.lang.Object removeHistoryItem(java.lang.Object);
    Code:
       0: aload_0
       1: getfield      #904                // Field contentProvider:Lorg/eclipse/ui/dialogs/FilteredItemsSelectionDialog$ContentProvider;
       4: aload_1
       5: invokevirtual #1077               // Method org/eclipse/ui/dialogs/FilteredItemsSelectionDialog$ContentProvider.removeHistoryElement:(Ljava/lang/Object;)Ljava/lang/Object;
       8: areturn

  protected void accessedHistoryItem(java.lang.Object);
    Code:
       0: aload_0
       1: getfield      #904                // Field contentProvider:Lorg/eclipse/ui/dialogs/FilteredItemsSelectionDialog$ContentProvider;
       4: aload_1
       5: invokevirtual #1067               // Method org/eclipse/ui/dialogs/FilteredItemsSelectionDialog$ContentProvider.addHistoryElement:(Ljava/lang/Object;)V
       8: return

  private java.util.Comparator<java.lang.Object> getHistoryComparator();
    Code:
       0: new           #460                // class org/eclipse/ui/dialogs/FilteredItemsSelectionDialog$HistoryComparator
       3: dup
       4: aload_0
       5: invokespecial #1089               // Method org/eclipse/ui/dialogs/FilteredItemsSelectionDialog$HistoryComparator."<init>":(Lorg/eclipse/ui/dialogs/FilteredItemsSelectionDialog;)V
       8: areturn

  protected org.eclipse.ui.dialogs.FilteredItemsSelectionDialog$SelectionHistory getSelectionHistory();
    Code:
       0: aload_0
       1: getfield      #904                // Field contentProvider:Lorg/eclipse/ui/dialogs/FilteredItemsSelectionDialog$ContentProvider;
       4: invokevirtual #1075               // Method org/eclipse/ui/dialogs/FilteredItemsSelectionDialog$ContentProvider.getSelectionHistory:()Lorg/eclipse/ui/dialogs/FilteredItemsSelectionDialog$SelectionHistory;
       7: areturn

  protected void setSelectionHistory(org.eclipse.ui.dialogs.FilteredItemsSelectionDialog$SelectionHistory);
    Code:
       0: aload_0
       1: getfield      #904                // Field contentProvider:Lorg/eclipse/ui/dialogs/FilteredItemsSelectionDialog$ContentProvider;
       4: ifnull        15
       7: aload_0
       8: getfield      #904                // Field contentProvider:Lorg/eclipse/ui/dialogs/FilteredItemsSelectionDialog$ContentProvider;
      11: aload_1
      12: invokevirtual #1076               // Method org/eclipse/ui/dialogs/FilteredItemsSelectionDialog$ContentProvider.setSelectionHistory:(Lorg/eclipse/ui/dialogs/FilteredItemsSelectionDialog$SelectionHistory;)V
      15: return

  public boolean isHistoryElement(java.lang.Object);
    Code:
       0: aload_0
       1: getfield      #904                // Field contentProvider:Lorg/eclipse/ui/dialogs/FilteredItemsSelectionDialog$ContentProvider;
       4: aload_1
       5: invokevirtual #1069               // Method org/eclipse/ui/dialogs/FilteredItemsSelectionDialog$ContentProvider.isHistoryElement:(Ljava/lang/Object;)Z
       8: ireturn

  public boolean isDuplicateElement(java.lang.Object);
    Code:
       0: aload_0
       1: getfield      #904                // Field contentProvider:Lorg/eclipse/ui/dialogs/FilteredItemsSelectionDialog$ContentProvider;
       4: aload_1
       5: invokevirtual #1068               // Method org/eclipse/ui/dialogs/FilteredItemsSelectionDialog$ContentProvider.isDuplicateElement:(Ljava/lang/Object;)Z
       8: ireturn

  public void setSeparatorLabel(java.lang.String);
    Code:
       0: aload_0
       1: new           #463                // class org/eclipse/ui/dialogs/FilteredItemsSelectionDialog$ItemsListSeparator
       4: dup
       5: aload_1
       6: invokespecial #1095               // Method org/eclipse/ui/dialogs/FilteredItemsSelectionDialog$ItemsListSeparator."<init>":(Ljava/lang/String;)V
       9: putfield      #910                // Field itemsListSeparator:Lorg/eclipse/ui/dialogs/FilteredItemsSelectionDialog$ItemsListSeparator;
      12: return

  public abstract java.lang.String getElementName(java.lang.Object);

  private static boolean showColoredLabels();
    Code:
       0: invokestatic  #1010               // Method org/eclipse/ui/PlatformUI.getPreferenceStore:()Lorg/eclipse/jface/preference/IPreferenceStore;
       3: ldc_w         #394                // String USE_COLORED_LABELS
       6: invokeinterface #1140,  2         // InterfaceMethod org/eclipse/jface/preference/IPreferenceStore.getBoolean:(Ljava/lang/String;)Z
      11: ireturn

  public org.eclipse.swt.widgets.Control getPatternControl();
    Code:
       0: aload_0
       1: getfield      #901                // Field pattern:Lorg/eclipse/swt/widgets/Text;
       4: areturn

  public org.eclipse.ui.dialogs.IStyledStringHighlighter getStyledStringHighlighter();
    Code:
       0: aload_0
       1: getfield      #915                // Field styledStringHighlighter:Lorg/eclipse/ui/dialogs/IStyledStringHighlighter;
       4: ifnonnull     18
       7: aload_0
       8: new           #473                // class org/eclipse/ui/dialogs/StyledStringHighlighter
      11: dup
      12: invokespecial #1116               // Method org/eclipse/ui/dialogs/StyledStringHighlighter."<init>":()V
      15: putfield      #915                // Field styledStringHighlighter:Lorg/eclipse/ui/dialogs/IStyledStringHighlighter;
      18: aload_0
      19: getfield      #915                // Field styledStringHighlighter:Lorg/eclipse/ui/dialogs/IStyledStringHighlighter;
      22: areturn

  public void setStyledStringHighlighter(org.eclipse.ui.dialogs.IStyledStringHighlighter);
    Code:
       0: aload_0
       1: aload_1
       2: putfield      #915                // Field styledStringHighlighter:Lorg/eclipse/ui/dialogs/IStyledStringHighlighter;
       5: return

  static org.eclipse.swt.widgets.Shell access$0(org.eclipse.ui.dialogs.FilteredItemsSelectionDialog);
    Code:
       0: aload_0
       1: invokevirtual #1047               // Method getParentShell:()Lorg/eclipse/swt/widgets/Shell;
       4: areturn

  static org.eclipse.swt.widgets.Control access$1(org.eclipse.ui.dialogs.FilteredItemsSelectionDialog);
    Code:
       0: aload_0
       1: invokevirtual #1045               // Method getDialogArea:()Lorg/eclipse/swt/widgets/Control;
       4: areturn

  private void lambda$0(org.eclipse.swt.events.TraverseEvent);
    Code:
       0: aload_1
       1: getfield      #876                // Field org/eclipse/swt/events/TraverseEvent.detail:I
       4: sipush        128
       7: if_icmpne     30
      10: aload_1
      11: getfield      #877                // Field org/eclipse/swt/events/TraverseEvent.doit:Z
      14: ifeq          30
      17: aload_1
      18: iconst_0
      19: putfield      #876                // Field org/eclipse/swt/events/TraverseEvent.detail:I
      22: aload_0
      23: getfield      #901                // Field pattern:Lorg/eclipse/swt/widgets/Text;
      26: invokevirtual #992                // Method org/eclipse/swt/widgets/Text.setFocus:()Z
      29: pop
      30: return

  private void lambda$1(org.eclipse.swt.events.TraverseEvent);
    Code:
       0: aload_1
       1: getfield      #876                // Field org/eclipse/swt/events/TraverseEvent.detail:I
       4: sipush        128
       7: if_icmpne     33
      10: aload_1
      11: getfield      #877                // Field org/eclipse/swt/events/TraverseEvent.doit:Z
      14: ifeq          33
      17: aload_1
      18: iconst_0
      19: putfield      #876                // Field org/eclipse/swt/events/TraverseEvent.detail:I
      22: aload_0
      23: getfield      #899                // Field tableViewer:Lorg/eclipse/jface/viewers/TableViewer;
      26: invokevirtual #963                // Method org/eclipse/jface/viewers/TableViewer.getTable:()Lorg/eclipse/swt/widgets/Table;
      29: invokevirtual #985                // Method org/eclipse/swt/widgets/Table.setFocus:()Z
      32: pop
      33: return

  private void lambda$2(org.eclipse.swt.events.SelectionEvent);
    Code:
       0: aload_0
       1: invokevirtual #1021               // Method showViewMenu:()V
       4: return

  private void lambda$4(org.eclipse.swt.events.ModifyEvent);
    Code:
       0: aload_0
       1: invokevirtual #1015               // Method applyFilter:()V
       4: return

  private void lambda$5(org.eclipse.jface.viewers.SelectionChangedEvent);
    Code:
       0: aload_1
       1: invokevirtual #944                // Method org/eclipse/jface/viewers/SelectionChangedEvent.getSelection:()Lorg/eclipse/jface/viewers/ISelection;
       4: checkcast     #423                // class org/eclipse/jface/viewers/StructuredSelection
       7: astore_2
       8: aload_0
       9: aload_2
      10: invokevirtual #1039               // Method handleSelected:(Lorg/eclipse/jface/viewers/StructuredSelection;)V
      13: return

  private void lambda$6(org.eclipse.jface.viewers.DoubleClickEvent);
    Code:
       0: aload_0
       1: invokevirtual #1017               // Method handleDoubleClick:()V
       4: return
}
