Compiled from "FilteredItemsSelectionDialog.java"
class org.eclipse.ui.dialogs.FilteredItemsSelectionDialog$ItemsListLabelProvider extends org.eclipse.jface.viewers.StyledCellLabelProvider implements org.eclipse.jface.viewers.ILabelProviderListener {
  private org.eclipse.jface.viewers.ILabelProvider provider;

  private org.eclipse.jface.viewers.ILabelDecorator selectionDecorator;

  private org.eclipse.core.runtime.ListenerList<org.eclipse.jface.viewers.ILabelProviderListener> listeners;

  final org.eclipse.ui.dialogs.FilteredItemsSelectionDialog this$0;

  public org.eclipse.ui.dialogs.FilteredItemsSelectionDialog$ItemsListLabelProvider(org.eclipse.ui.dialogs.FilteredItemsSelectionDialog, org.eclipse.jface.viewers.ILabelProvider, org.eclipse.jface.viewers.ILabelDecorator);
    Code:
       0: aload_0
       1: aload_1
       2: putfield      #277                // Field this$0:Lorg/eclipse/ui/dialogs/FilteredItemsSelectionDialog;
       5: aload_0
       6: invokespecial #291                // Method org/eclipse/jface/viewers/StyledCellLabelProvider."<init>":()V
       9: aload_0
      10: new           #129                // class org/eclipse/core/runtime/ListenerList
      13: dup
      14: invokespecial #287                // Method org/eclipse/core/runtime/ListenerList."<init>":()V
      17: putfield      #274                // Field listeners:Lorg/eclipse/core/runtime/ListenerList;
      20: aload_2
      21: invokestatic  #286                // Method org/eclipse/core/runtime/Assert.isNotNull:(Ljava/lang/Object;)V
      24: aload_0
      25: aload_2
      26: putfield      #276                // Field provider:Lorg/eclipse/jface/viewers/ILabelProvider;
      29: aload_0
      30: aload_3
      31: putfield      #275                // Field selectionDecorator:Lorg/eclipse/jface/viewers/ILabelDecorator;
      34: aload_0
      35: invokestatic  #316                // Method org/eclipse/ui/dialogs/FilteredItemsSelectionDialog.showColoredLabels:()Z
      38: ifeq          52
      41: aload_2
      42: instanceof    #130                // class org/eclipse/jface/viewers/DelegatingStyledCellLabelProvider$IStyledLabelProvider
      45: ifeq          52
      48: iconst_1
      49: goto          53
      52: iconst_0
      53: invokevirtual #317                // Method setOwnerDrawEnabled:(Z)V
      56: aload_2
      57: aload_0
      58: invokeinterface #341,  2          // InterfaceMethod org/eclipse/jface/viewers/ILabelProvider.addListener:(Lorg/eclipse/jface/viewers/ILabelProviderListener;)V
      63: aload_3
      64: ifnull        74
      67: aload_3
      68: aload_0
      69: invokeinterface #336,  2          // InterfaceMethod org/eclipse/jface/viewers/ILabelDecorator.addListener:(Lorg/eclipse/jface/viewers/ILabelProviderListener;)V
      74: return

  public void setSelectionDecorator(org.eclipse.jface.viewers.ILabelDecorator);
    Code:
       0: aload_0
       1: getfield      #275                // Field selectionDecorator:Lorg/eclipse/jface/viewers/ILabelDecorator;
       4: ifnull        26
       7: aload_0
       8: getfield      #275                // Field selectionDecorator:Lorg/eclipse/jface/viewers/ILabelDecorator;
      11: aload_0
      12: invokeinterface #337,  2          // InterfaceMethod org/eclipse/jface/viewers/ILabelDecorator.removeListener:(Lorg/eclipse/jface/viewers/ILabelProviderListener;)V
      17: aload_0
      18: getfield      #275                // Field selectionDecorator:Lorg/eclipse/jface/viewers/ILabelDecorator;
      21: invokeinterface #335,  1          // InterfaceMethod org/eclipse/jface/viewers/ILabelDecorator.dispose:()V
      26: aload_0
      27: aload_1
      28: putfield      #275                // Field selectionDecorator:Lorg/eclipse/jface/viewers/ILabelDecorator;
      31: aload_0
      32: getfield      #275                // Field selectionDecorator:Lorg/eclipse/jface/viewers/ILabelDecorator;
      35: ifnull        48
      38: aload_0
      39: getfield      #275                // Field selectionDecorator:Lorg/eclipse/jface/viewers/ILabelDecorator;
      42: aload_0
      43: invokeinterface #336,  2          // InterfaceMethod org/eclipse/jface/viewers/ILabelDecorator.addListener:(Lorg/eclipse/jface/viewers/ILabelProviderListener;)V
      48: return

  public org.eclipse.jface.viewers.ILabelDecorator getSelectionDecorator();
    Code:
       0: aload_0
       1: getfield      #275                // Field selectionDecorator:Lorg/eclipse/jface/viewers/ILabelDecorator;
       4: areturn

  public void setProvider(org.eclipse.jface.viewers.ILabelProvider);
    Code:
       0: aload_1
       1: invokestatic  #286                // Method org/eclipse/core/runtime/Assert.isNotNull:(Ljava/lang/Object;)V
       4: aload_0
       5: getfield      #276                // Field provider:Lorg/eclipse/jface/viewers/ILabelProvider;
       8: aload_0
       9: invokeinterface #342,  2          // InterfaceMethod org/eclipse/jface/viewers/ILabelProvider.removeListener:(Lorg/eclipse/jface/viewers/ILabelProviderListener;)V
      14: aload_0
      15: getfield      #276                // Field provider:Lorg/eclipse/jface/viewers/ILabelProvider;
      18: invokeinterface #340,  1          // InterfaceMethod org/eclipse/jface/viewers/ILabelProvider.dispose:()V
      23: aload_0
      24: aload_1
      25: putfield      #276                // Field provider:Lorg/eclipse/jface/viewers/ILabelProvider;
      28: aload_0
      29: getfield      #276                // Field provider:Lorg/eclipse/jface/viewers/ILabelProvider;
      32: aload_0
      33: invokeinterface #341,  2          // InterfaceMethod org/eclipse/jface/viewers/ILabelProvider.addListener:(Lorg/eclipse/jface/viewers/ILabelProviderListener;)V
      38: aload_0
      39: invokestatic  #316                // Method org/eclipse/ui/dialogs/FilteredItemsSelectionDialog.showColoredLabels:()Z
      42: ifeq          59
      45: aload_0
      46: getfield      #276                // Field provider:Lorg/eclipse/jface/viewers/ILabelProvider;
      49: instanceof    #130                // class org/eclipse/jface/viewers/DelegatingStyledCellLabelProvider$IStyledLabelProvider
      52: ifeq          59
      55: iconst_1
      56: goto          60
      59: iconst_0
      60: invokevirtual #317                // Method setOwnerDrawEnabled:(Z)V
      63: return

  private org.eclipse.swt.graphics.Image getImage(java.lang.Object);
    Code:
       0: aload_1
       1: instanceof    #150                // class org/eclipse/ui/dialogs/FilteredItemsSelectionDialog$ItemsListSeparator
       4: ifeq          13
       7: ldc           #1                  // String IMG_OBJ_SEPARATOR
       9: invokestatic  #327                // Method org/eclipse/ui/internal/WorkbenchImages.getImage:(Ljava/lang/String;)Lorg/eclipse/swt/graphics/Image;
      12: areturn
      13: aload_0
      14: getfield      #276                // Field provider:Lorg/eclipse/jface/viewers/ILabelProvider;
      17: aload_1
      18: invokeinterface #345,  2          // InterfaceMethod org/eclipse/jface/viewers/ILabelProvider.getImage:(Ljava/lang/Object;)Lorg/eclipse/swt/graphics/Image;
      23: areturn

  private boolean isSelected(java.lang.Object);
    Code:
       0: aload_1
       1: ifnull        56
       4: aload_0
       5: getfield      #277                // Field this$0:Lorg/eclipse/ui/dialogs/FilteredItemsSelectionDialog;
       8: getfield      #272                // Field org/eclipse/ui/dialogs/FilteredItemsSelectionDialog.currentSelection:[Ljava/lang/Object;
      11: ifnull        56
      14: aload_0
      15: getfield      #277                // Field this$0:Lorg/eclipse/ui/dialogs/FilteredItemsSelectionDialog;
      18: getfield      #272                // Field org/eclipse/ui/dialogs/FilteredItemsSelectionDialog.currentSelection:[Ljava/lang/Object;
      21: dup
      22: astore        5
      24: arraylength
      25: istore        4
      27: iconst_0
      28: istore_3
      29: goto          50
      32: aload         5
      34: iload_3
      35: aaload
      36: astore_2
      37: aload_1
      38: aload_2
      39: invokevirtual #278                // Method java/lang/Object.equals:(Ljava/lang/Object;)Z
      42: ifeq          47
      45: iconst_1
      46: ireturn
      47: iinc          3, 1
      50: iload_3
      51: iload         4
      53: if_icmplt     32
      56: iconst_0
      57: ireturn

  private java.lang.String getText(java.lang.Object);
    Code:
       0: aload_1
       1: instanceof    #150                // class org/eclipse/ui/dialogs/FilteredItemsSelectionDialog$ItemsListSeparator
       4: ifeq          19
       7: aload_0
       8: aload_1
       9: checkcast     #150                // class org/eclipse/ui/dialogs/FilteredItemsSelectionDialog$ItemsListSeparator
      12: invokevirtual #326                // Method org/eclipse/ui/dialogs/FilteredItemsSelectionDialog$ItemsListSeparator.getName:()Ljava/lang/String;
      15: invokevirtual #320                // Method getSeparatorLabel:(Ljava/lang/String;)Ljava/lang/String;
      18: areturn
      19: aload_0
      20: getfield      #276                // Field provider:Lorg/eclipse/jface/viewers/ILabelProvider;
      23: aload_1
      24: invokeinterface #343,  2          // InterfaceMethod org/eclipse/jface/viewers/ILabelProvider.getText:(Ljava/lang/Object;)Ljava/lang/String;
      29: astore_2
      30: aload_0
      31: getfield      #275                // Field selectionDecorator:Lorg/eclipse/jface/viewers/ILabelDecorator;
      34: ifnull        57
      37: aload_0
      38: aload_1
      39: invokevirtual #318                // Method isSelected:(Ljava/lang/Object;)Z
      42: ifeq          57
      45: aload_0
      46: getfield      #275                // Field selectionDecorator:Lorg/eclipse/jface/viewers/ILabelDecorator;
      49: aload_2
      50: aload_1
      51: invokeinterface #339,  3          // InterfaceMethod org/eclipse/jface/viewers/ILabelDecorator.decorateText:(Ljava/lang/String;Ljava/lang/Object;)Ljava/lang/String;
      56: areturn
      57: aload_2
      58: areturn

  private org.eclipse.jface.viewers.StyledString getStyledText(java.lang.Object, org.eclipse.jface.viewers.DelegatingStyledCellLabelProvider$IStyledLabelProvider);
    Code:
       0: aload_2
       1: aload_1
       2: invokeinterface #330,  2          // InterfaceMethod org/eclipse/jface/viewers/DelegatingStyledCellLabelProvider$IStyledLabelProvider.getStyledText:(Ljava/lang/Object;)Lorg/eclipse/jface/viewers/StyledString;
       7: astore_3
       8: aload_0
       9: getfield      #275                // Field selectionDecorator:Lorg/eclipse/jface/viewers/ILabelDecorator;
      12: ifnull        47
      15: aload_0
      16: aload_1
      17: invokevirtual #318                // Method isSelected:(Ljava/lang/Object;)Z
      20: ifeq          47
      23: aload_0
      24: getfield      #275                // Field selectionDecorator:Lorg/eclipse/jface/viewers/ILabelDecorator;
      27: aload_3
      28: invokevirtual #295                // Method org/eclipse/jface/viewers/StyledString.getString:()Ljava/lang/String;
      31: aload_1
      32: invokeinterface #339,  3          // InterfaceMethod org/eclipse/jface/viewers/ILabelDecorator.decorateText:(Ljava/lang/String;Ljava/lang/Object;)Ljava/lang/String;
      37: astore        4
      39: aload         4
      41: aconst_null
      42: aload_3
      43: invokestatic  #294                // Method org/eclipse/jface/viewers/StyledCellLabelProvider.styleDecoratedString:(Ljava/lang/String;Lorg/eclipse/jface/viewers/StyledString$Styler;Lorg/eclipse/jface/viewers/StyledString;)Lorg/eclipse/jface/viewers/StyledString;
      46: areturn
      47: aload_3
      48: areturn

  public void update(org.eclipse.jface.viewers.ViewerCell);
    Code:
       0: aload_1
       1: invokevirtual #298                // Method org/eclipse/jface/viewers/ViewerCell.getElement:()Ljava/lang/Object;
       4: astore_2
       5: aload_2
       6: instanceof    #150                // class org/eclipse/ui/dialogs/FilteredItemsSelectionDialog$ItemsListSeparator
       9: ifne          70
      12: aload_0
      13: getfield      #276                // Field provider:Lorg/eclipse/jface/viewers/ILabelProvider;
      16: instanceof    #130                // class org/eclipse/jface/viewers/DelegatingStyledCellLabelProvider$IStyledLabelProvider
      19: ifeq          70
      22: aload_0
      23: getfield      #276                // Field provider:Lorg/eclipse/jface/viewers/ILabelProvider;
      26: checkcast     #130                // class org/eclipse/jface/viewers/DelegatingStyledCellLabelProvider$IStyledLabelProvider
      29: astore_3
      30: aload_0
      31: aload_2
      32: aload_3
      33: invokevirtual #325                // Method getStyledText:(Ljava/lang/Object;Lorg/eclipse/jface/viewers/DelegatingStyledCellLabelProvider$IStyledLabelProvider;)Lorg/eclipse/jface/viewers/StyledString;
      36: astore        4
      38: aload_1
      39: aload         4
      41: invokevirtual #295                // Method org/eclipse/jface/viewers/StyledString.getString:()Ljava/lang/String;
      44: invokevirtual #299                // Method org/eclipse/jface/viewers/ViewerCell.setText:(Ljava/lang/String;)V
      47: aload_1
      48: aload         4
      50: invokevirtual #296                // Method org/eclipse/jface/viewers/StyledString.getStyleRanges:()[Lorg/eclipse/swt/custom/StyleRange;
      53: invokevirtual #300                // Method org/eclipse/jface/viewers/ViewerCell.setStyleRanges:([Lorg/eclipse/swt/custom/StyleRange;)V
      56: aload_1
      57: aload_3
      58: aload_2
      59: invokeinterface #331,  2          // InterfaceMethod org/eclipse/jface/viewers/DelegatingStyledCellLabelProvider$IStyledLabelProvider.getImage:(Ljava/lang/Object;)Lorg/eclipse/swt/graphics/Image;
      64: invokevirtual #304                // Method org/eclipse/jface/viewers/ViewerCell.setImage:(Lorg/eclipse/swt/graphics/Image;)V
      67: goto          88
      70: aload_1
      71: aload_0
      72: aload_2
      73: invokevirtual #319                // Method getText:(Ljava/lang/Object;)Ljava/lang/String;
      76: invokevirtual #299                // Method org/eclipse/jface/viewers/ViewerCell.setText:(Ljava/lang/String;)V
      79: aload_1
      80: aload_0
      81: aload_2
      82: invokevirtual #324                // Method getImage:(Ljava/lang/Object;)Lorg/eclipse/swt/graphics/Image;
      85: invokevirtual #304                // Method org/eclipse/jface/viewers/ViewerCell.setImage:(Lorg/eclipse/swt/graphics/Image;)V
      88: aload_1
      89: aload_0
      90: aload_2
      91: invokevirtual #323                // Method getFont:(Ljava/lang/Object;)Lorg/eclipse/swt/graphics/Font;
      94: invokevirtual #303                // Method org/eclipse/jface/viewers/ViewerCell.setFont:(Lorg/eclipse/swt/graphics/Font;)V
      97: aload_1
      98: aload_0
      99: aload_2
     100: invokevirtual #322                // Method getForeground:(Ljava/lang/Object;)Lorg/eclipse/swt/graphics/Color;
     103: invokevirtual #302                // Method org/eclipse/jface/viewers/ViewerCell.setForeground:(Lorg/eclipse/swt/graphics/Color;)V
     106: aload_1
     107: aload_0
     108: aload_2
     109: invokevirtual #321                // Method getBackground:(Ljava/lang/Object;)Lorg/eclipse/swt/graphics/Color;
     112: invokevirtual #301                // Method org/eclipse/jface/viewers/ViewerCell.setBackground:(Lorg/eclipse/swt/graphics/Color;)V
     115: aload_0
     116: aload_1
     117: invokespecial #293                // Method org/eclipse/jface/viewers/StyledCellLabelProvider.update:(Lorg/eclipse/jface/viewers/ViewerCell;)V
     120: return

  private java.lang.String getSeparatorLabel(java.lang.String);
    Code:
       0: aload_0
       1: getfield      #277                // Field this$0:Lorg/eclipse/ui/dialogs/FilteredItemsSelectionDialog;
       4: getfield      #273                // Field org/eclipse/ui/dialogs/FilteredItemsSelectionDialog.tableViewer:Lorg/eclipse/jface/viewers/TableViewer;
       7: invokevirtual #297                // Method org/eclipse/jface/viewers/TableViewer.getTable:()Lorg/eclipse/swt/widgets/Table;
      10: invokevirtual #314                // Method org/eclipse/swt/widgets/Table.getBounds:()Lorg/eclipse/swt/graphics/Rectangle;
      13: astore_2
      14: aload_0
      15: getfield      #277                // Field this$0:Lorg/eclipse/ui/dialogs/FilteredItemsSelectionDialog;
      18: getfield      #273                // Field org/eclipse/ui/dialogs/FilteredItemsSelectionDialog.tableViewer:Lorg/eclipse/jface/viewers/TableViewer;
      21: invokevirtual #297                // Method org/eclipse/jface/viewers/TableViewer.getTable:()Lorg/eclipse/swt/widgets/Table;
      24: iconst_0
      25: iconst_0
      26: iconst_0
      27: iconst_0
      28: invokevirtual #315                // Method org/eclipse/swt/widgets/Table.computeTrim:(IIII)Lorg/eclipse/swt/graphics/Rectangle;
      31: getfield      #271                // Field org/eclipse/swt/graphics/Rectangle.width:I
      34: istore_3
      35: ldc           #1                  // String IMG_OBJ_SEPARATOR
      37: invokestatic  #327                // Method org/eclipse/ui/internal/WorkbenchImages.getImage:(Ljava/lang/String;)Lorg/eclipse/swt/graphics/Image;
      40: invokevirtual #310                // Method org/eclipse/swt/graphics/Image.getBounds:()Lorg/eclipse/swt/graphics/Rectangle;
      43: getfield      #271                // Field org/eclipse/swt/graphics/Rectangle.width:I
      46: istore        4
      48: aload_2
      49: getfield      #271                // Field org/eclipse/swt/graphics/Rectangle.width:I
      52: iload_3
      53: isub
      54: iload         4
      56: isub
      57: istore        5
      59: new           #142                // class org/eclipse/swt/graphics/GC
      62: dup
      63: aload_0
      64: getfield      #277                // Field this$0:Lorg/eclipse/ui/dialogs/FilteredItemsSelectionDialog;
      67: getfield      #273                // Field org/eclipse/ui/dialogs/FilteredItemsSelectionDialog.tableViewer:Lorg/eclipse/jface/viewers/TableViewer;
      70: invokevirtual #297                // Method org/eclipse/jface/viewers/TableViewer.getTable:()Lorg/eclipse/swt/widgets/Table;
      73: invokespecial #307                // Method org/eclipse/swt/graphics/GC."<init>":(Lorg/eclipse/swt/graphics/Drawable;)V
      76: astore        6
      78: aload         6
      80: aload_0
      81: getfield      #277                // Field this$0:Lorg/eclipse/ui/dialogs/FilteredItemsSelectionDialog;
      84: getfield      #273                // Field org/eclipse/ui/dialogs/FilteredItemsSelectionDialog.tableViewer:Lorg/eclipse/jface/viewers/TableViewer;
      87: invokevirtual #297                // Method org/eclipse/jface/viewers/TableViewer.getTable:()Lorg/eclipse/swt/widgets/Table;
      90: invokevirtual #313                // Method org/eclipse/swt/widgets/Table.getFont:()Lorg/eclipse/swt/graphics/Font;
      93: invokevirtual #308                // Method org/eclipse/swt/graphics/GC.setFont:(Lorg/eclipse/swt/graphics/Font;)V
      96: aload         6
      98: bipush        45
     100: invokevirtual #306                // Method org/eclipse/swt/graphics/GC.getAdvanceWidth:(C)I
     103: istore        7
     105: aload         6
     107: aload_1
     108: invokevirtual #309                // Method org/eclipse/swt/graphics/GC.textExtent:(Ljava/lang/String;)Lorg/eclipse/swt/graphics/Point;
     111: getfield      #270                // Field org/eclipse/swt/graphics/Point.x:I
     114: istore        8
     116: aload         6
     118: invokevirtual #305                // Method org/eclipse/swt/graphics/GC.dispose:()V
     121: new           #126                // class java/lang/StringBuilder
     124: dup
     125: invokespecial #280                // Method java/lang/StringBuilder."<init>":()V
     128: astore        9
     130: iload         5
     132: iload         8
     134: isub
     135: iload         7
     137: idiv
     138: iconst_2
     139: idiv
     140: iconst_2
     141: isub
     142: istore        10
     144: iconst_0
     145: istore        11
     147: goto          161
     150: aload         9
     152: bipush        45
     154: invokevirtual #283                // Method java/lang/StringBuilder.append:(C)Ljava/lang/StringBuilder;
     157: pop
     158: iinc          11, 1
     161: iload         11
     163: iload         10
     165: if_icmplt     150
     168: new           #126                // class java/lang/StringBuilder
     171: dup
     172: invokespecial #280                // Method java/lang/StringBuilder."<init>":()V
     175: astore        11
     177: aload         11
     179: aload         9
     181: invokevirtual #284                // Method java/lang/StringBuilder.append:(Ljava/lang/CharSequence;)Ljava/lang/StringBuilder;
     184: pop
     185: aload         11
     187: new           #126                // class java/lang/StringBuilder
     190: dup
     191: ldc_w         #122                // String
     194: invokespecial #282                // Method java/lang/StringBuilder."<init>":(Ljava/lang/String;)V
     197: aload_1
     198: invokevirtual #285                // Method java/lang/StringBuilder.append:(Ljava/lang/String;)Ljava/lang/StringBuilder;
     201: ldc_w         #122                // String
     204: invokevirtual #285                // Method java/lang/StringBuilder.append:(Ljava/lang/String;)Ljava/lang/StringBuilder;
     207: invokevirtual #281                // Method java/lang/StringBuilder.toString:()Ljava/lang/String;
     210: invokevirtual #285                // Method java/lang/StringBuilder.append:(Ljava/lang/String;)Ljava/lang/StringBuilder;
     213: pop
     214: aload         11
     216: aload         9
     218: invokevirtual #284                // Method java/lang/StringBuilder.append:(Ljava/lang/CharSequence;)Ljava/lang/StringBuilder;
     221: pop
     222: aload         11
     224: invokevirtual #281                // Method java/lang/StringBuilder.toString:()Ljava/lang/String;
     227: invokevirtual #279                // Method java/lang/String.trim:()Ljava/lang/String;
     230: areturn

  public void addListener(org.eclipse.jface.viewers.ILabelProviderListener);
    Code:
       0: aload_0
       1: getfield      #274                // Field listeners:Lorg/eclipse/core/runtime/ListenerList;
       4: aload_1
       5: invokevirtual #288                // Method org/eclipse/core/runtime/ListenerList.add:(Ljava/lang/Object;)V
       8: return

  public void dispose();
    Code:
       0: aload_0
       1: getfield      #276                // Field provider:Lorg/eclipse/jface/viewers/ILabelProvider;
       4: aload_0
       5: invokeinterface #342,  2          // InterfaceMethod org/eclipse/jface/viewers/ILabelProvider.removeListener:(Lorg/eclipse/jface/viewers/ILabelProviderListener;)V
      10: aload_0
      11: getfield      #276                // Field provider:Lorg/eclipse/jface/viewers/ILabelProvider;
      14: invokeinterface #340,  1          // InterfaceMethod org/eclipse/jface/viewers/ILabelProvider.dispose:()V
      19: aload_0
      20: getfield      #275                // Field selectionDecorator:Lorg/eclipse/jface/viewers/ILabelDecorator;
      23: ifnull        45
      26: aload_0
      27: getfield      #275                // Field selectionDecorator:Lorg/eclipse/jface/viewers/ILabelDecorator;
      30: aload_0
      31: invokeinterface #337,  2          // InterfaceMethod org/eclipse/jface/viewers/ILabelDecorator.removeListener:(Lorg/eclipse/jface/viewers/ILabelProviderListener;)V
      36: aload_0
      37: getfield      #275                // Field selectionDecorator:Lorg/eclipse/jface/viewers/ILabelDecorator;
      40: invokeinterface #335,  1          // InterfaceMethod org/eclipse/jface/viewers/ILabelDecorator.dispose:()V
      45: aload_0
      46: invokespecial #292                // Method org/eclipse/jface/viewers/StyledCellLabelProvider.dispose:()V
      49: return

  public boolean isLabelProperty(java.lang.Object, java.lang.String);
    Code:
       0: aload_0
       1: getfield      #276                // Field provider:Lorg/eclipse/jface/viewers/ILabelProvider;
       4: aload_1
       5: aload_2
       6: invokeinterface #344,  3          // InterfaceMethod org/eclipse/jface/viewers/ILabelProvider.isLabelProperty:(Ljava/lang/Object;Ljava/lang/String;)Z
      11: ifeq          16
      14: iconst_1
      15: ireturn
      16: aload_0
      17: getfield      #275                // Field selectionDecorator:Lorg/eclipse/jface/viewers/ILabelDecorator;
      20: ifnull        39
      23: aload_0
      24: getfield      #275                // Field selectionDecorator:Lorg/eclipse/jface/viewers/ILabelDecorator;
      27: aload_1
      28: aload_2
      29: invokeinterface #338,  3          // InterfaceMethod org/eclipse/jface/viewers/ILabelDecorator.isLabelProperty:(Ljava/lang/Object;Ljava/lang/String;)Z
      34: ifeq          39
      37: iconst_1
      38: ireturn
      39: iconst_0
      40: ireturn

  public void removeListener(org.eclipse.jface.viewers.ILabelProviderListener);
    Code:
       0: aload_0
       1: getfield      #274                // Field listeners:Lorg/eclipse/core/runtime/ListenerList;
       4: aload_1
       5: invokevirtual #289                // Method org/eclipse/core/runtime/ListenerList.remove:(Ljava/lang/Object;)V
       8: return

  private org.eclipse.swt.graphics.Color getBackground(java.lang.Object);
    Code:
       0: aload_1
       1: instanceof    #150                // class org/eclipse/ui/dialogs/FilteredItemsSelectionDialog$ItemsListSeparator
       4: ifeq          9
       7: aconst_null
       8: areturn
       9: aload_0
      10: getfield      #276                // Field provider:Lorg/eclipse/jface/viewers/ILabelProvider;
      13: instanceof    #131                // class org/eclipse/jface/viewers/IColorProvider
      16: ifeq          33
      19: aload_0
      20: getfield      #276                // Field provider:Lorg/eclipse/jface/viewers/ILabelProvider;
      23: checkcast     #131                // class org/eclipse/jface/viewers/IColorProvider
      26: aload_1
      27: invokeinterface #332,  2          // InterfaceMethod org/eclipse/jface/viewers/IColorProvider.getBackground:(Ljava/lang/Object;)Lorg/eclipse/swt/graphics/Color;
      32: areturn
      33: aconst_null
      34: areturn

  private org.eclipse.swt.graphics.Color getForeground(java.lang.Object);
    Code:
       0: aload_1
       1: instanceof    #150                // class org/eclipse/ui/dialogs/FilteredItemsSelectionDialog$ItemsListSeparator
       4: ifeq          16
       7: invokestatic  #312                // Method org/eclipse/swt/widgets/Display.getCurrent:()Lorg/eclipse/swt/widgets/Display;
      10: bipush        18
      12: invokevirtual #311                // Method org/eclipse/swt/widgets/Display.getSystemColor:(I)Lorg/eclipse/swt/graphics/Color;
      15: areturn
      16: aload_0
      17: getfield      #276                // Field provider:Lorg/eclipse/jface/viewers/ILabelProvider;
      20: instanceof    #131                // class org/eclipse/jface/viewers/IColorProvider
      23: ifeq          40
      26: aload_0
      27: getfield      #276                // Field provider:Lorg/eclipse/jface/viewers/ILabelProvider;
      30: checkcast     #131                // class org/eclipse/jface/viewers/IColorProvider
      33: aload_1
      34: invokeinterface #333,  2          // InterfaceMethod org/eclipse/jface/viewers/IColorProvider.getForeground:(Ljava/lang/Object;)Lorg/eclipse/swt/graphics/Color;
      39: areturn
      40: aconst_null
      41: areturn

  private org.eclipse.swt.graphics.Font getFont(java.lang.Object);
    Code:
       0: aload_1
       1: instanceof    #150                // class org/eclipse/ui/dialogs/FilteredItemsSelectionDialog$ItemsListSeparator
       4: ifeq          9
       7: aconst_null
       8: areturn
       9: aload_0
      10: getfield      #276                // Field provider:Lorg/eclipse/jface/viewers/ILabelProvider;
      13: instanceof    #132                // class org/eclipse/jface/viewers/IFontProvider
      16: ifeq          33
      19: aload_0
      20: getfield      #276                // Field provider:Lorg/eclipse/jface/viewers/ILabelProvider;
      23: checkcast     #132                // class org/eclipse/jface/viewers/IFontProvider
      26: aload_1
      27: invokeinterface #334,  2          // InterfaceMethod org/eclipse/jface/viewers/IFontProvider.getFont:(Ljava/lang/Object;)Lorg/eclipse/swt/graphics/Font;
      32: areturn
      33: aconst_null
      34: areturn

  public void labelProviderChanged(org.eclipse.jface.viewers.LabelProviderChangedEvent);
    Code:
       0: aload_0
       1: getfield      #274                // Field listeners:Lorg/eclipse/core/runtime/ListenerList;
       4: invokevirtual #290                // Method org/eclipse/core/runtime/ListenerList.iterator:()Ljava/util/Iterator;
       7: astore_3
       8: goto          28
      11: aload_3
      12: invokeinterface #329,  1          // InterfaceMethod java/util/Iterator.next:()Ljava/lang/Object;
      17: checkcast     #135                // class org/eclipse/jface/viewers/ILabelProviderListener
      20: astore_2
      21: aload_2
      22: aload_1
      23: invokeinterface #346,  2          // InterfaceMethod org/eclipse/jface/viewers/ILabelProviderListener.labelProviderChanged:(Lorg/eclipse/jface/viewers/LabelProviderChangedEvent;)V
      28: aload_3
      29: invokeinterface #328,  1          // InterfaceMethod java/util/Iterator.hasNext:()Z
      34: ifne          11
      37: return
}
