Compiled from "HttpMethods.java"
public final class org.apache.camel.http.common.HttpMethods extends java.lang.Enum<org.apache.camel.http.common.HttpMethods> {
  public static final org.apache.camel.http.common.HttpMethods GET;

  public static final org.apache.camel.http.common.HttpMethods POST;

  public static final org.apache.camel.http.common.HttpMethods PUT;

  public static final org.apache.camel.http.common.HttpMethods DELETE;

  public static final org.apache.camel.http.common.HttpMethods HEAD;

  public static final org.apache.camel.http.common.HttpMethods OPTIONS;

  public static final org.apache.camel.http.common.HttpMethods TRACE;

  public static final org.apache.camel.http.common.HttpMethods PATCH;

  private static final org.apache.camel.http.common.HttpMethods[] $VALUES;

  public static org.apache.camel.http.common.HttpMethods[] values();
    Code:
       0: getstatic     #1                  // Field $VALUES:[Lorg/apache/camel/http/common/HttpMethods;
       3: invokevirtual #2                  // Method "[Lorg/apache/camel/http/common/HttpMethods;".clone:()Ljava/lang/Object;
       6: checkcast     #3                  // class "[Lorg/apache/camel/http/common/HttpMethods;"
       9: areturn

  public static org.apache.camel.http.common.HttpMethods valueOf(java.lang.String);
    Code:
       0: ldc           #4                  // class org/apache/camel/http/common/HttpMethods
       2: aload_0
       3: invokestatic  #5                  // Method java/lang/Enum.valueOf:(Ljava/lang/Class;Ljava/lang/String;)Ljava/lang/Enum;
       6: checkcast     #4                  // class org/apache/camel/http/common/HttpMethods
       9: areturn

  private org.apache.camel.http.common.HttpMethods();
    Code:
       0: aload_0
       1: aload_1
       2: iload_2
       3: invokespecial #6                  // Method java/lang/Enum."<init>":(Ljava/lang/String;I)V
       6: return

  static {};
    Code:
       0: new           #4                  // class org/apache/camel/http/common/HttpMethods
       3: dup
       4: ldc           #7                  // String GET
       6: iconst_0
       7: invokespecial #8                  // Method "<init>":(Ljava/lang/String;I)V
      10: putstatic     #9                  // Field GET:Lorg/apache/camel/http/common/HttpMethods;
      13: new           #4                  // class org/apache/camel/http/common/HttpMethods
      16: dup
      17: ldc           #10                 // String POST
      19: iconst_1
      20: invokespecial #8                  // Method "<init>":(Ljava/lang/String;I)V
      23: putstatic     #11                 // Field POST:Lorg/apache/camel/http/common/HttpMethods;
      26: new           #4                  // class org/apache/camel/http/common/HttpMethods
      29: dup
      30: ldc           #12                 // String PUT
      32: iconst_2
      33: invokespecial #8                  // Method "<init>":(Ljava/lang/String;I)V
      36: putstatic     #13                 // Field PUT:Lorg/apache/camel/http/common/HttpMethods;
      39: new           #4                  // class org/apache/camel/http/common/HttpMethods
      42: dup
      43: ldc           #14                 // String DELETE
      45: iconst_3
      46: invokespecial #8                  // Method "<init>":(Ljava/lang/String;I)V
      49: putstatic     #15                 // Field DELETE:Lorg/apache/camel/http/common/HttpMethods;
      52: new           #4                  // class org/apache/camel/http/common/HttpMethods
      55: dup
      56: ldc           #16                 // String HEAD
      58: iconst_4
      59: invokespecial #8                  // Method "<init>":(Ljava/lang/String;I)V
      62: putstatic     #17                 // Field HEAD:Lorg/apache/camel/http/common/HttpMethods;
      65: new           #4                  // class org/apache/camel/http/common/HttpMethods
      68: dup
      69: ldc           #18                 // String OPTIONS
      71: iconst_5
      72: invokespecial #8                  // Method "<init>":(Ljava/lang/String;I)V
      75: putstatic     #19                 // Field OPTIONS:Lorg/apache/camel/http/common/HttpMethods;
      78: new           #4                  // class org/apache/camel/http/common/HttpMethods
      81: dup
      82: ldc           #20                 // String TRACE
      84: bipush        6
      86: invokespecial #8                  // Method "<init>":(Ljava/lang/String;I)V
      89: putstatic     #21                 // Field TRACE:Lorg/apache/camel/http/common/HttpMethods;
      92: new           #4                  // class org/apache/camel/http/common/HttpMethods
      95: dup
      96: ldc           #22                 // String PATCH
      98: bipush        7
     100: invokespecial #8                  // Method "<init>":(Ljava/lang/String;I)V
     103: putstatic     #23                 // Field PATCH:Lorg/apache/camel/http/common/HttpMethods;
     106: bipush        8
     108: anewarray     #4                  // class org/apache/camel/http/common/HttpMethods
     111: dup
     112: iconst_0
     113: getstatic     #9                  // Field GET:Lorg/apache/camel/http/common/HttpMethods;
     116: aastore
     117: dup
     118: iconst_1
     119: getstatic     #11                 // Field POST:Lorg/apache/camel/http/common/HttpMethods;
     122: aastore
     123: dup
     124: iconst_2
     125: getstatic     #13                 // Field PUT:Lorg/apache/camel/http/common/HttpMethods;
     128: aastore
     129: dup
     130: iconst_3
     131: getstatic     #15                 // Field DELETE:Lorg/apache/camel/http/common/HttpMethods;
     134: aastore
     135: dup
     136: iconst_4
     137: getstatic     #17                 // Field HEAD:Lorg/apache/camel/http/common/HttpMethods;
     140: aastore
     141: dup
     142: iconst_5
     143: getstatic     #19                 // Field OPTIONS:Lorg/apache/camel/http/common/HttpMethods;
     146: aastore
     147: dup
     148: bipush        6
     150: getstatic     #21                 // Field TRACE:Lorg/apache/camel/http/common/HttpMethods;
     153: aastore
     154: dup
     155: bipush        7
     157: getstatic     #23                 // Field PATCH:Lorg/apache/camel/http/common/HttpMethods;
     160: aastore
     161: putstatic     #1                  // Field $VALUES:[Lorg/apache/camel/http/common/HttpMethods;
     164: return
}
