Compiled from "DiMeRemoteEventChannelConsumerProxy.java"
public class org.distributeme.support.eventservice.DiMeRemoteEventChannelConsumerProxy implements net.anotheria.anoprise.eventservice.RemoteEventChannelConsumerProxy {
  private static org.slf4j.Logger LOG;

  private java.util.concurrent.CopyOnWriteArrayList<net.anotheria.anoprise.eventservice.RemoteEventServiceConsumer> consumers;

  private java.lang.String channelName;

  org.distributeme.support.eventservice.DiMeRemoteEventChannelConsumerProxy(java.lang.String);
    Code:
       0: aload_0
       1: invokespecial #1                  // Method java/lang/Object."<init>":()V
       4: aload_0
       5: new           #2                  // class java/util/concurrent/CopyOnWriteArrayList
       8: dup
       9: invokespecial #3                  // Method java/util/concurrent/CopyOnWriteArrayList."<init>":()V
      12: putfield      #4                  // Field consumers:Ljava/util/concurrent/CopyOnWriteArrayList;
      15: aload_0
      16: aload_1
      17: putfield      #5                  // Field channelName:Ljava/lang/String;
      20: return

  public void addRemoteConsumer(net.anotheria.anoprise.eventservice.RemoteEventServiceConsumer);
    Code:
       0: aload_0
       1: getfield      #4                  // Field consumers:Ljava/util/concurrent/CopyOnWriteArrayList;
       4: aload_1
       5: invokevirtual #6                  // Method java/util/concurrent/CopyOnWriteArrayList.add:(Ljava/lang/Object;)Z
       8: pop
       9: return

  public void removeRemoteConsumer(net.anotheria.anoprise.eventservice.RemoteEventServiceConsumer);
    Code:
       0: aload_0
       1: getfield      #4                  // Field consumers:Ljava/util/concurrent/CopyOnWriteArrayList;
       4: aload_1
       5: invokevirtual #7                  // Method java/util/concurrent/CopyOnWriteArrayList.remove:(Ljava/lang/Object;)Z
       8: pop
       9: return

  public void addConsumer(net.anotheria.anoprise.eventservice.EventServiceConsumer);
    Code:
       0: new           #8                  // class java/lang/UnsupportedOperationException
       3: dup
       4: ldc           #9                  // String addConsumer
       6: invokespecial #10                 // Method java/lang/UnsupportedOperationException."<init>":(Ljava/lang/String;)V
       9: athrow

  public java.lang.String getName();
    Code:
       0: aload_0
       1: getfield      #5                  // Field channelName:Ljava/lang/String;
       4: areturn

  public void push(net.anotheria.anoprise.eventservice.Event);
    Code:
       0: new           #8                  // class java/lang/UnsupportedOperationException
       3: dup
       4: ldc           #9                  // String addConsumer
       6: invokespecial #10                 // Method java/lang/UnsupportedOperationException."<init>":(Ljava/lang/String;)V
       9: athrow

  public void removeConsumer(net.anotheria.anoprise.eventservice.EventServiceConsumer);
    Code:
       0: new           #8                  // class java/lang/UnsupportedOperationException
       3: dup
       4: ldc           #9                  // String addConsumer
       6: invokespecial #10                 // Method java/lang/UnsupportedOperationException."<init>":(Ljava/lang/String;)V
       9: athrow

  public void pushEvent(net.anotheria.anoprise.eventservice.Event);
    Code:
       0: new           #11                 // class net/anotheria/anoprise/eventservice/EventTransportShell
       3: dup
       4: invokespecial #12                 // Method net/anotheria/anoprise/eventservice/EventTransportShell."<init>":()V
       7: astore_2
       8: aload_2
       9: aload_0
      10: invokevirtual #13                 // Method getName:()Ljava/lang/String;
      13: invokevirtual #14                 // Method net/anotheria/anoprise/eventservice/EventTransportShell.setChannelName:(Ljava/lang/String;)V
      16: aload_2
      17: aload_1
      18: invokestatic  #15                 // Method net/anotheria/net/util/ByteArraySerializer.serializeObject:(Ljava/io/Serializable;)[B
      21: invokevirtual #16                 // Method net/anotheria/anoprise/eventservice/EventTransportShell.setData:([B)V
      24: goto          72
      27: astore_3
      28: getstatic     #18                 // Field LOG:Lorg/slf4j/Logger;
      31: ldc           #19                 // String Can\'t serialize event data, aborting event
      33: aload_3
      34: invokeinterface #20,  3           // InterfaceMethod org/slf4j/Logger.error:(Ljava/lang/String;Ljava/lang/Throwable;)V
      39: new           #21                 // class java/lang/IllegalArgumentException
      42: dup
      43: new           #22                 // class java/lang/StringBuilder
      46: dup
      47: invokespecial #23                 // Method java/lang/StringBuilder."<init>":()V
      50: ldc           #24                 // String Event
      52: invokevirtual #25                 // Method java/lang/StringBuilder.append:(Ljava/lang/String;)Ljava/lang/StringBuilder;
      55: aload_1
      56: invokevirtual #26                 // Method java/lang/StringBuilder.append:(Ljava/lang/Object;)Ljava/lang/StringBuilder;
      59: ldc           #27                 // String  contains not serializeable data part
      61: invokevirtual #25                 // Method java/lang/StringBuilder.append:(Ljava/lang/String;)Ljava/lang/StringBuilder;
      64: invokevirtual #28                 // Method java/lang/StringBuilder.toString:()Ljava/lang/String;
      67: aload_3
      68: invokespecial #29                 // Method java/lang/IllegalArgumentException."<init>":(Ljava/lang/String;Ljava/lang/Throwable;)V
      71: athrow
      72: aload_0
      73: getfield      #4                  // Field consumers:Ljava/util/concurrent/CopyOnWriteArrayList;
      76: invokevirtual #30                 // Method java/util/concurrent/CopyOnWriteArrayList.iterator:()Ljava/util/Iterator;
      79: astore_3
      80: aload_3
      81: invokeinterface #31,  1           // InterfaceMethod java/util/Iterator.hasNext:()Z
      86: ifeq          151
      89: aload_3
      90: invokeinterface #32,  1           // InterfaceMethod java/util/Iterator.next:()Ljava/lang/Object;
      95: checkcast     #33                 // class net/anotheria/anoprise/eventservice/RemoteEventServiceConsumer
      98: astore        4
     100: aload         4
     102: aload_2
     103: invokeinterface #34,  2           // InterfaceMethod net/anotheria/anoprise/eventservice/RemoteEventServiceConsumer.deliverEvent:(Lnet/anotheria/anoprise/eventservice/EventTransportShell;)V
     108: goto          148
     111: astore        5
     113: getstatic     #18                 // Field LOG:Lorg/slf4j/Logger;
     116: new           #22                 // class java/lang/StringBuilder
     119: dup
     120: invokespecial #23                 // Method java/lang/StringBuilder."<init>":()V
     123: ldc           #36                 // String Consumer
     125: invokevirtual #25                 // Method java/lang/StringBuilder.append:(Ljava/lang/String;)Ljava/lang/StringBuilder;
     128: aload         4
     130: invokevirtual #26                 // Method java/lang/StringBuilder.append:(Ljava/lang/Object;)Ljava/lang/StringBuilder;
     133: ldc           #37                 // String  failed, skipping
     135: invokevirtual #25                 // Method java/lang/StringBuilder.append:(Ljava/lang/String;)Ljava/lang/StringBuilder;
     138: invokevirtual #28                 // Method java/lang/StringBuilder.toString:()Ljava/lang/String;
     141: aload         5
     143: invokeinterface #38,  3           // InterfaceMethod org/slf4j/Logger.warn:(Ljava/lang/String;Ljava/lang/Throwable;)V
     148: goto          80
     151: return
    Exception table:
       from    to  target type
          16    24    27   Class java/io/IOException
         100   108   111   Class java/lang/Exception

  public boolean isLocal();
    Code:
       0: iconst_0
       1: ireturn

  static {};
    Code:
       0: ldc_w         #39                 // class org/distributeme/support/eventservice/DiMeRemoteEventChannelConsumerProxy
       3: invokestatic  #40                 // Method org/slf4j/LoggerFactory.getLogger:(Ljava/lang/Class;)Lorg/slf4j/Logger;
       6: putstatic     #18                 // Field LOG:Lorg/slf4j/Logger;
       9: return
}
