Compiled from "CarbonDataSource.java"
public class org.wso2.carbon.ndatasource.core.CarbonDataSource {
  private org.wso2.carbon.ndatasource.core.DataSourceMetaInfo dsmInfo;

  private org.wso2.carbon.ndatasource.core.DataSourceStatus dsStatus;

  private java.lang.Object dsObject;

  public org.wso2.carbon.ndatasource.core.CarbonDataSource(org.wso2.carbon.ndatasource.core.DataSourceMetaInfo, org.wso2.carbon.ndatasource.core.DataSourceStatus, java.lang.Object);
    Code:
       0: aload_0
       1: invokespecial #1                  // Method java/lang/Object."<init>":()V
       4: aload_0
       5: aload_1
       6: putfield      #2                  // Field dsmInfo:Lorg/wso2/carbon/ndatasource/core/DataSourceMetaInfo;
       9: aload_0
      10: aload_2
      11: putfield      #3                  // Field dsStatus:Lorg/wso2/carbon/ndatasource/core/DataSourceStatus;
      14: aload_0
      15: aload_3
      16: putfield      #4                  // Field dsObject:Ljava/lang/Object;
      19: return

  public org.wso2.carbon.ndatasource.core.DataSourceMetaInfo getDSMInfo();
    Code:
       0: aload_0
       1: getfield      #2                  // Field dsmInfo:Lorg/wso2/carbon/ndatasource/core/DataSourceMetaInfo;
       4: areturn

  public org.wso2.carbon.ndatasource.core.DataSourceStatus getDSStatus();
    Code:
       0: aload_0
       1: getfield      #3                  // Field dsStatus:Lorg/wso2/carbon/ndatasource/core/DataSourceStatus;
       4: areturn

  public java.lang.Object getDSObject();
    Code:
       0: aload_0
       1: getfield      #4                  // Field dsObject:Ljava/lang/Object;
       4: areturn
}
