Compiled from "DataSourceService.java"
public class org.wso2.carbon.ndatasource.core.DataSourceService {
  public org.wso2.carbon.ndatasource.core.DataSourceService();
    Code:
       0: aload_0
       1: invokespecial #1                  // Method java/lang/Object."<init>":()V
       4: return

  public java.util.List<org.wso2.carbon.ndatasource.core.CarbonDataSource> getAllDataSources() throws org.wso2.carbon.ndatasource.common.DataSourceException;
    Code:
       0: new           #2                  // class java/util/ArrayList
       3: dup
       4: invokestatic  #3                  // Method org/wso2/carbon/ndatasource/core/DataSourceManager.getInstance:()Lorg/wso2/carbon/ndatasource/core/DataSourceManager;
       7: invokevirtual #4                  // Method org/wso2/carbon/ndatasource/core/DataSourceManager.getDataSourceRepository:()Lorg/wso2/carbon/ndatasource/core/DataSourceRepository;
      10: invokevirtual #5                  // Method org/wso2/carbon/ndatasource/core/DataSourceRepository.getAllDataSources:()Ljava/util/Collection;
      13: invokespecial #6                  // Method java/util/ArrayList."<init>":(Ljava/util/Collection;)V
      16: areturn

  public java.util.List<org.wso2.carbon.ndatasource.core.CarbonDataSource> getAllDataSourcesForType(java.lang.String) throws org.wso2.carbon.ndatasource.common.DataSourceException;
    Code:
       0: new           #2                  // class java/util/ArrayList
       3: dup
       4: invokespecial #7                  // Method java/util/ArrayList."<init>":()V
       7: astore_2
       8: invokestatic  #3                  // Method org/wso2/carbon/ndatasource/core/DataSourceManager.getInstance:()Lorg/wso2/carbon/ndatasource/core/DataSourceManager;
      11: invokevirtual #4                  // Method org/wso2/carbon/ndatasource/core/DataSourceManager.getDataSourceRepository:()Lorg/wso2/carbon/ndatasource/core/DataSourceRepository;
      14: invokevirtual #5                  // Method org/wso2/carbon/ndatasource/core/DataSourceRepository.getAllDataSources:()Ljava/util/Collection;
      17: invokeinterface #8,  1            // InterfaceMethod java/util/Collection.iterator:()Ljava/util/Iterator;
      22: astore_3
      23: aload_3
      24: invokeinterface #9,  1            // InterfaceMethod java/util/Iterator.hasNext:()Z
      29: ifeq          73
      32: aload_3
      33: invokeinterface #10,  1           // InterfaceMethod java/util/Iterator.next:()Ljava/lang/Object;
      38: checkcast     #11                 // class org/wso2/carbon/ndatasource/core/CarbonDataSource
      41: astore        4
      43: aload_1
      44: aload         4
      46: invokevirtual #12                 // Method org/wso2/carbon/ndatasource/core/CarbonDataSource.getDSMInfo:()Lorg/wso2/carbon/ndatasource/core/DataSourceMetaInfo;
      49: invokevirtual #13                 // Method org/wso2/carbon/ndatasource/core/DataSourceMetaInfo.getDefinition:()Lorg/wso2/carbon/ndatasource/core/DataSourceMetaInfo$DataSourceDefinition;
      52: invokevirtual #14                 // Method org/wso2/carbon/ndatasource/core/DataSourceMetaInfo$DataSourceDefinition.getType:()Ljava/lang/String;
      55: invokevirtual #15                 // Method java/lang/String.equals:(Ljava/lang/Object;)Z
      58: ifeq          70
      61: aload_2
      62: aload         4
      64: invokeinterface #16,  2           // InterfaceMethod java/util/List.add:(Ljava/lang/Object;)Z
      69: pop
      70: goto          23
      73: aload_2
      74: areturn

  public org.wso2.carbon.ndatasource.core.CarbonDataSource getDataSource(java.lang.String) throws org.wso2.carbon.ndatasource.common.DataSourceException;
    Code:
       0: invokestatic  #3                  // Method org/wso2/carbon/ndatasource/core/DataSourceManager.getInstance:()Lorg/wso2/carbon/ndatasource/core/DataSourceManager;
       3: invokevirtual #4                  // Method org/wso2/carbon/ndatasource/core/DataSourceManager.getDataSourceRepository:()Lorg/wso2/carbon/ndatasource/core/DataSourceRepository;
       6: aload_1
       7: invokevirtual #17                 // Method org/wso2/carbon/ndatasource/core/DataSourceRepository.getDataSource:(Ljava/lang/String;)Lorg/wso2/carbon/ndatasource/core/CarbonDataSource;
      10: areturn

  public java.util.List<java.lang.String> getDataSourceTypes() throws org.wso2.carbon.ndatasource.common.DataSourceException;
    Code:
       0: invokestatic  #3                  // Method org/wso2/carbon/ndatasource/core/DataSourceManager.getInstance:()Lorg/wso2/carbon/ndatasource/core/DataSourceManager;
       3: invokevirtual #18                 // Method org/wso2/carbon/ndatasource/core/DataSourceManager.getDataSourceTypes:()Ljava/util/List;
       6: areturn

  public void reloadAllDataSources() throws org.wso2.carbon.ndatasource.common.DataSourceException;
    Code:
       0: invokestatic  #3                  // Method org/wso2/carbon/ndatasource/core/DataSourceManager.getInstance:()Lorg/wso2/carbon/ndatasource/core/DataSourceManager;
       3: invokevirtual #4                  // Method org/wso2/carbon/ndatasource/core/DataSourceManager.getDataSourceRepository:()Lorg/wso2/carbon/ndatasource/core/DataSourceRepository;
       6: invokevirtual #19                 // Method org/wso2/carbon/ndatasource/core/DataSourceRepository.refreshAllUserDataSources:()V
       9: return

  public void reloadDataSource(java.lang.String) throws org.wso2.carbon.ndatasource.common.DataSourceException;
    Code:
       0: invokestatic  #3                  // Method org/wso2/carbon/ndatasource/core/DataSourceManager.getInstance:()Lorg/wso2/carbon/ndatasource/core/DataSourceManager;
       3: invokevirtual #4                  // Method org/wso2/carbon/ndatasource/core/DataSourceManager.getDataSourceRepository:()Lorg/wso2/carbon/ndatasource/core/DataSourceRepository;
       6: aload_1
       7: invokevirtual #20                 // Method org/wso2/carbon/ndatasource/core/DataSourceRepository.refreshUserDataSource:(Ljava/lang/String;)V
      10: return

  public void addDataSource(org.wso2.carbon.ndatasource.core.DataSourceMetaInfo) throws org.wso2.carbon.ndatasource.common.DataSourceException;
    Code:
       0: invokestatic  #3                  // Method org/wso2/carbon/ndatasource/core/DataSourceManager.getInstance:()Lorg/wso2/carbon/ndatasource/core/DataSourceManager;
       3: invokevirtual #4                  // Method org/wso2/carbon/ndatasource/core/DataSourceManager.getDataSourceRepository:()Lorg/wso2/carbon/ndatasource/core/DataSourceRepository;
       6: aload_1
       7: invokevirtual #21                 // Method org/wso2/carbon/ndatasource/core/DataSourceRepository.addDataSource:(Lorg/wso2/carbon/ndatasource/core/DataSourceMetaInfo;)V
      10: return

  public void deleteDataSource(java.lang.String) throws org.wso2.carbon.ndatasource.common.DataSourceException;
    Code:
       0: invokestatic  #3                  // Method org/wso2/carbon/ndatasource/core/DataSourceManager.getInstance:()Lorg/wso2/carbon/ndatasource/core/DataSourceManager;
       3: invokevirtual #4                  // Method org/wso2/carbon/ndatasource/core/DataSourceManager.getDataSourceRepository:()Lorg/wso2/carbon/ndatasource/core/DataSourceRepository;
       6: aload_1
       7: invokevirtual #22                 // Method org/wso2/carbon/ndatasource/core/DataSourceRepository.deleteDataSource:(Ljava/lang/String;)V
      10: return
}
