Compiled from "SourceInfo.java"
public final class io.grpc.xds.shaded.com.google.api.expr.v1alpha1.SourceInfo$Builder extends com.google.protobuf.GeneratedMessageV3$Builder<io.grpc.xds.shaded.com.google.api.expr.v1alpha1.SourceInfo$Builder> implements io.grpc.xds.shaded.com.google.api.expr.v1alpha1.SourceInfoOrBuilder {
  private int bitField0_;

  private java.lang.Object syntaxVersion_;

  private java.lang.Object location_;

  private com.google.protobuf.Internal$IntList lineOffsets_;

  private com.google.protobuf.MapField<java.lang.Long, java.lang.Integer> positions_;

  private com.google.protobuf.MapField<java.lang.Long, io.grpc.xds.shaded.com.google.api.expr.v1alpha1.Expr> macroCalls_;

  public static final com.google.protobuf.Descriptors$Descriptor getDescriptor();
    Code:
       0: getstatic     #79                 // Field io/grpc/xds/shaded/com/google/api/expr/v1alpha1/SyntaxProto.internal_static_google_api_expr_v1alpha1_SourceInfo_descriptor:Lcom/google/protobuf/Descriptors$Descriptor;
       3: areturn

  protected com.google.protobuf.MapField internalGetMapField(int);
    Code:
       0: iload_1
       1: lookupswitch  { // 2
                     4: 28
                     5: 33
               default: 38
          }
      28: aload_0
      29: invokespecial #85                 // Method internalGetPositions:()Lcom/google/protobuf/MapField;
      32: areturn
      33: aload_0
      34: invokespecial #88                 // Method internalGetMacroCalls:()Lcom/google/protobuf/MapField;
      37: areturn
      38: new           #90                 // class java/lang/RuntimeException
      41: dup
      42: new           #92                 // class java/lang/StringBuilder
      45: dup
      46: invokespecial #96                 // Method java/lang/StringBuilder."<init>":()V
      49: ldc           #98                 // String Invalid map field number:
      51: invokevirtual #102                // Method java/lang/StringBuilder.append:(Ljava/lang/String;)Ljava/lang/StringBuilder;
      54: iload_1
      55: invokevirtual #105                // Method java/lang/StringBuilder.append:(I)Ljava/lang/StringBuilder;
      58: invokevirtual #109                // Method java/lang/StringBuilder.toString:()Ljava/lang/String;
      61: invokespecial #112                // Method java/lang/RuntimeException."<init>":(Ljava/lang/String;)V
      64: athrow

  protected com.google.protobuf.MapField internalGetMutableMapField(int);
    Code:
       0: iload_1
       1: lookupswitch  { // 2
                     4: 28
                     5: 33
               default: 38
          }
      28: aload_0
      29: invokespecial #119                // Method internalGetMutablePositions:()Lcom/google/protobuf/MapField;
      32: areturn
      33: aload_0
      34: invokespecial #122                // Method internalGetMutableMacroCalls:()Lcom/google/protobuf/MapField;
      37: areturn
      38: new           #90                 // class java/lang/RuntimeException
      41: dup
      42: new           #92                 // class java/lang/StringBuilder
      45: dup
      46: invokespecial #96                 // Method java/lang/StringBuilder."<init>":()V
      49: ldc           #98                 // String Invalid map field number:
      51: invokevirtual #102                // Method java/lang/StringBuilder.append:(Ljava/lang/String;)Ljava/lang/StringBuilder;
      54: iload_1
      55: invokevirtual #105                // Method java/lang/StringBuilder.append:(I)Ljava/lang/StringBuilder;
      58: invokevirtual #109                // Method java/lang/StringBuilder.toString:()Ljava/lang/String;
      61: invokespecial #112                // Method java/lang/RuntimeException."<init>":(Ljava/lang/String;)V
      64: athrow

  protected com.google.protobuf.GeneratedMessageV3$FieldAccessorTable internalGetFieldAccessorTable();
    Code:
       0: getstatic     #128                // Field io/grpc/xds/shaded/com/google/api/expr/v1alpha1/SyntaxProto.internal_static_google_api_expr_v1alpha1_SourceInfo_fieldAccessorTable:Lcom/google/protobuf/GeneratedMessageV3$FieldAccessorTable;
       3: ldc           #20                 // class io/grpc/xds/shaded/com/google/api/expr/v1alpha1/SourceInfo
       5: ldc           #2                  // class io/grpc/xds/shaded/com/google/api/expr/v1alpha1/SourceInfo$Builder
       7: invokevirtual #132                // Method com/google/protobuf/GeneratedMessageV3$FieldAccessorTable.ensureFieldAccessorsInitialized:(Ljava/lang/Class;Ljava/lang/Class;)Lcom/google/protobuf/GeneratedMessageV3$FieldAccessorTable;
      10: areturn

  private io.grpc.xds.shaded.com.google.api.expr.v1alpha1.SourceInfo$Builder();
    Code:
       0: aload_0
       1: invokespecial #133                // Method com/google/protobuf/GeneratedMessageV3$Builder."<init>":()V
       4: aload_0
       5: ldc           #135                // String
       7: putfield      #137                // Field syntaxVersion_:Ljava/lang/Object;
      10: aload_0
      11: ldc           #135                // String
      13: putfield      #139                // Field location_:Ljava/lang/Object;
      16: aload_0
      17: invokestatic  #143                // Method io/grpc/xds/shaded/com/google/api/expr/v1alpha1/SourceInfo.access$1600:()Lcom/google/protobuf/Internal$IntList;
      20: putfield      #145                // Field lineOffsets_:Lcom/google/protobuf/Internal$IntList;
      23: aload_0
      24: invokespecial #148                // Method maybeForceBuilderInitialization:()V
      27: return

  private io.grpc.xds.shaded.com.google.api.expr.v1alpha1.SourceInfo$Builder(com.google.protobuf.GeneratedMessageV3$BuilderParent);
    Code:
       0: aload_0
       1: aload_1
       2: invokespecial #151                // Method com/google/protobuf/GeneratedMessageV3$Builder."<init>":(Lcom/google/protobuf/GeneratedMessageV3$BuilderParent;)V
       5: aload_0
       6: ldc           #135                // String
       8: putfield      #137                // Field syntaxVersion_:Ljava/lang/Object;
      11: aload_0
      12: ldc           #135                // String
      14: putfield      #139                // Field location_:Ljava/lang/Object;
      17: aload_0
      18: invokestatic  #143                // Method io/grpc/xds/shaded/com/google/api/expr/v1alpha1/SourceInfo.access$1600:()Lcom/google/protobuf/Internal$IntList;
      21: putfield      #145                // Field lineOffsets_:Lcom/google/protobuf/Internal$IntList;
      24: aload_0
      25: invokespecial #148                // Method maybeForceBuilderInitialization:()V
      28: return

  private void maybeForceBuilderInitialization();
    Code:
       0: invokestatic  #157                // Method io/grpc/xds/shaded/com/google/api/expr/v1alpha1/SourceInfo.access$200:()Z
       3: ifeq          6
       6: return

  public io.grpc.xds.shaded.com.google.api.expr.v1alpha1.SourceInfo$Builder clear();
    Code:
       0: aload_0
       1: invokespecial #162                // Method com/google/protobuf/GeneratedMessageV3$Builder.clear:()Lcom/google/protobuf/GeneratedMessageV3$Builder;
       4: pop
       5: aload_0
       6: ldc           #135                // String
       8: putfield      #137                // Field syntaxVersion_:Ljava/lang/Object;
      11: aload_0
      12: ldc           #135                // String
      14: putfield      #139                // Field location_:Ljava/lang/Object;
      17: aload_0
      18: invokestatic  #165                // Method io/grpc/xds/shaded/com/google/api/expr/v1alpha1/SourceInfo.access$300:()Lcom/google/protobuf/Internal$IntList;
      21: putfield      #145                // Field lineOffsets_:Lcom/google/protobuf/Internal$IntList;
      24: aload_0
      25: aload_0
      26: getfield      #167                // Field bitField0_:I
      29: bipush        -2
      31: iand
      32: putfield      #167                // Field bitField0_:I
      35: aload_0
      36: invokespecial #119                // Method internalGetMutablePositions:()Lcom/google/protobuf/MapField;
      39: invokevirtual #171                // Method com/google/protobuf/MapField.clear:()V
      42: aload_0
      43: invokespecial #122                // Method internalGetMutableMacroCalls:()Lcom/google/protobuf/MapField;
      46: invokevirtual #171                // Method com/google/protobuf/MapField.clear:()V
      49: aload_0
      50: areturn

  public com.google.protobuf.Descriptors$Descriptor getDescriptorForType();
    Code:
       0: getstatic     #79                 // Field io/grpc/xds/shaded/com/google/api/expr/v1alpha1/SyntaxProto.internal_static_google_api_expr_v1alpha1_SourceInfo_descriptor:Lcom/google/protobuf/Descriptors$Descriptor;
       3: areturn

  public io.grpc.xds.shaded.com.google.api.expr.v1alpha1.SourceInfo getDefaultInstanceForType();
    Code:
       0: invokestatic  #177                // Method io/grpc/xds/shaded/com/google/api/expr/v1alpha1/SourceInfo.getDefaultInstance:()Lio/grpc/xds/shaded/com/google/api/expr/v1alpha1/SourceInfo;
       3: areturn

  public io.grpc.xds.shaded.com.google.api.expr.v1alpha1.SourceInfo build();
    Code:
       0: aload_0
       1: invokevirtual #181                // Method buildPartial:()Lio/grpc/xds/shaded/com/google/api/expr/v1alpha1/SourceInfo;
       4: astore_1
       5: aload_1
       6: invokevirtual #184                // Method io/grpc/xds/shaded/com/google/api/expr/v1alpha1/SourceInfo.isInitialized:()Z
       9: ifne          17
      12: aload_1
      13: invokestatic  #188                // Method newUninitializedMessageException:(Lcom/google/protobuf/Message;)Lcom/google/protobuf/UninitializedMessageException;
      16: athrow
      17: aload_1
      18: areturn

  public io.grpc.xds.shaded.com.google.api.expr.v1alpha1.SourceInfo buildPartial();
    Code:
       0: new           #20                 // class io/grpc/xds/shaded/com/google/api/expr/v1alpha1/SourceInfo
       3: dup
       4: aload_0
       5: aconst_null
       6: invokespecial #193                // Method io/grpc/xds/shaded/com/google/api/expr/v1alpha1/SourceInfo."<init>":(Lcom/google/protobuf/GeneratedMessageV3$Builder;Lio/grpc/xds/shaded/com/google/api/expr/v1alpha1/SourceInfo$1;)V
       9: astore_1
      10: aload_0
      11: getfield      #167                // Field bitField0_:I
      14: istore_2
      15: aload_1
      16: aload_0
      17: getfield      #137                // Field syntaxVersion_:Ljava/lang/Object;
      20: invokestatic  #197                // Method io/grpc/xds/shaded/com/google/api/expr/v1alpha1/SourceInfo.access$502:(Lio/grpc/xds/shaded/com/google/api/expr/v1alpha1/SourceInfo;Ljava/lang/Object;)Ljava/lang/Object;
      23: pop
      24: aload_1
      25: aload_0
      26: getfield      #139                // Field location_:Ljava/lang/Object;
      29: invokestatic  #200                // Method io/grpc/xds/shaded/com/google/api/expr/v1alpha1/SourceInfo.access$602:(Lio/grpc/xds/shaded/com/google/api/expr/v1alpha1/SourceInfo;Ljava/lang/Object;)Ljava/lang/Object;
      32: pop
      33: aload_0
      34: getfield      #167                // Field bitField0_:I
      37: iconst_1
      38: iand
      39: ifeq          62
      42: aload_0
      43: getfield      #145                // Field lineOffsets_:Lcom/google/protobuf/Internal$IntList;
      46: invokeinterface #203,  1          // InterfaceMethod com/google/protobuf/Internal$IntList.makeImmutable:()V
      51: aload_0
      52: aload_0
      53: getfield      #167                // Field bitField0_:I
      56: bipush        -2
      58: iand
      59: putfield      #167                // Field bitField0_:I
      62: aload_1
      63: aload_0
      64: getfield      #145                // Field lineOffsets_:Lcom/google/protobuf/Internal$IntList;
      67: invokestatic  #207                // Method io/grpc/xds/shaded/com/google/api/expr/v1alpha1/SourceInfo.access$702:(Lio/grpc/xds/shaded/com/google/api/expr/v1alpha1/SourceInfo;Lcom/google/protobuf/Internal$IntList;)Lcom/google/protobuf/Internal$IntList;
      70: pop
      71: aload_1
      72: aload_0
      73: invokespecial #85                 // Method internalGetPositions:()Lcom/google/protobuf/MapField;
      76: invokestatic  #211                // Method io/grpc/xds/shaded/com/google/api/expr/v1alpha1/SourceInfo.access$802:(Lio/grpc/xds/shaded/com/google/api/expr/v1alpha1/SourceInfo;Lcom/google/protobuf/MapField;)Lcom/google/protobuf/MapField;
      79: pop
      80: aload_1
      81: invokestatic  #215                // Method io/grpc/xds/shaded/com/google/api/expr/v1alpha1/SourceInfo.access$800:(Lio/grpc/xds/shaded/com/google/api/expr/v1alpha1/SourceInfo;)Lcom/google/protobuf/MapField;
      84: invokevirtual #216                // Method com/google/protobuf/MapField.makeImmutable:()V
      87: aload_1
      88: aload_0
      89: invokespecial #88                 // Method internalGetMacroCalls:()Lcom/google/protobuf/MapField;
      92: invokestatic  #219                // Method io/grpc/xds/shaded/com/google/api/expr/v1alpha1/SourceInfo.access$902:(Lio/grpc/xds/shaded/com/google/api/expr/v1alpha1/SourceInfo;Lcom/google/protobuf/MapField;)Lcom/google/protobuf/MapField;
      95: pop
      96: aload_1
      97: invokestatic  #222                // Method io/grpc/xds/shaded/com/google/api/expr/v1alpha1/SourceInfo.access$900:(Lio/grpc/xds/shaded/com/google/api/expr/v1alpha1/SourceInfo;)Lcom/google/protobuf/MapField;
     100: invokevirtual #216                // Method com/google/protobuf/MapField.makeImmutable:()V
     103: aload_0
     104: invokevirtual #225                // Method onBuilt:()V
     107: aload_1
     108: areturn

  public io.grpc.xds.shaded.com.google.api.expr.v1alpha1.SourceInfo$Builder clone();
    Code:
       0: aload_0
       1: invokespecial #229                // Method com/google/protobuf/GeneratedMessageV3$Builder.clone:()Lcom/google/protobuf/GeneratedMessageV3$Builder;
       4: checkcast     #2                  // class io/grpc/xds/shaded/com/google/api/expr/v1alpha1/SourceInfo$Builder
       7: areturn

  public io.grpc.xds.shaded.com.google.api.expr.v1alpha1.SourceInfo$Builder setField(com.google.protobuf.Descriptors$FieldDescriptor, java.lang.Object);
    Code:
       0: aload_0
       1: aload_1
       2: aload_2
       3: invokespecial #234                // Method com/google/protobuf/GeneratedMessageV3$Builder.setField:(Lcom/google/protobuf/Descriptors$FieldDescriptor;Ljava/lang/Object;)Lcom/google/protobuf/GeneratedMessageV3$Builder;
       6: checkcast     #2                  // class io/grpc/xds/shaded/com/google/api/expr/v1alpha1/SourceInfo$Builder
       9: areturn

  public io.grpc.xds.shaded.com.google.api.expr.v1alpha1.SourceInfo$Builder clearField(com.google.protobuf.Descriptors$FieldDescriptor);
    Code:
       0: aload_0
       1: aload_1
       2: invokespecial #242                // Method com/google/protobuf/GeneratedMessageV3$Builder.clearField:(Lcom/google/protobuf/Descriptors$FieldDescriptor;)Lcom/google/protobuf/GeneratedMessageV3$Builder;
       5: checkcast     #2                  // class io/grpc/xds/shaded/com/google/api/expr/v1alpha1/SourceInfo$Builder
       8: areturn

  public io.grpc.xds.shaded.com.google.api.expr.v1alpha1.SourceInfo$Builder clearOneof(com.google.protobuf.Descriptors$OneofDescriptor);
    Code:
       0: aload_0
       1: aload_1
       2: invokespecial #247                // Method com/google/protobuf/GeneratedMessageV3$Builder.clearOneof:(Lcom/google/protobuf/Descriptors$OneofDescriptor;)Lcom/google/protobuf/GeneratedMessageV3$Builder;
       5: checkcast     #2                  // class io/grpc/xds/shaded/com/google/api/expr/v1alpha1/SourceInfo$Builder
       8: areturn

  public io.grpc.xds.shaded.com.google.api.expr.v1alpha1.SourceInfo$Builder setRepeatedField(com.google.protobuf.Descriptors$FieldDescriptor, int, java.lang.Object);
    Code:
       0: aload_0
       1: aload_1
       2: iload_2
       3: aload_3
       4: invokespecial #254                // Method com/google/protobuf/GeneratedMessageV3$Builder.setRepeatedField:(Lcom/google/protobuf/Descriptors$FieldDescriptor;ILjava/lang/Object;)Lcom/google/protobuf/GeneratedMessageV3$Builder;
       7: checkcast     #2                  // class io/grpc/xds/shaded/com/google/api/expr/v1alpha1/SourceInfo$Builder
      10: areturn

  public io.grpc.xds.shaded.com.google.api.expr.v1alpha1.SourceInfo$Builder addRepeatedField(com.google.protobuf.Descriptors$FieldDescriptor, java.lang.Object);
    Code:
       0: aload_0
       1: aload_1
       2: aload_2
       3: invokespecial #258                // Method com/google/protobuf/GeneratedMessageV3$Builder.addRepeatedField:(Lcom/google/protobuf/Descriptors$FieldDescriptor;Ljava/lang/Object;)Lcom/google/protobuf/GeneratedMessageV3$Builder;
       6: checkcast     #2                  // class io/grpc/xds/shaded/com/google/api/expr/v1alpha1/SourceInfo$Builder
       9: areturn

  public io.grpc.xds.shaded.com.google.api.expr.v1alpha1.SourceInfo$Builder mergeFrom(com.google.protobuf.Message);
    Code:
       0: aload_1
       1: instanceof    #20                 // class io/grpc/xds/shaded/com/google/api/expr/v1alpha1/SourceInfo
       4: ifeq          16
       7: aload_0
       8: aload_1
       9: checkcast     #20                 // class io/grpc/xds/shaded/com/google/api/expr/v1alpha1/SourceInfo
      12: invokevirtual #263                // Method mergeFrom:(Lio/grpc/xds/shaded/com/google/api/expr/v1alpha1/SourceInfo;)Lio/grpc/xds/shaded/com/google/api/expr/v1alpha1/SourceInfo$Builder;
      15: areturn
      16: aload_0
      17: aload_1
      18: invokespecial #266                // Method com/google/protobuf/GeneratedMessageV3$Builder.mergeFrom:(Lcom/google/protobuf/Message;)Lcom/google/protobuf/AbstractMessage$Builder;
      21: pop
      22: aload_0
      23: areturn

  public io.grpc.xds.shaded.com.google.api.expr.v1alpha1.SourceInfo$Builder mergeFrom(io.grpc.xds.shaded.com.google.api.expr.v1alpha1.SourceInfo);
    Code:
       0: aload_1
       1: invokestatic  #177                // Method io/grpc/xds/shaded/com/google/api/expr/v1alpha1/SourceInfo.getDefaultInstance:()Lio/grpc/xds/shaded/com/google/api/expr/v1alpha1/SourceInfo;
       4: if_acmpne     9
       7: aload_0
       8: areturn
       9: aload_1
      10: invokevirtual #271                // Method io/grpc/xds/shaded/com/google/api/expr/v1alpha1/SourceInfo.getSyntaxVersion:()Ljava/lang/String;
      13: invokevirtual #276                // Method java/lang/String.isEmpty:()Z
      16: ifne          31
      19: aload_0
      20: aload_1
      21: invokestatic  #280                // Method io/grpc/xds/shaded/com/google/api/expr/v1alpha1/SourceInfo.access$500:(Lio/grpc/xds/shaded/com/google/api/expr/v1alpha1/SourceInfo;)Ljava/lang/Object;
      24: putfield      #137                // Field syntaxVersion_:Ljava/lang/Object;
      27: aload_0
      28: invokevirtual #283                // Method onChanged:()V
      31: aload_1
      32: invokevirtual #286                // Method io/grpc/xds/shaded/com/google/api/expr/v1alpha1/SourceInfo.getLocation:()Ljava/lang/String;
      35: invokevirtual #276                // Method java/lang/String.isEmpty:()Z
      38: ifne          53
      41: aload_0
      42: aload_1
      43: invokestatic  #289                // Method io/grpc/xds/shaded/com/google/api/expr/v1alpha1/SourceInfo.access$600:(Lio/grpc/xds/shaded/com/google/api/expr/v1alpha1/SourceInfo;)Ljava/lang/Object;
      46: putfield      #139                // Field location_:Ljava/lang/Object;
      49: aload_0
      50: invokevirtual #283                // Method onChanged:()V
      53: aload_1
      54: invokestatic  #293                // Method io/grpc/xds/shaded/com/google/api/expr/v1alpha1/SourceInfo.access$700:(Lio/grpc/xds/shaded/com/google/api/expr/v1alpha1/SourceInfo;)Lcom/google/protobuf/Internal$IntList;
      57: invokeinterface #294,  1          // InterfaceMethod com/google/protobuf/Internal$IntList.isEmpty:()Z
      62: ifne          121
      65: aload_0
      66: getfield      #145                // Field lineOffsets_:Lcom/google/protobuf/Internal$IntList;
      69: invokeinterface #294,  1          // InterfaceMethod com/google/protobuf/Internal$IntList.isEmpty:()Z
      74: ifeq          99
      77: aload_0
      78: aload_1
      79: invokestatic  #293                // Method io/grpc/xds/shaded/com/google/api/expr/v1alpha1/SourceInfo.access$700:(Lio/grpc/xds/shaded/com/google/api/expr/v1alpha1/SourceInfo;)Lcom/google/protobuf/Internal$IntList;
      82: putfield      #145                // Field lineOffsets_:Lcom/google/protobuf/Internal$IntList;
      85: aload_0
      86: aload_0
      87: getfield      #167                // Field bitField0_:I
      90: bipush        -2
      92: iand
      93: putfield      #167                // Field bitField0_:I
      96: goto          117
      99: aload_0
     100: invokespecial #297                // Method ensureLineOffsetsIsMutable:()V
     103: aload_0
     104: getfield      #145                // Field lineOffsets_:Lcom/google/protobuf/Internal$IntList;
     107: aload_1
     108: invokestatic  #293                // Method io/grpc/xds/shaded/com/google/api/expr/v1alpha1/SourceInfo.access$700:(Lio/grpc/xds/shaded/com/google/api/expr/v1alpha1/SourceInfo;)Lcom/google/protobuf/Internal$IntList;
     111: invokeinterface #301,  2          // InterfaceMethod com/google/protobuf/Internal$IntList.addAll:(Ljava/util/Collection;)Z
     116: pop
     117: aload_0
     118: invokevirtual #283                // Method onChanged:()V
     121: aload_0
     122: invokespecial #119                // Method internalGetMutablePositions:()Lcom/google/protobuf/MapField;
     125: aload_1
     126: invokestatic  #304                // Method io/grpc/xds/shaded/com/google/api/expr/v1alpha1/SourceInfo.access$1000:(Lio/grpc/xds/shaded/com/google/api/expr/v1alpha1/SourceInfo;)Lcom/google/protobuf/MapField;
     129: invokevirtual #307                // Method com/google/protobuf/MapField.mergeFrom:(Lcom/google/protobuf/MapField;)V
     132: aload_0
     133: invokespecial #122                // Method internalGetMutableMacroCalls:()Lcom/google/protobuf/MapField;
     136: aload_1
     137: invokestatic  #310                // Method io/grpc/xds/shaded/com/google/api/expr/v1alpha1/SourceInfo.access$1100:(Lio/grpc/xds/shaded/com/google/api/expr/v1alpha1/SourceInfo;)Lcom/google/protobuf/MapField;
     140: invokevirtual #307                // Method com/google/protobuf/MapField.mergeFrom:(Lcom/google/protobuf/MapField;)V
     143: aload_0
     144: aload_1
     145: invokestatic  #314                // Method io/grpc/xds/shaded/com/google/api/expr/v1alpha1/SourceInfo.access$1200:(Lio/grpc/xds/shaded/com/google/api/expr/v1alpha1/SourceInfo;)Lcom/google/protobuf/UnknownFieldSet;
     148: invokevirtual #318                // Method mergeUnknownFields:(Lcom/google/protobuf/UnknownFieldSet;)Lio/grpc/xds/shaded/com/google/api/expr/v1alpha1/SourceInfo$Builder;
     151: pop
     152: aload_0
     153: invokevirtual #283                // Method onChanged:()V
     156: aload_0
     157: areturn

  public final boolean isInitialized();
    Code:
       0: iconst_1
       1: ireturn

  public io.grpc.xds.shaded.com.google.api.expr.v1alpha1.SourceInfo$Builder mergeFrom(com.google.protobuf.CodedInputStream, com.google.protobuf.ExtensionRegistryLite) throws java.io.IOException;
    Code:
       0: aconst_null
       1: astore_3
       2: invokestatic  #327                // Method io/grpc/xds/shaded/com/google/api/expr/v1alpha1/SourceInfo.access$1300:()Lcom/google/protobuf/Parser;
       5: aload_1
       6: aload_2
       7: invokeinterface #333,  3          // InterfaceMethod com/google/protobuf/Parser.parsePartialFrom:(Lcom/google/protobuf/CodedInputStream;Lcom/google/protobuf/ExtensionRegistryLite;)Ljava/lang/Object;
      12: checkcast     #20                 // class io/grpc/xds/shaded/com/google/api/expr/v1alpha1/SourceInfo
      15: astore_3
      16: aload_3
      17: ifnull        61
      20: aload_0
      21: aload_3
      22: invokevirtual #263                // Method mergeFrom:(Lio/grpc/xds/shaded/com/google/api/expr/v1alpha1/SourceInfo;)Lio/grpc/xds/shaded/com/google/api/expr/v1alpha1/SourceInfo$Builder;
      25: pop
      26: goto          61
      29: astore        4
      31: aload         4
      33: invokevirtual #341                // Method com/google/protobuf/InvalidProtocolBufferException.getUnfinishedMessage:()Lcom/google/protobuf/MessageLite;
      36: checkcast     #20                 // class io/grpc/xds/shaded/com/google/api/expr/v1alpha1/SourceInfo
      39: astore_3
      40: aload         4
      42: invokevirtual #345                // Method com/google/protobuf/InvalidProtocolBufferException.unwrapIOException:()Ljava/io/IOException;
      45: athrow
      46: astore        5
      48: aload_3
      49: ifnull        58
      52: aload_0
      53: aload_3
      54: invokevirtual #263                // Method mergeFrom:(Lio/grpc/xds/shaded/com/google/api/expr/v1alpha1/SourceInfo;)Lio/grpc/xds/shaded/com/google/api/expr/v1alpha1/SourceInfo$Builder;
      57: pop
      58: aload         5
      60: athrow
      61: aload_0
      62: areturn
    Exception table:
       from    to  target type
           2    16    29   Class com/google/protobuf/InvalidProtocolBufferException
           2    16    46   any
          29    48    46   any

  public java.lang.String getSyntaxVersion();
    Code:
       0: aload_0
       1: getfield      #137                // Field syntaxVersion_:Ljava/lang/Object;
       4: astore_1
       5: aload_1
       6: instanceof    #273                // class java/lang/String
       9: ifne          29
      12: aload_1
      13: checkcast     #356                // class com/google/protobuf/ByteString
      16: astore_2
      17: aload_2
      18: invokevirtual #359                // Method com/google/protobuf/ByteString.toStringUtf8:()Ljava/lang/String;
      21: astore_3
      22: aload_0
      23: aload_3
      24: putfield      #137                // Field syntaxVersion_:Ljava/lang/Object;
      27: aload_3
      28: areturn
      29: aload_1
      30: checkcast     #273                // class java/lang/String
      33: areturn

  public com.google.protobuf.ByteString getSyntaxVersionBytes();
    Code:
       0: aload_0
       1: getfield      #137                // Field syntaxVersion_:Ljava/lang/Object;
       4: astore_1
       5: aload_1
       6: instanceof    #273                // class java/lang/String
       9: ifeq          27
      12: aload_1
      13: checkcast     #273                // class java/lang/String
      16: invokestatic  #372                // Method com/google/protobuf/ByteString.copyFromUtf8:(Ljava/lang/String;)Lcom/google/protobuf/ByteString;
      19: astore_2
      20: aload_0
      21: aload_2
      22: putfield      #137                // Field syntaxVersion_:Ljava/lang/Object;
      25: aload_2
      26: areturn
      27: aload_1
      28: checkcast     #356                // class com/google/protobuf/ByteString
      31: areturn

  public io.grpc.xds.shaded.com.google.api.expr.v1alpha1.SourceInfo$Builder setSyntaxVersion(java.lang.String);
    Code:
       0: aload_1
       1: ifnonnull     12
       4: new           #377                // class java/lang/NullPointerException
       7: dup
       8: invokespecial #378                // Method java/lang/NullPointerException."<init>":()V
      11: athrow
      12: aload_0
      13: aload_1
      14: putfield      #137                // Field syntaxVersion_:Ljava/lang/Object;
      17: aload_0
      18: invokevirtual #283                // Method onChanged:()V
      21: aload_0
      22: areturn

  public io.grpc.xds.shaded.com.google.api.expr.v1alpha1.SourceInfo$Builder clearSyntaxVersion();
    Code:
       0: aload_0
       1: invokestatic  #177                // Method io/grpc/xds/shaded/com/google/api/expr/v1alpha1/SourceInfo.getDefaultInstance:()Lio/grpc/xds/shaded/com/google/api/expr/v1alpha1/SourceInfo;
       4: invokevirtual #271                // Method io/grpc/xds/shaded/com/google/api/expr/v1alpha1/SourceInfo.getSyntaxVersion:()Ljava/lang/String;
       7: putfield      #137                // Field syntaxVersion_:Ljava/lang/Object;
      10: aload_0
      11: invokevirtual #283                // Method onChanged:()V
      14: aload_0
      15: areturn

  public io.grpc.xds.shaded.com.google.api.expr.v1alpha1.SourceInfo$Builder setSyntaxVersionBytes(com.google.protobuf.ByteString);
    Code:
       0: aload_1
       1: ifnonnull     12
       4: new           #377                // class java/lang/NullPointerException
       7: dup
       8: invokespecial #378                // Method java/lang/NullPointerException."<init>":()V
      11: athrow
      12: aload_1
      13: invokestatic  #385                // Method io/grpc/xds/shaded/com/google/api/expr/v1alpha1/SourceInfo.access$1400:(Lcom/google/protobuf/ByteString;)V
      16: aload_0
      17: aload_1
      18: putfield      #137                // Field syntaxVersion_:Ljava/lang/Object;
      21: aload_0
      22: invokevirtual #283                // Method onChanged:()V
      25: aload_0
      26: areturn

  public java.lang.String getLocation();
    Code:
       0: aload_0
       1: getfield      #139                // Field location_:Ljava/lang/Object;
       4: astore_1
       5: aload_1
       6: instanceof    #273                // class java/lang/String
       9: ifne          29
      12: aload_1
      13: checkcast     #356                // class com/google/protobuf/ByteString
      16: astore_2
      17: aload_2
      18: invokevirtual #359                // Method com/google/protobuf/ByteString.toStringUtf8:()Ljava/lang/String;
      21: astore_3
      22: aload_0
      23: aload_3
      24: putfield      #139                // Field location_:Ljava/lang/Object;
      27: aload_3
      28: areturn
      29: aload_1
      30: checkcast     #273                // class java/lang/String
      33: areturn

  public com.google.protobuf.ByteString getLocationBytes();
    Code:
       0: aload_0
       1: getfield      #139                // Field location_:Ljava/lang/Object;
       4: astore_1
       5: aload_1
       6: instanceof    #273                // class java/lang/String
       9: ifeq          27
      12: aload_1
      13: checkcast     #273                // class java/lang/String
      16: invokestatic  #372                // Method com/google/protobuf/ByteString.copyFromUtf8:(Ljava/lang/String;)Lcom/google/protobuf/ByteString;
      19: astore_2
      20: aload_0
      21: aload_2
      22: putfield      #139                // Field location_:Ljava/lang/Object;
      25: aload_2
      26: areturn
      27: aload_1
      28: checkcast     #356                // class com/google/protobuf/ByteString
      31: areturn

  public io.grpc.xds.shaded.com.google.api.expr.v1alpha1.SourceInfo$Builder setLocation(java.lang.String);
    Code:
       0: aload_1
       1: ifnonnull     12
       4: new           #377                // class java/lang/NullPointerException
       7: dup
       8: invokespecial #378                // Method java/lang/NullPointerException."<init>":()V
      11: athrow
      12: aload_0
      13: aload_1
      14: putfield      #139                // Field location_:Ljava/lang/Object;
      17: aload_0
      18: invokevirtual #283                // Method onChanged:()V
      21: aload_0
      22: areturn

  public io.grpc.xds.shaded.com.google.api.expr.v1alpha1.SourceInfo$Builder clearLocation();
    Code:
       0: aload_0
       1: invokestatic  #177                // Method io/grpc/xds/shaded/com/google/api/expr/v1alpha1/SourceInfo.getDefaultInstance:()Lio/grpc/xds/shaded/com/google/api/expr/v1alpha1/SourceInfo;
       4: invokevirtual #286                // Method io/grpc/xds/shaded/com/google/api/expr/v1alpha1/SourceInfo.getLocation:()Ljava/lang/String;
       7: putfield      #139                // Field location_:Ljava/lang/Object;
      10: aload_0
      11: invokevirtual #283                // Method onChanged:()V
      14: aload_0
      15: areturn

  public io.grpc.xds.shaded.com.google.api.expr.v1alpha1.SourceInfo$Builder setLocationBytes(com.google.protobuf.ByteString);
    Code:
       0: aload_1
       1: ifnonnull     12
       4: new           #377                // class java/lang/NullPointerException
       7: dup
       8: invokespecial #378                // Method java/lang/NullPointerException."<init>":()V
      11: athrow
      12: aload_1
      13: invokestatic  #392                // Method io/grpc/xds/shaded/com/google/api/expr/v1alpha1/SourceInfo.access$1500:(Lcom/google/protobuf/ByteString;)V
      16: aload_0
      17: aload_1
      18: putfield      #139                // Field location_:Ljava/lang/Object;
      21: aload_0
      22: invokevirtual #283                // Method onChanged:()V
      25: aload_0
      26: areturn

  private void ensureLineOffsetsIsMutable();
    Code:
       0: aload_0
       1: getfield      #167                // Field bitField0_:I
       4: iconst_1
       5: iand
       6: ifne          30
       9: aload_0
      10: aload_0
      11: getfield      #145                // Field lineOffsets_:Lcom/google/protobuf/Internal$IntList;
      14: invokestatic  #396                // Method io/grpc/xds/shaded/com/google/api/expr/v1alpha1/SourceInfo.access$1700:(Lcom/google/protobuf/Internal$IntList;)Lcom/google/protobuf/Internal$IntList;
      17: putfield      #145                // Field lineOffsets_:Lcom/google/protobuf/Internal$IntList;
      20: aload_0
      21: dup
      22: getfield      #167                // Field bitField0_:I
      25: iconst_1
      26: ior
      27: putfield      #167                // Field bitField0_:I
      30: return

  public java.util.List<java.lang.Integer> getLineOffsetsList();
    Code:
       0: aload_0
       1: getfield      #167                // Field bitField0_:I
       4: iconst_1
       5: iand
       6: ifeq          19
       9: aload_0
      10: getfield      #145                // Field lineOffsets_:Lcom/google/protobuf/Internal$IntList;
      13: invokestatic  #405                // Method java/util/Collections.unmodifiableList:(Ljava/util/List;)Ljava/util/List;
      16: goto          23
      19: aload_0
      20: getfield      #145                // Field lineOffsets_:Lcom/google/protobuf/Internal$IntList;
      23: areturn

  public int getLineOffsetsCount();
    Code:
       0: aload_0
       1: getfield      #145                // Field lineOffsets_:Lcom/google/protobuf/Internal$IntList;
       4: invokeinterface #412,  1          // InterfaceMethod com/google/protobuf/Internal$IntList.size:()I
       9: ireturn

  public int getLineOffsets(int);
    Code:
       0: aload_0
       1: getfield      #145                // Field lineOffsets_:Lcom/google/protobuf/Internal$IntList;
       4: iload_1
       5: invokeinterface #417,  2          // InterfaceMethod com/google/protobuf/Internal$IntList.getInt:(I)I
      10: ireturn

  public io.grpc.xds.shaded.com.google.api.expr.v1alpha1.SourceInfo$Builder setLineOffsets(int, int);
    Code:
       0: aload_0
       1: invokespecial #297                // Method ensureLineOffsetsIsMutable:()V
       4: aload_0
       5: getfield      #145                // Field lineOffsets_:Lcom/google/protobuf/Internal$IntList;
       8: iload_1
       9: iload_2
      10: invokeinterface #423,  3          // InterfaceMethod com/google/protobuf/Internal$IntList.setInt:(II)I
      15: pop
      16: aload_0
      17: invokevirtual #283                // Method onChanged:()V
      20: aload_0
      21: areturn

  public io.grpc.xds.shaded.com.google.api.expr.v1alpha1.SourceInfo$Builder addLineOffsets(int);
    Code:
       0: aload_0
       1: invokespecial #297                // Method ensureLineOffsetsIsMutable:()V
       4: aload_0
       5: getfield      #145                // Field lineOffsets_:Lcom/google/protobuf/Internal$IntList;
       8: iload_1
       9: invokeinterface #429,  2          // InterfaceMethod com/google/protobuf/Internal$IntList.addInt:(I)V
      14: aload_0
      15: invokevirtual #283                // Method onChanged:()V
      18: aload_0
      19: areturn

  public io.grpc.xds.shaded.com.google.api.expr.v1alpha1.SourceInfo$Builder addAllLineOffsets(java.lang.Iterable<? extends java.lang.Integer>);
    Code:
       0: aload_0
       1: invokespecial #297                // Method ensureLineOffsetsIsMutable:()V
       4: aload_1
       5: aload_0
       6: getfield      #145                // Field lineOffsets_:Lcom/google/protobuf/Internal$IntList;
       9: invokestatic  #435                // Method com/google/protobuf/AbstractMessageLite$Builder.addAll:(Ljava/lang/Iterable;Ljava/util/List;)V
      12: aload_0
      13: invokevirtual #283                // Method onChanged:()V
      16: aload_0
      17: areturn

  public io.grpc.xds.shaded.com.google.api.expr.v1alpha1.SourceInfo$Builder clearLineOffsets();
    Code:
       0: aload_0
       1: invokestatic  #442                // Method io/grpc/xds/shaded/com/google/api/expr/v1alpha1/SourceInfo.access$1800:()Lcom/google/protobuf/Internal$IntList;
       4: putfield      #145                // Field lineOffsets_:Lcom/google/protobuf/Internal$IntList;
       7: aload_0
       8: aload_0
       9: getfield      #167                // Field bitField0_:I
      12: bipush        -2
      14: iand
      15: putfield      #167                // Field bitField0_:I
      18: aload_0
      19: invokevirtual #283                // Method onChanged:()V
      22: aload_0
      23: areturn

  private com.google.protobuf.MapField<java.lang.Long, java.lang.Integer> internalGetPositions();
    Code:
       0: aload_0
       1: getfield      #445                // Field positions_:Lcom/google/protobuf/MapField;
       4: ifnonnull     14
       7: getstatic     #449                // Field io/grpc/xds/shaded/com/google/api/expr/v1alpha1/SourceInfo$PositionsDefaultEntryHolder.defaultEntry:Lcom/google/protobuf/MapEntry;
      10: invokestatic  #453                // Method com/google/protobuf/MapField.emptyMapField:(Lcom/google/protobuf/MapEntry;)Lcom/google/protobuf/MapField;
      13: areturn
      14: aload_0
      15: getfield      #445                // Field positions_:Lcom/google/protobuf/MapField;
      18: areturn

  private com.google.protobuf.MapField<java.lang.Long, java.lang.Integer> internalGetMutablePositions();
    Code:
       0: aload_0
       1: invokevirtual #283                // Method onChanged:()V
       4: aload_0
       5: getfield      #445                // Field positions_:Lcom/google/protobuf/MapField;
       8: ifnonnull     21
      11: aload_0
      12: getstatic     #449                // Field io/grpc/xds/shaded/com/google/api/expr/v1alpha1/SourceInfo$PositionsDefaultEntryHolder.defaultEntry:Lcom/google/protobuf/MapEntry;
      15: invokestatic  #456                // Method com/google/protobuf/MapField.newMapField:(Lcom/google/protobuf/MapEntry;)Lcom/google/protobuf/MapField;
      18: putfield      #445                // Field positions_:Lcom/google/protobuf/MapField;
      21: aload_0
      22: getfield      #445                // Field positions_:Lcom/google/protobuf/MapField;
      25: invokevirtual #459                // Method com/google/protobuf/MapField.isMutable:()Z
      28: ifne          42
      31: aload_0
      32: aload_0
      33: getfield      #445                // Field positions_:Lcom/google/protobuf/MapField;
      36: invokevirtual #462                // Method com/google/protobuf/MapField.copy:()Lcom/google/protobuf/MapField;
      39: putfield      #445                // Field positions_:Lcom/google/protobuf/MapField;
      42: aload_0
      43: getfield      #445                // Field positions_:Lcom/google/protobuf/MapField;
      46: areturn

  public int getPositionsCount();
    Code:
       0: aload_0
       1: invokespecial #85                 // Method internalGetPositions:()Lcom/google/protobuf/MapField;
       4: invokevirtual #467                // Method com/google/protobuf/MapField.getMap:()Ljava/util/Map;
       7: invokeinterface #470,  1          // InterfaceMethod java/util/Map.size:()I
      12: ireturn

  public boolean containsPositions(long);
    Code:
       0: aload_0
       1: invokespecial #85                 // Method internalGetPositions:()Lcom/google/protobuf/MapField;
       4: invokevirtual #467                // Method com/google/protobuf/MapField.getMap:()Ljava/util/Map;
       7: lload_1
       8: invokestatic  #478                // Method java/lang/Long.valueOf:(J)Ljava/lang/Long;
      11: invokeinterface #482,  2          // InterfaceMethod java/util/Map.containsKey:(Ljava/lang/Object;)Z
      16: ireturn

  public java.util.Map<java.lang.Long, java.lang.Integer> getPositions();
    Code:
       0: aload_0
       1: invokevirtual #490                // Method getPositionsMap:()Ljava/util/Map;
       4: areturn

  public java.util.Map<java.lang.Long, java.lang.Integer> getPositionsMap();
    Code:
       0: aload_0
       1: invokespecial #85                 // Method internalGetPositions:()Lcom/google/protobuf/MapField;
       4: invokevirtual #467                // Method com/google/protobuf/MapField.getMap:()Ljava/util/Map;
       7: areturn

  public int getPositionsOrDefault(long, int);
    Code:
       0: aload_0
       1: invokespecial #85                 // Method internalGetPositions:()Lcom/google/protobuf/MapField;
       4: invokevirtual #467                // Method com/google/protobuf/MapField.getMap:()Ljava/util/Map;
       7: astore        4
       9: aload         4
      11: lload_1
      12: invokestatic  #478                // Method java/lang/Long.valueOf:(J)Ljava/lang/Long;
      15: invokeinterface #482,  2          // InterfaceMethod java/util/Map.containsKey:(Ljava/lang/Object;)Z
      20: ifeq          43
      23: aload         4
      25: lload_1
      26: invokestatic  #478                // Method java/lang/Long.valueOf:(J)Ljava/lang/Long;
      29: invokeinterface #496,  2          // InterfaceMethod java/util/Map.get:(Ljava/lang/Object;)Ljava/lang/Object;
      34: checkcast     #498                // class java/lang/Integer
      37: invokevirtual #501                // Method java/lang/Integer.intValue:()I
      40: goto          44
      43: iload_3
      44: ireturn

  public int getPositionsOrThrow(long);
    Code:
       0: aload_0
       1: invokespecial #85                 // Method internalGetPositions:()Lcom/google/protobuf/MapField;
       4: invokevirtual #467                // Method com/google/protobuf/MapField.getMap:()Ljava/util/Map;
       7: astore_3
       8: aload_3
       9: lload_1
      10: invokestatic  #478                // Method java/lang/Long.valueOf:(J)Ljava/lang/Long;
      13: invokeinterface #482,  2          // InterfaceMethod java/util/Map.containsKey:(Ljava/lang/Object;)Z
      18: ifne          29
      21: new           #509                // class java/lang/IllegalArgumentException
      24: dup
      25: invokespecial #510                // Method java/lang/IllegalArgumentException."<init>":()V
      28: athrow
      29: aload_3
      30: lload_1
      31: invokestatic  #478                // Method java/lang/Long.valueOf:(J)Ljava/lang/Long;
      34: invokeinterface #496,  2          // InterfaceMethod java/util/Map.get:(Ljava/lang/Object;)Ljava/lang/Object;
      39: checkcast     #498                // class java/lang/Integer
      42: invokevirtual #501                // Method java/lang/Integer.intValue:()I
      45: ireturn

  public io.grpc.xds.shaded.com.google.api.expr.v1alpha1.SourceInfo$Builder clearPositions();
    Code:
       0: aload_0
       1: invokespecial #119                // Method internalGetMutablePositions:()Lcom/google/protobuf/MapField;
       4: invokevirtual #514                // Method com/google/protobuf/MapField.getMutableMap:()Ljava/util/Map;
       7: invokeinterface #515,  1          // InterfaceMethod java/util/Map.clear:()V
      12: aload_0
      13: areturn

  public io.grpc.xds.shaded.com.google.api.expr.v1alpha1.SourceInfo$Builder removePositions(long);
    Code:
       0: aload_0
       1: invokespecial #119                // Method internalGetMutablePositions:()Lcom/google/protobuf/MapField;
       4: invokevirtual #514                // Method com/google/protobuf/MapField.getMutableMap:()Ljava/util/Map;
       7: lload_1
       8: invokestatic  #478                // Method java/lang/Long.valueOf:(J)Ljava/lang/Long;
      11: invokeinterface #520,  2          // InterfaceMethod java/util/Map.remove:(Ljava/lang/Object;)Ljava/lang/Object;
      16: pop
      17: aload_0
      18: areturn

  public java.util.Map<java.lang.Long, java.lang.Integer> getMutablePositions();
    Code:
       0: aload_0
       1: invokespecial #119                // Method internalGetMutablePositions:()Lcom/google/protobuf/MapField;
       4: invokevirtual #514                // Method com/google/protobuf/MapField.getMutableMap:()Ljava/util/Map;
       7: areturn

  public io.grpc.xds.shaded.com.google.api.expr.v1alpha1.SourceInfo$Builder putPositions(long, int);
    Code:
       0: aload_0
       1: invokespecial #119                // Method internalGetMutablePositions:()Lcom/google/protobuf/MapField;
       4: invokevirtual #514                // Method com/google/protobuf/MapField.getMutableMap:()Ljava/util/Map;
       7: lload_1
       8: invokestatic  #478                // Method java/lang/Long.valueOf:(J)Ljava/lang/Long;
      11: iload_3
      12: invokestatic  #526                // Method java/lang/Integer.valueOf:(I)Ljava/lang/Integer;
      15: invokeinterface #530,  3          // InterfaceMethod java/util/Map.put:(Ljava/lang/Object;Ljava/lang/Object;)Ljava/lang/Object;
      20: pop
      21: aload_0
      22: areturn

  public io.grpc.xds.shaded.com.google.api.expr.v1alpha1.SourceInfo$Builder putAllPositions(java.util.Map<java.lang.Long, java.lang.Integer>);
    Code:
       0: aload_0
       1: invokespecial #119                // Method internalGetMutablePositions:()Lcom/google/protobuf/MapField;
       4: invokevirtual #514                // Method com/google/protobuf/MapField.getMutableMap:()Ljava/util/Map;
       7: aload_1
       8: invokeinterface #537,  2          // InterfaceMethod java/util/Map.putAll:(Ljava/util/Map;)V
      13: aload_0
      14: areturn

  private com.google.protobuf.MapField<java.lang.Long, io.grpc.xds.shaded.com.google.api.expr.v1alpha1.Expr> internalGetMacroCalls();
    Code:
       0: aload_0
       1: getfield      #540                // Field macroCalls_:Lcom/google/protobuf/MapField;
       4: ifnonnull     14
       7: getstatic     #541                // Field io/grpc/xds/shaded/com/google/api/expr/v1alpha1/SourceInfo$MacroCallsDefaultEntryHolder.defaultEntry:Lcom/google/protobuf/MapEntry;
      10: invokestatic  #453                // Method com/google/protobuf/MapField.emptyMapField:(Lcom/google/protobuf/MapEntry;)Lcom/google/protobuf/MapField;
      13: areturn
      14: aload_0
      15: getfield      #540                // Field macroCalls_:Lcom/google/protobuf/MapField;
      18: areturn

  private com.google.protobuf.MapField<java.lang.Long, io.grpc.xds.shaded.com.google.api.expr.v1alpha1.Expr> internalGetMutableMacroCalls();
    Code:
       0: aload_0
       1: invokevirtual #283                // Method onChanged:()V
       4: aload_0
       5: getfield      #540                // Field macroCalls_:Lcom/google/protobuf/MapField;
       8: ifnonnull     21
      11: aload_0
      12: getstatic     #541                // Field io/grpc/xds/shaded/com/google/api/expr/v1alpha1/SourceInfo$MacroCallsDefaultEntryHolder.defaultEntry:Lcom/google/protobuf/MapEntry;
      15: invokestatic  #456                // Method com/google/protobuf/MapField.newMapField:(Lcom/google/protobuf/MapEntry;)Lcom/google/protobuf/MapField;
      18: putfield      #540                // Field macroCalls_:Lcom/google/protobuf/MapField;
      21: aload_0
      22: getfield      #540                // Field macroCalls_:Lcom/google/protobuf/MapField;
      25: invokevirtual #459                // Method com/google/protobuf/MapField.isMutable:()Z
      28: ifne          42
      31: aload_0
      32: aload_0
      33: getfield      #540                // Field macroCalls_:Lcom/google/protobuf/MapField;
      36: invokevirtual #462                // Method com/google/protobuf/MapField.copy:()Lcom/google/protobuf/MapField;
      39: putfield      #540                // Field macroCalls_:Lcom/google/protobuf/MapField;
      42: aload_0
      43: getfield      #540                // Field macroCalls_:Lcom/google/protobuf/MapField;
      46: areturn

  public int getMacroCallsCount();
    Code:
       0: aload_0
       1: invokespecial #88                 // Method internalGetMacroCalls:()Lcom/google/protobuf/MapField;
       4: invokevirtual #467                // Method com/google/protobuf/MapField.getMap:()Ljava/util/Map;
       7: invokeinterface #470,  1          // InterfaceMethod java/util/Map.size:()I
      12: ireturn

  public boolean containsMacroCalls(long);
    Code:
       0: aload_0
       1: invokespecial #88                 // Method internalGetMacroCalls:()Lcom/google/protobuf/MapField;
       4: invokevirtual #467                // Method com/google/protobuf/MapField.getMap:()Ljava/util/Map;
       7: lload_1
       8: invokestatic  #478                // Method java/lang/Long.valueOf:(J)Ljava/lang/Long;
      11: invokeinterface #482,  2          // InterfaceMethod java/util/Map.containsKey:(Ljava/lang/Object;)Z
      16: ireturn

  public java.util.Map<java.lang.Long, io.grpc.xds.shaded.com.google.api.expr.v1alpha1.Expr> getMacroCalls();
    Code:
       0: aload_0
       1: invokevirtual #548                // Method getMacroCallsMap:()Ljava/util/Map;
       4: areturn

  public java.util.Map<java.lang.Long, io.grpc.xds.shaded.com.google.api.expr.v1alpha1.Expr> getMacroCallsMap();
    Code:
       0: aload_0
       1: invokespecial #88                 // Method internalGetMacroCalls:()Lcom/google/protobuf/MapField;
       4: invokevirtual #467                // Method com/google/protobuf/MapField.getMap:()Ljava/util/Map;
       7: areturn

  public io.grpc.xds.shaded.com.google.api.expr.v1alpha1.Expr getMacroCallsOrDefault(long, io.grpc.xds.shaded.com.google.api.expr.v1alpha1.Expr);
    Code:
       0: aload_0
       1: invokespecial #88                 // Method internalGetMacroCalls:()Lcom/google/protobuf/MapField;
       4: invokevirtual #467                // Method com/google/protobuf/MapField.getMap:()Ljava/util/Map;
       7: astore        4
       9: aload         4
      11: lload_1
      12: invokestatic  #478                // Method java/lang/Long.valueOf:(J)Ljava/lang/Long;
      15: invokeinterface #482,  2          // InterfaceMethod java/util/Map.containsKey:(Ljava/lang/Object;)Z
      20: ifeq          40
      23: aload         4
      25: lload_1
      26: invokestatic  #478                // Method java/lang/Long.valueOf:(J)Ljava/lang/Long;
      29: invokeinterface #496,  2          // InterfaceMethod java/util/Map.get:(Ljava/lang/Object;)Ljava/lang/Object;
      34: checkcast     #552                // class io/grpc/xds/shaded/com/google/api/expr/v1alpha1/Expr
      37: goto          41
      40: aload_3
      41: areturn

  public io.grpc.xds.shaded.com.google.api.expr.v1alpha1.Expr getMacroCallsOrThrow(long);
    Code:
       0: aload_0
       1: invokespecial #88                 // Method internalGetMacroCalls:()Lcom/google/protobuf/MapField;
       4: invokevirtual #467                // Method com/google/protobuf/MapField.getMap:()Ljava/util/Map;
       7: astore_3
       8: aload_3
       9: lload_1
      10: invokestatic  #478                // Method java/lang/Long.valueOf:(J)Ljava/lang/Long;
      13: invokeinterface #482,  2          // InterfaceMethod java/util/Map.containsKey:(Ljava/lang/Object;)Z
      18: ifne          29
      21: new           #509                // class java/lang/IllegalArgumentException
      24: dup
      25: invokespecial #510                // Method java/lang/IllegalArgumentException."<init>":()V
      28: athrow
      29: aload_3
      30: lload_1
      31: invokestatic  #478                // Method java/lang/Long.valueOf:(J)Ljava/lang/Long;
      34: invokeinterface #496,  2          // InterfaceMethod java/util/Map.get:(Ljava/lang/Object;)Ljava/lang/Object;
      39: checkcast     #552                // class io/grpc/xds/shaded/com/google/api/expr/v1alpha1/Expr
      42: areturn

  public io.grpc.xds.shaded.com.google.api.expr.v1alpha1.SourceInfo$Builder clearMacroCalls();
    Code:
       0: aload_0
       1: invokespecial #122                // Method internalGetMutableMacroCalls:()Lcom/google/protobuf/MapField;
       4: invokevirtual #514                // Method com/google/protobuf/MapField.getMutableMap:()Ljava/util/Map;
       7: invokeinterface #515,  1          // InterfaceMethod java/util/Map.clear:()V
      12: aload_0
      13: areturn

  public io.grpc.xds.shaded.com.google.api.expr.v1alpha1.SourceInfo$Builder removeMacroCalls(long);
    Code:
       0: aload_0
       1: invokespecial #122                // Method internalGetMutableMacroCalls:()Lcom/google/protobuf/MapField;
       4: invokevirtual #514                // Method com/google/protobuf/MapField.getMutableMap:()Ljava/util/Map;
       7: lload_1
       8: invokestatic  #478                // Method java/lang/Long.valueOf:(J)Ljava/lang/Long;
      11: invokeinterface #520,  2          // InterfaceMethod java/util/Map.remove:(Ljava/lang/Object;)Ljava/lang/Object;
      16: pop
      17: aload_0
      18: areturn

  public java.util.Map<java.lang.Long, io.grpc.xds.shaded.com.google.api.expr.v1alpha1.Expr> getMutableMacroCalls();
    Code:
       0: aload_0
       1: invokespecial #122                // Method internalGetMutableMacroCalls:()Lcom/google/protobuf/MapField;
       4: invokevirtual #514                // Method com/google/protobuf/MapField.getMutableMap:()Ljava/util/Map;
       7: areturn

  public io.grpc.xds.shaded.com.google.api.expr.v1alpha1.SourceInfo$Builder putMacroCalls(long, io.grpc.xds.shaded.com.google.api.expr.v1alpha1.Expr);
    Code:
       0: aload_3
       1: ifnonnull     12
       4: new           #377                // class java/lang/NullPointerException
       7: dup
       8: invokespecial #378                // Method java/lang/NullPointerException."<init>":()V
      11: athrow
      12: aload_0
      13: invokespecial #122                // Method internalGetMutableMacroCalls:()Lcom/google/protobuf/MapField;
      16: invokevirtual #514                // Method com/google/protobuf/MapField.getMutableMap:()Ljava/util/Map;
      19: lload_1
      20: invokestatic  #478                // Method java/lang/Long.valueOf:(J)Ljava/lang/Long;
      23: aload_3
      24: invokeinterface #530,  3          // InterfaceMethod java/util/Map.put:(Ljava/lang/Object;Ljava/lang/Object;)Ljava/lang/Object;
      29: pop
      30: aload_0
      31: areturn

  public io.grpc.xds.shaded.com.google.api.expr.v1alpha1.SourceInfo$Builder putAllMacroCalls(java.util.Map<java.lang.Long, io.grpc.xds.shaded.com.google.api.expr.v1alpha1.Expr>);
    Code:
       0: aload_0
       1: invokespecial #122                // Method internalGetMutableMacroCalls:()Lcom/google/protobuf/MapField;
       4: invokevirtual #514                // Method com/google/protobuf/MapField.getMutableMap:()Ljava/util/Map;
       7: aload_1
       8: invokeinterface #537,  2          // InterfaceMethod java/util/Map.putAll:(Ljava/util/Map;)V
      13: aload_0
      14: areturn

  public final io.grpc.xds.shaded.com.google.api.expr.v1alpha1.SourceInfo$Builder setUnknownFields(com.google.protobuf.UnknownFieldSet);
    Code:
       0: aload_0
       1: aload_1
       2: invokespecial #567                // Method com/google/protobuf/GeneratedMessageV3$Builder.setUnknownFields:(Lcom/google/protobuf/UnknownFieldSet;)Lcom/google/protobuf/GeneratedMessageV3$Builder;
       5: checkcast     #2                  // class io/grpc/xds/shaded/com/google/api/expr/v1alpha1/SourceInfo$Builder
       8: areturn

  public final io.grpc.xds.shaded.com.google.api.expr.v1alpha1.SourceInfo$Builder mergeUnknownFields(com.google.protobuf.UnknownFieldSet);
    Code:
       0: aload_0
       1: aload_1
       2: invokespecial #571                // Method com/google/protobuf/GeneratedMessageV3$Builder.mergeUnknownFields:(Lcom/google/protobuf/UnknownFieldSet;)Lcom/google/protobuf/GeneratedMessageV3$Builder;
       5: checkcast     #2                  // class io/grpc/xds/shaded/com/google/api/expr/v1alpha1/SourceInfo$Builder
       8: areturn

  public com.google.protobuf.GeneratedMessageV3$Builder mergeUnknownFields(com.google.protobuf.UnknownFieldSet);
    Code:
       0: aload_0
       1: aload_1
       2: invokevirtual #318                // Method mergeUnknownFields:(Lcom/google/protobuf/UnknownFieldSet;)Lio/grpc/xds/shaded/com/google/api/expr/v1alpha1/SourceInfo$Builder;
       5: areturn

  public com.google.protobuf.GeneratedMessageV3$Builder setUnknownFields(com.google.protobuf.UnknownFieldSet);
    Code:
       0: aload_0
       1: aload_1
       2: invokevirtual #573                // Method setUnknownFields:(Lcom/google/protobuf/UnknownFieldSet;)Lio/grpc/xds/shaded/com/google/api/expr/v1alpha1/SourceInfo$Builder;
       5: areturn

  public com.google.protobuf.GeneratedMessageV3$Builder addRepeatedField(com.google.protobuf.Descriptors$FieldDescriptor, java.lang.Object);
    Code:
       0: aload_0
       1: aload_1
       2: aload_2
       3: invokevirtual #575                // Method addRepeatedField:(Lcom/google/protobuf/Descriptors$FieldDescriptor;Ljava/lang/Object;)Lio/grpc/xds/shaded/com/google/api/expr/v1alpha1/SourceInfo$Builder;
       6: areturn

  public com.google.protobuf.GeneratedMessageV3$Builder setRepeatedField(com.google.protobuf.Descriptors$FieldDescriptor, int, java.lang.Object);
    Code:
       0: aload_0
       1: aload_1
       2: iload_2
       3: aload_3
       4: invokevirtual #577                // Method setRepeatedField:(Lcom/google/protobuf/Descriptors$FieldDescriptor;ILjava/lang/Object;)Lio/grpc/xds/shaded/com/google/api/expr/v1alpha1/SourceInfo$Builder;
       7: areturn

  public com.google.protobuf.GeneratedMessageV3$Builder clearOneof(com.google.protobuf.Descriptors$OneofDescriptor);
    Code:
       0: aload_0
       1: aload_1
       2: invokevirtual #579                // Method clearOneof:(Lcom/google/protobuf/Descriptors$OneofDescriptor;)Lio/grpc/xds/shaded/com/google/api/expr/v1alpha1/SourceInfo$Builder;
       5: areturn

  public com.google.protobuf.GeneratedMessageV3$Builder clearField(com.google.protobuf.Descriptors$FieldDescriptor);
    Code:
       0: aload_0
       1: aload_1
       2: invokevirtual #581                // Method clearField:(Lcom/google/protobuf/Descriptors$FieldDescriptor;)Lio/grpc/xds/shaded/com/google/api/expr/v1alpha1/SourceInfo$Builder;
       5: areturn

  public com.google.protobuf.GeneratedMessageV3$Builder setField(com.google.protobuf.Descriptors$FieldDescriptor, java.lang.Object);
    Code:
       0: aload_0
       1: aload_1
       2: aload_2
       3: invokevirtual #583                // Method setField:(Lcom/google/protobuf/Descriptors$FieldDescriptor;Ljava/lang/Object;)Lio/grpc/xds/shaded/com/google/api/expr/v1alpha1/SourceInfo$Builder;
       6: areturn

  public com.google.protobuf.GeneratedMessageV3$Builder clear();
    Code:
       0: aload_0
       1: invokevirtual #585                // Method clear:()Lio/grpc/xds/shaded/com/google/api/expr/v1alpha1/SourceInfo$Builder;
       4: areturn

  public com.google.protobuf.GeneratedMessageV3$Builder clone();
    Code:
       0: aload_0
       1: invokevirtual #587                // Method clone:()Lio/grpc/xds/shaded/com/google/api/expr/v1alpha1/SourceInfo$Builder;
       4: areturn

  public com.google.protobuf.AbstractMessage$Builder mergeUnknownFields(com.google.protobuf.UnknownFieldSet);
    Code:
       0: aload_0
       1: aload_1
       2: invokevirtual #318                // Method mergeUnknownFields:(Lcom/google/protobuf/UnknownFieldSet;)Lio/grpc/xds/shaded/com/google/api/expr/v1alpha1/SourceInfo$Builder;
       5: areturn

  public com.google.protobuf.AbstractMessage$Builder mergeFrom(com.google.protobuf.CodedInputStream, com.google.protobuf.ExtensionRegistryLite) throws java.io.IOException;
    Code:
       0: aload_0
       1: aload_1
       2: aload_2
       3: invokevirtual #591                // Method mergeFrom:(Lcom/google/protobuf/CodedInputStream;Lcom/google/protobuf/ExtensionRegistryLite;)Lio/grpc/xds/shaded/com/google/api/expr/v1alpha1/SourceInfo$Builder;
       6: areturn

  public com.google.protobuf.AbstractMessage$Builder mergeFrom(com.google.protobuf.Message);
    Code:
       0: aload_0
       1: aload_1
       2: invokevirtual #593                // Method mergeFrom:(Lcom/google/protobuf/Message;)Lio/grpc/xds/shaded/com/google/api/expr/v1alpha1/SourceInfo$Builder;
       5: areturn

  public com.google.protobuf.AbstractMessage$Builder clear();
    Code:
       0: aload_0
       1: invokevirtual #585                // Method clear:()Lio/grpc/xds/shaded/com/google/api/expr/v1alpha1/SourceInfo$Builder;
       4: areturn

  public com.google.protobuf.AbstractMessage$Builder clearOneof(com.google.protobuf.Descriptors$OneofDescriptor);
    Code:
       0: aload_0
       1: aload_1
       2: invokevirtual #579                // Method clearOneof:(Lcom/google/protobuf/Descriptors$OneofDescriptor;)Lio/grpc/xds/shaded/com/google/api/expr/v1alpha1/SourceInfo$Builder;
       5: areturn

  public com.google.protobuf.AbstractMessage$Builder clone();
    Code:
       0: aload_0
       1: invokevirtual #587                // Method clone:()Lio/grpc/xds/shaded/com/google/api/expr/v1alpha1/SourceInfo$Builder;
       4: areturn

  public com.google.protobuf.Message$Builder mergeUnknownFields(com.google.protobuf.UnknownFieldSet);
    Code:
       0: aload_0
       1: aload_1
       2: invokevirtual #318                // Method mergeUnknownFields:(Lcom/google/protobuf/UnknownFieldSet;)Lio/grpc/xds/shaded/com/google/api/expr/v1alpha1/SourceInfo$Builder;
       5: areturn

  public com.google.protobuf.Message$Builder setUnknownFields(com.google.protobuf.UnknownFieldSet);
    Code:
       0: aload_0
       1: aload_1
       2: invokevirtual #573                // Method setUnknownFields:(Lcom/google/protobuf/UnknownFieldSet;)Lio/grpc/xds/shaded/com/google/api/expr/v1alpha1/SourceInfo$Builder;
       5: areturn

  public com.google.protobuf.Message$Builder addRepeatedField(com.google.protobuf.Descriptors$FieldDescriptor, java.lang.Object);
    Code:
       0: aload_0
       1: aload_1
       2: aload_2
       3: invokevirtual #575                // Method addRepeatedField:(Lcom/google/protobuf/Descriptors$FieldDescriptor;Ljava/lang/Object;)Lio/grpc/xds/shaded/com/google/api/expr/v1alpha1/SourceInfo$Builder;
       6: areturn

  public com.google.protobuf.Message$Builder setRepeatedField(com.google.protobuf.Descriptors$FieldDescriptor, int, java.lang.Object);
    Code:
       0: aload_0
       1: aload_1
       2: iload_2
       3: aload_3
       4: invokevirtual #577                // Method setRepeatedField:(Lcom/google/protobuf/Descriptors$FieldDescriptor;ILjava/lang/Object;)Lio/grpc/xds/shaded/com/google/api/expr/v1alpha1/SourceInfo$Builder;
       7: areturn

  public com.google.protobuf.Message$Builder clearOneof(com.google.protobuf.Descriptors$OneofDescriptor);
    Code:
       0: aload_0
       1: aload_1
       2: invokevirtual #579                // Method clearOneof:(Lcom/google/protobuf/Descriptors$OneofDescriptor;)Lio/grpc/xds/shaded/com/google/api/expr/v1alpha1/SourceInfo$Builder;
       5: areturn

  public com.google.protobuf.Message$Builder clearField(com.google.protobuf.Descriptors$FieldDescriptor);
    Code:
       0: aload_0
       1: aload_1
       2: invokevirtual #581                // Method clearField:(Lcom/google/protobuf/Descriptors$FieldDescriptor;)Lio/grpc/xds/shaded/com/google/api/expr/v1alpha1/SourceInfo$Builder;
       5: areturn

  public com.google.protobuf.Message$Builder setField(com.google.protobuf.Descriptors$FieldDescriptor, java.lang.Object);
    Code:
       0: aload_0
       1: aload_1
       2: aload_2
       3: invokevirtual #583                // Method setField:(Lcom/google/protobuf/Descriptors$FieldDescriptor;Ljava/lang/Object;)Lio/grpc/xds/shaded/com/google/api/expr/v1alpha1/SourceInfo$Builder;
       6: areturn

  public com.google.protobuf.Message$Builder mergeFrom(com.google.protobuf.CodedInputStream, com.google.protobuf.ExtensionRegistryLite) throws java.io.IOException;
    Code:
       0: aload_0
       1: aload_1
       2: aload_2
       3: invokevirtual #591                // Method mergeFrom:(Lcom/google/protobuf/CodedInputStream;Lcom/google/protobuf/ExtensionRegistryLite;)Lio/grpc/xds/shaded/com/google/api/expr/v1alpha1/SourceInfo$Builder;
       6: areturn

  public com.google.protobuf.Message$Builder clone();
    Code:
       0: aload_0
       1: invokevirtual #587                // Method clone:()Lio/grpc/xds/shaded/com/google/api/expr/v1alpha1/SourceInfo$Builder;
       4: areturn

  public com.google.protobuf.Message buildPartial();
    Code:
       0: aload_0
       1: invokevirtual #181                // Method buildPartial:()Lio/grpc/xds/shaded/com/google/api/expr/v1alpha1/SourceInfo;
       4: areturn

  public com.google.protobuf.Message build();
    Code:
       0: aload_0
       1: invokevirtual #605                // Method build:()Lio/grpc/xds/shaded/com/google/api/expr/v1alpha1/SourceInfo;
       4: areturn

  public com.google.protobuf.Message$Builder mergeFrom(com.google.protobuf.Message);
    Code:
       0: aload_0
       1: aload_1
       2: invokevirtual #593                // Method mergeFrom:(Lcom/google/protobuf/Message;)Lio/grpc/xds/shaded/com/google/api/expr/v1alpha1/SourceInfo$Builder;
       5: areturn

  public com.google.protobuf.Message$Builder clear();
    Code:
       0: aload_0
       1: invokevirtual #585                // Method clear:()Lio/grpc/xds/shaded/com/google/api/expr/v1alpha1/SourceInfo$Builder;
       4: areturn

  public com.google.protobuf.MessageLite$Builder mergeFrom(com.google.protobuf.CodedInputStream, com.google.protobuf.ExtensionRegistryLite) throws java.io.IOException;
    Code:
       0: aload_0
       1: aload_1
       2: aload_2
       3: invokevirtual #591                // Method mergeFrom:(Lcom/google/protobuf/CodedInputStream;Lcom/google/protobuf/ExtensionRegistryLite;)Lio/grpc/xds/shaded/com/google/api/expr/v1alpha1/SourceInfo$Builder;
       6: areturn

  public com.google.protobuf.MessageLite$Builder clone();
    Code:
       0: aload_0
       1: invokevirtual #587                // Method clone:()Lio/grpc/xds/shaded/com/google/api/expr/v1alpha1/SourceInfo$Builder;
       4: areturn

  public com.google.protobuf.MessageLite buildPartial();
    Code:
       0: aload_0
       1: invokevirtual #181                // Method buildPartial:()Lio/grpc/xds/shaded/com/google/api/expr/v1alpha1/SourceInfo;
       4: areturn

  public com.google.protobuf.MessageLite build();
    Code:
       0: aload_0
       1: invokevirtual #605                // Method build:()Lio/grpc/xds/shaded/com/google/api/expr/v1alpha1/SourceInfo;
       4: areturn

  public com.google.protobuf.MessageLite$Builder clear();
    Code:
       0: aload_0
       1: invokevirtual #585                // Method clear:()Lio/grpc/xds/shaded/com/google/api/expr/v1alpha1/SourceInfo$Builder;
       4: areturn

  public com.google.protobuf.MessageLite getDefaultInstanceForType();
    Code:
       0: aload_0
       1: invokevirtual #610                // Method getDefaultInstanceForType:()Lio/grpc/xds/shaded/com/google/api/expr/v1alpha1/SourceInfo;
       4: areturn

  public com.google.protobuf.Message getDefaultInstanceForType();
    Code:
       0: aload_0
       1: invokevirtual #610                // Method getDefaultInstanceForType:()Lio/grpc/xds/shaded/com/google/api/expr/v1alpha1/SourceInfo;
       4: areturn

  public com.google.protobuf.AbstractMessageLite$Builder mergeFrom(com.google.protobuf.CodedInputStream, com.google.protobuf.ExtensionRegistryLite) throws java.io.IOException;
    Code:
       0: aload_0
       1: aload_1
       2: aload_2
       3: invokevirtual #591                // Method mergeFrom:(Lcom/google/protobuf/CodedInputStream;Lcom/google/protobuf/ExtensionRegistryLite;)Lio/grpc/xds/shaded/com/google/api/expr/v1alpha1/SourceInfo$Builder;
       6: areturn

  public com.google.protobuf.AbstractMessageLite$Builder clone();
    Code:
       0: aload_0
       1: invokevirtual #587                // Method clone:()Lio/grpc/xds/shaded/com/google/api/expr/v1alpha1/SourceInfo$Builder;
       4: areturn

  public java.lang.Object clone() throws java.lang.CloneNotSupportedException;
    Code:
       0: aload_0
       1: invokevirtual #587                // Method clone:()Lio/grpc/xds/shaded/com/google/api/expr/v1alpha1/SourceInfo$Builder;
       4: areturn

  io.grpc.xds.shaded.com.google.api.expr.v1alpha1.SourceInfo$Builder(io.grpc.xds.shaded.com.google.api.expr.v1alpha1.SourceInfo$1);
    Code:
       0: aload_0
       1: invokespecial #617                // Method "<init>":()V
       4: return

  io.grpc.xds.shaded.com.google.api.expr.v1alpha1.SourceInfo$Builder(com.google.protobuf.GeneratedMessageV3$BuilderParent, io.grpc.xds.shaded.com.google.api.expr.v1alpha1.SourceInfo$1);
    Code:
       0: aload_0
       1: aload_1
       2: invokespecial #621                // Method "<init>":(Lcom/google/protobuf/GeneratedMessageV3$BuilderParent;)V
       5: return
}
