Compiled from "NewLineEvent.java"
public class groovyjarjarantlr.debug.NewLineEvent extends groovyjarjarantlr.debug.Event {
  private int line;

  public groovyjarjarantlr.debug.NewLineEvent(java.lang.Object);
    Code:
       0: aload_0
       1: aload_1
       2: invokespecial #11                 // Method groovyjarjarantlr/debug/Event."<init>":(Ljava/lang/Object;)V
       5: return

  public groovyjarjarantlr.debug.NewLineEvent(java.lang.Object, int);
    Code:
       0: aload_0
       1: aload_1
       2: invokespecial #11                 // Method groovyjarjarantlr/debug/Event."<init>":(Ljava/lang/Object;)V
       5: aload_0
       6: iload_2
       7: invokevirtual #16                 // Method setValues:(I)V
      10: return

  public int getLine();
    Code:
       0: aload_0
       1: getfield      #20                 // Field line:I
       4: ireturn

  void setLine(int);
    Code:
       0: aload_0
       1: iload_1
       2: putfield      #20                 // Field line:I
       5: return

  void setValues(int);
    Code:
       0: aload_0
       1: iload_1
       2: invokevirtual #23                 // Method setLine:(I)V
       5: return

  public java.lang.String toString();
    Code:
       0: new           #27                 // class java/lang/StringBuffer
       3: dup
       4: invokespecial #30                 // Method java/lang/StringBuffer."<init>":()V
       7: ldc           #32                 // String NewLineEvent [
       9: invokevirtual #36                 // Method java/lang/StringBuffer.append:(Ljava/lang/String;)Ljava/lang/StringBuffer;
      12: aload_0
      13: getfield      #20                 // Field line:I
      16: invokevirtual #39                 // Method java/lang/StringBuffer.append:(I)Ljava/lang/StringBuffer;
      19: ldc           #41                 // String ]
      21: invokevirtual #36                 // Method java/lang/StringBuffer.append:(Ljava/lang/String;)Ljava/lang/StringBuffer;
      24: invokevirtual #43                 // Method java/lang/StringBuffer.toString:()Ljava/lang/String;
      27: areturn
}
