Compiled from "ParserReporter.java"
public class groovyjarjarantlr.debug.ParserReporter extends groovyjarjarantlr.debug.Tracer implements groovyjarjarantlr.debug.ParserListener {
  public groovyjarjarantlr.debug.ParserReporter();
    Code:
       0: aload_0
       1: invokespecial #11                 // Method groovyjarjarantlr/debug/Tracer."<init>":()V
       4: return

  public void parserConsume(groovyjarjarantlr.debug.ParserTokenEvent);
    Code:
       0: getstatic     #19                 // Field java/lang/System.out:Ljava/io/PrintStream;
       3: new           #21                 // class java/lang/StringBuffer
       6: dup
       7: invokespecial #22                 // Method java/lang/StringBuffer."<init>":()V
      10: aload_0
      11: getfield      #26                 // Field indent:Ljava/lang/String;
      14: invokevirtual #30                 // Method java/lang/StringBuffer.append:(Ljava/lang/String;)Ljava/lang/StringBuffer;
      17: aload_1
      18: invokevirtual #33                 // Method java/lang/StringBuffer.append:(Ljava/lang/Object;)Ljava/lang/StringBuffer;
      21: invokevirtual #37                 // Method java/lang/StringBuffer.toString:()Ljava/lang/String;
      24: invokevirtual #43                 // Method java/io/PrintStream.println:(Ljava/lang/String;)V
      27: return

  public void parserLA(groovyjarjarantlr.debug.ParserTokenEvent);
    Code:
       0: getstatic     #19                 // Field java/lang/System.out:Ljava/io/PrintStream;
       3: new           #21                 // class java/lang/StringBuffer
       6: dup
       7: invokespecial #22                 // Method java/lang/StringBuffer."<init>":()V
      10: aload_0
      11: getfield      #26                 // Field indent:Ljava/lang/String;
      14: invokevirtual #30                 // Method java/lang/StringBuffer.append:(Ljava/lang/String;)Ljava/lang/StringBuffer;
      17: aload_1
      18: invokevirtual #33                 // Method java/lang/StringBuffer.append:(Ljava/lang/Object;)Ljava/lang/StringBuffer;
      21: invokevirtual #37                 // Method java/lang/StringBuffer.toString:()Ljava/lang/String;
      24: invokevirtual #43                 // Method java/io/PrintStream.println:(Ljava/lang/String;)V
      27: return

  public void parserMatch(groovyjarjarantlr.debug.ParserMatchEvent);
    Code:
       0: getstatic     #19                 // Field java/lang/System.out:Ljava/io/PrintStream;
       3: new           #21                 // class java/lang/StringBuffer
       6: dup
       7: invokespecial #22                 // Method java/lang/StringBuffer."<init>":()V
      10: aload_0
      11: getfield      #26                 // Field indent:Ljava/lang/String;
      14: invokevirtual #30                 // Method java/lang/StringBuffer.append:(Ljava/lang/String;)Ljava/lang/StringBuffer;
      17: aload_1
      18: invokevirtual #33                 // Method java/lang/StringBuffer.append:(Ljava/lang/Object;)Ljava/lang/StringBuffer;
      21: invokevirtual #37                 // Method java/lang/StringBuffer.toString:()Ljava/lang/String;
      24: invokevirtual #43                 // Method java/io/PrintStream.println:(Ljava/lang/String;)V
      27: return

  public void parserMatchNot(groovyjarjarantlr.debug.ParserMatchEvent);
    Code:
       0: getstatic     #19                 // Field java/lang/System.out:Ljava/io/PrintStream;
       3: new           #21                 // class java/lang/StringBuffer
       6: dup
       7: invokespecial #22                 // Method java/lang/StringBuffer."<init>":()V
      10: aload_0
      11: getfield      #26                 // Field indent:Ljava/lang/String;
      14: invokevirtual #30                 // Method java/lang/StringBuffer.append:(Ljava/lang/String;)Ljava/lang/StringBuffer;
      17: aload_1
      18: invokevirtual #33                 // Method java/lang/StringBuffer.append:(Ljava/lang/Object;)Ljava/lang/StringBuffer;
      21: invokevirtual #37                 // Method java/lang/StringBuffer.toString:()Ljava/lang/String;
      24: invokevirtual #43                 // Method java/io/PrintStream.println:(Ljava/lang/String;)V
      27: return

  public void parserMismatch(groovyjarjarantlr.debug.ParserMatchEvent);
    Code:
       0: getstatic     #19                 // Field java/lang/System.out:Ljava/io/PrintStream;
       3: new           #21                 // class java/lang/StringBuffer
       6: dup
       7: invokespecial #22                 // Method java/lang/StringBuffer."<init>":()V
      10: aload_0
      11: getfield      #26                 // Field indent:Ljava/lang/String;
      14: invokevirtual #30                 // Method java/lang/StringBuffer.append:(Ljava/lang/String;)Ljava/lang/StringBuffer;
      17: aload_1
      18: invokevirtual #33                 // Method java/lang/StringBuffer.append:(Ljava/lang/Object;)Ljava/lang/StringBuffer;
      21: invokevirtual #37                 // Method java/lang/StringBuffer.toString:()Ljava/lang/String;
      24: invokevirtual #43                 // Method java/io/PrintStream.println:(Ljava/lang/String;)V
      27: return

  public void parserMismatchNot(groovyjarjarantlr.debug.ParserMatchEvent);
    Code:
       0: getstatic     #19                 // Field java/lang/System.out:Ljava/io/PrintStream;
       3: new           #21                 // class java/lang/StringBuffer
       6: dup
       7: invokespecial #22                 // Method java/lang/StringBuffer."<init>":()V
      10: aload_0
      11: getfield      #26                 // Field indent:Ljava/lang/String;
      14: invokevirtual #30                 // Method java/lang/StringBuffer.append:(Ljava/lang/String;)Ljava/lang/StringBuffer;
      17: aload_1
      18: invokevirtual #33                 // Method java/lang/StringBuffer.append:(Ljava/lang/Object;)Ljava/lang/StringBuffer;
      21: invokevirtual #37                 // Method java/lang/StringBuffer.toString:()Ljava/lang/String;
      24: invokevirtual #43                 // Method java/io/PrintStream.println:(Ljava/lang/String;)V
      27: return

  public void reportError(groovyjarjarantlr.debug.MessageEvent);
    Code:
       0: getstatic     #19                 // Field java/lang/System.out:Ljava/io/PrintStream;
       3: new           #21                 // class java/lang/StringBuffer
       6: dup
       7: invokespecial #22                 // Method java/lang/StringBuffer."<init>":()V
      10: aload_0
      11: getfield      #26                 // Field indent:Ljava/lang/String;
      14: invokevirtual #30                 // Method java/lang/StringBuffer.append:(Ljava/lang/String;)Ljava/lang/StringBuffer;
      17: aload_1
      18: invokevirtual #33                 // Method java/lang/StringBuffer.append:(Ljava/lang/Object;)Ljava/lang/StringBuffer;
      21: invokevirtual #37                 // Method java/lang/StringBuffer.toString:()Ljava/lang/String;
      24: invokevirtual #43                 // Method java/io/PrintStream.println:(Ljava/lang/String;)V
      27: return

  public void reportWarning(groovyjarjarantlr.debug.MessageEvent);
    Code:
       0: getstatic     #19                 // Field java/lang/System.out:Ljava/io/PrintStream;
       3: new           #21                 // class java/lang/StringBuffer
       6: dup
       7: invokespecial #22                 // Method java/lang/StringBuffer."<init>":()V
      10: aload_0
      11: getfield      #26                 // Field indent:Ljava/lang/String;
      14: invokevirtual #30                 // Method java/lang/StringBuffer.append:(Ljava/lang/String;)Ljava/lang/StringBuffer;
      17: aload_1
      18: invokevirtual #33                 // Method java/lang/StringBuffer.append:(Ljava/lang/Object;)Ljava/lang/StringBuffer;
      21: invokevirtual #37                 // Method java/lang/StringBuffer.toString:()Ljava/lang/String;
      24: invokevirtual #43                 // Method java/io/PrintStream.println:(Ljava/lang/String;)V
      27: return

  public void semanticPredicateEvaluated(groovyjarjarantlr.debug.SemanticPredicateEvent);
    Code:
       0: getstatic     #19                 // Field java/lang/System.out:Ljava/io/PrintStream;
       3: new           #21                 // class java/lang/StringBuffer
       6: dup
       7: invokespecial #22                 // Method java/lang/StringBuffer."<init>":()V
      10: aload_0
      11: getfield      #26                 // Field indent:Ljava/lang/String;
      14: invokevirtual #30                 // Method java/lang/StringBuffer.append:(Ljava/lang/String;)Ljava/lang/StringBuffer;
      17: aload_1
      18: invokevirtual #33                 // Method java/lang/StringBuffer.append:(Ljava/lang/Object;)Ljava/lang/StringBuffer;
      21: invokevirtual #37                 // Method java/lang/StringBuffer.toString:()Ljava/lang/String;
      24: invokevirtual #43                 // Method java/io/PrintStream.println:(Ljava/lang/String;)V
      27: return

  public void syntacticPredicateFailed(groovyjarjarantlr.debug.SyntacticPredicateEvent);
    Code:
       0: getstatic     #19                 // Field java/lang/System.out:Ljava/io/PrintStream;
       3: new           #21                 // class java/lang/StringBuffer
       6: dup
       7: invokespecial #22                 // Method java/lang/StringBuffer."<init>":()V
      10: aload_0
      11: getfield      #26                 // Field indent:Ljava/lang/String;
      14: invokevirtual #30                 // Method java/lang/StringBuffer.append:(Ljava/lang/String;)Ljava/lang/StringBuffer;
      17: aload_1
      18: invokevirtual #33                 // Method java/lang/StringBuffer.append:(Ljava/lang/Object;)Ljava/lang/StringBuffer;
      21: invokevirtual #37                 // Method java/lang/StringBuffer.toString:()Ljava/lang/String;
      24: invokevirtual #43                 // Method java/io/PrintStream.println:(Ljava/lang/String;)V
      27: return

  public void syntacticPredicateStarted(groovyjarjarantlr.debug.SyntacticPredicateEvent);
    Code:
       0: getstatic     #19                 // Field java/lang/System.out:Ljava/io/PrintStream;
       3: new           #21                 // class java/lang/StringBuffer
       6: dup
       7: invokespecial #22                 // Method java/lang/StringBuffer."<init>":()V
      10: aload_0
      11: getfield      #26                 // Field indent:Ljava/lang/String;
      14: invokevirtual #30                 // Method java/lang/StringBuffer.append:(Ljava/lang/String;)Ljava/lang/StringBuffer;
      17: aload_1
      18: invokevirtual #33                 // Method java/lang/StringBuffer.append:(Ljava/lang/Object;)Ljava/lang/StringBuffer;
      21: invokevirtual #37                 // Method java/lang/StringBuffer.toString:()Ljava/lang/String;
      24: invokevirtual #43                 // Method java/io/PrintStream.println:(Ljava/lang/String;)V
      27: return

  public void syntacticPredicateSucceeded(groovyjarjarantlr.debug.SyntacticPredicateEvent);
    Code:
       0: getstatic     #19                 // Field java/lang/System.out:Ljava/io/PrintStream;
       3: new           #21                 // class java/lang/StringBuffer
       6: dup
       7: invokespecial #22                 // Method java/lang/StringBuffer."<init>":()V
      10: aload_0
      11: getfield      #26                 // Field indent:Ljava/lang/String;
      14: invokevirtual #30                 // Method java/lang/StringBuffer.append:(Ljava/lang/String;)Ljava/lang/StringBuffer;
      17: aload_1
      18: invokevirtual #33                 // Method java/lang/StringBuffer.append:(Ljava/lang/Object;)Ljava/lang/StringBuffer;
      21: invokevirtual #37                 // Method java/lang/StringBuffer.toString:()Ljava/lang/String;
      24: invokevirtual #43                 // Method java/io/PrintStream.println:(Ljava/lang/String;)V
      27: return
}
