Compiled from "HandlerTypeImpl.java"
public class org.jboss.shrinkwrap.descriptor.impl.javaeewebservicesclient14.HandlerTypeImpl<T> implements org.jboss.shrinkwrap.descriptor.api.Child<T>, org.jboss.shrinkwrap.descriptor.api.javaeewebservicesclient14.HandlerType<T> {
  private T t;

  private org.jboss.shrinkwrap.descriptor.spi.node.Node childNode;

  public org.jboss.shrinkwrap.descriptor.impl.javaeewebservicesclient14.HandlerTypeImpl(T, java.lang.String, org.jboss.shrinkwrap.descriptor.spi.node.Node);
    Code:
       0: aload_0
       1: invokespecial #1                  // Method java/lang/Object."<init>":()V
       4: aload_0
       5: aload_1
       6: putfield      #2                  // Field t:Ljava/lang/Object;
       9: aload_0
      10: aload_3
      11: aload_2
      12: invokevirtual #3                  // Method org/jboss/shrinkwrap/descriptor/spi/node/Node.createChild:(Ljava/lang/String;)Lorg/jboss/shrinkwrap/descriptor/spi/node/Node;
      15: putfield      #4                  // Field childNode:Lorg/jboss/shrinkwrap/descriptor/spi/node/Node;
      18: return

  public org.jboss.shrinkwrap.descriptor.impl.javaeewebservicesclient14.HandlerTypeImpl(T, java.lang.String, org.jboss.shrinkwrap.descriptor.spi.node.Node, org.jboss.shrinkwrap.descriptor.spi.node.Node);
    Code:
       0: aload_0
       1: invokespecial #1                  // Method java/lang/Object."<init>":()V
       4: aload_0
       5: aload_1
       6: putfield      #2                  // Field t:Ljava/lang/Object;
       9: aload_0
      10: aload         4
      12: putfield      #4                  // Field childNode:Lorg/jboss/shrinkwrap/descriptor/spi/node/Node;
      15: return

  public T up();
    Code:
       0: aload_0
       1: getfield      #2                  // Field t:Ljava/lang/Object;
       4: areturn

  public org.jboss.shrinkwrap.descriptor.api.javaeewebservicesclient14.HandlerType<T> description(java.lang.String...);
    Code:
       0: aload_1
       1: ifnull        45
       4: aload_1
       5: astore_2
       6: aload_2
       7: arraylength
       8: istore_3
       9: iconst_0
      10: istore        4
      12: iload         4
      14: iload_3
      15: if_icmpge     45
      18: aload_2
      19: iload         4
      21: aaload
      22: astore        5
      24: aload_0
      25: getfield      #4                  // Field childNode:Lorg/jboss/shrinkwrap/descriptor/spi/node/Node;
      28: ldc           #5                  // String description
      30: invokevirtual #3                  // Method org/jboss/shrinkwrap/descriptor/spi/node/Node.createChild:(Ljava/lang/String;)Lorg/jboss/shrinkwrap/descriptor/spi/node/Node;
      33: aload         5
      35: invokevirtual #6                  // Method org/jboss/shrinkwrap/descriptor/spi/node/Node.text:(Ljava/lang/String;)Lorg/jboss/shrinkwrap/descriptor/spi/node/Node;
      38: pop
      39: iinc          4, 1
      42: goto          12
      45: aload_0
      46: areturn

  public java.util.List<java.lang.String> getAllDescription();
    Code:
       0: new           #7                  // class java/util/ArrayList
       3: dup
       4: invokespecial #8                  // Method java/util/ArrayList."<init>":()V
       7: astore_1
       8: aload_0
       9: getfield      #4                  // Field childNode:Lorg/jboss/shrinkwrap/descriptor/spi/node/Node;
      12: ldc           #5                  // String description
      14: invokevirtual #9                  // Method org/jboss/shrinkwrap/descriptor/spi/node/Node.get:(Ljava/lang/String;)Ljava/util/List;
      17: astore_2
      18: aload_2
      19: invokeinterface #10,  1           // InterfaceMethod java/util/List.iterator:()Ljava/util/Iterator;
      24: astore_3
      25: aload_3
      26: invokeinterface #11,  1           // InterfaceMethod java/util/Iterator.hasNext:()Z
      31: ifeq          60
      34: aload_3
      35: invokeinterface #12,  1           // InterfaceMethod java/util/Iterator.next:()Ljava/lang/Object;
      40: checkcast     #13                 // class org/jboss/shrinkwrap/descriptor/spi/node/Node
      43: astore        4
      45: aload_1
      46: aload         4
      48: invokevirtual #14                 // Method org/jboss/shrinkwrap/descriptor/spi/node/Node.getText:()Ljava/lang/String;
      51: invokeinterface #15,  2           // InterfaceMethod java/util/List.add:(Ljava/lang/Object;)Z
      56: pop
      57: goto          25
      60: aload_1
      61: areturn

  public org.jboss.shrinkwrap.descriptor.api.javaeewebservicesclient14.HandlerType<T> removeAllDescription();
    Code:
       0: aload_0
       1: getfield      #4                  // Field childNode:Lorg/jboss/shrinkwrap/descriptor/spi/node/Node;
       4: ldc           #5                  // String description
       6: invokevirtual #16                 // Method org/jboss/shrinkwrap/descriptor/spi/node/Node.removeChildren:(Ljava/lang/String;)Ljava/util/List;
       9: pop
      10: aload_0
      11: areturn

  public org.jboss.shrinkwrap.descriptor.api.javaeewebservicesclient14.HandlerType<T> displayName(java.lang.String...);
    Code:
       0: aload_1
       1: ifnull        45
       4: aload_1
       5: astore_2
       6: aload_2
       7: arraylength
       8: istore_3
       9: iconst_0
      10: istore        4
      12: iload         4
      14: iload_3
      15: if_icmpge     45
      18: aload_2
      19: iload         4
      21: aaload
      22: astore        5
      24: aload_0
      25: getfield      #4                  // Field childNode:Lorg/jboss/shrinkwrap/descriptor/spi/node/Node;
      28: ldc           #17                 // String display-name
      30: invokevirtual #3                  // Method org/jboss/shrinkwrap/descriptor/spi/node/Node.createChild:(Ljava/lang/String;)Lorg/jboss/shrinkwrap/descriptor/spi/node/Node;
      33: aload         5
      35: invokevirtual #6                  // Method org/jboss/shrinkwrap/descriptor/spi/node/Node.text:(Ljava/lang/String;)Lorg/jboss/shrinkwrap/descriptor/spi/node/Node;
      38: pop
      39: iinc          4, 1
      42: goto          12
      45: aload_0
      46: areturn

  public java.util.List<java.lang.String> getAllDisplayName();
    Code:
       0: new           #7                  // class java/util/ArrayList
       3: dup
       4: invokespecial #8                  // Method java/util/ArrayList."<init>":()V
       7: astore_1
       8: aload_0
       9: getfield      #4                  // Field childNode:Lorg/jboss/shrinkwrap/descriptor/spi/node/Node;
      12: ldc           #17                 // String display-name
      14: invokevirtual #9                  // Method org/jboss/shrinkwrap/descriptor/spi/node/Node.get:(Ljava/lang/String;)Ljava/util/List;
      17: astore_2
      18: aload_2
      19: invokeinterface #10,  1           // InterfaceMethod java/util/List.iterator:()Ljava/util/Iterator;
      24: astore_3
      25: aload_3
      26: invokeinterface #11,  1           // InterfaceMethod java/util/Iterator.hasNext:()Z
      31: ifeq          60
      34: aload_3
      35: invokeinterface #12,  1           // InterfaceMethod java/util/Iterator.next:()Ljava/lang/Object;
      40: checkcast     #13                 // class org/jboss/shrinkwrap/descriptor/spi/node/Node
      43: astore        4
      45: aload_1
      46: aload         4
      48: invokevirtual #14                 // Method org/jboss/shrinkwrap/descriptor/spi/node/Node.getText:()Ljava/lang/String;
      51: invokeinterface #15,  2           // InterfaceMethod java/util/List.add:(Ljava/lang/Object;)Z
      56: pop
      57: goto          25
      60: aload_1
      61: areturn

  public org.jboss.shrinkwrap.descriptor.api.javaeewebservicesclient14.HandlerType<T> removeAllDisplayName();
    Code:
       0: aload_0
       1: getfield      #4                  // Field childNode:Lorg/jboss/shrinkwrap/descriptor/spi/node/Node;
       4: ldc           #17                 // String display-name
       6: invokevirtual #16                 // Method org/jboss/shrinkwrap/descriptor/spi/node/Node.removeChildren:(Ljava/lang/String;)Ljava/util/List;
       9: pop
      10: aload_0
      11: areturn

  public org.jboss.shrinkwrap.descriptor.api.javaee7.IconType<org.jboss.shrinkwrap.descriptor.api.javaeewebservicesclient14.HandlerType<T>> getOrCreateIcon();
    Code:
       0: aload_0
       1: getfield      #4                  // Field childNode:Lorg/jboss/shrinkwrap/descriptor/spi/node/Node;
       4: ldc           #18                 // String icon
       6: invokevirtual #9                  // Method org/jboss/shrinkwrap/descriptor/spi/node/Node.get:(Ljava/lang/String;)Ljava/util/List;
       9: astore_1
      10: aload_1
      11: ifnull        48
      14: aload_1
      15: invokeinterface #19,  1           // InterfaceMethod java/util/List.size:()I
      20: ifle          48
      23: new           #20                 // class org/jboss/shrinkwrap/descriptor/impl/javaee7/IconTypeImpl
      26: dup
      27: aload_0
      28: ldc           #18                 // String icon
      30: aload_0
      31: getfield      #4                  // Field childNode:Lorg/jboss/shrinkwrap/descriptor/spi/node/Node;
      34: aload_1
      35: iconst_0
      36: invokeinterface #21,  2           // InterfaceMethod java/util/List.get:(I)Ljava/lang/Object;
      41: checkcast     #13                 // class org/jboss/shrinkwrap/descriptor/spi/node/Node
      44: invokespecial #22                 // Method org/jboss/shrinkwrap/descriptor/impl/javaee7/IconTypeImpl."<init>":(Ljava/lang/Object;Ljava/lang/String;Lorg/jboss/shrinkwrap/descriptor/spi/node/Node;Lorg/jboss/shrinkwrap/descriptor/spi/node/Node;)V
      47: areturn
      48: aload_0
      49: invokevirtual #23                 // Method createIcon:()Lorg/jboss/shrinkwrap/descriptor/api/javaee7/IconType;
      52: areturn

  public org.jboss.shrinkwrap.descriptor.api.javaee7.IconType<org.jboss.shrinkwrap.descriptor.api.javaeewebservicesclient14.HandlerType<T>> createIcon();
    Code:
       0: new           #20                 // class org/jboss/shrinkwrap/descriptor/impl/javaee7/IconTypeImpl
       3: dup
       4: aload_0
       5: ldc           #18                 // String icon
       7: aload_0
       8: getfield      #4                  // Field childNode:Lorg/jboss/shrinkwrap/descriptor/spi/node/Node;
      11: invokespecial #24                 // Method org/jboss/shrinkwrap/descriptor/impl/javaee7/IconTypeImpl."<init>":(Ljava/lang/Object;Ljava/lang/String;Lorg/jboss/shrinkwrap/descriptor/spi/node/Node;)V
      14: areturn

  public java.util.List<org.jboss.shrinkwrap.descriptor.api.javaee7.IconType<org.jboss.shrinkwrap.descriptor.api.javaeewebservicesclient14.HandlerType<T>>> getAllIcon();
    Code:
       0: new           #7                  // class java/util/ArrayList
       3: dup
       4: invokespecial #8                  // Method java/util/ArrayList."<init>":()V
       7: astore_1
       8: aload_0
       9: getfield      #4                  // Field childNode:Lorg/jboss/shrinkwrap/descriptor/spi/node/Node;
      12: ldc           #18                 // String icon
      14: invokevirtual #9                  // Method org/jboss/shrinkwrap/descriptor/spi/node/Node.get:(Ljava/lang/String;)Ljava/util/List;
      17: astore_2
      18: aload_2
      19: invokeinterface #10,  1           // InterfaceMethod java/util/List.iterator:()Ljava/util/Iterator;
      24: astore_3
      25: aload_3
      26: invokeinterface #11,  1           // InterfaceMethod java/util/Iterator.hasNext:()Z
      31: ifeq          75
      34: aload_3
      35: invokeinterface #12,  1           // InterfaceMethod java/util/Iterator.next:()Ljava/lang/Object;
      40: checkcast     #13                 // class org/jboss/shrinkwrap/descriptor/spi/node/Node
      43: astore        4
      45: new           #20                 // class org/jboss/shrinkwrap/descriptor/impl/javaee7/IconTypeImpl
      48: dup
      49: aload_0
      50: ldc           #18                 // String icon
      52: aload_0
      53: getfield      #4                  // Field childNode:Lorg/jboss/shrinkwrap/descriptor/spi/node/Node;
      56: aload         4
      58: invokespecial #22                 // Method org/jboss/shrinkwrap/descriptor/impl/javaee7/IconTypeImpl."<init>":(Ljava/lang/Object;Ljava/lang/String;Lorg/jboss/shrinkwrap/descriptor/spi/node/Node;Lorg/jboss/shrinkwrap/descriptor/spi/node/Node;)V
      61: astore        5
      63: aload_1
      64: aload         5
      66: invokeinterface #15,  2           // InterfaceMethod java/util/List.add:(Ljava/lang/Object;)Z
      71: pop
      72: goto          25
      75: aload_1
      76: areturn

  public org.jboss.shrinkwrap.descriptor.api.javaeewebservicesclient14.HandlerType<T> removeAllIcon();
    Code:
       0: aload_0
       1: getfield      #4                  // Field childNode:Lorg/jboss/shrinkwrap/descriptor/spi/node/Node;
       4: ldc           #18                 // String icon
       6: invokevirtual #16                 // Method org/jboss/shrinkwrap/descriptor/spi/node/Node.removeChildren:(Ljava/lang/String;)Ljava/util/List;
       9: pop
      10: aload_0
      11: areturn

  public org.jboss.shrinkwrap.descriptor.api.javaeewebservicesclient14.HandlerType<T> handlerName(java.lang.String);
    Code:
       0: aload_0
       1: getfield      #4                  // Field childNode:Lorg/jboss/shrinkwrap/descriptor/spi/node/Node;
       4: ldc           #25                 // String handler-name
       6: invokevirtual #26                 // Method org/jboss/shrinkwrap/descriptor/spi/node/Node.getOrCreate:(Ljava/lang/String;)Lorg/jboss/shrinkwrap/descriptor/spi/node/Node;
       9: aload_1
      10: invokevirtual #6                  // Method org/jboss/shrinkwrap/descriptor/spi/node/Node.text:(Ljava/lang/String;)Lorg/jboss/shrinkwrap/descriptor/spi/node/Node;
      13: pop
      14: aload_0
      15: areturn

  public java.lang.String getHandlerName();
    Code:
       0: aload_0
       1: getfield      #4                  // Field childNode:Lorg/jboss/shrinkwrap/descriptor/spi/node/Node;
       4: ldc           #25                 // String handler-name
       6: invokevirtual #27                 // Method org/jboss/shrinkwrap/descriptor/spi/node/Node.getTextValueForPatternName:(Ljava/lang/String;)Ljava/lang/String;
       9: areturn

  public org.jboss.shrinkwrap.descriptor.api.javaeewebservicesclient14.HandlerType<T> removeHandlerName();
    Code:
       0: aload_0
       1: getfield      #4                  // Field childNode:Lorg/jboss/shrinkwrap/descriptor/spi/node/Node;
       4: ldc           #25                 // String handler-name
       6: invokevirtual #16                 // Method org/jboss/shrinkwrap/descriptor/spi/node/Node.removeChildren:(Ljava/lang/String;)Ljava/util/List;
       9: pop
      10: aload_0
      11: areturn

  public org.jboss.shrinkwrap.descriptor.api.javaeewebservicesclient14.HandlerType<T> handlerClass(java.lang.String);
    Code:
       0: aload_0
       1: getfield      #4                  // Field childNode:Lorg/jboss/shrinkwrap/descriptor/spi/node/Node;
       4: ldc           #28                 // String handler-class
       6: invokevirtual #26                 // Method org/jboss/shrinkwrap/descriptor/spi/node/Node.getOrCreate:(Ljava/lang/String;)Lorg/jboss/shrinkwrap/descriptor/spi/node/Node;
       9: aload_1
      10: invokevirtual #6                  // Method org/jboss/shrinkwrap/descriptor/spi/node/Node.text:(Ljava/lang/String;)Lorg/jboss/shrinkwrap/descriptor/spi/node/Node;
      13: pop
      14: aload_0
      15: areturn

  public java.lang.String getHandlerClass();
    Code:
       0: aload_0
       1: getfield      #4                  // Field childNode:Lorg/jboss/shrinkwrap/descriptor/spi/node/Node;
       4: ldc           #28                 // String handler-class
       6: invokevirtual #27                 // Method org/jboss/shrinkwrap/descriptor/spi/node/Node.getTextValueForPatternName:(Ljava/lang/String;)Ljava/lang/String;
       9: areturn

  public org.jboss.shrinkwrap.descriptor.api.javaeewebservicesclient14.HandlerType<T> removeHandlerClass();
    Code:
       0: aload_0
       1: getfield      #4                  // Field childNode:Lorg/jboss/shrinkwrap/descriptor/spi/node/Node;
       4: ldc           #28                 // String handler-class
       6: invokevirtual #16                 // Method org/jboss/shrinkwrap/descriptor/spi/node/Node.removeChildren:(Ljava/lang/String;)Ljava/util/List;
       9: pop
      10: aload_0
      11: areturn

  public org.jboss.shrinkwrap.descriptor.api.javaee7.ParamValueType<org.jboss.shrinkwrap.descriptor.api.javaeewebservicesclient14.HandlerType<T>> getOrCreateInitParam();
    Code:
       0: aload_0
       1: getfield      #4                  // Field childNode:Lorg/jboss/shrinkwrap/descriptor/spi/node/Node;
       4: ldc           #29                 // String init-param
       6: invokevirtual #9                  // Method org/jboss/shrinkwrap/descriptor/spi/node/Node.get:(Ljava/lang/String;)Ljava/util/List;
       9: astore_1
      10: aload_1
      11: ifnull        48
      14: aload_1
      15: invokeinterface #19,  1           // InterfaceMethod java/util/List.size:()I
      20: ifle          48
      23: new           #30                 // class org/jboss/shrinkwrap/descriptor/impl/javaee7/ParamValueTypeImpl
      26: dup
      27: aload_0
      28: ldc           #29                 // String init-param
      30: aload_0
      31: getfield      #4                  // Field childNode:Lorg/jboss/shrinkwrap/descriptor/spi/node/Node;
      34: aload_1
      35: iconst_0
      36: invokeinterface #21,  2           // InterfaceMethod java/util/List.get:(I)Ljava/lang/Object;
      41: checkcast     #13                 // class org/jboss/shrinkwrap/descriptor/spi/node/Node
      44: invokespecial #31                 // Method org/jboss/shrinkwrap/descriptor/impl/javaee7/ParamValueTypeImpl."<init>":(Ljava/lang/Object;Ljava/lang/String;Lorg/jboss/shrinkwrap/descriptor/spi/node/Node;Lorg/jboss/shrinkwrap/descriptor/spi/node/Node;)V
      47: areturn
      48: aload_0
      49: invokevirtual #32                 // Method createInitParam:()Lorg/jboss/shrinkwrap/descriptor/api/javaee7/ParamValueType;
      52: areturn

  public org.jboss.shrinkwrap.descriptor.api.javaee7.ParamValueType<org.jboss.shrinkwrap.descriptor.api.javaeewebservicesclient14.HandlerType<T>> createInitParam();
    Code:
       0: new           #30                 // class org/jboss/shrinkwrap/descriptor/impl/javaee7/ParamValueTypeImpl
       3: dup
       4: aload_0
       5: ldc           #29                 // String init-param
       7: aload_0
       8: getfield      #4                  // Field childNode:Lorg/jboss/shrinkwrap/descriptor/spi/node/Node;
      11: invokespecial #33                 // Method org/jboss/shrinkwrap/descriptor/impl/javaee7/ParamValueTypeImpl."<init>":(Ljava/lang/Object;Ljava/lang/String;Lorg/jboss/shrinkwrap/descriptor/spi/node/Node;)V
      14: areturn

  public java.util.List<org.jboss.shrinkwrap.descriptor.api.javaee7.ParamValueType<org.jboss.shrinkwrap.descriptor.api.javaeewebservicesclient14.HandlerType<T>>> getAllInitParam();
    Code:
       0: new           #7                  // class java/util/ArrayList
       3: dup
       4: invokespecial #8                  // Method java/util/ArrayList."<init>":()V
       7: astore_1
       8: aload_0
       9: getfield      #4                  // Field childNode:Lorg/jboss/shrinkwrap/descriptor/spi/node/Node;
      12: ldc           #29                 // String init-param
      14: invokevirtual #9                  // Method org/jboss/shrinkwrap/descriptor/spi/node/Node.get:(Ljava/lang/String;)Ljava/util/List;
      17: astore_2
      18: aload_2
      19: invokeinterface #10,  1           // InterfaceMethod java/util/List.iterator:()Ljava/util/Iterator;
      24: astore_3
      25: aload_3
      26: invokeinterface #11,  1           // InterfaceMethod java/util/Iterator.hasNext:()Z
      31: ifeq          75
      34: aload_3
      35: invokeinterface #12,  1           // InterfaceMethod java/util/Iterator.next:()Ljava/lang/Object;
      40: checkcast     #13                 // class org/jboss/shrinkwrap/descriptor/spi/node/Node
      43: astore        4
      45: new           #30                 // class org/jboss/shrinkwrap/descriptor/impl/javaee7/ParamValueTypeImpl
      48: dup
      49: aload_0
      50: ldc           #29                 // String init-param
      52: aload_0
      53: getfield      #4                  // Field childNode:Lorg/jboss/shrinkwrap/descriptor/spi/node/Node;
      56: aload         4
      58: invokespecial #31                 // Method org/jboss/shrinkwrap/descriptor/impl/javaee7/ParamValueTypeImpl."<init>":(Ljava/lang/Object;Ljava/lang/String;Lorg/jboss/shrinkwrap/descriptor/spi/node/Node;Lorg/jboss/shrinkwrap/descriptor/spi/node/Node;)V
      61: astore        5
      63: aload_1
      64: aload         5
      66: invokeinterface #15,  2           // InterfaceMethod java/util/List.add:(Ljava/lang/Object;)Z
      71: pop
      72: goto          25
      75: aload_1
      76: areturn

  public org.jboss.shrinkwrap.descriptor.api.javaeewebservicesclient14.HandlerType<T> removeAllInitParam();
    Code:
       0: aload_0
       1: getfield      #4                  // Field childNode:Lorg/jboss/shrinkwrap/descriptor/spi/node/Node;
       4: ldc           #29                 // String init-param
       6: invokevirtual #16                 // Method org/jboss/shrinkwrap/descriptor/spi/node/Node.removeChildren:(Ljava/lang/String;)Ljava/util/List;
       9: pop
      10: aload_0
      11: areturn

  public org.jboss.shrinkwrap.descriptor.api.javaeewebservicesclient14.HandlerType<T> soapHeader(java.lang.String...);
    Code:
       0: aload_1
       1: ifnull        45
       4: aload_1
       5: astore_2
       6: aload_2
       7: arraylength
       8: istore_3
       9: iconst_0
      10: istore        4
      12: iload         4
      14: iload_3
      15: if_icmpge     45
      18: aload_2
      19: iload         4
      21: aaload
      22: astore        5
      24: aload_0
      25: getfield      #4                  // Field childNode:Lorg/jboss/shrinkwrap/descriptor/spi/node/Node;
      28: ldc           #34                 // String soap-header
      30: invokevirtual #3                  // Method org/jboss/shrinkwrap/descriptor/spi/node/Node.createChild:(Ljava/lang/String;)Lorg/jboss/shrinkwrap/descriptor/spi/node/Node;
      33: aload         5
      35: invokevirtual #6                  // Method org/jboss/shrinkwrap/descriptor/spi/node/Node.text:(Ljava/lang/String;)Lorg/jboss/shrinkwrap/descriptor/spi/node/Node;
      38: pop
      39: iinc          4, 1
      42: goto          12
      45: aload_0
      46: areturn

  public java.util.List<java.lang.String> getAllSoapHeader();
    Code:
       0: new           #7                  // class java/util/ArrayList
       3: dup
       4: invokespecial #8                  // Method java/util/ArrayList."<init>":()V
       7: astore_1
       8: aload_0
       9: getfield      #4                  // Field childNode:Lorg/jboss/shrinkwrap/descriptor/spi/node/Node;
      12: ldc           #34                 // String soap-header
      14: invokevirtual #9                  // Method org/jboss/shrinkwrap/descriptor/spi/node/Node.get:(Ljava/lang/String;)Ljava/util/List;
      17: astore_2
      18: aload_2
      19: invokeinterface #10,  1           // InterfaceMethod java/util/List.iterator:()Ljava/util/Iterator;
      24: astore_3
      25: aload_3
      26: invokeinterface #11,  1           // InterfaceMethod java/util/Iterator.hasNext:()Z
      31: ifeq          60
      34: aload_3
      35: invokeinterface #12,  1           // InterfaceMethod java/util/Iterator.next:()Ljava/lang/Object;
      40: checkcast     #13                 // class org/jboss/shrinkwrap/descriptor/spi/node/Node
      43: astore        4
      45: aload_1
      46: aload         4
      48: invokevirtual #14                 // Method org/jboss/shrinkwrap/descriptor/spi/node/Node.getText:()Ljava/lang/String;
      51: invokeinterface #15,  2           // InterfaceMethod java/util/List.add:(Ljava/lang/Object;)Z
      56: pop
      57: goto          25
      60: aload_1
      61: areturn

  public org.jboss.shrinkwrap.descriptor.api.javaeewebservicesclient14.HandlerType<T> removeAllSoapHeader();
    Code:
       0: aload_0
       1: getfield      #4                  // Field childNode:Lorg/jboss/shrinkwrap/descriptor/spi/node/Node;
       4: ldc           #34                 // String soap-header
       6: invokevirtual #16                 // Method org/jboss/shrinkwrap/descriptor/spi/node/Node.removeChildren:(Ljava/lang/String;)Ljava/util/List;
       9: pop
      10: aload_0
      11: areturn

  public org.jboss.shrinkwrap.descriptor.api.javaeewebservicesclient14.HandlerType<T> soapRole(java.lang.String...);
    Code:
       0: aload_1
       1: ifnull        45
       4: aload_1
       5: astore_2
       6: aload_2
       7: arraylength
       8: istore_3
       9: iconst_0
      10: istore        4
      12: iload         4
      14: iload_3
      15: if_icmpge     45
      18: aload_2
      19: iload         4
      21: aaload
      22: astore        5
      24: aload_0
      25: getfield      #4                  // Field childNode:Lorg/jboss/shrinkwrap/descriptor/spi/node/Node;
      28: ldc           #35                 // String soap-role
      30: invokevirtual #3                  // Method org/jboss/shrinkwrap/descriptor/spi/node/Node.createChild:(Ljava/lang/String;)Lorg/jboss/shrinkwrap/descriptor/spi/node/Node;
      33: aload         5
      35: invokevirtual #6                  // Method org/jboss/shrinkwrap/descriptor/spi/node/Node.text:(Ljava/lang/String;)Lorg/jboss/shrinkwrap/descriptor/spi/node/Node;
      38: pop
      39: iinc          4, 1
      42: goto          12
      45: aload_0
      46: areturn

  public java.util.List<java.lang.String> getAllSoapRole();
    Code:
       0: new           #7                  // class java/util/ArrayList
       3: dup
       4: invokespecial #8                  // Method java/util/ArrayList."<init>":()V
       7: astore_1
       8: aload_0
       9: getfield      #4                  // Field childNode:Lorg/jboss/shrinkwrap/descriptor/spi/node/Node;
      12: ldc           #35                 // String soap-role
      14: invokevirtual #9                  // Method org/jboss/shrinkwrap/descriptor/spi/node/Node.get:(Ljava/lang/String;)Ljava/util/List;
      17: astore_2
      18: aload_2
      19: invokeinterface #10,  1           // InterfaceMethod java/util/List.iterator:()Ljava/util/Iterator;
      24: astore_3
      25: aload_3
      26: invokeinterface #11,  1           // InterfaceMethod java/util/Iterator.hasNext:()Z
      31: ifeq          60
      34: aload_3
      35: invokeinterface #12,  1           // InterfaceMethod java/util/Iterator.next:()Ljava/lang/Object;
      40: checkcast     #13                 // class org/jboss/shrinkwrap/descriptor/spi/node/Node
      43: astore        4
      45: aload_1
      46: aload         4
      48: invokevirtual #14                 // Method org/jboss/shrinkwrap/descriptor/spi/node/Node.getText:()Ljava/lang/String;
      51: invokeinterface #15,  2           // InterfaceMethod java/util/List.add:(Ljava/lang/Object;)Z
      56: pop
      57: goto          25
      60: aload_1
      61: areturn

  public org.jboss.shrinkwrap.descriptor.api.javaeewebservicesclient14.HandlerType<T> removeAllSoapRole();
    Code:
       0: aload_0
       1: getfield      #4                  // Field childNode:Lorg/jboss/shrinkwrap/descriptor/spi/node/Node;
       4: ldc           #35                 // String soap-role
       6: invokevirtual #16                 // Method org/jboss/shrinkwrap/descriptor/spi/node/Node.removeChildren:(Ljava/lang/String;)Ljava/util/List;
       9: pop
      10: aload_0
      11: areturn

  public org.jboss.shrinkwrap.descriptor.api.javaeewebservicesclient14.HandlerType<T> portName(java.lang.String...);
    Code:
       0: aload_1
       1: ifnull        45
       4: aload_1
       5: astore_2
       6: aload_2
       7: arraylength
       8: istore_3
       9: iconst_0
      10: istore        4
      12: iload         4
      14: iload_3
      15: if_icmpge     45
      18: aload_2
      19: iload         4
      21: aaload
      22: astore        5
      24: aload_0
      25: getfield      #4                  // Field childNode:Lorg/jboss/shrinkwrap/descriptor/spi/node/Node;
      28: ldc           #36                 // String port-name
      30: invokevirtual #3                  // Method org/jboss/shrinkwrap/descriptor/spi/node/Node.createChild:(Ljava/lang/String;)Lorg/jboss/shrinkwrap/descriptor/spi/node/Node;
      33: aload         5
      35: invokevirtual #6                  // Method org/jboss/shrinkwrap/descriptor/spi/node/Node.text:(Ljava/lang/String;)Lorg/jboss/shrinkwrap/descriptor/spi/node/Node;
      38: pop
      39: iinc          4, 1
      42: goto          12
      45: aload_0
      46: areturn

  public java.util.List<java.lang.String> getAllPortName();
    Code:
       0: new           #7                  // class java/util/ArrayList
       3: dup
       4: invokespecial #8                  // Method java/util/ArrayList."<init>":()V
       7: astore_1
       8: aload_0
       9: getfield      #4                  // Field childNode:Lorg/jboss/shrinkwrap/descriptor/spi/node/Node;
      12: ldc           #36                 // String port-name
      14: invokevirtual #9                  // Method org/jboss/shrinkwrap/descriptor/spi/node/Node.get:(Ljava/lang/String;)Ljava/util/List;
      17: astore_2
      18: aload_2
      19: invokeinterface #10,  1           // InterfaceMethod java/util/List.iterator:()Ljava/util/Iterator;
      24: astore_3
      25: aload_3
      26: invokeinterface #11,  1           // InterfaceMethod java/util/Iterator.hasNext:()Z
      31: ifeq          60
      34: aload_3
      35: invokeinterface #12,  1           // InterfaceMethod java/util/Iterator.next:()Ljava/lang/Object;
      40: checkcast     #13                 // class org/jboss/shrinkwrap/descriptor/spi/node/Node
      43: astore        4
      45: aload_1
      46: aload         4
      48: invokevirtual #14                 // Method org/jboss/shrinkwrap/descriptor/spi/node/Node.getText:()Ljava/lang/String;
      51: invokeinterface #15,  2           // InterfaceMethod java/util/List.add:(Ljava/lang/Object;)Z
      56: pop
      57: goto          25
      60: aload_1
      61: areturn

  public org.jboss.shrinkwrap.descriptor.api.javaeewebservicesclient14.HandlerType<T> removeAllPortName();
    Code:
       0: aload_0
       1: getfield      #4                  // Field childNode:Lorg/jboss/shrinkwrap/descriptor/spi/node/Node;
       4: ldc           #36                 // String port-name
       6: invokevirtual #16                 // Method org/jboss/shrinkwrap/descriptor/spi/node/Node.removeChildren:(Ljava/lang/String;)Ljava/util/List;
       9: pop
      10: aload_0
      11: areturn

  public org.jboss.shrinkwrap.descriptor.api.javaeewebservicesclient14.HandlerType<T> id(java.lang.String);
    Code:
       0: aload_0
       1: getfield      #4                  // Field childNode:Lorg/jboss/shrinkwrap/descriptor/spi/node/Node;
       4: ldc           #37                 // String id
       6: aload_1
       7: invokevirtual #38                 // Method org/jboss/shrinkwrap/descriptor/spi/node/Node.attribute:(Ljava/lang/String;Ljava/lang/String;)Lorg/jboss/shrinkwrap/descriptor/spi/node/Node;
      10: pop
      11: aload_0
      12: areturn

  public java.lang.String getId();
    Code:
       0: aload_0
       1: getfield      #4                  // Field childNode:Lorg/jboss/shrinkwrap/descriptor/spi/node/Node;
       4: ldc           #37                 // String id
       6: invokevirtual #39                 // Method org/jboss/shrinkwrap/descriptor/spi/node/Node.getAttribute:(Ljava/lang/String;)Ljava/lang/String;
       9: areturn

  public org.jboss.shrinkwrap.descriptor.api.javaeewebservicesclient14.HandlerType<T> removeId();
    Code:
       0: aload_0
       1: getfield      #4                  // Field childNode:Lorg/jboss/shrinkwrap/descriptor/spi/node/Node;
       4: ldc           #37                 // String id
       6: invokevirtual #40                 // Method org/jboss/shrinkwrap/descriptor/spi/node/Node.removeAttribute:(Ljava/lang/String;)Ljava/lang/String;
       9: pop
      10: aload_0
      11: areturn
}
