Compiled from "ProduceServiceGrpc.java"
final class io.vertx.tp.ipc.service.ProduceServiceGrpc$1 implements io.grpc.stub.StreamObserver<T> {
  private volatile boolean resolved;

  final io.vertx.core.Handler val$handler;

  io.vertx.tp.ipc.service.ProduceServiceGrpc$1(io.vertx.core.Handler);
    Code:
       0: aload_0
       1: aload_1
       2: putfield      #1                  // Field val$handler:Lio/vertx/core/Handler;
       5: aload_0
       6: invokespecial #2                  // Method java/lang/Object."<init>":()V
       9: aload_0
      10: iconst_0
      11: putfield      #3                  // Field resolved:Z
      14: return

  public void onNext(T);
    Code:
       0: aload_0
       1: getfield      #3                  // Field resolved:Z
       4: ifne          25
       7: aload_0
       8: iconst_1
       9: putfield      #3                  // Field resolved:Z
      12: aload_0
      13: getfield      #1                  // Field val$handler:Lio/vertx/core/Handler;
      16: aload_1
      17: invokestatic  #4                  // InterfaceMethod io/vertx/core/Future.succeededFuture:(Ljava/lang/Object;)Lio/vertx/core/Future;
      20: invokeinterface #5,  2            // InterfaceMethod io/vertx/core/Handler.handle:(Ljava/lang/Object;)V
      25: return

  public void onError(java.lang.Throwable);
    Code:
       0: aload_0
       1: getfield      #3                  // Field resolved:Z
       4: ifne          25
       7: aload_0
       8: iconst_1
       9: putfield      #3                  // Field resolved:Z
      12: aload_0
      13: getfield      #1                  // Field val$handler:Lio/vertx/core/Handler;
      16: aload_1
      17: invokestatic  #6                  // InterfaceMethod io/vertx/core/Future.failedFuture:(Ljava/lang/Throwable;)Lio/vertx/core/Future;
      20: invokeinterface #5,  2            // InterfaceMethod io/vertx/core/Handler.handle:(Ljava/lang/Object;)V
      25: return

  public void onCompleted();
    Code:
       0: aload_0
       1: getfield      #3                  // Field resolved:Z
       4: ifne          24
       7: aload_0
       8: iconst_1
       9: putfield      #3                  // Field resolved:Z
      12: aload_0
      13: getfield      #1                  // Field val$handler:Lio/vertx/core/Handler;
      16: invokestatic  #7                  // InterfaceMethod io/vertx/core/Future.succeededFuture:()Lio/vertx/core/Future;
      19: invokeinterface #5,  2            // InterfaceMethod io/vertx/core/Handler.handle:(Ljava/lang/Object;)V
      24: return
}
