Compiled from "BulkWriteBatch.java"
class com.mongodb.operation.BulkWriteBatch$WriteRequestEncoder implements org.bson.codecs.Encoder<com.mongodb.bulk.WriteRequest> {
  com.mongodb.operation.BulkWriteBatch$WriteRequestEncoder();
    Code:
       0: aload_0
       1: invokespecial #1                  // Method java/lang/Object."<init>":()V
       4: return

  public void encode(org.bson.BsonWriter, com.mongodb.bulk.WriteRequest, org.bson.codecs.EncoderContext);
    Code:
       0: aload_2
       1: invokevirtual #2                  // Method com/mongodb/bulk/WriteRequest.getType:()Lcom/mongodb/bulk/WriteRequest$Type;
       4: getstatic     #3                  // Field com/mongodb/bulk/WriteRequest$Type.INSERT:Lcom/mongodb/bulk/WriteRequest$Type;
       7: if_acmpne     45
      10: aload_2
      11: checkcast     #4                  // class com/mongodb/bulk/InsertRequest
      14: invokevirtual #5                  // Method com/mongodb/bulk/InsertRequest.getDocument:()Lorg/bson/BsonDocument;
      17: astore        4
      19: aload         4
      21: invokestatic  #6                  // Method com/mongodb/operation/BulkWriteBatch.access$200:(Lorg/bson/BsonDocument;)Lorg/bson/codecs/Codec;
      24: aload_1
      25: aload         4
      27: invokestatic  #7                  // Method org/bson/codecs/EncoderContext.builder:()Lorg/bson/codecs/EncoderContext$Builder;
      30: iconst_1
      31: invokevirtual #8                  // Method org/bson/codecs/EncoderContext$Builder.isEncodingCollectibleDocument:(Z)Lorg/bson/codecs/EncoderContext$Builder;
      34: invokevirtual #9                  // Method org/bson/codecs/EncoderContext$Builder.build:()Lorg/bson/codecs/EncoderContext;
      37: invokeinterface #10,  4           // InterfaceMethod org/bson/codecs/Codec.encode:(Lorg/bson/BsonWriter;Ljava/lang/Object;Lorg/bson/codecs/EncoderContext;)V
      42: goto          466
      45: aload_2
      46: invokevirtual #2                  // Method com/mongodb/bulk/WriteRequest.getType:()Lcom/mongodb/bulk/WriteRequest$Type;
      49: getstatic     #11                 // Field com/mongodb/bulk/WriteRequest$Type.UPDATE:Lcom/mongodb/bulk/WriteRequest$Type;
      52: if_acmpeq     65
      55: aload_2
      56: invokevirtual #2                  // Method com/mongodb/bulk/WriteRequest.getType:()Lcom/mongodb/bulk/WriteRequest$Type;
      59: getstatic     #12                 // Field com/mongodb/bulk/WriteRequest$Type.REPLACE:Lcom/mongodb/bulk/WriteRequest$Type;
      62: if_acmpne     349
      65: aload_2
      66: checkcast     #13                 // class com/mongodb/bulk/UpdateRequest
      69: astore        4
      71: aload_1
      72: invokeinterface #14,  1           // InterfaceMethod org/bson/BsonWriter.writeStartDocument:()V
      77: aload_1
      78: ldc           #15                 // String q
      80: invokeinterface #16,  2           // InterfaceMethod org/bson/BsonWriter.writeName:(Ljava/lang/String;)V
      85: aload         4
      87: invokevirtual #17                 // Method com/mongodb/bulk/UpdateRequest.getFilter:()Lorg/bson/BsonDocument;
      90: invokestatic  #6                  // Method com/mongodb/operation/BulkWriteBatch.access$200:(Lorg/bson/BsonDocument;)Lorg/bson/codecs/Codec;
      93: aload_1
      94: aload         4
      96: invokevirtual #17                 // Method com/mongodb/bulk/UpdateRequest.getFilter:()Lorg/bson/BsonDocument;
      99: invokestatic  #7                  // Method org/bson/codecs/EncoderContext.builder:()Lorg/bson/codecs/EncoderContext$Builder;
     102: invokevirtual #9                  // Method org/bson/codecs/EncoderContext$Builder.build:()Lorg/bson/codecs/EncoderContext;
     105: invokeinterface #10,  4           // InterfaceMethod org/bson/codecs/Codec.encode:(Lorg/bson/BsonWriter;Ljava/lang/Object;Lorg/bson/codecs/EncoderContext;)V
     110: aload_1
     111: ldc           #18                 // String u
     113: invokeinterface #16,  2           // InterfaceMethod org/bson/BsonWriter.writeName:(Ljava/lang/String;)V
     118: aload         4
     120: invokevirtual #19                 // Method com/mongodb/bulk/UpdateRequest.getType:()Lcom/mongodb/bulk/WriteRequest$Type;
     123: getstatic     #11                 // Field com/mongodb/bulk/WriteRequest$Type.UPDATE:Lcom/mongodb/bulk/WriteRequest$Type;
     126: if_acmpne     150
     129: aload         4
     131: invokevirtual #20                 // Method com/mongodb/bulk/UpdateRequest.getUpdate:()Lorg/bson/BsonDocument;
     134: invokevirtual #21                 // Method org/bson/BsonDocument.isEmpty:()Z
     137: ifeq          150
     140: new           #22                 // class java/lang/IllegalArgumentException
     143: dup
     144: ldc           #23                 // String Invalid BSON document for an update
     146: invokespecial #24                 // Method java/lang/IllegalArgumentException."<init>":(Ljava/lang/String;)V
     149: athrow
     150: aload         4
     152: invokevirtual #20                 // Method com/mongodb/bulk/UpdateRequest.getUpdate:()Lorg/bson/BsonDocument;
     155: invokestatic  #6                  // Method com/mongodb/operation/BulkWriteBatch.access$200:(Lorg/bson/BsonDocument;)Lorg/bson/codecs/Codec;
     158: aload_1
     159: aload         4
     161: invokevirtual #20                 // Method com/mongodb/bulk/UpdateRequest.getUpdate:()Lorg/bson/BsonDocument;
     164: invokestatic  #7                  // Method org/bson/codecs/EncoderContext.builder:()Lorg/bson/codecs/EncoderContext$Builder;
     167: invokevirtual #9                  // Method org/bson/codecs/EncoderContext$Builder.build:()Lorg/bson/codecs/EncoderContext;
     170: invokeinterface #10,  4           // InterfaceMethod org/bson/codecs/Codec.encode:(Lorg/bson/BsonWriter;Ljava/lang/Object;Lorg/bson/codecs/EncoderContext;)V
     175: aload         4
     177: invokevirtual #25                 // Method com/mongodb/bulk/UpdateRequest.isMulti:()Z
     180: ifeq          196
     183: aload_1
     184: ldc           #26                 // String multi
     186: aload         4
     188: invokevirtual #25                 // Method com/mongodb/bulk/UpdateRequest.isMulti:()Z
     191: invokeinterface #27,  3           // InterfaceMethod org/bson/BsonWriter.writeBoolean:(Ljava/lang/String;Z)V
     196: aload         4
     198: invokevirtual #28                 // Method com/mongodb/bulk/UpdateRequest.isUpsert:()Z
     201: ifeq          217
     204: aload_1
     205: ldc           #29                 // String upsert
     207: aload         4
     209: invokevirtual #28                 // Method com/mongodb/bulk/UpdateRequest.isUpsert:()Z
     212: invokeinterface #27,  3           // InterfaceMethod org/bson/BsonWriter.writeBoolean:(Ljava/lang/String;Z)V
     217: aload         4
     219: invokevirtual #30                 // Method com/mongodb/bulk/UpdateRequest.getCollation:()Lcom/mongodb/client/model/Collation;
     222: ifnull        262
     225: aload_1
     226: ldc           #31                 // String collation
     228: invokeinterface #16,  2           // InterfaceMethod org/bson/BsonWriter.writeName:(Ljava/lang/String;)V
     233: aload         4
     235: invokevirtual #30                 // Method com/mongodb/bulk/UpdateRequest.getCollation:()Lcom/mongodb/client/model/Collation;
     238: invokevirtual #32                 // Method com/mongodb/client/model/Collation.asDocument:()Lorg/bson/BsonDocument;
     241: astore        5
     243: aload         5
     245: invokestatic  #6                  // Method com/mongodb/operation/BulkWriteBatch.access$200:(Lorg/bson/BsonDocument;)Lorg/bson/codecs/Codec;
     248: aload_1
     249: aload         5
     251: invokestatic  #7                  // Method org/bson/codecs/EncoderContext.builder:()Lorg/bson/codecs/EncoderContext$Builder;
     254: invokevirtual #9                  // Method org/bson/codecs/EncoderContext$Builder.build:()Lorg/bson/codecs/EncoderContext;
     257: invokeinterface #10,  4           // InterfaceMethod org/bson/codecs/Codec.encode:(Lorg/bson/BsonWriter;Ljava/lang/Object;Lorg/bson/codecs/EncoderContext;)V
     262: aload         4
     264: invokevirtual #33                 // Method com/mongodb/bulk/UpdateRequest.getArrayFilters:()Ljava/util/List;
     267: ifnull        340
     270: aload_1
     271: ldc           #34                 // String arrayFilters
     273: invokeinterface #35,  2           // InterfaceMethod org/bson/BsonWriter.writeStartArray:(Ljava/lang/String;)V
     278: aload         4
     280: invokevirtual #33                 // Method com/mongodb/bulk/UpdateRequest.getArrayFilters:()Ljava/util/List;
     283: invokeinterface #36,  1           // InterfaceMethod java/util/List.iterator:()Ljava/util/Iterator;
     288: astore        5
     290: aload         5
     292: invokeinterface #37,  1           // InterfaceMethod java/util/Iterator.hasNext:()Z
     297: ifeq          334
     300: aload         5
     302: invokeinterface #38,  1           // InterfaceMethod java/util/Iterator.next:()Ljava/lang/Object;
     307: checkcast     #39                 // class org/bson/BsonDocument
     310: astore        6
     312: aload         6
     314: invokestatic  #6                  // Method com/mongodb/operation/BulkWriteBatch.access$200:(Lorg/bson/BsonDocument;)Lorg/bson/codecs/Codec;
     317: aload_1
     318: aload         6
     320: invokestatic  #7                  // Method org/bson/codecs/EncoderContext.builder:()Lorg/bson/codecs/EncoderContext$Builder;
     323: invokevirtual #9                  // Method org/bson/codecs/EncoderContext$Builder.build:()Lorg/bson/codecs/EncoderContext;
     326: invokeinterface #10,  4           // InterfaceMethod org/bson/codecs/Codec.encode:(Lorg/bson/BsonWriter;Ljava/lang/Object;Lorg/bson/codecs/EncoderContext;)V
     331: goto          290
     334: aload_1
     335: invokeinterface #40,  1           // InterfaceMethod org/bson/BsonWriter.writeEndArray:()V
     340: aload_1
     341: invokeinterface #41,  1           // InterfaceMethod org/bson/BsonWriter.writeEndDocument:()V
     346: goto          466
     349: aload_2
     350: checkcast     #42                 // class com/mongodb/bulk/DeleteRequest
     353: astore        4
     355: aload_1
     356: invokeinterface #14,  1           // InterfaceMethod org/bson/BsonWriter.writeStartDocument:()V
     361: aload_1
     362: ldc           #15                 // String q
     364: invokeinterface #16,  2           // InterfaceMethod org/bson/BsonWriter.writeName:(Ljava/lang/String;)V
     369: aload         4
     371: invokevirtual #43                 // Method com/mongodb/bulk/DeleteRequest.getFilter:()Lorg/bson/BsonDocument;
     374: invokestatic  #6                  // Method com/mongodb/operation/BulkWriteBatch.access$200:(Lorg/bson/BsonDocument;)Lorg/bson/codecs/Codec;
     377: aload_1
     378: aload         4
     380: invokevirtual #43                 // Method com/mongodb/bulk/DeleteRequest.getFilter:()Lorg/bson/BsonDocument;
     383: invokestatic  #7                  // Method org/bson/codecs/EncoderContext.builder:()Lorg/bson/codecs/EncoderContext$Builder;
     386: invokevirtual #9                  // Method org/bson/codecs/EncoderContext$Builder.build:()Lorg/bson/codecs/EncoderContext;
     389: invokeinterface #10,  4           // InterfaceMethod org/bson/codecs/Codec.encode:(Lorg/bson/BsonWriter;Ljava/lang/Object;Lorg/bson/codecs/EncoderContext;)V
     394: aload_1
     395: ldc           #44                 // String limit
     397: aload         4
     399: invokevirtual #45                 // Method com/mongodb/bulk/DeleteRequest.isMulti:()Z
     402: ifeq          409
     405: iconst_0
     406: goto          410
     409: iconst_1
     410: invokeinterface #46,  3           // InterfaceMethod org/bson/BsonWriter.writeInt32:(Ljava/lang/String;I)V
     415: aload         4
     417: invokevirtual #47                 // Method com/mongodb/bulk/DeleteRequest.getCollation:()Lcom/mongodb/client/model/Collation;
     420: ifnull        460
     423: aload_1
     424: ldc           #31                 // String collation
     426: invokeinterface #16,  2           // InterfaceMethod org/bson/BsonWriter.writeName:(Ljava/lang/String;)V
     431: aload         4
     433: invokevirtual #47                 // Method com/mongodb/bulk/DeleteRequest.getCollation:()Lcom/mongodb/client/model/Collation;
     436: invokevirtual #32                 // Method com/mongodb/client/model/Collation.asDocument:()Lorg/bson/BsonDocument;
     439: astore        5
     441: aload         5
     443: invokestatic  #6                  // Method com/mongodb/operation/BulkWriteBatch.access$200:(Lorg/bson/BsonDocument;)Lorg/bson/codecs/Codec;
     446: aload_1
     447: aload         5
     449: invokestatic  #7                  // Method org/bson/codecs/EncoderContext.builder:()Lorg/bson/codecs/EncoderContext$Builder;
     452: invokevirtual #9                  // Method org/bson/codecs/EncoderContext$Builder.build:()Lorg/bson/codecs/EncoderContext;
     455: invokeinterface #10,  4           // InterfaceMethod org/bson/codecs/Codec.encode:(Lorg/bson/BsonWriter;Ljava/lang/Object;Lorg/bson/codecs/EncoderContext;)V
     460: aload_1
     461: invokeinterface #41,  1           // InterfaceMethod org/bson/BsonWriter.writeEndDocument:()V
     466: return

  public java.lang.Class<com.mongodb.bulk.WriteRequest> getEncoderClass();
    Code:
       0: ldc           #48                 // class com/mongodb/bulk/WriteRequest
       2: areturn

  public void encode(org.bson.BsonWriter, java.lang.Object, org.bson.codecs.EncoderContext);
    Code:
       0: aload_0
       1: aload_1
       2: aload_2
       3: checkcast     #48                 // class com/mongodb/bulk/WriteRequest
       6: aload_3
       7: invokevirtual #49                 // Method encode:(Lorg/bson/BsonWriter;Lcom/mongodb/bulk/WriteRequest;Lorg/bson/codecs/EncoderContext;)V
      10: return
}
