Compiled from "CountOperation.java"
class com.mongodb.operation.CountOperation$3 implements com.mongodb.operation.CommandOperationHelper$CommandTransformer<org.bson.BsonDocument, java.lang.Long> {
  final com.mongodb.operation.CountOperation this$0;

  com.mongodb.operation.CountOperation$3(com.mongodb.operation.CountOperation);
    Code:
       0: aload_0
       1: aload_1
       2: putfield      #1                  // Field this$0:Lcom/mongodb/operation/CountOperation;
       5: aload_0
       6: invokespecial #2                  // Method java/lang/Object."<init>":()V
       9: return

  public java.lang.Long apply(org.bson.BsonDocument, com.mongodb.ServerAddress);
    Code:
       0: aload_1
       1: ldc           #3                  // String n
       3: invokevirtual #4                  // Method org/bson/BsonDocument.getNumber:(Ljava/lang/Object;)Lorg/bson/BsonNumber;
       6: invokevirtual #5                  // Method org/bson/BsonNumber.longValue:()J
       9: invokestatic  #6                  // Method java/lang/Long.valueOf:(J)Ljava/lang/Long;
      12: areturn

  public java.lang.Object apply(java.lang.Object, com.mongodb.ServerAddress);
    Code:
       0: aload_0
       1: aload_1
       2: checkcast     #7                  // class org/bson/BsonDocument
       5: aload_2
       6: invokevirtual #8                  // Method apply:(Lorg/bson/BsonDocument;Lcom/mongodb/ServerAddress;)Ljava/lang/Long;
       9: areturn
}
