Compiled from "FindAndModifyHelper.java"
final class com.mongodb.operation.FindAndModifyHelper {
  static <T> com.mongodb.operation.CommandOperationHelper$CommandTransformer<org.bson.BsonDocument, T> transformer();
    Code:
       0: new           #3                  // class com/mongodb/operation/FindAndModifyHelper$1
       3: dup
       4: invokespecial #4                  // Method com/mongodb/operation/FindAndModifyHelper$1."<init>":()V
       7: areturn

  private static com.mongodb.bulk.WriteConcernError createWriteConcernError(org.bson.BsonDocument);
    Code:
       0: new           #5                  // class com/mongodb/bulk/WriteConcernError
       3: dup
       4: aload_0
       5: ldc           #6                  // String code
       7: invokevirtual #7                  // Method org/bson/BsonDocument.getNumber:(Ljava/lang/Object;)Lorg/bson/BsonNumber;
      10: invokevirtual #8                  // Method org/bson/BsonNumber.intValue:()I
      13: aload_0
      14: ldc           #9                  // String errmsg
      16: invokevirtual #10                 // Method org/bson/BsonDocument.getString:(Ljava/lang/Object;)Lorg/bson/BsonString;
      19: invokevirtual #11                 // Method org/bson/BsonString.getValue:()Ljava/lang/String;
      22: aload_0
      23: ldc           #12                 // String errInfo
      25: new           #13                 // class org/bson/BsonDocument
      28: dup
      29: invokespecial #14                 // Method org/bson/BsonDocument."<init>":()V
      32: invokevirtual #15                 // Method org/bson/BsonDocument.getDocument:(Ljava/lang/Object;Lorg/bson/BsonDocument;)Lorg/bson/BsonDocument;
      35: invokespecial #16                 // Method com/mongodb/bulk/WriteConcernError."<init>":(ILjava/lang/String;Lorg/bson/BsonDocument;)V
      38: areturn

  private static com.mongodb.WriteConcernResult createWriteConcernResult(org.bson.BsonDocument);
    Code:
       0: aload_0
       1: ldc           #17                 // String updatedExisting
       3: getstatic     #18                 // Field org/bson/BsonBoolean.FALSE:Lorg/bson/BsonBoolean;
       6: invokevirtual #19                 // Method org/bson/BsonDocument.getBoolean:(Ljava/lang/Object;Lorg/bson/BsonBoolean;)Lorg/bson/BsonBoolean;
       9: astore_1
      10: aload_0
      11: ldc           #20                 // String n
      13: new           #21                 // class org/bson/BsonInt32
      16: dup
      17: iconst_0
      18: invokespecial #22                 // Method org/bson/BsonInt32."<init>":(I)V
      21: invokevirtual #23                 // Method org/bson/BsonDocument.getNumber:(Ljava/lang/Object;Lorg/bson/BsonNumber;)Lorg/bson/BsonNumber;
      24: invokevirtual #8                  // Method org/bson/BsonNumber.intValue:()I
      27: aload_1
      28: invokevirtual #24                 // Method org/bson/BsonBoolean.getValue:()Z
      31: aload_0
      32: ldc           #25                 // String upserted
      34: invokevirtual #26                 // Method org/bson/BsonDocument.get:(Ljava/lang/Object;)Lorg/bson/BsonValue;
      37: invokestatic  #27                 // Method com/mongodb/WriteConcernResult.acknowledged:(IZLorg/bson/BsonValue;)Lcom/mongodb/WriteConcernResult;
      40: areturn

  private com.mongodb.operation.FindAndModifyHelper();
    Code:
       0: aload_0
       1: invokespecial #28                 // Method java/lang/Object."<init>":()V
       4: return

  static com.mongodb.bulk.WriteConcernError access$000(org.bson.BsonDocument);
    Code:
       0: aload_0
       1: invokestatic  #2                  // Method createWriteConcernError:(Lorg/bson/BsonDocument;)Lcom/mongodb/bulk/WriteConcernError;
       4: areturn

  static com.mongodb.WriteConcernResult access$100(org.bson.BsonDocument);
    Code:
       0: aload_0
       1: invokestatic  #1                  // Method createWriteConcernResult:(Lorg/bson/BsonDocument;)Lcom/mongodb/WriteConcernResult;
       4: areturn
}
