Compiled from "UserExistsOperation.java"
class com.mongodb.operation.UserExistsOperation$3 implements com.mongodb.operation.CommandOperationHelper$CommandTransformer<org.bson.BsonDocument, java.lang.Boolean> {
  final com.mongodb.operation.UserExistsOperation this$0;

  com.mongodb.operation.UserExistsOperation$3(com.mongodb.operation.UserExistsOperation);
    Code:
       0: aload_0
       1: aload_1
       2: putfield      #1                  // Field this$0:Lcom/mongodb/operation/UserExistsOperation;
       5: aload_0
       6: invokespecial #2                  // Method java/lang/Object."<init>":()V
       9: return

  public java.lang.Boolean apply(org.bson.BsonDocument, com.mongodb.ServerAddress);
    Code:
       0: aload_1
       1: ldc           #3                  // String users
       3: invokevirtual #4                  // Method org/bson/BsonDocument.get:(Ljava/lang/Object;)Lorg/bson/BsonValue;
       6: invokevirtual #5                  // Method org/bson/BsonValue.isArray:()Z
       9: ifeq          28
      12: aload_1
      13: ldc           #3                  // String users
      15: invokevirtual #6                  // Method org/bson/BsonDocument.getArray:(Ljava/lang/Object;)Lorg/bson/BsonArray;
      18: invokevirtual #7                  // Method org/bson/BsonArray.isEmpty:()Z
      21: ifne          28
      24: iconst_1
      25: goto          29
      28: iconst_0
      29: invokestatic  #8                  // Method java/lang/Boolean.valueOf:(Z)Ljava/lang/Boolean;
      32: areturn

  public java.lang.Object apply(java.lang.Object, com.mongodb.ServerAddress);
    Code:
       0: aload_0
       1: aload_1
       2: checkcast     #9                  // class org/bson/BsonDocument
       5: aload_2
       6: invokevirtual #10                 // Method apply:(Lorg/bson/BsonDocument;Lcom/mongodb/ServerAddress;)Ljava/lang/Boolean;
       9: areturn
}
