Compiled from "Codec.java"
public class org.graylog2.plugin.inputs.codecs.Codec$Descriptor extends org.graylog2.plugin.AbstractDescriptor {
  public org.graylog2.plugin.inputs.codecs.Codec$Descriptor();
    Code:
       0: aload_0
       1: ldc           #1                  // String
       3: invokespecial #2                  // Method "<init>":(Ljava/lang/String;)V
       6: return

  protected org.graylog2.plugin.inputs.codecs.Codec$Descriptor(java.lang.String);
    Code:
       0: aload_0
       1: aload_1
       2: iconst_0
       3: ldc           #1                  // String
       5: invokespecial #3                  // Method org/graylog2/plugin/AbstractDescriptor."<init>":(Ljava/lang/String;ZLjava/lang/String;)V
       8: return
}
