Compiled from "AdaptiveLoadBalancing.scala"
public final class akka.cluster.routing.AdaptiveLoadBalancingGroup$ extends scala.runtime.AbstractFunction3<akka.cluster.routing.MetricsSelector, scala.collection.immutable.Iterable<java.lang.String>, java.lang.String, akka.cluster.routing.AdaptiveLoadBalancingGroup> implements scala.Serializable {
  public static final akka.cluster.routing.AdaptiveLoadBalancingGroup$ MODULE$;

  public static {};
    Code:
       0: new           #2                  // class akka/cluster/routing/AdaptiveLoadBalancingGroup$
       3: invokespecial #15                 // Method "<init>":()V
       6: return

  public final java.lang.String toString();
    Code:
       0: ldc           #19                 // String AdaptiveLoadBalancingGroup
       2: areturn

  public akka.cluster.routing.AdaptiveLoadBalancingGroup apply(akka.cluster.routing.MetricsSelector, scala.collection.immutable.Iterable<java.lang.String>, java.lang.String);
    Code:
       0: new           #24                 // class akka/cluster/routing/AdaptiveLoadBalancingGroup
       3: dup
       4: aload_1
       5: aload_2
       6: aload_3
       7: invokespecial #27                 // Method akka/cluster/routing/AdaptiveLoadBalancingGroup."<init>":(Lakka/cluster/routing/MetricsSelector;Lscala/collection/immutable/Iterable;Ljava/lang/String;)V
      10: areturn

  public scala.Option<scala.Tuple3<akka.cluster.routing.MetricsSelector, scala.collection.immutable.Iterable<java.lang.String>, java.lang.String>> unapply(akka.cluster.routing.AdaptiveLoadBalancingGroup);
    Code:
       0: aload_1
       1: ifnonnull     10
       4: getstatic     #40                 // Field scala/None$.MODULE$:Lscala/None$;
       7: goto          36
      10: new           #42                 // class scala/Some
      13: dup
      14: new           #44                 // class scala/Tuple3
      17: dup
      18: aload_1
      19: invokevirtual #47                 // Method akka/cluster/routing/AdaptiveLoadBalancingGroup.metricsSelector:()Lakka/cluster/routing/MetricsSelector;
      22: aload_1
      23: invokevirtual #50                 // Method akka/cluster/routing/AdaptiveLoadBalancingGroup.paths:()Lscala/collection/immutable/Iterable;
      26: aload_1
      27: invokevirtual #52                 // Method akka/cluster/routing/AdaptiveLoadBalancingGroup.routerDispatcher:()Ljava/lang/String;
      30: invokespecial #55                 // Method scala/Tuple3."<init>":(Ljava/lang/Object;Ljava/lang/Object;Ljava/lang/Object;)V
      33: invokespecial #58                 // Method scala/Some."<init>":(Ljava/lang/Object;)V
      36: areturn

  public akka.cluster.routing.MetricsSelector $lessinit$greater$default$1();
    Code:
       0: getstatic     #68                 // Field akka/cluster/routing/MixMetricsSelector$.MODULE$:Lakka/cluster/routing/MixMetricsSelector$;
       3: areturn

  public scala.collection.immutable.Iterable<java.lang.String> $lessinit$greater$default$2();
    Code:
       0: getstatic     #74                 // Field scala/collection/immutable/Nil$.MODULE$:Lscala/collection/immutable/Nil$;
       3: areturn

  public java.lang.String $lessinit$greater$default$3();
    Code:
       0: ldc           #77                 // String akka.actor.default-dispatcher
       2: areturn

  public akka.cluster.routing.MetricsSelector apply$default$1();
    Code:
       0: getstatic     #68                 // Field akka/cluster/routing/MixMetricsSelector$.MODULE$:Lakka/cluster/routing/MixMetricsSelector$;
       3: areturn

  public scala.collection.immutable.Iterable<java.lang.String> apply$default$2();
    Code:
       0: getstatic     #74                 // Field scala/collection/immutable/Nil$.MODULE$:Lscala/collection/immutable/Nil$;
       3: areturn

  public java.lang.String apply$default$3();
    Code:
       0: ldc           #77                 // String akka.actor.default-dispatcher
       2: areturn

  private java.lang.Object readResolve();
    Code:
       0: getstatic     #84                 // Field MODULE$:Lakka/cluster/routing/AdaptiveLoadBalancingGroup$;
       3: areturn

  public java.lang.Object apply(java.lang.Object, java.lang.Object, java.lang.Object);
    Code:
       0: aload_0
       1: aload_1
       2: checkcast     #87                 // class akka/cluster/routing/MetricsSelector
       5: aload_2
       6: checkcast     #89                 // class scala/collection/immutable/Iterable
       9: aload_3
      10: checkcast     #91                 // class java/lang/String
      13: invokevirtual #93                 // Method apply:(Lakka/cluster/routing/MetricsSelector;Lscala/collection/immutable/Iterable;Ljava/lang/String;)Lakka/cluster/routing/AdaptiveLoadBalancingGroup;
      16: areturn

  private akka.cluster.routing.AdaptiveLoadBalancingGroup$();
    Code:
       0: aload_0
       1: invokespecial #98                 // Method scala/runtime/AbstractFunction3."<init>":()V
       4: aload_0
       5: putstatic     #84                 // Field MODULE$:Lakka/cluster/routing/AdaptiveLoadBalancingGroup$;
       8: return
}
