Compiled from "TypeConverterLoaderException.java"
public class org.apache.camel.TypeConverterLoaderException extends org.apache.camel.CamelException {
  private static final long serialVersionUID;

  public org.apache.camel.TypeConverterLoaderException(java.lang.String);
    Code:
       0: aload_0
       1: new           #13                 // class java/lang/StringBuilder
       4: dup
       5: invokespecial #16                 // Method java/lang/StringBuilder."<init>":()V
       8: ldc           #18                 // String Failed to load type converters because of:
      10: invokevirtual #22                 // Method java/lang/StringBuilder.append:(Ljava/lang/String;)Ljava/lang/StringBuilder;
      13: aload_1
      14: invokevirtual #22                 // Method java/lang/StringBuilder.append:(Ljava/lang/String;)Ljava/lang/StringBuilder;
      17: invokevirtual #26                 // Method java/lang/StringBuilder.toString:()Ljava/lang/String;
      20: invokespecial #28                 // Method org/apache/camel/CamelException."<init>":(Ljava/lang/String;)V
      23: return

  public org.apache.camel.TypeConverterLoaderException(java.lang.String, java.lang.Throwable);
    Code:
       0: aload_0
       1: new           #13                 // class java/lang/StringBuilder
       4: dup
       5: invokespecial #16                 // Method java/lang/StringBuilder."<init>":()V
       8: ldc           #18                 // String Failed to load type converters because of:
      10: invokevirtual #22                 // Method java/lang/StringBuilder.append:(Ljava/lang/String;)Ljava/lang/StringBuilder;
      13: aload_1
      14: invokevirtual #22                 // Method java/lang/StringBuilder.append:(Ljava/lang/String;)Ljava/lang/StringBuilder;
      17: invokevirtual #26                 // Method java/lang/StringBuilder.toString:()Ljava/lang/String;
      20: aload_2
      21: invokespecial #35                 // Method org/apache/camel/CamelException."<init>":(Ljava/lang/String;Ljava/lang/Throwable;)V
      24: return
}
