Compiled from "HealthIndicatorBeansComposite.java"
class org.springframework.boot.actuate.autoconfigure.health.HealthIndicatorBeansComposite$ReactiveHealthIndicators {
  private org.springframework.boot.actuate.autoconfigure.health.HealthIndicatorBeansComposite$ReactiveHealthIndicators();
    Code:
       0: aload_0
       1: invokespecial #2                  // Method java/lang/Object."<init>":()V
       4: return

  public java.util.Map<java.lang.String, org.springframework.boot.actuate.health.HealthIndicator> get(org.springframework.context.ApplicationContext);
    Code:
       0: new           #3                  // class java/util/LinkedHashMap
       3: dup
       4: invokespecial #4                  // Method java/util/LinkedHashMap."<init>":()V
       7: astore_2
       8: aload_1
       9: ldc           #5                  // class org/springframework/boot/actuate/health/ReactiveHealthIndicator
      11: invokeinterface #6,  2            // InterfaceMethod org/springframework/context/ApplicationContext.getBeansOfType:(Ljava/lang/Class;)Ljava/util/Map;
      16: aload_0
      17: aload_2
      18: invokedynamic #7,  0              // InvokeDynamic #0:accept:(Lorg/springframework/boot/actuate/autoconfigure/health/HealthIndicatorBeansComposite$ReactiveHealthIndicators;Ljava/util/Map;)Ljava/util/function/BiConsumer;
      23: invokeinterface #8,  2            // InterfaceMethod java/util/Map.forEach:(Ljava/util/function/BiConsumer;)V
      28: aload_2
      29: areturn

  private org.springframework.boot.actuate.health.HealthIndicator adapt(org.springframework.boot.actuate.health.ReactiveHealthIndicator);
    Code:
       0: aload_1
       1: invokedynamic #9,  0              // InvokeDynamic #1:health:(Lorg/springframework/boot/actuate/health/ReactiveHealthIndicator;)Lorg/springframework/boot/actuate/health/HealthIndicator;
       6: areturn

  private static org.springframework.boot.actuate.health.Health lambda$adapt$1(org.springframework.boot.actuate.health.ReactiveHealthIndicator);
    Code:
       0: aload_0
       1: invokeinterface #10,  1           // InterfaceMethod org/springframework/boot/actuate/health/ReactiveHealthIndicator.health:()Lreactor/core/publisher/Mono;
       6: invokevirtual #11                 // Method reactor/core/publisher/Mono.block:()Ljava/lang/Object;
       9: checkcast     #12                 // class org/springframework/boot/actuate/health/Health
      12: areturn

  private void lambda$get$0(java.util.Map, java.lang.String, org.springframework.boot.actuate.health.ReactiveHealthIndicator);
    Code:
       0: aload_1
       1: aload_2
       2: aload_0
       3: aload_3
       4: invokespecial #13                 // Method adapt:(Lorg/springframework/boot/actuate/health/ReactiveHealthIndicator;)Lorg/springframework/boot/actuate/health/HealthIndicator;
       7: invokeinterface #14,  3           // InterfaceMethod java/util/Map.put:(Ljava/lang/Object;Ljava/lang/Object;)Ljava/lang/Object;
      12: checkcast     #15                 // class org/springframework/boot/actuate/health/HealthIndicator
      15: pop
      16: return

  org.springframework.boot.actuate.autoconfigure.health.HealthIndicatorBeansComposite$ReactiveHealthIndicators(org.springframework.boot.actuate.autoconfigure.health.HealthIndicatorBeansComposite$1);
    Code:
       0: aload_0
       1: invokespecial #1                  // Method "<init>":()V
       4: return
}
