Compiled from "HealthEndpointWebExtensionConfiguration.java"
class org.springframework.boot.actuate.autoconfigure.health.HealthEndpointWebExtensionConfiguration$ReactiveWebHealthConfiguration {
  private final org.springframework.boot.actuate.health.ReactiveHealthIndicator reactiveHealthIndicator;

  org.springframework.boot.actuate.autoconfigure.health.HealthEndpointWebExtensionConfiguration$ReactiveWebHealthConfiguration(org.springframework.beans.factory.ObjectProvider<org.springframework.boot.actuate.health.HealthAggregator>, org.springframework.beans.factory.ObjectProvider<java.util.Map<java.lang.String, org.springframework.boot.actuate.health.ReactiveHealthIndicator>>, org.springframework.beans.factory.ObjectProvider<java.util.Map<java.lang.String, org.springframework.boot.actuate.health.HealthIndicator>>);
    Code:
       0: aload_0
       1: invokespecial #1                  // Method java/lang/Object."<init>":()V
       4: aload_0
       5: new           #2                  // class org/springframework/boot/actuate/health/CompositeReactiveHealthIndicatorFactory
       8: dup
       9: invokespecial #3                  // Method org/springframework/boot/actuate/health/CompositeReactiveHealthIndicatorFactory."<init>":()V
      12: aload_1
      13: invokedynamic #4,  0              // InvokeDynamic #0:get:()Ljava/util/function/Supplier;
      18: invokeinterface #5,  2            // InterfaceMethod org/springframework/beans/factory/ObjectProvider.getIfAvailable:(Ljava/util/function/Supplier;)Ljava/lang/Object;
      23: checkcast     #6                  // class org/springframework/boot/actuate/health/HealthAggregator
      26: aload_2
      27: invokedynamic #7,  0              // InvokeDynamic #1:get:()Ljava/util/function/Supplier;
      32: invokeinterface #5,  2            // InterfaceMethod org/springframework/beans/factory/ObjectProvider.getIfAvailable:(Ljava/util/function/Supplier;)Ljava/lang/Object;
      37: checkcast     #8                  // class java/util/Map
      40: aload_3
      41: invokedynamic #7,  0              // InvokeDynamic #1:get:()Ljava/util/function/Supplier;
      46: invokeinterface #5,  2            // InterfaceMethod org/springframework/beans/factory/ObjectProvider.getIfAvailable:(Ljava/util/function/Supplier;)Ljava/lang/Object;
      51: checkcast     #8                  // class java/util/Map
      54: invokevirtual #9                  // Method org/springframework/boot/actuate/health/CompositeReactiveHealthIndicatorFactory.createReactiveHealthIndicator:(Lorg/springframework/boot/actuate/health/HealthAggregator;Ljava/util/Map;Ljava/util/Map;)Lorg/springframework/boot/actuate/health/CompositeReactiveHealthIndicator;
      57: putfield      #10                 // Field reactiveHealthIndicator:Lorg/springframework/boot/actuate/health/ReactiveHealthIndicator;
      60: return

  public org.springframework.boot.actuate.health.ReactiveHealthEndpointWebExtension reactiveHealthEndpointWebExtension(org.springframework.boot.actuate.health.HealthWebEndpointResponseMapper);
    Code:
       0: new           #11                 // class org/springframework/boot/actuate/health/ReactiveHealthEndpointWebExtension
       3: dup
       4: aload_0
       5: getfield      #10                 // Field reactiveHealthIndicator:Lorg/springframework/boot/actuate/health/ReactiveHealthIndicator;
       8: aload_1
       9: invokespecial #12                 // Method org/springframework/boot/actuate/health/ReactiveHealthEndpointWebExtension."<init>":(Lorg/springframework/boot/actuate/health/ReactiveHealthIndicator;Lorg/springframework/boot/actuate/health/HealthWebEndpointResponseMapper;)V
      12: areturn
}
