Compiled from "ListToSet.java"
public abstract class org.jboss.weld.util.collections.ListToSet<T> extends java.util.AbstractSet<T> {
  public org.jboss.weld.util.collections.ListToSet();
    Code:
       0: aload_0
       1: invokespecial #1                  // Method java/util/AbstractSet."<init>":()V
       4: return

  protected abstract java.util.List<T> delegate();

  public java.util.Iterator<T> iterator();
    Code:
       0: aload_0
       1: invokevirtual #2                  // Method delegate:()Ljava/util/List;
       4: invokeinterface #3,  1            // InterfaceMethod java/util/List.iterator:()Ljava/util/Iterator;
       9: areturn

  public int size();
    Code:
       0: aload_0
       1: invokevirtual #2                  // Method delegate:()Ljava/util/List;
       4: invokeinterface #4,  1            // InterfaceMethod java/util/List.size:()I
       9: ireturn
}
