Compiled from "IndexRangeComparator.java"
public class org.graylog2.indexer.ranges.IndexRangeComparator implements java.util.Comparator<org.graylog2.indexer.ranges.IndexRange> {
  public org.graylog2.indexer.ranges.IndexRangeComparator();
    Code:
       0: aload_0
       1: invokespecial #1                  // Method java/lang/Object."<init>":()V
       4: return

  public int compare(org.graylog2.indexer.ranges.IndexRange, org.graylog2.indexer.ranges.IndexRange);
    Code:
       0: invokestatic  #2                  // Method com/google/common/collect/ComparisonChain.start:()Lcom/google/common/collect/ComparisonChain;
       3: aload_1
       4: invokeinterface #3,  1            // InterfaceMethod org/graylog2/indexer/ranges/IndexRange.end:()Lorg/joda/time/DateTime;
       9: aload_2
      10: invokeinterface #3,  1            // InterfaceMethod org/graylog2/indexer/ranges/IndexRange.end:()Lorg/joda/time/DateTime;
      15: invokevirtual #4                  // Method com/google/common/collect/ComparisonChain.compare:(Ljava/lang/Comparable;Ljava/lang/Comparable;)Lcom/google/common/collect/ComparisonChain;
      18: aload_1
      19: invokeinterface #5,  1            // InterfaceMethod org/graylog2/indexer/ranges/IndexRange.begin:()Lorg/joda/time/DateTime;
      24: aload_2
      25: invokeinterface #5,  1            // InterfaceMethod org/graylog2/indexer/ranges/IndexRange.begin:()Lorg/joda/time/DateTime;
      30: invokevirtual #4                  // Method com/google/common/collect/ComparisonChain.compare:(Ljava/lang/Comparable;Ljava/lang/Comparable;)Lcom/google/common/collect/ComparisonChain;
      33: aload_1
      34: invokeinterface #6,  1            // InterfaceMethod org/graylog2/indexer/ranges/IndexRange.indexName:()Ljava/lang/String;
      39: aload_2
      40: invokeinterface #6,  1            // InterfaceMethod org/graylog2/indexer/ranges/IndexRange.indexName:()Ljava/lang/String;
      45: invokevirtual #4                  // Method com/google/common/collect/ComparisonChain.compare:(Ljava/lang/Comparable;Ljava/lang/Comparable;)Lcom/google/common/collect/ComparisonChain;
      48: invokevirtual #7                  // Method com/google/common/collect/ComparisonChain.result:()I
      51: ireturn

  public int compare(java.lang.Object, java.lang.Object);
    Code:
       0: aload_0
       1: aload_1
       2: checkcast     #8                  // class org/graylog2/indexer/ranges/IndexRange
       5: aload_2
       6: checkcast     #8                  // class org/graylog2/indexer/ranges/IndexRange
       9: invokevirtual #9                  // Method compare:(Lorg/graylog2/indexer/ranges/IndexRange;Lorg/graylog2/indexer/ranges/IndexRange;)I
      12: ireturn
}
