Compiled from "ByteValidator.java"
public class org.apache.commons.validator.routines.ByteValidator extends org.apache.commons.validator.routines.AbstractNumberValidator {
  private static final long serialVersionUID;

  private static final org.apache.commons.validator.routines.ByteValidator VALIDATOR;

  public static org.apache.commons.validator.routines.ByteValidator getInstance();
    Code:
       0: getstatic     #1                  // Field VALIDATOR:Lorg/apache/commons/validator/routines/ByteValidator;
       3: areturn

  public org.apache.commons.validator.routines.ByteValidator();
    Code:
       0: aload_0
       1: iconst_1
       2: iconst_0
       3: invokespecial #2                  // Method "<init>":(ZI)V
       6: return

  public org.apache.commons.validator.routines.ByteValidator(boolean, int);
    Code:
       0: aload_0
       1: iload_1
       2: iload_2
       3: iconst_0
       4: invokespecial #3                  // Method org/apache/commons/validator/routines/AbstractNumberValidator."<init>":(ZIZ)V
       7: return

  public java.lang.Byte validate(java.lang.String);
    Code:
       0: aload_0
       1: aload_1
       2: aconst_null
       3: checkcast     #4                  // class java/lang/String
       6: aconst_null
       7: checkcast     #5                  // class java/util/Locale
      10: invokevirtual #6                  // Method parse:(Ljava/lang/String;Ljava/lang/String;Ljava/util/Locale;)Ljava/lang/Object;
      13: checkcast     #7                  // class java/lang/Byte
      16: areturn

  public java.lang.Byte validate(java.lang.String, java.lang.String);
    Code:
       0: aload_0
       1: aload_1
       2: aload_2
       3: aconst_null
       4: checkcast     #5                  // class java/util/Locale
       7: invokevirtual #6                  // Method parse:(Ljava/lang/String;Ljava/lang/String;Ljava/util/Locale;)Ljava/lang/Object;
      10: checkcast     #7                  // class java/lang/Byte
      13: areturn

  public java.lang.Byte validate(java.lang.String, java.util.Locale);
    Code:
       0: aload_0
       1: aload_1
       2: aconst_null
       3: checkcast     #4                  // class java/lang/String
       6: aload_2
       7: invokevirtual #6                  // Method parse:(Ljava/lang/String;Ljava/lang/String;Ljava/util/Locale;)Ljava/lang/Object;
      10: checkcast     #7                  // class java/lang/Byte
      13: areturn

  public java.lang.Byte validate(java.lang.String, java.lang.String, java.util.Locale);
    Code:
       0: aload_0
       1: aload_1
       2: aload_2
       3: aload_3
       4: invokevirtual #6                  // Method parse:(Ljava/lang/String;Ljava/lang/String;Ljava/util/Locale;)Ljava/lang/Object;
       7: checkcast     #7                  // class java/lang/Byte
      10: areturn

  public boolean isInRange(byte, byte, byte);
    Code:
       0: iload_1
       1: iload_2
       2: if_icmplt     14
       5: iload_1
       6: iload_3
       7: if_icmpgt     14
      10: iconst_1
      11: goto          15
      14: iconst_0
      15: ireturn

  public boolean isInRange(java.lang.Byte, byte, byte);
    Code:
       0: aload_0
       1: aload_1
       2: invokevirtual #8                  // Method java/lang/Byte.byteValue:()B
       5: iload_2
       6: iload_3
       7: invokevirtual #9                  // Method isInRange:(BBB)Z
      10: ireturn

  public boolean minValue(byte, byte);
    Code:
       0: iload_1
       1: iload_2
       2: if_icmplt     9
       5: iconst_1
       6: goto          10
       9: iconst_0
      10: ireturn

  public boolean minValue(java.lang.Byte, byte);
    Code:
       0: aload_0
       1: aload_1
       2: invokevirtual #8                  // Method java/lang/Byte.byteValue:()B
       5: iload_2
       6: invokevirtual #10                 // Method minValue:(BB)Z
       9: ireturn

  public boolean maxValue(byte, byte);
    Code:
       0: iload_1
       1: iload_2
       2: if_icmpgt     9
       5: iconst_1
       6: goto          10
       9: iconst_0
      10: ireturn

  public boolean maxValue(java.lang.Byte, byte);
    Code:
       0: aload_0
       1: aload_1
       2: invokevirtual #8                  // Method java/lang/Byte.byteValue:()B
       5: iload_2
       6: invokevirtual #11                 // Method maxValue:(BB)Z
       9: ireturn

  protected java.lang.Object processParsedValue(java.lang.Object, java.text.Format);
    Code:
       0: aload_1
       1: checkcast     #12                 // class java/lang/Number
       4: invokevirtual #13                 // Method java/lang/Number.longValue:()J
       7: lstore_3
       8: lload_3
       9: ldc2_w        #14                 // long -128l
      12: lcmp
      13: iflt          24
      16: lload_3
      17: ldc2_w        #16                 // long 127l
      20: lcmp
      21: ifle          26
      24: aconst_null
      25: areturn
      26: new           #7                  // class java/lang/Byte
      29: dup
      30: lload_3
      31: l2i
      32: i2b
      33: invokespecial #18                 // Method java/lang/Byte."<init>":(B)V
      36: areturn

  static {};
    Code:
       0: new           #19                 // class org/apache/commons/validator/routines/ByteValidator
       3: dup
       4: invokespecial #20                 // Method "<init>":()V
       7: putstatic     #1                  // Field VALIDATOR:Lorg/apache/commons/validator/routines/ByteValidator;
      10: return
}
