Compiled from "ISBNValidator.java"
public class org.apache.commons.validator.routines.ISBNValidator implements java.io.Serializable {
  private static final long serialVersionUID;

  private static final java.lang.String SEP;

  private static final java.lang.String GROUP;

  private static final java.lang.String PUBLISHER;

  private static final java.lang.String TITLE;

  static final java.lang.String ISBN10_REGEX;

  static final java.lang.String ISBN13_REGEX;

  private static final org.apache.commons.validator.routines.ISBNValidator ISBN_VALIDATOR;

  private static final org.apache.commons.validator.routines.ISBNValidator ISBN_VALIDATOR_NO_CONVERT;

  private final org.apache.commons.validator.routines.CodeValidator isbn10Validator;

  private final org.apache.commons.validator.routines.CodeValidator isbn13Validator;

  private final boolean convert;

  public static org.apache.commons.validator.routines.ISBNValidator getInstance();
    Code:
       0: getstatic     #1                  // Field ISBN_VALIDATOR:Lorg/apache/commons/validator/routines/ISBNValidator;
       3: areturn

  public static org.apache.commons.validator.routines.ISBNValidator getInstance(boolean);
    Code:
       0: iload_0
       1: ifeq          10
       4: getstatic     #1                  // Field ISBN_VALIDATOR:Lorg/apache/commons/validator/routines/ISBNValidator;
       7: goto          13
      10: getstatic     #2                  // Field ISBN_VALIDATOR_NO_CONVERT:Lorg/apache/commons/validator/routines/ISBNValidator;
      13: areturn

  public org.apache.commons.validator.routines.ISBNValidator();
    Code:
       0: aload_0
       1: iconst_1
       2: invokespecial #3                  // Method "<init>":(Z)V
       5: return

  public org.apache.commons.validator.routines.ISBNValidator(boolean);
    Code:
       0: aload_0
       1: invokespecial #4                  // Method java/lang/Object."<init>":()V
       4: aload_0
       5: new           #5                  // class org/apache/commons/validator/routines/CodeValidator
       8: dup
       9: ldc           #6                  // String ^(?:(\\d{9}[0-9X])|(?:(\\d{1,5})(?:\\-|\\s)(\\d{1,7})(?:\\-|\\s)(\\d{1,6})(?:\\-|\\s)([0-9X])))$
      11: bipush        10
      13: getstatic     #7                  // Field org/apache/commons/validator/routines/checkdigit/ISBN10CheckDigit.ISBN10_CHECK_DIGIT:Lorg/apache/commons/validator/routines/checkdigit/CheckDigit;
      16: invokespecial #8                  // Method org/apache/commons/validator/routines/CodeValidator."<init>":(Ljava/lang/String;ILorg/apache/commons/validator/routines/checkdigit/CheckDigit;)V
      19: putfield      #9                  // Field isbn10Validator:Lorg/apache/commons/validator/routines/CodeValidator;
      22: aload_0
      23: new           #5                  // class org/apache/commons/validator/routines/CodeValidator
      26: dup
      27: ldc           #10                 // String ^(978|979)(?:(\\d{10})|(?:(?:\\-|\\s)(\\d{1,5})(?:\\-|\\s)(\\d{1,7})(?:\\-|\\s)(\\d{1,6})(?:\\-|\\s)([0-9])))$
      29: bipush        13
      31: getstatic     #11                 // Field org/apache/commons/validator/routines/checkdigit/EAN13CheckDigit.EAN13_CHECK_DIGIT:Lorg/apache/commons/validator/routines/checkdigit/CheckDigit;
      34: invokespecial #8                  // Method org/apache/commons/validator/routines/CodeValidator."<init>":(Ljava/lang/String;ILorg/apache/commons/validator/routines/checkdigit/CheckDigit;)V
      37: putfield      #12                 // Field isbn13Validator:Lorg/apache/commons/validator/routines/CodeValidator;
      40: aload_0
      41: iload_1
      42: putfield      #13                 // Field convert:Z
      45: return

  public boolean isValid(java.lang.String);
    Code:
       0: aload_0
       1: aload_1
       2: invokevirtual #14                 // Method isValidISBN13:(Ljava/lang/String;)Z
       5: ifne          16
       8: aload_0
       9: aload_1
      10: invokevirtual #15                 // Method isValidISBN10:(Ljava/lang/String;)Z
      13: ifeq          20
      16: iconst_1
      17: goto          21
      20: iconst_0
      21: ireturn

  public boolean isValidISBN10(java.lang.String);
    Code:
       0: aload_0
       1: getfield      #9                  // Field isbn10Validator:Lorg/apache/commons/validator/routines/CodeValidator;
       4: aload_1
       5: invokevirtual #16                 // Method org/apache/commons/validator/routines/CodeValidator.isValid:(Ljava/lang/String;)Z
       8: ireturn

  public boolean isValidISBN13(java.lang.String);
    Code:
       0: aload_0
       1: getfield      #12                 // Field isbn13Validator:Lorg/apache/commons/validator/routines/CodeValidator;
       4: aload_1
       5: invokevirtual #16                 // Method org/apache/commons/validator/routines/CodeValidator.isValid:(Ljava/lang/String;)Z
       8: ireturn

  public java.lang.String validate(java.lang.String);
    Code:
       0: aload_0
       1: aload_1
       2: invokevirtual #17                 // Method validateISBN13:(Ljava/lang/String;)Ljava/lang/String;
       5: astore_2
       6: aload_2
       7: ifnonnull     33
      10: aload_0
      11: aload_1
      12: invokevirtual #18                 // Method validateISBN10:(Ljava/lang/String;)Ljava/lang/String;
      15: astore_2
      16: aload_2
      17: ifnull        33
      20: aload_0
      21: getfield      #13                 // Field convert:Z
      24: ifeq          33
      27: aload_0
      28: aload_2
      29: invokevirtual #19                 // Method convertToISBN13:(Ljava/lang/String;)Ljava/lang/String;
      32: astore_2
      33: aload_2
      34: areturn

  public java.lang.String validateISBN10(java.lang.String);
    Code:
       0: aload_0
       1: getfield      #9                  // Field isbn10Validator:Lorg/apache/commons/validator/routines/CodeValidator;
       4: aload_1
       5: invokevirtual #20                 // Method org/apache/commons/validator/routines/CodeValidator.validate:(Ljava/lang/String;)Ljava/lang/Object;
       8: astore_2
       9: aload_2
      10: ifnonnull     17
      13: aconst_null
      14: goto          21
      17: aload_2
      18: invokevirtual #21                 // Method java/lang/Object.toString:()Ljava/lang/String;
      21: areturn

  public java.lang.String validateISBN13(java.lang.String);
    Code:
       0: aload_0
       1: getfield      #12                 // Field isbn13Validator:Lorg/apache/commons/validator/routines/CodeValidator;
       4: aload_1
       5: invokevirtual #20                 // Method org/apache/commons/validator/routines/CodeValidator.validate:(Ljava/lang/String;)Ljava/lang/Object;
       8: astore_2
       9: aload_2
      10: ifnonnull     17
      13: aconst_null
      14: goto          21
      17: aload_2
      18: invokevirtual #21                 // Method java/lang/Object.toString:()Ljava/lang/String;
      21: areturn

  public java.lang.String convertToISBN13(java.lang.String);
    Code:
       0: aload_1
       1: ifnonnull     6
       4: aconst_null
       5: areturn
       6: aload_1
       7: invokevirtual #22                 // Method java/lang/String.trim:()Ljava/lang/String;
      10: astore_2
      11: aload_2
      12: invokevirtual #23                 // Method java/lang/String.length:()I
      15: bipush        10
      17: if_icmpeq     64
      20: new           #24                 // class java/lang/IllegalArgumentException
      23: dup
      24: new           #25                 // class java/lang/StringBuilder
      27: dup
      28: invokespecial #26                 // Method java/lang/StringBuilder."<init>":()V
      31: ldc           #27                 // String Invalid length
      33: invokevirtual #28                 // Method java/lang/StringBuilder.append:(Ljava/lang/String;)Ljava/lang/StringBuilder;
      36: aload_2
      37: invokevirtual #23                 // Method java/lang/String.length:()I
      40: invokevirtual #29                 // Method java/lang/StringBuilder.append:(I)Ljava/lang/StringBuilder;
      43: ldc           #30                 // String  for \'
      45: invokevirtual #28                 // Method java/lang/StringBuilder.append:(Ljava/lang/String;)Ljava/lang/StringBuilder;
      48: aload_2
      49: invokevirtual #28                 // Method java/lang/StringBuilder.append:(Ljava/lang/String;)Ljava/lang/StringBuilder;
      52: ldc           #31                 // String \'
      54: invokevirtual #28                 // Method java/lang/StringBuilder.append:(Ljava/lang/String;)Ljava/lang/StringBuilder;
      57: invokevirtual #32                 // Method java/lang/StringBuilder.toString:()Ljava/lang/String;
      60: invokespecial #33                 // Method java/lang/IllegalArgumentException."<init>":(Ljava/lang/String;)V
      63: athrow
      64: new           #25                 // class java/lang/StringBuilder
      67: dup
      68: invokespecial #26                 // Method java/lang/StringBuilder."<init>":()V
      71: ldc           #34                 // String 978
      73: invokevirtual #28                 // Method java/lang/StringBuilder.append:(Ljava/lang/String;)Ljava/lang/StringBuilder;
      76: aload_2
      77: iconst_0
      78: bipush        9
      80: invokevirtual #35                 // Method java/lang/String.substring:(II)Ljava/lang/String;
      83: invokevirtual #28                 // Method java/lang/StringBuilder.append:(Ljava/lang/String;)Ljava/lang/StringBuilder;
      86: invokevirtual #32                 // Method java/lang/StringBuilder.toString:()Ljava/lang/String;
      89: astore_3
      90: aload_0
      91: getfield      #12                 // Field isbn13Validator:Lorg/apache/commons/validator/routines/CodeValidator;
      94: invokevirtual #36                 // Method org/apache/commons/validator/routines/CodeValidator.getCheckDigit:()Lorg/apache/commons/validator/routines/checkdigit/CheckDigit;
      97: aload_3
      98: invokeinterface #37,  2           // InterfaceMethod org/apache/commons/validator/routines/checkdigit/CheckDigit.calculate:(Ljava/lang/String;)Ljava/lang/String;
     103: astore        4
     105: new           #25                 // class java/lang/StringBuilder
     108: dup
     109: invokespecial #26                 // Method java/lang/StringBuilder."<init>":()V
     112: aload_3
     113: invokevirtual #28                 // Method java/lang/StringBuilder.append:(Ljava/lang/String;)Ljava/lang/StringBuilder;
     116: aload         4
     118: invokevirtual #28                 // Method java/lang/StringBuilder.append:(Ljava/lang/String;)Ljava/lang/StringBuilder;
     121: invokevirtual #32                 // Method java/lang/StringBuilder.toString:()Ljava/lang/String;
     124: astore_3
     125: aload_3
     126: areturn
     127: astore        4
     129: new           #24                 // class java/lang/IllegalArgumentException
     132: dup
     133: new           #25                 // class java/lang/StringBuilder
     136: dup
     137: invokespecial #26                 // Method java/lang/StringBuilder."<init>":()V
     140: ldc           #39                 // String Check digit error for \'
     142: invokevirtual #28                 // Method java/lang/StringBuilder.append:(Ljava/lang/String;)Ljava/lang/StringBuilder;
     145: aload_2
     146: invokevirtual #28                 // Method java/lang/StringBuilder.append:(Ljava/lang/String;)Ljava/lang/StringBuilder;
     149: ldc           #40                 // String \' -
     151: invokevirtual #28                 // Method java/lang/StringBuilder.append:(Ljava/lang/String;)Ljava/lang/StringBuilder;
     154: aload         4
     156: invokevirtual #41                 // Method org/apache/commons/validator/routines/checkdigit/CheckDigitException.getMessage:()Ljava/lang/String;
     159: invokevirtual #28                 // Method java/lang/StringBuilder.append:(Ljava/lang/String;)Ljava/lang/StringBuilder;
     162: invokevirtual #32                 // Method java/lang/StringBuilder.toString:()Ljava/lang/String;
     165: invokespecial #33                 // Method java/lang/IllegalArgumentException."<init>":(Ljava/lang/String;)V
     168: athrow
    Exception table:
       from    to  target type
          90   126   127   Class org/apache/commons/validator/routines/checkdigit/CheckDigitException

  static {};
    Code:
       0: new           #42                 // class org/apache/commons/validator/routines/ISBNValidator
       3: dup
       4: invokespecial #43                 // Method "<init>":()V
       7: putstatic     #1                  // Field ISBN_VALIDATOR:Lorg/apache/commons/validator/routines/ISBNValidator;
      10: new           #42                 // class org/apache/commons/validator/routines/ISBNValidator
      13: dup
      14: iconst_0
      15: invokespecial #3                  // Method "<init>":(Z)V
      18: putstatic     #2                  // Field ISBN_VALIDATOR_NO_CONVERT:Lorg/apache/commons/validator/routines/ISBNValidator;
      21: return
}
