Compiled from "WatchConnectionManager.java"
abstract class io.fabric8.kubernetes.client.dsl.internal.WatchConnectionManager$NamedRunnable implements java.lang.Runnable {
  private final java.lang.String name;

  public io.fabric8.kubernetes.client.dsl.internal.WatchConnectionManager$NamedRunnable(java.lang.String);
    Code:
       0: aload_0
       1: invokespecial #1                  // Method java/lang/Object."<init>":()V
       4: aload_0
       5: aload_1
       6: invokestatic  #2                  // Method java/util/Objects.requireNonNull:(Ljava/lang/Object;)Ljava/lang/Object;
       9: checkcast     #3                  // class java/lang/String
      12: putfield      #4                  // Field name:Ljava/lang/String;
      15: return

  private void tryToSetName(java.lang.String);
    Code:
       0: invokestatic  #5                  // Method java/lang/Thread.currentThread:()Ljava/lang/Thread;
       3: aload_1
       4: invokevirtual #6                  // Method java/lang/Thread.setName:(Ljava/lang/String;)V
       7: goto          11
      10: astore_2
      11: return
    Exception table:
       from    to  target type
           0     7    10   Class java/lang/SecurityException

  public final void run();
    Code:
       0: invokestatic  #5                  // Method java/lang/Thread.currentThread:()Ljava/lang/Thread;
       3: invokevirtual #8                  // Method java/lang/Thread.getName:()Ljava/lang/String;
       6: astore_1
       7: aload_0
       8: new           #9                  // class java/lang/StringBuilder
      11: dup
      12: invokespecial #10                 // Method java/lang/StringBuilder."<init>":()V
      15: aload_0
      16: getfield      #4                  // Field name:Ljava/lang/String;
      19: invokevirtual #11                 // Method java/lang/StringBuilder.append:(Ljava/lang/String;)Ljava/lang/StringBuilder;
      22: ldc           #12                 // String |
      24: invokevirtual #11                 // Method java/lang/StringBuilder.append:(Ljava/lang/String;)Ljava/lang/StringBuilder;
      27: aload_1
      28: invokevirtual #11                 // Method java/lang/StringBuilder.append:(Ljava/lang/String;)Ljava/lang/StringBuilder;
      31: invokevirtual #13                 // Method java/lang/StringBuilder.toString:()Ljava/lang/String;
      34: invokespecial #14                 // Method tryToSetName:(Ljava/lang/String;)V
      37: aload_0
      38: invokevirtual #15                 // Method execute:()V
      41: aload_0
      42: aload_1
      43: invokespecial #14                 // Method tryToSetName:(Ljava/lang/String;)V
      46: goto          57
      49: astore_2
      50: aload_0
      51: aload_1
      52: invokespecial #14                 // Method tryToSetName:(Ljava/lang/String;)V
      55: aload_2
      56: athrow
      57: return
    Exception table:
       from    to  target type
          37    41    49   any

  protected abstract void execute();
}
