Compiled from "Network.scala"
public final class fs2.io.net.Network$ {
  public static fs2.io.net.Network$ MODULE$;

  private java.nio.channels.AsynchronousChannelGroup fs2$io$net$Network$$globalAcg;

  private fs2.io.net.AsynchronousDatagramSocketGroup fs2$io$net$Network$$globalAdsg;

  private volatile byte bitmap$0;

  public static {};
    Code:
       0: new           #2                  // class fs2/io/net/Network$
       3: invokespecial #20                 // Method "<init>":()V
       6: return

  private java.nio.channels.AsynchronousChannelGroup globalAcg$lzycompute();
    Code:
       0: aload_0
       1: dup
       2: astore_1
       3: monitorenter
       4: aload_0
       5: getfield      #24                 // Field bitmap$0:B
       8: iconst_1
       9: iand
      10: i2b
      11: iconst_0
      12: if_icmpne     49
      15: aload_0
      16: iconst_1
      17: getstatic     #29                 // Field fs2/internal/ThreadFactories$.MODULE$:Lfs2/internal/ThreadFactories$;
      20: ldc           #31                 // String fs2-global-tcp
      22: iconst_1
      23: getstatic     #29                 // Field fs2/internal/ThreadFactories$.MODULE$:Lfs2/internal/ThreadFactories$;
      26: invokevirtual #35                 // Method fs2/internal/ThreadFactories$.named$default$3:()Z
      29: invokevirtual #39                 // Method fs2/internal/ThreadFactories$.named:(Ljava/lang/String;ZZ)Ljava/util/concurrent/ThreadFactory;
      32: invokestatic  #45                 // Method java/nio/channels/AsynchronousChannelGroup.withFixedThreadPool:(ILjava/util/concurrent/ThreadFactory;)Ljava/nio/channels/AsynchronousChannelGroup;
      35: putfield      #47                 // Field fs2$io$net$Network$$globalAcg:Ljava/nio/channels/AsynchronousChannelGroup;
      38: aload_0
      39: aload_0
      40: getfield      #24                 // Field bitmap$0:B
      43: iconst_1
      44: ior
      45: i2b
      46: putfield      #24                 // Field bitmap$0:B
      49: aload_1
      50: monitorexit
      51: goto          57
      54: aload_1
      55: monitorexit
      56: athrow
      57: aload_0
      58: getfield      #47                 // Field fs2$io$net$Network$$globalAcg:Ljava/nio/channels/AsynchronousChannelGroup;
      61: areturn
    Exception table:
       from    to  target type
           4    49    54   any

  public java.nio.channels.AsynchronousChannelGroup fs2$io$net$Network$$globalAcg();
    Code:
       0: aload_0
       1: getfield      #24                 // Field bitmap$0:B
       4: iconst_1
       5: iand
       6: i2b
       7: iconst_0
       8: if_icmpne     18
      11: aload_0
      12: invokespecial #52                 // Method globalAcg$lzycompute:()Ljava/nio/channels/AsynchronousChannelGroup;
      15: goto          22
      18: aload_0
      19: getfield      #47                 // Field fs2$io$net$Network$$globalAcg:Ljava/nio/channels/AsynchronousChannelGroup;
      22: areturn

  private fs2.io.net.AsynchronousDatagramSocketGroup globalAdsg$lzycompute();
    Code:
       0: aload_0
       1: dup
       2: astore_1
       3: monitorenter
       4: aload_0
       5: getfield      #24                 // Field bitmap$0:B
       8: iconst_2
       9: iand
      10: i2b
      11: iconst_0
      12: if_icmpne     51
      15: aload_0
      16: getstatic     #59                 // Field fs2/io/net/AsynchronousDatagramSocketGroup$.MODULE$:Lfs2/io/net/AsynchronousDatagramSocketGroup$;
      19: getstatic     #29                 // Field fs2/internal/ThreadFactories$.MODULE$:Lfs2/internal/ThreadFactories$;
      22: ldc           #61                 // String fs2-global-udp
      24: iconst_1
      25: getstatic     #29                 // Field fs2/internal/ThreadFactories$.MODULE$:Lfs2/internal/ThreadFactories$;
      28: invokevirtual #35                 // Method fs2/internal/ThreadFactories$.named$default$3:()Z
      31: invokevirtual #39                 // Method fs2/internal/ThreadFactories$.named:(Ljava/lang/String;ZZ)Ljava/util/concurrent/ThreadFactory;
      34: invokevirtual #65                 // Method fs2/io/net/AsynchronousDatagramSocketGroup$.unsafe:(Ljava/util/concurrent/ThreadFactory;)Lfs2/io/net/AsynchronousDatagramSocketGroup;
      37: putfield      #67                 // Field fs2$io$net$Network$$globalAdsg:Lfs2/io/net/AsynchronousDatagramSocketGroup;
      40: aload_0
      41: aload_0
      42: getfield      #24                 // Field bitmap$0:B
      45: iconst_2
      46: ior
      47: i2b
      48: putfield      #24                 // Field bitmap$0:B
      51: aload_1
      52: monitorexit
      53: goto          59
      56: aload_1
      57: monitorexit
      58: athrow
      59: aload_0
      60: getfield      #67                 // Field fs2$io$net$Network$$globalAdsg:Lfs2/io/net/AsynchronousDatagramSocketGroup;
      63: areturn
    Exception table:
       from    to  target type
           4    51    56   any

  public fs2.io.net.AsynchronousDatagramSocketGroup fs2$io$net$Network$$globalAdsg();
    Code:
       0: aload_0
       1: getfield      #24                 // Field bitmap$0:B
       4: iconst_2
       5: iand
       6: i2b
       7: iconst_0
       8: if_icmpne     18
      11: aload_0
      12: invokespecial #69                 // Method globalAdsg$lzycompute:()Lfs2/io/net/AsynchronousDatagramSocketGroup;
      15: goto          22
      18: aload_0
      19: getfield      #67                 // Field fs2$io$net$Network$$globalAdsg:Lfs2/io/net/AsynchronousDatagramSocketGroup;
      22: areturn

  public <F> fs2.io.net.Network<F> apply(fs2.io.net.Network<F>);
    Code:
       0: aload_1
       1: areturn

  public <F> fs2.io.net.Network<F> forAsync(cats.effect.kernel.Async<F>);
    Code:
       0: new           #7                  // class fs2/io/net/Network$$anon$1
       3: dup
       4: aload_1
       5: invokespecial #82                 // Method fs2/io/net/Network$$anon$1."<init>":(Lcats/effect/kernel/Async;)V
       8: areturn

  private fs2.io.net.Network$();
    Code:
       0: aload_0
       1: invokespecial #84                 // Method java/lang/Object."<init>":()V
       4: aload_0
       5: putstatic     #86                 // Field MODULE$:Lfs2/io/net/Network$;
       8: return
}
