Compiled from "SocketGroup.scala"
public final class fs2.io.net.SocketGroup$AsyncSocketGroup$$anon$1 implements java.nio.channels.CompletionHandler<java.lang.Void, java.lang.Void> {
  private final scala.Function1 cb$1;

  private final java.nio.channels.AsynchronousSocketChannel ch$2;

  public void completed(java.lang.Void, java.lang.Void);
    Code:
       0: aload_0
       1: getfield      #26                 // Field cb$1:Lscala/Function1;
       4: getstatic     #32                 // Field scala/package$.MODULE$:Lscala/package$;
       7: invokevirtual #36                 // Method scala/package$.Right:()Lscala/util/Right$;
      10: aload_0
      11: getfield      #38                 // Field ch$2:Ljava/nio/channels/AsynchronousSocketChannel;
      14: invokevirtual #44                 // Method scala/util/Right$.apply:(Ljava/lang/Object;)Lscala/util/Right;
      17: invokeinterface #49,  2           // InterfaceMethod scala/Function1.apply:(Ljava/lang/Object;)Ljava/lang/Object;
      22: pop
      23: return

  public void failed(java.lang.Throwable, java.lang.Void);
    Code:
       0: aload_0
       1: getfield      #26                 // Field cb$1:Lscala/Function1;
       4: getstatic     #32                 // Field scala/package$.MODULE$:Lscala/package$;
       7: invokevirtual #59                 // Method scala/package$.Left:()Lscala/util/Left$;
      10: aload_1
      11: invokevirtual #64                 // Method scala/util/Left$.apply:(Ljava/lang/Object;)Lscala/util/Left;
      14: invokeinterface #49,  2           // InterfaceMethod scala/Function1.apply:(Ljava/lang/Object;)Ljava/lang/Object;
      19: pop
      20: return

  public void failed(java.lang.Throwable, java.lang.Object);
    Code:
       0: aload_0
       1: aload_1
       2: aload_2
       3: checkcast     #70                 // class java/lang/Void
       6: invokevirtual #72                 // Method failed:(Ljava/lang/Throwable;Ljava/lang/Void;)V
       9: return

  public void completed(java.lang.Object, java.lang.Object);
    Code:
       0: aload_0
       1: aload_1
       2: checkcast     #70                 // class java/lang/Void
       5: aload_2
       6: checkcast     #70                 // class java/lang/Void
       9: invokevirtual #76                 // Method completed:(Ljava/lang/Void;Ljava/lang/Void;)V
      12: return

  public fs2.io.net.SocketGroup$AsyncSocketGroup$$anon$1(fs2.io.net.SocketGroup$AsyncSocketGroup, scala.Function1, java.nio.channels.AsynchronousSocketChannel);
    Code:
       0: aload_0
       1: aload_2
       2: putfield      #26                 // Field cb$1:Lscala/Function1;
       5: aload_0
       6: aload_3
       7: putfield      #38                 // Field ch$2:Ljava/nio/channels/AsynchronousSocketChannel;
      10: aload_0
      11: invokespecial #82                 // Method java/lang/Object."<init>":()V
      14: return
}
