Compiled from "DefaultModelCache.java"
class org.apache.maven.repository.internal.DefaultModelCache implements org.apache.maven.model.building.ModelCache {
  private final org.sonatype.aether.RepositorySystemSession session;

  private final org.sonatype.aether.RepositoryCache cache;

  public static org.apache.maven.model.building.ModelCache newInstance(org.sonatype.aether.RepositorySystemSession);
    Code:
       0: aload_0
       1: invokeinterface #1,  1            // InterfaceMethod org/sonatype/aether/RepositorySystemSession.getCache:()Lorg/sonatype/aether/RepositoryCache;
       6: ifnonnull     11
       9: aconst_null
      10: areturn
      11: new           #2                  // class org/apache/maven/repository/internal/DefaultModelCache
      14: dup
      15: aload_0
      16: invokespecial #3                  // Method "<init>":(Lorg/sonatype/aether/RepositorySystemSession;)V
      19: areturn

  private org.apache.maven.repository.internal.DefaultModelCache(org.sonatype.aether.RepositorySystemSession);
    Code:
       0: aload_0
       1: invokespecial #4                  // Method java/lang/Object."<init>":()V
       4: aload_0
       5: aload_1
       6: putfield      #5                  // Field session:Lorg/sonatype/aether/RepositorySystemSession;
       9: aload_0
      10: aload_1
      11: invokeinterface #1,  1            // InterfaceMethod org/sonatype/aether/RepositorySystemSession.getCache:()Lorg/sonatype/aether/RepositoryCache;
      16: putfield      #6                  // Field cache:Lorg/sonatype/aether/RepositoryCache;
      19: return

  public java.lang.Object get(java.lang.String, java.lang.String, java.lang.String, java.lang.String);
    Code:
       0: aload_0
       1: getfield      #6                  // Field cache:Lorg/sonatype/aether/RepositoryCache;
       4: aload_0
       5: getfield      #5                  // Field session:Lorg/sonatype/aether/RepositorySystemSession;
       8: new           #7                  // class org/apache/maven/repository/internal/DefaultModelCache$Key
      11: dup
      12: aload_1
      13: aload_2
      14: aload_3
      15: aload         4
      17: invokespecial #8                  // Method org/apache/maven/repository/internal/DefaultModelCache$Key."<init>":(Ljava/lang/String;Ljava/lang/String;Ljava/lang/String;Ljava/lang/String;)V
      20: invokeinterface #9,  3            // InterfaceMethod org/sonatype/aether/RepositoryCache.get:(Lorg/sonatype/aether/RepositorySystemSession;Ljava/lang/Object;)Ljava/lang/Object;
      25: areturn

  public void put(java.lang.String, java.lang.String, java.lang.String, java.lang.String, java.lang.Object);
    Code:
       0: aload_0
       1: getfield      #6                  // Field cache:Lorg/sonatype/aether/RepositoryCache;
       4: aload_0
       5: getfield      #5                  // Field session:Lorg/sonatype/aether/RepositorySystemSession;
       8: new           #7                  // class org/apache/maven/repository/internal/DefaultModelCache$Key
      11: dup
      12: aload_1
      13: aload_2
      14: aload_3
      15: aload         4
      17: invokespecial #8                  // Method org/apache/maven/repository/internal/DefaultModelCache$Key."<init>":(Ljava/lang/String;Ljava/lang/String;Ljava/lang/String;Ljava/lang/String;)V
      20: aload         5
      22: invokeinterface #10,  4           // InterfaceMethod org/sonatype/aether/RepositoryCache.put:(Lorg/sonatype/aether/RepositorySystemSession;Ljava/lang/Object;Ljava/lang/Object;)V
      27: return
}
