Compiled from "TracingAsyncClientHttpRequestInterceptor.java"
final class brave.spring.web.TracingAsyncClientHttpRequestInterceptor$TraceListenableFutureCallback implements org.springframework.util.concurrent.ListenableFutureCallback<org.springframework.http.client.ClientHttpResponse> {
  final brave.Span span;

  final brave.http.HttpClientHandler<org.springframework.http.HttpRequest, org.springframework.http.client.ClientHttpResponse> handler;

  brave.spring.web.TracingAsyncClientHttpRequestInterceptor$TraceListenableFutureCallback(brave.Span, brave.http.HttpClientHandler<org.springframework.http.HttpRequest, org.springframework.http.client.ClientHttpResponse>);
    Code:
       0: aload_0
       1: invokespecial #22                 // Method java/lang/Object."<init>":()V
       4: aload_0
       5: aload_1
       6: putfield      #24                 // Field span:Lbrave/Span;
       9: aload_0
      10: aload_2
      11: putfield      #26                 // Field handler:Lbrave/http/HttpClientHandler;
      14: return

  public void onFailure(java.lang.Throwable);
    Code:
       0: aload_0
       1: getfield      #26                 // Field handler:Lbrave/http/HttpClientHandler;
       4: aconst_null
       5: aload_1
       6: aload_0
       7: getfield      #24                 // Field span:Lbrave/Span;
      10: invokevirtual #36                 // Method brave/http/HttpClientHandler.handleReceive:(Ljava/lang/Object;Ljava/lang/Throwable;Lbrave/Span;)V
      13: return

  public void onSuccess(org.springframework.http.client.ClientHttpResponse);
    Code:
       0: aload_0
       1: getfield      #26                 // Field handler:Lbrave/http/HttpClientHandler;
       4: aload_1
       5: aconst_null
       6: aload_0
       7: getfield      #24                 // Field span:Lbrave/Span;
      10: invokevirtual #36                 // Method brave/http/HttpClientHandler.handleReceive:(Ljava/lang/Object;Ljava/lang/Throwable;Lbrave/Span;)V
      13: return

  public void onSuccess(java.lang.Object);
    Code:
       0: aload_0
       1: aload_1
       2: checkcast     #45                 // class org/springframework/http/client/ClientHttpResponse
       5: invokevirtual #47                 // Method onSuccess:(Lorg/springframework/http/client/ClientHttpResponse;)V
       8: return
}
