Compiled from "EtypeInfo2Entry.java"
public class org.apache.kerby.kerberos.kerb.type.base.EtypeInfo2Entry extends org.apache.kerby.kerberos.kerb.type.KrbSequenceType {
  static org.apache.kerby.asn1.Asn1FieldInfo[] fieldInfos;

  public org.apache.kerby.kerberos.kerb.type.base.EtypeInfo2Entry();
    Code:
       0: aload_0
       1: getstatic     #1                  // Field fieldInfos:[Lorg/apache/kerby/asn1/Asn1FieldInfo;
       4: invokespecial #2                  // Method org/apache/kerby/kerberos/kerb/type/KrbSequenceType."<init>":([Lorg/apache/kerby/asn1/Asn1FieldInfo;)V
       7: return

  public org.apache.kerby.kerberos.kerb.type.base.EncryptionType getEtype();
    Code:
       0: aload_0
       1: getstatic     #3                  // Field org/apache/kerby/kerberos/kerb/type/base/EtypeInfo2Entry$EtypeInfo2EntryField.ETYPE:Lorg/apache/kerby/kerberos/kerb/type/base/EtypeInfo2Entry$EtypeInfo2EntryField;
       4: invokevirtual #4                  // Method getFieldAsInt:(Lorg/apache/kerby/asn1/EnumType;)I
       7: invokestatic  #5                  // Method java/lang/Integer.valueOf:(I)Ljava/lang/Integer;
      10: invokestatic  #6                  // Method org/apache/kerby/kerberos/kerb/type/base/EncryptionType.fromValue:(Ljava/lang/Integer;)Lorg/apache/kerby/kerberos/kerb/type/base/EncryptionType;
      13: areturn

  public void setEtype(org.apache.kerby.kerberos.kerb.type.base.EncryptionType);
    Code:
       0: aload_0
       1: getstatic     #3                  // Field org/apache/kerby/kerberos/kerb/type/base/EtypeInfo2Entry$EtypeInfo2EntryField.ETYPE:Lorg/apache/kerby/kerberos/kerb/type/base/EtypeInfo2Entry$EtypeInfo2EntryField;
       4: aload_1
       5: invokevirtual #7                  // Method setField:(Lorg/apache/kerby/asn1/EnumType;Lorg/apache/kerby/asn1/EnumType;)V
       8: return

  public java.lang.String getSalt();
    Code:
       0: aload_0
       1: getstatic     #8                  // Field org/apache/kerby/kerberos/kerb/type/base/EtypeInfo2Entry$EtypeInfo2EntryField.SALT:Lorg/apache/kerby/kerberos/kerb/type/base/EtypeInfo2Entry$EtypeInfo2EntryField;
       4: invokevirtual #9                  // Method getFieldAsString:(Lorg/apache/kerby/asn1/EnumType;)Ljava/lang/String;
       7: areturn

  public void setSalt(java.lang.String);
    Code:
       0: aload_0
       1: getstatic     #8                  // Field org/apache/kerby/kerberos/kerb/type/base/EtypeInfo2Entry$EtypeInfo2EntryField.SALT:Lorg/apache/kerby/kerberos/kerb/type/base/EtypeInfo2Entry$EtypeInfo2EntryField;
       4: aload_1
       5: invokevirtual #10                 // Method setFieldAsString:(Lorg/apache/kerby/asn1/EnumType;Ljava/lang/String;)V
       8: return

  public byte[] getS2kParams();
    Code:
       0: aload_0
       1: getstatic     #11                 // Field org/apache/kerby/kerberos/kerb/type/base/EtypeInfo2Entry$EtypeInfo2EntryField.S2KPARAMS:Lorg/apache/kerby/kerberos/kerb/type/base/EtypeInfo2Entry$EtypeInfo2EntryField;
       4: invokevirtual #12                 // Method getFieldAsOctets:(Lorg/apache/kerby/asn1/EnumType;)[B
       7: areturn

  public void setS2kParams(byte[]);
    Code:
       0: aload_0
       1: getstatic     #11                 // Field org/apache/kerby/kerberos/kerb/type/base/EtypeInfo2Entry$EtypeInfo2EntryField.S2KPARAMS:Lorg/apache/kerby/kerberos/kerb/type/base/EtypeInfo2Entry$EtypeInfo2EntryField;
       4: aload_1
       5: invokevirtual #13                 // Method setFieldAsOctets:(Lorg/apache/kerby/asn1/EnumType;[B)V
       8: return

  static {};
    Code:
       0: iconst_3
       1: anewarray     #14                 // class org/apache/kerby/asn1/Asn1FieldInfo
       4: dup
       5: iconst_0
       6: new           #15                 // class org/apache/kerby/asn1/ExplicitField
       9: dup
      10: getstatic     #3                  // Field org/apache/kerby/kerberos/kerb/type/base/EtypeInfo2Entry$EtypeInfo2EntryField.ETYPE:Lorg/apache/kerby/kerberos/kerb/type/base/EtypeInfo2Entry$EtypeInfo2EntryField;
      13: ldc_w         #16                 // class org/apache/kerby/asn1/type/Asn1Integer
      16: invokespecial #17                 // Method org/apache/kerby/asn1/ExplicitField."<init>":(Lorg/apache/kerby/asn1/EnumType;Ljava/lang/Class;)V
      19: aastore
      20: dup
      21: iconst_1
      22: new           #15                 // class org/apache/kerby/asn1/ExplicitField
      25: dup
      26: getstatic     #8                  // Field org/apache/kerby/kerberos/kerb/type/base/EtypeInfo2Entry$EtypeInfo2EntryField.SALT:Lorg/apache/kerby/kerberos/kerb/type/base/EtypeInfo2Entry$EtypeInfo2EntryField;
      29: ldc_w         #18                 // class org/apache/kerby/kerberos/kerb/type/KerberosString
      32: invokespecial #17                 // Method org/apache/kerby/asn1/ExplicitField."<init>":(Lorg/apache/kerby/asn1/EnumType;Ljava/lang/Class;)V
      35: aastore
      36: dup
      37: iconst_2
      38: new           #15                 // class org/apache/kerby/asn1/ExplicitField
      41: dup
      42: getstatic     #11                 // Field org/apache/kerby/kerberos/kerb/type/base/EtypeInfo2Entry$EtypeInfo2EntryField.S2KPARAMS:Lorg/apache/kerby/kerberos/kerb/type/base/EtypeInfo2Entry$EtypeInfo2EntryField;
      45: ldc_w         #19                 // class org/apache/kerby/asn1/type/Asn1OctetString
      48: invokespecial #17                 // Method org/apache/kerby/asn1/ExplicitField."<init>":(Lorg/apache/kerby/asn1/EnumType;Ljava/lang/Class;)V
      51: aastore
      52: putstatic     #1                  // Field fieldInfos:[Lorg/apache/kerby/asn1/Asn1FieldInfo;
      55: return
}
