Compiled from "Coeval.scala"
public final class monix.eval.Coeval$$anonfun$2$$anonfun$apply$8 extends scala.runtime.AbstractFunction2<scala.collection.mutable.Builder<A, M>, A, scala.collection.mutable.Builder<A, M>> implements scala.Serializable {
  public static final long serialVersionUID;

  public final scala.collection.mutable.Builder<A, M> apply(scala.collection.mutable.Builder<A, M>, A);
    Code:
       0: aload_1
       1: aload_2
       2: invokeinterface #22,  2           // InterfaceMethod scala/collection/mutable/Builder.$plus$eq:(Ljava/lang/Object;)Lscala/collection/mutable/Builder;
       7: areturn

  public final java.lang.Object apply(java.lang.Object, java.lang.Object);
    Code:
       0: aload_0
       1: aload_1
       2: checkcast     #18                 // class scala/collection/mutable/Builder
       5: aload_2
       6: invokevirtual #31                 // Method apply:(Lscala/collection/mutable/Builder;Ljava/lang/Object;)Lscala/collection/mutable/Builder;
       9: areturn

  public monix.eval.Coeval$$anonfun$2$$anonfun$apply$8(monix.eval.Coeval$$anonfun$2);
    Code:
       0: aload_0
       1: invokespecial #38                 // Method scala/runtime/AbstractFunction2."<init>":()V
       4: return
}
