Compiled from "Task.scala"
public final class monix.eval.Task$$anonfun$mapBoth$1$$anon$34 implements java.lang.Runnable {
  private final monix.eval.Task$$anonfun$mapBoth$1 $outer;

  public final monix.execution.Scheduler scheduler$11;

  public final monix.execution.cancelables.StackedCancelable conn$14;

  public final monix.eval.Callback cb$14;

  public void run();
    Code:
       0: getstatic     #25                 // Field monix/execution/atomic/AtomicBuilder$.MODULE$:Lmonix/execution/atomic/AtomicBuilder$;
       3: invokevirtual #29                 // Method monix/execution/atomic/AtomicBuilder$.AtomicRefBuilder:()Lmonix/execution/atomic/AtomicBuilder;
       6: aconst_null
       7: getstatic     #34                 // Field monix/execution/atomic/PaddingStrategy$NoPadding$.MODULE$:Lmonix/execution/atomic/PaddingStrategy$NoPadding$;
      10: invokeinterface #40,  3           // InterfaceMethod monix/execution/atomic/AtomicBuilder.buildInstance:(Ljava/lang/Object;Lmonix/execution/atomic/PaddingStrategy;)Lmonix/execution/atomic/Atomic;
      15: checkcast     #42                 // class monix/execution/atomic/AtomicAny
      18: astore_1
      19: getstatic     #47                 // Field monix/execution/cancelables/StackedCancelable$.MODULE$:Lmonix/execution/cancelables/StackedCancelable$;
      22: invokevirtual #51                 // Method monix/execution/cancelables/StackedCancelable$.apply:()Lmonix/execution/cancelables/StackedCancelable;
      25: astore_2
      26: getstatic     #47                 // Field monix/execution/cancelables/StackedCancelable$.MODULE$:Lmonix/execution/cancelables/StackedCancelable$;
      29: invokevirtual #51                 // Method monix/execution/cancelables/StackedCancelable$.apply:()Lmonix/execution/cancelables/StackedCancelable;
      32: astore_3
      33: aload_0
      34: getfield      #53                 // Field conn$14:Lmonix/execution/cancelables/StackedCancelable;
      37: getstatic     #58                 // Field monix/execution/cancelables/CompositeCancelable$.MODULE$:Lmonix/execution/cancelables/CompositeCancelable$;
      40: getstatic     #63                 // Field scala/Predef$.MODULE$:Lscala/Predef$;
      43: iconst_2
      44: anewarray     #65                 // class monix/execution/Cancelable
      47: dup
      48: iconst_0
      49: aload_2
      50: aastore
      51: dup
      52: iconst_1
      53: aload_3
      54: aastore
      55: invokevirtual #69                 // Method scala/Predef$.genericWrapArray:(Ljava/lang/Object;)Lscala/collection/mutable/WrappedArray;
      58: invokevirtual #72                 // Method monix/execution/cancelables/CompositeCancelable$.apply:(Lscala/collection/Seq;)Lmonix/execution/cancelables/CompositeCancelable;
      61: invokevirtual #78                 // Method monix/execution/cancelables/StackedCancelable.push:(Lmonix/execution/Cancelable;)V
      64: aload_0
      65: getfield      #80                 // Field scheduler$11:Lmonix/execution/Scheduler;
      68: new           #82                 // class monix/eval/Task$$anonfun$mapBoth$1$$anon$34$$anon$25
      71: dup
      72: aload_0
      73: aload_1
      74: aload_2
      75: invokespecial #86                 // Method monix/eval/Task$$anonfun$mapBoth$1$$anon$34$$anon$25."<init>":(Lmonix/eval/Task$$anonfun$mapBoth$1$$anon$34;Lmonix/execution/atomic/AtomicAny;Lmonix/execution/cancelables/StackedCancelable;)V
      78: invokevirtual #92                 // Method monix/execution/Scheduler.execute:(Ljava/lang/Runnable;)V
      81: aload_0
      82: getfield      #80                 // Field scheduler$11:Lmonix/execution/Scheduler;
      85: new           #94                 // class monix/eval/Task$$anonfun$mapBoth$1$$anon$34$$anon$26
      88: dup
      89: aload_0
      90: aload_1
      91: aload_3
      92: invokespecial #95                 // Method monix/eval/Task$$anonfun$mapBoth$1$$anon$34$$anon$26."<init>":(Lmonix/eval/Task$$anonfun$mapBoth$1$$anon$34;Lmonix/execution/atomic/AtomicAny;Lmonix/execution/cancelables/StackedCancelable;)V
      95: invokevirtual #92                 // Method monix/execution/Scheduler.execute:(Ljava/lang/Runnable;)V
      98: return

  public monix.eval.Task$$anonfun$mapBoth$1 monix$eval$Task$$anonfun$$anon$$$outer();
    Code:
       0: aload_0
       1: getfield      #105                // Field $outer:Lmonix/eval/Task$$anonfun$mapBoth$1;
       4: areturn

  public monix.eval.Task$$anonfun$mapBoth$1$$anon$34(monix.eval.Task$$anonfun$mapBoth$1, monix.execution.Scheduler, monix.execution.cancelables.StackedCancelable, monix.eval.Callback);
    Code:
       0: aload_1
       1: ifnonnull     6
       4: aconst_null
       5: athrow
       6: aload_0
       7: aload_1
       8: putfield      #105                // Field $outer:Lmonix/eval/Task$$anonfun$mapBoth$1;
      11: aload_0
      12: aload_2
      13: putfield      #80                 // Field scheduler$11:Lmonix/execution/Scheduler;
      16: aload_0
      17: aload_3
      18: putfield      #53                 // Field conn$14:Lmonix/execution/cancelables/StackedCancelable;
      21: aload_0
      22: aload         4
      24: putfield      #108                // Field cb$14:Lmonix/eval/Callback;
      27: aload_0
      28: invokespecial #110                // Method java/lang/Object."<init>":()V
      31: return
}
