Compiled from "WSSConfig.java"
public class org.apache.wss4j.dom.engine.WSSConfig {
  public static final javax.xml.datatype.DatatypeFactory datatypeFactory;

  private static final org.slf4j.Logger LOG;

  private static final java.util.Map<java.lang.Integer, java.lang.Class<?>> DEFAULT_ACTIONS;

  private static final java.util.Map<javax.xml.namespace.QName, java.lang.Class<?>> DEFAULT_PROCESSORS;

  private static final java.util.Map<javax.xml.namespace.QName, java.lang.Class<?>> DEFAULT_VALIDATORS;

  private static boolean addJceProviders;

  private static boolean staticallyInitialized;

  private org.apache.wss4j.common.util.WSTimeSource currentTime;

  public static final org.apache.wss4j.dom.WsuIdAllocator DEFAULT_ID_ALLOCATOR;

  protected org.apache.wss4j.dom.WsuIdAllocator idAllocator;

  private final java.util.Map<java.lang.Integer, java.lang.Object> actionMap;

  private final java.util.Map<javax.xml.namespace.QName, java.lang.Object> processorMap;

  private final java.util.Map<javax.xml.namespace.QName, java.lang.Object> validatorMap;

  private org.apache.wss4j.dom.engine.WSSConfig();
    Code:
       0: aload_0
       1: invokespecial #1                  // Method java/lang/Object."<init>":()V
       4: aload_0
       5: getstatic     #2                  // Field DEFAULT_ID_ALLOCATOR:Lorg/apache/wss4j/dom/WsuIdAllocator;
       8: putfield      #3                  // Field idAllocator:Lorg/apache/wss4j/dom/WsuIdAllocator;
      11: aload_0
      12: new           #4                  // class java/util/HashMap
      15: dup
      16: getstatic     #5                  // Field DEFAULT_ACTIONS:Ljava/util/Map;
      19: invokespecial #6                  // Method java/util/HashMap."<init>":(Ljava/util/Map;)V
      22: putfield      #7                  // Field actionMap:Ljava/util/Map;
      25: aload_0
      26: new           #4                  // class java/util/HashMap
      29: dup
      30: getstatic     #8                  // Field DEFAULT_PROCESSORS:Ljava/util/Map;
      33: invokespecial #6                  // Method java/util/HashMap."<init>":(Ljava/util/Map;)V
      36: putfield      #9                  // Field processorMap:Ljava/util/Map;
      39: aload_0
      40: new           #4                  // class java/util/HashMap
      43: dup
      44: getstatic     #10                 // Field DEFAULT_VALIDATORS:Ljava/util/Map;
      47: invokespecial #6                  // Method java/util/HashMap."<init>":(Ljava/util/Map;)V
      50: putfield      #11                 // Field validatorMap:Ljava/util/Map;
      53: return

  public static synchronized void init();
    Code:
       0: getstatic     #12                 // Field staticallyInitialized:Z
       3: ifne          30
       6: getstatic     #13                 // Field addJceProviders:Z
       9: ifeq          23
      12: new           #14                 // class org/apache/wss4j/dom/engine/WSSConfig$2
      15: dup
      16: invokespecial #15                 // Method org/apache/wss4j/dom/engine/WSSConfig$2."<init>":()V
      19: invokestatic  #16                 // Method java/security/AccessController.doPrivileged:(Ljava/security/PrivilegedAction;)Ljava/lang/Object;
      22: pop
      23: invokestatic  #17                 // Method org/apache/wss4j/common/crypto/WSProviderConfig.init:()V
      26: iconst_1
      27: putstatic     #12                 // Field staticallyInitialized:Z
      30: return

  public static org.apache.wss4j.dom.engine.WSSConfig getNewInstance();
    Code:
       0: invokestatic  #18                 // Method init:()V
       3: new           #19                 // class org/apache/wss4j/dom/engine/WSSConfig
       6: dup
       7: invokespecial #20                 // Method "<init>":()V
      10: areturn

  public org.apache.wss4j.dom.WsuIdAllocator getIdAllocator();
    Code:
       0: aload_0
       1: getfield      #3                  // Field idAllocator:Lorg/apache/wss4j/dom/WsuIdAllocator;
       4: areturn

  public void setIdAllocator(org.apache.wss4j.dom.WsuIdAllocator);
    Code:
       0: aload_0
       1: aload_1
       2: putfield      #3                  // Field idAllocator:Lorg/apache/wss4j/dom/WsuIdAllocator;
       5: return

  public java.lang.Class<?> setAction(int, org.apache.wss4j.dom.action.Action);
    Code:
       0: aload_0
       1: getfield      #7                  // Field actionMap:Ljava/util/Map;
       4: iload_1
       5: invokestatic  #21                 // Method java/lang/Integer.valueOf:(I)Ljava/lang/Integer;
       8: aload_2
       9: invokeinterface #22,  3           // InterfaceMethod java/util/Map.put:(Ljava/lang/Object;Ljava/lang/Object;)Ljava/lang/Object;
      14: astore_3
      15: aload_3
      16: instanceof    #23                 // class java/lang/Class
      19: ifeq          27
      22: aload_3
      23: checkcast     #23                 // class java/lang/Class
      26: areturn
      27: aload_3
      28: instanceof    #24                 // class org/apache/wss4j/dom/action/Action
      31: ifeq          39
      34: aload_3
      35: invokevirtual #25                 // Method java/lang/Object.getClass:()Ljava/lang/Class;
      38: areturn
      39: aconst_null
      40: areturn

  public java.lang.Class<?> setAction(int, java.lang.Class<?>);
    Code:
       0: aload_0
       1: getfield      #7                  // Field actionMap:Ljava/util/Map;
       4: iload_1
       5: invokestatic  #21                 // Method java/lang/Integer.valueOf:(I)Ljava/lang/Integer;
       8: aload_2
       9: invokeinterface #22,  3           // InterfaceMethod java/util/Map.put:(Ljava/lang/Object;Ljava/lang/Object;)Ljava/lang/Object;
      14: astore_3
      15: aload_3
      16: instanceof    #23                 // class java/lang/Class
      19: ifeq          27
      22: aload_3
      23: checkcast     #23                 // class java/lang/Class
      26: areturn
      27: aload_3
      28: instanceof    #24                 // class org/apache/wss4j/dom/action/Action
      31: ifeq          39
      34: aload_3
      35: invokevirtual #25                 // Method java/lang/Object.getClass:()Ljava/lang/Class;
      38: areturn
      39: aconst_null
      40: areturn

  public org.apache.wss4j.dom.action.Action getAction(int) throws org.apache.wss4j.common.ext.WSSecurityException;
    Code:
       0: aload_0
       1: getfield      #7                  // Field actionMap:Ljava/util/Map;
       4: iload_1
       5: invokestatic  #21                 // Method java/lang/Integer.valueOf:(I)Ljava/lang/Integer;
       8: invokeinterface #26,  2           // InterfaceMethod java/util/Map.get:(Ljava/lang/Object;)Ljava/lang/Object;
      13: astore_2
      14: aload_2
      15: instanceof    #23                 // class java/lang/Class
      18: ifeq          85
      21: aload_2
      22: checkcast     #23                 // class java/lang/Class
      25: invokevirtual #27                 // Method java/lang/Class.newInstance:()Ljava/lang/Object;
      28: checkcast     #24                 // class org/apache/wss4j/dom/action/Action
      31: areturn
      32: astore_3
      33: getstatic     #29                 // Field LOG:Lorg/slf4j/Logger;
      36: invokeinterface #30,  1           // InterfaceMethod org/slf4j/Logger.isDebugEnabled:()Z
      41: ifeq          57
      44: getstatic     #29                 // Field LOG:Lorg/slf4j/Logger;
      47: aload_3
      48: invokevirtual #31                 // Method java/lang/Exception.getMessage:()Ljava/lang/String;
      51: aload_3
      52: invokeinterface #32,  3           // InterfaceMethod org/slf4j/Logger.debug:(Ljava/lang/String;Ljava/lang/Throwable;)V
      57: new           #33                 // class org/apache/wss4j/common/ext/WSSecurityException
      60: dup
      61: getstatic     #34                 // Field org/apache/wss4j/common/ext/WSSecurityException$ErrorCode.FAILURE:Lorg/apache/wss4j/common/ext/WSSecurityException$ErrorCode;
      64: aload_3
      65: ldc           #35                 // String unableToLoadClass
      67: iconst_1
      68: anewarray     #36                 // class java/lang/Object
      71: dup
      72: iconst_0
      73: aload_2
      74: checkcast     #23                 // class java/lang/Class
      77: invokevirtual #37                 // Method java/lang/Class.getName:()Ljava/lang/String;
      80: aastore
      81: invokespecial #38                 // Method org/apache/wss4j/common/ext/WSSecurityException."<init>":(Lorg/apache/wss4j/common/ext/WSSecurityException$ErrorCode;Ljava/lang/Exception;Ljava/lang/String;[Ljava/lang/Object;)V
      84: athrow
      85: aload_2
      86: instanceof    #24                 // class org/apache/wss4j/dom/action/Action
      89: ifeq          97
      92: aload_2
      93: checkcast     #24                 // class org/apache/wss4j/dom/action/Action
      96: areturn
      97: aconst_null
      98: areturn
    Exception table:
       from    to  target type
          21    31    32   Class java/lang/Exception

  public java.lang.Class<?> setProcessor(javax.xml.namespace.QName, org.apache.wss4j.dom.processor.Processor);
    Code:
       0: aload_0
       1: getfield      #9                  // Field processorMap:Ljava/util/Map;
       4: aload_1
       5: aload_2
       6: invokeinterface #22,  3           // InterfaceMethod java/util/Map.put:(Ljava/lang/Object;Ljava/lang/Object;)Ljava/lang/Object;
      11: astore_3
      12: aload_3
      13: instanceof    #23                 // class java/lang/Class
      16: ifeq          24
      19: aload_3
      20: checkcast     #23                 // class java/lang/Class
      23: areturn
      24: aload_3
      25: instanceof    #39                 // class org/apache/wss4j/dom/processor/Processor
      28: ifeq          36
      31: aload_3
      32: invokevirtual #25                 // Method java/lang/Object.getClass:()Ljava/lang/Class;
      35: areturn
      36: aconst_null
      37: areturn

  public java.lang.Class<?> setProcessor(javax.xml.namespace.QName, java.lang.Class<?>);
    Code:
       0: aload_0
       1: getfield      #9                  // Field processorMap:Ljava/util/Map;
       4: aload_1
       5: aload_2
       6: invokeinterface #22,  3           // InterfaceMethod java/util/Map.put:(Ljava/lang/Object;Ljava/lang/Object;)Ljava/lang/Object;
      11: astore_3
      12: aload_3
      13: instanceof    #23                 // class java/lang/Class
      16: ifeq          24
      19: aload_3
      20: checkcast     #23                 // class java/lang/Class
      23: areturn
      24: aload_3
      25: instanceof    #39                 // class org/apache/wss4j/dom/processor/Processor
      28: ifeq          36
      31: aload_3
      32: invokevirtual #25                 // Method java/lang/Object.getClass:()Ljava/lang/Class;
      35: areturn
      36: aconst_null
      37: areturn

  public java.lang.Class<?> setValidator(javax.xml.namespace.QName, org.apache.wss4j.dom.validate.Validator);
    Code:
       0: aload_0
       1: getfield      #11                 // Field validatorMap:Ljava/util/Map;
       4: aload_1
       5: aload_2
       6: invokeinterface #22,  3           // InterfaceMethod java/util/Map.put:(Ljava/lang/Object;Ljava/lang/Object;)Ljava/lang/Object;
      11: astore_3
      12: aload_3
      13: instanceof    #23                 // class java/lang/Class
      16: ifeq          24
      19: aload_3
      20: checkcast     #23                 // class java/lang/Class
      23: areturn
      24: aload_3
      25: instanceof    #40                 // class org/apache/wss4j/dom/validate/Validator
      28: ifeq          36
      31: aload_3
      32: invokevirtual #25                 // Method java/lang/Object.getClass:()Ljava/lang/Class;
      35: areturn
      36: aconst_null
      37: areturn

  public java.lang.Class<?> setValidator(javax.xml.namespace.QName, java.lang.Class<?>);
    Code:
       0: aload_0
       1: getfield      #11                 // Field validatorMap:Ljava/util/Map;
       4: aload_1
       5: aload_2
       6: invokeinterface #22,  3           // InterfaceMethod java/util/Map.put:(Ljava/lang/Object;Ljava/lang/Object;)Ljava/lang/Object;
      11: astore_3
      12: aload_3
      13: instanceof    #23                 // class java/lang/Class
      16: ifeq          24
      19: aload_3
      20: checkcast     #23                 // class java/lang/Class
      23: areturn
      24: aload_3
      25: instanceof    #40                 // class org/apache/wss4j/dom/validate/Validator
      28: ifeq          36
      31: aload_3
      32: invokevirtual #25                 // Method java/lang/Object.getClass:()Ljava/lang/Class;
      35: areturn
      36: aconst_null
      37: areturn

  public org.apache.wss4j.dom.validate.Validator getValidator(javax.xml.namespace.QName) throws org.apache.wss4j.common.ext.WSSecurityException;
    Code:
       0: aload_0
       1: getfield      #11                 // Field validatorMap:Ljava/util/Map;
       4: aload_1
       5: invokeinterface #26,  2           // InterfaceMethod java/util/Map.get:(Ljava/lang/Object;)Ljava/lang/Object;
      10: astore_2
      11: aload_2
      12: instanceof    #23                 // class java/lang/Class
      15: ifeq          82
      18: aload_2
      19: checkcast     #23                 // class java/lang/Class
      22: invokevirtual #27                 // Method java/lang/Class.newInstance:()Ljava/lang/Object;
      25: checkcast     #40                 // class org/apache/wss4j/dom/validate/Validator
      28: areturn
      29: astore_3
      30: getstatic     #29                 // Field LOG:Lorg/slf4j/Logger;
      33: invokeinterface #30,  1           // InterfaceMethod org/slf4j/Logger.isDebugEnabled:()Z
      38: ifeq          54
      41: getstatic     #29                 // Field LOG:Lorg/slf4j/Logger;
      44: aload_3
      45: invokevirtual #31                 // Method java/lang/Exception.getMessage:()Ljava/lang/String;
      48: aload_3
      49: invokeinterface #32,  3           // InterfaceMethod org/slf4j/Logger.debug:(Ljava/lang/String;Ljava/lang/Throwable;)V
      54: new           #33                 // class org/apache/wss4j/common/ext/WSSecurityException
      57: dup
      58: getstatic     #34                 // Field org/apache/wss4j/common/ext/WSSecurityException$ErrorCode.FAILURE:Lorg/apache/wss4j/common/ext/WSSecurityException$ErrorCode;
      61: aload_3
      62: ldc           #35                 // String unableToLoadClass
      64: iconst_1
      65: anewarray     #36                 // class java/lang/Object
      68: dup
      69: iconst_0
      70: aload_2
      71: checkcast     #23                 // class java/lang/Class
      74: invokevirtual #37                 // Method java/lang/Class.getName:()Ljava/lang/String;
      77: aastore
      78: invokespecial #38                 // Method org/apache/wss4j/common/ext/WSSecurityException."<init>":(Lorg/apache/wss4j/common/ext/WSSecurityException$ErrorCode;Ljava/lang/Exception;Ljava/lang/String;[Ljava/lang/Object;)V
      81: athrow
      82: aload_2
      83: instanceof    #40                 // class org/apache/wss4j/dom/validate/Validator
      86: ifeq          94
      89: aload_2
      90: checkcast     #40                 // class org/apache/wss4j/dom/validate/Validator
      93: areturn
      94: aconst_null
      95: areturn
    Exception table:
       from    to  target type
          18    28    29   Class java/lang/Exception

  public org.apache.wss4j.dom.processor.Processor getProcessor(javax.xml.namespace.QName) throws org.apache.wss4j.common.ext.WSSecurityException;
    Code:
       0: aload_0
       1: getfield      #9                  // Field processorMap:Ljava/util/Map;
       4: aload_1
       5: invokeinterface #26,  2           // InterfaceMethod java/util/Map.get:(Ljava/lang/Object;)Ljava/lang/Object;
      10: astore_2
      11: aload_2
      12: instanceof    #23                 // class java/lang/Class
      15: ifeq          82
      18: aload_2
      19: checkcast     #23                 // class java/lang/Class
      22: invokevirtual #27                 // Method java/lang/Class.newInstance:()Ljava/lang/Object;
      25: checkcast     #39                 // class org/apache/wss4j/dom/processor/Processor
      28: areturn
      29: astore_3
      30: getstatic     #29                 // Field LOG:Lorg/slf4j/Logger;
      33: invokeinterface #30,  1           // InterfaceMethod org/slf4j/Logger.isDebugEnabled:()Z
      38: ifeq          54
      41: getstatic     #29                 // Field LOG:Lorg/slf4j/Logger;
      44: aload_3
      45: invokevirtual #31                 // Method java/lang/Exception.getMessage:()Ljava/lang/String;
      48: aload_3
      49: invokeinterface #32,  3           // InterfaceMethod org/slf4j/Logger.debug:(Ljava/lang/String;Ljava/lang/Throwable;)V
      54: new           #33                 // class org/apache/wss4j/common/ext/WSSecurityException
      57: dup
      58: getstatic     #34                 // Field org/apache/wss4j/common/ext/WSSecurityException$ErrorCode.FAILURE:Lorg/apache/wss4j/common/ext/WSSecurityException$ErrorCode;
      61: aload_3
      62: ldc           #35                 // String unableToLoadClass
      64: iconst_1
      65: anewarray     #36                 // class java/lang/Object
      68: dup
      69: iconst_0
      70: aload_2
      71: checkcast     #23                 // class java/lang/Class
      74: invokevirtual #37                 // Method java/lang/Class.getName:()Ljava/lang/String;
      77: aastore
      78: invokespecial #38                 // Method org/apache/wss4j/common/ext/WSSecurityException."<init>":(Lorg/apache/wss4j/common/ext/WSSecurityException$ErrorCode;Ljava/lang/Exception;Ljava/lang/String;[Ljava/lang/Object;)V
      81: athrow
      82: aload_2
      83: instanceof    #39                 // class org/apache/wss4j/dom/processor/Processor
      86: ifeq          94
      89: aload_2
      90: checkcast     #39                 // class org/apache/wss4j/dom/processor/Processor
      93: areturn
      94: aconst_null
      95: areturn
    Exception table:
       from    to  target type
          18    28    29   Class java/lang/Exception

  public org.apache.wss4j.common.util.WSTimeSource getCurrentTime();
    Code:
       0: aload_0
       1: getfield      #41                 // Field currentTime:Lorg/apache/wss4j/common/util/WSTimeSource;
       4: ifnull        12
       7: aload_0
       8: getfield      #41                 // Field currentTime:Lorg/apache/wss4j/common/util/WSTimeSource;
      11: areturn
      12: new           #42                 // class org/apache/wss4j/common/util/WSCurrentTimeSource
      15: dup
      16: invokespecial #43                 // Method org/apache/wss4j/common/util/WSCurrentTimeSource."<init>":()V
      19: areturn

  public void setCurrentTime(org.apache.wss4j.common.util.WSTimeSource);
    Code:
       0: aload_0
       1: aload_1
       2: putfield      #41                 // Field currentTime:Lorg/apache/wss4j/common/util/WSTimeSource;
       5: return

  public static boolean isAddJceProviders();
    Code:
       0: getstatic     #13                 // Field addJceProviders:Z
       3: ireturn

  public static void setAddJceProviders(boolean);
    Code:
       0: iload_0
       1: putstatic     #13                 // Field addJceProviders:Z
       4: iload_0
       5: invokestatic  #44                 // Method org/apache/wss4j/common/crypto/WSProviderConfig.setAddJceProviders:(Z)V
       8: return

  static {};
    Code:
       0: invokestatic  #45                 // Method javax/xml/datatype/DatatypeFactory.newInstance:()Ljavax/xml/datatype/DatatypeFactory;
       3: putstatic     #46                 // Field datatypeFactory:Ljavax/xml/datatype/DatatypeFactory;
       6: goto          19
       9: astore_0
      10: new           #48                 // class java/lang/RuntimeException
      13: dup
      14: aload_0
      15: invokespecial #49                 // Method java/lang/RuntimeException."<init>":(Ljava/lang/Throwable;)V
      18: athrow
      19: ldc_w         #19                 // class org/apache/wss4j/dom/engine/WSSConfig
      22: invokestatic  #50                 // Method org/slf4j/LoggerFactory.getLogger:(Ljava/lang/Class;)Lorg/slf4j/Logger;
      25: putstatic     #29                 // Field LOG:Lorg/slf4j/Logger;
      28: new           #4                  // class java/util/HashMap
      31: dup
      32: invokespecial #51                 // Method java/util/HashMap."<init>":()V
      35: astore_0
      36: aload_0
      37: iconst_1
      38: invokestatic  #21                 // Method java/lang/Integer.valueOf:(I)Ljava/lang/Integer;
      41: ldc_w         #52                 // class org/apache/wss4j/dom/action/UsernameTokenAction
      44: invokeinterface #22,  3           // InterfaceMethod java/util/Map.put:(Ljava/lang/Object;Ljava/lang/Object;)Ljava/lang/Object;
      49: pop
      50: aload_0
      51: iconst_4
      52: invokestatic  #21                 // Method java/lang/Integer.valueOf:(I)Ljava/lang/Integer;
      55: ldc_w         #53                 // class org/apache/wss4j/dom/action/EncryptionAction
      58: invokeinterface #22,  3           // InterfaceMethod java/util/Map.put:(Ljava/lang/Object;Ljava/lang/Object;)Ljava/lang/Object;
      63: pop
      64: aload_0
      65: iconst_2
      66: invokestatic  #21                 // Method java/lang/Integer.valueOf:(I)Ljava/lang/Integer;
      69: ldc_w         #54                 // class org/apache/wss4j/dom/action/SignatureAction
      72: invokeinterface #22,  3           // InterfaceMethod java/util/Map.put:(Ljava/lang/Object;Ljava/lang/Object;)Ljava/lang/Object;
      77: pop
      78: aload_0
      79: ldc           #55                 // int 32768
      81: invokestatic  #21                 // Method java/lang/Integer.valueOf:(I)Ljava/lang/Integer;
      84: ldc_w         #56                 // class org/apache/wss4j/dom/action/SignatureDerivedAction
      87: invokeinterface #22,  3           // InterfaceMethod java/util/Map.put:(Ljava/lang/Object;Ljava/lang/Object;)Ljava/lang/Object;
      92: pop
      93: aload_0
      94: ldc           #57                 // int 65536
      96: invokestatic  #21                 // Method java/lang/Integer.valueOf:(I)Ljava/lang/Integer;
      99: ldc_w         #58                 // class org/apache/wss4j/dom/action/EncryptionDerivedAction
     102: invokeinterface #22,  3           // InterfaceMethod java/util/Map.put:(Ljava/lang/Object;Ljava/lang/Object;)Ljava/lang/Object;
     107: pop
     108: aload_0
     109: bipush        16
     111: invokestatic  #21                 // Method java/lang/Integer.valueOf:(I)Ljava/lang/Integer;
     114: ldc_w         #59                 // class org/apache/wss4j/dom/action/SAMLTokenSignedAction
     117: invokeinterface #22,  3           // InterfaceMethod java/util/Map.put:(Ljava/lang/Object;Ljava/lang/Object;)Ljava/lang/Object;
     122: pop
     123: aload_0
     124: bipush        8
     126: invokestatic  #21                 // Method java/lang/Integer.valueOf:(I)Ljava/lang/Integer;
     129: ldc_w         #60                 // class org/apache/wss4j/dom/action/SAMLTokenUnsignedAction
     132: invokeinterface #22,  3           // InterfaceMethod java/util/Map.put:(Ljava/lang/Object;Ljava/lang/Object;)Ljava/lang/Object;
     137: pop
     138: aload_0
     139: bipush        32
     141: invokestatic  #21                 // Method java/lang/Integer.valueOf:(I)Ljava/lang/Integer;
     144: ldc_w         #61                 // class org/apache/wss4j/dom/action/TimestampAction
     147: invokeinterface #22,  3           // InterfaceMethod java/util/Map.put:(Ljava/lang/Object;Ljava/lang/Object;)Ljava/lang/Object;
     152: pop
     153: aload_0
     154: bipush        64
     156: invokestatic  #21                 // Method java/lang/Integer.valueOf:(I)Ljava/lang/Integer;
     159: ldc_w         #62                 // class org/apache/wss4j/dom/action/UsernameTokenSignedAction
     162: invokeinterface #22,  3           // InterfaceMethod java/util/Map.put:(Ljava/lang/Object;Ljava/lang/Object;)Ljava/lang/Object;
     167: pop
     168: aload_0
     169: sipush        128
     172: invokestatic  #21                 // Method java/lang/Integer.valueOf:(I)Ljava/lang/Integer;
     175: ldc_w         #63                 // class org/apache/wss4j/dom/action/SignatureConfirmationAction
     178: invokeinterface #22,  3           // InterfaceMethod java/util/Map.put:(Ljava/lang/Object;Ljava/lang/Object;)Ljava/lang/Object;
     183: pop
     184: aload_0
     185: sipush        16384
     188: invokestatic  #21                 // Method java/lang/Integer.valueOf:(I)Ljava/lang/Integer;
     191: ldc_w         #64                 // class org/apache/wss4j/dom/action/CustomTokenAction
     194: invokeinterface #22,  3           // InterfaceMethod java/util/Map.put:(Ljava/lang/Object;Ljava/lang/Object;)Ljava/lang/Object;
     199: pop
     200: goto          228
     203: astore_1
     204: getstatic     #29                 // Field LOG:Lorg/slf4j/Logger;
     207: invokeinterface #30,  1           // InterfaceMethod org/slf4j/Logger.isDebugEnabled:()Z
     212: ifeq          228
     215: getstatic     #29                 // Field LOG:Lorg/slf4j/Logger;
     218: aload_1
     219: invokevirtual #31                 // Method java/lang/Exception.getMessage:()Ljava/lang/String;
     222: aload_1
     223: invokeinterface #32,  3           // InterfaceMethod org/slf4j/Logger.debug:(Ljava/lang/String;Ljava/lang/Throwable;)V
     228: aload_0
     229: invokestatic  #65                 // Method java/util/Collections.unmodifiableMap:(Ljava/util/Map;)Ljava/util/Map;
     232: putstatic     #5                  // Field DEFAULT_ACTIONS:Ljava/util/Map;
     235: new           #4                  // class java/util/HashMap
     238: dup
     239: invokespecial #51                 // Method java/util/HashMap."<init>":()V
     242: astore_0
     243: aload_0
     244: getstatic     #66                 // Field org/apache/wss4j/dom/WSConstants.SAML_TOKEN:Ljavax/xml/namespace/QName;
     247: ldc_w         #67                 // class org/apache/wss4j/dom/processor/SAMLTokenProcessor
     250: invokeinterface #22,  3           // InterfaceMethod java/util/Map.put:(Ljava/lang/Object;Ljava/lang/Object;)Ljava/lang/Object;
     255: pop
     256: aload_0
     257: getstatic     #68                 // Field org/apache/wss4j/dom/WSConstants.SAML2_TOKEN:Ljavax/xml/namespace/QName;
     260: ldc_w         #67                 // class org/apache/wss4j/dom/processor/SAMLTokenProcessor
     263: invokeinterface #22,  3           // InterfaceMethod java/util/Map.put:(Ljava/lang/Object;Ljava/lang/Object;)Ljava/lang/Object;
     268: pop
     269: aload_0
     270: getstatic     #69                 // Field org/apache/wss4j/dom/WSConstants.ENCRYPTED_ASSERTION:Ljavax/xml/namespace/QName;
     273: ldc_w         #70                 // class org/apache/wss4j/dom/processor/EncryptedAssertionProcessor
     276: invokeinterface #22,  3           // InterfaceMethod java/util/Map.put:(Ljava/lang/Object;Ljava/lang/Object;)Ljava/lang/Object;
     281: pop
     282: aload_0
     283: getstatic     #71                 // Field org/apache/wss4j/dom/WSConstants.ENCRYPTED_KEY:Ljavax/xml/namespace/QName;
     286: ldc_w         #72                 // class org/apache/wss4j/dom/processor/EncryptedKeyProcessor
     289: invokeinterface #22,  3           // InterfaceMethod java/util/Map.put:(Ljava/lang/Object;Ljava/lang/Object;)Ljava/lang/Object;
     294: pop
     295: aload_0
     296: getstatic     #73                 // Field org/apache/wss4j/dom/WSConstants.SIGNATURE:Ljavax/xml/namespace/QName;
     299: ldc_w         #74                 // class org/apache/wss4j/dom/processor/SignatureProcessor
     302: invokeinterface #22,  3           // InterfaceMethod java/util/Map.put:(Ljava/lang/Object;Ljava/lang/Object;)Ljava/lang/Object;
     307: pop
     308: aload_0
     309: getstatic     #75                 // Field org/apache/wss4j/dom/WSConstants.TIMESTAMP:Ljavax/xml/namespace/QName;
     312: ldc_w         #76                 // class org/apache/wss4j/dom/processor/TimestampProcessor
     315: invokeinterface #22,  3           // InterfaceMethod java/util/Map.put:(Ljava/lang/Object;Ljava/lang/Object;)Ljava/lang/Object;
     320: pop
     321: aload_0
     322: getstatic     #77                 // Field org/apache/wss4j/dom/WSConstants.USERNAME_TOKEN:Ljavax/xml/namespace/QName;
     325: ldc_w         #78                 // class org/apache/wss4j/dom/processor/UsernameTokenProcessor
     328: invokeinterface #22,  3           // InterfaceMethod java/util/Map.put:(Ljava/lang/Object;Ljava/lang/Object;)Ljava/lang/Object;
     333: pop
     334: aload_0
     335: getstatic     #79                 // Field org/apache/wss4j/dom/WSConstants.REFERENCE_LIST:Ljavax/xml/namespace/QName;
     338: ldc_w         #80                 // class org/apache/wss4j/dom/processor/ReferenceListProcessor
     341: invokeinterface #22,  3           // InterfaceMethod java/util/Map.put:(Ljava/lang/Object;Ljava/lang/Object;)Ljava/lang/Object;
     346: pop
     347: aload_0
     348: getstatic     #81                 // Field org/apache/wss4j/dom/WSConstants.SIGNATURE_CONFIRMATION:Ljavax/xml/namespace/QName;
     351: ldc_w         #82                 // class org/apache/wss4j/dom/processor/SignatureConfirmationProcessor
     354: invokeinterface #22,  3           // InterfaceMethod java/util/Map.put:(Ljava/lang/Object;Ljava/lang/Object;)Ljava/lang/Object;
     359: pop
     360: aload_0
     361: getstatic     #83                 // Field org/apache/wss4j/dom/WSConstants.DERIVED_KEY_TOKEN_05_02:Ljavax/xml/namespace/QName;
     364: ldc_w         #84                 // class org/apache/wss4j/dom/processor/DerivedKeyTokenProcessor
     367: invokeinterface #22,  3           // InterfaceMethod java/util/Map.put:(Ljava/lang/Object;Ljava/lang/Object;)Ljava/lang/Object;
     372: pop
     373: aload_0
     374: getstatic     #85                 // Field org/apache/wss4j/dom/WSConstants.DERIVED_KEY_TOKEN_05_12:Ljavax/xml/namespace/QName;
     377: aload_0
     378: getstatic     #83                 // Field org/apache/wss4j/dom/WSConstants.DERIVED_KEY_TOKEN_05_02:Ljavax/xml/namespace/QName;
     381: invokeinterface #26,  2           // InterfaceMethod java/util/Map.get:(Ljava/lang/Object;)Ljava/lang/Object;
     386: invokeinterface #22,  3           // InterfaceMethod java/util/Map.put:(Ljava/lang/Object;Ljava/lang/Object;)Ljava/lang/Object;
     391: pop
     392: aload_0
     393: getstatic     #86                 // Field org/apache/wss4j/dom/WSConstants.SECURITY_CONTEXT_TOKEN_05_02:Ljavax/xml/namespace/QName;
     396: ldc_w         #87                 // class org/apache/wss4j/dom/processor/SecurityContextTokenProcessor
     399: invokeinterface #22,  3           // InterfaceMethod java/util/Map.put:(Ljava/lang/Object;Ljava/lang/Object;)Ljava/lang/Object;
     404: pop
     405: aload_0
     406: getstatic     #88                 // Field org/apache/wss4j/dom/WSConstants.SECURITY_CONTEXT_TOKEN_05_12:Ljavax/xml/namespace/QName;
     409: aload_0
     410: getstatic     #86                 // Field org/apache/wss4j/dom/WSConstants.SECURITY_CONTEXT_TOKEN_05_02:Ljavax/xml/namespace/QName;
     413: invokeinterface #26,  2           // InterfaceMethod java/util/Map.get:(Ljava/lang/Object;)Ljava/lang/Object;
     418: invokeinterface #22,  3           // InterfaceMethod java/util/Map.put:(Ljava/lang/Object;Ljava/lang/Object;)Ljava/lang/Object;
     423: pop
     424: aload_0
     425: getstatic     #89                 // Field org/apache/wss4j/dom/WSConstants.BINARY_TOKEN:Ljavax/xml/namespace/QName;
     428: ldc_w         #90                 // class org/apache/wss4j/dom/processor/BinarySecurityTokenProcessor
     431: invokeinterface #22,  3           // InterfaceMethod java/util/Map.put:(Ljava/lang/Object;Ljava/lang/Object;)Ljava/lang/Object;
     436: pop
     437: aload_0
     438: getstatic     #91                 // Field org/apache/wss4j/dom/WSConstants.ENCRYPTED_DATA:Ljavax/xml/namespace/QName;
     441: ldc_w         #92                 // class org/apache/wss4j/dom/processor/EncryptedDataProcessor
     444: invokeinterface #22,  3           // InterfaceMethod java/util/Map.put:(Ljava/lang/Object;Ljava/lang/Object;)Ljava/lang/Object;
     449: pop
     450: goto          478
     453: astore_1
     454: getstatic     #29                 // Field LOG:Lorg/slf4j/Logger;
     457: invokeinterface #30,  1           // InterfaceMethod org/slf4j/Logger.isDebugEnabled:()Z
     462: ifeq          478
     465: getstatic     #29                 // Field LOG:Lorg/slf4j/Logger;
     468: aload_1
     469: invokevirtual #31                 // Method java/lang/Exception.getMessage:()Ljava/lang/String;
     472: aload_1
     473: invokeinterface #32,  3           // InterfaceMethod org/slf4j/Logger.debug:(Ljava/lang/String;Ljava/lang/Throwable;)V
     478: aload_0
     479: invokestatic  #65                 // Method java/util/Collections.unmodifiableMap:(Ljava/util/Map;)Ljava/util/Map;
     482: putstatic     #8                  // Field DEFAULT_PROCESSORS:Ljava/util/Map;
     485: new           #4                  // class java/util/HashMap
     488: dup
     489: invokespecial #51                 // Method java/util/HashMap."<init>":()V
     492: astore_0
     493: aload_0
     494: getstatic     #66                 // Field org/apache/wss4j/dom/WSConstants.SAML_TOKEN:Ljavax/xml/namespace/QName;
     497: ldc_w         #93                 // class org/apache/wss4j/dom/validate/SamlAssertionValidator
     500: invokeinterface #22,  3           // InterfaceMethod java/util/Map.put:(Ljava/lang/Object;Ljava/lang/Object;)Ljava/lang/Object;
     505: pop
     506: aload_0
     507: getstatic     #68                 // Field org/apache/wss4j/dom/WSConstants.SAML2_TOKEN:Ljavax/xml/namespace/QName;
     510: ldc_w         #93                 // class org/apache/wss4j/dom/validate/SamlAssertionValidator
     513: invokeinterface #22,  3           // InterfaceMethod java/util/Map.put:(Ljava/lang/Object;Ljava/lang/Object;)Ljava/lang/Object;
     518: pop
     519: aload_0
     520: getstatic     #73                 // Field org/apache/wss4j/dom/WSConstants.SIGNATURE:Ljavax/xml/namespace/QName;
     523: ldc_w         #94                 // class org/apache/wss4j/dom/validate/SignatureTrustValidator
     526: invokeinterface #22,  3           // InterfaceMethod java/util/Map.put:(Ljava/lang/Object;Ljava/lang/Object;)Ljava/lang/Object;
     531: pop
     532: aload_0
     533: getstatic     #75                 // Field org/apache/wss4j/dom/WSConstants.TIMESTAMP:Ljavax/xml/namespace/QName;
     536: ldc_w         #95                 // class org/apache/wss4j/dom/validate/TimestampValidator
     539: invokeinterface #22,  3           // InterfaceMethod java/util/Map.put:(Ljava/lang/Object;Ljava/lang/Object;)Ljava/lang/Object;
     544: pop
     545: aload_0
     546: getstatic     #77                 // Field org/apache/wss4j/dom/WSConstants.USERNAME_TOKEN:Ljavax/xml/namespace/QName;
     549: ldc_w         #96                 // class org/apache/wss4j/dom/validate/UsernameTokenValidator
     552: invokeinterface #22,  3           // InterfaceMethod java/util/Map.put:(Ljava/lang/Object;Ljava/lang/Object;)Ljava/lang/Object;
     557: pop
     558: goto          586
     561: astore_1
     562: getstatic     #29                 // Field LOG:Lorg/slf4j/Logger;
     565: invokeinterface #30,  1           // InterfaceMethod org/slf4j/Logger.isDebugEnabled:()Z
     570: ifeq          586
     573: getstatic     #29                 // Field LOG:Lorg/slf4j/Logger;
     576: aload_1
     577: invokevirtual #31                 // Method java/lang/Exception.getMessage:()Ljava/lang/String;
     580: aload_1
     581: invokeinterface #32,  3           // InterfaceMethod org/slf4j/Logger.debug:(Ljava/lang/String;Ljava/lang/Throwable;)V
     586: aload_0
     587: invokestatic  #65                 // Method java/util/Collections.unmodifiableMap:(Ljava/util/Map;)Ljava/util/Map;
     590: putstatic     #10                 // Field DEFAULT_VALIDATORS:Ljava/util/Map;
     593: iconst_1
     594: putstatic     #13                 // Field addJceProviders:Z
     597: iconst_0
     598: putstatic     #12                 // Field staticallyInitialized:Z
     601: new           #97                 // class org/apache/wss4j/dom/engine/WSSConfig$1
     604: dup
     605: invokespecial #98                 // Method org/apache/wss4j/dom/engine/WSSConfig$1."<init>":()V
     608: putstatic     #2                  // Field DEFAULT_ID_ALLOCATOR:Lorg/apache/wss4j/dom/WsuIdAllocator;
     611: ldc           #99                 // String http://docs.oasis-open.org/wss/oasis-wss-SwAProfile-1.1#Attachment-Ciphertext-Transform
     613: ldc_w         #100                // class org/apache/wss4j/dom/transform/AttachmentCiphertextTransform
     616: invokestatic  #101                // Method org/apache/xml/security/transforms/Transform.register:(Ljava/lang/String;Ljava/lang/Class;)V
     619: goto          647
     622: astore_0
     623: getstatic     #29                 // Field LOG:Lorg/slf4j/Logger;
     626: invokeinterface #30,  1           // InterfaceMethod org/slf4j/Logger.isDebugEnabled:()Z
     631: ifeq          647
     634: getstatic     #29                 // Field LOG:Lorg/slf4j/Logger;
     637: aload_0
     638: invokevirtual #31                 // Method java/lang/Exception.getMessage:()Ljava/lang/String;
     641: aload_0
     642: invokeinterface #32,  3           // InterfaceMethod org/slf4j/Logger.debug:(Ljava/lang/String;Ljava/lang/Throwable;)V
     647: new           #102                // class org/apache/wss4j/dom/resolvers/ResolverAttachment
     650: dup
     651: invokespecial #103                // Method org/apache/wss4j/dom/resolvers/ResolverAttachment."<init>":()V
     654: iconst_0
     655: invokestatic  #104                // Method org/apache/xml/security/utils/resolver/ResourceResolver.register:(Lorg/apache/xml/security/utils/resolver/ResourceResolverSpi;Z)V
     658: return
    Exception table:
       from    to  target type
           0     6     9   Class javax/xml/datatype/DatatypeConfigurationException
          36   200   203   Class java/lang/Exception
         243   450   453   Class java/lang/Exception
         493   558   561   Class java/lang/Exception
         611   619   622   Class java/lang/Exception
}
