Compiled from "ErrorPattern.java"
public class org.kohsuke.rngom.binary.ErrorPattern extends org.kohsuke.rngom.binary.Pattern {
  org.kohsuke.rngom.binary.ErrorPattern();
    Code:
       0: aload_0
       1: iconst_0
       2: iconst_0
       3: iconst_3
       4: invokespecial #1                  // Method org/kohsuke/rngom/binary/Pattern."<init>":(ZII)V
       7: return

  boolean samePattern(org.kohsuke.rngom.binary.Pattern);
    Code:
       0: aload_1
       1: instanceof    #2                  // class org/kohsuke/rngom/binary/ErrorPattern
       4: ireturn

  public void accept(org.kohsuke.rngom.binary.visitor.PatternVisitor);
    Code:
       0: aload_1
       1: invokeinterface #3,  1            // InterfaceMethod org/kohsuke/rngom/binary/visitor/PatternVisitor.visitError:()V
       6: return

  public java.lang.Object apply(org.kohsuke.rngom.binary.visitor.PatternFunction);
    Code:
       0: aload_1
       1: aload_0
       2: invokeinterface #4,  2            // InterfaceMethod org/kohsuke/rngom/binary/visitor/PatternFunction.caseError:(Lorg/kohsuke/rngom/binary/ErrorPattern;)Ljava/lang/Object;
       7: areturn
}
