Compiled from "Ordering.scala"
public class scala.math.Ordering$Float$ implements scala.math.Ordering$FloatOrdering {
  public static final scala.math.Ordering$Float$ MODULE$;

  public static {};
    Code:
       0: new           #2                  // class scala/math/Ordering$Float$
       3: invokespecial #14                 // Method "<init>":()V
       6: return

  public int compare(float, float);
    Code:
       0: aload_0
       1: fload_1
       2: fload_2
       3: invokestatic  #21                 // Method scala/math/Ordering$FloatOrdering$class.compare:(Lscala/math/Ordering$FloatOrdering;FF)I
       6: ireturn

  public boolean lteq(float, float);
    Code:
       0: aload_0
       1: fload_1
       2: fload_2
       3: invokestatic  #30                 // Method scala/math/Ordering$FloatOrdering$class.lteq:(Lscala/math/Ordering$FloatOrdering;FF)Z
       6: ireturn

  public boolean gteq(float, float);
    Code:
       0: aload_0
       1: fload_1
       2: fload_2
       3: invokestatic  #33                 // Method scala/math/Ordering$FloatOrdering$class.gteq:(Lscala/math/Ordering$FloatOrdering;FF)Z
       6: ireturn

  public boolean lt(float, float);
    Code:
       0: aload_0
       1: fload_1
       2: fload_2
       3: invokestatic  #36                 // Method scala/math/Ordering$FloatOrdering$class.lt:(Lscala/math/Ordering$FloatOrdering;FF)Z
       6: ireturn

  public boolean gt(float, float);
    Code:
       0: aload_0
       1: fload_1
       2: fload_2
       3: invokestatic  #39                 // Method scala/math/Ordering$FloatOrdering$class.gt:(Lscala/math/Ordering$FloatOrdering;FF)Z
       6: ireturn

  public boolean equiv(float, float);
    Code:
       0: aload_0
       1: fload_1
       2: fload_2
       3: invokestatic  #42                 // Method scala/math/Ordering$FloatOrdering$class.equiv:(Lscala/math/Ordering$FloatOrdering;FF)Z
       6: ireturn

  public float max(float, float);
    Code:
       0: aload_0
       1: fload_1
       2: fload_2
       3: invokestatic  #47                 // Method scala/math/Ordering$FloatOrdering$class.max:(Lscala/math/Ordering$FloatOrdering;FF)F
       6: freturn

  public float min(float, float);
    Code:
       0: aload_0
       1: fload_1
       2: fload_2
       3: invokestatic  #50                 // Method scala/math/Ordering$FloatOrdering$class.min:(Lscala/math/Ordering$FloatOrdering;FF)F
       6: freturn

  public scala.math.Ordering<java.lang.Object> reverse();
    Code:
       0: aload_0
       1: invokestatic  #55                 // Method scala/math/Ordering$FloatOrdering$class.reverse:(Lscala/math/Ordering$FloatOrdering;)Lscala/math/Ordering;
       4: areturn

  public scala.Some tryCompare(java.lang.Object, java.lang.Object);
    Code:
       0: aload_0
       1: aload_1
       2: aload_2
       3: invokestatic  #62                 // Method scala/math/Ordering$class.tryCompare:(Lscala/math/Ordering;Ljava/lang/Object;Ljava/lang/Object;)Lscala/Some;
       6: areturn

  public <U> scala.math.Ordering<U> on(scala.Function1<U, java.lang.Object>);
    Code:
       0: aload_0
       1: aload_1
       2: invokestatic  #68                 // Method scala/math/Ordering$class.on:(Lscala/math/Ordering;Lscala/Function1;)Lscala/math/Ordering;
       5: areturn

  public scala.math.Ordering$Ops mkOrderingOps(java.lang.Object);
    Code:
       0: aload_0
       1: aload_1
       2: invokestatic  #75                 // Method scala/math/Ordering$class.mkOrderingOps:(Lscala/math/Ordering;Ljava/lang/Object;)Lscala/math/Ordering$Ops;
       5: areturn

  private java.lang.Object readResolve();
    Code:
       0: getstatic     #80                 // Field MODULE$:Lscala/math/Ordering$Float$;
       3: areturn

  public scala.Option tryCompare(java.lang.Object, java.lang.Object);
    Code:
       0: aload_0
       1: aload_1
       2: aload_2
       3: invokevirtual #83                 // Method tryCompare:(Ljava/lang/Object;Ljava/lang/Object;)Lscala/Some;
       6: areturn

  public scala.math.PartialOrdering reverse();
    Code:
       0: aload_0
       1: invokevirtual #86                 // Method reverse:()Lscala/math/Ordering;
       4: areturn

  public java.lang.Object min(java.lang.Object, java.lang.Object);
    Code:
       0: aload_0
       1: aload_1
       2: invokestatic  #93                 // Method scala/runtime/BoxesRunTime.unboxToFloat:(Ljava/lang/Object;)F
       5: aload_2
       6: invokestatic  #93                 // Method scala/runtime/BoxesRunTime.unboxToFloat:(Ljava/lang/Object;)F
       9: invokevirtual #95                 // Method min:(FF)F
      12: invokestatic  #99                 // Method scala/runtime/BoxesRunTime.boxToFloat:(F)Ljava/lang/Float;
      15: areturn

  public java.lang.Object max(java.lang.Object, java.lang.Object);
    Code:
       0: aload_0
       1: aload_1
       2: invokestatic  #93                 // Method scala/runtime/BoxesRunTime.unboxToFloat:(Ljava/lang/Object;)F
       5: aload_2
       6: invokestatic  #93                 // Method scala/runtime/BoxesRunTime.unboxToFloat:(Ljava/lang/Object;)F
       9: invokevirtual #101                // Method max:(FF)F
      12: invokestatic  #99                 // Method scala/runtime/BoxesRunTime.boxToFloat:(F)Ljava/lang/Float;
      15: areturn

  public boolean equiv(java.lang.Object, java.lang.Object);
    Code:
       0: aload_0
       1: aload_1
       2: invokestatic  #93                 // Method scala/runtime/BoxesRunTime.unboxToFloat:(Ljava/lang/Object;)F
       5: aload_2
       6: invokestatic  #93                 // Method scala/runtime/BoxesRunTime.unboxToFloat:(Ljava/lang/Object;)F
       9: invokevirtual #104                // Method equiv:(FF)Z
      12: ireturn

  public boolean gt(java.lang.Object, java.lang.Object);
    Code:
       0: aload_0
       1: aload_1
       2: invokestatic  #93                 // Method scala/runtime/BoxesRunTime.unboxToFloat:(Ljava/lang/Object;)F
       5: aload_2
       6: invokestatic  #93                 // Method scala/runtime/BoxesRunTime.unboxToFloat:(Ljava/lang/Object;)F
       9: invokevirtual #106                // Method gt:(FF)Z
      12: ireturn

  public boolean lt(java.lang.Object, java.lang.Object);
    Code:
       0: aload_0
       1: aload_1
       2: invokestatic  #93                 // Method scala/runtime/BoxesRunTime.unboxToFloat:(Ljava/lang/Object;)F
       5: aload_2
       6: invokestatic  #93                 // Method scala/runtime/BoxesRunTime.unboxToFloat:(Ljava/lang/Object;)F
       9: invokevirtual #108                // Method lt:(FF)Z
      12: ireturn

  public boolean gteq(java.lang.Object, java.lang.Object);
    Code:
       0: aload_0
       1: aload_1
       2: invokestatic  #93                 // Method scala/runtime/BoxesRunTime.unboxToFloat:(Ljava/lang/Object;)F
       5: aload_2
       6: invokestatic  #93                 // Method scala/runtime/BoxesRunTime.unboxToFloat:(Ljava/lang/Object;)F
       9: invokevirtual #110                // Method gteq:(FF)Z
      12: ireturn

  public boolean lteq(java.lang.Object, java.lang.Object);
    Code:
       0: aload_0
       1: aload_1
       2: invokestatic  #93                 // Method scala/runtime/BoxesRunTime.unboxToFloat:(Ljava/lang/Object;)F
       5: aload_2
       6: invokestatic  #93                 // Method scala/runtime/BoxesRunTime.unboxToFloat:(Ljava/lang/Object;)F
       9: invokevirtual #112                // Method lteq:(FF)Z
      12: ireturn

  public int compare(java.lang.Object, java.lang.Object);
    Code:
       0: aload_0
       1: aload_1
       2: invokestatic  #93                 // Method scala/runtime/BoxesRunTime.unboxToFloat:(Ljava/lang/Object;)F
       5: aload_2
       6: invokestatic  #93                 // Method scala/runtime/BoxesRunTime.unboxToFloat:(Ljava/lang/Object;)F
       9: invokevirtual #115                // Method compare:(FF)I
      12: ireturn

  public scala.math.Ordering$Float$();
    Code:
       0: aload_0
       1: invokespecial #116                // Method java/lang/Object."<init>":()V
       4: aload_0
       5: putstatic     #80                 // Field MODULE$:Lscala/math/Ordering$Float$;
       8: aload_0
       9: invokestatic  #122                // Method scala/math/PartialOrdering$class.$init$:(Lscala/math/PartialOrdering;)V
      12: aload_0
      13: invokestatic  #125                // Method scala/math/Ordering$class.$init$:(Lscala/math/Ordering;)V
      16: aload_0
      17: invokestatic  #128                // Method scala/math/Ordering$FloatOrdering$class.$init$:(Lscala/math/Ordering$FloatOrdering;)V
      20: return
}
