Compiled from "Ordering.scala"
public abstract class scala.math.Ordering$DoubleOrdering$class {
  public static int compare(scala.math.Ordering$DoubleOrdering, double, double);
    Code:
       0: dload_1
       1: dload_3
       2: invokestatic  #12                 // Method java/lang/Double.compare:(DD)I
       5: ireturn

  public static boolean lteq(scala.math.Ordering$DoubleOrdering, double, double);
    Code:
       0: dload_1
       1: dload_3
       2: dcmpg
       3: ifgt          10
       6: iconst_1
       7: goto          11
      10: iconst_0
      11: ireturn

  public static boolean gteq(scala.math.Ordering$DoubleOrdering, double, double);
    Code:
       0: dload_1
       1: dload_3
       2: dcmpl
       3: iflt          10
       6: iconst_1
       7: goto          11
      10: iconst_0
      11: ireturn

  public static boolean lt(scala.math.Ordering$DoubleOrdering, double, double);
    Code:
       0: dload_1
       1: dload_3
       2: dcmpg
       3: ifge          10
       6: iconst_1
       7: goto          11
      10: iconst_0
      11: ireturn

  public static boolean gt(scala.math.Ordering$DoubleOrdering, double, double);
    Code:
       0: dload_1
       1: dload_3
       2: dcmpl
       3: ifle          10
       6: iconst_1
       7: goto          11
      10: iconst_0
      11: ireturn

  public static boolean equiv(scala.math.Ordering$DoubleOrdering, double, double);
    Code:
       0: dload_1
       1: dload_3
       2: dcmpl
       3: ifne          10
       6: iconst_1
       7: goto          11
      10: iconst_0
      11: ireturn

  public static double max(scala.math.Ordering$DoubleOrdering, double, double);
    Code:
       0: getstatic     #31                 // Field scala/math/package$.MODULE$:Lscala/math/package$;
       3: dload_1
       4: dload_3
       5: invokevirtual #34                 // Method scala/math/package$.max:(DD)D
       8: dreturn

  public static double min(scala.math.Ordering$DoubleOrdering, double, double);
    Code:
       0: getstatic     #31                 // Field scala/math/package$.MODULE$:Lscala/math/package$;
       3: dload_1
       4: dload_3
       5: invokevirtual #37                 // Method scala/math/package$.min:(DD)D
       8: dreturn

  public static scala.math.Ordering reverse(scala.math.Ordering$DoubleOrdering);
    Code:
       0: new           #41                 // class scala/math/Ordering$DoubleOrdering$$anon$2
       3: dup
       4: aload_0
       5: invokespecial #45                 // Method scala/math/Ordering$DoubleOrdering$$anon$2."<init>":(Lscala/math/Ordering$DoubleOrdering;)V
       8: areturn

  public static void $init$(scala.math.Ordering$DoubleOrdering);
    Code:
       0: return
}
