Compiled from "PathResourceDefinition.java"
class org.jboss.as.controller.services.path.PathResourceDefinition$SpecifiedNoServicesPathResourceDefinition extends org.jboss.as.controller.services.path.PathResourceDefinition {
  org.jboss.as.controller.services.path.PathResourceDefinition$SpecifiedNoServicesPathResourceDefinition(org.jboss.as.controller.services.path.PathManagerService, boolean);
    Code:
       0: aload_0
       1: aload_1
       2: iconst_1
       3: anewarray     #2                  // class java/lang/String
       6: dup
       7: iconst_0
       8: ldc           #3                  // String specified_path
      10: aastore
      11: invokestatic  #4                  // Method org/jboss/as/controller/descriptions/common/ControllerResolver.getResolver:([Ljava/lang/String;)Lorg/jboss/as/controller/descriptions/ResourceDescriptionResolver;
      14: aload_1
      15: invokestatic  #5                  // Method org/jboss/as/controller/services/path/PathAddHandler.createSpecifiedNoServicesInstance:(Lorg/jboss/as/controller/services/path/PathManagerService;)Lorg/jboss/as/controller/services/path/PathAddHandler;
      18: aload_1
      19: invokestatic  #6                  // Method org/jboss/as/controller/services/path/PathRemoveHandler.createSpecifiedNoServicesInstance:(Lorg/jboss/as/controller/services/path/PathManagerService;)Lorg/jboss/as/controller/services/path/PathRemoveHandler;
      22: iconst_1
      23: iconst_0
      24: iload_2
      25: aconst_null
      26: invokespecial #7                  // Method org/jboss/as/controller/services/path/PathResourceDefinition."<init>":(Lorg/jboss/as/controller/services/path/PathManagerService;Lorg/jboss/as/controller/descriptions/ResourceDescriptionResolver;Lorg/jboss/as/controller/services/path/PathAddHandler;Lorg/jboss/as/controller/services/path/PathRemoveHandler;ZZZLorg/jboss/as/controller/services/path/PathResourceDefinition$1;)V
      29: return
}
