Compiled from "NNTPClient.java"
public class org.apache.commons.net.nntp.NNTPClient extends org.apache.commons.net.nntp.NNTP {
  private static final org.apache.commons.net.nntp.NewsgroupInfo[] EMPTY_NEWSGROUP_INFO_ARRAY;

  public org.apache.commons.net.nntp.NNTPClient();
    Code:
       0: aload_0
       1: invokespecial #1                  // Method org/apache/commons/net/nntp/NNTP."<init>":()V
       4: return

  static org.apache.commons.net.nntp.Article parseArticleEntry(java.lang.String);
    Code:
       0: new           #2                  // class org/apache/commons/net/nntp/Article
       3: dup
       4: invokespecial #3                  // Method org/apache/commons/net/nntp/Article."<init>":()V
       7: astore_1
       8: aload_1
       9: aload_0
      10: invokevirtual #4                  // Method org/apache/commons/net/nntp/Article.setSubject:(Ljava/lang/String;)V
      13: aload_0
      14: ldc           #5                  // String \t
      16: invokevirtual #6                  // Method java/lang/String.split:(Ljava/lang/String;)[Ljava/lang/String;
      19: astore_2
      20: aload_2
      21: arraylength
      22: bipush        6
      24: if_icmple     97
      27: iconst_0
      28: istore_3
      29: aload_1
      30: aload_2
      31: iload_3
      32: iinc          3, 1
      35: aaload
      36: invokestatic  #7                  // Method java/lang/Long.parseLong:(Ljava/lang/String;)J
      39: invokevirtual #8                  // Method org/apache/commons/net/nntp/Article.setArticleNumber:(J)V
      42: aload_1
      43: aload_2
      44: iload_3
      45: iinc          3, 1
      48: aaload
      49: invokevirtual #4                  // Method org/apache/commons/net/nntp/Article.setSubject:(Ljava/lang/String;)V
      52: aload_1
      53: aload_2
      54: iload_3
      55: iinc          3, 1
      58: aaload
      59: invokevirtual #9                  // Method org/apache/commons/net/nntp/Article.setFrom:(Ljava/lang/String;)V
      62: aload_1
      63: aload_2
      64: iload_3
      65: iinc          3, 1
      68: aaload
      69: invokevirtual #10                 // Method org/apache/commons/net/nntp/Article.setDate:(Ljava/lang/String;)V
      72: aload_1
      73: aload_2
      74: iload_3
      75: iinc          3, 1
      78: aaload
      79: invokevirtual #11                 // Method org/apache/commons/net/nntp/Article.setArticleId:(Ljava/lang/String;)V
      82: aload_1
      83: aload_2
      84: iload_3
      85: iinc          3, 1
      88: aaload
      89: invokevirtual #12                 // Method org/apache/commons/net/nntp/Article.addReference:(Ljava/lang/String;)V
      92: goto          97
      95: astore        4
      97: aload_1
      98: areturn
    Exception table:
       from    to  target type
          29    92    95   Class java/lang/NumberFormatException

  private static void parseGroupReply(java.lang.String, org.apache.commons.net.nntp.NewsgroupInfo) throws org.apache.commons.net.MalformedServerReplyException;
    Code:
       0: aload_0
       1: ldc           #14                 // String
       3: invokevirtual #6                  // Method java/lang/String.split:(Ljava/lang/String;)[Ljava/lang/String;
       6: astore_2
       7: aload_2
       8: arraylength
       9: iconst_5
      10: if_icmplt     72
      13: iconst_1
      14: istore_3
      15: aload_1
      16: aload_2
      17: iload_3
      18: iinc          3, 1
      21: aaload
      22: invokestatic  #7                  // Method java/lang/Long.parseLong:(Ljava/lang/String;)J
      25: invokevirtual #15                 // Method org/apache/commons/net/nntp/NewsgroupInfo.setArticleCount:(J)V
      28: aload_1
      29: aload_2
      30: iload_3
      31: iinc          3, 1
      34: aaload
      35: invokestatic  #7                  // Method java/lang/Long.parseLong:(Ljava/lang/String;)J
      38: invokevirtual #16                 // Method org/apache/commons/net/nntp/NewsgroupInfo.setFirstArticle:(J)V
      41: aload_1
      42: aload_2
      43: iload_3
      44: iinc          3, 1
      47: aaload
      48: invokestatic  #7                  // Method java/lang/Long.parseLong:(Ljava/lang/String;)J
      51: invokevirtual #17                 // Method org/apache/commons/net/nntp/NewsgroupInfo.setLastArticle:(J)V
      54: aload_1
      55: aload_2
      56: iload_3
      57: iinc          3, 1
      60: aaload
      61: invokevirtual #18                 // Method org/apache/commons/net/nntp/NewsgroupInfo.setNewsgroup:(Ljava/lang/String;)V
      64: aload_1
      65: iconst_0
      66: invokevirtual #20                 // Method org/apache/commons/net/nntp/NewsgroupInfo.setPostingPermission:(I)V
      69: return
      70: astore        4
      72: new           #21                 // class org/apache/commons/net/MalformedServerReplyException
      75: dup
      76: new           #22                 // class java/lang/StringBuilder
      79: dup
      80: invokespecial #23                 // Method java/lang/StringBuilder."<init>":()V
      83: ldc           #24                 // String Could not parse newsgroup info.\nServer reply:
      85: invokevirtual #25                 // Method java/lang/StringBuilder.append:(Ljava/lang/String;)Ljava/lang/StringBuilder;
      88: aload_0
      89: invokevirtual #25                 // Method java/lang/StringBuilder.append:(Ljava/lang/String;)Ljava/lang/StringBuilder;
      92: invokevirtual #26                 // Method java/lang/StringBuilder.toString:()Ljava/lang/String;
      95: invokespecial #27                 // Method org/apache/commons/net/MalformedServerReplyException."<init>":(Ljava/lang/String;)V
      98: athrow
    Exception table:
       from    to  target type
          15    69    70   Class java/lang/NumberFormatException

  static org.apache.commons.net.nntp.NewsgroupInfo parseNewsgroupListEntry(java.lang.String);
    Code:
       0: aload_0
       1: ldc           #14                 // String
       3: invokevirtual #6                  // Method java/lang/String.split:(Ljava/lang/String;)[Ljava/lang/String;
       6: astore_1
       7: aload_1
       8: arraylength
       9: iconst_4
      10: if_icmpge     15
      13: aconst_null
      14: areturn
      15: new           #19                 // class org/apache/commons/net/nntp/NewsgroupInfo
      18: dup
      19: invokespecial #28                 // Method org/apache/commons/net/nntp/NewsgroupInfo."<init>":()V
      22: astore_2
      23: iconst_0
      24: istore_3
      25: aload_2
      26: aload_1
      27: iload_3
      28: iinc          3, 1
      31: aaload
      32: invokevirtual #18                 // Method org/apache/commons/net/nntp/NewsgroupInfo.setNewsgroup:(Ljava/lang/String;)V
      35: aload_1
      36: iload_3
      37: iinc          3, 1
      40: aaload
      41: invokestatic  #7                  // Method java/lang/Long.parseLong:(Ljava/lang/String;)J
      44: lstore        4
      46: aload_1
      47: iload_3
      48: iinc          3, 1
      51: aaload
      52: invokestatic  #7                  // Method java/lang/Long.parseLong:(Ljava/lang/String;)J
      55: lstore        6
      57: aload_2
      58: lload         6
      60: invokevirtual #16                 // Method org/apache/commons/net/nntp/NewsgroupInfo.setFirstArticle:(J)V
      63: aload_2
      64: lload         4
      66: invokevirtual #17                 // Method org/apache/commons/net/nntp/NewsgroupInfo.setLastArticle:(J)V
      69: lload         6
      71: lconst_0
      72: lcmp
      73: ifne          91
      76: lload         4
      78: lconst_0
      79: lcmp
      80: ifne          91
      83: aload_2
      84: lconst_0
      85: invokevirtual #15                 // Method org/apache/commons/net/nntp/NewsgroupInfo.setArticleCount:(J)V
      88: goto          102
      91: aload_2
      92: lload         4
      94: lload         6
      96: lsub
      97: lconst_1
      98: ladd
      99: invokevirtual #15                 // Method org/apache/commons/net/nntp/NewsgroupInfo.setArticleCount:(J)V
     102: goto          109
     105: astore        4
     107: aconst_null
     108: areturn
     109: aload_1
     110: iload_3
     111: iinc          3, 1
     114: aaload
     115: iconst_0
     116: invokevirtual #29                 // Method java/lang/String.charAt:(I)C
     119: lookupswitch  { // 6
                    77: 192
                    78: 184
                    89: 176
                   109: 192
                   110: 184
                   121: 176
               default: 200
          }
     176: aload_2
     177: iconst_2
     178: invokevirtual #20                 // Method org/apache/commons/net/nntp/NewsgroupInfo.setPostingPermission:(I)V
     181: goto          205
     184: aload_2
     185: iconst_3
     186: invokevirtual #20                 // Method org/apache/commons/net/nntp/NewsgroupInfo.setPostingPermission:(I)V
     189: goto          205
     192: aload_2
     193: iconst_1
     194: invokevirtual #20                 // Method org/apache/commons/net/nntp/NewsgroupInfo.setPostingPermission:(I)V
     197: goto          205
     200: aload_2
     201: iconst_0
     202: invokevirtual #20                 // Method org/apache/commons/net/nntp/NewsgroupInfo.setPostingPermission:(I)V
     205: aload_2
     206: areturn
    Exception table:
       from    to  target type
          35   102   105   Class java/lang/NumberFormatException

  private void ai2ap(org.apache.commons.net.nntp.ArticleInfo, org.apache.commons.net.nntp.ArticlePointer);
    Code:
       0: aload_2
       1: ifnull        21
       4: aload_2
       5: aload_1
       6: getfield      #30                 // Field org/apache/commons/net/nntp/ArticleInfo.articleId:Ljava/lang/String;
       9: putfield      #31                 // Field org/apache/commons/net/nntp/ArticlePointer.articleId:Ljava/lang/String;
      12: aload_2
      13: aload_1
      14: getfield      #32                 // Field org/apache/commons/net/nntp/ArticleInfo.articleNumber:J
      17: l2i
      18: putfield      #33                 // Field org/apache/commons/net/nntp/ArticlePointer.articleNumber:I
      21: return

  private org.apache.commons.net.nntp.ArticleInfo ap2ai(org.apache.commons.net.nntp.ArticlePointer);
    Code:
       0: aload_1
       1: ifnonnull     6
       4: aconst_null
       5: areturn
       6: new           #34                 // class org/apache/commons/net/nntp/ArticleInfo
       9: dup
      10: invokespecial #35                 // Method org/apache/commons/net/nntp/ArticleInfo."<init>":()V
      13: astore_2
      14: aload_2
      15: areturn

  public boolean authenticate(java.lang.String, java.lang.String) throws java.io.IOException;
    Code:
       0: aload_0
       1: aload_1
       2: invokevirtual #36                 // Method authinfoUser:(Ljava/lang/String;)I
       5: istore_3
       6: iload_3
       7: sipush        381
      10: if_icmpne     33
      13: aload_0
      14: aload_2
      15: invokevirtual #38                 // Method authinfoPass:(Ljava/lang/String;)I
      18: istore_3
      19: iload_3
      20: sipush        281
      23: if_icmpne     33
      26: aload_0
      27: iconst_1
      28: putfield      #39                 // Field _isAllowedToPost:Z
      31: iconst_1
      32: ireturn
      33: iconst_0
      34: ireturn

  public boolean completePendingCommand() throws java.io.IOException;
    Code:
       0: aload_0
       1: invokevirtual #40                 // Method getReply:()I
       4: invokestatic  #41                 // Method org/apache/commons/net/nntp/NNTPReply.isPositiveCompletion:(I)Z
       7: ireturn

  public java.io.Writer forwardArticle(java.lang.String) throws java.io.IOException;
    Code:
       0: aload_0
       1: aload_1
       2: invokevirtual #42                 // Method ihave:(Ljava/lang/String;)I
       5: invokestatic  #43                 // Method org/apache/commons/net/nntp/NNTPReply.isPositiveIntermediate:(I)Z
       8: ifne          13
      11: aconst_null
      12: areturn
      13: new           #44                 // class org/apache/commons/net/io/DotTerminatedMessageWriter
      16: dup
      17: aload_0
      18: getfield      #45                 // Field _writer_:Ljava/io/BufferedWriter;
      21: invokespecial #46                 // Method org/apache/commons/net/io/DotTerminatedMessageWriter."<init>":(Ljava/io/Writer;)V
      24: areturn

  public java.lang.Iterable<org.apache.commons.net.nntp.Article> iterateArticleInfo(long, long) throws java.io.IOException;
    Code:
       0: aload_0
       1: lload_1
       2: lload_3
       3: invokevirtual #47                 // Method retrieveArticleInfo:(JJ)Ljava/io/BufferedReader;
       6: astore        5
       8: aload         5
      10: ifnonnull     43
      13: new           #48                 // class java/io/IOException
      16: dup
      17: new           #22                 // class java/lang/StringBuilder
      20: dup
      21: invokespecial #23                 // Method java/lang/StringBuilder."<init>":()V
      24: ldc           #49                 // String XOVER command failed:
      26: invokevirtual #25                 // Method java/lang/StringBuilder.append:(Ljava/lang/String;)Ljava/lang/StringBuilder;
      29: aload_0
      30: invokevirtual #50                 // Method getReplyString:()Ljava/lang/String;
      33: invokevirtual #25                 // Method java/lang/StringBuilder.append:(Ljava/lang/String;)Ljava/lang/StringBuilder;
      36: invokevirtual #26                 // Method java/lang/StringBuilder.toString:()Ljava/lang/String;
      39: invokespecial #51                 // Method java/io/IOException."<init>":(Ljava/lang/String;)V
      42: athrow
      43: new           #52                 // class org/apache/commons/net/nntp/ArticleIterator
      46: dup
      47: new           #53                 // class org/apache/commons/net/nntp/ReplyIterator
      50: dup
      51: aload         5
      53: iconst_0
      54: invokespecial #54                 // Method org/apache/commons/net/nntp/ReplyIterator."<init>":(Ljava/io/BufferedReader;Z)V
      57: invokespecial #55                 // Method org/apache/commons/net/nntp/ArticleIterator."<init>":(Ljava/lang/Iterable;)V
      60: areturn

  public java.lang.Iterable<java.lang.String> iterateNewNews(org.apache.commons.net.nntp.NewGroupsOrNewsQuery) throws java.io.IOException;
    Code:
       0: aload_0
       1: aload_1
       2: invokevirtual #56                 // Method org/apache/commons/net/nntp/NewGroupsOrNewsQuery.getNewsgroups:()Ljava/lang/String;
       5: aload_1
       6: invokevirtual #57                 // Method org/apache/commons/net/nntp/NewGroupsOrNewsQuery.getDate:()Ljava/lang/String;
       9: aload_1
      10: invokevirtual #58                 // Method org/apache/commons/net/nntp/NewGroupsOrNewsQuery.getTime:()Ljava/lang/String;
      13: aload_1
      14: invokevirtual #59                 // Method org/apache/commons/net/nntp/NewGroupsOrNewsQuery.isGMT:()Z
      17: aload_1
      18: invokevirtual #60                 // Method org/apache/commons/net/nntp/NewGroupsOrNewsQuery.getDistributions:()Ljava/lang/String;
      21: invokevirtual #61                 // Method newnews:(Ljava/lang/String;Ljava/lang/String;Ljava/lang/String;ZLjava/lang/String;)I
      24: invokestatic  #41                 // Method org/apache/commons/net/nntp/NNTPReply.isPositiveCompletion:(I)Z
      27: ifeq          42
      30: new           #53                 // class org/apache/commons/net/nntp/ReplyIterator
      33: dup
      34: aload_0
      35: getfield      #62                 // Field _reader_:Ljava/io/BufferedReader;
      38: invokespecial #63                 // Method org/apache/commons/net/nntp/ReplyIterator."<init>":(Ljava/io/BufferedReader;)V
      41: areturn
      42: new           #48                 // class java/io/IOException
      45: dup
      46: new           #22                 // class java/lang/StringBuilder
      49: dup
      50: invokespecial #23                 // Method java/lang/StringBuilder."<init>":()V
      53: ldc           #64                 // String NEWNEWS command failed:
      55: invokevirtual #25                 // Method java/lang/StringBuilder.append:(Ljava/lang/String;)Ljava/lang/StringBuilder;
      58: aload_0
      59: invokevirtual #50                 // Method getReplyString:()Ljava/lang/String;
      62: invokevirtual #25                 // Method java/lang/StringBuilder.append:(Ljava/lang/String;)Ljava/lang/StringBuilder;
      65: invokevirtual #26                 // Method java/lang/StringBuilder.toString:()Ljava/lang/String;
      68: invokespecial #51                 // Method java/io/IOException."<init>":(Ljava/lang/String;)V
      71: athrow

  public java.lang.Iterable<java.lang.String> iterateNewNewsgroupListing(org.apache.commons.net.nntp.NewGroupsOrNewsQuery) throws java.io.IOException;
    Code:
       0: aload_0
       1: aload_1
       2: invokevirtual #57                 // Method org/apache/commons/net/nntp/NewGroupsOrNewsQuery.getDate:()Ljava/lang/String;
       5: aload_1
       6: invokevirtual #58                 // Method org/apache/commons/net/nntp/NewGroupsOrNewsQuery.getTime:()Ljava/lang/String;
       9: aload_1
      10: invokevirtual #59                 // Method org/apache/commons/net/nntp/NewGroupsOrNewsQuery.isGMT:()Z
      13: aload_1
      14: invokevirtual #60                 // Method org/apache/commons/net/nntp/NewGroupsOrNewsQuery.getDistributions:()Ljava/lang/String;
      17: invokevirtual #65                 // Method newgroups:(Ljava/lang/String;Ljava/lang/String;ZLjava/lang/String;)I
      20: invokestatic  #41                 // Method org/apache/commons/net/nntp/NNTPReply.isPositiveCompletion:(I)Z
      23: ifeq          38
      26: new           #53                 // class org/apache/commons/net/nntp/ReplyIterator
      29: dup
      30: aload_0
      31: getfield      #62                 // Field _reader_:Ljava/io/BufferedReader;
      34: invokespecial #63                 // Method org/apache/commons/net/nntp/ReplyIterator."<init>":(Ljava/io/BufferedReader;)V
      37: areturn
      38: new           #48                 // class java/io/IOException
      41: dup
      42: new           #22                 // class java/lang/StringBuilder
      45: dup
      46: invokespecial #23                 // Method java/lang/StringBuilder."<init>":()V
      49: ldc           #66                 // String NEWGROUPS command failed:
      51: invokevirtual #25                 // Method java/lang/StringBuilder.append:(Ljava/lang/String;)Ljava/lang/StringBuilder;
      54: aload_0
      55: invokevirtual #50                 // Method getReplyString:()Ljava/lang/String;
      58: invokevirtual #25                 // Method java/lang/StringBuilder.append:(Ljava/lang/String;)Ljava/lang/StringBuilder;
      61: invokevirtual #26                 // Method java/lang/StringBuilder.toString:()Ljava/lang/String;
      64: invokespecial #51                 // Method java/io/IOException."<init>":(Ljava/lang/String;)V
      67: athrow

  public java.lang.Iterable<org.apache.commons.net.nntp.NewsgroupInfo> iterateNewNewsgroups(org.apache.commons.net.nntp.NewGroupsOrNewsQuery) throws java.io.IOException;
    Code:
       0: new           #67                 // class org/apache/commons/net/nntp/NewsgroupIterator
       3: dup
       4: aload_0
       5: aload_1
       6: invokevirtual #68                 // Method iterateNewNewsgroupListing:(Lorg/apache/commons/net/nntp/NewGroupsOrNewsQuery;)Ljava/lang/Iterable;
       9: invokespecial #69                 // Method org/apache/commons/net/nntp/NewsgroupIterator."<init>":(Ljava/lang/Iterable;)V
      12: areturn

  public java.lang.Iterable<java.lang.String> iterateNewsgroupListing() throws java.io.IOException;
    Code:
       0: aload_0
       1: invokevirtual #70                 // Method list:()I
       4: invokestatic  #41                 // Method org/apache/commons/net/nntp/NNTPReply.isPositiveCompletion:(I)Z
       7: ifeq          22
      10: new           #53                 // class org/apache/commons/net/nntp/ReplyIterator
      13: dup
      14: aload_0
      15: getfield      #62                 // Field _reader_:Ljava/io/BufferedReader;
      18: invokespecial #63                 // Method org/apache/commons/net/nntp/ReplyIterator."<init>":(Ljava/io/BufferedReader;)V
      21: areturn
      22: new           #48                 // class java/io/IOException
      25: dup
      26: new           #22                 // class java/lang/StringBuilder
      29: dup
      30: invokespecial #23                 // Method java/lang/StringBuilder."<init>":()V
      33: ldc           #71                 // String LIST command failed:
      35: invokevirtual #25                 // Method java/lang/StringBuilder.append:(Ljava/lang/String;)Ljava/lang/StringBuilder;
      38: aload_0
      39: invokevirtual #50                 // Method getReplyString:()Ljava/lang/String;
      42: invokevirtual #25                 // Method java/lang/StringBuilder.append:(Ljava/lang/String;)Ljava/lang/StringBuilder;
      45: invokevirtual #26                 // Method java/lang/StringBuilder.toString:()Ljava/lang/String;
      48: invokespecial #51                 // Method java/io/IOException."<init>":(Ljava/lang/String;)V
      51: athrow

  public java.lang.Iterable<java.lang.String> iterateNewsgroupListing(java.lang.String) throws java.io.IOException;
    Code:
       0: aload_0
       1: aload_1
       2: invokevirtual #72                 // Method listActive:(Ljava/lang/String;)I
       5: invokestatic  #41                 // Method org/apache/commons/net/nntp/NNTPReply.isPositiveCompletion:(I)Z
       8: ifeq          23
      11: new           #53                 // class org/apache/commons/net/nntp/ReplyIterator
      14: dup
      15: aload_0
      16: getfield      #62                 // Field _reader_:Ljava/io/BufferedReader;
      19: invokespecial #63                 // Method org/apache/commons/net/nntp/ReplyIterator."<init>":(Ljava/io/BufferedReader;)V
      22: areturn
      23: new           #48                 // class java/io/IOException
      26: dup
      27: new           #22                 // class java/lang/StringBuilder
      30: dup
      31: invokespecial #23                 // Method java/lang/StringBuilder."<init>":()V
      34: ldc           #73                 // String LIST ACTIVE
      36: invokevirtual #25                 // Method java/lang/StringBuilder.append:(Ljava/lang/String;)Ljava/lang/StringBuilder;
      39: aload_1
      40: invokevirtual #25                 // Method java/lang/StringBuilder.append:(Ljava/lang/String;)Ljava/lang/StringBuilder;
      43: ldc           #74                 // String  command failed:
      45: invokevirtual #25                 // Method java/lang/StringBuilder.append:(Ljava/lang/String;)Ljava/lang/StringBuilder;
      48: aload_0
      49: invokevirtual #50                 // Method getReplyString:()Ljava/lang/String;
      52: invokevirtual #25                 // Method java/lang/StringBuilder.append:(Ljava/lang/String;)Ljava/lang/StringBuilder;
      55: invokevirtual #26                 // Method java/lang/StringBuilder.toString:()Ljava/lang/String;
      58: invokespecial #51                 // Method java/io/IOException."<init>":(Ljava/lang/String;)V
      61: athrow

  public java.lang.Iterable<org.apache.commons.net.nntp.NewsgroupInfo> iterateNewsgroups() throws java.io.IOException;
    Code:
       0: new           #67                 // class org/apache/commons/net/nntp/NewsgroupIterator
       3: dup
       4: aload_0
       5: invokevirtual #75                 // Method iterateNewsgroupListing:()Ljava/lang/Iterable;
       8: invokespecial #69                 // Method org/apache/commons/net/nntp/NewsgroupIterator."<init>":(Ljava/lang/Iterable;)V
      11: areturn

  public java.lang.Iterable<org.apache.commons.net.nntp.NewsgroupInfo> iterateNewsgroups(java.lang.String) throws java.io.IOException;
    Code:
       0: new           #67                 // class org/apache/commons/net/nntp/NewsgroupIterator
       3: dup
       4: aload_0
       5: aload_1
       6: invokevirtual #76                 // Method iterateNewsgroupListing:(Ljava/lang/String;)Ljava/lang/Iterable;
       9: invokespecial #69                 // Method org/apache/commons/net/nntp/NewsgroupIterator."<init>":(Ljava/lang/Iterable;)V
      12: areturn

  public java.lang.String listHelp() throws java.io.IOException;
    Code:
       0: aload_0
       1: invokevirtual #77                 // Method help:()I
       4: invokestatic  #78                 // Method org/apache/commons/net/nntp/NNTPReply.isInformational:(I)Z
       7: ifne          12
      10: aconst_null
      11: areturn
      12: new           #79                 // class java/io/StringWriter
      15: dup
      16: invokespecial #80                 // Method java/io/StringWriter."<init>":()V
      19: astore_1
      20: aconst_null
      21: astore_2
      22: new           #81                 // class org/apache/commons/net/io/DotTerminatedMessageReader
      25: dup
      26: aload_0
      27: getfield      #62                 // Field _reader_:Ljava/io/BufferedReader;
      30: invokespecial #82                 // Method org/apache/commons/net/io/DotTerminatedMessageReader."<init>":(Ljava/io/Reader;)V
      33: astore_3
      34: aconst_null
      35: astore        4
      37: aload_3
      38: aload_1
      39: invokestatic  #83                 // Method org/apache/commons/net/io/Util.copyReader:(Ljava/io/Reader;Ljava/io/Writer;)J
      42: pop2
      43: aload_1
      44: invokevirtual #84                 // Method java/io/StringWriter.toString:()Ljava/lang/String;
      47: astore        5
      49: aload_3
      50: ifnull        81
      53: aload         4
      55: ifnull        77
      58: aload_3
      59: invokevirtual #85                 // Method java/io/BufferedReader.close:()V
      62: goto          81
      65: astore        6
      67: aload         4
      69: aload         6
      71: invokevirtual #87                 // Method java/lang/Throwable.addSuppressed:(Ljava/lang/Throwable;)V
      74: goto          81
      77: aload_3
      78: invokevirtual #85                 // Method java/io/BufferedReader.close:()V
      81: aload_1
      82: ifnull        111
      85: aload_2
      86: ifnull        107
      89: aload_1
      90: invokevirtual #88                 // Method java/io/StringWriter.close:()V
      93: goto          111
      96: astore        6
      98: aload_2
      99: aload         6
     101: invokevirtual #87                 // Method java/lang/Throwable.addSuppressed:(Ljava/lang/Throwable;)V
     104: goto          111
     107: aload_1
     108: invokevirtual #88                 // Method java/io/StringWriter.close:()V
     111: aload         5
     113: areturn
     114: astore        5
     116: aload         5
     118: astore        4
     120: aload         5
     122: athrow
     123: astore        7
     125: aload_3
     126: ifnull        157
     129: aload         4
     131: ifnull        153
     134: aload_3
     135: invokevirtual #85                 // Method java/io/BufferedReader.close:()V
     138: goto          157
     141: astore        8
     143: aload         4
     145: aload         8
     147: invokevirtual #87                 // Method java/lang/Throwable.addSuppressed:(Ljava/lang/Throwable;)V
     150: goto          157
     153: aload_3
     154: invokevirtual #85                 // Method java/io/BufferedReader.close:()V
     157: aload         7
     159: athrow
     160: astore_3
     161: aload_3
     162: astore_2
     163: aload_3
     164: athrow
     165: astore        9
     167: aload_1
     168: ifnull        197
     171: aload_2
     172: ifnull        193
     175: aload_1
     176: invokevirtual #88                 // Method java/io/StringWriter.close:()V
     179: goto          197
     182: astore        10
     184: aload_2
     185: aload         10
     187: invokevirtual #87                 // Method java/lang/Throwable.addSuppressed:(Ljava/lang/Throwable;)V
     190: goto          197
     193: aload_1
     194: invokevirtual #88                 // Method java/io/StringWriter.close:()V
     197: aload         9
     199: athrow
    Exception table:
       from    to  target type
          58    62    65   Class java/lang/Throwable
          89    93    96   Class java/lang/Throwable
          37    49   114   Class java/lang/Throwable
          37    49   123   any
         134   138   141   Class java/lang/Throwable
         114   125   123   any
          22    81   160   Class java/lang/Throwable
         114   160   160   Class java/lang/Throwable
          22    81   165   any
         175   179   182   Class java/lang/Throwable
         114   167   165   any

  public java.lang.String[] listNewNews(org.apache.commons.net.nntp.NewGroupsOrNewsQuery) throws java.io.IOException;
    Code:
       0: aload_0
       1: aload_1
       2: invokevirtual #56                 // Method org/apache/commons/net/nntp/NewGroupsOrNewsQuery.getNewsgroups:()Ljava/lang/String;
       5: aload_1
       6: invokevirtual #57                 // Method org/apache/commons/net/nntp/NewGroupsOrNewsQuery.getDate:()Ljava/lang/String;
       9: aload_1
      10: invokevirtual #58                 // Method org/apache/commons/net/nntp/NewGroupsOrNewsQuery.getTime:()Ljava/lang/String;
      13: aload_1
      14: invokevirtual #59                 // Method org/apache/commons/net/nntp/NewGroupsOrNewsQuery.isGMT:()Z
      17: aload_1
      18: invokevirtual #60                 // Method org/apache/commons/net/nntp/NewGroupsOrNewsQuery.getDistributions:()Ljava/lang/String;
      21: invokevirtual #61                 // Method newnews:(Ljava/lang/String;Ljava/lang/String;Ljava/lang/String;ZLjava/lang/String;)I
      24: invokestatic  #41                 // Method org/apache/commons/net/nntp/NNTPReply.isPositiveCompletion:(I)Z
      27: ifne          32
      30: aconst_null
      31: areturn
      32: new           #89                 // class java/util/Vector
      35: dup
      36: invokespecial #90                 // Method java/util/Vector."<init>":()V
      39: astore_2
      40: new           #81                 // class org/apache/commons/net/io/DotTerminatedMessageReader
      43: dup
      44: aload_0
      45: getfield      #62                 // Field _reader_:Ljava/io/BufferedReader;
      48: invokespecial #82                 // Method org/apache/commons/net/io/DotTerminatedMessageReader."<init>":(Ljava/io/Reader;)V
      51: astore_3
      52: aconst_null
      53: astore        4
      55: aload_3
      56: invokevirtual #91                 // Method java/io/BufferedReader.readLine:()Ljava/lang/String;
      59: dup
      60: astore        5
      62: ifnull        74
      65: aload_2
      66: aload         5
      68: invokevirtual #92                 // Method java/util/Vector.addElement:(Ljava/lang/Object;)V
      71: goto          55
      74: aload_3
      75: ifnull        155
      78: aload         4
      80: ifnull        102
      83: aload_3
      84: invokevirtual #85                 // Method java/io/BufferedReader.close:()V
      87: goto          155
      90: astore        5
      92: aload         4
      94: aload         5
      96: invokevirtual #87                 // Method java/lang/Throwable.addSuppressed:(Ljava/lang/Throwable;)V
      99: goto          155
     102: aload_3
     103: invokevirtual #85                 // Method java/io/BufferedReader.close:()V
     106: goto          155
     109: astore        5
     111: aload         5
     113: astore        4
     115: aload         5
     117: athrow
     118: astore        6
     120: aload_3
     121: ifnull        152
     124: aload         4
     126: ifnull        148
     129: aload_3
     130: invokevirtual #85                 // Method java/io/BufferedReader.close:()V
     133: goto          152
     136: astore        7
     138: aload         4
     140: aload         7
     142: invokevirtual #87                 // Method java/lang/Throwable.addSuppressed:(Ljava/lang/Throwable;)V
     145: goto          152
     148: aload_3
     149: invokevirtual #85                 // Method java/io/BufferedReader.close:()V
     152: aload         6
     154: athrow
     155: aload_2
     156: invokevirtual #93                 // Method java/util/Vector.size:()I
     159: istore_3
     160: iload_3
     161: iconst_1
     162: if_icmpge     169
     165: getstatic     #94                 // Field org/apache/commons/net/util/NetConstants.EMPTY_STRING_ARRAY:[Ljava/lang/String;
     168: areturn
     169: iload_3
     170: anewarray     #95                 // class java/lang/String
     173: astore        4
     175: aload_2
     176: aload         4
     178: invokevirtual #96                 // Method java/util/Vector.copyInto:([Ljava/lang/Object;)V
     181: aload         4
     183: areturn
    Exception table:
       from    to  target type
          83    87    90   Class java/lang/Throwable
          55    74   109   Class java/lang/Throwable
          55    74   118   any
         129   133   136   Class java/lang/Throwable
         109   120   118   any

  public org.apache.commons.net.nntp.NewsgroupInfo[] listNewNewsgroups(org.apache.commons.net.nntp.NewGroupsOrNewsQuery) throws java.io.IOException;
    Code:
       0: aload_0
       1: aload_1
       2: invokevirtual #57                 // Method org/apache/commons/net/nntp/NewGroupsOrNewsQuery.getDate:()Ljava/lang/String;
       5: aload_1
       6: invokevirtual #58                 // Method org/apache/commons/net/nntp/NewGroupsOrNewsQuery.getTime:()Ljava/lang/String;
       9: aload_1
      10: invokevirtual #59                 // Method org/apache/commons/net/nntp/NewGroupsOrNewsQuery.isGMT:()Z
      13: aload_1
      14: invokevirtual #60                 // Method org/apache/commons/net/nntp/NewGroupsOrNewsQuery.getDistributions:()Ljava/lang/String;
      17: invokevirtual #65                 // Method newgroups:(Ljava/lang/String;Ljava/lang/String;ZLjava/lang/String;)I
      20: invokestatic  #41                 // Method org/apache/commons/net/nntp/NNTPReply.isPositiveCompletion:(I)Z
      23: ifne          28
      26: aconst_null
      27: areturn
      28: aload_0
      29: invokespecial #97                 // Method readNewsgroupListing:()[Lorg/apache/commons/net/nntp/NewsgroupInfo;
      32: areturn

  public org.apache.commons.net.nntp.NewsgroupInfo[] listNewsgroups() throws java.io.IOException;
    Code:
       0: aload_0
       1: invokevirtual #70                 // Method list:()I
       4: invokestatic  #41                 // Method org/apache/commons/net/nntp/NNTPReply.isPositiveCompletion:(I)Z
       7: ifne          12
      10: aconst_null
      11: areturn
      12: aload_0
      13: invokespecial #97                 // Method readNewsgroupListing:()[Lorg/apache/commons/net/nntp/NewsgroupInfo;
      16: areturn

  public org.apache.commons.net.nntp.NewsgroupInfo[] listNewsgroups(java.lang.String) throws java.io.IOException;
    Code:
       0: aload_0
       1: aload_1
       2: invokevirtual #72                 // Method listActive:(Ljava/lang/String;)I
       5: invokestatic  #41                 // Method org/apache/commons/net/nntp/NNTPReply.isPositiveCompletion:(I)Z
       8: ifne          13
      11: aconst_null
      12: areturn
      13: aload_0
      14: invokespecial #97                 // Method readNewsgroupListing:()[Lorg/apache/commons/net/nntp/NewsgroupInfo;
      17: areturn

  public java.lang.String[] listOverviewFmt() throws java.io.IOException;
    Code:
       0: aload_0
       1: ldc           #98                 // String LIST
       3: ldc           #99                 // String OVERVIEW.FMT
       5: invokevirtual #100                // Method sendCommand:(Ljava/lang/String;Ljava/lang/String;)I
       8: invokestatic  #41                 // Method org/apache/commons/net/nntp/NNTPReply.isPositiveCompletion:(I)Z
      11: ifne          16
      14: aconst_null
      15: areturn
      16: new           #81                 // class org/apache/commons/net/io/DotTerminatedMessageReader
      19: dup
      20: aload_0
      21: getfield      #62                 // Field _reader_:Ljava/io/BufferedReader;
      24: invokespecial #82                 // Method org/apache/commons/net/io/DotTerminatedMessageReader."<init>":(Ljava/io/Reader;)V
      27: astore_1
      28: aconst_null
      29: astore_2
      30: new           #101                // class java/util/ArrayList
      33: dup
      34: invokespecial #102                // Method java/util/ArrayList."<init>":()V
      37: astore        4
      39: aload_1
      40: invokevirtual #91                 // Method java/io/BufferedReader.readLine:()Ljava/lang/String;
      43: dup
      44: astore_3
      45: ifnull        58
      48: aload         4
      50: aload_3
      51: invokevirtual #103                // Method java/util/ArrayList.add:(Ljava/lang/Object;)Z
      54: pop
      55: goto          39
      58: aload         4
      60: getstatic     #94                 // Field org/apache/commons/net/util/NetConstants.EMPTY_STRING_ARRAY:[Ljava/lang/String;
      63: invokevirtual #104                // Method java/util/ArrayList.toArray:([Ljava/lang/Object;)[Ljava/lang/Object;
      66: checkcast     #105                // class "[Ljava/lang/String;"
      69: astore        5
      71: aload_1
      72: ifnull        101
      75: aload_2
      76: ifnull        97
      79: aload_1
      80: invokevirtual #85                 // Method java/io/BufferedReader.close:()V
      83: goto          101
      86: astore        6
      88: aload_2
      89: aload         6
      91: invokevirtual #87                 // Method java/lang/Throwable.addSuppressed:(Ljava/lang/Throwable;)V
      94: goto          101
      97: aload_1
      98: invokevirtual #85                 // Method java/io/BufferedReader.close:()V
     101: aload         5
     103: areturn
     104: astore_3
     105: aload_3
     106: astore_2
     107: aload_3
     108: athrow
     109: astore        7
     111: aload_1
     112: ifnull        141
     115: aload_2
     116: ifnull        137
     119: aload_1
     120: invokevirtual #85                 // Method java/io/BufferedReader.close:()V
     123: goto          141
     126: astore        8
     128: aload_2
     129: aload         8
     131: invokevirtual #87                 // Method java/lang/Throwable.addSuppressed:(Ljava/lang/Throwable;)V
     134: goto          141
     137: aload_1
     138: invokevirtual #85                 // Method java/io/BufferedReader.close:()V
     141: aload         7
     143: athrow
    Exception table:
       from    to  target type
          79    83    86   Class java/lang/Throwable
          30    71   104   Class java/lang/Throwable
          30    71   109   any
         119   123   126   Class java/lang/Throwable
         104   111   109   any

  public boolean logout() throws java.io.IOException;
    Code:
       0: aload_0
       1: invokevirtual #106                // Method quit:()I
       4: invokestatic  #41                 // Method org/apache/commons/net/nntp/NNTPReply.isPositiveCompletion:(I)Z
       7: ireturn

  private void parseArticlePointer(java.lang.String, org.apache.commons.net.nntp.ArticleInfo) throws org.apache.commons.net.MalformedServerReplyException;
    Code:
       0: aload_1
       1: ldc           #14                 // String
       3: invokevirtual #6                  // Method java/lang/String.split:(Ljava/lang/String;)[Ljava/lang/String;
       6: astore_3
       7: aload_3
       8: arraylength
       9: iconst_3
      10: if_icmplt     44
      13: iconst_1
      14: istore        4
      16: aload_2
      17: aload_3
      18: iload         4
      20: iinc          4, 1
      23: aaload
      24: invokestatic  #7                  // Method java/lang/Long.parseLong:(Ljava/lang/String;)J
      27: putfield      #32                 // Field org/apache/commons/net/nntp/ArticleInfo.articleNumber:J
      30: aload_2
      31: aload_3
      32: iload         4
      34: iinc          4, 1
      37: aaload
      38: putfield      #30                 // Field org/apache/commons/net/nntp/ArticleInfo.articleId:Ljava/lang/String;
      41: return
      42: astore        5
      44: new           #21                 // class org/apache/commons/net/MalformedServerReplyException
      47: dup
      48: new           #22                 // class java/lang/StringBuilder
      51: dup
      52: invokespecial #23                 // Method java/lang/StringBuilder."<init>":()V
      55: ldc           #107                // String Could not parse article pointer.\nServer reply:
      57: invokevirtual #25                 // Method java/lang/StringBuilder.append:(Ljava/lang/String;)Ljava/lang/StringBuilder;
      60: aload_1
      61: invokevirtual #25                 // Method java/lang/StringBuilder.append:(Ljava/lang/String;)Ljava/lang/StringBuilder;
      64: invokevirtual #26                 // Method java/lang/StringBuilder.toString:()Ljava/lang/String;
      67: invokespecial #27                 // Method org/apache/commons/net/MalformedServerReplyException."<init>":(Ljava/lang/String;)V
      70: athrow
    Exception table:
       from    to  target type
          16    41    42   Class java/lang/NumberFormatException

  public java.io.Writer postArticle() throws java.io.IOException;
    Code:
       0: aload_0
       1: invokevirtual #108                // Method post:()I
       4: invokestatic  #43                 // Method org/apache/commons/net/nntp/NNTPReply.isPositiveIntermediate:(I)Z
       7: ifne          12
      10: aconst_null
      11: areturn
      12: new           #44                 // class org/apache/commons/net/io/DotTerminatedMessageWriter
      15: dup
      16: aload_0
      17: getfield      #45                 // Field _writer_:Ljava/io/BufferedWriter;
      20: invokespecial #46                 // Method org/apache/commons/net/io/DotTerminatedMessageWriter."<init>":(Ljava/io/Writer;)V
      23: areturn

  private org.apache.commons.net.nntp.NewsgroupInfo[] readNewsgroupListing() throws java.io.IOException;
    Code:
       0: new           #89                 // class java/util/Vector
       3: dup
       4: sipush        2048
       7: invokespecial #109                // Method java/util/Vector."<init>":(I)V
      10: astore_1
      11: new           #81                 // class org/apache/commons/net/io/DotTerminatedMessageReader
      14: dup
      15: aload_0
      16: getfield      #62                 // Field _reader_:Ljava/io/BufferedReader;
      19: invokespecial #82                 // Method org/apache/commons/net/io/DotTerminatedMessageReader."<init>":(Ljava/io/Reader;)V
      22: astore_3
      23: aconst_null
      24: astore        4
      26: aload_3
      27: invokevirtual #91                 // Method java/io/BufferedReader.readLine:()Ljava/lang/String;
      30: dup
      31: astore_2
      32: ifnull        64
      35: aload_2
      36: invokestatic  #110                // Method parseNewsgroupListEntry:(Ljava/lang/String;)Lorg/apache/commons/net/nntp/NewsgroupInfo;
      39: astore        5
      41: aload         5
      43: ifnonnull     55
      46: new           #21                 // class org/apache/commons/net/MalformedServerReplyException
      49: dup
      50: aload_2
      51: invokespecial #27                 // Method org/apache/commons/net/MalformedServerReplyException."<init>":(Ljava/lang/String;)V
      54: athrow
      55: aload_1
      56: aload         5
      58: invokevirtual #92                 // Method java/util/Vector.addElement:(Ljava/lang/Object;)V
      61: goto          26
      64: aload_3
      65: ifnull        145
      68: aload         4
      70: ifnull        92
      73: aload_3
      74: invokevirtual #85                 // Method java/io/BufferedReader.close:()V
      77: goto          145
      80: astore        5
      82: aload         4
      84: aload         5
      86: invokevirtual #87                 // Method java/lang/Throwable.addSuppressed:(Ljava/lang/Throwable;)V
      89: goto          145
      92: aload_3
      93: invokevirtual #85                 // Method java/io/BufferedReader.close:()V
      96: goto          145
      99: astore        5
     101: aload         5
     103: astore        4
     105: aload         5
     107: athrow
     108: astore        6
     110: aload_3
     111: ifnull        142
     114: aload         4
     116: ifnull        138
     119: aload_3
     120: invokevirtual #85                 // Method java/io/BufferedReader.close:()V
     123: goto          142
     126: astore        7
     128: aload         4
     130: aload         7
     132: invokevirtual #87                 // Method java/lang/Throwable.addSuppressed:(Ljava/lang/Throwable;)V
     135: goto          142
     138: aload_3
     139: invokevirtual #85                 // Method java/io/BufferedReader.close:()V
     142: aload         6
     144: athrow
     145: aload_1
     146: invokevirtual #93                 // Method java/util/Vector.size:()I
     149: dup
     150: istore_3
     151: iconst_1
     152: if_icmpge     159
     155: getstatic     #111                // Field EMPTY_NEWSGROUP_INFO_ARRAY:[Lorg/apache/commons/net/nntp/NewsgroupInfo;
     158: areturn
     159: iload_3
     160: anewarray     #19                 // class org/apache/commons/net/nntp/NewsgroupInfo
     163: astore        4
     165: aload_1
     166: aload         4
     168: invokevirtual #96                 // Method java/util/Vector.copyInto:([Ljava/lang/Object;)V
     171: aload         4
     173: areturn
    Exception table:
       from    to  target type
          73    77    80   Class java/lang/Throwable
          26    64    99   Class java/lang/Throwable
          26    64   108   any
         119   123   126   Class java/lang/Throwable
          99   110   108   any

  private java.io.BufferedReader retrieve(int, long, org.apache.commons.net.nntp.ArticleInfo) throws java.io.IOException;
    Code:
       0: aload_0
       1: iload_1
       2: lload_2
       3: invokestatic  #112                // Method java/lang/Long.toString:(J)Ljava/lang/String;
       6: invokevirtual #113                // Method sendCommand:(ILjava/lang/String;)I
       9: invokestatic  #41                 // Method org/apache/commons/net/nntp/NNTPReply.isPositiveCompletion:(I)Z
      12: ifne          17
      15: aconst_null
      16: areturn
      17: aload         4
      19: ifnull        32
      22: aload_0
      23: aload_0
      24: invokevirtual #50                 // Method getReplyString:()Ljava/lang/String;
      27: aload         4
      29: invokespecial #114                // Method parseArticlePointer:(Ljava/lang/String;Lorg/apache/commons/net/nntp/ArticleInfo;)V
      32: new           #81                 // class org/apache/commons/net/io/DotTerminatedMessageReader
      35: dup
      36: aload_0
      37: getfield      #62                 // Field _reader_:Ljava/io/BufferedReader;
      40: invokespecial #82                 // Method org/apache/commons/net/io/DotTerminatedMessageReader."<init>":(Ljava/io/Reader;)V
      43: areturn

  private java.io.BufferedReader retrieve(int, java.lang.String, org.apache.commons.net.nntp.ArticleInfo) throws java.io.IOException;
    Code:
       0: aload_2
       1: ifnull        18
       4: aload_0
       5: iload_1
       6: aload_2
       7: invokevirtual #113                // Method sendCommand:(ILjava/lang/String;)I
      10: invokestatic  #41                 // Method org/apache/commons/net/nntp/NNTPReply.isPositiveCompletion:(I)Z
      13: ifne          31
      16: aconst_null
      17: areturn
      18: aload_0
      19: iload_1
      20: invokevirtual #115                // Method sendCommand:(I)I
      23: invokestatic  #41                 // Method org/apache/commons/net/nntp/NNTPReply.isPositiveCompletion:(I)Z
      26: ifne          31
      29: aconst_null
      30: areturn
      31: aload_3
      32: ifnull        44
      35: aload_0
      36: aload_0
      37: invokevirtual #50                 // Method getReplyString:()Ljava/lang/String;
      40: aload_3
      41: invokespecial #114                // Method parseArticlePointer:(Ljava/lang/String;Lorg/apache/commons/net/nntp/ArticleInfo;)V
      44: new           #81                 // class org/apache/commons/net/io/DotTerminatedMessageReader
      47: dup
      48: aload_0
      49: getfield      #62                 // Field _reader_:Ljava/io/BufferedReader;
      52: invokespecial #82                 // Method org/apache/commons/net/io/DotTerminatedMessageReader."<init>":(Ljava/io/Reader;)V
      55: areturn

  public java.io.Reader retrieveArticle() throws java.io.IOException;
    Code:
       0: aload_0
       1: aconst_null
       2: checkcast     #95                 // class java/lang/String
       5: invokevirtual #116                // Method retrieveArticle:(Ljava/lang/String;)Ljava/io/Reader;
       8: areturn

  public java.io.Reader retrieveArticle(int) throws java.io.IOException;
    Code:
       0: aload_0
       1: iload_1
       2: i2l
       3: invokevirtual #117                // Method retrieveArticle:(J)Ljava/io/BufferedReader;
       6: areturn

  public java.io.Reader retrieveArticle(int, org.apache.commons.net.nntp.ArticlePointer) throws java.io.IOException;
    Code:
       0: aload_0
       1: aload_2
       2: invokespecial #118                // Method ap2ai:(Lorg/apache/commons/net/nntp/ArticlePointer;)Lorg/apache/commons/net/nntp/ArticleInfo;
       5: astore_3
       6: aload_0
       7: iload_1
       8: i2l
       9: aload_3
      10: invokevirtual #119                // Method retrieveArticle:(JLorg/apache/commons/net/nntp/ArticleInfo;)Ljava/io/BufferedReader;
      13: astore        4
      15: aload_0
      16: aload_3
      17: aload_2
      18: invokespecial #120                // Method ai2ap:(Lorg/apache/commons/net/nntp/ArticleInfo;Lorg/apache/commons/net/nntp/ArticlePointer;)V
      21: aload         4
      23: areturn

  public java.io.BufferedReader retrieveArticle(long) throws java.io.IOException;
    Code:
       0: aload_0
       1: lload_1
       2: aconst_null
       3: invokevirtual #119                // Method retrieveArticle:(JLorg/apache/commons/net/nntp/ArticleInfo;)Ljava/io/BufferedReader;
       6: areturn

  public java.io.BufferedReader retrieveArticle(long, org.apache.commons.net.nntp.ArticleInfo) throws java.io.IOException;
    Code:
       0: aload_0
       1: iconst_0
       2: lload_1
       3: aload_3
       4: invokespecial #122                // Method retrieve:(IJLorg/apache/commons/net/nntp/ArticleInfo;)Ljava/io/BufferedReader;
       7: areturn

  public java.io.Reader retrieveArticle(java.lang.String) throws java.io.IOException;
    Code:
       0: aload_0
       1: aload_1
       2: aconst_null
       3: checkcast     #34                 // class org/apache/commons/net/nntp/ArticleInfo
       6: invokevirtual #123                // Method retrieveArticle:(Ljava/lang/String;Lorg/apache/commons/net/nntp/ArticleInfo;)Ljava/io/BufferedReader;
       9: areturn

  public java.io.BufferedReader retrieveArticle(java.lang.String, org.apache.commons.net.nntp.ArticleInfo) throws java.io.IOException;
    Code:
       0: aload_0
       1: iconst_0
       2: aload_1
       3: aload_2
       4: invokespecial #124                // Method retrieve:(ILjava/lang/String;Lorg/apache/commons/net/nntp/ArticleInfo;)Ljava/io/BufferedReader;
       7: areturn

  public java.io.Reader retrieveArticle(java.lang.String, org.apache.commons.net.nntp.ArticlePointer) throws java.io.IOException;
    Code:
       0: aload_0
       1: aload_2
       2: invokespecial #118                // Method ap2ai:(Lorg/apache/commons/net/nntp/ArticlePointer;)Lorg/apache/commons/net/nntp/ArticleInfo;
       5: astore_3
       6: aload_0
       7: aload_1
       8: aload_3
       9: invokevirtual #123                // Method retrieveArticle:(Ljava/lang/String;Lorg/apache/commons/net/nntp/ArticleInfo;)Ljava/io/BufferedReader;
      12: astore        4
      14: aload_0
      15: aload_3
      16: aload_2
      17: invokespecial #120                // Method ai2ap:(Lorg/apache/commons/net/nntp/ArticleInfo;Lorg/apache/commons/net/nntp/ArticlePointer;)V
      20: aload         4
      22: areturn

  public java.io.Reader retrieveArticleBody() throws java.io.IOException;
    Code:
       0: aload_0
       1: aconst_null
       2: invokevirtual #125                // Method retrieveArticleBody:(Ljava/lang/String;)Ljava/io/Reader;
       5: areturn

  public java.io.Reader retrieveArticleBody(int) throws java.io.IOException;
    Code:
       0: aload_0
       1: iload_1
       2: i2l
       3: invokevirtual #126                // Method retrieveArticleBody:(J)Ljava/io/BufferedReader;
       6: areturn

  public java.io.Reader retrieveArticleBody(int, org.apache.commons.net.nntp.ArticlePointer) throws java.io.IOException;
    Code:
       0: aload_0
       1: aload_2
       2: invokespecial #118                // Method ap2ai:(Lorg/apache/commons/net/nntp/ArticlePointer;)Lorg/apache/commons/net/nntp/ArticleInfo;
       5: astore_3
       6: aload_0
       7: iload_1
       8: i2l
       9: aload_3
      10: invokevirtual #127                // Method retrieveArticleBody:(JLorg/apache/commons/net/nntp/ArticleInfo;)Ljava/io/BufferedReader;
      13: astore        4
      15: aload_0
      16: aload_3
      17: aload_2
      18: invokespecial #120                // Method ai2ap:(Lorg/apache/commons/net/nntp/ArticleInfo;Lorg/apache/commons/net/nntp/ArticlePointer;)V
      21: aload         4
      23: areturn

  public java.io.BufferedReader retrieveArticleBody(long) throws java.io.IOException;
    Code:
       0: aload_0
       1: lload_1
       2: aconst_null
       3: invokevirtual #127                // Method retrieveArticleBody:(JLorg/apache/commons/net/nntp/ArticleInfo;)Ljava/io/BufferedReader;
       6: areturn

  public java.io.BufferedReader retrieveArticleBody(long, org.apache.commons.net.nntp.ArticleInfo) throws java.io.IOException;
    Code:
       0: aload_0
       1: iconst_1
       2: lload_1
       3: aload_3
       4: invokespecial #122                // Method retrieve:(IJLorg/apache/commons/net/nntp/ArticleInfo;)Ljava/io/BufferedReader;
       7: areturn

  public java.io.Reader retrieveArticleBody(java.lang.String) throws java.io.IOException;
    Code:
       0: aload_0
       1: aload_1
       2: aconst_null
       3: checkcast     #34                 // class org/apache/commons/net/nntp/ArticleInfo
       6: invokevirtual #128                // Method retrieveArticleBody:(Ljava/lang/String;Lorg/apache/commons/net/nntp/ArticleInfo;)Ljava/io/BufferedReader;
       9: areturn

  public java.io.BufferedReader retrieveArticleBody(java.lang.String, org.apache.commons.net.nntp.ArticleInfo) throws java.io.IOException;
    Code:
       0: aload_0
       1: iconst_1
       2: aload_1
       3: aload_2
       4: invokespecial #124                // Method retrieve:(ILjava/lang/String;Lorg/apache/commons/net/nntp/ArticleInfo;)Ljava/io/BufferedReader;
       7: areturn

  public java.io.Reader retrieveArticleBody(java.lang.String, org.apache.commons.net.nntp.ArticlePointer) throws java.io.IOException;
    Code:
       0: aload_0
       1: aload_2
       2: invokespecial #118                // Method ap2ai:(Lorg/apache/commons/net/nntp/ArticlePointer;)Lorg/apache/commons/net/nntp/ArticleInfo;
       5: astore_3
       6: aload_0
       7: aload_1
       8: aload_3
       9: invokevirtual #128                // Method retrieveArticleBody:(Ljava/lang/String;Lorg/apache/commons/net/nntp/ArticleInfo;)Ljava/io/BufferedReader;
      12: astore        4
      14: aload_0
      15: aload_3
      16: aload_2
      17: invokespecial #120                // Method ai2ap:(Lorg/apache/commons/net/nntp/ArticleInfo;Lorg/apache/commons/net/nntp/ArticlePointer;)V
      20: aload         4
      22: areturn

  public java.io.Reader retrieveArticleHeader() throws java.io.IOException;
    Code:
       0: aload_0
       1: aconst_null
       2: checkcast     #95                 // class java/lang/String
       5: invokevirtual #129                // Method retrieveArticleHeader:(Ljava/lang/String;)Ljava/io/Reader;
       8: areturn

  public java.io.Reader retrieveArticleHeader(int) throws java.io.IOException;
    Code:
       0: aload_0
       1: iload_1
       2: i2l
       3: invokevirtual #130                // Method retrieveArticleHeader:(J)Ljava/io/BufferedReader;
       6: areturn

  public java.io.Reader retrieveArticleHeader(int, org.apache.commons.net.nntp.ArticlePointer) throws java.io.IOException;
    Code:
       0: aload_0
       1: aload_2
       2: invokespecial #118                // Method ap2ai:(Lorg/apache/commons/net/nntp/ArticlePointer;)Lorg/apache/commons/net/nntp/ArticleInfo;
       5: astore_3
       6: aload_0
       7: iload_1
       8: i2l
       9: aload_3
      10: invokevirtual #131                // Method retrieveArticleHeader:(JLorg/apache/commons/net/nntp/ArticleInfo;)Ljava/io/BufferedReader;
      13: astore        4
      15: aload_0
      16: aload_3
      17: aload_2
      18: invokespecial #120                // Method ai2ap:(Lorg/apache/commons/net/nntp/ArticleInfo;Lorg/apache/commons/net/nntp/ArticlePointer;)V
      21: aload         4
      23: areturn

  public java.io.BufferedReader retrieveArticleHeader(long) throws java.io.IOException;
    Code:
       0: aload_0
       1: lload_1
       2: aconst_null
       3: invokevirtual #131                // Method retrieveArticleHeader:(JLorg/apache/commons/net/nntp/ArticleInfo;)Ljava/io/BufferedReader;
       6: areturn

  public java.io.BufferedReader retrieveArticleHeader(long, org.apache.commons.net.nntp.ArticleInfo) throws java.io.IOException;
    Code:
       0: aload_0
       1: iconst_3
       2: lload_1
       3: aload_3
       4: invokespecial #122                // Method retrieve:(IJLorg/apache/commons/net/nntp/ArticleInfo;)Ljava/io/BufferedReader;
       7: areturn

  public java.io.Reader retrieveArticleHeader(java.lang.String) throws java.io.IOException;
    Code:
       0: aload_0
       1: aload_1
       2: aconst_null
       3: checkcast     #34                 // class org/apache/commons/net/nntp/ArticleInfo
       6: invokevirtual #132                // Method retrieveArticleHeader:(Ljava/lang/String;Lorg/apache/commons/net/nntp/ArticleInfo;)Ljava/io/BufferedReader;
       9: areturn

  public java.io.BufferedReader retrieveArticleHeader(java.lang.String, org.apache.commons.net.nntp.ArticleInfo) throws java.io.IOException;
    Code:
       0: aload_0
       1: iconst_3
       2: aload_1
       3: aload_2
       4: invokespecial #124                // Method retrieve:(ILjava/lang/String;Lorg/apache/commons/net/nntp/ArticleInfo;)Ljava/io/BufferedReader;
       7: areturn

  public java.io.Reader retrieveArticleHeader(java.lang.String, org.apache.commons.net.nntp.ArticlePointer) throws java.io.IOException;
    Code:
       0: aload_0
       1: aload_2
       2: invokespecial #118                // Method ap2ai:(Lorg/apache/commons/net/nntp/ArticlePointer;)Lorg/apache/commons/net/nntp/ArticleInfo;
       5: astore_3
       6: aload_0
       7: aload_1
       8: aload_3
       9: invokevirtual #132                // Method retrieveArticleHeader:(Ljava/lang/String;Lorg/apache/commons/net/nntp/ArticleInfo;)Ljava/io/BufferedReader;
      12: astore        4
      14: aload_0
      15: aload_3
      16: aload_2
      17: invokespecial #120                // Method ai2ap:(Lorg/apache/commons/net/nntp/ArticleInfo;Lorg/apache/commons/net/nntp/ArticlePointer;)V
      20: aload         4
      22: areturn

  public java.io.Reader retrieveArticleInfo(int) throws java.io.IOException;
    Code:
       0: aload_0
       1: iload_1
       2: i2l
       3: invokevirtual #133                // Method retrieveArticleInfo:(J)Ljava/io/BufferedReader;
       6: areturn

  public java.io.Reader retrieveArticleInfo(int, int) throws java.io.IOException;
    Code:
       0: aload_0
       1: iload_1
       2: i2l
       3: iload_2
       4: i2l
       5: invokevirtual #47                 // Method retrieveArticleInfo:(JJ)Ljava/io/BufferedReader;
       8: areturn

  public java.io.BufferedReader retrieveArticleInfo(long) throws java.io.IOException;
    Code:
       0: aload_0
       1: lload_1
       2: invokestatic  #112                // Method java/lang/Long.toString:(J)Ljava/lang/String;
       5: invokespecial #134                // Method retrieveArticleInfo:(Ljava/lang/String;)Ljava/io/BufferedReader;
       8: areturn

  public java.io.BufferedReader retrieveArticleInfo(long, long) throws java.io.IOException;
    Code:
       0: aload_0
       1: new           #22                 // class java/lang/StringBuilder
       4: dup
       5: invokespecial #23                 // Method java/lang/StringBuilder."<init>":()V
       8: lload_1
       9: invokevirtual #135                // Method java/lang/StringBuilder.append:(J)Ljava/lang/StringBuilder;
      12: ldc           #136                // String -
      14: invokevirtual #25                 // Method java/lang/StringBuilder.append:(Ljava/lang/String;)Ljava/lang/StringBuilder;
      17: lload_3
      18: invokevirtual #135                // Method java/lang/StringBuilder.append:(J)Ljava/lang/StringBuilder;
      21: invokevirtual #26                 // Method java/lang/StringBuilder.toString:()Ljava/lang/String;
      24: invokespecial #134                // Method retrieveArticleInfo:(Ljava/lang/String;)Ljava/io/BufferedReader;
      27: areturn

  private java.io.BufferedReader retrieveArticleInfo(java.lang.String) throws java.io.IOException;
    Code:
       0: aload_0
       1: aload_1
       2: invokevirtual #137                // Method xover:(Ljava/lang/String;)I
       5: invokestatic  #41                 // Method org/apache/commons/net/nntp/NNTPReply.isPositiveCompletion:(I)Z
       8: ifne          13
      11: aconst_null
      12: areturn
      13: new           #81                 // class org/apache/commons/net/io/DotTerminatedMessageReader
      16: dup
      17: aload_0
      18: getfield      #62                 // Field _reader_:Ljava/io/BufferedReader;
      21: invokespecial #82                 // Method org/apache/commons/net/io/DotTerminatedMessageReader."<init>":(Ljava/io/Reader;)V
      24: areturn

  public java.io.Reader retrieveHeader(java.lang.String, int) throws java.io.IOException;
    Code:
       0: aload_0
       1: aload_1
       2: iload_2
       3: i2l
       4: invokevirtual #138                // Method retrieveHeader:(Ljava/lang/String;J)Ljava/io/BufferedReader;
       7: areturn

  public java.io.Reader retrieveHeader(java.lang.String, int, int) throws java.io.IOException;
    Code:
       0: aload_0
       1: aload_1
       2: iload_2
       3: i2l
       4: iload_3
       5: i2l
       6: invokevirtual #139                // Method retrieveHeader:(Ljava/lang/String;JJ)Ljava/io/BufferedReader;
       9: areturn

  public java.io.BufferedReader retrieveHeader(java.lang.String, long) throws java.io.IOException;
    Code:
       0: aload_0
       1: aload_1
       2: lload_2
       3: invokestatic  #112                // Method java/lang/Long.toString:(J)Ljava/lang/String;
       6: invokespecial #140                // Method retrieveHeader:(Ljava/lang/String;Ljava/lang/String;)Ljava/io/BufferedReader;
       9: areturn

  public java.io.BufferedReader retrieveHeader(java.lang.String, long, long) throws java.io.IOException;
    Code:
       0: aload_0
       1: aload_1
       2: new           #22                 // class java/lang/StringBuilder
       5: dup
       6: invokespecial #23                 // Method java/lang/StringBuilder."<init>":()V
       9: lload_2
      10: invokevirtual #135                // Method java/lang/StringBuilder.append:(J)Ljava/lang/StringBuilder;
      13: ldc           #136                // String -
      15: invokevirtual #25                 // Method java/lang/StringBuilder.append:(Ljava/lang/String;)Ljava/lang/StringBuilder;
      18: lload         4
      20: invokevirtual #135                // Method java/lang/StringBuilder.append:(J)Ljava/lang/StringBuilder;
      23: invokevirtual #26                 // Method java/lang/StringBuilder.toString:()Ljava/lang/String;
      26: invokespecial #140                // Method retrieveHeader:(Ljava/lang/String;Ljava/lang/String;)Ljava/io/BufferedReader;
      29: areturn

  private java.io.BufferedReader retrieveHeader(java.lang.String, java.lang.String) throws java.io.IOException;
    Code:
       0: aload_0
       1: aload_1
       2: aload_2
       3: invokevirtual #141                // Method xhdr:(Ljava/lang/String;Ljava/lang/String;)I
       6: invokestatic  #41                 // Method org/apache/commons/net/nntp/NNTPReply.isPositiveCompletion:(I)Z
       9: ifne          14
      12: aconst_null
      13: areturn
      14: new           #81                 // class org/apache/commons/net/io/DotTerminatedMessageReader
      17: dup
      18: aload_0
      19: getfield      #62                 // Field _reader_:Ljava/io/BufferedReader;
      22: invokespecial #82                 // Method org/apache/commons/net/io/DotTerminatedMessageReader."<init>":(Ljava/io/Reader;)V
      25: areturn

  public boolean selectArticle(org.apache.commons.net.nntp.ArticleInfo) throws java.io.IOException;
    Code:
       0: aload_0
       1: aconst_null
       2: aload_1
       3: invokevirtual #142                // Method selectArticle:(Ljava/lang/String;Lorg/apache/commons/net/nntp/ArticleInfo;)Z
       6: ireturn

  public boolean selectArticle(org.apache.commons.net.nntp.ArticlePointer) throws java.io.IOException;
    Code:
       0: aload_0
       1: aload_1
       2: invokespecial #118                // Method ap2ai:(Lorg/apache/commons/net/nntp/ArticlePointer;)Lorg/apache/commons/net/nntp/ArticleInfo;
       5: astore_2
       6: aload_0
       7: aload_2
       8: invokevirtual #143                // Method selectArticle:(Lorg/apache/commons/net/nntp/ArticleInfo;)Z
      11: istore_3
      12: aload_0
      13: aload_2
      14: aload_1
      15: invokespecial #120                // Method ai2ap:(Lorg/apache/commons/net/nntp/ArticleInfo;Lorg/apache/commons/net/nntp/ArticlePointer;)V
      18: iload_3
      19: ireturn

  public boolean selectArticle(int) throws java.io.IOException;
    Code:
       0: aload_0
       1: iload_1
       2: i2l
       3: invokevirtual #144                // Method selectArticle:(J)Z
       6: ireturn

  public boolean selectArticle(int, org.apache.commons.net.nntp.ArticlePointer) throws java.io.IOException;
    Code:
       0: aload_0
       1: aload_2
       2: invokespecial #118                // Method ap2ai:(Lorg/apache/commons/net/nntp/ArticlePointer;)Lorg/apache/commons/net/nntp/ArticleInfo;
       5: astore_3
       6: aload_0
       7: iload_1
       8: i2l
       9: aload_3
      10: invokevirtual #145                // Method selectArticle:(JLorg/apache/commons/net/nntp/ArticleInfo;)Z
      13: istore        4
      15: aload_0
      16: aload_3
      17: aload_2
      18: invokespecial #120                // Method ai2ap:(Lorg/apache/commons/net/nntp/ArticleInfo;Lorg/apache/commons/net/nntp/ArticlePointer;)V
      21: iload         4
      23: ireturn

  public boolean selectArticle(long) throws java.io.IOException;
    Code:
       0: aload_0
       1: lload_1
       2: aconst_null
       3: invokevirtual #145                // Method selectArticle:(JLorg/apache/commons/net/nntp/ArticleInfo;)Z
       6: ireturn

  public boolean selectArticle(long, org.apache.commons.net.nntp.ArticleInfo) throws java.io.IOException;
    Code:
       0: aload_0
       1: lload_1
       2: invokevirtual #146                // Method stat:(J)I
       5: invokestatic  #41                 // Method org/apache/commons/net/nntp/NNTPReply.isPositiveCompletion:(I)Z
       8: ifne          13
      11: iconst_0
      12: ireturn
      13: aload_3
      14: ifnull        26
      17: aload_0
      18: aload_0
      19: invokevirtual #50                 // Method getReplyString:()Ljava/lang/String;
      22: aload_3
      23: invokespecial #114                // Method parseArticlePointer:(Ljava/lang/String;Lorg/apache/commons/net/nntp/ArticleInfo;)V
      26: iconst_1
      27: ireturn

  public boolean selectArticle(java.lang.String) throws java.io.IOException;
    Code:
       0: aload_0
       1: aload_1
       2: aconst_null
       3: checkcast     #34                 // class org/apache/commons/net/nntp/ArticleInfo
       6: invokevirtual #142                // Method selectArticle:(Ljava/lang/String;Lorg/apache/commons/net/nntp/ArticleInfo;)Z
       9: ireturn

  public boolean selectArticle(java.lang.String, org.apache.commons.net.nntp.ArticleInfo) throws java.io.IOException;
    Code:
       0: aload_1
       1: ifnull        17
       4: aload_0
       5: aload_1
       6: invokevirtual #147                // Method stat:(Ljava/lang/String;)I
       9: invokestatic  #41                 // Method org/apache/commons/net/nntp/NNTPReply.isPositiveCompletion:(I)Z
      12: ifne          29
      15: iconst_0
      16: ireturn
      17: aload_0
      18: invokevirtual #148                // Method stat:()I
      21: invokestatic  #41                 // Method org/apache/commons/net/nntp/NNTPReply.isPositiveCompletion:(I)Z
      24: ifne          29
      27: iconst_0
      28: ireturn
      29: aload_2
      30: ifnull        42
      33: aload_0
      34: aload_0
      35: invokevirtual #50                 // Method getReplyString:()Ljava/lang/String;
      38: aload_2
      39: invokespecial #114                // Method parseArticlePointer:(Ljava/lang/String;Lorg/apache/commons/net/nntp/ArticleInfo;)V
      42: iconst_1
      43: ireturn

  public boolean selectArticle(java.lang.String, org.apache.commons.net.nntp.ArticlePointer) throws java.io.IOException;
    Code:
       0: aload_0
       1: aload_2
       2: invokespecial #118                // Method ap2ai:(Lorg/apache/commons/net/nntp/ArticlePointer;)Lorg/apache/commons/net/nntp/ArticleInfo;
       5: astore_3
       6: aload_0
       7: aload_1
       8: aload_3
       9: invokevirtual #142                // Method selectArticle:(Ljava/lang/String;Lorg/apache/commons/net/nntp/ArticleInfo;)Z
      12: istore        4
      14: aload_0
      15: aload_3
      16: aload_2
      17: invokespecial #120                // Method ai2ap:(Lorg/apache/commons/net/nntp/ArticleInfo;Lorg/apache/commons/net/nntp/ArticlePointer;)V
      20: iload         4
      22: ireturn

  public boolean selectNewsgroup(java.lang.String) throws java.io.IOException;
    Code:
       0: aload_0
       1: aload_1
       2: aconst_null
       3: invokevirtual #149                // Method selectNewsgroup:(Ljava/lang/String;Lorg/apache/commons/net/nntp/NewsgroupInfo;)Z
       6: ireturn

  public boolean selectNewsgroup(java.lang.String, org.apache.commons.net.nntp.NewsgroupInfo) throws java.io.IOException;
    Code:
       0: aload_0
       1: aload_1
       2: invokevirtual #150                // Method group:(Ljava/lang/String;)I
       5: invokestatic  #41                 // Method org/apache/commons/net/nntp/NNTPReply.isPositiveCompletion:(I)Z
       8: ifne          13
      11: iconst_0
      12: ireturn
      13: aload_2
      14: ifnull        25
      17: aload_0
      18: invokevirtual #50                 // Method getReplyString:()Ljava/lang/String;
      21: aload_2
      22: invokestatic  #151                // Method parseGroupReply:(Ljava/lang/String;Lorg/apache/commons/net/nntp/NewsgroupInfo;)V
      25: iconst_1
      26: ireturn

  public boolean selectNextArticle() throws java.io.IOException;
    Code:
       0: aload_0
       1: aconst_null
       2: checkcast     #34                 // class org/apache/commons/net/nntp/ArticleInfo
       5: invokevirtual #152                // Method selectNextArticle:(Lorg/apache/commons/net/nntp/ArticleInfo;)Z
       8: ireturn

  public boolean selectNextArticle(org.apache.commons.net.nntp.ArticleInfo) throws java.io.IOException;
    Code:
       0: aload_0
       1: invokevirtual #153                // Method next:()I
       4: invokestatic  #41                 // Method org/apache/commons/net/nntp/NNTPReply.isPositiveCompletion:(I)Z
       7: ifne          12
      10: iconst_0
      11: ireturn
      12: aload_1
      13: ifnull        25
      16: aload_0
      17: aload_0
      18: invokevirtual #50                 // Method getReplyString:()Ljava/lang/String;
      21: aload_1
      22: invokespecial #114                // Method parseArticlePointer:(Ljava/lang/String;Lorg/apache/commons/net/nntp/ArticleInfo;)V
      25: iconst_1
      26: ireturn

  public boolean selectNextArticle(org.apache.commons.net.nntp.ArticlePointer) throws java.io.IOException;
    Code:
       0: aload_0
       1: aload_1
       2: invokespecial #118                // Method ap2ai:(Lorg/apache/commons/net/nntp/ArticlePointer;)Lorg/apache/commons/net/nntp/ArticleInfo;
       5: astore_2
       6: aload_0
       7: aload_2
       8: invokevirtual #152                // Method selectNextArticle:(Lorg/apache/commons/net/nntp/ArticleInfo;)Z
      11: istore_3
      12: aload_0
      13: aload_2
      14: aload_1
      15: invokespecial #120                // Method ai2ap:(Lorg/apache/commons/net/nntp/ArticleInfo;Lorg/apache/commons/net/nntp/ArticlePointer;)V
      18: iload_3
      19: ireturn

  public boolean selectPreviousArticle() throws java.io.IOException;
    Code:
       0: aload_0
       1: aconst_null
       2: checkcast     #34                 // class org/apache/commons/net/nntp/ArticleInfo
       5: invokevirtual #154                // Method selectPreviousArticle:(Lorg/apache/commons/net/nntp/ArticleInfo;)Z
       8: ireturn

  public boolean selectPreviousArticle(org.apache.commons.net.nntp.ArticleInfo) throws java.io.IOException;
    Code:
       0: aload_0
       1: invokevirtual #155                // Method last:()I
       4: invokestatic  #41                 // Method org/apache/commons/net/nntp/NNTPReply.isPositiveCompletion:(I)Z
       7: ifne          12
      10: iconst_0
      11: ireturn
      12: aload_1
      13: ifnull        25
      16: aload_0
      17: aload_0
      18: invokevirtual #50                 // Method getReplyString:()Ljava/lang/String;
      21: aload_1
      22: invokespecial #114                // Method parseArticlePointer:(Ljava/lang/String;Lorg/apache/commons/net/nntp/ArticleInfo;)V
      25: iconst_1
      26: ireturn

  public boolean selectPreviousArticle(org.apache.commons.net.nntp.ArticlePointer) throws java.io.IOException;
    Code:
       0: aload_0
       1: aload_1
       2: invokespecial #118                // Method ap2ai:(Lorg/apache/commons/net/nntp/ArticlePointer;)Lorg/apache/commons/net/nntp/ArticleInfo;
       5: astore_2
       6: aload_0
       7: aload_2
       8: invokevirtual #154                // Method selectPreviousArticle:(Lorg/apache/commons/net/nntp/ArticleInfo;)Z
      11: istore_3
      12: aload_0
      13: aload_2
      14: aload_1
      15: invokespecial #120                // Method ai2ap:(Lorg/apache/commons/net/nntp/ArticleInfo;Lorg/apache/commons/net/nntp/ArticlePointer;)V
      18: iload_3
      19: ireturn

  static {};
    Code:
       0: iconst_0
       1: anewarray     #19                 // class org/apache/commons/net/nntp/NewsgroupInfo
       4: putstatic     #111                // Field EMPTY_NEWSGROUP_INFO_ARRAY:[Lorg/apache/commons/net/nntp/NewsgroupInfo;
       7: return
}
