Compiled from "PojoEndpointBase.java"
public abstract class org.apache.tomcat.websocket.pojo.PojoEndpointBase extends javax.websocket.Endpoint {
  private static final org.apache.juli.logging.Log log;

  private static final org.apache.tomcat.util.res.StringManager sm;

  private java.lang.Object pojo;

  private java.util.Map<java.lang.String, java.lang.String> pathParameters;

  private org.apache.tomcat.websocket.pojo.PojoMethodMapping methodMapping;

  public org.apache.tomcat.websocket.pojo.PojoEndpointBase();
    Code:
       0: aload_0
       1: invokespecial #1                  // Method javax/websocket/Endpoint."<init>":()V
       4: return

  protected final void doOnOpen(javax.websocket.Session, javax.websocket.EndpointConfig);
    Code:
       0: aload_0
       1: invokevirtual #2                  // Method getMethodMapping:()Lorg/apache/tomcat/websocket/pojo/PojoMethodMapping;
       4: astore_3
       5: aload_0
       6: invokevirtual #3                  // Method getPojo:()Ljava/lang/Object;
       9: astore        4
      11: aload_0
      12: invokevirtual #4                  // Method getPathParameters:()Ljava/util/Map;
      15: astore        5
      17: aload_3
      18: aload         4
      20: aload         5
      22: aload_1
      23: aload_2
      24: invokevirtual #5                  // Method org/apache/tomcat/websocket/pojo/PojoMethodMapping.getMessageHandlers:(Ljava/lang/Object;Ljava/util/Map;Ljavax/websocket/Session;Ljavax/websocket/EndpointConfig;)Ljava/util/Set;
      27: invokeinterface #6,  1            // InterfaceMethod java/util/Set.iterator:()Ljava/util/Iterator;
      32: astore        6
      34: aload         6
      36: invokeinterface #7,  1            // InterfaceMethod java/util/Iterator.hasNext:()Z
      41: ifeq          67
      44: aload         6
      46: invokeinterface #8,  1            // InterfaceMethod java/util/Iterator.next:()Ljava/lang/Object;
      51: checkcast     #9                  // class javax/websocket/MessageHandler
      54: astore        7
      56: aload_1
      57: aload         7
      59: invokeinterface #10,  2           // InterfaceMethod javax/websocket/Session.addMessageHandler:(Ljavax/websocket/MessageHandler;)V
      64: goto          34
      67: aload_3
      68: invokevirtual #11                 // Method org/apache/tomcat/websocket/pojo/PojoMethodMapping.getOnOpen:()Ljava/lang/reflect/Method;
      71: ifnull        165
      74: aload_3
      75: invokevirtual #11                 // Method org/apache/tomcat/websocket/pojo/PojoMethodMapping.getOnOpen:()Ljava/lang/reflect/Method;
      78: aload         4
      80: aload_3
      81: aload         5
      83: aload_1
      84: aload_2
      85: invokevirtual #12                 // Method org/apache/tomcat/websocket/pojo/PojoMethodMapping.getOnOpenArgs:(Ljava/util/Map;Ljavax/websocket/Session;Ljavax/websocket/EndpointConfig;)[Ljava/lang/Object;
      88: invokevirtual #13                 // Method java/lang/reflect/Method.invoke:(Ljava/lang/Object;[Ljava/lang/Object;)Ljava/lang/Object;
      91: pop
      92: goto          165
      95: astore        6
      97: getstatic     #15                 // Field log:Lorg/apache/juli/logging/Log;
     100: getstatic     #16                 // Field sm:Lorg/apache/tomcat/util/res/StringManager;
     103: ldc           #17                 // String pojoEndpointBase.onOpenFail
     105: iconst_1
     106: anewarray     #18                 // class java/lang/Object
     109: dup
     110: iconst_0
     111: aload         4
     113: invokevirtual #19                 // Method java/lang/Object.getClass:()Ljava/lang/Class;
     116: invokevirtual #20                 // Method java/lang/Class.getName:()Ljava/lang/String;
     119: aastore
     120: invokevirtual #21                 // Method org/apache/tomcat/util/res/StringManager.getString:(Ljava/lang/String;[Ljava/lang/Object;)Ljava/lang/String;
     123: aload         6
     125: invokeinterface #22,  3           // InterfaceMethod org/apache/juli/logging/Log.error:(Ljava/lang/Object;Ljava/lang/Throwable;)V
     130: aload_0
     131: aload_1
     132: aload         6
     134: invokespecial #23                 // Method handleOnOpenOrCloseError:(Ljavax/websocket/Session;Ljava/lang/Throwable;)V
     137: return
     138: astore        6
     140: aload         6
     142: invokevirtual #25                 // Method java/lang/reflect/InvocationTargetException.getCause:()Ljava/lang/Throwable;
     145: astore        7
     147: aload_0
     148: aload_1
     149: aload         7
     151: invokespecial #23                 // Method handleOnOpenOrCloseError:(Ljavax/websocket/Session;Ljava/lang/Throwable;)V
     154: return
     155: astore        6
     157: aload_0
     158: aload_1
     159: aload         6
     161: invokespecial #23                 // Method handleOnOpenOrCloseError:(Ljavax/websocket/Session;Ljava/lang/Throwable;)V
     164: return
     165: return
    Exception table:
       from    to  target type
          74    92    95   Class java/lang/IllegalAccessException
          74    92   138   Class java/lang/reflect/InvocationTargetException
          74    92   155   Class java/lang/Throwable

  private void handleOnOpenOrCloseError(javax.websocket.Session, java.lang.Throwable);
    Code:
       0: aload_2
       1: invokestatic  #27                 // Method org/apache/tomcat/util/ExceptionUtils.handleThrowable:(Ljava/lang/Throwable;)V
       4: aload_0
       5: aload_1
       6: aload_2
       7: invokevirtual #28                 // Method onError:(Ljavax/websocket/Session;Ljava/lang/Throwable;)V
      10: aload_1
      11: invokeinterface #29,  1           // InterfaceMethod javax/websocket/Session.close:()V
      16: goto          37
      19: astore_3
      20: getstatic     #15                 // Field log:Lorg/apache/juli/logging/Log;
      23: getstatic     #16                 // Field sm:Lorg/apache/tomcat/util/res/StringManager;
      26: ldc           #31                 // String pojoEndpointBase.closeSessionFail
      28: invokevirtual #32                 // Method org/apache/tomcat/util/res/StringManager.getString:(Ljava/lang/String;)Ljava/lang/String;
      31: aload_3
      32: invokeinterface #33,  3           // InterfaceMethod org/apache/juli/logging/Log.warn:(Ljava/lang/Object;Ljava/lang/Throwable;)V
      37: return
    Exception table:
       from    to  target type
          10    16    19   Class java/io/IOException

  public final void onClose(javax.websocket.Session, javax.websocket.CloseReason);
    Code:
       0: aload_0
       1: getfield      #34                 // Field methodMapping:Lorg/apache/tomcat/websocket/pojo/PojoMethodMapping;
       4: invokevirtual #35                 // Method org/apache/tomcat/websocket/pojo/PojoMethodMapping.getOnClose:()Ljava/lang/reflect/Method;
       7: ifnull        82
      10: aload_0
      11: getfield      #34                 // Field methodMapping:Lorg/apache/tomcat/websocket/pojo/PojoMethodMapping;
      14: invokevirtual #35                 // Method org/apache/tomcat/websocket/pojo/PojoMethodMapping.getOnClose:()Ljava/lang/reflect/Method;
      17: aload_0
      18: getfield      #36                 // Field pojo:Ljava/lang/Object;
      21: aload_0
      22: getfield      #34                 // Field methodMapping:Lorg/apache/tomcat/websocket/pojo/PojoMethodMapping;
      25: aload_0
      26: getfield      #37                 // Field pathParameters:Ljava/util/Map;
      29: aload_1
      30: aload_2
      31: invokevirtual #38                 // Method org/apache/tomcat/websocket/pojo/PojoMethodMapping.getOnCloseArgs:(Ljava/util/Map;Ljavax/websocket/Session;Ljavax/websocket/CloseReason;)[Ljava/lang/Object;
      34: invokevirtual #13                 // Method java/lang/reflect/Method.invoke:(Ljava/lang/Object;[Ljava/lang/Object;)Ljava/lang/Object;
      37: pop
      38: goto          82
      41: astore_3
      42: getstatic     #15                 // Field log:Lorg/apache/juli/logging/Log;
      45: getstatic     #16                 // Field sm:Lorg/apache/tomcat/util/res/StringManager;
      48: ldc           #39                 // String pojoEndpointBase.onCloseFail
      50: iconst_1
      51: anewarray     #18                 // class java/lang/Object
      54: dup
      55: iconst_0
      56: aload_0
      57: getfield      #36                 // Field pojo:Ljava/lang/Object;
      60: invokevirtual #19                 // Method java/lang/Object.getClass:()Ljava/lang/Class;
      63: invokevirtual #20                 // Method java/lang/Class.getName:()Ljava/lang/String;
      66: aastore
      67: invokevirtual #21                 // Method org/apache/tomcat/util/res/StringManager.getString:(Ljava/lang/String;[Ljava/lang/Object;)Ljava/lang/String;
      70: aload_3
      71: invokeinterface #22,  3           // InterfaceMethod org/apache/juli/logging/Log.error:(Ljava/lang/Object;Ljava/lang/Throwable;)V
      76: aload_0
      77: aload_1
      78: aload_3
      79: invokespecial #23                 // Method handleOnOpenOrCloseError:(Ljavax/websocket/Session;Ljava/lang/Throwable;)V
      82: aload_1
      83: invokeinterface #40,  1           // InterfaceMethod javax/websocket/Session.getMessageHandlers:()Ljava/util/Set;
      88: astore_3
      89: aload_3
      90: invokeinterface #6,  1            // InterfaceMethod java/util/Set.iterator:()Ljava/util/Iterator;
      95: astore        4
      97: aload         4
      99: invokeinterface #7,  1            // InterfaceMethod java/util/Iterator.hasNext:()Z
     104: ifeq          138
     107: aload         4
     109: invokeinterface #8,  1            // InterfaceMethod java/util/Iterator.next:()Ljava/lang/Object;
     114: checkcast     #9                  // class javax/websocket/MessageHandler
     117: astore        5
     119: aload         5
     121: instanceof    #41                 // class org/apache/tomcat/websocket/pojo/PojoMessageHandlerWholeBase
     124: ifeq          135
     127: aload         5
     129: checkcast     #41                 // class org/apache/tomcat/websocket/pojo/PojoMessageHandlerWholeBase
     132: invokevirtual #42                 // Method org/apache/tomcat/websocket/pojo/PojoMessageHandlerWholeBase.onClose:()V
     135: goto          97
     138: return
    Exception table:
       from    to  target type
          10    38    41   Class java/lang/Throwable

  public final void onError(javax.websocket.Session, java.lang.Throwable);
    Code:
       0: aload_0
       1: getfield      #34                 // Field methodMapping:Lorg/apache/tomcat/websocket/pojo/PojoMethodMapping;
       4: invokevirtual #43                 // Method org/apache/tomcat/websocket/pojo/PojoMethodMapping.getOnError:()Ljava/lang/reflect/Method;
       7: ifnonnull     47
      10: getstatic     #15                 // Field log:Lorg/apache/juli/logging/Log;
      13: getstatic     #16                 // Field sm:Lorg/apache/tomcat/util/res/StringManager;
      16: ldc           #44                 // String pojoEndpointBase.onError
      18: iconst_1
      19: anewarray     #18                 // class java/lang/Object
      22: dup
      23: iconst_0
      24: aload_0
      25: getfield      #36                 // Field pojo:Ljava/lang/Object;
      28: invokevirtual #19                 // Method java/lang/Object.getClass:()Ljava/lang/Class;
      31: invokevirtual #20                 // Method java/lang/Class.getName:()Ljava/lang/String;
      34: aastore
      35: invokevirtual #21                 // Method org/apache/tomcat/util/res/StringManager.getString:(Ljava/lang/String;[Ljava/lang/Object;)Ljava/lang/String;
      38: aload_2
      39: invokeinterface #22,  3           // InterfaceMethod org/apache/juli/logging/Log.error:(Ljava/lang/Object;Ljava/lang/Throwable;)V
      44: goto          117
      47: aload_0
      48: getfield      #34                 // Field methodMapping:Lorg/apache/tomcat/websocket/pojo/PojoMethodMapping;
      51: invokevirtual #43                 // Method org/apache/tomcat/websocket/pojo/PojoMethodMapping.getOnError:()Ljava/lang/reflect/Method;
      54: aload_0
      55: getfield      #36                 // Field pojo:Ljava/lang/Object;
      58: aload_0
      59: getfield      #34                 // Field methodMapping:Lorg/apache/tomcat/websocket/pojo/PojoMethodMapping;
      62: aload_0
      63: getfield      #37                 // Field pathParameters:Ljava/util/Map;
      66: aload_1
      67: aload_2
      68: invokevirtual #45                 // Method org/apache/tomcat/websocket/pojo/PojoMethodMapping.getOnErrorArgs:(Ljava/util/Map;Ljavax/websocket/Session;Ljava/lang/Throwable;)[Ljava/lang/Object;
      71: invokevirtual #13                 // Method java/lang/reflect/Method.invoke:(Ljava/lang/Object;[Ljava/lang/Object;)Ljava/lang/Object;
      74: pop
      75: goto          117
      78: astore_3
      79: aload_3
      80: invokestatic  #27                 // Method org/apache/tomcat/util/ExceptionUtils.handleThrowable:(Ljava/lang/Throwable;)V
      83: getstatic     #15                 // Field log:Lorg/apache/juli/logging/Log;
      86: getstatic     #16                 // Field sm:Lorg/apache/tomcat/util/res/StringManager;
      89: ldc           #46                 // String pojoEndpointBase.onErrorFail
      91: iconst_1
      92: anewarray     #18                 // class java/lang/Object
      95: dup
      96: iconst_0
      97: aload_0
      98: getfield      #36                 // Field pojo:Ljava/lang/Object;
     101: invokevirtual #19                 // Method java/lang/Object.getClass:()Ljava/lang/Class;
     104: invokevirtual #20                 // Method java/lang/Class.getName:()Ljava/lang/String;
     107: aastore
     108: invokevirtual #21                 // Method org/apache/tomcat/util/res/StringManager.getString:(Ljava/lang/String;[Ljava/lang/Object;)Ljava/lang/String;
     111: aload_3
     112: invokeinterface #22,  3           // InterfaceMethod org/apache/juli/logging/Log.error:(Ljava/lang/Object;Ljava/lang/Throwable;)V
     117: return
    Exception table:
       from    to  target type
          47    75    78   Class java/lang/Throwable

  protected java.lang.Object getPojo();
    Code:
       0: aload_0
       1: getfield      #36                 // Field pojo:Ljava/lang/Object;
       4: areturn

  protected void setPojo(java.lang.Object);
    Code:
       0: aload_0
       1: aload_1
       2: putfield      #36                 // Field pojo:Ljava/lang/Object;
       5: return

  protected java.util.Map<java.lang.String, java.lang.String> getPathParameters();
    Code:
       0: aload_0
       1: getfield      #37                 // Field pathParameters:Ljava/util/Map;
       4: areturn

  protected void setPathParameters(java.util.Map<java.lang.String, java.lang.String>);
    Code:
       0: aload_0
       1: aload_1
       2: putfield      #37                 // Field pathParameters:Ljava/util/Map;
       5: return

  protected org.apache.tomcat.websocket.pojo.PojoMethodMapping getMethodMapping();
    Code:
       0: aload_0
       1: getfield      #34                 // Field methodMapping:Lorg/apache/tomcat/websocket/pojo/PojoMethodMapping;
       4: areturn

  protected void setMethodMapping(org.apache.tomcat.websocket.pojo.PojoMethodMapping);
    Code:
       0: aload_0
       1: aload_1
       2: putfield      #34                 // Field methodMapping:Lorg/apache/tomcat/websocket/pojo/PojoMethodMapping;
       5: return

  static {};
    Code:
       0: ldc_w         #47                 // class org/apache/tomcat/websocket/pojo/PojoEndpointBase
       3: invokestatic  #48                 // Method org/apache/juli/logging/LogFactory.getLog:(Ljava/lang/Class;)Lorg/apache/juli/logging/Log;
       6: putstatic     #15                 // Field log:Lorg/apache/juli/logging/Log;
       9: ldc_w         #47                 // class org/apache/tomcat/websocket/pojo/PojoEndpointBase
      12: invokestatic  #49                 // Method org/apache/tomcat/util/res/StringManager.getManager:(Ljava/lang/Class;)Lorg/apache/tomcat/util/res/StringManager;
      15: putstatic     #16                 // Field sm:Lorg/apache/tomcat/util/res/StringManager;
      18: return
}
