Compiled from "TriGPlusReader.java"
public class de.uni_koblenz.aggrimm.icp.crypto.sign.trigplus.TriGPlusReader {
  private static java.util.ArrayList<java.lang.String> line;

  private static int l;

  private static int lines;

  private static int c;

  private static int len;

  private static java.lang.String lc;

  private static char curChar;

  private static de.uni_koblenz.aggrimm.icp.crypto.sign.graph.NamedGraph curGraph;

  private static java.util.Stack<de.uni_koblenz.aggrimm.icp.crypto.sign.graph.NamedGraph> hierarchy;

  private static de.uni_koblenz.aggrimm.icp.crypto.sign.graph.GraphCollection gc;

  private static de.uni_koblenz.aggrimm.icp.crypto.sign.graph.NamedGraph rootGraph;

  public de.uni_koblenz.aggrimm.icp.crypto.sign.trigplus.TriGPlusReader();
    Code:
       0: aload_0
       1: invokespecial #1                  // Method java/lang/Object."<init>":()V
       4: return

  public static de.uni_koblenz.aggrimm.icp.crypto.sign.graph.GraphCollection readFile(java.lang.String) throws java.lang.Exception;
    Code:
       0: aload_0
       1: iconst_1
       2: invokestatic  #2                  // Method readFile:(Ljava/lang/String;Z)Lde/uni_koblenz/aggrimm/icp/crypto/sign/graph/GraphCollection;
       5: areturn

  public static de.uni_koblenz.aggrimm.icp.crypto.sign.graph.GraphCollection readFile(java.lang.String, boolean) throws java.lang.Exception;
    Code:
       0: new           #3                  // class java/io/BufferedReader
       3: dup
       4: new           #4                  // class java/io/FileReader
       7: dup
       8: aload_0
       9: invokespecial #5                  // Method java/io/FileReader."<init>":(Ljava/lang/String;)V
      12: invokespecial #6                  // Method java/io/BufferedReader."<init>":(Ljava/io/Reader;)V
      15: astore_2
      16: new           #7                  // class java/util/ArrayList
      19: dup
      20: invokespecial #8                  // Method java/util/ArrayList."<init>":()V
      23: putstatic     #9                  // Field line:Ljava/util/ArrayList;
      26: aload_2
      27: invokevirtual #10                 // Method java/io/BufferedReader.readLine:()Ljava/lang/String;
      30: dup
      31: astore_3
      32: ifnull        46
      35: getstatic     #9                  // Field line:Ljava/util/ArrayList;
      38: aload_3
      39: invokevirtual #11                 // Method java/util/ArrayList.add:(Ljava/lang/Object;)Z
      42: pop
      43: goto          26
      46: aload_2
      47: invokevirtual #12                 // Method java/io/BufferedReader.close:()V
      50: getstatic     #9                  // Field line:Ljava/util/ArrayList;
      53: invokevirtual #13                 // Method java/util/ArrayList.size:()I
      56: putstatic     #14                 // Field lines:I
      59: iconst_0
      60: invokestatic  #15                 // Method setLine:(I)V
      63: new           #16                 // class java/util/Stack
      66: dup
      67: invokespecial #17                 // Method java/util/Stack."<init>":()V
      70: putstatic     #18                 // Field hierarchy:Ljava/util/Stack;
      73: new           #19                 // class de/uni_koblenz/aggrimm/icp/crypto/sign/graph/GraphCollection
      76: dup
      77: invokespecial #20                 // Method de/uni_koblenz/aggrimm/icp/crypto/sign/graph/GraphCollection."<init>":()V
      80: putstatic     #21                 // Field gc:Lde/uni_koblenz/aggrimm/icp/crypto/sign/graph/GraphCollection;
      83: new           #22                 // class de/uni_koblenz/aggrimm/icp/crypto/sign/graph/NamedGraph
      86: dup
      87: ldc           #23                 // String
      89: iconst_m1
      90: aconst_null
      91: invokespecial #24                 // Method de/uni_koblenz/aggrimm/icp/crypto/sign/graph/NamedGraph."<init>":(Ljava/lang/String;ILde/uni_koblenz/aggrimm/icp/crypto/sign/graph/NamedGraph;)V
      94: putstatic     #25                 // Field rootGraph:Lde/uni_koblenz/aggrimm/icp/crypto/sign/graph/NamedGraph;
      97: getstatic     #21                 // Field gc:Lde/uni_koblenz/aggrimm/icp/crypto/sign/graph/GraphCollection;
     100: getstatic     #25                 // Field rootGraph:Lde/uni_koblenz/aggrimm/icp/crypto/sign/graph/NamedGraph;
     103: invokevirtual #26                 // Method de/uni_koblenz/aggrimm/icp/crypto/sign/graph/GraphCollection.addGraph:(Lde/uni_koblenz/aggrimm/icp/crypto/sign/graph/NamedGraph;)V
     106: aconst_null
     107: putstatic     #27                 // Field curGraph:Lde/uni_koblenz/aggrimm/icp/crypto/sign/graph/NamedGraph;
     110: getstatic     #28                 // Field l:I
     113: getstatic     #14                 // Field lines:I
     116: if_icmpge     900
     119: getstatic     #29                 // Field c:I
     122: getstatic     #30                 // Field len:I
     125: if_icmpge     889
     128: iconst_2
     129: newarray       int
     131: dup
     132: iconst_0
     133: getstatic     #28                 // Field l:I
     136: iastore
     137: dup
     138: iconst_1
     139: getstatic     #29                 // Field c:I
     142: iastore
     143: astore        4
     145: invokestatic  #31                 // Method parseSequence:()[Ljava/lang/String;
     148: astore        5
     150: iconst_2
     151: newarray       int
     153: dup
     154: iconst_0
     155: getstatic     #28                 // Field l:I
     158: iastore
     159: dup
     160: iconst_1
     161: getstatic     #29                 // Field c:I
     164: iastore
     165: astore        6
     167: invokestatic  #31                 // Method parseSequence:()[Ljava/lang/String;
     170: astore        7
     172: aload         5
     174: iconst_1
     175: aaload
     176: invokevirtual #32                 // Method java/lang/String.length:()I
     179: ifle          878
     182: aload         5
     184: iconst_1
     185: aaload
     186: iconst_0
     187: invokevirtual #33                 // Method java/lang/String.charAt:(I)C
     190: bipush        35
     192: if_icmpne     211
     195: aload         4
     197: iconst_0
     198: iaload
     199: invokestatic  #15                 // Method setLine:(I)V
     202: getstatic     #30                 // Field len:I
     205: putstatic     #29                 // Field c:I
     208: goto          889
     211: aload         5
     213: iconst_1
     214: aaload
     215: iconst_0
     216: invokevirtual #33                 // Method java/lang/String.charAt:(I)C
     219: bipush        64
     221: if_icmpne     405
     224: aload         5
     226: iconst_1
     227: aaload
     228: ldc           #34                 // String @prefix
     230: invokevirtual #35                 // Method java/lang/String.equals:(Ljava/lang/Object;)Z
     233: ifeq          284
     236: invokestatic  #31                 // Method parseSequence:()[Ljava/lang/String;
     239: astore        8
     241: getstatic     #21                 // Field gc:Lde/uni_koblenz/aggrimm/icp/crypto/sign/graph/GraphCollection;
     244: new           #36                 // class de/uni_koblenz/aggrimm/icp/crypto/sign/graph/Prefix
     247: dup
     248: aload         7
     250: iconst_1
     251: aaload
     252: aload         8
     254: iconst_1
     255: aaload
     256: invokespecial #37                 // Method de/uni_koblenz/aggrimm/icp/crypto/sign/graph/Prefix."<init>":(Ljava/lang/String;Ljava/lang/String;)V
     259: invokevirtual #38                 // Method de/uni_koblenz/aggrimm/icp/crypto/sign/graph/GraphCollection.addPrefix:(Lde/uni_koblenz/aggrimm/icp/crypto/sign/graph/Prefix;)V
     262: invokestatic  #39                 // Method peek:()C
     265: putstatic     #40                 // Field curChar:C
     268: getstatic     #40                 // Field curChar:C
     271: bipush        46
     273: if_icmpeq     281
     276: ldc           #41                 // String Expecting \'.\' literal to end \'@prefix\' directive
     278: invokestatic  #42                 // Method parseError:(Ljava/lang/String;)V
     281: goto          878
     284: aload         5
     286: iconst_1
     287: aaload
     288: ldc           #43                 // String @base
     290: invokevirtual #35                 // Method java/lang/String.equals:(Ljava/lang/Object;)Z
     293: ifeq          368
     296: aload         7
     298: iconst_1
     299: aaload
     300: ldc           #44                 // String <
     302: invokevirtual #45                 // Method java/lang/String.startsWith:(Ljava/lang/String;)Z
     305: ifne          341
     308: new           #46                 // class java/lang/StringBuilder
     311: dup
     312: invokespecial #47                 // Method java/lang/StringBuilder."<init>":()V
     315: ldc           #48                 // String Expecting IRI after \'@base\' directive (found \'
     317: invokevirtual #49                 // Method java/lang/StringBuilder.append:(Ljava/lang/String;)Ljava/lang/StringBuilder;
     320: aload         7
     322: iconst_1
     323: aaload
     324: invokevirtual #49                 // Method java/lang/StringBuilder.append:(Ljava/lang/String;)Ljava/lang/StringBuilder;
     327: ldc           #50                 // String \')
     329: invokevirtual #49                 // Method java/lang/StringBuilder.append:(Ljava/lang/String;)Ljava/lang/StringBuilder;
     332: invokevirtual #51                 // Method java/lang/StringBuilder.toString:()Ljava/lang/String;
     335: invokestatic  #42                 // Method parseError:(Ljava/lang/String;)V
     338: goto          346
     341: ldc           #52                 // String \'@base\' is not supported by this parser
     343: invokestatic  #42                 // Method parseError:(Ljava/lang/String;)V
     346: invokestatic  #39                 // Method peek:()C
     349: putstatic     #40                 // Field curChar:C
     352: getstatic     #40                 // Field curChar:C
     355: bipush        46
     357: if_icmpeq     878
     360: ldc           #53                 // String Expecting \'.\' literal to end \'@base\' directive
     362: invokestatic  #42                 // Method parseError:(Ljava/lang/String;)V
     365: goto          878
     368: new           #46                 // class java/lang/StringBuilder
     371: dup
     372: invokespecial #47                 // Method java/lang/StringBuilder."<init>":()V
     375: ldc           #54                 // String Expecting \'prefix\' or \'base\' literal after \'@\' for a directive (found \'
     377: invokevirtual #49                 // Method java/lang/StringBuilder.append:(Ljava/lang/String;)Ljava/lang/StringBuilder;
     380: aload         5
     382: iconst_1
     383: aaload
     384: iconst_1
     385: invokevirtual #55                 // Method java/lang/String.substring:(I)Ljava/lang/String;
     388: invokevirtual #49                 // Method java/lang/StringBuilder.append:(Ljava/lang/String;)Ljava/lang/StringBuilder;
     391: ldc           #50                 // String \')
     393: invokevirtual #49                 // Method java/lang/StringBuilder.append:(Ljava/lang/String;)Ljava/lang/StringBuilder;
     396: invokevirtual #51                 // Method java/lang/StringBuilder.toString:()Ljava/lang/String;
     399: invokestatic  #42                 // Method parseError:(Ljava/lang/String;)V
     402: goto          878
     405: aload         5
     407: iconst_1
     408: aaload
     409: ldc           #56                 // String }
     411: invokevirtual #35                 // Method java/lang/String.equals:(Ljava/lang/Object;)Z
     414: ifeq          483
     417: getstatic     #18                 // Field hierarchy:Ljava/util/Stack;
     420: invokevirtual #57                 // Method java/util/Stack.size:()I
     423: ifle          475
     426: getstatic     #18                 // Field hierarchy:Ljava/util/Stack;
     429: invokevirtual #58                 // Method java/util/Stack.pop:()Ljava/lang/Object;
     432: pop
     433: getstatic     #18                 // Field hierarchy:Ljava/util/Stack;
     436: invokevirtual #57                 // Method java/util/Stack.size:()I
     439: ifle          457
     442: getstatic     #18                 // Field hierarchy:Ljava/util/Stack;
     445: invokevirtual #59                 // Method java/util/Stack.peek:()Ljava/lang/Object;
     448: checkcast     #22                 // class de/uni_koblenz/aggrimm/icp/crypto/sign/graph/NamedGraph
     451: putstatic     #27                 // Field curGraph:Lde/uni_koblenz/aggrimm/icp/crypto/sign/graph/NamedGraph;
     454: goto          461
     457: aconst_null
     458: putstatic     #27                 // Field curGraph:Lde/uni_koblenz/aggrimm/icp/crypto/sign/graph/NamedGraph;
     461: aload         6
     463: iconst_0
     464: iaload
     465: aload         6
     467: iconst_1
     468: iaload
     469: invokestatic  #60                 // Method jumpTo:(II)V
     472: goto          878
     475: ldc           #61                 // String Unexpected \'}\' literal. There is no graph which could be closed.
     477: invokestatic  #42                 // Method parseError:(Ljava/lang/String;)V
     480: goto          878
     483: aload         5
     485: iconst_1
     486: aaload
     487: ldc           #62                 // String {
     489: invokevirtual #35                 // Method java/lang/String.equals:(Ljava/lang/Object;)Z
     492: ifne          519
     495: aload         7
     497: iconst_1
     498: aaload
     499: ldc           #62                 // String {
     501: invokevirtual #35                 // Method java/lang/String.equals:(Ljava/lang/Object;)Z
     504: ifne          519
     507: aload         7
     509: iconst_1
     510: aaload
     511: ldc           #63                 // String =
     513: invokevirtual #35                 // Method java/lang/String.equals:(Ljava/lang/Object;)Z
     516: ifeq          837
     519: aload         7
     521: iconst_1
     522: aaload
     523: ldc           #63                 // String =
     525: invokevirtual #35                 // Method java/lang/String.equals:(Ljava/lang/Object;)Z
     528: ifeq          553
     531: iconst_2
     532: newarray       int
     534: dup
     535: iconst_0
     536: getstatic     #28                 // Field l:I
     539: iastore
     540: dup
     541: iconst_1
     542: getstatic     #29                 // Field c:I
     545: iastore
     546: astore        6
     548: invokestatic  #31                 // Method parseSequence:()[Ljava/lang/String;
     551: astore        7
     553: aload         7
     555: iconst_1
     556: aaload
     557: ldc           #62                 // String {
     559: invokevirtual #35                 // Method java/lang/String.equals:(Ljava/lang/Object;)Z
     562: ifeq          582
     565: aload         5
     567: iconst_1
     568: aaload
     569: astore        8
     571: getstatic     #29                 // Field c:I
     574: iconst_1
     575: isub
     576: putstatic     #29                 // Field c:I
     579: goto          597
     582: ldc           #23                 // String
     584: astore        8
     586: aload         6
     588: iconst_0
     589: iaload
     590: aload         6
     592: iconst_1
     593: iaload
     594: invokestatic  #60                 // Method jumpTo:(II)V
     597: aconst_null
     598: astore        9
     600: getstatic     #27                 // Field curGraph:Lde/uni_koblenz/aggrimm/icp/crypto/sign/graph/NamedGraph;
     603: ifnull        679
     606: getstatic     #27                 // Field curGraph:Lde/uni_koblenz/aggrimm/icp/crypto/sign/graph/NamedGraph;
     609: invokevirtual #64                 // Method de/uni_koblenz/aggrimm/icp/crypto/sign/graph/NamedGraph.getChildren:()Ljava/util/LinkedList;
     612: invokevirtual #65                 // Method java/util/LinkedList.iterator:()Ljava/util/Iterator;
     615: astore        10
     617: aload         10
     619: invokeinterface #66,  1           // InterfaceMethod java/util/Iterator.hasNext:()Z
     624: ifeq          676
     627: aload         10
     629: invokeinterface #67,  1           // InterfaceMethod java/util/Iterator.next:()Ljava/lang/Object;
     634: checkcast     #22                 // class de/uni_koblenz/aggrimm/icp/crypto/sign/graph/NamedGraph
     637: astore        11
     639: aload         11
     641: invokevirtual #68                 // Method de/uni_koblenz/aggrimm/icp/crypto/sign/graph/NamedGraph.getName:()Ljava/lang/String;
     644: aload         8
     646: invokevirtual #35                 // Method java/lang/String.equals:(Ljava/lang/Object;)Z
     649: ifeq          673
     652: aload         11
     654: invokevirtual #69                 // Method de/uni_koblenz/aggrimm/icp/crypto/sign/graph/NamedGraph.getDepth:()I
     657: getstatic     #18                 // Field hierarchy:Ljava/util/Stack;
     660: invokevirtual #57                 // Method java/util/Stack.size:()I
     663: if_icmpne     673
     666: aload         11
     668: astore        9
     670: goto          676
     673: goto          617
     676: goto          749
     679: getstatic     #21                 // Field gc:Lde/uni_koblenz/aggrimm/icp/crypto/sign/graph/GraphCollection;
     682: invokevirtual #70                 // Method de/uni_koblenz/aggrimm/icp/crypto/sign/graph/GraphCollection.getGraphs:()Ljava/util/LinkedList;
     685: invokevirtual #65                 // Method java/util/LinkedList.iterator:()Ljava/util/Iterator;
     688: astore        10
     690: aload         10
     692: invokeinterface #66,  1           // InterfaceMethod java/util/Iterator.hasNext:()Z
     697: ifeq          749
     700: aload         10
     702: invokeinterface #67,  1           // InterfaceMethod java/util/Iterator.next:()Ljava/lang/Object;
     707: checkcast     #22                 // class de/uni_koblenz/aggrimm/icp/crypto/sign/graph/NamedGraph
     710: astore        11
     712: aload         11
     714: invokevirtual #68                 // Method de/uni_koblenz/aggrimm/icp/crypto/sign/graph/NamedGraph.getName:()Ljava/lang/String;
     717: aload         8
     719: invokevirtual #35                 // Method java/lang/String.equals:(Ljava/lang/Object;)Z
     722: ifeq          746
     725: aload         11
     727: invokevirtual #69                 // Method de/uni_koblenz/aggrimm/icp/crypto/sign/graph/NamedGraph.getDepth:()I
     730: getstatic     #18                 // Field hierarchy:Ljava/util/Stack;
     733: invokevirtual #57                 // Method java/util/Stack.size:()I
     736: if_icmpne     746
     739: aload         11
     741: astore        9
     743: goto          749
     746: goto          690
     749: aload         9
     751: ifnonnull     819
     754: getstatic     #18                 // Field hierarchy:Ljava/util/Stack;
     757: invokevirtual #57                 // Method java/util/Stack.size:()I
     760: ifne          789
     763: new           #22                 // class de/uni_koblenz/aggrimm/icp/crypto/sign/graph/NamedGraph
     766: dup
     767: aload         8
     769: iconst_0
     770: aconst_null
     771: invokespecial #24                 // Method de/uni_koblenz/aggrimm/icp/crypto/sign/graph/NamedGraph."<init>":(Ljava/lang/String;ILde/uni_koblenz/aggrimm/icp/crypto/sign/graph/NamedGraph;)V
     774: putstatic     #27                 // Field curGraph:Lde/uni_koblenz/aggrimm/icp/crypto/sign/graph/NamedGraph;
     777: getstatic     #21                 // Field gc:Lde/uni_koblenz/aggrimm/icp/crypto/sign/graph/GraphCollection;
     780: getstatic     #27                 // Field curGraph:Lde/uni_koblenz/aggrimm/icp/crypto/sign/graph/NamedGraph;
     783: invokevirtual #26                 // Method de/uni_koblenz/aggrimm/icp/crypto/sign/graph/GraphCollection.addGraph:(Lde/uni_koblenz/aggrimm/icp/crypto/sign/graph/NamedGraph;)V
     786: goto          824
     789: new           #22                 // class de/uni_koblenz/aggrimm/icp/crypto/sign/graph/NamedGraph
     792: dup
     793: aload         8
     795: getstatic     #18                 // Field hierarchy:Ljava/util/Stack;
     798: invokevirtual #57                 // Method java/util/Stack.size:()I
     801: getstatic     #18                 // Field hierarchy:Ljava/util/Stack;
     804: invokevirtual #59                 // Method java/util/Stack.peek:()Ljava/lang/Object;
     807: checkcast     #22                 // class de/uni_koblenz/aggrimm/icp/crypto/sign/graph/NamedGraph
     810: invokespecial #24                 // Method de/uni_koblenz/aggrimm/icp/crypto/sign/graph/NamedGraph."<init>":(Ljava/lang/String;ILde/uni_koblenz/aggrimm/icp/crypto/sign/graph/NamedGraph;)V
     813: putstatic     #27                 // Field curGraph:Lde/uni_koblenz/aggrimm/icp/crypto/sign/graph/NamedGraph;
     816: goto          824
     819: aload         9
     821: putstatic     #27                 // Field curGraph:Lde/uni_koblenz/aggrimm/icp/crypto/sign/graph/NamedGraph;
     824: getstatic     #18                 // Field hierarchy:Ljava/util/Stack;
     827: getstatic     #27                 // Field curGraph:Lde/uni_koblenz/aggrimm/icp/crypto/sign/graph/NamedGraph;
     830: invokevirtual #71                 // Method java/util/Stack.push:(Ljava/lang/Object;)Ljava/lang/Object;
     833: pop
     834: goto          878
     837: iconst_3
     838: anewarray     #72                 // class java/lang/String
     841: astore        8
     843: aload         5
     845: iconst_0
     846: aaload
     847: ldc           #73                 // String [
     849: invokevirtual #35                 // Method java/lang/String.equals:(Ljava/lang/Object;)Z
     852: ifeq          858
     855: goto          878
     858: aload         6
     860: iconst_1
     861: iaload
     862: putstatic     #29                 // Field c:I
     865: aload         8
     867: iconst_0
     868: aload         5
     870: iconst_1
     871: aaload
     872: aastore
     873: aload         8
     875: invokestatic  #74                 // Method parsePredicateObjectList:([Ljava/lang/String;)V
     878: getstatic     #29                 // Field c:I
     881: iconst_1
     882: iadd
     883: putstatic     #29                 // Field c:I
     886: goto          119
     889: getstatic     #28                 // Field l:I
     892: iconst_1
     893: iadd
     894: invokestatic  #15                 // Method setLine:(I)V
     897: goto          110
     900: iload_1
     901: ifeq          910
     904: getstatic     #21                 // Field gc:Lde/uni_koblenz/aggrimm/icp/crypto/sign/graph/GraphCollection;
     907: invokevirtual #75                 // Method de/uni_koblenz/aggrimm/icp/crypto/sign/graph/GraphCollection.resolvePrefixes:()V
     910: getstatic     #21                 // Field gc:Lde/uni_koblenz/aggrimm/icp/crypto/sign/graph/GraphCollection;
     913: areturn

  private static void setLine(int);
    Code:
       0: iload_0
       1: putstatic     #28                 // Field l:I
       4: iload_0
       5: getstatic     #14                 // Field lines:I
       8: if_icmpge     29
      11: getstatic     #9                  // Field line:Ljava/util/ArrayList;
      14: getstatic     #28                 // Field l:I
      17: invokevirtual #76                 // Method java/util/ArrayList.get:(I)Ljava/lang/Object;
      20: checkcast     #72                 // class java/lang/String
      23: putstatic     #77                 // Field lc:Ljava/lang/String;
      26: goto          34
      29: ldc           #23                 // String
      31: putstatic     #77                 // Field lc:Ljava/lang/String;
      34: getstatic     #77                 // Field lc:Ljava/lang/String;
      37: invokevirtual #32                 // Method java/lang/String.length:()I
      40: putstatic     #30                 // Field len:I
      43: iconst_0
      44: putstatic     #29                 // Field c:I
      47: return

  private static void jumpTo(int, int);
    Code:
       0: iload_0
       1: getstatic     #28                 // Field l:I
       4: if_icmpeq     11
       7: iload_0
       8: invokestatic  #15                 // Method setLine:(I)V
      11: iload_1
      12: putstatic     #29                 // Field c:I
      15: return

  private static char peek();
    Code:
       0: getstatic     #28                 // Field l:I
       3: getstatic     #14                 // Field lines:I
       6: if_icmpge     59
       9: getstatic     #29                 // Field c:I
      12: getstatic     #30                 // Field len:I
      15: if_icmpge     48
      18: getstatic     #77                 // Field lc:Ljava/lang/String;
      21: getstatic     #29                 // Field c:I
      24: invokevirtual #33                 // Method java/lang/String.charAt:(I)C
      27: istore_0
      28: iload_0
      29: invokestatic  #78                 // Method java/lang/Character.isWhitespace:(C)Z
      32: ifne          37
      35: iload_0
      36: ireturn
      37: getstatic     #29                 // Field c:I
      40: iconst_1
      41: iadd
      42: putstatic     #29                 // Field c:I
      45: goto          9
      48: getstatic     #28                 // Field l:I
      51: iconst_1
      52: iadd
      53: invokestatic  #15                 // Method setLine:(I)V
      56: goto          0
      59: bipush        32
      61: ireturn

  private static void parseError(java.lang.String) throws java.lang.Exception;
    Code:
       0: new           #79                 // class java/lang/Exception
       3: dup
       4: new           #46                 // class java/lang/StringBuilder
       7: dup
       8: invokespecial #47                 // Method java/lang/StringBuilder."<init>":()V
      11: ldc           #80                 // String TriG+ Parser Error (
      13: invokevirtual #49                 // Method java/lang/StringBuilder.append:(Ljava/lang/String;)Ljava/lang/StringBuilder;
      16: getstatic     #28                 // Field l:I
      19: invokevirtual #81                 // Method java/lang/StringBuilder.append:(I)Ljava/lang/StringBuilder;
      22: ldc           #82                 // String :
      24: invokevirtual #49                 // Method java/lang/StringBuilder.append:(Ljava/lang/String;)Ljava/lang/StringBuilder;
      27: getstatic     #29                 // Field c:I
      30: invokevirtual #81                 // Method java/lang/StringBuilder.append:(I)Ljava/lang/StringBuilder;
      33: ldc           #83                 // String ):
      35: invokevirtual #49                 // Method java/lang/StringBuilder.append:(Ljava/lang/String;)Ljava/lang/StringBuilder;
      38: aload_0
      39: invokevirtual #49                 // Method java/lang/StringBuilder.append:(Ljava/lang/String;)Ljava/lang/StringBuilder;
      42: invokevirtual #51                 // Method java/lang/StringBuilder.toString:()Ljava/lang/String;
      45: invokespecial #84                 // Method java/lang/Exception."<init>":(Ljava/lang/String;)V
      48: athrow

  private static void parseDebug(java.lang.String);
    Code:
       0: getstatic     #85                 // Field java/lang/System.out:Ljava/io/PrintStream;
       3: new           #46                 // class java/lang/StringBuilder
       6: dup
       7: invokespecial #47                 // Method java/lang/StringBuilder."<init>":()V
      10: ldc           #86                 // String TriG+ Parser Debug (
      12: invokevirtual #49                 // Method java/lang/StringBuilder.append:(Ljava/lang/String;)Ljava/lang/StringBuilder;
      15: getstatic     #28                 // Field l:I
      18: invokevirtual #81                 // Method java/lang/StringBuilder.append:(I)Ljava/lang/StringBuilder;
      21: ldc           #82                 // String :
      23: invokevirtual #49                 // Method java/lang/StringBuilder.append:(Ljava/lang/String;)Ljava/lang/StringBuilder;
      26: getstatic     #29                 // Field c:I
      29: invokevirtual #81                 // Method java/lang/StringBuilder.append:(I)Ljava/lang/StringBuilder;
      32: ldc           #83                 // String ):
      34: invokevirtual #49                 // Method java/lang/StringBuilder.append:(Ljava/lang/String;)Ljava/lang/StringBuilder;
      37: aload_0
      38: invokevirtual #49                 // Method java/lang/StringBuilder.append:(Ljava/lang/String;)Ljava/lang/StringBuilder;
      41: invokevirtual #51                 // Method java/lang/StringBuilder.toString:()Ljava/lang/String;
      44: invokevirtual #87                 // Method java/io/PrintStream.println:(Ljava/lang/String;)V
      47: return

  private static void parsePredicateObjectList(java.lang.String[]) throws java.lang.Exception;
    Code:
       0: invokestatic  #31                 // Method parseSequence:()[Ljava/lang/String;
       3: astore_1
       4: aload_0
       5: iconst_1
       6: aload_1
       7: iconst_1
       8: aaload
       9: aastore
      10: iconst_1
      11: istore_2
      12: iload_2
      13: ifeq          267
      16: iconst_0
      17: istore_2
      18: getstatic     #28                 // Field l:I
      21: istore_3
      22: getstatic     #29                 // Field c:I
      25: istore        4
      27: invokestatic  #88                 // Method parseComplexSequence:()Ljava/lang/String;
      30: astore        5
      32: getstatic     #28                 // Field l:I
      35: istore        6
      37: getstatic     #29                 // Field c:I
      40: istore        7
      42: aload         5
      44: ldc           #73                 // String [
      46: invokevirtual #45                 // Method java/lang/String.startsWith:(Ljava/lang/String;)Z
      49: ifeq          126
      52: iload_3
      53: invokestatic  #15                 // Method setLine:(I)V
      56: iload         4
      58: iconst_1
      59: iadd
      60: putstatic     #29                 // Field c:I
      63: iconst_3
      64: anewarray     #72                 // class java/lang/String
      67: dup
      68: iconst_0
      69: aload_0
      70: iconst_2
      71: aaload
      72: aastore
      73: dup
      74: iconst_1
      75: ldc           #23                 // String
      77: aastore
      78: dup
      79: iconst_2
      80: ldc           #23                 // String
      82: aastore
      83: invokestatic  #74                 // Method parsePredicateObjectList:([Ljava/lang/String;)V
      86: iload         6
      88: invokestatic  #15                 // Method setLine:(I)V
      91: iload         7
      93: putstatic     #29                 // Field c:I
      96: getstatic     #29                 // Field c:I
      99: istore        8
     101: invokestatic  #39                 // Method peek:()C
     104: istore        9
     106: iload         9
     108: bipush        44
     110: if_icmpne     118
     113: iconst_1
     114: istore_2
     115: goto          123
     118: iload         8
     120: putstatic     #29                 // Field c:I
     123: goto          264
     126: aload         5
     128: ldc           #89                 // String ,
     130: invokevirtual #90                 // Method java/lang/String.endsWith:(Ljava/lang/String;)Z
     133: ifeq          156
     136: iconst_1
     137: istore_2
     138: aload         5
     140: iconst_0
     141: aload         5
     143: invokevirtual #32                 // Method java/lang/String.length:()I
     146: iconst_1
     147: isub
     148: invokevirtual #91                 // Method java/lang/String.substring:(II)Ljava/lang/String;
     151: astore        5
     153: goto          183
     156: getstatic     #29                 // Field c:I
     159: istore        8
     161: invokestatic  #39                 // Method peek:()C
     164: istore        9
     166: iload         9
     168: bipush        44
     170: if_icmpne     178
     173: iconst_1
     174: istore_2
     175: goto          183
     178: iload         8
     180: putstatic     #29                 // Field c:I
     183: aload_0
     184: iconst_2
     185: aload         5
     187: aastore
     188: getstatic     #29                 // Field c:I
     191: istore        8
     193: invokestatic  #39                 // Method peek:()C
     196: istore        9
     198: iload_2
     199: ifne          247
     202: iload         9
     204: bipush        59
     206: if_icmpeq     247
     209: iload         9
     211: bipush        46
     213: if_icmpeq     247
     216: iload         9
     218: bipush        125
     220: if_icmpeq     247
     223: invokestatic  #31                 // Method parseSequence:()[Ljava/lang/String;
     226: iconst_1
     227: aaload
     228: astore        10
     230: aload_0
     231: iconst_0
     232: aaload
     233: aload_0
     234: iconst_1
     235: aaload
     236: aload_0
     237: iconst_2
     238: aaload
     239: aload         10
     241: invokestatic  #92                 // Method addQuad:(Ljava/lang/String;Ljava/lang/String;Ljava/lang/String;Ljava/lang/String;)V
     244: goto          264
     247: iload         8
     249: putstatic     #29                 // Field c:I
     252: aload_0
     253: iconst_0
     254: aaload
     255: aload_0
     256: iconst_1
     257: aaload
     258: aload_0
     259: iconst_2
     260: aaload
     261: invokestatic  #93                 // Method addTriple:(Ljava/lang/String;Ljava/lang/String;Ljava/lang/String;)V
     264: goto          12
     267: invokestatic  #39                 // Method peek:()C
     270: putstatic     #40                 // Field curChar:C
     273: getstatic     #40                 // Field curChar:C
     276: bipush        59
     278: if_icmpeq     327
     281: getstatic     #40                 // Field curChar:C
     284: bipush        46
     286: if_icmpeq     326
     289: getstatic     #40                 // Field curChar:C
     292: bipush        125
     294: if_icmpeq     326
     297: new           #46                 // class java/lang/StringBuilder
     300: dup
     301: invokespecial #47                 // Method java/lang/StringBuilder."<init>":()V
     304: ldc           #94                 // String Expecting \'.\' or \';\' to end triple definition (found \'
     306: invokevirtual #49                 // Method java/lang/StringBuilder.append:(Ljava/lang/String;)Ljava/lang/StringBuilder;
     309: getstatic     #40                 // Field curChar:C
     312: invokevirtual #95                 // Method java/lang/StringBuilder.append:(C)Ljava/lang/StringBuilder;
     315: ldc           #50                 // String \')
     317: invokevirtual #49                 // Method java/lang/StringBuilder.append:(Ljava/lang/String;)Ljava/lang/StringBuilder;
     320: invokevirtual #51                 // Method java/lang/StringBuilder.toString:()Ljava/lang/String;
     323: invokestatic  #42                 // Method parseError:(Ljava/lang/String;)V
     326: return
     327: getstatic     #29                 // Field c:I
     330: iconst_1
     331: iadd
     332: putstatic     #29                 // Field c:I
     335: goto          0

  private static java.lang.String[] parseSequence();
    Code:
       0: iconst_3
       1: anewarray     #72                 // class java/lang/String
       4: astore_0
       5: iconst_0
       6: istore_1
       7: invokestatic  #39                 // Method peek:()C
      10: putstatic     #40                 // Field curChar:C
      13: getstatic     #40                 // Field curChar:C
      16: lookupswitch  { // 5
                    34: 107
                    39: 175
                    40: 94
                    60: 68
                    91: 81
               default: 243
          }
      68: aload_0
      69: iconst_0
      70: ldc           #44                 // String <
      72: aastore
      73: aload_0
      74: iconst_2
      75: ldc           #96                 // String >
      77: aastore
      78: goto          253
      81: aload_0
      82: iconst_0
      83: ldc           #73                 // String [
      85: aastore
      86: aload_0
      87: iconst_2
      88: ldc           #97                 // String ]
      90: aastore
      91: goto          253
      94: aload_0
      95: iconst_0
      96: ldc           #98                 // String (
      98: aastore
      99: aload_0
     100: iconst_2
     101: ldc           #99                 // String )
     103: aastore
     104: goto          253
     107: aload_0
     108: iconst_0
     109: ldc           #100                // String \"
     111: aastore
     112: aload_0
     113: iconst_2
     114: ldc           #100                // String \"
     116: aastore
     117: getstatic     #29                 // Field c:I
     120: iconst_5
     121: iadd
     122: getstatic     #30                 // Field len:I
     125: if_icmpgt     170
     128: getstatic     #77                 // Field lc:Ljava/lang/String;
     131: getstatic     #29                 // Field c:I
     134: iconst_1
     135: iadd
     136: invokevirtual #33                 // Method java/lang/String.charAt:(I)C
     139: bipush        34
     141: if_icmpne     170
     144: getstatic     #77                 // Field lc:Ljava/lang/String;
     147: getstatic     #29                 // Field c:I
     150: iconst_2
     151: iadd
     152: invokevirtual #33                 // Method java/lang/String.charAt:(I)C
     155: bipush        34
     157: if_icmpne     170
     160: aload_0
     161: iconst_0
     162: ldc           #101                // String \"\"\"
     164: aastore
     165: aload_0
     166: iconst_2
     167: ldc           #101                // String \"\"\"
     169: aastore
     170: iconst_1
     171: istore_1
     172: goto          253
     175: aload_0
     176: iconst_0
     177: ldc           #102                // String \'
     179: aastore
     180: aload_0
     181: iconst_2
     182: ldc           #102                // String \'
     184: aastore
     185: getstatic     #29                 // Field c:I
     188: iconst_5
     189: iadd
     190: getstatic     #30                 // Field len:I
     193: if_icmpgt     238
     196: getstatic     #77                 // Field lc:Ljava/lang/String;
     199: getstatic     #29                 // Field c:I
     202: iconst_1
     203: iadd
     204: invokevirtual #33                 // Method java/lang/String.charAt:(I)C
     207: bipush        39
     209: if_icmpne     238
     212: getstatic     #77                 // Field lc:Ljava/lang/String;
     215: getstatic     #29                 // Field c:I
     218: iconst_2
     219: iadd
     220: invokevirtual #33                 // Method java/lang/String.charAt:(I)C
     223: bipush        39
     225: if_icmpne     238
     228: aload_0
     229: iconst_0
     230: ldc           #103                // String \'\'\'
     232: aastore
     233: aload_0
     234: iconst_2
     235: ldc           #103                // String \'\'\'
     237: aastore
     238: iconst_1
     239: istore_1
     240: goto          253
     243: aload_0
     244: iconst_0
     245: ldc           #23                 // String
     247: aastore
     248: aload_0
     249: iconst_2
     250: ldc           #23                 // String
     252: aastore
     253: getstatic     #29                 // Field c:I
     256: istore_2
     257: getstatic     #29                 // Field c:I
     260: aload_0
     261: iconst_0
     262: aaload
     263: invokevirtual #32                 // Method java/lang/String.length:()I
     266: iadd
     267: putstatic     #29                 // Field c:I
     270: aload_0
     271: iconst_2
     272: aaload
     273: invokevirtual #32                 // Method java/lang/String.length:()I
     276: istore_3
     277: getstatic     #29                 // Field c:I
     280: getstatic     #30                 // Field len:I
     283: if_icmpge     503
     286: iload_3
     287: ifne          336
     290: getstatic     #77                 // Field lc:Ljava/lang/String;
     293: getstatic     #29                 // Field c:I
     296: invokevirtual #33                 // Method java/lang/String.charAt:(I)C
     299: putstatic     #40                 // Field curChar:C
     302: getstatic     #40                 // Field curChar:C
     305: invokestatic  #78                 // Method java/lang/Character.isWhitespace:(C)Z
     308: ifeq          492
     311: getstatic     #29                 // Field c:I
     314: iconst_1
     315: iadd
     316: putstatic     #29                 // Field c:I
     319: aload_0
     320: iconst_1
     321: getstatic     #77                 // Field lc:Ljava/lang/String;
     324: iload_2
     325: getstatic     #29                 // Field c:I
     328: iconst_1
     329: isub
     330: invokevirtual #91                 // Method java/lang/String.substring:(II)Ljava/lang/String;
     333: aastore
     334: aload_0
     335: areturn
     336: getstatic     #77                 // Field lc:Ljava/lang/String;
     339: getstatic     #29                 // Field c:I
     342: getstatic     #29                 // Field c:I
     345: iload_3
     346: iadd
     347: invokevirtual #91                 // Method java/lang/String.substring:(II)Ljava/lang/String;
     350: aload_0
     351: iconst_2
     352: aaload
     353: invokevirtual #35                 // Method java/lang/String.equals:(Ljava/lang/Object;)Z
     356: ifeq          492
     359: iload_1
     360: ifeq          388
     363: getstatic     #29                 // Field c:I
     366: ifle          388
     369: getstatic     #77                 // Field lc:Ljava/lang/String;
     372: getstatic     #29                 // Field c:I
     375: iconst_1
     376: isub
     377: invokevirtual #33                 // Method java/lang/String.charAt:(I)C
     380: bipush        92
     382: if_icmpne     388
     385: goto          492
     388: getstatic     #29                 // Field c:I
     391: iload_3
     392: iadd
     393: putstatic     #29                 // Field c:I
     396: iload_1
     397: ifeq          469
     400: getstatic     #29                 // Field c:I
     403: iload_3
     404: iadd
     405: iconst_2
     406: iadd
     407: getstatic     #30                 // Field len:I
     410: if_icmpge     469
     413: getstatic     #77                 // Field lc:Ljava/lang/String;
     416: getstatic     #29                 // Field c:I
     419: iload_3
     420: iadd
     421: iconst_1
     422: isub
     423: getstatic     #29                 // Field c:I
     426: iload_3
     427: iadd
     428: invokevirtual #91                 // Method java/lang/String.substring:(II)Ljava/lang/String;
     431: ldc           #104                // String @
     433: invokevirtual #35                 // Method java/lang/String.equals:(Ljava/lang/Object;)Z
     436: ifne          467
     439: getstatic     #77                 // Field lc:Ljava/lang/String;
     442: getstatic     #29                 // Field c:I
     445: iload_3
     446: iadd
     447: iconst_1
     448: isub
     449: getstatic     #29                 // Field c:I
     452: iload_3
     453: iadd
     454: iconst_1
     455: iadd
     456: invokevirtual #91                 // Method java/lang/String.substring:(II)Ljava/lang/String;
     459: ldc           #105                // String ^^
     461: invokevirtual #35                 // Method java/lang/String.equals:(Ljava/lang/Object;)Z
     464: ifeq          469
     467: iconst_0
     468: istore_3
     469: iload_3
     470: ifeq          492
     473: aload_0
     474: iconst_1
     475: getstatic     #77                 // Field lc:Ljava/lang/String;
     478: iload_2
     479: getstatic     #29                 // Field c:I
     482: iload_3
     483: iadd
     484: iconst_1
     485: isub
     486: invokevirtual #91                 // Method java/lang/String.substring:(II)Ljava/lang/String;
     489: aastore
     490: aload_0
     491: areturn
     492: getstatic     #29                 // Field c:I
     495: iconst_1
     496: iadd
     497: putstatic     #29                 // Field c:I
     500: goto          277
     503: getstatic     #29                 // Field c:I
     506: iconst_1
     507: iadd
     508: putstatic     #29                 // Field c:I
     511: aload_0
     512: iconst_1
     513: getstatic     #77                 // Field lc:Ljava/lang/String;
     516: iload_2
     517: invokevirtual #55                 // Method java/lang/String.substring:(I)Ljava/lang/String;
     520: aastore
     521: aload_0
     522: areturn

  private static java.lang.String parseComplexSequence();
    Code:
       0: invokestatic  #39                 // Method peek:()C
       3: putstatic     #40                 // Field curChar:C
       6: getstatic     #40                 // Field curChar:C
       9: bipush        91
      11: if_icmpne     174
      14: getstatic     #29                 // Field c:I
      17: iconst_1
      18: iadd
      19: putstatic     #29                 // Field c:I
      22: iconst_1
      23: istore_0
      24: ldc           #73                 // String [
      26: astore_1
      27: getstatic     #29                 // Field c:I
      30: getstatic     #30                 // Field len:I
      33: if_icmpge     51
      36: getstatic     #77                 // Field lc:Ljava/lang/String;
      39: getstatic     #29                 // Field c:I
      42: invokevirtual #33                 // Method java/lang/String.charAt:(I)C
      45: putstatic     #40                 // Field curChar:C
      48: goto          103
      51: getstatic     #28                 // Field l:I
      54: getstatic     #14                 // Field lines:I
      57: if_icmpge     92
      60: getstatic     #28                 // Field l:I
      63: iconst_1
      64: iadd
      65: invokestatic  #15                 // Method setLine:(I)V
      68: getstatic     #29                 // Field c:I
      71: getstatic     #30                 // Field len:I
      74: if_icmpge     51
      77: getstatic     #77                 // Field lc:Ljava/lang/String;
      80: getstatic     #29                 // Field c:I
      83: invokevirtual #33                 // Method java/lang/String.charAt:(I)C
      86: putstatic     #40                 // Field curChar:C
      89: goto          92
      92: getstatic     #28                 // Field l:I
      95: getstatic     #14                 // Field lines:I
      98: if_icmplt     103
     101: aload_1
     102: areturn
     103: new           #46                 // class java/lang/StringBuilder
     106: dup
     107: invokespecial #47                 // Method java/lang/StringBuilder."<init>":()V
     110: aload_1
     111: invokevirtual #49                 // Method java/lang/StringBuilder.append:(Ljava/lang/String;)Ljava/lang/StringBuilder;
     114: getstatic     #40                 // Field curChar:C
     117: invokevirtual #95                 // Method java/lang/StringBuilder.append:(C)Ljava/lang/StringBuilder;
     120: invokevirtual #51                 // Method java/lang/StringBuilder.toString:()Ljava/lang/String;
     123: astore_1
     124: getstatic     #40                 // Field curChar:C
     127: bipush        91
     129: if_icmpne     138
     132: iinc          0, 1
     135: goto          163
     138: getstatic     #40                 // Field curChar:C
     141: bipush        93
     143: if_icmpne     163
     146: iinc          0, -1
     149: iload_0
     150: ifne          163
     153: getstatic     #29                 // Field c:I
     156: iconst_1
     157: iadd
     158: putstatic     #29                 // Field c:I
     161: aload_1
     162: areturn
     163: getstatic     #29                 // Field c:I
     166: iconst_1
     167: iadd
     168: putstatic     #29                 // Field c:I
     171: goto          27
     174: invokestatic  #31                 // Method parseSequence:()[Ljava/lang/String;
     177: iconst_1
     178: aaload
     179: areturn

  private static void addTriple(java.lang.String, java.lang.String, java.lang.String);
    Code:
       0: getstatic     #27                 // Field curGraph:Lde/uni_koblenz/aggrimm/icp/crypto/sign/graph/NamedGraph;
       3: ifnull        25
       6: getstatic     #27                 // Field curGraph:Lde/uni_koblenz/aggrimm/icp/crypto/sign/graph/NamedGraph;
       9: new           #106                // class de/uni_koblenz/aggrimm/icp/crypto/sign/graph/Triple
      12: dup
      13: aload_0
      14: aload_1
      15: aload_2
      16: invokespecial #107                // Method de/uni_koblenz/aggrimm/icp/crypto/sign/graph/Triple."<init>":(Ljava/lang/String;Ljava/lang/String;Ljava/lang/String;)V
      19: invokevirtual #108                // Method de/uni_koblenz/aggrimm/icp/crypto/sign/graph/NamedGraph.addTriple:(Lde/uni_koblenz/aggrimm/icp/crypto/sign/graph/Triple;)V
      22: goto          41
      25: getstatic     #25                 // Field rootGraph:Lde/uni_koblenz/aggrimm/icp/crypto/sign/graph/NamedGraph;
      28: new           #106                // class de/uni_koblenz/aggrimm/icp/crypto/sign/graph/Triple
      31: dup
      32: aload_0
      33: aload_1
      34: aload_2
      35: invokespecial #107                // Method de/uni_koblenz/aggrimm/icp/crypto/sign/graph/Triple."<init>":(Ljava/lang/String;Ljava/lang/String;Ljava/lang/String;)V
      38: invokevirtual #108                // Method de/uni_koblenz/aggrimm/icp/crypto/sign/graph/NamedGraph.addTriple:(Lde/uni_koblenz/aggrimm/icp/crypto/sign/graph/Triple;)V
      41: return

  private static void addQuad(java.lang.String, java.lang.String, java.lang.String, java.lang.String);
    Code:
       0: aconst_null
       1: astore        4
       3: getstatic     #21                 // Field gc:Lde/uni_koblenz/aggrimm/icp/crypto/sign/graph/GraphCollection;
       6: invokevirtual #70                 // Method de/uni_koblenz/aggrimm/icp/crypto/sign/graph/GraphCollection.getGraphs:()Ljava/util/LinkedList;
       9: invokevirtual #65                 // Method java/util/LinkedList.iterator:()Ljava/util/Iterator;
      12: astore        5
      14: aload         5
      16: invokeinterface #66,  1           // InterfaceMethod java/util/Iterator.hasNext:()Z
      21: ifeq          66
      24: aload         5
      26: invokeinterface #67,  1           // InterfaceMethod java/util/Iterator.next:()Ljava/lang/Object;
      31: checkcast     #22                 // class de/uni_koblenz/aggrimm/icp/crypto/sign/graph/NamedGraph
      34: astore        6
      36: aload         6
      38: invokevirtual #69                 // Method de/uni_koblenz/aggrimm/icp/crypto/sign/graph/NamedGraph.getDepth:()I
      41: ifne          63
      44: aload         6
      46: invokevirtual #68                 // Method de/uni_koblenz/aggrimm/icp/crypto/sign/graph/NamedGraph.getName:()Ljava/lang/String;
      49: aload_3
      50: invokevirtual #35                 // Method java/lang/String.equals:(Ljava/lang/Object;)Z
      53: ifeq          63
      56: aload         6
      58: astore        4
      60: goto          66
      63: goto          14
      66: aload         4
      68: ifnonnull     91
      71: new           #22                 // class de/uni_koblenz/aggrimm/icp/crypto/sign/graph/NamedGraph
      74: dup
      75: aload_3
      76: iconst_0
      77: aconst_null
      78: invokespecial #24                 // Method de/uni_koblenz/aggrimm/icp/crypto/sign/graph/NamedGraph."<init>":(Ljava/lang/String;ILde/uni_koblenz/aggrimm/icp/crypto/sign/graph/NamedGraph;)V
      81: astore        4
      83: getstatic     #21                 // Field gc:Lde/uni_koblenz/aggrimm/icp/crypto/sign/graph/GraphCollection;
      86: aload         4
      88: invokevirtual #26                 // Method de/uni_koblenz/aggrimm/icp/crypto/sign/graph/GraphCollection.addGraph:(Lde/uni_koblenz/aggrimm/icp/crypto/sign/graph/NamedGraph;)V
      91: aload         4
      93: new           #106                // class de/uni_koblenz/aggrimm/icp/crypto/sign/graph/Triple
      96: dup
      97: aload_0
      98: aload_1
      99: aload_2
     100: invokespecial #107                // Method de/uni_koblenz/aggrimm/icp/crypto/sign/graph/Triple."<init>":(Ljava/lang/String;Ljava/lang/String;Ljava/lang/String;)V
     103: invokevirtual #108                // Method de/uni_koblenz/aggrimm/icp/crypto/sign/graph/NamedGraph.addTriple:(Lde/uni_koblenz/aggrimm/icp/crypto/sign/graph/Triple;)V
     106: return

  static {};
    Code:
       0: iconst_0
       1: putstatic     #28                 // Field l:I
       4: iconst_0
       5: putstatic     #14                 // Field lines:I
       8: iconst_0
       9: putstatic     #29                 // Field c:I
      12: iconst_0
      13: putstatic     #30                 // Field len:I
      16: return
}
