Compiled from "InterceptingHTTPServletResponse.java"
public class org.owasp.esapi.waf.internal.InterceptingHTTPServletResponse extends javax.servlet.http.HttpServletResponseWrapper {
  private org.owasp.esapi.waf.internal.InterceptingPrintWriter ipw;

  private org.owasp.esapi.waf.internal.InterceptingServletOutputStream isos;

  private java.lang.String contentType;

  private java.util.List<org.owasp.esapi.waf.rules.AddSecureFlagRule> addSecureFlagRules;

  private java.util.List<org.owasp.esapi.waf.rules.AddHTTPOnlyFlagRule> addHTTPOnlyFlagRules;

  private boolean alreadyCalledWriter;

  private boolean alreadyCalledOutputStream;

  public org.owasp.esapi.waf.internal.InterceptingHTTPServletResponse(javax.servlet.http.HttpServletResponse, boolean, java.util.List<org.owasp.esapi.waf.rules.Rule>) throws java.io.IOException;
    Code:
       0: aload_0
       1: aload_1
       2: invokespecial #1                  // Method javax/servlet/http/HttpServletResponseWrapper."<init>":(Ljavax/servlet/http/HttpServletResponse;)V
       5: aload_0
       6: aconst_null
       7: putfield      #2                  // Field addSecureFlagRules:Ljava/util/List;
      10: aload_0
      11: aconst_null
      12: putfield      #3                  // Field addHTTPOnlyFlagRules:Ljava/util/List;
      15: aload_0
      16: iconst_0
      17: putfield      #4                  // Field alreadyCalledWriter:Z
      20: aload_0
      21: iconst_0
      22: putfield      #5                  // Field alreadyCalledOutputStream:Z
      25: aload_0
      26: aload_1
      27: invokeinterface #6,  1            // InterfaceMethod javax/servlet/http/HttpServletResponse.getContentType:()Ljava/lang/String;
      32: putfield      #7                  // Field contentType:Ljava/lang/String;
      35: aload_0
      36: new           #8                  // class org/owasp/esapi/waf/internal/InterceptingServletOutputStream
      39: dup
      40: aload_1
      41: invokeinterface #9,  1            // InterfaceMethod javax/servlet/http/HttpServletResponse.getOutputStream:()Ljavax/servlet/ServletOutputStream;
      46: iload_2
      47: invokespecial #10                 // Method org/owasp/esapi/waf/internal/InterceptingServletOutputStream."<init>":(Ljavax/servlet/ServletOutputStream;Z)V
      50: putfield      #11                 // Field isos:Lorg/owasp/esapi/waf/internal/InterceptingServletOutputStream;
      53: aload_0
      54: new           #12                 // class org/owasp/esapi/waf/internal/InterceptingPrintWriter
      57: dup
      58: new           #13                 // class java/io/PrintWriter
      61: dup
      62: aload_0
      63: getfield      #11                 // Field isos:Lorg/owasp/esapi/waf/internal/InterceptingServletOutputStream;
      66: invokespecial #14                 // Method java/io/PrintWriter."<init>":(Ljava/io/OutputStream;)V
      69: invokespecial #15                 // Method org/owasp/esapi/waf/internal/InterceptingPrintWriter."<init>":(Ljava/io/Writer;)V
      72: putfield      #16                 // Field ipw:Lorg/owasp/esapi/waf/internal/InterceptingPrintWriter;
      75: aload_0
      76: new           #17                 // class java/util/ArrayList
      79: dup
      80: invokespecial #18                 // Method java/util/ArrayList."<init>":()V
      83: putfield      #2                  // Field addSecureFlagRules:Ljava/util/List;
      86: aload_0
      87: new           #17                 // class java/util/ArrayList
      90: dup
      91: invokespecial #18                 // Method java/util/ArrayList."<init>":()V
      94: putfield      #3                  // Field addHTTPOnlyFlagRules:Ljava/util/List;
      97: iconst_0
      98: istore        4
     100: iload         4
     102: aload_3
     103: invokeinterface #19,  1           // InterfaceMethod java/util/List.size:()I
     108: if_icmpge     179
     111: aload_3
     112: iload         4
     114: invokeinterface #20,  2           // InterfaceMethod java/util/List.get:(I)Ljava/lang/Object;
     119: checkcast     #21                 // class org/owasp/esapi/waf/rules/Rule
     122: astore        5
     124: aload         5
     126: instanceof    #22                 // class org/owasp/esapi/waf/rules/AddSecureFlagRule
     129: ifeq          150
     132: aload_0
     133: getfield      #2                  // Field addSecureFlagRules:Ljava/util/List;
     136: aload         5
     138: checkcast     #22                 // class org/owasp/esapi/waf/rules/AddSecureFlagRule
     141: invokeinterface #23,  2           // InterfaceMethod java/util/List.add:(Ljava/lang/Object;)Z
     146: pop
     147: goto          173
     150: aload         5
     152: instanceof    #24                 // class org/owasp/esapi/waf/rules/AddHTTPOnlyFlagRule
     155: ifeq          173
     158: aload_0
     159: getfield      #3                  // Field addHTTPOnlyFlagRules:Ljava/util/List;
     162: aload         5
     164: checkcast     #24                 // class org/owasp/esapi/waf/rules/AddHTTPOnlyFlagRule
     167: invokeinterface #23,  2           // InterfaceMethod java/util/List.add:(Ljava/lang/Object;)Z
     172: pop
     173: iinc          4, 1
     176: goto          100
     179: return

  public boolean isUsingWriter();
    Code:
       0: aload_0
       1: getfield      #4                  // Field alreadyCalledWriter:Z
       4: ireturn

  public org.owasp.esapi.waf.internal.InterceptingServletOutputStream getInterceptingServletOutputStream();
    Code:
       0: aload_0
       1: getfield      #11                 // Field isos:Lorg/owasp/esapi/waf/internal/InterceptingServletOutputStream;
       4: areturn

  public javax.servlet.ServletOutputStream getOutputStream() throws java.lang.IllegalStateException, java.io.IOException;
    Code:
       0: aload_0
       1: getfield      #4                  // Field alreadyCalledWriter:Z
       4: iconst_1
       5: if_icmpne     16
       8: new           #25                 // class java/lang/IllegalStateException
      11: dup
      12: invokespecial #26                 // Method java/lang/IllegalStateException."<init>":()V
      15: athrow
      16: aload_0
      17: iconst_1
      18: putfield      #5                  // Field alreadyCalledOutputStream:Z
      21: aload_0
      22: getfield      #11                 // Field isos:Lorg/owasp/esapi/waf/internal/InterceptingServletOutputStream;
      25: areturn

  public java.io.PrintWriter getWriter() throws java.io.IOException;
    Code:
       0: aload_0
       1: getfield      #5                  // Field alreadyCalledOutputStream:Z
       4: iconst_1
       5: if_icmpne     16
       8: new           #25                 // class java/lang/IllegalStateException
      11: dup
      12: invokespecial #26                 // Method java/lang/IllegalStateException."<init>":()V
      15: athrow
      16: aload_0
      17: iconst_1
      18: putfield      #4                  // Field alreadyCalledWriter:Z
      21: aload_0
      22: getfield      #16                 // Field ipw:Lorg/owasp/esapi/waf/internal/InterceptingPrintWriter;
      25: areturn

  public java.lang.String getContentType();
    Code:
       0: aload_0
       1: getfield      #7                  // Field contentType:Ljava/lang/String;
       4: areturn

  public void setContentType(java.lang.String);
    Code:
       0: aload_0
       1: aload_1
       2: putfield      #7                  // Field contentType:Ljava/lang/String;
       5: return

  public void flush();
    Code:
       0: aload_0
       1: getfield      #16                 // Field ipw:Lorg/owasp/esapi/waf/internal/InterceptingPrintWriter;
       4: invokevirtual #27                 // Method org/owasp/esapi/waf/internal/InterceptingPrintWriter.flush:()V
       7: return

  public void commit() throws java.io.IOException;
    Code:
       0: aload_0
       1: getfield      #4                  // Field alreadyCalledWriter:Z
       4: ifeq          14
       7: aload_0
       8: getfield      #16                 // Field ipw:Lorg/owasp/esapi/waf/internal/InterceptingPrintWriter;
      11: invokevirtual #27                 // Method org/owasp/esapi/waf/internal/InterceptingPrintWriter.flush:()V
      14: aload_0
      15: getfield      #11                 // Field isos:Lorg/owasp/esapi/waf/internal/InterceptingServletOutputStream;
      18: invokevirtual #28                 // Method org/owasp/esapi/waf/internal/InterceptingServletOutputStream.commit:()V
      21: return

  public void addCookie(javax.servlet.http.Cookie);
    Code:
       0: aload_0
       1: aload_1
       2: aload_1
       3: invokevirtual #29                 // Method javax/servlet/http/Cookie.getMaxAge:()I
       6: ifgt          13
       9: iconst_1
      10: goto          14
      13: iconst_0
      14: invokevirtual #30                 // Method addCookie:(Ljavax/servlet/http/Cookie;Z)V
      17: return

  public void addCookie(javax.servlet.http.Cookie, boolean);
    Code:
       0: aload_1
       1: invokevirtual #31                 // Method javax/servlet/http/Cookie.getSecure:()Z
       4: istore_3
       5: iconst_0
       6: istore        4
       8: aload_1
       9: invokevirtual #31                 // Method javax/servlet/http/Cookie.getSecure:()Z
      12: ifne          75
      15: aload_0
      16: getfield      #2                  // Field addSecureFlagRules:Ljava/util/List;
      19: ifnull        75
      22: iconst_0
      23: istore        5
      25: iload         5
      27: aload_0
      28: getfield      #2                  // Field addSecureFlagRules:Ljava/util/List;
      31: invokeinterface #19,  1           // InterfaceMethod java/util/List.size:()I
      36: if_icmpge     75
      39: aload_0
      40: getfield      #2                  // Field addSecureFlagRules:Ljava/util/List;
      43: iload         5
      45: invokeinterface #20,  2           // InterfaceMethod java/util/List.get:(I)Ljava/lang/Object;
      50: checkcast     #22                 // class org/owasp/esapi/waf/rules/AddSecureFlagRule
      53: astore        6
      55: aload         6
      57: aload_1
      58: invokevirtual #32                 // Method javax/servlet/http/Cookie.getName:()Ljava/lang/String;
      61: invokevirtual #33                 // Method org/owasp/esapi/waf/rules/AddSecureFlagRule.doesCookieMatch:(Ljava/lang/String;)Z
      64: ifeq          69
      67: iconst_1
      68: istore_3
      69: iinc          5, 1
      72: goto          25
      75: aload_0
      76: getfield      #3                  // Field addHTTPOnlyFlagRules:Ljava/util/List;
      79: ifnull        136
      82: iconst_0
      83: istore        5
      85: iload         5
      87: aload_0
      88: getfield      #3                  // Field addHTTPOnlyFlagRules:Ljava/util/List;
      91: invokeinterface #19,  1           // InterfaceMethod java/util/List.size:()I
      96: if_icmpge     136
      99: aload_0
     100: getfield      #3                  // Field addHTTPOnlyFlagRules:Ljava/util/List;
     103: iload         5
     105: invokeinterface #20,  2           // InterfaceMethod java/util/List.get:(I)Ljava/lang/Object;
     110: checkcast     #24                 // class org/owasp/esapi/waf/rules/AddHTTPOnlyFlagRule
     113: astore        6
     115: aload         6
     117: aload_1
     118: invokevirtual #32                 // Method javax/servlet/http/Cookie.getName:()Ljava/lang/String;
     121: invokevirtual #34                 // Method org/owasp/esapi/waf/rules/AddHTTPOnlyFlagRule.doesCookieMatch:(Ljava/lang/String;)Z
     124: ifeq          130
     127: iconst_1
     128: istore        4
     130: iinc          5, 1
     133: goto          85
     136: aload_0
     137: aload_1
     138: invokevirtual #32                 // Method javax/servlet/http/Cookie.getName:()Ljava/lang/String;
     141: aload_1
     142: invokevirtual #35                 // Method javax/servlet/http/Cookie.getValue:()Ljava/lang/String;
     145: aload_1
     146: invokevirtual #29                 // Method javax/servlet/http/Cookie.getMaxAge:()I
     149: aload_1
     150: invokevirtual #36                 // Method javax/servlet/http/Cookie.getDomain:()Ljava/lang/String;
     153: aload_1
     154: invokevirtual #37                 // Method javax/servlet/http/Cookie.getPath:()Ljava/lang/String;
     157: iload_3
     158: iload         4
     160: iload_2
     161: invokespecial #38                 // Method createCookieHeader:(Ljava/lang/String;Ljava/lang/String;ILjava/lang/String;Ljava/lang/String;ZZZ)Ljava/lang/String;
     164: astore        5
     166: aload_0
     167: ldc           #39                 // String Set-Cookie
     169: aload         5
     171: invokevirtual #40                 // Method addHeader:(Ljava/lang/String;Ljava/lang/String;)V
     174: return

  private java.lang.String createCookieHeader(java.lang.String, java.lang.String, int, java.lang.String, java.lang.String, boolean, boolean, boolean);
    Code:
       0: new           #41                 // class java/lang/StringBuilder
       3: dup
       4: invokespecial #42                 // Method java/lang/StringBuilder."<init>":()V
       7: aload_1
       8: invokevirtual #43                 // Method java/lang/StringBuilder.append:(Ljava/lang/String;)Ljava/lang/StringBuilder;
      11: ldc           #44                 // String =
      13: invokevirtual #43                 // Method java/lang/StringBuilder.append:(Ljava/lang/String;)Ljava/lang/StringBuilder;
      16: aload_2
      17: invokevirtual #43                 // Method java/lang/StringBuilder.append:(Ljava/lang/String;)Ljava/lang/StringBuilder;
      20: invokevirtual #45                 // Method java/lang/StringBuilder.toString:()Ljava/lang/String;
      23: astore        9
      25: iload         8
      27: ifne          56
      30: new           #41                 // class java/lang/StringBuilder
      33: dup
      34: invokespecial #42                 // Method java/lang/StringBuilder."<init>":()V
      37: aload         9
      39: invokevirtual #43                 // Method java/lang/StringBuilder.append:(Ljava/lang/String;)Ljava/lang/StringBuilder;
      42: ldc           #46                 // String ; Max-Age=
      44: invokevirtual #43                 // Method java/lang/StringBuilder.append:(Ljava/lang/String;)Ljava/lang/StringBuilder;
      47: iload_3
      48: invokevirtual #47                 // Method java/lang/StringBuilder.append:(I)Ljava/lang/StringBuilder;
      51: invokevirtual #45                 // Method java/lang/StringBuilder.toString:()Ljava/lang/String;
      54: astore        9
      56: aload         4
      58: ifnull        88
      61: new           #41                 // class java/lang/StringBuilder
      64: dup
      65: invokespecial #42                 // Method java/lang/StringBuilder."<init>":()V
      68: aload         9
      70: invokevirtual #43                 // Method java/lang/StringBuilder.append:(Ljava/lang/String;)Ljava/lang/StringBuilder;
      73: ldc           #48                 // String ; Domain=
      75: invokevirtual #43                 // Method java/lang/StringBuilder.append:(Ljava/lang/String;)Ljava/lang/StringBuilder;
      78: aload         4
      80: invokevirtual #43                 // Method java/lang/StringBuilder.append:(Ljava/lang/String;)Ljava/lang/StringBuilder;
      83: invokevirtual #45                 // Method java/lang/StringBuilder.toString:()Ljava/lang/String;
      86: astore        9
      88: aload         5
      90: ifnull        120
      93: new           #41                 // class java/lang/StringBuilder
      96: dup
      97: invokespecial #42                 // Method java/lang/StringBuilder."<init>":()V
     100: aload         9
     102: invokevirtual #43                 // Method java/lang/StringBuilder.append:(Ljava/lang/String;)Ljava/lang/StringBuilder;
     105: ldc           #49                 // String ; Path=
     107: invokevirtual #43                 // Method java/lang/StringBuilder.append:(Ljava/lang/String;)Ljava/lang/StringBuilder;
     110: aload         5
     112: invokevirtual #43                 // Method java/lang/StringBuilder.append:(Ljava/lang/String;)Ljava/lang/StringBuilder;
     115: invokevirtual #45                 // Method java/lang/StringBuilder.toString:()Ljava/lang/String;
     118: astore        9
     120: iload         6
     122: ifeq          147
     125: new           #41                 // class java/lang/StringBuilder
     128: dup
     129: invokespecial #42                 // Method java/lang/StringBuilder."<init>":()V
     132: aload         9
     134: invokevirtual #43                 // Method java/lang/StringBuilder.append:(Ljava/lang/String;)Ljava/lang/StringBuilder;
     137: ldc           #50                 // String ; Secure
     139: invokevirtual #43                 // Method java/lang/StringBuilder.append:(Ljava/lang/String;)Ljava/lang/StringBuilder;
     142: invokevirtual #45                 // Method java/lang/StringBuilder.toString:()Ljava/lang/String;
     145: astore        9
     147: iload         7
     149: ifeq          174
     152: new           #41                 // class java/lang/StringBuilder
     155: dup
     156: invokespecial #42                 // Method java/lang/StringBuilder."<init>":()V
     159: aload         9
     161: invokevirtual #43                 // Method java/lang/StringBuilder.append:(Ljava/lang/String;)Ljava/lang/StringBuilder;
     164: ldc           #51                 // String ; HttpOnly
     166: invokevirtual #43                 // Method java/lang/StringBuilder.append:(Ljava/lang/String;)Ljava/lang/StringBuilder;
     169: invokevirtual #45                 // Method java/lang/StringBuilder.toString:()Ljava/lang/String;
     172: astore        9
     174: aload         9
     176: areturn
}
