Compiled from "MuteAnalytics.java"
final class net.openhft.chronicle.core.internal.analytics.MuteAnalytics extends java.lang.Enum<net.openhft.chronicle.core.internal.analytics.MuteAnalytics> implements net.openhft.chronicle.core.analytics.AnalyticsFacade {
  public static final net.openhft.chronicle.core.internal.analytics.MuteAnalytics INSTANCE;

  int invocationCounter;

  private static final net.openhft.chronicle.core.internal.analytics.MuteAnalytics[] $VALUES;

  public static net.openhft.chronicle.core.internal.analytics.MuteAnalytics[] values();
    Code:
       0: getstatic     #1                  // Field $VALUES:[Lnet/openhft/chronicle/core/internal/analytics/MuteAnalytics;
       3: invokevirtual #2                  // Method "[Lnet/openhft/chronicle/core/internal/analytics/MuteAnalytics;".clone:()Ljava/lang/Object;
       6: checkcast     #3                  // class "[Lnet/openhft/chronicle/core/internal/analytics/MuteAnalytics;"
       9: areturn

  public static net.openhft.chronicle.core.internal.analytics.MuteAnalytics valueOf(java.lang.String);
    Code:
       0: ldc           #4                  // class net/openhft/chronicle/core/internal/analytics/MuteAnalytics
       2: aload_0
       3: invokestatic  #5                  // Method java/lang/Enum.valueOf:(Ljava/lang/Class;Ljava/lang/String;)Ljava/lang/Enum;
       6: checkcast     #4                  // class net/openhft/chronicle/core/internal/analytics/MuteAnalytics
       9: areturn

  private net.openhft.chronicle.core.internal.analytics.MuteAnalytics();
    Code:
       0: aload_0
       1: aload_1
       2: iload_2
       3: invokespecial #6                  // Method java/lang/Enum."<init>":(Ljava/lang/String;I)V
       6: return

  public void sendEvent(java.lang.String, java.util.Map<java.lang.String, java.lang.String>);
    Code:
       0: aload_1
       1: invokestatic  #7                  // Method net/openhft/chronicle/core/util/ObjectUtils.requireNonNull:(Ljava/lang/Object;)Ljava/lang/Object;
       4: pop
       5: aload_2
       6: invokestatic  #7                  // Method net/openhft/chronicle/core/util/ObjectUtils.requireNonNull:(Ljava/lang/Object;)Ljava/lang/Object;
       9: pop
      10: aload_0
      11: dup
      12: getfield      #8                  // Field invocationCounter:I
      15: iconst_1
      16: iadd
      17: putfield      #8                  // Field invocationCounter:I
      20: return

  static {};
    Code:
       0: new           #4                  // class net/openhft/chronicle/core/internal/analytics/MuteAnalytics
       3: dup
       4: ldc           #9                  // String INSTANCE
       6: iconst_0
       7: invokespecial #10                 // Method "<init>":(Ljava/lang/String;I)V
      10: putstatic     #11                 // Field INSTANCE:Lnet/openhft/chronicle/core/internal/analytics/MuteAnalytics;
      13: iconst_1
      14: anewarray     #4                  // class net/openhft/chronicle/core/internal/analytics/MuteAnalytics
      17: dup
      18: iconst_0
      19: getstatic     #11                 // Field INSTANCE:Lnet/openhft/chronicle/core/internal/analytics/MuteAnalytics;
      22: aastore
      23: putstatic     #1                  // Field $VALUES:[Lnet/openhft/chronicle/core/internal/analytics/MuteAnalytics;
      26: return
}
