Compiled from "SAMLMetadataContext.java"
public class org.opensaml.saml.common.messaging.context.SAMLMetadataContext extends org.opensaml.messaging.context.BaseContext {
  private org.opensaml.saml.saml2.metadata.EntityDescriptor entityDescriptor;

  private transient org.opensaml.saml.saml2.metadata.RoleDescriptor roleDescriptor;

  public org.opensaml.saml.common.messaging.context.SAMLMetadataContext();
    Code:
       0: aload_0
       1: invokespecial #1                  // Method org/opensaml/messaging/context/BaseContext."<init>":()V
       4: return

  public org.opensaml.saml.saml2.metadata.EntityDescriptor getEntityDescriptor();
    Code:
       0: aload_0
       1: getfield      #2                  // Field entityDescriptor:Lorg/opensaml/saml/saml2/metadata/EntityDescriptor;
       4: areturn

  public void setEntityDescriptor(org.opensaml.saml.saml2.metadata.EntityDescriptor);
    Code:
       0: aload_0
       1: aload_1
       2: putfield      #2                  // Field entityDescriptor:Lorg/opensaml/saml/saml2/metadata/EntityDescriptor;
       5: return

  public org.opensaml.saml.saml2.metadata.RoleDescriptor getRoleDescriptor();
    Code:
       0: aload_0
       1: getfield      #3                  // Field roleDescriptor:Lorg/opensaml/saml/saml2/metadata/RoleDescriptor;
       4: areturn

  public void setRoleDescriptor(org.opensaml.saml.saml2.metadata.RoleDescriptor);
    Code:
       0: aload_0
       1: aload_1
       2: putfield      #3                  // Field roleDescriptor:Lorg/opensaml/saml/saml2/metadata/RoleDescriptor;
       5: return
}
