Compiled from "CompositeACLPermission.java"
public class org.jboss.security.acl.CompositeACLPermission implements org.jboss.security.acl.BitMaskPermission {
  private int mask;

  public org.jboss.security.acl.CompositeACLPermission(int);
    Code:
       0: aload_0
       1: invokespecial #1                  // Method java/lang/Object."<init>":()V
       4: aload_0
       5: iconst_0
       6: putfield      #2                  // Field mask:I
       9: aload_0
      10: iload_1
      11: putfield      #2                  // Field mask:I
      14: return

  public org.jboss.security.acl.CompositeACLPermission(org.jboss.security.acl.BasicACLPermission...);
    Code:
       0: aload_0
       1: invokespecial #1                  // Method java/lang/Object."<init>":()V
       4: aload_0
       5: iconst_0
       6: putfield      #2                  // Field mask:I
       9: aload_1
      10: astore_2
      11: aload_2
      12: arraylength
      13: istore_3
      14: iconst_0
      15: istore        4
      17: iload         4
      19: iload_3
      20: if_icmpge     49
      23: aload_2
      24: iload         4
      26: aaload
      27: astore        5
      29: aload_0
      30: dup
      31: getfield      #2                  // Field mask:I
      34: aload         5
      36: invokevirtual #3                  // Method org/jboss/security/acl/BasicACLPermission.getMaskValue:()I
      39: ior
      40: putfield      #2                  // Field mask:I
      43: iinc          4, 1
      46: goto          17
      49: return

  public int getMaskValue();
    Code:
       0: aload_0
       1: getfield      #2                  // Field mask:I
       4: ireturn

  public boolean equals(java.lang.Object);
    Code:
       0: aload_1
       1: instanceof    #4                  // class org/jboss/security/acl/BitMaskPermission
       4: ifeq          29
       7: aload_0
       8: getfield      #2                  // Field mask:I
      11: aload_1
      12: checkcast     #4                  // class org/jboss/security/acl/BitMaskPermission
      15: invokeinterface #5,  1            // InterfaceMethod org/jboss/security/acl/BitMaskPermission.getMaskValue:()I
      20: if_icmpne     27
      23: iconst_1
      24: goto          28
      27: iconst_0
      28: ireturn
      29: iconst_0
      30: ireturn

  public int hashCode();
    Code:
       0: aload_0
       1: getfield      #2                  // Field mask:I
       4: ireturn

  public java.lang.String toString();
    Code:
       0: aload_0
       1: getfield      #2                  // Field mask:I
       4: ifne          10
       7: ldc           #6                  // String NO PERMISSION
       9: areturn
      10: new           #7                  // class java/lang/StringBuffer
      13: dup
      14: invokespecial #8                  // Method java/lang/StringBuffer."<init>":()V
      17: astore_1
      18: invokestatic  #9                  // Method org/jboss/security/acl/BasicACLPermission.values:()[Lorg/jboss/security/acl/BasicACLPermission;
      21: astore_2
      22: aload_2
      23: arraylength
      24: istore_3
      25: iconst_0
      26: istore        4
      28: iload         4
      30: iload_3
      31: if_icmpge     87
      34: aload_2
      35: iload         4
      37: aaload
      38: astore        5
      40: aload         5
      42: invokevirtual #3                  // Method org/jboss/security/acl/BasicACLPermission.getMaskValue:()I
      45: aload_0
      46: getfield      #2                  // Field mask:I
      49: iand
      50: ifeq          81
      53: aload_1
      54: new           #10                 // class java/lang/StringBuilder
      57: dup
      58: invokespecial #11                 // Method java/lang/StringBuilder."<init>":()V
      61: aload         5
      63: invokevirtual #12                 // Method org/jboss/security/acl/BasicACLPermission.toString:()Ljava/lang/String;
      66: invokevirtual #13                 // Method java/lang/StringBuilder.append:(Ljava/lang/String;)Ljava/lang/StringBuilder;
      69: ldc           #14                 // String ,
      71: invokevirtual #13                 // Method java/lang/StringBuilder.append:(Ljava/lang/String;)Ljava/lang/StringBuilder;
      74: invokevirtual #15                 // Method java/lang/StringBuilder.toString:()Ljava/lang/String;
      77: invokevirtual #16                 // Method java/lang/StringBuffer.append:(Ljava/lang/String;)Ljava/lang/StringBuffer;
      80: pop
      81: iinc          4, 1
      84: goto          28
      87: aload_1
      88: iconst_0
      89: aload_1
      90: ldc           #14                 // String ,
      92: invokevirtual #17                 // Method java/lang/StringBuffer.lastIndexOf:(Ljava/lang/String;)I
      95: invokevirtual #18                 // Method java/lang/StringBuffer.substring:(II)Ljava/lang/String;
      98: areturn

  public java.lang.String toBinaryString();
    Code:
       0: aload_0
       1: getfield      #2                  // Field mask:I
       4: invokestatic  #19                 // Method java/lang/Integer.toBinaryString:(I)Ljava/lang/String;
       7: areturn
}
