Compiled from "CreatePortalRequest.kt"
public final class aws.sdk.kotlin.services.workspacesweb.model.CreatePortalRequest$Builder {
  private java.util.Map<java.lang.String, java.lang.String> additionalEncryptionContext;

  private java.lang.String clientToken;

  private java.lang.String customerManagedKey;

  private java.lang.String displayName;

  private java.util.List<aws.sdk.kotlin.services.workspacesweb.model.Tag> tags;

  public final java.util.Map<java.lang.String, java.lang.String> getAdditionalEncryptionContext();
    Code:
       0: aload_0
       1: getfield      #12                 // Field additionalEncryptionContext:Ljava/util/Map;
       4: areturn

  public final void setAdditionalEncryptionContext(java.util.Map<java.lang.String, java.lang.String>);
    Code:
       0: aload_0
       1: aload_1
       2: putfield      #12                 // Field additionalEncryptionContext:Ljava/util/Map;
       5: return

  public final java.lang.String getClientToken();
    Code:
       0: aload_0
       1: getfield      #24                 // Field clientToken:Ljava/lang/String;
       4: areturn

  public final void setClientToken(java.lang.String);
    Code:
       0: aload_0
       1: aload_1
       2: putfield      #24                 // Field clientToken:Ljava/lang/String;
       5: return

  public final java.lang.String getCustomerManagedKey();
    Code:
       0: aload_0
       1: getfield      #30                 // Field customerManagedKey:Ljava/lang/String;
       4: areturn

  public final void setCustomerManagedKey(java.lang.String);
    Code:
       0: aload_0
       1: aload_1
       2: putfield      #30                 // Field customerManagedKey:Ljava/lang/String;
       5: return

  public final java.lang.String getDisplayName();
    Code:
       0: aload_0
       1: getfield      #35                 // Field displayName:Ljava/lang/String;
       4: areturn

  public final void setDisplayName(java.lang.String);
    Code:
       0: aload_0
       1: aload_1
       2: putfield      #35                 // Field displayName:Ljava/lang/String;
       5: return

  public final java.util.List<aws.sdk.kotlin.services.workspacesweb.model.Tag> getTags();
    Code:
       0: aload_0
       1: getfield      #43                 // Field tags:Ljava/util/List;
       4: areturn

  public final void setTags(java.util.List<aws.sdk.kotlin.services.workspacesweb.model.Tag>);
    Code:
       0: aload_0
       1: aload_1
       2: putfield      #43                 // Field tags:Ljava/util/List;
       5: return

  public aws.sdk.kotlin.services.workspacesweb.model.CreatePortalRequest$Builder();
    Code:
       0: aload_0
       1: invokespecial #50                 // Method java/lang/Object."<init>":()V
       4: return

  public aws.sdk.kotlin.services.workspacesweb.model.CreatePortalRequest$Builder(aws.sdk.kotlin.services.workspacesweb.model.CreatePortalRequest);
    Code:
       0: aload_1
       1: ldc           #55                 // String x
       3: invokestatic  #61                 // Method kotlin/jvm/internal/Intrinsics.checkNotNullParameter:(Ljava/lang/Object;Ljava/lang/String;)V
       6: aload_0
       7: invokespecial #62                 // Method "<init>":()V
      10: aload_0
      11: aload_1
      12: invokevirtual #66                 // Method aws/sdk/kotlin/services/workspacesweb/model/CreatePortalRequest.getAdditionalEncryptionContext:()Ljava/util/Map;
      15: putfield      #12                 // Field additionalEncryptionContext:Ljava/util/Map;
      18: aload_0
      19: aload_1
      20: invokevirtual #68                 // Method aws/sdk/kotlin/services/workspacesweb/model/CreatePortalRequest.getClientToken:()Ljava/lang/String;
      23: putfield      #24                 // Field clientToken:Ljava/lang/String;
      26: aload_0
      27: aload_1
      28: invokevirtual #70                 // Method aws/sdk/kotlin/services/workspacesweb/model/CreatePortalRequest.getCustomerManagedKey:()Ljava/lang/String;
      31: putfield      #30                 // Field customerManagedKey:Ljava/lang/String;
      34: aload_0
      35: aload_1
      36: invokevirtual #72                 // Method aws/sdk/kotlin/services/workspacesweb/model/CreatePortalRequest.getDisplayName:()Ljava/lang/String;
      39: putfield      #35                 // Field displayName:Ljava/lang/String;
      42: aload_0
      43: aload_1
      44: invokevirtual #74                 // Method aws/sdk/kotlin/services/workspacesweb/model/CreatePortalRequest.getTags:()Ljava/util/List;
      47: putfield      #43                 // Field tags:Ljava/util/List;
      50: return

  public final aws.sdk.kotlin.services.workspacesweb.model.CreatePortalRequest build();
    Code:
       0: new           #64                 // class aws/sdk/kotlin/services/workspacesweb/model/CreatePortalRequest
       3: dup
       4: aload_0
       5: aconst_null
       6: invokespecial #80                 // Method aws/sdk/kotlin/services/workspacesweb/model/CreatePortalRequest."<init>":(Laws/sdk/kotlin/services/workspacesweb/model/CreatePortalRequest$Builder;Lkotlin/jvm/internal/DefaultConstructorMarker;)V
       9: areturn
}
