Compiled from "ReactiveStreamsBodyGenerator.java"
class org.asynchttpclient.request.body.generator.ReactiveStreamsBodyGenerator$StreamedBody implements org.asynchttpclient.request.body.Body {
  private final java.util.concurrent.atomic.AtomicBoolean initialized;

  private final org.asynchttpclient.request.body.generator.ReactiveStreamsBodyGenerator$SimpleSubscriber subscriber;

  private final org.asynchttpclient.request.body.Body body;

  private final long contentLength;

  final org.asynchttpclient.request.body.generator.ReactiveStreamsBodyGenerator this$0;

  public org.asynchttpclient.request.body.generator.ReactiveStreamsBodyGenerator$StreamedBody(org.asynchttpclient.request.body.generator.ReactiveStreamsBodyGenerator, org.asynchttpclient.request.body.generator.FeedableBodyGenerator, long);
    Code:
       0: aload_0
       1: aload_1
       2: putfield      #1                  // Field this$0:Lorg/asynchttpclient/request/body/generator/ReactiveStreamsBodyGenerator;
       5: aload_0
       6: invokespecial #2                  // Method java/lang/Object."<init>":()V
       9: aload_0
      10: new           #3                  // class java/util/concurrent/atomic/AtomicBoolean
      13: dup
      14: iconst_0
      15: invokespecial #4                  // Method java/util/concurrent/atomic/AtomicBoolean."<init>":(Z)V
      18: putfield      #5                  // Field initialized:Ljava/util/concurrent/atomic/AtomicBoolean;
      21: aload_0
      22: aload_2
      23: invokeinterface #6,  1            // InterfaceMethod org/asynchttpclient/request/body/generator/FeedableBodyGenerator.createBody:()Lorg/asynchttpclient/request/body/Body;
      28: putfield      #7                  // Field body:Lorg/asynchttpclient/request/body/Body;
      31: aload_0
      32: new           #8                  // class org/asynchttpclient/request/body/generator/ReactiveStreamsBodyGenerator$SimpleSubscriber
      35: dup
      36: aload_1
      37: aload_2
      38: invokespecial #9                  // Method org/asynchttpclient/request/body/generator/ReactiveStreamsBodyGenerator$SimpleSubscriber."<init>":(Lorg/asynchttpclient/request/body/generator/ReactiveStreamsBodyGenerator;Lorg/asynchttpclient/request/body/generator/FeedableBodyGenerator;)V
      41: putfield      #10                 // Field subscriber:Lorg/asynchttpclient/request/body/generator/ReactiveStreamsBodyGenerator$SimpleSubscriber;
      44: aload_0
      45: lload_3
      46: putfield      #11                 // Field contentLength:J
      49: return

  public void close() throws java.io.IOException;
    Code:
       0: aload_0
       1: getfield      #7                  // Field body:Lorg/asynchttpclient/request/body/Body;
       4: invokeinterface #12,  1           // InterfaceMethod org/asynchttpclient/request/body/Body.close:()V
       9: return

  public long getContentLength();
    Code:
       0: aload_0
       1: getfield      #11                 // Field contentLength:J
       4: lreturn

  public org.asynchttpclient.request.body.Body$BodyState transferTo(io.netty.buffer.ByteBuf) throws java.io.IOException;
    Code:
       0: aload_0
       1: getfield      #5                  // Field initialized:Ljava/util/concurrent/atomic/AtomicBoolean;
       4: iconst_0
       5: iconst_1
       6: invokevirtual #13                 // Method java/util/concurrent/atomic/AtomicBoolean.compareAndSet:(ZZ)Z
       9: ifeq          28
      12: aload_0
      13: getfield      #1                  // Field this$0:Lorg/asynchttpclient/request/body/generator/ReactiveStreamsBodyGenerator;
      16: invokestatic  #14                 // Method org/asynchttpclient/request/body/generator/ReactiveStreamsBodyGenerator.access$000:(Lorg/asynchttpclient/request/body/generator/ReactiveStreamsBodyGenerator;)Lorg/reactivestreams/Publisher;
      19: aload_0
      20: getfield      #10                 // Field subscriber:Lorg/asynchttpclient/request/body/generator/ReactiveStreamsBodyGenerator$SimpleSubscriber;
      23: invokeinterface #15,  2           // InterfaceMethod org/reactivestreams/Publisher.subscribe:(Lorg/reactivestreams/Subscriber;)V
      28: aload_0
      29: getfield      #7                  // Field body:Lorg/asynchttpclient/request/body/Body;
      32: aload_1
      33: invokeinterface #16,  2           // InterfaceMethod org/asynchttpclient/request/body/Body.transferTo:(Lio/netty/buffer/ByteBuf;)Lorg/asynchttpclient/request/body/Body$BodyState;
      38: areturn
}
