Compiled from "DebugMeshCallback.java"
public class com.jme3.bullet.util.DebugMeshCallback {
  private java.util.ArrayList<com.jme3.math.Vector3f> list;

  public com.jme3.bullet.util.DebugMeshCallback();
    Code:
       0: aload_0
       1: invokespecial #1                  // Method java/lang/Object."<init>":()V
       4: aload_0
       5: new           #2                  // class java/util/ArrayList
       8: dup
       9: invokespecial #3                  // Method java/util/ArrayList."<init>":()V
      12: putfield      #4                  // Field list:Ljava/util/ArrayList;
      15: return

  public void addVector(float, float, float, int, int);
    Code:
       0: aload_0
       1: getfield      #4                  // Field list:Ljava/util/ArrayList;
       4: new           #5                  // class com/jme3/math/Vector3f
       7: dup
       8: fload_1
       9: fload_2
      10: fload_3
      11: invokespecial #6                  // Method com/jme3/math/Vector3f."<init>":(FFF)V
      14: invokevirtual #7                  // Method java/util/ArrayList.add:(Ljava/lang/Object;)Z
      17: pop
      18: return

  public java.nio.FloatBuffer getVertices();
    Code:
       0: aload_0
       1: getfield      #4                  // Field list:Ljava/util/ArrayList;
       4: invokevirtual #8                  // Method java/util/ArrayList.size:()I
       7: iconst_3
       8: imul
       9: invokestatic  #9                  // Method com/jme3/util/BufferUtils.createFloatBuffer:(I)Ljava/nio/FloatBuffer;
      12: astore_1
      13: iconst_0
      14: istore_2
      15: iload_2
      16: aload_0
      17: getfield      #4                  // Field list:Ljava/util/ArrayList;
      20: invokevirtual #8                  // Method java/util/ArrayList.size:()I
      23: if_icmpge     71
      26: aload_0
      27: getfield      #4                  // Field list:Ljava/util/ArrayList;
      30: iload_2
      31: invokevirtual #10                 // Method java/util/ArrayList.get:(I)Ljava/lang/Object;
      34: checkcast     #5                  // class com/jme3/math/Vector3f
      37: astore_3
      38: aload_1
      39: aload_3
      40: getfield      #11                 // Field com/jme3/math/Vector3f.x:F
      43: invokevirtual #12                 // Method java/nio/FloatBuffer.put:(F)Ljava/nio/FloatBuffer;
      46: pop
      47: aload_1
      48: aload_3
      49: getfield      #13                 // Field com/jme3/math/Vector3f.y:F
      52: invokevirtual #12                 // Method java/nio/FloatBuffer.put:(F)Ljava/nio/FloatBuffer;
      55: pop
      56: aload_1
      57: aload_3
      58: getfield      #14                 // Field com/jme3/math/Vector3f.z:F
      61: invokevirtual #12                 // Method java/nio/FloatBuffer.put:(F)Ljava/nio/FloatBuffer;
      64: pop
      65: iinc          2, 1
      68: goto          15
      71: aload_1
      72: areturn
}
