Compiled from "AlignerHelper.java"
public class org.biojava.nbio.alignment.routines.AlignerHelper$Cut {
  private int queryIndex;

  private int[][] targetIndices;

  private int[][] tiLast;

  private int[][] ti1;

  private int[][] ti2;

  public org.biojava.nbio.alignment.routines.AlignerHelper$Cut(int, int[]);
    Code:
       0: aload_0
       1: invokespecial #1                  // Method java/lang/Object."<init>":()V
       4: aload_0
       5: iload_1
       6: putfield      #2                  // Field queryIndex:I
       9: aload_0
      10: aload_0
      11: aload_2
      12: iconst_1
      13: iaload
      14: aload_2
      15: iconst_2
      16: iaload
      17: multianewarray #3,  2             // class "[[I"
      21: dup_x1
      22: putfield      #4                  // Field ti1:[[I
      25: putfield      #5                  // Field targetIndices:[[I
      28: aload_0
      29: aload_2
      30: iconst_1
      31: iaload
      32: aload_2
      33: iconst_2
      34: iaload
      35: multianewarray #3,  2             // class "[[I"
      39: putfield      #6                  // Field ti2:[[I
      42: return

  public int getQueryIndex();
    Code:
       0: aload_0
       1: getfield      #2                  // Field queryIndex:I
       4: ireturn

  public int getTargetIndex(int);
    Code:
       0: aload_0
       1: getfield      #5                  // Field targetIndices:[[I
       4: aload_0
       5: getfield      #5                  // Field targetIndices:[[I
       8: arraylength
       9: iconst_1
      10: isub
      11: aaload
      12: iload_1
      13: iaload
      14: ireturn

  public void update(int, org.biojava.nbio.alignment.routines.AlignerHelper$Subproblem, org.biojava.nbio.alignment.routines.AlignerHelper$Last[][]);
    Code:
       0: aload_3
       1: aload_2
       2: invokevirtual #7                  // Method org/biojava/nbio/alignment/routines/AlignerHelper$Subproblem.getTargetStartIndex:()I
       5: aaload
       6: arraylength
       7: iconst_1
       8: if_icmpne     47
      11: aload_0
      12: getfield      #2                  // Field queryIndex:I
      15: iload_1
      16: iconst_1
      17: isub
      18: if_icmpne     30
      21: aload_0
      22: aload_2
      23: aload_3
      24: invokespecial #8                  // Method updateLinearInitial:(Lorg/biojava/nbio/alignment/routines/AlignerHelper$Subproblem;[[Lorg/biojava/nbio/alignment/routines/AlignerHelper$Last;)V
      27: goto          80
      30: aload_0
      31: getfield      #2                  // Field queryIndex:I
      34: iload_1
      35: if_icmpge     80
      38: aload_0
      39: aload_2
      40: aload_3
      41: invokespecial #9                  // Method updateLinearAdvance:(Lorg/biojava/nbio/alignment/routines/AlignerHelper$Subproblem;[[Lorg/biojava/nbio/alignment/routines/AlignerHelper$Last;)V
      44: goto          80
      47: aload_0
      48: getfield      #2                  // Field queryIndex:I
      51: iload_1
      52: iconst_1
      53: isub
      54: if_icmpne     66
      57: aload_0
      58: aload_2
      59: aload_3
      60: invokespecial #10                 // Method updateInitial:(Lorg/biojava/nbio/alignment/routines/AlignerHelper$Subproblem;[[Lorg/biojava/nbio/alignment/routines/AlignerHelper$Last;)V
      63: goto          80
      66: aload_0
      67: getfield      #2                  // Field queryIndex:I
      70: iload_1
      71: if_icmpge     80
      74: aload_0
      75: aload_2
      76: aload_3
      77: invokespecial #11                 // Method updateAdvance:(Lorg/biojava/nbio/alignment/routines/AlignerHelper$Subproblem;[[Lorg/biojava/nbio/alignment/routines/AlignerHelper$Last;)V
      80: return

  private void updateAdvance(org.biojava.nbio.alignment.routines.AlignerHelper$Subproblem, org.biojava.nbio.alignment.routines.AlignerHelper$Last[][]);
    Code:
       0: aload_0
       1: aload_0
       2: getfield      #5                  // Field targetIndices:[[I
       5: putfield      #12                 // Field tiLast:[[I
       8: aload_0
       9: aload_0
      10: getfield      #5                  // Field targetIndices:[[I
      13: aload_0
      14: getfield      #6                  // Field ti2:[[I
      17: if_acmpne     27
      20: aload_0
      21: getfield      #4                  // Field ti1:[[I
      24: goto          31
      27: aload_0
      28: getfield      #6                  // Field ti2:[[I
      31: putfield      #5                  // Field targetIndices:[[I
      34: aload_1
      35: invokevirtual #7                  // Method org/biojava/nbio/alignment/routines/AlignerHelper$Subproblem.getTargetStartIndex:()I
      38: istore_3
      39: iload_3
      40: aload_1
      41: invokevirtual #13                 // Method org/biojava/nbio/alignment/routines/AlignerHelper$Subproblem.getTargetEndIndex:()I
      44: if_icmpgt     150
      47: aload_2
      48: iload_3
      49: aaload
      50: iconst_0
      51: aaload
      52: ifnull        80
      55: aload_0
      56: getfield      #5                  // Field targetIndices:[[I
      59: iload_3
      60: aaload
      61: iconst_0
      62: aload_0
      63: getfield      #12                 // Field tiLast:[[I
      66: iload_3
      67: iconst_1
      68: isub
      69: aaload
      70: aload_2
      71: iload_3
      72: aaload
      73: iconst_0
      74: aaload
      75: invokevirtual #14                 // Method org/biojava/nbio/alignment/routines/AlignerHelper$Last.ordinal:()I
      78: iaload
      79: iastore
      80: aload_2
      81: iload_3
      82: aaload
      83: iconst_1
      84: aaload
      85: ifnull        111
      88: aload_0
      89: getfield      #5                  // Field targetIndices:[[I
      92: iload_3
      93: aaload
      94: iconst_1
      95: aload_0
      96: getfield      #12                 // Field tiLast:[[I
      99: iload_3
     100: aaload
     101: aload_2
     102: iload_3
     103: aaload
     104: iconst_1
     105: aaload
     106: invokevirtual #14                 // Method org/biojava/nbio/alignment/routines/AlignerHelper$Last.ordinal:()I
     109: iaload
     110: iastore
     111: aload_2
     112: iload_3
     113: aaload
     114: iconst_2
     115: aaload
     116: ifnull        144
     119: aload_0
     120: getfield      #5                  // Field targetIndices:[[I
     123: iload_3
     124: aaload
     125: iconst_2
     126: aload_0
     127: getfield      #5                  // Field targetIndices:[[I
     130: iload_3
     131: iconst_1
     132: isub
     133: aaload
     134: aload_2
     135: iload_3
     136: aaload
     137: iconst_2
     138: aaload
     139: invokevirtual #14                 // Method org/biojava/nbio/alignment/routines/AlignerHelper$Last.ordinal:()I
     142: iaload
     143: iastore
     144: iinc          3, 1
     147: goto          39
     150: return

  private void updateInitial(org.biojava.nbio.alignment.routines.AlignerHelper$Subproblem, org.biojava.nbio.alignment.routines.AlignerHelper$Last[][]);
    Code:
       0: aload_1
       1: invokevirtual #7                  // Method org/biojava/nbio/alignment/routines/AlignerHelper$Subproblem.getTargetStartIndex:()I
       4: istore_3
       5: iload_3
       6: aload_1
       7: invokevirtual #13                 // Method org/biojava/nbio/alignment/routines/AlignerHelper$Subproblem.getTargetEndIndex:()I
      10: if_icmpgt     81
      13: aload_2
      14: iload_3
      15: aaload
      16: iconst_0
      17: aaload
      18: ifnull        32
      21: aload_0
      22: getfield      #5                  // Field targetIndices:[[I
      25: iload_3
      26: aaload
      27: iconst_0
      28: iload_3
      29: iconst_1
      30: isub
      31: iastore
      32: aload_2
      33: iload_3
      34: aaload
      35: iconst_1
      36: aaload
      37: ifnull        49
      40: aload_0
      41: getfield      #5                  // Field targetIndices:[[I
      44: iload_3
      45: aaload
      46: iconst_1
      47: iload_3
      48: iastore
      49: aload_2
      50: iload_3
      51: aaload
      52: iconst_2
      53: aaload
      54: ifnull        75
      57: aload_0
      58: getfield      #5                  // Field targetIndices:[[I
      61: iload_3
      62: aaload
      63: iconst_2
      64: aload_0
      65: getfield      #5                  // Field targetIndices:[[I
      68: iload_3
      69: iconst_1
      70: isub
      71: aaload
      72: iconst_2
      73: iaload
      74: iastore
      75: iinc          3, 1
      78: goto          5
      81: return

  private void updateLinearAdvance(org.biojava.nbio.alignment.routines.AlignerHelper$Subproblem, org.biojava.nbio.alignment.routines.AlignerHelper$Last[][]);
    Code:
       0: aload_0
       1: aload_0
       2: getfield      #5                  // Field targetIndices:[[I
       5: putfield      #12                 // Field tiLast:[[I
       8: aload_0
       9: aload_0
      10: getfield      #5                  // Field targetIndices:[[I
      13: aload_0
      14: getfield      #6                  // Field ti2:[[I
      17: if_acmpne     27
      20: aload_0
      21: getfield      #4                  // Field ti1:[[I
      24: goto          31
      27: aload_0
      28: getfield      #6                  // Field ti2:[[I
      31: putfield      #5                  // Field targetIndices:[[I
      34: aload_1
      35: invokevirtual #7                  // Method org/biojava/nbio/alignment/routines/AlignerHelper$Subproblem.getTargetStartIndex:()I
      38: istore_3
      39: iload_3
      40: aload_1
      41: invokevirtual #13                 // Method org/biojava/nbio/alignment/routines/AlignerHelper$Subproblem.getTargetEndIndex:()I
      44: if_icmpgt     148
      47: getstatic     #15                 // Field org/biojava/nbio/alignment/routines/AlignerHelper$1.$SwitchMap$org$biojava$nbio$alignment$routines$AlignerHelper$Last:[I
      50: aload_2
      51: iload_3
      52: aaload
      53: iconst_0
      54: aaload
      55: invokevirtual #14                 // Method org/biojava/nbio/alignment/routines/AlignerHelper$Last.ordinal:()I
      58: iaload
      59: tableswitch   { // 1 to 3
                     1: 84
                     2: 103
                     3: 124
               default: 142
          }
      84: aload_0
      85: getfield      #5                  // Field targetIndices:[[I
      88: iload_3
      89: aaload
      90: iconst_0
      91: aload_0
      92: getfield      #12                 // Field tiLast:[[I
      95: iload_3
      96: aaload
      97: iconst_0
      98: iaload
      99: iastore
     100: goto          142
     103: aload_0
     104: getfield      #5                  // Field targetIndices:[[I
     107: iload_3
     108: aaload
     109: iconst_0
     110: aload_0
     111: getfield      #12                 // Field tiLast:[[I
     114: iload_3
     115: iconst_1
     116: isub
     117: aaload
     118: iconst_0
     119: iaload
     120: iastore
     121: goto          142
     124: aload_0
     125: getfield      #5                  // Field targetIndices:[[I
     128: iload_3
     129: aaload
     130: iconst_0
     131: aload_0
     132: getfield      #5                  // Field targetIndices:[[I
     135: iload_3
     136: iconst_1
     137: isub
     138: aaload
     139: iconst_0
     140: iaload
     141: iastore
     142: iinc          3, 1
     145: goto          39
     148: return

  private void updateLinearInitial(org.biojava.nbio.alignment.routines.AlignerHelper$Subproblem, org.biojava.nbio.alignment.routines.AlignerHelper$Last[][]);
    Code:
       0: aload_1
       1: invokevirtual #7                  // Method org/biojava/nbio/alignment/routines/AlignerHelper$Subproblem.getTargetStartIndex:()I
       4: istore_3
       5: iload_3
       6: aload_1
       7: invokevirtual #13                 // Method org/biojava/nbio/alignment/routines/AlignerHelper$Subproblem.getTargetEndIndex:()I
      10: if_icmpgt     110
      13: aload_2
      14: iload_3
      15: aaload
      16: iconst_0
      17: aaload
      18: ifnull        104
      21: getstatic     #15                 // Field org/biojava/nbio/alignment/routines/AlignerHelper$1.$SwitchMap$org$biojava$nbio$alignment$routines$AlignerHelper$Last:[I
      24: aload_2
      25: iload_3
      26: aaload
      27: iconst_0
      28: aaload
      29: invokevirtual #14                 // Method org/biojava/nbio/alignment/routines/AlignerHelper$Last.ordinal:()I
      32: iaload
      33: tableswitch   { // 1 to 3
                     1: 60
                     2: 72
                     3: 86
               default: 104
          }
      60: aload_0
      61: getfield      #5                  // Field targetIndices:[[I
      64: iload_3
      65: aaload
      66: iconst_0
      67: iload_3
      68: iastore
      69: goto          104
      72: aload_0
      73: getfield      #5                  // Field targetIndices:[[I
      76: iload_3
      77: aaload
      78: iconst_0
      79: iload_3
      80: iconst_1
      81: isub
      82: iastore
      83: goto          104
      86: aload_0
      87: getfield      #5                  // Field targetIndices:[[I
      90: iload_3
      91: aaload
      92: iconst_0
      93: aload_0
      94: getfield      #5                  // Field targetIndices:[[I
      97: iload_3
      98: iconst_1
      99: isub
     100: aaload
     101: iconst_0
     102: iaload
     103: iastore
     104: iinc          3, 1
     107: goto          5
     110: return
}
