Compiled from "TableLayout.java"
public class groovy.swing.impl.TableLayout extends javax.swing.JPanel {
  private int rowCount;

  private int cellpadding;

  public groovy.swing.impl.TableLayout();
    Code:
       0: aload_0
       1: invokespecial #12                 // Method javax/swing/JPanel."<init>":()V
       4: aload_0
       5: new           #14                 // class java/awt/GridBagLayout
       8: dup
       9: invokespecial #15                 // Method java/awt/GridBagLayout."<init>":()V
      12: invokevirtual #19                 // Method setLayout:(Ljava/awt/LayoutManager;)V
      15: return

  public int getCellpadding();
    Code:
       0: aload_0
       1: getfield      #25                 // Field cellpadding:I
       4: ireturn

  public void setCellpadding(int);
    Code:
       0: aload_0
       1: iload_1
       2: putfield      #25                 // Field cellpadding:I
       5: return

  public void addCell(groovy.swing.impl.TableLayoutCell);
    Code:
       0: aload_1
       1: invokevirtual #35                 // Method groovy/swing/impl/TableLayoutCell.getConstraints:()Ljava/awt/GridBagConstraints;
       4: astore_2
       5: aload_2
       6: new           #37                 // class java/awt/Insets
       9: dup
      10: aload_0
      11: getfield      #25                 // Field cellpadding:I
      14: aload_0
      15: getfield      #25                 // Field cellpadding:I
      18: aload_0
      19: getfield      #25                 // Field cellpadding:I
      22: aload_0
      23: getfield      #25                 // Field cellpadding:I
      26: invokespecial #40                 // Method java/awt/Insets."<init>":(IIII)V
      29: putfield      #46                 // Field java/awt/GridBagConstraints.insets:Ljava/awt/Insets;
      32: aload_0
      33: aload_1
      34: invokevirtual #50                 // Method groovy/swing/impl/TableLayoutCell.getComponent:()Ljava/awt/Component;
      37: aload_2
      38: invokevirtual #54                 // Method add:(Ljava/awt/Component;Ljava/lang/Object;)V
      41: return

  public int nextRowIndex();
    Code:
       0: aload_0
       1: dup
       2: getfield      #61                 // Field rowCount:I
       5: dup_x1
       6: iconst_1
       7: iadd
       8: putfield      #61                 // Field rowCount:I
      11: ireturn
}
