Compiled from "EESubsystemParser20.java"
class org.jboss.as.ee.subsystem.EESubsystemParser20$1 {
  static final int[] $SwitchMap$org$jboss$as$ee$subsystem$Element;

  static final int[] $SwitchMap$org$jboss$as$ee$subsystem$Namespace;

  static final int[] $SwitchMap$org$jboss$as$ee$subsystem$Attribute;

  static {};
    Code:
       0: invokestatic  #1                  // Method org/jboss/as/ee/subsystem/Attribute.values:()[Lorg/jboss/as/ee/subsystem/Attribute;
       3: arraylength
       4: newarray       int
       6: putstatic     #2                  // Field $SwitchMap$org$jboss$as$ee$subsystem$Attribute:[I
       9: getstatic     #2                  // Field $SwitchMap$org$jboss$as$ee$subsystem$Attribute:[I
      12: getstatic     #3                  // Field org/jboss/as/ee/subsystem/Attribute.NAME:Lorg/jboss/as/ee/subsystem/Attribute;
      15: invokevirtual #4                  // Method org/jboss/as/ee/subsystem/Attribute.ordinal:()I
      18: iconst_1
      19: iastore
      20: goto          24
      23: astore_0
      24: getstatic     #2                  // Field $SwitchMap$org$jboss$as$ee$subsystem$Attribute:[I
      27: getstatic     #6                  // Field org/jboss/as/ee/subsystem/Attribute.SLOT:Lorg/jboss/as/ee/subsystem/Attribute;
      30: invokevirtual #4                  // Method org/jboss/as/ee/subsystem/Attribute.ordinal:()I
      33: iconst_2
      34: iastore
      35: goto          39
      38: astore_0
      39: getstatic     #2                  // Field $SwitchMap$org$jboss$as$ee$subsystem$Attribute:[I
      42: getstatic     #7                  // Field org/jboss/as/ee/subsystem/Attribute.ANNOTATIONS:Lorg/jboss/as/ee/subsystem/Attribute;
      45: invokevirtual #4                  // Method org/jboss/as/ee/subsystem/Attribute.ordinal:()I
      48: iconst_3
      49: iastore
      50: goto          54
      53: astore_0
      54: getstatic     #2                  // Field $SwitchMap$org$jboss$as$ee$subsystem$Attribute:[I
      57: getstatic     #8                  // Field org/jboss/as/ee/subsystem/Attribute.SERVICES:Lorg/jboss/as/ee/subsystem/Attribute;
      60: invokevirtual #4                  // Method org/jboss/as/ee/subsystem/Attribute.ordinal:()I
      63: iconst_4
      64: iastore
      65: goto          69
      68: astore_0
      69: getstatic     #2                  // Field $SwitchMap$org$jboss$as$ee$subsystem$Attribute:[I
      72: getstatic     #9                  // Field org/jboss/as/ee/subsystem/Attribute.META_INF:Lorg/jboss/as/ee/subsystem/Attribute;
      75: invokevirtual #4                  // Method org/jboss/as/ee/subsystem/Attribute.ordinal:()I
      78: iconst_5
      79: iastore
      80: goto          84
      83: astore_0
      84: getstatic     #2                  // Field $SwitchMap$org$jboss$as$ee$subsystem$Attribute:[I
      87: getstatic     #10                 // Field org/jboss/as/ee/subsystem/Attribute.JNDI_NAME:Lorg/jboss/as/ee/subsystem/Attribute;
      90: invokevirtual #4                  // Method org/jboss/as/ee/subsystem/Attribute.ordinal:()I
      93: bipush        6
      95: iastore
      96: goto          100
      99: astore_0
     100: getstatic     #2                  // Field $SwitchMap$org$jboss$as$ee$subsystem$Attribute:[I
     103: getstatic     #11                 // Field org/jboss/as/ee/subsystem/Attribute.USE_TRANSACTION_SETUP_PROVIDER:Lorg/jboss/as/ee/subsystem/Attribute;
     106: invokevirtual #4                  // Method org/jboss/as/ee/subsystem/Attribute.ordinal:()I
     109: bipush        7
     111: iastore
     112: goto          116
     115: astore_0
     116: getstatic     #2                  // Field $SwitchMap$org$jboss$as$ee$subsystem$Attribute:[I
     119: getstatic     #12                 // Field org/jboss/as/ee/subsystem/Attribute.CONTEXT_SERVICE:Lorg/jboss/as/ee/subsystem/Attribute;
     122: invokevirtual #4                  // Method org/jboss/as/ee/subsystem/Attribute.ordinal:()I
     125: bipush        8
     127: iastore
     128: goto          132
     131: astore_0
     132: getstatic     #2                  // Field $SwitchMap$org$jboss$as$ee$subsystem$Attribute:[I
     135: getstatic     #13                 // Field org/jboss/as/ee/subsystem/Attribute.PRIORITY:Lorg/jboss/as/ee/subsystem/Attribute;
     138: invokevirtual #4                  // Method org/jboss/as/ee/subsystem/Attribute.ordinal:()I
     141: bipush        9
     143: iastore
     144: goto          148
     147: astore_0
     148: getstatic     #2                  // Field $SwitchMap$org$jboss$as$ee$subsystem$Attribute:[I
     151: getstatic     #14                 // Field org/jboss/as/ee/subsystem/Attribute.THREAD_FACTORY:Lorg/jboss/as/ee/subsystem/Attribute;
     154: invokevirtual #4                  // Method org/jboss/as/ee/subsystem/Attribute.ordinal:()I
     157: bipush        10
     159: iastore
     160: goto          164
     163: astore_0
     164: getstatic     #2                  // Field $SwitchMap$org$jboss$as$ee$subsystem$Attribute:[I
     167: getstatic     #15                 // Field org/jboss/as/ee/subsystem/Attribute.HUNG_TASK_THRESHOLD:Lorg/jboss/as/ee/subsystem/Attribute;
     170: invokevirtual #4                  // Method org/jboss/as/ee/subsystem/Attribute.ordinal:()I
     173: bipush        11
     175: iastore
     176: goto          180
     179: astore_0
     180: getstatic     #2                  // Field $SwitchMap$org$jboss$as$ee$subsystem$Attribute:[I
     183: getstatic     #16                 // Field org/jboss/as/ee/subsystem/Attribute.LONG_RUNNING_TASKS:Lorg/jboss/as/ee/subsystem/Attribute;
     186: invokevirtual #4                  // Method org/jboss/as/ee/subsystem/Attribute.ordinal:()I
     189: bipush        12
     191: iastore
     192: goto          196
     195: astore_0
     196: getstatic     #2                  // Field $SwitchMap$org$jboss$as$ee$subsystem$Attribute:[I
     199: getstatic     #17                 // Field org/jboss/as/ee/subsystem/Attribute.CORE_THREADS:Lorg/jboss/as/ee/subsystem/Attribute;
     202: invokevirtual #4                  // Method org/jboss/as/ee/subsystem/Attribute.ordinal:()I
     205: bipush        13
     207: iastore
     208: goto          212
     211: astore_0
     212: getstatic     #2                  // Field $SwitchMap$org$jboss$as$ee$subsystem$Attribute:[I
     215: getstatic     #18                 // Field org/jboss/as/ee/subsystem/Attribute.MAX_THREADS:Lorg/jboss/as/ee/subsystem/Attribute;
     218: invokevirtual #4                  // Method org/jboss/as/ee/subsystem/Attribute.ordinal:()I
     221: bipush        14
     223: iastore
     224: goto          228
     227: astore_0
     228: getstatic     #2                  // Field $SwitchMap$org$jboss$as$ee$subsystem$Attribute:[I
     231: getstatic     #19                 // Field org/jboss/as/ee/subsystem/Attribute.KEEPALIVE_TIME:Lorg/jboss/as/ee/subsystem/Attribute;
     234: invokevirtual #4                  // Method org/jboss/as/ee/subsystem/Attribute.ordinal:()I
     237: bipush        15
     239: iastore
     240: goto          244
     243: astore_0
     244: getstatic     #2                  // Field $SwitchMap$org$jboss$as$ee$subsystem$Attribute:[I
     247: getstatic     #20                 // Field org/jboss/as/ee/subsystem/Attribute.QUEUE_LENGTH:Lorg/jboss/as/ee/subsystem/Attribute;
     250: invokevirtual #4                  // Method org/jboss/as/ee/subsystem/Attribute.ordinal:()I
     253: bipush        16
     255: iastore
     256: goto          260
     259: astore_0
     260: getstatic     #2                  // Field $SwitchMap$org$jboss$as$ee$subsystem$Attribute:[I
     263: getstatic     #21                 // Field org/jboss/as/ee/subsystem/Attribute.REJECT_POLICY:Lorg/jboss/as/ee/subsystem/Attribute;
     266: invokevirtual #4                  // Method org/jboss/as/ee/subsystem/Attribute.ordinal:()I
     269: bipush        17
     271: iastore
     272: goto          276
     275: astore_0
     276: getstatic     #2                  // Field $SwitchMap$org$jboss$as$ee$subsystem$Attribute:[I
     279: getstatic     #22                 // Field org/jboss/as/ee/subsystem/Attribute.DATASOURCE:Lorg/jboss/as/ee/subsystem/Attribute;
     282: invokevirtual #4                  // Method org/jboss/as/ee/subsystem/Attribute.ordinal:()I
     285: bipush        18
     287: iastore
     288: goto          292
     291: astore_0
     292: getstatic     #2                  // Field $SwitchMap$org$jboss$as$ee$subsystem$Attribute:[I
     295: getstatic     #23                 // Field org/jboss/as/ee/subsystem/Attribute.JMS_CONNECTION_FACTORY:Lorg/jboss/as/ee/subsystem/Attribute;
     298: invokevirtual #4                  // Method org/jboss/as/ee/subsystem/Attribute.ordinal:()I
     301: bipush        19
     303: iastore
     304: goto          308
     307: astore_0
     308: getstatic     #2                  // Field $SwitchMap$org$jboss$as$ee$subsystem$Attribute:[I
     311: getstatic     #24                 // Field org/jboss/as/ee/subsystem/Attribute.MANAGED_EXECUTOR_SERVICE:Lorg/jboss/as/ee/subsystem/Attribute;
     314: invokevirtual #4                  // Method org/jboss/as/ee/subsystem/Attribute.ordinal:()I
     317: bipush        20
     319: iastore
     320: goto          324
     323: astore_0
     324: getstatic     #2                  // Field $SwitchMap$org$jboss$as$ee$subsystem$Attribute:[I
     327: getstatic     #25                 // Field org/jboss/as/ee/subsystem/Attribute.MANAGED_SCHEDULED_EXECUTOR_SERVICE:Lorg/jboss/as/ee/subsystem/Attribute;
     330: invokevirtual #4                  // Method org/jboss/as/ee/subsystem/Attribute.ordinal:()I
     333: bipush        21
     335: iastore
     336: goto          340
     339: astore_0
     340: getstatic     #2                  // Field $SwitchMap$org$jboss$as$ee$subsystem$Attribute:[I
     343: getstatic     #26                 // Field org/jboss/as/ee/subsystem/Attribute.MANAGED_THREAD_FACTORY:Lorg/jboss/as/ee/subsystem/Attribute;
     346: invokevirtual #4                  // Method org/jboss/as/ee/subsystem/Attribute.ordinal:()I
     349: bipush        22
     351: iastore
     352: goto          356
     355: astore_0
     356: invokestatic  #27                 // Method org/jboss/as/ee/subsystem/Namespace.values:()[Lorg/jboss/as/ee/subsystem/Namespace;
     359: arraylength
     360: newarray       int
     362: putstatic     #28                 // Field $SwitchMap$org$jboss$as$ee$subsystem$Namespace:[I
     365: getstatic     #28                 // Field $SwitchMap$org$jboss$as$ee$subsystem$Namespace:[I
     368: getstatic     #29                 // Field org/jboss/as/ee/subsystem/Namespace.EE_2_0:Lorg/jboss/as/ee/subsystem/Namespace;
     371: invokevirtual #30                 // Method org/jboss/as/ee/subsystem/Namespace.ordinal:()I
     374: iconst_1
     375: iastore
     376: goto          380
     379: astore_0
     380: getstatic     #28                 // Field $SwitchMap$org$jboss$as$ee$subsystem$Namespace:[I
     383: getstatic     #31                 // Field org/jboss/as/ee/subsystem/Namespace.EE_3_0:Lorg/jboss/as/ee/subsystem/Namespace;
     386: invokevirtual #30                 // Method org/jboss/as/ee/subsystem/Namespace.ordinal:()I
     389: iconst_2
     390: iastore
     391: goto          395
     394: astore_0
     395: invokestatic  #32                 // Method org/jboss/as/ee/subsystem/Element.values:()[Lorg/jboss/as/ee/subsystem/Element;
     398: arraylength
     399: newarray       int
     401: putstatic     #33                 // Field $SwitchMap$org$jboss$as$ee$subsystem$Element:[I
     404: getstatic     #33                 // Field $SwitchMap$org$jboss$as$ee$subsystem$Element:[I
     407: getstatic     #34                 // Field org/jboss/as/ee/subsystem/Element.GLOBAL_MODULES:Lorg/jboss/as/ee/subsystem/Element;
     410: invokevirtual #35                 // Method org/jboss/as/ee/subsystem/Element.ordinal:()I
     413: iconst_1
     414: iastore
     415: goto          419
     418: astore_0
     419: getstatic     #33                 // Field $SwitchMap$org$jboss$as$ee$subsystem$Element:[I
     422: getstatic     #36                 // Field org/jboss/as/ee/subsystem/Element.EAR_SUBDEPLOYMENTS_ISOLATED:Lorg/jboss/as/ee/subsystem/Element;
     425: invokevirtual #35                 // Method org/jboss/as/ee/subsystem/Element.ordinal:()I
     428: iconst_2
     429: iastore
     430: goto          434
     433: astore_0
     434: getstatic     #33                 // Field $SwitchMap$org$jboss$as$ee$subsystem$Element:[I
     437: getstatic     #37                 // Field org/jboss/as/ee/subsystem/Element.SPEC_DESCRIPTOR_PROPERTY_REPLACEMENT:Lorg/jboss/as/ee/subsystem/Element;
     440: invokevirtual #35                 // Method org/jboss/as/ee/subsystem/Element.ordinal:()I
     443: iconst_3
     444: iastore
     445: goto          449
     448: astore_0
     449: getstatic     #33                 // Field $SwitchMap$org$jboss$as$ee$subsystem$Element:[I
     452: getstatic     #38                 // Field org/jboss/as/ee/subsystem/Element.JBOSS_DESCRIPTOR_PROPERTY_REPLACEMENT:Lorg/jboss/as/ee/subsystem/Element;
     455: invokevirtual #35                 // Method org/jboss/as/ee/subsystem/Element.ordinal:()I
     458: iconst_4
     459: iastore
     460: goto          464
     463: astore_0
     464: getstatic     #33                 // Field $SwitchMap$org$jboss$as$ee$subsystem$Element:[I
     467: getstatic     #39                 // Field org/jboss/as/ee/subsystem/Element.ANNOTATION_PROPERTY_REPLACEMENT:Lorg/jboss/as/ee/subsystem/Element;
     470: invokevirtual #35                 // Method org/jboss/as/ee/subsystem/Element.ordinal:()I
     473: iconst_5
     474: iastore
     475: goto          479
     478: astore_0
     479: getstatic     #33                 // Field $SwitchMap$org$jboss$as$ee$subsystem$Element:[I
     482: getstatic     #40                 // Field org/jboss/as/ee/subsystem/Element.CONCURRENT:Lorg/jboss/as/ee/subsystem/Element;
     485: invokevirtual #35                 // Method org/jboss/as/ee/subsystem/Element.ordinal:()I
     488: bipush        6
     490: iastore
     491: goto          495
     494: astore_0
     495: getstatic     #33                 // Field $SwitchMap$org$jboss$as$ee$subsystem$Element:[I
     498: getstatic     #41                 // Field org/jboss/as/ee/subsystem/Element.DEFAULT_BINDINGS:Lorg/jboss/as/ee/subsystem/Element;
     501: invokevirtual #35                 // Method org/jboss/as/ee/subsystem/Element.ordinal:()I
     504: bipush        7
     506: iastore
     507: goto          511
     510: astore_0
     511: getstatic     #33                 // Field $SwitchMap$org$jboss$as$ee$subsystem$Element:[I
     514: getstatic     #42                 // Field org/jboss/as/ee/subsystem/Element.MODULE:Lorg/jboss/as/ee/subsystem/Element;
     517: invokevirtual #35                 // Method org/jboss/as/ee/subsystem/Element.ordinal:()I
     520: bipush        8
     522: iastore
     523: goto          527
     526: astore_0
     527: getstatic     #33                 // Field $SwitchMap$org$jboss$as$ee$subsystem$Element:[I
     530: getstatic     #43                 // Field org/jboss/as/ee/subsystem/Element.CONTEXT_SERVICES:Lorg/jboss/as/ee/subsystem/Element;
     533: invokevirtual #35                 // Method org/jboss/as/ee/subsystem/Element.ordinal:()I
     536: bipush        9
     538: iastore
     539: goto          543
     542: astore_0
     543: getstatic     #33                 // Field $SwitchMap$org$jboss$as$ee$subsystem$Element:[I
     546: getstatic     #44                 // Field org/jboss/as/ee/subsystem/Element.MANAGED_THREAD_FACTORIES:Lorg/jboss/as/ee/subsystem/Element;
     549: invokevirtual #35                 // Method org/jboss/as/ee/subsystem/Element.ordinal:()I
     552: bipush        10
     554: iastore
     555: goto          559
     558: astore_0
     559: getstatic     #33                 // Field $SwitchMap$org$jboss$as$ee$subsystem$Element:[I
     562: getstatic     #45                 // Field org/jboss/as/ee/subsystem/Element.MANAGED_EXECUTOR_SERVICES:Lorg/jboss/as/ee/subsystem/Element;
     565: invokevirtual #35                 // Method org/jboss/as/ee/subsystem/Element.ordinal:()I
     568: bipush        11
     570: iastore
     571: goto          575
     574: astore_0
     575: getstatic     #33                 // Field $SwitchMap$org$jboss$as$ee$subsystem$Element:[I
     578: getstatic     #46                 // Field org/jboss/as/ee/subsystem/Element.MANAGED_SCHEDULED_EXECUTOR_SERVICES:Lorg/jboss/as/ee/subsystem/Element;
     581: invokevirtual #35                 // Method org/jboss/as/ee/subsystem/Element.ordinal:()I
     584: bipush        12
     586: iastore
     587: goto          591
     590: astore_0
     591: getstatic     #33                 // Field $SwitchMap$org$jboss$as$ee$subsystem$Element:[I
     594: getstatic     #47                 // Field org/jboss/as/ee/subsystem/Element.CONTEXT_SERVICE:Lorg/jboss/as/ee/subsystem/Element;
     597: invokevirtual #35                 // Method org/jboss/as/ee/subsystem/Element.ordinal:()I
     600: bipush        13
     602: iastore
     603: goto          607
     606: astore_0
     607: getstatic     #33                 // Field $SwitchMap$org$jboss$as$ee$subsystem$Element:[I
     610: getstatic     #48                 // Field org/jboss/as/ee/subsystem/Element.MANAGED_THREAD_FACTORY:Lorg/jboss/as/ee/subsystem/Element;
     613: invokevirtual #35                 // Method org/jboss/as/ee/subsystem/Element.ordinal:()I
     616: bipush        14
     618: iastore
     619: goto          623
     622: astore_0
     623: getstatic     #33                 // Field $SwitchMap$org$jboss$as$ee$subsystem$Element:[I
     626: getstatic     #49                 // Field org/jboss/as/ee/subsystem/Element.MANAGED_EXECUTOR_SERVICE:Lorg/jboss/as/ee/subsystem/Element;
     629: invokevirtual #35                 // Method org/jboss/as/ee/subsystem/Element.ordinal:()I
     632: bipush        15
     634: iastore
     635: goto          639
     638: astore_0
     639: getstatic     #33                 // Field $SwitchMap$org$jboss$as$ee$subsystem$Element:[I
     642: getstatic     #50                 // Field org/jboss/as/ee/subsystem/Element.MANAGED_SCHEDULED_EXECUTOR_SERVICE:Lorg/jboss/as/ee/subsystem/Element;
     645: invokevirtual #35                 // Method org/jboss/as/ee/subsystem/Element.ordinal:()I
     648: bipush        16
     650: iastore
     651: goto          655
     654: astore_0
     655: return
    Exception table:
       from    to  target type
           9    20    23   Class java/lang/NoSuchFieldError
          24    35    38   Class java/lang/NoSuchFieldError
          39    50    53   Class java/lang/NoSuchFieldError
          54    65    68   Class java/lang/NoSuchFieldError
          69    80    83   Class java/lang/NoSuchFieldError
          84    96    99   Class java/lang/NoSuchFieldError
         100   112   115   Class java/lang/NoSuchFieldError
         116   128   131   Class java/lang/NoSuchFieldError
         132   144   147   Class java/lang/NoSuchFieldError
         148   160   163   Class java/lang/NoSuchFieldError
         164   176   179   Class java/lang/NoSuchFieldError
         180   192   195   Class java/lang/NoSuchFieldError
         196   208   211   Class java/lang/NoSuchFieldError
         212   224   227   Class java/lang/NoSuchFieldError
         228   240   243   Class java/lang/NoSuchFieldError
         244   256   259   Class java/lang/NoSuchFieldError
         260   272   275   Class java/lang/NoSuchFieldError
         276   288   291   Class java/lang/NoSuchFieldError
         292   304   307   Class java/lang/NoSuchFieldError
         308   320   323   Class java/lang/NoSuchFieldError
         324   336   339   Class java/lang/NoSuchFieldError
         340   352   355   Class java/lang/NoSuchFieldError
         365   376   379   Class java/lang/NoSuchFieldError
         380   391   394   Class java/lang/NoSuchFieldError
         404   415   418   Class java/lang/NoSuchFieldError
         419   430   433   Class java/lang/NoSuchFieldError
         434   445   448   Class java/lang/NoSuchFieldError
         449   460   463   Class java/lang/NoSuchFieldError
         464   475   478   Class java/lang/NoSuchFieldError
         479   491   494   Class java/lang/NoSuchFieldError
         495   507   510   Class java/lang/NoSuchFieldError
         511   523   526   Class java/lang/NoSuchFieldError
         527   539   542   Class java/lang/NoSuchFieldError
         543   555   558   Class java/lang/NoSuchFieldError
         559   571   574   Class java/lang/NoSuchFieldError
         575   587   590   Class java/lang/NoSuchFieldError
         591   603   606   Class java/lang/NoSuchFieldError
         607   619   622   Class java/lang/NoSuchFieldError
         623   635   638   Class java/lang/NoSuchFieldError
         639   651   654   Class java/lang/NoSuchFieldError
}
