Compiled from "XmlMarshallingHandler.java"
public class org.jboss.as.controller.operations.common.XmlMarshallingHandler implements org.jboss.as.controller.OperationStepHandler {
  private static final java.lang.String OPERATION_NAME;

  public static final org.jboss.as.controller.SimpleOperationDefinition DEFINITION;

  private static final java.util.Set<org.jboss.as.controller.access.Action$ActionEffect> EFFECTS;

  private final org.jboss.as.controller.persistence.ConfigurationPersister configPersister;

  public org.jboss.as.controller.operations.common.XmlMarshallingHandler(org.jboss.as.controller.persistence.ConfigurationPersister);
    Code:
       0: aload_0
       1: invokespecial #2                  // Method java/lang/Object."<init>":()V
       4: aload_0
       5: aload_1
       6: putfield      #3                  // Field configPersister:Lorg/jboss/as/controller/persistence/ConfigurationPersister;
       9: return

  public void execute(org.jboss.as.controller.OperationContext, org.jboss.dmr.ModelNode);
    Code:
       0: aload_1
       1: invokeinterface #4,  1            // InterfaceMethod org/jboss/as/controller/OperationContext.getCurrentAddress:()Lorg/jboss/as/controller/PathAddress;
       6: astore_3
       7: aload_1
       8: aload_2
       9: getstatic     #5                  // Field EFFECTS:Ljava/util/Set;
      12: invokeinterface #6,  3            // InterfaceMethod org/jboss/as/controller/OperationContext.authorize:(Lorg/jboss/dmr/ModelNode;Ljava/util/Set;)Lorg/jboss/as/controller/access/AuthorizationResult;
      17: astore        4
      19: aload         4
      21: invokevirtual #7                  // Method org/jboss/as/controller/access/AuthorizationResult.getDecision:()Lorg/jboss/as/controller/access/AuthorizationResult$Decision;
      24: getstatic     #8                  // Field org/jboss/as/controller/access/AuthorizationResult$Decision.PERMIT:Lorg/jboss/as/controller/access/AuthorizationResult$Decision;
      27: if_acmpeq     54
      30: getstatic     #9                  // Field org/jboss/as/controller/logging/ControllerLogger.ROOT_LOGGER:Lorg/jboss/as/controller/logging/ControllerLogger;
      33: aload_2
      34: ldc           #10                 // String operation
      36: invokevirtual #11                 // Method org/jboss/dmr/ModelNode.require:(Ljava/lang/String;)Lorg/jboss/dmr/ModelNode;
      39: invokevirtual #12                 // Method org/jboss/dmr/ModelNode.asString:()Ljava/lang/String;
      42: aload_3
      43: aload         4
      45: invokevirtual #13                 // Method org/jboss/as/controller/access/AuthorizationResult.getExplanation:()Lorg/jboss/dmr/ModelNode;
      48: invokeinterface #14,  4           // InterfaceMethod org/jboss/as/controller/logging/ControllerLogger.unauthorized:(Ljava/lang/String;Lorg/jboss/as/controller/PathAddress;Lorg/jboss/dmr/ModelNode;)Lorg/jboss/as/controller/UnauthorizedException;
      53: athrow
      54: aload_1
      55: aload_0
      56: invokevirtual #15                 // Method getBaseAddress:()Lorg/jboss/as/controller/PathAddress;
      59: invokeinterface #16,  2           // InterfaceMethod org/jboss/as/controller/OperationContext.readResourceFromRoot:(Lorg/jboss/as/controller/PathAddress;)Lorg/jboss/as/controller/registry/Resource;
      64: astore        5
      66: aload         5
      68: invokestatic  #17                 // Method org/jboss/as/controller/registry/Resource$Tools.readModel:(Lorg/jboss/as/controller/registry/Resource;)Lorg/jboss/dmr/ModelNode;
      71: astore        6
      73: new           #18                 // class java/io/ByteArrayOutputStream
      76: dup
      77: invokespecial #19                 // Method java/io/ByteArrayOutputStream."<init>":()V
      80: astore        7
      82: new           #20                 // class java/io/BufferedOutputStream
      85: dup
      86: aload         7
      88: invokespecial #21                 // Method java/io/BufferedOutputStream."<init>":(Ljava/io/OutputStream;)V
      91: astore        8
      93: aload_0
      94: getfield      #3                  // Field configPersister:Lorg/jboss/as/controller/persistence/ConfigurationPersister;
      97: aload         6
      99: aload         8
     101: invokeinterface #22,  3           // InterfaceMethod org/jboss/as/controller/persistence/ConfigurationPersister.marshallAsXml:(Lorg/jboss/dmr/ModelNode;Ljava/io/OutputStream;)V
     106: aload         8
     108: invokevirtual #23                 // Method java/io/BufferedOutputStream.close:()V
     111: aload         7
     113: invokevirtual #24                 // Method java/io/ByteArrayOutputStream.close:()V
     116: aload_0
     117: aload         7
     119: invokespecial #25                 // Method safeClose:(Ljava/io/Closeable;)V
     122: goto          136
     125: astore        9
     127: aload_0
     128: aload         7
     130: invokespecial #25                 // Method safeClose:(Ljava/io/Closeable;)V
     133: aload         9
     135: athrow
     136: new           #26                 // class java/lang/String
     139: dup
     140: aload         7
     142: invokevirtual #27                 // Method java/io/ByteArrayOutputStream.toByteArray:()[B
     145: invokespecial #28                 // Method java/lang/String."<init>":([B)V
     148: astore        8
     150: aload_1
     151: invokeinterface #29,  1           // InterfaceMethod org/jboss/as/controller/OperationContext.getResult:()Lorg/jboss/dmr/ModelNode;
     156: aload         8
     158: invokevirtual #30                 // Method org/jboss/dmr/ModelNode.set:(Ljava/lang/String;)Lorg/jboss/dmr/ModelNode;
     161: pop
     162: goto          204
     165: astore        7
     167: aload         7
     169: athrow
     170: astore        7
     172: getstatic     #33                 // Field org/jboss/as/controller/logging/ControllerLogger.MGMT_OP_LOGGER:Lorg/jboss/as/controller/logging/ControllerLogger;
     175: aload         7
     177: aload_2
     178: ldc           #10                 // String operation
     180: invokevirtual #11                 // Method org/jboss/dmr/ModelNode.require:(Ljava/lang/String;)Lorg/jboss/dmr/ModelNode;
     183: aload_3
     184: invokeinterface #34,  4           // InterfaceMethod org/jboss/as/controller/logging/ControllerLogger.failedExecutingOperation:(Ljava/lang/Throwable;Lorg/jboss/dmr/ModelNode;Lorg/jboss/as/controller/PathAddress;)V
     189: aload_1
     190: invokeinterface #35,  1           // InterfaceMethod org/jboss/as/controller/OperationContext.getFailureDescription:()Lorg/jboss/dmr/ModelNode;
     195: aload         7
     197: invokevirtual #36                 // Method java/lang/Exception.toString:()Ljava/lang/String;
     200: invokevirtual #30                 // Method org/jboss/dmr/ModelNode.set:(Ljava/lang/String;)Lorg/jboss/dmr/ModelNode;
     203: pop
     204: return
    Exception table:
       from    to  target type
          82   116   125   any
         125   127   125   any
          73   162   165   Class java/lang/RuntimeException
          73   162   170   Class java/lang/Exception

  protected org.jboss.as.controller.PathAddress getBaseAddress();
    Code:
       0: getstatic     #37                 // Field org/jboss/as/controller/PathAddress.EMPTY_ADDRESS:Lorg/jboss/as/controller/PathAddress;
       3: areturn

  private void safeClose(java.io.Closeable);
    Code:
       0: aload_1
       1: ifnull        24
       4: aload_1
       5: invokeinterface #38,  1           // InterfaceMethod java/io/Closeable.close:()V
      10: goto          24
      13: astore_2
      14: getstatic     #33                 // Field org/jboss/as/controller/logging/ControllerLogger.MGMT_OP_LOGGER:Lorg/jboss/as/controller/logging/ControllerLogger;
      17: aload_2
      18: aload_1
      19: invokeinterface #40,  3           // InterfaceMethod org/jboss/as/controller/logging/ControllerLogger.failedToCloseResource:(Ljava/lang/Throwable;Ljava/io/Closeable;)V
      24: return
    Exception table:
       from    to  target type
           4    10    13   Class java/lang/Throwable

  static {};
    Code:
       0: new           #41                 // class org/jboss/as/controller/SimpleOperationDefinitionBuilder
       3: dup
       4: ldc           #43                 // String read-config-as-xml
       6: iconst_0
       7: anewarray     #26                 // class java/lang/String
      10: invokestatic  #44                 // Method org/jboss/as/controller/descriptions/common/ControllerResolver.getResolver:([Ljava/lang/String;)Lorg/jboss/as/controller/descriptions/ResourceDescriptionResolver;
      13: invokespecial #45                 // Method org/jboss/as/controller/SimpleOperationDefinitionBuilder."<init>":(Ljava/lang/String;Lorg/jboss/as/controller/descriptions/ResourceDescriptionResolver;)V
      16: getstatic     #46                 // Field org/jboss/as/controller/access/management/SensitiveTargetAccessConstraintDefinition.READ_WHOLE_CONFIG:Lorg/jboss/as/controller/access/management/SensitiveTargetAccessConstraintDefinition;
      19: invokevirtual #47                 // Method org/jboss/as/controller/SimpleOperationDefinitionBuilder.addAccessConstraint:(Lorg/jboss/as/controller/access/management/AccessConstraintDefinition;)Lorg/jboss/as/controller/SimpleOperationDefinitionBuilder;
      22: getstatic     #48                 // Field org/jboss/dmr/ModelType.STRING:Lorg/jboss/dmr/ModelType;
      25: invokevirtual #49                 // Method org/jboss/as/controller/SimpleOperationDefinitionBuilder.setReplyType:(Lorg/jboss/dmr/ModelType;)Lorg/jboss/as/controller/SimpleOperationDefinitionBuilder;
      28: invokevirtual #50                 // Method org/jboss/as/controller/SimpleOperationDefinitionBuilder.setReadOnly:()Lorg/jboss/as/controller/SimpleOperationDefinitionBuilder;
      31: invokevirtual #51                 // Method org/jboss/as/controller/SimpleOperationDefinitionBuilder.setRuntimeOnly:()Lorg/jboss/as/controller/SimpleOperationDefinitionBuilder;
      34: invokevirtual #52                 // Method org/jboss/as/controller/SimpleOperationDefinitionBuilder.build:()Lorg/jboss/as/controller/SimpleOperationDefinition;
      37: putstatic     #53                 // Field DEFINITION:Lorg/jboss/as/controller/SimpleOperationDefinition;
      40: getstatic     #54                 // Field org/jboss/as/controller/access/Action$ActionEffect.ADDRESS:Lorg/jboss/as/controller/access/Action$ActionEffect;
      43: getstatic     #55                 // Field org/jboss/as/controller/access/Action$ActionEffect.READ_CONFIG:Lorg/jboss/as/controller/access/Action$ActionEffect;
      46: invokestatic  #56                 // Method java/util/EnumSet.of:(Ljava/lang/Enum;Ljava/lang/Enum;)Ljava/util/EnumSet;
      49: invokestatic  #57                 // Method java/util/Collections.unmodifiableSet:(Ljava/util/Set;)Ljava/util/Set;
      52: putstatic     #5                  // Field EFFECTS:Ljava/util/Set;
      55: return
}
