Compiled from "TotalHitsSearchResponseExtractor.java"
public class io.manbang.ebatis.core.response.TotalHitsSearchResponseExtractor implements io.manbang.ebatis.core.response.SearchResponseExtractor<java.lang.Long> {
  public static final io.manbang.ebatis.core.response.TotalHitsSearchResponseExtractor INSTANCE;

  private io.manbang.ebatis.core.response.TotalHitsSearchResponseExtractor();
    Code:
       0: aload_0
       1: invokespecial #1                  // Method java/lang/Object."<init>":()V
       4: return

  public java.lang.Long doExtractData(org.elasticsearch.action.search.SearchResponse);
    Code:
       0: aload_1
       1: invokevirtual #2                  // Method org/elasticsearch/action/search/SearchResponse.getHits:()Lorg/elasticsearch/search/SearchHits;
       4: invokevirtual #3                  // Method org/elasticsearch/search/SearchHits.getTotalHits:()Lorg/apache/lucene/search/TotalHits;
       7: getfield      #4                  // Field org/apache/lucene/search/TotalHits.value:J
      10: invokestatic  #5                  // Method java/lang/Long.valueOf:(J)Ljava/lang/Long;
      13: areturn

  public java.lang.Object doExtractData(org.elasticsearch.action.ActionResponse);
    Code:
       0: aload_0
       1: aload_1
       2: checkcast     #6                  // class org/elasticsearch/action/search/SearchResponse
       5: invokevirtual #7                  // Method doExtractData:(Lorg/elasticsearch/action/search/SearchResponse;)Ljava/lang/Long;
       8: areturn

  static {};
    Code:
       0: new           #8                  // class io/manbang/ebatis/core/response/TotalHitsSearchResponseExtractor
       3: dup
       4: invokespecial #9                  // Method "<init>":()V
       7: putstatic     #10                 // Field INSTANCE:Lio/manbang/ebatis/core/response/TotalHitsSearchResponseExtractor;
      10: return
}
