Compiled from "XAttr.java"
public class org.apache.hadoop.fs.XAttr {
  private final org.apache.hadoop.fs.XAttr$NameSpace ns;

  private final java.lang.String name;

  private final byte[] value;

  private org.apache.hadoop.fs.XAttr(org.apache.hadoop.fs.XAttr$NameSpace, java.lang.String, byte[]);
    Code:
       0: aload_0
       1: invokespecial #2                  // Method java/lang/Object."<init>":()V
       4: aload_0
       5: aload_1
       6: putfield      #3                  // Field ns:Lorg/apache/hadoop/fs/XAttr$NameSpace;
       9: aload_0
      10: aload_2
      11: putfield      #4                  // Field name:Ljava/lang/String;
      14: aload_0
      15: aload_3
      16: putfield      #5                  // Field value:[B
      19: return

  public org.apache.hadoop.fs.XAttr$NameSpace getNameSpace();
    Code:
       0: aload_0
       1: getfield      #3                  // Field ns:Lorg/apache/hadoop/fs/XAttr$NameSpace;
       4: areturn

  public java.lang.String getName();
    Code:
       0: aload_0
       1: getfield      #4                  // Field name:Ljava/lang/String;
       4: areturn

  public byte[] getValue();
    Code:
       0: aload_0
       1: getfield      #5                  // Field value:[B
       4: areturn

  public int hashCode();
    Code:
       0: new           #6                  // class org/apache/commons/lang3/builder/HashCodeBuilder
       3: dup
       4: sipush        811
       7: bipush        67
       9: invokespecial #7                  // Method org/apache/commons/lang3/builder/HashCodeBuilder."<init>":(II)V
      12: aload_0
      13: getfield      #4                  // Field name:Ljava/lang/String;
      16: invokevirtual #8                  // Method org/apache/commons/lang3/builder/HashCodeBuilder.append:(Ljava/lang/Object;)Lorg/apache/commons/lang3/builder/HashCodeBuilder;
      19: aload_0
      20: getfield      #3                  // Field ns:Lorg/apache/hadoop/fs/XAttr$NameSpace;
      23: invokevirtual #8                  // Method org/apache/commons/lang3/builder/HashCodeBuilder.append:(Ljava/lang/Object;)Lorg/apache/commons/lang3/builder/HashCodeBuilder;
      26: aload_0
      27: getfield      #5                  // Field value:[B
      30: invokevirtual #9                  // Method org/apache/commons/lang3/builder/HashCodeBuilder.append:([B)Lorg/apache/commons/lang3/builder/HashCodeBuilder;
      33: invokevirtual #10                 // Method org/apache/commons/lang3/builder/HashCodeBuilder.toHashCode:()I
      36: ireturn

  public boolean equals(java.lang.Object);
    Code:
       0: aload_1
       1: ifnonnull     6
       4: iconst_0
       5: ireturn
       6: aload_1
       7: aload_0
       8: if_acmpne     13
      11: iconst_1
      12: ireturn
      13: aload_1
      14: invokevirtual #11                 // Method java/lang/Object.getClass:()Ljava/lang/Class;
      17: aload_0
      18: invokevirtual #11                 // Method java/lang/Object.getClass:()Ljava/lang/Class;
      21: if_acmpeq     26
      24: iconst_0
      25: ireturn
      26: aload_1
      27: checkcast     #12                 // class org/apache/hadoop/fs/XAttr
      30: astore_2
      31: new           #13                 // class org/apache/commons/lang3/builder/EqualsBuilder
      34: dup
      35: invokespecial #14                 // Method org/apache/commons/lang3/builder/EqualsBuilder."<init>":()V
      38: aload_0
      39: getfield      #3                  // Field ns:Lorg/apache/hadoop/fs/XAttr$NameSpace;
      42: aload_2
      43: getfield      #3                  // Field ns:Lorg/apache/hadoop/fs/XAttr$NameSpace;
      46: invokevirtual #15                 // Method org/apache/commons/lang3/builder/EqualsBuilder.append:(Ljava/lang/Object;Ljava/lang/Object;)Lorg/apache/commons/lang3/builder/EqualsBuilder;
      49: aload_0
      50: getfield      #4                  // Field name:Ljava/lang/String;
      53: aload_2
      54: getfield      #4                  // Field name:Ljava/lang/String;
      57: invokevirtual #15                 // Method org/apache/commons/lang3/builder/EqualsBuilder.append:(Ljava/lang/Object;Ljava/lang/Object;)Lorg/apache/commons/lang3/builder/EqualsBuilder;
      60: aload_0
      61: getfield      #5                  // Field value:[B
      64: aload_2
      65: getfield      #5                  // Field value:[B
      68: invokevirtual #16                 // Method org/apache/commons/lang3/builder/EqualsBuilder.append:([B[B)Lorg/apache/commons/lang3/builder/EqualsBuilder;
      71: invokevirtual #17                 // Method org/apache/commons/lang3/builder/EqualsBuilder.isEquals:()Z
      74: ireturn

  public boolean equalsIgnoreValue(java.lang.Object);
    Code:
       0: aload_1
       1: ifnonnull     6
       4: iconst_0
       5: ireturn
       6: aload_1
       7: aload_0
       8: if_acmpne     13
      11: iconst_1
      12: ireturn
      13: aload_1
      14: invokevirtual #11                 // Method java/lang/Object.getClass:()Ljava/lang/Class;
      17: aload_0
      18: invokevirtual #11                 // Method java/lang/Object.getClass:()Ljava/lang/Class;
      21: if_acmpeq     26
      24: iconst_0
      25: ireturn
      26: aload_1
      27: checkcast     #12                 // class org/apache/hadoop/fs/XAttr
      30: astore_2
      31: new           #13                 // class org/apache/commons/lang3/builder/EqualsBuilder
      34: dup
      35: invokespecial #14                 // Method org/apache/commons/lang3/builder/EqualsBuilder."<init>":()V
      38: aload_0
      39: getfield      #3                  // Field ns:Lorg/apache/hadoop/fs/XAttr$NameSpace;
      42: aload_2
      43: getfield      #3                  // Field ns:Lorg/apache/hadoop/fs/XAttr$NameSpace;
      46: invokevirtual #15                 // Method org/apache/commons/lang3/builder/EqualsBuilder.append:(Ljava/lang/Object;Ljava/lang/Object;)Lorg/apache/commons/lang3/builder/EqualsBuilder;
      49: aload_0
      50: getfield      #4                  // Field name:Ljava/lang/String;
      53: aload_2
      54: getfield      #4                  // Field name:Ljava/lang/String;
      57: invokevirtual #15                 // Method org/apache/commons/lang3/builder/EqualsBuilder.append:(Ljava/lang/Object;Ljava/lang/Object;)Lorg/apache/commons/lang3/builder/EqualsBuilder;
      60: invokevirtual #17                 // Method org/apache/commons/lang3/builder/EqualsBuilder.isEquals:()Z
      63: ireturn

  public java.lang.String toString();
    Code:
       0: new           #18                 // class java/lang/StringBuilder
       3: dup
       4: invokespecial #19                 // Method java/lang/StringBuilder."<init>":()V
       7: ldc           #20                 // String XAttr [ns=
       9: invokevirtual #21                 // Method java/lang/StringBuilder.append:(Ljava/lang/String;)Ljava/lang/StringBuilder;
      12: aload_0
      13: getfield      #3                  // Field ns:Lorg/apache/hadoop/fs/XAttr$NameSpace;
      16: invokevirtual #22                 // Method java/lang/StringBuilder.append:(Ljava/lang/Object;)Ljava/lang/StringBuilder;
      19: ldc           #23                 // String , name=
      21: invokevirtual #21                 // Method java/lang/StringBuilder.append:(Ljava/lang/String;)Ljava/lang/StringBuilder;
      24: aload_0
      25: getfield      #4                  // Field name:Ljava/lang/String;
      28: invokevirtual #21                 // Method java/lang/StringBuilder.append:(Ljava/lang/String;)Ljava/lang/StringBuilder;
      31: ldc           #24                 // String , value=
      33: invokevirtual #21                 // Method java/lang/StringBuilder.append:(Ljava/lang/String;)Ljava/lang/StringBuilder;
      36: aload_0
      37: getfield      #5                  // Field value:[B
      40: invokestatic  #25                 // Method java/util/Arrays.toString:([B)Ljava/lang/String;
      43: invokevirtual #21                 // Method java/lang/StringBuilder.append:(Ljava/lang/String;)Ljava/lang/StringBuilder;
      46: ldc           #26                 // String ]
      48: invokevirtual #21                 // Method java/lang/StringBuilder.append:(Ljava/lang/String;)Ljava/lang/StringBuilder;
      51: invokevirtual #27                 // Method java/lang/StringBuilder.toString:()Ljava/lang/String;
      54: areturn

  org.apache.hadoop.fs.XAttr(org.apache.hadoop.fs.XAttr$NameSpace, java.lang.String, byte[], org.apache.hadoop.fs.XAttr$1);
    Code:
       0: aload_0
       1: aload_1
       2: aload_2
       3: aload_3
       4: invokespecial #1                  // Method "<init>":(Lorg/apache/hadoop/fs/XAttr$NameSpace;Ljava/lang/String;[B)V
       7: return
}
