Compiled from "NotNull.java"
public class org.mockito.internal.matchers.NotNull extends org.mockito.ArgumentMatcher<java.lang.Object> implements java.io.Serializable {
  private static final long serialVersionUID;

  public static final org.mockito.internal.matchers.NotNull NOT_NULL;

  private org.mockito.internal.matchers.NotNull();
    Code:
       0: aload_0
       1: invokespecial #1                  // Method org/mockito/ArgumentMatcher."<init>":()V
       4: return

  public boolean matches(java.lang.Object);
    Code:
       0: aload_1
       1: ifnull        8
       4: iconst_1
       5: goto          9
       8: iconst_0
       9: ireturn

  public void describeTo(org.hamcrest.Description);
    Code:
       0: aload_1
       1: ldc           #2                  // String notNull()
       3: invokeinterface #3,  2            // InterfaceMethod org/hamcrest/Description.appendText:(Ljava/lang/String;)Lorg/hamcrest/Description;
       8: pop
       9: return

  static {};
    Code:
       0: new           #4                  // class org/mockito/internal/matchers/NotNull
       3: dup
       4: invokespecial #5                  // Method "<init>":()V
       7: putstatic     #6                  // Field NOT_NULL:Lorg/mockito/internal/matchers/NotNull;
      10: return
}
