Compiled from "AnnotationRepositoryMetadata.java"
public class org.springframework.data.repository.core.support.AnnotationRepositoryMetadata extends org.springframework.data.repository.core.support.AbstractRepositoryMetadata {
  private static final java.lang.String NO_ANNOTATION_FOUND;

  private final java.lang.Class<?> idType;

  private final java.lang.Class<?> domainType;

  public org.springframework.data.repository.core.support.AnnotationRepositoryMetadata(java.lang.Class<?>);
    Code:
       0: aload_0
       1: aload_1
       2: invokespecial #1                  // Method org/springframework/data/repository/core/support/AbstractRepositoryMetadata."<init>":(Ljava/lang/Class;)V
       5: aload_1
       6: ldc           #2                  // class org/springframework/data/repository/RepositoryDefinition
       8: invokevirtual #3                  // Method java/lang/Class.isAnnotationPresent:(Ljava/lang/Class;)Z
      11: getstatic     #4                  // Field NO_ANNOTATION_FOUND:Ljava/lang/String;
      14: invokestatic  #5                  // Method org/springframework/util/Assert.isTrue:(ZLjava/lang/String;)V
      17: aload_0
      18: aload_0
      19: aload_1
      20: invokespecial #6                  // Method resolveIdType:(Ljava/lang/Class;)Ljava/lang/Class;
      23: putfield      #7                  // Field idType:Ljava/lang/Class;
      26: aload_0
      27: aload_0
      28: aload_1
      29: invokespecial #8                  // Method resolveDomainType:(Ljava/lang/Class;)Ljava/lang/Class;
      32: putfield      #9                  // Field domainType:Ljava/lang/Class;
      35: return

  public java.lang.Class<?> getIdType();
    Code:
       0: aload_0
       1: getfield      #7                  // Field idType:Ljava/lang/Class;
       4: areturn

  public java.lang.Class<?> getDomainType();
    Code:
       0: aload_0
       1: getfield      #9                  // Field domainType:Ljava/lang/Class;
       4: areturn

  private java.lang.Class<?> resolveIdType(java.lang.Class<?>);
    Code:
       0: aload_1
       1: ldc           #2                  // class org/springframework/data/repository/RepositoryDefinition
       3: invokevirtual #10                 // Method java/lang/Class.getAnnotation:(Ljava/lang/Class;)Ljava/lang/annotation/Annotation;
       6: checkcast     #2                  // class org/springframework/data/repository/RepositoryDefinition
       9: astore_2
      10: aload_2
      11: ifnull        23
      14: aload_2
      15: invokeinterface #11,  1           // InterfaceMethod org/springframework/data/repository/RepositoryDefinition.idClass:()Ljava/lang/Class;
      20: ifnonnull     44
      23: new           #12                 // class java/lang/IllegalArgumentException
      26: dup
      27: ldc           #13                 // String Could not resolve id type of %s!
      29: iconst_1
      30: anewarray     #14                 // class java/lang/Object
      33: dup
      34: iconst_0
      35: aload_1
      36: aastore
      37: invokestatic  #15                 // Method java/lang/String.format:(Ljava/lang/String;[Ljava/lang/Object;)Ljava/lang/String;
      40: invokespecial #16                 // Method java/lang/IllegalArgumentException."<init>":(Ljava/lang/String;)V
      43: athrow
      44: aload_2
      45: invokeinterface #11,  1           // InterfaceMethod org/springframework/data/repository/RepositoryDefinition.idClass:()Ljava/lang/Class;
      50: areturn

  private java.lang.Class<?> resolveDomainType(java.lang.Class<?>);
    Code:
       0: aload_1
       1: ldc           #2                  // class org/springframework/data/repository/RepositoryDefinition
       3: invokevirtual #10                 // Method java/lang/Class.getAnnotation:(Ljava/lang/Class;)Ljava/lang/annotation/Annotation;
       6: checkcast     #2                  // class org/springframework/data/repository/RepositoryDefinition
       9: astore_2
      10: aload_2
      11: ifnull        23
      14: aload_2
      15: invokeinterface #17,  1           // InterfaceMethod org/springframework/data/repository/RepositoryDefinition.domainClass:()Ljava/lang/Class;
      20: ifnonnull     44
      23: new           #12                 // class java/lang/IllegalArgumentException
      26: dup
      27: ldc           #18                 // String Could not resolve domain type of %s!
      29: iconst_1
      30: anewarray     #14                 // class java/lang/Object
      33: dup
      34: iconst_0
      35: aload_1
      36: aastore
      37: invokestatic  #15                 // Method java/lang/String.format:(Ljava/lang/String;[Ljava/lang/Object;)Ljava/lang/String;
      40: invokespecial #16                 // Method java/lang/IllegalArgumentException."<init>":(Ljava/lang/String;)V
      43: athrow
      44: aload_2
      45: invokeinterface #17,  1           // InterfaceMethod org/springframework/data/repository/RepositoryDefinition.domainClass:()Ljava/lang/Class;
      50: areturn

  static {};
    Code:
       0: ldc           #19                 // String Interface must be annotated with @%s!
       2: iconst_1
       3: anewarray     #14                 // class java/lang/Object
       6: dup
       7: iconst_0
       8: ldc           #2                  // class org/springframework/data/repository/RepositoryDefinition
      10: invokevirtual #20                 // Method java/lang/Class.getName:()Ljava/lang/String;
      13: aastore
      14: invokestatic  #15                 // Method java/lang/String.format:(Ljava/lang/String;[Ljava/lang/Object;)Ljava/lang/String;
      17: putstatic     #4                  // Field NO_ANNOTATION_FOUND:Ljava/lang/String;
      20: return
}
