Compiled from "JavaBeanExecutable.java"
public abstract class org.hibernate.validator.internal.properties.javabean.JavaBeanExecutable<T extends java.lang.reflect.Executable> implements org.hibernate.validator.internal.properties.Callable, org.hibernate.validator.internal.properties.javabean.JavaBeanAnnotatedConstrainable {
  protected final T executable;

  private final java.lang.reflect.Type typeForValidatorResolution;

  private final boolean hasReturnValue;

  private final java.lang.reflect.Type type;

  private final java.util.List<org.hibernate.validator.internal.properties.javabean.JavaBeanParameter> parameters;

  org.hibernate.validator.internal.properties.javabean.JavaBeanExecutable(T, boolean);
    Code:
       0: aload_0
       1: invokespecial #1                  // Method java/lang/Object."<init>":()V
       4: aload_0
       5: aload_1
       6: putfield      #7                  // Field executable:Ljava/lang/reflect/Executable;
       9: aload_0
      10: aload_1
      11: invokestatic  #13                 // Method org/hibernate/validator/internal/util/ReflectionHelper.typeOf:(Ljava/lang/reflect/Member;)Ljava/lang/reflect/Type;
      14: putfield      #19                 // Field type:Ljava/lang/reflect/Type;
      17: aload_0
      18: aload_0
      19: getfield      #19                 // Field type:Ljava/lang/reflect/Type;
      22: invokestatic  #23                 // Method org/hibernate/validator/internal/util/ReflectionHelper.boxedType:(Ljava/lang/reflect/Type;)Ljava/lang/reflect/Type;
      25: putfield      #27                 // Field typeForValidatorResolution:Ljava/lang/reflect/Type;
      28: aload_0
      29: iload_2
      30: putfield      #30                 // Field hasReturnValue:Z
      33: aload_0
      34: aload_1
      35: invokestatic  #34                 // Method getParameters:(Ljava/lang/reflect/Executable;)Ljava/util/List;
      38: putfield      #38                 // Field parameters:Ljava/util/List;
      41: return

  public boolean hasReturnValue();
    Code:
       0: aload_0
       1: getfield      #30                 // Field hasReturnValue:Z
       4: ireturn

  public boolean hasParameters();
    Code:
       0: aload_0
       1: getfield      #38                 // Field parameters:Ljava/util/List;
       4: invokeinterface #42,  1           // InterfaceMethod java/util/List.isEmpty:()Z
       9: ifne          16
      12: iconst_1
      13: goto          17
      16: iconst_0
      17: ireturn

  public java.lang.String getName();
    Code:
       0: aload_0
       1: getfield      #7                  // Field executable:Ljava/lang/reflect/Executable;
       4: invokevirtual #48                 // Method java/lang/reflect/Executable.getName:()Ljava/lang/String;
       7: areturn

  public java.lang.Class<?> getDeclaringClass();
    Code:
       0: aload_0
       1: getfield      #7                  // Field executable:Ljava/lang/reflect/Executable;
       4: invokevirtual #54                 // Method java/lang/reflect/Executable.getDeclaringClass:()Ljava/lang/Class;
       7: areturn

  public java.lang.reflect.Type getTypeForValidatorResolution();
    Code:
       0: aload_0
       1: getfield      #27                 // Field typeForValidatorResolution:Ljava/lang/reflect/Type;
       4: areturn

  public java.lang.reflect.Type getType();
    Code:
       0: aload_0
       1: getfield      #19                 // Field type:Ljava/lang/reflect/Type;
       4: areturn

  public java.lang.String getParameterName(org.hibernate.validator.internal.util.ExecutableParameterNameProvider, int);
    Code:
       0: aload_1
       1: aload_0
       2: getfield      #7                  // Field executable:Ljava/lang/reflect/Executable;
       5: invokevirtual #58                 // Method org/hibernate/validator/internal/util/ExecutableParameterNameProvider.getParameterNames:(Ljava/lang/reflect/Executable;)Ljava/util/List;
       8: iload_2
       9: invokeinterface #63,  2           // InterfaceMethod java/util/List.get:(I)Ljava/lang/Object;
      14: checkcast     #67                 // class java/lang/String
      17: areturn

  public boolean isPrivate();
    Code:
       0: aload_0
       1: getfield      #7                  // Field executable:Ljava/lang/reflect/Executable;
       4: invokevirtual #69                 // Method java/lang/reflect/Executable.getModifiers:()I
       7: invokestatic  #73                 // Method java/lang/reflect/Modifier.isPrivate:(I)Z
      10: ireturn

  public org.hibernate.validator.internal.properties.Signature getSignature();
    Code:
       0: aload_0
       1: getfield      #7                  // Field executable:Ljava/lang/reflect/Executable;
       4: invokestatic  #79                 // Method org/hibernate/validator/internal/util/ExecutableHelper.getSignature:(Ljava/lang/reflect/Executable;)Lorg/hibernate/validator/internal/properties/Signature;
       7: areturn

  public java.lang.annotation.Annotation[] getDeclaredAnnotations();
    Code:
       0: aload_0
       1: getfield      #7                  // Field executable:Ljava/lang/reflect/Executable;
       4: invokevirtual #85                 // Method java/lang/reflect/Executable.getDeclaredAnnotations:()[Ljava/lang/annotation/Annotation;
       7: areturn

  public boolean overrides(org.hibernate.validator.internal.util.ExecutableHelper, org.hibernate.validator.internal.properties.Callable);
    Code:
       0: aload_1
       1: aload_0
       2: getfield      #7                  // Field executable:Ljava/lang/reflect/Executable;
       5: checkcast     #89                 // class java/lang/reflect/Method
       8: aload_2
       9: checkcast     #8                  // class org/hibernate/validator/internal/properties/javabean/JavaBeanExecutable
      12: getfield      #7                  // Field executable:Ljava/lang/reflect/Executable;
      15: checkcast     #89                 // class java/lang/reflect/Method
      18: invokevirtual #91                 // Method org/hibernate/validator/internal/util/ExecutableHelper.overrides:(Ljava/lang/reflect/Method;Ljava/lang/reflect/Method;)Z
      21: ireturn

  public boolean isResolvedToSameMethodInHierarchy(org.hibernate.validator.internal.util.ExecutableHelper, java.lang.Class<?>, org.hibernate.validator.internal.properties.Callable);
    Code:
       0: aload_1
       1: aload_2
       2: aload_0
       3: getfield      #7                  // Field executable:Ljava/lang/reflect/Executable;
       6: checkcast     #89                 // class java/lang/reflect/Method
       9: aload_3
      10: checkcast     #8                  // class org/hibernate/validator/internal/properties/javabean/JavaBeanExecutable
      13: getfield      #7                  // Field executable:Ljava/lang/reflect/Executable;
      16: checkcast     #89                 // class java/lang/reflect/Method
      19: invokevirtual #95                 // Method org/hibernate/validator/internal/util/ExecutableHelper.isResolvedToSameMethodInHierarchy:(Ljava/lang/Class;Ljava/lang/reflect/Method;Ljava/lang/reflect/Method;)Z
      22: ireturn

  public java.lang.reflect.Type getGenericType();
    Code:
       0: aload_0
       1: getfield      #7                  // Field executable:Ljava/lang/reflect/Executable;
       4: invokestatic  #13                 // Method org/hibernate/validator/internal/util/ReflectionHelper.typeOf:(Ljava/lang/reflect/Member;)Ljava/lang/reflect/Type;
       7: areturn

  public java.lang.reflect.AnnotatedType getAnnotatedType();
    Code:
       0: aload_0
       1: getfield      #7                  // Field executable:Ljava/lang/reflect/Executable;
       4: invokevirtual #99                 // Method java/lang/reflect/Executable.getAnnotatedReturnType:()Ljava/lang/reflect/AnnotatedType;
       7: areturn

  public <A extends java.lang.annotation.Annotation> A getAnnotation(java.lang.Class<A>);
    Code:
       0: aload_0
       1: getfield      #7                  // Field executable:Ljava/lang/reflect/Executable;
       4: aload_1
       5: invokevirtual #103                // Method java/lang/reflect/Executable.getAnnotation:(Ljava/lang/Class;)Ljava/lang/annotation/Annotation;
       8: areturn

  public java.util.List<org.hibernate.validator.internal.properties.javabean.JavaBeanParameter> getParameters();
    Code:
       0: aload_0
       1: getfield      #38                 // Field parameters:Ljava/util/List;
       4: areturn

  public java.lang.reflect.Type getParameterGenericType(int);
    Code:
       0: aload_0
       1: getfield      #38                 // Field parameters:Ljava/util/List;
       4: iload_1
       5: invokeinterface #63,  2           // InterfaceMethod java/util/List.get:(I)Ljava/lang/Object;
      10: checkcast     #107                // class org/hibernate/validator/internal/properties/javabean/JavaBeanParameter
      13: invokevirtual #109                // Method org/hibernate/validator/internal/properties/javabean/JavaBeanParameter.getGenericType:()Ljava/lang/reflect/Type;
      16: areturn

  public int getParameterCount();
    Code:
       0: aload_0
       1: getfield      #38                 // Field parameters:Ljava/util/List;
       4: invokeinterface #113,  1          // InterfaceMethod java/util/List.size:()I
       9: ireturn

  public java.lang.Class<?>[] getParameterTypes();
    Code:
       0: aload_0
       1: getfield      #7                  // Field executable:Ljava/lang/reflect/Executable;
       4: invokevirtual #116                // Method java/lang/reflect/Executable.getParameterTypes:()[Ljava/lang/Class;
       7: areturn

  public boolean equals(java.lang.Object);
    Code:
       0: aload_0
       1: aload_1
       2: if_acmpne     7
       5: iconst_1
       6: ireturn
       7: aload_1
       8: ifnull        22
      11: aload_0
      12: invokevirtual #120                // Method java/lang/Object.getClass:()Ljava/lang/Class;
      15: aload_1
      16: invokevirtual #120                // Method java/lang/Object.getClass:()Ljava/lang/Class;
      19: if_acmpeq     24
      22: iconst_0
      23: ireturn
      24: aload_1
      25: checkcast     #8                  // class org/hibernate/validator/internal/properties/javabean/JavaBeanExecutable
      28: astore_2
      29: aload_0
      30: getfield      #30                 // Field hasReturnValue:Z
      33: aload_2
      34: getfield      #30                 // Field hasReturnValue:Z
      37: if_icmpeq     42
      40: iconst_0
      41: ireturn
      42: aload_0
      43: getfield      #7                  // Field executable:Ljava/lang/reflect/Executable;
      46: aload_2
      47: getfield      #7                  // Field executable:Ljava/lang/reflect/Executable;
      50: invokevirtual #123                // Method java/lang/Object.equals:(Ljava/lang/Object;)Z
      53: ifne          58
      56: iconst_0
      57: ireturn
      58: aload_0
      59: getfield      #27                 // Field typeForValidatorResolution:Ljava/lang/reflect/Type;
      62: aload_2
      63: getfield      #27                 // Field typeForValidatorResolution:Ljava/lang/reflect/Type;
      66: invokevirtual #123                // Method java/lang/Object.equals:(Ljava/lang/Object;)Z
      69: ifne          74
      72: iconst_0
      73: ireturn
      74: aload_0
      75: getfield      #19                 // Field type:Ljava/lang/reflect/Type;
      78: aload_2
      79: getfield      #19                 // Field type:Ljava/lang/reflect/Type;
      82: invokevirtual #123                // Method java/lang/Object.equals:(Ljava/lang/Object;)Z
      85: ireturn

  public int hashCode();
    Code:
       0: aload_0
       1: getfield      #7                  // Field executable:Ljava/lang/reflect/Executable;
       4: invokevirtual #127                // Method java/lang/Object.hashCode:()I
       7: istore_1
       8: bipush        31
      10: iload_1
      11: imul
      12: aload_0
      13: getfield      #27                 // Field typeForValidatorResolution:Ljava/lang/reflect/Type;
      16: invokevirtual #127                // Method java/lang/Object.hashCode:()I
      19: iadd
      20: istore_1
      21: bipush        31
      23: iload_1
      24: imul
      25: aload_0
      26: getfield      #30                 // Field hasReturnValue:Z
      29: ifeq          36
      32: iconst_1
      33: goto          37
      36: iconst_0
      37: iadd
      38: istore_1
      39: bipush        31
      41: iload_1
      42: imul
      43: aload_0
      44: getfield      #19                 // Field type:Ljava/lang/reflect/Type;
      47: invokevirtual #127                // Method java/lang/Object.hashCode:()I
      50: iadd
      51: istore_1
      52: iload_1
      53: ireturn

  public java.lang.String toString();
    Code:
       0: aload_0
       1: invokevirtual #130                // Method getDeclaringClass:()Ljava/lang/Class;
       4: invokevirtual #131                // Method java/lang/Class.getSimpleName:()Ljava/lang/String;
       7: aload_0
       8: getfield      #7                  // Field executable:Ljava/lang/reflect/Executable;
      11: invokevirtual #48                 // Method java/lang/reflect/Executable.getName:()Ljava/lang/String;
      14: invokedynamic #136,  0            // InvokeDynamic #0:makeConcatWithConstants:(Ljava/lang/String;Ljava/lang/String;)Ljava/lang/String;
      19: aload_0
      20: getfield      #7                  // Field executable:Ljava/lang/reflect/Executable;
      23: invokevirtual #116                // Method java/lang/reflect/Executable.getParameterTypes:()[Ljava/lang/Class;
      26: invokestatic  #140                // Method org/hibernate/validator/internal/util/ExecutableHelper.getExecutableAsString:(Ljava/lang/String;[Ljava/lang/Class;)Ljava/lang/String;
      29: areturn

  private static java.util.List<org.hibernate.validator.internal.properties.javabean.JavaBeanParameter> getParameters(java.lang.reflect.Executable);
    Code:
       0: aload_0
       1: invokevirtual #144                // Method java/lang/reflect/Executable.getParameterCount:()I
       4: ifne          11
       7: invokestatic  #147                // Method java/util/Collections.emptyList:()Ljava/util/List;
      10: areturn
      11: aload_0
      12: invokevirtual #144                // Method java/lang/reflect/Executable.getParameterCount:()I
      15: istore_1
      16: new           #153                // class java/util/ArrayList
      19: dup
      20: iload_1
      21: invokespecial #155                // Method java/util/ArrayList."<init>":(I)V
      24: astore_2
      25: aload_0
      26: invokevirtual #158                // Method java/lang/reflect/Executable.getParameters:()[Ljava/lang/reflect/Parameter;
      29: astore_3
      30: aload_0
      31: invokevirtual #116                // Method java/lang/reflect/Executable.getParameterTypes:()[Ljava/lang/Class;
      34: astore        4
      36: aload_0
      37: invokevirtual #161                // Method java/lang/reflect/Executable.getAnnotatedParameterTypes:()[Ljava/lang/reflect/AnnotatedType;
      40: astore        5
      42: aload_0
      43: invokevirtual #165                // Method java/lang/reflect/Executable.getParameterAnnotations:()[[Ljava/lang/annotation/Annotation;
      46: astore        6
      48: aload_3
      49: aload         6
      51: invokestatic  #169                // Method recomputeParameterAnnotationsForJDK8303112:([Ljava/lang/reflect/Parameter;[[Ljava/lang/annotation/Annotation;)[[Ljava/lang/annotation/Annotation;
      54: astore        7
      56: iconst_0
      57: istore        8
      59: iload         8
      61: aload_3
      62: arraylength
      63: if_icmpge     116
      66: aload_2
      67: new           #107                // class org/hibernate/validator/internal/properties/javabean/JavaBeanParameter
      70: dup
      71: iload         8
      73: aload_3
      74: iload         8
      76: aaload
      77: aload         4
      79: iload         8
      81: aaload
      82: aload         5
      84: iload         8
      86: aaload
      87: aload         7
      89: ifnull        100
      92: aload         7
      94: iload         8
      96: aaload
      97: goto          101
     100: aconst_null
     101: invokespecial #173                // Method org/hibernate/validator/internal/properties/javabean/JavaBeanParameter."<init>":(ILjava/lang/reflect/Parameter;Ljava/lang/Class;Ljava/lang/reflect/AnnotatedType;[Ljava/lang/annotation/Annotation;)V
     104: invokeinterface #176,  2          // InterfaceMethod java/util/List.add:(Ljava/lang/Object;)Z
     109: pop
     110: iinc          8, 1
     113: goto          59
     116: aload_2
     117: invokestatic  #179                // Method org/hibernate/validator/internal/util/CollectionHelper.toImmutableList:(Ljava/util/List;)Ljava/util/List;
     120: areturn

  private static java.lang.annotation.Annotation[][] recomputeParameterAnnotationsForJDK8303112(java.lang.reflect.Parameter[], java.lang.annotation.Annotation[][]);
    Code:
       0: aload_0
       1: arraylength
       2: istore_2
       3: aload_1
       4: arraylength
       5: iload_2
       6: if_icmpne     11
       9: aconst_null
      10: areturn
      11: iload_2
      12: anewarray     #185                // class "[Ljava/lang/annotation/Annotation;"
      15: astore_3
      16: iconst_0
      17: istore        4
      19: iconst_0
      20: istore        5
      22: iload         5
      24: iload_2
      25: if_icmpge     117
      28: aload_0
      29: iload         5
      31: aaload
      32: astore        6
      34: aload         6
      36: invokevirtual #187                // Method java/lang/reflect/Parameter.isImplicit:()Z
      39: ifne          50
      42: aload         6
      44: invokevirtual #192                // Method java/lang/reflect/Parameter.isSynthetic:()Z
      47: ifeq          61
      50: aload_3
      51: iload         5
      53: iconst_0
      54: anewarray     #195                // class java/lang/annotation/Annotation
      57: aastore
      58: goto          111
      61: iload         4
      63: aload_1
      64: arraylength
      65: if_icmpge     82
      68: aload_3
      69: iload         5
      71: aload_1
      72: iload         4
      74: aaload
      75: aastore
      76: iinc          4, 1
      79: goto          111
      82: iload_2
      83: aload_1
      84: arraylength
      85: isub
      86: istore        4
      88: aload_3
      89: iconst_0
      90: iload         4
      92: iconst_0
      93: anewarray     #195                // class java/lang/annotation/Annotation
      96: invokestatic  #197                // Method java/util/Arrays.fill:([Ljava/lang/Object;IILjava/lang/Object;)V
      99: aload_1
     100: iconst_0
     101: aload_3
     102: iload         4
     104: aload_1
     105: arraylength
     106: invokestatic  #203                // Method java/lang/System.arraycopy:(Ljava/lang/Object;ILjava/lang/Object;II)V
     109: aload_3
     110: areturn
     111: iinc          5, 1
     114: goto          22
     117: aload_3
     118: areturn
}
