Compiled from "LoadBalancerStatus.java"
public final class org.graylog2.plugin.lifecycles.LoadBalancerStatus extends java.lang.Enum<org.graylog2.plugin.lifecycles.LoadBalancerStatus> {
  public static final org.graylog2.plugin.lifecycles.LoadBalancerStatus DEAD;

  public static final org.graylog2.plugin.lifecycles.LoadBalancerStatus ALIVE;

  public static final org.graylog2.plugin.lifecycles.LoadBalancerStatus THROTTLED;

  private static final org.graylog2.plugin.lifecycles.LoadBalancerStatus[] $VALUES;

  public static org.graylog2.plugin.lifecycles.LoadBalancerStatus[] values();
    Code:
       0: getstatic     #1                  // Field $VALUES:[Lorg/graylog2/plugin/lifecycles/LoadBalancerStatus;
       3: invokevirtual #2                  // Method "[Lorg/graylog2/plugin/lifecycles/LoadBalancerStatus;".clone:()Ljava/lang/Object;
       6: checkcast     #3                  // class "[Lorg/graylog2/plugin/lifecycles/LoadBalancerStatus;"
       9: areturn

  public static org.graylog2.plugin.lifecycles.LoadBalancerStatus valueOf(java.lang.String);
    Code:
       0: ldc           #4                  // class org/graylog2/plugin/lifecycles/LoadBalancerStatus
       2: aload_0
       3: invokestatic  #5                  // Method java/lang/Enum.valueOf:(Ljava/lang/Class;Ljava/lang/String;)Ljava/lang/Enum;
       6: checkcast     #4                  // class org/graylog2/plugin/lifecycles/LoadBalancerStatus
       9: areturn

  private org.graylog2.plugin.lifecycles.LoadBalancerStatus();
    Code:
       0: aload_0
       1: aload_1
       2: iload_2
       3: invokespecial #6                  // Method java/lang/Enum."<init>":(Ljava/lang/String;I)V
       6: return

  static {};
    Code:
       0: new           #4                  // class org/graylog2/plugin/lifecycles/LoadBalancerStatus
       3: dup
       4: ldc           #7                  // String DEAD
       6: iconst_0
       7: invokespecial #8                  // Method "<init>":(Ljava/lang/String;I)V
      10: putstatic     #9                  // Field DEAD:Lorg/graylog2/plugin/lifecycles/LoadBalancerStatus;
      13: new           #4                  // class org/graylog2/plugin/lifecycles/LoadBalancerStatus
      16: dup
      17: ldc           #10                 // String ALIVE
      19: iconst_1
      20: invokespecial #8                  // Method "<init>":(Ljava/lang/String;I)V
      23: putstatic     #11                 // Field ALIVE:Lorg/graylog2/plugin/lifecycles/LoadBalancerStatus;
      26: new           #4                  // class org/graylog2/plugin/lifecycles/LoadBalancerStatus
      29: dup
      30: ldc           #12                 // String THROTTLED
      32: iconst_2
      33: invokespecial #8                  // Method "<init>":(Ljava/lang/String;I)V
      36: putstatic     #13                 // Field THROTTLED:Lorg/graylog2/plugin/lifecycles/LoadBalancerStatus;
      39: iconst_3
      40: anewarray     #4                  // class org/graylog2/plugin/lifecycles/LoadBalancerStatus
      43: dup
      44: iconst_0
      45: getstatic     #9                  // Field DEAD:Lorg/graylog2/plugin/lifecycles/LoadBalancerStatus;
      48: aastore
      49: dup
      50: iconst_1
      51: getstatic     #11                 // Field ALIVE:Lorg/graylog2/plugin/lifecycles/LoadBalancerStatus;
      54: aastore
      55: dup
      56: iconst_2
      57: getstatic     #13                 // Field THROTTLED:Lorg/graylog2/plugin/lifecycles/LoadBalancerStatus;
      60: aastore
      61: putstatic     #1                  // Field $VALUES:[Lorg/graylog2/plugin/lifecycles/LoadBalancerStatus;
      64: return
}
