Compiled from "LSAIdentificationPriorityValue.java"
public final class org.mobicents.protocols.ss7.map.api.service.mobility.subscriberManagement.LSAIdentificationPriorityValue extends java.lang.Enum<org.mobicents.protocols.ss7.map.api.service.mobility.subscriberManagement.LSAIdentificationPriorityValue> {
  public static final org.mobicents.protocols.ss7.map.api.service.mobility.subscriberManagement.LSAIdentificationPriorityValue Priority_1;

  public static final org.mobicents.protocols.ss7.map.api.service.mobility.subscriberManagement.LSAIdentificationPriorityValue Priority_2;

  public static final org.mobicents.protocols.ss7.map.api.service.mobility.subscriberManagement.LSAIdentificationPriorityValue Priority_3;

  public static final org.mobicents.protocols.ss7.map.api.service.mobility.subscriberManagement.LSAIdentificationPriorityValue Priority_4;

  public static final org.mobicents.protocols.ss7.map.api.service.mobility.subscriberManagement.LSAIdentificationPriorityValue Priority_5;

  public static final org.mobicents.protocols.ss7.map.api.service.mobility.subscriberManagement.LSAIdentificationPriorityValue Priority_6;

  public static final org.mobicents.protocols.ss7.map.api.service.mobility.subscriberManagement.LSAIdentificationPriorityValue Priority_7;

  public static final org.mobicents.protocols.ss7.map.api.service.mobility.subscriberManagement.LSAIdentificationPriorityValue Priority_8;

  public static final org.mobicents.protocols.ss7.map.api.service.mobility.subscriberManagement.LSAIdentificationPriorityValue Priority_9;

  public static final org.mobicents.protocols.ss7.map.api.service.mobility.subscriberManagement.LSAIdentificationPriorityValue Priority_10;

  public static final org.mobicents.protocols.ss7.map.api.service.mobility.subscriberManagement.LSAIdentificationPriorityValue Priority_11;

  public static final org.mobicents.protocols.ss7.map.api.service.mobility.subscriberManagement.LSAIdentificationPriorityValue Priority_12;

  public static final org.mobicents.protocols.ss7.map.api.service.mobility.subscriberManagement.LSAIdentificationPriorityValue Priority_13;

  public static final org.mobicents.protocols.ss7.map.api.service.mobility.subscriberManagement.LSAIdentificationPriorityValue Priority_14;

  public static final org.mobicents.protocols.ss7.map.api.service.mobility.subscriberManagement.LSAIdentificationPriorityValue Priority_15;

  public static final org.mobicents.protocols.ss7.map.api.service.mobility.subscriberManagement.LSAIdentificationPriorityValue Priority_16;

  private int code;

  private static final org.mobicents.protocols.ss7.map.api.service.mobility.subscriberManagement.LSAIdentificationPriorityValue[] $VALUES;

  public static org.mobicents.protocols.ss7.map.api.service.mobility.subscriberManagement.LSAIdentificationPriorityValue[] values();
    Code:
       0: getstatic     #1                  // Field $VALUES:[Lorg/mobicents/protocols/ss7/map/api/service/mobility/subscriberManagement/LSAIdentificationPriorityValue;
       3: invokevirtual #2                  // Method "[Lorg/mobicents/protocols/ss7/map/api/service/mobility/subscriberManagement/LSAIdentificationPriorityValue;".clone:()Ljava/lang/Object;
       6: checkcast     #3                  // class "[Lorg/mobicents/protocols/ss7/map/api/service/mobility/subscriberManagement/LSAIdentificationPriorityValue;"
       9: areturn

  public static org.mobicents.protocols.ss7.map.api.service.mobility.subscriberManagement.LSAIdentificationPriorityValue valueOf(java.lang.String);
    Code:
       0: ldc_w         #4                  // class org/mobicents/protocols/ss7/map/api/service/mobility/subscriberManagement/LSAIdentificationPriorityValue
       3: aload_0
       4: invokestatic  #5                  // Method java/lang/Enum.valueOf:(Ljava/lang/Class;Ljava/lang/String;)Ljava/lang/Enum;
       7: checkcast     #4                  // class org/mobicents/protocols/ss7/map/api/service/mobility/subscriberManagement/LSAIdentificationPriorityValue
      10: areturn

  private org.mobicents.protocols.ss7.map.api.service.mobility.subscriberManagement.LSAIdentificationPriorityValue(int);
    Code:
       0: aload_0
       1: aload_1
       2: iload_2
       3: invokespecial #6                  // Method java/lang/Enum."<init>":(Ljava/lang/String;I)V
       6: aload_0
       7: iload_3
       8: putfield      #7                  // Field code:I
      11: return

  public int getCode();
    Code:
       0: aload_0
       1: getfield      #7                  // Field code:I
       4: ireturn

  public static org.mobicents.protocols.ss7.map.api.service.mobility.subscriberManagement.LSAIdentificationPriorityValue getInstance(int);
    Code:
       0: iload_0
       1: tableswitch   { // 0 to 15
                     0: 80
                     1: 84
                     2: 88
                     3: 92
                     4: 96
                     5: 100
                     6: 104
                     7: 108
                     8: 112
                     9: 116
                    10: 120
                    11: 124
                    12: 128
                    13: 132
                    14: 136
                    15: 140
               default: 144
          }
      80: getstatic     #8                  // Field Priority_1:Lorg/mobicents/protocols/ss7/map/api/service/mobility/subscriberManagement/LSAIdentificationPriorityValue;
      83: areturn
      84: getstatic     #9                  // Field Priority_2:Lorg/mobicents/protocols/ss7/map/api/service/mobility/subscriberManagement/LSAIdentificationPriorityValue;
      87: areturn
      88: getstatic     #10                 // Field Priority_3:Lorg/mobicents/protocols/ss7/map/api/service/mobility/subscriberManagement/LSAIdentificationPriorityValue;
      91: areturn
      92: getstatic     #11                 // Field Priority_4:Lorg/mobicents/protocols/ss7/map/api/service/mobility/subscriberManagement/LSAIdentificationPriorityValue;
      95: areturn
      96: getstatic     #12                 // Field Priority_5:Lorg/mobicents/protocols/ss7/map/api/service/mobility/subscriberManagement/LSAIdentificationPriorityValue;
      99: areturn
     100: getstatic     #13                 // Field Priority_6:Lorg/mobicents/protocols/ss7/map/api/service/mobility/subscriberManagement/LSAIdentificationPriorityValue;
     103: areturn
     104: getstatic     #14                 // Field Priority_7:Lorg/mobicents/protocols/ss7/map/api/service/mobility/subscriberManagement/LSAIdentificationPriorityValue;
     107: areturn
     108: getstatic     #15                 // Field Priority_8:Lorg/mobicents/protocols/ss7/map/api/service/mobility/subscriberManagement/LSAIdentificationPriorityValue;
     111: areturn
     112: getstatic     #16                 // Field Priority_9:Lorg/mobicents/protocols/ss7/map/api/service/mobility/subscriberManagement/LSAIdentificationPriorityValue;
     115: areturn
     116: getstatic     #17                 // Field Priority_10:Lorg/mobicents/protocols/ss7/map/api/service/mobility/subscriberManagement/LSAIdentificationPriorityValue;
     119: areturn
     120: getstatic     #18                 // Field Priority_11:Lorg/mobicents/protocols/ss7/map/api/service/mobility/subscriberManagement/LSAIdentificationPriorityValue;
     123: areturn
     124: getstatic     #19                 // Field Priority_12:Lorg/mobicents/protocols/ss7/map/api/service/mobility/subscriberManagement/LSAIdentificationPriorityValue;
     127: areturn
     128: getstatic     #20                 // Field Priority_13:Lorg/mobicents/protocols/ss7/map/api/service/mobility/subscriberManagement/LSAIdentificationPriorityValue;
     131: areturn
     132: getstatic     #21                 // Field Priority_14:Lorg/mobicents/protocols/ss7/map/api/service/mobility/subscriberManagement/LSAIdentificationPriorityValue;
     135: areturn
     136: getstatic     #22                 // Field Priority_15:Lorg/mobicents/protocols/ss7/map/api/service/mobility/subscriberManagement/LSAIdentificationPriorityValue;
     139: areturn
     140: getstatic     #23                 // Field Priority_16:Lorg/mobicents/protocols/ss7/map/api/service/mobility/subscriberManagement/LSAIdentificationPriorityValue;
     143: areturn
     144: aconst_null
     145: areturn

  static {};
    Code:
       0: new           #4                  // class org/mobicents/protocols/ss7/map/api/service/mobility/subscriberManagement/LSAIdentificationPriorityValue
       3: dup
       4: ldc           #24                 // String Priority_1
       6: iconst_0
       7: iconst_0
       8: invokespecial #25                 // Method "<init>":(Ljava/lang/String;II)V
      11: putstatic     #8                  // Field Priority_1:Lorg/mobicents/protocols/ss7/map/api/service/mobility/subscriberManagement/LSAIdentificationPriorityValue;
      14: new           #4                  // class org/mobicents/protocols/ss7/map/api/service/mobility/subscriberManagement/LSAIdentificationPriorityValue
      17: dup
      18: ldc           #26                 // String Priority_2
      20: iconst_1
      21: iconst_1
      22: invokespecial #25                 // Method "<init>":(Ljava/lang/String;II)V
      25: putstatic     #9                  // Field Priority_2:Lorg/mobicents/protocols/ss7/map/api/service/mobility/subscriberManagement/LSAIdentificationPriorityValue;
      28: new           #4                  // class org/mobicents/protocols/ss7/map/api/service/mobility/subscriberManagement/LSAIdentificationPriorityValue
      31: dup
      32: ldc           #27                 // String Priority_3
      34: iconst_2
      35: iconst_2
      36: invokespecial #25                 // Method "<init>":(Ljava/lang/String;II)V
      39: putstatic     #10                 // Field Priority_3:Lorg/mobicents/protocols/ss7/map/api/service/mobility/subscriberManagement/LSAIdentificationPriorityValue;
      42: new           #4                  // class org/mobicents/protocols/ss7/map/api/service/mobility/subscriberManagement/LSAIdentificationPriorityValue
      45: dup
      46: ldc           #28                 // String Priority_4
      48: iconst_3
      49: iconst_3
      50: invokespecial #25                 // Method "<init>":(Ljava/lang/String;II)V
      53: putstatic     #11                 // Field Priority_4:Lorg/mobicents/protocols/ss7/map/api/service/mobility/subscriberManagement/LSAIdentificationPriorityValue;
      56: new           #4                  // class org/mobicents/protocols/ss7/map/api/service/mobility/subscriberManagement/LSAIdentificationPriorityValue
      59: dup
      60: ldc           #29                 // String Priority_5
      62: iconst_4
      63: iconst_4
      64: invokespecial #25                 // Method "<init>":(Ljava/lang/String;II)V
      67: putstatic     #12                 // Field Priority_5:Lorg/mobicents/protocols/ss7/map/api/service/mobility/subscriberManagement/LSAIdentificationPriorityValue;
      70: new           #4                  // class org/mobicents/protocols/ss7/map/api/service/mobility/subscriberManagement/LSAIdentificationPriorityValue
      73: dup
      74: ldc           #30                 // String Priority_6
      76: iconst_5
      77: iconst_5
      78: invokespecial #25                 // Method "<init>":(Ljava/lang/String;II)V
      81: putstatic     #13                 // Field Priority_6:Lorg/mobicents/protocols/ss7/map/api/service/mobility/subscriberManagement/LSAIdentificationPriorityValue;
      84: new           #4                  // class org/mobicents/protocols/ss7/map/api/service/mobility/subscriberManagement/LSAIdentificationPriorityValue
      87: dup
      88: ldc           #31                 // String Priority_7
      90: bipush        6
      92: bipush        6
      94: invokespecial #25                 // Method "<init>":(Ljava/lang/String;II)V
      97: putstatic     #14                 // Field Priority_7:Lorg/mobicents/protocols/ss7/map/api/service/mobility/subscriberManagement/LSAIdentificationPriorityValue;
     100: new           #4                  // class org/mobicents/protocols/ss7/map/api/service/mobility/subscriberManagement/LSAIdentificationPriorityValue
     103: dup
     104: ldc           #32                 // String Priority_8
     106: bipush        7
     108: bipush        7
     110: invokespecial #25                 // Method "<init>":(Ljava/lang/String;II)V
     113: putstatic     #15                 // Field Priority_8:Lorg/mobicents/protocols/ss7/map/api/service/mobility/subscriberManagement/LSAIdentificationPriorityValue;
     116: new           #4                  // class org/mobicents/protocols/ss7/map/api/service/mobility/subscriberManagement/LSAIdentificationPriorityValue
     119: dup
     120: ldc           #33                 // String Priority_9
     122: bipush        8
     124: bipush        8
     126: invokespecial #25                 // Method "<init>":(Ljava/lang/String;II)V
     129: putstatic     #16                 // Field Priority_9:Lorg/mobicents/protocols/ss7/map/api/service/mobility/subscriberManagement/LSAIdentificationPriorityValue;
     132: new           #4                  // class org/mobicents/protocols/ss7/map/api/service/mobility/subscriberManagement/LSAIdentificationPriorityValue
     135: dup
     136: ldc           #34                 // String Priority_10
     138: bipush        9
     140: bipush        9
     142: invokespecial #25                 // Method "<init>":(Ljava/lang/String;II)V
     145: putstatic     #17                 // Field Priority_10:Lorg/mobicents/protocols/ss7/map/api/service/mobility/subscriberManagement/LSAIdentificationPriorityValue;
     148: new           #4                  // class org/mobicents/protocols/ss7/map/api/service/mobility/subscriberManagement/LSAIdentificationPriorityValue
     151: dup
     152: ldc           #35                 // String Priority_11
     154: bipush        10
     156: bipush        10
     158: invokespecial #25                 // Method "<init>":(Ljava/lang/String;II)V
     161: putstatic     #18                 // Field Priority_11:Lorg/mobicents/protocols/ss7/map/api/service/mobility/subscriberManagement/LSAIdentificationPriorityValue;
     164: new           #4                  // class org/mobicents/protocols/ss7/map/api/service/mobility/subscriberManagement/LSAIdentificationPriorityValue
     167: dup
     168: ldc           #36                 // String Priority_12
     170: bipush        11
     172: bipush        11
     174: invokespecial #25                 // Method "<init>":(Ljava/lang/String;II)V
     177: putstatic     #19                 // Field Priority_12:Lorg/mobicents/protocols/ss7/map/api/service/mobility/subscriberManagement/LSAIdentificationPriorityValue;
     180: new           #4                  // class org/mobicents/protocols/ss7/map/api/service/mobility/subscriberManagement/LSAIdentificationPriorityValue
     183: dup
     184: ldc           #37                 // String Priority_13
     186: bipush        12
     188: bipush        12
     190: invokespecial #25                 // Method "<init>":(Ljava/lang/String;II)V
     193: putstatic     #20                 // Field Priority_13:Lorg/mobicents/protocols/ss7/map/api/service/mobility/subscriberManagement/LSAIdentificationPriorityValue;
     196: new           #4                  // class org/mobicents/protocols/ss7/map/api/service/mobility/subscriberManagement/LSAIdentificationPriorityValue
     199: dup
     200: ldc           #38                 // String Priority_14
     202: bipush        13
     204: bipush        13
     206: invokespecial #25                 // Method "<init>":(Ljava/lang/String;II)V
     209: putstatic     #21                 // Field Priority_14:Lorg/mobicents/protocols/ss7/map/api/service/mobility/subscriberManagement/LSAIdentificationPriorityValue;
     212: new           #4                  // class org/mobicents/protocols/ss7/map/api/service/mobility/subscriberManagement/LSAIdentificationPriorityValue
     215: dup
     216: ldc           #39                 // String Priority_15
     218: bipush        14
     220: bipush        13
     222: invokespecial #25                 // Method "<init>":(Ljava/lang/String;II)V
     225: putstatic     #22                 // Field Priority_15:Lorg/mobicents/protocols/ss7/map/api/service/mobility/subscriberManagement/LSAIdentificationPriorityValue;
     228: new           #4                  // class org/mobicents/protocols/ss7/map/api/service/mobility/subscriberManagement/LSAIdentificationPriorityValue
     231: dup
     232: ldc           #40                 // String Priority_16
     234: bipush        15
     236: bipush        15
     238: invokespecial #25                 // Method "<init>":(Ljava/lang/String;II)V
     241: putstatic     #23                 // Field Priority_16:Lorg/mobicents/protocols/ss7/map/api/service/mobility/subscriberManagement/LSAIdentificationPriorityValue;
     244: bipush        16
     246: anewarray     #4                  // class org/mobicents/protocols/ss7/map/api/service/mobility/subscriberManagement/LSAIdentificationPriorityValue
     249: dup
     250: iconst_0
     251: getstatic     #8                  // Field Priority_1:Lorg/mobicents/protocols/ss7/map/api/service/mobility/subscriberManagement/LSAIdentificationPriorityValue;
     254: aastore
     255: dup
     256: iconst_1
     257: getstatic     #9                  // Field Priority_2:Lorg/mobicents/protocols/ss7/map/api/service/mobility/subscriberManagement/LSAIdentificationPriorityValue;
     260: aastore
     261: dup
     262: iconst_2
     263: getstatic     #10                 // Field Priority_3:Lorg/mobicents/protocols/ss7/map/api/service/mobility/subscriberManagement/LSAIdentificationPriorityValue;
     266: aastore
     267: dup
     268: iconst_3
     269: getstatic     #11                 // Field Priority_4:Lorg/mobicents/protocols/ss7/map/api/service/mobility/subscriberManagement/LSAIdentificationPriorityValue;
     272: aastore
     273: dup
     274: iconst_4
     275: getstatic     #12                 // Field Priority_5:Lorg/mobicents/protocols/ss7/map/api/service/mobility/subscriberManagement/LSAIdentificationPriorityValue;
     278: aastore
     279: dup
     280: iconst_5
     281: getstatic     #13                 // Field Priority_6:Lorg/mobicents/protocols/ss7/map/api/service/mobility/subscriberManagement/LSAIdentificationPriorityValue;
     284: aastore
     285: dup
     286: bipush        6
     288: getstatic     #14                 // Field Priority_7:Lorg/mobicents/protocols/ss7/map/api/service/mobility/subscriberManagement/LSAIdentificationPriorityValue;
     291: aastore
     292: dup
     293: bipush        7
     295: getstatic     #15                 // Field Priority_8:Lorg/mobicents/protocols/ss7/map/api/service/mobility/subscriberManagement/LSAIdentificationPriorityValue;
     298: aastore
     299: dup
     300: bipush        8
     302: getstatic     #16                 // Field Priority_9:Lorg/mobicents/protocols/ss7/map/api/service/mobility/subscriberManagement/LSAIdentificationPriorityValue;
     305: aastore
     306: dup
     307: bipush        9
     309: getstatic     #17                 // Field Priority_10:Lorg/mobicents/protocols/ss7/map/api/service/mobility/subscriberManagement/LSAIdentificationPriorityValue;
     312: aastore
     313: dup
     314: bipush        10
     316: getstatic     #18                 // Field Priority_11:Lorg/mobicents/protocols/ss7/map/api/service/mobility/subscriberManagement/LSAIdentificationPriorityValue;
     319: aastore
     320: dup
     321: bipush        11
     323: getstatic     #19                 // Field Priority_12:Lorg/mobicents/protocols/ss7/map/api/service/mobility/subscriberManagement/LSAIdentificationPriorityValue;
     326: aastore
     327: dup
     328: bipush        12
     330: getstatic     #20                 // Field Priority_13:Lorg/mobicents/protocols/ss7/map/api/service/mobility/subscriberManagement/LSAIdentificationPriorityValue;
     333: aastore
     334: dup
     335: bipush        13
     337: getstatic     #21                 // Field Priority_14:Lorg/mobicents/protocols/ss7/map/api/service/mobility/subscriberManagement/LSAIdentificationPriorityValue;
     340: aastore
     341: dup
     342: bipush        14
     344: getstatic     #22                 // Field Priority_15:Lorg/mobicents/protocols/ss7/map/api/service/mobility/subscriberManagement/LSAIdentificationPriorityValue;
     347: aastore
     348: dup
     349: bipush        15
     351: getstatic     #23                 // Field Priority_16:Lorg/mobicents/protocols/ss7/map/api/service/mobility/subscriberManagement/LSAIdentificationPriorityValue;
     354: aastore
     355: putstatic     #1                  // Field $VALUES:[Lorg/mobicents/protocols/ss7/map/api/service/mobility/subscriberManagement/LSAIdentificationPriorityValue;
     358: return
}
