Compiled from "NonEscapingSetAssignment.java"
public class com.datastax.driver.core.querybuilder.NonEscapingSetAssignment extends com.datastax.driver.core.querybuilder.Assignment$SetAssignment {
  private final java.lang.Object value;

  public static final com.datastax.driver.core.querybuilder.NonEscapingSetAssignment of(java.lang.String, java.lang.Object);
    Code:
       0: new           #1                  // class com/datastax/driver/core/querybuilder/NonEscapingSetAssignment
       3: dup
       4: aload_0
       5: aload_1
       6: invokespecial #2                  // Method "<init>":(Ljava/lang/String;Ljava/lang/Object;)V
       9: areturn

  private com.datastax.driver.core.querybuilder.NonEscapingSetAssignment(java.lang.String, java.lang.Object);
    Code:
       0: aload_0
       1: aload_1
       2: aload_2
       3: invokespecial #3                  // Method com/datastax/driver/core/querybuilder/Assignment$SetAssignment."<init>":(Ljava/lang/String;Ljava/lang/Object;)V
       6: aload_0
       7: aload_2
       8: putfield      #4                  // Field value:Ljava/lang/Object;
      11: return

  boolean isIdempotent();
    Code:
       0: aload_0
       1: getfield      #4                  // Field value:Ljava/lang/Object;
       4: invokestatic  #5                  // Method com/datastax/driver/core/querybuilder/Utils.isIdempotent:(Ljava/lang/Object;)Z
       7: ireturn

  void appendTo(java.lang.StringBuilder, java.util.List<java.lang.Object>, com.datastax.driver.core.CodecRegistry);
    Code:
       0: aload_1
       1: aload_0
       2: getfield      #6                  // Field name:Ljava/lang/String;
       5: invokevirtual #7                  // Method java/lang/String.trim:()Ljava/lang/String;
       8: invokevirtual #8                  // Method java/lang/StringBuilder.append:(Ljava/lang/String;)Ljava/lang/StringBuilder;
      11: bipush        61
      13: invokevirtual #9                  // Method java/lang/StringBuilder.append:(C)Ljava/lang/StringBuilder;
      16: pop
      17: aload_0
      18: getfield      #4                  // Field value:Ljava/lang/Object;
      21: aload_3
      22: aload_1
      23: aload_2
      24: invokestatic  #10                 // Method com/datastax/driver/core/querybuilder/Utils.appendValue:(Ljava/lang/Object;Lcom/datastax/driver/core/CodecRegistry;Ljava/lang/StringBuilder;Ljava/util/List;)Ljava/lang/StringBuilder;
      27: pop
      28: return

  boolean containsBindMarker();
    Code:
       0: aload_0
       1: getfield      #4                  // Field value:Ljava/lang/Object;
       4: invokestatic  #11                 // Method com/datastax/driver/core/querybuilder/Utils.containsBindMarker:(Ljava/lang/Object;)Z
       7: ireturn
}
