Compiled from "context.kt"
public final class kotlin.reflect.jvm.internal.impl.serialization.deserialization.DeserializationComponents {
  private final kotlin.reflect.jvm.internal.impl.storage.StorageManager storageManager;

  private final kotlin.reflect.jvm.internal.impl.descriptors.ModuleDescriptor moduleDescriptor;

  private final kotlin.reflect.jvm.internal.impl.serialization.deserialization.DeserializationConfiguration configuration;

  private final kotlin.reflect.jvm.internal.impl.serialization.deserialization.ClassDataFinder classDataFinder;

  private final kotlin.reflect.jvm.internal.impl.serialization.deserialization.AnnotationAndConstantLoader<kotlin.reflect.jvm.internal.impl.descriptors.annotations.AnnotationDescriptor, kotlin.reflect.jvm.internal.impl.resolve.constants.ConstantValue<?>> annotationAndConstantLoader;

  private final kotlin.reflect.jvm.internal.impl.descriptors.PackageFragmentProvider packageFragmentProvider;

  private final kotlin.reflect.jvm.internal.impl.serialization.deserialization.LocalClassifierTypeSettings localClassifierTypeSettings;

  private final kotlin.reflect.jvm.internal.impl.serialization.deserialization.ErrorReporter errorReporter;

  private final kotlin.reflect.jvm.internal.impl.incremental.components.LookupTracker lookupTracker;

  private final kotlin.reflect.jvm.internal.impl.serialization.deserialization.FlexibleTypeDeserializer flexibleTypeDeserializer;

  private final java.lang.Iterable<kotlin.reflect.jvm.internal.impl.descriptors.deserialization.ClassDescriptorFactory> fictitiousClassDescriptorFactories;

  private final kotlin.reflect.jvm.internal.impl.descriptors.NotFoundClasses notFoundClasses;

  private final kotlin.reflect.jvm.internal.impl.serialization.deserialization.ContractDeserializer contractDeserializer;

  private final kotlin.reflect.jvm.internal.impl.descriptors.deserialization.AdditionalClassPartsProvider additionalClassPartsProvider;

  private final kotlin.reflect.jvm.internal.impl.descriptors.deserialization.PlatformDependentDeclarationFilter platformDependentDeclarationFilter;

  private final kotlin.reflect.jvm.internal.impl.protobuf.ExtensionRegistryLite extensionRegistryLite;

  private final kotlin.reflect.jvm.internal.impl.types.checker.NewKotlinTypeChecker kotlinTypeChecker;

  private final kotlin.reflect.jvm.internal.impl.resolve.sam.SamConversionResolver samConversionResolver;

  private final kotlin.reflect.jvm.internal.impl.descriptors.deserialization.PlatformDependentTypeTransformer platformDependentTypeTransformer;

  private final java.util.List<kotlin.reflect.jvm.internal.impl.types.TypeAttributeTranslator> typeAttributeTranslators;

  private final kotlin.reflect.jvm.internal.impl.serialization.deserialization.EnumEntriesDeserializationSupport enumEntriesDeserializationSupport;

  private final kotlin.reflect.jvm.internal.impl.serialization.deserialization.ClassDeserializer classDeserializer;

  public kotlin.reflect.jvm.internal.impl.serialization.deserialization.DeserializationComponents(kotlin.reflect.jvm.internal.impl.storage.StorageManager, kotlin.reflect.jvm.internal.impl.descriptors.ModuleDescriptor, kotlin.reflect.jvm.internal.impl.serialization.deserialization.DeserializationConfiguration, kotlin.reflect.jvm.internal.impl.serialization.deserialization.ClassDataFinder, kotlin.reflect.jvm.internal.impl.serialization.deserialization.AnnotationAndConstantLoader<? extends kotlin.reflect.jvm.internal.impl.descriptors.annotations.AnnotationDescriptor, ? extends kotlin.reflect.jvm.internal.impl.resolve.constants.ConstantValue<?>>, kotlin.reflect.jvm.internal.impl.descriptors.PackageFragmentProvider, kotlin.reflect.jvm.internal.impl.serialization.deserialization.LocalClassifierTypeSettings, kotlin.reflect.jvm.internal.impl.serialization.deserialization.ErrorReporter, kotlin.reflect.jvm.internal.impl.incremental.components.LookupTracker, kotlin.reflect.jvm.internal.impl.serialization.deserialization.FlexibleTypeDeserializer, java.lang.Iterable<? extends kotlin.reflect.jvm.internal.impl.descriptors.deserialization.ClassDescriptorFactory>, kotlin.reflect.jvm.internal.impl.descriptors.NotFoundClasses, kotlin.reflect.jvm.internal.impl.serialization.deserialization.ContractDeserializer, kotlin.reflect.jvm.internal.impl.descriptors.deserialization.AdditionalClassPartsProvider, kotlin.reflect.jvm.internal.impl.descriptors.deserialization.PlatformDependentDeclarationFilter, kotlin.reflect.jvm.internal.impl.protobuf.ExtensionRegistryLite, kotlin.reflect.jvm.internal.impl.types.checker.NewKotlinTypeChecker, kotlin.reflect.jvm.internal.impl.resolve.sam.SamConversionResolver, kotlin.reflect.jvm.internal.impl.descriptors.deserialization.PlatformDependentTypeTransformer, java.util.List<? extends kotlin.reflect.jvm.internal.impl.types.TypeAttributeTranslator>, kotlin.reflect.jvm.internal.impl.serialization.deserialization.EnumEntriesDeserializationSupport);
    Code:
       0: aload_1
       1: ldc           #28                 // String storageManager
       3: invokestatic  #100                // Method kotlin/jvm/internal/Intrinsics.checkNotNullParameter:(Ljava/lang/Object;Ljava/lang/String;)V
       6: aload_2
       7: ldc           #21                 // String moduleDescriptor
       9: invokestatic  #100                // Method kotlin/jvm/internal/Intrinsics.checkNotNullParameter:(Ljava/lang/Object;Ljava/lang/String;)V
      12: aload_3
      13: ldc           #9                  // String configuration
      15: invokestatic  #100                // Method kotlin/jvm/internal/Intrinsics.checkNotNullParameter:(Ljava/lang/Object;Ljava/lang/String;)V
      18: aload         4
      20: ldc           #7                  // String classDataFinder
      22: invokestatic  #100                // Method kotlin/jvm/internal/Intrinsics.checkNotNullParameter:(Ljava/lang/Object;Ljava/lang/String;)V
      25: aload         5
      27: ldc           #6                  // String annotationAndConstantLoader
      29: invokestatic  #100                // Method kotlin/jvm/internal/Intrinsics.checkNotNullParameter:(Ljava/lang/Object;Ljava/lang/String;)V
      32: aload         6
      34: ldc           #24                 // String packageFragmentProvider
      36: invokestatic  #100                // Method kotlin/jvm/internal/Intrinsics.checkNotNullParameter:(Ljava/lang/Object;Ljava/lang/String;)V
      39: aload         7
      41: ldc           #18                 // String localClassifierTypeSettings
      43: invokestatic  #100                // Method kotlin/jvm/internal/Intrinsics.checkNotNullParameter:(Ljava/lang/Object;Ljava/lang/String;)V
      46: aload         8
      48: ldc           #13                 // String errorReporter
      50: invokestatic  #100                // Method kotlin/jvm/internal/Intrinsics.checkNotNullParameter:(Ljava/lang/Object;Ljava/lang/String;)V
      53: aload         9
      55: ldc           #19                 // String lookupTracker
      57: invokestatic  #100                // Method kotlin/jvm/internal/Intrinsics.checkNotNullParameter:(Ljava/lang/Object;Ljava/lang/String;)V
      60: aload         10
      62: ldc           #16                 // String flexibleTypeDeserializer
      64: invokestatic  #100                // Method kotlin/jvm/internal/Intrinsics.checkNotNullParameter:(Ljava/lang/Object;Ljava/lang/String;)V
      67: aload         11
      69: ldc           #15                 // String fictitiousClassDescriptorFactories
      71: invokestatic  #100                // Method kotlin/jvm/internal/Intrinsics.checkNotNullParameter:(Ljava/lang/Object;Ljava/lang/String;)V
      74: aload         12
      76: ldc           #23                 // String notFoundClasses
      78: invokestatic  #100                // Method kotlin/jvm/internal/Intrinsics.checkNotNullParameter:(Ljava/lang/Object;Ljava/lang/String;)V
      81: aload         13
      83: ldc           #10                 // String contractDeserializer
      85: invokestatic  #100                // Method kotlin/jvm/internal/Intrinsics.checkNotNullParameter:(Ljava/lang/Object;Ljava/lang/String;)V
      88: aload         14
      90: ldc           #5                  // String additionalClassPartsProvider
      92: invokestatic  #100                // Method kotlin/jvm/internal/Intrinsics.checkNotNullParameter:(Ljava/lang/Object;Ljava/lang/String;)V
      95: aload         15
      97: ldc           #25                 // String platformDependentDeclarationFilter
      99: invokestatic  #100                // Method kotlin/jvm/internal/Intrinsics.checkNotNullParameter:(Ljava/lang/Object;Ljava/lang/String;)V
     102: aload         16
     104: ldc           #14                 // String extensionRegistryLite
     106: invokestatic  #100                // Method kotlin/jvm/internal/Intrinsics.checkNotNullParameter:(Ljava/lang/Object;Ljava/lang/String;)V
     109: aload         17
     111: ldc           #17                 // String kotlinTypeChecker
     113: invokestatic  #100                // Method kotlin/jvm/internal/Intrinsics.checkNotNullParameter:(Ljava/lang/Object;Ljava/lang/String;)V
     116: aload         18
     118: ldc           #27                 // String samConversionResolver
     120: invokestatic  #100                // Method kotlin/jvm/internal/Intrinsics.checkNotNullParameter:(Ljava/lang/Object;Ljava/lang/String;)V
     123: aload         19
     125: ldc           #26                 // String platformDependentTypeTransformer
     127: invokestatic  #100                // Method kotlin/jvm/internal/Intrinsics.checkNotNullParameter:(Ljava/lang/Object;Ljava/lang/String;)V
     130: aload         20
     132: ldc           #29                 // String typeAttributeTranslators
     134: invokestatic  #100                // Method kotlin/jvm/internal/Intrinsics.checkNotNullParameter:(Ljava/lang/Object;Ljava/lang/String;)V
     137: aload         21
     139: ldc           #12                 // String enumEntriesDeserializationSupport
     141: invokestatic  #100                // Method kotlin/jvm/internal/Intrinsics.checkNotNullParameter:(Ljava/lang/Object;Ljava/lang/String;)V
     144: aload_0
     145: invokespecial #97                 // Method java/lang/Object."<init>":()V
     148: aload_0
     149: aload_1
     150: putfield      #92                 // Field storageManager:Lkotlin/reflect/jvm/internal/impl/storage/StorageManager;
     153: aload_0
     154: aload_2
     155: putfield      #86                 // Field moduleDescriptor:Lkotlin/reflect/jvm/internal/impl/descriptors/ModuleDescriptor;
     158: aload_0
     159: aload_3
     160: putfield      #76                 // Field configuration:Lkotlin/reflect/jvm/internal/impl/serialization/deserialization/DeserializationConfiguration;
     163: aload_0
     164: aload         4
     166: putfield      #74                 // Field classDataFinder:Lkotlin/reflect/jvm/internal/impl/serialization/deserialization/ClassDataFinder;
     169: aload_0
     170: aload         5
     172: putfield      #73                 // Field annotationAndConstantLoader:Lkotlin/reflect/jvm/internal/impl/serialization/deserialization/AnnotationAndConstantLoader;
     175: aload_0
     176: aload         6
     178: putfield      #88                 // Field packageFragmentProvider:Lkotlin/reflect/jvm/internal/impl/descriptors/PackageFragmentProvider;
     181: aload_0
     182: aload         7
     184: putfield      #84                 // Field localClassifierTypeSettings:Lkotlin/reflect/jvm/internal/impl/serialization/deserialization/LocalClassifierTypeSettings;
     187: aload_0
     188: aload         8
     190: putfield      #79                 // Field errorReporter:Lkotlin/reflect/jvm/internal/impl/serialization/deserialization/ErrorReporter;
     193: aload_0
     194: aload         9
     196: putfield      #85                 // Field lookupTracker:Lkotlin/reflect/jvm/internal/impl/incremental/components/LookupTracker;
     199: aload_0
     200: aload         10
     202: putfield      #82                 // Field flexibleTypeDeserializer:Lkotlin/reflect/jvm/internal/impl/serialization/deserialization/FlexibleTypeDeserializer;
     205: aload_0
     206: aload         11
     208: putfield      #81                 // Field fictitiousClassDescriptorFactories:Ljava/lang/Iterable;
     211: aload_0
     212: aload         12
     214: putfield      #87                 // Field notFoundClasses:Lkotlin/reflect/jvm/internal/impl/descriptors/NotFoundClasses;
     217: aload_0
     218: aload         13
     220: putfield      #77                 // Field contractDeserializer:Lkotlin/reflect/jvm/internal/impl/serialization/deserialization/ContractDeserializer;
     223: aload_0
     224: aload         14
     226: putfield      #72                 // Field additionalClassPartsProvider:Lkotlin/reflect/jvm/internal/impl/descriptors/deserialization/AdditionalClassPartsProvider;
     229: aload_0
     230: aload         15
     232: putfield      #89                 // Field platformDependentDeclarationFilter:Lkotlin/reflect/jvm/internal/impl/descriptors/deserialization/PlatformDependentDeclarationFilter;
     235: aload_0
     236: aload         16
     238: putfield      #80                 // Field extensionRegistryLite:Lkotlin/reflect/jvm/internal/impl/protobuf/ExtensionRegistryLite;
     241: aload_0
     242: aload         17
     244: putfield      #83                 // Field kotlinTypeChecker:Lkotlin/reflect/jvm/internal/impl/types/checker/NewKotlinTypeChecker;
     247: aload_0
     248: aload         18
     250: putfield      #91                 // Field samConversionResolver:Lkotlin/reflect/jvm/internal/impl/resolve/sam/SamConversionResolver;
     253: aload_0
     254: aload         19
     256: putfield      #90                 // Field platformDependentTypeTransformer:Lkotlin/reflect/jvm/internal/impl/descriptors/deserialization/PlatformDependentTypeTransformer;
     259: aload_0
     260: aload         20
     262: putfield      #93                 // Field typeAttributeTranslators:Ljava/util/List;
     265: aload_0
     266: aload         21
     268: putfield      #78                 // Field enumEntriesDeserializationSupport:Lkotlin/reflect/jvm/internal/impl/serialization/deserialization/EnumEntriesDeserializationSupport;
     271: aload_0
     272: new           #55                 // class kotlin/reflect/jvm/internal/impl/serialization/deserialization/ClassDeserializer
     275: dup
     276: aload_0
     277: invokespecial #101                // Method kotlin/reflect/jvm/internal/impl/serialization/deserialization/ClassDeserializer."<init>":(Lkotlin/reflect/jvm/internal/impl/serialization/deserialization/DeserializationComponents;)V
     280: putfield      #75                 // Field classDeserializer:Lkotlin/reflect/jvm/internal/impl/serialization/deserialization/ClassDeserializer;
     283: return

  public kotlin.reflect.jvm.internal.impl.serialization.deserialization.DeserializationComponents(kotlin.reflect.jvm.internal.impl.storage.StorageManager, kotlin.reflect.jvm.internal.impl.descriptors.ModuleDescriptor, kotlin.reflect.jvm.internal.impl.serialization.deserialization.DeserializationConfiguration, kotlin.reflect.jvm.internal.impl.serialization.deserialization.ClassDataFinder, kotlin.reflect.jvm.internal.impl.serialization.deserialization.AnnotationAndConstantLoader, kotlin.reflect.jvm.internal.impl.descriptors.PackageFragmentProvider, kotlin.reflect.jvm.internal.impl.serialization.deserialization.LocalClassifierTypeSettings, kotlin.reflect.jvm.internal.impl.serialization.deserialization.ErrorReporter, kotlin.reflect.jvm.internal.impl.incremental.components.LookupTracker, kotlin.reflect.jvm.internal.impl.serialization.deserialization.FlexibleTypeDeserializer, java.lang.Iterable, kotlin.reflect.jvm.internal.impl.descriptors.NotFoundClasses, kotlin.reflect.jvm.internal.impl.serialization.deserialization.ContractDeserializer, kotlin.reflect.jvm.internal.impl.descriptors.deserialization.AdditionalClassPartsProvider, kotlin.reflect.jvm.internal.impl.descriptors.deserialization.PlatformDependentDeclarationFilter, kotlin.reflect.jvm.internal.impl.protobuf.ExtensionRegistryLite, kotlin.reflect.jvm.internal.impl.types.checker.NewKotlinTypeChecker, kotlin.reflect.jvm.internal.impl.resolve.sam.SamConversionResolver, kotlin.reflect.jvm.internal.impl.descriptors.deserialization.PlatformDependentTypeTransformer, java.util.List, kotlin.reflect.jvm.internal.impl.serialization.deserialization.EnumEntriesDeserializationSupport, int, kotlin.jvm.internal.DefaultConstructorMarker);
    Code:
       0: iload         22
       2: sipush        8192
       5: iand
       6: ifeq          17
       9: getstatic     #69                 // Field kotlin/reflect/jvm/internal/impl/descriptors/deserialization/AdditionalClassPartsProvider$None.INSTANCE:Lkotlin/reflect/jvm/internal/impl/descriptors/deserialization/AdditionalClassPartsProvider$None;
      12: checkcast     #42                 // class kotlin/reflect/jvm/internal/impl/descriptors/deserialization/AdditionalClassPartsProvider
      15: astore        14
      17: iload         22
      19: sipush        16384
      22: iand
      23: ifeq          34
      26: getstatic     #70                 // Field kotlin/reflect/jvm/internal/impl/descriptors/deserialization/PlatformDependentDeclarationFilter$All.INSTANCE:Lkotlin/reflect/jvm/internal/impl/descriptors/deserialization/PlatformDependentDeclarationFilter$All;
      29: checkcast     #44                 // class kotlin/reflect/jvm/internal/impl/descriptors/deserialization/PlatformDependentDeclarationFilter
      32: astore        15
      34: iload         22
      36: ldc           #1                  // int 65536
      38: iand
      39: ifeq          53
      42: getstatic     #96                 // Field kotlin/reflect/jvm/internal/impl/types/checker/NewKotlinTypeChecker.Companion:Lkotlin/reflect/jvm/internal/impl/types/checker/NewKotlinTypeChecker$Companion;
      45: invokevirtual #105                // Method kotlin/reflect/jvm/internal/impl/types/checker/NewKotlinTypeChecker$Companion.getDefault:()Lkotlin/reflect/jvm/internal/impl/types/checker/NewKotlinTypeCheckerImpl;
      48: checkcast     #67                 // class kotlin/reflect/jvm/internal/impl/types/checker/NewKotlinTypeChecker
      51: astore        17
      53: iload         22
      55: ldc           #2                  // int 262144
      57: iand
      58: ifeq          69
      61: getstatic     #71                 // Field kotlin/reflect/jvm/internal/impl/descriptors/deserialization/PlatformDependentTypeTransformer$None.INSTANCE:Lkotlin/reflect/jvm/internal/impl/descriptors/deserialization/PlatformDependentTypeTransformer$None;
      64: checkcast     #46                 // class kotlin/reflect/jvm/internal/impl/descriptors/deserialization/PlatformDependentTypeTransformer
      67: astore        19
      69: iload         22
      71: ldc           #3                  // int 524288
      73: iand
      74: ifeq          85
      77: getstatic     #95                 // Field kotlin/reflect/jvm/internal/impl/types/DefaultTypeAttributeTranslator.INSTANCE:Lkotlin/reflect/jvm/internal/impl/types/DefaultTypeAttributeTranslator;
      80: invokestatic  #99                 // Method kotlin/collections/CollectionsKt.listOf:(Ljava/lang/Object;)Ljava/util/List;
      83: astore        20
      85: iload         22
      87: ldc           #4                  // int 1048576
      89: iand
      90: ifeq          101
      93: getstatic     #94                 // Field kotlin/reflect/jvm/internal/impl/serialization/deserialization/EnumEntriesDeserializationSupport$Default.INSTANCE:Lkotlin/reflect/jvm/internal/impl/serialization/deserialization/EnumEntriesDeserializationSupport$Default;
      96: checkcast     #60                 // class kotlin/reflect/jvm/internal/impl/serialization/deserialization/EnumEntriesDeserializationSupport
      99: astore        21
     101: aload_0
     102: aload_1
     103: aload_2
     104: aload_3
     105: aload         4
     107: aload         5
     109: aload         6
     111: aload         7
     113: aload         8
     115: aload         9
     117: aload         10
     119: aload         11
     121: aload         12
     123: aload         13
     125: aload         14
     127: aload         15
     129: aload         16
     131: aload         17
     133: aload         18
     135: aload         19
     137: aload         20
     139: aload         21
     141: invokespecial #103                // Method "<init>":(Lkotlin/reflect/jvm/internal/impl/storage/StorageManager;Lkotlin/reflect/jvm/internal/impl/descriptors/ModuleDescriptor;Lkotlin/reflect/jvm/internal/impl/serialization/deserialization/DeserializationConfiguration;Lkotlin/reflect/jvm/internal/impl/serialization/deserialization/ClassDataFinder;Lkotlin/reflect/jvm/internal/impl/serialization/deserialization/AnnotationAndConstantLoader;Lkotlin/reflect/jvm/internal/impl/descriptors/PackageFragmentProvider;Lkotlin/reflect/jvm/internal/impl/serialization/deserialization/LocalClassifierTypeSettings;Lkotlin/reflect/jvm/internal/impl/serialization/deserialization/ErrorReporter;Lkotlin/reflect/jvm/internal/impl/incremental/components/LookupTracker;Lkotlin/reflect/jvm/internal/impl/serialization/deserialization/FlexibleTypeDeserializer;Ljava/lang/Iterable;Lkotlin/reflect/jvm/internal/impl/descriptors/NotFoundClasses;Lkotlin/reflect/jvm/internal/impl/serialization/deserialization/ContractDeserializer;Lkotlin/reflect/jvm/internal/impl/descriptors/deserialization/AdditionalClassPartsProvider;Lkotlin/reflect/jvm/internal/impl/descriptors/deserialization/PlatformDependentDeclarationFilter;Lkotlin/reflect/jvm/internal/impl/protobuf/ExtensionRegistryLite;Lkotlin/reflect/jvm/internal/impl/types/checker/NewKotlinTypeChecker;Lkotlin/reflect/jvm/internal/impl/resolve/sam/SamConversionResolver;Lkotlin/reflect/jvm/internal/impl/descriptors/deserialization/PlatformDependentTypeTransformer;Ljava/util/List;Lkotlin/reflect/jvm/internal/impl/serialization/deserialization/EnumEntriesDeserializationSupport;)V
     144: return

  public final kotlin.reflect.jvm.internal.impl.storage.StorageManager getStorageManager();
    Code:
       0: aload_0
       1: getfield      #92                 // Field storageManager:Lkotlin/reflect/jvm/internal/impl/storage/StorageManager;
       4: areturn

  public final kotlin.reflect.jvm.internal.impl.descriptors.ModuleDescriptor getModuleDescriptor();
    Code:
       0: aload_0
       1: getfield      #86                 // Field moduleDescriptor:Lkotlin/reflect/jvm/internal/impl/descriptors/ModuleDescriptor;
       4: areturn

  public final kotlin.reflect.jvm.internal.impl.serialization.deserialization.DeserializationConfiguration getConfiguration();
    Code:
       0: aload_0
       1: getfield      #76                 // Field configuration:Lkotlin/reflect/jvm/internal/impl/serialization/deserialization/DeserializationConfiguration;
       4: areturn

  public final kotlin.reflect.jvm.internal.impl.serialization.deserialization.ClassDataFinder getClassDataFinder();
    Code:
       0: aload_0
       1: getfield      #74                 // Field classDataFinder:Lkotlin/reflect/jvm/internal/impl/serialization/deserialization/ClassDataFinder;
       4: areturn

  public final kotlin.reflect.jvm.internal.impl.serialization.deserialization.AnnotationAndConstantLoader<kotlin.reflect.jvm.internal.impl.descriptors.annotations.AnnotationDescriptor, kotlin.reflect.jvm.internal.impl.resolve.constants.ConstantValue<?>> getAnnotationAndConstantLoader();
    Code:
       0: aload_0
       1: getfield      #73                 // Field annotationAndConstantLoader:Lkotlin/reflect/jvm/internal/impl/serialization/deserialization/AnnotationAndConstantLoader;
       4: areturn

  public final kotlin.reflect.jvm.internal.impl.descriptors.PackageFragmentProvider getPackageFragmentProvider();
    Code:
       0: aload_0
       1: getfield      #88                 // Field packageFragmentProvider:Lkotlin/reflect/jvm/internal/impl/descriptors/PackageFragmentProvider;
       4: areturn

  public final kotlin.reflect.jvm.internal.impl.serialization.deserialization.LocalClassifierTypeSettings getLocalClassifierTypeSettings();
    Code:
       0: aload_0
       1: getfield      #84                 // Field localClassifierTypeSettings:Lkotlin/reflect/jvm/internal/impl/serialization/deserialization/LocalClassifierTypeSettings;
       4: areturn

  public final kotlin.reflect.jvm.internal.impl.serialization.deserialization.ErrorReporter getErrorReporter();
    Code:
       0: aload_0
       1: getfield      #79                 // Field errorReporter:Lkotlin/reflect/jvm/internal/impl/serialization/deserialization/ErrorReporter;
       4: areturn

  public final kotlin.reflect.jvm.internal.impl.incremental.components.LookupTracker getLookupTracker();
    Code:
       0: aload_0
       1: getfield      #85                 // Field lookupTracker:Lkotlin/reflect/jvm/internal/impl/incremental/components/LookupTracker;
       4: areturn

  public final kotlin.reflect.jvm.internal.impl.serialization.deserialization.FlexibleTypeDeserializer getFlexibleTypeDeserializer();
    Code:
       0: aload_0
       1: getfield      #82                 // Field flexibleTypeDeserializer:Lkotlin/reflect/jvm/internal/impl/serialization/deserialization/FlexibleTypeDeserializer;
       4: areturn

  public final java.lang.Iterable<kotlin.reflect.jvm.internal.impl.descriptors.deserialization.ClassDescriptorFactory> getFictitiousClassDescriptorFactories();
    Code:
       0: aload_0
       1: getfield      #81                 // Field fictitiousClassDescriptorFactories:Ljava/lang/Iterable;
       4: areturn

  public final kotlin.reflect.jvm.internal.impl.descriptors.NotFoundClasses getNotFoundClasses();
    Code:
       0: aload_0
       1: getfield      #87                 // Field notFoundClasses:Lkotlin/reflect/jvm/internal/impl/descriptors/NotFoundClasses;
       4: areturn

  public final kotlin.reflect.jvm.internal.impl.serialization.deserialization.ContractDeserializer getContractDeserializer();
    Code:
       0: aload_0
       1: getfield      #77                 // Field contractDeserializer:Lkotlin/reflect/jvm/internal/impl/serialization/deserialization/ContractDeserializer;
       4: areturn

  public final kotlin.reflect.jvm.internal.impl.descriptors.deserialization.AdditionalClassPartsProvider getAdditionalClassPartsProvider();
    Code:
       0: aload_0
       1: getfield      #72                 // Field additionalClassPartsProvider:Lkotlin/reflect/jvm/internal/impl/descriptors/deserialization/AdditionalClassPartsProvider;
       4: areturn

  public final kotlin.reflect.jvm.internal.impl.descriptors.deserialization.PlatformDependentDeclarationFilter getPlatformDependentDeclarationFilter();
    Code:
       0: aload_0
       1: getfield      #89                 // Field platformDependentDeclarationFilter:Lkotlin/reflect/jvm/internal/impl/descriptors/deserialization/PlatformDependentDeclarationFilter;
       4: areturn

  public final kotlin.reflect.jvm.internal.impl.protobuf.ExtensionRegistryLite getExtensionRegistryLite();
    Code:
       0: aload_0
       1: getfield      #80                 // Field extensionRegistryLite:Lkotlin/reflect/jvm/internal/impl/protobuf/ExtensionRegistryLite;
       4: areturn

  public final kotlin.reflect.jvm.internal.impl.types.checker.NewKotlinTypeChecker getKotlinTypeChecker();
    Code:
       0: aload_0
       1: getfield      #83                 // Field kotlinTypeChecker:Lkotlin/reflect/jvm/internal/impl/types/checker/NewKotlinTypeChecker;
       4: areturn

  public final kotlin.reflect.jvm.internal.impl.descriptors.deserialization.PlatformDependentTypeTransformer getPlatformDependentTypeTransformer();
    Code:
       0: aload_0
       1: getfield      #90                 // Field platformDependentTypeTransformer:Lkotlin/reflect/jvm/internal/impl/descriptors/deserialization/PlatformDependentTypeTransformer;
       4: areturn

  public final java.util.List<kotlin.reflect.jvm.internal.impl.types.TypeAttributeTranslator> getTypeAttributeTranslators();
    Code:
       0: aload_0
       1: getfield      #93                 // Field typeAttributeTranslators:Ljava/util/List;
       4: areturn

  public final kotlin.reflect.jvm.internal.impl.serialization.deserialization.EnumEntriesDeserializationSupport getEnumEntriesDeserializationSupport();
    Code:
       0: aload_0
       1: getfield      #78                 // Field enumEntriesDeserializationSupport:Lkotlin/reflect/jvm/internal/impl/serialization/deserialization/EnumEntriesDeserializationSupport;
       4: areturn

  public final kotlin.reflect.jvm.internal.impl.serialization.deserialization.ClassDeserializer getClassDeserializer();
    Code:
       0: aload_0
       1: getfield      #75                 // Field classDeserializer:Lkotlin/reflect/jvm/internal/impl/serialization/deserialization/ClassDeserializer;
       4: areturn

  public final kotlin.reflect.jvm.internal.impl.descriptors.ClassDescriptor deserializeClass(kotlin.reflect.jvm.internal.impl.name.ClassId);
    Code:
       0: aload_1
       1: ldc           #8                  // String classId
       3: invokestatic  #100                // Method kotlin/jvm/internal/Intrinsics.checkNotNullParameter:(Ljava/lang/Object;Ljava/lang/String;)V
       6: aload_0
       7: getfield      #75                 // Field classDeserializer:Lkotlin/reflect/jvm/internal/impl/serialization/deserialization/ClassDeserializer;
      10: aload_1
      11: aconst_null
      12: iconst_2
      13: aconst_null
      14: invokestatic  #102                // Method kotlin/reflect/jvm/internal/impl/serialization/deserialization/ClassDeserializer.deserializeClass$default:(Lkotlin/reflect/jvm/internal/impl/serialization/deserialization/ClassDeserializer;Lkotlin/reflect/jvm/internal/impl/name/ClassId;Lkotlin/reflect/jvm/internal/impl/serialization/deserialization/ClassData;ILjava/lang/Object;)Lkotlin/reflect/jvm/internal/impl/descriptors/ClassDescriptor;
      17: areturn

  public final kotlin.reflect.jvm.internal.impl.serialization.deserialization.DeserializationContext createContext(kotlin.reflect.jvm.internal.impl.descriptors.PackageFragmentDescriptor, kotlin.reflect.jvm.internal.impl.metadata.deserialization.NameResolver, kotlin.reflect.jvm.internal.impl.metadata.deserialization.TypeTable, kotlin.reflect.jvm.internal.impl.metadata.deserialization.VersionRequirementTable, kotlin.reflect.jvm.internal.impl.metadata.deserialization.BinaryVersion, kotlin.reflect.jvm.internal.impl.serialization.deserialization.descriptors.DeserializedContainerSource);
    Code:
       0: aload_1
       1: ldc           #11                 // String descriptor
       3: invokestatic  #100                // Method kotlin/jvm/internal/Intrinsics.checkNotNullParameter:(Ljava/lang/Object;Ljava/lang/String;)V
       6: aload_2
       7: ldc           #22                 // String nameResolver
       9: invokestatic  #100                // Method kotlin/jvm/internal/Intrinsics.checkNotNullParameter:(Ljava/lang/Object;Ljava/lang/String;)V
      12: aload_3
      13: ldc           #30                 // String typeTable
      15: invokestatic  #100                // Method kotlin/jvm/internal/Intrinsics.checkNotNullParameter:(Ljava/lang/Object;Ljava/lang/String;)V
      18: aload         4
      20: ldc           #31                 // String versionRequirementTable
      22: invokestatic  #100                // Method kotlin/jvm/internal/Intrinsics.checkNotNullParameter:(Ljava/lang/Object;Ljava/lang/String;)V
      25: aload         5
      27: ldc           #20                 // String metadataVersion
      29: invokestatic  #100                // Method kotlin/jvm/internal/Intrinsics.checkNotNullParameter:(Ljava/lang/Object;Ljava/lang/String;)V
      32: new           #59                 // class kotlin/reflect/jvm/internal/impl/serialization/deserialization/DeserializationContext
      35: dup
      36: aload_0
      37: aload_2
      38: aload_1
      39: checkcast     #38                 // class kotlin/reflect/jvm/internal/impl/descriptors/DeclarationDescriptor
      42: aload_3
      43: aload         4
      45: aload         5
      47: aload         6
      49: aconst_null
      50: invokestatic  #98                 // Method kotlin/collections/CollectionsKt.emptyList:()Ljava/util/List;
      53: invokespecial #104                // Method kotlin/reflect/jvm/internal/impl/serialization/deserialization/DeserializationContext."<init>":(Lkotlin/reflect/jvm/internal/impl/serialization/deserialization/DeserializationComponents;Lkotlin/reflect/jvm/internal/impl/metadata/deserialization/NameResolver;Lkotlin/reflect/jvm/internal/impl/descriptors/DeclarationDescriptor;Lkotlin/reflect/jvm/internal/impl/metadata/deserialization/TypeTable;Lkotlin/reflect/jvm/internal/impl/metadata/deserialization/VersionRequirementTable;Lkotlin/reflect/jvm/internal/impl/metadata/deserialization/BinaryVersion;Lkotlin/reflect/jvm/internal/impl/serialization/deserialization/descriptors/DeserializedContainerSource;Lkotlin/reflect/jvm/internal/impl/serialization/deserialization/TypeDeserializer;Ljava/util/List;)V
      56: areturn
}
