Compiled from "STSTokenRetriever.java"
public class org.apache.cxf.ws.security.trust.STSTokenRetriever$TokenRequestParams {
  private org.w3c.dom.Element issuer;

  private org.apache.wss4j.policy.model.Trust10 trust10;

  private org.apache.wss4j.policy.model.Trust13 trust13;

  private org.w3c.dom.Element tokenTemplate;

  private java.lang.String wspNamespace;

  private org.w3c.dom.Element claims;

  public org.apache.cxf.ws.security.trust.STSTokenRetriever$TokenRequestParams();
    Code:
       0: aload_0
       1: invokespecial #1                  // Method java/lang/Object."<init>":()V
       4: return

  public org.w3c.dom.Element getIssuer();
    Code:
       0: aload_0
       1: getfield      #2                  // Field issuer:Lorg/w3c/dom/Element;
       4: areturn

  public void setIssuer(org.w3c.dom.Element);
    Code:
       0: aload_0
       1: aload_1
       2: putfield      #2                  // Field issuer:Lorg/w3c/dom/Element;
       5: return

  public org.apache.wss4j.policy.model.Trust10 getTrust10();
    Code:
       0: aload_0
       1: getfield      #3                  // Field trust10:Lorg/apache/wss4j/policy/model/Trust10;
       4: areturn

  public void setTrust10(org.apache.wss4j.policy.model.Trust10);
    Code:
       0: aload_0
       1: aload_1
       2: putfield      #3                  // Field trust10:Lorg/apache/wss4j/policy/model/Trust10;
       5: return

  public org.apache.wss4j.policy.model.Trust13 getTrust13();
    Code:
       0: aload_0
       1: getfield      #4                  // Field trust13:Lorg/apache/wss4j/policy/model/Trust13;
       4: areturn

  public void setTrust13(org.apache.wss4j.policy.model.Trust13);
    Code:
       0: aload_0
       1: aload_1
       2: putfield      #4                  // Field trust13:Lorg/apache/wss4j/policy/model/Trust13;
       5: return

  public org.w3c.dom.Element getTokenTemplate();
    Code:
       0: aload_0
       1: getfield      #5                  // Field tokenTemplate:Lorg/w3c/dom/Element;
       4: areturn

  public void setTokenTemplate(org.w3c.dom.Element);
    Code:
       0: aload_0
       1: aload_1
       2: putfield      #5                  // Field tokenTemplate:Lorg/w3c/dom/Element;
       5: return

  public java.lang.String getWspNamespace();
    Code:
       0: aload_0
       1: getfield      #6                  // Field wspNamespace:Ljava/lang/String;
       4: areturn

  public void setWspNamespace(java.lang.String);
    Code:
       0: aload_0
       1: aload_1
       2: putfield      #6                  // Field wspNamespace:Ljava/lang/String;
       5: return

  public org.w3c.dom.Element getClaims();
    Code:
       0: aload_0
       1: getfield      #7                  // Field claims:Lorg/w3c/dom/Element;
       4: areturn

  public void setClaims(org.w3c.dom.Element);
    Code:
       0: aload_0
       1: aload_1
       2: putfield      #7                  // Field claims:Lorg/w3c/dom/Element;
       5: return
}
