Compiled from "VolatileIntHolder.java"
public class com.mchange.v2.holders.VolatileIntHolder implements com.mchange.v2.holders.ThreadSafeIntHolder,java.io.Serializable {
  volatile transient int value;

  static final long serialVersionUID;

  private static final short VERSION;

  public com.mchange.v2.holders.VolatileIntHolder();
    Code:
       0: aload_0
       1: invokespecial #1                  // Method java/lang/Object."<init>":()V
       4: return

  public int getValue();
    Code:
       0: aload_0
       1: getfield      #2                  // Field value:I
       4: ireturn

  public void setValue(int);
    Code:
       0: aload_0
       1: iload_1
       2: putfield      #2                  // Field value:I
       5: return

  private void writeObject(java.io.ObjectOutputStream) throws java.io.IOException;
    Code:
       0: aload_1
       1: iconst_1
       2: invokevirtual #4                  // Method java/io/ObjectOutputStream.writeShort:(I)V
       5: aload_1
       6: aload_0
       7: getfield      #2                  // Field value:I
      10: invokevirtual #5                  // Method java/io/ObjectOutputStream.writeInt:(I)V
      13: return

  private void readObject(java.io.ObjectInputStream) throws java.io.IOException;
    Code:
       0: aload_1
       1: invokevirtual #6                  // Method java/io/ObjectInputStream.readShort:()S
       4: istore_2
       5: iload_2
       6: lookupswitch  { // 1
                     1: 24
               default: 35
          }
      24: aload_0
      25: aload_1
      26: invokevirtual #7                  // Method java/io/ObjectInputStream.readInt:()I
      29: putfield      #2                  // Field value:I
      32: goto          45
      35: new           #8                  // class com/mchange/v2/ser/UnsupportedVersionException
      38: dup
      39: aload_0
      40: iload_2
      41: invokespecial #9                  // Method com/mchange/v2/ser/UnsupportedVersionException."<init>":(Ljava/lang/Object;I)V
      44: athrow
      45: return
}
