Compiled from "SystemDefaultRoutePlanner.java"
class org.apache.hc.client5.http.impl.routing.SystemDefaultRoutePlanner$1 {
  static final int[] $SwitchMap$java$net$Proxy$Type;

  static {};
    Code:
       0: invokestatic  #1                  // Method java/net/Proxy$Type.values:()[Ljava/net/Proxy$Type;
       3: arraylength
       4: newarray       int
       6: putstatic     #2                  // Field $SwitchMap$java$net$Proxy$Type:[I
       9: getstatic     #2                  // Field $SwitchMap$java$net$Proxy$Type:[I
      12: getstatic     #3                  // Field java/net/Proxy$Type.DIRECT:Ljava/net/Proxy$Type;
      15: invokevirtual #4                  // Method java/net/Proxy$Type.ordinal:()I
      18: iconst_1
      19: iastore
      20: goto          24
      23: astore_0
      24: getstatic     #2                  // Field $SwitchMap$java$net$Proxy$Type:[I
      27: getstatic     #6                  // Field java/net/Proxy$Type.HTTP:Ljava/net/Proxy$Type;
      30: invokevirtual #4                  // Method java/net/Proxy$Type.ordinal:()I
      33: iconst_2
      34: iastore
      35: goto          39
      38: astore_0
      39: getstatic     #2                  // Field $SwitchMap$java$net$Proxy$Type:[I
      42: getstatic     #7                  // Field java/net/Proxy$Type.SOCKS:Ljava/net/Proxy$Type;
      45: invokevirtual #4                  // Method java/net/Proxy$Type.ordinal:()I
      48: iconst_3
      49: iastore
      50: goto          54
      53: astore_0
      54: return
    Exception table:
       from    to  target type
           9    20    23   Class java/lang/NoSuchFieldError
          24    35    38   Class java/lang/NoSuchFieldError
          39    50    53   Class java/lang/NoSuchFieldError
}
