Compiled from "PartitionHandlingManagerImpl.java"
class org.infinispan.partitionhandling.impl.PartitionHandlingManagerImpl$Commit1PCTransactionInfo extends org.infinispan.partitionhandling.impl.PartitionHandlingManagerImpl$BaseTransactionInfo {
  private final java.util.List<org.infinispan.commands.write.WriteCommand> modifications;

  public org.infinispan.partitionhandling.impl.PartitionHandlingManagerImpl$Commit1PCTransactionInfo(org.infinispan.transaction.xa.GlobalTransaction, java.util.Collection<org.infinispan.remoting.transport.Address>, java.util.Collection<java.lang.Object>, java.util.List<org.infinispan.commands.write.WriteCommand>);
    Code:
       0: aload_0
       1: aload_1
       2: aload_2
       3: aload_3
       4: invokespecial #1                  // Method org/infinispan/partitionhandling/impl/PartitionHandlingManagerImpl$BaseTransactionInfo."<init>":(Lorg/infinispan/transaction/xa/GlobalTransaction;Ljava/util/Collection;Ljava/util/Collection;)V
       7: aload_0
       8: aload         4
      10: putfield      #2                  // Field modifications:Ljava/util/List;
      13: return

  public boolean isRolledBack();
    Code:
       0: iconst_0
       1: ireturn

  public org.infinispan.commands.ReplicableCommand buildCommand(org.infinispan.commands.CommandsFactory, boolean);
    Code:
       0: iload_2
       1: ifeq          14
       4: new           #3                  // class java/lang/IllegalArgumentException
       7: dup
       8: ldc           #4                  // String Cannot build a versioned one-phase-commit prepare command.
      10: invokespecial #5                  // Method java/lang/IllegalArgumentException."<init>":(Ljava/lang/String;)V
      13: athrow
      14: aload_1
      15: aload_0
      16: invokevirtual #6                  // Method getGlobalTransaction:()Lorg/infinispan/transaction/xa/GlobalTransaction;
      19: aload_0
      20: getfield      #2                  // Field modifications:Ljava/util/List;
      23: iconst_1
      24: invokeinterface #7,  4            // InterfaceMethod org/infinispan/commands/CommandsFactory.buildPrepareCommand:(Lorg/infinispan/transaction/xa/GlobalTransaction;Ljava/util/List;Z)Lorg/infinispan/commands/tx/PrepareCommand;
      29: areturn
}
