Compiled from "QueryParserServicesInitiatior.java"
class org.hibernate.ogm.service.impl.QueryParserServicesInitiatior extends org.hibernate.ogm.service.impl.OptionalServiceInitiator<org.hibernate.ogm.service.impl.QueryParserService> {
  public static final org.hibernate.service.spi.BasicServiceInitiator INSTANCE;

  org.hibernate.ogm.service.impl.QueryParserServicesInitiatior();
    Code:
       0: aload_0
       1: invokespecial #1                  // Method org/hibernate/ogm/service/impl/OptionalServiceInitiator."<init>":()V
       4: return

  public java.lang.Class<org.hibernate.ogm.service.impl.QueryParserService> getServiceInitiated();
    Code:
       0: ldc_w         #2                  // class org/hibernate/ogm/service/impl/QueryParserService
       3: areturn

  protected org.hibernate.ogm.service.impl.QueryParserService buildServiceInstance(java.util.Map, org.hibernate.service.spi.ServiceRegistryImplementor);
    Code:
       0: new           #3                  // class org/hibernate/ogm/service/impl/LuceneBasedQueryParserService
       3: dup
       4: aload_2
       5: aload_1
       6: invokespecial #4                  // Method org/hibernate/ogm/service/impl/LuceneBasedQueryParserService."<init>":(Lorg/hibernate/service/spi/ServiceRegistryImplementor;Ljava/util/Map;)V
       9: areturn

  protected org.hibernate.service.spi.BasicServiceInitiator<org.hibernate.ogm.service.impl.QueryParserService> backupInitiator();
    Code:
       0: aconst_null
       1: areturn

  protected org.hibernate.service.Service buildServiceInstance(java.util.Map, org.hibernate.service.spi.ServiceRegistryImplementor);
    Code:
       0: aload_0
       1: aload_1
       2: aload_2
       3: invokevirtual #5                  // Method buildServiceInstance:(Ljava/util/Map;Lorg/hibernate/service/spi/ServiceRegistryImplementor;)Lorg/hibernate/ogm/service/impl/QueryParserService;
       6: areturn

  static {};
    Code:
       0: new           #6                  // class org/hibernate/ogm/service/impl/QueryParserServicesInitiatior
       3: dup
       4: invokespecial #7                  // Method "<init>":()V
       7: putstatic     #8                  // Field INSTANCE:Lorg/hibernate/service/spi/BasicServiceInitiator;
      10: return
}
