Compiled from "AbstractIndicesPrivileges.java"
public class org.elasticsearch.client.security.user.privileges.AbstractIndicesPrivileges$FieldSecurity implements org.elasticsearch.common.xcontent.ToXContentObject {
  static final org.elasticsearch.common.ParseField GRANT_FIELDS;

  static final org.elasticsearch.common.ParseField EXCEPT_FIELDS;

  private static final org.elasticsearch.common.xcontent.ConstructingObjectParser<org.elasticsearch.client.security.user.privileges.AbstractIndicesPrivileges$FieldSecurity, java.lang.Void> PARSER;

  private final java.util.Set<java.lang.String> grantedFields;

  private final java.util.Set<java.lang.String> deniedFields;

  private static org.elasticsearch.client.security.user.privileges.AbstractIndicesPrivileges$FieldSecurity buildObjectFromParserArgs(java.lang.Object[]);
    Code:
       0: new           #1                  // class org/elasticsearch/client/security/user/privileges/AbstractIndicesPrivileges$FieldSecurity
       3: dup
       4: aload_0
       5: iconst_0
       6: aaload
       7: checkcast     #2                  // class java/util/Collection
      10: aload_0
      11: iconst_1
      12: aaload
      13: checkcast     #2                  // class java/util/Collection
      16: invokespecial #3                  // Method "<init>":(Ljava/util/Collection;Ljava/util/Collection;)V
      19: areturn

  static org.elasticsearch.client.security.user.privileges.AbstractIndicesPrivileges$FieldSecurity parse(org.elasticsearch.common.xcontent.XContentParser, java.lang.Void) throws java.io.IOException;
    Code:
       0: getstatic     #4                  // Field PARSER:Lorg/elasticsearch/common/xcontent/ConstructingObjectParser;
       3: aload_0
       4: aload_1
       5: invokevirtual #5                  // Method org/elasticsearch/common/xcontent/ConstructingObjectParser.parse:(Lorg/elasticsearch/common/xcontent/XContentParser;Ljava/lang/Object;)Ljava/lang/Object;
       8: checkcast     #1                  // class org/elasticsearch/client/security/user/privileges/AbstractIndicesPrivileges$FieldSecurity
      11: areturn

  org.elasticsearch.client.security.user.privileges.AbstractIndicesPrivileges$FieldSecurity(java.util.Collection<java.lang.String>, java.util.Collection<java.lang.String>);
    Code:
       0: aload_0
       1: invokespecial #6                  // Method java/lang/Object."<init>":()V
       4: aload_0
       5: aload_1
       6: ifnonnull     13
       9: aconst_null
      10: goto          24
      13: new           #7                  // class java/util/HashSet
      16: dup
      17: aload_1
      18: invokespecial #8                  // Method java/util/HashSet."<init>":(Ljava/util/Collection;)V
      21: invokestatic  #9                  // Method java/util/Collections.unmodifiableSet:(Ljava/util/Set;)Ljava/util/Set;
      24: putfield      #10                 // Field grantedFields:Ljava/util/Set;
      27: aload_0
      28: aload_2
      29: ifnonnull     36
      32: aconst_null
      33: goto          47
      36: new           #7                  // class java/util/HashSet
      39: dup
      40: aload_2
      41: invokespecial #8                  // Method java/util/HashSet."<init>":(Ljava/util/Collection;)V
      44: invokestatic  #9                  // Method java/util/Collections.unmodifiableSet:(Ljava/util/Set;)Ljava/util/Set;
      47: putfield      #11                 // Field deniedFields:Ljava/util/Set;
      50: return

  public java.util.Set<java.lang.String> getGrantedFields();
    Code:
       0: aload_0
       1: getfield      #10                 // Field grantedFields:Ljava/util/Set;
       4: areturn

  public java.util.Set<java.lang.String> getDeniedFields();
    Code:
       0: aload_0
       1: getfield      #11                 // Field deniedFields:Ljava/util/Set;
       4: areturn

  public boolean isUsingFieldLevelSecurity();
    Code:
       0: aload_0
       1: invokespecial #12                 // Method limitsGrantedFields:()Z
       4: ifne          14
       7: aload_0
       8: invokespecial #13                 // Method hasDeniedFields:()Z
      11: ifeq          18
      14: iconst_1
      15: goto          19
      18: iconst_0
      19: ireturn

  private boolean hasDeniedFields();
    Code:
       0: aload_0
       1: getfield      #11                 // Field deniedFields:Ljava/util/Set;
       4: ifnull        24
       7: iconst_0
       8: aload_0
       9: getfield      #11                 // Field deniedFields:Ljava/util/Set;
      12: invokeinterface #14,  1           // InterfaceMethod java/util/Set.isEmpty:()Z
      17: if_icmpne     24
      20: iconst_1
      21: goto          25
      24: iconst_0
      25: ireturn

  private boolean limitsGrantedFields();
    Code:
       0: aload_0
       1: getfield      #10                 // Field grantedFields:Ljava/util/Set;
       4: ifnull        45
       7: aload_0
       8: getfield      #10                 // Field grantedFields:Ljava/util/Set;
      11: invokeinterface #15,  1           // InterfaceMethod java/util/Set.size:()I
      16: iconst_1
      17: if_icmpne     47
      20: aload_0
      21: getfield      #10                 // Field grantedFields:Ljava/util/Set;
      24: invokeinterface #16,  1           // InterfaceMethod java/util/Set.iterator:()Ljava/util/Iterator;
      29: invokeinterface #17,  1           // InterfaceMethod java/util/Iterator.next:()Ljava/lang/Object;
      34: checkcast     #18                 // class java/lang/String
      37: ldc           #19                 // String *
      39: invokevirtual #20                 // Method java/lang/String.equals:(Ljava/lang/Object;)Z
      42: ifeq          47
      45: iconst_0
      46: ireturn
      47: iconst_1
      48: ireturn

  public org.elasticsearch.common.xcontent.XContentBuilder toXContent(org.elasticsearch.common.xcontent.XContentBuilder, org.elasticsearch.common.xcontent.ToXContent$Params) throws java.io.IOException;
    Code:
       0: aload_1
       1: invokevirtual #21                 // Method org/elasticsearch/common/xcontent/XContentBuilder.startObject:()Lorg/elasticsearch/common/xcontent/XContentBuilder;
       4: pop
       5: aload_0
       6: getfield      #10                 // Field grantedFields:Ljava/util/Set;
       9: ifnonnull     31
      12: aload_1
      13: getstatic     #22                 // Field GRANT_FIELDS:Lorg/elasticsearch/common/ParseField;
      16: invokevirtual #23                 // Method org/elasticsearch/common/ParseField.getPreferredName:()Ljava/lang/String;
      19: ldc           #19                 // String *
      21: invokestatic  #24                 // Method java/util/Collections.singletonList:(Ljava/lang/Object;)Ljava/util/List;
      24: invokevirtual #25                 // Method org/elasticsearch/common/xcontent/XContentBuilder.field:(Ljava/lang/String;Ljava/lang/Iterable;)Lorg/elasticsearch/common/xcontent/XContentBuilder;
      27: pop
      28: goto          46
      31: aload_1
      32: getstatic     #22                 // Field GRANT_FIELDS:Lorg/elasticsearch/common/ParseField;
      35: invokevirtual #23                 // Method org/elasticsearch/common/ParseField.getPreferredName:()Ljava/lang/String;
      38: aload_0
      39: getfield      #10                 // Field grantedFields:Ljava/util/Set;
      42: invokevirtual #25                 // Method org/elasticsearch/common/xcontent/XContentBuilder.field:(Ljava/lang/String;Ljava/lang/Iterable;)Lorg/elasticsearch/common/xcontent/XContentBuilder;
      45: pop
      46: aload_0
      47: getfield      #11                 // Field deniedFields:Ljava/util/Set;
      50: ifnull        68
      53: aload_1
      54: getstatic     #26                 // Field EXCEPT_FIELDS:Lorg/elasticsearch/common/ParseField;
      57: invokevirtual #23                 // Method org/elasticsearch/common/ParseField.getPreferredName:()Ljava/lang/String;
      60: aload_0
      61: getfield      #11                 // Field deniedFields:Ljava/util/Set;
      64: invokevirtual #25                 // Method org/elasticsearch/common/xcontent/XContentBuilder.field:(Ljava/lang/String;Ljava/lang/Iterable;)Lorg/elasticsearch/common/xcontent/XContentBuilder;
      67: pop
      68: aload_1
      69: invokevirtual #27                 // Method org/elasticsearch/common/xcontent/XContentBuilder.endObject:()Lorg/elasticsearch/common/xcontent/XContentBuilder;
      72: areturn

  public java.lang.String toString();
    Code:
       0: aload_0
       1: getstatic     #28                 // Field org/elasticsearch/common/xcontent/XContentType.JSON:Lorg/elasticsearch/common/xcontent/XContentType;
       4: iconst_1
       5: invokestatic  #29                 // Method org/elasticsearch/common/xcontent/XContentHelper.toXContent:(Lorg/elasticsearch/common/xcontent/ToXContent;Lorg/elasticsearch/common/xcontent/XContentType;Z)Lorg/elasticsearch/common/bytes/BytesReference;
       8: invokevirtual #30                 // Method org/elasticsearch/common/bytes/BytesReference.utf8ToString:()Ljava/lang/String;
      11: areturn
      12: astore_1
      13: new           #32                 // class java/io/UncheckedIOException
      16: dup
      17: ldc           #33                 // String Unexpected
      19: aload_1
      20: invokespecial #34                 // Method java/io/UncheckedIOException."<init>":(Ljava/lang/String;Ljava/io/IOException;)V
      23: athrow
    Exception table:
       from    to  target type
           0    11    12   Class java/io/IOException

  public boolean equals(java.lang.Object);
    Code:
       0: aload_0
       1: aload_1
       2: if_acmpne     7
       5: iconst_1
       6: ireturn
       7: aload_1
       8: ifnull        22
      11: aload_0
      12: invokevirtual #35                 // Method java/lang/Object.getClass:()Ljava/lang/Class;
      15: aload_1
      16: invokevirtual #35                 // Method java/lang/Object.getClass:()Ljava/lang/Class;
      19: if_acmpeq     24
      22: iconst_0
      23: ireturn
      24: aload_1
      25: checkcast     #1                  // class org/elasticsearch/client/security/user/privileges/AbstractIndicesPrivileges$FieldSecurity
      28: astore_2
      29: aload_0
      30: getfield      #10                 // Field grantedFields:Ljava/util/Set;
      33: aload_2
      34: getfield      #10                 // Field grantedFields:Ljava/util/Set;
      37: invokestatic  #36                 // Method java/util/Objects.equals:(Ljava/lang/Object;Ljava/lang/Object;)Z
      40: ifeq          61
      43: aload_0
      44: getfield      #11                 // Field deniedFields:Ljava/util/Set;
      47: aload_2
      48: getfield      #11                 // Field deniedFields:Ljava/util/Set;
      51: invokestatic  #36                 // Method java/util/Objects.equals:(Ljava/lang/Object;Ljava/lang/Object;)Z
      54: ifeq          61
      57: iconst_1
      58: goto          62
      61: iconst_0
      62: ireturn

  public int hashCode();
    Code:
       0: iconst_2
       1: anewarray     #37                 // class java/lang/Object
       4: dup
       5: iconst_0
       6: aload_0
       7: getfield      #10                 // Field grantedFields:Ljava/util/Set;
      10: aastore
      11: dup
      12: iconst_1
      13: aload_0
      14: getfield      #11                 // Field deniedFields:Ljava/util/Set;
      17: aastore
      18: invokestatic  #38                 // Method java/util/Objects.hash:([Ljava/lang/Object;)I
      21: ireturn

  static {};
    Code:
       0: new           #39                 // class org/elasticsearch/common/ParseField
       3: dup
       4: ldc           #40                 // String grant
       6: iconst_0
       7: anewarray     #18                 // class java/lang/String
      10: invokespecial #41                 // Method org/elasticsearch/common/ParseField."<init>":(Ljava/lang/String;[Ljava/lang/String;)V
      13: putstatic     #22                 // Field GRANT_FIELDS:Lorg/elasticsearch/common/ParseField;
      16: new           #39                 // class org/elasticsearch/common/ParseField
      19: dup
      20: ldc           #42                 // String except
      22: iconst_0
      23: anewarray     #18                 // class java/lang/String
      26: invokespecial #41                 // Method org/elasticsearch/common/ParseField."<init>":(Ljava/lang/String;[Ljava/lang/String;)V
      29: putstatic     #26                 // Field EXCEPT_FIELDS:Lorg/elasticsearch/common/ParseField;
      32: new           #43                 // class org/elasticsearch/common/xcontent/ConstructingObjectParser
      35: dup
      36: getstatic     #44                 // Field org/elasticsearch/client/security/user/privileges/AbstractIndicesPrivileges.FIELD_PERMISSIONS:Lorg/elasticsearch/common/ParseField;
      39: invokevirtual #23                 // Method org/elasticsearch/common/ParseField.getPreferredName:()Ljava/lang/String;
      42: iconst_1
      43: invokedynamic #45,  0             // InvokeDynamic #0:apply:()Ljava/util/function/Function;
      48: invokespecial #46                 // Method org/elasticsearch/common/xcontent/ConstructingObjectParser."<init>":(Ljava/lang/String;ZLjava/util/function/Function;)V
      51: putstatic     #4                  // Field PARSER:Lorg/elasticsearch/common/xcontent/ConstructingObjectParser;
      54: getstatic     #4                  // Field PARSER:Lorg/elasticsearch/common/xcontent/ConstructingObjectParser;
      57: invokestatic  #47                 // Method org/elasticsearch/common/xcontent/ConstructingObjectParser.optionalConstructorArg:()Ljava/util/function/BiConsumer;
      60: getstatic     #22                 // Field GRANT_FIELDS:Lorg/elasticsearch/common/ParseField;
      63: invokevirtual #48                 // Method org/elasticsearch/common/xcontent/ConstructingObjectParser.declareStringArray:(Ljava/util/function/BiConsumer;Lorg/elasticsearch/common/ParseField;)V
      66: getstatic     #4                  // Field PARSER:Lorg/elasticsearch/common/xcontent/ConstructingObjectParser;
      69: invokestatic  #47                 // Method org/elasticsearch/common/xcontent/ConstructingObjectParser.optionalConstructorArg:()Ljava/util/function/BiConsumer;
      72: getstatic     #26                 // Field EXCEPT_FIELDS:Lorg/elasticsearch/common/ParseField;
      75: invokevirtual #48                 // Method org/elasticsearch/common/xcontent/ConstructingObjectParser.declareStringArray:(Ljava/util/function/BiConsumer;Lorg/elasticsearch/common/ParseField;)V
      78: return
}
