Compiled from "ConversionSchemas.java"
class com.amazonaws.services.dynamodbv2.datamodeling.ConversionSchemas$CachingUnmarshallerSet implements com.amazonaws.services.dynamodbv2.datamodeling.ConversionSchemas$UnmarshallerSet {
  private final java.util.Map<java.lang.reflect.Method, com.amazonaws.services.dynamodbv2.datamodeling.ArgumentUnmarshaller> cache;

  private final java.util.Map<java.lang.reflect.Type, com.amazonaws.services.dynamodbv2.datamodeling.ArgumentUnmarshaller> memberCache;

  private final com.amazonaws.services.dynamodbv2.datamodeling.ConversionSchemas$UnmarshallerSet wrapped;

  public com.amazonaws.services.dynamodbv2.datamodeling.ConversionSchemas$CachingUnmarshallerSet(com.amazonaws.services.dynamodbv2.datamodeling.ConversionSchemas$UnmarshallerSet);
    Code:
       0: aload_0
       1: invokespecial #1                  // Method java/lang/Object."<init>":()V
       4: aload_0
       5: new           #2                  // class java/util/HashMap
       8: dup
       9: invokespecial #3                  // Method java/util/HashMap."<init>":()V
      12: putfield      #4                  // Field cache:Ljava/util/Map;
      15: aload_0
      16: new           #2                  // class java/util/HashMap
      19: dup
      20: invokespecial #3                  // Method java/util/HashMap."<init>":()V
      23: putfield      #5                  // Field memberCache:Ljava/util/Map;
      26: aload_0
      27: aload_1
      28: putfield      #6                  // Field wrapped:Lcom/amazonaws/services/dynamodbv2/datamodeling/ConversionSchemas$UnmarshallerSet;
      31: return

  public com.amazonaws.services.dynamodbv2.datamodeling.ArgumentUnmarshaller getUnmarshaller(java.lang.reflect.Method, java.lang.reflect.Method);
    Code:
       0: aload_0
       1: getfield      #4                  // Field cache:Ljava/util/Map;
       4: dup
       5: astore_3
       6: monitorenter
       7: aload_0
       8: getfield      #4                  // Field cache:Ljava/util/Map;
      11: aload_1
      12: invokeinterface #7,  2            // InterfaceMethod java/util/Map.get:(Ljava/lang/Object;)Ljava/lang/Object;
      17: checkcast     #8                  // class com/amazonaws/services/dynamodbv2/datamodeling/ArgumentUnmarshaller
      20: astore        4
      22: aload         4
      24: ifnull        32
      27: aload         4
      29: aload_3
      30: monitorexit
      31: areturn
      32: aload_0
      33: getfield      #6                  // Field wrapped:Lcom/amazonaws/services/dynamodbv2/datamodeling/ConversionSchemas$UnmarshallerSet;
      36: aload_1
      37: aload_2
      38: invokeinterface #9,  3            // InterfaceMethod com/amazonaws/services/dynamodbv2/datamodeling/ConversionSchemas$UnmarshallerSet.getUnmarshaller:(Ljava/lang/reflect/Method;Ljava/lang/reflect/Method;)Lcom/amazonaws/services/dynamodbv2/datamodeling/ArgumentUnmarshaller;
      43: astore        4
      45: aload_0
      46: getfield      #4                  // Field cache:Ljava/util/Map;
      49: aload_1
      50: aload         4
      52: invokeinterface #10,  3           // InterfaceMethod java/util/Map.put:(Ljava/lang/Object;Ljava/lang/Object;)Ljava/lang/Object;
      57: pop
      58: aload         4
      60: aload_3
      61: monitorexit
      62: areturn
      63: astore        5
      65: aload_3
      66: monitorexit
      67: aload         5
      69: athrow
    Exception table:
       from    to  target type
           7    31    63   any
          32    62    63   any
          63    67    63   any

  public com.amazonaws.services.dynamodbv2.datamodeling.ArgumentUnmarshaller getMemberUnmarshaller(java.lang.reflect.Type);
    Code:
       0: aload_0
       1: getfield      #5                  // Field memberCache:Ljava/util/Map;
       4: dup
       5: astore_2
       6: monitorenter
       7: aload_0
       8: getfield      #5                  // Field memberCache:Ljava/util/Map;
      11: aload_1
      12: invokeinterface #7,  2            // InterfaceMethod java/util/Map.get:(Ljava/lang/Object;)Ljava/lang/Object;
      17: checkcast     #8                  // class com/amazonaws/services/dynamodbv2/datamodeling/ArgumentUnmarshaller
      20: astore_3
      21: aload_3
      22: ifnull        29
      25: aload_3
      26: aload_2
      27: monitorexit
      28: areturn
      29: aload_0
      30: getfield      #6                  // Field wrapped:Lcom/amazonaws/services/dynamodbv2/datamodeling/ConversionSchemas$UnmarshallerSet;
      33: aload_1
      34: invokeinterface #11,  2           // InterfaceMethod com/amazonaws/services/dynamodbv2/datamodeling/ConversionSchemas$UnmarshallerSet.getMemberUnmarshaller:(Ljava/lang/reflect/Type;)Lcom/amazonaws/services/dynamodbv2/datamodeling/ArgumentUnmarshaller;
      39: astore_3
      40: aload_0
      41: getfield      #5                  // Field memberCache:Ljava/util/Map;
      44: aload_1
      45: aload_3
      46: invokeinterface #10,  3           // InterfaceMethod java/util/Map.put:(Ljava/lang/Object;Ljava/lang/Object;)Ljava/lang/Object;
      51: pop
      52: aload_3
      53: aload_2
      54: monitorexit
      55: areturn
      56: astore        4
      58: aload_2
      59: monitorexit
      60: aload         4
      62: athrow
    Exception table:
       from    to  target type
           7    28    56   any
          29    55    56   any
          56    60    56   any
}
