Compiled from "DynamoDBReflector.java"
class com.amazonaws.services.dynamodbv2.datamodeling.DynamoDBReflector {
  private final java.util.Map<java.lang.Class<?>, java.util.Collection<java.lang.reflect.Method>> getterCache;

  private final java.util.Map<java.lang.Class<?>, java.lang.reflect.Method> primaryHashKeyGetterCache;

  private final java.util.Map<java.lang.Class<?>, java.lang.reflect.Method> primaryRangeKeyGetterCache;

  private final java.util.Map<java.lang.Class<?>, java.util.List<java.lang.reflect.Method>> primaryKeyGettersCache;

  private final java.util.Map<java.lang.reflect.Method, java.lang.reflect.Method> setterCache;

  private final java.util.Map<java.lang.reflect.Method, java.lang.String> attributeNameCache;

  private final java.util.Map<java.lang.reflect.Method, java.lang.Boolean> versionAttributeGetterCache;

  private final java.util.Map<java.lang.reflect.Method, java.lang.Boolean> autoGeneratedKeyGetterCache;

  private final java.util.concurrent.locks.ReentrantReadWriteLock readWriteLockAttrName;

  private final java.util.concurrent.locks.ReentrantReadWriteLock$ReadLock readLockAttrName;

  private final java.util.concurrent.locks.ReentrantReadWriteLock$WriteLock writeLockAttrName;

  com.amazonaws.services.dynamodbv2.datamodeling.DynamoDBReflector();
    Code:
       0: aload_0
       1: invokespecial #1                  // Method java/lang/Object."<init>":()V
       4: aload_0
       5: new           #2                  // class java/util/HashMap
       8: dup
       9: invokespecial #3                  // Method java/util/HashMap."<init>":()V
      12: putfield      #4                  // Field getterCache:Ljava/util/Map;
      15: aload_0
      16: new           #2                  // class java/util/HashMap
      19: dup
      20: invokespecial #3                  // Method java/util/HashMap."<init>":()V
      23: putfield      #5                  // Field primaryHashKeyGetterCache:Ljava/util/Map;
      26: aload_0
      27: new           #2                  // class java/util/HashMap
      30: dup
      31: invokespecial #3                  // Method java/util/HashMap."<init>":()V
      34: putfield      #6                  // Field primaryRangeKeyGetterCache:Ljava/util/Map;
      37: aload_0
      38: new           #2                  // class java/util/HashMap
      41: dup
      42: invokespecial #3                  // Method java/util/HashMap."<init>":()V
      45: putfield      #7                  // Field primaryKeyGettersCache:Ljava/util/Map;
      48: aload_0
      49: new           #2                  // class java/util/HashMap
      52: dup
      53: invokespecial #3                  // Method java/util/HashMap."<init>":()V
      56: putfield      #8                  // Field setterCache:Ljava/util/Map;
      59: aload_0
      60: new           #2                  // class java/util/HashMap
      63: dup
      64: invokespecial #3                  // Method java/util/HashMap."<init>":()V
      67: putfield      #9                  // Field attributeNameCache:Ljava/util/Map;
      70: aload_0
      71: new           #2                  // class java/util/HashMap
      74: dup
      75: invokespecial #3                  // Method java/util/HashMap."<init>":()V
      78: putfield      #10                 // Field versionAttributeGetterCache:Ljava/util/Map;
      81: aload_0
      82: new           #2                  // class java/util/HashMap
      85: dup
      86: invokespecial #3                  // Method java/util/HashMap."<init>":()V
      89: putfield      #11                 // Field autoGeneratedKeyGetterCache:Ljava/util/Map;
      92: aload_0
      93: new           #12                 // class java/util/concurrent/locks/ReentrantReadWriteLock
      96: dup
      97: invokespecial #13                 // Method java/util/concurrent/locks/ReentrantReadWriteLock."<init>":()V
     100: putfield      #14                 // Field readWriteLockAttrName:Ljava/util/concurrent/locks/ReentrantReadWriteLock;
     103: aload_0
     104: aload_0
     105: getfield      #14                 // Field readWriteLockAttrName:Ljava/util/concurrent/locks/ReentrantReadWriteLock;
     108: invokevirtual #15                 // Method java/util/concurrent/locks/ReentrantReadWriteLock.readLock:()Ljava/util/concurrent/locks/ReentrantReadWriteLock$ReadLock;
     111: putfield      #16                 // Field readLockAttrName:Ljava/util/concurrent/locks/ReentrantReadWriteLock$ReadLock;
     114: aload_0
     115: aload_0
     116: getfield      #14                 // Field readWriteLockAttrName:Ljava/util/concurrent/locks/ReentrantReadWriteLock;
     119: invokevirtual #17                 // Method java/util/concurrent/locks/ReentrantReadWriteLock.writeLock:()Ljava/util/concurrent/locks/ReentrantReadWriteLock$WriteLock;
     122: putfield      #18                 // Field writeLockAttrName:Ljava/util/concurrent/locks/ReentrantReadWriteLock$WriteLock;
     125: return

  java.util.Collection<java.lang.reflect.Method> getRelevantGetters(java.lang.Class<?>);
    Code:
       0: aload_0
       1: getfield      #4                  // Field getterCache:Ljava/util/Map;
       4: dup
       5: astore_2
       6: monitorenter
       7: aload_0
       8: getfield      #4                  // Field getterCache:Ljava/util/Map;
      11: aload_1
      12: invokeinterface #19,  2           // InterfaceMethod java/util/Map.containsKey:(Ljava/lang/Object;)Z
      17: ifne          37
      20: aload_1
      21: invokestatic  #20                 // Method findRelevantGetters:(Ljava/lang/Class;)Ljava/util/List;
      24: astore_3
      25: aload_0
      26: getfield      #4                  // Field getterCache:Ljava/util/Map;
      29: aload_1
      30: aload_3
      31: invokeinterface #21,  3           // InterfaceMethod java/util/Map.put:(Ljava/lang/Object;Ljava/lang/Object;)Ljava/lang/Object;
      36: pop
      37: aload_0
      38: getfield      #4                  // Field getterCache:Ljava/util/Map;
      41: aload_1
      42: invokeinterface #22,  2           // InterfaceMethod java/util/Map.get:(Ljava/lang/Object;)Ljava/lang/Object;
      47: checkcast     #23                 // class java/util/Collection
      50: aload_2
      51: monitorexit
      52: areturn
      53: astore        4
      55: aload_2
      56: monitorexit
      57: aload         4
      59: athrow
    Exception table:
       from    to  target type
           7    52    53   any
          53    57    53   any

  static java.util.List<java.lang.reflect.Method> findRelevantGetters(java.lang.Class<?>);
    Code:
       0: new           #24                 // class java/util/LinkedList
       3: dup
       4: invokespecial #25                 // Method java/util/LinkedList."<init>":()V
       7: astore_1
       8: aload_0
       9: invokevirtual #26                 // Method java/lang/Class.getMethods:()[Ljava/lang/reflect/Method;
      12: astore_2
      13: aload_2
      14: arraylength
      15: istore_3
      16: iconst_0
      17: istore        4
      19: iload         4
      21: iload_3
      22: if_icmpge     54
      25: aload_2
      26: iload         4
      28: aaload
      29: astore        5
      31: aload         5
      33: invokestatic  #27                 // Method isRelevantGetter:(Ljava/lang/reflect/Method;)Z
      36: ifeq          48
      39: aload_1
      40: aload         5
      42: invokeinterface #28,  2           // InterfaceMethod java/util/List.add:(Ljava/lang/Object;)Z
      47: pop
      48: iinc          4, 1
      51: goto          19
      54: aload_1
      55: areturn

  private static boolean isRelevantGetter(java.lang.reflect.Method);
    Code:
       0: aload_0
       1: invokevirtual #29                 // Method java/lang/reflect/Method.getName:()Ljava/lang/String;
       4: ldc           #30                 // String get
       6: invokevirtual #31                 // Method java/lang/String.startsWith:(Ljava/lang/String;)Z
       9: ifne          24
      12: aload_0
      13: invokevirtual #29                 // Method java/lang/reflect/Method.getName:()Ljava/lang/String;
      16: ldc           #32                 // String is
      18: invokevirtual #31                 // Method java/lang/String.startsWith:(Ljava/lang/String;)Z
      21: ifeq          69
      24: aload_0
      25: invokevirtual #33                 // Method java/lang/reflect/Method.getParameterTypes:()[Ljava/lang/Class;
      28: arraylength
      29: ifne          69
      32: aload_0
      33: invokevirtual #34                 // Method java/lang/reflect/Method.isBridge:()Z
      36: ifne          69
      39: aload_0
      40: invokevirtual #35                 // Method java/lang/reflect/Method.isSynthetic:()Z
      43: ifne          69
      46: aload_0
      47: invokevirtual #36                 // Method java/lang/reflect/Method.getDeclaringClass:()Ljava/lang/Class;
      50: invokestatic  #37                 // Method isDocumentType:(Ljava/lang/Class;)Z
      53: ifeq          69
      56: aload_0
      57: ldc           #38                 // class com/amazonaws/services/dynamodbv2/datamodeling/DynamoDBIgnore
      59: invokestatic  #39                 // Method com/amazonaws/services/dynamodbv2/datamodeling/ReflectionUtils.getterOrFieldHasAnnotation:(Ljava/lang/reflect/Method;Ljava/lang/Class;)Z
      62: ifne          69
      65: iconst_1
      66: goto          70
      69: iconst_0
      70: ireturn

  private static boolean isDocumentType(java.lang.Class<?>);
    Code:
       0: aload_0
       1: ldc           #40                 // class com/amazonaws/services/dynamodbv2/datamodeling/DynamoDBTable
       3: invokevirtual #41                 // Method java/lang/Class.getAnnotation:(Ljava/lang/Class;)Ljava/lang/annotation/Annotation;
       6: ifnonnull     18
       9: aload_0
      10: ldc           #42                 // class com/amazonaws/services/dynamodbv2/datamodeling/DynamoDBDocument
      12: invokevirtual #41                 // Method java/lang/Class.getAnnotation:(Ljava/lang/Class;)Ljava/lang/annotation/Annotation;
      15: ifnull        22
      18: iconst_1
      19: goto          23
      22: iconst_0
      23: ireturn

  <T> java.lang.reflect.Method getPrimaryRangeKeyGetter(java.lang.Class<T>);
    Code:
       0: aload_0
       1: getfield      #6                  // Field primaryRangeKeyGetterCache:Ljava/util/Map;
       4: dup
       5: astore_2
       6: monitorenter
       7: aload_0
       8: getfield      #6                  // Field primaryRangeKeyGetterCache:Ljava/util/Map;
      11: aload_1
      12: invokeinterface #19,  2           // InterfaceMethod java/util/Map.containsKey:(Ljava/lang/Object;)Z
      17: ifne          96
      20: aconst_null
      21: astore_3
      22: aload_0
      23: aload_1
      24: invokevirtual #43                 // Method getRelevantGetters:(Ljava/lang/Class;)Ljava/util/Collection;
      27: invokeinterface #44,  1           // InterfaceMethod java/util/Collection.iterator:()Ljava/util/Iterator;
      32: astore        4
      34: aload         4
      36: invokeinterface #45,  1           // InterfaceMethod java/util/Iterator.hasNext:()Z
      41: ifeq          84
      44: aload         4
      46: invokeinterface #46,  1           // InterfaceMethod java/util/Iterator.next:()Ljava/lang/Object;
      51: checkcast     #47                 // class java/lang/reflect/Method
      54: astore        5
      56: aload         5
      58: invokevirtual #33                 // Method java/lang/reflect/Method.getParameterTypes:()[Ljava/lang/Class;
      61: arraylength
      62: ifne          81
      65: aload         5
      67: ldc           #48                 // class com/amazonaws/services/dynamodbv2/datamodeling/DynamoDBRangeKey
      69: invokestatic  #39                 // Method com/amazonaws/services/dynamodbv2/datamodeling/ReflectionUtils.getterOrFieldHasAnnotation:(Ljava/lang/reflect/Method;Ljava/lang/Class;)Z
      72: ifeq          81
      75: aload         5
      77: astore_3
      78: goto          84
      81: goto          34
      84: aload_0
      85: getfield      #6                  // Field primaryRangeKeyGetterCache:Ljava/util/Map;
      88: aload_1
      89: aload_3
      90: invokeinterface #21,  3           // InterfaceMethod java/util/Map.put:(Ljava/lang/Object;Ljava/lang/Object;)Ljava/lang/Object;
      95: pop
      96: aload_0
      97: getfield      #6                  // Field primaryRangeKeyGetterCache:Ljava/util/Map;
     100: aload_1
     101: invokeinterface #22,  2           // InterfaceMethod java/util/Map.get:(Ljava/lang/Object;)Ljava/lang/Object;
     106: checkcast     #47                 // class java/lang/reflect/Method
     109: aload_2
     110: monitorexit
     111: areturn
     112: astore        6
     114: aload_2
     115: monitorexit
     116: aload         6
     118: athrow
    Exception table:
       from    to  target type
           7   111   112   any
         112   116   112   any

  <T> java.util.Collection<java.lang.reflect.Method> getPrimaryKeyGetters(java.lang.Class<T>);
    Code:
       0: aload_0
       1: getfield      #7                  // Field primaryKeyGettersCache:Ljava/util/Map;
       4: dup
       5: astore_2
       6: monitorenter
       7: aload_0
       8: getfield      #7                  // Field primaryKeyGettersCache:Ljava/util/Map;
      11: aload_1
      12: invokeinterface #19,  2           // InterfaceMethod java/util/Map.containsKey:(Ljava/lang/Object;)Z
      17: ifne          106
      20: new           #24                 // class java/util/LinkedList
      23: dup
      24: invokespecial #25                 // Method java/util/LinkedList."<init>":()V
      27: astore_3
      28: aload_0
      29: aload_1
      30: invokevirtual #43                 // Method getRelevantGetters:(Ljava/lang/Class;)Ljava/util/Collection;
      33: invokeinterface #44,  1           // InterfaceMethod java/util/Collection.iterator:()Ljava/util/Iterator;
      38: astore        4
      40: aload         4
      42: invokeinterface #45,  1           // InterfaceMethod java/util/Iterator.hasNext:()Z
      47: ifeq          94
      50: aload         4
      52: invokeinterface #46,  1           // InterfaceMethod java/util/Iterator.next:()Ljava/lang/Object;
      57: checkcast     #47                 // class java/lang/reflect/Method
      60: astore        5
      62: aload         5
      64: ldc           #49                 // class com/amazonaws/services/dynamodbv2/datamodeling/DynamoDBHashKey
      66: invokestatic  #39                 // Method com/amazonaws/services/dynamodbv2/datamodeling/ReflectionUtils.getterOrFieldHasAnnotation:(Ljava/lang/reflect/Method;Ljava/lang/Class;)Z
      69: ifne          82
      72: aload         5
      74: ldc           #48                 // class com/amazonaws/services/dynamodbv2/datamodeling/DynamoDBRangeKey
      76: invokestatic  #39                 // Method com/amazonaws/services/dynamodbv2/datamodeling/ReflectionUtils.getterOrFieldHasAnnotation:(Ljava/lang/reflect/Method;Ljava/lang/Class;)Z
      79: ifeq          91
      82: aload_3
      83: aload         5
      85: invokeinterface #28,  2           // InterfaceMethod java/util/List.add:(Ljava/lang/Object;)Z
      90: pop
      91: goto          40
      94: aload_0
      95: getfield      #7                  // Field primaryKeyGettersCache:Ljava/util/Map;
      98: aload_1
      99: aload_3
     100: invokeinterface #21,  3           // InterfaceMethod java/util/Map.put:(Ljava/lang/Object;Ljava/lang/Object;)Ljava/lang/Object;
     105: pop
     106: aload_0
     107: getfield      #7                  // Field primaryKeyGettersCache:Ljava/util/Map;
     110: aload_1
     111: invokeinterface #22,  2           // InterfaceMethod java/util/Map.get:(Ljava/lang/Object;)Ljava/lang/Object;
     116: checkcast     #23                 // class java/util/Collection
     119: aload_2
     120: monitorexit
     121: areturn
     122: astore        6
     124: aload_2
     125: monitorexit
     126: aload         6
     128: athrow
    Exception table:
       from    to  target type
           7   121   122   any
         122   126   122   any

  <T> java.lang.reflect.Method getPrimaryHashKeyGetter(java.lang.Class<T>);
    Code:
       0: aload_0
       1: getfield      #5                  // Field primaryHashKeyGetterCache:Ljava/util/Map;
       4: dup
       5: astore_3
       6: monitorenter
       7: aload_0
       8: getfield      #5                  // Field primaryHashKeyGetterCache:Ljava/util/Map;
      11: aload_1
      12: invokeinterface #19,  2           // InterfaceMethod java/util/Map.containsKey:(Ljava/lang/Object;)Z
      17: ifne          92
      20: aload_0
      21: aload_1
      22: invokevirtual #43                 // Method getRelevantGetters:(Ljava/lang/Class;)Ljava/util/Collection;
      25: invokeinterface #44,  1           // InterfaceMethod java/util/Collection.iterator:()Ljava/util/Iterator;
      30: astore        4
      32: aload         4
      34: invokeinterface #45,  1           // InterfaceMethod java/util/Iterator.hasNext:()Z
      39: ifeq          92
      42: aload         4
      44: invokeinterface #46,  1           // InterfaceMethod java/util/Iterator.next:()Ljava/lang/Object;
      49: checkcast     #47                 // class java/lang/reflect/Method
      52: astore        5
      54: aload         5
      56: invokevirtual #33                 // Method java/lang/reflect/Method.getParameterTypes:()[Ljava/lang/Class;
      59: arraylength
      60: ifne          89
      63: aload         5
      65: ldc           #49                 // class com/amazonaws/services/dynamodbv2/datamodeling/DynamoDBHashKey
      67: invokestatic  #39                 // Method com/amazonaws/services/dynamodbv2/datamodeling/ReflectionUtils.getterOrFieldHasAnnotation:(Ljava/lang/reflect/Method;Ljava/lang/Class;)Z
      70: ifeq          89
      73: aload_0
      74: getfield      #5                  // Field primaryHashKeyGetterCache:Ljava/util/Map;
      77: aload_1
      78: aload         5
      80: invokeinterface #21,  3           // InterfaceMethod java/util/Map.put:(Ljava/lang/Object;Ljava/lang/Object;)Ljava/lang/Object;
      85: pop
      86: goto          92
      89: goto          32
      92: aload_0
      93: getfield      #5                  // Field primaryHashKeyGetterCache:Ljava/util/Map;
      96: aload_1
      97: invokeinterface #22,  2           // InterfaceMethod java/util/Map.get:(Ljava/lang/Object;)Ljava/lang/Object;
     102: checkcast     #47                 // class java/lang/reflect/Method
     105: astore_2
     106: aload_3
     107: monitorexit
     108: goto          118
     111: astore        6
     113: aload_3
     114: monitorexit
     115: aload         6
     117: athrow
     118: aload_2
     119: ifnonnull     150
     122: new           #50                 // class com/amazonaws/services/dynamodbv2/datamodeling/DynamoDBMappingException
     125: dup
     126: new           #51                 // class java/lang/StringBuilder
     129: dup
     130: invokespecial #52                 // Method java/lang/StringBuilder."<init>":()V
     133: ldc           #53                 // String Public, zero-parameter hash key property must be annotated with
     135: invokevirtual #54                 // Method java/lang/StringBuilder.append:(Ljava/lang/String;)Ljava/lang/StringBuilder;
     138: ldc           #49                 // class com/amazonaws/services/dynamodbv2/datamodeling/DynamoDBHashKey
     140: invokevirtual #55                 // Method java/lang/StringBuilder.append:(Ljava/lang/Object;)Ljava/lang/StringBuilder;
     143: invokevirtual #56                 // Method java/lang/StringBuilder.toString:()Ljava/lang/String;
     146: invokespecial #57                 // Method com/amazonaws/services/dynamodbv2/datamodeling/DynamoDBMappingException."<init>":(Ljava/lang/String;)V
     149: athrow
     150: aload_2
     151: areturn
    Exception table:
       from    to  target type
           7   108   111   any
         111   115   111   any

  <T> com.amazonaws.services.dynamodbv2.datamodeling.DynamoDBTable getTable(java.lang.Class<T>);
    Code:
       0: aload_1
       1: ldc           #40                 // class com/amazonaws/services/dynamodbv2/datamodeling/DynamoDBTable
       3: invokevirtual #41                 // Method java/lang/Class.getAnnotation:(Ljava/lang/Class;)Ljava/lang/annotation/Annotation;
       6: checkcast     #40                 // class com/amazonaws/services/dynamodbv2/datamodeling/DynamoDBTable
       9: astore_2
      10: aload_2
      11: ifnonnull     51
      14: new           #50                 // class com/amazonaws/services/dynamodbv2/datamodeling/DynamoDBMappingException
      17: dup
      18: new           #51                 // class java/lang/StringBuilder
      21: dup
      22: invokespecial #52                 // Method java/lang/StringBuilder."<init>":()V
      25: ldc           #58                 // String Class
      27: invokevirtual #54                 // Method java/lang/StringBuilder.append:(Ljava/lang/String;)Ljava/lang/StringBuilder;
      30: aload_1
      31: invokevirtual #55                 // Method java/lang/StringBuilder.append:(Ljava/lang/Object;)Ljava/lang/StringBuilder;
      34: ldc           #59                 // String  must be annotated with
      36: invokevirtual #54                 // Method java/lang/StringBuilder.append:(Ljava/lang/String;)Ljava/lang/StringBuilder;
      39: ldc           #40                 // class com/amazonaws/services/dynamodbv2/datamodeling/DynamoDBTable
      41: invokevirtual #55                 // Method java/lang/StringBuilder.append:(Ljava/lang/Object;)Ljava/lang/StringBuilder;
      44: invokevirtual #56                 // Method java/lang/StringBuilder.toString:()Ljava/lang/String;
      47: invokespecial #57                 // Method com/amazonaws/services/dynamodbv2/datamodeling/DynamoDBMappingException."<init>":(Ljava/lang/String;)V
      50: athrow
      51: aload_2
      52: areturn

  java.lang.String getAttributeName(java.lang.reflect.Method);
    Code:
       0: aload_0
       1: getfield      #16                 // Field readLockAttrName:Ljava/util/concurrent/locks/ReentrantReadWriteLock$ReadLock;
       4: invokevirtual #60                 // Method java/util/concurrent/locks/ReentrantReadWriteLock$ReadLock.lock:()V
       7: aload_0
       8: getfield      #9                  // Field attributeNameCache:Ljava/util/Map;
      11: aload_1
      12: invokeinterface #22,  2           // InterfaceMethod java/util/Map.get:(Ljava/lang/Object;)Ljava/lang/Object;
      17: checkcast     #61                 // class java/lang/String
      20: astore_2
      21: aload_0
      22: getfield      #16                 // Field readLockAttrName:Ljava/util/concurrent/locks/ReentrantReadWriteLock$ReadLock;
      25: invokevirtual #62                 // Method java/util/concurrent/locks/ReentrantReadWriteLock$ReadLock.unlock:()V
      28: goto          41
      31: astore_3
      32: aload_0
      33: getfield      #16                 // Field readLockAttrName:Ljava/util/concurrent/locks/ReentrantReadWriteLock$ReadLock;
      36: invokevirtual #62                 // Method java/util/concurrent/locks/ReentrantReadWriteLock$ReadLock.unlock:()V
      39: aload_3
      40: athrow
      41: aload_2
      42: ifnull        47
      45: aload_2
      46: areturn
      47: aload_1
      48: ldc           #49                 // class com/amazonaws/services/dynamodbv2/datamodeling/DynamoDBHashKey
      50: invokestatic  #63                 // Method com/amazonaws/services/dynamodbv2/datamodeling/ReflectionUtils.getAnnotationFromGetterOrField:(Ljava/lang/reflect/Method;Ljava/lang/Class;)Ljava/lang/annotation/Annotation;
      53: checkcast     #49                 // class com/amazonaws/services/dynamodbv2/datamodeling/DynamoDBHashKey
      56: astore_3
      57: aload_3
      58: ifnull        86
      61: aload_3
      62: invokeinterface #64,  1           // InterfaceMethod com/amazonaws/services/dynamodbv2/datamodeling/DynamoDBHashKey.attributeName:()Ljava/lang/String;
      67: astore_2
      68: aload_2
      69: ifnull        86
      72: aload_2
      73: invokevirtual #65                 // Method java/lang/String.length:()I
      76: ifle          86
      79: aload_0
      80: aload_1
      81: aload_2
      82: invokespecial #66                 // Method cacheAttributeName:(Ljava/lang/reflect/Method;Ljava/lang/String;)Ljava/lang/String;
      85: areturn
      86: aload_1
      87: ldc           #67                 // class com/amazonaws/services/dynamodbv2/datamodeling/DynamoDBIndexHashKey
      89: invokestatic  #63                 // Method com/amazonaws/services/dynamodbv2/datamodeling/ReflectionUtils.getAnnotationFromGetterOrField:(Ljava/lang/reflect/Method;Ljava/lang/Class;)Ljava/lang/annotation/Annotation;
      92: checkcast     #67                 // class com/amazonaws/services/dynamodbv2/datamodeling/DynamoDBIndexHashKey
      95: astore        4
      97: aload         4
      99: ifnull        128
     102: aload         4
     104: invokeinterface #68,  1           // InterfaceMethod com/amazonaws/services/dynamodbv2/datamodeling/DynamoDBIndexHashKey.attributeName:()Ljava/lang/String;
     109: astore_2
     110: aload_2
     111: ifnull        128
     114: aload_2
     115: invokevirtual #65                 // Method java/lang/String.length:()I
     118: ifle          128
     121: aload_0
     122: aload_1
     123: aload_2
     124: invokespecial #66                 // Method cacheAttributeName:(Ljava/lang/reflect/Method;Ljava/lang/String;)Ljava/lang/String;
     127: areturn
     128: aload_1
     129: ldc           #48                 // class com/amazonaws/services/dynamodbv2/datamodeling/DynamoDBRangeKey
     131: invokestatic  #63                 // Method com/amazonaws/services/dynamodbv2/datamodeling/ReflectionUtils.getAnnotationFromGetterOrField:(Ljava/lang/reflect/Method;Ljava/lang/Class;)Ljava/lang/annotation/Annotation;
     134: checkcast     #48                 // class com/amazonaws/services/dynamodbv2/datamodeling/DynamoDBRangeKey
     137: astore        5
     139: aload         5
     141: ifnull        170
     144: aload         5
     146: invokeinterface #69,  1           // InterfaceMethod com/amazonaws/services/dynamodbv2/datamodeling/DynamoDBRangeKey.attributeName:()Ljava/lang/String;
     151: astore_2
     152: aload_2
     153: ifnull        170
     156: aload_2
     157: invokevirtual #65                 // Method java/lang/String.length:()I
     160: ifle          170
     163: aload_0
     164: aload_1
     165: aload_2
     166: invokespecial #66                 // Method cacheAttributeName:(Ljava/lang/reflect/Method;Ljava/lang/String;)Ljava/lang/String;
     169: areturn
     170: aload_1
     171: ldc           #70                 // class com/amazonaws/services/dynamodbv2/datamodeling/DynamoDBIndexRangeKey
     173: invokestatic  #63                 // Method com/amazonaws/services/dynamodbv2/datamodeling/ReflectionUtils.getAnnotationFromGetterOrField:(Ljava/lang/reflect/Method;Ljava/lang/Class;)Ljava/lang/annotation/Annotation;
     176: checkcast     #70                 // class com/amazonaws/services/dynamodbv2/datamodeling/DynamoDBIndexRangeKey
     179: astore        6
     181: aload         6
     183: ifnull        212
     186: aload         6
     188: invokeinterface #71,  1           // InterfaceMethod com/amazonaws/services/dynamodbv2/datamodeling/DynamoDBIndexRangeKey.attributeName:()Ljava/lang/String;
     193: astore_2
     194: aload_2
     195: ifnull        212
     198: aload_2
     199: invokevirtual #65                 // Method java/lang/String.length:()I
     202: ifle          212
     205: aload_0
     206: aload_1
     207: aload_2
     208: invokespecial #66                 // Method cacheAttributeName:(Ljava/lang/reflect/Method;Ljava/lang/String;)Ljava/lang/String;
     211: areturn
     212: aload_1
     213: ldc           #72                 // class com/amazonaws/services/dynamodbv2/datamodeling/DynamoDBAttribute
     215: invokestatic  #63                 // Method com/amazonaws/services/dynamodbv2/datamodeling/ReflectionUtils.getAnnotationFromGetterOrField:(Ljava/lang/reflect/Method;Ljava/lang/Class;)Ljava/lang/annotation/Annotation;
     218: checkcast     #72                 // class com/amazonaws/services/dynamodbv2/datamodeling/DynamoDBAttribute
     221: astore        7
     223: aload         7
     225: ifnull        254
     228: aload         7
     230: invokeinterface #73,  1           // InterfaceMethod com/amazonaws/services/dynamodbv2/datamodeling/DynamoDBAttribute.attributeName:()Ljava/lang/String;
     235: astore_2
     236: aload_2
     237: ifnull        254
     240: aload_2
     241: invokevirtual #65                 // Method java/lang/String.length:()I
     244: ifle          254
     247: aload_0
     248: aload_1
     249: aload_2
     250: invokespecial #66                 // Method cacheAttributeName:(Ljava/lang/reflect/Method;Ljava/lang/String;)Ljava/lang/String;
     253: areturn
     254: aload_1
     255: ldc           #74                 // class com/amazonaws/services/dynamodbv2/datamodeling/DynamoDBVersionAttribute
     257: invokestatic  #63                 // Method com/amazonaws/services/dynamodbv2/datamodeling/ReflectionUtils.getAnnotationFromGetterOrField:(Ljava/lang/reflect/Method;Ljava/lang/Class;)Ljava/lang/annotation/Annotation;
     260: checkcast     #74                 // class com/amazonaws/services/dynamodbv2/datamodeling/DynamoDBVersionAttribute
     263: astore        8
     265: aload         8
     267: ifnull        296
     270: aload         8
     272: invokeinterface #75,  1           // InterfaceMethod com/amazonaws/services/dynamodbv2/datamodeling/DynamoDBVersionAttribute.attributeName:()Ljava/lang/String;
     277: astore_2
     278: aload_2
     279: ifnull        296
     282: aload_2
     283: invokevirtual #65                 // Method java/lang/String.length:()I
     286: ifle          296
     289: aload_0
     290: aload_1
     291: aload_2
     292: invokespecial #66                 // Method cacheAttributeName:(Ljava/lang/reflect/Method;Ljava/lang/String;)Ljava/lang/String;
     295: areturn
     296: aload_1
     297: iconst_1
     298: invokestatic  #76                 // Method com/amazonaws/services/dynamodbv2/datamodeling/ReflectionUtils.getFieldNameByGetter:(Ljava/lang/reflect/Method;Z)Ljava/lang/String;
     301: astore_2
     302: aload_0
     303: aload_1
     304: aload_2
     305: invokespecial #66                 // Method cacheAttributeName:(Ljava/lang/reflect/Method;Ljava/lang/String;)Ljava/lang/String;
     308: areturn
    Exception table:
       from    to  target type
           7    21    31   any

  private java.lang.String cacheAttributeName(java.lang.reflect.Method, java.lang.String);
    Code:
       0: aload_0
       1: getfield      #18                 // Field writeLockAttrName:Ljava/util/concurrent/locks/ReentrantReadWriteLock$WriteLock;
       4: invokevirtual #77                 // Method java/util/concurrent/locks/ReentrantReadWriteLock$WriteLock.lock:()V
       7: aload_0
       8: getfield      #9                  // Field attributeNameCache:Ljava/util/Map;
      11: aload_1
      12: aload_2
      13: invokeinterface #21,  3           // InterfaceMethod java/util/Map.put:(Ljava/lang/Object;Ljava/lang/Object;)Ljava/lang/Object;
      18: pop
      19: aload_0
      20: getfield      #18                 // Field writeLockAttrName:Ljava/util/concurrent/locks/ReentrantReadWriteLock$WriteLock;
      23: invokevirtual #78                 // Method java/util/concurrent/locks/ReentrantReadWriteLock$WriteLock.unlock:()V
      26: goto          39
      29: astore_3
      30: aload_0
      31: getfield      #18                 // Field writeLockAttrName:Ljava/util/concurrent/locks/ReentrantReadWriteLock$WriteLock;
      34: invokevirtual #78                 // Method java/util/concurrent/locks/ReentrantReadWriteLock$WriteLock.unlock:()V
      37: aload_3
      38: athrow
      39: aload_2
      40: areturn
    Exception table:
       from    to  target type
           7    19    29   any

  java.lang.reflect.Method getSetter(java.lang.reflect.Method);
    Code:
       0: aload_0
       1: getfield      #8                  // Field setterCache:Ljava/util/Map;
       4: dup
       5: astore_2
       6: monitorenter
       7: aload_0
       8: getfield      #8                  // Field setterCache:Ljava/util/Map;
      11: aload_1
      12: invokeinterface #19,  2           // InterfaceMethod java/util/Map.containsKey:(Ljava/lang/Object;)Z
      17: ifne          176
      20: aload_1
      21: iconst_0
      22: invokestatic  #76                 // Method com/amazonaws/services/dynamodbv2/datamodeling/ReflectionUtils.getFieldNameByGetter:(Ljava/lang/reflect/Method;Z)Ljava/lang/String;
      25: astore_3
      26: new           #51                 // class java/lang/StringBuilder
      29: dup
      30: invokespecial #52                 // Method java/lang/StringBuilder."<init>":()V
      33: ldc           #79                 // String set
      35: invokevirtual #54                 // Method java/lang/StringBuilder.append:(Ljava/lang/String;)Ljava/lang/StringBuilder;
      38: aload_3
      39: invokevirtual #54                 // Method java/lang/StringBuilder.append:(Ljava/lang/String;)Ljava/lang/StringBuilder;
      42: invokevirtual #56                 // Method java/lang/StringBuilder.toString:()Ljava/lang/String;
      45: astore        4
      47: aconst_null
      48: astore        5
      50: aload_1
      51: invokevirtual #36                 // Method java/lang/reflect/Method.getDeclaringClass:()Ljava/lang/Class;
      54: aload         4
      56: iconst_1
      57: anewarray     #80                 // class java/lang/Class
      60: dup
      61: iconst_0
      62: aload_1
      63: invokevirtual #81                 // Method java/lang/reflect/Method.getReturnType:()Ljava/lang/Class;
      66: aastore
      67: invokevirtual #82                 // Method java/lang/Class.getMethod:(Ljava/lang/String;[Ljava/lang/Class;)Ljava/lang/reflect/Method;
      70: astore        5
      72: goto          163
      75: astore        6
      77: new           #50                 // class com/amazonaws/services/dynamodbv2/datamodeling/DynamoDBMappingException
      80: dup
      81: new           #51                 // class java/lang/StringBuilder
      84: dup
      85: invokespecial #52                 // Method java/lang/StringBuilder."<init>":()V
      88: ldc           #84                 // String Expected a public, one-argument method called
      90: invokevirtual #54                 // Method java/lang/StringBuilder.append:(Ljava/lang/String;)Ljava/lang/StringBuilder;
      93: aload         4
      95: invokevirtual #54                 // Method java/lang/StringBuilder.append:(Ljava/lang/String;)Ljava/lang/StringBuilder;
      98: ldc           #85                 // String  on
     100: invokevirtual #54                 // Method java/lang/StringBuilder.append:(Ljava/lang/String;)Ljava/lang/StringBuilder;
     103: aload_1
     104: invokevirtual #36                 // Method java/lang/reflect/Method.getDeclaringClass:()Ljava/lang/Class;
     107: invokevirtual #55                 // Method java/lang/StringBuilder.append:(Ljava/lang/Object;)Ljava/lang/StringBuilder;
     110: invokevirtual #56                 // Method java/lang/StringBuilder.toString:()Ljava/lang/String;
     113: aload         6
     115: invokespecial #86                 // Method com/amazonaws/services/dynamodbv2/datamodeling/DynamoDBMappingException."<init>":(Ljava/lang/String;Ljava/lang/Throwable;)V
     118: athrow
     119: astore        6
     121: new           #50                 // class com/amazonaws/services/dynamodbv2/datamodeling/DynamoDBMappingException
     124: dup
     125: new           #51                 // class java/lang/StringBuilder
     128: dup
     129: invokespecial #52                 // Method java/lang/StringBuilder."<init>":()V
     132: ldc           #88                 // String No access to public, one-argument method called
     134: invokevirtual #54                 // Method java/lang/StringBuilder.append:(Ljava/lang/String;)Ljava/lang/StringBuilder;
     137: aload         4
     139: invokevirtual #54                 // Method java/lang/StringBuilder.append:(Ljava/lang/String;)Ljava/lang/StringBuilder;
     142: ldc           #85                 // String  on
     144: invokevirtual #54                 // Method java/lang/StringBuilder.append:(Ljava/lang/String;)Ljava/lang/StringBuilder;
     147: aload_1
     148: invokevirtual #36                 // Method java/lang/reflect/Method.getDeclaringClass:()Ljava/lang/Class;
     151: invokevirtual #55                 // Method java/lang/StringBuilder.append:(Ljava/lang/Object;)Ljava/lang/StringBuilder;
     154: invokevirtual #56                 // Method java/lang/StringBuilder.toString:()Ljava/lang/String;
     157: aload         6
     159: invokespecial #86                 // Method com/amazonaws/services/dynamodbv2/datamodeling/DynamoDBMappingException."<init>":(Ljava/lang/String;Ljava/lang/Throwable;)V
     162: athrow
     163: aload_0
     164: getfield      #8                  // Field setterCache:Ljava/util/Map;
     167: aload_1
     168: aload         5
     170: invokeinterface #21,  3           // InterfaceMethod java/util/Map.put:(Ljava/lang/Object;Ljava/lang/Object;)Ljava/lang/Object;
     175: pop
     176: aload_0
     177: getfield      #8                  // Field setterCache:Ljava/util/Map;
     180: aload_1
     181: invokeinterface #22,  2           // InterfaceMethod java/util/Map.get:(Ljava/lang/Object;)Ljava/lang/Object;
     186: checkcast     #47                 // class java/lang/reflect/Method
     189: aload_2
     190: monitorexit
     191: areturn
     192: astore        7
     194: aload_2
     195: monitorexit
     196: aload         7
     198: athrow
    Exception table:
       from    to  target type
          50    72    75   Class java/lang/NoSuchMethodException
          50    72   119   Class java/lang/SecurityException
           7   191   192   any
         192   196   192   any

  boolean isVersionAttributeGetter(java.lang.reflect.Method);
    Code:
       0: aload_0
       1: getfield      #10                 // Field versionAttributeGetterCache:Ljava/util/Map;
       4: dup
       5: astore_2
       6: monitorenter
       7: aload_0
       8: getfield      #10                 // Field versionAttributeGetterCache:Ljava/util/Map;
      11: aload_1
      12: invokeinterface #19,  2           // InterfaceMethod java/util/Map.containsKey:(Ljava/lang/Object;)Z
      17: ifne          68
      20: aload_0
      21: getfield      #10                 // Field versionAttributeGetterCache:Ljava/util/Map;
      24: aload_1
      25: aload_1
      26: invokevirtual #29                 // Method java/lang/reflect/Method.getName:()Ljava/lang/String;
      29: ldc           #30                 // String get
      31: invokevirtual #31                 // Method java/lang/String.startsWith:(Ljava/lang/String;)Z
      34: ifeq          58
      37: aload_1
      38: invokevirtual #33                 // Method java/lang/reflect/Method.getParameterTypes:()[Ljava/lang/Class;
      41: arraylength
      42: ifne          58
      45: aload_1
      46: ldc           #74                 // class com/amazonaws/services/dynamodbv2/datamodeling/DynamoDBVersionAttribute
      48: invokestatic  #39                 // Method com/amazonaws/services/dynamodbv2/datamodeling/ReflectionUtils.getterOrFieldHasAnnotation:(Ljava/lang/reflect/Method;Ljava/lang/Class;)Z
      51: ifeq          58
      54: iconst_1
      55: goto          59
      58: iconst_0
      59: invokestatic  #89                 // Method java/lang/Boolean.valueOf:(Z)Ljava/lang/Boolean;
      62: invokeinterface #21,  3           // InterfaceMethod java/util/Map.put:(Ljava/lang/Object;Ljava/lang/Object;)Ljava/lang/Object;
      67: pop
      68: aload_0
      69: getfield      #10                 // Field versionAttributeGetterCache:Ljava/util/Map;
      72: aload_1
      73: invokeinterface #22,  2           // InterfaceMethod java/util/Map.get:(Ljava/lang/Object;)Ljava/lang/Object;
      78: checkcast     #90                 // class java/lang/Boolean
      81: invokevirtual #91                 // Method java/lang/Boolean.booleanValue:()Z
      84: aload_2
      85: monitorexit
      86: ireturn
      87: astore_3
      88: aload_2
      89: monitorexit
      90: aload_3
      91: athrow
    Exception table:
       from    to  target type
           7    86    87   any
          87    90    87   any

  boolean isAssignableKey(java.lang.reflect.Method);
    Code:
       0: aload_0
       1: getfield      #11                 // Field autoGeneratedKeyGetterCache:Ljava/util/Map;
       4: dup
       5: astore_2
       6: monitorenter
       7: aload_0
       8: getfield      #11                 // Field autoGeneratedKeyGetterCache:Ljava/util/Map;
      11: aload_1
      12: invokeinterface #19,  2           // InterfaceMethod java/util/Map.containsKey:(Ljava/lang/Object;)Z
      17: ifne          84
      20: aload_0
      21: getfield      #11                 // Field autoGeneratedKeyGetterCache:Ljava/util/Map;
      24: aload_1
      25: aload_1
      26: ldc           #92                 // class com/amazonaws/services/dynamodbv2/datamodeling/DynamoDBAutoGeneratedKey
      28: invokestatic  #39                 // Method com/amazonaws/services/dynamodbv2/datamodeling/ReflectionUtils.getterOrFieldHasAnnotation:(Ljava/lang/reflect/Method;Ljava/lang/Class;)Z
      31: ifeq          74
      34: aload_1
      35: ldc           #49                 // class com/amazonaws/services/dynamodbv2/datamodeling/DynamoDBHashKey
      37: invokestatic  #39                 // Method com/amazonaws/services/dynamodbv2/datamodeling/ReflectionUtils.getterOrFieldHasAnnotation:(Ljava/lang/reflect/Method;Ljava/lang/Class;)Z
      40: ifne          70
      43: aload_1
      44: ldc           #48                 // class com/amazonaws/services/dynamodbv2/datamodeling/DynamoDBRangeKey
      46: invokestatic  #39                 // Method com/amazonaws/services/dynamodbv2/datamodeling/ReflectionUtils.getterOrFieldHasAnnotation:(Ljava/lang/reflect/Method;Ljava/lang/Class;)Z
      49: ifne          70
      52: aload_1
      53: ldc           #67                 // class com/amazonaws/services/dynamodbv2/datamodeling/DynamoDBIndexHashKey
      55: invokestatic  #39                 // Method com/amazonaws/services/dynamodbv2/datamodeling/ReflectionUtils.getterOrFieldHasAnnotation:(Ljava/lang/reflect/Method;Ljava/lang/Class;)Z
      58: ifne          70
      61: aload_1
      62: ldc           #70                 // class com/amazonaws/services/dynamodbv2/datamodeling/DynamoDBIndexRangeKey
      64: invokestatic  #39                 // Method com/amazonaws/services/dynamodbv2/datamodeling/ReflectionUtils.getterOrFieldHasAnnotation:(Ljava/lang/reflect/Method;Ljava/lang/Class;)Z
      67: ifeq          74
      70: iconst_1
      71: goto          75
      74: iconst_0
      75: invokestatic  #89                 // Method java/lang/Boolean.valueOf:(Z)Ljava/lang/Boolean;
      78: invokeinterface #21,  3           // InterfaceMethod java/util/Map.put:(Ljava/lang/Object;Ljava/lang/Object;)Ljava/lang/Object;
      83: pop
      84: aload_0
      85: getfield      #11                 // Field autoGeneratedKeyGetterCache:Ljava/util/Map;
      88: aload_1
      89: invokeinterface #22,  2           // InterfaceMethod java/util/Map.get:(Ljava/lang/Object;)Ljava/lang/Object;
      94: checkcast     #90                 // class java/lang/Boolean
      97: invokevirtual #91                 // Method java/lang/Boolean.booleanValue:()Z
     100: aload_2
     101: monitorexit
     102: ireturn
     103: astore_3
     104: aload_2
     105: monitorexit
     106: aload_3
     107: athrow
    Exception table:
       from    to  target type
           7   102   103   any
         103   106   103   any

  java.lang.String getPrimaryHashKeyName(java.lang.Class<?>);
    Code:
       0: aload_0
       1: aload_0
       2: aload_1
       3: invokevirtual #93                 // Method getPrimaryHashKeyGetter:(Ljava/lang/Class;)Ljava/lang/reflect/Method;
       6: invokevirtual #94                 // Method getAttributeName:(Ljava/lang/reflect/Method;)Ljava/lang/String;
       9: areturn

  java.lang.String getPrimaryRangeKeyName(java.lang.Class<?>);
    Code:
       0: aload_0
       1: aload_1
       2: invokevirtual #93                 // Method getPrimaryHashKeyGetter:(Ljava/lang/Class;)Ljava/lang/reflect/Method;
       5: astore_2
       6: aload_2
       7: ifnonnull     14
      10: aconst_null
      11: goto          23
      14: aload_0
      15: aload_0
      16: aload_1
      17: invokevirtual #95                 // Method getPrimaryRangeKeyGetter:(Ljava/lang/Class;)Ljava/lang/reflect/Method;
      20: invokevirtual #94                 // Method getAttributeName:(Ljava/lang/reflect/Method;)Ljava/lang/String;
      23: areturn

  boolean hasPrimaryRangeKey(java.lang.Class<?>);
    Code:
       0: aload_0
       1: aload_1
       2: invokevirtual #95                 // Method getPrimaryRangeKeyGetter:(Ljava/lang/Class;)Ljava/lang/reflect/Method;
       5: ifnull        12
       8: iconst_1
       9: goto          13
      12: iconst_0
      13: ireturn
}
