Compiled from "DynamoDBMapperConfig.java"
public final class com.amazonaws.services.dynamodbv2.datamodeling.DynamoDBMapperConfig$TableNameOverride {
  private final java.lang.String tableNameOverride;

  private final java.lang.String tableNamePrefix;

  public static com.amazonaws.services.dynamodbv2.datamodeling.DynamoDBMapperConfig$TableNameOverride withTableNamePrefix(java.lang.String);
    Code:
       0: new           #1                  // class com/amazonaws/services/dynamodbv2/datamodeling/DynamoDBMapperConfig$TableNameOverride
       3: dup
       4: aconst_null
       5: aload_0
       6: invokespecial #2                  // Method "<init>":(Ljava/lang/String;Ljava/lang/String;)V
       9: areturn

  public static com.amazonaws.services.dynamodbv2.datamodeling.DynamoDBMapperConfig$TableNameOverride withTableNameReplacement(java.lang.String);
    Code:
       0: new           #1                  // class com/amazonaws/services/dynamodbv2/datamodeling/DynamoDBMapperConfig$TableNameOverride
       3: dup
       4: aload_0
       5: aconst_null
       6: invokespecial #2                  // Method "<init>":(Ljava/lang/String;Ljava/lang/String;)V
       9: areturn

  private com.amazonaws.services.dynamodbv2.datamodeling.DynamoDBMapperConfig$TableNameOverride(java.lang.String, java.lang.String);
    Code:
       0: aload_0
       1: invokespecial #3                  // Method java/lang/Object."<init>":()V
       4: aload_0
       5: aload_1
       6: putfield      #4                  // Field tableNameOverride:Ljava/lang/String;
       9: aload_0
      10: aload_2
      11: putfield      #5                  // Field tableNamePrefix:Ljava/lang/String;
      14: return

  public com.amazonaws.services.dynamodbv2.datamodeling.DynamoDBMapperConfig$TableNameOverride(java.lang.String);
    Code:
       0: aload_0
       1: aload_1
       2: aconst_null
       3: invokespecial #2                  // Method "<init>":(Ljava/lang/String;Ljava/lang/String;)V
       6: return

  public java.lang.String getTableName();
    Code:
       0: aload_0
       1: getfield      #4                  // Field tableNameOverride:Ljava/lang/String;
       4: areturn

  public java.lang.String getTableNamePrefix();
    Code:
       0: aload_0
       1: getfield      #5                  // Field tableNamePrefix:Ljava/lang/String;
       4: areturn
}
