Compiled from "S3Link.java"
public class com.amazonaws.services.dynamodbv2.datamodeling.S3Link {
  private final com.amazonaws.services.dynamodbv2.datamodeling.S3ClientCache s3cc;

  private final com.amazonaws.services.dynamodbv2.datamodeling.S3Link$ID id;

  com.amazonaws.services.dynamodbv2.datamodeling.S3Link(com.amazonaws.services.dynamodbv2.datamodeling.S3ClientCache, java.lang.String, java.lang.String);
    Code:
       0: aload_0
       1: aload_1
       2: new           #1                  // class com/amazonaws/services/dynamodbv2/datamodeling/S3Link$ID
       5: dup
       6: aload_2
       7: aload_3
       8: invokespecial #2                  // Method com/amazonaws/services/dynamodbv2/datamodeling/S3Link$ID."<init>":(Ljava/lang/String;Ljava/lang/String;)V
      11: invokespecial #3                  // Method "<init>":(Lcom/amazonaws/services/dynamodbv2/datamodeling/S3ClientCache;Lcom/amazonaws/services/dynamodbv2/datamodeling/S3Link$ID;)V
      14: return

  com.amazonaws.services.dynamodbv2.datamodeling.S3Link(com.amazonaws.services.dynamodbv2.datamodeling.S3ClientCache, com.amazonaws.services.s3.model.Region, java.lang.String, java.lang.String);
    Code:
       0: aload_0
       1: aload_1
       2: new           #1                  // class com/amazonaws/services/dynamodbv2/datamodeling/S3Link$ID
       5: dup
       6: aload_2
       7: aload_3
       8: aload         4
      10: invokespecial #4                  // Method com/amazonaws/services/dynamodbv2/datamodeling/S3Link$ID."<init>":(Lcom/amazonaws/services/s3/model/Region;Ljava/lang/String;Ljava/lang/String;)V
      13: invokespecial #3                  // Method "<init>":(Lcom/amazonaws/services/dynamodbv2/datamodeling/S3ClientCache;Lcom/amazonaws/services/dynamodbv2/datamodeling/S3Link$ID;)V
      16: return

  private com.amazonaws.services.dynamodbv2.datamodeling.S3Link(com.amazonaws.services.dynamodbv2.datamodeling.S3ClientCache, com.amazonaws.services.dynamodbv2.datamodeling.S3Link$ID);
    Code:
       0: aload_0
       1: invokespecial #5                  // Method java/lang/Object."<init>":()V
       4: aload_0
       5: aload_1
       6: putfield      #6                  // Field s3cc:Lcom/amazonaws/services/dynamodbv2/datamodeling/S3ClientCache;
       9: aload_0
      10: aload_2
      11: putfield      #7                  // Field id:Lcom/amazonaws/services/dynamodbv2/datamodeling/S3Link$ID;
      14: aload_1
      15: ifnonnull     28
      18: new           #8                  // class java/lang/IllegalArgumentException
      21: dup
      22: ldc           #9                  // String S3ClientCache must be configured for use with S3Link
      24: invokespecial #10                 // Method java/lang/IllegalArgumentException."<init>":(Ljava/lang/String;)V
      27: athrow
      28: aload_2
      29: ifnull        46
      32: aload_2
      33: invokevirtual #11                 // Method com/amazonaws/services/dynamodbv2/datamodeling/S3Link$ID.getBucket:()Ljava/lang/String;
      36: ifnull        46
      39: aload_2
      40: invokevirtual #12                 // Method com/amazonaws/services/dynamodbv2/datamodeling/S3Link$ID.getKey:()Ljava/lang/String;
      43: ifnonnull     56
      46: new           #8                  // class java/lang/IllegalArgumentException
      49: dup
      50: ldc           #13                 // String Bucket and key must be specified for S3Link
      52: invokespecial #10                 // Method java/lang/IllegalArgumentException."<init>":(Ljava/lang/String;)V
      55: athrow
      56: return

  public java.lang.String getKey();
    Code:
       0: aload_0
       1: getfield      #7                  // Field id:Lcom/amazonaws/services/dynamodbv2/datamodeling/S3Link$ID;
       4: invokevirtual #12                 // Method com/amazonaws/services/dynamodbv2/datamodeling/S3Link$ID.getKey:()Ljava/lang/String;
       7: areturn

  public java.lang.String getBucketName();
    Code:
       0: aload_0
       1: getfield      #7                  // Field id:Lcom/amazonaws/services/dynamodbv2/datamodeling/S3Link$ID;
       4: invokevirtual #11                 // Method com/amazonaws/services/dynamodbv2/datamodeling/S3Link$ID.getBucket:()Ljava/lang/String;
       7: areturn

  public com.amazonaws.services.s3.model.Region getS3Region();
    Code:
       0: aload_0
       1: getfield      #7                  // Field id:Lcom/amazonaws/services/dynamodbv2/datamodeling/S3Link$ID;
       4: invokevirtual #14                 // Method com/amazonaws/services/dynamodbv2/datamodeling/S3Link$ID.getRegionId:()Ljava/lang/String;
       7: invokestatic  #15                 // Method com/amazonaws/services/s3/model/Region.fromValue:(Ljava/lang/String;)Lcom/amazonaws/services/s3/model/Region;
      10: areturn

  public java.lang.String toJson();
    Code:
       0: aload_0
       1: getfield      #7                  // Field id:Lcom/amazonaws/services/dynamodbv2/datamodeling/S3Link$ID;
       4: invokevirtual #16                 // Method com/amazonaws/services/dynamodbv2/datamodeling/S3Link$ID.toJson:()Ljava/lang/String;
       7: areturn

  public static com.amazonaws.services.dynamodbv2.datamodeling.S3Link fromJson(com.amazonaws.services.dynamodbv2.datamodeling.S3ClientCache, java.lang.String);
    Code:
       0: aload_1
       1: ldc           #1                  // class com/amazonaws/services/dynamodbv2/datamodeling/S3Link$ID
       3: invokestatic  #17                 // Method com/amazonaws/util/json/Jackson.fromJsonString:(Ljava/lang/String;Ljava/lang/Class;)Ljava/lang/Object;
       6: checkcast     #1                  // class com/amazonaws/services/dynamodbv2/datamodeling/S3Link$ID
       9: astore_2
      10: new           #18                 // class com/amazonaws/services/dynamodbv2/datamodeling/S3Link
      13: dup
      14: aload_0
      15: aload_2
      16: invokespecial #3                  // Method "<init>":(Lcom/amazonaws/services/dynamodbv2/datamodeling/S3ClientCache;Lcom/amazonaws/services/dynamodbv2/datamodeling/S3Link$ID;)V
      19: areturn

  public com.amazonaws.services.s3.AmazonS3 getAmazonS3Client();
    Code:
       0: aload_0
       1: getfield      #6                  // Field s3cc:Lcom/amazonaws/services/dynamodbv2/datamodeling/S3ClientCache;
       4: aload_0
       5: invokevirtual #19                 // Method getS3Region:()Lcom/amazonaws/services/s3/model/Region;
       8: invokevirtual #20                 // Method com/amazonaws/services/dynamodbv2/datamodeling/S3ClientCache.getClient:(Lcom/amazonaws/services/s3/model/Region;)Lcom/amazonaws/services/s3/AmazonS3;
      11: areturn

  public com.amazonaws.services.s3.transfer.TransferManager getTransferManager();
    Code:
       0: aload_0
       1: getfield      #6                  // Field s3cc:Lcom/amazonaws/services/dynamodbv2/datamodeling/S3ClientCache;
       4: aload_0
       5: invokevirtual #19                 // Method getS3Region:()Lcom/amazonaws/services/s3/model/Region;
       8: invokevirtual #21                 // Method com/amazonaws/services/dynamodbv2/datamodeling/S3ClientCache.getTransferManager:(Lcom/amazonaws/services/s3/model/Region;)Lcom/amazonaws/services/s3/transfer/TransferManager;
      11: areturn

  public com.amazonaws.services.s3.model.PutObjectResult uploadFrom(java.io.File);
    Code:
       0: aload_0
       1: aload_1
       2: aconst_null
       3: invokespecial #22                 // Method uploadFrom0:(Ljava/io/File;Lcom/amazonaws/metrics/RequestMetricCollector;)Lcom/amazonaws/services/s3/model/PutObjectResult;
       6: areturn

  public com.amazonaws.services.s3.model.PutObjectResult uploadFrom(java.io.File, com.amazonaws.metrics.RequestMetricCollector);
    Code:
       0: aload_0
       1: aload_1
       2: aload_2
       3: invokespecial #22                 // Method uploadFrom0:(Ljava/io/File;Lcom/amazonaws/metrics/RequestMetricCollector;)Lcom/amazonaws/services/s3/model/PutObjectResult;
       6: areturn

  private com.amazonaws.services.s3.model.PutObjectResult uploadFrom0(java.io.File, com.amazonaws.metrics.RequestMetricCollector);
    Code:
       0: new           #23                 // class com/amazonaws/services/s3/model/PutObjectRequest
       3: dup
       4: aload_0
       5: invokevirtual #24                 // Method getBucketName:()Ljava/lang/String;
       8: aload_0
       9: invokevirtual #25                 // Method getKey:()Ljava/lang/String;
      12: aload_1
      13: invokespecial #26                 // Method com/amazonaws/services/s3/model/PutObjectRequest."<init>":(Ljava/lang/String;Ljava/lang/String;Ljava/io/File;)V
      16: aload_2
      17: invokevirtual #27                 // Method com/amazonaws/services/s3/model/PutObjectRequest.withRequestMetricCollector:(Lcom/amazonaws/metrics/RequestMetricCollector;)Lcom/amazonaws/AmazonWebServiceRequest;
      20: checkcast     #23                 // class com/amazonaws/services/s3/model/PutObjectRequest
      23: astore_3
      24: aload_0
      25: invokevirtual #28                 // Method getAmazonS3Client:()Lcom/amazonaws/services/s3/AmazonS3;
      28: aload_3
      29: invokeinterface #29,  2           // InterfaceMethod com/amazonaws/services/s3/AmazonS3.putObject:(Lcom/amazonaws/services/s3/model/PutObjectRequest;)Lcom/amazonaws/services/s3/model/PutObjectResult;
      34: areturn

  public com.amazonaws.services.s3.model.PutObjectResult uploadFrom(byte[]);
    Code:
       0: aload_0
       1: aload_1
       2: aconst_null
       3: invokespecial #30                 // Method uploadFrom0:([BLcom/amazonaws/metrics/RequestMetricCollector;)Lcom/amazonaws/services/s3/model/PutObjectResult;
       6: areturn

  public com.amazonaws.services.s3.model.PutObjectResult uploadFrom(byte[], com.amazonaws.metrics.RequestMetricCollector);
    Code:
       0: aload_0
       1: aload_1
       2: aload_2
       3: invokespecial #30                 // Method uploadFrom0:([BLcom/amazonaws/metrics/RequestMetricCollector;)Lcom/amazonaws/services/s3/model/PutObjectResult;
       6: areturn

  private com.amazonaws.services.s3.model.PutObjectResult uploadFrom0(byte[], com.amazonaws.metrics.RequestMetricCollector);
    Code:
       0: new           #31                 // class com/amazonaws/services/s3/model/ObjectMetadata
       3: dup
       4: invokespecial #32                 // Method com/amazonaws/services/s3/model/ObjectMetadata."<init>":()V
       7: astore_3
       8: aload_3
       9: aload_1
      10: arraylength
      11: i2l
      12: invokevirtual #33                 // Method com/amazonaws/services/s3/model/ObjectMetadata.setContentLength:(J)V
      15: new           #23                 // class com/amazonaws/services/s3/model/PutObjectRequest
      18: dup
      19: aload_0
      20: invokevirtual #24                 // Method getBucketName:()Ljava/lang/String;
      23: aload_0
      24: invokevirtual #25                 // Method getKey:()Ljava/lang/String;
      27: new           #34                 // class java/io/ByteArrayInputStream
      30: dup
      31: aload_1
      32: invokespecial #35                 // Method java/io/ByteArrayInputStream."<init>":([B)V
      35: aload_3
      36: invokespecial #36                 // Method com/amazonaws/services/s3/model/PutObjectRequest."<init>":(Ljava/lang/String;Ljava/lang/String;Ljava/io/InputStream;Lcom/amazonaws/services/s3/model/ObjectMetadata;)V
      39: aload_2
      40: invokevirtual #27                 // Method com/amazonaws/services/s3/model/PutObjectRequest.withRequestMetricCollector:(Lcom/amazonaws/metrics/RequestMetricCollector;)Lcom/amazonaws/AmazonWebServiceRequest;
      43: checkcast     #23                 // class com/amazonaws/services/s3/model/PutObjectRequest
      46: astore        4
      48: aload_0
      49: invokevirtual #28                 // Method getAmazonS3Client:()Lcom/amazonaws/services/s3/AmazonS3;
      52: aload         4
      54: invokeinterface #29,  2           // InterfaceMethod com/amazonaws/services/s3/AmazonS3.putObject:(Lcom/amazonaws/services/s3/model/PutObjectRequest;)Lcom/amazonaws/services/s3/model/PutObjectResult;
      59: areturn

  public void setAcl(com.amazonaws.services.s3.model.CannedAccessControlList);
    Code:
       0: aload_0
       1: aload_1
       2: aconst_null
       3: invokespecial #37                 // Method setAcl0:(Lcom/amazonaws/services/s3/model/CannedAccessControlList;Lcom/amazonaws/metrics/RequestMetricCollector;)V
       6: return

  public void setAcl(com.amazonaws.services.s3.model.CannedAccessControlList, com.amazonaws.metrics.RequestMetricCollector);
    Code:
       0: aload_0
       1: aload_1
       2: aload_2
       3: invokespecial #37                 // Method setAcl0:(Lcom/amazonaws/services/s3/model/CannedAccessControlList;Lcom/amazonaws/metrics/RequestMetricCollector;)V
       6: return

  private void setAcl0(com.amazonaws.services.s3.model.CannedAccessControlList, com.amazonaws.metrics.RequestMetricCollector);
    Code:
       0: new           #38                 // class com/amazonaws/services/s3/model/SetObjectAclRequest
       3: dup
       4: aload_0
       5: invokevirtual #24                 // Method getBucketName:()Ljava/lang/String;
       8: aload_0
       9: invokevirtual #25                 // Method getKey:()Ljava/lang/String;
      12: aload_1
      13: invokespecial #39                 // Method com/amazonaws/services/s3/model/SetObjectAclRequest."<init>":(Ljava/lang/String;Ljava/lang/String;Lcom/amazonaws/services/s3/model/CannedAccessControlList;)V
      16: aload_2
      17: invokevirtual #40                 // Method com/amazonaws/services/s3/model/SetObjectAclRequest.withRequestMetricCollector:(Lcom/amazonaws/metrics/RequestMetricCollector;)Lcom/amazonaws/AmazonWebServiceRequest;
      20: checkcast     #38                 // class com/amazonaws/services/s3/model/SetObjectAclRequest
      23: astore_3
      24: aload_0
      25: invokevirtual #28                 // Method getAmazonS3Client:()Lcom/amazonaws/services/s3/AmazonS3;
      28: aload_3
      29: invokeinterface #41,  2           // InterfaceMethod com/amazonaws/services/s3/AmazonS3.setObjectAcl:(Lcom/amazonaws/services/s3/model/SetObjectAclRequest;)V
      34: return

  public void setAcl(com.amazonaws.services.s3.model.AccessControlList);
    Code:
       0: aload_0
       1: aload_1
       2: aconst_null
       3: invokespecial #42                 // Method setAcl0:(Lcom/amazonaws/services/s3/model/AccessControlList;Lcom/amazonaws/metrics/RequestMetricCollector;)V
       6: return

  public void setAcl(com.amazonaws.services.s3.model.AccessControlList, com.amazonaws.metrics.RequestMetricCollector);
    Code:
       0: aload_0
       1: aload_1
       2: aload_2
       3: invokespecial #42                 // Method setAcl0:(Lcom/amazonaws/services/s3/model/AccessControlList;Lcom/amazonaws/metrics/RequestMetricCollector;)V
       6: return

  private void setAcl0(com.amazonaws.services.s3.model.AccessControlList, com.amazonaws.metrics.RequestMetricCollector);
    Code:
       0: new           #38                 // class com/amazonaws/services/s3/model/SetObjectAclRequest
       3: dup
       4: aload_0
       5: invokevirtual #24                 // Method getBucketName:()Ljava/lang/String;
       8: aload_0
       9: invokevirtual #25                 // Method getKey:()Ljava/lang/String;
      12: aload_1
      13: invokespecial #43                 // Method com/amazonaws/services/s3/model/SetObjectAclRequest."<init>":(Ljava/lang/String;Ljava/lang/String;Lcom/amazonaws/services/s3/model/AccessControlList;)V
      16: aload_2
      17: invokevirtual #40                 // Method com/amazonaws/services/s3/model/SetObjectAclRequest.withRequestMetricCollector:(Lcom/amazonaws/metrics/RequestMetricCollector;)Lcom/amazonaws/AmazonWebServiceRequest;
      20: checkcast     #38                 // class com/amazonaws/services/s3/model/SetObjectAclRequest
      23: astore_3
      24: aload_0
      25: invokevirtual #28                 // Method getAmazonS3Client:()Lcom/amazonaws/services/s3/AmazonS3;
      28: aload_3
      29: invokeinterface #41,  2           // InterfaceMethod com/amazonaws/services/s3/AmazonS3.setObjectAcl:(Lcom/amazonaws/services/s3/model/SetObjectAclRequest;)V
      34: return

  public java.net.URL getUrl();
    Code:
       0: aload_0
       1: invokevirtual #28                 // Method getAmazonS3Client:()Lcom/amazonaws/services/s3/AmazonS3;
       4: aload_0
       5: invokevirtual #24                 // Method getBucketName:()Ljava/lang/String;
       8: aload_0
       9: invokevirtual #25                 // Method getKey:()Ljava/lang/String;
      12: invokeinterface #44,  3           // InterfaceMethod com/amazonaws/services/s3/AmazonS3.getUrl:(Ljava/lang/String;Ljava/lang/String;)Ljava/net/URL;
      17: areturn

  public com.amazonaws.services.s3.model.ObjectMetadata downloadTo(java.io.File);
    Code:
       0: aload_0
       1: aload_1
       2: aconst_null
       3: invokespecial #45                 // Method downloadTo0:(Ljava/io/File;Lcom/amazonaws/metrics/RequestMetricCollector;)Lcom/amazonaws/services/s3/model/ObjectMetadata;
       6: areturn

  public com.amazonaws.services.s3.model.ObjectMetadata downloadTo(java.io.File, com.amazonaws.metrics.RequestMetricCollector);
    Code:
       0: aload_0
       1: aload_1
       2: aload_2
       3: invokespecial #45                 // Method downloadTo0:(Ljava/io/File;Lcom/amazonaws/metrics/RequestMetricCollector;)Lcom/amazonaws/services/s3/model/ObjectMetadata;
       6: areturn

  private com.amazonaws.services.s3.model.ObjectMetadata downloadTo0(java.io.File, com.amazonaws.metrics.RequestMetricCollector);
    Code:
       0: new           #46                 // class com/amazonaws/services/s3/model/GetObjectRequest
       3: dup
       4: aload_0
       5: invokevirtual #24                 // Method getBucketName:()Ljava/lang/String;
       8: aload_0
       9: invokevirtual #25                 // Method getKey:()Ljava/lang/String;
      12: invokespecial #47                 // Method com/amazonaws/services/s3/model/GetObjectRequest."<init>":(Ljava/lang/String;Ljava/lang/String;)V
      15: aload_2
      16: invokevirtual #48                 // Method com/amazonaws/services/s3/model/GetObjectRequest.withRequestMetricCollector:(Lcom/amazonaws/metrics/RequestMetricCollector;)Lcom/amazonaws/AmazonWebServiceRequest;
      19: checkcast     #46                 // class com/amazonaws/services/s3/model/GetObjectRequest
      22: astore_3
      23: aload_0
      24: invokevirtual #28                 // Method getAmazonS3Client:()Lcom/amazonaws/services/s3/AmazonS3;
      27: aload_3
      28: aload_1
      29: invokeinterface #49,  3           // InterfaceMethod com/amazonaws/services/s3/AmazonS3.getObject:(Lcom/amazonaws/services/s3/model/GetObjectRequest;Ljava/io/File;)Lcom/amazonaws/services/s3/model/ObjectMetadata;
      34: areturn

  public com.amazonaws.services.s3.model.ObjectMetadata downloadTo(java.io.OutputStream);
    Code:
       0: aload_0
       1: aload_1
       2: aconst_null
       3: invokespecial #50                 // Method downloadTo0:(Ljava/io/OutputStream;Lcom/amazonaws/metrics/RequestMetricCollector;)Lcom/amazonaws/services/s3/model/ObjectMetadata;
       6: areturn

  public com.amazonaws.services.s3.model.ObjectMetadata downloadTo(java.io.OutputStream, com.amazonaws.metrics.RequestMetricCollector);
    Code:
       0: aload_0
       1: aload_1
       2: aload_2
       3: invokespecial #50                 // Method downloadTo0:(Ljava/io/OutputStream;Lcom/amazonaws/metrics/RequestMetricCollector;)Lcom/amazonaws/services/s3/model/ObjectMetadata;
       6: areturn

  private com.amazonaws.services.s3.model.ObjectMetadata downloadTo0(java.io.OutputStream, com.amazonaws.metrics.RequestMetricCollector);
    Code:
       0: new           #46                 // class com/amazonaws/services/s3/model/GetObjectRequest
       3: dup
       4: aload_0
       5: invokevirtual #24                 // Method getBucketName:()Ljava/lang/String;
       8: aload_0
       9: invokevirtual #25                 // Method getKey:()Ljava/lang/String;
      12: invokespecial #47                 // Method com/amazonaws/services/s3/model/GetObjectRequest."<init>":(Ljava/lang/String;Ljava/lang/String;)V
      15: aload_2
      16: invokevirtual #48                 // Method com/amazonaws/services/s3/model/GetObjectRequest.withRequestMetricCollector:(Lcom/amazonaws/metrics/RequestMetricCollector;)Lcom/amazonaws/AmazonWebServiceRequest;
      19: checkcast     #46                 // class com/amazonaws/services/s3/model/GetObjectRequest
      22: astore_3
      23: aload_0
      24: invokevirtual #28                 // Method getAmazonS3Client:()Lcom/amazonaws/services/s3/AmazonS3;
      27: aload_3
      28: invokeinterface #51,  2           // InterfaceMethod com/amazonaws/services/s3/AmazonS3.getObject:(Lcom/amazonaws/services/s3/model/GetObjectRequest;)Lcom/amazonaws/services/s3/model/S3Object;
      33: astore        4
      35: aload         4
      37: invokevirtual #52                 // Method com/amazonaws/services/s3/model/S3Object.getObjectContent:()Lcom/amazonaws/services/s3/model/S3ObjectInputStream;
      40: astore        5
      42: sipush        10240
      45: newarray       byte
      47: astore        6
      49: iconst_m1
      50: istore        7
      52: aload         5
      54: aload         6
      56: invokevirtual #53                 // Method com/amazonaws/services/s3/model/S3ObjectInputStream.read:([B)I
      59: dup
      60: istore        7
      62: iconst_m1
      63: if_icmple     78
      66: aload_1
      67: aload         6
      69: iconst_0
      70: iload         7
      72: invokevirtual #54                 // Method java/io/OutputStream.write:([BII)V
      75: goto          52
      78: aload         5
      80: invokevirtual #55                 // Method com/amazonaws/services/s3/model/S3ObjectInputStream.close:()V
      83: goto          125
      86: astore        6
      88: goto          125
      91: astore        6
      93: aload         5
      95: invokevirtual #57                 // Method com/amazonaws/services/s3/model/S3ObjectInputStream.abort:()V
      98: new           #58                 // class com/amazonaws/AmazonClientException
     101: dup
     102: ldc           #59                 // String Unable to transfer content from Amazon S3 to the output stream
     104: aload         6
     106: invokespecial #60                 // Method com/amazonaws/AmazonClientException."<init>":(Ljava/lang/String;Ljava/lang/Throwable;)V
     109: athrow
     110: astore        8
     112: aload         5
     114: invokevirtual #55                 // Method com/amazonaws/services/s3/model/S3ObjectInputStream.close:()V
     117: goto          122
     120: astore        9
     122: aload         8
     124: athrow
     125: aload         4
     127: invokevirtual #61                 // Method com/amazonaws/services/s3/model/S3Object.getObjectMetadata:()Lcom/amazonaws/services/s3/model/ObjectMetadata;
     130: areturn
    Exception table:
       from    to  target type
          78    83    86   Class java/io/IOException
          42    78    91   Class java/io/IOException
          42    78   110   any
         112   117   120   Class java/io/IOException
          91   112   110   any
}
