Compiled from "Pricing.scala"
public class zio.aws.pricing.Pricing$PricingImpl<R> implements zio.aws.pricing.Pricing, zio.aws.core.AwsServiceBase<R> {
  private final software.amazon.awssdk.services.pricing.PricingAsyncClient api;

  private final zio.ZIOAspect<scala.runtime.Nothing$, R, zio.aws.core.AwsError, zio.aws.core.AwsError, scala.runtime.Nothing$, zio.aws.core.aspects.package$Described<?>> aspect;

  private final zio.ZEnvironment<R> r;

  private final java.lang.String serviceName;

  public final <Request, Response> zio.ZIO<R, zio.aws.core.AwsError, Response> asyncRequestResponse(java.lang.String, scala.Function1<Request, java.util.concurrent.CompletableFuture<Response>>, Request);
    Code:
       0: aload_0
       1: aload_1
       2: aload_2
       3: aload_3
       4: invokestatic  #88                 // InterfaceMethod zio/aws/core/AwsServiceBase.asyncRequestResponse$:(Lzio/aws/core/AwsServiceBase;Ljava/lang/String;Lscala/Function1;Ljava/lang/Object;)Lzio/ZIO;
       7: areturn

  public final <Request, Item, Response> zio.stream.ZStream<R, zio.aws.core.AwsError, Item> asyncJavaPaginatedRequest(java.lang.String, scala.Function1<Request, Response>, scala.Function1<Response, org.reactivestreams.Publisher<Item>>, Request);
    Code:
       0: aload_0
       1: aload_1
       2: aload_2
       3: aload_3
       4: aload         4
       6: invokestatic  #100                // InterfaceMethod zio/aws/core/AwsServiceBase.asyncJavaPaginatedRequest$:(Lzio/aws/core/AwsServiceBase;Ljava/lang/String;Lscala/Function1;Lscala/Function1;Ljava/lang/Object;)Lzio/stream/ZStream;
       9: areturn

  public final <Request, Response, Item> zio.stream.ZStream<R, zio.aws.core.AwsError, Item> asyncSimplePaginatedRequest(java.lang.String, scala.Function1<Request, java.util.concurrent.CompletableFuture<Response>>, scala.Function2<Request, java.lang.String, Request>, scala.Function1<Response, scala.Option<java.lang.String>>, scala.Function1<Response, zio.Chunk<Item>>, Request);
    Code:
       0: aload_0
       1: aload_1
       2: aload_2
       3: aload_3
       4: aload         4
       6: aload         5
       8: aload         6
      10: invokestatic  #110                // InterfaceMethod zio/aws/core/AwsServiceBase.asyncSimplePaginatedRequest$:(Lzio/aws/core/AwsServiceBase;Ljava/lang/String;Lscala/Function1;Lscala/Function2;Lscala/Function1;Lscala/Function1;Ljava/lang/Object;)Lzio/stream/ZStream;
      13: areturn

  public final <Request, Response, Item> zio.ZIO<R, zio.aws.core.AwsError, zio.aws.core.StreamingOutputResult<R, Response, Item>> asyncPaginatedRequest(java.lang.String, scala.Function1<Request, java.util.concurrent.CompletableFuture<Response>>, scala.Function2<Request, java.lang.String, Request>, scala.Function1<Response, scala.Option<java.lang.String>>, scala.Function1<Response, zio.Chunk<Item>>, Request);
    Code:
       0: aload_0
       1: aload_1
       2: aload_2
       3: aload_3
       4: aload         4
       6: aload         5
       8: aload         6
      10: invokestatic  #118                // InterfaceMethod zio/aws/core/AwsServiceBase.asyncPaginatedRequest$:(Lzio/aws/core/AwsServiceBase;Ljava/lang/String;Lscala/Function1;Lscala/Function2;Lscala/Function1;Lscala/Function1;Ljava/lang/Object;)Lzio/ZIO;
      13: areturn

  public final <Request, Response> zio.ZIO<R, zio.aws.core.AwsError, zio.aws.core.StreamingOutputResult<R, Response, java.lang.Object>> asyncRequestOutputStream(java.lang.String, scala.Function2<Request, software.amazon.awssdk.core.async.AsyncResponseTransformer<Response, zio.ZIO<java.lang.Object, java.lang.Throwable, zio.aws.core.StreamingOutputResult<R, Response, java.lang.Object>>>, java.util.concurrent.CompletableFuture<zio.ZIO<java.lang.Object, java.lang.Throwable, zio.aws.core.StreamingOutputResult<R, Response, java.lang.Object>>>>, Request);
    Code:
       0: aload_0
       1: aload_1
       2: aload_2
       3: aload_3
       4: invokestatic  #125                // InterfaceMethod zio/aws/core/AwsServiceBase.asyncRequestOutputStream$:(Lzio/aws/core/AwsServiceBase;Ljava/lang/String;Lscala/Function2;Ljava/lang/Object;)Lzio/ZIO;
       7: areturn

  public final <Request, Response> zio.ZIO<R, zio.aws.core.AwsError, Response> asyncRequestInputStream(java.lang.String, scala.Function2<Request, software.amazon.awssdk.core.async.AsyncRequestBody, java.util.concurrent.CompletableFuture<Response>>, Request, zio.stream.ZStream<R, zio.aws.core.AwsError, java.lang.Object>);
    Code:
       0: aload_0
       1: aload_1
       2: aload_2
       3: aload_3
       4: aload         4
       6: invokestatic  #133                // InterfaceMethod zio/aws/core/AwsServiceBase.asyncRequestInputStream$:(Lzio/aws/core/AwsServiceBase;Ljava/lang/String;Lscala/Function2;Ljava/lang/Object;Lzio/stream/ZStream;)Lzio/ZIO;
       9: areturn

  public final <Request, Response> zio.ZIO<R, zio.aws.core.AwsError, zio.aws.core.StreamingOutputResult<R, Response, java.lang.Object>> asyncRequestInputOutputStream(java.lang.String, scala.Function3<Request, software.amazon.awssdk.core.async.AsyncRequestBody, software.amazon.awssdk.core.async.AsyncResponseTransformer<Response, zio.ZIO<java.lang.Object, java.lang.Throwable, zio.aws.core.StreamingOutputResult<R, Response, java.lang.Object>>>, java.util.concurrent.CompletableFuture<zio.ZIO<java.lang.Object, java.lang.Throwable, zio.aws.core.StreamingOutputResult<R, Response, java.lang.Object>>>>, Request, zio.stream.ZStream<R, zio.aws.core.AwsError, java.lang.Object>);
    Code:
       0: aload_0
       1: aload_1
       2: aload_2
       3: aload_3
       4: aload         4
       6: invokestatic  #141                // InterfaceMethod zio/aws/core/AwsServiceBase.asyncRequestInputOutputStream$:(Lzio/aws/core/AwsServiceBase;Ljava/lang/String;Lscala/Function3;Ljava/lang/Object;Lzio/stream/ZStream;)Lzio/ZIO;
       9: areturn

  public final <Request, Response, ResponseHandler extends software.amazon.awssdk.awscore.eventstream.EventStreamResponseHandler<Response, EventI>, EventI, Event> zio.stream.ZStream<R, zio.aws.core.AwsError, Event> asyncRequestEventOutputStream(java.lang.String, scala.Function2<Request, ResponseHandler, java.util.concurrent.CompletableFuture<java.lang.Void>>, scala.Function1<software.amazon.awssdk.awscore.eventstream.EventStreamResponseHandler<Response, EventI>, ResponseHandler>, Request, scala.reflect.ClassTag<Event>);
    Code:
       0: aload_0
       1: aload_1
       2: aload_2
       3: aload_3
       4: aload         4
       6: aload         5
       8: invokestatic  #151                // InterfaceMethod zio/aws/core/AwsServiceBase.asyncRequestEventOutputStream$:(Lzio/aws/core/AwsServiceBase;Ljava/lang/String;Lscala/Function2;Lscala/Function1;Ljava/lang/Object;Lscala/reflect/ClassTag;)Lzio/stream/ZStream;
      11: areturn

  public final <Request, Response, Event> zio.ZIO<R, zio.aws.core.AwsError, Response> asyncRequestEventInputStream(java.lang.String, scala.Function2<Request, org.reactivestreams.Publisher<Event>, java.util.concurrent.CompletableFuture<Response>>, Request, zio.stream.ZStream<R, zio.aws.core.AwsError, Event>);
    Code:
       0: aload_0
       1: aload_1
       2: aload_2
       3: aload_3
       4: aload         4
       6: invokestatic  #158                // InterfaceMethod zio/aws/core/AwsServiceBase.asyncRequestEventInputStream$:(Lzio/aws/core/AwsServiceBase;Ljava/lang/String;Lscala/Function2;Ljava/lang/Object;Lzio/stream/ZStream;)Lzio/ZIO;
       9: areturn

  public final <Request, Response, InEvent, ResponseHandler extends software.amazon.awssdk.awscore.eventstream.EventStreamResponseHandler<Response, OutEventI>, OutEventI, OutEvent> zio.stream.ZStream<R, zio.aws.core.AwsError, OutEvent> asyncRequestEventInputOutputStream(java.lang.String, scala.Function3<Request, org.reactivestreams.Publisher<InEvent>, ResponseHandler, java.util.concurrent.CompletableFuture<java.lang.Void>>, scala.Function1<software.amazon.awssdk.awscore.eventstream.EventStreamResponseHandler<Response, OutEventI>, ResponseHandler>, Request, zio.stream.ZStream<R, zio.aws.core.AwsError, InEvent>, scala.reflect.ClassTag<OutEvent>);
    Code:
       0: aload_0
       1: aload_1
       2: aload_2
       3: aload_3
       4: aload         4
       6: aload         5
       8: aload         6
      10: invokestatic  #165                // InterfaceMethod zio/aws/core/AwsServiceBase.asyncRequestEventInputOutputStream$:(Lzio/aws/core/AwsServiceBase;Ljava/lang/String;Lscala/Function3;Lscala/Function1;Ljava/lang/Object;Lzio/stream/ZStream;Lscala/reflect/ClassTag;)Lzio/stream/ZStream;
      13: areturn

  public software.amazon.awssdk.services.pricing.PricingAsyncClient api();
    Code:
       0: aload_0
       1: getfield      #168                // Field api:Lsoftware/amazon/awssdk/services/pricing/PricingAsyncClient;
       4: areturn

  public zio.ZIOAspect<scala.runtime.Nothing$, R, zio.aws.core.AwsError, zio.aws.core.AwsError, scala.runtime.Nothing$, zio.aws.core.aspects.package$Described<?>> aspect();
    Code:
       0: aload_0
       1: getfield      #172                // Field aspect:Lzio/ZIOAspect;
       4: areturn

  public java.lang.String serviceName();
    Code:
       0: aload_0
       1: getfield      #175                // Field serviceName:Ljava/lang/String;
       4: areturn

  public <R1> zio.aws.pricing.Pricing$PricingImpl<R1> withAspect(zio.ZIOAspect<scala.runtime.Nothing$, R1, zio.aws.core.AwsError, zio.aws.core.AwsError, scala.runtime.Nothing$, zio.aws.core.aspects.package$Described<?>>, zio.ZEnvironment<R1>);
    Code:
       0: new           #2                  // class zio/aws/pricing/Pricing$PricingImpl
       3: dup
       4: aload_0
       5: invokevirtual #181                // Method api:()Lsoftware/amazon/awssdk/services/pricing/PricingAsyncClient;
       8: aload_1
       9: aload_2
      10: invokespecial #185                // Method "<init>":(Lsoftware/amazon/awssdk/services/pricing/PricingAsyncClient;Lzio/ZIOAspect;Lzio/ZEnvironment;)V
      13: areturn

  public zio.ZIO<java.lang.Object, zio.aws.core.AwsError, zio.aws.core.StreamingOutputResult<java.lang.Object, zio.aws.pricing.model.DescribeServicesResponse$ReadOnly, zio.aws.pricing.model.Service$ReadOnly>> describeServices(zio.aws.pricing.model.DescribeServicesRequest);
    Code:
       0: aload_0
       1: ldc           #189                // String describeServices
       3: aload_0
       4: invokedynamic #213,  0            // InvokeDynamic #0:apply:(Lzio/aws/pricing/Pricing$PricingImpl;)Lscala/Function1;
       9: invokedynamic #224,  0            // InvokeDynamic #1:apply:()Lscala/Function2;
      14: invokedynamic #233,  0            // InvokeDynamic #2:apply:()Lscala/Function1;
      19: invokedynamic #240,  0            // InvokeDynamic #3:apply:()Lscala/Function1;
      24: aload_1
      25: invokevirtual #246                // Method zio/aws/pricing/model/DescribeServicesRequest.buildAwsValue:()Lsoftware/amazon/awssdk/services/pricing/model/DescribeServicesRequest;
      28: invokevirtual #248                // Method asyncPaginatedRequest:(Ljava/lang/String;Lscala/Function1;Lscala/Function2;Lscala/Function1;Lscala/Function1;Ljava/lang/Object;)Lzio/ZIO;
      31: aload_0
      32: invokedynamic #256,  0            // InvokeDynamic #4:apply:(Lzio/aws/pricing/Pricing$PricingImpl;)Lscala/Function1;
      37: ldc_w         #258                // String zio.aws.pricing.Pricing.PricingImpl.describeServices(Pricing.scala:115)
      40: invokeinterface #264,  3          // InterfaceMethod zio/ZIO.map:(Lscala/Function1;Ljava/lang/Object;)Lzio/ZIO;
      45: aload_0
      46: invokedynamic #276,  0            // InvokeDynamic #5:apply:(Lzio/aws/pricing/Pricing$PricingImpl;)Lscala/Function0;
      51: ldc_w         #278                // String zio.aws.pricing.Pricing.PricingImpl.describeServices(Pricing.scala:121)
      54: invokeinterface #282,  3          // InterfaceMethod zio/ZIO.provideEnvironment:(Lscala/Function0;Ljava/lang/Object;)Lzio/ZIO;
      59: areturn

  public zio.ZIO<java.lang.Object, zio.aws.core.AwsError, zio.aws.pricing.model.DescribeServicesResponse$ReadOnly> describeServicesPaginated(zio.aws.pricing.model.DescribeServicesRequest);
    Code:
       0: aload_0
       1: ldc           #189                // String describeServices
       3: aload_0
       4: invokedynamic #290,  0            // InvokeDynamic #6:apply:(Lzio/aws/pricing/Pricing$PricingImpl;)Lscala/Function1;
       9: aload_1
      10: invokevirtual #246                // Method zio/aws/pricing/model/DescribeServicesRequest.buildAwsValue:()Lsoftware/amazon/awssdk/services/pricing/model/DescribeServicesRequest;
      13: invokevirtual #292                // Method asyncRequestResponse:(Ljava/lang/String;Lscala/Function1;Ljava/lang/Object;)Lzio/ZIO;
      16: invokedynamic #299,  0            // InvokeDynamic #7:apply:()Lscala/Function1;
      21: ldc_w         #301                // String zio.aws.pricing.Pricing.PricingImpl.describeServicesPaginated(Pricing.scala:129)
      24: invokeinterface #264,  3          // InterfaceMethod zio/ZIO.map:(Lscala/Function1;Ljava/lang/Object;)Lzio/ZIO;
      29: aload_0
      30: invokedynamic #306,  0            // InvokeDynamic #8:apply:(Lzio/aws/pricing/Pricing$PricingImpl;)Lscala/Function0;
      35: ldc_w         #308                // String zio.aws.pricing.Pricing.PricingImpl.describeServicesPaginated(Pricing.scala:130)
      38: invokeinterface #282,  3          // InterfaceMethod zio/ZIO.provideEnvironment:(Lscala/Function0;Ljava/lang/Object;)Lzio/ZIO;
      43: areturn

  public zio.stream.ZStream<java.lang.Object, zio.aws.core.AwsError, zio.aws.pricing.model.AttributeValue$ReadOnly> getAttributeValues(zio.aws.pricing.model.GetAttributeValuesRequest);
    Code:
       0: aload_0
       1: ldc_w         #312                // String getAttributeValues
       4: aload_0
       5: invokedynamic #320,  0            // InvokeDynamic #9:apply:(Lzio/aws/pricing/Pricing$PricingImpl;)Lscala/Function1;
      10: invokedynamic #327,  0            // InvokeDynamic #10:apply:()Lscala/Function2;
      15: invokedynamic #334,  0            // InvokeDynamic #11:apply:()Lscala/Function1;
      20: invokedynamic #341,  0            // InvokeDynamic #12:apply:()Lscala/Function1;
      25: aload_1
      26: invokevirtual #346                // Method zio/aws/pricing/model/GetAttributeValuesRequest.buildAwsValue:()Lsoftware/amazon/awssdk/services/pricing/model/GetAttributeValuesRequest;
      29: invokevirtual #348                // Method asyncSimplePaginatedRequest:(Ljava/lang/String;Lscala/Function1;Lscala/Function2;Lscala/Function1;Lscala/Function1;Ljava/lang/Object;)Lzio/stream/ZStream;
      32: invokedynamic #355,  0            // InvokeDynamic #13:apply:()Lscala/Function1;
      37: ldc_w         #357                // String zio.aws.pricing.Pricing.PricingImpl.getAttributeValues(Pricing.scala:145)
      40: invokevirtual #362                // Method zio/stream/ZStream.map:(Lscala/Function1;Ljava/lang/Object;)Lzio/stream/ZStream;
      43: aload_0
      44: invokedynamic #367,  0            // InvokeDynamic #14:apply:(Lzio/aws/pricing/Pricing$PricingImpl;)Lscala/Function0;
      49: ldc_w         #369                // String zio.aws.pricing.Pricing.PricingImpl.getAttributeValues(Pricing.scala:146)
      52: invokevirtual #372                // Method zio/stream/ZStream.provideEnvironment:(Lscala/Function0;Ljava/lang/Object;)Lzio/stream/ZStream;
      55: areturn

  public zio.ZIO<java.lang.Object, zio.aws.core.AwsError, zio.aws.pricing.model.GetAttributeValuesResponse$ReadOnly> getAttributeValuesPaginated(zio.aws.pricing.model.GetAttributeValuesRequest);
    Code:
       0: aload_0
       1: ldc_w         #312                // String getAttributeValues
       4: aload_0
       5: invokedynamic #381,  0            // InvokeDynamic #15:apply:(Lzio/aws/pricing/Pricing$PricingImpl;)Lscala/Function1;
      10: aload_1
      11: invokevirtual #346                // Method zio/aws/pricing/model/GetAttributeValuesRequest.buildAwsValue:()Lsoftware/amazon/awssdk/services/pricing/model/GetAttributeValuesRequest;
      14: invokevirtual #292                // Method asyncRequestResponse:(Ljava/lang/String;Lscala/Function1;Ljava/lang/Object;)Lzio/ZIO;
      17: invokedynamic #388,  0            // InvokeDynamic #16:apply:()Lscala/Function1;
      22: ldc_w         #390                // String zio.aws.pricing.Pricing.PricingImpl.getAttributeValuesPaginated(Pricing.scala:154)
      25: invokeinterface #264,  3          // InterfaceMethod zio/ZIO.map:(Lscala/Function1;Ljava/lang/Object;)Lzio/ZIO;
      30: aload_0
      31: invokedynamic #395,  0            // InvokeDynamic #17:apply:(Lzio/aws/pricing/Pricing$PricingImpl;)Lscala/Function0;
      36: ldc_w         #397                // String zio.aws.pricing.Pricing.PricingImpl.getAttributeValuesPaginated(Pricing.scala:155)
      39: invokeinterface #282,  3          // InterfaceMethod zio/ZIO.provideEnvironment:(Lscala/Function0;Ljava/lang/Object;)Lzio/ZIO;
      44: areturn

  public zio.ZIO<java.lang.Object, zio.aws.core.AwsError, zio.aws.core.StreamingOutputResult<java.lang.Object, zio.aws.pricing.model.GetProductsResponse$ReadOnly, java.lang.String>> getProducts(zio.aws.pricing.model.GetProductsRequest);
    Code:
       0: aload_0
       1: ldc_w         #401                // String getProducts
       4: aload_0
       5: invokedynamic #409,  0            // InvokeDynamic #18:apply:(Lzio/aws/pricing/Pricing$PricingImpl;)Lscala/Function1;
      10: invokedynamic #416,  0            // InvokeDynamic #19:apply:()Lscala/Function2;
      15: invokedynamic #423,  0            // InvokeDynamic #20:apply:()Lscala/Function1;
      20: invokedynamic #430,  0            // InvokeDynamic #21:apply:()Lscala/Function1;
      25: aload_1
      26: invokevirtual #435                // Method zio/aws/pricing/model/GetProductsRequest.buildAwsValue:()Lsoftware/amazon/awssdk/services/pricing/model/GetProductsRequest;
      29: invokevirtual #248                // Method asyncPaginatedRequest:(Ljava/lang/String;Lscala/Function1;Lscala/Function2;Lscala/Function1;Lscala/Function1;Ljava/lang/Object;)Lzio/ZIO;
      32: aload_0
      33: invokedynamic #440,  0            // InvokeDynamic #22:apply:(Lzio/aws/pricing/Pricing$PricingImpl;)Lscala/Function1;
      38: ldc_w         #442                // String zio.aws.pricing.Pricing.PricingImpl.getProducts(Pricing.scala:173)
      41: invokeinterface #264,  3          // InterfaceMethod zio/ZIO.map:(Lscala/Function1;Ljava/lang/Object;)Lzio/ZIO;
      46: aload_0
      47: invokedynamic #447,  0            // InvokeDynamic #23:apply:(Lzio/aws/pricing/Pricing$PricingImpl;)Lscala/Function0;
      52: ldc_w         #449                // String zio.aws.pricing.Pricing.PricingImpl.getProducts(Pricing.scala:183)
      55: invokeinterface #282,  3          // InterfaceMethod zio/ZIO.provideEnvironment:(Lscala/Function0;Ljava/lang/Object;)Lzio/ZIO;
      60: areturn

  public zio.ZIO<java.lang.Object, zio.aws.core.AwsError, zio.aws.pricing.model.GetProductsResponse$ReadOnly> getProductsPaginated(zio.aws.pricing.model.GetProductsRequest);
    Code:
       0: aload_0
       1: ldc_w         #401                // String getProducts
       4: aload_0
       5: invokedynamic #457,  0            // InvokeDynamic #24:apply:(Lzio/aws/pricing/Pricing$PricingImpl;)Lscala/Function1;
      10: aload_1
      11: invokevirtual #435                // Method zio/aws/pricing/model/GetProductsRequest.buildAwsValue:()Lsoftware/amazon/awssdk/services/pricing/model/GetProductsRequest;
      14: invokevirtual #292                // Method asyncRequestResponse:(Ljava/lang/String;Lscala/Function1;Ljava/lang/Object;)Lzio/ZIO;
      17: invokedynamic #464,  0            // InvokeDynamic #25:apply:()Lscala/Function1;
      22: ldc_w         #466                // String zio.aws.pricing.Pricing.PricingImpl.getProductsPaginated(Pricing.scala:191)
      25: invokeinterface #264,  3          // InterfaceMethod zio/ZIO.map:(Lscala/Function1;Ljava/lang/Object;)Lzio/ZIO;
      30: aload_0
      31: invokedynamic #471,  0            // InvokeDynamic #26:apply:(Lzio/aws/pricing/Pricing$PricingImpl;)Lscala/Function0;
      36: ldc_w         #473                // String zio.aws.pricing.Pricing.PricingImpl.getProductsPaginated(Pricing.scala:192)
      39: invokeinterface #282,  3          // InterfaceMethod zio/ZIO.provideEnvironment:(Lscala/Function0;Ljava/lang/Object;)Lzio/ZIO;
      44: areturn

  public java.lang.Object withAspect(zio.ZIOAspect, zio.ZEnvironment);
    Code:
       0: aload_0
       1: aload_1
       2: aload_2
       3: invokevirtual #476                // Method withAspect:(Lzio/ZIOAspect;Lzio/ZEnvironment;)Lzio/aws/pricing/Pricing$PricingImpl;
       6: areturn

  public static final java.util.concurrent.CompletableFuture $anonfun$describeServices$1(zio.aws.pricing.Pricing$PricingImpl, software.amazon.awssdk.services.pricing.model.DescribeServicesRequest);
    Code:
       0: aload_0
       1: invokevirtual #181                // Method api:()Lsoftware/amazon/awssdk/services/pricing/PricingAsyncClient;
       4: aload_1
       5: invokeinterface #482,  2          // InterfaceMethod software/amazon/awssdk/services/pricing/PricingAsyncClient.describeServices:(Lsoftware/amazon/awssdk/services/pricing/model/DescribeServicesRequest;)Ljava/util/concurrent/CompletableFuture;
      10: areturn

  public static final software.amazon.awssdk.services.pricing.model.DescribeServicesRequest $anonfun$describeServices$2(software.amazon.awssdk.services.pricing.model.DescribeServicesRequest, java.lang.String);
    Code:
       0: aload_0
       1: invokevirtual #488                // Method software/amazon/awssdk/services/pricing/model/DescribeServicesRequest.toBuilder:()Lsoftware/amazon/awssdk/services/pricing/model/DescribeServicesRequest$Builder;
       4: aload_1
       5: invokeinterface #492,  2          // InterfaceMethod software/amazon/awssdk/services/pricing/model/DescribeServicesRequest$Builder.nextToken:(Ljava/lang/String;)Lsoftware/amazon/awssdk/services/pricing/model/DescribeServicesRequest$Builder;
      10: invokeinterface #495,  1          // InterfaceMethod software/amazon/awssdk/services/pricing/model/DescribeServicesRequest$Builder.build:()Ljava/lang/Object;
      15: checkcast     #24                 // class software/amazon/awssdk/services/pricing/model/DescribeServicesRequest
      18: areturn

  public static final scala.Option $anonfun$describeServices$3(software.amazon.awssdk.services.pricing.model.DescribeServicesResponse);
    Code:
       0: getstatic     #501                // Field scala/Option$.MODULE$:Lscala/Option$;
       3: aload_0
       4: invokevirtual #505                // Method software/amazon/awssdk/services/pricing/model/DescribeServicesResponse.nextToken:()Ljava/lang/String;
       7: invokevirtual #508                // Method scala/Option$.apply:(Ljava/lang/Object;)Lscala/Option;
      10: areturn

  public static final zio.Chunk $anonfun$describeServices$4(software.amazon.awssdk.services.pricing.model.DescribeServicesResponse);
    Code:
       0: getstatic     #514                // Field zio/Chunk$.MODULE$:Lzio/Chunk$;
       3: getstatic     #519                // Field scala/jdk/CollectionConverters$.MODULE$:Lscala/jdk/CollectionConverters$;
       6: aload_0
       7: invokevirtual #523                // Method software/amazon/awssdk/services/pricing/model/DescribeServicesResponse.services:()Ljava/util/List;
      10: invokevirtual #527                // Method scala/jdk/CollectionConverters$.asScalaBufferConverter:(Ljava/util/List;)Lscala/collection/convert/Decorators$AsScala;
      13: invokevirtual #530                // Method scala/collection/convert/Decorators$AsScala.asScala:()Ljava/lang/Object;
      16: checkcast     #532                // class scala/collection/Iterable
      19: invokevirtual #536                // Method zio/Chunk$.fromIterable:(Lscala/collection/Iterable;)Lzio/Chunk;
      22: areturn

  public static final zio.aws.pricing.model.DescribeServicesResponse$ReadOnly $anonfun$describeServices$6(software.amazon.awssdk.services.pricing.model.DescribeServicesResponse);
    Code:
       0: getstatic     #542                // Field zio/aws/pricing/model/DescribeServicesResponse$.MODULE$:Lzio/aws/pricing/model/DescribeServicesResponse$;
       3: aload_0
       4: invokevirtual #545                // Method zio/aws/pricing/model/DescribeServicesResponse$.wrap:(Lsoftware/amazon/awssdk/services/pricing/model/DescribeServicesResponse;)Lzio/aws/pricing/model/DescribeServicesResponse$ReadOnly;
       7: areturn

  public static final zio.aws.pricing.model.Service$ReadOnly $anonfun$describeServices$8(software.amazon.awssdk.services.pricing.model.Service);
    Code:
       0: getstatic     #553                // Field zio/aws/pricing/model/Service$.MODULE$:Lzio/aws/pricing/model/Service$;
       3: aload_0
       4: invokevirtual #555                // Method zio/aws/pricing/model/Service$.wrap:(Lsoftware/amazon/awssdk/services/pricing/model/Service;)Lzio/aws/pricing/model/Service$ReadOnly;
       7: areturn

  public static final zio.stream.ZStream $anonfun$describeServices$7(zio.stream.ZStream);
    Code:
       0: aload_0
       1: invokedynamic #564,  0            // InvokeDynamic #27:apply:()Lscala/Function1;
       6: ldc_w         #566                // String zio.aws.pricing.Pricing.PricingImpl.describeServices(Pricing.scala:118)
       9: invokevirtual #362                // Method zio/stream/ZStream.map:(Lscala/Function1;Ljava/lang/Object;)Lzio/stream/ZStream;
      12: areturn

  public static final zio.aws.core.StreamingOutputResult $anonfun$describeServices$5(zio.aws.pricing.Pricing$PricingImpl, zio.aws.core.StreamingOutputResult);
    Code:
       0: aload_1
       1: invokedynamic #571,  0            // InvokeDynamic #28:apply:()Lscala/Function1;
       6: invokevirtual #577                // Method zio/aws/core/StreamingOutputResult.mapResponse:(Lscala/Function1;)Lzio/aws/core/StreamingOutputResult;
       9: invokedynamic #582,  0            // InvokeDynamic #29:apply:()Lscala/Function1;
      14: invokevirtual #585                // Method zio/aws/core/StreamingOutputResult.mapOutput:(Lscala/Function1;)Lzio/aws/core/StreamingOutputResult;
      17: aload_0
      18: getfield      #587                // Field r:Lzio/ZEnvironment;
      21: invokevirtual #590                // Method zio/aws/core/StreamingOutputResult.provideEnvironment:(Lzio/ZEnvironment;)Lzio/aws/core/StreamingOutputResult;
      24: areturn

  public static final zio.ZEnvironment $anonfun$describeServices$9(zio.aws.pricing.Pricing$PricingImpl);
    Code:
       0: aload_0
       1: getfield      #587                // Field r:Lzio/ZEnvironment;
       4: areturn

  public static final java.util.concurrent.CompletableFuture $anonfun$describeServicesPaginated$1(zio.aws.pricing.Pricing$PricingImpl, software.amazon.awssdk.services.pricing.model.DescribeServicesRequest);
    Code:
       0: aload_0
       1: invokevirtual #181                // Method api:()Lsoftware/amazon/awssdk/services/pricing/PricingAsyncClient;
       4: aload_1
       5: invokeinterface #482,  2          // InterfaceMethod software/amazon/awssdk/services/pricing/PricingAsyncClient.describeServices:(Lsoftware/amazon/awssdk/services/pricing/model/DescribeServicesRequest;)Ljava/util/concurrent/CompletableFuture;
      10: areturn

  public static final zio.aws.pricing.model.DescribeServicesResponse$ReadOnly $anonfun$describeServicesPaginated$2(software.amazon.awssdk.services.pricing.model.DescribeServicesResponse);
    Code:
       0: getstatic     #542                // Field zio/aws/pricing/model/DescribeServicesResponse$.MODULE$:Lzio/aws/pricing/model/DescribeServicesResponse$;
       3: aload_0
       4: invokevirtual #545                // Method zio/aws/pricing/model/DescribeServicesResponse$.wrap:(Lsoftware/amazon/awssdk/services/pricing/model/DescribeServicesResponse;)Lzio/aws/pricing/model/DescribeServicesResponse$ReadOnly;
       7: areturn

  public static final zio.ZEnvironment $anonfun$describeServicesPaginated$3(zio.aws.pricing.Pricing$PricingImpl);
    Code:
       0: aload_0
       1: getfield      #587                // Field r:Lzio/ZEnvironment;
       4: areturn

  public static final java.util.concurrent.CompletableFuture $anonfun$getAttributeValues$1(zio.aws.pricing.Pricing$PricingImpl, software.amazon.awssdk.services.pricing.model.GetAttributeValuesRequest);
    Code:
       0: aload_0
       1: invokevirtual #181                // Method api:()Lsoftware/amazon/awssdk/services/pricing/PricingAsyncClient;
       4: aload_1
       5: invokeinterface #593,  2          // InterfaceMethod software/amazon/awssdk/services/pricing/PricingAsyncClient.getAttributeValues:(Lsoftware/amazon/awssdk/services/pricing/model/GetAttributeValuesRequest;)Ljava/util/concurrent/CompletableFuture;
      10: areturn

  public static final software.amazon.awssdk.services.pricing.model.GetAttributeValuesRequest $anonfun$getAttributeValues$2(software.amazon.awssdk.services.pricing.model.GetAttributeValuesRequest, java.lang.String);
    Code:
       0: aload_0
       1: invokevirtual #597                // Method software/amazon/awssdk/services/pricing/model/GetAttributeValuesRequest.toBuilder:()Lsoftware/amazon/awssdk/services/pricing/model/GetAttributeValuesRequest$Builder;
       4: aload_1
       5: invokeinterface #600,  2          // InterfaceMethod software/amazon/awssdk/services/pricing/model/GetAttributeValuesRequest$Builder.nextToken:(Ljava/lang/String;)Lsoftware/amazon/awssdk/services/pricing/model/GetAttributeValuesRequest$Builder;
      10: invokeinterface #601,  1          // InterfaceMethod software/amazon/awssdk/services/pricing/model/GetAttributeValuesRequest$Builder.build:()Ljava/lang/Object;
      15: checkcast     #29                 // class software/amazon/awssdk/services/pricing/model/GetAttributeValuesRequest
      18: areturn

  public static final scala.Option $anonfun$getAttributeValues$3(software.amazon.awssdk.services.pricing.model.GetAttributeValuesResponse);
    Code:
       0: getstatic     #501                // Field scala/Option$.MODULE$:Lscala/Option$;
       3: aload_0
       4: invokevirtual #604                // Method software/amazon/awssdk/services/pricing/model/GetAttributeValuesResponse.nextToken:()Ljava/lang/String;
       7: invokevirtual #508                // Method scala/Option$.apply:(Ljava/lang/Object;)Lscala/Option;
      10: areturn

  public static final zio.Chunk $anonfun$getAttributeValues$4(software.amazon.awssdk.services.pricing.model.GetAttributeValuesResponse);
    Code:
       0: getstatic     #514                // Field zio/Chunk$.MODULE$:Lzio/Chunk$;
       3: getstatic     #519                // Field scala/jdk/CollectionConverters$.MODULE$:Lscala/jdk/CollectionConverters$;
       6: aload_0
       7: invokevirtual #608                // Method software/amazon/awssdk/services/pricing/model/GetAttributeValuesResponse.attributeValues:()Ljava/util/List;
      10: invokevirtual #527                // Method scala/jdk/CollectionConverters$.asScalaBufferConverter:(Ljava/util/List;)Lscala/collection/convert/Decorators$AsScala;
      13: invokevirtual #530                // Method scala/collection/convert/Decorators$AsScala.asScala:()Ljava/lang/Object;
      16: checkcast     #532                // class scala/collection/Iterable
      19: invokevirtual #536                // Method zio/Chunk$.fromIterable:(Lscala/collection/Iterable;)Lzio/Chunk;
      22: areturn

  public static final zio.aws.pricing.model.AttributeValue$ReadOnly $anonfun$getAttributeValues$5(software.amazon.awssdk.services.pricing.model.AttributeValue);
    Code:
       0: getstatic     #613                // Field zio/aws/pricing/model/AttributeValue$.MODULE$:Lzio/aws/pricing/model/AttributeValue$;
       3: aload_0
       4: invokevirtual #615                // Method zio/aws/pricing/model/AttributeValue$.wrap:(Lsoftware/amazon/awssdk/services/pricing/model/AttributeValue;)Lzio/aws/pricing/model/AttributeValue$ReadOnly;
       7: areturn

  public static final zio.ZEnvironment $anonfun$getAttributeValues$6(zio.aws.pricing.Pricing$PricingImpl);
    Code:
       0: aload_0
       1: getfield      #587                // Field r:Lzio/ZEnvironment;
       4: areturn

  public static final java.util.concurrent.CompletableFuture $anonfun$getAttributeValuesPaginated$1(zio.aws.pricing.Pricing$PricingImpl, software.amazon.awssdk.services.pricing.model.GetAttributeValuesRequest);
    Code:
       0: aload_0
       1: invokevirtual #181                // Method api:()Lsoftware/amazon/awssdk/services/pricing/PricingAsyncClient;
       4: aload_1
       5: invokeinterface #593,  2          // InterfaceMethod software/amazon/awssdk/services/pricing/PricingAsyncClient.getAttributeValues:(Lsoftware/amazon/awssdk/services/pricing/model/GetAttributeValuesRequest;)Ljava/util/concurrent/CompletableFuture;
      10: areturn

  public static final zio.aws.pricing.model.GetAttributeValuesResponse$ReadOnly $anonfun$getAttributeValuesPaginated$2(software.amazon.awssdk.services.pricing.model.GetAttributeValuesResponse);
    Code:
       0: getstatic     #621                // Field zio/aws/pricing/model/GetAttributeValuesResponse$.MODULE$:Lzio/aws/pricing/model/GetAttributeValuesResponse$;
       3: aload_0
       4: invokevirtual #623                // Method zio/aws/pricing/model/GetAttributeValuesResponse$.wrap:(Lsoftware/amazon/awssdk/services/pricing/model/GetAttributeValuesResponse;)Lzio/aws/pricing/model/GetAttributeValuesResponse$ReadOnly;
       7: areturn

  public static final zio.ZEnvironment $anonfun$getAttributeValuesPaginated$3(zio.aws.pricing.Pricing$PricingImpl);
    Code:
       0: aload_0
       1: getfield      #587                // Field r:Lzio/ZEnvironment;
       4: areturn

  public static final java.util.concurrent.CompletableFuture $anonfun$getProducts$1(zio.aws.pricing.Pricing$PricingImpl, software.amazon.awssdk.services.pricing.model.GetProductsRequest);
    Code:
       0: aload_0
       1: invokevirtual #181                // Method api:()Lsoftware/amazon/awssdk/services/pricing/PricingAsyncClient;
       4: aload_1
       5: invokeinterface #625,  2          // InterfaceMethod software/amazon/awssdk/services/pricing/PricingAsyncClient.getProducts:(Lsoftware/amazon/awssdk/services/pricing/model/GetProductsRequest;)Ljava/util/concurrent/CompletableFuture;
      10: areturn

  public static final software.amazon.awssdk.services.pricing.model.GetProductsRequest $anonfun$getProducts$2(software.amazon.awssdk.services.pricing.model.GetProductsRequest, java.lang.String);
    Code:
       0: aload_0
       1: invokevirtual #629                // Method software/amazon/awssdk/services/pricing/model/GetProductsRequest.toBuilder:()Lsoftware/amazon/awssdk/services/pricing/model/GetProductsRequest$Builder;
       4: aload_1
       5: invokeinterface #632,  2          // InterfaceMethod software/amazon/awssdk/services/pricing/model/GetProductsRequest$Builder.nextToken:(Ljava/lang/String;)Lsoftware/amazon/awssdk/services/pricing/model/GetProductsRequest$Builder;
      10: invokeinterface #633,  1          // InterfaceMethod software/amazon/awssdk/services/pricing/model/GetProductsRequest$Builder.build:()Ljava/lang/Object;
      15: checkcast     #33                 // class software/amazon/awssdk/services/pricing/model/GetProductsRequest
      18: areturn

  public static final scala.Option $anonfun$getProducts$3(software.amazon.awssdk.services.pricing.model.GetProductsResponse);
    Code:
       0: getstatic     #501                // Field scala/Option$.MODULE$:Lscala/Option$;
       3: aload_0
       4: invokevirtual #636                // Method software/amazon/awssdk/services/pricing/model/GetProductsResponse.nextToken:()Ljava/lang/String;
       7: invokevirtual #508                // Method scala/Option$.apply:(Ljava/lang/Object;)Lscala/Option;
      10: areturn

  public static final zio.Chunk $anonfun$getProducts$4(software.amazon.awssdk.services.pricing.model.GetProductsResponse);
    Code:
       0: getstatic     #514                // Field zio/Chunk$.MODULE$:Lzio/Chunk$;
       3: getstatic     #519                // Field scala/jdk/CollectionConverters$.MODULE$:Lscala/jdk/CollectionConverters$;
       6: aload_0
       7: invokevirtual #640                // Method software/amazon/awssdk/services/pricing/model/GetProductsResponse.priceList:()Ljava/util/List;
      10: invokevirtual #527                // Method scala/jdk/CollectionConverters$.asScalaBufferConverter:(Ljava/util/List;)Lscala/collection/convert/Decorators$AsScala;
      13: invokevirtual #530                // Method scala/collection/convert/Decorators$AsScala.asScala:()Ljava/lang/Object;
      16: checkcast     #532                // class scala/collection/Iterable
      19: invokevirtual #536                // Method zio/Chunk$.fromIterable:(Lscala/collection/Iterable;)Lzio/Chunk;
      22: areturn

  public static final zio.aws.pricing.model.GetProductsResponse$ReadOnly $anonfun$getProducts$6(software.amazon.awssdk.services.pricing.model.GetProductsResponse);
    Code:
       0: getstatic     #646                // Field zio/aws/pricing/model/GetProductsResponse$.MODULE$:Lzio/aws/pricing/model/GetProductsResponse$;
       3: aload_0
       4: invokevirtual #648                // Method zio/aws/pricing/model/GetProductsResponse$.wrap:(Lsoftware/amazon/awssdk/services/pricing/model/GetProductsResponse;)Lzio/aws/pricing/model/GetProductsResponse$ReadOnly;
       7: areturn

  public static final java.lang.String $anonfun$getProducts$8(java.lang.String);
    Code:
       0: getstatic     #655                // Field zio/prelude/Newtype$.MODULE$:Lzio/prelude/Newtype$;
       3: getstatic     #658                // Field zio/aws/pricing/model/package$primitives$PriceListItemJSON$.MODULE$:Lzio/aws/pricing/model/package$primitives$PriceListItemJSON$;
       6: aload_0
       7: invokevirtual #662                // Method zio/prelude/Newtype$.unsafeWrap:(Lzio/prelude/Newtype;Ljava/lang/Object;)Ljava/lang/Object;
      10: checkcast     #664                // class java/lang/String
      13: areturn

  public static final zio.stream.ZStream $anonfun$getProducts$7(zio.stream.ZStream);
    Code:
       0: aload_0
       1: invokedynamic #671,  0            // InvokeDynamic #30:apply:()Lscala/Function1;
       6: ldc_w         #673                // String zio.aws.pricing.Pricing.PricingImpl.getProducts(Pricing.scala:177)
       9: invokevirtual #362                // Method zio/stream/ZStream.map:(Lscala/Function1;Ljava/lang/Object;)Lzio/stream/ZStream;
      12: areturn

  public static final zio.aws.core.StreamingOutputResult $anonfun$getProducts$5(zio.aws.pricing.Pricing$PricingImpl, zio.aws.core.StreamingOutputResult);
    Code:
       0: aload_1
       1: invokedynamic #677,  0            // InvokeDynamic #31:apply:()Lscala/Function1;
       6: invokevirtual #577                // Method zio/aws/core/StreamingOutputResult.mapResponse:(Lscala/Function1;)Lzio/aws/core/StreamingOutputResult;
       9: invokedynamic #681,  0            // InvokeDynamic #32:apply:()Lscala/Function1;
      14: invokevirtual #585                // Method zio/aws/core/StreamingOutputResult.mapOutput:(Lscala/Function1;)Lzio/aws/core/StreamingOutputResult;
      17: aload_0
      18: getfield      #587                // Field r:Lzio/ZEnvironment;
      21: invokevirtual #590                // Method zio/aws/core/StreamingOutputResult.provideEnvironment:(Lzio/ZEnvironment;)Lzio/aws/core/StreamingOutputResult;
      24: areturn

  public static final zio.ZEnvironment $anonfun$getProducts$9(zio.aws.pricing.Pricing$PricingImpl);
    Code:
       0: aload_0
       1: getfield      #587                // Field r:Lzio/ZEnvironment;
       4: areturn

  public static final java.util.concurrent.CompletableFuture $anonfun$getProductsPaginated$1(zio.aws.pricing.Pricing$PricingImpl, software.amazon.awssdk.services.pricing.model.GetProductsRequest);
    Code:
       0: aload_0
       1: invokevirtual #181                // Method api:()Lsoftware/amazon/awssdk/services/pricing/PricingAsyncClient;
       4: aload_1
       5: invokeinterface #625,  2          // InterfaceMethod software/amazon/awssdk/services/pricing/PricingAsyncClient.getProducts:(Lsoftware/amazon/awssdk/services/pricing/model/GetProductsRequest;)Ljava/util/concurrent/CompletableFuture;
      10: areturn

  public static final zio.aws.pricing.model.GetProductsResponse$ReadOnly $anonfun$getProductsPaginated$2(software.amazon.awssdk.services.pricing.model.GetProductsResponse);
    Code:
       0: getstatic     #646                // Field zio/aws/pricing/model/GetProductsResponse$.MODULE$:Lzio/aws/pricing/model/GetProductsResponse$;
       3: aload_0
       4: invokevirtual #648                // Method zio/aws/pricing/model/GetProductsResponse$.wrap:(Lsoftware/amazon/awssdk/services/pricing/model/GetProductsResponse;)Lzio/aws/pricing/model/GetProductsResponse$ReadOnly;
       7: areturn

  public static final zio.ZEnvironment $anonfun$getProductsPaginated$3(zio.aws.pricing.Pricing$PricingImpl);
    Code:
       0: aload_0
       1: getfield      #587                // Field r:Lzio/ZEnvironment;
       4: areturn

  public zio.aws.pricing.Pricing$PricingImpl(software.amazon.awssdk.services.pricing.PricingAsyncClient, zio.ZIOAspect<scala.runtime.Nothing$, R, zio.aws.core.AwsError, zio.aws.core.AwsError, scala.runtime.Nothing$, zio.aws.core.aspects.package$Described<?>>, zio.ZEnvironment<R>);
    Code:
       0: aload_0
       1: aload_1
       2: putfield      #168                // Field api:Lsoftware/amazon/awssdk/services/pricing/PricingAsyncClient;
       5: aload_0
       6: aload_2
       7: putfield      #172                // Field aspect:Lzio/ZIOAspect;
      10: aload_0
      11: aload_3
      12: putfield      #587                // Field r:Lzio/ZEnvironment;
      15: aload_0
      16: invokespecial #685                // Method java/lang/Object."<init>":()V
      19: aload_0
      20: invokestatic  #689                // InterfaceMethod zio/aws/core/AwsServiceBase.$init$:(Lzio/aws/core/AwsServiceBase;)V
      23: aload_0
      24: ldc_w         #691                // String Pricing
      27: putfield      #175                // Field serviceName:Ljava/lang/String;
      30: return

  private static java.lang.Object $deserializeLambda$(java.lang.invoke.SerializedLambda);
    Code:
       0: aload_0
       1: invokedynamic #703,  0            // InvokeDynamic #33:lambdaDeserialize:(Ljava/lang/invoke/SerializedLambda;)Ljava/lang/Object;
       6: areturn
}
