Compiled from "VehicleTuning.java"
public class com.jme3.bullet.objects.infos.VehicleTuning {
  public float suspensionStiffness;

  public float suspensionCompression;

  public float suspensionDamping;

  public float maxSuspensionTravelCm;

  public float maxSuspensionForce;

  public float frictionSlip;

  public com.jme3.bullet.objects.infos.VehicleTuning();
    Code:
       0: aload_0
       1: invokespecial #1                  // Method java/lang/Object."<init>":()V
       4: aload_0
       5: ldc           #2                  // float 5.88f
       7: putfield      #3                  // Field suspensionStiffness:F
      10: aload_0
      11: ldc           #4                  // float 0.83f
      13: putfield      #5                  // Field suspensionCompression:F
      16: aload_0
      17: ldc           #6                  // float 0.88f
      19: putfield      #7                  // Field suspensionDamping:F
      22: aload_0
      23: ldc           #8                  // float 500.0f
      25: putfield      #9                  // Field maxSuspensionTravelCm:F
      28: aload_0
      29: ldc           #10                 // float 6000.0f
      31: putfield      #11                 // Field maxSuspensionForce:F
      34: aload_0
      35: ldc           #12                 // float 10.5f
      37: putfield      #13                 // Field frictionSlip:F
      40: return
}
