Compiled from "Dispatcher.java"
final class com.google.common.eventbus.Dispatcher$LegacyAsyncDispatcher$EventWithSubscriber {
  private final java.lang.Object event;

  private final com.google.common.eventbus.Subscriber subscriber;

  private com.google.common.eventbus.Dispatcher$LegacyAsyncDispatcher$EventWithSubscriber(java.lang.Object, com.google.common.eventbus.Subscriber);
    Code:
       0: aload_0
       1: invokespecial #4                  // Method java/lang/Object."<init>":()V
       4: aload_0
       5: aload_1
       6: putfield      #2                  // Field event:Ljava/lang/Object;
       9: aload_0
      10: aload_2
      11: putfield      #1                  // Field subscriber:Lcom/google/common/eventbus/Subscriber;
      14: return

  com.google.common.eventbus.Dispatcher$LegacyAsyncDispatcher$EventWithSubscriber(java.lang.Object, com.google.common.eventbus.Subscriber, com.google.common.eventbus.Dispatcher$1);
    Code:
       0: aload_0
       1: aload_1
       2: aload_2
       3: invokespecial #3                  // Method "<init>":(Ljava/lang/Object;Lcom/google/common/eventbus/Subscriber;)V
       6: return

  static java.lang.Object access$700(com.google.common.eventbus.Dispatcher$LegacyAsyncDispatcher$EventWithSubscriber);
    Code:
       0: aload_0
       1: getfield      #2                  // Field event:Ljava/lang/Object;
       4: areturn

  static com.google.common.eventbus.Subscriber access$800(com.google.common.eventbus.Dispatcher$LegacyAsyncDispatcher$EventWithSubscriber);
    Code:
       0: aload_0
       1: getfield      #1                  // Field subscriber:Lcom/google/common/eventbus/Subscriber;
       4: areturn
}
