final class org.bouncycastle.jcajce.provider.drbg.DRBG$3 implements java.security.PrivilegedAction<org.bouncycastle.crypto.prng.EntropySourceProvider> {
  final java.lang.String val$sourceClass;

  org.bouncycastle.jcajce.provider.drbg.DRBG$3(java.lang.String);
    Code:
       0: aload_0
       1: aload_1
       2: putfield      #54                 // Field val$sourceClass:Ljava/lang/String;
       5: aload_0
       6: invokespecial #58                 // Method java/lang/Object."<init>":()V
       9: return

  public org.bouncycastle.crypto.prng.EntropySourceProvider run();
    Code:
       0: ldc           #3                  // class org/bouncycastle/jcajce/provider/drbg/DRBG
       2: aload_0
       3: getfield      #54                 // Field val$sourceClass:Ljava/lang/String;
       6: invokestatic  #63                 // Method org/bouncycastle/jcajce/provider/symmetric/util/ClassUtil.loadClass:(Ljava/lang/Class;Ljava/lang/String;)Ljava/lang/Class;
       9: astore_1
      10: aload_1
      11: invokevirtual #55                 // Method java/lang/Class.newInstance:()Ljava/lang/Object;
      14: checkcast     #32                 // class org/bouncycastle/crypto/prng/EntropySourceProvider
      17: areturn
      18: astore_1
      19: new           #28                 // class java/lang/IllegalStateException
      22: dup
      23: new           #30                 // class java/lang/StringBuilder
      26: dup
      27: invokespecial #59                 // Method java/lang/StringBuilder."<init>":()V
      30: ldc           #2                  // String entropy source
      32: invokevirtual #61                 // Method java/lang/StringBuilder.append:(Ljava/lang/String;)Ljava/lang/StringBuilder;
      35: aload_0
      36: getfield      #54                 // Field val$sourceClass:Ljava/lang/String;
      39: invokevirtual #61                 // Method java/lang/StringBuilder.append:(Ljava/lang/String;)Ljava/lang/StringBuilder;
      42: ldc           #1                  // String  not created:
      44: invokevirtual #61                 // Method java/lang/StringBuilder.append:(Ljava/lang/String;)Ljava/lang/StringBuilder;
      47: aload_1
      48: invokevirtual #56                 // Method java/lang/Exception.getMessage:()Ljava/lang/String;
      51: invokevirtual #61                 // Method java/lang/StringBuilder.append:(Ljava/lang/String;)Ljava/lang/StringBuilder;
      54: invokevirtual #60                 // Method java/lang/StringBuilder.toString:()Ljava/lang/String;
      57: aload_1
      58: invokespecial #57                 // Method java/lang/IllegalStateException."<init>":(Ljava/lang/String;Ljava/lang/Throwable;)V
      61: athrow
    Exception table:
       from    to  target type
           0    17    18   Class java/lang/Exception

  public java.lang.Object run();
    Code:
       0: aload_0
       1: invokevirtual #62                 // Method run:()Lorg/bouncycastle/crypto/prng/EntropySourceProvider;
       4: areturn
}
