Compiled from "StringCachedClass.java"
public class org.codehaus.groovy.reflection.stdclasses.StringCachedClass extends org.codehaus.groovy.reflection.CachedClass {
  private static final java.lang.Class STRING_CLASS;

  private static final java.lang.Class GSTRING_CLASS;

  public org.codehaus.groovy.reflection.stdclasses.StringCachedClass(org.codehaus.groovy.reflection.ClassInfo);
    Code:
       0: aload_0
       1: getstatic     #12                 // Field STRING_CLASS:Ljava/lang/Class;
       4: aload_1
       5: invokespecial #15                 // Method org/codehaus/groovy/reflection/CachedClass."<init>":(Ljava/lang/Class;Lorg/codehaus/groovy/reflection/ClassInfo;)V
       8: return

  public boolean isDirectlyAssignable(java.lang.Object);
    Code:
       0: aload_1
       1: instanceof    #23                 // class java/lang/String
       4: ireturn

  public boolean isAssignableFrom(java.lang.Class);
    Code:
       0: aload_1
       1: ifnull        21
       4: aload_1
       5: getstatic     #12                 // Field STRING_CLASS:Ljava/lang/Class;
       8: if_acmpeq     21
      11: getstatic     #29                 // Field GSTRING_CLASS:Ljava/lang/Class;
      14: aload_1
      15: invokestatic  #34                 // Method org/codehaus/groovy/reflection/ReflectionCache.isAssignableFrom:(Ljava/lang/Class;Ljava/lang/Class;)Z
      18: ifeq          25
      21: iconst_1
      22: goto          26
      25: iconst_0
      26: ireturn

  public java.lang.Object coerceArgument(java.lang.Object);
    Code:
       0: aload_1
       1: instanceof    #39                 // class groovy/lang/GString
       4: ifeq          14
       7: aload_1
       8: invokevirtual #45                 // Method java/lang/Object.toString:()Ljava/lang/String;
      11: goto          15
      14: aload_1
      15: areturn

  static {};
    Code:
       0: ldc           #23                 // class java/lang/String
       2: putstatic     #12                 // Field STRING_CLASS:Ljava/lang/Class;
       5: ldc           #39                 // class groovy/lang/GString
       7: putstatic     #29                 // Field GSTRING_CLASS:Ljava/lang/Class;
      10: return
}
