Compiled from "JmxBuilderModelMBean.java"
public class groovy.jmx.builder.JmxBuilderModelMBean extends javax.management.modelmbean.RequiredModelMBean implements javax.management.NotificationListener {
  private java.util.List<java.lang.String> methodListeners;

  private java.lang.Object managedObject;

  public groovy.jmx.builder.JmxBuilderModelMBean(java.lang.Object) throws javax.management.MBeanException, javax.management.RuntimeOperationsException, javax.management.InstanceNotFoundException, javax.management.modelmbean.InvalidTargetObjectTypeException;
    Code:
       0: aload_0
       1: invokespecial #36                 // Method javax/management/modelmbean/RequiredModelMBean."<init>":()V
       4: aload_0
       5: new           #38                 // class java/util/ArrayList
       8: dup
       9: iconst_0
      10: invokespecial #41                 // Method java/util/ArrayList."<init>":(I)V
      13: putfield      #43                 // Field methodListeners:Ljava/util/List;
      16: aload_0
      17: aload_1
      18: ldc           #45                 // String ObjectReference
      20: invokespecial #49                 // Method javax/management/modelmbean/RequiredModelMBean.setManagedResource:(Ljava/lang/Object;Ljava/lang/String;)V
      23: return

  public groovy.jmx.builder.JmxBuilderModelMBean() throws javax.management.MBeanException, javax.management.RuntimeOperationsException;
    Code:
       0: aload_0
       1: invokespecial #36                 // Method javax/management/modelmbean/RequiredModelMBean."<init>":()V
       4: aload_0
       5: new           #38                 // class java/util/ArrayList
       8: dup
       9: iconst_0
      10: invokespecial #41                 // Method java/util/ArrayList."<init>":(I)V
      13: putfield      #43                 // Field methodListeners:Ljava/util/List;
      16: return

  public groovy.jmx.builder.JmxBuilderModelMBean(javax.management.modelmbean.ModelMBeanInfo) throws javax.management.MBeanException, javax.management.RuntimeOperationsException;
    Code:
       0: aload_0
       1: aload_1
       2: invokespecial #55                 // Method javax/management/modelmbean/RequiredModelMBean."<init>":(Ljavax/management/modelmbean/ModelMBeanInfo;)V
       5: aload_0
       6: new           #38                 // class java/util/ArrayList
       9: dup
      10: iconst_0
      11: invokespecial #41                 // Method java/util/ArrayList."<init>":(I)V
      14: putfield      #43                 // Field methodListeners:Ljava/util/List;
      17: return

  public synchronized void setManagedResource(java.lang.Object);
    Code:
       0: aload_0
       1: aload_1
       2: putfield      #61                 // Field managedObject:Ljava/lang/Object;
       5: aload_0
       6: aload_1
       7: ldc           #45                 // String ObjectReference
       9: invokespecial #49                 // Method javax/management/modelmbean/RequiredModelMBean.setManagedResource:(Ljava/lang/Object;Ljava/lang/String;)V
      12: goto          25
      15: astore_2
      16: new           #63                 // class groovy/jmx/builder/JmxBuilderException
      19: dup
      20: aload_2
      21: invokespecial #66                 // Method groovy/jmx/builder/JmxBuilderException."<init>":(Ljava/lang/Throwable;)V
      24: athrow
      25: return
    Exception table:
       from    to  target type
           5    12    15   Class java/lang/Exception

  public void addOperationCallListeners(java.util.Map<java.lang.String, java.util.Map<java.lang.String, java.util.Map<java.lang.String, java.lang.Object>>>);
    Code:
       0: aload_1
       1: ifnonnull     5
       4: return
       5: aload_1
       6: invokeinterface #75,  1           // InterfaceMethod java/util/Map.entrySet:()Ljava/util/Set;
      11: invokeinterface #81,  1           // InterfaceMethod java/util/Set.iterator:()Ljava/util/Iterator;
      16: astore_2
      17: aload_2
      18: invokeinterface #87,  1           // InterfaceMethod java/util/Iterator.hasNext:()Z
      23: ifeq          238
      26: aload_2
      27: invokeinterface #91,  1           // InterfaceMethod java/util/Iterator.next:()Ljava/lang/Object;
      32: checkcast     #15                 // class java/util/Map$Entry
      35: astore_3
      36: aload_3
      37: invokeinterface #94,  1           // InterfaceMethod java/util/Map$Entry.getValue:()Ljava/lang/Object;
      42: checkcast     #17                 // class java/util/Map
      45: ldc           #96                 // String methodListener
      47: invokeinterface #100,  2          // InterfaceMethod java/util/Map.containsKey:(Ljava/lang/Object;)Z
      52: ifeq          235
      55: aload_3
      56: invokeinterface #94,  1           // InterfaceMethod java/util/Map$Entry.getValue:()Ljava/lang/Object;
      61: checkcast     #17                 // class java/util/Map
      64: ldc           #96                 // String methodListener
      66: invokeinterface #104,  2          // InterfaceMethod java/util/Map.get:(Ljava/lang/Object;)Ljava/lang/Object;
      71: checkcast     #17                 // class java/util/Map
      74: astore        4
      76: aload         4
      78: ldc           #106                // String target
      80: invokeinterface #104,  2          // InterfaceMethod java/util/Map.get:(Ljava/lang/Object;)Ljava/lang/Object;
      85: checkcast     #108                // class java/lang/String
      88: astore        5
      90: aload_0
      91: getfield      #43                 // Field methodListeners:Ljava/util/List;
      94: aload         5
      96: invokeinterface #113,  2          // InterfaceMethod java/util/List.add:(Ljava/lang/Object;)Z
     101: pop
     102: aload         4
     104: ldc           #115                // String type
     106: invokeinterface #104,  2          // InterfaceMethod java/util/Map.get:(Ljava/lang/Object;)Ljava/lang/Object;
     111: checkcast     #108                // class java/lang/String
     114: astore        6
     116: aload         4
     118: ldc           #116                // String managedObject
     120: aload_0
     121: getfield      #61                 // Field managedObject:Ljava/lang/Object;
     124: invokeinterface #120,  3          // InterfaceMethod java/util/Map.put:(Ljava/lang/Object;Ljava/lang/Object;)Ljava/lang/Object;
     129: pop
     130: aload         6
     132: ldc           #122                // String attributeChangeListener
     134: invokevirtual #125                // Method java/lang/String.equals:(Ljava/lang/Object;)Z
     137: ifeq          176
     140: aload_0
     141: invokestatic  #129                // Method groovy/jmx/builder/JmxBuilderModelMBean$AttributeChangedListener.getListener:()Lgroovy/jmx/builder/JmxBuilderModelMBean$AttributeChangedListener;
     144: aload         4
     146: ldc           #131                // String attribute
     148: invokeinterface #104,  2          // InterfaceMethod java/util/Map.get:(Ljava/lang/Object;)Ljava/lang/Object;
     153: checkcast     #108                // class java/lang/String
     156: aload         4
     158: invokevirtual #135                // Method addAttributeChangeNotificationListener:(Ljavax/management/NotificationListener;Ljava/lang/String;Ljava/lang/Object;)V
     161: goto          176
     164: astore        7
     166: new           #63                 // class groovy/jmx/builder/JmxBuilderException
     169: dup
     170: aload         7
     172: invokespecial #66                 // Method groovy/jmx/builder/JmxBuilderException."<init>":(Ljava/lang/Throwable;)V
     175: athrow
     176: aload         6
     178: ldc           #137                // String operationCallListener
     180: invokevirtual #125                // Method java/lang/String.equals:(Ljava/lang/Object;)Z
     183: ifeq          235
     186: new           #139                // class java/lang/StringBuilder
     189: dup
     190: invokespecial #140                // Method java/lang/StringBuilder."<init>":()V
     193: ldc           #142                // String jmx.operation.call.
     195: invokevirtual #146                // Method java/lang/StringBuilder.append:(Ljava/lang/String;)Ljava/lang/StringBuilder;
     198: aload         5
     200: invokevirtual #146                // Method java/lang/StringBuilder.append:(Ljava/lang/String;)Ljava/lang/StringBuilder;
     203: invokevirtual #150                // Method java/lang/StringBuilder.toString:()Ljava/lang/String;
     206: astore        7
     208: new           #152                // class javax/management/NotificationFilterSupport
     211: dup
     212: invokespecial #153                // Method javax/management/NotificationFilterSupport."<init>":()V
     215: astore        8
     217: aload         8
     219: aload         7
     221: invokevirtual #157                // Method javax/management/NotificationFilterSupport.enableType:(Ljava/lang/String;)V
     224: aload_0
     225: invokestatic  #162                // Method groovy/jmx/builder/JmxEventListener.getListener:()Lgroovy/jmx/builder/JmxEventListener;
     228: aload         8
     230: aload         4
     232: invokevirtual #166                // Method addNotificationListener:(Ljavax/management/NotificationListener;Ljavax/management/NotificationFilter;Ljava/lang/Object;)V
     235: goto          17
     238: return
    Exception table:
       from    to  target type
         140   161   164   Class javax/management/MBeanException

  public void addEventListeners(javax.management.MBeanServer, java.util.Map<java.lang.String, java.util.Map<java.lang.String, java.lang.Object>>);
    Code:
       0: aload_2
       1: invokeinterface #75,  1           // InterfaceMethod java/util/Map.entrySet:()Ljava/util/Set;
       6: invokeinterface #81,  1           // InterfaceMethod java/util/Set.iterator:()Ljava/util/Iterator;
      11: astore_3
      12: aload_3
      13: invokeinterface #87,  1           // InterfaceMethod java/util/Iterator.hasNext:()Z
      18: ifeq          143
      21: aload_3
      22: invokeinterface #91,  1           // InterfaceMethod java/util/Iterator.next:()Ljava/lang/Object;
      27: checkcast     #15                 // class java/util/Map$Entry
      30: astore        4
      32: aload         4
      34: invokeinterface #94,  1           // InterfaceMethod java/util/Map$Entry.getValue:()Ljava/lang/Object;
      39: checkcast     #17                 // class java/util/Map
      42: astore        5
      44: aload         5
      46: ldc           #185                // String from
      48: invokeinterface #104,  2          // InterfaceMethod java/util/Map.get:(Ljava/lang/Object;)Ljava/lang/Object;
      53: checkcast     #187                // class javax/management/ObjectName
      56: astore        6
      58: aload         5
      60: ldc           #189                // String event
      62: invokeinterface #104,  2          // InterfaceMethod java/util/Map.get:(Ljava/lang/Object;)Ljava/lang/Object;
      67: checkcast     #108                // class java/lang/String
      70: astore        7
      72: aload         7
      74: ifnull        111
      77: new           #152                // class javax/management/NotificationFilterSupport
      80: dup
      81: invokespecial #153                // Method javax/management/NotificationFilterSupport."<init>":()V
      84: astore        8
      86: aload         8
      88: aload         7
      90: invokevirtual #157                // Method javax/management/NotificationFilterSupport.enableType:(Ljava/lang/String;)V
      93: aload_1
      94: aload         6
      96: invokestatic  #162                // Method groovy/jmx/builder/JmxEventListener.getListener:()Lgroovy/jmx/builder/JmxEventListener;
      99: aload         8
     101: aload         5
     103: invokeinterface #194,  5          // InterfaceMethod javax/management/MBeanServer.addNotificationListener:(Ljavax/management/ObjectName;Ljavax/management/NotificationListener;Ljavax/management/NotificationFilter;Ljava/lang/Object;)V
     108: goto          125
     111: aload_1
     112: aload         6
     114: invokestatic  #162                // Method groovy/jmx/builder/JmxEventListener.getListener:()Lgroovy/jmx/builder/JmxEventListener;
     117: aconst_null
     118: aload         5
     120: invokeinterface #194,  5          // InterfaceMethod javax/management/MBeanServer.addNotificationListener:(Ljavax/management/ObjectName;Ljavax/management/NotificationListener;Ljavax/management/NotificationFilter;Ljava/lang/Object;)V
     125: goto          140
     128: astore        7
     130: new           #63                 // class groovy/jmx/builder/JmxBuilderException
     133: dup
     134: aload         7
     136: invokespecial #66                 // Method groovy/jmx/builder/JmxBuilderException."<init>":(Ljava/lang/Throwable;)V
     139: athrow
     140: goto          12
     143: return
    Exception table:
       from    to  target type
          58   125   128   Class javax/management/InstanceNotFoundException

  public java.lang.Object invoke(java.lang.String, java.lang.Object[], java.lang.String[]) throws javax.management.MBeanException, javax.management.ReflectionException;
    Code:
       0: aload_0
       1: aload_1
       2: aload_2
       3: aload_3
       4: invokespecial #207                // Method javax/management/modelmbean/RequiredModelMBean.invoke:(Ljava/lang/String;[Ljava/lang/Object;[Ljava/lang/String;)Ljava/lang/Object;
       7: astore        4
       9: aload_0
      10: getfield      #43                 // Field methodListeners:Ljava/util/List;
      13: aload_1
      14: invokeinterface #210,  2          // InterfaceMethod java/util/List.contains:(Ljava/lang/Object;)Z
      19: ifeq          31
      22: aload_0
      23: aload_0
      24: aload_1
      25: invokespecial #214                // Method buildCallListenerNotification:(Ljava/lang/String;)Ljavax/management/Notification;
      28: invokevirtual #218                // Method sendNotification:(Ljavax/management/Notification;)V
      31: aload         4
      33: areturn

  public void handleNotification(javax.management.Notification, java.lang.Object);
    Code:
       0: return

  private javax.management.Notification buildCallListenerNotification(java.lang.String);
    Code:
       0: new           #233                // class javax/management/Notification
       3: dup
       4: new           #139                // class java/lang/StringBuilder
       7: dup
       8: invokespecial #140                // Method java/lang/StringBuilder."<init>":()V
      11: ldc           #142                // String jmx.operation.call.
      13: invokevirtual #146                // Method java/lang/StringBuilder.append:(Ljava/lang/String;)Ljava/lang/StringBuilder;
      16: aload_1
      17: invokevirtual #146                // Method java/lang/StringBuilder.append:(Ljava/lang/String;)Ljava/lang/StringBuilder;
      20: invokevirtual #150                // Method java/lang/StringBuilder.toString:()Ljava/lang/String;
      23: aload_0
      24: invokestatic  #237                // Method groovy/jmx/builder/JmxBuilderModelMBean$NumberSequencer.getNextSequence:()J
      27: invokestatic  #242                // Method java/lang/System.currentTimeMillis:()J
      30: invokespecial #245                // Method javax/management/Notification."<init>":(Ljava/lang/String;Ljava/lang/Object;JJ)V
      33: areturn
}
