Compiled from "DocBookCodeGenerator.java"
public class antlr.DocBookCodeGenerator extends antlr.CodeGenerator {
  protected int syntacticPredLevel;

  protected boolean doingLexRules;

  protected boolean firstElementInAlt;

  protected antlr.AlternativeElement prevAltElem;

  public antlr.DocBookCodeGenerator();
    Code:
       0: aload_0
       1: invokespecial #1                  // Method antlr/CodeGenerator."<init>":()V
       4: aload_0
       5: iconst_0
       6: putfield      #2                  // Field syntacticPredLevel:I
       9: aload_0
      10: iconst_0
      11: putfield      #3                  // Field doingLexRules:Z
      14: aload_0
      15: aconst_null
      16: putfield      #4                  // Field prevAltElem:Lantlr/AlternativeElement;
      19: aload_0
      20: new           #5                  // class antlr/JavaCharFormatter
      23: dup
      24: invokespecial #6                  // Method antlr/JavaCharFormatter."<init>":()V
      27: putfield      #7                  // Field charFormatter:Lantlr/CharFormatter;
      30: return

  static java.lang.String HTMLEncode(java.lang.String);
    Code:
       0: new           #8                  // class java/lang/StringBuffer
       3: dup
       4: invokespecial #9                  // Method java/lang/StringBuffer."<init>":()V
       7: astore_1
       8: iconst_0
       9: istore_2
      10: aload_0
      11: invokevirtual #10                 // Method java/lang/String.length:()I
      14: istore_3
      15: iload_2
      16: iload_3
      17: if_icmpge     125
      20: aload_0
      21: iload_2
      22: invokevirtual #11                 // Method java/lang/String.charAt:(I)C
      25: istore        4
      27: iload         4
      29: bipush        38
      31: if_icmpne     44
      34: aload_1
      35: ldc           #12                 // String &amp;
      37: invokevirtual #13                 // Method java/lang/StringBuffer.append:(Ljava/lang/String;)Ljava/lang/StringBuffer;
      40: pop
      41: goto          119
      44: iload         4
      46: bipush        34
      48: if_icmpne     61
      51: aload_1
      52: ldc           #14                 // String &quot;
      54: invokevirtual #13                 // Method java/lang/StringBuffer.append:(Ljava/lang/String;)Ljava/lang/StringBuffer;
      57: pop
      58: goto          119
      61: iload         4
      63: bipush        39
      65: if_icmpne     78
      68: aload_1
      69: ldc           #15                 // String &#039;
      71: invokevirtual #13                 // Method java/lang/StringBuffer.append:(Ljava/lang/String;)Ljava/lang/StringBuffer;
      74: pop
      75: goto          119
      78: iload         4
      80: bipush        60
      82: if_icmpne     95
      85: aload_1
      86: ldc           #16                 // String &lt;
      88: invokevirtual #13                 // Method java/lang/StringBuffer.append:(Ljava/lang/String;)Ljava/lang/StringBuffer;
      91: pop
      92: goto          119
      95: iload         4
      97: bipush        62
      99: if_icmpne     112
     102: aload_1
     103: ldc           #17                 // String &gt;
     105: invokevirtual #13                 // Method java/lang/StringBuffer.append:(Ljava/lang/String;)Ljava/lang/StringBuffer;
     108: pop
     109: goto          119
     112: aload_1
     113: iload         4
     115: invokevirtual #18                 // Method java/lang/StringBuffer.append:(C)Ljava/lang/StringBuffer;
     118: pop
     119: iinc          2, 1
     122: goto          15
     125: aload_1
     126: invokevirtual #19                 // Method java/lang/StringBuffer.toString:()Ljava/lang/String;
     129: areturn

  static java.lang.String QuoteForId(java.lang.String);
    Code:
       0: new           #8                  // class java/lang/StringBuffer
       3: dup
       4: invokespecial #9                  // Method java/lang/StringBuffer."<init>":()V
       7: astore_1
       8: iconst_0
       9: istore_2
      10: aload_0
      11: invokevirtual #10                 // Method java/lang/String.length:()I
      14: istore_3
      15: iload_2
      16: iload_3
      17: if_icmpge     57
      20: aload_0
      21: iload_2
      22: invokevirtual #11                 // Method java/lang/String.charAt:(I)C
      25: istore        4
      27: iload         4
      29: bipush        95
      31: if_icmpne     44
      34: aload_1
      35: ldc           #20                 // String .
      37: invokevirtual #13                 // Method java/lang/StringBuffer.append:(Ljava/lang/String;)Ljava/lang/StringBuffer;
      40: pop
      41: goto          51
      44: aload_1
      45: iload         4
      47: invokevirtual #18                 // Method java/lang/StringBuffer.append:(C)Ljava/lang/StringBuffer;
      50: pop
      51: iinc          2, 1
      54: goto          15
      57: aload_1
      58: invokevirtual #19                 // Method java/lang/StringBuffer.toString:()Ljava/lang/String;
      61: areturn

  public void gen();
    Code:
       0: aload_0
       1: getfield      #21                 // Field behavior:Lantlr/DefineGrammarSymbols;
       4: getfield      #22                 // Field antlr/DefineGrammarSymbols.grammars:Ljava/util/Hashtable;
       7: invokevirtual #23                 // Method java/util/Hashtable.elements:()Ljava/util/Enumeration;
      10: astore_1
      11: aload_1
      12: invokeinterface #24,  1           // InterfaceMethod java/util/Enumeration.hasMoreElements:()Z
      17: ifeq          61
      20: aload_1
      21: invokeinterface #25,  1           // InterfaceMethod java/util/Enumeration.nextElement:()Ljava/lang/Object;
      26: checkcast     #26                 // class antlr/Grammar
      29: astore_2
      30: aload_2
      31: aload_0
      32: invokevirtual #27                 // Method antlr/Grammar.setCodeGenerator:(Lantlr/CodeGenerator;)V
      35: aload_2
      36: invokevirtual #28                 // Method antlr/Grammar.generate:()V
      39: aload_0
      40: getfield      #29                 // Field antlrTool:Lantlr/Tool;
      43: invokevirtual #30                 // Method antlr/Tool.hasError:()Z
      46: ifeq          11
      49: aload_0
      50: getfield      #29                 // Field antlrTool:Lantlr/Tool;
      53: ldc           #31                 // String Exiting due to errors.
      55: invokevirtual #32                 // Method antlr/Tool.fatalError:(Ljava/lang/String;)V
      58: goto          11
      61: goto          74
      64: astore_1
      65: aload_0
      66: getfield      #29                 // Field antlrTool:Lantlr/Tool;
      69: aload_1
      70: aconst_null
      71: invokevirtual #34                 // Method antlr/Tool.reportException:(Ljava/lang/Exception;Ljava/lang/String;)V
      74: return
    Exception table:
       from    to  target type
           0    61    64   Class java/io/IOException

  public void gen(antlr.ActionElement);
    Code:
       0: return

  public void gen(antlr.AlternativeBlock);
    Code:
       0: aload_0
       1: aload_1
       2: ldc           #35                 // String
       4: invokevirtual #36                 // Method genGenericBlock:(Lantlr/AlternativeBlock;Ljava/lang/String;)V
       7: return

  public void gen(antlr.BlockEndElement);
    Code:
       0: return

  public void gen(antlr.CharLiteralElement);
    Code:
       0: aload_1
       1: getfield      #37                 // Field antlr/CharLiteralElement.not:Z
       4: ifeq          13
       7: aload_0
       8: ldc           #38                 // String ~
      10: invokevirtual #39                 // Method _print:(Ljava/lang/String;)V
      13: aload_0
      14: new           #8                  // class java/lang/StringBuffer
      17: dup
      18: invokespecial #9                  // Method java/lang/StringBuffer."<init>":()V
      21: aload_1
      22: getfield      #40                 // Field antlr/CharLiteralElement.atomText:Ljava/lang/String;
      25: invokestatic  #41                 // Method HTMLEncode:(Ljava/lang/String;)Ljava/lang/String;
      28: invokevirtual #13                 // Method java/lang/StringBuffer.append:(Ljava/lang/String;)Ljava/lang/StringBuffer;
      31: ldc           #42                 // String
      33: invokevirtual #13                 // Method java/lang/StringBuffer.append:(Ljava/lang/String;)Ljava/lang/StringBuffer;
      36: invokevirtual #19                 // Method java/lang/StringBuffer.toString:()Ljava/lang/String;
      39: invokevirtual #39                 // Method _print:(Ljava/lang/String;)V
      42: return

  public void gen(antlr.CharRangeElement);
    Code:
       0: aload_0
       1: new           #8                  // class java/lang/StringBuffer
       4: dup
       5: invokespecial #9                  // Method java/lang/StringBuffer."<init>":()V
       8: aload_1
       9: getfield      #43                 // Field antlr/CharRangeElement.beginText:Ljava/lang/String;
      12: invokevirtual #13                 // Method java/lang/StringBuffer.append:(Ljava/lang/String;)Ljava/lang/StringBuffer;
      15: ldc           #44                 // String ..
      17: invokevirtual #13                 // Method java/lang/StringBuffer.append:(Ljava/lang/String;)Ljava/lang/StringBuffer;
      20: aload_1
      21: getfield      #45                 // Field antlr/CharRangeElement.endText:Ljava/lang/String;
      24: invokevirtual #13                 // Method java/lang/StringBuffer.append:(Ljava/lang/String;)Ljava/lang/StringBuffer;
      27: ldc           #42                 // String
      29: invokevirtual #13                 // Method java/lang/StringBuffer.append:(Ljava/lang/String;)Ljava/lang/StringBuffer;
      32: invokevirtual #19                 // Method java/lang/StringBuffer.toString:()Ljava/lang/String;
      35: invokevirtual #46                 // Method print:(Ljava/lang/String;)V
      38: return

  public void gen(antlr.LexerGrammar) throws java.io.IOException;
    Code:
       0: aload_0
       1: aload_1
       2: invokevirtual #47                 // Method setGrammar:(Lantlr/Grammar;)V
       5: aload_0
       6: getfield      #29                 // Field antlrTool:Lantlr/Tool;
       9: new           #8                  // class java/lang/StringBuffer
      12: dup
      13: invokespecial #9                  // Method java/lang/StringBuffer."<init>":()V
      16: ldc           #48                 // String Generating
      18: invokevirtual #13                 // Method java/lang/StringBuffer.append:(Ljava/lang/String;)Ljava/lang/StringBuffer;
      21: aload_0
      22: getfield      #49                 // Field grammar:Lantlr/Grammar;
      25: invokevirtual #50                 // Method antlr/Grammar.getClassName:()Ljava/lang/String;
      28: invokevirtual #13                 // Method java/lang/StringBuffer.append:(Ljava/lang/String;)Ljava/lang/StringBuffer;
      31: ldc           #51                 // String .sgml
      33: invokevirtual #13                 // Method java/lang/StringBuffer.append:(Ljava/lang/String;)Ljava/lang/StringBuffer;
      36: invokevirtual #19                 // Method java/lang/StringBuffer.toString:()Ljava/lang/String;
      39: invokevirtual #52                 // Method antlr/Tool.reportProgress:(Ljava/lang/String;)V
      42: aload_0
      43: aload_0
      44: getfield      #29                 // Field antlrTool:Lantlr/Tool;
      47: new           #8                  // class java/lang/StringBuffer
      50: dup
      51: invokespecial #9                  // Method java/lang/StringBuffer."<init>":()V
      54: aload_0
      55: getfield      #49                 // Field grammar:Lantlr/Grammar;
      58: invokevirtual #50                 // Method antlr/Grammar.getClassName:()Ljava/lang/String;
      61: invokevirtual #13                 // Method java/lang/StringBuffer.append:(Ljava/lang/String;)Ljava/lang/StringBuffer;
      64: ldc           #51                 // String .sgml
      66: invokevirtual #13                 // Method java/lang/StringBuffer.append:(Ljava/lang/String;)Ljava/lang/StringBuffer;
      69: invokevirtual #19                 // Method java/lang/StringBuffer.toString:()Ljava/lang/String;
      72: invokevirtual #53                 // Method antlr/Tool.openOutputFile:(Ljava/lang/String;)Ljava/io/PrintWriter;
      75: putfield      #54                 // Field currentOutput:Ljava/io/PrintWriter;
      78: aload_0
      79: iconst_0
      80: putfield      #55                 // Field tabs:I
      83: aload_0
      84: iconst_1
      85: putfield      #3                  // Field doingLexRules:Z
      88: aload_0
      89: invokevirtual #56                 // Method genHeader:()V
      92: aload_0
      93: ldc           #35                 // String
      95: invokevirtual #57                 // Method println:(Ljava/lang/String;)V
      98: aload_0
      99: getfield      #49                 // Field grammar:Lantlr/Grammar;
     102: getfield      #58                 // Field antlr/Grammar.comment:Ljava/lang/String;
     105: ifnull        122
     108: aload_0
     109: aload_0
     110: getfield      #49                 // Field grammar:Lantlr/Grammar;
     113: getfield      #58                 // Field antlr/Grammar.comment:Ljava/lang/String;
     116: invokestatic  #41                 // Method HTMLEncode:(Ljava/lang/String;)Ljava/lang/String;
     119: invokevirtual #59                 // Method _println:(Ljava/lang/String;)V
     122: aload_0
     123: new           #8                  // class java/lang/StringBuffer
     126: dup
     127: invokespecial #9                  // Method java/lang/StringBuffer."<init>":()V
     130: ldc           #60                 // String <para>Definition of lexer
     132: invokevirtual #13                 // Method java/lang/StringBuffer.append:(Ljava/lang/String;)Ljava/lang/StringBuffer;
     135: aload_0
     136: getfield      #49                 // Field grammar:Lantlr/Grammar;
     139: invokevirtual #50                 // Method antlr/Grammar.getClassName:()Ljava/lang/String;
     142: invokevirtual #13                 // Method java/lang/StringBuffer.append:(Ljava/lang/String;)Ljava/lang/StringBuffer;
     145: ldc           #61                 // String , which is a subclass of
     147: invokevirtual #13                 // Method java/lang/StringBuffer.append:(Ljava/lang/String;)Ljava/lang/StringBuffer;
     150: aload_0
     151: getfield      #49                 // Field grammar:Lantlr/Grammar;
     154: invokevirtual #62                 // Method antlr/Grammar.getSuperClass:()Ljava/lang/String;
     157: invokevirtual #13                 // Method java/lang/StringBuffer.append:(Ljava/lang/String;)Ljava/lang/StringBuffer;
     160: ldc           #63                 // String .</para>
     162: invokevirtual #13                 // Method java/lang/StringBuffer.append:(Ljava/lang/String;)Ljava/lang/StringBuffer;
     165: invokevirtual #19                 // Method java/lang/StringBuffer.toString:()Ljava/lang/String;
     168: invokevirtual #57                 // Method println:(Ljava/lang/String;)V
     171: aload_0
     172: invokevirtual #64                 // Method genNextToken:()V
     175: aload_0
     176: getfield      #49                 // Field grammar:Lantlr/Grammar;
     179: getfield      #65                 // Field antlr/Grammar.rules:Lantlr/collections/impl/Vector;
     182: invokevirtual #66                 // Method antlr/collections/impl/Vector.elements:()Ljava/util/Enumeration;
     185: astore_2
     186: aload_2
     187: invokeinterface #24,  1           // InterfaceMethod java/util/Enumeration.hasMoreElements:()Z
     192: ifeq          225
     195: aload_2
     196: invokeinterface #25,  1           // InterfaceMethod java/util/Enumeration.nextElement:()Ljava/lang/Object;
     201: checkcast     #67                 // class antlr/RuleSymbol
     204: astore_3
     205: aload_3
     206: getfield      #68                 // Field antlr/RuleSymbol.id:Ljava/lang/String;
     209: ldc           #69                 // String mnextToken
     211: invokevirtual #70                 // Method java/lang/String.equals:(Ljava/lang/Object;)Z
     214: ifne          186
     217: aload_0
     218: aload_3
     219: invokevirtual #71                 // Method genRule:(Lantlr/RuleSymbol;)V
     222: goto          186
     225: aload_0
     226: getfield      #54                 // Field currentOutput:Ljava/io/PrintWriter;
     229: invokevirtual #72                 // Method java/io/PrintWriter.close:()V
     232: aload_0
     233: aconst_null
     234: putfield      #54                 // Field currentOutput:Ljava/io/PrintWriter;
     237: aload_0
     238: iconst_0
     239: putfield      #3                  // Field doingLexRules:Z
     242: return

  public void gen(antlr.OneOrMoreBlock);
    Code:
       0: aload_0
       1: aload_1
       2: ldc           #73                 // String +
       4: invokevirtual #36                 // Method genGenericBlock:(Lantlr/AlternativeBlock;Ljava/lang/String;)V
       7: return

  public void gen(antlr.ParserGrammar) throws java.io.IOException;
    Code:
       0: aload_0
       1: aload_1
       2: invokevirtual #47                 // Method setGrammar:(Lantlr/Grammar;)V
       5: aload_0
       6: getfield      #29                 // Field antlrTool:Lantlr/Tool;
       9: new           #8                  // class java/lang/StringBuffer
      12: dup
      13: invokespecial #9                  // Method java/lang/StringBuffer."<init>":()V
      16: ldc           #48                 // String Generating
      18: invokevirtual #13                 // Method java/lang/StringBuffer.append:(Ljava/lang/String;)Ljava/lang/StringBuffer;
      21: aload_0
      22: getfield      #49                 // Field grammar:Lantlr/Grammar;
      25: invokevirtual #50                 // Method antlr/Grammar.getClassName:()Ljava/lang/String;
      28: invokevirtual #13                 // Method java/lang/StringBuffer.append:(Ljava/lang/String;)Ljava/lang/StringBuffer;
      31: ldc           #51                 // String .sgml
      33: invokevirtual #13                 // Method java/lang/StringBuffer.append:(Ljava/lang/String;)Ljava/lang/StringBuffer;
      36: invokevirtual #19                 // Method java/lang/StringBuffer.toString:()Ljava/lang/String;
      39: invokevirtual #52                 // Method antlr/Tool.reportProgress:(Ljava/lang/String;)V
      42: aload_0
      43: aload_0
      44: getfield      #29                 // Field antlrTool:Lantlr/Tool;
      47: new           #8                  // class java/lang/StringBuffer
      50: dup
      51: invokespecial #9                  // Method java/lang/StringBuffer."<init>":()V
      54: aload_0
      55: getfield      #49                 // Field grammar:Lantlr/Grammar;
      58: invokevirtual #50                 // Method antlr/Grammar.getClassName:()Ljava/lang/String;
      61: invokevirtual #13                 // Method java/lang/StringBuffer.append:(Ljava/lang/String;)Ljava/lang/StringBuffer;
      64: ldc           #51                 // String .sgml
      66: invokevirtual #13                 // Method java/lang/StringBuffer.append:(Ljava/lang/String;)Ljava/lang/StringBuffer;
      69: invokevirtual #19                 // Method java/lang/StringBuffer.toString:()Ljava/lang/String;
      72: invokevirtual #53                 // Method antlr/Tool.openOutputFile:(Ljava/lang/String;)Ljava/io/PrintWriter;
      75: putfield      #54                 // Field currentOutput:Ljava/io/PrintWriter;
      78: aload_0
      79: iconst_0
      80: putfield      #55                 // Field tabs:I
      83: aload_0
      84: invokevirtual #56                 // Method genHeader:()V
      87: aload_0
      88: ldc           #35                 // String
      90: invokevirtual #57                 // Method println:(Ljava/lang/String;)V
      93: aload_0
      94: getfield      #49                 // Field grammar:Lantlr/Grammar;
      97: getfield      #58                 // Field antlr/Grammar.comment:Ljava/lang/String;
     100: ifnull        117
     103: aload_0
     104: aload_0
     105: getfield      #49                 // Field grammar:Lantlr/Grammar;
     108: getfield      #58                 // Field antlr/Grammar.comment:Ljava/lang/String;
     111: invokestatic  #41                 // Method HTMLEncode:(Ljava/lang/String;)Ljava/lang/String;
     114: invokevirtual #59                 // Method _println:(Ljava/lang/String;)V
     117: aload_0
     118: new           #8                  // class java/lang/StringBuffer
     121: dup
     122: invokespecial #9                  // Method java/lang/StringBuffer."<init>":()V
     125: ldc           #74                 // String <para>Definition of parser
     127: invokevirtual #13                 // Method java/lang/StringBuffer.append:(Ljava/lang/String;)Ljava/lang/StringBuffer;
     130: aload_0
     131: getfield      #49                 // Field grammar:Lantlr/Grammar;
     134: invokevirtual #50                 // Method antlr/Grammar.getClassName:()Ljava/lang/String;
     137: invokevirtual #13                 // Method java/lang/StringBuffer.append:(Ljava/lang/String;)Ljava/lang/StringBuffer;
     140: ldc           #61                 // String , which is a subclass of
     142: invokevirtual #13                 // Method java/lang/StringBuffer.append:(Ljava/lang/String;)Ljava/lang/StringBuffer;
     145: aload_0
     146: getfield      #49                 // Field grammar:Lantlr/Grammar;
     149: invokevirtual #62                 // Method antlr/Grammar.getSuperClass:()Ljava/lang/String;
     152: invokevirtual #13                 // Method java/lang/StringBuffer.append:(Ljava/lang/String;)Ljava/lang/StringBuffer;
     155: ldc           #63                 // String .</para>
     157: invokevirtual #13                 // Method java/lang/StringBuffer.append:(Ljava/lang/String;)Ljava/lang/StringBuffer;
     160: invokevirtual #19                 // Method java/lang/StringBuffer.toString:()Ljava/lang/String;
     163: invokevirtual #57                 // Method println:(Ljava/lang/String;)V
     166: aload_0
     167: getfield      #49                 // Field grammar:Lantlr/Grammar;
     170: getfield      #65                 // Field antlr/Grammar.rules:Lantlr/collections/impl/Vector;
     173: invokevirtual #66                 // Method antlr/collections/impl/Vector.elements:()Ljava/util/Enumeration;
     176: astore_2
     177: aload_2
     178: invokeinterface #24,  1           // InterfaceMethod java/util/Enumeration.hasMoreElements:()Z
     183: ifeq          220
     186: aload_0
     187: ldc           #35                 // String
     189: invokevirtual #57                 // Method println:(Ljava/lang/String;)V
     192: aload_2
     193: invokeinterface #25,  1           // InterfaceMethod java/util/Enumeration.nextElement:()Ljava/lang/Object;
     198: checkcast     #75                 // class antlr/GrammarSymbol
     201: astore_3
     202: aload_3
     203: instanceof    #67                 // class antlr/RuleSymbol
     206: ifeq          177
     209: aload_0
     210: aload_3
     211: checkcast     #67                 // class antlr/RuleSymbol
     214: invokevirtual #71                 // Method genRule:(Lantlr/RuleSymbol;)V
     217: goto          177
     220: aload_0
     221: dup
     222: getfield      #55                 // Field tabs:I
     225: iconst_1
     226: isub
     227: putfield      #55                 // Field tabs:I
     230: aload_0
     231: ldc           #35                 // String
     233: invokevirtual #57                 // Method println:(Ljava/lang/String;)V
     236: aload_0
     237: invokevirtual #76                 // Method genTail:()V
     240: aload_0
     241: getfield      #54                 // Field currentOutput:Ljava/io/PrintWriter;
     244: invokevirtual #72                 // Method java/io/PrintWriter.close:()V
     247: aload_0
     248: aconst_null
     249: putfield      #54                 // Field currentOutput:Ljava/io/PrintWriter;
     252: return

  public void gen(antlr.RuleRefElement);
    Code:
       0: aload_0
       1: getfield      #49                 // Field grammar:Lantlr/Grammar;
       4: aload_1
       5: getfield      #77                 // Field antlr/RuleRefElement.targetRule:Ljava/lang/String;
       8: invokevirtual #78                 // Method antlr/Grammar.getSymbol:(Ljava/lang/String;)Lantlr/GrammarSymbol;
      11: checkcast     #67                 // class antlr/RuleSymbol
      14: astore_2
      15: aload_0
      16: new           #8                  // class java/lang/StringBuffer
      19: dup
      20: invokespecial #9                  // Method java/lang/StringBuffer."<init>":()V
      23: ldc           #79                 // String <link linkend=\"
      25: invokevirtual #13                 // Method java/lang/StringBuffer.append:(Ljava/lang/String;)Ljava/lang/StringBuffer;
      28: aload_1
      29: getfield      #77                 // Field antlr/RuleRefElement.targetRule:Ljava/lang/String;
      32: invokestatic  #80                 // Method QuoteForId:(Ljava/lang/String;)Ljava/lang/String;
      35: invokevirtual #13                 // Method java/lang/StringBuffer.append:(Ljava/lang/String;)Ljava/lang/StringBuffer;
      38: ldc           #81                 // String \">
      40: invokevirtual #13                 // Method java/lang/StringBuffer.append:(Ljava/lang/String;)Ljava/lang/StringBuffer;
      43: invokevirtual #19                 // Method java/lang/StringBuffer.toString:()Ljava/lang/String;
      46: invokevirtual #39                 // Method _print:(Ljava/lang/String;)V
      49: aload_0
      50: aload_1
      51: getfield      #77                 // Field antlr/RuleRefElement.targetRule:Ljava/lang/String;
      54: invokevirtual #39                 // Method _print:(Ljava/lang/String;)V
      57: aload_0
      58: ldc           #82                 // String </link>
      60: invokevirtual #39                 // Method _print:(Ljava/lang/String;)V
      63: aload_0
      64: ldc           #42                 // String
      66: invokevirtual #39                 // Method _print:(Ljava/lang/String;)V
      69: return

  public void gen(antlr.StringLiteralElement);
    Code:
       0: aload_1
       1: getfield      #83                 // Field antlr/StringLiteralElement.not:Z
       4: ifeq          13
       7: aload_0
       8: ldc           #38                 // String ~
      10: invokevirtual #39                 // Method _print:(Ljava/lang/String;)V
      13: aload_0
      14: aload_1
      15: getfield      #84                 // Field antlr/StringLiteralElement.atomText:Ljava/lang/String;
      18: invokestatic  #41                 // Method HTMLEncode:(Ljava/lang/String;)Ljava/lang/String;
      21: invokevirtual #39                 // Method _print:(Ljava/lang/String;)V
      24: aload_0
      25: ldc           #42                 // String
      27: invokevirtual #39                 // Method _print:(Ljava/lang/String;)V
      30: return

  public void gen(antlr.TokenRangeElement);
    Code:
       0: aload_0
       1: new           #8                  // class java/lang/StringBuffer
       4: dup
       5: invokespecial #9                  // Method java/lang/StringBuffer."<init>":()V
       8: aload_1
       9: getfield      #85                 // Field antlr/TokenRangeElement.beginText:Ljava/lang/String;
      12: invokevirtual #13                 // Method java/lang/StringBuffer.append:(Ljava/lang/String;)Ljava/lang/StringBuffer;
      15: ldc           #44                 // String ..
      17: invokevirtual #13                 // Method java/lang/StringBuffer.append:(Ljava/lang/String;)Ljava/lang/StringBuffer;
      20: aload_1
      21: getfield      #86                 // Field antlr/TokenRangeElement.endText:Ljava/lang/String;
      24: invokevirtual #13                 // Method java/lang/StringBuffer.append:(Ljava/lang/String;)Ljava/lang/StringBuffer;
      27: ldc           #42                 // String
      29: invokevirtual #13                 // Method java/lang/StringBuffer.append:(Ljava/lang/String;)Ljava/lang/StringBuffer;
      32: invokevirtual #19                 // Method java/lang/StringBuffer.toString:()Ljava/lang/String;
      35: invokevirtual #46                 // Method print:(Ljava/lang/String;)V
      38: return

  public void gen(antlr.TokenRefElement);
    Code:
       0: aload_1
       1: getfield      #87                 // Field antlr/TokenRefElement.not:Z
       4: ifeq          13
       7: aload_0
       8: ldc           #38                 // String ~
      10: invokevirtual #39                 // Method _print:(Ljava/lang/String;)V
      13: aload_0
      14: aload_1
      15: getfield      #88                 // Field antlr/TokenRefElement.atomText:Ljava/lang/String;
      18: invokevirtual #39                 // Method _print:(Ljava/lang/String;)V
      21: aload_0
      22: ldc           #42                 // String
      24: invokevirtual #39                 // Method _print:(Ljava/lang/String;)V
      27: return

  public void gen(antlr.TreeElement);
    Code:
       0: aload_0
       1: new           #8                  // class java/lang/StringBuffer
       4: dup
       5: invokespecial #9                  // Method java/lang/StringBuffer."<init>":()V
       8: aload_1
       9: invokevirtual #89                 // Method java/lang/StringBuffer.append:(Ljava/lang/Object;)Ljava/lang/StringBuffer;
      12: ldc           #42                 // String
      14: invokevirtual #13                 // Method java/lang/StringBuffer.append:(Ljava/lang/String;)Ljava/lang/StringBuffer;
      17: invokevirtual #19                 // Method java/lang/StringBuffer.toString:()Ljava/lang/String;
      20: invokevirtual #46                 // Method print:(Ljava/lang/String;)V
      23: return

  public void gen(antlr.TreeWalkerGrammar) throws java.io.IOException;
    Code:
       0: aload_0
       1: aload_1
       2: invokevirtual #47                 // Method setGrammar:(Lantlr/Grammar;)V
       5: aload_0
       6: getfield      #29                 // Field antlrTool:Lantlr/Tool;
       9: new           #8                  // class java/lang/StringBuffer
      12: dup
      13: invokespecial #9                  // Method java/lang/StringBuffer."<init>":()V
      16: ldc           #48                 // String Generating
      18: invokevirtual #13                 // Method java/lang/StringBuffer.append:(Ljava/lang/String;)Ljava/lang/StringBuffer;
      21: aload_0
      22: getfield      #49                 // Field grammar:Lantlr/Grammar;
      25: invokevirtual #50                 // Method antlr/Grammar.getClassName:()Ljava/lang/String;
      28: invokevirtual #13                 // Method java/lang/StringBuffer.append:(Ljava/lang/String;)Ljava/lang/StringBuffer;
      31: ldc           #51                 // String .sgml
      33: invokevirtual #13                 // Method java/lang/StringBuffer.append:(Ljava/lang/String;)Ljava/lang/StringBuffer;
      36: invokevirtual #19                 // Method java/lang/StringBuffer.toString:()Ljava/lang/String;
      39: invokevirtual #52                 // Method antlr/Tool.reportProgress:(Ljava/lang/String;)V
      42: aload_0
      43: aload_0
      44: getfield      #29                 // Field antlrTool:Lantlr/Tool;
      47: new           #8                  // class java/lang/StringBuffer
      50: dup
      51: invokespecial #9                  // Method java/lang/StringBuffer."<init>":()V
      54: aload_0
      55: getfield      #49                 // Field grammar:Lantlr/Grammar;
      58: invokevirtual #50                 // Method antlr/Grammar.getClassName:()Ljava/lang/String;
      61: invokevirtual #13                 // Method java/lang/StringBuffer.append:(Ljava/lang/String;)Ljava/lang/StringBuffer;
      64: ldc           #51                 // String .sgml
      66: invokevirtual #13                 // Method java/lang/StringBuffer.append:(Ljava/lang/String;)Ljava/lang/StringBuffer;
      69: invokevirtual #19                 // Method java/lang/StringBuffer.toString:()Ljava/lang/String;
      72: invokevirtual #53                 // Method antlr/Tool.openOutputFile:(Ljava/lang/String;)Ljava/io/PrintWriter;
      75: putfield      #54                 // Field currentOutput:Ljava/io/PrintWriter;
      78: aload_0
      79: iconst_0
      80: putfield      #55                 // Field tabs:I
      83: aload_0
      84: invokevirtual #56                 // Method genHeader:()V
      87: aload_0
      88: ldc           #35                 // String
      90: invokevirtual #57                 // Method println:(Ljava/lang/String;)V
      93: aload_0
      94: ldc           #35                 // String
      96: invokevirtual #57                 // Method println:(Ljava/lang/String;)V
      99: aload_0
     100: getfield      #49                 // Field grammar:Lantlr/Grammar;
     103: getfield      #58                 // Field antlr/Grammar.comment:Ljava/lang/String;
     106: ifnull        123
     109: aload_0
     110: aload_0
     111: getfield      #49                 // Field grammar:Lantlr/Grammar;
     114: getfield      #58                 // Field antlr/Grammar.comment:Ljava/lang/String;
     117: invokestatic  #41                 // Method HTMLEncode:(Ljava/lang/String;)Ljava/lang/String;
     120: invokevirtual #59                 // Method _println:(Ljava/lang/String;)V
     123: aload_0
     124: new           #8                  // class java/lang/StringBuffer
     127: dup
     128: invokespecial #9                  // Method java/lang/StringBuffer."<init>":()V
     131: ldc           #90                 // String <para>Definition of tree parser
     133: invokevirtual #13                 // Method java/lang/StringBuffer.append:(Ljava/lang/String;)Ljava/lang/StringBuffer;
     136: aload_0
     137: getfield      #49                 // Field grammar:Lantlr/Grammar;
     140: invokevirtual #50                 // Method antlr/Grammar.getClassName:()Ljava/lang/String;
     143: invokevirtual #13                 // Method java/lang/StringBuffer.append:(Ljava/lang/String;)Ljava/lang/StringBuffer;
     146: ldc           #61                 // String , which is a subclass of
     148: invokevirtual #13                 // Method java/lang/StringBuffer.append:(Ljava/lang/String;)Ljava/lang/StringBuffer;
     151: aload_0
     152: getfield      #49                 // Field grammar:Lantlr/Grammar;
     155: invokevirtual #62                 // Method antlr/Grammar.getSuperClass:()Ljava/lang/String;
     158: invokevirtual #13                 // Method java/lang/StringBuffer.append:(Ljava/lang/String;)Ljava/lang/StringBuffer;
     161: ldc           #63                 // String .</para>
     163: invokevirtual #13                 // Method java/lang/StringBuffer.append:(Ljava/lang/String;)Ljava/lang/StringBuffer;
     166: invokevirtual #19                 // Method java/lang/StringBuffer.toString:()Ljava/lang/String;
     169: invokevirtual #57                 // Method println:(Ljava/lang/String;)V
     172: aload_0
     173: ldc           #35                 // String
     175: invokevirtual #57                 // Method println:(Ljava/lang/String;)V
     178: aload_0
     179: dup
     180: getfield      #55                 // Field tabs:I
     183: iconst_1
     184: iadd
     185: putfield      #55                 // Field tabs:I
     188: aload_0
     189: getfield      #49                 // Field grammar:Lantlr/Grammar;
     192: getfield      #65                 // Field antlr/Grammar.rules:Lantlr/collections/impl/Vector;
     195: invokevirtual #66                 // Method antlr/collections/impl/Vector.elements:()Ljava/util/Enumeration;
     198: astore_2
     199: aload_2
     200: invokeinterface #24,  1           // InterfaceMethod java/util/Enumeration.hasMoreElements:()Z
     205: ifeq          242
     208: aload_0
     209: ldc           #35                 // String
     211: invokevirtual #57                 // Method println:(Ljava/lang/String;)V
     214: aload_2
     215: invokeinterface #25,  1           // InterfaceMethod java/util/Enumeration.nextElement:()Ljava/lang/Object;
     220: checkcast     #75                 // class antlr/GrammarSymbol
     223: astore_3
     224: aload_3
     225: instanceof    #67                 // class antlr/RuleSymbol
     228: ifeq          199
     231: aload_0
     232: aload_3
     233: checkcast     #67                 // class antlr/RuleSymbol
     236: invokevirtual #71                 // Method genRule:(Lantlr/RuleSymbol;)V
     239: goto          199
     242: aload_0
     243: dup
     244: getfield      #55                 // Field tabs:I
     247: iconst_1
     248: isub
     249: putfield      #55                 // Field tabs:I
     252: aload_0
     253: ldc           #35                 // String
     255: invokevirtual #57                 // Method println:(Ljava/lang/String;)V
     258: aload_0
     259: getfield      #54                 // Field currentOutput:Ljava/io/PrintWriter;
     262: invokevirtual #72                 // Method java/io/PrintWriter.close:()V
     265: aload_0
     266: aconst_null
     267: putfield      #54                 // Field currentOutput:Ljava/io/PrintWriter;
     270: return

  public void gen(antlr.WildcardElement);
    Code:
       0: aload_0
       1: ldc           #91                 // String .
       3: invokevirtual #39                 // Method _print:(Ljava/lang/String;)V
       6: return

  public void gen(antlr.ZeroOrMoreBlock);
    Code:
       0: aload_0
       1: aload_1
       2: ldc           #92                 // String *
       4: invokevirtual #36                 // Method genGenericBlock:(Lantlr/AlternativeBlock;Ljava/lang/String;)V
       7: return

  protected void genAlt(antlr.Alternative);
    Code:
       0: aload_1
       1: invokevirtual #93                 // Method antlr/Alternative.getTreeSpecifier:()Lantlr/Token;
       4: ifnull        18
       7: aload_0
       8: aload_1
       9: invokevirtual #93                 // Method antlr/Alternative.getTreeSpecifier:()Lantlr/Token;
      12: invokevirtual #94                 // Method antlr/Token.getText:()Ljava/lang/String;
      15: invokevirtual #39                 // Method _print:(Ljava/lang/String;)V
      18: aload_0
      19: aconst_null
      20: putfield      #4                  // Field prevAltElem:Lantlr/AlternativeElement;
      23: aload_1
      24: getfield      #95                 // Field antlr/Alternative.head:Lantlr/AlternativeElement;
      27: astore_2
      28: aload_2
      29: instanceof    #96                 // class antlr/BlockEndElement
      32: ifne          57
      35: aload_2
      36: invokevirtual #97                 // Method antlr/AlternativeElement.generate:()V
      39: aload_0
      40: iconst_0
      41: putfield      #98                 // Field firstElementInAlt:Z
      44: aload_0
      45: aload_2
      46: putfield      #4                  // Field prevAltElem:Lantlr/AlternativeElement;
      49: aload_2
      50: getfield      #99                 // Field antlr/AlternativeElement.next:Lantlr/AlternativeElement;
      53: astore_2
      54: goto          28
      57: return

  public void genCommonBlock(antlr.AlternativeBlock);
    Code:
       0: aload_1
       1: getfield      #100                // Field antlr/AlternativeBlock.alternatives:Lantlr/collections/impl/Vector;
       4: invokevirtual #101                // Method antlr/collections/impl/Vector.size:()I
       7: iconst_1
       8: if_icmple     17
      11: aload_0
      12: ldc           #102                // String <itemizedlist mark=\"none\">
      14: invokevirtual #57                 // Method println:(Ljava/lang/String;)V
      17: iconst_0
      18: istore_2
      19: iload_2
      20: aload_1
      21: getfield      #100                // Field antlr/AlternativeBlock.alternatives:Lantlr/collections/impl/Vector;
      24: invokevirtual #101                // Method antlr/collections/impl/Vector.size:()I
      27: if_icmpge     145
      30: aload_1
      31: iload_2
      32: invokevirtual #103                // Method antlr/AlternativeBlock.getAlternativeAt:(I)Lantlr/Alternative;
      35: astore_3
      36: aload_3
      37: getfield      #95                 // Field antlr/Alternative.head:Lantlr/AlternativeElement;
      40: astore        4
      42: aload_1
      43: getfield      #100                // Field antlr/AlternativeBlock.alternatives:Lantlr/collections/impl/Vector;
      46: invokevirtual #101                // Method antlr/collections/impl/Vector.size:()I
      49: iconst_1
      50: if_icmple     59
      53: aload_0
      54: ldc           #104                // String <listitem><para>
      56: invokevirtual #46                 // Method print:(Ljava/lang/String;)V
      59: iload_2
      60: ifle          80
      63: aload_1
      64: getfield      #100                // Field antlr/AlternativeBlock.alternatives:Lantlr/collections/impl/Vector;
      67: invokevirtual #101                // Method antlr/collections/impl/Vector.size:()I
      70: iconst_1
      71: if_icmple     80
      74: aload_0
      75: ldc           #105                // String |
      77: invokevirtual #39                 // Method _print:(Ljava/lang/String;)V
      80: aload_0
      81: getfield      #98                 // Field firstElementInAlt:Z
      84: istore        5
      86: aload_0
      87: iconst_1
      88: putfield      #98                 // Field firstElementInAlt:Z
      91: aload_0
      92: dup
      93: getfield      #55                 // Field tabs:I
      96: iconst_1
      97: iadd
      98: putfield      #55                 // Field tabs:I
     101: aload_0
     102: aload_3
     103: invokevirtual #106                // Method genAlt:(Lantlr/Alternative;)V
     106: aload_0
     107: dup
     108: getfield      #55                 // Field tabs:I
     111: iconst_1
     112: isub
     113: putfield      #55                 // Field tabs:I
     116: aload_0
     117: iload         5
     119: putfield      #98                 // Field firstElementInAlt:Z
     122: aload_1
     123: getfield      #100                // Field antlr/AlternativeBlock.alternatives:Lantlr/collections/impl/Vector;
     126: invokevirtual #101                // Method antlr/collections/impl/Vector.size:()I
     129: iconst_1
     130: if_icmple     139
     133: aload_0
     134: ldc           #107                // String </para></listitem>
     136: invokevirtual #59                 // Method _println:(Ljava/lang/String;)V
     139: iinc          2, 1
     142: goto          19
     145: aload_1
     146: getfield      #100                // Field antlr/AlternativeBlock.alternatives:Lantlr/collections/impl/Vector;
     149: invokevirtual #101                // Method antlr/collections/impl/Vector.size:()I
     152: iconst_1
     153: if_icmple     162
     156: aload_0
     157: ldc           #108                // String </itemizedlist>
     159: invokevirtual #57                 // Method println:(Ljava/lang/String;)V
     162: return

  public void genFollowSetForRuleBlock(antlr.RuleBlock);
    Code:
       0: aload_0
       1: getfield      #49                 // Field grammar:Lantlr/Grammar;
       4: getfield      #109                // Field antlr/Grammar.theLLkAnalyzer:Lantlr/LLkGrammarAnalyzer;
       7: iconst_1
       8: aload_1
       9: getfield      #110                // Field antlr/RuleBlock.endNode:Lantlr/RuleEndElement;
      12: invokeinterface #111,  3          // InterfaceMethod antlr/LLkGrammarAnalyzer.FOLLOW:(ILantlr/RuleEndElement;)Lantlr/Lookahead;
      17: astore_2
      18: aload_0
      19: aload_0
      20: getfield      #49                 // Field grammar:Lantlr/Grammar;
      23: getfield      #112                // Field antlr/Grammar.maxk:I
      26: iconst_1
      27: aload_2
      28: invokevirtual #113                // Method printSet:(IILantlr/Lookahead;)V
      31: return

  protected void genGenericBlock(antlr.AlternativeBlock, java.lang.String);
    Code:
       0: aload_1
       1: getfield      #100                // Field antlr/AlternativeBlock.alternatives:Lantlr/collections/impl/Vector;
       4: invokevirtual #101                // Method antlr/collections/impl/Vector.size:()I
       7: iconst_1
       8: if_icmple     42
      11: aload_0
      12: ldc           #35                 // String
      14: invokevirtual #59                 // Method _println:(Ljava/lang/String;)V
      17: aload_0
      18: getfield      #98                 // Field firstElementInAlt:Z
      21: ifne          33
      24: aload_0
      25: ldc           #114                // String (
      27: invokevirtual #59                 // Method _println:(Ljava/lang/String;)V
      30: goto          48
      33: aload_0
      34: ldc           #114                // String (
      36: invokevirtual #39                 // Method _print:(Ljava/lang/String;)V
      39: goto          48
      42: aload_0
      43: ldc           #115                // String (
      45: invokevirtual #39                 // Method _print:(Ljava/lang/String;)V
      48: aload_0
      49: aload_1
      50: invokevirtual #116                // Method genCommonBlock:(Lantlr/AlternativeBlock;)V
      53: aload_1
      54: getfield      #100                // Field antlr/AlternativeBlock.alternatives:Lantlr/collections/impl/Vector;
      57: invokevirtual #101                // Method antlr/collections/impl/Vector.size:()I
      60: iconst_1
      61: if_icmple     123
      64: aload_0
      65: ldc           #35                 // String
      67: invokevirtual #59                 // Method _println:(Ljava/lang/String;)V
      70: aload_0
      71: new           #8                  // class java/lang/StringBuffer
      74: dup
      75: invokespecial #9                  // Method java/lang/StringBuffer."<init>":()V
      78: ldc           #117                // String )
      80: invokevirtual #13                 // Method java/lang/StringBuffer.append:(Ljava/lang/String;)Ljava/lang/StringBuffer;
      83: aload_2
      84: invokevirtual #13                 // Method java/lang/StringBuffer.append:(Ljava/lang/String;)Ljava/lang/StringBuffer;
      87: ldc           #42                 // String
      89: invokevirtual #13                 // Method java/lang/StringBuffer.append:(Ljava/lang/String;)Ljava/lang/StringBuffer;
      92: invokevirtual #19                 // Method java/lang/StringBuffer.toString:()Ljava/lang/String;
      95: invokevirtual #46                 // Method print:(Ljava/lang/String;)V
      98: aload_1
      99: getfield      #118                // Field antlr/AlternativeBlock.next:Lantlr/AlternativeElement;
     102: instanceof    #96                 // class antlr/BlockEndElement
     105: ifne          151
     108: aload_0
     109: ldc           #35                 // String
     111: invokevirtual #59                 // Method _println:(Ljava/lang/String;)V
     114: aload_0
     115: ldc           #35                 // String
     117: invokevirtual #46                 // Method print:(Ljava/lang/String;)V
     120: goto          151
     123: aload_0
     124: new           #8                  // class java/lang/StringBuffer
     127: dup
     128: invokespecial #9                  // Method java/lang/StringBuffer."<init>":()V
     131: ldc           #117                // String )
     133: invokevirtual #13                 // Method java/lang/StringBuffer.append:(Ljava/lang/String;)Ljava/lang/StringBuffer;
     136: aload_2
     137: invokevirtual #13                 // Method java/lang/StringBuffer.append:(Ljava/lang/String;)Ljava/lang/StringBuffer;
     140: ldc           #42                 // String
     142: invokevirtual #13                 // Method java/lang/StringBuffer.append:(Ljava/lang/String;)Ljava/lang/StringBuffer;
     145: invokevirtual #19                 // Method java/lang/StringBuffer.toString:()Ljava/lang/String;
     148: invokevirtual #39                 // Method _print:(Ljava/lang/String;)V
     151: return

  protected void genHeader();
    Code:
       0: aload_0
       1: ldc           #119                // String <?xml version=\"1.0\" standalone=\"no\"?>
       3: invokevirtual #57                 // Method println:(Ljava/lang/String;)V
       6: aload_0
       7: ldc           #120                // String <!DOCTYPE book PUBLIC \"-//OASIS//DTD DocBook V3.1//EN\">
       9: invokevirtual #57                 // Method println:(Ljava/lang/String;)V
      12: aload_0
      13: ldc           #121                // String <book lang=\"en\">
      15: invokevirtual #57                 // Method println:(Ljava/lang/String;)V
      18: aload_0
      19: ldc           #122                // String <bookinfo>
      21: invokevirtual #57                 // Method println:(Ljava/lang/String;)V
      24: aload_0
      25: new           #8                  // class java/lang/StringBuffer
      28: dup
      29: invokespecial #9                  // Method java/lang/StringBuffer."<init>":()V
      32: ldc           #123                // String <title>Grammar
      34: invokevirtual #13                 // Method java/lang/StringBuffer.append:(Ljava/lang/String;)Ljava/lang/StringBuffer;
      37: aload_0
      38: getfield      #49                 // Field grammar:Lantlr/Grammar;
      41: invokevirtual #50                 // Method antlr/Grammar.getClassName:()Ljava/lang/String;
      44: invokevirtual #13                 // Method java/lang/StringBuffer.append:(Ljava/lang/String;)Ljava/lang/StringBuffer;
      47: ldc           #124                // String </title>
      49: invokevirtual #13                 // Method java/lang/StringBuffer.append:(Ljava/lang/String;)Ljava/lang/StringBuffer;
      52: invokevirtual #19                 // Method java/lang/StringBuffer.toString:()Ljava/lang/String;
      55: invokevirtual #57                 // Method println:(Ljava/lang/String;)V
      58: aload_0
      59: ldc           #125                // String   <author>
      61: invokevirtual #57                 // Method println:(Ljava/lang/String;)V
      64: aload_0
      65: ldc           #126                // String     <firstname></firstname>
      67: invokevirtual #57                 // Method println:(Ljava/lang/String;)V
      70: aload_0
      71: ldc           #127                // String     <othername></othername>
      73: invokevirtual #57                 // Method println:(Ljava/lang/String;)V
      76: aload_0
      77: ldc           #128                // String     <surname></surname>
      79: invokevirtual #57                 // Method println:(Ljava/lang/String;)V
      82: aload_0
      83: ldc           #129                // String     <affiliation>
      85: invokevirtual #57                 // Method println:(Ljava/lang/String;)V
      88: aload_0
      89: ldc           #130                // String      <address>
      91: invokevirtual #57                 // Method println:(Ljava/lang/String;)V
      94: aload_0
      95: ldc           #131                // String      <email></email>
      97: invokevirtual #57                 // Method println:(Ljava/lang/String;)V
     100: aload_0
     101: ldc           #132                // String      </address>
     103: invokevirtual #57                 // Method println:(Ljava/lang/String;)V
     106: aload_0
     107: ldc           #133                // String     </affiliation>
     109: invokevirtual #57                 // Method println:(Ljava/lang/String;)V
     112: aload_0
     113: ldc           #134                // String   </author>
     115: invokevirtual #57                 // Method println:(Ljava/lang/String;)V
     118: aload_0
     119: ldc           #135                // String   <othercredit>
     121: invokevirtual #57                 // Method println:(Ljava/lang/String;)V
     124: aload_0
     125: ldc           #136                // String     <contrib>
     127: invokevirtual #57                 // Method println:(Ljava/lang/String;)V
     130: aload_0
     131: new           #8                  // class java/lang/StringBuffer
     134: dup
     135: invokespecial #9                  // Method java/lang/StringBuffer."<init>":()V
     138: ldc           #137                // String     Generated by <ulink url=\"http://www.ANTLR.org/\">ANTLR</ulink>
     140: invokevirtual #13                 // Method java/lang/StringBuffer.append:(Ljava/lang/String;)Ljava/lang/StringBuffer;
     143: aload_0
     144: getfield      #29                 // Field antlrTool:Lantlr/Tool;
     147: pop
     148: getstatic     #138                // Field antlr/Tool.version:Ljava/lang/String;
     151: invokevirtual #13                 // Method java/lang/StringBuffer.append:(Ljava/lang/String;)Ljava/lang/StringBuffer;
     154: invokevirtual #19                 // Method java/lang/StringBuffer.toString:()Ljava/lang/String;
     157: invokevirtual #57                 // Method println:(Ljava/lang/String;)V
     160: aload_0
     161: new           #8                  // class java/lang/StringBuffer
     164: dup
     165: invokespecial #9                  // Method java/lang/StringBuffer."<init>":()V
     168: ldc           #139                // String     from
     170: invokevirtual #13                 // Method java/lang/StringBuffer.append:(Ljava/lang/String;)Ljava/lang/StringBuffer;
     173: aload_0
     174: getfield      #29                 // Field antlrTool:Lantlr/Tool;
     177: getfield      #140                // Field antlr/Tool.grammarFile:Ljava/lang/String;
     180: invokevirtual #13                 // Method java/lang/StringBuffer.append:(Ljava/lang/String;)Ljava/lang/StringBuffer;
     183: invokevirtual #19                 // Method java/lang/StringBuffer.toString:()Ljava/lang/String;
     186: invokevirtual #57                 // Method println:(Ljava/lang/String;)V
     189: aload_0
     190: ldc           #141                // String     </contrib>
     192: invokevirtual #57                 // Method println:(Ljava/lang/String;)V
     195: aload_0
     196: ldc           #142                // String   </othercredit>
     198: invokevirtual #57                 // Method println:(Ljava/lang/String;)V
     201: aload_0
     202: ldc           #143                // String   <pubdate></pubdate>
     204: invokevirtual #57                 // Method println:(Ljava/lang/String;)V
     207: aload_0
     208: ldc           #144                // String   <abstract>
     210: invokevirtual #57                 // Method println:(Ljava/lang/String;)V
     213: aload_0
     214: ldc           #145                // String   <para>
     216: invokevirtual #57                 // Method println:(Ljava/lang/String;)V
     219: aload_0
     220: ldc           #146                // String   </para>
     222: invokevirtual #57                 // Method println:(Ljava/lang/String;)V
     225: aload_0
     226: ldc           #147                // String   </abstract>
     228: invokevirtual #57                 // Method println:(Ljava/lang/String;)V
     231: aload_0
     232: ldc           #148                // String </bookinfo>
     234: invokevirtual #57                 // Method println:(Ljava/lang/String;)V
     237: aload_0
     238: ldc           #149                // String <chapter>
     240: invokevirtual #57                 // Method println:(Ljava/lang/String;)V
     243: aload_0
     244: ldc           #150                // String <title></title>
     246: invokevirtual #57                 // Method println:(Ljava/lang/String;)V
     249: return

  protected void genLookaheadSetForAlt(antlr.Alternative);
    Code:
       0: aload_0
       1: getfield      #3                  // Field doingLexRules:Z
       4: ifeq          26
       7: aload_1
       8: getfield      #151                // Field antlr/Alternative.cache:[Lantlr/Lookahead;
      11: iconst_1
      12: aaload
      13: invokevirtual #152                // Method antlr/Lookahead.containsEpsilon:()Z
      16: ifeq          26
      19: aload_0
      20: ldc           #153                // String MATCHES ALL
      22: invokevirtual #57                 // Method println:(Ljava/lang/String;)V
      25: return
      26: aload_1
      27: getfield      #154                // Field antlr/Alternative.lookaheadDepth:I
      30: istore_2
      31: iload_2
      32: ldc           #155                // int 2147483647
      34: if_icmpne     45
      37: aload_0
      38: getfield      #49                 // Field grammar:Lantlr/Grammar;
      41: getfield      #112                // Field antlr/Grammar.maxk:I
      44: istore_2
      45: iconst_1
      46: istore_3
      47: iload_3
      48: iload_2
      49: if_icmpgt     74
      52: aload_1
      53: getfield      #151                // Field antlr/Alternative.cache:[Lantlr/Lookahead;
      56: iload_3
      57: aaload
      58: astore        4
      60: aload_0
      61: iload_2
      62: iload_3
      63: aload         4
      65: invokevirtual #113                // Method printSet:(IILantlr/Lookahead;)V
      68: iinc          3, 1
      71: goto          47
      74: return

  public void genLookaheadSetForBlock(antlr.AlternativeBlock);
    Code:
       0: iconst_0
       1: istore_2
       2: iconst_0
       3: istore_3
       4: iload_3
       5: aload_1
       6: getfield      #100                // Field antlr/AlternativeBlock.alternatives:Lantlr/collections/impl/Vector;
       9: invokevirtual #101                // Method antlr/collections/impl/Vector.size:()I
      12: if_icmpge     64
      15: aload_1
      16: iload_3
      17: invokevirtual #103                // Method antlr/AlternativeBlock.getAlternativeAt:(I)Lantlr/Alternative;
      20: astore        4
      22: aload         4
      24: getfield      #154                // Field antlr/Alternative.lookaheadDepth:I
      27: ldc           #155                // int 2147483647
      29: if_icmpne     43
      32: aload_0
      33: getfield      #49                 // Field grammar:Lantlr/Grammar;
      36: getfield      #112                // Field antlr/Grammar.maxk:I
      39: istore_2
      40: goto          64
      43: iload_2
      44: aload         4
      46: getfield      #154                // Field antlr/Alternative.lookaheadDepth:I
      49: if_icmpge     58
      52: aload         4
      54: getfield      #154                // Field antlr/Alternative.lookaheadDepth:I
      57: istore_2
      58: iinc          3, 1
      61: goto          4
      64: iconst_1
      65: istore_3
      66: iload_3
      67: iload_2
      68: if_icmpgt     101
      71: aload_0
      72: getfield      #49                 // Field grammar:Lantlr/Grammar;
      75: getfield      #109                // Field antlr/Grammar.theLLkAnalyzer:Lantlr/LLkGrammarAnalyzer;
      78: iload_3
      79: aload_1
      80: invokeinterface #156,  3          // InterfaceMethod antlr/LLkGrammarAnalyzer.look:(ILantlr/AlternativeBlock;)Lantlr/Lookahead;
      85: astore        4
      87: aload_0
      88: iload_2
      89: iload_3
      90: aload         4
      92: invokevirtual #113                // Method printSet:(IILantlr/Lookahead;)V
      95: iinc          3, 1
      98: goto          66
     101: return

  public void genNextToken();
    Code:
       0: aload_0
       1: ldc           #35                 // String
       3: invokevirtual #57                 // Method println:(Ljava/lang/String;)V
       6: aload_0
       7: ldc           #157                // String /** Lexer nextToken rule:
       9: invokevirtual #57                 // Method println:(Ljava/lang/String;)V
      12: aload_0
      13: ldc           #158                // String  *  The lexer nextToken rule is synthesized from all of the user-defined
      15: invokevirtual #57                 // Method println:(Ljava/lang/String;)V
      18: aload_0
      19: ldc           #159                // String  *  lexer rules.  It logically consists of one big alternative block with
      21: invokevirtual #57                 // Method println:(Ljava/lang/String;)V
      24: aload_0
      25: ldc           #160                // String  *  each user-defined rule being an alternative.
      27: invokevirtual #57                 // Method println:(Ljava/lang/String;)V
      30: aload_0
      31: ldc           #161                // String  */
      33: invokevirtual #57                 // Method println:(Ljava/lang/String;)V
      36: aload_0
      37: getfield      #49                 // Field grammar:Lantlr/Grammar;
      40: aload_0
      41: getfield      #49                 // Field grammar:Lantlr/Grammar;
      44: getfield      #65                 // Field antlr/Grammar.rules:Lantlr/collections/impl/Vector;
      47: ldc           #162                // String nextToken
      49: invokestatic  #163                // Method antlr/MakeGrammar.createNextTokenRule:(Lantlr/Grammar;Lantlr/collections/impl/Vector;Ljava/lang/String;)Lantlr/RuleBlock;
      52: astore_1
      53: new           #67                 // class antlr/RuleSymbol
      56: dup
      57: ldc           #69                 // String mnextToken
      59: invokespecial #164                // Method antlr/RuleSymbol."<init>":(Ljava/lang/String;)V
      62: astore_2
      63: aload_2
      64: invokevirtual #165                // Method antlr/RuleSymbol.setDefined:()V
      67: aload_2
      68: aload_1
      69: invokevirtual #166                // Method antlr/RuleSymbol.setBlock:(Lantlr/RuleBlock;)V
      72: aload_2
      73: ldc           #167                // String private
      75: putfield      #168                // Field antlr/RuleSymbol.access:Ljava/lang/String;
      78: aload_0
      79: getfield      #49                 // Field grammar:Lantlr/Grammar;
      82: aload_2
      83: invokevirtual #169                // Method antlr/Grammar.define:(Lantlr/RuleSymbol;)V
      86: aload_0
      87: aload_1
      88: invokevirtual #116                // Method genCommonBlock:(Lantlr/AlternativeBlock;)V
      91: return

  public void genRule(antlr.RuleSymbol);
    Code:
       0: aload_1
       1: ifnull        11
       4: aload_1
       5: invokevirtual #170                // Method antlr/RuleSymbol.isDefined:()Z
       8: ifne          12
      11: return
      12: aload_0
      13: ldc           #35                 // String
      15: invokevirtual #57                 // Method println:(Ljava/lang/String;)V
      18: aload_1
      19: getfield      #168                // Field antlr/RuleSymbol.access:Ljava/lang/String;
      22: invokevirtual #10                 // Method java/lang/String.length:()I
      25: ifeq          71
      28: aload_1
      29: getfield      #168                // Field antlr/RuleSymbol.access:Ljava/lang/String;
      32: ldc           #171                // String public
      34: invokevirtual #70                 // Method java/lang/String.equals:(Ljava/lang/Object;)Z
      37: ifne          71
      40: aload_0
      41: new           #8                  // class java/lang/StringBuffer
      44: dup
      45: invokespecial #9                  // Method java/lang/StringBuffer."<init>":()V
      48: ldc           #172                // String <para>
      50: invokevirtual #13                 // Method java/lang/StringBuffer.append:(Ljava/lang/String;)Ljava/lang/StringBuffer;
      53: aload_1
      54: getfield      #168                // Field antlr/RuleSymbol.access:Ljava/lang/String;
      57: invokevirtual #13                 // Method java/lang/StringBuffer.append:(Ljava/lang/String;)Ljava/lang/StringBuffer;
      60: ldc           #173                // String  </para>
      62: invokevirtual #13                 // Method java/lang/StringBuffer.append:(Ljava/lang/String;)Ljava/lang/StringBuffer;
      65: invokevirtual #19                 // Method java/lang/StringBuffer.toString:()Ljava/lang/String;
      68: invokevirtual #39                 // Method _print:(Ljava/lang/String;)V
      71: aload_0
      72: new           #8                  // class java/lang/StringBuffer
      75: dup
      76: invokespecial #9                  // Method java/lang/StringBuffer."<init>":()V
      79: ldc           #174                // String <section id=\"
      81: invokevirtual #13                 // Method java/lang/StringBuffer.append:(Ljava/lang/String;)Ljava/lang/StringBuffer;
      84: aload_1
      85: invokevirtual #175                // Method antlr/RuleSymbol.getId:()Ljava/lang/String;
      88: invokestatic  #80                 // Method QuoteForId:(Ljava/lang/String;)Ljava/lang/String;
      91: invokevirtual #13                 // Method java/lang/StringBuffer.append:(Ljava/lang/String;)Ljava/lang/StringBuffer;
      94: ldc           #81                 // String \">
      96: invokevirtual #13                 // Method java/lang/StringBuffer.append:(Ljava/lang/String;)Ljava/lang/StringBuffer;
      99: invokevirtual #19                 // Method java/lang/StringBuffer.toString:()Ljava/lang/String;
     102: invokevirtual #57                 // Method println:(Ljava/lang/String;)V
     105: aload_0
     106: new           #8                  // class java/lang/StringBuffer
     109: dup
     110: invokespecial #9                  // Method java/lang/StringBuffer."<init>":()V
     113: ldc           #176                // String <title>
     115: invokevirtual #13                 // Method java/lang/StringBuffer.append:(Ljava/lang/String;)Ljava/lang/StringBuffer;
     118: aload_1
     119: invokevirtual #175                // Method antlr/RuleSymbol.getId:()Ljava/lang/String;
     122: invokevirtual #13                 // Method java/lang/StringBuffer.append:(Ljava/lang/String;)Ljava/lang/StringBuffer;
     125: ldc           #124                // String </title>
     127: invokevirtual #13                 // Method java/lang/StringBuffer.append:(Ljava/lang/String;)Ljava/lang/StringBuffer;
     130: invokevirtual #19                 // Method java/lang/StringBuffer.toString:()Ljava/lang/String;
     133: invokevirtual #57                 // Method println:(Ljava/lang/String;)V
     136: aload_1
     137: getfield      #177                // Field antlr/RuleSymbol.comment:Ljava/lang/String;
     140: ifnull        177
     143: aload_0
     144: new           #8                  // class java/lang/StringBuffer
     147: dup
     148: invokespecial #9                  // Method java/lang/StringBuffer."<init>":()V
     151: ldc           #172                // String <para>
     153: invokevirtual #13                 // Method java/lang/StringBuffer.append:(Ljava/lang/String;)Ljava/lang/StringBuffer;
     156: aload_1
     157: getfield      #177                // Field antlr/RuleSymbol.comment:Ljava/lang/String;
     160: invokestatic  #41                 // Method HTMLEncode:(Ljava/lang/String;)Ljava/lang/String;
     163: invokevirtual #13                 // Method java/lang/StringBuffer.append:(Ljava/lang/String;)Ljava/lang/StringBuffer;
     166: ldc           #178                // String </para>
     168: invokevirtual #13                 // Method java/lang/StringBuffer.append:(Ljava/lang/String;)Ljava/lang/StringBuffer;
     171: invokevirtual #19                 // Method java/lang/StringBuffer.toString:()Ljava/lang/String;
     174: invokevirtual #59                 // Method _println:(Ljava/lang/String;)V
     177: aload_0
     178: ldc           #172                // String <para>
     180: invokevirtual #57                 // Method println:(Ljava/lang/String;)V
     183: aload_1
     184: invokevirtual #179                // Method antlr/RuleSymbol.getBlock:()Lantlr/RuleBlock;
     187: astore_2
     188: aload_0
     189: ldc           #35                 // String
     191: invokevirtual #59                 // Method _println:(Ljava/lang/String;)V
     194: aload_0
     195: new           #8                  // class java/lang/StringBuffer
     198: dup
     199: invokespecial #9                  // Method java/lang/StringBuffer."<init>":()V
     202: aload_1
     203: invokevirtual #175                // Method antlr/RuleSymbol.getId:()Ljava/lang/String;
     206: invokevirtual #13                 // Method java/lang/StringBuffer.append:(Ljava/lang/String;)Ljava/lang/StringBuffer;
     209: ldc           #180                // String :\t
     211: invokevirtual #13                 // Method java/lang/StringBuffer.append:(Ljava/lang/String;)Ljava/lang/StringBuffer;
     214: invokevirtual #19                 // Method java/lang/StringBuffer.toString:()Ljava/lang/String;
     217: invokevirtual #46                 // Method print:(Ljava/lang/String;)V
     220: aload_0
     221: dup
     222: getfield      #55                 // Field tabs:I
     225: iconst_1
     226: iadd
     227: putfield      #55                 // Field tabs:I
     230: aload_0
     231: aload_2
     232: invokevirtual #116                // Method genCommonBlock:(Lantlr/AlternativeBlock;)V
     235: aload_0
     236: ldc           #35                 // String
     238: invokevirtual #59                 // Method _println:(Ljava/lang/String;)V
     241: aload_0
     242: dup
     243: getfield      #55                 // Field tabs:I
     246: iconst_1
     247: isub
     248: putfield      #55                 // Field tabs:I
     251: aload_0
     252: ldc           #178                // String </para>
     254: invokevirtual #59                 // Method _println:(Ljava/lang/String;)V
     257: aload_0
     258: new           #8                  // class java/lang/StringBuffer
     261: dup
     262: invokespecial #9                  // Method java/lang/StringBuffer."<init>":()V
     265: ldc           #181                // String </section><!-- section \"
     267: invokevirtual #13                 // Method java/lang/StringBuffer.append:(Ljava/lang/String;)Ljava/lang/StringBuffer;
     270: aload_1
     271: invokevirtual #175                // Method antlr/RuleSymbol.getId:()Ljava/lang/String;
     274: invokevirtual #13                 // Method java/lang/StringBuffer.append:(Ljava/lang/String;)Ljava/lang/StringBuffer;
     277: ldc           #182                // String \" -->
     279: invokevirtual #13                 // Method java/lang/StringBuffer.append:(Ljava/lang/String;)Ljava/lang/StringBuffer;
     282: invokevirtual #19                 // Method java/lang/StringBuffer.toString:()Ljava/lang/String;
     285: invokevirtual #59                 // Method _println:(Ljava/lang/String;)V
     288: return

  protected void genSynPred(antlr.SynPredBlock);
    Code:
       0: return

  public void genTail();
    Code:
       0: aload_0
       1: ldc           #183                // String </chapter>
       3: invokevirtual #57                 // Method println:(Ljava/lang/String;)V
       6: aload_0
       7: ldc           #184                // String </book>
       9: invokevirtual #57                 // Method println:(Ljava/lang/String;)V
      12: return

  protected void genTokenTypes(antlr.TokenManager) throws java.io.IOException;
    Code:
       0: aload_0
       1: getfield      #29                 // Field antlrTool:Lantlr/Tool;
       4: new           #8                  // class java/lang/StringBuffer
       7: dup
       8: invokespecial #9                  // Method java/lang/StringBuffer."<init>":()V
      11: ldc           #48                 // String Generating
      13: invokevirtual #13                 // Method java/lang/StringBuffer.append:(Ljava/lang/String;)Ljava/lang/StringBuffer;
      16: aload_1
      17: invokeinterface #185,  1          // InterfaceMethod antlr/TokenManager.getName:()Ljava/lang/String;
      22: invokevirtual #13                 // Method java/lang/StringBuffer.append:(Ljava/lang/String;)Ljava/lang/StringBuffer;
      25: getstatic     #186                // Field TokenTypesFileSuffix:Ljava/lang/String;
      28: invokevirtual #13                 // Method java/lang/StringBuffer.append:(Ljava/lang/String;)Ljava/lang/StringBuffer;
      31: getstatic     #187                // Field TokenTypesFileExt:Ljava/lang/String;
      34: invokevirtual #13                 // Method java/lang/StringBuffer.append:(Ljava/lang/String;)Ljava/lang/StringBuffer;
      37: invokevirtual #19                 // Method java/lang/StringBuffer.toString:()Ljava/lang/String;
      40: invokevirtual #52                 // Method antlr/Tool.reportProgress:(Ljava/lang/String;)V
      43: aload_0
      44: aload_0
      45: getfield      #29                 // Field antlrTool:Lantlr/Tool;
      48: new           #8                  // class java/lang/StringBuffer
      51: dup
      52: invokespecial #9                  // Method java/lang/StringBuffer."<init>":()V
      55: aload_1
      56: invokeinterface #185,  1          // InterfaceMethod antlr/TokenManager.getName:()Ljava/lang/String;
      61: invokevirtual #13                 // Method java/lang/StringBuffer.append:(Ljava/lang/String;)Ljava/lang/StringBuffer;
      64: getstatic     #186                // Field TokenTypesFileSuffix:Ljava/lang/String;
      67: invokevirtual #13                 // Method java/lang/StringBuffer.append:(Ljava/lang/String;)Ljava/lang/StringBuffer;
      70: getstatic     #187                // Field TokenTypesFileExt:Ljava/lang/String;
      73: invokevirtual #13                 // Method java/lang/StringBuffer.append:(Ljava/lang/String;)Ljava/lang/StringBuffer;
      76: invokevirtual #19                 // Method java/lang/StringBuffer.toString:()Ljava/lang/String;
      79: invokevirtual #53                 // Method antlr/Tool.openOutputFile:(Ljava/lang/String;)Ljava/io/PrintWriter;
      82: putfield      #54                 // Field currentOutput:Ljava/io/PrintWriter;
      85: aload_0
      86: iconst_0
      87: putfield      #55                 // Field tabs:I
      90: aload_0
      91: invokevirtual #56                 // Method genHeader:()V
      94: aload_0
      95: ldc           #35                 // String
      97: invokevirtual #57                 // Method println:(Ljava/lang/String;)V
     100: aload_0
     101: ldc           #188                // String *** Tokens used by the parser
     103: invokevirtual #57                 // Method println:(Ljava/lang/String;)V
     106: aload_0
     107: ldc           #189                // String This is a list of the token numeric values and the corresponding
     109: invokevirtual #57                 // Method println:(Ljava/lang/String;)V
     112: aload_0
     113: ldc           #190                // String token identifiers.  Some tokens are literals, and because of that
     115: invokevirtual #57                 // Method println:(Ljava/lang/String;)V
     118: aload_0
     119: ldc           #191                // String they have no identifiers.  Literals are double-quoted.
     121: invokevirtual #57                 // Method println:(Ljava/lang/String;)V
     124: aload_0
     125: dup
     126: getfield      #55                 // Field tabs:I
     129: iconst_1
     130: iadd
     131: putfield      #55                 // Field tabs:I
     134: aload_1
     135: invokeinterface #192,  1          // InterfaceMethod antlr/TokenManager.getVocabulary:()Lantlr/collections/impl/Vector;
     140: astore_2
     141: iconst_4
     142: istore_3
     143: iload_3
     144: aload_2
     145: invokevirtual #101                // Method antlr/collections/impl/Vector.size:()I
     148: if_icmpge     200
     151: aload_2
     152: iload_3
     153: invokevirtual #193                // Method antlr/collections/impl/Vector.elementAt:(I)Ljava/lang/Object;
     156: checkcast     #194                // class java/lang/String
     159: astore        4
     161: aload         4
     163: ifnull        194
     166: aload_0
     167: new           #8                  // class java/lang/StringBuffer
     170: dup
     171: invokespecial #9                  // Method java/lang/StringBuffer."<init>":()V
     174: aload         4
     176: invokevirtual #13                 // Method java/lang/StringBuffer.append:(Ljava/lang/String;)Ljava/lang/StringBuffer;
     179: ldc           #195                // String  =
     181: invokevirtual #13                 // Method java/lang/StringBuffer.append:(Ljava/lang/String;)Ljava/lang/StringBuffer;
     184: iload_3
     185: invokevirtual #196                // Method java/lang/StringBuffer.append:(I)Ljava/lang/StringBuffer;
     188: invokevirtual #19                 // Method java/lang/StringBuffer.toString:()Ljava/lang/String;
     191: invokevirtual #57                 // Method println:(Ljava/lang/String;)V
     194: iinc          3, 1
     197: goto          143
     200: aload_0
     201: dup
     202: getfield      #55                 // Field tabs:I
     205: iconst_1
     206: isub
     207: putfield      #55                 // Field tabs:I
     210: aload_0
     211: ldc           #197                // String *** End of tokens used by the parser
     213: invokevirtual #57                 // Method println:(Ljava/lang/String;)V
     216: aload_0
     217: getfield      #54                 // Field currentOutput:Ljava/io/PrintWriter;
     220: invokevirtual #72                 // Method java/io/PrintWriter.close:()V
     223: aload_0
     224: aconst_null
     225: putfield      #54                 // Field currentOutput:Ljava/io/PrintWriter;
     228: return

  protected java.lang.String processActionForSpecialSymbols(java.lang.String, int, antlr.RuleBlock, antlr.ActionTransInfo);
    Code:
       0: aload_1
       1: areturn

  public java.lang.String getASTCreateString(antlr.collections.impl.Vector);
    Code:
       0: aconst_null
       1: areturn

  public java.lang.String getASTCreateString(antlr.GrammarAtom, java.lang.String);
    Code:
       0: aconst_null
       1: areturn

  public java.lang.String mapTreeId(java.lang.String, antlr.ActionTransInfo);
    Code:
       0: aload_1
       1: areturn

  public void printSet(int, int, antlr.Lookahead);
    Code:
       0: iconst_5
       1: istore        4
       3: aload_3
       4: getfield      #198                // Field antlr/Lookahead.fset:Lantlr/collections/impl/BitSet;
       7: invokevirtual #199                // Method antlr/collections/impl/BitSet.toArray:()[I
      10: astore        5
      12: iload_1
      13: iconst_1
      14: if_icmpeq     48
      17: aload_0
      18: new           #8                  // class java/lang/StringBuffer
      21: dup
      22: invokespecial #9                  // Method java/lang/StringBuffer."<init>":()V
      25: ldc           #200                // String k==
      27: invokevirtual #13                 // Method java/lang/StringBuffer.append:(Ljava/lang/String;)Ljava/lang/StringBuffer;
      30: iload_2
      31: invokevirtual #196                // Method java/lang/StringBuffer.append:(I)Ljava/lang/StringBuffer;
      34: ldc           #201                // String : {
      36: invokevirtual #13                 // Method java/lang/StringBuffer.append:(Ljava/lang/String;)Ljava/lang/StringBuffer;
      39: invokevirtual #19                 // Method java/lang/StringBuffer.toString:()Ljava/lang/String;
      42: invokevirtual #46                 // Method print:(Ljava/lang/String;)V
      45: goto          54
      48: aload_0
      49: ldc           #202                // String {
      51: invokevirtual #46                 // Method print:(Ljava/lang/String;)V
      54: aload         5
      56: arraylength
      57: iload         4
      59: if_icmple     84
      62: aload_0
      63: ldc           #35                 // String
      65: invokevirtual #59                 // Method _println:(Ljava/lang/String;)V
      68: aload_0
      69: dup
      70: getfield      #55                 // Field tabs:I
      73: iconst_1
      74: iadd
      75: putfield      #55                 // Field tabs:I
      78: aload_0
      79: ldc           #35                 // String
      81: invokevirtual #46                 // Method print:(Ljava/lang/String;)V
      84: iconst_0
      85: istore        6
      87: iconst_0
      88: istore        7
      90: iload         7
      92: aload         5
      94: arraylength
      95: if_icmpge     200
      98: iinc          6, 1
     101: iload         6
     103: iload         4
     105: if_icmple     123
     108: aload_0
     109: ldc           #35                 // String
     111: invokevirtual #59                 // Method _println:(Ljava/lang/String;)V
     114: aload_0
     115: ldc           #35                 // String
     117: invokevirtual #46                 // Method print:(Ljava/lang/String;)V
     120: iconst_0
     121: istore        6
     123: aload_0
     124: getfield      #3                  // Field doingLexRules:Z
     127: ifeq          151
     130: aload_0
     131: aload_0
     132: getfield      #7                  // Field charFormatter:Lantlr/CharFormatter;
     135: aload         5
     137: iload         7
     139: iaload
     140: invokeinterface #203,  2          // InterfaceMethod antlr/CharFormatter.literalChar:(I)Ljava/lang/String;
     145: invokevirtual #39                 // Method _print:(Ljava/lang/String;)V
     148: goto          178
     151: aload_0
     152: aload_0
     153: getfield      #49                 // Field grammar:Lantlr/Grammar;
     156: getfield      #204                // Field antlr/Grammar.tokenManager:Lantlr/TokenManager;
     159: invokeinterface #192,  1          // InterfaceMethod antlr/TokenManager.getVocabulary:()Lantlr/collections/impl/Vector;
     164: aload         5
     166: iload         7
     168: iaload
     169: invokevirtual #193                // Method antlr/collections/impl/Vector.elementAt:(I)Ljava/lang/Object;
     172: checkcast     #194                // class java/lang/String
     175: invokevirtual #39                 // Method _print:(Ljava/lang/String;)V
     178: iload         7
     180: aload         5
     182: arraylength
     183: iconst_1
     184: isub
     185: if_icmpeq     194
     188: aload_0
     189: ldc           #205                // String ,
     191: invokevirtual #39                 // Method _print:(Ljava/lang/String;)V
     194: iinc          7, 1
     197: goto          90
     200: aload         5
     202: arraylength
     203: iload         4
     205: if_icmple     230
     208: aload_0
     209: ldc           #35                 // String
     211: invokevirtual #59                 // Method _println:(Ljava/lang/String;)V
     214: aload_0
     215: dup
     216: getfield      #55                 // Field tabs:I
     219: iconst_1
     220: isub
     221: putfield      #55                 // Field tabs:I
     224: aload_0
     225: ldc           #35                 // String
     227: invokevirtual #46                 // Method print:(Ljava/lang/String;)V
     230: aload_0
     231: ldc           #206                // String  }
     233: invokevirtual #59                 // Method _println:(Ljava/lang/String;)V
     236: return
}
