Compiled from "MigrationsModule.java"
public class org.graylog2.migrations.MigrationsModule extends org.graylog2.plugin.PluginModule {
  public org.graylog2.migrations.MigrationsModule();
    Code:
       0: aload_0
       1: invokespecial #1                  // Method org/graylog2/plugin/PluginModule."<init>":()V
       4: return

  protected void configure();
    Code:
       0: aload_0
       1: ldc           #2                  // class org/graylog2/migrations/V20151210140600_ElasticsearchConfigMigration
       3: invokevirtual #3                  // Method addMigration:(Ljava/lang/Class;)V
       6: aload_0
       7: ldc           #4                  // class org/graylog2/migrations/V20161116172100_DefaultIndexSetMigration
       9: invokevirtual #3                  // Method addMigration:(Ljava/lang/Class;)V
      12: aload_0
      13: ldc           #5                  // class org/graylog2/migrations/V20161116172200_CreateDefaultStreamMigration
      15: invokevirtual #3                  // Method addMigration:(Ljava/lang/Class;)V
      18: aload_0
      19: ldc           #6                  // class org/graylog2/migrations/V20161122174500_AssignIndexSetsToStreamsMigration
      21: invokevirtual #3                  // Method addMigration:(Ljava/lang/Class;)V
      24: aload_0
      25: ldc           #7                  // class org/graylog2/migrations/V20161124104700_AddRetentionRotationAndDefaultFlagToIndexSetMigration
      27: invokevirtual #3                  // Method addMigration:(Ljava/lang/Class;)V
      30: aload_0
      31: ldc           #8                  // class org/graylog2/migrations/V20161125142400_EmailAlarmCallbackMigration
      33: invokevirtual #3                  // Method addMigration:(Ljava/lang/Class;)V
      36: aload_0
      37: ldc           #9                  // class org/graylog2/migrations/V20161125161400_AlertReceiversMigration
      39: invokevirtual #3                  // Method addMigration:(Ljava/lang/Class;)V
      42: aload_0
      43: ldc           #10                 // class org/graylog2/migrations/V20161130141500_DefaultStreamRecalcIndexRanges
      45: invokevirtual #3                  // Method addMigration:(Ljava/lang/Class;)V
      48: aload_0
      49: ldc           #11                 // class org/graylog2/migrations/V20161215163900_MoveIndexSetDefaultConfig
      51: invokevirtual #3                  // Method addMigration:(Ljava/lang/Class;)V
      54: aload_0
      55: ldc           #12                 // class org/graylog2/migrations/V20161216123500_DefaultIndexSetMigration
      57: invokevirtual #3                  // Method addMigration:(Ljava/lang/Class;)V
      60: aload_0
      61: ldc           #13                 // class org/graylog2/migrations/V20170110150100_FixAlertConditionsMigration
      63: invokevirtual #3                  // Method addMigration:(Ljava/lang/Class;)V
      66: aload_0
      67: ldc           #14                 // class org/graylog2/migrations/V20170607164210_MigrateReopenedIndicesToAliases
      69: invokevirtual #3                  // Method addMigration:(Ljava/lang/Class;)V
      72: aload_0
      73: ldc           #15                 // class org/graylog2/migrations/V20180214093600_AdjustDashboardPositionToNewResolution
      75: invokevirtual #3                  // Method addMigration:(Ljava/lang/Class;)V
      78: aload_0
      79: ldc           #16                 // class org/graylog2/migrations/V2018070614390000_EnforceUniqueGrokPatterns
      81: invokevirtual #3                  // Method addMigration:(Ljava/lang/Class;)V
      84: aload_0
      85: ldc           #17                 // class org/graylog2/migrations/V20180718155800_AddContentPackIdAndRev
      87: invokevirtual #3                  // Method addMigration:(Ljava/lang/Class;)V
      90: aload_0
      91: ldc           #18                 // class org/graylog2/migrations/V20180924111644_AddDefaultGrokPatterns
      93: invokevirtual #3                  // Method addMigration:(Ljava/lang/Class;)V
      96: return
}
