Compiled from "V20161130141500_DefaultStreamRecalcIndexRanges.java"
public class org.graylog2.migrations.V20161130141500_DefaultStreamRecalcIndexRanges extends org.graylog2.migrations.Migration {
  private static final org.slf4j.Logger LOG;

  private final org.graylog2.indexer.IndexSetRegistry indexSetRegistry;

  private final org.graylog2.indexer.indexset.IndexSetService indexSetService;

  private final org.graylog2.indexer.MongoIndexSet$Factory indexSetFactory;

  private final org.graylog2.indexer.ranges.IndexRangeService indexRangeService;

  private final org.graylog2.indexer.ranges.CreateNewSingleIndexRangeJob$Factory rebuildIndexRangeJobFactory;

  private final org.graylog2.indexer.cluster.Cluster cluster;

  public org.graylog2.migrations.V20161130141500_DefaultStreamRecalcIndexRanges(org.graylog2.indexer.IndexSetRegistry, org.graylog2.indexer.indexset.IndexSetService, org.graylog2.indexer.MongoIndexSet$Factory, org.graylog2.indexer.ranges.IndexRangeService, org.graylog2.indexer.ranges.CreateNewSingleIndexRangeJob$Factory, org.graylog2.indexer.cluster.Cluster);
    Code:
       0: aload_0
       1: invokespecial #1                  // Method org/graylog2/migrations/Migration."<init>":()V
       4: aload_0
       5: aload_1
       6: putfield      #2                  // Field indexSetRegistry:Lorg/graylog2/indexer/IndexSetRegistry;
       9: aload_0
      10: aload_2
      11: putfield      #3                  // Field indexSetService:Lorg/graylog2/indexer/indexset/IndexSetService;
      14: aload_0
      15: aload_3
      16: putfield      #4                  // Field indexSetFactory:Lorg/graylog2/indexer/MongoIndexSet$Factory;
      19: aload_0
      20: aload         4
      22: putfield      #5                  // Field indexRangeService:Lorg/graylog2/indexer/ranges/IndexRangeService;
      25: aload_0
      26: aload         5
      28: putfield      #6                  // Field rebuildIndexRangeJobFactory:Lorg/graylog2/indexer/ranges/CreateNewSingleIndexRangeJob$Factory;
      31: aload_0
      32: aload         6
      34: putfield      #7                  // Field cluster:Lorg/graylog2/indexer/cluster/Cluster;
      37: return

  public java.time.ZonedDateTime createdAt();
    Code:
       0: ldc           #8                  // String 2016-11-30T14:15:00Z
       2: invokestatic  #9                  // Method java/time/ZonedDateTime.parse:(Ljava/lang/CharSequence;)Ljava/time/ZonedDateTime;
       5: areturn

  public void upgrade();
    Code:
       0: aload_0
       1: getfield      #2                  // Field indexSetRegistry:Lorg/graylog2/indexer/IndexSetRegistry;
       4: invokeinterface #10,  1           // InterfaceMethod org/graylog2/indexer/IndexSetRegistry.getDefault:()Lorg/graylog2/indexer/IndexSet;
       9: astore_1
      10: goto          55
      13: astore_2
      14: aload_0
      15: getfield      #3                  // Field indexSetService:Lorg/graylog2/indexer/indexset/IndexSetService;
      18: ldc           #12                 // String default
      20: iconst_1
      21: invokestatic  #13                 // Method java/lang/Boolean.valueOf:(Z)Ljava/lang/Boolean;
      24: invokestatic  #14                 // Method org/mongojack/DBQuery.is:(Ljava/lang/String;Ljava/lang/Object;)Lorg/mongojack/DBQuery$Query;
      27: invokeinterface #15,  2           // InterfaceMethod org/graylog2/indexer/indexset/IndexSetService.findOne:(Lorg/mongojack/DBQuery$Query;)Ljava/util/Optional;
      32: invokedynamic #16,  0             // InvokeDynamic #0:get:()Ljava/util/function/Supplier;
      37: invokevirtual #17                 // Method java/util/Optional.orElseThrow:(Ljava/util/function/Supplier;)Ljava/lang/Object;
      40: checkcast     #18                 // class org/graylog2/indexer/indexset/IndexSetConfig
      43: astore_3
      44: aload_0
      45: getfield      #4                  // Field indexSetFactory:Lorg/graylog2/indexer/MongoIndexSet$Factory;
      48: aload_3
      49: invokeinterface #19,  2           // InterfaceMethod org/graylog2/indexer/MongoIndexSet$Factory.create:(Lorg/graylog2/indexer/indexset/IndexSetConfig;)Lorg/graylog2/indexer/MongoIndexSet;
      54: astore_1
      55: aload_1
      56: astore_2
      57: aload_0
      58: getfield      #7                  // Field cluster:Lorg/graylog2/indexer/cluster/Cluster;
      61: invokevirtual #20                 // Method org/graylog2/indexer/cluster/Cluster.isConnected:()Z
      64: ifne          101
      67: getstatic     #21                 // Field LOG:Lorg/slf4j/Logger;
      70: ldc           #22                 // String Cluster not connected yet, delaying migration until it is reachable.
      72: invokeinterface #23,  2           // InterfaceMethod org/slf4j/Logger.info:(Ljava/lang/String;)V
      77: aload_0
      78: getfield      #7                  // Field cluster:Lorg/graylog2/indexer/cluster/Cluster;
      81: invokevirtual #24                 // Method org/graylog2/indexer/cluster/Cluster.waitForConnectedAndDeflectorHealthy:()V
      84: goto          101
      87: astore_3
      88: getstatic     #21                 // Field LOG:Lorg/slf4j/Logger;
      91: ldc           #27                 // String Interrupted or timed out waiting for Elasticsearch cluster, checking again.
      93: invokeinterface #28,  2           // InterfaceMethod org/slf4j/Logger.warn:(Ljava/lang/String;)V
      98: goto          77
     101: aload_0
     102: getfield      #5                  // Field indexRangeService:Lorg/graylog2/indexer/ranges/IndexRangeService;
     105: invokeinterface #29,  1           // InterfaceMethod org/graylog2/indexer/ranges/IndexRangeService.findAll:()Ljava/util/SortedSet;
     110: invokeinterface #30,  1           // InterfaceMethod java/util/SortedSet.stream:()Ljava/util/stream/Stream;
     115: aload_2
     116: invokedynamic #31,  0             // InvokeDynamic #1:test:(Lorg/graylog2/indexer/IndexSet;)Ljava/util/function/Predicate;
     121: invokeinterface #32,  2           // InterfaceMethod java/util/stream/Stream.filter:(Ljava/util/function/Predicate;)Ljava/util/stream/Stream;
     126: invokedynamic #33,  0             // InvokeDynamic #2:test:()Ljava/util/function/Predicate;
     131: invokeinterface #32,  2           // InterfaceMethod java/util/stream/Stream.filter:(Ljava/util/function/Predicate;)Ljava/util/stream/Stream;
     136: invokedynamic #34,  0             // InvokeDynamic #3:apply:()Ljava/util/function/Function;
     141: invokeinterface #35,  2           // InterfaceMethod java/util/stream/Stream.map:(Ljava/util/function/Function;)Ljava/util/stream/Stream;
     146: invokestatic  #36                 // Method java/util/stream/Collectors.toSet:()Ljava/util/stream/Collector;
     149: invokeinterface #37,  2           // InterfaceMethod java/util/stream/Stream.collect:(Ljava/util/stream/Collector;)Ljava/lang/Object;
     154: checkcast     #38                 // class java/util/Set
     157: astore_3
     158: aload_3
     159: invokeinterface #39,  1           // InterfaceMethod java/util/Set.size:()I
     164: ifne          168
     167: return
     168: aload_2
     169: invokeinterface #40,  1           // InterfaceMethod org/graylog2/indexer/IndexSet.getActiveWriteIndex:()Ljava/lang/String;
     174: astore        4
     176: goto          194
     179: astore        5
     181: getstatic     #21                 // Field LOG:Lorg/slf4j/Logger;
     184: ldc           #42                 // String Multiple write targets found for write alias. Cannot continue to assign streams to older indices
     186: aload         5
     188: invokeinterface #43,  3           // InterfaceMethod org/slf4j/Logger.error:(Ljava/lang/String;Ljava/lang/Throwable;)V
     193: return
     194: aload_2
     195: invokeinterface #44,  1           // InterfaceMethod org/graylog2/indexer/IndexSet.getManagedIndices:()[Ljava/lang/String;
     200: astore        5
     202: aload         5
     204: arraylength
     205: istore        6
     207: iconst_0
     208: istore        7
     210: iload         7
     212: iload         6
     214: if_icmpge     296
     217: aload         5
     219: iload         7
     221: aaload
     222: astore        8
     224: aload         8
     226: aload         4
     228: invokevirtual #45                 // Method java/lang/String.equals:(Ljava/lang/Object;)Z
     231: ifeq          237
     234: goto          290
     237: aload_3
     238: aload         8
     240: invokeinterface #46,  2           // InterfaceMethod java/util/Set.contains:(Ljava/lang/Object;)Z
     245: ifne          251
     248: goto          290
     251: getstatic     #21                 // Field LOG:Lorg/slf4j/Logger;
     254: ldc           #47                 // String Recalculating streams in index {}
     256: aload         8
     258: invokeinterface #48,  3           // InterfaceMethod org/slf4j/Logger.info:(Ljava/lang/String;Ljava/lang/Object;)V
     263: aload_0
     264: getfield      #6                  // Field rebuildIndexRangeJobFactory:Lorg/graylog2/indexer/ranges/CreateNewSingleIndexRangeJob$Factory;
     267: aload_0
     268: getfield      #2                  // Field indexSetRegistry:Lorg/graylog2/indexer/IndexSetRegistry;
     271: invokeinterface #49,  1           // InterfaceMethod org/graylog2/indexer/IndexSetRegistry.getAll:()Ljava/util/Set;
     276: aload         8
     278: invokeinterface #50,  3           // InterfaceMethod org/graylog2/indexer/ranges/CreateNewSingleIndexRangeJob$Factory.create:(Ljava/util/Set;Ljava/lang/String;)Lorg/graylog2/indexer/ranges/CreateNewSingleIndexRangeJob;
     283: astore        9
     285: aload         9
     287: invokevirtual #51                 // Method org/graylog2/indexer/ranges/CreateNewSingleIndexRangeJob.execute:()V
     290: iinc          7, 1
     293: goto          210
     296: return
    Exception table:
       from    to  target type
           0    10    13   Class java/lang/IllegalStateException
          77    84    87   Class java/lang/InterruptedException
          77    84    87   Class java/util/concurrent/TimeoutException
         168   176   179   Class org/graylog2/indexer/indices/TooManyAliasesException

  private static boolean lambda$upgrade$2(org.graylog2.indexer.ranges.IndexRange);
    Code:
       0: aload_0
       1: invokeinterface #52,  1           // InterfaceMethod org/graylog2/indexer/ranges/IndexRange.streamIds:()Ljava/util/List;
       6: ifnonnull     13
       9: iconst_1
      10: goto          14
      13: iconst_0
      14: ireturn

  private static boolean lambda$upgrade$1(org.graylog2.indexer.IndexSet, org.graylog2.indexer.ranges.IndexRange);
    Code:
       0: aload_0
       1: aload_1
       2: invokeinterface #53,  1           // InterfaceMethod org/graylog2/indexer/ranges/IndexRange.indexName:()Ljava/lang/String;
       7: invokeinterface #54,  2           // InterfaceMethod org/graylog2/indexer/IndexSet.isManagedIndex:(Ljava/lang/String;)Z
      12: ireturn

  private static java.lang.IllegalStateException lambda$upgrade$0();
    Code:
       0: new           #11                 // class java/lang/IllegalStateException
       3: dup
       4: ldc           #55                 // String No default index set configured! This is a bug!
       6: invokespecial #56                 // Method java/lang/IllegalStateException."<init>":(Ljava/lang/String;)V
       9: areturn

  static {};
    Code:
       0: ldc           #57                 // class org/graylog2/migrations/V20161130141500_DefaultStreamRecalcIndexRanges
       2: invokestatic  #58                 // Method org/slf4j/LoggerFactory.getLogger:(Ljava/lang/Class;)Lorg/slf4j/Logger;
       5: putstatic     #21                 // Field LOG:Lorg/slf4j/Logger;
       8: return
}
