Compiled from "V20161125142400_EmailAlarmCallbackMigration.java"
public abstract class org.graylog2.migrations.V20161125142400_EmailAlarmCallbackMigration$MigrationCompleted {
  private static final java.lang.String FIELD_CALLBACK_IDS;

  public org.graylog2.migrations.V20161125142400_EmailAlarmCallbackMigration$MigrationCompleted();
    Code:
       0: aload_0
       1: invokespecial #1                  // Method java/lang/Object."<init>":()V
       4: return

  public abstract java.util.Map<java.lang.String, java.util.Optional<java.lang.String>> callbackIds();

  public static org.graylog2.migrations.V20161125142400_EmailAlarmCallbackMigration$MigrationCompleted create(java.util.Map<java.lang.String, java.util.Optional<java.lang.String>>);
    Code:
       0: new           #2                  // class org/graylog2/migrations/AutoValue_V20161125142400_EmailAlarmCallbackMigration_MigrationCompleted
       3: dup
       4: aload_0
       5: invokespecial #3                  // Method org/graylog2/migrations/AutoValue_V20161125142400_EmailAlarmCallbackMigration_MigrationCompleted."<init>":(Ljava/util/Map;)V
       8: areturn
}
