Compiled from "AnnotationValueShortFormProvider.java"
public class org.protege.editor.owl.ui.renderer.AnnotationValueShortFormProvider implements org.semanticweb.owlapi.util.ShortFormProvider {
  private final org.semanticweb.owlapi.model.OWLOntologySetProvider ontologySetProvider;

  private final org.semanticweb.owlapi.util.ShortFormProvider alternateShortFormProvider;

  private final org.semanticweb.owlapi.util.IRIShortFormProvider alternateIRIShortFormProvider;

  private final java.util.List<org.semanticweb.owlapi.model.OWLAnnotationProperty> annotationProperties;

  private final java.util.Map<org.semanticweb.owlapi.model.OWLAnnotationProperty, java.util.List<java.lang.String>> preferredLanguageMap;

  private org.semanticweb.owlapi.util.StringAnnotationVisitor literalRenderer;

  public org.protege.editor.owl.ui.renderer.AnnotationValueShortFormProvider(java.util.List<org.semanticweb.owlapi.model.OWLAnnotationProperty>, java.util.Map<org.semanticweb.owlapi.model.OWLAnnotationProperty, java.util.List<java.lang.String>>, org.semanticweb.owlapi.model.OWLOntologySetProvider);
    Code:
       0: aload_0
       1: aload_1
       2: aload_2
       3: aload_3
       4: new           #1                  // class org/semanticweb/owlapi/util/SimpleShortFormProvider
       7: dup
       8: invokespecial #2                  // Method org/semanticweb/owlapi/util/SimpleShortFormProvider."<init>":()V
      11: invokespecial #3                  // Method "<init>":(Ljava/util/List;Ljava/util/Map;Lorg/semanticweb/owlapi/model/OWLOntologySetProvider;Lorg/semanticweb/owlapi/util/ShortFormProvider;)V
      14: return

  public org.protege.editor.owl.ui.renderer.AnnotationValueShortFormProvider(java.util.List<org.semanticweb.owlapi.model.OWLAnnotationProperty>, java.util.Map<org.semanticweb.owlapi.model.OWLAnnotationProperty, java.util.List<java.lang.String>>, org.semanticweb.owlapi.model.OWLOntologySetProvider, org.semanticweb.owlapi.util.ShortFormProvider);
    Code:
       0: aload_0
       1: aload_3
       2: aload         4
       4: new           #4                  // class org/semanticweb/owlapi/util/SimpleIRIShortFormProvider
       7: dup
       8: invokespecial #5                  // Method org/semanticweb/owlapi/util/SimpleIRIShortFormProvider."<init>":()V
      11: aload_1
      12: aload_2
      13: invokespecial #6                  // Method "<init>":(Lorg/semanticweb/owlapi/model/OWLOntologySetProvider;Lorg/semanticweb/owlapi/util/ShortFormProvider;Lorg/semanticweb/owlapi/util/IRIShortFormProvider;Ljava/util/List;Ljava/util/Map;)V
      16: return

  public org.protege.editor.owl.ui.renderer.AnnotationValueShortFormProvider(org.semanticweb.owlapi.model.OWLOntologySetProvider, org.semanticweb.owlapi.util.ShortFormProvider, org.semanticweb.owlapi.util.IRIShortFormProvider, java.util.List<org.semanticweb.owlapi.model.OWLAnnotationProperty>, java.util.Map<org.semanticweb.owlapi.model.OWLAnnotationProperty, java.util.List<java.lang.String>>);
    Code:
       0: aload_0
       1: invokespecial #7                  // Method java/lang/Object."<init>":()V
       4: aload_0
       5: new           #8                  // class org/semanticweb/owlapi/util/StringAnnotationVisitor
       8: dup
       9: invokespecial #9                  // Method org/semanticweb/owlapi/util/StringAnnotationVisitor."<init>":()V
      12: putfield      #10                 // Field literalRenderer:Lorg/semanticweb/owlapi/util/StringAnnotationVisitor;
      15: aload_0
      16: aload_1
      17: ldc           #11                 // String ontologySetProvider cannot be null
      19: invokestatic  #12                 // Method org/semanticweb/owlapi/util/OWLAPIPreconditions.checkNotNull:(Ljava/lang/Object;Ljava/lang/String;)Ljava/lang/Object;
      22: checkcast     #13                 // class org/semanticweb/owlapi/model/OWLOntologySetProvider
      25: putfield      #14                 // Field ontologySetProvider:Lorg/semanticweb/owlapi/model/OWLOntologySetProvider;
      28: aload_0
      29: aload_2
      30: ldc           #15                 // String alternateShortFormProvider cannot be null
      32: invokestatic  #12                 // Method org/semanticweb/owlapi/util/OWLAPIPreconditions.checkNotNull:(Ljava/lang/Object;Ljava/lang/String;)Ljava/lang/Object;
      35: checkcast     #16                 // class org/semanticweb/owlapi/util/ShortFormProvider
      38: putfield      #17                 // Field alternateShortFormProvider:Lorg/semanticweb/owlapi/util/ShortFormProvider;
      41: aload_0
      42: aload_3
      43: ldc           #18                 // String alternateIRIShortFormProvider cannot be null
      45: invokestatic  #12                 // Method org/semanticweb/owlapi/util/OWLAPIPreconditions.checkNotNull:(Ljava/lang/Object;Ljava/lang/String;)Ljava/lang/Object;
      48: checkcast     #19                 // class org/semanticweb/owlapi/util/IRIShortFormProvider
      51: putfield      #20                 // Field alternateIRIShortFormProvider:Lorg/semanticweb/owlapi/util/IRIShortFormProvider;
      54: aload_0
      55: aload         4
      57: ldc           #21                 // String annotationProperties cannot be null
      59: invokestatic  #12                 // Method org/semanticweb/owlapi/util/OWLAPIPreconditions.checkNotNull:(Ljava/lang/Object;Ljava/lang/String;)Ljava/lang/Object;
      62: checkcast     #22                 // class java/util/List
      65: putfield      #23                 // Field annotationProperties:Ljava/util/List;
      68: aload_0
      69: aload         5
      71: ldc           #24                 // String preferredLanguageMap cannot be null
      73: invokestatic  #12                 // Method org/semanticweb/owlapi/util/OWLAPIPreconditions.checkNotNull:(Ljava/lang/Object;Ljava/lang/String;)Ljava/lang/Object;
      76: checkcast     #25                 // class java/util/Map
      79: putfield      #26                 // Field preferredLanguageMap:Ljava/util/Map;
      82: return

  public java.lang.String getShortForm(org.semanticweb.owlapi.model.OWLEntity);
    Code:
       0: aload_0
       1: getfield      #23                 // Field annotationProperties:Ljava/util/List;
       4: invokeinterface #27,  1           // InterfaceMethod java/util/List.iterator:()Ljava/util/Iterator;
       9: astore_2
      10: aload_2
      11: invokeinterface #28,  1           // InterfaceMethod java/util/Iterator.hasNext:()Z
      16: ifeq          169
      19: aload_2
      20: invokeinterface #29,  1           // InterfaceMethod java/util/Iterator.next:()Ljava/lang/Object;
      25: checkcast     #30                 // class org/semanticweb/owlapi/model/OWLAnnotationProperty
      28: astore_3
      29: new           #31                 // class org/protege/editor/owl/ui/renderer/AnnotationValueShortFormProvider$AnnotationLanguageFilter
      32: dup
      33: aload_3
      34: aload_0
      35: getfield      #26                 // Field preferredLanguageMap:Ljava/util/Map;
      38: aload_3
      39: invokeinterface #32,  2           // InterfaceMethod java/util/Map.get:(Ljava/lang/Object;)Ljava/lang/Object;
      44: checkcast     #22                 // class java/util/List
      47: invokespecial #33                 // Method org/protege/editor/owl/ui/renderer/AnnotationValueShortFormProvider$AnnotationLanguageFilter."<init>":(Lorg/semanticweb/owlapi/model/OWLAnnotationProperty;Ljava/util/List;)V
      50: astore        4
      52: aload_0
      53: getfield      #14                 // Field ontologySetProvider:Lorg/semanticweb/owlapi/model/OWLOntologySetProvider;
      56: invokeinterface #34,  1           // InterfaceMethod org/semanticweb/owlapi/model/OWLOntologySetProvider.getOntologies:()Ljava/util/Set;
      61: invokeinterface #35,  1           // InterfaceMethod java/util/Set.iterator:()Ljava/util/Iterator;
      66: astore        5
      68: aload         5
      70: invokeinterface #28,  1           // InterfaceMethod java/util/Iterator.hasNext:()Z
      75: ifeq          147
      78: aload         5
      80: invokeinterface #29,  1           // InterfaceMethod java/util/Iterator.next:()Ljava/lang/Object;
      85: checkcast     #36                 // class org/semanticweb/owlapi/model/OWLOntology
      88: astore        6
      90: aload         6
      92: aload_1
      93: invokeinterface #37,  1           // InterfaceMethod org/semanticweb/owlapi/model/OWLEntity.getIRI:()Lorg/semanticweb/owlapi/model/IRI;
      98: invokeinterface #38,  2           // InterfaceMethod org/semanticweb/owlapi/model/OWLOntology.getAnnotationAssertionAxioms:(Lorg/semanticweb/owlapi/model/OWLAnnotationSubject;)Ljava/util/Set;
     103: invokeinterface #35,  1           // InterfaceMethod java/util/Set.iterator:()Ljava/util/Iterator;
     108: astore        7
     110: aload         7
     112: invokeinterface #28,  1           // InterfaceMethod java/util/Iterator.hasNext:()Z
     117: ifeq          144
     120: aload         7
     122: invokeinterface #29,  1           // InterfaceMethod java/util/Iterator.next:()Ljava/lang/Object;
     127: checkcast     #39                 // class org/semanticweb/owlapi/model/OWLAxiom
     130: astore        8
     132: aload         8
     134: aload         4
     136: invokeinterface #40,  2           // InterfaceMethod org/semanticweb/owlapi/model/OWLAxiom.accept:(Lorg/semanticweb/owlapi/model/OWLObjectVisitor;)V
     141: goto          110
     144: goto          68
     147: aload         4
     149: invokevirtual #41                 // Method org/protege/editor/owl/ui/renderer/AnnotationValueShortFormProvider$AnnotationLanguageFilter.getMatch:()Lorg/semanticweb/owlapi/model/OWLObject;
     152: astore        5
     154: aload         5
     156: ifnull        166
     159: aload_0
     160: aload         5
     162: invokespecial #42                 // Method getRendering:(Lorg/semanticweb/owlapi/model/OWLObject;)Ljava/lang/String;
     165: areturn
     166: goto          10
     169: aload_0
     170: getfield      #17                 // Field alternateShortFormProvider:Lorg/semanticweb/owlapi/util/ShortFormProvider;
     173: aload_1
     174: invokeinterface #43,  2           // InterfaceMethod org/semanticweb/owlapi/util/ShortFormProvider.getShortForm:(Lorg/semanticweb/owlapi/model/OWLEntity;)Ljava/lang/String;
     179: areturn

  private java.lang.String getRendering(org.semanticweb.owlapi.model.OWLObject);
    Code:
       0: aload_1
       1: instanceof    #44                 // class org/semanticweb/owlapi/model/OWLLiteral
       4: ifeq          19
       7: aload_0
       8: getfield      #10                 // Field literalRenderer:Lorg/semanticweb/owlapi/util/StringAnnotationVisitor;
      11: aload_1
      12: checkcast     #44                 // class org/semanticweb/owlapi/model/OWLLiteral
      15: invokevirtual #45                 // Method org/semanticweb/owlapi/util/StringAnnotationVisitor.visit:(Lorg/semanticweb/owlapi/model/OWLLiteral;)Ljava/lang/String;
      18: areturn
      19: aload_1
      20: instanceof    #46                 // class org/semanticweb/owlapi/model/IRI
      23: ifeq          40
      26: aload_0
      27: getfield      #20                 // Field alternateIRIShortFormProvider:Lorg/semanticweb/owlapi/util/IRIShortFormProvider;
      30: aload_1
      31: checkcast     #46                 // class org/semanticweb/owlapi/model/IRI
      34: invokeinterface #47,  2           // InterfaceMethod org/semanticweb/owlapi/util/IRIShortFormProvider.getShortForm:(Lorg/semanticweb/owlapi/model/IRI;)Ljava/lang/String;
      39: areturn
      40: aload_0
      41: getfield      #17                 // Field alternateShortFormProvider:Lorg/semanticweb/owlapi/util/ShortFormProvider;
      44: aload_1
      45: checkcast     #48                 // class org/semanticweb/owlapi/model/OWLEntity
      48: invokeinterface #43,  2           // InterfaceMethod org/semanticweb/owlapi/util/ShortFormProvider.getShortForm:(Lorg/semanticweb/owlapi/model/OWLEntity;)Ljava/lang/String;
      53: areturn

  public java.util.List<org.semanticweb.owlapi.model.OWLAnnotationProperty> getAnnotationProperties();
    Code:
       0: aload_0
       1: getfield      #23                 // Field annotationProperties:Ljava/util/List;
       4: areturn

  public java.util.Map<org.semanticweb.owlapi.model.OWLAnnotationProperty, java.util.List<java.lang.String>> getPreferredLanguageMap();
    Code:
       0: aload_0
       1: getfield      #26                 // Field preferredLanguageMap:Ljava/util/Map;
       4: areturn

  public void dispose();
    Code:
       0: return

  public void setLiteralRenderer(org.semanticweb.owlapi.util.StringAnnotationVisitor);
    Code:
       0: aload_0
       1: aload_1
       2: invokestatic  #49                 // Method org/semanticweb/owlapi/util/OWLAPIPreconditions.checkNotNull:(Ljava/lang/Object;)Ljava/lang/Object;
       5: checkcast     #8                  // class org/semanticweb/owlapi/util/StringAnnotationVisitor
       8: putfield      #10                 // Field literalRenderer:Lorg/semanticweb/owlapi/util/StringAnnotationVisitor;
      11: return
}
