Compiled from "OWLCellRenderer.java"
class org.protege.editor.owl.ui.renderer.OWLCellRenderer$ActiveEntityVisitor implements org.semanticweb.owlapi.model.OWLEntityVisitor {
  final org.protege.editor.owl.ui.renderer.OWLCellRenderer this$0;

  private org.protege.editor.owl.ui.renderer.OWLCellRenderer$ActiveEntityVisitor(org.protege.editor.owl.ui.renderer.OWLCellRenderer);
    Code:
       0: aload_0
       1: aload_1
       2: putfield      #2                  // Field this$0:Lorg/protege/editor/owl/ui/renderer/OWLCellRenderer;
       5: aload_0
       6: invokespecial #3                  // Method java/lang/Object."<init>":()V
       9: return

  public void visit(org.semanticweb.owlapi.model.OWLClass);
    Code:
       0: aload_0
       1: getfield      #2                  // Field this$0:Lorg/protege/editor/owl/ui/renderer/OWLCellRenderer;
       4: invokestatic  #4                  // Method org/protege/editor/owl/ui/renderer/OWLCellRenderer.access$300:(Lorg/protege/editor/owl/ui/renderer/OWLCellRenderer;)Lorg/protege/editor/owl/model/OWLModelManager;
       7: invokeinterface #5,  1            // InterfaceMethod org/protege/editor/owl/model/OWLModelManager.getActiveOntology:()Lorg/semanticweb/owlapi/model/OWLOntology;
      12: aload_1
      13: invokeinterface #6,  2            // InterfaceMethod org/semanticweb/owlapi/model/OWLOntology.getAxioms:(Lorg/semanticweb/owlapi/model/OWLClass;)Ljava/util/Set;
      18: invokeinterface #7,  1            // InterfaceMethod java/util/Set.isEmpty:()Z
      23: ifne          46
      26: aload_0
      27: getfield      #2                  // Field this$0:Lorg/protege/editor/owl/ui/renderer/OWLCellRenderer;
      30: aload_0
      31: getfield      #2                  // Field this$0:Lorg/protege/editor/owl/ui/renderer/OWLCellRenderer;
      34: invokestatic  #4                  // Method org/protege/editor/owl/ui/renderer/OWLCellRenderer.access$300:(Lorg/protege/editor/owl/ui/renderer/OWLCellRenderer;)Lorg/protege/editor/owl/model/OWLModelManager;
      37: invokeinterface #5,  1            // InterfaceMethod org/protege/editor/owl/model/OWLModelManager.getActiveOntology:()Lorg/semanticweb/owlapi/model/OWLOntology;
      42: invokestatic  #8                  // Method org/protege/editor/owl/ui/renderer/OWLCellRenderer.access$402:(Lorg/protege/editor/owl/ui/renderer/OWLCellRenderer;Lorg/semanticweb/owlapi/model/OWLOntology;)Lorg/semanticweb/owlapi/model/OWLOntology;
      45: pop
      46: return

  public void visit(org.semanticweb.owlapi.model.OWLDatatype);
    Code:
       0: aload_0
       1: getfield      #2                  // Field this$0:Lorg/protege/editor/owl/ui/renderer/OWLCellRenderer;
       4: invokestatic  #4                  // Method org/protege/editor/owl/ui/renderer/OWLCellRenderer.access$300:(Lorg/protege/editor/owl/ui/renderer/OWLCellRenderer;)Lorg/protege/editor/owl/model/OWLModelManager;
       7: invokeinterface #5,  1            // InterfaceMethod org/protege/editor/owl/model/OWLModelManager.getActiveOntology:()Lorg/semanticweb/owlapi/model/OWLOntology;
      12: aload_1
      13: invokeinterface #9,  2            // InterfaceMethod org/semanticweb/owlapi/model/OWLOntology.getAxioms:(Lorg/semanticweb/owlapi/model/OWLDatatype;)Ljava/util/Set;
      18: invokeinterface #7,  1            // InterfaceMethod java/util/Set.isEmpty:()Z
      23: ifne          46
      26: aload_0
      27: getfield      #2                  // Field this$0:Lorg/protege/editor/owl/ui/renderer/OWLCellRenderer;
      30: aload_0
      31: getfield      #2                  // Field this$0:Lorg/protege/editor/owl/ui/renderer/OWLCellRenderer;
      34: invokestatic  #4                  // Method org/protege/editor/owl/ui/renderer/OWLCellRenderer.access$300:(Lorg/protege/editor/owl/ui/renderer/OWLCellRenderer;)Lorg/protege/editor/owl/model/OWLModelManager;
      37: invokeinterface #5,  1            // InterfaceMethod org/protege/editor/owl/model/OWLModelManager.getActiveOntology:()Lorg/semanticweb/owlapi/model/OWLOntology;
      42: invokestatic  #8                  // Method org/protege/editor/owl/ui/renderer/OWLCellRenderer.access$402:(Lorg/protege/editor/owl/ui/renderer/OWLCellRenderer;Lorg/semanticweb/owlapi/model/OWLOntology;)Lorg/semanticweb/owlapi/model/OWLOntology;
      45: pop
      46: return

  public void visit(org.semanticweb.owlapi.model.OWLNamedIndividual);
    Code:
       0: aload_0
       1: getfield      #2                  // Field this$0:Lorg/protege/editor/owl/ui/renderer/OWLCellRenderer;
       4: invokestatic  #4                  // Method org/protege/editor/owl/ui/renderer/OWLCellRenderer.access$300:(Lorg/protege/editor/owl/ui/renderer/OWLCellRenderer;)Lorg/protege/editor/owl/model/OWLModelManager;
       7: invokeinterface #5,  1            // InterfaceMethod org/protege/editor/owl/model/OWLModelManager.getActiveOntology:()Lorg/semanticweb/owlapi/model/OWLOntology;
      12: aload_1
      13: invokeinterface #10,  2           // InterfaceMethod org/semanticweb/owlapi/model/OWLOntology.getAxioms:(Lorg/semanticweb/owlapi/model/OWLIndividual;)Ljava/util/Set;
      18: invokeinterface #7,  1            // InterfaceMethod java/util/Set.isEmpty:()Z
      23: ifne          46
      26: aload_0
      27: getfield      #2                  // Field this$0:Lorg/protege/editor/owl/ui/renderer/OWLCellRenderer;
      30: aload_0
      31: getfield      #2                  // Field this$0:Lorg/protege/editor/owl/ui/renderer/OWLCellRenderer;
      34: invokestatic  #4                  // Method org/protege/editor/owl/ui/renderer/OWLCellRenderer.access$300:(Lorg/protege/editor/owl/ui/renderer/OWLCellRenderer;)Lorg/protege/editor/owl/model/OWLModelManager;
      37: invokeinterface #5,  1            // InterfaceMethod org/protege/editor/owl/model/OWLModelManager.getActiveOntology:()Lorg/semanticweb/owlapi/model/OWLOntology;
      42: invokestatic  #8                  // Method org/protege/editor/owl/ui/renderer/OWLCellRenderer.access$402:(Lorg/protege/editor/owl/ui/renderer/OWLCellRenderer;Lorg/semanticweb/owlapi/model/OWLOntology;)Lorg/semanticweb/owlapi/model/OWLOntology;
      45: pop
      46: return

  public void visit(org.semanticweb.owlapi.model.OWLDataProperty);
    Code:
       0: aload_0
       1: getfield      #2                  // Field this$0:Lorg/protege/editor/owl/ui/renderer/OWLCellRenderer;
       4: invokestatic  #4                  // Method org/protege/editor/owl/ui/renderer/OWLCellRenderer.access$300:(Lorg/protege/editor/owl/ui/renderer/OWLCellRenderer;)Lorg/protege/editor/owl/model/OWLModelManager;
       7: invokeinterface #5,  1            // InterfaceMethod org/protege/editor/owl/model/OWLModelManager.getActiveOntology:()Lorg/semanticweb/owlapi/model/OWLOntology;
      12: aload_1
      13: invokeinterface #11,  2           // InterfaceMethod org/semanticweb/owlapi/model/OWLOntology.getAxioms:(Lorg/semanticweb/owlapi/model/OWLDataProperty;)Ljava/util/Set;
      18: invokeinterface #7,  1            // InterfaceMethod java/util/Set.isEmpty:()Z
      23: ifne          46
      26: aload_0
      27: getfield      #2                  // Field this$0:Lorg/protege/editor/owl/ui/renderer/OWLCellRenderer;
      30: aload_0
      31: getfield      #2                  // Field this$0:Lorg/protege/editor/owl/ui/renderer/OWLCellRenderer;
      34: invokestatic  #4                  // Method org/protege/editor/owl/ui/renderer/OWLCellRenderer.access$300:(Lorg/protege/editor/owl/ui/renderer/OWLCellRenderer;)Lorg/protege/editor/owl/model/OWLModelManager;
      37: invokeinterface #5,  1            // InterfaceMethod org/protege/editor/owl/model/OWLModelManager.getActiveOntology:()Lorg/semanticweb/owlapi/model/OWLOntology;
      42: invokestatic  #8                  // Method org/protege/editor/owl/ui/renderer/OWLCellRenderer.access$402:(Lorg/protege/editor/owl/ui/renderer/OWLCellRenderer;Lorg/semanticweb/owlapi/model/OWLOntology;)Lorg/semanticweb/owlapi/model/OWLOntology;
      45: pop
      46: return

  public void visit(org.semanticweb.owlapi.model.OWLObjectProperty);
    Code:
       0: aload_0
       1: getfield      #2                  // Field this$0:Lorg/protege/editor/owl/ui/renderer/OWLCellRenderer;
       4: invokestatic  #4                  // Method org/protege/editor/owl/ui/renderer/OWLCellRenderer.access$300:(Lorg/protege/editor/owl/ui/renderer/OWLCellRenderer;)Lorg/protege/editor/owl/model/OWLModelManager;
       7: invokeinterface #5,  1            // InterfaceMethod org/protege/editor/owl/model/OWLModelManager.getActiveOntology:()Lorg/semanticweb/owlapi/model/OWLOntology;
      12: aload_1
      13: invokeinterface #12,  2           // InterfaceMethod org/semanticweb/owlapi/model/OWLOntology.getAxioms:(Lorg/semanticweb/owlapi/model/OWLObjectPropertyExpression;)Ljava/util/Set;
      18: invokeinterface #7,  1            // InterfaceMethod java/util/Set.isEmpty:()Z
      23: ifne          46
      26: aload_0
      27: getfield      #2                  // Field this$0:Lorg/protege/editor/owl/ui/renderer/OWLCellRenderer;
      30: aload_0
      31: getfield      #2                  // Field this$0:Lorg/protege/editor/owl/ui/renderer/OWLCellRenderer;
      34: invokestatic  #4                  // Method org/protege/editor/owl/ui/renderer/OWLCellRenderer.access$300:(Lorg/protege/editor/owl/ui/renderer/OWLCellRenderer;)Lorg/protege/editor/owl/model/OWLModelManager;
      37: invokeinterface #5,  1            // InterfaceMethod org/protege/editor/owl/model/OWLModelManager.getActiveOntology:()Lorg/semanticweb/owlapi/model/OWLOntology;
      42: invokestatic  #8                  // Method org/protege/editor/owl/ui/renderer/OWLCellRenderer.access$402:(Lorg/protege/editor/owl/ui/renderer/OWLCellRenderer;Lorg/semanticweb/owlapi/model/OWLOntology;)Lorg/semanticweb/owlapi/model/OWLOntology;
      45: pop
      46: return

  public void visit(org.semanticweb.owlapi.model.OWLAnnotationProperty);
    Code:
       0: aload_0
       1: getfield      #2                  // Field this$0:Lorg/protege/editor/owl/ui/renderer/OWLCellRenderer;
       4: invokestatic  #4                  // Method org/protege/editor/owl/ui/renderer/OWLCellRenderer.access$300:(Lorg/protege/editor/owl/ui/renderer/OWLCellRenderer;)Lorg/protege/editor/owl/model/OWLModelManager;
       7: invokeinterface #5,  1            // InterfaceMethod org/protege/editor/owl/model/OWLModelManager.getActiveOntology:()Lorg/semanticweb/owlapi/model/OWLOntology;
      12: aload_1
      13: invokeinterface #13,  2           // InterfaceMethod org/semanticweb/owlapi/model/OWLOntology.getAxioms:(Lorg/semanticweb/owlapi/model/OWLAnnotationProperty;)Ljava/util/Set;
      18: invokeinterface #7,  1            // InterfaceMethod java/util/Set.isEmpty:()Z
      23: ifne          46
      26: aload_0
      27: getfield      #2                  // Field this$0:Lorg/protege/editor/owl/ui/renderer/OWLCellRenderer;
      30: aload_0
      31: getfield      #2                  // Field this$0:Lorg/protege/editor/owl/ui/renderer/OWLCellRenderer;
      34: invokestatic  #4                  // Method org/protege/editor/owl/ui/renderer/OWLCellRenderer.access$300:(Lorg/protege/editor/owl/ui/renderer/OWLCellRenderer;)Lorg/protege/editor/owl/model/OWLModelManager;
      37: invokeinterface #5,  1            // InterfaceMethod org/protege/editor/owl/model/OWLModelManager.getActiveOntology:()Lorg/semanticweb/owlapi/model/OWLOntology;
      42: invokestatic  #8                  // Method org/protege/editor/owl/ui/renderer/OWLCellRenderer.access$402:(Lorg/protege/editor/owl/ui/renderer/OWLCellRenderer;Lorg/semanticweb/owlapi/model/OWLOntology;)Lorg/semanticweb/owlapi/model/OWLOntology;
      45: pop
      46: return

  org.protege.editor.owl.ui.renderer.OWLCellRenderer$ActiveEntityVisitor(org.protege.editor.owl.ui.renderer.OWLCellRenderer, org.protege.editor.owl.ui.renderer.OWLCellRenderer$1);
    Code:
       0: aload_0
       1: aload_1
       2: invokespecial #1                  // Method "<init>":(Lorg/protege/editor/owl/ui/renderer/OWLCellRenderer;)V
       5: return
}
