Compiled from "OWLObjectRendererImpl.java"
public class org.protege.editor.owl.ui.renderer.OWLObjectRendererImpl implements org.protege.editor.owl.ui.renderer.OWLObjectRenderer {
  private final org.protege.editor.owl.model.OWLModelManager mngr;

  private org.protege.editor.owl.ui.renderer.OWLObjectRendererImpl$WriterDelegate writerDelegate;

  private uk.ac.manchester.cs.owl.owlapi.mansyntaxrenderer.ManchesterOWLSyntaxObjectRenderer delegate;

  private org.semanticweb.owlapi.util.OntologyIRIShortFormProvider ontURISFP;

  public org.protege.editor.owl.ui.renderer.OWLObjectRendererImpl(org.protege.editor.owl.model.OWLModelManager);
    Code:
       0: aload_0
       1: invokespecial #2                  // Method java/lang/Object."<init>":()V
       4: aload_0
       5: aload_1
       6: putfield      #1                  // Field mngr:Lorg/protege/editor/owl/model/OWLModelManager;
       9: aload_0
      10: new           #3                  // class org/protege/editor/owl/ui/renderer/OWLObjectRendererImpl$WriterDelegate
      13: dup
      14: aload_0
      15: aconst_null
      16: invokespecial #4                  // Method org/protege/editor/owl/ui/renderer/OWLObjectRendererImpl$WriterDelegate."<init>":(Lorg/protege/editor/owl/ui/renderer/OWLObjectRendererImpl;Lorg/protege/editor/owl/ui/renderer/OWLObjectRendererImpl$1;)V
      19: putfield      #5                  // Field writerDelegate:Lorg/protege/editor/owl/ui/renderer/OWLObjectRendererImpl$WriterDelegate;
      22: aload_0
      23: new           #6                  // class org/protege/editor/owl/ui/renderer/OWLObjectRendererImpl$PatchedManchesterOWLSyntaxObjectRenderer
      26: dup
      27: aload_0
      28: aload_0
      29: getfield      #5                  // Field writerDelegate:Lorg/protege/editor/owl/ui/renderer/OWLObjectRendererImpl$WriterDelegate;
      32: new           #7                  // class org/protege/editor/owl/ui/renderer/OWLObjectRendererImpl$1
      35: dup
      36: aload_0
      37: invokespecial #8                  // Method org/protege/editor/owl/ui/renderer/OWLObjectRendererImpl$1."<init>":(Lorg/protege/editor/owl/ui/renderer/OWLObjectRendererImpl;)V
      40: invokespecial #9                  // Method org/protege/editor/owl/ui/renderer/OWLObjectRendererImpl$PatchedManchesterOWLSyntaxObjectRenderer."<init>":(Lorg/protege/editor/owl/ui/renderer/OWLObjectRendererImpl;Ljava/io/Writer;Lorg/semanticweb/owlapi/util/ShortFormProvider;)V
      43: putfield      #10                 // Field delegate:Luk/ac/manchester/cs/owl/owlapi/mansyntaxrenderer/ManchesterOWLSyntaxObjectRenderer;
      46: aload_0
      47: new           #11                 // class org/semanticweb/owlapi/util/OntologyIRIShortFormProvider
      50: dup
      51: invokespecial #12                 // Method org/semanticweb/owlapi/util/OntologyIRIShortFormProvider."<init>":()V
      54: putfield      #13                 // Field ontURISFP:Lorg/semanticweb/owlapi/util/OntologyIRIShortFormProvider;
      57: return

  public java.lang.String render(org.semanticweb.owlapi.model.OWLObject);
    Code:
       0: aload_1
       1: instanceof    #14                 // class org/semanticweb/owlapi/model/OWLOntology
       4: ifeq          16
       7: aload_0
       8: aload_1
       9: checkcast     #14                 // class org/semanticweb/owlapi/model/OWLOntology
      12: invokespecial #15                 // Method renderOntology:(Lorg/semanticweb/owlapi/model/OWLOntology;)Ljava/lang/String;
      15: areturn
      16: aload_0
      17: getfield      #5                  // Field writerDelegate:Lorg/protege/editor/owl/ui/renderer/OWLObjectRendererImpl$WriterDelegate;
      20: invokestatic  #16                 // Method org/protege/editor/owl/ui/renderer/OWLObjectRendererImpl$WriterDelegate.access$200:(Lorg/protege/editor/owl/ui/renderer/OWLObjectRendererImpl$WriterDelegate;)V
      23: aload_1
      24: aload_0
      25: getfield      #10                 // Field delegate:Luk/ac/manchester/cs/owl/owlapi/mansyntaxrenderer/ManchesterOWLSyntaxObjectRenderer;
      28: invokeinterface #17,  2           // InterfaceMethod org/semanticweb/owlapi/model/OWLObject.accept:(Lorg/semanticweb/owlapi/model/OWLObjectVisitor;)V
      33: aload_0
      34: getfield      #5                  // Field writerDelegate:Lorg/protege/editor/owl/ui/renderer/OWLObjectRendererImpl$WriterDelegate;
      37: invokevirtual #18                 // Method org/protege/editor/owl/ui/renderer/OWLObjectRendererImpl$WriterDelegate.toString:()Ljava/lang/String;
      40: areturn

  private java.lang.String renderOntology(org.semanticweb.owlapi.model.OWLOntology);
    Code:
       0: aload_1
       1: invokeinterface #19,  1           // InterfaceMethod org/semanticweb/owlapi/model/OWLOntology.isAnonymous:()Z
       6: ifeq          19
       9: aload_1
      10: invokeinterface #20,  1           // InterfaceMethod org/semanticweb/owlapi/model/OWLOntology.getOntologyID:()Lorg/semanticweb/owlapi/model/OWLOntologyID;
      15: invokevirtual #21                 // Method org/semanticweb/owlapi/model/OWLOntologyID.toString:()Ljava/lang/String;
      18: areturn
      19: aload_1
      20: invokeinterface #20,  1           // InterfaceMethod org/semanticweb/owlapi/model/OWLOntology.getOntologyID:()Lorg/semanticweb/owlapi/model/OWLOntologyID;
      25: invokevirtual #22                 // Method org/semanticweb/owlapi/model/OWLOntologyID.getDefaultDocumentIRI:()Lcom/google/common/base/Optional;
      28: astore_2
      29: aload_2
      30: invokevirtual #23                 // Method com/google/common/base/Optional.isPresent:()Z
      33: ifeq          51
      36: aload_0
      37: getfield      #13                 // Field ontURISFP:Lorg/semanticweb/owlapi/util/OntologyIRIShortFormProvider;
      40: aload_2
      41: invokevirtual #24                 // Method com/google/common/base/Optional.get:()Ljava/lang/Object;
      44: checkcast     #25                 // class org/semanticweb/owlapi/model/IRI
      47: invokevirtual #26                 // Method org/semanticweb/owlapi/util/OntologyIRIShortFormProvider.getShortForm:(Lorg/semanticweb/owlapi/model/IRI;)Ljava/lang/String;
      50: areturn
      51: ldc           #27                 // String Anonymous Ontology
      53: areturn

  static org.protege.editor.owl.model.OWLModelManager access$100(org.protege.editor.owl.ui.renderer.OWLObjectRendererImpl);
    Code:
       0: aload_0
       1: getfield      #1                  // Field mngr:Lorg/protege/editor/owl/model/OWLModelManager;
       4: areturn
}
