Compiled from "EntityReferenceEventImpl.java"
public class org.codehaus.stax2.ri.evt.EntityReferenceEventImpl extends org.codehaus.stax2.ri.evt.BaseEventImpl implements javax.xml.stream.events.EntityReference {
  protected final javax.xml.stream.events.EntityDeclaration mDecl;

  public org.codehaus.stax2.ri.evt.EntityReferenceEventImpl(javax.xml.stream.Location, javax.xml.stream.events.EntityDeclaration);
    Code:
       0: aload_0
       1: aload_1
       2: invokespecial #1                  // Method org/codehaus/stax2/ri/evt/BaseEventImpl."<init>":(Ljavax/xml/stream/Location;)V
       5: aload_0
       6: aload_2
       7: putfield      #2                  // Field mDecl:Ljavax/xml/stream/events/EntityDeclaration;
      10: return

  public org.codehaus.stax2.ri.evt.EntityReferenceEventImpl(javax.xml.stream.Location, java.lang.String);
    Code:
       0: aload_0
       1: aload_1
       2: invokespecial #1                  // Method org/codehaus/stax2/ri/evt/BaseEventImpl."<init>":(Ljavax/xml/stream/Location;)V
       5: aload_0
       6: new           #3                  // class org/codehaus/stax2/ri/evt/EntityDeclarationEventImpl
       9: dup
      10: aload_1
      11: aload_2
      12: invokespecial #4                  // Method org/codehaus/stax2/ri/evt/EntityDeclarationEventImpl."<init>":(Ljavax/xml/stream/Location;Ljava/lang/String;)V
      15: putfield      #2                  // Field mDecl:Ljavax/xml/stream/events/EntityDeclaration;
      18: return

  public javax.xml.stream.events.EntityDeclaration getDeclaration();
    Code:
       0: aload_0
       1: getfield      #2                  // Field mDecl:Ljavax/xml/stream/events/EntityDeclaration;
       4: areturn

  public java.lang.String getName();
    Code:
       0: aload_0
       1: getfield      #2                  // Field mDecl:Ljavax/xml/stream/events/EntityDeclaration;
       4: invokeinterface #5,  1            // InterfaceMethod javax/xml/stream/events/EntityDeclaration.getName:()Ljava/lang/String;
       9: areturn

  public int getEventType();
    Code:
       0: bipush        9
       2: ireturn

  public boolean isEntityReference();
    Code:
       0: iconst_1
       1: ireturn

  public void writeAsEncodedUnicode(java.io.Writer) throws javax.xml.stream.XMLStreamException;
    Code:
       0: aload_1
       1: bipush        38
       3: invokevirtual #6                  // Method java/io/Writer.write:(I)V
       6: aload_1
       7: aload_0
       8: invokevirtual #7                  // Method getName:()Ljava/lang/String;
      11: invokevirtual #8                  // Method java/io/Writer.write:(Ljava/lang/String;)V
      14: aload_1
      15: bipush        59
      17: invokevirtual #6                  // Method java/io/Writer.write:(I)V
      20: goto          29
      23: astore_2
      24: aload_0
      25: aload_2
      26: invokevirtual #10                 // Method throwFromIOE:(Ljava/io/IOException;)V
      29: return
    Exception table:
       from    to  target type
           0    20    23   Class java/io/IOException

  public void writeUsing(org.codehaus.stax2.XMLStreamWriter2) throws javax.xml.stream.XMLStreamException;
    Code:
       0: aload_1
       1: aload_0
       2: invokevirtual #7                  // Method getName:()Ljava/lang/String;
       5: invokeinterface #11,  2           // InterfaceMethod org/codehaus/stax2/XMLStreamWriter2.writeEntityRef:(Ljava/lang/String;)V
      10: return

  public boolean equals(java.lang.Object);
    Code:
       0: aload_1
       1: aload_0
       2: if_acmpne     7
       5: iconst_1
       6: ireturn
       7: aload_1
       8: ifnonnull     13
      11: iconst_0
      12: ireturn
      13: aload_1
      14: instanceof    #12                 // class javax/xml/stream/events/EntityReference
      17: ifne          22
      20: iconst_0
      21: ireturn
      22: aload_1
      23: checkcast     #12                 // class javax/xml/stream/events/EntityReference
      26: astore_2
      27: aload_0
      28: invokevirtual #7                  // Method getName:()Ljava/lang/String;
      31: aload_2
      32: invokeinterface #13,  1           // InterfaceMethod javax/xml/stream/events/EntityReference.getName:()Ljava/lang/String;
      37: invokevirtual #14                 // Method java/lang/String.equals:(Ljava/lang/Object;)Z
      40: ireturn

  public int hashCode();
    Code:
       0: aload_0
       1: invokevirtual #7                  // Method getName:()Ljava/lang/String;
       4: invokevirtual #15                 // Method java/lang/String.hashCode:()I
       7: ireturn
}
