Compiled from "KafkaConsumerRepositoryTest.java"
public class no.nav.common.kafka.consumer.feilhandtering.KafkaConsumerRepositoryTest {
  public static final org.testcontainers.containers.PostgreSQLContainer<?> postgreSQLContainer;

  private final javax.sql.DataSource dataSource;

  private final no.nav.common.kafka.consumer.feilhandtering.KafkaConsumerRepository kafkaConsumerRepository;

  public static java.util.Collection<java.lang.Object[]> data();
    Code:
       0: getstatic     #1                  // Field postgreSQLContainer:Lorg/testcontainers/containers/PostgreSQLContainer;
       3: invokevirtual #2                  // Method org/testcontainers/containers/PostgreSQLContainer.start:()V
       6: getstatic     #1                  // Field postgreSQLContainer:Lorg/testcontainers/containers/PostgreSQLContainer;
       9: invokestatic  #3                  // Method no/nav/common/kafka/utils/LocalPostgresDatabase.createPostgresDataSource:(Lorg/testcontainers/containers/PostgreSQLContainer;)Ljavax/sql/DataSource;
      12: astore_0
      13: aload_0
      14: ldc           #4                  // String kafka-consumer-record-postgres.sql
      16: invokestatic  #5                  // Method no/nav/common/kafka/utils/DbUtils.runScript:(Ljavax/sql/DataSource;Ljava/lang/String;)V
      19: new           #6                  // class no/nav/common/kafka/spring/PostgresJdbcTemplateConsumerRepository
      22: dup
      23: new           #7                  // class org/springframework/jdbc/core/JdbcTemplate
      26: dup
      27: aload_0
      28: invokespecial #8                  // Method org/springframework/jdbc/core/JdbcTemplate."<init>":(Ljavax/sql/DataSource;)V
      31: invokespecial #9                  // Method no/nav/common/kafka/spring/PostgresJdbcTemplateConsumerRepository."<init>":(Lorg/springframework/jdbc/core/JdbcTemplate;)V
      34: astore_1
      35: invokestatic  #10                 // Method no/nav/common/kafka/utils/LocalOracleH2Database.createDatabase:()Ljavax/sql/DataSource;
      38: astore_2
      39: aload_2
      40: ldc           #11                 // String kafka-consumer-record-oracle.sql
      42: invokestatic  #5                  // Method no/nav/common/kafka/utils/DbUtils.runScript:(Ljavax/sql/DataSource;Ljava/lang/String;)V
      45: aload_2
      46: ldc           #12                 // String oracle-mock.sql
      48: invokestatic  #5                  // Method no/nav/common/kafka/utils/DbUtils.runScript:(Ljavax/sql/DataSource;Ljava/lang/String;)V
      51: new           #13                 // class no/nav/common/kafka/spring/OracleJdbcTemplateConsumerRepository
      54: dup
      55: new           #7                  // class org/springframework/jdbc/core/JdbcTemplate
      58: dup
      59: aload_2
      60: invokespecial #8                  // Method org/springframework/jdbc/core/JdbcTemplate."<init>":(Ljavax/sql/DataSource;)V
      63: invokespecial #14                 // Method no/nav/common/kafka/spring/OracleJdbcTemplateConsumerRepository."<init>":(Lorg/springframework/jdbc/core/JdbcTemplate;)V
      66: astore_3
      67: iconst_2
      68: anewarray     #15                 // class "[Ljava/lang/Object;"
      71: dup
      72: iconst_0
      73: iconst_3
      74: anewarray     #16                 // class java/lang/Object
      77: dup
      78: iconst_0
      79: ldc           #17                 // String POSTGRES
      81: aastore
      82: dup
      83: iconst_1
      84: aload_0
      85: aastore
      86: dup
      87: iconst_2
      88: aload_1
      89: aastore
      90: aastore
      91: dup
      92: iconst_1
      93: iconst_3
      94: anewarray     #16                 // class java/lang/Object
      97: dup
      98: iconst_0
      99: ldc           #18                 // String ORACLE
     101: aastore
     102: dup
     103: iconst_1
     104: aload_2
     105: aastore
     106: dup
     107: iconst_2
     108: aload_3
     109: aastore
     110: aastore
     111: invokestatic  #19                 // Method java/util/Arrays.asList:([Ljava/lang/Object;)Ljava/util/List;
     114: areturn

  public no.nav.common.kafka.consumer.feilhandtering.KafkaConsumerRepositoryTest(java.lang.String, javax.sql.DataSource, no.nav.common.kafka.consumer.feilhandtering.KafkaConsumerRepository);
    Code:
       0: aload_0
       1: invokespecial #20                 // Method java/lang/Object."<init>":()V
       4: aload_0
       5: aload_2
       6: putfield      #21                 // Field dataSource:Ljavax/sql/DataSource;
       9: aload_0
      10: aload_3
      11: putfield      #22                 // Field kafkaConsumerRepository:Lno/nav/common/kafka/consumer/feilhandtering/KafkaConsumerRepository;
      14: return

  public static void stop();
    Code:
       0: getstatic     #1                  // Field postgreSQLContainer:Lorg/testcontainers/containers/PostgreSQLContainer;
       3: invokevirtual #23                 // Method org/testcontainers/containers/PostgreSQLContainer.stop:()V
       6: return

  public void cleanup();
    Code:
       0: aload_0
       1: getfield      #21                 // Field dataSource:Ljavax/sql/DataSource;
       4: invokestatic  #24                 // Method no/nav/common/kafka/utils/DbUtils.cleanupConsumer:(Ljavax/sql/DataSource;)V
       7: return

  public void should_insert_consumer_record();
    Code:
       0: new           #25                 // class org/apache/kafka/clients/consumer/ConsumerRecord
       3: dup
       4: ldc           #26                 // String topic
       6: iconst_1
       7: lconst_1
       8: ldc           #27                 // String key
      10: ldc           #28                 // String value
      12: invokespecial #29                 // Method org/apache/kafka/clients/consumer/ConsumerRecord."<init>":(Ljava/lang/String;IJLjava/lang/Object;Ljava/lang/Object;)V
      15: astore_1
      16: aload_0
      17: getfield      #22                 // Field kafkaConsumerRepository:Lno/nav/common/kafka/consumer/feilhandtering/KafkaConsumerRepository;
      20: aload_0
      21: aload_1
      22: invokevirtual #30                 // Method mapRecord:(Lorg/apache/kafka/clients/consumer/ConsumerRecord;)Lno/nav/common/kafka/consumer/feilhandtering/StoredConsumerRecord;
      25: invokeinterface #31,  2           // InterfaceMethod no/nav/common/kafka/consumer/feilhandtering/KafkaConsumerRepository.storeRecord:(Lno/nav/common/kafka/consumer/feilhandtering/StoredConsumerRecord;)J
      30: lstore_2
      31: lconst_1
      32: lload_2
      33: invokestatic  #32                 // Method org/junit/Assert.assertEquals:(JJ)V
      36: return

  public void should_insert_consumer_record_with_null_value();
    Code:
       0: new           #25                 // class org/apache/kafka/clients/consumer/ConsumerRecord
       3: dup
       4: ldc           #26                 // String topic
       6: iconst_1
       7: lconst_1
       8: ldc           #27                 // String key
      10: aconst_null
      11: invokespecial #29                 // Method org/apache/kafka/clients/consumer/ConsumerRecord."<init>":(Ljava/lang/String;IJLjava/lang/Object;Ljava/lang/Object;)V
      14: astore_1
      15: aload_0
      16: getfield      #22                 // Field kafkaConsumerRepository:Lno/nav/common/kafka/consumer/feilhandtering/KafkaConsumerRepository;
      19: aload_0
      20: aload_1
      21: invokevirtual #30                 // Method mapRecord:(Lorg/apache/kafka/clients/consumer/ConsumerRecord;)Lno/nav/common/kafka/consumer/feilhandtering/StoredConsumerRecord;
      24: invokeinterface #31,  2           // InterfaceMethod no/nav/common/kafka/consumer/feilhandtering/KafkaConsumerRepository.storeRecord:(Lno/nav/common/kafka/consumer/feilhandtering/StoredConsumerRecord;)J
      29: lstore_2
      30: lconst_1
      31: lload_2
      32: invokestatic  #32                 // Method org/junit/Assert.assertEquals:(JJ)V
      35: return

  public void should_insert_consumer_record_with_null_key();
    Code:
       0: new           #25                 // class org/apache/kafka/clients/consumer/ConsumerRecord
       3: dup
       4: ldc           #26                 // String topic
       6: iconst_1
       7: lconst_1
       8: aconst_null
       9: ldc           #28                 // String value
      11: invokespecial #29                 // Method org/apache/kafka/clients/consumer/ConsumerRecord."<init>":(Ljava/lang/String;IJLjava/lang/Object;Ljava/lang/Object;)V
      14: astore_1
      15: aload_0
      16: getfield      #22                 // Field kafkaConsumerRepository:Lno/nav/common/kafka/consumer/feilhandtering/KafkaConsumerRepository;
      19: aload_0
      20: aload_1
      21: invokevirtual #30                 // Method mapRecord:(Lorg/apache/kafka/clients/consumer/ConsumerRecord;)Lno/nav/common/kafka/consumer/feilhandtering/StoredConsumerRecord;
      24: invokeinterface #31,  2           // InterfaceMethod no/nav/common/kafka/consumer/feilhandtering/KafkaConsumerRepository.storeRecord:(Lno/nav/common/kafka/consumer/feilhandtering/StoredConsumerRecord;)J
      29: lstore_2
      30: lconst_1
      31: lload_2
      32: invokestatic  #32                 // Method org/junit/Assert.assertEquals:(JJ)V
      35: return

  public void should_not_insert_more_than_1_record_with_same_topic_partition_offset();
    Code:
       0: new           #25                 // class org/apache/kafka/clients/consumer/ConsumerRecord
       3: dup
       4: ldc           #26                 // String topic
       6: iconst_1
       7: lconst_1
       8: ldc           #27                 // String key
      10: ldc           #28                 // String value
      12: invokespecial #29                 // Method org/apache/kafka/clients/consumer/ConsumerRecord."<init>":(Ljava/lang/String;IJLjava/lang/Object;Ljava/lang/Object;)V
      15: astore_1
      16: aload_0
      17: getfield      #22                 // Field kafkaConsumerRepository:Lno/nav/common/kafka/consumer/feilhandtering/KafkaConsumerRepository;
      20: aload_0
      21: aload_1
      22: invokevirtual #30                 // Method mapRecord:(Lorg/apache/kafka/clients/consumer/ConsumerRecord;)Lno/nav/common/kafka/consumer/feilhandtering/StoredConsumerRecord;
      25: invokeinterface #31,  2           // InterfaceMethod no/nav/common/kafka/consumer/feilhandtering/KafkaConsumerRepository.storeRecord:(Lno/nav/common/kafka/consumer/feilhandtering/StoredConsumerRecord;)J
      30: lstore_2
      31: aload_0
      32: getfield      #22                 // Field kafkaConsumerRepository:Lno/nav/common/kafka/consumer/feilhandtering/KafkaConsumerRepository;
      35: aload_0
      36: aload_1
      37: invokevirtual #30                 // Method mapRecord:(Lorg/apache/kafka/clients/consumer/ConsumerRecord;)Lno/nav/common/kafka/consumer/feilhandtering/StoredConsumerRecord;
      40: invokeinterface #31,  2           // InterfaceMethod no/nav/common/kafka/consumer/feilhandtering/KafkaConsumerRepository.storeRecord:(Lno/nav/common/kafka/consumer/feilhandtering/StoredConsumerRecord;)J
      45: lstore        4
      47: lconst_1
      48: lload_2
      49: invokestatic  #32                 // Method org/junit/Assert.assertEquals:(JJ)V
      52: ldc2_w        #33                 // long -1l
      55: lload         4
      57: invokestatic  #32                 // Method org/junit/Assert.assertEquals:(JJ)V
      60: return

  public void should_retrieve_record();
    Code:
       0: invokestatic  #35                 // Method java/lang/System.currentTimeMillis:()J
       3: lstore_1
       4: new           #25                 // class org/apache/kafka/clients/consumer/ConsumerRecord
       7: dup
       8: ldc           #36                 // String topic1
      10: iconst_1
      11: ldc2_w        #37                 // long 2l
      14: lload_1
      15: getstatic     #39                 // Field org/apache/kafka/common/record/TimestampType.CREATE_TIME:Lorg/apache/kafka/common/record/TimestampType;
      18: ldc2_w        #33                 // long -1l
      21: iconst_m1
      22: iconst_m1
      23: ldc           #27                 // String key
      25: ldc           #28                 // String value
      27: invokespecial #40                 // Method org/apache/kafka/clients/consumer/ConsumerRecord."<init>":(Ljava/lang/String;IJJLorg/apache/kafka/common/record/TimestampType;JIILjava/lang/Object;Ljava/lang/Object;)V
      30: astore_3
      31: aload_3
      32: invokevirtual #41                 // Method org/apache/kafka/clients/consumer/ConsumerRecord.headers:()Lorg/apache/kafka/common/header/Headers;
      35: new           #42                 // class org/apache/kafka/common/header/internals/RecordHeader
      38: dup
      39: ldc           #43                 // String header1
      41: ldc           #44                 // String test
      43: invokevirtual #45                 // Method java/lang/String.getBytes:()[B
      46: invokespecial #46                 // Method org/apache/kafka/common/header/internals/RecordHeader."<init>":(Ljava/lang/String;[B)V
      49: invokeinterface #47,  2           // InterfaceMethod org/apache/kafka/common/header/Headers.add:(Lorg/apache/kafka/common/header/Header;)Lorg/apache/kafka/common/header/Headers;
      54: pop
      55: aload_0
      56: getfield      #22                 // Field kafkaConsumerRepository:Lno/nav/common/kafka/consumer/feilhandtering/KafkaConsumerRepository;
      59: aload_0
      60: aload_3
      61: invokevirtual #30                 // Method mapRecord:(Lorg/apache/kafka/clients/consumer/ConsumerRecord;)Lno/nav/common/kafka/consumer/feilhandtering/StoredConsumerRecord;
      64: invokeinterface #31,  2           // InterfaceMethod no/nav/common/kafka/consumer/feilhandtering/KafkaConsumerRepository.storeRecord:(Lno/nav/common/kafka/consumer/feilhandtering/StoredConsumerRecord;)J
      69: pop2
      70: aload_0
      71: getfield      #22                 // Field kafkaConsumerRepository:Lno/nav/common/kafka/consumer/feilhandtering/KafkaConsumerRepository;
      74: ldc           #36                 // String topic1
      76: iconst_1
      77: iconst_5
      78: invokeinterface #48,  4           // InterfaceMethod no/nav/common/kafka/consumer/feilhandtering/KafkaConsumerRepository.getRecords:(Ljava/lang/String;II)Ljava/util/List;
      83: iconst_0
      84: invokeinterface #49,  2           // InterfaceMethod java/util/List.get:(I)Ljava/lang/Object;
      89: checkcast     #50                 // class no/nav/common/kafka/consumer/feilhandtering/StoredConsumerRecord
      92: astore        4
      94: lconst_1
      95: aload         4
      97: invokevirtual #51                 // Method no/nav/common/kafka/consumer/feilhandtering/StoredConsumerRecord.getId:()J
     100: invokestatic  #32                 // Method org/junit/Assert.assertEquals:(JJ)V
     103: ldc           #36                 // String topic1
     105: aload         4
     107: invokevirtual #52                 // Method no/nav/common/kafka/consumer/feilhandtering/StoredConsumerRecord.getTopic:()Ljava/lang/String;
     110: invokestatic  #53                 // Method org/junit/Assert.assertEquals:(Ljava/lang/Object;Ljava/lang/Object;)V
     113: lconst_1
     114: aload         4
     116: invokevirtual #54                 // Method no/nav/common/kafka/consumer/feilhandtering/StoredConsumerRecord.getPartition:()I
     119: i2l
     120: invokestatic  #32                 // Method org/junit/Assert.assertEquals:(JJ)V
     123: ldc2_w        #37                 // long 2l
     126: aload         4
     128: invokevirtual #55                 // Method no/nav/common/kafka/consumer/feilhandtering/StoredConsumerRecord.getOffset:()J
     131: invokestatic  #32                 // Method org/junit/Assert.assertEquals:(JJ)V
     134: ldc           #27                 // String key
     136: invokevirtual #45                 // Method java/lang/String.getBytes:()[B
     139: aload         4
     141: invokevirtual #56                 // Method no/nav/common/kafka/consumer/feilhandtering/StoredConsumerRecord.getKey:()[B
     144: invokestatic  #57                 // Method org/junit/Assert.assertArrayEquals:([B[B)V
     147: ldc           #28                 // String value
     149: invokevirtual #45                 // Method java/lang/String.getBytes:()[B
     152: aload         4
     154: invokevirtual #58                 // Method no/nav/common/kafka/consumer/feilhandtering/StoredConsumerRecord.getValue:()[B
     157: invokestatic  #57                 // Method org/junit/Assert.assertArrayEquals:([B[B)V
     160: lload_1
     161: aload         4
     163: invokevirtual #59                 // Method no/nav/common/kafka/consumer/feilhandtering/StoredConsumerRecord.getTimestamp:()J
     166: invokestatic  #32                 // Method org/junit/Assert.assertEquals:(JJ)V
     169: ldc           #60                 // String [{\"key\":\"header1\",\"value\":\"dGVzdA==\"}]
     171: aload         4
     173: invokevirtual #61                 // Method no/nav/common/kafka/consumer/feilhandtering/StoredConsumerRecord.getHeadersJson:()Ljava/lang/String;
     176: invokestatic  #53                 // Method org/junit/Assert.assertEquals:(Ljava/lang/Object;Ljava/lang/Object;)V
     179: return

  public void should_retrieve_records_in_order();
    Code:
       0: aload_0
       1: getfield      #22                 // Field kafkaConsumerRepository:Lno/nav/common/kafka/consumer/feilhandtering/KafkaConsumerRepository;
       4: aload_0
       5: new           #25                 // class org/apache/kafka/clients/consumer/ConsumerRecord
       8: dup
       9: ldc           #36                 // String topic1
      11: iconst_1
      12: ldc2_w        #37                 // long 2l
      15: ldc           #27                 // String key
      17: ldc           #28                 // String value
      19: invokespecial #29                 // Method org/apache/kafka/clients/consumer/ConsumerRecord."<init>":(Ljava/lang/String;IJLjava/lang/Object;Ljava/lang/Object;)V
      22: invokevirtual #30                 // Method mapRecord:(Lorg/apache/kafka/clients/consumer/ConsumerRecord;)Lno/nav/common/kafka/consumer/feilhandtering/StoredConsumerRecord;
      25: invokeinterface #31,  2           // InterfaceMethod no/nav/common/kafka/consumer/feilhandtering/KafkaConsumerRepository.storeRecord:(Lno/nav/common/kafka/consumer/feilhandtering/StoredConsumerRecord;)J
      30: pop2
      31: aload_0
      32: getfield      #22                 // Field kafkaConsumerRepository:Lno/nav/common/kafka/consumer/feilhandtering/KafkaConsumerRepository;
      35: aload_0
      36: new           #25                 // class org/apache/kafka/clients/consumer/ConsumerRecord
      39: dup
      40: ldc           #36                 // String topic1
      42: iconst_1
      43: ldc2_w        #62                 // long 3l
      46: ldc           #27                 // String key
      48: aconst_null
      49: invokespecial #29                 // Method org/apache/kafka/clients/consumer/ConsumerRecord."<init>":(Ljava/lang/String;IJLjava/lang/Object;Ljava/lang/Object;)V
      52: invokevirtual #30                 // Method mapRecord:(Lorg/apache/kafka/clients/consumer/ConsumerRecord;)Lno/nav/common/kafka/consumer/feilhandtering/StoredConsumerRecord;
      55: invokeinterface #31,  2           // InterfaceMethod no/nav/common/kafka/consumer/feilhandtering/KafkaConsumerRepository.storeRecord:(Lno/nav/common/kafka/consumer/feilhandtering/StoredConsumerRecord;)J
      60: pop2
      61: aload_0
      62: getfield      #22                 // Field kafkaConsumerRepository:Lno/nav/common/kafka/consumer/feilhandtering/KafkaConsumerRepository;
      65: aload_0
      66: new           #25                 // class org/apache/kafka/clients/consumer/ConsumerRecord
      69: dup
      70: ldc           #36                 // String topic1
      72: iconst_1
      73: ldc2_w        #64                 // long 4l
      76: ldc           #27                 // String key
      78: ldc           #28                 // String value
      80: invokespecial #29                 // Method org/apache/kafka/clients/consumer/ConsumerRecord."<init>":(Ljava/lang/String;IJLjava/lang/Object;Ljava/lang/Object;)V
      83: invokevirtual #30                 // Method mapRecord:(Lorg/apache/kafka/clients/consumer/ConsumerRecord;)Lno/nav/common/kafka/consumer/feilhandtering/StoredConsumerRecord;
      86: invokeinterface #31,  2           // InterfaceMethod no/nav/common/kafka/consumer/feilhandtering/KafkaConsumerRepository.storeRecord:(Lno/nav/common/kafka/consumer/feilhandtering/StoredConsumerRecord;)J
      91: pop2
      92: aload_0
      93: getfield      #22                 // Field kafkaConsumerRepository:Lno/nav/common/kafka/consumer/feilhandtering/KafkaConsumerRepository;
      96: aload_0
      97: new           #25                 // class org/apache/kafka/clients/consumer/ConsumerRecord
     100: dup
     101: ldc           #36                 // String topic1
     103: iconst_1
     104: lconst_1
     105: ldc           #27                 // String key
     107: ldc           #28                 // String value
     109: invokespecial #29                 // Method org/apache/kafka/clients/consumer/ConsumerRecord."<init>":(Ljava/lang/String;IJLjava/lang/Object;Ljava/lang/Object;)V
     112: invokevirtual #30                 // Method mapRecord:(Lorg/apache/kafka/clients/consumer/ConsumerRecord;)Lno/nav/common/kafka/consumer/feilhandtering/StoredConsumerRecord;
     115: invokeinterface #31,  2           // InterfaceMethod no/nav/common/kafka/consumer/feilhandtering/KafkaConsumerRepository.storeRecord:(Lno/nav/common/kafka/consumer/feilhandtering/StoredConsumerRecord;)J
     120: pop2
     121: aload_0
     122: getfield      #22                 // Field kafkaConsumerRepository:Lno/nav/common/kafka/consumer/feilhandtering/KafkaConsumerRepository;
     125: ldc           #36                 // String topic1
     127: iconst_1
     128: iconst_5
     129: invokeinterface #48,  4           // InterfaceMethod no/nav/common/kafka/consumer/feilhandtering/KafkaConsumerRepository.getRecords:(Ljava/lang/String;II)Ljava/util/List;
     134: astore_1
     135: aload_1
     136: invokeinterface #66,  1           // InterfaceMethod java/util/List.stream:()Ljava/util/stream/Stream;
     141: invokedynamic #67,  0             // InvokeDynamic #0:compare:()Ljava/util/Comparator;
     146: invokeinterface #68,  2           // InterfaceMethod java/util/stream/Stream.sorted:(Ljava/util/Comparator;)Ljava/util/stream/Stream;
     151: invokestatic  #69                 // Method java/util/stream/Collectors.toList:()Ljava/util/stream/Collector;
     154: invokeinterface #70,  2           // InterfaceMethod java/util/stream/Stream.collect:(Ljava/util/stream/Collector;)Ljava/lang/Object;
     159: checkcast     #71                 // class java/util/List
     162: astore_2
     163: iconst_0
     164: istore_3
     165: iload_3
     166: aload_1
     167: invokeinterface #72,  1           // InterfaceMethod java/util/List.size:()I
     172: if_icmpge     198
     175: aload_1
     176: iload_3
     177: invokeinterface #49,  2           // InterfaceMethod java/util/List.get:(I)Ljava/lang/Object;
     182: aload_2
     183: iload_3
     184: invokeinterface #49,  2           // InterfaceMethod java/util/List.get:(I)Ljava/lang/Object;
     189: invokestatic  #53                 // Method org/junit/Assert.assertEquals:(Ljava/lang/Object;Ljava/lang/Object;)V
     192: iinc          3, 1
     195: goto          165
     198: return

  public void should_retrieve_records_with_limit();
    Code:
       0: aload_0
       1: getfield      #22                 // Field kafkaConsumerRepository:Lno/nav/common/kafka/consumer/feilhandtering/KafkaConsumerRepository;
       4: aload_0
       5: new           #25                 // class org/apache/kafka/clients/consumer/ConsumerRecord
       8: dup
       9: ldc           #36                 // String topic1
      11: iconst_1
      12: lconst_1
      13: ldc           #27                 // String key
      15: ldc           #28                 // String value
      17: invokespecial #29                 // Method org/apache/kafka/clients/consumer/ConsumerRecord."<init>":(Ljava/lang/String;IJLjava/lang/Object;Ljava/lang/Object;)V
      20: invokevirtual #30                 // Method mapRecord:(Lorg/apache/kafka/clients/consumer/ConsumerRecord;)Lno/nav/common/kafka/consumer/feilhandtering/StoredConsumerRecord;
      23: invokeinterface #31,  2           // InterfaceMethod no/nav/common/kafka/consumer/feilhandtering/KafkaConsumerRepository.storeRecord:(Lno/nav/common/kafka/consumer/feilhandtering/StoredConsumerRecord;)J
      28: pop2
      29: aload_0
      30: getfield      #22                 // Field kafkaConsumerRepository:Lno/nav/common/kafka/consumer/feilhandtering/KafkaConsumerRepository;
      33: aload_0
      34: new           #25                 // class org/apache/kafka/clients/consumer/ConsumerRecord
      37: dup
      38: ldc           #36                 // String topic1
      40: iconst_1
      41: ldc2_w        #37                 // long 2l
      44: ldc           #27                 // String key
      46: ldc           #28                 // String value
      48: invokespecial #29                 // Method org/apache/kafka/clients/consumer/ConsumerRecord."<init>":(Ljava/lang/String;IJLjava/lang/Object;Ljava/lang/Object;)V
      51: invokevirtual #30                 // Method mapRecord:(Lorg/apache/kafka/clients/consumer/ConsumerRecord;)Lno/nav/common/kafka/consumer/feilhandtering/StoredConsumerRecord;
      54: invokeinterface #31,  2           // InterfaceMethod no/nav/common/kafka/consumer/feilhandtering/KafkaConsumerRepository.storeRecord:(Lno/nav/common/kafka/consumer/feilhandtering/StoredConsumerRecord;)J
      59: pop2
      60: aload_0
      61: getfield      #22                 // Field kafkaConsumerRepository:Lno/nav/common/kafka/consumer/feilhandtering/KafkaConsumerRepository;
      64: aload_0
      65: new           #25                 // class org/apache/kafka/clients/consumer/ConsumerRecord
      68: dup
      69: ldc           #36                 // String topic1
      71: iconst_1
      72: ldc2_w        #62                 // long 3l
      75: ldc           #27                 // String key
      77: ldc           #28                 // String value
      79: invokespecial #29                 // Method org/apache/kafka/clients/consumer/ConsumerRecord."<init>":(Ljava/lang/String;IJLjava/lang/Object;Ljava/lang/Object;)V
      82: invokevirtual #30                 // Method mapRecord:(Lorg/apache/kafka/clients/consumer/ConsumerRecord;)Lno/nav/common/kafka/consumer/feilhandtering/StoredConsumerRecord;
      85: invokeinterface #31,  2           // InterfaceMethod no/nav/common/kafka/consumer/feilhandtering/KafkaConsumerRepository.storeRecord:(Lno/nav/common/kafka/consumer/feilhandtering/StoredConsumerRecord;)J
      90: pop2
      91: aload_0
      92: getfield      #22                 // Field kafkaConsumerRepository:Lno/nav/common/kafka/consumer/feilhandtering/KafkaConsumerRepository;
      95: aload_0
      96: new           #25                 // class org/apache/kafka/clients/consumer/ConsumerRecord
      99: dup
     100: ldc           #36                 // String topic1
     102: iconst_1
     103: ldc2_w        #64                 // long 4l
     106: ldc           #27                 // String key
     108: ldc           #28                 // String value
     110: invokespecial #29                 // Method org/apache/kafka/clients/consumer/ConsumerRecord."<init>":(Ljava/lang/String;IJLjava/lang/Object;Ljava/lang/Object;)V
     113: invokevirtual #30                 // Method mapRecord:(Lorg/apache/kafka/clients/consumer/ConsumerRecord;)Lno/nav/common/kafka/consumer/feilhandtering/StoredConsumerRecord;
     116: invokeinterface #31,  2           // InterfaceMethod no/nav/common/kafka/consumer/feilhandtering/KafkaConsumerRepository.storeRecord:(Lno/nav/common/kafka/consumer/feilhandtering/StoredConsumerRecord;)J
     121: pop2
     122: aload_0
     123: getfield      #22                 // Field kafkaConsumerRepository:Lno/nav/common/kafka/consumer/feilhandtering/KafkaConsumerRepository;
     126: ldc           #36                 // String topic1
     128: iconst_1
     129: iconst_3
     130: invokeinterface #48,  4           // InterfaceMethod no/nav/common/kafka/consumer/feilhandtering/KafkaConsumerRepository.getRecords:(Ljava/lang/String;II)Ljava/util/List;
     135: astore_1
     136: ldc2_w        #62                 // long 3l
     139: aload_1
     140: invokeinterface #72,  1           // InterfaceMethod java/util/List.size:()I
     145: i2l
     146: invokestatic  #32                 // Method org/junit/Assert.assertEquals:(JJ)V
     149: return

  public void should_find_record_with_key();
    Code:
       0: ldc           #73                 // String key2
       2: astore_1
       3: aload_0
       4: getfield      #22                 // Field kafkaConsumerRepository:Lno/nav/common/kafka/consumer/feilhandtering/KafkaConsumerRepository;
       7: aload_0
       8: new           #25                 // class org/apache/kafka/clients/consumer/ConsumerRecord
      11: dup
      12: ldc           #36                 // String topic1
      14: iconst_1
      15: ldc2_w        #37                 // long 2l
      18: aload_1
      19: ldc           #28                 // String value
      21: invokespecial #29                 // Method org/apache/kafka/clients/consumer/ConsumerRecord."<init>":(Ljava/lang/String;IJLjava/lang/Object;Ljava/lang/Object;)V
      24: invokevirtual #30                 // Method mapRecord:(Lorg/apache/kafka/clients/consumer/ConsumerRecord;)Lno/nav/common/kafka/consumer/feilhandtering/StoredConsumerRecord;
      27: invokeinterface #31,  2           // InterfaceMethod no/nav/common/kafka/consumer/feilhandtering/KafkaConsumerRepository.storeRecord:(Lno/nav/common/kafka/consumer/feilhandtering/StoredConsumerRecord;)J
      32: pop2
      33: aload_0
      34: getfield      #22                 // Field kafkaConsumerRepository:Lno/nav/common/kafka/consumer/feilhandtering/KafkaConsumerRepository;
      37: ldc           #36                 // String topic1
      39: iconst_1
      40: aload_1
      41: invokevirtual #45                 // Method java/lang/String.getBytes:()[B
      44: invokeinterface #74,  4           // InterfaceMethod no/nav/common/kafka/consumer/feilhandtering/KafkaConsumerRepository.hasRecordWithKey:(Ljava/lang/String;I[B)Z
      49: invokestatic  #75                 // Method org/junit/Assert.assertTrue:(Z)V
      52: return

  public void should_not_find_record_with_different_key();
    Code:
       0: ldc           #73                 // String key2
       2: astore_1
       3: aload_0
       4: getfield      #22                 // Field kafkaConsumerRepository:Lno/nav/common/kafka/consumer/feilhandtering/KafkaConsumerRepository;
       7: aload_0
       8: new           #25                 // class org/apache/kafka/clients/consumer/ConsumerRecord
      11: dup
      12: ldc           #36                 // String topic1
      14: iconst_1
      15: ldc2_w        #37                 // long 2l
      18: ldc           #76                 // String key1
      20: ldc           #28                 // String value
      22: invokespecial #29                 // Method org/apache/kafka/clients/consumer/ConsumerRecord."<init>":(Ljava/lang/String;IJLjava/lang/Object;Ljava/lang/Object;)V
      25: invokevirtual #30                 // Method mapRecord:(Lorg/apache/kafka/clients/consumer/ConsumerRecord;)Lno/nav/common/kafka/consumer/feilhandtering/StoredConsumerRecord;
      28: invokeinterface #31,  2           // InterfaceMethod no/nav/common/kafka/consumer/feilhandtering/KafkaConsumerRepository.storeRecord:(Lno/nav/common/kafka/consumer/feilhandtering/StoredConsumerRecord;)J
      33: pop2
      34: aload_0
      35: getfield      #22                 // Field kafkaConsumerRepository:Lno/nav/common/kafka/consumer/feilhandtering/KafkaConsumerRepository;
      38: ldc           #36                 // String topic1
      40: iconst_1
      41: aload_1
      42: invokevirtual #45                 // Method java/lang/String.getBytes:()[B
      45: invokeinterface #74,  4           // InterfaceMethod no/nav/common/kafka/consumer/feilhandtering/KafkaConsumerRepository.hasRecordWithKey:(Ljava/lang/String;I[B)Z
      50: invokestatic  #77                 // Method org/junit/Assert.assertFalse:(Z)V
      53: return

  public void should_increment_retries();
    Code:
       0: aload_0
       1: getfield      #22                 // Field kafkaConsumerRepository:Lno/nav/common/kafka/consumer/feilhandtering/KafkaConsumerRepository;
       4: aload_0
       5: new           #25                 // class org/apache/kafka/clients/consumer/ConsumerRecord
       8: dup
       9: ldc           #36                 // String topic1
      11: iconst_1
      12: ldc2_w        #37                 // long 2l
      15: ldc           #76                 // String key1
      17: ldc           #28                 // String value
      19: invokespecial #29                 // Method org/apache/kafka/clients/consumer/ConsumerRecord."<init>":(Ljava/lang/String;IJLjava/lang/Object;Ljava/lang/Object;)V
      22: invokevirtual #30                 // Method mapRecord:(Lorg/apache/kafka/clients/consumer/ConsumerRecord;)Lno/nav/common/kafka/consumer/feilhandtering/StoredConsumerRecord;
      25: invokeinterface #31,  2           // InterfaceMethod no/nav/common/kafka/consumer/feilhandtering/KafkaConsumerRepository.storeRecord:(Lno/nav/common/kafka/consumer/feilhandtering/StoredConsumerRecord;)J
      30: lstore_1
      31: aload_0
      32: getfield      #22                 // Field kafkaConsumerRepository:Lno/nav/common/kafka/consumer/feilhandtering/KafkaConsumerRepository;
      35: lload_1
      36: invokeinterface #78,  3           // InterfaceMethod no/nav/common/kafka/consumer/feilhandtering/KafkaConsumerRepository.incrementRetries:(J)V
      41: aload_0
      42: getfield      #22                 // Field kafkaConsumerRepository:Lno/nav/common/kafka/consumer/feilhandtering/KafkaConsumerRepository;
      45: lload_1
      46: invokeinterface #78,  3           // InterfaceMethod no/nav/common/kafka/consumer/feilhandtering/KafkaConsumerRepository.incrementRetries:(J)V
      51: aload_0
      52: getfield      #22                 // Field kafkaConsumerRepository:Lno/nav/common/kafka/consumer/feilhandtering/KafkaConsumerRepository;
      55: ldc           #36                 // String topic1
      57: iconst_1
      58: iconst_3
      59: invokeinterface #48,  4           // InterfaceMethod no/nav/common/kafka/consumer/feilhandtering/KafkaConsumerRepository.getRecords:(Ljava/lang/String;II)Ljava/util/List;
      64: astore_3
      65: ldc2_w        #37                 // long 2l
      68: aload_3
      69: iconst_0
      70: invokeinterface #49,  2           // InterfaceMethod java/util/List.get:(I)Ljava/lang/Object;
      75: checkcast     #50                 // class no/nav/common/kafka/consumer/feilhandtering/StoredConsumerRecord
      78: invokevirtual #79                 // Method no/nav/common/kafka/consumer/feilhandtering/StoredConsumerRecord.getRetries:()I
      81: i2l
      82: invokestatic  #32                 // Method org/junit/Assert.assertEquals:(JJ)V
      85: aload_3
      86: iconst_0
      87: invokeinterface #49,  2           // InterfaceMethod java/util/List.get:(I)Ljava/lang/Object;
      92: checkcast     #50                 // class no/nav/common/kafka/consumer/feilhandtering/StoredConsumerRecord
      95: invokevirtual #80                 // Method no/nav/common/kafka/consumer/feilhandtering/StoredConsumerRecord.getLastRetry:()Ljava/sql/Timestamp;
      98: invokestatic  #81                 // Method org/junit/Assert.assertNotNull:(Ljava/lang/Object;)V
     101: return

  public void should_get_topic_partitions();
    Code:
       0: aload_0
       1: getfield      #22                 // Field kafkaConsumerRepository:Lno/nav/common/kafka/consumer/feilhandtering/KafkaConsumerRepository;
       4: aload_0
       5: new           #25                 // class org/apache/kafka/clients/consumer/ConsumerRecord
       8: dup
       9: ldc           #36                 // String topic1
      11: iconst_1
      12: lconst_1
      13: ldc           #76                 // String key1
      15: ldc           #28                 // String value
      17: invokespecial #29                 // Method org/apache/kafka/clients/consumer/ConsumerRecord."<init>":(Ljava/lang/String;IJLjava/lang/Object;Ljava/lang/Object;)V
      20: invokevirtual #30                 // Method mapRecord:(Lorg/apache/kafka/clients/consumer/ConsumerRecord;)Lno/nav/common/kafka/consumer/feilhandtering/StoredConsumerRecord;
      23: invokeinterface #31,  2           // InterfaceMethod no/nav/common/kafka/consumer/feilhandtering/KafkaConsumerRepository.storeRecord:(Lno/nav/common/kafka/consumer/feilhandtering/StoredConsumerRecord;)J
      28: pop2
      29: aload_0
      30: getfield      #22                 // Field kafkaConsumerRepository:Lno/nav/common/kafka/consumer/feilhandtering/KafkaConsumerRepository;
      33: aload_0
      34: new           #25                 // class org/apache/kafka/clients/consumer/ConsumerRecord
      37: dup
      38: ldc           #36                 // String topic1
      40: iconst_2
      41: lconst_1
      42: ldc           #76                 // String key1
      44: ldc           #28                 // String value
      46: invokespecial #29                 // Method org/apache/kafka/clients/consumer/ConsumerRecord."<init>":(Ljava/lang/String;IJLjava/lang/Object;Ljava/lang/Object;)V
      49: invokevirtual #30                 // Method mapRecord:(Lorg/apache/kafka/clients/consumer/ConsumerRecord;)Lno/nav/common/kafka/consumer/feilhandtering/StoredConsumerRecord;
      52: invokeinterface #31,  2           // InterfaceMethod no/nav/common/kafka/consumer/feilhandtering/KafkaConsumerRepository.storeRecord:(Lno/nav/common/kafka/consumer/feilhandtering/StoredConsumerRecord;)J
      57: pop2
      58: aload_0
      59: getfield      #22                 // Field kafkaConsumerRepository:Lno/nav/common/kafka/consumer/feilhandtering/KafkaConsumerRepository;
      62: aload_0
      63: new           #25                 // class org/apache/kafka/clients/consumer/ConsumerRecord
      66: dup
      67: ldc           #36                 // String topic1
      69: iconst_2
      70: ldc2_w        #37                 // long 2l
      73: ldc           #76                 // String key1
      75: ldc           #28                 // String value
      77: invokespecial #29                 // Method org/apache/kafka/clients/consumer/ConsumerRecord."<init>":(Ljava/lang/String;IJLjava/lang/Object;Ljava/lang/Object;)V
      80: invokevirtual #30                 // Method mapRecord:(Lorg/apache/kafka/clients/consumer/ConsumerRecord;)Lno/nav/common/kafka/consumer/feilhandtering/StoredConsumerRecord;
      83: invokeinterface #31,  2           // InterfaceMethod no/nav/common/kafka/consumer/feilhandtering/KafkaConsumerRepository.storeRecord:(Lno/nav/common/kafka/consumer/feilhandtering/StoredConsumerRecord;)J
      88: pop2
      89: aload_0
      90: getfield      #22                 // Field kafkaConsumerRepository:Lno/nav/common/kafka/consumer/feilhandtering/KafkaConsumerRepository;
      93: aload_0
      94: new           #25                 // class org/apache/kafka/clients/consumer/ConsumerRecord
      97: dup
      98: ldc           #82                 // String topic2
     100: iconst_1
     101: lconst_1
     102: ldc           #76                 // String key1
     104: ldc           #28                 // String value
     106: invokespecial #29                 // Method org/apache/kafka/clients/consumer/ConsumerRecord."<init>":(Ljava/lang/String;IJLjava/lang/Object;Ljava/lang/Object;)V
     109: invokevirtual #30                 // Method mapRecord:(Lorg/apache/kafka/clients/consumer/ConsumerRecord;)Lno/nav/common/kafka/consumer/feilhandtering/StoredConsumerRecord;
     112: invokeinterface #31,  2           // InterfaceMethod no/nav/common/kafka/consumer/feilhandtering/KafkaConsumerRepository.storeRecord:(Lno/nav/common/kafka/consumer/feilhandtering/StoredConsumerRecord;)J
     117: pop2
     118: aload_0
     119: getfield      #22                 // Field kafkaConsumerRepository:Lno/nav/common/kafka/consumer/feilhandtering/KafkaConsumerRepository;
     122: aload_0
     123: new           #25                 // class org/apache/kafka/clients/consumer/ConsumerRecord
     126: dup
     127: ldc           #83                 // String topic3
     129: iconst_1
     130: lconst_1
     131: ldc           #76                 // String key1
     133: ldc           #28                 // String value
     135: invokespecial #29                 // Method org/apache/kafka/clients/consumer/ConsumerRecord."<init>":(Ljava/lang/String;IJLjava/lang/Object;Ljava/lang/Object;)V
     138: invokevirtual #30                 // Method mapRecord:(Lorg/apache/kafka/clients/consumer/ConsumerRecord;)Lno/nav/common/kafka/consumer/feilhandtering/StoredConsumerRecord;
     141: invokeinterface #31,  2           // InterfaceMethod no/nav/common/kafka/consumer/feilhandtering/KafkaConsumerRepository.storeRecord:(Lno/nav/common/kafka/consumer/feilhandtering/StoredConsumerRecord;)J
     146: pop2
     147: aload_0
     148: getfield      #22                 // Field kafkaConsumerRepository:Lno/nav/common/kafka/consumer/feilhandtering/KafkaConsumerRepository;
     151: ldc           #36                 // String topic1
     153: ldc           #83                 // String topic3
     155: invokestatic  #84                 // InterfaceMethod java/util/List.of:(Ljava/lang/Object;Ljava/lang/Object;)Ljava/util/List;
     158: invokeinterface #85,  2           // InterfaceMethod no/nav/common/kafka/consumer/feilhandtering/KafkaConsumerRepository.getTopicPartitions:(Ljava/util/List;)Ljava/util/List;
     163: astore_1
     164: ldc2_w        #62                 // long 3l
     167: aload_1
     168: invokeinterface #72,  1           // InterfaceMethod java/util/List.size:()I
     173: i2l
     174: invokestatic  #32                 // Method org/junit/Assert.assertEquals:(JJ)V
     177: new           #86                 // class org/apache/kafka/common/TopicPartition
     180: dup
     181: ldc           #36                 // String topic1
     183: iconst_1
     184: invokespecial #87                 // Method org/apache/kafka/common/TopicPartition."<init>":(Ljava/lang/String;I)V
     187: aload_1
     188: iconst_0
     189: invokeinterface #49,  2           // InterfaceMethod java/util/List.get:(I)Ljava/lang/Object;
     194: invokestatic  #53                 // Method org/junit/Assert.assertEquals:(Ljava/lang/Object;Ljava/lang/Object;)V
     197: new           #86                 // class org/apache/kafka/common/TopicPartition
     200: dup
     201: ldc           #36                 // String topic1
     203: iconst_2
     204: invokespecial #87                 // Method org/apache/kafka/common/TopicPartition."<init>":(Ljava/lang/String;I)V
     207: aload_1
     208: iconst_1
     209: invokeinterface #49,  2           // InterfaceMethod java/util/List.get:(I)Ljava/lang/Object;
     214: invokestatic  #53                 // Method org/junit/Assert.assertEquals:(Ljava/lang/Object;Ljava/lang/Object;)V
     217: new           #86                 // class org/apache/kafka/common/TopicPartition
     220: dup
     221: ldc           #83                 // String topic3
     223: iconst_1
     224: invokespecial #87                 // Method org/apache/kafka/common/TopicPartition."<init>":(Ljava/lang/String;I)V
     227: aload_1
     228: iconst_2
     229: invokeinterface #49,  2           // InterfaceMethod java/util/List.get:(I)Ljava/lang/Object;
     234: invokestatic  #53                 // Method org/junit/Assert.assertEquals:(Ljava/lang/Object;Ljava/lang/Object;)V
     237: return

  public void should_delete_records();
    Code:
       0: aload_0
       1: getfield      #22                 // Field kafkaConsumerRepository:Lno/nav/common/kafka/consumer/feilhandtering/KafkaConsumerRepository;
       4: aload_0
       5: new           #25                 // class org/apache/kafka/clients/consumer/ConsumerRecord
       8: dup
       9: ldc           #36                 // String topic1
      11: iconst_1
      12: lconst_1
      13: ldc           #27                 // String key
      15: ldc           #28                 // String value
      17: invokespecial #29                 // Method org/apache/kafka/clients/consumer/ConsumerRecord."<init>":(Ljava/lang/String;IJLjava/lang/Object;Ljava/lang/Object;)V
      20: invokevirtual #30                 // Method mapRecord:(Lorg/apache/kafka/clients/consumer/ConsumerRecord;)Lno/nav/common/kafka/consumer/feilhandtering/StoredConsumerRecord;
      23: invokeinterface #31,  2           // InterfaceMethod no/nav/common/kafka/consumer/feilhandtering/KafkaConsumerRepository.storeRecord:(Lno/nav/common/kafka/consumer/feilhandtering/StoredConsumerRecord;)J
      28: lstore_1
      29: aload_0
      30: getfield      #22                 // Field kafkaConsumerRepository:Lno/nav/common/kafka/consumer/feilhandtering/KafkaConsumerRepository;
      33: aload_0
      34: new           #25                 // class org/apache/kafka/clients/consumer/ConsumerRecord
      37: dup
      38: ldc           #36                 // String topic1
      40: iconst_1
      41: ldc2_w        #37                 // long 2l
      44: ldc           #27                 // String key
      46: ldc           #28                 // String value
      48: invokespecial #29                 // Method org/apache/kafka/clients/consumer/ConsumerRecord."<init>":(Ljava/lang/String;IJLjava/lang/Object;Ljava/lang/Object;)V
      51: invokevirtual #30                 // Method mapRecord:(Lorg/apache/kafka/clients/consumer/ConsumerRecord;)Lno/nav/common/kafka/consumer/feilhandtering/StoredConsumerRecord;
      54: invokeinterface #31,  2           // InterfaceMethod no/nav/common/kafka/consumer/feilhandtering/KafkaConsumerRepository.storeRecord:(Lno/nav/common/kafka/consumer/feilhandtering/StoredConsumerRecord;)J
      59: lstore_3
      60: aload_0
      61: getfield      #22                 // Field kafkaConsumerRepository:Lno/nav/common/kafka/consumer/feilhandtering/KafkaConsumerRepository;
      64: aload_0
      65: new           #25                 // class org/apache/kafka/clients/consumer/ConsumerRecord
      68: dup
      69: ldc           #36                 // String topic1
      71: iconst_1
      72: ldc2_w        #62                 // long 3l
      75: ldc           #27                 // String key
      77: ldc           #28                 // String value
      79: invokespecial #29                 // Method org/apache/kafka/clients/consumer/ConsumerRecord."<init>":(Ljava/lang/String;IJLjava/lang/Object;Ljava/lang/Object;)V
      82: invokevirtual #30                 // Method mapRecord:(Lorg/apache/kafka/clients/consumer/ConsumerRecord;)Lno/nav/common/kafka/consumer/feilhandtering/StoredConsumerRecord;
      85: invokeinterface #31,  2           // InterfaceMethod no/nav/common/kafka/consumer/feilhandtering/KafkaConsumerRepository.storeRecord:(Lno/nav/common/kafka/consumer/feilhandtering/StoredConsumerRecord;)J
      90: lstore        5
      92: aload_0
      93: getfield      #22                 // Field kafkaConsumerRepository:Lno/nav/common/kafka/consumer/feilhandtering/KafkaConsumerRepository;
      96: lload_1
      97: invokestatic  #88                 // Method java/lang/Long.valueOf:(J)Ljava/lang/Long;
     100: lload         5
     102: invokestatic  #88                 // Method java/lang/Long.valueOf:(J)Ljava/lang/Long;
     105: invokestatic  #84                 // InterfaceMethod java/util/List.of:(Ljava/lang/Object;Ljava/lang/Object;)Ljava/util/List;
     108: invokeinterface #89,  2           // InterfaceMethod no/nav/common/kafka/consumer/feilhandtering/KafkaConsumerRepository.deleteRecords:(Ljava/util/List;)V
     113: aload_0
     114: getfield      #22                 // Field kafkaConsumerRepository:Lno/nav/common/kafka/consumer/feilhandtering/KafkaConsumerRepository;
     117: ldc           #36                 // String topic1
     119: iconst_1
     120: iconst_5
     121: invokeinterface #48,  4           // InterfaceMethod no/nav/common/kafka/consumer/feilhandtering/KafkaConsumerRepository.getRecords:(Ljava/lang/String;II)Ljava/util/List;
     126: astore        7
     128: lconst_1
     129: aload         7
     131: invokeinterface #72,  1           // InterfaceMethod java/util/List.size:()I
     136: i2l
     137: invokestatic  #32                 // Method org/junit/Assert.assertEquals:(JJ)V
     140: lload_3
     141: aload         7
     143: iconst_0
     144: invokeinterface #49,  2           // InterfaceMethod java/util/List.get:(I)Ljava/lang/Object;
     149: checkcast     #50                 // class no/nav/common/kafka/consumer/feilhandtering/StoredConsumerRecord
     152: invokevirtual #51                 // Method no/nav/common/kafka/consumer/feilhandtering/StoredConsumerRecord.getId:()J
     155: invokestatic  #32                 // Method org/junit/Assert.assertEquals:(JJ)V
     158: return

  private no.nav.common.kafka.consumer.feilhandtering.StoredConsumerRecord mapRecord(org.apache.kafka.clients.consumer.ConsumerRecord<java.lang.String, java.lang.String>);
    Code:
       0: aload_1
       1: new           #90                 // class org/apache/kafka/common/serialization/StringSerializer
       4: dup
       5: invokespecial #91                 // Method org/apache/kafka/common/serialization/StringSerializer."<init>":()V
       8: new           #90                 // class org/apache/kafka/common/serialization/StringSerializer
      11: dup
      12: invokespecial #91                 // Method org/apache/kafka/common/serialization/StringSerializer."<init>":()V
      15: invokestatic  #92                 // Method no/nav/common/kafka/consumer/util/ConsumerUtils.mapToStoredRecord:(Lorg/apache/kafka/clients/consumer/ConsumerRecord;Lorg/apache/kafka/common/serialization/Serializer;Lorg/apache/kafka/common/serialization/Serializer;)Lno/nav/common/kafka/consumer/feilhandtering/StoredConsumerRecord;
      18: areturn

  private static int lambda$should_retrieve_records_in_order$0(no.nav.common.kafka.consumer.feilhandtering.StoredConsumerRecord, no.nav.common.kafka.consumer.feilhandtering.StoredConsumerRecord);
    Code:
       0: aload_0
       1: invokevirtual #55                 // Method no/nav/common/kafka/consumer/feilhandtering/StoredConsumerRecord.getOffset:()J
       4: aload_1
       5: invokevirtual #55                 // Method no/nav/common/kafka/consumer/feilhandtering/StoredConsumerRecord.getOffset:()J
       8: lsub
       9: l2i
      10: ireturn

  static {};
    Code:
       0: invokestatic  #93                 // Method no/nav/common/kafka/utils/LocalPostgresDatabase.createPostgresContainer:()Lorg/testcontainers/containers/PostgreSQLContainer;
       3: putstatic     #1                  // Field postgreSQLContainer:Lorg/testcontainers/containers/PostgreSQLContainer;
       6: return
}
