Compiled from "ServerProxy.java"
class org.jboss.remotingjmx.protocol.v1.ServerProxy$RemoteNotificationManager {
  private java.util.Map<java.lang.Integer, org.jboss.remotingjmx.protocol.v1.ServerProxy$RemoteNotificationManager$Association> listeners;

  final org.jboss.remotingjmx.protocol.v1.ServerProxy this$0;

  private org.jboss.remotingjmx.protocol.v1.ServerProxy$RemoteNotificationManager(org.jboss.remotingjmx.protocol.v1.ServerProxy);
    Code:
       0: aload_0
       1: aload_1
       2: putfield      #5                  // Field this$0:Lorg/jboss/remotingjmx/protocol/v1/ServerProxy;
       5: aload_0
       6: invokespecial #6                  // Method java/lang/Object."<init>":()V
       9: aload_0
      10: new           #7                  // class java/util/HashMap
      13: dup
      14: invokespecial #8                  // Method java/util/HashMap."<init>":()V
      17: putfield      #9                  // Field listeners:Ljava/util/Map;
      20: return

  private synchronized void addNotificationListener(javax.management.ObjectName, int, javax.management.NotificationFilter, java.lang.Object) throws javax.management.InstanceNotFoundException, java.io.IOException;
    Code:
       0: new           #10                 // class org/jboss/remotingjmx/protocol/v1/ServerProxy$RemoteNotificationManager$NotificationProxy
       3: dup
       4: aload_0
       5: iload_2
       6: aconst_null
       7: invokespecial #11                 // Method org/jboss/remotingjmx/protocol/v1/ServerProxy$RemoteNotificationManager$NotificationProxy."<init>":(Lorg/jboss/remotingjmx/protocol/v1/ServerProxy$RemoteNotificationManager;ILorg/jboss/remotingjmx/protocol/v1/ServerProxy$1;)V
      10: astore        5
      12: aload_0
      13: getfield      #5                  // Field this$0:Lorg/jboss/remotingjmx/protocol/v1/ServerProxy;
      16: invokestatic  #12                 // Method org/jboss/remotingjmx/protocol/v1/ServerProxy.access$2800:(Lorg/jboss/remotingjmx/protocol/v1/ServerProxy;)Lorg/jboss/remotingjmx/WrappedMBeanServerConnection;
      19: invokeinterface #13,  1           // InterfaceMethod org/jboss/remotingjmx/WrappedMBeanServerConnection.getMBeanServerConnection:()Ljavax/management/MBeanServerConnection;
      24: aload_1
      25: aload         5
      27: aload_3
      28: aload         4
      30: invokeinterface #14,  5           // InterfaceMethod javax/management/MBeanServerConnection.addNotificationListener:(Ljavax/management/ObjectName;Ljavax/management/NotificationListener;Ljavax/management/NotificationFilter;Ljava/lang/Object;)V
      35: new           #15                 // class org/jboss/remotingjmx/protocol/v1/ServerProxy$RemoteNotificationManager$Association
      38: dup
      39: aload_0
      40: aconst_null
      41: invokespecial #16                 // Method org/jboss/remotingjmx/protocol/v1/ServerProxy$RemoteNotificationManager$Association."<init>":(Lorg/jboss/remotingjmx/protocol/v1/ServerProxy$RemoteNotificationManager;Lorg/jboss/remotingjmx/protocol/v1/ServerProxy$1;)V
      44: astore        6
      46: aload         6
      48: aload_1
      49: invokestatic  #17                 // Method org/jboss/remotingjmx/protocol/v1/ServerProxy$RemoteNotificationManager$Association.access$3102:(Lorg/jboss/remotingjmx/protocol/v1/ServerProxy$RemoteNotificationManager$Association;Ljavax/management/ObjectName;)Ljavax/management/ObjectName;
      52: pop
      53: aload         6
      55: aload         5
      57: invokestatic  #18                 // Method org/jboss/remotingjmx/protocol/v1/ServerProxy$RemoteNotificationManager$Association.access$3202:(Lorg/jboss/remotingjmx/protocol/v1/ServerProxy$RemoteNotificationManager$Association;Ljavax/management/NotificationListener;)Ljavax/management/NotificationListener;
      60: pop
      61: aload         6
      63: aload_3
      64: invokestatic  #19                 // Method org/jboss/remotingjmx/protocol/v1/ServerProxy$RemoteNotificationManager$Association.access$3302:(Lorg/jboss/remotingjmx/protocol/v1/ServerProxy$RemoteNotificationManager$Association;Ljavax/management/NotificationFilter;)Ljavax/management/NotificationFilter;
      67: pop
      68: aload         6
      70: aload         4
      72: invokestatic  #20                 // Method org/jboss/remotingjmx/protocol/v1/ServerProxy$RemoteNotificationManager$Association.access$3402:(Lorg/jboss/remotingjmx/protocol/v1/ServerProxy$RemoteNotificationManager$Association;Ljava/lang/Object;)Ljava/lang/Object;
      75: pop
      76: aload_0
      77: getfield      #9                  // Field listeners:Ljava/util/Map;
      80: iload_2
      81: invokestatic  #21                 // Method java/lang/Integer.valueOf:(I)Ljava/lang/Integer;
      84: aload         6
      86: invokeinterface #22,  3           // InterfaceMethod java/util/Map.put:(Ljava/lang/Object;Ljava/lang/Object;)Ljava/lang/Object;
      91: pop
      92: return

  private synchronized void removeNotificationListener();
    Code:
       0: aload_0
       1: getfield      #9                  // Field listeners:Ljava/util/Map;
       4: invokeinterface #23,  1           // InterfaceMethod java/util/Map.keySet:()Ljava/util/Set;
       9: invokeinterface #24,  1           // InterfaceMethod java/util/Set.iterator:()Ljava/util/Iterator;
      14: astore_1
      15: aload_0
      16: getfield      #9                  // Field listeners:Ljava/util/Map;
      19: invokeinterface #25,  1           // InterfaceMethod java/util/Map.size:()I
      24: newarray       int
      26: astore_2
      27: iconst_0
      28: istore_3
      29: iload_3
      30: aload_2
      31: arraylength
      32: if_icmpge     56
      35: aload_2
      36: iload_3
      37: aload_1
      38: invokeinterface #26,  1           // InterfaceMethod java/util/Iterator.next:()Ljava/lang/Object;
      43: checkcast     #27                 // class java/lang/Integer
      46: invokevirtual #28                 // Method java/lang/Integer.intValue:()I
      49: iastore
      50: iinc          3, 1
      53: goto          29
      56: aload_0
      57: aload_2
      58: invokespecial #1                  // Method removeNotificationListeners:([I)V
      61: return

  private synchronized void removeNotificationListener(int) throws javax.management.ListenerNotFoundException, javax.management.InstanceNotFoundException, java.io.IOException;
    Code:
       0: aload_0
       1: getfield      #9                  // Field listeners:Ljava/util/Map;
       4: iload_1
       5: invokestatic  #21                 // Method java/lang/Integer.valueOf:(I)Ljava/lang/Integer;
       8: invokeinterface #29,  2           // InterfaceMethod java/util/Map.remove:(Ljava/lang/Object;)Ljava/lang/Object;
      13: checkcast     #15                 // class org/jboss/remotingjmx/protocol/v1/ServerProxy$RemoteNotificationManager$Association
      16: astore_2
      17: aload_2
      18: ifnull        57
      21: aload_0
      22: getfield      #5                  // Field this$0:Lorg/jboss/remotingjmx/protocol/v1/ServerProxy;
      25: invokestatic  #12                 // Method org/jboss/remotingjmx/protocol/v1/ServerProxy.access$2800:(Lorg/jboss/remotingjmx/protocol/v1/ServerProxy;)Lorg/jboss/remotingjmx/WrappedMBeanServerConnection;
      28: invokeinterface #13,  1           // InterfaceMethod org/jboss/remotingjmx/WrappedMBeanServerConnection.getMBeanServerConnection:()Ljavax/management/MBeanServerConnection;
      33: aload_2
      34: invokestatic  #30                 // Method org/jboss/remotingjmx/protocol/v1/ServerProxy$RemoteNotificationManager$Association.access$3100:(Lorg/jboss/remotingjmx/protocol/v1/ServerProxy$RemoteNotificationManager$Association;)Ljavax/management/ObjectName;
      37: aload_2
      38: invokestatic  #31                 // Method org/jboss/remotingjmx/protocol/v1/ServerProxy$RemoteNotificationManager$Association.access$3200:(Lorg/jboss/remotingjmx/protocol/v1/ServerProxy$RemoteNotificationManager$Association;)Ljavax/management/NotificationListener;
      41: aload_2
      42: invokestatic  #32                 // Method org/jboss/remotingjmx/protocol/v1/ServerProxy$RemoteNotificationManager$Association.access$3300:(Lorg/jboss/remotingjmx/protocol/v1/ServerProxy$RemoteNotificationManager$Association;)Ljavax/management/NotificationFilter;
      45: aload_2
      46: invokestatic  #33                 // Method org/jboss/remotingjmx/protocol/v1/ServerProxy$RemoteNotificationManager$Association.access$3400:(Lorg/jboss/remotingjmx/protocol/v1/ServerProxy$RemoteNotificationManager$Association;)Ljava/lang/Object;
      49: invokeinterface #34,  5           // InterfaceMethod javax/management/MBeanServerConnection.removeNotificationListener:(Ljavax/management/ObjectName;Ljavax/management/NotificationListener;Ljavax/management/NotificationFilter;Ljava/lang/Object;)V
      54: goto          69
      57: invokestatic  #35                 // Method org/jboss/remotingjmx/protocol/v1/ServerProxy.access$2200:()Lorg/jboss/logging/Logger;
      60: ldc           #36                 // String Request to removeNotificationListener, listener with ID %d not found.
      62: iload_1
      63: invokestatic  #21                 // Method java/lang/Integer.valueOf:(I)Ljava/lang/Integer;
      66: invokevirtual #37                 // Method org/jboss/logging/Logger.warnf:(Ljava/lang/String;Ljava/lang/Object;)V
      69: return

  private void removeNotificationListeners(int[]);
    Code:
       0: aload_1
       1: astore_2
       2: aload_2
       3: arraylength
       4: istore_3
       5: iconst_0
       6: istore        4
       8: iload         4
      10: iload_3
      11: if_icmpge     77
      14: aload_2
      15: iload         4
      17: iaload
      18: istore        5
      20: aload_0
      21: iload         5
      23: invokespecial #38                 // Method removeNotificationListener:(I)V
      26: goto          71
      29: astore        6
      31: invokestatic  #35                 // Method org/jboss/remotingjmx/protocol/v1/ServerProxy.access$2200:()Lorg/jboss/logging/Logger;
      34: ldc           #40                 // String Failure removing notification listener
      36: aload         6
      38: invokevirtual #41                 // Method org/jboss/logging/Logger.warn:(Ljava/lang/Object;Ljava/lang/Throwable;)V
      41: goto          71
      44: astore        6
      46: invokestatic  #35                 // Method org/jboss/remotingjmx/protocol/v1/ServerProxy.access$2200:()Lorg/jboss/logging/Logger;
      49: ldc           #40                 // String Failure removing notification listener
      51: aload         6
      53: invokevirtual #41                 // Method org/jboss/logging/Logger.warn:(Ljava/lang/Object;Ljava/lang/Throwable;)V
      56: goto          71
      59: astore        6
      61: invokestatic  #35                 // Method org/jboss/remotingjmx/protocol/v1/ServerProxy.access$2200:()Lorg/jboss/logging/Logger;
      64: ldc           #40                 // String Failure removing notification listener
      66: aload         6
      68: invokevirtual #41                 // Method org/jboss/logging/Logger.warn:(Ljava/lang/Object;Ljava/lang/Throwable;)V
      71: iinc          4, 1
      74: goto          8
      77: return
    Exception table:
       from    to  target type
          20    26    29   Class javax/management/ListenerNotFoundException
          20    26    44   Class javax/management/InstanceNotFoundException
          20    26    59   Class java/io/IOException

  org.jboss.remotingjmx.protocol.v1.ServerProxy$RemoteNotificationManager(org.jboss.remotingjmx.protocol.v1.ServerProxy, org.jboss.remotingjmx.protocol.v1.ServerProxy$1);
    Code:
       0: aload_0
       1: aload_1
       2: invokespecial #4                  // Method "<init>":(Lorg/jboss/remotingjmx/protocol/v1/ServerProxy;)V
       5: return

  static void access$2100(org.jboss.remotingjmx.protocol.v1.ServerProxy$RemoteNotificationManager);
    Code:
       0: aload_0
       1: invokespecial #3                  // Method removeNotificationListener:()V
       4: return

  static void access$3700(org.jboss.remotingjmx.protocol.v1.ServerProxy$RemoteNotificationManager, javax.management.ObjectName, int, javax.management.NotificationFilter, java.lang.Object) throws javax.management.InstanceNotFoundException, java.io.IOException;
    Code:
       0: aload_0
       1: aload_1
       2: iload_2
       3: aload_3
       4: aload         4
       6: invokespecial #2                  // Method addNotificationListener:(Ljavax/management/ObjectName;ILjavax/management/NotificationFilter;Ljava/lang/Object;)V
       9: return

  static void access$4600(org.jboss.remotingjmx.protocol.v1.ServerProxy$RemoteNotificationManager, int[]);
    Code:
       0: aload_0
       1: aload_1
       2: invokespecial #1                  // Method removeNotificationListeners:([I)V
       5: return
}
