Compiled from "AppState.java"
public class edu.internet2.middleware.grouper.grouperUi.beans.json.AppState implements java.io.Serializable {
  private boolean inittedSimpleMembershipUpdate;

  private boolean initted;

  private java.lang.String urlInCache;

  private java.util.Map<java.lang.String, edu.internet2.middleware.grouper.grouperUi.beans.json.GuiHideShow> hideShows;

  private java.util.Map<java.lang.String, edu.internet2.middleware.grouper.grouperUi.beans.json.GuiPaging> pagers;

  private java.util.Map<java.lang.String, java.lang.String> urlArgObjects;

  public java.lang.String getUrlArgObjectOrParam(java.lang.String);
    Code:
       0: invokestatic  #1                  // Method edu/internet2/middleware/grouper/ui/GrouperUiFilter.retrieveHttpServletRequest:()Ljavax/servlet/http/HttpServletRequest;
       3: astore_2
       4: aconst_null
       5: astore_3
       6: aload_0
       7: invokevirtual #2                  // Method getUrlArgObjects:()Ljava/util/Map;
      10: ifnull        27
      13: aload_0
      14: invokevirtual #2                  // Method getUrlArgObjects:()Ljava/util/Map;
      17: aload_1
      18: invokeinterface #3,  2            // InterfaceMethod java/util/Map.get:(Ljava/lang/Object;)Ljava/lang/Object;
      23: checkcast     #4                  // class java/lang/String
      26: astore_3
      27: aload_3
      28: invokestatic  #5                  // Method org/apache/commons/lang/StringUtils.isBlank:(Ljava/lang/String;)Z
      31: ifeq          42
      34: aload_2
      35: aload_1
      36: invokeinterface #6,  2            // InterfaceMethod javax/servlet/http/HttpServletRequest.getParameter:(Ljava/lang/String;)Ljava/lang/String;
      41: astore_3
      42: aload_3
      43: areturn

  public boolean isInittedSimpleMembershipUpdate();
    Code:
       0: aload_0
       1: getfield      #7                  // Field inittedSimpleMembershipUpdate:Z
       4: ireturn

  public void setInittedSimpleMembershipUpdate(boolean);
    Code:
       0: aload_0
       1: iload_1
       2: putfield      #7                  // Field inittedSimpleMembershipUpdate:Z
       5: return

  public java.lang.Object getUrlArgObjectMap();
    Code:
       0: aconst_null
       1: areturn

  public void setUrlArgObjectMap(java.lang.Object);
    Code:
       0: return

  public void storeToRequest();
    Code:
       0: invokestatic  #1                  // Method edu/internet2/middleware/grouper/ui/GrouperUiFilter.retrieveHttpServletRequest:()Ljavax/servlet/http/HttpServletRequest;
       3: astore_1
       4: aload_1
       5: ldc           #8                  // String appState
       7: aload_0
       8: invokeinterface #9,  3            // InterfaceMethod javax/servlet/http/HttpServletRequest.setAttribute:(Ljava/lang/String;Ljava/lang/Object;)V
      13: return

  public static edu.internet2.middleware.grouper.grouperUi.beans.json.AppState retrieveFromRequest();
    Code:
       0: invokestatic  #1                  // Method edu/internet2/middleware/grouper/ui/GrouperUiFilter.retrieveHttpServletRequest:()Ljavax/servlet/http/HttpServletRequest;
       3: astore_0
       4: aload_0
       5: ldc           #8                  // String appState
       7: invokeinterface #10,  2           // InterfaceMethod javax/servlet/http/HttpServletRequest.getAttribute:(Ljava/lang/String;)Ljava/lang/Object;
      12: checkcast     #11                 // class edu/internet2/middleware/grouper/grouperUi/beans/json/AppState
      15: astore_1
      16: aload_1
      17: ifnonnull     30
      20: new           #12                 // class java/lang/RuntimeException
      23: dup
      24: ldc           #13                 // String App state is null
      26: invokespecial #14                 // Method java/lang/RuntimeException."<init>":(Ljava/lang/String;)V
      29: athrow
      30: aload_1
      31: areturn

  public boolean isInitted();
    Code:
       0: aload_0
       1: getfield      #15                 // Field initted:Z
       4: ireturn

  public void setInitted(boolean);
    Code:
       0: aload_0
       1: iload_1
       2: putfield      #15                 // Field initted:Z
       5: return

  public edu.internet2.middleware.grouper.grouperUi.beans.json.AppState();
    Code:
       0: aload_0
       1: invokespecial #16                 // Method java/lang/Object."<init>":()V
       4: aload_0
       5: new           #17                 // class java/util/LinkedHashMap
       8: dup
       9: invokespecial #18                 // Method java/util/LinkedHashMap."<init>":()V
      12: putfield      #19                 // Field hideShows:Ljava/util/Map;
      15: aload_0
      16: new           #17                 // class java/util/LinkedHashMap
      19: dup
      20: invokespecial #18                 // Method java/util/LinkedHashMap."<init>":()V
      23: putfield      #20                 // Field pagers:Ljava/util/Map;
      26: aload_0
      27: new           #17                 // class java/util/LinkedHashMap
      30: dup
      31: invokespecial #18                 // Method java/util/LinkedHashMap."<init>":()V
      34: putfield      #21                 // Field urlArgObjects:Ljava/util/Map;
      37: return

  public void initRequest();
    Code:
       0: invokestatic  #22                 // Method edu/internet2/middleware/grouper/grouperUi/beans/SessionContainer.retrieveFromSession:()Ledu/internet2/middleware/grouper/grouperUi/beans/SessionContainer;
       3: astore_1
       4: aload_0
       5: invokevirtual #23                 // Method getHideShows:()Ljava/util/Map;
       8: astore_2
       9: new           #24                 // class net/sf/ezmorph/bean/BeanMorpher
      12: dup
      13: ldc           #25                 // class edu/internet2/middleware/grouper/grouperUi/beans/json/GuiHideShow
      15: invokestatic  #26                 // Method net/sf/json/util/JSONUtils.getMorpherRegistry:()Lnet/sf/ezmorph/MorpherRegistry;
      18: invokespecial #27                 // Method net/sf/ezmorph/bean/BeanMorpher."<init>":(Ljava/lang/Class;Lnet/sf/ezmorph/MorpherRegistry;)V
      21: astore_3
      22: aload_2
      23: ifnull        193
      26: new           #17                 // class java/util/LinkedHashMap
      29: dup
      30: invokespecial #18                 // Method java/util/LinkedHashMap."<init>":()V
      33: astore        4
      35: aload_2
      36: invokeinterface #28,  1           // InterfaceMethod java/util/Map.keySet:()Ljava/util/Set;
      41: invokeinterface #29,  1           // InterfaceMethod java/util/Set.iterator:()Ljava/util/Iterator;
      46: astore        5
      48: aload         5
      50: invokeinterface #30,  1           // InterfaceMethod java/util/Iterator.hasNext:()Z
      55: ifeq          102
      58: aload         5
      60: invokeinterface #31,  1           // InterfaceMethod java/util/Iterator.next:()Ljava/lang/Object;
      65: checkcast     #4                  // class java/lang/String
      68: astore        6
      70: aload_3
      71: aload_2
      72: aload         6
      74: invokeinterface #3,  2            // InterfaceMethod java/util/Map.get:(Ljava/lang/Object;)Ljava/lang/Object;
      79: invokevirtual #32                 // Method net/sf/ezmorph/bean/BeanMorpher.morph:(Ljava/lang/Object;)Ljava/lang/Object;
      82: checkcast     #25                 // class edu/internet2/middleware/grouper/grouperUi/beans/json/GuiHideShow
      85: astore        7
      87: aload         4
      89: aload         6
      91: aload         7
      93: invokeinterface #33,  3           // InterfaceMethod java/util/Map.put:(Ljava/lang/Object;Ljava/lang/Object;)Ljava/lang/Object;
      98: pop
      99: goto          48
     102: aload_0
     103: aload         4
     105: invokevirtual #34                 // Method setHideShows:(Ljava/util/Map;)V
     108: aload         4
     110: astore_2
     111: aload_2
     112: invokeinterface #28,  1           // InterfaceMethod java/util/Map.keySet:()Ljava/util/Set;
     117: invokeinterface #29,  1           // InterfaceMethod java/util/Set.iterator:()Ljava/util/Iterator;
     122: astore        5
     124: aload         5
     126: invokeinterface #30,  1           // InterfaceMethod java/util/Iterator.hasNext:()Z
     131: ifeq          193
     134: aload         5
     136: invokeinterface #31,  1           // InterfaceMethod java/util/Iterator.next:()Ljava/lang/Object;
     141: checkcast     #4                  // class java/lang/String
     144: astore        6
     146: aload_1
     147: invokevirtual #35                 // Method edu/internet2/middleware/grouper/grouperUi/beans/SessionContainer.getHideShows:()Ljava/util/Map;
     150: aload         6
     152: invokeinterface #3,  2            // InterfaceMethod java/util/Map.get:(Ljava/lang/Object;)Ljava/lang/Object;
     157: checkcast     #25                 // class edu/internet2/middleware/grouper/grouperUi/beans/json/GuiHideShow
     160: astore        7
     162: aload         7
     164: ifnull        190
     167: aload_2
     168: aload         6
     170: invokeinterface #3,  2            // InterfaceMethod java/util/Map.get:(Ljava/lang/Object;)Ljava/lang/Object;
     175: checkcast     #25                 // class edu/internet2/middleware/grouper/grouperUi/beans/json/GuiHideShow
     178: astore        8
     180: aload         7
     182: aload         8
     184: invokevirtual #36                 // Method edu/internet2/middleware/grouper/grouperUi/beans/json/GuiHideShow.isShowing:()Z
     187: invokevirtual #37                 // Method edu/internet2/middleware/grouper/grouperUi/beans/json/GuiHideShow.setShowing:(Z)V
     190: goto          124
     193: aload_0
     194: invokevirtual #38                 // Method getPagers:()Ljava/util/Map;
     197: astore_2
     198: new           #24                 // class net/sf/ezmorph/bean/BeanMorpher
     201: dup
     202: ldc           #39                 // class edu/internet2/middleware/grouper/grouperUi/beans/json/GuiPaging
     204: invokestatic  #26                 // Method net/sf/json/util/JSONUtils.getMorpherRegistry:()Lnet/sf/ezmorph/MorpherRegistry;
     207: invokespecial #27                 // Method net/sf/ezmorph/bean/BeanMorpher."<init>":(Ljava/lang/Class;Lnet/sf/ezmorph/MorpherRegistry;)V
     210: astore_3
     211: aload_2
     212: ifnull        297
     215: new           #17                 // class java/util/LinkedHashMap
     218: dup
     219: invokespecial #18                 // Method java/util/LinkedHashMap."<init>":()V
     222: astore        4
     224: aload_2
     225: invokeinterface #28,  1           // InterfaceMethod java/util/Map.keySet:()Ljava/util/Set;
     230: invokeinterface #29,  1           // InterfaceMethod java/util/Set.iterator:()Ljava/util/Iterator;
     235: astore        5
     237: aload         5
     239: invokeinterface #30,  1           // InterfaceMethod java/util/Iterator.hasNext:()Z
     244: ifeq          291
     247: aload         5
     249: invokeinterface #31,  1           // InterfaceMethod java/util/Iterator.next:()Ljava/lang/Object;
     254: checkcast     #4                  // class java/lang/String
     257: astore        6
     259: aload_3
     260: aload_2
     261: aload         6
     263: invokeinterface #3,  2            // InterfaceMethod java/util/Map.get:(Ljava/lang/Object;)Ljava/lang/Object;
     268: invokevirtual #32                 // Method net/sf/ezmorph/bean/BeanMorpher.morph:(Ljava/lang/Object;)Ljava/lang/Object;
     271: checkcast     #39                 // class edu/internet2/middleware/grouper/grouperUi/beans/json/GuiPaging
     274: astore        7
     276: aload         4
     278: aload         6
     280: aload         7
     282: invokeinterface #33,  3           // InterfaceMethod java/util/Map.put:(Ljava/lang/Object;Ljava/lang/Object;)Ljava/lang/Object;
     287: pop
     288: goto          237
     291: aload_0
     292: aload         4
     294: invokevirtual #40                 // Method setPagers:(Ljava/util/Map;)V
     297: aload_0
     298: invokevirtual #41                 // Method storeToRequest:()V
     301: return

  public java.lang.String getUrlInCache();
    Code:
       0: aload_0
       1: getfield      #42                 // Field urlInCache:Ljava/lang/String;
       4: areturn

  public void setUrlInCache(java.lang.String);
    Code:
       0: aload_0
       1: aload_1
       2: putfield      #42                 // Field urlInCache:Ljava/lang/String;
       5: return

  public java.util.Map<java.lang.String, edu.internet2.middleware.grouper.grouperUi.beans.json.GuiHideShow> getHideShows();
    Code:
       0: aload_0
       1: getfield      #19                 // Field hideShows:Ljava/util/Map;
       4: areturn

  public void setHideShows(java.util.Map<java.lang.String, edu.internet2.middleware.grouper.grouperUi.beans.json.GuiHideShow>);
    Code:
       0: aload_0
       1: aload_1
       2: putfield      #19                 // Field hideShows:Ljava/util/Map;
       5: return

  public java.util.Map<java.lang.String, edu.internet2.middleware.grouper.grouperUi.beans.json.GuiPaging> getPagers();
    Code:
       0: aload_0
       1: getfield      #20                 // Field pagers:Ljava/util/Map;
       4: areturn

  public void setPagers(java.util.Map<java.lang.String, edu.internet2.middleware.grouper.grouperUi.beans.json.GuiPaging>);
    Code:
       0: aload_0
       1: aload_1
       2: putfield      #20                 // Field pagers:Ljava/util/Map;
       5: return

  public java.util.Map<java.lang.String, java.lang.String> getUrlArgObjects();
    Code:
       0: aload_0
       1: getfield      #21                 // Field urlArgObjects:Ljava/util/Map;
       4: areturn

  public void setUrlArgObjects(java.util.Map<java.lang.String, java.lang.String>);
    Code:
       0: aload_0
       1: aload_1
       2: putfield      #21                 // Field urlArgObjects:Ljava/util/Map;
       5: return
}
