Compiled from "WebSocketPrincipalHandshakeHandler.java"
public class cn.herodotus.engine.message.websocket.interceptor.WebSocketPrincipalHandshakeHandler extends org.springframework.web.socket.server.support.DefaultHandshakeHandler {
  private static final org.slf4j.Logger log;

  public cn.herodotus.engine.message.websocket.interceptor.WebSocketPrincipalHandshakeHandler();
    Code:
       0: aload_0
       1: invokespecial #1                  // Method org/springframework/web/socket/server/support/DefaultHandshakeHandler."<init>":()V
       4: return

  protected java.security.Principal determineUser(org.springframework.http.server.ServerHttpRequest, org.springframework.web.socket.WebSocketHandler, java.util.Map<java.lang.String, java.lang.Object>);
    Code:
       0: aload_1
       1: invokestatic  #7                  // Method cn/herodotus/engine/message/websocket/utils/WebSocketUtils.getHttpServletRequest:(Lorg/springframework/http/server/ServerHttpRequest;)Ljakarta/servlet/http/HttpServletRequest;
       4: astore        4
       6: aload         4
       8: invokestatic  #13                 // Method org/apache/commons/lang3/ObjectUtils.isNotEmpty:(Ljava/lang/Object;)Z
      11: ifeq          121
      14: aload_3
      15: ldc           #21                 // String principal
      17: invokeinterface #23,  2           // InterfaceMethod java/util/Map.get:(Ljava/lang/Object;)Ljava/lang/Object;
      22: astore        5
      24: aload         5
      26: invokestatic  #13                 // Method org/apache/commons/lang3/ObjectUtils.isNotEmpty:(Ljava/lang/Object;)Z
      29: ifeq          76
      32: aload         5
      34: instanceof    #29                 // class cn/herodotus/engine/assistant/core/domain/PrincipalDetails
      37: ifeq          76
      40: aload         5
      42: checkcast     #29                 // class cn/herodotus/engine/assistant/core/domain/PrincipalDetails
      45: astore        6
      47: new           #31                 // class cn/herodotus/engine/message/websocket/domain/WebSocketPrincipal
      50: dup
      51: aload         6
      53: invokespecial #33                 // Method cn/herodotus/engine/message/websocket/domain/WebSocketPrincipal."<init>":(Lcn/herodotus/engine/assistant/core/domain/PrincipalDetails;)V
      56: astore        7
      58: getstatic     #36                 // Field log:Lorg/slf4j/Logger;
      61: ldc           #42                 // String [Herodotus] |- Determine user by request parameter, userId is  [{}].
      63: aload         7
      65: invokevirtual #44                 // Method cn/herodotus/engine/message/websocket/domain/WebSocketPrincipal.getUserId:()Ljava/lang/String;
      68: invokeinterface #48,  3           // InterfaceMethod org/slf4j/Logger.debug:(Ljava/lang/String;Ljava/lang/Object;)V
      73: aload         7
      75: areturn
      76: aload         4
      78: ldc           #54                 // String openid
      80: invokeinterface #56,  2           // InterfaceMethod jakarta/servlet/http/HttpServletRequest.getParameter:(Ljava/lang/String;)Ljava/lang/String;
      85: astore        6
      87: aload         6
      89: invokestatic  #62                 // Method org/apache/commons/lang3/StringUtils.isNotBlank:(Ljava/lang/CharSequence;)Z
      92: ifeq          121
      95: new           #31                 // class cn/herodotus/engine/message/websocket/domain/WebSocketPrincipal
      98: dup
      99: aload         6
     101: invokespecial #68                 // Method cn/herodotus/engine/message/websocket/domain/WebSocketPrincipal."<init>":(Ljava/lang/String;)V
     104: astore        7
     106: getstatic     #36                 // Field log:Lorg/slf4j/Logger;
     109: ldc           #42                 // String [Herodotus] |- Determine user by request parameter, userId is  [{}].
     111: aload         6
     113: invokeinterface #48,  3           // InterfaceMethod org/slf4j/Logger.debug:(Ljava/lang/String;Ljava/lang/Object;)V
     118: aload         7
     120: areturn
     121: aload_1
     122: invokeinterface #71,  1           // InterfaceMethod org/springframework/http/server/ServerHttpRequest.getPrincipal:()Ljava/security/Principal;
     127: astore        5
     129: aload         5
     131: invokestatic  #13                 // Method org/apache/commons/lang3/ObjectUtils.isNotEmpty:(Ljava/lang/Object;)Z
     134: ifeq          157
     137: getstatic     #36                 // Field log:Lorg/slf4j/Logger;
     140: ldc           #77                 // String [Herodotus] |- Determine user from request, value is  [{}].
     142: aload         5
     144: invokeinterface #79,  1           // InterfaceMethod java/security/Principal.getName:()Ljava/lang/String;
     149: invokeinterface #48,  3           // InterfaceMethod org/slf4j/Logger.debug:(Ljava/lang/String;Ljava/lang/Object;)V
     154: aload         5
     156: areturn
     157: getstatic     #36                 // Field log:Lorg/slf4j/Logger;
     160: ldc           #84                 // String [Herodotus] |- Can not determine user from request.
     162: invokeinterface #86,  2           // InterfaceMethod org/slf4j/Logger.warn:(Ljava/lang/String;)V
     167: aconst_null
     168: areturn

  static {};
    Code:
       0: ldc           #37                 // class cn/herodotus/engine/message/websocket/interceptor/WebSocketPrincipalHandshakeHandler
       2: invokestatic  #89                 // Method org/slf4j/LoggerFactory.getLogger:(Ljava/lang/Class;)Lorg/slf4j/Logger;
       5: putstatic     #36                 // Field log:Lorg/slf4j/Logger;
       8: return
}
