Compiled from "ObserverFactory.java"
public class org.jboss.weld.event.ObserverFactory {
  private org.jboss.weld.event.ObserverFactory();
    Code:
       0: aload_0
       1: invokespecial #1                  // Method java/lang/Object."<init>":()V
       4: return

  public static <T, X> org.jboss.weld.event.ObserverMethodImpl<T, X> create(org.jboss.weld.annotated.enhanced.EnhancedAnnotatedMethod<T, ? super X>, org.jboss.weld.bean.RIBean<X>, org.jboss.weld.manager.BeanManagerImpl);
    Code:
       0: aconst_null
       1: astore_3
       2: aload_1
       3: instanceof    #2                  // class org/jboss/weld/bean/builtin/ExtensionBean
       6: ifeq          23
       9: new           #3                  // class org/jboss/weld/event/ExtensionObserverMethodImpl
      12: dup
      13: aload_0
      14: aload_1
      15: aload_2
      16: invokespecial #4                  // Method org/jboss/weld/event/ExtensionObserverMethodImpl."<init>":(Lorg/jboss/weld/annotated/enhanced/EnhancedAnnotatedMethod;Lorg/jboss/weld/bean/RIBean;Lorg/jboss/weld/manager/BeanManagerImpl;)V
      19: astore_3
      20: goto          34
      23: new           #5                  // class org/jboss/weld/event/ObserverMethodImpl
      26: dup
      27: aload_0
      28: aload_1
      29: aload_2
      30: invokespecial #6                  // Method org/jboss/weld/event/ObserverMethodImpl."<init>":(Lorg/jboss/weld/annotated/enhanced/EnhancedAnnotatedMethod;Lorg/jboss/weld/bean/RIBean;Lorg/jboss/weld/manager/BeanManagerImpl;)V
      33: astore_3
      34: aload_3
      35: areturn

  public static javax.enterprise.event.TransactionPhase getTransactionalPhase(org.jboss.weld.annotated.enhanced.EnhancedAnnotatedMethod<?, ?>);
    Code:
       0: aload_0
       1: ldc           #7                  // class javax/enterprise/event/Observes
       3: invokeinterface #8,  2            // InterfaceMethod org/jboss/weld/annotated/enhanced/EnhancedAnnotatedMethod.getEnhancedParameters:(Ljava/lang/Class;)Ljava/util/List;
       8: invokeinterface #9,  1            // InterfaceMethod java/util/List.iterator:()Ljava/util/Iterator;
      13: invokeinterface #10,  1           // InterfaceMethod java/util/Iterator.next:()Ljava/lang/Object;
      18: checkcast     #11                 // class org/jboss/weld/annotated/enhanced/EnhancedAnnotatedParameter
      21: astore_1
      22: aload_1
      23: ldc           #7                  // class javax/enterprise/event/Observes
      25: invokeinterface #12,  2           // InterfaceMethod org/jboss/weld/annotated/enhanced/EnhancedAnnotatedParameter.getAnnotation:(Ljava/lang/Class;)Ljava/lang/annotation/Annotation;
      30: checkcast     #7                  // class javax/enterprise/event/Observes
      33: invokeinterface #13,  1           // InterfaceMethod javax/enterprise/event/Observes.during:()Ljavax/enterprise/event/TransactionPhase;
      38: areturn
}
