Compiled from "JstlFmtTLV.java"
public class org.apache.taglibs.standard.tlv.JstlFmtTLV extends org.apache.taglibs.standard.tlv.JstlBaseTLV {
  private final java.lang.String SETLOCALE;

  private final java.lang.String SETBUNDLE;

  private final java.lang.String SETTIMEZONE;

  private final java.lang.String BUNDLE;

  private final java.lang.String MESSAGE;

  private final java.lang.String MESSAGE_PARAM;

  private final java.lang.String FORMAT_NUMBER;

  private final java.lang.String PARSE_NUMBER;

  private final java.lang.String PARSE_DATE;

  private final java.lang.String JSP_TEXT;

  private final java.lang.String EVAL;

  private final java.lang.String MESSAGE_KEY;

  private final java.lang.String BUNDLE_PREFIX;

  private final java.lang.String VALUE;

  public org.apache.taglibs.standard.tlv.JstlFmtTLV();
    Code:
       0: aload_0
       1: invokespecial #1                  // Method org/apache/taglibs/standard/tlv/JstlBaseTLV."<init>":()V
       4: aload_0
       5: ldc           #2                  // String setLocale
       7: putfield      #3                  // Field SETLOCALE:Ljava/lang/String;
      10: aload_0
      11: ldc           #4                  // String setBundle
      13: putfield      #5                  // Field SETBUNDLE:Ljava/lang/String;
      16: aload_0
      17: ldc           #6                  // String setTimeZone
      19: putfield      #7                  // Field SETTIMEZONE:Ljava/lang/String;
      22: aload_0
      23: ldc           #8                  // String bundle
      25: putfield      #9                  // Field BUNDLE:Ljava/lang/String;
      28: aload_0
      29: ldc           #10                 // String message
      31: putfield      #11                 // Field MESSAGE:Ljava/lang/String;
      34: aload_0
      35: ldc           #12                 // String param
      37: putfield      #13                 // Field MESSAGE_PARAM:Ljava/lang/String;
      40: aload_0
      41: ldc           #14                 // String formatNumber
      43: putfield      #15                 // Field FORMAT_NUMBER:Ljava/lang/String;
      46: aload_0
      47: ldc           #16                 // String parseNumber
      49: putfield      #17                 // Field PARSE_NUMBER:Ljava/lang/String;
      52: aload_0
      53: ldc           #18                 // String parseDate
      55: putfield      #19                 // Field PARSE_DATE:Ljava/lang/String;
      58: aload_0
      59: ldc           #20                 // String jsp:text
      61: putfield      #21                 // Field JSP_TEXT:Ljava/lang/String;
      64: aload_0
      65: ldc           #22                 // String evaluator
      67: putfield      #23                 // Field EVAL:Ljava/lang/String;
      70: aload_0
      71: ldc           #24                 // String key
      73: putfield      #25                 // Field MESSAGE_KEY:Ljava/lang/String;
      76: aload_0
      77: ldc           #26                 // String prefix
      79: putfield      #27                 // Field BUNDLE_PREFIX:Ljava/lang/String;
      82: aload_0
      83: ldc           #28                 // String value
      85: putfield      #29                 // Field VALUE:Ljava/lang/String;
      88: return

  public javax.servlet.jsp.tagext.ValidationMessage[] validate(java.lang.String, java.lang.String, javax.servlet.jsp.tagext.PageData);
    Code:
       0: aload_0
       1: iconst_2
       2: aload_1
       3: aload_2
       4: aload_3
       5: invokespecial #30                 // Method org/apache/taglibs/standard/tlv/JstlBaseTLV.validate:(ILjava/lang/String;Ljava/lang/String;Ljavax/servlet/jsp/tagext/PageData;)[Ljavax/servlet/jsp/tagext/ValidationMessage;
       8: areturn

  protected org.xml.sax.helpers.DefaultHandler getHandler();
    Code:
       0: new           #31                 // class org/apache/taglibs/standard/tlv/JstlFmtTLV$Handler
       3: dup
       4: aload_0
       5: aconst_null
       6: invokespecial #32                 // Method org/apache/taglibs/standard/tlv/JstlFmtTLV$Handler."<init>":(Lorg/apache/taglibs/standard/tlv/JstlFmtTLV;Lorg/apache/taglibs/standard/tlv/JstlFmtTLV$1;)V
       9: areturn
}
