Compiled from "EcrEndpointParams.java"
public final class software.amazon.awssdk.services.ecr.endpoints.EcrEndpointParams implements software.amazon.awssdk.utils.builder.ToCopyableBuilder<software.amazon.awssdk.services.ecr.endpoints.EcrEndpointParams$Builder, software.amazon.awssdk.services.ecr.endpoints.EcrEndpointParams> {
  private final software.amazon.awssdk.regions.Region region;

  private final java.lang.Boolean useDualStack;

  private final java.lang.Boolean useFIPS;

  private final java.lang.String endpoint;

  private software.amazon.awssdk.services.ecr.endpoints.EcrEndpointParams(software.amazon.awssdk.services.ecr.endpoints.EcrEndpointParams$BuilderImpl);
    Code:
       0: aload_0
       1: invokespecial #6                  // Method java/lang/Object."<init>":()V
       4: aload_0
       5: aload_1
       6: invokestatic  #7                  // Method software/amazon/awssdk/services/ecr/endpoints/EcrEndpointParams$BuilderImpl.access$000:(Lsoftware/amazon/awssdk/services/ecr/endpoints/EcrEndpointParams$BuilderImpl;)Lsoftware/amazon/awssdk/regions/Region;
       9: putfield      #5                  // Field region:Lsoftware/amazon/awssdk/regions/Region;
      12: aload_0
      13: aload_1
      14: invokestatic  #8                  // Method software/amazon/awssdk/services/ecr/endpoints/EcrEndpointParams$BuilderImpl.access$100:(Lsoftware/amazon/awssdk/services/ecr/endpoints/EcrEndpointParams$BuilderImpl;)Ljava/lang/Boolean;
      17: putfield      #4                  // Field useDualStack:Ljava/lang/Boolean;
      20: aload_0
      21: aload_1
      22: invokestatic  #9                  // Method software/amazon/awssdk/services/ecr/endpoints/EcrEndpointParams$BuilderImpl.access$200:(Lsoftware/amazon/awssdk/services/ecr/endpoints/EcrEndpointParams$BuilderImpl;)Ljava/lang/Boolean;
      25: putfield      #3                  // Field useFIPS:Ljava/lang/Boolean;
      28: aload_0
      29: aload_1
      30: invokestatic  #10                 // Method software/amazon/awssdk/services/ecr/endpoints/EcrEndpointParams$BuilderImpl.access$300:(Lsoftware/amazon/awssdk/services/ecr/endpoints/EcrEndpointParams$BuilderImpl;)Ljava/lang/String;
      33: putfield      #2                  // Field endpoint:Ljava/lang/String;
      36: return

  public static software.amazon.awssdk.services.ecr.endpoints.EcrEndpointParams$Builder builder();
    Code:
       0: new           #11                 // class software/amazon/awssdk/services/ecr/endpoints/EcrEndpointParams$BuilderImpl
       3: dup
       4: aconst_null
       5: invokespecial #12                 // Method software/amazon/awssdk/services/ecr/endpoints/EcrEndpointParams$BuilderImpl."<init>":(Lsoftware/amazon/awssdk/services/ecr/endpoints/EcrEndpointParams$1;)V
       8: areturn

  public software.amazon.awssdk.regions.Region region();
    Code:
       0: aload_0
       1: getfield      #5                  // Field region:Lsoftware/amazon/awssdk/regions/Region;
       4: areturn

  public java.lang.Boolean useDualStack();
    Code:
       0: aload_0
       1: getfield      #4                  // Field useDualStack:Ljava/lang/Boolean;
       4: areturn

  public java.lang.Boolean useFips();
    Code:
       0: aload_0
       1: getfield      #3                  // Field useFIPS:Ljava/lang/Boolean;
       4: areturn

  public java.lang.String endpoint();
    Code:
       0: aload_0
       1: getfield      #2                  // Field endpoint:Ljava/lang/String;
       4: areturn

  public software.amazon.awssdk.services.ecr.endpoints.EcrEndpointParams$Builder toBuilder();
    Code:
       0: new           #11                 // class software/amazon/awssdk/services/ecr/endpoints/EcrEndpointParams$BuilderImpl
       3: dup
       4: aload_0
       5: aconst_null
       6: invokespecial #13                 // Method software/amazon/awssdk/services/ecr/endpoints/EcrEndpointParams$BuilderImpl."<init>":(Lsoftware/amazon/awssdk/services/ecr/endpoints/EcrEndpointParams;Lsoftware/amazon/awssdk/services/ecr/endpoints/EcrEndpointParams$1;)V
       9: areturn

  public software.amazon.awssdk.utils.builder.CopyableBuilder toBuilder();
    Code:
       0: aload_0
       1: invokevirtual #14                 // Method toBuilder:()Lsoftware/amazon/awssdk/services/ecr/endpoints/EcrEndpointParams$Builder;
       4: areturn

  static software.amazon.awssdk.regions.Region access$600(software.amazon.awssdk.services.ecr.endpoints.EcrEndpointParams);
    Code:
       0: aload_0
       1: getfield      #5                  // Field region:Lsoftware/amazon/awssdk/regions/Region;
       4: areturn

  static java.lang.Boolean access$700(software.amazon.awssdk.services.ecr.endpoints.EcrEndpointParams);
    Code:
       0: aload_0
       1: getfield      #4                  // Field useDualStack:Ljava/lang/Boolean;
       4: areturn

  static java.lang.Boolean access$800(software.amazon.awssdk.services.ecr.endpoints.EcrEndpointParams);
    Code:
       0: aload_0
       1: getfield      #3                  // Field useFIPS:Ljava/lang/Boolean;
       4: areturn

  static java.lang.String access$900(software.amazon.awssdk.services.ecr.endpoints.EcrEndpointParams);
    Code:
       0: aload_0
       1: getfield      #2                  // Field endpoint:Ljava/lang/String;
       4: areturn

  software.amazon.awssdk.services.ecr.endpoints.EcrEndpointParams(software.amazon.awssdk.services.ecr.endpoints.EcrEndpointParams$BuilderImpl, software.amazon.awssdk.services.ecr.endpoints.EcrEndpointParams$1);
    Code:
       0: aload_0
       1: aload_1
       2: invokespecial #1                  // Method "<init>":(Lsoftware/amazon/awssdk/services/ecr/endpoints/EcrEndpointParams$BuilderImpl;)V
       5: return
}
