Compiled from "BasicPhasedHandlerChain.java"
public class org.opensaml.ws.message.handler.BasicPhasedHandlerChain extends org.opensaml.ws.message.handler.BasicHandlerChain implements org.opensaml.ws.message.handler.PhasedHandlerChain {
  private final org.slf4j.Logger log;

  private java.util.List<java.lang.String> phaseOrder;

  private java.util.Map<java.lang.String, org.opensaml.ws.message.handler.HandlerChain> phaseChains;

  public org.opensaml.ws.message.handler.BasicPhasedHandlerChain();
    Code:
       0: aload_0
       1: invokespecial #1                  // Method org/opensaml/ws/message/handler/BasicHandlerChain."<init>":()V
       4: aload_0
       5: ldc_w         #2                  // class org/opensaml/ws/message/handler/BasicPhasedHandlerChain
       8: invokestatic  #3                  // Method org/slf4j/LoggerFactory.getLogger:(Ljava/lang/Class;)Lorg/slf4j/Logger;
      11: putfield      #4                  // Field log:Lorg/slf4j/Logger;
      14: aload_0
      15: new           #5                  // class org/opensaml/xml/util/LazyList
      18: dup
      19: invokespecial #6                  // Method org/opensaml/xml/util/LazyList."<init>":()V
      22: putfield      #7                  // Field phaseOrder:Ljava/util/List;
      25: aload_0
      26: new           #8                  // class org/opensaml/xml/util/LazyMap
      29: dup
      30: invokespecial #9                  // Method org/opensaml/xml/util/LazyMap."<init>":()V
      33: putfield      #10                 // Field phaseChains:Ljava/util/Map;
      36: return

  public java.util.List<org.opensaml.ws.message.handler.Handler> getHandlers();
    Code:
       0: new           #11                 // class java/util/ArrayList
       3: dup
       4: invokespecial #12                 // Method java/util/ArrayList."<init>":()V
       7: astore_1
       8: aload_0
       9: invokevirtual #13                 // Method getPhaseOrder:()Ljava/util/List;
      12: invokeinterface #14,  1           // InterfaceMethod java/util/List.iterator:()Ljava/util/Iterator;
      17: astore_2
      18: aload_2
      19: invokeinterface #15,  1           // InterfaceMethod java/util/Iterator.hasNext:()Z
      24: ifeq          125
      27: aload_2
      28: invokeinterface #16,  1           // InterfaceMethod java/util/Iterator.next:()Ljava/lang/Object;
      33: checkcast     #17                 // class java/lang/String
      36: astore_3
      37: aload_0
      38: invokevirtual #18                 // Method getPhaseChains:()Ljava/util/Map;
      41: aload_3
      42: invokeinterface #19,  2           // InterfaceMethod java/util/Map.get:(Ljava/lang/Object;)Ljava/lang/Object;
      47: checkcast     #20                 // class org/opensaml/ws/message/handler/HandlerChain
      50: astore        4
      52: aload         4
      54: ifnull        101
      57: aload         4
      59: invokeinterface #21,  1           // InterfaceMethod org/opensaml/ws/message/handler/HandlerChain.getHandlers:()Ljava/util/List;
      64: astore        5
      66: aload         5
      68: invokeinterface #22,  1           // InterfaceMethod java/util/List.isEmpty:()Z
      73: ifne          86
      76: aload_1
      77: aload         5
      79: invokevirtual #23                 // Method java/util/ArrayList.addAll:(Ljava/util/Collection;)Z
      82: pop
      83: goto          98
      86: aload_0
      87: getfield      #4                  // Field log:Lorg/slf4j/Logger;
      90: ldc           #24                 // String Specified phase name \'{}\' exists in PhasedHandlerChain, but contains no handlers
      92: aload_3
      93: invokeinterface #25,  3           // InterfaceMethod org/slf4j/Logger.info:(Ljava/lang/String;Ljava/lang/Object;)V
      98: goto          122
     101: aload_0
     102: getfield      #4                  // Field log:Lorg/slf4j/Logger;
     105: ldc           #26                 // String Specified phase name \'{}\' does not exist in PhasedHandlerChain: {}
     107: aload_3
     108: aload_0
     109: invokevirtual #18                 // Method getPhaseChains:()Ljava/util/Map;
     112: invokeinterface #27,  1           // InterfaceMethod java/util/Map.keySet:()Ljava/util/Set;
     117: invokeinterface #28,  4           // InterfaceMethod org/slf4j/Logger.warn:(Ljava/lang/String;Ljava/lang/Object;Ljava/lang/Object;)V
     122: goto          18
     125: aload_1
     126: invokestatic  #29                 // Method java/util/Collections.unmodifiableList:(Ljava/util/List;)Ljava/util/List;
     129: areturn

  public java.util.Map<java.lang.String, org.opensaml.ws.message.handler.HandlerChain> getPhaseChains();
    Code:
       0: aload_0
       1: getfield      #10                 // Field phaseChains:Ljava/util/Map;
       4: areturn

  public java.util.List<java.lang.String> getPhaseOrder();
    Code:
       0: aload_0
       1: getfield      #7                  // Field phaseOrder:Ljava/util/List;
       4: areturn

  public void setPhaseOrder(java.util.List<java.lang.String>);
    Code:
       0: aload_0
       1: aload_1
       2: putfield      #7                  // Field phaseOrder:Ljava/util/List;
       5: return
}
