Compiled from "AsyncAppenderBase.java"
public class ch.qos.logback.core.AsyncAppenderBase<E> extends ch.qos.logback.core.UnsynchronizedAppenderBase<E> implements ch.qos.logback.core.spi.AppenderAttachable<E> {
  ch.qos.logback.core.spi.AppenderAttachableImpl<E> aai;

  java.util.concurrent.BlockingQueue<E> blockingQueue;

  public static final int DEFAULT_QUEUE_SIZE;

  int queueSize;

  int appenderCount;

  static final int UNDEFINED;

  int discardingThreshold;

  boolean neverBlock;

  ch.qos.logback.core.AsyncAppenderBase<E>.Worker worker;

  public static final int DEFAULT_MAX_FLUSH_TIME;

  int maxFlushTime;

  public ch.qos.logback.core.AsyncAppenderBase();
    Code:
       0: aload_0
       1: invokespecial #1                  // Method ch/qos/logback/core/UnsynchronizedAppenderBase."<init>":()V
       4: aload_0
       5: new           #2                  // class ch/qos/logback/core/spi/AppenderAttachableImpl
       8: dup
       9: invokespecial #3                  // Method ch/qos/logback/core/spi/AppenderAttachableImpl."<init>":()V
      12: putfield      #4                  // Field aai:Lch/qos/logback/core/spi/AppenderAttachableImpl;
      15: aload_0
      16: sipush        256
      19: putfield      #5                  // Field queueSize:I
      22: aload_0
      23: iconst_0
      24: putfield      #6                  // Field appenderCount:I
      27: aload_0
      28: iconst_m1
      29: putfield      #7                  // Field discardingThreshold:I
      32: aload_0
      33: iconst_0
      34: putfield      #8                  // Field neverBlock:Z
      37: aload_0
      38: new           #9                  // class ch/qos/logback/core/AsyncAppenderBase$Worker
      41: dup
      42: aload_0
      43: invokespecial #10                 // Method ch/qos/logback/core/AsyncAppenderBase$Worker."<init>":(Lch/qos/logback/core/AsyncAppenderBase;)V
      46: putfield      #11                 // Field worker:Lch/qos/logback/core/AsyncAppenderBase$Worker;
      49: aload_0
      50: sipush        1000
      53: putfield      #12                 // Field maxFlushTime:I
      56: return

  protected boolean isDiscardable(E);
    Code:
       0: iconst_0
       1: ireturn

  protected void preprocess(E);
    Code:
       0: return

  public void start();
    Code:
       0: aload_0
       1: invokevirtual #13                 // Method isStarted:()Z
       4: ifeq          8
       7: return
       8: aload_0
       9: getfield      #6                  // Field appenderCount:I
      12: ifne          22
      15: aload_0
      16: ldc           #14                 // String No attached appenders found.
      18: invokevirtual #15                 // Method addError:(Ljava/lang/String;)V
      21: return
      22: aload_0
      23: getfield      #5                  // Field queueSize:I
      26: iconst_1
      27: if_icmpge     62
      30: aload_0
      31: new           #16                 // class java/lang/StringBuilder
      34: dup
      35: invokespecial #17                 // Method java/lang/StringBuilder."<init>":()V
      38: ldc           #18                 // String Invalid queue size [
      40: invokevirtual #19                 // Method java/lang/StringBuilder.append:(Ljava/lang/String;)Ljava/lang/StringBuilder;
      43: aload_0
      44: getfield      #5                  // Field queueSize:I
      47: invokevirtual #20                 // Method java/lang/StringBuilder.append:(I)Ljava/lang/StringBuilder;
      50: ldc           #21                 // String ]
      52: invokevirtual #19                 // Method java/lang/StringBuilder.append:(Ljava/lang/String;)Ljava/lang/StringBuilder;
      55: invokevirtual #22                 // Method java/lang/StringBuilder.toString:()Ljava/lang/String;
      58: invokevirtual #15                 // Method addError:(Ljava/lang/String;)V
      61: return
      62: aload_0
      63: new           #23                 // class java/util/concurrent/ArrayBlockingQueue
      66: dup
      67: aload_0
      68: getfield      #5                  // Field queueSize:I
      71: invokespecial #24                 // Method java/util/concurrent/ArrayBlockingQueue."<init>":(I)V
      74: putfield      #25                 // Field blockingQueue:Ljava/util/concurrent/BlockingQueue;
      77: aload_0
      78: getfield      #7                  // Field discardingThreshold:I
      81: iconst_m1
      82: if_icmpne     95
      85: aload_0
      86: aload_0
      87: getfield      #5                  // Field queueSize:I
      90: iconst_5
      91: idiv
      92: putfield      #7                  // Field discardingThreshold:I
      95: aload_0
      96: new           #16                 // class java/lang/StringBuilder
      99: dup
     100: invokespecial #17                 // Method java/lang/StringBuilder."<init>":()V
     103: ldc           #26                 // String Setting discardingThreshold to
     105: invokevirtual #19                 // Method java/lang/StringBuilder.append:(Ljava/lang/String;)Ljava/lang/StringBuilder;
     108: aload_0
     109: getfield      #7                  // Field discardingThreshold:I
     112: invokevirtual #20                 // Method java/lang/StringBuilder.append:(I)Ljava/lang/StringBuilder;
     115: invokevirtual #22                 // Method java/lang/StringBuilder.toString:()Ljava/lang/String;
     118: invokevirtual #27                 // Method addInfo:(Ljava/lang/String;)V
     121: aload_0
     122: getfield      #11                 // Field worker:Lch/qos/logback/core/AsyncAppenderBase$Worker;
     125: iconst_1
     126: invokevirtual #28                 // Method ch/qos/logback/core/AsyncAppenderBase$Worker.setDaemon:(Z)V
     129: aload_0
     130: getfield      #11                 // Field worker:Lch/qos/logback/core/AsyncAppenderBase$Worker;
     133: new           #16                 // class java/lang/StringBuilder
     136: dup
     137: invokespecial #17                 // Method java/lang/StringBuilder."<init>":()V
     140: ldc           #29                 // String AsyncAppender-Worker-
     142: invokevirtual #19                 // Method java/lang/StringBuilder.append:(Ljava/lang/String;)Ljava/lang/StringBuilder;
     145: aload_0
     146: invokevirtual #30                 // Method getName:()Ljava/lang/String;
     149: invokevirtual #19                 // Method java/lang/StringBuilder.append:(Ljava/lang/String;)Ljava/lang/StringBuilder;
     152: invokevirtual #22                 // Method java/lang/StringBuilder.toString:()Ljava/lang/String;
     155: invokevirtual #31                 // Method ch/qos/logback/core/AsyncAppenderBase$Worker.setName:(Ljava/lang/String;)V
     158: aload_0
     159: invokespecial #32                 // Method ch/qos/logback/core/UnsynchronizedAppenderBase.start:()V
     162: aload_0
     163: getfield      #11                 // Field worker:Lch/qos/logback/core/AsyncAppenderBase$Worker;
     166: invokevirtual #33                 // Method ch/qos/logback/core/AsyncAppenderBase$Worker.start:()V
     169: return

  public void stop();
    Code:
       0: aload_0
       1: invokevirtual #13                 // Method isStarted:()Z
       4: ifne          8
       7: return
       8: aload_0
       9: invokespecial #34                 // Method ch/qos/logback/core/UnsynchronizedAppenderBase.stop:()V
      12: aload_0
      13: getfield      #11                 // Field worker:Lch/qos/logback/core/AsyncAppenderBase$Worker;
      16: invokevirtual #35                 // Method ch/qos/logback/core/AsyncAppenderBase$Worker.interrupt:()V
      19: new           #36                 // class ch/qos/logback/core/util/InterruptUtil
      22: dup
      23: aload_0
      24: getfield      #37                 // Field context:Lch/qos/logback/core/Context;
      27: invokespecial #38                 // Method ch/qos/logback/core/util/InterruptUtil."<init>":(Lch/qos/logback/core/Context;)V
      30: astore_1
      31: aload_1
      32: invokevirtual #39                 // Method ch/qos/logback/core/util/InterruptUtil.maskInterruptFlag:()V
      35: aload_0
      36: getfield      #11                 // Field worker:Lch/qos/logback/core/AsyncAppenderBase$Worker;
      39: aload_0
      40: getfield      #12                 // Field maxFlushTime:I
      43: i2l
      44: invokevirtual #40                 // Method ch/qos/logback/core/AsyncAppenderBase$Worker.join:(J)V
      47: aload_0
      48: getfield      #11                 // Field worker:Lch/qos/logback/core/AsyncAppenderBase$Worker;
      51: invokevirtual #41                 // Method ch/qos/logback/core/AsyncAppenderBase$Worker.isAlive:()Z
      54: ifeq          108
      57: aload_0
      58: new           #16                 // class java/lang/StringBuilder
      61: dup
      62: invokespecial #17                 // Method java/lang/StringBuilder."<init>":()V
      65: ldc           #42                 // String Max queue flush timeout (
      67: invokevirtual #19                 // Method java/lang/StringBuilder.append:(Ljava/lang/String;)Ljava/lang/StringBuilder;
      70: aload_0
      71: getfield      #12                 // Field maxFlushTime:I
      74: invokevirtual #20                 // Method java/lang/StringBuilder.append:(I)Ljava/lang/StringBuilder;
      77: ldc           #43                 // String  ms) exceeded. Approximately
      79: invokevirtual #19                 // Method java/lang/StringBuilder.append:(Ljava/lang/String;)Ljava/lang/StringBuilder;
      82: aload_0
      83: getfield      #25                 // Field blockingQueue:Ljava/util/concurrent/BlockingQueue;
      86: invokeinterface #44,  1           // InterfaceMethod java/util/concurrent/BlockingQueue.size:()I
      91: invokevirtual #20                 // Method java/lang/StringBuilder.append:(I)Ljava/lang/StringBuilder;
      94: ldc           #45                 // String  queued events were possibly discarded.
      96: invokevirtual #19                 // Method java/lang/StringBuilder.append:(Ljava/lang/String;)Ljava/lang/StringBuilder;
      99: invokevirtual #22                 // Method java/lang/StringBuilder.toString:()Ljava/lang/String;
     102: invokevirtual #46                 // Method addWarn:(Ljava/lang/String;)V
     105: goto          114
     108: aload_0
     109: ldc           #47                 // String Queue flush finished successfully within timeout.
     111: invokevirtual #27                 // Method addInfo:(Ljava/lang/String;)V
     114: aload_1
     115: invokevirtual #48                 // Method ch/qos/logback/core/util/InterruptUtil.unmaskInterruptFlag:()V
     118: goto          177
     121: astore_2
     122: aload_0
     123: getfield      #25                 // Field blockingQueue:Ljava/util/concurrent/BlockingQueue;
     126: invokeinterface #44,  1           // InterfaceMethod java/util/concurrent/BlockingQueue.size:()I
     131: istore_3
     132: aload_0
     133: new           #16                 // class java/lang/StringBuilder
     136: dup
     137: invokespecial #17                 // Method java/lang/StringBuilder."<init>":()V
     140: ldc           #50                 // String Failed to join worker thread.
     142: invokevirtual #19                 // Method java/lang/StringBuilder.append:(Ljava/lang/String;)Ljava/lang/StringBuilder;
     145: iload_3
     146: invokevirtual #20                 // Method java/lang/StringBuilder.append:(I)Ljava/lang/StringBuilder;
     149: ldc           #51                 // String  queued events may be discarded.
     151: invokevirtual #19                 // Method java/lang/StringBuilder.append:(Ljava/lang/String;)Ljava/lang/StringBuilder;
     154: invokevirtual #22                 // Method java/lang/StringBuilder.toString:()Ljava/lang/String;
     157: aload_2
     158: invokevirtual #52                 // Method addError:(Ljava/lang/String;Ljava/lang/Throwable;)V
     161: aload_1
     162: invokevirtual #48                 // Method ch/qos/logback/core/util/InterruptUtil.unmaskInterruptFlag:()V
     165: goto          177
     168: astore        4
     170: aload_1
     171: invokevirtual #48                 // Method ch/qos/logback/core/util/InterruptUtil.unmaskInterruptFlag:()V
     174: aload         4
     176: athrow
     177: return
    Exception table:
       from    to  target type
          31   114   121   Class java/lang/InterruptedException
          31   114   168   any
         121   161   168   any
         168   170   168   any

  protected void append(E);
    Code:
       0: aload_0
       1: invokespecial #53                 // Method isQueueBelowDiscardingThreshold:()Z
       4: ifeq          16
       7: aload_0
       8: aload_1
       9: invokevirtual #54                 // Method isDiscardable:(Ljava/lang/Object;)Z
      12: ifeq          16
      15: return
      16: aload_0
      17: aload_1
      18: invokevirtual #55                 // Method preprocess:(Ljava/lang/Object;)V
      21: aload_0
      22: aload_1
      23: invokespecial #56                 // Method put:(Ljava/lang/Object;)V
      26: return

  private boolean isQueueBelowDiscardingThreshold();
    Code:
       0: aload_0
       1: getfield      #25                 // Field blockingQueue:Ljava/util/concurrent/BlockingQueue;
       4: invokeinterface #57,  1           // InterfaceMethod java/util/concurrent/BlockingQueue.remainingCapacity:()I
       9: aload_0
      10: getfield      #7                  // Field discardingThreshold:I
      13: if_icmpge     20
      16: iconst_1
      17: goto          21
      20: iconst_0
      21: ireturn

  private void put(E);
    Code:
       0: aload_0
       1: getfield      #8                  // Field neverBlock:Z
       4: ifeq          21
       7: aload_0
       8: getfield      #25                 // Field blockingQueue:Ljava/util/concurrent/BlockingQueue;
      11: aload_1
      12: invokeinterface #58,  2           // InterfaceMethod java/util/concurrent/BlockingQueue.offer:(Ljava/lang/Object;)Z
      17: pop
      18: goto          26
      21: aload_0
      22: aload_1
      23: invokespecial #59                 // Method putUninterruptibly:(Ljava/lang/Object;)V
      26: return

  private void putUninterruptibly(E);
    Code:
       0: iconst_0
       1: istore_2
       2: aload_0
       3: getfield      #25                 // Field blockingQueue:Ljava/util/concurrent/BlockingQueue;
       6: aload_1
       7: invokeinterface #60,  2           // InterfaceMethod java/util/concurrent/BlockingQueue.put:(Ljava/lang/Object;)V
      12: goto          21
      15: astore_3
      16: iconst_1
      17: istore_2
      18: goto          2
      21: iload_2
      22: ifeq          49
      25: invokestatic  #61                 // Method java/lang/Thread.currentThread:()Ljava/lang/Thread;
      28: invokevirtual #62                 // Method java/lang/Thread.interrupt:()V
      31: goto          49
      34: astore        4
      36: iload_2
      37: ifeq          46
      40: invokestatic  #61                 // Method java/lang/Thread.currentThread:()Ljava/lang/Thread;
      43: invokevirtual #62                 // Method java/lang/Thread.interrupt:()V
      46: aload         4
      48: athrow
      49: return
    Exception table:
       from    to  target type
           2    12    15   Class java/lang/InterruptedException
           2    21    34   any
          34    36    34   any

  public int getQueueSize();
    Code:
       0: aload_0
       1: getfield      #5                  // Field queueSize:I
       4: ireturn

  public void setQueueSize(int);
    Code:
       0: aload_0
       1: iload_1
       2: putfield      #5                  // Field queueSize:I
       5: return

  public int getDiscardingThreshold();
    Code:
       0: aload_0
       1: getfield      #7                  // Field discardingThreshold:I
       4: ireturn

  public void setDiscardingThreshold(int);
    Code:
       0: aload_0
       1: iload_1
       2: putfield      #7                  // Field discardingThreshold:I
       5: return

  public int getMaxFlushTime();
    Code:
       0: aload_0
       1: getfield      #12                 // Field maxFlushTime:I
       4: ireturn

  public void setMaxFlushTime(int);
    Code:
       0: aload_0
       1: iload_1
       2: putfield      #12                 // Field maxFlushTime:I
       5: return

  public int getNumberOfElementsInQueue();
    Code:
       0: aload_0
       1: getfield      #25                 // Field blockingQueue:Ljava/util/concurrent/BlockingQueue;
       4: invokeinterface #44,  1           // InterfaceMethod java/util/concurrent/BlockingQueue.size:()I
       9: ireturn

  public void setNeverBlock(boolean);
    Code:
       0: aload_0
       1: iload_1
       2: putfield      #8                  // Field neverBlock:Z
       5: return

  public boolean isNeverBlock();
    Code:
       0: aload_0
       1: getfield      #8                  // Field neverBlock:Z
       4: ireturn

  public int getRemainingCapacity();
    Code:
       0: aload_0
       1: getfield      #25                 // Field blockingQueue:Ljava/util/concurrent/BlockingQueue;
       4: invokeinterface #57,  1           // InterfaceMethod java/util/concurrent/BlockingQueue.remainingCapacity:()I
       9: ireturn

  public void addAppender(ch.qos.logback.core.Appender<E>);
    Code:
       0: aload_0
       1: getfield      #6                  // Field appenderCount:I
       4: ifne          61
       7: aload_0
       8: dup
       9: getfield      #6                  // Field appenderCount:I
      12: iconst_1
      13: iadd
      14: putfield      #6                  // Field appenderCount:I
      17: aload_0
      18: new           #16                 // class java/lang/StringBuilder
      21: dup
      22: invokespecial #17                 // Method java/lang/StringBuilder."<init>":()V
      25: ldc           #63                 // String Attaching appender named [
      27: invokevirtual #19                 // Method java/lang/StringBuilder.append:(Ljava/lang/String;)Ljava/lang/StringBuilder;
      30: aload_1
      31: invokeinterface #64,  1           // InterfaceMethod ch/qos/logback/core/Appender.getName:()Ljava/lang/String;
      36: invokevirtual #19                 // Method java/lang/StringBuilder.append:(Ljava/lang/String;)Ljava/lang/StringBuilder;
      39: ldc           #65                 // String ] to AsyncAppender.
      41: invokevirtual #19                 // Method java/lang/StringBuilder.append:(Ljava/lang/String;)Ljava/lang/StringBuilder;
      44: invokevirtual #22                 // Method java/lang/StringBuilder.toString:()Ljava/lang/String;
      47: invokevirtual #27                 // Method addInfo:(Ljava/lang/String;)V
      50: aload_0
      51: getfield      #4                  // Field aai:Lch/qos/logback/core/spi/AppenderAttachableImpl;
      54: aload_1
      55: invokevirtual #66                 // Method ch/qos/logback/core/spi/AppenderAttachableImpl.addAppender:(Lch/qos/logback/core/Appender;)V
      58: goto          100
      61: aload_0
      62: ldc           #67                 // String One and only one appender may be attached to AsyncAppender.
      64: invokevirtual #46                 // Method addWarn:(Ljava/lang/String;)V
      67: aload_0
      68: new           #16                 // class java/lang/StringBuilder
      71: dup
      72: invokespecial #17                 // Method java/lang/StringBuilder."<init>":()V
      75: ldc           #68                 // String Ignoring additional appender named [
      77: invokevirtual #19                 // Method java/lang/StringBuilder.append:(Ljava/lang/String;)Ljava/lang/StringBuilder;
      80: aload_1
      81: invokeinterface #64,  1           // InterfaceMethod ch/qos/logback/core/Appender.getName:()Ljava/lang/String;
      86: invokevirtual #19                 // Method java/lang/StringBuilder.append:(Ljava/lang/String;)Ljava/lang/StringBuilder;
      89: ldc           #21                 // String ]
      91: invokevirtual #19                 // Method java/lang/StringBuilder.append:(Ljava/lang/String;)Ljava/lang/StringBuilder;
      94: invokevirtual #22                 // Method java/lang/StringBuilder.toString:()Ljava/lang/String;
      97: invokevirtual #46                 // Method addWarn:(Ljava/lang/String;)V
     100: return

  public java.util.Iterator<ch.qos.logback.core.Appender<E>> iteratorForAppenders();
    Code:
       0: aload_0
       1: getfield      #4                  // Field aai:Lch/qos/logback/core/spi/AppenderAttachableImpl;
       4: invokevirtual #69                 // Method ch/qos/logback/core/spi/AppenderAttachableImpl.iteratorForAppenders:()Ljava/util/Iterator;
       7: areturn

  public ch.qos.logback.core.Appender<E> getAppender(java.lang.String);
    Code:
       0: aload_0
       1: getfield      #4                  // Field aai:Lch/qos/logback/core/spi/AppenderAttachableImpl;
       4: aload_1
       5: invokevirtual #70                 // Method ch/qos/logback/core/spi/AppenderAttachableImpl.getAppender:(Ljava/lang/String;)Lch/qos/logback/core/Appender;
       8: areturn

  public boolean isAttached(ch.qos.logback.core.Appender<E>);
    Code:
       0: aload_0
       1: getfield      #4                  // Field aai:Lch/qos/logback/core/spi/AppenderAttachableImpl;
       4: aload_1
       5: invokevirtual #71                 // Method ch/qos/logback/core/spi/AppenderAttachableImpl.isAttached:(Lch/qos/logback/core/Appender;)Z
       8: ireturn

  public void detachAndStopAllAppenders();
    Code:
       0: aload_0
       1: getfield      #4                  // Field aai:Lch/qos/logback/core/spi/AppenderAttachableImpl;
       4: invokevirtual #72                 // Method ch/qos/logback/core/spi/AppenderAttachableImpl.detachAndStopAllAppenders:()V
       7: return

  public boolean detachAppender(ch.qos.logback.core.Appender<E>);
    Code:
       0: aload_0
       1: getfield      #4                  // Field aai:Lch/qos/logback/core/spi/AppenderAttachableImpl;
       4: aload_1
       5: invokevirtual #73                 // Method ch/qos/logback/core/spi/AppenderAttachableImpl.detachAppender:(Lch/qos/logback/core/Appender;)Z
       8: ireturn

  public boolean detachAppender(java.lang.String);
    Code:
       0: aload_0
       1: getfield      #4                  // Field aai:Lch/qos/logback/core/spi/AppenderAttachableImpl;
       4: aload_1
       5: invokevirtual #74                 // Method ch/qos/logback/core/spi/AppenderAttachableImpl.detachAppender:(Ljava/lang/String;)Z
       8: ireturn
}
