Compiled from "ReplCacheDemo.java"
class org.jgroups.demos.ReplCacheDemo$MyTableModel<K, V> extends javax.swing.table.AbstractTableModel implements org.jgroups.blocks.ReplCache$ChangeListener {
  private java.util.concurrent.ConcurrentMap<K, org.jgroups.blocks.Cache$Value<org.jgroups.blocks.ReplCache$Value<V>>> map;

  private final java.lang.String[] columnNames;

  private static final long serialVersionUID;

  final org.jgroups.demos.ReplCacheDemo this$0;

  private org.jgroups.demos.ReplCacheDemo$MyTableModel(org.jgroups.demos.ReplCacheDemo);
    Code:
       0: aload_0
       1: aload_1
       2: putfield      #2                  // Field this$0:Lorg/jgroups/demos/ReplCacheDemo;
       5: aload_0
       6: invokespecial #3                  // Method javax/swing/table/AbstractTableModel."<init>":()V
       9: aload_0
      10: iconst_4
      11: anewarray     #4                  // class java/lang/String
      14: dup
      15: iconst_0
      16: ldc           #5                  // String Key
      18: aastore
      19: dup
      20: iconst_1
      21: ldc           #6                  // String Value
      23: aastore
      24: dup
      25: iconst_2
      26: ldc           #7                  // String Replication Count
      28: aastore
      29: dup
      30: iconst_3
      31: ldc           #8                  // String Timeout
      33: aastore
      34: putfield      #9                  // Field columnNames:[Ljava/lang/String;
      37: return

  public void setMap(java.util.concurrent.ConcurrentMap<K, org.jgroups.blocks.Cache$Value<org.jgroups.blocks.ReplCache$Value<V>>>);
    Code:
       0: aload_0
       1: aload_1
       2: putfield      #10                 // Field map:Ljava/util/concurrent/ConcurrentMap;
       5: return

  public int getColumnCount();
    Code:
       0: aload_0
       1: getfield      #9                  // Field columnNames:[Ljava/lang/String;
       4: arraylength
       5: ireturn

  public int getRowCount();
    Code:
       0: aload_0
       1: getfield      #10                 // Field map:Ljava/util/concurrent/ConcurrentMap;
       4: invokeinterface #11,  1           // InterfaceMethod java/util/concurrent/ConcurrentMap.size:()I
       9: ireturn

  public java.lang.String getColumnName(int);
    Code:
       0: aload_0
       1: getfield      #9                  // Field columnNames:[Ljava/lang/String;
       4: iload_1
       5: aaload
       6: areturn

  public java.lang.Object getValueAt(int, int);
    Code:
       0: iconst_0
       1: istore_3
       2: aload_0
       3: getfield      #10                 // Field map:Ljava/util/concurrent/ConcurrentMap;
       6: invokeinterface #12,  1           // InterfaceMethod java/util/concurrent/ConcurrentMap.entrySet:()Ljava/util/Set;
      11: invokeinterface #13,  1           // InterfaceMethod java/util/Set.iterator:()Ljava/util/Iterator;
      16: astore        4
      18: aload         4
      20: invokeinterface #14,  1           // InterfaceMethod java/util/Iterator.hasNext:()Z
      25: ifeq          187
      28: aload         4
      30: invokeinterface #15,  1           // InterfaceMethod java/util/Iterator.next:()Ljava/lang/Object;
      35: checkcast     #16                 // class java/util/Map$Entry
      38: astore        5
      40: iload_3
      41: iinc          3, 1
      44: iload_1
      45: if_icmplt     184
      48: aload         5
      50: invokeinterface #17,  1           // InterfaceMethod java/util/Map$Entry.getKey:()Ljava/lang/Object;
      55: astore        6
      57: aload         5
      59: invokeinterface #18,  1           // InterfaceMethod java/util/Map$Entry.getValue:()Ljava/lang/Object;
      64: checkcast     #19                 // class org/jgroups/blocks/Cache$Value
      67: astore        7
      69: aload         7
      71: invokevirtual #20                 // Method org/jgroups/blocks/Cache$Value.getValue:()Ljava/lang/Object;
      74: checkcast     #21                 // class org/jgroups/blocks/ReplCache$Value
      77: astore        8
      79: iload_2
      80: tableswitch   { // 0 to 3
                     0: 112
                     1: 115
                     2: 163
                     3: 172
               default: 181
          }
     112: aload         6
     114: areturn
     115: aload         8
     117: invokevirtual #22                 // Method org/jgroups/blocks/ReplCache$Value.getVal:()Ljava/lang/Object;
     120: astore        9
     122: aload         9
     124: instanceof    #23                 // class "[B"
     127: ifeq          160
     130: new           #24                 // class java/lang/StringBuilder
     133: dup
     134: invokespecial #25                 // Method java/lang/StringBuilder."<init>":()V
     137: aload         9
     139: checkcast     #23                 // class "[B"
     142: checkcast     #23                 // class "[B"
     145: arraylength
     146: invokevirtual #26                 // Method java/lang/StringBuilder.append:(I)Ljava/lang/StringBuilder;
     149: ldc           #27                 // String  bytes
     151: invokevirtual #28                 // Method java/lang/StringBuilder.append:(Ljava/lang/String;)Ljava/lang/StringBuilder;
     154: invokevirtual #29                 // Method java/lang/StringBuilder.toString:()Ljava/lang/String;
     157: goto          162
     160: aload         9
     162: areturn
     163: aload         8
     165: invokevirtual #30                 // Method org/jgroups/blocks/ReplCache$Value.getReplicationCount:()S
     168: invokestatic  #31                 // Method java/lang/Short.valueOf:(S)Ljava/lang/Short;
     171: areturn
     172: aload         7
     174: invokevirtual #32                 // Method org/jgroups/blocks/Cache$Value.getTimeout:()J
     177: invokestatic  #33                 // Method java/lang/Long.valueOf:(J)Ljava/lang/Long;
     180: areturn
     181: ldc           #34                 // String n/a
     183: areturn
     184: goto          18
     187: new           #35                 // class java/lang/IllegalArgumentException
     190: dup
     191: new           #24                 // class java/lang/StringBuilder
     194: dup
     195: invokespecial #25                 // Method java/lang/StringBuilder."<init>":()V
     198: ldc           #36                 // String row=
     200: invokevirtual #28                 // Method java/lang/StringBuilder.append:(Ljava/lang/String;)Ljava/lang/StringBuilder;
     203: iload_1
     204: invokevirtual #26                 // Method java/lang/StringBuilder.append:(I)Ljava/lang/StringBuilder;
     207: ldc           #37                 // String , col=
     209: invokevirtual #28                 // Method java/lang/StringBuilder.append:(Ljava/lang/String;)Ljava/lang/StringBuilder;
     212: iload_2
     213: invokevirtual #26                 // Method java/lang/StringBuilder.append:(I)Ljava/lang/StringBuilder;
     216: invokevirtual #29                 // Method java/lang/StringBuilder.toString:()Ljava/lang/String;
     219: invokespecial #38                 // Method java/lang/IllegalArgumentException."<init>":(Ljava/lang/String;)V
     222: athrow

  public void changed();
    Code:
       0: aload_0
       1: invokevirtual #39                 // Method fireTableDataChanged:()V
       4: aload_0
       5: getfield      #2                  // Field this$0:Lorg/jgroups/demos/ReplCacheDemo;
       8: invokestatic  #40                 // Method org/jgroups/demos/ReplCacheDemo.access$300:(Lorg/jgroups/demos/ReplCacheDemo;)Ljavax/swing/JLabel;
      11: new           #24                 // class java/lang/StringBuilder
      14: dup
      15: invokespecial #25                 // Method java/lang/StringBuilder."<init>":()V
      18: aload_0
      19: getfield      #2                  // Field this$0:Lorg/jgroups/demos/ReplCacheDemo;
      22: invokestatic  #41                 // Method org/jgroups/demos/ReplCacheDemo.access$000:(Lorg/jgroups/demos/ReplCacheDemo;)Lorg/jgroups/blocks/ReplCache;
      25: invokevirtual #42                 // Method org/jgroups/blocks/ReplCache.getL2Cache:()Lorg/jgroups/blocks/Cache;
      28: invokevirtual #43                 // Method org/jgroups/blocks/Cache.getSize:()I
      31: invokevirtual #26                 // Method java/lang/StringBuilder.append:(I)Ljava/lang/StringBuilder;
      34: ldc           #44                 // String  elements
      36: invokevirtual #28                 // Method java/lang/StringBuilder.append:(Ljava/lang/String;)Ljava/lang/StringBuilder;
      39: invokevirtual #29                 // Method java/lang/StringBuilder.toString:()Ljava/lang/String;
      42: invokevirtual #45                 // Method javax/swing/JLabel.setText:(Ljava/lang/String;)V
      45: return

  org.jgroups.demos.ReplCacheDemo$MyTableModel(org.jgroups.demos.ReplCacheDemo, org.jgroups.demos.ReplCacheDemo$1);
    Code:
       0: aload_0
       1: aload_1
       2: invokespecial #1                  // Method "<init>":(Lorg/jgroups/demos/ReplCacheDemo;)V
       5: return
}
