Compiled from "TotalOrder.java"
class org.jgroups.demos.TotalOrder$6 extends org.jgroups.ReceiverAdapter {
  final org.jgroups.demos.TotalOrder this$0;

  org.jgroups.demos.TotalOrder$6(org.jgroups.demos.TotalOrder);
    Code:
       0: aload_0
       1: aload_1
       2: putfield      #1                  // Field this$0:Lorg/jgroups/demos/TotalOrder;
       5: aload_0
       6: invokespecial #2                  // Method org/jgroups/ReceiverAdapter."<init>":()V
       9: return

  public void receive(org.jgroups.Message);
    Code:
       0: new           #3                  // class org/jgroups/demos/TotOrderRequest
       3: dup
       4: invokespecial #4                  // Method org/jgroups/demos/TotOrderRequest."<init>":()V
       7: astore_2
       8: aload_1
       9: invokevirtual #5                  // Method org/jgroups/Message.getRawBuffer:()[B
      12: aload_1
      13: invokevirtual #6                  // Method org/jgroups/Message.getOffset:()I
      16: aload_1
      17: invokevirtual #7                  // Method org/jgroups/Message.getLength:()I
      20: invokestatic  #8                  // Method java/nio/ByteBuffer.wrap:([BII)Ljava/nio/ByteBuffer;
      23: astore_3
      24: aload_2
      25: aload_3
      26: invokevirtual #9                  // Method org/jgroups/demos/TotOrderRequest.init:(Ljava/nio/ByteBuffer;)V
      29: aload_0
      30: getfield      #1                  // Field this$0:Lorg/jgroups/demos/TotalOrder;
      33: aload_2
      34: invokevirtual #10                 // Method org/jgroups/demos/TotalOrder.processRequest:(Lorg/jgroups/demos/TotOrderRequest;)V
      37: goto          48
      40: astore_2
      41: getstatic     #12                 // Field java/lang/System.err:Ljava/io/PrintStream;
      44: aload_2
      45: invokevirtual #13                 // Method java/io/PrintStream.println:(Ljava/lang/Object;)V
      48: return
    Exception table:
       from    to  target type
           0    37    40   Class java/lang/Exception

  public void getState(java.io.OutputStream) throws java.lang.Exception;
    Code:
       0: aload_0
       1: getfield      #1                  // Field this$0:Lorg/jgroups/demos/TotalOrder;
       4: getfield      #14                 // Field org/jgroups/demos/TotalOrder.canvas:Lorg/jgroups/demos/MyCanvas;
       7: invokevirtual #15                 // Method org/jgroups/demos/MyCanvas.getCopyOfState:()[[I
      10: astore_2
      11: aload_2
      12: new           #16                 // class java/io/DataOutputStream
      15: dup
      16: aload_1
      17: invokespecial #17                 // Method java/io/DataOutputStream."<init>":(Ljava/io/OutputStream;)V
      20: invokestatic  #18                 // Method org/jgroups/util/Util.objectToStream:(Ljava/lang/Object;Ljava/io/DataOutput;)V
      23: return

  public void setState(java.io.InputStream) throws java.lang.Exception;
    Code:
       0: aload_0
       1: getfield      #1                  // Field this$0:Lorg/jgroups/demos/TotalOrder;
       4: getfield      #14                 // Field org/jgroups/demos/TotalOrder.canvas:Lorg/jgroups/demos/MyCanvas;
       7: new           #19                 // class java/io/DataInputStream
      10: dup
      11: aload_1
      12: invokespecial #20                 // Method java/io/DataInputStream."<init>":(Ljava/io/InputStream;)V
      15: invokestatic  #21                 // Method org/jgroups/util/Util.objectFromStream:(Ljava/io/DataInput;)Ljava/lang/Object;
      18: invokevirtual #22                 // Method org/jgroups/demos/MyCanvas.setState:(Ljava/lang/Object;)V
      21: return

  public void viewAccepted(org.jgroups.View);
    Code:
       0: getstatic     #23                 // Field java/lang/System.out:Ljava/io/PrintStream;
       3: new           #24                 // class java/lang/StringBuilder
       6: dup
       7: invokespecial #25                 // Method java/lang/StringBuilder."<init>":()V
      10: ldc           #26                 // String view =
      12: invokevirtual #27                 // Method java/lang/StringBuilder.append:(Ljava/lang/String;)Ljava/lang/StringBuilder;
      15: aload_1
      16: invokevirtual #28                 // Method java/lang/StringBuilder.append:(Ljava/lang/Object;)Ljava/lang/StringBuilder;
      19: invokevirtual #29                 // Method java/lang/StringBuilder.toString:()Ljava/lang/String;
      22: invokevirtual #30                 // Method java/io/PrintStream.println:(Ljava/lang/String;)V
      25: return
}
