Compiled from "TotalOrder.java"
class org.jgroups.demos.TotalOrder$5 implements java.awt.event.ActionListener {
  final org.jgroups.demos.TotalOrder this$0;

  org.jgroups.demos.TotalOrder$5(org.jgroups.demos.TotalOrder);
    Code:
       0: aload_0
       1: aload_1
       2: putfield      #1                  // Field this$0:Lorg/jgroups/demos/TotalOrder;
       5: aload_0
       6: invokespecial #2                  // Method java/lang/Object."<init>":()V
       9: return

  public void actionPerformed(java.awt.event.ActionEvent);
    Code:
       0: aload_0
       1: getfield      #1                  // Field this$0:Lorg/jgroups/demos/TotalOrder;
       4: getfield      #3                  // Field org/jgroups/demos/TotalOrder.channel:Lorg/jgroups/Channel;
       7: invokevirtual #4                  // Method org/jgroups/Channel.disconnect:()V
      10: aload_0
      11: getfield      #1                  // Field this$0:Lorg/jgroups/demos/TotalOrder;
      14: getfield      #3                  // Field org/jgroups/demos/TotalOrder.channel:Lorg/jgroups/Channel;
      17: invokevirtual #5                  // Method org/jgroups/Channel.close:()V
      20: iconst_0
      21: invokestatic  #6                  // Method java/lang/System.exit:(I)V
      24: return
}
