Compiled from "Integration.kt"
final class org.jetbrains.kotlinx.ggdsl.letsplot.Integration$onLoaded$1 extends kotlin.jvm.internal.Lambda implements kotlin.jvm.functions.Function1<org.jetbrains.kotlinx.jupyter.api.KotlinKernelHost, kotlin.Unit> {
  final org.jetbrains.kotlinx.ggdsl.letsplot.Integration this$0;

  org.jetbrains.kotlinx.ggdsl.letsplot.Integration$onLoaded$1(org.jetbrains.kotlinx.ggdsl.letsplot.Integration);
    Code:
       0: aload_0
       1: aload_1
       2: putfield      #13                 // Field this$0:Lorg/jetbrains/kotlinx/ggdsl/letsplot/Integration;
       5: aload_0
       6: iconst_1
       7: invokespecial #16                 // Method kotlin/jvm/internal/Lambda."<init>":(I)V
      10: return

  public final void invoke(org.jetbrains.kotlinx.jupyter.api.KotlinKernelHost);
    Code:
       0: aload_1
       1: ldc           #24                 // String $this$onLoaded
       3: invokestatic  #30                 // Method kotlin/jvm/internal/Intrinsics.checkNotNullParameter:(Ljava/lang/Object;Ljava/lang/String;)V
       6: aload_0
       7: getfield      #13                 // Field this$0:Lorg/jetbrains/kotlinx/ggdsl/letsplot/Integration;
      10: getstatic     #36                 // Field org/jetbrains/letsPlot/LetsPlot.INSTANCE:Lorg/jetbrains/letsPlot/LetsPlot;
      13: ldc           #38                 // String 2.4.0
      15: iconst_1
      16: invokestatic  #44                 // Method java/lang/Boolean.valueOf:(Z)Ljava/lang/Boolean;
      19: new           #46                 // class org/jetbrains/kotlinx/ggdsl/letsplot/Integration$onLoaded$1$1
      22: dup
      23: aload_1
      24: invokespecial #48                 // Method org/jetbrains/kotlinx/ggdsl/letsplot/Integration$onLoaded$1$1."<init>":(Lorg/jetbrains/kotlinx/jupyter/api/KotlinKernelHost;)V
      27: checkcast     #7                  // class kotlin/jvm/functions/Function1
      30: invokevirtual #52                 // Method org/jetbrains/letsPlot/LetsPlot.setupNotebook:(Ljava/lang/String;Ljava/lang/Boolean;Lkotlin/jvm/functions/Function1;)Lorg/jetbrains/letsPlot/frontend/NotebookFrontendContext;
      33: invokevirtual #58                 // Method org/jetbrains/kotlinx/ggdsl/letsplot/Integration.setFrontendContext:(Lorg/jetbrains/letsPlot/frontend/NotebookFrontendContext;)V
      36: getstatic     #36                 // Field org/jetbrains/letsPlot/LetsPlot.INSTANCE:Lorg/jetbrains/letsPlot/LetsPlot;
      39: ldc           #60                 // String 4.0.0
      41: invokevirtual #64                 // Method org/jetbrains/letsPlot/LetsPlot.setApiVersion:(Ljava/lang/String;)V
      44: aload_1
      45: aload_0
      46: getfield      #13                 // Field this$0:Lorg/jetbrains/kotlinx/ggdsl/letsplot/Integration;
      49: invokevirtual #68                 // Method org/jetbrains/kotlinx/ggdsl/letsplot/Integration.getFrontendContext:()Lorg/jetbrains/letsPlot/frontend/NotebookFrontendContext;
      52: invokevirtual #74                 // Method org/jetbrains/letsPlot/frontend/NotebookFrontendContext.getConfigureHtml:()Ljava/lang/String;
      55: iconst_0
      56: iconst_2
      57: aconst_null
      58: invokestatic  #80                 // Method org/jetbrains/kotlinx/jupyter/api/ResultsKt.HTML$default:(Ljava/lang/String;ZILjava/lang/Object;)Lorg/jetbrains/kotlinx/jupyter/api/MimeTypedResult;
      61: invokeinterface #86,  2           // InterfaceMethod org/jetbrains/kotlinx/jupyter/api/KotlinKernelHost.display:(Ljava/lang/Object;)V
      66: return

  public java.lang.Object invoke(java.lang.Object);
    Code:
       0: aload_0
       1: aload_1
       2: checkcast     #82                 // class org/jetbrains/kotlinx/jupyter/api/KotlinKernelHost
       5: invokevirtual #90                 // Method invoke:(Lorg/jetbrains/kotlinx/jupyter/api/KotlinKernelHost;)V
       8: getstatic     #95                 // Field kotlin/Unit.INSTANCE:Lkotlin/Unit;
      11: areturn
}
