Compiled from "MapTypeAdapterFactory.java"
final class org.sonarsource.sonarlint.shaded.com.google.gson.internal.bind.MapTypeAdapterFactory$Adapter<K, V> extends org.sonarsource.sonarlint.shaded.com.google.gson.TypeAdapter<java.util.Map<K, V>> {
  private final org.sonarsource.sonarlint.shaded.com.google.gson.TypeAdapter<K> keyTypeAdapter;

  private final org.sonarsource.sonarlint.shaded.com.google.gson.TypeAdapter<V> valueTypeAdapter;

  private final org.sonarsource.sonarlint.shaded.com.google.gson.internal.ObjectConstructor<? extends java.util.Map<K, V>> constructor;

  final org.sonarsource.sonarlint.shaded.com.google.gson.internal.bind.MapTypeAdapterFactory this$0;

  public org.sonarsource.sonarlint.shaded.com.google.gson.internal.bind.MapTypeAdapterFactory$Adapter(org.sonarsource.sonarlint.shaded.com.google.gson.Gson, java.lang.reflect.Type, org.sonarsource.sonarlint.shaded.com.google.gson.TypeAdapter<K>, java.lang.reflect.Type, org.sonarsource.sonarlint.shaded.com.google.gson.TypeAdapter<V>, org.sonarsource.sonarlint.shaded.com.google.gson.internal.ObjectConstructor<? extends java.util.Map<K, V>>);
    Code:
       0: aload_0
       1: aload_1
       2: putfield      #29                 // Field this$0:Lorg/sonarsource/sonarlint/shaded/com/google/gson/internal/bind/MapTypeAdapterFactory;
       5: aload_0
       6: invokespecial #32                 // Method org/sonarsource/sonarlint/shaded/com/google/gson/TypeAdapter."<init>":()V
       9: aload_0
      10: new           #34                 // class org/sonarsource/sonarlint/shaded/com/google/gson/internal/bind/TypeAdapterRuntimeTypeWrapper
      13: dup
      14: aload_2
      15: aload         4
      17: aload_3
      18: invokespecial #37                 // Method org/sonarsource/sonarlint/shaded/com/google/gson/internal/bind/TypeAdapterRuntimeTypeWrapper."<init>":(Lorg/sonarsource/sonarlint/shaded/com/google/gson/Gson;Lorg/sonarsource/sonarlint/shaded/com/google/gson/TypeAdapter;Ljava/lang/reflect/Type;)V
      21: putfield      #39                 // Field keyTypeAdapter:Lorg/sonarsource/sonarlint/shaded/com/google/gson/TypeAdapter;
      24: aload_0
      25: new           #34                 // class org/sonarsource/sonarlint/shaded/com/google/gson/internal/bind/TypeAdapterRuntimeTypeWrapper
      28: dup
      29: aload_2
      30: aload         6
      32: aload         5
      34: invokespecial #37                 // Method org/sonarsource/sonarlint/shaded/com/google/gson/internal/bind/TypeAdapterRuntimeTypeWrapper."<init>":(Lorg/sonarsource/sonarlint/shaded/com/google/gson/Gson;Lorg/sonarsource/sonarlint/shaded/com/google/gson/TypeAdapter;Ljava/lang/reflect/Type;)V
      37: putfield      #41                 // Field valueTypeAdapter:Lorg/sonarsource/sonarlint/shaded/com/google/gson/TypeAdapter;
      40: aload_0
      41: aload         7
      43: putfield      #43                 // Field constructor:Lorg/sonarsource/sonarlint/shaded/com/google/gson/internal/ObjectConstructor;
      46: return

  public java.util.Map<K, V> read(org.sonarsource.sonarlint.shaded.com.google.gson.stream.JsonReader) throws java.io.IOException;
    Code:
       0: aload_1
       1: invokevirtual #62                 // Method org/sonarsource/sonarlint/shaded/com/google/gson/stream/JsonReader.peek:()Lorg/sonarsource/sonarlint/shaded/com/google/gson/stream/JsonToken;
       4: astore_2
       5: aload_2
       6: getstatic     #68                 // Field org/sonarsource/sonarlint/shaded/com/google/gson/stream/JsonToken.NULL:Lorg/sonarsource/sonarlint/shaded/com/google/gson/stream/JsonToken;
       9: if_acmpne     18
      12: aload_1
      13: invokevirtual #71                 // Method org/sonarsource/sonarlint/shaded/com/google/gson/stream/JsonReader.nextNull:()V
      16: aconst_null
      17: areturn
      18: aload_0
      19: getfield      #43                 // Field constructor:Lorg/sonarsource/sonarlint/shaded/com/google/gson/internal/ObjectConstructor;
      22: invokeinterface #77,  1           // InterfaceMethod org/sonarsource/sonarlint/shaded/com/google/gson/internal/ObjectConstructor.construct:()Ljava/lang/Object;
      27: checkcast     #13                 // class java/util/Map
      30: astore_3
      31: aload_2
      32: getstatic     #80                 // Field org/sonarsource/sonarlint/shaded/com/google/gson/stream/JsonToken.BEGIN_ARRAY:Lorg/sonarsource/sonarlint/shaded/com/google/gson/stream/JsonToken;
      35: if_acmpne     132
      38: aload_1
      39: invokevirtual #83                 // Method org/sonarsource/sonarlint/shaded/com/google/gson/stream/JsonReader.beginArray:()V
      42: aload_1
      43: invokevirtual #87                 // Method org/sonarsource/sonarlint/shaded/com/google/gson/stream/JsonReader.hasNext:()Z
      46: ifeq          125
      49: aload_1
      50: invokevirtual #83                 // Method org/sonarsource/sonarlint/shaded/com/google/gson/stream/JsonReader.beginArray:()V
      53: aload_0
      54: getfield      #39                 // Field keyTypeAdapter:Lorg/sonarsource/sonarlint/shaded/com/google/gson/TypeAdapter;
      57: aload_1
      58: invokevirtual #90                 // Method org/sonarsource/sonarlint/shaded/com/google/gson/TypeAdapter.read:(Lorg/sonarsource/sonarlint/shaded/com/google/gson/stream/JsonReader;)Ljava/lang/Object;
      61: astore        4
      63: aload_0
      64: getfield      #41                 // Field valueTypeAdapter:Lorg/sonarsource/sonarlint/shaded/com/google/gson/TypeAdapter;
      67: aload_1
      68: invokevirtual #90                 // Method org/sonarsource/sonarlint/shaded/com/google/gson/TypeAdapter.read:(Lorg/sonarsource/sonarlint/shaded/com/google/gson/stream/JsonReader;)Ljava/lang/Object;
      71: astore        5
      73: aload_3
      74: aload         4
      76: aload         5
      78: invokeinterface #94,  3           // InterfaceMethod java/util/Map.put:(Ljava/lang/Object;Ljava/lang/Object;)Ljava/lang/Object;
      83: astore        6
      85: aload         6
      87: ifnull        118
      90: new           #96                 // class org/sonarsource/sonarlint/shaded/com/google/gson/JsonSyntaxException
      93: dup
      94: new           #98                 // class java/lang/StringBuilder
      97: dup
      98: invokespecial #99                 // Method java/lang/StringBuilder."<init>":()V
     101: ldc           #101                // String duplicate key:
     103: invokevirtual #105                // Method java/lang/StringBuilder.append:(Ljava/lang/String;)Ljava/lang/StringBuilder;
     106: aload         4
     108: invokevirtual #108                // Method java/lang/StringBuilder.append:(Ljava/lang/Object;)Ljava/lang/StringBuilder;
     111: invokevirtual #112                // Method java/lang/StringBuilder.toString:()Ljava/lang/String;
     114: invokespecial #115                // Method org/sonarsource/sonarlint/shaded/com/google/gson/JsonSyntaxException."<init>":(Ljava/lang/String;)V
     117: athrow
     118: aload_1
     119: invokevirtual #120                // Method org/sonarsource/sonarlint/shaded/com/google/gson/stream/JsonReader.endArray:()V
     122: goto          42
     125: aload_1
     126: invokevirtual #120                // Method org/sonarsource/sonarlint/shaded/com/google/gson/stream/JsonReader.endArray:()V
     129: goto          222
     132: aload_1
     133: invokevirtual #123                // Method org/sonarsource/sonarlint/shaded/com/google/gson/stream/JsonReader.beginObject:()V
     136: aload_1
     137: invokevirtual #87                 // Method org/sonarsource/sonarlint/shaded/com/google/gson/stream/JsonReader.hasNext:()Z
     140: ifeq          218
     143: getstatic     #129                // Field org/sonarsource/sonarlint/shaded/com/google/gson/internal/JsonReaderInternalAccess.INSTANCE:Lorg/sonarsource/sonarlint/shaded/com/google/gson/internal/JsonReaderInternalAccess;
     146: aload_1
     147: invokevirtual #133                // Method org/sonarsource/sonarlint/shaded/com/google/gson/internal/JsonReaderInternalAccess.promoteNameToValue:(Lorg/sonarsource/sonarlint/shaded/com/google/gson/stream/JsonReader;)V
     150: aload_0
     151: getfield      #39                 // Field keyTypeAdapter:Lorg/sonarsource/sonarlint/shaded/com/google/gson/TypeAdapter;
     154: aload_1
     155: invokevirtual #90                 // Method org/sonarsource/sonarlint/shaded/com/google/gson/TypeAdapter.read:(Lorg/sonarsource/sonarlint/shaded/com/google/gson/stream/JsonReader;)Ljava/lang/Object;
     158: astore        4
     160: aload_0
     161: getfield      #41                 // Field valueTypeAdapter:Lorg/sonarsource/sonarlint/shaded/com/google/gson/TypeAdapter;
     164: aload_1
     165: invokevirtual #90                 // Method org/sonarsource/sonarlint/shaded/com/google/gson/TypeAdapter.read:(Lorg/sonarsource/sonarlint/shaded/com/google/gson/stream/JsonReader;)Ljava/lang/Object;
     168: astore        5
     170: aload_3
     171: aload         4
     173: aload         5
     175: invokeinterface #94,  3           // InterfaceMethod java/util/Map.put:(Ljava/lang/Object;Ljava/lang/Object;)Ljava/lang/Object;
     180: astore        6
     182: aload         6
     184: ifnull        215
     187: new           #96                 // class org/sonarsource/sonarlint/shaded/com/google/gson/JsonSyntaxException
     190: dup
     191: new           #98                 // class java/lang/StringBuilder
     194: dup
     195: invokespecial #99                 // Method java/lang/StringBuilder."<init>":()V
     198: ldc           #101                // String duplicate key:
     200: invokevirtual #105                // Method java/lang/StringBuilder.append:(Ljava/lang/String;)Ljava/lang/StringBuilder;
     203: aload         4
     205: invokevirtual #108                // Method java/lang/StringBuilder.append:(Ljava/lang/Object;)Ljava/lang/StringBuilder;
     208: invokevirtual #112                // Method java/lang/StringBuilder.toString:()Ljava/lang/String;
     211: invokespecial #115                // Method org/sonarsource/sonarlint/shaded/com/google/gson/JsonSyntaxException."<init>":(Ljava/lang/String;)V
     214: athrow
     215: goto          136
     218: aload_1
     219: invokevirtual #136                // Method org/sonarsource/sonarlint/shaded/com/google/gson/stream/JsonReader.endObject:()V
     222: aload_3
     223: areturn

  public void write(org.sonarsource.sonarlint.shaded.com.google.gson.stream.JsonWriter, java.util.Map<K, V>) throws java.io.IOException;
    Code:
       0: aload_2
       1: ifnonnull     10
       4: aload_1
       5: invokevirtual #156                // Method org/sonarsource/sonarlint/shaded/com/google/gson/stream/JsonWriter.nullValue:()Lorg/sonarsource/sonarlint/shaded/com/google/gson/stream/JsonWriter;
       8: pop
       9: return
      10: aload_0
      11: getfield      #29                 // Field this$0:Lorg/sonarsource/sonarlint/shaded/com/google/gson/internal/bind/MapTypeAdapterFactory;
      14: getfield      #160                // Field org/sonarsource/sonarlint/shaded/com/google/gson/internal/bind/MapTypeAdapterFactory.complexMapKeySerialization:Z
      17: ifne          96
      20: aload_1
      21: invokevirtual #162                // Method org/sonarsource/sonarlint/shaded/com/google/gson/stream/JsonWriter.beginObject:()Lorg/sonarsource/sonarlint/shaded/com/google/gson/stream/JsonWriter;
      24: pop
      25: aload_2
      26: invokeinterface #166,  1          // InterfaceMethod java/util/Map.entrySet:()Ljava/util/Set;
      31: invokeinterface #172,  1          // InterfaceMethod java/util/Set.iterator:()Ljava/util/Iterator;
      36: astore_3
      37: aload_3
      38: invokeinterface #175,  1          // InterfaceMethod java/util/Iterator.hasNext:()Z
      43: ifeq          90
      46: aload_3
      47: invokeinterface #178,  1          // InterfaceMethod java/util/Iterator.next:()Ljava/lang/Object;
      52: checkcast     #11                 // class java/util/Map$Entry
      55: astore        4
      57: aload_1
      58: aload         4
      60: invokeinterface #181,  1          // InterfaceMethod java/util/Map$Entry.getKey:()Ljava/lang/Object;
      65: invokestatic  #187                // Method java/lang/String.valueOf:(Ljava/lang/Object;)Ljava/lang/String;
      68: invokevirtual #191                // Method org/sonarsource/sonarlint/shaded/com/google/gson/stream/JsonWriter.name:(Ljava/lang/String;)Lorg/sonarsource/sonarlint/shaded/com/google/gson/stream/JsonWriter;
      71: pop
      72: aload_0
      73: getfield      #41                 // Field valueTypeAdapter:Lorg/sonarsource/sonarlint/shaded/com/google/gson/TypeAdapter;
      76: aload_1
      77: aload         4
      79: invokeinterface #194,  1          // InterfaceMethod java/util/Map$Entry.getValue:()Ljava/lang/Object;
      84: invokevirtual #197                // Method org/sonarsource/sonarlint/shaded/com/google/gson/TypeAdapter.write:(Lorg/sonarsource/sonarlint/shaded/com/google/gson/stream/JsonWriter;Ljava/lang/Object;)V
      87: goto          37
      90: aload_1
      91: invokevirtual #199                // Method org/sonarsource/sonarlint/shaded/com/google/gson/stream/JsonWriter.endObject:()Lorg/sonarsource/sonarlint/shaded/com/google/gson/stream/JsonWriter;
      94: pop
      95: return
      96: iconst_0
      97: istore_3
      98: new           #201                // class java/util/ArrayList
     101: dup
     102: aload_2
     103: invokeinterface #205,  1          // InterfaceMethod java/util/Map.size:()I
     108: invokespecial #208                // Method java/util/ArrayList."<init>":(I)V
     111: astore        4
     113: new           #201                // class java/util/ArrayList
     116: dup
     117: aload_2
     118: invokeinterface #205,  1          // InterfaceMethod java/util/Map.size:()I
     123: invokespecial #208                // Method java/util/ArrayList."<init>":(I)V
     126: astore        5
     128: aload_2
     129: invokeinterface #166,  1          // InterfaceMethod java/util/Map.entrySet:()Ljava/util/Set;
     134: invokeinterface #172,  1          // InterfaceMethod java/util/Set.iterator:()Ljava/util/Iterator;
     139: astore        6
     141: aload         6
     143: invokeinterface #175,  1          // InterfaceMethod java/util/Iterator.hasNext:()Z
     148: ifeq          231
     151: aload         6
     153: invokeinterface #178,  1          // InterfaceMethod java/util/Iterator.next:()Ljava/lang/Object;
     158: checkcast     #11                 // class java/util/Map$Entry
     161: astore        7
     163: aload_0
     164: getfield      #39                 // Field keyTypeAdapter:Lorg/sonarsource/sonarlint/shaded/com/google/gson/TypeAdapter;
     167: aload         7
     169: invokeinterface #181,  1          // InterfaceMethod java/util/Map$Entry.getKey:()Ljava/lang/Object;
     174: invokevirtual #214                // Method org/sonarsource/sonarlint/shaded/com/google/gson/TypeAdapter.toJsonTree:(Ljava/lang/Object;)Lorg/sonarsource/sonarlint/shaded/com/google/gson/JsonElement;
     177: astore        8
     179: aload         4
     181: aload         8
     183: invokeinterface #218,  2          // InterfaceMethod java/util/List.add:(Ljava/lang/Object;)Z
     188: pop
     189: aload         5
     191: aload         7
     193: invokeinterface #194,  1          // InterfaceMethod java/util/Map$Entry.getValue:()Ljava/lang/Object;
     198: invokeinterface #218,  2          // InterfaceMethod java/util/List.add:(Ljava/lang/Object;)Z
     203: pop
     204: iload_3
     205: aload         8
     207: invokevirtual #223                // Method org/sonarsource/sonarlint/shaded/com/google/gson/JsonElement.isJsonArray:()Z
     210: ifne          221
     213: aload         8
     215: invokevirtual #226                // Method org/sonarsource/sonarlint/shaded/com/google/gson/JsonElement.isJsonObject:()Z
     218: ifeq          225
     221: iconst_1
     222: goto          226
     225: iconst_0
     226: ior
     227: istore_3
     228: goto          141
     231: iload_3
     232: ifeq          316
     235: aload_1
     236: invokevirtual #228                // Method org/sonarsource/sonarlint/shaded/com/google/gson/stream/JsonWriter.beginArray:()Lorg/sonarsource/sonarlint/shaded/com/google/gson/stream/JsonWriter;
     239: pop
     240: iconst_0
     241: istore        6
     243: aload         4
     245: invokeinterface #229,  1          // InterfaceMethod java/util/List.size:()I
     250: istore        7
     252: iload         6
     254: iload         7
     256: if_icmpge     308
     259: aload_1
     260: invokevirtual #228                // Method org/sonarsource/sonarlint/shaded/com/google/gson/stream/JsonWriter.beginArray:()Lorg/sonarsource/sonarlint/shaded/com/google/gson/stream/JsonWriter;
     263: pop
     264: aload         4
     266: iload         6
     268: invokeinterface #233,  2          // InterfaceMethod java/util/List.get:(I)Ljava/lang/Object;
     273: checkcast     #220                // class org/sonarsource/sonarlint/shaded/com/google/gson/JsonElement
     276: aload_1
     277: invokestatic  #238                // Method org/sonarsource/sonarlint/shaded/com/google/gson/internal/Streams.write:(Lorg/sonarsource/sonarlint/shaded/com/google/gson/JsonElement;Lorg/sonarsource/sonarlint/shaded/com/google/gson/stream/JsonWriter;)V
     280: aload_0
     281: getfield      #41                 // Field valueTypeAdapter:Lorg/sonarsource/sonarlint/shaded/com/google/gson/TypeAdapter;
     284: aload_1
     285: aload         5
     287: iload         6
     289: invokeinterface #233,  2          // InterfaceMethod java/util/List.get:(I)Ljava/lang/Object;
     294: invokevirtual #197                // Method org/sonarsource/sonarlint/shaded/com/google/gson/TypeAdapter.write:(Lorg/sonarsource/sonarlint/shaded/com/google/gson/stream/JsonWriter;Ljava/lang/Object;)V
     297: aload_1
     298: invokevirtual #240                // Method org/sonarsource/sonarlint/shaded/com/google/gson/stream/JsonWriter.endArray:()Lorg/sonarsource/sonarlint/shaded/com/google/gson/stream/JsonWriter;
     301: pop
     302: iinc          6, 1
     305: goto          252
     308: aload_1
     309: invokevirtual #240                // Method org/sonarsource/sonarlint/shaded/com/google/gson/stream/JsonWriter.endArray:()Lorg/sonarsource/sonarlint/shaded/com/google/gson/stream/JsonWriter;
     312: pop
     313: goto          393
     316: aload_1
     317: invokevirtual #162                // Method org/sonarsource/sonarlint/shaded/com/google/gson/stream/JsonWriter.beginObject:()Lorg/sonarsource/sonarlint/shaded/com/google/gson/stream/JsonWriter;
     320: pop
     321: iconst_0
     322: istore        6
     324: aload         4
     326: invokeinterface #229,  1          // InterfaceMethod java/util/List.size:()I
     331: istore        7
     333: iload         6
     335: iload         7
     337: if_icmpge     388
     340: aload         4
     342: iload         6
     344: invokeinterface #233,  2          // InterfaceMethod java/util/List.get:(I)Ljava/lang/Object;
     349: checkcast     #220                // class org/sonarsource/sonarlint/shaded/com/google/gson/JsonElement
     352: astore        8
     354: aload_1
     355: aload_0
     356: aload         8
     358: invokespecial #244                // Method keyToString:(Lorg/sonarsource/sonarlint/shaded/com/google/gson/JsonElement;)Ljava/lang/String;
     361: invokevirtual #191                // Method org/sonarsource/sonarlint/shaded/com/google/gson/stream/JsonWriter.name:(Ljava/lang/String;)Lorg/sonarsource/sonarlint/shaded/com/google/gson/stream/JsonWriter;
     364: pop
     365: aload_0
     366: getfield      #41                 // Field valueTypeAdapter:Lorg/sonarsource/sonarlint/shaded/com/google/gson/TypeAdapter;
     369: aload_1
     370: aload         5
     372: iload         6
     374: invokeinterface #233,  2          // InterfaceMethod java/util/List.get:(I)Ljava/lang/Object;
     379: invokevirtual #197                // Method org/sonarsource/sonarlint/shaded/com/google/gson/TypeAdapter.write:(Lorg/sonarsource/sonarlint/shaded/com/google/gson/stream/JsonWriter;Ljava/lang/Object;)V
     382: iinc          6, 1
     385: goto          333
     388: aload_1
     389: invokevirtual #199                // Method org/sonarsource/sonarlint/shaded/com/google/gson/stream/JsonWriter.endObject:()Lorg/sonarsource/sonarlint/shaded/com/google/gson/stream/JsonWriter;
     392: pop
     393: return

  private java.lang.String keyToString(org.sonarsource.sonarlint.shaded.com.google.gson.JsonElement);
    Code:
       0: aload_1
       1: invokevirtual #262                // Method org/sonarsource/sonarlint/shaded/com/google/gson/JsonElement.isJsonPrimitive:()Z
       4: ifeq          62
       7: aload_1
       8: invokevirtual #266                // Method org/sonarsource/sonarlint/shaded/com/google/gson/JsonElement.getAsJsonPrimitive:()Lorg/sonarsource/sonarlint/shaded/com/google/gson/JsonPrimitive;
      11: astore_2
      12: aload_2
      13: invokevirtual #271                // Method org/sonarsource/sonarlint/shaded/com/google/gson/JsonPrimitive.isNumber:()Z
      16: ifeq          27
      19: aload_2
      20: invokevirtual #275                // Method org/sonarsource/sonarlint/shaded/com/google/gson/JsonPrimitive.getAsNumber:()Ljava/lang/Number;
      23: invokestatic  #187                // Method java/lang/String.valueOf:(Ljava/lang/Object;)Ljava/lang/String;
      26: areturn
      27: aload_2
      28: invokevirtual #278                // Method org/sonarsource/sonarlint/shaded/com/google/gson/JsonPrimitive.isBoolean:()Z
      31: ifeq          42
      34: aload_2
      35: invokevirtual #281                // Method org/sonarsource/sonarlint/shaded/com/google/gson/JsonPrimitive.getAsBoolean:()Z
      38: invokestatic  #286                // Method java/lang/Boolean.toString:(Z)Ljava/lang/String;
      41: areturn
      42: aload_2
      43: invokevirtual #289                // Method org/sonarsource/sonarlint/shaded/com/google/gson/JsonPrimitive.isString:()Z
      46: ifeq          54
      49: aload_2
      50: invokevirtual #292                // Method org/sonarsource/sonarlint/shaded/com/google/gson/JsonPrimitive.getAsString:()Ljava/lang/String;
      53: areturn
      54: new           #294                // class java/lang/AssertionError
      57: dup
      58: invokespecial #295                // Method java/lang/AssertionError."<init>":()V
      61: athrow
      62: aload_1
      63: invokevirtual #298                // Method org/sonarsource/sonarlint/shaded/com/google/gson/JsonElement.isJsonNull:()Z
      66: ifeq          73
      69: ldc_w         #300                // String null
      72: areturn
      73: new           #294                // class java/lang/AssertionError
      76: dup
      77: invokespecial #295                // Method java/lang/AssertionError."<init>":()V
      80: athrow

  public java.lang.Object read(org.sonarsource.sonarlint.shaded.com.google.gson.stream.JsonReader) throws java.io.IOException;
    Code:
       0: aload_0
       1: aload_1
       2: invokevirtual #304                // Method read:(Lorg/sonarsource/sonarlint/shaded/com/google/gson/stream/JsonReader;)Ljava/util/Map;
       5: areturn

  public void write(org.sonarsource.sonarlint.shaded.com.google.gson.stream.JsonWriter, java.lang.Object) throws java.io.IOException;
    Code:
       0: aload_0
       1: aload_1
       2: aload_2
       3: checkcast     #13                 // class java/util/Map
       6: invokevirtual #306                // Method write:(Lorg/sonarsource/sonarlint/shaded/com/google/gson/stream/JsonWriter;Ljava/util/Map;)V
       9: return
}
