Compiled from "SqlDateTypeAdapter.java"
class org.sonarsource.sonarlint.shaded.com.google.gson.internal.bind.SqlDateTypeAdapter$1 implements org.sonarsource.sonarlint.shaded.com.google.gson.TypeAdapterFactory {
  org.sonarsource.sonarlint.shaded.com.google.gson.internal.bind.SqlDateTypeAdapter$1();
    Code:
       0: aload_0
       1: invokespecial #13                 // Method java/lang/Object."<init>":()V
       4: return

  public <T> org.sonarsource.sonarlint.shaded.com.google.gson.TypeAdapter<T> create(org.sonarsource.sonarlint.shaded.com.google.gson.Gson, org.sonarsource.sonarlint.shaded.com.google.gson.reflect.TypeToken<T>);
    Code:
       0: aload_2
       1: invokevirtual #24                 // Method org/sonarsource/sonarlint/shaded/com/google/gson/reflect/TypeToken.getRawType:()Ljava/lang/Class;
       4: ldc           #26                 // class java/sql/Date
       6: if_acmpne     19
       9: new           #9                  // class org/sonarsource/sonarlint/shaded/com/google/gson/internal/bind/SqlDateTypeAdapter
      12: dup
      13: invokespecial #27                 // Method org/sonarsource/sonarlint/shaded/com/google/gson/internal/bind/SqlDateTypeAdapter."<init>":()V
      16: goto          20
      19: aconst_null
      20: areturn
}
