Compiled from "AnnotationProcessingOptionsImpl.java"
public class org.hibernate.validator.internal.metadata.core.AnnotationProcessingOptionsImpl implements org.hibernate.validator.internal.metadata.core.AnnotationProcessingOptions {
  private static final org.hibernate.validator.internal.util.logging.Log LOG;

  private final java.util.Map<java.lang.Class<?>, java.lang.Boolean> ignoreAnnotationDefaults;

  private final java.util.Map<java.lang.Class<?>, java.lang.Boolean> annotationIgnoresForClasses;

  private final java.util.Map<org.hibernate.validator.internal.properties.Constrainable, java.lang.Boolean> annotationIgnoredForMembers;

  private final java.util.Map<org.hibernate.validator.internal.properties.Constrainable, java.lang.Boolean> annotationIgnoresForReturnValues;

  private final java.util.Map<org.hibernate.validator.internal.properties.Constrainable, java.lang.Boolean> annotationIgnoresForCrossParameter;

  private final java.util.Map<org.hibernate.validator.internal.metadata.core.AnnotationProcessingOptionsImpl$ExecutableParameterKey, java.lang.Boolean> annotationIgnoresForMethodParameter;

  public org.hibernate.validator.internal.metadata.core.AnnotationProcessingOptionsImpl();
    Code:
       0: aload_0
       1: invokespecial #1                  // Method java/lang/Object."<init>":()V
       4: aload_0
       5: invokestatic  #7                  // Method org/hibernate/validator/internal/util/CollectionHelper.newHashMap:()Ljava/util/HashMap;
       8: putfield      #13                 // Field ignoreAnnotationDefaults:Ljava/util/Map;
      11: aload_0
      12: invokestatic  #7                  // Method org/hibernate/validator/internal/util/CollectionHelper.newHashMap:()Ljava/util/HashMap;
      15: putfield      #19                 // Field annotationIgnoresForClasses:Ljava/util/Map;
      18: aload_0
      19: invokestatic  #7                  // Method org/hibernate/validator/internal/util/CollectionHelper.newHashMap:()Ljava/util/HashMap;
      22: putfield      #22                 // Field annotationIgnoredForMembers:Ljava/util/Map;
      25: aload_0
      26: invokestatic  #7                  // Method org/hibernate/validator/internal/util/CollectionHelper.newHashMap:()Ljava/util/HashMap;
      29: putfield      #25                 // Field annotationIgnoresForReturnValues:Ljava/util/Map;
      32: aload_0
      33: invokestatic  #7                  // Method org/hibernate/validator/internal/util/CollectionHelper.newHashMap:()Ljava/util/HashMap;
      36: putfield      #28                 // Field annotationIgnoresForCrossParameter:Ljava/util/Map;
      39: aload_0
      40: invokestatic  #7                  // Method org/hibernate/validator/internal/util/CollectionHelper.newHashMap:()Ljava/util/HashMap;
      43: putfield      #31                 // Field annotationIgnoresForMethodParameter:Ljava/util/Map;
      46: return

  public boolean areMemberConstraintsIgnoredFor(org.hibernate.validator.internal.properties.Constrainable);
    Code:
       0: aload_1
       1: invokeinterface #34,  1           // InterfaceMethod org/hibernate/validator/internal/properties/Constrainable.getDeclaringClass:()Ljava/lang/Class;
       6: astore_2
       7: aload_0
       8: getfield      #22                 // Field annotationIgnoredForMembers:Ljava/util/Map;
      11: aload_1
      12: invokeinterface #40,  2           // InterfaceMethod java/util/Map.get:(Ljava/lang/Object;)Ljava/lang/Object;
      17: checkcast     #46                 // class java/lang/Boolean
      20: astore_3
      21: aload_3
      22: ifnull        30
      25: aload_3
      26: invokevirtual #48                 // Method java/lang/Boolean.booleanValue:()Z
      29: ireturn
      30: aload_0
      31: aload_2
      32: invokevirtual #52                 // Method areAllConstraintAnnotationsIgnoredFor:(Ljava/lang/Class;)Z
      35: ireturn

  public boolean areReturnValueConstraintsIgnoredFor(org.hibernate.validator.internal.properties.Constrainable);
    Code:
       0: aload_0
       1: getfield      #25                 // Field annotationIgnoresForReturnValues:Ljava/util/Map;
       4: aload_1
       5: invokeinterface #40,  2           // InterfaceMethod java/util/Map.get:(Ljava/lang/Object;)Ljava/lang/Object;
      10: checkcast     #46                 // class java/lang/Boolean
      13: astore_2
      14: aload_2
      15: ifnull        23
      18: aload_2
      19: invokevirtual #48                 // Method java/lang/Boolean.booleanValue:()Z
      22: ireturn
      23: aload_0
      24: aload_1
      25: invokevirtual #56                 // Method areMemberConstraintsIgnoredFor:(Lorg/hibernate/validator/internal/properties/Constrainable;)Z
      28: ireturn

  public boolean areCrossParameterConstraintsIgnoredFor(org.hibernate.validator.internal.properties.Constrainable);
    Code:
       0: aload_0
       1: getfield      #28                 // Field annotationIgnoresForCrossParameter:Ljava/util/Map;
       4: aload_1
       5: invokeinterface #40,  2           // InterfaceMethod java/util/Map.get:(Ljava/lang/Object;)Ljava/lang/Object;
      10: checkcast     #46                 // class java/lang/Boolean
      13: astore_2
      14: aload_2
      15: ifnull        23
      18: aload_2
      19: invokevirtual #48                 // Method java/lang/Boolean.booleanValue:()Z
      22: ireturn
      23: aload_0
      24: aload_1
      25: invokevirtual #56                 // Method areMemberConstraintsIgnoredFor:(Lorg/hibernate/validator/internal/properties/Constrainable;)Z
      28: ireturn

  public boolean areParameterConstraintsIgnoredFor(org.hibernate.validator.internal.properties.Constrainable, int);
    Code:
       0: new           #60                 // class org/hibernate/validator/internal/metadata/core/AnnotationProcessingOptionsImpl$ExecutableParameterKey
       3: dup
       4: aload_0
       5: aload_1
       6: iload_2
       7: invokespecial #62                 // Method org/hibernate/validator/internal/metadata/core/AnnotationProcessingOptionsImpl$ExecutableParameterKey."<init>":(Lorg/hibernate/validator/internal/metadata/core/AnnotationProcessingOptionsImpl;Lorg/hibernate/validator/internal/properties/Constrainable;I)V
      10: astore_3
      11: aload_0
      12: getfield      #31                 // Field annotationIgnoresForMethodParameter:Ljava/util/Map;
      15: aload_3
      16: invokeinterface #40,  2           // InterfaceMethod java/util/Map.get:(Ljava/lang/Object;)Ljava/lang/Object;
      21: checkcast     #46                 // class java/lang/Boolean
      24: astore        4
      26: aload         4
      28: ifnull        37
      31: aload         4
      33: invokevirtual #48                 // Method java/lang/Boolean.booleanValue:()Z
      36: ireturn
      37: aload_0
      38: aload_1
      39: invokevirtual #56                 // Method areMemberConstraintsIgnoredFor:(Lorg/hibernate/validator/internal/properties/Constrainable;)Z
      42: ireturn

  public boolean areClassLevelConstraintsIgnoredFor(java.lang.Class<?>);
    Code:
       0: aload_0
       1: getfield      #19                 // Field annotationIgnoresForClasses:Ljava/util/Map;
       4: aload_1
       5: invokeinterface #40,  2           // InterfaceMethod java/util/Map.get:(Ljava/lang/Object;)Ljava/lang/Object;
      10: checkcast     #46                 // class java/lang/Boolean
      13: astore_3
      14: aload_3
      15: ifnull        26
      18: aload_3
      19: invokevirtual #48                 // Method java/lang/Boolean.booleanValue:()Z
      22: istore_2
      23: goto          32
      26: aload_0
      27: aload_1
      28: invokevirtual #52                 // Method areAllConstraintAnnotationsIgnoredFor:(Ljava/lang/Class;)Z
      31: istore_2
      32: getstatic     #65                 // Field LOG:Lorg/hibernate/validator/internal/util/logging/Log;
      35: invokeinterface #69,  1           // InterfaceMethod org/hibernate/validator/internal/util/logging/Log.isDebugEnabled:()Z
      40: ifeq          61
      43: iload_2
      44: ifeq          61
      47: getstatic     #65                 // Field LOG:Lorg/hibernate/validator/internal/util/logging/Log;
      50: ldc           #74                 // String Class level annotation are getting ignored for %s.
      52: aload_1
      53: invokevirtual #76                 // Method java/lang/Class.getName:()Ljava/lang/String;
      56: invokeinterface #82,  3           // InterfaceMethod org/hibernate/validator/internal/util/logging/Log.debugf:(Ljava/lang/String;Ljava/lang/Object;)V
      61: iload_2
      62: ireturn

  public void merge(org.hibernate.validator.internal.metadata.core.AnnotationProcessingOptions);
    Code:
       0: aload_1
       1: checkcast     #14                 // class org/hibernate/validator/internal/metadata/core/AnnotationProcessingOptionsImpl
       4: astore_2
       5: aload_0
       6: getfield      #13                 // Field ignoreAnnotationDefaults:Ljava/util/Map;
       9: aload_2
      10: getfield      #13                 // Field ignoreAnnotationDefaults:Ljava/util/Map;
      13: invokeinterface #86,  2           // InterfaceMethod java/util/Map.putAll:(Ljava/util/Map;)V
      18: aload_0
      19: getfield      #19                 // Field annotationIgnoresForClasses:Ljava/util/Map;
      22: aload_2
      23: getfield      #19                 // Field annotationIgnoresForClasses:Ljava/util/Map;
      26: invokeinterface #86,  2           // InterfaceMethod java/util/Map.putAll:(Ljava/util/Map;)V
      31: aload_0
      32: getfield      #22                 // Field annotationIgnoredForMembers:Ljava/util/Map;
      35: aload_2
      36: getfield      #22                 // Field annotationIgnoredForMembers:Ljava/util/Map;
      39: invokeinterface #86,  2           // InterfaceMethod java/util/Map.putAll:(Ljava/util/Map;)V
      44: aload_0
      45: getfield      #25                 // Field annotationIgnoresForReturnValues:Ljava/util/Map;
      48: aload_2
      49: getfield      #25                 // Field annotationIgnoresForReturnValues:Ljava/util/Map;
      52: invokeinterface #86,  2           // InterfaceMethod java/util/Map.putAll:(Ljava/util/Map;)V
      57: aload_0
      58: getfield      #28                 // Field annotationIgnoresForCrossParameter:Ljava/util/Map;
      61: aload_2
      62: getfield      #28                 // Field annotationIgnoresForCrossParameter:Ljava/util/Map;
      65: invokeinterface #86,  2           // InterfaceMethod java/util/Map.putAll:(Ljava/util/Map;)V
      70: aload_0
      71: getfield      #31                 // Field annotationIgnoresForMethodParameter:Ljava/util/Map;
      74: aload_2
      75: getfield      #31                 // Field annotationIgnoresForMethodParameter:Ljava/util/Map;
      78: invokeinterface #86,  2           // InterfaceMethod java/util/Map.putAll:(Ljava/util/Map;)V
      83: return

  public void ignoreAnnotationConstraintForClass(java.lang.Class<?>, java.lang.Boolean);
    Code:
       0: aload_2
       1: ifnonnull     21
       4: aload_0
       5: getfield      #13                 // Field ignoreAnnotationDefaults:Ljava/util/Map;
       8: aload_1
       9: getstatic     #90                 // Field java/lang/Boolean.TRUE:Ljava/lang/Boolean;
      12: invokeinterface #94,  3           // InterfaceMethod java/util/Map.put:(Ljava/lang/Object;Ljava/lang/Object;)Ljava/lang/Object;
      17: pop
      18: goto          33
      21: aload_0
      22: getfield      #13                 // Field ignoreAnnotationDefaults:Ljava/util/Map;
      25: aload_1
      26: aload_2
      27: invokeinterface #94,  3           // InterfaceMethod java/util/Map.put:(Ljava/lang/Object;Ljava/lang/Object;)Ljava/lang/Object;
      32: pop
      33: return

  public void ignoreConstraintAnnotationsOnMember(org.hibernate.validator.internal.properties.Constrainable, java.lang.Boolean);
    Code:
       0: aload_0
       1: getfield      #22                 // Field annotationIgnoredForMembers:Ljava/util/Map;
       4: aload_1
       5: aload_2
       6: invokeinterface #94,  3           // InterfaceMethod java/util/Map.put:(Ljava/lang/Object;Ljava/lang/Object;)Ljava/lang/Object;
      11: pop
      12: return

  public void ignoreConstraintAnnotationsForReturnValue(org.hibernate.validator.internal.properties.Constrainable, java.lang.Boolean);
    Code:
       0: aload_0
       1: getfield      #25                 // Field annotationIgnoresForReturnValues:Ljava/util/Map;
       4: aload_1
       5: aload_2
       6: invokeinterface #94,  3           // InterfaceMethod java/util/Map.put:(Ljava/lang/Object;Ljava/lang/Object;)Ljava/lang/Object;
      11: pop
      12: return

  public void ignoreConstraintAnnotationsForCrossParameterConstraint(org.hibernate.validator.internal.properties.Constrainable, java.lang.Boolean);
    Code:
       0: aload_0
       1: getfield      #28                 // Field annotationIgnoresForCrossParameter:Ljava/util/Map;
       4: aload_1
       5: aload_2
       6: invokeinterface #94,  3           // InterfaceMethod java/util/Map.put:(Ljava/lang/Object;Ljava/lang/Object;)Ljava/lang/Object;
      11: pop
      12: return

  public void ignoreConstraintAnnotationsOnParameter(org.hibernate.validator.internal.properties.Constrainable, int, java.lang.Boolean);
    Code:
       0: new           #60                 // class org/hibernate/validator/internal/metadata/core/AnnotationProcessingOptionsImpl$ExecutableParameterKey
       3: dup
       4: aload_0
       5: aload_1
       6: iload_2
       7: invokespecial #62                 // Method org/hibernate/validator/internal/metadata/core/AnnotationProcessingOptionsImpl$ExecutableParameterKey."<init>":(Lorg/hibernate/validator/internal/metadata/core/AnnotationProcessingOptionsImpl;Lorg/hibernate/validator/internal/properties/Constrainable;I)V
      10: astore        4
      12: aload_0
      13: getfield      #31                 // Field annotationIgnoresForMethodParameter:Ljava/util/Map;
      16: aload         4
      18: aload_3
      19: invokeinterface #94,  3           // InterfaceMethod java/util/Map.put:(Ljava/lang/Object;Ljava/lang/Object;)Ljava/lang/Object;
      24: pop
      25: return

  public void ignoreClassLevelConstraintAnnotations(java.lang.Class<?>, boolean);
    Code:
       0: aload_0
       1: getfield      #19                 // Field annotationIgnoresForClasses:Ljava/util/Map;
       4: aload_1
       5: iload_2
       6: invokestatic  #98                 // Method java/lang/Boolean.valueOf:(Z)Ljava/lang/Boolean;
       9: invokeinterface #94,  3           // InterfaceMethod java/util/Map.put:(Ljava/lang/Object;Ljava/lang/Object;)Ljava/lang/Object;
      14: pop
      15: return

  private boolean areAllConstraintAnnotationsIgnoredFor(java.lang.Class<?>);
    Code:
       0: aload_0
       1: getfield      #13                 // Field ignoreAnnotationDefaults:Ljava/util/Map;
       4: aload_1
       5: invokeinterface #102,  2          // InterfaceMethod java/util/Map.containsKey:(Ljava/lang/Object;)Z
      10: ifeq          36
      13: aload_0
      14: getfield      #13                 // Field ignoreAnnotationDefaults:Ljava/util/Map;
      17: aload_1
      18: invokeinterface #40,  2           // InterfaceMethod java/util/Map.get:(Ljava/lang/Object;)Ljava/lang/Object;
      23: checkcast     #46                 // class java/lang/Boolean
      26: invokevirtual #48                 // Method java/lang/Boolean.booleanValue:()Z
      29: ifeq          36
      32: iconst_1
      33: goto          37
      36: iconst_0
      37: ireturn

  static {};
    Code:
       0: invokestatic  #106                // Method java/lang/invoke/MethodHandles.lookup:()Ljava/lang/invoke/MethodHandles$Lookup;
       3: invokestatic  #112                // Method org/hibernate/validator/internal/util/logging/LoggerFactory.make:(Ljava/lang/invoke/MethodHandles$Lookup;)Lorg/hibernate/validator/internal/util/logging/Log;
       6: putstatic     #65                 // Field LOG:Lorg/hibernate/validator/internal/util/logging/Log;
       9: return
}
