Compiled from "BuiltinConstraint.java"
final class org.hibernate.validator.internal.metadata.core.BuiltinConstraint extends java.lang.Enum<org.hibernate.validator.internal.metadata.core.BuiltinConstraint> {
  public static final org.hibernate.validator.internal.metadata.core.BuiltinConstraint JAKARTA_VALIDATION_CONSTRAINTS_ASSERT_FALSE;

  public static final org.hibernate.validator.internal.metadata.core.BuiltinConstraint JAKARTA_VALIDATION_CONSTRAINTS_ASSERT_TRUE;

  public static final org.hibernate.validator.internal.metadata.core.BuiltinConstraint JAKARTA_VALIDATION_CONSTRAINTS_DECIMAL_MAX;

  public static final org.hibernate.validator.internal.metadata.core.BuiltinConstraint JAKARTA_VALIDATION_CONSTRAINTS_DECIMAL_MIN;

  public static final org.hibernate.validator.internal.metadata.core.BuiltinConstraint JAKARTA_VALIDATION_CONSTRAINTS_DIGITS;

  public static final org.hibernate.validator.internal.metadata.core.BuiltinConstraint JAKARTA_VALIDATION_CONSTRAINTS_EMAIL;

  public static final org.hibernate.validator.internal.metadata.core.BuiltinConstraint JAKARTA_VALIDATION_CONSTRAINTS_FUTURE;

  public static final org.hibernate.validator.internal.metadata.core.BuiltinConstraint JAKARTA_VALIDATION_CONSTRAINTS_FUTURE_OR_PRESENT;

  public static final org.hibernate.validator.internal.metadata.core.BuiltinConstraint JAKARTA_VALIDATION_CONSTRAINTS_MIN;

  public static final org.hibernate.validator.internal.metadata.core.BuiltinConstraint JAKARTA_VALIDATION_CONSTRAINTS_MAX;

  public static final org.hibernate.validator.internal.metadata.core.BuiltinConstraint JAKARTA_VALIDATION_CONSTRAINTS_NEGATIVE;

  public static final org.hibernate.validator.internal.metadata.core.BuiltinConstraint JAKARTA_VALIDATION_CONSTRAINTS_NEGATIVE_OR_ZERO;

  public static final org.hibernate.validator.internal.metadata.core.BuiltinConstraint JAKARTA_VALIDATION_CONSTRAINTS_NOT_BLANK;

  public static final org.hibernate.validator.internal.metadata.core.BuiltinConstraint JAKARTA_VALIDATION_CONSTRAINTS_NOT_EMPTY;

  public static final org.hibernate.validator.internal.metadata.core.BuiltinConstraint JAKARTA_VALIDATION_CONSTRAINTS_NOT_NULL;

  public static final org.hibernate.validator.internal.metadata.core.BuiltinConstraint JAKARTA_VALIDATION_CONSTRAINTS_NULL;

  public static final org.hibernate.validator.internal.metadata.core.BuiltinConstraint JAKARTA_VALIDATION_CONSTRAINTS_PAST;

  public static final org.hibernate.validator.internal.metadata.core.BuiltinConstraint JAKARTA_VALIDATION_CONSTRAINTS_PAST_OR_PRESENT;

  public static final org.hibernate.validator.internal.metadata.core.BuiltinConstraint JAKARTA_VALIDATION_CONSTRAINTS_PATTERN;

  public static final org.hibernate.validator.internal.metadata.core.BuiltinConstraint JAKARTA_VALIDATION_CONSTRAINTS_POSITIVE;

  public static final org.hibernate.validator.internal.metadata.core.BuiltinConstraint JAKARTA_VALIDATION_CONSTRAINTS_POSITIVE_OR_ZERO;

  public static final org.hibernate.validator.internal.metadata.core.BuiltinConstraint JAKARTA_VALIDATION_CONSTRAINTS_SIZE;

  public static final org.hibernate.validator.internal.metadata.core.BuiltinConstraint ORG_HIBERNATE_VALIDATOR_CONSTRAINTS_CODE_POINT_LENGTH;

  public static final org.hibernate.validator.internal.metadata.core.BuiltinConstraint ORG_HIBERNATE_VALIDATOR_CONSTRAINTS_CURRENCY;

  public static final org.hibernate.validator.internal.metadata.core.BuiltinConstraint ORG_HIBERNATE_VALIDATOR_CONSTRAINTS_EMAIL;

  public static final org.hibernate.validator.internal.metadata.core.BuiltinConstraint ORG_HIBERNATE_VALIDATOR_CONSTRAINTS_ISBN;

  public static final org.hibernate.validator.internal.metadata.core.BuiltinConstraint ORG_HIBERNATE_VALIDATOR_CONSTRAINTS_LENGTH;

  public static final org.hibernate.validator.internal.metadata.core.BuiltinConstraint ORG_HIBERNATE_VALIDATOR_CONSTRAINTS_LUHN_CHECK;

  public static final org.hibernate.validator.internal.metadata.core.BuiltinConstraint ORG_HIBERNATE_VALIDATOR_CONSTRAINTS_CREDIT_CARD_NUMBER;

  public static final org.hibernate.validator.internal.metadata.core.BuiltinConstraint ORG_HIBERNATE_VALIDATOR_CONSTRAINTS_MOD10_CHECK;

  public static final org.hibernate.validator.internal.metadata.core.BuiltinConstraint ORG_HIBERNATE_VALIDATOR_CONSTRAINTS_MOD11_CHECK;

  public static final org.hibernate.validator.internal.metadata.core.BuiltinConstraint ORG_HIBERNATE_VALIDATOR_CONSTRAINTS_MOD_CHECK;

  public static final org.hibernate.validator.internal.metadata.core.BuiltinConstraint ORG_HIBERNATE_VALIDATOR_CONSTRAINTS_NORMALIZED;

  public static final org.hibernate.validator.internal.metadata.core.BuiltinConstraint ORG_HIBERNATE_VALIDATOR_CONSTRAINTS_EAN;

  public static final org.hibernate.validator.internal.metadata.core.BuiltinConstraint ORG_HIBERNATE_VALIDATOR_CONSTRAINTS_NOT_BLANK;

  public static final org.hibernate.validator.internal.metadata.core.BuiltinConstraint ORG_HIBERNATE_VALIDATOR_CONSTRAINTS_NOT_EMPTY;

  public static final org.hibernate.validator.internal.metadata.core.BuiltinConstraint ORG_HIBERNATE_VALIDATOR_CONSTRAINTS_PARAMETER_SCRIPT_ASSERT;

  public static final org.hibernate.validator.internal.metadata.core.BuiltinConstraint ORG_HIBERNATE_VALIDATOR_CONSTRAINTS_RANGE;

  public static final org.hibernate.validator.internal.metadata.core.BuiltinConstraint ORG_HIBERNATE_VALIDATOR_CONSTRAINTS_SCRIPT_ASSERT;

  public static final org.hibernate.validator.internal.metadata.core.BuiltinConstraint ORG_HIBERNATE_VALIDATOR_CONSTRAINTS_URL;

  public static final org.hibernate.validator.internal.metadata.core.BuiltinConstraint ORG_HIBERNATE_VALIDATOR_CONSTRAINTS_UNIQUE_ELEMENTS;

  public static final org.hibernate.validator.internal.metadata.core.BuiltinConstraint ORG_HIBERNATE_VALIDATOR_CONSTRAINTS_BR_CNPJ;

  public static final org.hibernate.validator.internal.metadata.core.BuiltinConstraint ORG_HIBERNATE_VALIDATOR_CONSTRAINTS_BR_CPF;

  public static final org.hibernate.validator.internal.metadata.core.BuiltinConstraint ORG_HIBERNATE_VALIDATOR_CONSTRAINTS_BR_TITULO_ELEITORAL;

  public static final org.hibernate.validator.internal.metadata.core.BuiltinConstraint ORG_HIBERNATE_VALIDATOR_CONSTRAINTS_PL_NIP;

  public static final org.hibernate.validator.internal.metadata.core.BuiltinConstraint ORG_HIBERNATE_VALIDATOR_CONSTRAINTS_PL_PESEL;

  public static final org.hibernate.validator.internal.metadata.core.BuiltinConstraint ORG_HIBERNATE_VALIDATOR_CONSTRAINTS_PL_REGON;

  public static final org.hibernate.validator.internal.metadata.core.BuiltinConstraint ORG_HIBERNATE_VALIDATOR_CONSTRAINTS_RU_INN;

  public static final org.hibernate.validator.internal.metadata.core.BuiltinConstraint ORG_HIBERNATE_VALIDATOR_CONSTRAINTS_TIME_DURATION_MAX;

  public static final org.hibernate.validator.internal.metadata.core.BuiltinConstraint ORG_HIBERNATE_VALIDATOR_CONSTRAINTS_TIME_DURATION_MIN;

  public static final org.hibernate.validator.internal.metadata.core.BuiltinConstraint ORG_HIBERNATE_VALIDATOR_CONSTRAINTS_UUID;

  private static final java.util.Map<java.lang.String, java.util.Set<org.hibernate.validator.internal.metadata.core.BuiltinConstraint>> CONSTRAINT_MAPPING;

  private java.lang.String annotationClassName;

  private java.util.List<org.hibernate.validator.internal.metadata.core.BuiltinConstraint> constraintDependencies;

  private static final org.hibernate.validator.internal.metadata.core.BuiltinConstraint[] $VALUES;

  public static org.hibernate.validator.internal.metadata.core.BuiltinConstraint[] values();
    Code:
       0: getstatic     #157                // Field $VALUES:[Lorg/hibernate/validator/internal/metadata/core/BuiltinConstraint;
       3: invokevirtual #161                // Method "[Lorg/hibernate/validator/internal/metadata/core/BuiltinConstraint;".clone:()Ljava/lang/Object;
       6: checkcast     #162                // class "[Lorg/hibernate/validator/internal/metadata/core/BuiltinConstraint;"
       9: areturn

  public static org.hibernate.validator.internal.metadata.core.BuiltinConstraint valueOf(java.lang.String);
    Code:
       0: ldc           #1                  // class org/hibernate/validator/internal/metadata/core/BuiltinConstraint
       2: aload_0
       3: invokestatic  #166                // Method java/lang/Enum.valueOf:(Ljava/lang/Class;Ljava/lang/String;)Ljava/lang/Enum;
       6: checkcast     #1                  // class org/hibernate/validator/internal/metadata/core/BuiltinConstraint
       9: areturn

  private org.hibernate.validator.internal.metadata.core.BuiltinConstraint(java.lang.String);
    Code:
       0: aload_0
       1: aload_1
       2: iload_2
       3: aload_3
       4: invokestatic  #172                // Method java/util/Collections.emptyList:()Ljava/util/List;
       7: invokespecial #178                // Method "<init>":(Ljava/lang/String;ILjava/lang/String;Ljava/util/List;)V
      10: return

  private org.hibernate.validator.internal.metadata.core.BuiltinConstraint(java.lang.String, java.util.List<org.hibernate.validator.internal.metadata.core.BuiltinConstraint>);
    Code:
       0: aload_0
       1: aload_1
       2: iload_2
       3: invokespecial #182                // Method java/lang/Enum."<init>":(Ljava/lang/String;I)V
       6: aload_0
       7: aload_3
       8: putfield      #185                // Field annotationClassName:Ljava/lang/String;
      11: aload_0
      12: aload         4
      14: putfield      #189                // Field constraintDependencies:Ljava/util/List;
      17: return

  static java.util.Set<org.hibernate.validator.internal.metadata.core.BuiltinConstraint> resolve(java.util.Set<java.lang.String>);
    Code:
       0: new           #193                // class java/util/HashSet
       3: dup
       4: invokespecial #195                // Method java/util/HashSet."<init>":()V
       7: astore_1
       8: aload_0
       9: invokeinterface #198,  1          // InterfaceMethod java/util/Set.iterator:()Ljava/util/Iterator;
      14: astore_2
      15: aload_2
      16: invokeinterface #204,  1          // InterfaceMethod java/util/Iterator.hasNext:()Z
      21: ifeq          65
      24: aload_2
      25: invokeinterface #210,  1          // InterfaceMethod java/util/Iterator.next:()Ljava/lang/Object;
      30: checkcast     #213                // class java/lang/String
      33: astore_3
      34: getstatic     #215                // Field CONSTRAINT_MAPPING:Ljava/util/Map;
      37: aload_3
      38: invokeinterface #219,  2          // InterfaceMethod java/util/Map.get:(Ljava/lang/Object;)Ljava/lang/Object;
      43: checkcast     #199                // class java/util/Set
      46: astore        4
      48: aload         4
      50: ifnull        62
      53: aload_1
      54: aload         4
      56: invokeinterface #225,  2          // InterfaceMethod java/util/Set.addAll:(Ljava/util/Collection;)Z
      61: pop
      62: goto          15
      65: aload_1
      66: areturn

  static boolean isBuiltin(java.lang.String);
    Code:
       0: getstatic     #215                // Field CONSTRAINT_MAPPING:Ljava/util/Map;
       3: aload_0
       4: invokeinterface #229,  2          // InterfaceMethod java/util/Map.containsKey:(Ljava/lang/Object;)Z
       9: ireturn

  static java.util.Set<java.lang.String> set();
    Code:
       0: getstatic     #215                // Field CONSTRAINT_MAPPING:Ljava/util/Map;
       3: invokeinterface #233,  1          // InterfaceMethod java/util/Map.keySet:()Ljava/util/Set;
       8: areturn

  private static org.hibernate.validator.internal.metadata.core.BuiltinConstraint[] $values();
    Code:
       0: bipush        51
       2: anewarray     #1                  // class org/hibernate/validator/internal/metadata/core/BuiltinConstraint
       5: dup
       6: iconst_0
       7: getstatic     #3                  // Field JAKARTA_VALIDATION_CONSTRAINTS_ASSERT_FALSE:Lorg/hibernate/validator/internal/metadata/core/BuiltinConstraint;
      10: aastore
      11: dup
      12: iconst_1
      13: getstatic     #7                  // Field JAKARTA_VALIDATION_CONSTRAINTS_ASSERT_TRUE:Lorg/hibernate/validator/internal/metadata/core/BuiltinConstraint;
      16: aastore
      17: dup
      18: iconst_2
      19: getstatic     #10                 // Field JAKARTA_VALIDATION_CONSTRAINTS_DECIMAL_MAX:Lorg/hibernate/validator/internal/metadata/core/BuiltinConstraint;
      22: aastore
      23: dup
      24: iconst_3
      25: getstatic     #13                 // Field JAKARTA_VALIDATION_CONSTRAINTS_DECIMAL_MIN:Lorg/hibernate/validator/internal/metadata/core/BuiltinConstraint;
      28: aastore
      29: dup
      30: iconst_4
      31: getstatic     #16                 // Field JAKARTA_VALIDATION_CONSTRAINTS_DIGITS:Lorg/hibernate/validator/internal/metadata/core/BuiltinConstraint;
      34: aastore
      35: dup
      36: iconst_5
      37: getstatic     #19                 // Field JAKARTA_VALIDATION_CONSTRAINTS_EMAIL:Lorg/hibernate/validator/internal/metadata/core/BuiltinConstraint;
      40: aastore
      41: dup
      42: bipush        6
      44: getstatic     #22                 // Field JAKARTA_VALIDATION_CONSTRAINTS_FUTURE:Lorg/hibernate/validator/internal/metadata/core/BuiltinConstraint;
      47: aastore
      48: dup
      49: bipush        7
      51: getstatic     #25                 // Field JAKARTA_VALIDATION_CONSTRAINTS_FUTURE_OR_PRESENT:Lorg/hibernate/validator/internal/metadata/core/BuiltinConstraint;
      54: aastore
      55: dup
      56: bipush        8
      58: getstatic     #28                 // Field JAKARTA_VALIDATION_CONSTRAINTS_MIN:Lorg/hibernate/validator/internal/metadata/core/BuiltinConstraint;
      61: aastore
      62: dup
      63: bipush        9
      65: getstatic     #31                 // Field JAKARTA_VALIDATION_CONSTRAINTS_MAX:Lorg/hibernate/validator/internal/metadata/core/BuiltinConstraint;
      68: aastore
      69: dup
      70: bipush        10
      72: getstatic     #34                 // Field JAKARTA_VALIDATION_CONSTRAINTS_NEGATIVE:Lorg/hibernate/validator/internal/metadata/core/BuiltinConstraint;
      75: aastore
      76: dup
      77: bipush        11
      79: getstatic     #37                 // Field JAKARTA_VALIDATION_CONSTRAINTS_NEGATIVE_OR_ZERO:Lorg/hibernate/validator/internal/metadata/core/BuiltinConstraint;
      82: aastore
      83: dup
      84: bipush        12
      86: getstatic     #40                 // Field JAKARTA_VALIDATION_CONSTRAINTS_NOT_BLANK:Lorg/hibernate/validator/internal/metadata/core/BuiltinConstraint;
      89: aastore
      90: dup
      91: bipush        13
      93: getstatic     #43                 // Field JAKARTA_VALIDATION_CONSTRAINTS_NOT_EMPTY:Lorg/hibernate/validator/internal/metadata/core/BuiltinConstraint;
      96: aastore
      97: dup
      98: bipush        14
     100: getstatic     #46                 // Field JAKARTA_VALIDATION_CONSTRAINTS_NOT_NULL:Lorg/hibernate/validator/internal/metadata/core/BuiltinConstraint;
     103: aastore
     104: dup
     105: bipush        15
     107: getstatic     #49                 // Field JAKARTA_VALIDATION_CONSTRAINTS_NULL:Lorg/hibernate/validator/internal/metadata/core/BuiltinConstraint;
     110: aastore
     111: dup
     112: bipush        16
     114: getstatic     #52                 // Field JAKARTA_VALIDATION_CONSTRAINTS_PAST:Lorg/hibernate/validator/internal/metadata/core/BuiltinConstraint;
     117: aastore
     118: dup
     119: bipush        17
     121: getstatic     #55                 // Field JAKARTA_VALIDATION_CONSTRAINTS_PAST_OR_PRESENT:Lorg/hibernate/validator/internal/metadata/core/BuiltinConstraint;
     124: aastore
     125: dup
     126: bipush        18
     128: getstatic     #58                 // Field JAKARTA_VALIDATION_CONSTRAINTS_PATTERN:Lorg/hibernate/validator/internal/metadata/core/BuiltinConstraint;
     131: aastore
     132: dup
     133: bipush        19
     135: getstatic     #61                 // Field JAKARTA_VALIDATION_CONSTRAINTS_POSITIVE:Lorg/hibernate/validator/internal/metadata/core/BuiltinConstraint;
     138: aastore
     139: dup
     140: bipush        20
     142: getstatic     #64                 // Field JAKARTA_VALIDATION_CONSTRAINTS_POSITIVE_OR_ZERO:Lorg/hibernate/validator/internal/metadata/core/BuiltinConstraint;
     145: aastore
     146: dup
     147: bipush        21
     149: getstatic     #67                 // Field JAKARTA_VALIDATION_CONSTRAINTS_SIZE:Lorg/hibernate/validator/internal/metadata/core/BuiltinConstraint;
     152: aastore
     153: dup
     154: bipush        22
     156: getstatic     #70                 // Field ORG_HIBERNATE_VALIDATOR_CONSTRAINTS_CODE_POINT_LENGTH:Lorg/hibernate/validator/internal/metadata/core/BuiltinConstraint;
     159: aastore
     160: dup
     161: bipush        23
     163: getstatic     #73                 // Field ORG_HIBERNATE_VALIDATOR_CONSTRAINTS_CURRENCY:Lorg/hibernate/validator/internal/metadata/core/BuiltinConstraint;
     166: aastore
     167: dup
     168: bipush        24
     170: getstatic     #76                 // Field ORG_HIBERNATE_VALIDATOR_CONSTRAINTS_EMAIL:Lorg/hibernate/validator/internal/metadata/core/BuiltinConstraint;
     173: aastore
     174: dup
     175: bipush        25
     177: getstatic     #79                 // Field ORG_HIBERNATE_VALIDATOR_CONSTRAINTS_ISBN:Lorg/hibernate/validator/internal/metadata/core/BuiltinConstraint;
     180: aastore
     181: dup
     182: bipush        26
     184: getstatic     #82                 // Field ORG_HIBERNATE_VALIDATOR_CONSTRAINTS_LENGTH:Lorg/hibernate/validator/internal/metadata/core/BuiltinConstraint;
     187: aastore
     188: dup
     189: bipush        27
     191: getstatic     #85                 // Field ORG_HIBERNATE_VALIDATOR_CONSTRAINTS_LUHN_CHECK:Lorg/hibernate/validator/internal/metadata/core/BuiltinConstraint;
     194: aastore
     195: dup
     196: bipush        28
     198: getstatic     #88                 // Field ORG_HIBERNATE_VALIDATOR_CONSTRAINTS_CREDIT_CARD_NUMBER:Lorg/hibernate/validator/internal/metadata/core/BuiltinConstraint;
     201: aastore
     202: dup
     203: bipush        29
     205: getstatic     #91                 // Field ORG_HIBERNATE_VALIDATOR_CONSTRAINTS_MOD10_CHECK:Lorg/hibernate/validator/internal/metadata/core/BuiltinConstraint;
     208: aastore
     209: dup
     210: bipush        30
     212: getstatic     #94                 // Field ORG_HIBERNATE_VALIDATOR_CONSTRAINTS_MOD11_CHECK:Lorg/hibernate/validator/internal/metadata/core/BuiltinConstraint;
     215: aastore
     216: dup
     217: bipush        31
     219: getstatic     #97                 // Field ORG_HIBERNATE_VALIDATOR_CONSTRAINTS_MOD_CHECK:Lorg/hibernate/validator/internal/metadata/core/BuiltinConstraint;
     222: aastore
     223: dup
     224: bipush        32
     226: getstatic     #100                // Field ORG_HIBERNATE_VALIDATOR_CONSTRAINTS_NORMALIZED:Lorg/hibernate/validator/internal/metadata/core/BuiltinConstraint;
     229: aastore
     230: dup
     231: bipush        33
     233: getstatic     #103                // Field ORG_HIBERNATE_VALIDATOR_CONSTRAINTS_EAN:Lorg/hibernate/validator/internal/metadata/core/BuiltinConstraint;
     236: aastore
     237: dup
     238: bipush        34
     240: getstatic     #106                // Field ORG_HIBERNATE_VALIDATOR_CONSTRAINTS_NOT_BLANK:Lorg/hibernate/validator/internal/metadata/core/BuiltinConstraint;
     243: aastore
     244: dup
     245: bipush        35
     247: getstatic     #109                // Field ORG_HIBERNATE_VALIDATOR_CONSTRAINTS_NOT_EMPTY:Lorg/hibernate/validator/internal/metadata/core/BuiltinConstraint;
     250: aastore
     251: dup
     252: bipush        36
     254: getstatic     #112                // Field ORG_HIBERNATE_VALIDATOR_CONSTRAINTS_PARAMETER_SCRIPT_ASSERT:Lorg/hibernate/validator/internal/metadata/core/BuiltinConstraint;
     257: aastore
     258: dup
     259: bipush        37
     261: getstatic     #115                // Field ORG_HIBERNATE_VALIDATOR_CONSTRAINTS_RANGE:Lorg/hibernate/validator/internal/metadata/core/BuiltinConstraint;
     264: aastore
     265: dup
     266: bipush        38
     268: getstatic     #118                // Field ORG_HIBERNATE_VALIDATOR_CONSTRAINTS_SCRIPT_ASSERT:Lorg/hibernate/validator/internal/metadata/core/BuiltinConstraint;
     271: aastore
     272: dup
     273: bipush        39
     275: getstatic     #121                // Field ORG_HIBERNATE_VALIDATOR_CONSTRAINTS_URL:Lorg/hibernate/validator/internal/metadata/core/BuiltinConstraint;
     278: aastore
     279: dup
     280: bipush        40
     282: getstatic     #124                // Field ORG_HIBERNATE_VALIDATOR_CONSTRAINTS_UNIQUE_ELEMENTS:Lorg/hibernate/validator/internal/metadata/core/BuiltinConstraint;
     285: aastore
     286: dup
     287: bipush        41
     289: getstatic     #127                // Field ORG_HIBERNATE_VALIDATOR_CONSTRAINTS_BR_CNPJ:Lorg/hibernate/validator/internal/metadata/core/BuiltinConstraint;
     292: aastore
     293: dup
     294: bipush        42
     296: getstatic     #130                // Field ORG_HIBERNATE_VALIDATOR_CONSTRAINTS_BR_CPF:Lorg/hibernate/validator/internal/metadata/core/BuiltinConstraint;
     299: aastore
     300: dup
     301: bipush        43
     303: getstatic     #133                // Field ORG_HIBERNATE_VALIDATOR_CONSTRAINTS_BR_TITULO_ELEITORAL:Lorg/hibernate/validator/internal/metadata/core/BuiltinConstraint;
     306: aastore
     307: dup
     308: bipush        44
     310: getstatic     #136                // Field ORG_HIBERNATE_VALIDATOR_CONSTRAINTS_PL_NIP:Lorg/hibernate/validator/internal/metadata/core/BuiltinConstraint;
     313: aastore
     314: dup
     315: bipush        45
     317: getstatic     #139                // Field ORG_HIBERNATE_VALIDATOR_CONSTRAINTS_PL_PESEL:Lorg/hibernate/validator/internal/metadata/core/BuiltinConstraint;
     320: aastore
     321: dup
     322: bipush        46
     324: getstatic     #142                // Field ORG_HIBERNATE_VALIDATOR_CONSTRAINTS_PL_REGON:Lorg/hibernate/validator/internal/metadata/core/BuiltinConstraint;
     327: aastore
     328: dup
     329: bipush        47
     331: getstatic     #145                // Field ORG_HIBERNATE_VALIDATOR_CONSTRAINTS_RU_INN:Lorg/hibernate/validator/internal/metadata/core/BuiltinConstraint;
     334: aastore
     335: dup
     336: bipush        48
     338: getstatic     #148                // Field ORG_HIBERNATE_VALIDATOR_CONSTRAINTS_TIME_DURATION_MAX:Lorg/hibernate/validator/internal/metadata/core/BuiltinConstraint;
     341: aastore
     342: dup
     343: bipush        49
     345: getstatic     #151                // Field ORG_HIBERNATE_VALIDATOR_CONSTRAINTS_TIME_DURATION_MIN:Lorg/hibernate/validator/internal/metadata/core/BuiltinConstraint;
     348: aastore
     349: dup
     350: bipush        50
     352: getstatic     #154                // Field ORG_HIBERNATE_VALIDATOR_CONSTRAINTS_UUID:Lorg/hibernate/validator/internal/metadata/core/BuiltinConstraint;
     355: aastore
     356: areturn

  static {};
    Code:
       0: new           #1                  // class org/hibernate/validator/internal/metadata/core/BuiltinConstraint
       3: dup
       4: ldc           #237                // String JAKARTA_VALIDATION_CONSTRAINTS_ASSERT_FALSE
       6: iconst_0
       7: ldc           #238                // String jakarta.validation.constraints.AssertFalse
       9: invokespecial #240                // Method "<init>":(Ljava/lang/String;ILjava/lang/String;)V
      12: putstatic     #3                  // Field JAKARTA_VALIDATION_CONSTRAINTS_ASSERT_FALSE:Lorg/hibernate/validator/internal/metadata/core/BuiltinConstraint;
      15: new           #1                  // class org/hibernate/validator/internal/metadata/core/BuiltinConstraint
      18: dup
      19: ldc           #243                // String JAKARTA_VALIDATION_CONSTRAINTS_ASSERT_TRUE
      21: iconst_1
      22: ldc           #244                // String jakarta.validation.constraints.AssertTrue
      24: invokespecial #240                // Method "<init>":(Ljava/lang/String;ILjava/lang/String;)V
      27: putstatic     #7                  // Field JAKARTA_VALIDATION_CONSTRAINTS_ASSERT_TRUE:Lorg/hibernate/validator/internal/metadata/core/BuiltinConstraint;
      30: new           #1                  // class org/hibernate/validator/internal/metadata/core/BuiltinConstraint
      33: dup
      34: ldc           #246                // String JAKARTA_VALIDATION_CONSTRAINTS_DECIMAL_MAX
      36: iconst_2
      37: ldc           #247                // String jakarta.validation.constraints.DecimalMax
      39: invokespecial #240                // Method "<init>":(Ljava/lang/String;ILjava/lang/String;)V
      42: putstatic     #10                 // Field JAKARTA_VALIDATION_CONSTRAINTS_DECIMAL_MAX:Lorg/hibernate/validator/internal/metadata/core/BuiltinConstraint;
      45: new           #1                  // class org/hibernate/validator/internal/metadata/core/BuiltinConstraint
      48: dup
      49: ldc           #249                // String JAKARTA_VALIDATION_CONSTRAINTS_DECIMAL_MIN
      51: iconst_3
      52: ldc           #250                // String jakarta.validation.constraints.DecimalMin
      54: invokespecial #240                // Method "<init>":(Ljava/lang/String;ILjava/lang/String;)V
      57: putstatic     #13                 // Field JAKARTA_VALIDATION_CONSTRAINTS_DECIMAL_MIN:Lorg/hibernate/validator/internal/metadata/core/BuiltinConstraint;
      60: new           #1                  // class org/hibernate/validator/internal/metadata/core/BuiltinConstraint
      63: dup
      64: ldc           #252                // String JAKARTA_VALIDATION_CONSTRAINTS_DIGITS
      66: iconst_4
      67: ldc           #253                // String jakarta.validation.constraints.Digits
      69: invokespecial #240                // Method "<init>":(Ljava/lang/String;ILjava/lang/String;)V
      72: putstatic     #16                 // Field JAKARTA_VALIDATION_CONSTRAINTS_DIGITS:Lorg/hibernate/validator/internal/metadata/core/BuiltinConstraint;
      75: new           #1                  // class org/hibernate/validator/internal/metadata/core/BuiltinConstraint
      78: dup
      79: ldc           #255                // String JAKARTA_VALIDATION_CONSTRAINTS_EMAIL
      81: iconst_5
      82: ldc_w         #256                // String jakarta.validation.constraints.Email
      85: invokespecial #240                // Method "<init>":(Ljava/lang/String;ILjava/lang/String;)V
      88: putstatic     #19                 // Field JAKARTA_VALIDATION_CONSTRAINTS_EMAIL:Lorg/hibernate/validator/internal/metadata/core/BuiltinConstraint;
      91: new           #1                  // class org/hibernate/validator/internal/metadata/core/BuiltinConstraint
      94: dup
      95: ldc_w         #258                // String JAKARTA_VALIDATION_CONSTRAINTS_FUTURE
      98: bipush        6
     100: ldc_w         #259                // String jakarta.validation.constraints.Future
     103: invokespecial #240                // Method "<init>":(Ljava/lang/String;ILjava/lang/String;)V
     106: putstatic     #22                 // Field JAKARTA_VALIDATION_CONSTRAINTS_FUTURE:Lorg/hibernate/validator/internal/metadata/core/BuiltinConstraint;
     109: new           #1                  // class org/hibernate/validator/internal/metadata/core/BuiltinConstraint
     112: dup
     113: ldc_w         #261                // String JAKARTA_VALIDATION_CONSTRAINTS_FUTURE_OR_PRESENT
     116: bipush        7
     118: ldc_w         #262                // String jakarta.validation.constraints.FutureOrPresent
     121: invokespecial #240                // Method "<init>":(Ljava/lang/String;ILjava/lang/String;)V
     124: putstatic     #25                 // Field JAKARTA_VALIDATION_CONSTRAINTS_FUTURE_OR_PRESENT:Lorg/hibernate/validator/internal/metadata/core/BuiltinConstraint;
     127: new           #1                  // class org/hibernate/validator/internal/metadata/core/BuiltinConstraint
     130: dup
     131: ldc_w         #264                // String JAKARTA_VALIDATION_CONSTRAINTS_MIN
     134: bipush        8
     136: ldc_w         #265                // String jakarta.validation.constraints.Min
     139: invokespecial #240                // Method "<init>":(Ljava/lang/String;ILjava/lang/String;)V
     142: putstatic     #28                 // Field JAKARTA_VALIDATION_CONSTRAINTS_MIN:Lorg/hibernate/validator/internal/metadata/core/BuiltinConstraint;
     145: new           #1                  // class org/hibernate/validator/internal/metadata/core/BuiltinConstraint
     148: dup
     149: ldc_w         #267                // String JAKARTA_VALIDATION_CONSTRAINTS_MAX
     152: bipush        9
     154: ldc_w         #268                // String jakarta.validation.constraints.Max
     157: invokespecial #240                // Method "<init>":(Ljava/lang/String;ILjava/lang/String;)V
     160: putstatic     #31                 // Field JAKARTA_VALIDATION_CONSTRAINTS_MAX:Lorg/hibernate/validator/internal/metadata/core/BuiltinConstraint;
     163: new           #1                  // class org/hibernate/validator/internal/metadata/core/BuiltinConstraint
     166: dup
     167: ldc_w         #270                // String JAKARTA_VALIDATION_CONSTRAINTS_NEGATIVE
     170: bipush        10
     172: ldc_w         #271                // String jakarta.validation.constraints.Negative
     175: invokespecial #240                // Method "<init>":(Ljava/lang/String;ILjava/lang/String;)V
     178: putstatic     #34                 // Field JAKARTA_VALIDATION_CONSTRAINTS_NEGATIVE:Lorg/hibernate/validator/internal/metadata/core/BuiltinConstraint;
     181: new           #1                  // class org/hibernate/validator/internal/metadata/core/BuiltinConstraint
     184: dup
     185: ldc_w         #273                // String JAKARTA_VALIDATION_CONSTRAINTS_NEGATIVE_OR_ZERO
     188: bipush        11
     190: ldc_w         #274                // String jakarta.validation.constraints.NegativeOrZero
     193: invokespecial #240                // Method "<init>":(Ljava/lang/String;ILjava/lang/String;)V
     196: putstatic     #37                 // Field JAKARTA_VALIDATION_CONSTRAINTS_NEGATIVE_OR_ZERO:Lorg/hibernate/validator/internal/metadata/core/BuiltinConstraint;
     199: new           #1                  // class org/hibernate/validator/internal/metadata/core/BuiltinConstraint
     202: dup
     203: ldc_w         #276                // String JAKARTA_VALIDATION_CONSTRAINTS_NOT_BLANK
     206: bipush        12
     208: ldc_w         #277                // String jakarta.validation.constraints.NotBlank
     211: invokespecial #240                // Method "<init>":(Ljava/lang/String;ILjava/lang/String;)V
     214: putstatic     #40                 // Field JAKARTA_VALIDATION_CONSTRAINTS_NOT_BLANK:Lorg/hibernate/validator/internal/metadata/core/BuiltinConstraint;
     217: new           #1                  // class org/hibernate/validator/internal/metadata/core/BuiltinConstraint
     220: dup
     221: ldc_w         #279                // String JAKARTA_VALIDATION_CONSTRAINTS_NOT_EMPTY
     224: bipush        13
     226: ldc_w         #280                // String jakarta.validation.constraints.NotEmpty
     229: invokespecial #240                // Method "<init>":(Ljava/lang/String;ILjava/lang/String;)V
     232: putstatic     #43                 // Field JAKARTA_VALIDATION_CONSTRAINTS_NOT_EMPTY:Lorg/hibernate/validator/internal/metadata/core/BuiltinConstraint;
     235: new           #1                  // class org/hibernate/validator/internal/metadata/core/BuiltinConstraint
     238: dup
     239: ldc_w         #282                // String JAKARTA_VALIDATION_CONSTRAINTS_NOT_NULL
     242: bipush        14
     244: ldc_w         #283                // String jakarta.validation.constraints.NotNull
     247: invokespecial #240                // Method "<init>":(Ljava/lang/String;ILjava/lang/String;)V
     250: putstatic     #46                 // Field JAKARTA_VALIDATION_CONSTRAINTS_NOT_NULL:Lorg/hibernate/validator/internal/metadata/core/BuiltinConstraint;
     253: new           #1                  // class org/hibernate/validator/internal/metadata/core/BuiltinConstraint
     256: dup
     257: ldc_w         #285                // String JAKARTA_VALIDATION_CONSTRAINTS_NULL
     260: bipush        15
     262: ldc_w         #286                // String jakarta.validation.constraints.Null
     265: invokespecial #240                // Method "<init>":(Ljava/lang/String;ILjava/lang/String;)V
     268: putstatic     #49                 // Field JAKARTA_VALIDATION_CONSTRAINTS_NULL:Lorg/hibernate/validator/internal/metadata/core/BuiltinConstraint;
     271: new           #1                  // class org/hibernate/validator/internal/metadata/core/BuiltinConstraint
     274: dup
     275: ldc_w         #288                // String JAKARTA_VALIDATION_CONSTRAINTS_PAST
     278: bipush        16
     280: ldc_w         #289                // String jakarta.validation.constraints.Past
     283: invokespecial #240                // Method "<init>":(Ljava/lang/String;ILjava/lang/String;)V
     286: putstatic     #52                 // Field JAKARTA_VALIDATION_CONSTRAINTS_PAST:Lorg/hibernate/validator/internal/metadata/core/BuiltinConstraint;
     289: new           #1                  // class org/hibernate/validator/internal/metadata/core/BuiltinConstraint
     292: dup
     293: ldc_w         #291                // String JAKARTA_VALIDATION_CONSTRAINTS_PAST_OR_PRESENT
     296: bipush        17
     298: ldc_w         #292                // String jakarta.validation.constraints.PastOrPresent
     301: invokespecial #240                // Method "<init>":(Ljava/lang/String;ILjava/lang/String;)V
     304: putstatic     #55                 // Field JAKARTA_VALIDATION_CONSTRAINTS_PAST_OR_PRESENT:Lorg/hibernate/validator/internal/metadata/core/BuiltinConstraint;
     307: new           #1                  // class org/hibernate/validator/internal/metadata/core/BuiltinConstraint
     310: dup
     311: ldc_w         #294                // String JAKARTA_VALIDATION_CONSTRAINTS_PATTERN
     314: bipush        18
     316: ldc_w         #295                // String jakarta.validation.constraints.Pattern
     319: invokespecial #240                // Method "<init>":(Ljava/lang/String;ILjava/lang/String;)V
     322: putstatic     #58                 // Field JAKARTA_VALIDATION_CONSTRAINTS_PATTERN:Lorg/hibernate/validator/internal/metadata/core/BuiltinConstraint;
     325: new           #1                  // class org/hibernate/validator/internal/metadata/core/BuiltinConstraint
     328: dup
     329: ldc_w         #297                // String JAKARTA_VALIDATION_CONSTRAINTS_POSITIVE
     332: bipush        19
     334: ldc_w         #298                // String jakarta.validation.constraints.Positive
     337: invokespecial #240                // Method "<init>":(Ljava/lang/String;ILjava/lang/String;)V
     340: putstatic     #61                 // Field JAKARTA_VALIDATION_CONSTRAINTS_POSITIVE:Lorg/hibernate/validator/internal/metadata/core/BuiltinConstraint;
     343: new           #1                  // class org/hibernate/validator/internal/metadata/core/BuiltinConstraint
     346: dup
     347: ldc_w         #300                // String JAKARTA_VALIDATION_CONSTRAINTS_POSITIVE_OR_ZERO
     350: bipush        20
     352: ldc_w         #301                // String jakarta.validation.constraints.PositiveOrZero
     355: invokespecial #240                // Method "<init>":(Ljava/lang/String;ILjava/lang/String;)V
     358: putstatic     #64                 // Field JAKARTA_VALIDATION_CONSTRAINTS_POSITIVE_OR_ZERO:Lorg/hibernate/validator/internal/metadata/core/BuiltinConstraint;
     361: new           #1                  // class org/hibernate/validator/internal/metadata/core/BuiltinConstraint
     364: dup
     365: ldc_w         #303                // String JAKARTA_VALIDATION_CONSTRAINTS_SIZE
     368: bipush        21
     370: ldc_w         #304                // String jakarta.validation.constraints.Size
     373: invokespecial #240                // Method "<init>":(Ljava/lang/String;ILjava/lang/String;)V
     376: putstatic     #67                 // Field JAKARTA_VALIDATION_CONSTRAINTS_SIZE:Lorg/hibernate/validator/internal/metadata/core/BuiltinConstraint;
     379: new           #1                  // class org/hibernate/validator/internal/metadata/core/BuiltinConstraint
     382: dup
     383: ldc_w         #306                // String ORG_HIBERNATE_VALIDATOR_CONSTRAINTS_CODE_POINT_LENGTH
     386: bipush        22
     388: ldc_w         #307                // String org.hibernate.validator.constraints.CodePointLength
     391: invokespecial #240                // Method "<init>":(Ljava/lang/String;ILjava/lang/String;)V
     394: putstatic     #70                 // Field ORG_HIBERNATE_VALIDATOR_CONSTRAINTS_CODE_POINT_LENGTH:Lorg/hibernate/validator/internal/metadata/core/BuiltinConstraint;
     397: new           #1                  // class org/hibernate/validator/internal/metadata/core/BuiltinConstraint
     400: dup
     401: ldc_w         #309                // String ORG_HIBERNATE_VALIDATOR_CONSTRAINTS_CURRENCY
     404: bipush        23
     406: ldc_w         #310                // String org.hibernate.validator.constraints.Currency
     409: invokespecial #240                // Method "<init>":(Ljava/lang/String;ILjava/lang/String;)V
     412: putstatic     #73                 // Field ORG_HIBERNATE_VALIDATOR_CONSTRAINTS_CURRENCY:Lorg/hibernate/validator/internal/metadata/core/BuiltinConstraint;
     415: new           #1                  // class org/hibernate/validator/internal/metadata/core/BuiltinConstraint
     418: dup
     419: ldc_w         #312                // String ORG_HIBERNATE_VALIDATOR_CONSTRAINTS_EMAIL
     422: bipush        24
     424: ldc_w         #313                // String org.hibernate.validator.constraints.Email
     427: iconst_1
     428: anewarray     #1                  // class org/hibernate/validator/internal/metadata/core/BuiltinConstraint
     431: dup
     432: iconst_0
     433: getstatic     #58                 // Field JAKARTA_VALIDATION_CONSTRAINTS_PATTERN:Lorg/hibernate/validator/internal/metadata/core/BuiltinConstraint;
     436: aastore
     437: invokestatic  #315                // Method java/util/Arrays.asList:([Ljava/lang/Object;)Ljava/util/List;
     440: invokespecial #178                // Method "<init>":(Ljava/lang/String;ILjava/lang/String;Ljava/util/List;)V
     443: putstatic     #76                 // Field ORG_HIBERNATE_VALIDATOR_CONSTRAINTS_EMAIL:Lorg/hibernate/validator/internal/metadata/core/BuiltinConstraint;
     446: new           #1                  // class org/hibernate/validator/internal/metadata/core/BuiltinConstraint
     449: dup
     450: ldc_w         #321                // String ORG_HIBERNATE_VALIDATOR_CONSTRAINTS_ISBN
     453: bipush        25
     455: ldc_w         #322                // String org.hibernate.validator.constraints.ISBN
     458: invokespecial #240                // Method "<init>":(Ljava/lang/String;ILjava/lang/String;)V
     461: putstatic     #79                 // Field ORG_HIBERNATE_VALIDATOR_CONSTRAINTS_ISBN:Lorg/hibernate/validator/internal/metadata/core/BuiltinConstraint;
     464: new           #1                  // class org/hibernate/validator/internal/metadata/core/BuiltinConstraint
     467: dup
     468: ldc_w         #324                // String ORG_HIBERNATE_VALIDATOR_CONSTRAINTS_LENGTH
     471: bipush        26
     473: ldc_w         #325                // String org.hibernate.validator.constraints.Length
     476: invokespecial #240                // Method "<init>":(Ljava/lang/String;ILjava/lang/String;)V
     479: putstatic     #82                 // Field ORG_HIBERNATE_VALIDATOR_CONSTRAINTS_LENGTH:Lorg/hibernate/validator/internal/metadata/core/BuiltinConstraint;
     482: new           #1                  // class org/hibernate/validator/internal/metadata/core/BuiltinConstraint
     485: dup
     486: ldc_w         #327                // String ORG_HIBERNATE_VALIDATOR_CONSTRAINTS_LUHN_CHECK
     489: bipush        27
     491: ldc_w         #328                // String org.hibernate.validator.constraints.LuhnCheck
     494: invokespecial #240                // Method "<init>":(Ljava/lang/String;ILjava/lang/String;)V
     497: putstatic     #85                 // Field ORG_HIBERNATE_VALIDATOR_CONSTRAINTS_LUHN_CHECK:Lorg/hibernate/validator/internal/metadata/core/BuiltinConstraint;
     500: new           #1                  // class org/hibernate/validator/internal/metadata/core/BuiltinConstraint
     503: dup
     504: ldc_w         #330                // String ORG_HIBERNATE_VALIDATOR_CONSTRAINTS_CREDIT_CARD_NUMBER
     507: bipush        28
     509: ldc_w         #331                // String org.hibernate.validator.constraints.CreditCardNumber
     512: iconst_1
     513: anewarray     #1                  // class org/hibernate/validator/internal/metadata/core/BuiltinConstraint
     516: dup
     517: iconst_0
     518: getstatic     #85                 // Field ORG_HIBERNATE_VALIDATOR_CONSTRAINTS_LUHN_CHECK:Lorg/hibernate/validator/internal/metadata/core/BuiltinConstraint;
     521: aastore
     522: invokestatic  #315                // Method java/util/Arrays.asList:([Ljava/lang/Object;)Ljava/util/List;
     525: invokespecial #178                // Method "<init>":(Ljava/lang/String;ILjava/lang/String;Ljava/util/List;)V
     528: putstatic     #88                 // Field ORG_HIBERNATE_VALIDATOR_CONSTRAINTS_CREDIT_CARD_NUMBER:Lorg/hibernate/validator/internal/metadata/core/BuiltinConstraint;
     531: new           #1                  // class org/hibernate/validator/internal/metadata/core/BuiltinConstraint
     534: dup
     535: ldc_w         #333                // String ORG_HIBERNATE_VALIDATOR_CONSTRAINTS_MOD10_CHECK
     538: bipush        29
     540: ldc_w         #334                // String org.hibernate.validator.constraints.Mod10Check
     543: invokespecial #240                // Method "<init>":(Ljava/lang/String;ILjava/lang/String;)V
     546: putstatic     #91                 // Field ORG_HIBERNATE_VALIDATOR_CONSTRAINTS_MOD10_CHECK:Lorg/hibernate/validator/internal/metadata/core/BuiltinConstraint;
     549: new           #1                  // class org/hibernate/validator/internal/metadata/core/BuiltinConstraint
     552: dup
     553: ldc_w         #336                // String ORG_HIBERNATE_VALIDATOR_CONSTRAINTS_MOD11_CHECK
     556: bipush        30
     558: ldc_w         #337                // String org.hibernate.validator.constraints.Mod11Check
     561: invokespecial #240                // Method "<init>":(Ljava/lang/String;ILjava/lang/String;)V
     564: putstatic     #94                 // Field ORG_HIBERNATE_VALIDATOR_CONSTRAINTS_MOD11_CHECK:Lorg/hibernate/validator/internal/metadata/core/BuiltinConstraint;
     567: new           #1                  // class org/hibernate/validator/internal/metadata/core/BuiltinConstraint
     570: dup
     571: ldc_w         #339                // String ORG_HIBERNATE_VALIDATOR_CONSTRAINTS_MOD_CHECK
     574: bipush        31
     576: ldc_w         #340                // String org.hibernate.validator.constraints.ModCheck
     579: invokespecial #240                // Method "<init>":(Ljava/lang/String;ILjava/lang/String;)V
     582: putstatic     #97                 // Field ORG_HIBERNATE_VALIDATOR_CONSTRAINTS_MOD_CHECK:Lorg/hibernate/validator/internal/metadata/core/BuiltinConstraint;
     585: new           #1                  // class org/hibernate/validator/internal/metadata/core/BuiltinConstraint
     588: dup
     589: ldc_w         #342                // String ORG_HIBERNATE_VALIDATOR_CONSTRAINTS_NORMALIZED
     592: bipush        32
     594: ldc_w         #343                // String org.hibernate.validator.constraints.Normalized
     597: invokespecial #240                // Method "<init>":(Ljava/lang/String;ILjava/lang/String;)V
     600: putstatic     #100                // Field ORG_HIBERNATE_VALIDATOR_CONSTRAINTS_NORMALIZED:Lorg/hibernate/validator/internal/metadata/core/BuiltinConstraint;
     603: new           #1                  // class org/hibernate/validator/internal/metadata/core/BuiltinConstraint
     606: dup
     607: ldc_w         #345                // String ORG_HIBERNATE_VALIDATOR_CONSTRAINTS_EAN
     610: bipush        33
     612: ldc_w         #346                // String org.hibernate.validator.constraints.EAN
     615: iconst_1
     616: anewarray     #1                  // class org/hibernate/validator/internal/metadata/core/BuiltinConstraint
     619: dup
     620: iconst_0
     621: getstatic     #91                 // Field ORG_HIBERNATE_VALIDATOR_CONSTRAINTS_MOD10_CHECK:Lorg/hibernate/validator/internal/metadata/core/BuiltinConstraint;
     624: aastore
     625: invokestatic  #315                // Method java/util/Arrays.asList:([Ljava/lang/Object;)Ljava/util/List;
     628: invokespecial #178                // Method "<init>":(Ljava/lang/String;ILjava/lang/String;Ljava/util/List;)V
     631: putstatic     #103                // Field ORG_HIBERNATE_VALIDATOR_CONSTRAINTS_EAN:Lorg/hibernate/validator/internal/metadata/core/BuiltinConstraint;
     634: new           #1                  // class org/hibernate/validator/internal/metadata/core/BuiltinConstraint
     637: dup
     638: ldc_w         #348                // String ORG_HIBERNATE_VALIDATOR_CONSTRAINTS_NOT_BLANK
     641: bipush        34
     643: ldc_w         #349                // String org.hibernate.validator.constraints.NotBlank
     646: iconst_1
     647: anewarray     #1                  // class org/hibernate/validator/internal/metadata/core/BuiltinConstraint
     650: dup
     651: iconst_0
     652: getstatic     #46                 // Field JAKARTA_VALIDATION_CONSTRAINTS_NOT_NULL:Lorg/hibernate/validator/internal/metadata/core/BuiltinConstraint;
     655: aastore
     656: invokestatic  #315                // Method java/util/Arrays.asList:([Ljava/lang/Object;)Ljava/util/List;
     659: invokespecial #178                // Method "<init>":(Ljava/lang/String;ILjava/lang/String;Ljava/util/List;)V
     662: putstatic     #106                // Field ORG_HIBERNATE_VALIDATOR_CONSTRAINTS_NOT_BLANK:Lorg/hibernate/validator/internal/metadata/core/BuiltinConstraint;
     665: new           #1                  // class org/hibernate/validator/internal/metadata/core/BuiltinConstraint
     668: dup
     669: ldc_w         #351                // String ORG_HIBERNATE_VALIDATOR_CONSTRAINTS_NOT_EMPTY
     672: bipush        35
     674: ldc_w         #352                // String org.hibernate.validator.constraints.NotEmpty
     677: iconst_2
     678: anewarray     #1                  // class org/hibernate/validator/internal/metadata/core/BuiltinConstraint
     681: dup
     682: iconst_0
     683: getstatic     #46                 // Field JAKARTA_VALIDATION_CONSTRAINTS_NOT_NULL:Lorg/hibernate/validator/internal/metadata/core/BuiltinConstraint;
     686: aastore
     687: dup
     688: iconst_1
     689: getstatic     #67                 // Field JAKARTA_VALIDATION_CONSTRAINTS_SIZE:Lorg/hibernate/validator/internal/metadata/core/BuiltinConstraint;
     692: aastore
     693: invokestatic  #315                // Method java/util/Arrays.asList:([Ljava/lang/Object;)Ljava/util/List;
     696: invokespecial #178                // Method "<init>":(Ljava/lang/String;ILjava/lang/String;Ljava/util/List;)V
     699: putstatic     #109                // Field ORG_HIBERNATE_VALIDATOR_CONSTRAINTS_NOT_EMPTY:Lorg/hibernate/validator/internal/metadata/core/BuiltinConstraint;
     702: new           #1                  // class org/hibernate/validator/internal/metadata/core/BuiltinConstraint
     705: dup
     706: ldc_w         #354                // String ORG_HIBERNATE_VALIDATOR_CONSTRAINTS_PARAMETER_SCRIPT_ASSERT
     709: bipush        36
     711: ldc_w         #355                // String org.hibernate.validator.constraints.ParameterScriptAssert
     714: invokespecial #240                // Method "<init>":(Ljava/lang/String;ILjava/lang/String;)V
     717: putstatic     #112                // Field ORG_HIBERNATE_VALIDATOR_CONSTRAINTS_PARAMETER_SCRIPT_ASSERT:Lorg/hibernate/validator/internal/metadata/core/BuiltinConstraint;
     720: new           #1                  // class org/hibernate/validator/internal/metadata/core/BuiltinConstraint
     723: dup
     724: ldc_w         #357                // String ORG_HIBERNATE_VALIDATOR_CONSTRAINTS_RANGE
     727: bipush        37
     729: ldc_w         #358                // String org.hibernate.validator.constraints.Range
     732: iconst_2
     733: anewarray     #1                  // class org/hibernate/validator/internal/metadata/core/BuiltinConstraint
     736: dup
     737: iconst_0
     738: getstatic     #28                 // Field JAKARTA_VALIDATION_CONSTRAINTS_MIN:Lorg/hibernate/validator/internal/metadata/core/BuiltinConstraint;
     741: aastore
     742: dup
     743: iconst_1
     744: getstatic     #31                 // Field JAKARTA_VALIDATION_CONSTRAINTS_MAX:Lorg/hibernate/validator/internal/metadata/core/BuiltinConstraint;
     747: aastore
     748: invokestatic  #315                // Method java/util/Arrays.asList:([Ljava/lang/Object;)Ljava/util/List;
     751: invokespecial #178                // Method "<init>":(Ljava/lang/String;ILjava/lang/String;Ljava/util/List;)V
     754: putstatic     #115                // Field ORG_HIBERNATE_VALIDATOR_CONSTRAINTS_RANGE:Lorg/hibernate/validator/internal/metadata/core/BuiltinConstraint;
     757: new           #1                  // class org/hibernate/validator/internal/metadata/core/BuiltinConstraint
     760: dup
     761: ldc_w         #360                // String ORG_HIBERNATE_VALIDATOR_CONSTRAINTS_SCRIPT_ASSERT
     764: bipush        38
     766: ldc_w         #361                // String org.hibernate.validator.constraints.ScriptAssert
     769: invokespecial #240                // Method "<init>":(Ljava/lang/String;ILjava/lang/String;)V
     772: putstatic     #118                // Field ORG_HIBERNATE_VALIDATOR_CONSTRAINTS_SCRIPT_ASSERT:Lorg/hibernate/validator/internal/metadata/core/BuiltinConstraint;
     775: new           #1                  // class org/hibernate/validator/internal/metadata/core/BuiltinConstraint
     778: dup
     779: ldc_w         #363                // String ORG_HIBERNATE_VALIDATOR_CONSTRAINTS_URL
     782: bipush        39
     784: ldc_w         #364                // String org.hibernate.validator.constraints.URL
     787: iconst_1
     788: anewarray     #1                  // class org/hibernate/validator/internal/metadata/core/BuiltinConstraint
     791: dup
     792: iconst_0
     793: getstatic     #58                 // Field JAKARTA_VALIDATION_CONSTRAINTS_PATTERN:Lorg/hibernate/validator/internal/metadata/core/BuiltinConstraint;
     796: aastore
     797: invokestatic  #315                // Method java/util/Arrays.asList:([Ljava/lang/Object;)Ljava/util/List;
     800: invokespecial #178                // Method "<init>":(Ljava/lang/String;ILjava/lang/String;Ljava/util/List;)V
     803: putstatic     #121                // Field ORG_HIBERNATE_VALIDATOR_CONSTRAINTS_URL:Lorg/hibernate/validator/internal/metadata/core/BuiltinConstraint;
     806: new           #1                  // class org/hibernate/validator/internal/metadata/core/BuiltinConstraint
     809: dup
     810: ldc_w         #366                // String ORG_HIBERNATE_VALIDATOR_CONSTRAINTS_UNIQUE_ELEMENTS
     813: bipush        40
     815: ldc_w         #367                // String org.hibernate.validator.constraints.UniqueElements
     818: invokespecial #240                // Method "<init>":(Ljava/lang/String;ILjava/lang/String;)V
     821: putstatic     #124                // Field ORG_HIBERNATE_VALIDATOR_CONSTRAINTS_UNIQUE_ELEMENTS:Lorg/hibernate/validator/internal/metadata/core/BuiltinConstraint;
     824: new           #1                  // class org/hibernate/validator/internal/metadata/core/BuiltinConstraint
     827: dup
     828: ldc_w         #369                // String ORG_HIBERNATE_VALIDATOR_CONSTRAINTS_BR_CNPJ
     831: bipush        41
     833: ldc_w         #370                // String org.hibernate.validator.constraints.br.CNPJ
     836: iconst_1
     837: anewarray     #1                  // class org/hibernate/validator/internal/metadata/core/BuiltinConstraint
     840: dup
     841: iconst_0
     842: getstatic     #58                 // Field JAKARTA_VALIDATION_CONSTRAINTS_PATTERN:Lorg/hibernate/validator/internal/metadata/core/BuiltinConstraint;
     845: aastore
     846: invokestatic  #315                // Method java/util/Arrays.asList:([Ljava/lang/Object;)Ljava/util/List;
     849: invokespecial #178                // Method "<init>":(Ljava/lang/String;ILjava/lang/String;Ljava/util/List;)V
     852: putstatic     #127                // Field ORG_HIBERNATE_VALIDATOR_CONSTRAINTS_BR_CNPJ:Lorg/hibernate/validator/internal/metadata/core/BuiltinConstraint;
     855: new           #1                  // class org/hibernate/validator/internal/metadata/core/BuiltinConstraint
     858: dup
     859: ldc_w         #372                // String ORG_HIBERNATE_VALIDATOR_CONSTRAINTS_BR_CPF
     862: bipush        42
     864: ldc_w         #373                // String org.hibernate.validator.constraints.br.CPF
     867: iconst_1
     868: anewarray     #1                  // class org/hibernate/validator/internal/metadata/core/BuiltinConstraint
     871: dup
     872: iconst_0
     873: getstatic     #58                 // Field JAKARTA_VALIDATION_CONSTRAINTS_PATTERN:Lorg/hibernate/validator/internal/metadata/core/BuiltinConstraint;
     876: aastore
     877: invokestatic  #315                // Method java/util/Arrays.asList:([Ljava/lang/Object;)Ljava/util/List;
     880: invokespecial #178                // Method "<init>":(Ljava/lang/String;ILjava/lang/String;Ljava/util/List;)V
     883: putstatic     #130                // Field ORG_HIBERNATE_VALIDATOR_CONSTRAINTS_BR_CPF:Lorg/hibernate/validator/internal/metadata/core/BuiltinConstraint;
     886: new           #1                  // class org/hibernate/validator/internal/metadata/core/BuiltinConstraint
     889: dup
     890: ldc_w         #375                // String ORG_HIBERNATE_VALIDATOR_CONSTRAINTS_BR_TITULO_ELEITORAL
     893: bipush        43
     895: ldc_w         #376                // String org.hibernate.validator.constraints.br.TituloEleitoral
     898: iconst_2
     899: anewarray     #1                  // class org/hibernate/validator/internal/metadata/core/BuiltinConstraint
     902: dup
     903: iconst_0
     904: getstatic     #58                 // Field JAKARTA_VALIDATION_CONSTRAINTS_PATTERN:Lorg/hibernate/validator/internal/metadata/core/BuiltinConstraint;
     907: aastore
     908: dup
     909: iconst_1
     910: getstatic     #94                 // Field ORG_HIBERNATE_VALIDATOR_CONSTRAINTS_MOD11_CHECK:Lorg/hibernate/validator/internal/metadata/core/BuiltinConstraint;
     913: aastore
     914: invokestatic  #315                // Method java/util/Arrays.asList:([Ljava/lang/Object;)Ljava/util/List;
     917: invokespecial #178                // Method "<init>":(Ljava/lang/String;ILjava/lang/String;Ljava/util/List;)V
     920: putstatic     #133                // Field ORG_HIBERNATE_VALIDATOR_CONSTRAINTS_BR_TITULO_ELEITORAL:Lorg/hibernate/validator/internal/metadata/core/BuiltinConstraint;
     923: new           #1                  // class org/hibernate/validator/internal/metadata/core/BuiltinConstraint
     926: dup
     927: ldc_w         #378                // String ORG_HIBERNATE_VALIDATOR_CONSTRAINTS_PL_NIP
     930: bipush        44
     932: ldc_w         #379                // String org.hibernate.validator.constraints.pl.NIP
     935: invokespecial #240                // Method "<init>":(Ljava/lang/String;ILjava/lang/String;)V
     938: putstatic     #136                // Field ORG_HIBERNATE_VALIDATOR_CONSTRAINTS_PL_NIP:Lorg/hibernate/validator/internal/metadata/core/BuiltinConstraint;
     941: new           #1                  // class org/hibernate/validator/internal/metadata/core/BuiltinConstraint
     944: dup
     945: ldc_w         #381                // String ORG_HIBERNATE_VALIDATOR_CONSTRAINTS_PL_PESEL
     948: bipush        45
     950: ldc_w         #382                // String org.hibernate.validator.constraints.pl.PESEL
     953: invokespecial #240                // Method "<init>":(Ljava/lang/String;ILjava/lang/String;)V
     956: putstatic     #139                // Field ORG_HIBERNATE_VALIDATOR_CONSTRAINTS_PL_PESEL:Lorg/hibernate/validator/internal/metadata/core/BuiltinConstraint;
     959: new           #1                  // class org/hibernate/validator/internal/metadata/core/BuiltinConstraint
     962: dup
     963: ldc_w         #384                // String ORG_HIBERNATE_VALIDATOR_CONSTRAINTS_PL_REGON
     966: bipush        46
     968: ldc_w         #385                // String org.hibernate.validator.constraints.pl.REGON
     971: invokespecial #240                // Method "<init>":(Ljava/lang/String;ILjava/lang/String;)V
     974: putstatic     #142                // Field ORG_HIBERNATE_VALIDATOR_CONSTRAINTS_PL_REGON:Lorg/hibernate/validator/internal/metadata/core/BuiltinConstraint;
     977: new           #1                  // class org/hibernate/validator/internal/metadata/core/BuiltinConstraint
     980: dup
     981: ldc_w         #387                // String ORG_HIBERNATE_VALIDATOR_CONSTRAINTS_RU_INN
     984: bipush        47
     986: ldc_w         #388                // String org.hibernate.validator.constraints.ru.INN
     989: invokespecial #240                // Method "<init>":(Ljava/lang/String;ILjava/lang/String;)V
     992: putstatic     #145                // Field ORG_HIBERNATE_VALIDATOR_CONSTRAINTS_RU_INN:Lorg/hibernate/validator/internal/metadata/core/BuiltinConstraint;
     995: new           #1                  // class org/hibernate/validator/internal/metadata/core/BuiltinConstraint
     998: dup
     999: ldc_w         #390                // String ORG_HIBERNATE_VALIDATOR_CONSTRAINTS_TIME_DURATION_MAX
    1002: bipush        48
    1004: ldc_w         #391                // String org.hibernate.validator.constraints.time.DurationMax
    1007: invokespecial #240                // Method "<init>":(Ljava/lang/String;ILjava/lang/String;)V
    1010: putstatic     #148                // Field ORG_HIBERNATE_VALIDATOR_CONSTRAINTS_TIME_DURATION_MAX:Lorg/hibernate/validator/internal/metadata/core/BuiltinConstraint;
    1013: new           #1                  // class org/hibernate/validator/internal/metadata/core/BuiltinConstraint
    1016: dup
    1017: ldc_w         #393                // String ORG_HIBERNATE_VALIDATOR_CONSTRAINTS_TIME_DURATION_MIN
    1020: bipush        49
    1022: ldc_w         #394                // String org.hibernate.validator.constraints.time.DurationMin
    1025: invokespecial #240                // Method "<init>":(Ljava/lang/String;ILjava/lang/String;)V
    1028: putstatic     #151                // Field ORG_HIBERNATE_VALIDATOR_CONSTRAINTS_TIME_DURATION_MIN:Lorg/hibernate/validator/internal/metadata/core/BuiltinConstraint;
    1031: new           #1                  // class org/hibernate/validator/internal/metadata/core/BuiltinConstraint
    1034: dup
    1035: ldc_w         #396                // String ORG_HIBERNATE_VALIDATOR_CONSTRAINTS_UUID
    1038: bipush        50
    1040: ldc_w         #397                // String org.hibernate.validator.constraints.UUID
    1043: invokespecial #240                // Method "<init>":(Ljava/lang/String;ILjava/lang/String;)V
    1046: putstatic     #154                // Field ORG_HIBERNATE_VALIDATOR_CONSTRAINTS_UUID:Lorg/hibernate/validator/internal/metadata/core/BuiltinConstraint;
    1049: invokestatic  #399                // Method $values:()[Lorg/hibernate/validator/internal/metadata/core/BuiltinConstraint;
    1052: putstatic     #157                // Field $VALUES:[Lorg/hibernate/validator/internal/metadata/core/BuiltinConstraint;
    1055: new           #403                // class java/util/HashMap
    1058: dup
    1059: invokespecial #405                // Method java/util/HashMap."<init>":()V
    1062: putstatic     #215                // Field CONSTRAINT_MAPPING:Ljava/util/Map;
    1065: invokestatic  #406                // Method values:()[Lorg/hibernate/validator/internal/metadata/core/BuiltinConstraint;
    1068: astore_0
    1069: aload_0
    1070: arraylength
    1071: istore_1
    1072: iconst_0
    1073: istore_2
    1074: iload_2
    1075: iload_1
    1076: if_icmpge     1166
    1079: aload_0
    1080: iload_2
    1081: aaload
    1082: astore_3
    1083: aload_3
    1084: getfield      #189                // Field constraintDependencies:Ljava/util/List;
    1087: invokeinterface #409,  1          // InterfaceMethod java/util/List.isEmpty:()Z
    1092: ifeq          1115
    1095: getstatic     #215                // Field CONSTRAINT_MAPPING:Ljava/util/Map;
    1098: aload_3
    1099: getfield      #185                // Field annotationClassName:Ljava/lang/String;
    1102: aload_3
    1103: invokestatic  #414                // Method java/util/Collections.singleton:(Ljava/lang/Object;)Ljava/util/Set;
    1106: invokeinterface #418,  3          // InterfaceMethod java/util/Map.put:(Ljava/lang/Object;Ljava/lang/Object;)Ljava/lang/Object;
    1111: pop
    1112: goto          1160
    1115: new           #193                // class java/util/HashSet
    1118: dup
    1119: invokespecial #195                // Method java/util/HashSet."<init>":()V
    1122: astore        4
    1124: aload         4
    1126: aload_3
    1127: invokeinterface #422,  2          // InterfaceMethod java/util/Set.add:(Ljava/lang/Object;)Z
    1132: pop
    1133: aload         4
    1135: aload_3
    1136: getfield      #189                // Field constraintDependencies:Ljava/util/List;
    1139: invokeinterface #225,  2          // InterfaceMethod java/util/Set.addAll:(Ljava/util/Collection;)Z
    1144: pop
    1145: getstatic     #215                // Field CONSTRAINT_MAPPING:Ljava/util/Map;
    1148: aload_3
    1149: getfield      #185                // Field annotationClassName:Ljava/lang/String;
    1152: aload         4
    1154: invokeinterface #418,  3          // InterfaceMethod java/util/Map.put:(Ljava/lang/Object;Ljava/lang/Object;)Ljava/lang/Object;
    1159: pop
    1160: iinc          2, 1
    1163: goto          1074
    1166: return
}
