Compiled from "ApplicationMetricsProperties.java"
public class org.springframework.cloud.stream.micrometer.ApplicationMetricsProperties implements org.springframework.context.EnvironmentAware,org.springframework.context.ApplicationContextAware {
  public static final java.lang.String PREFIX;

  public static final java.lang.String EXPORT_FILTER;

  private static final org.springframework.boot.context.properties.bind.Bindable<java.util.Map<java.lang.String, java.lang.String>> STRING_STRING_MAP;

  private java.lang.String meterFilter;

  private java.lang.String key;

  private java.lang.String[] properties;

  private java.time.Duration scheduleInterval;

  private java.util.Map<java.lang.String, java.lang.Object> exportProperties;

  private org.springframework.core.env.Environment environment;

  private org.springframework.context.ApplicationContext applicationContext;

  public org.springframework.cloud.stream.micrometer.ApplicationMetricsProperties();
    Code:
       0: aload_0
       1: invokespecial #2                  // Method java/lang/Object."<init>":()V
       4: aload_0
       5: ldc2_w        #3                  // long 60l
       8: invokestatic  #5                  // Method java/time/Duration.ofSeconds:(J)Ljava/time/Duration;
      11: putfield      #6                  // Field scheduleInterval:Ljava/time/Duration;
      14: return

  public void setEnvironment(org.springframework.core.env.Environment);
    Code:
       0: aload_0
       1: aload_1
       2: putfield      #7                  // Field environment:Lorg/springframework/core/env/Environment;
       5: return

  public void setApplicationContext(org.springframework.context.ApplicationContext) throws org.springframework.beans.BeansException;
    Code:
       0: aload_0
       1: aload_1
       2: putfield      #8                  // Field applicationContext:Lorg/springframework/context/ApplicationContext;
       5: return

  public java.lang.String getKey();
    Code:
       0: aload_0
       1: getfield      #9                  // Field key:Ljava/lang/String;
       4: areturn

  public void setKey(java.lang.String);
    Code:
       0: aload_0
       1: aload_1
       2: putfield      #9                  // Field key:Ljava/lang/String;
       5: return

  public java.lang.String[] getProperties();
    Code:
       0: aload_0
       1: getfield      #10                 // Field properties:[Ljava/lang/String;
       4: areturn

  public void setProperties(java.lang.String[]);
    Code:
       0: aload_0
       1: aload_1
       2: putfield      #10                 // Field properties:[Ljava/lang/String;
       5: return

  public java.util.Map<java.lang.String, java.lang.Object> getExportProperties();
    Code:
       0: aload_0
       1: getfield      #11                 // Field exportProperties:Ljava/util/Map;
       4: ifnonnull     15
       7: aload_0
       8: aload_0
       9: invokespecial #12                 // Method buildExportProperties:()Ljava/util/Map;
      12: putfield      #11                 // Field exportProperties:Ljava/util/Map;
      15: aload_0
      16: getfield      #11                 // Field exportProperties:Ljava/util/Map;
      19: areturn

  public java.time.Duration getScheduleInterval();
    Code:
       0: aload_0
       1: getfield      #6                  // Field scheduleInterval:Ljava/time/Duration;
       4: areturn

  public void setScheduleInterval(java.time.Duration);
    Code:
       0: aload_0
       1: aload_1
       2: putfield      #6                  // Field scheduleInterval:Ljava/time/Duration;
       5: return

  public java.lang.String getMeterFilter();
    Code:
       0: aload_0
       1: getfield      #13                 // Field meterFilter:Ljava/lang/String;
       4: areturn

  public void setMeterFilter(java.lang.String);
    Code:
       0: aload_0
       1: aload_1
       2: putfield      #13                 // Field meterFilter:Ljava/lang/String;
       5: return

  private boolean isMatch(java.lang.String, java.lang.String[], java.lang.String[]);
    Code:
       0: aload_2
       1: invokestatic  #14                 // Method org/springframework/util/ObjectUtils.isEmpty:([Ljava/lang/Object;)Z
       4: ifne          15
       7: aload_2
       8: aload_1
       9: invokestatic  #15                 // Method org/springframework/util/PatternMatchUtils.simpleMatch:([Ljava/lang/String;Ljava/lang/String;)Z
      12: ifeq          29
      15: aload_3
      16: aload_1
      17: invokestatic  #15                 // Method org/springframework/util/PatternMatchUtils.simpleMatch:([Ljava/lang/String;Ljava/lang/String;)Z
      20: ifne          27
      23: iconst_1
      24: goto          28
      27: iconst_0
      28: ireturn
      29: iconst_0
      30: ireturn

  private java.util.Map<java.lang.String, java.lang.Object> buildExportProperties();
    Code:
       0: new           #16                 // class java/util/HashMap
       3: dup
       4: invokespecial #17                 // Method java/util/HashMap."<init>":()V
       7: astore_1
       8: aload_0
       9: getfield      #10                 // Field properties:[Ljava/lang/String;
      12: invokestatic  #14                 // Method org/springframework/util/ObjectUtils.isEmpty:([Ljava/lang/Object;)Z
      15: ifne          204
      18: aload_0
      19: invokespecial #18                 // Method bindProperties:()Ljava/util/Map;
      22: astore_2
      23: aload_0
      24: getfield      #8                  // Field applicationContext:Lorg/springframework/context/ApplicationContext;
      27: checkcast     #19                 // class org/springframework/context/ConfigurableApplicationContext
      30: invokeinterface #20,  1           // InterfaceMethod org/springframework/context/ConfigurableApplicationContext.getBeanFactory:()Lorg/springframework/beans/factory/config/ConfigurableListableBeanFactory;
      35: invokeinterface #21,  1           // InterfaceMethod org/springframework/beans/factory/config/ConfigurableListableBeanFactory.getBeanExpressionResolver:()Lorg/springframework/beans/factory/config/BeanExpressionResolver;
      40: astore_3
      41: new           #22                 // class org/springframework/beans/factory/config/BeanExpressionContext
      44: dup
      45: aload_0
      46: getfield      #8                  // Field applicationContext:Lorg/springframework/context/ApplicationContext;
      49: checkcast     #19                 // class org/springframework/context/ConfigurableApplicationContext
      52: invokeinterface #20,  1           // InterfaceMethod org/springframework/context/ConfigurableApplicationContext.getBeanFactory:()Lorg/springframework/beans/factory/config/ConfigurableListableBeanFactory;
      57: aconst_null
      58: invokespecial #23                 // Method org/springframework/beans/factory/config/BeanExpressionContext."<init>":(Lorg/springframework/beans/factory/config/ConfigurableBeanFactory;Lorg/springframework/beans/factory/config/Scope;)V
      61: astore        4
      63: aload_2
      64: invokeinterface #24,  1           // InterfaceMethod java/util/Map.entrySet:()Ljava/util/Set;
      69: invokeinterface #25,  1           // InterfaceMethod java/util/Set.iterator:()Ljava/util/Iterator;
      74: astore        5
      76: aload         5
      78: invokeinterface #26,  1           // InterfaceMethod java/util/Iterator.hasNext:()Z
      83: ifeq          204
      86: aload         5
      88: invokeinterface #27,  1           // InterfaceMethod java/util/Iterator.next:()Ljava/lang/Object;
      93: checkcast     #28                 // class java/util/Map$Entry
      96: astore        6
      98: aload_0
      99: aload         6
     101: invokeinterface #29,  1           // InterfaceMethod java/util/Map$Entry.getKey:()Ljava/lang/Object;
     106: checkcast     #30                 // class java/lang/String
     109: aload_0
     110: getfield      #10                 // Field properties:[Ljava/lang/String;
     113: aconst_null
     114: invokespecial #31                 // Method isMatch:(Ljava/lang/String;[Ljava/lang/String;[Ljava/lang/String;)Z
     117: ifeq          201
     120: aload         6
     122: invokeinterface #32,  1           // InterfaceMethod java/util/Map$Entry.getValue:()Ljava/lang/Object;
     127: invokestatic  #33                 // Method org/springframework/util/ObjectUtils.nullSafeToString:(Ljava/lang/Object;)Ljava/lang/String;
     130: astore        7
     132: aconst_null
     133: astore        8
     135: aload         7
     137: ifnull        185
     140: aload         7
     142: ldc           #34                 // String #{
     144: invokevirtual #35                 // Method java/lang/String.startsWith:(Ljava/lang/String;)Z
     147: ifeq          172
     150: aload_3
     151: aload_0
     152: getfield      #7                  // Field environment:Lorg/springframework/core/env/Environment;
     155: aload         7
     157: invokeinterface #36,  2           // InterfaceMethod org/springframework/core/env/Environment.resolvePlaceholders:(Ljava/lang/String;)Ljava/lang/String;
     162: aload         4
     164: invokeinterface #37,  3           // InterfaceMethod org/springframework/beans/factory/config/BeanExpressionResolver.evaluate:(Ljava/lang/String;Lorg/springframework/beans/factory/config/BeanExpressionContext;)Ljava/lang/Object;
     169: goto          183
     172: aload_0
     173: getfield      #7                  // Field environment:Lorg/springframework/core/env/Environment;
     176: aload         7
     178: invokeinterface #36,  2           // InterfaceMethod org/springframework/core/env/Environment.resolvePlaceholders:(Ljava/lang/String;)Ljava/lang/String;
     183: astore        8
     185: aload_1
     186: aload         6
     188: invokeinterface #29,  1           // InterfaceMethod java/util/Map$Entry.getKey:()Ljava/lang/Object;
     193: aload         8
     195: invokeinterface #38,  3           // InterfaceMethod java/util/Map.put:(Ljava/lang/Object;Ljava/lang/Object;)Ljava/lang/Object;
     200: pop
     201: goto          76
     204: aload_1
     205: areturn

  private java.util.Map<java.lang.String, java.lang.String> bindProperties();
    Code:
       0: aload_0
       1: getfield      #7                  // Field environment:Lorg/springframework/core/env/Environment;
       4: invokestatic  #39                 // Method org/springframework/boot/context/properties/bind/Binder.get:(Lorg/springframework/core/env/Environment;)Lorg/springframework/boot/context/properties/bind/Binder;
       7: ldc           #40                 // String
       9: getstatic     #41                 // Field STRING_STRING_MAP:Lorg/springframework/boot/context/properties/bind/Bindable;
      12: invokevirtual #42                 // Method org/springframework/boot/context/properties/bind/Binder.bind:(Ljava/lang/String;Lorg/springframework/boot/context/properties/bind/Bindable;)Lorg/springframework/boot/context/properties/bind/BindResult;
      15: astore_2
      16: aload_2
      17: invokevirtual #43                 // Method org/springframework/boot/context/properties/bind/BindResult.isBound:()Z
      20: ifeq          34
      23: aload_2
      24: invokevirtual #44                 // Method org/springframework/boot/context/properties/bind/BindResult.get:()Ljava/lang/Object;
      27: checkcast     #45                 // class java/util/Map
      30: astore_1
      31: goto          42
      34: new           #16                 // class java/util/HashMap
      37: dup
      38: invokespecial #17                 // Method java/util/HashMap."<init>":()V
      41: astore_1
      42: aload_1
      43: areturn

  static {};
    Code:
       0: ldc           #30                 // class java/lang/String
       2: ldc           #30                 // class java/lang/String
       4: invokestatic  #46                 // Method org/springframework/boot/context/properties/bind/Bindable.mapOf:(Ljava/lang/Class;Ljava/lang/Class;)Lorg/springframework/boot/context/properties/bind/Bindable;
       7: putstatic     #41                 // Field STRING_STRING_MAP:Lorg/springframework/boot/context/properties/bind/Bindable;
      10: return
}
