final class org.bouncycastle.asn1.teletrust.TeleTrusTNamedCurves$13 extends org.bouncycastle.asn1.x9.X9ECParametersHolder {
  org.bouncycastle.asn1.teletrust.TeleTrusTNamedCurves$13();
    Code:
       0: aload_0
       1: invokespecial #53                 // Method org/bouncycastle/asn1/x9/X9ECParametersHolder."<init>":()V
       4: return

  protected org.bouncycastle.asn1.x9.X9ECParameters createParameters();
    Code:
       0: new           #28                 // class java/math/BigInteger
       3: dup
       4: ldc           #5                  // String AADD9DB8DBE9C48B3FD4E6AE33C9FC07CB308DB3B3C9D20ED6639CCA70330870553E5C414CA92619418661197FAC10471DB1D381085DDADDB58796829CA90069
       6: bipush        16
       8: invokespecial #50                 // Method java/math/BigInteger."<init>":(Ljava/lang/String;I)V
      11: astore_1
      12: new           #28                 // class java/math/BigInteger
      15: dup
      16: ldc           #1                  // String 01
      18: bipush        16
      20: invokespecial #50                 // Method java/math/BigInteger."<init>":(Ljava/lang/String;I)V
      23: astore_2
      24: new           #34                 // class org/bouncycastle/math/ec/ECCurve$Fp
      27: dup
      28: new           #28                 // class java/math/BigInteger
      31: dup
      32: ldc           #6                  // String AADD9DB8DBE9C48B3FD4E6AE33C9FC07CB308DB3B3C9D20ED6639CCA703308717D4D9B009BC66842AECDA12AE6A380E62881FF2F2D82C68528AA6056583A48F3
      34: bipush        16
      36: invokespecial #50                 // Method java/math/BigInteger."<init>":(Ljava/lang/String;I)V
      39: new           #28                 // class java/math/BigInteger
      42: dup
      43: ldc           #4                  // String 7830A3318B603B89E2327145AC234CC594CBDD8D3DF91610A83441CAEA9863BC2DED5D5AA8253AA10A2EF1C98B9AC8B57F1117A72BF2C7B9E7C1AC4D77FC94CA
      45: bipush        16
      47: invokespecial #50                 // Method java/math/BigInteger."<init>":(Ljava/lang/String;I)V
      50: new           #28                 // class java/math/BigInteger
      53: dup
      54: ldc           #3                  // String 3DF91610A83441CAEA9863BC2DED5D5AA8253AA10A2EF1C98B9AC8B57F1117A72BF2C7B9E7C1AC4D77FC94CADC083E67984050B75EBAE5DD2809BD638016F723
      56: bipush        16
      58: invokespecial #50                 // Method java/math/BigInteger."<init>":(Ljava/lang/String;I)V
      61: aload_1
      62: aload_2
      63: invokespecial #55                 // Method org/bouncycastle/math/ec/ECCurve$Fp."<init>":(Ljava/math/BigInteger;Ljava/math/BigInteger;Ljava/math/BigInteger;Ljava/math/BigInteger;Ljava/math/BigInteger;)V
      66: invokestatic  #51                 // Method org/bouncycastle/asn1/teletrust/TeleTrusTNamedCurves.access$000:(Lorg/bouncycastle/math/ec/ECCurve;)Lorg/bouncycastle/math/ec/ECCurve;
      69: astore_3
      70: new           #31                 // class org/bouncycastle/asn1/x9/X9ECParameters
      73: dup
      74: aload_3
      75: aload_3
      76: ldc           #2                  // String 0481AEE4BDD82ED9645A21322E9C4C6A9385ED9F70B5D916C1B43B62EEF4D0098EFF3B1F78E2D0D48D50D1687B93B97D5F7C6D5047406A5E688B352209BCB9F8227DDE385D566332ECC0EABFA9CF7822FDF209F70024A57B1AA000C55B881F8111B2DCDE494A5F485E5BCA4BD88A2763AED1CA2B2FA8F0540678CD1E0F3AD80892
      78: invokestatic  #56                 // Method org/bouncycastle/util/encoders/Hex.decode:(Ljava/lang/String;)[B
      81: invokevirtual #54                 // Method org/bouncycastle/math/ec/ECCurve.decodePoint:([B)Lorg/bouncycastle/math/ec/ECPoint;
      84: aload_1
      85: aload_2
      86: invokespecial #52                 // Method org/bouncycastle/asn1/x9/X9ECParameters."<init>":(Lorg/bouncycastle/math/ec/ECCurve;Lorg/bouncycastle/math/ec/ECPoint;Ljava/math/BigInteger;Ljava/math/BigInteger;)V
      89: areturn
}
