final class org.bouncycastle.asn1.teletrust.TeleTrusTNamedCurves$8 extends org.bouncycastle.asn1.x9.X9ECParametersHolder {
  org.bouncycastle.asn1.teletrust.TeleTrusTNamedCurves$8();
    Code:
       0: aload_0
       1: invokespecial #53                 // Method org/bouncycastle/asn1/x9/X9ECParametersHolder."<init>":()V
       4: return

  protected org.bouncycastle.asn1.x9.X9ECParameters createParameters();
    Code:
       0: new           #28                 // class java/math/BigInteger
       3: dup
       4: ldc           #4                  // String A9FB57DBA1EEA9BC3E660A909D838D718C397AA3B561A6F7901E0E82974856A7
       6: bipush        16
       8: invokespecial #50                 // Method java/math/BigInteger."<init>":(Ljava/lang/String;I)V
      11: astore_1
      12: new           #28                 // class java/math/BigInteger
      15: dup
      16: ldc           #1                  // String 01
      18: bipush        16
      20: invokespecial #50                 // Method java/math/BigInteger."<init>":(Ljava/lang/String;I)V
      23: astore_2
      24: new           #34                 // class org/bouncycastle/math/ec/ECCurve$Fp
      27: dup
      28: new           #28                 // class java/math/BigInteger
      31: dup
      32: ldc           #6                  // String A9FB57DBA1EEA9BC3E660A909D838D726E3BF623D52620282013481D1F6E5377
      34: bipush        16
      36: invokespecial #50                 // Method java/math/BigInteger."<init>":(Ljava/lang/String;I)V
      39: new           #28                 // class java/math/BigInteger
      42: dup
      43: ldc           #5                  // String A9FB57DBA1EEA9BC3E660A909D838D726E3BF623D52620282013481D1F6E5374
      45: bipush        16
      47: invokespecial #50                 // Method java/math/BigInteger."<init>":(Ljava/lang/String;I)V
      50: new           #28                 // class java/math/BigInteger
      53: dup
      54: ldc           #3                  // String 662C61C430D84EA4FE66A7733D0B76B7BF93EBC4AF2F49256AE58101FEE92B04
      56: bipush        16
      58: invokespecial #50                 // Method java/math/BigInteger."<init>":(Ljava/lang/String;I)V
      61: aload_1
      62: aload_2
      63: invokespecial #55                 // Method org/bouncycastle/math/ec/ECCurve$Fp."<init>":(Ljava/math/BigInteger;Ljava/math/BigInteger;Ljava/math/BigInteger;Ljava/math/BigInteger;Ljava/math/BigInteger;)V
      66: invokestatic  #51                 // Method org/bouncycastle/asn1/teletrust/TeleTrusTNamedCurves.access$000:(Lorg/bouncycastle/math/ec/ECCurve;)Lorg/bouncycastle/math/ec/ECCurve;
      69: astore_3
      70: new           #31                 // class org/bouncycastle/asn1/x9/X9ECParameters
      73: dup
      74: aload_3
      75: aload_3
      76: ldc           #2                  // String 04A3E8EB3CC1CFE7B7732213B23A656149AFA142C47AAFBC2B79A191562E1305F42D996C823439C56D7F7B22E14644417E69BCB6DE39D027001DABE8F35B25C9BE
      78: invokestatic  #56                 // Method org/bouncycastle/util/encoders/Hex.decode:(Ljava/lang/String;)[B
      81: invokevirtual #54                 // Method org/bouncycastle/math/ec/ECCurve.decodePoint:([B)Lorg/bouncycastle/math/ec/ECPoint;
      84: aload_1
      85: aload_2
      86: invokespecial #52                 // Method org/bouncycastle/asn1/x9/X9ECParameters."<init>":(Lorg/bouncycastle/math/ec/ECCurve;Lorg/bouncycastle/math/ec/ECPoint;Ljava/math/BigInteger;Ljava/math/BigInteger;)V
      89: areturn
}
