Compiled from "Callback.java"
class coldsrc.coldlib.util.functional.Callback$1 implements coldsrc.coldlib.util.functional.Callback<V> {
  java.util.function.Function<V, coldsrc.coldlib.util.functional.HandlerResult> consumer;

  java.util.concurrent.CompletableFuture<V> future;

  coldsrc.coldlib.util.functional.Callback$1();
    Code:
       0: aload_0
       1: invokespecial #1                  // Method java/lang/Object."<init>":()V
       4: return

  public coldsrc.coldlib.util.functional.Callback<V> then(java.util.function.Function<V, coldsrc.coldlib.util.functional.HandlerResult>);
    Code:
       0: aload_0
       1: aload_1
       2: putfield      #7                  // Field consumer:Ljava/util/function/Function;
       5: aload_0
       6: areturn

  public java.util.concurrent.CompletableFuture<V> await();
    Code:
       0: aload_0
       1: getfield      #13                 // Field future:Ljava/util/concurrent/CompletableFuture;
       4: ifnull        14
       7: aload_0
       8: getfield      #13                 // Field future:Ljava/util/concurrent/CompletableFuture;
      11: goto          26
      14: aload_0
      15: new           #17                 // class java/util/concurrent/CompletableFuture
      18: dup
      19: invokespecial #19                 // Method java/util/concurrent/CompletableFuture."<init>":()V
      22: dup_x1
      23: putfield      #13                 // Field future:Ljava/util/concurrent/CompletableFuture;
      26: areturn

  public void call(V);
    Code:
       0: aload_0
       1: getfield      #7                  // Field consumer:Ljava/util/function/Function;
       4: ifnull        28
       7: aload_0
       8: getfield      #7                  // Field consumer:Ljava/util/function/Function;
      11: aload_1
      12: invokeinterface #20,  2           // InterfaceMethod java/util/function/Function.apply:(Ljava/lang/Object;)Ljava/lang/Object;
      17: getstatic     #26                 // Field coldsrc/coldlib/util/functional/HandlerResult.REMOVE:Lcoldsrc/coldlib/util/functional/HandlerResult;
      20: if_acmpne     28
      23: aload_0
      24: aconst_null
      25: putfield      #7                  // Field consumer:Ljava/util/function/Function;
      28: aload_0
      29: getfield      #13                 // Field future:Ljava/util/concurrent/CompletableFuture;
      32: ifnull        44
      35: aload_0
      36: getfield      #13                 // Field future:Ljava/util/concurrent/CompletableFuture;
      39: aload_1
      40: invokevirtual #32                 // Method java/util/concurrent/CompletableFuture.complete:(Ljava/lang/Object;)Z
      43: pop
      44: return
}
