Compiled from "HttpTraceEndpointAutoConfiguration.java"
public class org.springframework.boot.actuate.autoconfigure.trace.http.HttpTraceEndpointAutoConfiguration {
  public org.springframework.boot.actuate.autoconfigure.trace.http.HttpTraceEndpointAutoConfiguration();
    Code:
       0: aload_0
       1: invokespecial #1                  // Method java/lang/Object."<init>":()V
       4: return

  public org.springframework.boot.actuate.trace.http.HttpTraceEndpoint httpTraceEndpoint(org.springframework.boot.actuate.trace.http.HttpTraceRepository);
    Code:
       0: new           #2                  // class org/springframework/boot/actuate/trace/http/HttpTraceEndpoint
       3: dup
       4: aload_1
       5: invokespecial #3                  // Method org/springframework/boot/actuate/trace/http/HttpTraceEndpoint."<init>":(Lorg/springframework/boot/actuate/trace/http/HttpTraceRepository;)V
       8: areturn
}
