Compiled from "InMemoryServicesModule.java"
public class org.graylog.plugins.pipelineprocessor.db.memory.InMemoryServicesModule extends org.graylog2.plugin.PluginModule {
  public org.graylog.plugins.pipelineprocessor.db.memory.InMemoryServicesModule();
    Code:
       0: aload_0
       1: invokespecial #1                  // Method org/graylog2/plugin/PluginModule."<init>":()V
       4: return

  protected void configure();
    Code:
       0: aload_0
       1: ldc           #2                  // class org/graylog/plugins/pipelineprocessor/db/RuleService
       3: invokevirtual #3                  // Method bind:(Ljava/lang/Class;)Lcom/google/inject/binder/AnnotatedBindingBuilder;
       6: ldc           #4                  // class org/graylog/plugins/pipelineprocessor/db/memory/InMemoryRuleService
       8: invokeinterface #5,  2            // InterfaceMethod com/google/inject/binder/AnnotatedBindingBuilder.to:(Ljava/lang/Class;)Lcom/google/inject/binder/ScopedBindingBuilder;
      13: invokeinterface #6,  1            // InterfaceMethod com/google/inject/binder/ScopedBindingBuilder.asEagerSingleton:()V
      18: aload_0
      19: ldc           #7                  // class org/graylog/plugins/pipelineprocessor/db/PipelineService
      21: invokevirtual #3                  // Method bind:(Ljava/lang/Class;)Lcom/google/inject/binder/AnnotatedBindingBuilder;
      24: ldc           #8                  // class org/graylog/plugins/pipelineprocessor/db/memory/InMemoryPipelineService
      26: invokeinterface #5,  2            // InterfaceMethod com/google/inject/binder/AnnotatedBindingBuilder.to:(Ljava/lang/Class;)Lcom/google/inject/binder/ScopedBindingBuilder;
      31: invokeinterface #6,  1            // InterfaceMethod com/google/inject/binder/ScopedBindingBuilder.asEagerSingleton:()V
      36: aload_0
      37: ldc           #9                  // class org/graylog/plugins/pipelineprocessor/db/PipelineStreamConnectionsService
      39: invokevirtual #3                  // Method bind:(Ljava/lang/Class;)Lcom/google/inject/binder/AnnotatedBindingBuilder;
      42: ldc           #10                 // class org/graylog/plugins/pipelineprocessor/db/memory/InMemoryPipelineStreamConnectionsService
      44: invokeinterface #5,  2            // InterfaceMethod com/google/inject/binder/AnnotatedBindingBuilder.to:(Ljava/lang/Class;)Lcom/google/inject/binder/ScopedBindingBuilder;
      49: invokeinterface #6,  1            // InterfaceMethod com/google/inject/binder/ScopedBindingBuilder.asEagerSingleton:()V
      54: return
}
