Compiled from "FunctionConverters.scala"
public final class scala.compat.java8.FunctionConverters.package {
  public static scala.Function2 enrichAsJavaBiFunction(scala.Function2);
    Code:
       0: getstatic     #16                 // Field scala/compat/java8/FunctionConverters/package$.MODULE$:Lscala/compat/java8/FunctionConverters/package$;
       3: aload_0
       4: invokevirtual #18                 // Method scala/compat/java8/FunctionConverters/package$.enrichAsJavaBiFunction:(Lscala/Function2;)Lscala/Function2;
       7: areturn

  public static scala.Function2 enrichAsJavaToLongBiFunction(scala.Function2);
    Code:
       0: getstatic     #16                 // Field scala/compat/java8/FunctionConverters/package$.MODULE$:Lscala/compat/java8/FunctionConverters/package$;
       3: aload_0
       4: invokevirtual #21                 // Method scala/compat/java8/FunctionConverters/package$.enrichAsJavaToLongBiFunction:(Lscala/Function2;)Lscala/Function2;
       7: areturn

  public static scala.Function2 enrichAsJavaToIntBiFunction(scala.Function2);
    Code:
       0: getstatic     #16                 // Field scala/compat/java8/FunctionConverters/package$.MODULE$:Lscala/compat/java8/FunctionConverters/package$;
       3: aload_0
       4: invokevirtual #24                 // Method scala/compat/java8/FunctionConverters/package$.enrichAsJavaToIntBiFunction:(Lscala/Function2;)Lscala/Function2;
       7: areturn

  public static scala.Function2 enrichAsJavaToDoubleBiFunction(scala.Function2);
    Code:
       0: getstatic     #16                 // Field scala/compat/java8/FunctionConverters/package$.MODULE$:Lscala/compat/java8/FunctionConverters/package$;
       3: aload_0
       4: invokevirtual #27                 // Method scala/compat/java8/FunctionConverters/package$.enrichAsJavaToDoubleBiFunction:(Lscala/Function2;)Lscala/Function2;
       7: areturn

  public static scala.Function1 enrichAsJavaFunction(scala.Function1);
    Code:
       0: getstatic     #16                 // Field scala/compat/java8/FunctionConverters/package$.MODULE$:Lscala/compat/java8/FunctionConverters/package$;
       3: aload_0
       4: invokevirtual #31                 // Method scala/compat/java8/FunctionConverters/package$.enrichAsJavaFunction:(Lscala/Function1;)Lscala/Function1;
       7: areturn

  public static scala.Function2 enrichAsJavaBiPredicate(scala.Function2);
    Code:
       0: getstatic     #16                 // Field scala/compat/java8/FunctionConverters/package$.MODULE$:Lscala/compat/java8/FunctionConverters/package$;
       3: aload_0
       4: invokevirtual #34                 // Method scala/compat/java8/FunctionConverters/package$.enrichAsJavaBiPredicate:(Lscala/Function2;)Lscala/Function2;
       7: areturn

  public static scala.Function2 enrichAsJavaBiConsumer(scala.Function2);
    Code:
       0: getstatic     #16                 // Field scala/compat/java8/FunctionConverters/package$.MODULE$:Lscala/compat/java8/FunctionConverters/package$;
       3: aload_0
       4: invokevirtual #37                 // Method scala/compat/java8/FunctionConverters/package$.enrichAsJavaBiConsumer:(Lscala/Function2;)Lscala/Function2;
       7: areturn

  public static scala.Function1 enrichAsJavaUnaryOperator(scala.Function1, scala.Predef$$eq$colon$eq);
    Code:
       0: getstatic     #16                 // Field scala/compat/java8/FunctionConverters/package$.MODULE$:Lscala/compat/java8/FunctionConverters/package$;
       3: aload_0
       4: aload_1
       5: invokevirtual #41                 // Method scala/compat/java8/FunctionConverters/package$.enrichAsJavaUnaryOperator:(Lscala/Function1;Lscala/Predef$$eq$colon$eq;)Lscala/Function1;
       8: areturn

  public static scala.Function1 enrichAsJavaToLongFunction(scala.Function1);
    Code:
       0: getstatic     #16                 // Field scala/compat/java8/FunctionConverters/package$.MODULE$:Lscala/compat/java8/FunctionConverters/package$;
       3: aload_0
       4: invokevirtual #44                 // Method scala/compat/java8/FunctionConverters/package$.enrichAsJavaToLongFunction:(Lscala/Function1;)Lscala/Function1;
       7: areturn

  public static scala.Function1 enrichAsJavaToIntFunction(scala.Function1);
    Code:
       0: getstatic     #16                 // Field scala/compat/java8/FunctionConverters/package$.MODULE$:Lscala/compat/java8/FunctionConverters/package$;
       3: aload_0
       4: invokevirtual #47                 // Method scala/compat/java8/FunctionConverters/package$.enrichAsJavaToIntFunction:(Lscala/Function1;)Lscala/Function1;
       7: areturn

  public static scala.Function1 enrichAsJavaToDoubleFunction(scala.Function1);
    Code:
       0: getstatic     #16                 // Field scala/compat/java8/FunctionConverters/package$.MODULE$:Lscala/compat/java8/FunctionConverters/package$;
       3: aload_0
       4: invokevirtual #50                 // Method scala/compat/java8/FunctionConverters/package$.enrichAsJavaToDoubleFunction:(Lscala/Function1;)Lscala/Function1;
       7: areturn

  public static scala.Function0 enrichAsJavaSupplier(scala.Function0);
    Code:
       0: getstatic     #16                 // Field scala/compat/java8/FunctionConverters/package$.MODULE$:Lscala/compat/java8/FunctionConverters/package$;
       3: aload_0
       4: invokevirtual #54                 // Method scala/compat/java8/FunctionConverters/package$.enrichAsJavaSupplier:(Lscala/Function0;)Lscala/Function0;
       7: areturn

  public static scala.Function1 enrichAsJavaPredicate(scala.Function1);
    Code:
       0: getstatic     #16                 // Field scala/compat/java8/FunctionConverters/package$.MODULE$:Lscala/compat/java8/FunctionConverters/package$;
       3: aload_0
       4: invokevirtual #57                 // Method scala/compat/java8/FunctionConverters/package$.enrichAsJavaPredicate:(Lscala/Function1;)Lscala/Function1;
       7: areturn

  public static scala.Function2 enrichAsJavaObjLongConsumer(scala.Function2, scala.Predef$$eq$colon$eq);
    Code:
       0: getstatic     #16                 // Field scala/compat/java8/FunctionConverters/package$.MODULE$:Lscala/compat/java8/FunctionConverters/package$;
       3: aload_0
       4: aload_1
       5: invokevirtual #61                 // Method scala/compat/java8/FunctionConverters/package$.enrichAsJavaObjLongConsumer:(Lscala/Function2;Lscala/Predef$$eq$colon$eq;)Lscala/Function2;
       8: areturn

  public static scala.Function2 enrichAsJavaObjIntConsumer(scala.Function2, scala.Predef$$eq$colon$eq);
    Code:
       0: getstatic     #16                 // Field scala/compat/java8/FunctionConverters/package$.MODULE$:Lscala/compat/java8/FunctionConverters/package$;
       3: aload_0
       4: aload_1
       5: invokevirtual #64                 // Method scala/compat/java8/FunctionConverters/package$.enrichAsJavaObjIntConsumer:(Lscala/Function2;Lscala/Predef$$eq$colon$eq;)Lscala/Function2;
       8: areturn

  public static scala.Function2 enrichAsJavaObjDoubleConsumer(scala.Function2, scala.Predef$$eq$colon$eq);
    Code:
       0: getstatic     #16                 // Field scala/compat/java8/FunctionConverters/package$.MODULE$:Lscala/compat/java8/FunctionConverters/package$;
       3: aload_0
       4: aload_1
       5: invokevirtual #67                 // Method scala/compat/java8/FunctionConverters/package$.enrichAsJavaObjDoubleConsumer:(Lscala/Function2;Lscala/Predef$$eq$colon$eq;)Lscala/Function2;
       8: areturn

  public static scala.Function1 enrichAsJavaLongFunction(scala.Function1, scala.Predef$$eq$colon$eq);
    Code:
       0: getstatic     #16                 // Field scala/compat/java8/FunctionConverters/package$.MODULE$:Lscala/compat/java8/FunctionConverters/package$;
       3: aload_0
       4: aload_1
       5: invokevirtual #70                 // Method scala/compat/java8/FunctionConverters/package$.enrichAsJavaLongFunction:(Lscala/Function1;Lscala/Predef$$eq$colon$eq;)Lscala/Function1;
       8: areturn

  public static scala.Function1 enrichAsJavaIntFunction(scala.Function1, scala.Predef$$eq$colon$eq);
    Code:
       0: getstatic     #16                 // Field scala/compat/java8/FunctionConverters/package$.MODULE$:Lscala/compat/java8/FunctionConverters/package$;
       3: aload_0
       4: aload_1
       5: invokevirtual #73                 // Method scala/compat/java8/FunctionConverters/package$.enrichAsJavaIntFunction:(Lscala/Function1;Lscala/Predef$$eq$colon$eq;)Lscala/Function1;
       8: areturn

  public static scala.Function1 enrichAsJavaDoubleFunction(scala.Function1, scala.Predef$$eq$colon$eq);
    Code:
       0: getstatic     #16                 // Field scala/compat/java8/FunctionConverters/package$.MODULE$:Lscala/compat/java8/FunctionConverters/package$;
       3: aload_0
       4: aload_1
       5: invokevirtual #76                 // Method scala/compat/java8/FunctionConverters/package$.enrichAsJavaDoubleFunction:(Lscala/Function1;Lscala/Predef$$eq$colon$eq;)Lscala/Function1;
       8: areturn

  public static scala.Function1 enrichAsJavaConsumer(scala.Function1);
    Code:
       0: getstatic     #16                 // Field scala/compat/java8/FunctionConverters/package$.MODULE$:Lscala/compat/java8/FunctionConverters/package$;
       3: aload_0
       4: invokevirtual #79                 // Method scala/compat/java8/FunctionConverters/package$.enrichAsJavaConsumer:(Lscala/Function1;)Lscala/Function1;
       7: areturn

  public static scala.Function2 enrichAsJavaBinaryOperator(scala.Function2, scala.Predef$$eq$colon$eq, scala.Predef$$eq$colon$eq);
    Code:
       0: getstatic     #16                 // Field scala/compat/java8/FunctionConverters/package$.MODULE$:Lscala/compat/java8/FunctionConverters/package$;
       3: aload_0
       4: aload_1
       5: aload_2
       6: invokevirtual #83                 // Method scala/compat/java8/FunctionConverters/package$.enrichAsJavaBinaryOperator:(Lscala/Function2;Lscala/Predef$$eq$colon$eq;Lscala/Predef$$eq$colon$eq;)Lscala/Function2;
       9: areturn

  public static java.util.function.UnaryOperator enrichAsScalaFromUnaryOperator(java.util.function.UnaryOperator);
    Code:
       0: getstatic     #16                 // Field scala/compat/java8/FunctionConverters/package$.MODULE$:Lscala/compat/java8/FunctionConverters/package$;
       3: aload_0
       4: invokevirtual #87                 // Method scala/compat/java8/FunctionConverters/package$.enrichAsScalaFromUnaryOperator:(Ljava/util/function/UnaryOperator;)Ljava/util/function/UnaryOperator;
       7: areturn

  public static java.util.function.ToLongFunction enrichAsScalaFromToLongFunction(java.util.function.ToLongFunction);
    Code:
       0: getstatic     #16                 // Field scala/compat/java8/FunctionConverters/package$.MODULE$:Lscala/compat/java8/FunctionConverters/package$;
       3: aload_0
       4: invokevirtual #91                 // Method scala/compat/java8/FunctionConverters/package$.enrichAsScalaFromToLongFunction:(Ljava/util/function/ToLongFunction;)Ljava/util/function/ToLongFunction;
       7: areturn

  public static java.util.function.ToLongBiFunction enrichAsScalaFromToLongBiFunction(java.util.function.ToLongBiFunction);
    Code:
       0: getstatic     #16                 // Field scala/compat/java8/FunctionConverters/package$.MODULE$:Lscala/compat/java8/FunctionConverters/package$;
       3: aload_0
       4: invokevirtual #95                 // Method scala/compat/java8/FunctionConverters/package$.enrichAsScalaFromToLongBiFunction:(Ljava/util/function/ToLongBiFunction;)Ljava/util/function/ToLongBiFunction;
       7: areturn

  public static java.util.function.ToIntFunction enrichAsScalaFromToIntFunction(java.util.function.ToIntFunction);
    Code:
       0: getstatic     #16                 // Field scala/compat/java8/FunctionConverters/package$.MODULE$:Lscala/compat/java8/FunctionConverters/package$;
       3: aload_0
       4: invokevirtual #99                 // Method scala/compat/java8/FunctionConverters/package$.enrichAsScalaFromToIntFunction:(Ljava/util/function/ToIntFunction;)Ljava/util/function/ToIntFunction;
       7: areturn

  public static java.util.function.ToIntBiFunction enrichAsScalaFromToIntBiFunction(java.util.function.ToIntBiFunction);
    Code:
       0: getstatic     #16                 // Field scala/compat/java8/FunctionConverters/package$.MODULE$:Lscala/compat/java8/FunctionConverters/package$;
       3: aload_0
       4: invokevirtual #103                // Method scala/compat/java8/FunctionConverters/package$.enrichAsScalaFromToIntBiFunction:(Ljava/util/function/ToIntBiFunction;)Ljava/util/function/ToIntBiFunction;
       7: areturn

  public static java.util.function.ToDoubleFunction enrichAsScalaFromToDoubleFunction(java.util.function.ToDoubleFunction);
    Code:
       0: getstatic     #16                 // Field scala/compat/java8/FunctionConverters/package$.MODULE$:Lscala/compat/java8/FunctionConverters/package$;
       3: aload_0
       4: invokevirtual #107                // Method scala/compat/java8/FunctionConverters/package$.enrichAsScalaFromToDoubleFunction:(Ljava/util/function/ToDoubleFunction;)Ljava/util/function/ToDoubleFunction;
       7: areturn

  public static java.util.function.ToDoubleBiFunction enrichAsScalaFromToDoubleBiFunction(java.util.function.ToDoubleBiFunction);
    Code:
       0: getstatic     #16                 // Field scala/compat/java8/FunctionConverters/package$.MODULE$:Lscala/compat/java8/FunctionConverters/package$;
       3: aload_0
       4: invokevirtual #111                // Method scala/compat/java8/FunctionConverters/package$.enrichAsScalaFromToDoubleBiFunction:(Ljava/util/function/ToDoubleBiFunction;)Ljava/util/function/ToDoubleBiFunction;
       7: areturn

  public static java.util.function.Supplier enrichAsScalaFromSupplier(java.util.function.Supplier);
    Code:
       0: getstatic     #16                 // Field scala/compat/java8/FunctionConverters/package$.MODULE$:Lscala/compat/java8/FunctionConverters/package$;
       3: aload_0
       4: invokevirtual #115                // Method scala/compat/java8/FunctionConverters/package$.enrichAsScalaFromSupplier:(Ljava/util/function/Supplier;)Ljava/util/function/Supplier;
       7: areturn

  public static java.util.function.Predicate enrichAsScalaFromPredicate(java.util.function.Predicate);
    Code:
       0: getstatic     #16                 // Field scala/compat/java8/FunctionConverters/package$.MODULE$:Lscala/compat/java8/FunctionConverters/package$;
       3: aload_0
       4: invokevirtual #119                // Method scala/compat/java8/FunctionConverters/package$.enrichAsScalaFromPredicate:(Ljava/util/function/Predicate;)Ljava/util/function/Predicate;
       7: areturn

  public static java.util.function.ObjLongConsumer enrichAsScalaFromObjLongConsumer(java.util.function.ObjLongConsumer);
    Code:
       0: getstatic     #16                 // Field scala/compat/java8/FunctionConverters/package$.MODULE$:Lscala/compat/java8/FunctionConverters/package$;
       3: aload_0
       4: invokevirtual #123                // Method scala/compat/java8/FunctionConverters/package$.enrichAsScalaFromObjLongConsumer:(Ljava/util/function/ObjLongConsumer;)Ljava/util/function/ObjLongConsumer;
       7: areturn

  public static java.util.function.ObjIntConsumer enrichAsScalaFromObjIntConsumer(java.util.function.ObjIntConsumer);
    Code:
       0: getstatic     #16                 // Field scala/compat/java8/FunctionConverters/package$.MODULE$:Lscala/compat/java8/FunctionConverters/package$;
       3: aload_0
       4: invokevirtual #127                // Method scala/compat/java8/FunctionConverters/package$.enrichAsScalaFromObjIntConsumer:(Ljava/util/function/ObjIntConsumer;)Ljava/util/function/ObjIntConsumer;
       7: areturn

  public static java.util.function.ObjDoubleConsumer enrichAsScalaFromObjDoubleConsumer(java.util.function.ObjDoubleConsumer);
    Code:
       0: getstatic     #16                 // Field scala/compat/java8/FunctionConverters/package$.MODULE$:Lscala/compat/java8/FunctionConverters/package$;
       3: aload_0
       4: invokevirtual #131                // Method scala/compat/java8/FunctionConverters/package$.enrichAsScalaFromObjDoubleConsumer:(Ljava/util/function/ObjDoubleConsumer;)Ljava/util/function/ObjDoubleConsumer;
       7: areturn

  public static java.util.function.LongUnaryOperator enrichAsScalaFromLongUnaryOperator(java.util.function.LongUnaryOperator);
    Code:
       0: getstatic     #16                 // Field scala/compat/java8/FunctionConverters/package$.MODULE$:Lscala/compat/java8/FunctionConverters/package$;
       3: aload_0
       4: invokevirtual #135                // Method scala/compat/java8/FunctionConverters/package$.enrichAsScalaFromLongUnaryOperator:(Ljava/util/function/LongUnaryOperator;)Ljava/util/function/LongUnaryOperator;
       7: areturn

  public static java.util.function.LongToIntFunction enrichAsScalaFromLongToIntFunction(java.util.function.LongToIntFunction);
    Code:
       0: getstatic     #16                 // Field scala/compat/java8/FunctionConverters/package$.MODULE$:Lscala/compat/java8/FunctionConverters/package$;
       3: aload_0
       4: invokevirtual #139                // Method scala/compat/java8/FunctionConverters/package$.enrichAsScalaFromLongToIntFunction:(Ljava/util/function/LongToIntFunction;)Ljava/util/function/LongToIntFunction;
       7: areturn

  public static java.util.function.LongToDoubleFunction enrichAsScalaFromLongToDoubleFunction(java.util.function.LongToDoubleFunction);
    Code:
       0: getstatic     #16                 // Field scala/compat/java8/FunctionConverters/package$.MODULE$:Lscala/compat/java8/FunctionConverters/package$;
       3: aload_0
       4: invokevirtual #143                // Method scala/compat/java8/FunctionConverters/package$.enrichAsScalaFromLongToDoubleFunction:(Ljava/util/function/LongToDoubleFunction;)Ljava/util/function/LongToDoubleFunction;
       7: areturn

  public static java.util.function.LongSupplier enrichAsScalaFromLongSupplier(java.util.function.LongSupplier);
    Code:
       0: getstatic     #16                 // Field scala/compat/java8/FunctionConverters/package$.MODULE$:Lscala/compat/java8/FunctionConverters/package$;
       3: aload_0
       4: invokevirtual #147                // Method scala/compat/java8/FunctionConverters/package$.enrichAsScalaFromLongSupplier:(Ljava/util/function/LongSupplier;)Ljava/util/function/LongSupplier;
       7: areturn

  public static java.util.function.LongPredicate enrichAsScalaFromLongPredicate(java.util.function.LongPredicate);
    Code:
       0: getstatic     #16                 // Field scala/compat/java8/FunctionConverters/package$.MODULE$:Lscala/compat/java8/FunctionConverters/package$;
       3: aload_0
       4: invokevirtual #151                // Method scala/compat/java8/FunctionConverters/package$.enrichAsScalaFromLongPredicate:(Ljava/util/function/LongPredicate;)Ljava/util/function/LongPredicate;
       7: areturn

  public static java.util.function.LongFunction enrichAsScalaFromLongFunction(java.util.function.LongFunction);
    Code:
       0: getstatic     #16                 // Field scala/compat/java8/FunctionConverters/package$.MODULE$:Lscala/compat/java8/FunctionConverters/package$;
       3: aload_0
       4: invokevirtual #155                // Method scala/compat/java8/FunctionConverters/package$.enrichAsScalaFromLongFunction:(Ljava/util/function/LongFunction;)Ljava/util/function/LongFunction;
       7: areturn

  public static java.util.function.LongConsumer enrichAsScalaFromLongConsumer(java.util.function.LongConsumer);
    Code:
       0: getstatic     #16                 // Field scala/compat/java8/FunctionConverters/package$.MODULE$:Lscala/compat/java8/FunctionConverters/package$;
       3: aload_0
       4: invokevirtual #159                // Method scala/compat/java8/FunctionConverters/package$.enrichAsScalaFromLongConsumer:(Ljava/util/function/LongConsumer;)Ljava/util/function/LongConsumer;
       7: areturn

  public static java.util.function.LongBinaryOperator enrichAsScalaFromLongBinaryOperator(java.util.function.LongBinaryOperator);
    Code:
       0: getstatic     #16                 // Field scala/compat/java8/FunctionConverters/package$.MODULE$:Lscala/compat/java8/FunctionConverters/package$;
       3: aload_0
       4: invokevirtual #163                // Method scala/compat/java8/FunctionConverters/package$.enrichAsScalaFromLongBinaryOperator:(Ljava/util/function/LongBinaryOperator;)Ljava/util/function/LongBinaryOperator;
       7: areturn

  public static java.util.function.IntUnaryOperator enrichAsScalaFromIntUnaryOperator(java.util.function.IntUnaryOperator);
    Code:
       0: getstatic     #16                 // Field scala/compat/java8/FunctionConverters/package$.MODULE$:Lscala/compat/java8/FunctionConverters/package$;
       3: aload_0
       4: invokevirtual #167                // Method scala/compat/java8/FunctionConverters/package$.enrichAsScalaFromIntUnaryOperator:(Ljava/util/function/IntUnaryOperator;)Ljava/util/function/IntUnaryOperator;
       7: areturn

  public static java.util.function.IntToLongFunction enrichAsScalaFromIntToLongFunction(java.util.function.IntToLongFunction);
    Code:
       0: getstatic     #16                 // Field scala/compat/java8/FunctionConverters/package$.MODULE$:Lscala/compat/java8/FunctionConverters/package$;
       3: aload_0
       4: invokevirtual #171                // Method scala/compat/java8/FunctionConverters/package$.enrichAsScalaFromIntToLongFunction:(Ljava/util/function/IntToLongFunction;)Ljava/util/function/IntToLongFunction;
       7: areturn

  public static java.util.function.IntToDoubleFunction enrichAsScalaFromIntToDoubleFunction(java.util.function.IntToDoubleFunction);
    Code:
       0: getstatic     #16                 // Field scala/compat/java8/FunctionConverters/package$.MODULE$:Lscala/compat/java8/FunctionConverters/package$;
       3: aload_0
       4: invokevirtual #175                // Method scala/compat/java8/FunctionConverters/package$.enrichAsScalaFromIntToDoubleFunction:(Ljava/util/function/IntToDoubleFunction;)Ljava/util/function/IntToDoubleFunction;
       7: areturn

  public static java.util.function.IntSupplier enrichAsScalaFromIntSupplier(java.util.function.IntSupplier);
    Code:
       0: getstatic     #16                 // Field scala/compat/java8/FunctionConverters/package$.MODULE$:Lscala/compat/java8/FunctionConverters/package$;
       3: aload_0
       4: invokevirtual #179                // Method scala/compat/java8/FunctionConverters/package$.enrichAsScalaFromIntSupplier:(Ljava/util/function/IntSupplier;)Ljava/util/function/IntSupplier;
       7: areturn

  public static java.util.function.IntPredicate enrichAsScalaFromIntPredicate(java.util.function.IntPredicate);
    Code:
       0: getstatic     #16                 // Field scala/compat/java8/FunctionConverters/package$.MODULE$:Lscala/compat/java8/FunctionConverters/package$;
       3: aload_0
       4: invokevirtual #183                // Method scala/compat/java8/FunctionConverters/package$.enrichAsScalaFromIntPredicate:(Ljava/util/function/IntPredicate;)Ljava/util/function/IntPredicate;
       7: areturn

  public static java.util.function.IntFunction enrichAsScalaFromIntFunction(java.util.function.IntFunction);
    Code:
       0: getstatic     #16                 // Field scala/compat/java8/FunctionConverters/package$.MODULE$:Lscala/compat/java8/FunctionConverters/package$;
       3: aload_0
       4: invokevirtual #187                // Method scala/compat/java8/FunctionConverters/package$.enrichAsScalaFromIntFunction:(Ljava/util/function/IntFunction;)Ljava/util/function/IntFunction;
       7: areturn

  public static java.util.function.IntConsumer enrichAsScalaFromIntConsumer(java.util.function.IntConsumer);
    Code:
       0: getstatic     #16                 // Field scala/compat/java8/FunctionConverters/package$.MODULE$:Lscala/compat/java8/FunctionConverters/package$;
       3: aload_0
       4: invokevirtual #191                // Method scala/compat/java8/FunctionConverters/package$.enrichAsScalaFromIntConsumer:(Ljava/util/function/IntConsumer;)Ljava/util/function/IntConsumer;
       7: areturn

  public static java.util.function.IntBinaryOperator enrichAsScalaFromIntBinaryOperator(java.util.function.IntBinaryOperator);
    Code:
       0: getstatic     #16                 // Field scala/compat/java8/FunctionConverters/package$.MODULE$:Lscala/compat/java8/FunctionConverters/package$;
       3: aload_0
       4: invokevirtual #195                // Method scala/compat/java8/FunctionConverters/package$.enrichAsScalaFromIntBinaryOperator:(Ljava/util/function/IntBinaryOperator;)Ljava/util/function/IntBinaryOperator;
       7: areturn

  public static java.util.function.Function enrichAsScalaFromFunction(java.util.function.Function);
    Code:
       0: getstatic     #16                 // Field scala/compat/java8/FunctionConverters/package$.MODULE$:Lscala/compat/java8/FunctionConverters/package$;
       3: aload_0
       4: invokevirtual #199                // Method scala/compat/java8/FunctionConverters/package$.enrichAsScalaFromFunction:(Ljava/util/function/Function;)Ljava/util/function/Function;
       7: areturn

  public static java.util.function.DoubleUnaryOperator enrichAsScalaFromDoubleUnaryOperator(java.util.function.DoubleUnaryOperator);
    Code:
       0: getstatic     #16                 // Field scala/compat/java8/FunctionConverters/package$.MODULE$:Lscala/compat/java8/FunctionConverters/package$;
       3: aload_0
       4: invokevirtual #203                // Method scala/compat/java8/FunctionConverters/package$.enrichAsScalaFromDoubleUnaryOperator:(Ljava/util/function/DoubleUnaryOperator;)Ljava/util/function/DoubleUnaryOperator;
       7: areturn

  public static java.util.function.DoubleToLongFunction enrichAsScalaFromDoubleToLongFunction(java.util.function.DoubleToLongFunction);
    Code:
       0: getstatic     #16                 // Field scala/compat/java8/FunctionConverters/package$.MODULE$:Lscala/compat/java8/FunctionConverters/package$;
       3: aload_0
       4: invokevirtual #207                // Method scala/compat/java8/FunctionConverters/package$.enrichAsScalaFromDoubleToLongFunction:(Ljava/util/function/DoubleToLongFunction;)Ljava/util/function/DoubleToLongFunction;
       7: areturn

  public static java.util.function.DoubleToIntFunction enrichAsScalaFromDoubleToIntFunction(java.util.function.DoubleToIntFunction);
    Code:
       0: getstatic     #16                 // Field scala/compat/java8/FunctionConverters/package$.MODULE$:Lscala/compat/java8/FunctionConverters/package$;
       3: aload_0
       4: invokevirtual #211                // Method scala/compat/java8/FunctionConverters/package$.enrichAsScalaFromDoubleToIntFunction:(Ljava/util/function/DoubleToIntFunction;)Ljava/util/function/DoubleToIntFunction;
       7: areturn

  public static java.util.function.DoubleSupplier enrichAsScalaFromDoubleSupplier(java.util.function.DoubleSupplier);
    Code:
       0: getstatic     #16                 // Field scala/compat/java8/FunctionConverters/package$.MODULE$:Lscala/compat/java8/FunctionConverters/package$;
       3: aload_0
       4: invokevirtual #215                // Method scala/compat/java8/FunctionConverters/package$.enrichAsScalaFromDoubleSupplier:(Ljava/util/function/DoubleSupplier;)Ljava/util/function/DoubleSupplier;
       7: areturn

  public static java.util.function.DoublePredicate enrichAsScalaFromDoublePredicate(java.util.function.DoublePredicate);
    Code:
       0: getstatic     #16                 // Field scala/compat/java8/FunctionConverters/package$.MODULE$:Lscala/compat/java8/FunctionConverters/package$;
       3: aload_0
       4: invokevirtual #219                // Method scala/compat/java8/FunctionConverters/package$.enrichAsScalaFromDoublePredicate:(Ljava/util/function/DoublePredicate;)Ljava/util/function/DoublePredicate;
       7: areturn

  public static java.util.function.DoubleFunction enrichAsScalaFromDoubleFunction(java.util.function.DoubleFunction);
    Code:
       0: getstatic     #16                 // Field scala/compat/java8/FunctionConverters/package$.MODULE$:Lscala/compat/java8/FunctionConverters/package$;
       3: aload_0
       4: invokevirtual #223                // Method scala/compat/java8/FunctionConverters/package$.enrichAsScalaFromDoubleFunction:(Ljava/util/function/DoubleFunction;)Ljava/util/function/DoubleFunction;
       7: areturn

  public static java.util.function.DoubleConsumer enrichAsScalaFromDoubleConsumer(java.util.function.DoubleConsumer);
    Code:
       0: getstatic     #16                 // Field scala/compat/java8/FunctionConverters/package$.MODULE$:Lscala/compat/java8/FunctionConverters/package$;
       3: aload_0
       4: invokevirtual #227                // Method scala/compat/java8/FunctionConverters/package$.enrichAsScalaFromDoubleConsumer:(Ljava/util/function/DoubleConsumer;)Ljava/util/function/DoubleConsumer;
       7: areturn

  public static java.util.function.DoubleBinaryOperator enrichAsScalaFromDoubleBinaryOperator(java.util.function.DoubleBinaryOperator);
    Code:
       0: getstatic     #16                 // Field scala/compat/java8/FunctionConverters/package$.MODULE$:Lscala/compat/java8/FunctionConverters/package$;
       3: aload_0
       4: invokevirtual #231                // Method scala/compat/java8/FunctionConverters/package$.enrichAsScalaFromDoubleBinaryOperator:(Ljava/util/function/DoubleBinaryOperator;)Ljava/util/function/DoubleBinaryOperator;
       7: areturn

  public static java.util.function.Consumer enrichAsScalaFromConsumer(java.util.function.Consumer);
    Code:
       0: getstatic     #16                 // Field scala/compat/java8/FunctionConverters/package$.MODULE$:Lscala/compat/java8/FunctionConverters/package$;
       3: aload_0
       4: invokevirtual #235                // Method scala/compat/java8/FunctionConverters/package$.enrichAsScalaFromConsumer:(Ljava/util/function/Consumer;)Ljava/util/function/Consumer;
       7: areturn

  public static java.util.function.BooleanSupplier enrichAsScalaFromBooleanSupplier(java.util.function.BooleanSupplier);
    Code:
       0: getstatic     #16                 // Field scala/compat/java8/FunctionConverters/package$.MODULE$:Lscala/compat/java8/FunctionConverters/package$;
       3: aload_0
       4: invokevirtual #239                // Method scala/compat/java8/FunctionConverters/package$.enrichAsScalaFromBooleanSupplier:(Ljava/util/function/BooleanSupplier;)Ljava/util/function/BooleanSupplier;
       7: areturn

  public static java.util.function.BinaryOperator enrichAsScalaFromBinaryOperator(java.util.function.BinaryOperator);
    Code:
       0: getstatic     #16                 // Field scala/compat/java8/FunctionConverters/package$.MODULE$:Lscala/compat/java8/FunctionConverters/package$;
       3: aload_0
       4: invokevirtual #243                // Method scala/compat/java8/FunctionConverters/package$.enrichAsScalaFromBinaryOperator:(Ljava/util/function/BinaryOperator;)Ljava/util/function/BinaryOperator;
       7: areturn

  public static java.util.function.BiPredicate enrichAsScalaFromBiPredicate(java.util.function.BiPredicate);
    Code:
       0: getstatic     #16                 // Field scala/compat/java8/FunctionConverters/package$.MODULE$:Lscala/compat/java8/FunctionConverters/package$;
       3: aload_0
       4: invokevirtual #247                // Method scala/compat/java8/FunctionConverters/package$.enrichAsScalaFromBiPredicate:(Ljava/util/function/BiPredicate;)Ljava/util/function/BiPredicate;
       7: areturn

  public static java.util.function.BiFunction enrichAsScalaFromBiFunction(java.util.function.BiFunction);
    Code:
       0: getstatic     #16                 // Field scala/compat/java8/FunctionConverters/package$.MODULE$:Lscala/compat/java8/FunctionConverters/package$;
       3: aload_0
       4: invokevirtual #251                // Method scala/compat/java8/FunctionConverters/package$.enrichAsScalaFromBiFunction:(Ljava/util/function/BiFunction;)Ljava/util/function/BiFunction;
       7: areturn

  public static java.util.function.BiConsumer enrichAsScalaFromBiConsumer(java.util.function.BiConsumer);
    Code:
       0: getstatic     #16                 // Field scala/compat/java8/FunctionConverters/package$.MODULE$:Lscala/compat/java8/FunctionConverters/package$;
       3: aload_0
       4: invokevirtual #255                // Method scala/compat/java8/FunctionConverters/package$.enrichAsScalaFromBiConsumer:(Ljava/util/function/BiConsumer;)Ljava/util/function/BiConsumer;
       7: areturn

  public static scala.Function1 enrichAsJavaLongUnaryOperator(scala.Function1, scala.Predef$$eq$colon$eq);
    Code:
       0: getstatic     #16                 // Field scala/compat/java8/FunctionConverters/package$.MODULE$:Lscala/compat/java8/FunctionConverters/package$;
       3: aload_0
       4: aload_1
       5: invokevirtual #258                // Method scala/compat/java8/FunctionConverters/package$.enrichAsJavaLongUnaryOperator:(Lscala/Function1;Lscala/Predef$$eq$colon$eq;)Lscala/Function1;
       8: areturn

  public static scala.Function1 enrichAsJavaLongToIntFunction(scala.Function1, scala.Predef$$eq$colon$eq);
    Code:
       0: getstatic     #16                 // Field scala/compat/java8/FunctionConverters/package$.MODULE$:Lscala/compat/java8/FunctionConverters/package$;
       3: aload_0
       4: aload_1
       5: invokevirtual #261                // Method scala/compat/java8/FunctionConverters/package$.enrichAsJavaLongToIntFunction:(Lscala/Function1;Lscala/Predef$$eq$colon$eq;)Lscala/Function1;
       8: areturn

  public static scala.Function1 enrichAsJavaLongToDoubleFunction(scala.Function1, scala.Predef$$eq$colon$eq);
    Code:
       0: getstatic     #16                 // Field scala/compat/java8/FunctionConverters/package$.MODULE$:Lscala/compat/java8/FunctionConverters/package$;
       3: aload_0
       4: aload_1
       5: invokevirtual #264                // Method scala/compat/java8/FunctionConverters/package$.enrichAsJavaLongToDoubleFunction:(Lscala/Function1;Lscala/Predef$$eq$colon$eq;)Lscala/Function1;
       8: areturn

  public static scala.Function0 enrichAsJavaLongSupplier(scala.Function0);
    Code:
       0: getstatic     #16                 // Field scala/compat/java8/FunctionConverters/package$.MODULE$:Lscala/compat/java8/FunctionConverters/package$;
       3: aload_0
       4: invokevirtual #267                // Method scala/compat/java8/FunctionConverters/package$.enrichAsJavaLongSupplier:(Lscala/Function0;)Lscala/Function0;
       7: areturn

  public static scala.Function1 enrichAsJavaLongPredicate(scala.Function1, scala.Predef$$eq$colon$eq);
    Code:
       0: getstatic     #16                 // Field scala/compat/java8/FunctionConverters/package$.MODULE$:Lscala/compat/java8/FunctionConverters/package$;
       3: aload_0
       4: aload_1
       5: invokevirtual #270                // Method scala/compat/java8/FunctionConverters/package$.enrichAsJavaLongPredicate:(Lscala/Function1;Lscala/Predef$$eq$colon$eq;)Lscala/Function1;
       8: areturn

  public static scala.Function1 enrichAsJavaLongConsumer(scala.Function1, scala.Predef$$eq$colon$eq);
    Code:
       0: getstatic     #16                 // Field scala/compat/java8/FunctionConverters/package$.MODULE$:Lscala/compat/java8/FunctionConverters/package$;
       3: aload_0
       4: aload_1
       5: invokevirtual #273                // Method scala/compat/java8/FunctionConverters/package$.enrichAsJavaLongConsumer:(Lscala/Function1;Lscala/Predef$$eq$colon$eq;)Lscala/Function1;
       8: areturn

  public static scala.Function2 enrichAsJavaLongBinaryOperator(scala.Function2, scala.Predef$$eq$colon$eq, scala.Predef$$eq$colon$eq);
    Code:
       0: getstatic     #16                 // Field scala/compat/java8/FunctionConverters/package$.MODULE$:Lscala/compat/java8/FunctionConverters/package$;
       3: aload_0
       4: aload_1
       5: aload_2
       6: invokevirtual #276                // Method scala/compat/java8/FunctionConverters/package$.enrichAsJavaLongBinaryOperator:(Lscala/Function2;Lscala/Predef$$eq$colon$eq;Lscala/Predef$$eq$colon$eq;)Lscala/Function2;
       9: areturn

  public static scala.Function1 enrichAsJavaIntUnaryOperator(scala.Function1, scala.Predef$$eq$colon$eq);
    Code:
       0: getstatic     #16                 // Field scala/compat/java8/FunctionConverters/package$.MODULE$:Lscala/compat/java8/FunctionConverters/package$;
       3: aload_0
       4: aload_1
       5: invokevirtual #279                // Method scala/compat/java8/FunctionConverters/package$.enrichAsJavaIntUnaryOperator:(Lscala/Function1;Lscala/Predef$$eq$colon$eq;)Lscala/Function1;
       8: areturn

  public static scala.Function1 enrichAsJavaIntToLongFunction(scala.Function1, scala.Predef$$eq$colon$eq);
    Code:
       0: getstatic     #16                 // Field scala/compat/java8/FunctionConverters/package$.MODULE$:Lscala/compat/java8/FunctionConverters/package$;
       3: aload_0
       4: aload_1
       5: invokevirtual #282                // Method scala/compat/java8/FunctionConverters/package$.enrichAsJavaIntToLongFunction:(Lscala/Function1;Lscala/Predef$$eq$colon$eq;)Lscala/Function1;
       8: areturn

  public static scala.Function1 enrichAsJavaIntToDoubleFunction(scala.Function1, scala.Predef$$eq$colon$eq);
    Code:
       0: getstatic     #16                 // Field scala/compat/java8/FunctionConverters/package$.MODULE$:Lscala/compat/java8/FunctionConverters/package$;
       3: aload_0
       4: aload_1
       5: invokevirtual #285                // Method scala/compat/java8/FunctionConverters/package$.enrichAsJavaIntToDoubleFunction:(Lscala/Function1;Lscala/Predef$$eq$colon$eq;)Lscala/Function1;
       8: areturn

  public static scala.Function0 enrichAsJavaIntSupplier(scala.Function0);
    Code:
       0: getstatic     #16                 // Field scala/compat/java8/FunctionConverters/package$.MODULE$:Lscala/compat/java8/FunctionConverters/package$;
       3: aload_0
       4: invokevirtual #288                // Method scala/compat/java8/FunctionConverters/package$.enrichAsJavaIntSupplier:(Lscala/Function0;)Lscala/Function0;
       7: areturn

  public static scala.Function1 enrichAsJavaIntPredicate(scala.Function1, scala.Predef$$eq$colon$eq);
    Code:
       0: getstatic     #16                 // Field scala/compat/java8/FunctionConverters/package$.MODULE$:Lscala/compat/java8/FunctionConverters/package$;
       3: aload_0
       4: aload_1
       5: invokevirtual #291                // Method scala/compat/java8/FunctionConverters/package$.enrichAsJavaIntPredicate:(Lscala/Function1;Lscala/Predef$$eq$colon$eq;)Lscala/Function1;
       8: areturn

  public static scala.Function1 enrichAsJavaIntConsumer(scala.Function1, scala.Predef$$eq$colon$eq);
    Code:
       0: getstatic     #16                 // Field scala/compat/java8/FunctionConverters/package$.MODULE$:Lscala/compat/java8/FunctionConverters/package$;
       3: aload_0
       4: aload_1
       5: invokevirtual #294                // Method scala/compat/java8/FunctionConverters/package$.enrichAsJavaIntConsumer:(Lscala/Function1;Lscala/Predef$$eq$colon$eq;)Lscala/Function1;
       8: areturn

  public static scala.Function2 enrichAsJavaIntBinaryOperator(scala.Function2, scala.Predef$$eq$colon$eq, scala.Predef$$eq$colon$eq);
    Code:
       0: getstatic     #16                 // Field scala/compat/java8/FunctionConverters/package$.MODULE$:Lscala/compat/java8/FunctionConverters/package$;
       3: aload_0
       4: aload_1
       5: aload_2
       6: invokevirtual #297                // Method scala/compat/java8/FunctionConverters/package$.enrichAsJavaIntBinaryOperator:(Lscala/Function2;Lscala/Predef$$eq$colon$eq;Lscala/Predef$$eq$colon$eq;)Lscala/Function2;
       9: areturn

  public static scala.Function1 enrichAsJavaDoubleUnaryOperator(scala.Function1, scala.Predef$$eq$colon$eq);
    Code:
       0: getstatic     #16                 // Field scala/compat/java8/FunctionConverters/package$.MODULE$:Lscala/compat/java8/FunctionConverters/package$;
       3: aload_0
       4: aload_1
       5: invokevirtual #300                // Method scala/compat/java8/FunctionConverters/package$.enrichAsJavaDoubleUnaryOperator:(Lscala/Function1;Lscala/Predef$$eq$colon$eq;)Lscala/Function1;
       8: areturn

  public static scala.Function1 enrichAsJavaDoubleToLongFunction(scala.Function1, scala.Predef$$eq$colon$eq);
    Code:
       0: getstatic     #16                 // Field scala/compat/java8/FunctionConverters/package$.MODULE$:Lscala/compat/java8/FunctionConverters/package$;
       3: aload_0
       4: aload_1
       5: invokevirtual #303                // Method scala/compat/java8/FunctionConverters/package$.enrichAsJavaDoubleToLongFunction:(Lscala/Function1;Lscala/Predef$$eq$colon$eq;)Lscala/Function1;
       8: areturn

  public static scala.Function1 enrichAsJavaDoubleToIntFunction(scala.Function1, scala.Predef$$eq$colon$eq);
    Code:
       0: getstatic     #16                 // Field scala/compat/java8/FunctionConverters/package$.MODULE$:Lscala/compat/java8/FunctionConverters/package$;
       3: aload_0
       4: aload_1
       5: invokevirtual #306                // Method scala/compat/java8/FunctionConverters/package$.enrichAsJavaDoubleToIntFunction:(Lscala/Function1;Lscala/Predef$$eq$colon$eq;)Lscala/Function1;
       8: areturn

  public static scala.Function0 enrichAsJavaDoubleSupplier(scala.Function0);
    Code:
       0: getstatic     #16                 // Field scala/compat/java8/FunctionConverters/package$.MODULE$:Lscala/compat/java8/FunctionConverters/package$;
       3: aload_0
       4: invokevirtual #309                // Method scala/compat/java8/FunctionConverters/package$.enrichAsJavaDoubleSupplier:(Lscala/Function0;)Lscala/Function0;
       7: areturn

  public static scala.Function1 enrichAsJavaDoublePredicate(scala.Function1, scala.Predef$$eq$colon$eq);
    Code:
       0: getstatic     #16                 // Field scala/compat/java8/FunctionConverters/package$.MODULE$:Lscala/compat/java8/FunctionConverters/package$;
       3: aload_0
       4: aload_1
       5: invokevirtual #312                // Method scala/compat/java8/FunctionConverters/package$.enrichAsJavaDoublePredicate:(Lscala/Function1;Lscala/Predef$$eq$colon$eq;)Lscala/Function1;
       8: areturn

  public static scala.Function1 enrichAsJavaDoubleConsumer(scala.Function1, scala.Predef$$eq$colon$eq);
    Code:
       0: getstatic     #16                 // Field scala/compat/java8/FunctionConverters/package$.MODULE$:Lscala/compat/java8/FunctionConverters/package$;
       3: aload_0
       4: aload_1
       5: invokevirtual #315                // Method scala/compat/java8/FunctionConverters/package$.enrichAsJavaDoubleConsumer:(Lscala/Function1;Lscala/Predef$$eq$colon$eq;)Lscala/Function1;
       8: areturn

  public static scala.Function2 enrichAsJavaDoubleBinaryOperator(scala.Function2, scala.Predef$$eq$colon$eq, scala.Predef$$eq$colon$eq);
    Code:
       0: getstatic     #16                 // Field scala/compat/java8/FunctionConverters/package$.MODULE$:Lscala/compat/java8/FunctionConverters/package$;
       3: aload_0
       4: aload_1
       5: aload_2
       6: invokevirtual #318                // Method scala/compat/java8/FunctionConverters/package$.enrichAsJavaDoubleBinaryOperator:(Lscala/Function2;Lscala/Predef$$eq$colon$eq;Lscala/Predef$$eq$colon$eq;)Lscala/Function2;
       9: areturn

  public static scala.Function0 enrichAsJavaBooleanSupplier(scala.Function0);
    Code:
       0: getstatic     #16                 // Field scala/compat/java8/FunctionConverters/package$.MODULE$:Lscala/compat/java8/FunctionConverters/package$;
       3: aload_0
       4: invokevirtual #321                // Method scala/compat/java8/FunctionConverters/package$.enrichAsJavaBooleanSupplier:(Lscala/Function0;)Lscala/Function0;
       7: areturn

  public static <T> java.util.function.UnaryOperator<T> asJavaUnaryOperator(scala.Function1<T, T>);
    Code:
       0: getstatic     #16                 // Field scala/compat/java8/FunctionConverters/package$.MODULE$:Lscala/compat/java8/FunctionConverters/package$;
       3: aload_0
       4: invokevirtual #325                // Method scala/compat/java8/FunctionConverters/package$.asJavaUnaryOperator:(Lscala/Function1;)Ljava/util/function/UnaryOperator;
       7: areturn

  public static <T> scala.Function1<T, T> asScalaFromUnaryOperator(java.util.function.UnaryOperator<T>);
    Code:
       0: getstatic     #16                 // Field scala/compat/java8/FunctionConverters/package$.MODULE$:Lscala/compat/java8/FunctionConverters/package$;
       3: aload_0
       4: invokevirtual #329                // Method scala/compat/java8/FunctionConverters/package$.asScalaFromUnaryOperator:(Ljava/util/function/UnaryOperator;)Lscala/Function1;
       7: areturn

  public static <T> java.util.function.ToLongFunction<T> asJavaToLongFunction(scala.Function1<T, java.lang.Object>);
    Code:
       0: getstatic     #16                 // Field scala/compat/java8/FunctionConverters/package$.MODULE$:Lscala/compat/java8/FunctionConverters/package$;
       3: aload_0
       4: invokevirtual #333                // Method scala/compat/java8/FunctionConverters/package$.asJavaToLongFunction:(Lscala/Function1;)Ljava/util/function/ToLongFunction;
       7: areturn

  public static <T> scala.Function1<T, java.lang.Object> asScalaFromToLongFunction(java.util.function.ToLongFunction<T>);
    Code:
       0: getstatic     #16                 // Field scala/compat/java8/FunctionConverters/package$.MODULE$:Lscala/compat/java8/FunctionConverters/package$;
       3: aload_0
       4: invokevirtual #337                // Method scala/compat/java8/FunctionConverters/package$.asScalaFromToLongFunction:(Ljava/util/function/ToLongFunction;)Lscala/Function1;
       7: areturn

  public static <T, U> java.util.function.ToLongBiFunction<T, U> asJavaToLongBiFunction(scala.Function2<T, U, java.lang.Object>);
    Code:
       0: getstatic     #16                 // Field scala/compat/java8/FunctionConverters/package$.MODULE$:Lscala/compat/java8/FunctionConverters/package$;
       3: aload_0
       4: invokevirtual #341                // Method scala/compat/java8/FunctionConverters/package$.asJavaToLongBiFunction:(Lscala/Function2;)Ljava/util/function/ToLongBiFunction;
       7: areturn

  public static <T, U> scala.Function2<T, U, java.lang.Object> asScalaFromToLongBiFunction(java.util.function.ToLongBiFunction<T, U>);
    Code:
       0: getstatic     #16                 // Field scala/compat/java8/FunctionConverters/package$.MODULE$:Lscala/compat/java8/FunctionConverters/package$;
       3: aload_0
       4: invokevirtual #345                // Method scala/compat/java8/FunctionConverters/package$.asScalaFromToLongBiFunction:(Ljava/util/function/ToLongBiFunction;)Lscala/Function2;
       7: areturn

  public static <T> java.util.function.ToIntFunction<T> asJavaToIntFunction(scala.Function1<T, java.lang.Object>);
    Code:
       0: getstatic     #16                 // Field scala/compat/java8/FunctionConverters/package$.MODULE$:Lscala/compat/java8/FunctionConverters/package$;
       3: aload_0
       4: invokevirtual #349                // Method scala/compat/java8/FunctionConverters/package$.asJavaToIntFunction:(Lscala/Function1;)Ljava/util/function/ToIntFunction;
       7: areturn

  public static <T> scala.Function1<T, java.lang.Object> asScalaFromToIntFunction(java.util.function.ToIntFunction<T>);
    Code:
       0: getstatic     #16                 // Field scala/compat/java8/FunctionConverters/package$.MODULE$:Lscala/compat/java8/FunctionConverters/package$;
       3: aload_0
       4: invokevirtual #353                // Method scala/compat/java8/FunctionConverters/package$.asScalaFromToIntFunction:(Ljava/util/function/ToIntFunction;)Lscala/Function1;
       7: areturn

  public static <T, U> java.util.function.ToIntBiFunction<T, U> asJavaToIntBiFunction(scala.Function2<T, U, java.lang.Object>);
    Code:
       0: getstatic     #16                 // Field scala/compat/java8/FunctionConverters/package$.MODULE$:Lscala/compat/java8/FunctionConverters/package$;
       3: aload_0
       4: invokevirtual #357                // Method scala/compat/java8/FunctionConverters/package$.asJavaToIntBiFunction:(Lscala/Function2;)Ljava/util/function/ToIntBiFunction;
       7: areturn

  public static <T, U> scala.Function2<T, U, java.lang.Object> asScalaFromToIntBiFunction(java.util.function.ToIntBiFunction<T, U>);
    Code:
       0: getstatic     #16                 // Field scala/compat/java8/FunctionConverters/package$.MODULE$:Lscala/compat/java8/FunctionConverters/package$;
       3: aload_0
       4: invokevirtual #361                // Method scala/compat/java8/FunctionConverters/package$.asScalaFromToIntBiFunction:(Ljava/util/function/ToIntBiFunction;)Lscala/Function2;
       7: areturn

  public static <T> java.util.function.ToDoubleFunction<T> asJavaToDoubleFunction(scala.Function1<T, java.lang.Object>);
    Code:
       0: getstatic     #16                 // Field scala/compat/java8/FunctionConverters/package$.MODULE$:Lscala/compat/java8/FunctionConverters/package$;
       3: aload_0
       4: invokevirtual #365                // Method scala/compat/java8/FunctionConverters/package$.asJavaToDoubleFunction:(Lscala/Function1;)Ljava/util/function/ToDoubleFunction;
       7: areturn

  public static <T> scala.Function1<T, java.lang.Object> asScalaFromToDoubleFunction(java.util.function.ToDoubleFunction<T>);
    Code:
       0: getstatic     #16                 // Field scala/compat/java8/FunctionConverters/package$.MODULE$:Lscala/compat/java8/FunctionConverters/package$;
       3: aload_0
       4: invokevirtual #369                // Method scala/compat/java8/FunctionConverters/package$.asScalaFromToDoubleFunction:(Ljava/util/function/ToDoubleFunction;)Lscala/Function1;
       7: areturn

  public static <T, U> java.util.function.ToDoubleBiFunction<T, U> asJavaToDoubleBiFunction(scala.Function2<T, U, java.lang.Object>);
    Code:
       0: getstatic     #16                 // Field scala/compat/java8/FunctionConverters/package$.MODULE$:Lscala/compat/java8/FunctionConverters/package$;
       3: aload_0
       4: invokevirtual #373                // Method scala/compat/java8/FunctionConverters/package$.asJavaToDoubleBiFunction:(Lscala/Function2;)Ljava/util/function/ToDoubleBiFunction;
       7: areturn

  public static <T, U> scala.Function2<T, U, java.lang.Object> asScalaFromToDoubleBiFunction(java.util.function.ToDoubleBiFunction<T, U>);
    Code:
       0: getstatic     #16                 // Field scala/compat/java8/FunctionConverters/package$.MODULE$:Lscala/compat/java8/FunctionConverters/package$;
       3: aload_0
       4: invokevirtual #377                // Method scala/compat/java8/FunctionConverters/package$.asScalaFromToDoubleBiFunction:(Ljava/util/function/ToDoubleBiFunction;)Lscala/Function2;
       7: areturn

  public static <T> java.util.function.Supplier<T> asJavaSupplier(scala.Function0<T>);
    Code:
       0: getstatic     #16                 // Field scala/compat/java8/FunctionConverters/package$.MODULE$:Lscala/compat/java8/FunctionConverters/package$;
       3: aload_0
       4: invokevirtual #381                // Method scala/compat/java8/FunctionConverters/package$.asJavaSupplier:(Lscala/Function0;)Ljava/util/function/Supplier;
       7: areturn

  public static <T> scala.Function0<T> asScalaFromSupplier(java.util.function.Supplier<T>);
    Code:
       0: getstatic     #16                 // Field scala/compat/java8/FunctionConverters/package$.MODULE$:Lscala/compat/java8/FunctionConverters/package$;
       3: aload_0
       4: invokevirtual #385                // Method scala/compat/java8/FunctionConverters/package$.asScalaFromSupplier:(Ljava/util/function/Supplier;)Lscala/Function0;
       7: areturn

  public static <T> java.util.function.Predicate<T> asJavaPredicate(scala.Function1<T, java.lang.Object>);
    Code:
       0: getstatic     #16                 // Field scala/compat/java8/FunctionConverters/package$.MODULE$:Lscala/compat/java8/FunctionConverters/package$;
       3: aload_0
       4: invokevirtual #389                // Method scala/compat/java8/FunctionConverters/package$.asJavaPredicate:(Lscala/Function1;)Ljava/util/function/Predicate;
       7: areturn

  public static <T> scala.Function1<T, java.lang.Object> asScalaFromPredicate(java.util.function.Predicate<T>);
    Code:
       0: getstatic     #16                 // Field scala/compat/java8/FunctionConverters/package$.MODULE$:Lscala/compat/java8/FunctionConverters/package$;
       3: aload_0
       4: invokevirtual #393                // Method scala/compat/java8/FunctionConverters/package$.asScalaFromPredicate:(Ljava/util/function/Predicate;)Lscala/Function1;
       7: areturn

  public static <T> java.util.function.ObjLongConsumer<T> asJavaObjLongConsumer(scala.Function2<T, java.lang.Object, scala.runtime.BoxedUnit>);
    Code:
       0: getstatic     #16                 // Field scala/compat/java8/FunctionConverters/package$.MODULE$:Lscala/compat/java8/FunctionConverters/package$;
       3: aload_0
       4: invokevirtual #397                // Method scala/compat/java8/FunctionConverters/package$.asJavaObjLongConsumer:(Lscala/Function2;)Ljava/util/function/ObjLongConsumer;
       7: areturn

  public static <T> scala.Function2<T, java.lang.Object, scala.runtime.BoxedUnit> asScalaFromObjLongConsumer(java.util.function.ObjLongConsumer<T>);
    Code:
       0: getstatic     #16                 // Field scala/compat/java8/FunctionConverters/package$.MODULE$:Lscala/compat/java8/FunctionConverters/package$;
       3: aload_0
       4: invokevirtual #401                // Method scala/compat/java8/FunctionConverters/package$.asScalaFromObjLongConsumer:(Ljava/util/function/ObjLongConsumer;)Lscala/Function2;
       7: areturn

  public static <T> java.util.function.ObjIntConsumer<T> asJavaObjIntConsumer(scala.Function2<T, java.lang.Object, scala.runtime.BoxedUnit>);
    Code:
       0: getstatic     #16                 // Field scala/compat/java8/FunctionConverters/package$.MODULE$:Lscala/compat/java8/FunctionConverters/package$;
       3: aload_0
       4: invokevirtual #405                // Method scala/compat/java8/FunctionConverters/package$.asJavaObjIntConsumer:(Lscala/Function2;)Ljava/util/function/ObjIntConsumer;
       7: areturn

  public static <T> scala.Function2<T, java.lang.Object, scala.runtime.BoxedUnit> asScalaFromObjIntConsumer(java.util.function.ObjIntConsumer<T>);
    Code:
       0: getstatic     #16                 // Field scala/compat/java8/FunctionConverters/package$.MODULE$:Lscala/compat/java8/FunctionConverters/package$;
       3: aload_0
       4: invokevirtual #409                // Method scala/compat/java8/FunctionConverters/package$.asScalaFromObjIntConsumer:(Ljava/util/function/ObjIntConsumer;)Lscala/Function2;
       7: areturn

  public static <T> java.util.function.ObjDoubleConsumer<T> asJavaObjDoubleConsumer(scala.Function2<T, java.lang.Object, scala.runtime.BoxedUnit>);
    Code:
       0: getstatic     #16                 // Field scala/compat/java8/FunctionConverters/package$.MODULE$:Lscala/compat/java8/FunctionConverters/package$;
       3: aload_0
       4: invokevirtual #413                // Method scala/compat/java8/FunctionConverters/package$.asJavaObjDoubleConsumer:(Lscala/Function2;)Ljava/util/function/ObjDoubleConsumer;
       7: areturn

  public static <T> scala.Function2<T, java.lang.Object, scala.runtime.BoxedUnit> asScalaFromObjDoubleConsumer(java.util.function.ObjDoubleConsumer<T>);
    Code:
       0: getstatic     #16                 // Field scala/compat/java8/FunctionConverters/package$.MODULE$:Lscala/compat/java8/FunctionConverters/package$;
       3: aload_0
       4: invokevirtual #417                // Method scala/compat/java8/FunctionConverters/package$.asScalaFromObjDoubleConsumer:(Ljava/util/function/ObjDoubleConsumer;)Lscala/Function2;
       7: areturn

  public static java.util.function.LongUnaryOperator asJavaLongUnaryOperator(scala.Function1<java.lang.Object, java.lang.Object>);
    Code:
       0: getstatic     #16                 // Field scala/compat/java8/FunctionConverters/package$.MODULE$:Lscala/compat/java8/FunctionConverters/package$;
       3: aload_0
       4: invokevirtual #421                // Method scala/compat/java8/FunctionConverters/package$.asJavaLongUnaryOperator:(Lscala/Function1;)Ljava/util/function/LongUnaryOperator;
       7: areturn

  public static scala.Function1<java.lang.Object, java.lang.Object> asScalaFromLongUnaryOperator(java.util.function.LongUnaryOperator);
    Code:
       0: getstatic     #16                 // Field scala/compat/java8/FunctionConverters/package$.MODULE$:Lscala/compat/java8/FunctionConverters/package$;
       3: aload_0
       4: invokevirtual #425                // Method scala/compat/java8/FunctionConverters/package$.asScalaFromLongUnaryOperator:(Ljava/util/function/LongUnaryOperator;)Lscala/Function1;
       7: areturn

  public static java.util.function.LongToIntFunction asJavaLongToIntFunction(scala.Function1<java.lang.Object, java.lang.Object>);
    Code:
       0: getstatic     #16                 // Field scala/compat/java8/FunctionConverters/package$.MODULE$:Lscala/compat/java8/FunctionConverters/package$;
       3: aload_0
       4: invokevirtual #429                // Method scala/compat/java8/FunctionConverters/package$.asJavaLongToIntFunction:(Lscala/Function1;)Ljava/util/function/LongToIntFunction;
       7: areturn

  public static scala.Function1<java.lang.Object, java.lang.Object> asScalaFromLongToIntFunction(java.util.function.LongToIntFunction);
    Code:
       0: getstatic     #16                 // Field scala/compat/java8/FunctionConverters/package$.MODULE$:Lscala/compat/java8/FunctionConverters/package$;
       3: aload_0
       4: invokevirtual #433                // Method scala/compat/java8/FunctionConverters/package$.asScalaFromLongToIntFunction:(Ljava/util/function/LongToIntFunction;)Lscala/Function1;
       7: areturn

  public static java.util.function.LongToDoubleFunction asJavaLongToDoubleFunction(scala.Function1<java.lang.Object, java.lang.Object>);
    Code:
       0: getstatic     #16                 // Field scala/compat/java8/FunctionConverters/package$.MODULE$:Lscala/compat/java8/FunctionConverters/package$;
       3: aload_0
       4: invokevirtual #437                // Method scala/compat/java8/FunctionConverters/package$.asJavaLongToDoubleFunction:(Lscala/Function1;)Ljava/util/function/LongToDoubleFunction;
       7: areturn

  public static scala.Function1<java.lang.Object, java.lang.Object> asScalaFromLongToDoubleFunction(java.util.function.LongToDoubleFunction);
    Code:
       0: getstatic     #16                 // Field scala/compat/java8/FunctionConverters/package$.MODULE$:Lscala/compat/java8/FunctionConverters/package$;
       3: aload_0
       4: invokevirtual #441                // Method scala/compat/java8/FunctionConverters/package$.asScalaFromLongToDoubleFunction:(Ljava/util/function/LongToDoubleFunction;)Lscala/Function1;
       7: areturn

  public static java.util.function.LongSupplier asJavaLongSupplier(scala.Function0<java.lang.Object>);
    Code:
       0: getstatic     #16                 // Field scala/compat/java8/FunctionConverters/package$.MODULE$:Lscala/compat/java8/FunctionConverters/package$;
       3: aload_0
       4: invokevirtual #445                // Method scala/compat/java8/FunctionConverters/package$.asJavaLongSupplier:(Lscala/Function0;)Ljava/util/function/LongSupplier;
       7: areturn

  public static scala.Function0<java.lang.Object> asScalaFromLongSupplier(java.util.function.LongSupplier);
    Code:
       0: getstatic     #16                 // Field scala/compat/java8/FunctionConverters/package$.MODULE$:Lscala/compat/java8/FunctionConverters/package$;
       3: aload_0
       4: invokevirtual #449                // Method scala/compat/java8/FunctionConverters/package$.asScalaFromLongSupplier:(Ljava/util/function/LongSupplier;)Lscala/Function0;
       7: areturn

  public static java.util.function.LongPredicate asJavaLongPredicate(scala.Function1<java.lang.Object, java.lang.Object>);
    Code:
       0: getstatic     #16                 // Field scala/compat/java8/FunctionConverters/package$.MODULE$:Lscala/compat/java8/FunctionConverters/package$;
       3: aload_0
       4: invokevirtual #453                // Method scala/compat/java8/FunctionConverters/package$.asJavaLongPredicate:(Lscala/Function1;)Ljava/util/function/LongPredicate;
       7: areturn

  public static scala.Function1<java.lang.Object, java.lang.Object> asScalaFromLongPredicate(java.util.function.LongPredicate);
    Code:
       0: getstatic     #16                 // Field scala/compat/java8/FunctionConverters/package$.MODULE$:Lscala/compat/java8/FunctionConverters/package$;
       3: aload_0
       4: invokevirtual #457                // Method scala/compat/java8/FunctionConverters/package$.asScalaFromLongPredicate:(Ljava/util/function/LongPredicate;)Lscala/Function1;
       7: areturn

  public static <R> java.util.function.LongFunction<R> asJavaLongFunction(scala.Function1<java.lang.Object, R>);
    Code:
       0: getstatic     #16                 // Field scala/compat/java8/FunctionConverters/package$.MODULE$:Lscala/compat/java8/FunctionConverters/package$;
       3: aload_0
       4: invokevirtual #461                // Method scala/compat/java8/FunctionConverters/package$.asJavaLongFunction:(Lscala/Function1;)Ljava/util/function/LongFunction;
       7: areturn

  public static <R> scala.Function1<java.lang.Object, R> asScalaFromLongFunction(java.util.function.LongFunction<R>);
    Code:
       0: getstatic     #16                 // Field scala/compat/java8/FunctionConverters/package$.MODULE$:Lscala/compat/java8/FunctionConverters/package$;
       3: aload_0
       4: invokevirtual #465                // Method scala/compat/java8/FunctionConverters/package$.asScalaFromLongFunction:(Ljava/util/function/LongFunction;)Lscala/Function1;
       7: areturn

  public static java.util.function.LongConsumer asJavaLongConsumer(scala.Function1<java.lang.Object, scala.runtime.BoxedUnit>);
    Code:
       0: getstatic     #16                 // Field scala/compat/java8/FunctionConverters/package$.MODULE$:Lscala/compat/java8/FunctionConverters/package$;
       3: aload_0
       4: invokevirtual #469                // Method scala/compat/java8/FunctionConverters/package$.asJavaLongConsumer:(Lscala/Function1;)Ljava/util/function/LongConsumer;
       7: areturn

  public static scala.Function1<java.lang.Object, scala.runtime.BoxedUnit> asScalaFromLongConsumer(java.util.function.LongConsumer);
    Code:
       0: getstatic     #16                 // Field scala/compat/java8/FunctionConverters/package$.MODULE$:Lscala/compat/java8/FunctionConverters/package$;
       3: aload_0
       4: invokevirtual #473                // Method scala/compat/java8/FunctionConverters/package$.asScalaFromLongConsumer:(Ljava/util/function/LongConsumer;)Lscala/Function1;
       7: areturn

  public static java.util.function.LongBinaryOperator asJavaLongBinaryOperator(scala.Function2<java.lang.Object, java.lang.Object, java.lang.Object>);
    Code:
       0: getstatic     #16                 // Field scala/compat/java8/FunctionConverters/package$.MODULE$:Lscala/compat/java8/FunctionConverters/package$;
       3: aload_0
       4: invokevirtual #477                // Method scala/compat/java8/FunctionConverters/package$.asJavaLongBinaryOperator:(Lscala/Function2;)Ljava/util/function/LongBinaryOperator;
       7: areturn

  public static scala.Function2<java.lang.Object, java.lang.Object, java.lang.Object> asScalaFromLongBinaryOperator(java.util.function.LongBinaryOperator);
    Code:
       0: getstatic     #16                 // Field scala/compat/java8/FunctionConverters/package$.MODULE$:Lscala/compat/java8/FunctionConverters/package$;
       3: aload_0
       4: invokevirtual #481                // Method scala/compat/java8/FunctionConverters/package$.asScalaFromLongBinaryOperator:(Ljava/util/function/LongBinaryOperator;)Lscala/Function2;
       7: areturn

  public static java.util.function.IntUnaryOperator asJavaIntUnaryOperator(scala.Function1<java.lang.Object, java.lang.Object>);
    Code:
       0: getstatic     #16                 // Field scala/compat/java8/FunctionConverters/package$.MODULE$:Lscala/compat/java8/FunctionConverters/package$;
       3: aload_0
       4: invokevirtual #485                // Method scala/compat/java8/FunctionConverters/package$.asJavaIntUnaryOperator:(Lscala/Function1;)Ljava/util/function/IntUnaryOperator;
       7: areturn

  public static scala.Function1<java.lang.Object, java.lang.Object> asScalaFromIntUnaryOperator(java.util.function.IntUnaryOperator);
    Code:
       0: getstatic     #16                 // Field scala/compat/java8/FunctionConverters/package$.MODULE$:Lscala/compat/java8/FunctionConverters/package$;
       3: aload_0
       4: invokevirtual #489                // Method scala/compat/java8/FunctionConverters/package$.asScalaFromIntUnaryOperator:(Ljava/util/function/IntUnaryOperator;)Lscala/Function1;
       7: areturn

  public static java.util.function.IntToLongFunction asJavaIntToLongFunction(scala.Function1<java.lang.Object, java.lang.Object>);
    Code:
       0: getstatic     #16                 // Field scala/compat/java8/FunctionConverters/package$.MODULE$:Lscala/compat/java8/FunctionConverters/package$;
       3: aload_0
       4: invokevirtual #493                // Method scala/compat/java8/FunctionConverters/package$.asJavaIntToLongFunction:(Lscala/Function1;)Ljava/util/function/IntToLongFunction;
       7: areturn

  public static scala.Function1<java.lang.Object, java.lang.Object> asScalaFromIntToLongFunction(java.util.function.IntToLongFunction);
    Code:
       0: getstatic     #16                 // Field scala/compat/java8/FunctionConverters/package$.MODULE$:Lscala/compat/java8/FunctionConverters/package$;
       3: aload_0
       4: invokevirtual #497                // Method scala/compat/java8/FunctionConverters/package$.asScalaFromIntToLongFunction:(Ljava/util/function/IntToLongFunction;)Lscala/Function1;
       7: areturn

  public static java.util.function.IntToDoubleFunction asJavaIntToDoubleFunction(scala.Function1<java.lang.Object, java.lang.Object>);
    Code:
       0: getstatic     #16                 // Field scala/compat/java8/FunctionConverters/package$.MODULE$:Lscala/compat/java8/FunctionConverters/package$;
       3: aload_0
       4: invokevirtual #501                // Method scala/compat/java8/FunctionConverters/package$.asJavaIntToDoubleFunction:(Lscala/Function1;)Ljava/util/function/IntToDoubleFunction;
       7: areturn

  public static scala.Function1<java.lang.Object, java.lang.Object> asScalaFromIntToDoubleFunction(java.util.function.IntToDoubleFunction);
    Code:
       0: getstatic     #16                 // Field scala/compat/java8/FunctionConverters/package$.MODULE$:Lscala/compat/java8/FunctionConverters/package$;
       3: aload_0
       4: invokevirtual #505                // Method scala/compat/java8/FunctionConverters/package$.asScalaFromIntToDoubleFunction:(Ljava/util/function/IntToDoubleFunction;)Lscala/Function1;
       7: areturn

  public static java.util.function.IntSupplier asJavaIntSupplier(scala.Function0<java.lang.Object>);
    Code:
       0: getstatic     #16                 // Field scala/compat/java8/FunctionConverters/package$.MODULE$:Lscala/compat/java8/FunctionConverters/package$;
       3: aload_0
       4: invokevirtual #509                // Method scala/compat/java8/FunctionConverters/package$.asJavaIntSupplier:(Lscala/Function0;)Ljava/util/function/IntSupplier;
       7: areturn

  public static scala.Function0<java.lang.Object> asScalaFromIntSupplier(java.util.function.IntSupplier);
    Code:
       0: getstatic     #16                 // Field scala/compat/java8/FunctionConverters/package$.MODULE$:Lscala/compat/java8/FunctionConverters/package$;
       3: aload_0
       4: invokevirtual #513                // Method scala/compat/java8/FunctionConverters/package$.asScalaFromIntSupplier:(Ljava/util/function/IntSupplier;)Lscala/Function0;
       7: areturn

  public static java.util.function.IntPredicate asJavaIntPredicate(scala.Function1<java.lang.Object, java.lang.Object>);
    Code:
       0: getstatic     #16                 // Field scala/compat/java8/FunctionConverters/package$.MODULE$:Lscala/compat/java8/FunctionConverters/package$;
       3: aload_0
       4: invokevirtual #517                // Method scala/compat/java8/FunctionConverters/package$.asJavaIntPredicate:(Lscala/Function1;)Ljava/util/function/IntPredicate;
       7: areturn

  public static scala.Function1<java.lang.Object, java.lang.Object> asScalaFromIntPredicate(java.util.function.IntPredicate);
    Code:
       0: getstatic     #16                 // Field scala/compat/java8/FunctionConverters/package$.MODULE$:Lscala/compat/java8/FunctionConverters/package$;
       3: aload_0
       4: invokevirtual #521                // Method scala/compat/java8/FunctionConverters/package$.asScalaFromIntPredicate:(Ljava/util/function/IntPredicate;)Lscala/Function1;
       7: areturn

  public static <R> java.util.function.IntFunction<R> asJavaIntFunction(scala.Function1<java.lang.Object, R>);
    Code:
       0: getstatic     #16                 // Field scala/compat/java8/FunctionConverters/package$.MODULE$:Lscala/compat/java8/FunctionConverters/package$;
       3: aload_0
       4: invokevirtual #525                // Method scala/compat/java8/FunctionConverters/package$.asJavaIntFunction:(Lscala/Function1;)Ljava/util/function/IntFunction;
       7: areturn

  public static <R> scala.Function1<java.lang.Object, R> asScalaFromIntFunction(java.util.function.IntFunction<R>);
    Code:
       0: getstatic     #16                 // Field scala/compat/java8/FunctionConverters/package$.MODULE$:Lscala/compat/java8/FunctionConverters/package$;
       3: aload_0
       4: invokevirtual #529                // Method scala/compat/java8/FunctionConverters/package$.asScalaFromIntFunction:(Ljava/util/function/IntFunction;)Lscala/Function1;
       7: areturn

  public static java.util.function.IntConsumer asJavaIntConsumer(scala.Function1<java.lang.Object, scala.runtime.BoxedUnit>);
    Code:
       0: getstatic     #16                 // Field scala/compat/java8/FunctionConverters/package$.MODULE$:Lscala/compat/java8/FunctionConverters/package$;
       3: aload_0
       4: invokevirtual #533                // Method scala/compat/java8/FunctionConverters/package$.asJavaIntConsumer:(Lscala/Function1;)Ljava/util/function/IntConsumer;
       7: areturn

  public static scala.Function1<java.lang.Object, scala.runtime.BoxedUnit> asScalaFromIntConsumer(java.util.function.IntConsumer);
    Code:
       0: getstatic     #16                 // Field scala/compat/java8/FunctionConverters/package$.MODULE$:Lscala/compat/java8/FunctionConverters/package$;
       3: aload_0
       4: invokevirtual #537                // Method scala/compat/java8/FunctionConverters/package$.asScalaFromIntConsumer:(Ljava/util/function/IntConsumer;)Lscala/Function1;
       7: areturn

  public static java.util.function.IntBinaryOperator asJavaIntBinaryOperator(scala.Function2<java.lang.Object, java.lang.Object, java.lang.Object>);
    Code:
       0: getstatic     #16                 // Field scala/compat/java8/FunctionConverters/package$.MODULE$:Lscala/compat/java8/FunctionConverters/package$;
       3: aload_0
       4: invokevirtual #541                // Method scala/compat/java8/FunctionConverters/package$.asJavaIntBinaryOperator:(Lscala/Function2;)Ljava/util/function/IntBinaryOperator;
       7: areturn

  public static scala.Function2<java.lang.Object, java.lang.Object, java.lang.Object> asScalaFromIntBinaryOperator(java.util.function.IntBinaryOperator);
    Code:
       0: getstatic     #16                 // Field scala/compat/java8/FunctionConverters/package$.MODULE$:Lscala/compat/java8/FunctionConverters/package$;
       3: aload_0
       4: invokevirtual #545                // Method scala/compat/java8/FunctionConverters/package$.asScalaFromIntBinaryOperator:(Ljava/util/function/IntBinaryOperator;)Lscala/Function2;
       7: areturn

  public static <T, R> java.util.function.Function<T, R> asJavaFunction(scala.Function1<T, R>);
    Code:
       0: getstatic     #16                 // Field scala/compat/java8/FunctionConverters/package$.MODULE$:Lscala/compat/java8/FunctionConverters/package$;
       3: aload_0
       4: invokevirtual #549                // Method scala/compat/java8/FunctionConverters/package$.asJavaFunction:(Lscala/Function1;)Ljava/util/function/Function;
       7: areturn

  public static <T, R> scala.Function1<T, R> asScalaFromFunction(java.util.function.Function<T, R>);
    Code:
       0: getstatic     #16                 // Field scala/compat/java8/FunctionConverters/package$.MODULE$:Lscala/compat/java8/FunctionConverters/package$;
       3: aload_0
       4: invokevirtual #553                // Method scala/compat/java8/FunctionConverters/package$.asScalaFromFunction:(Ljava/util/function/Function;)Lscala/Function1;
       7: areturn

  public static java.util.function.DoubleUnaryOperator asJavaDoubleUnaryOperator(scala.Function1<java.lang.Object, java.lang.Object>);
    Code:
       0: getstatic     #16                 // Field scala/compat/java8/FunctionConverters/package$.MODULE$:Lscala/compat/java8/FunctionConverters/package$;
       3: aload_0
       4: invokevirtual #557                // Method scala/compat/java8/FunctionConverters/package$.asJavaDoubleUnaryOperator:(Lscala/Function1;)Ljava/util/function/DoubleUnaryOperator;
       7: areturn

  public static scala.Function1<java.lang.Object, java.lang.Object> asScalaFromDoubleUnaryOperator(java.util.function.DoubleUnaryOperator);
    Code:
       0: getstatic     #16                 // Field scala/compat/java8/FunctionConverters/package$.MODULE$:Lscala/compat/java8/FunctionConverters/package$;
       3: aload_0
       4: invokevirtual #561                // Method scala/compat/java8/FunctionConverters/package$.asScalaFromDoubleUnaryOperator:(Ljava/util/function/DoubleUnaryOperator;)Lscala/Function1;
       7: areturn

  public static java.util.function.DoubleToLongFunction asJavaDoubleToLongFunction(scala.Function1<java.lang.Object, java.lang.Object>);
    Code:
       0: getstatic     #16                 // Field scala/compat/java8/FunctionConverters/package$.MODULE$:Lscala/compat/java8/FunctionConverters/package$;
       3: aload_0
       4: invokevirtual #565                // Method scala/compat/java8/FunctionConverters/package$.asJavaDoubleToLongFunction:(Lscala/Function1;)Ljava/util/function/DoubleToLongFunction;
       7: areturn

  public static scala.Function1<java.lang.Object, java.lang.Object> asScalaFromDoubleToLongFunction(java.util.function.DoubleToLongFunction);
    Code:
       0: getstatic     #16                 // Field scala/compat/java8/FunctionConverters/package$.MODULE$:Lscala/compat/java8/FunctionConverters/package$;
       3: aload_0
       4: invokevirtual #569                // Method scala/compat/java8/FunctionConverters/package$.asScalaFromDoubleToLongFunction:(Ljava/util/function/DoubleToLongFunction;)Lscala/Function1;
       7: areturn

  public static java.util.function.DoubleToIntFunction asJavaDoubleToIntFunction(scala.Function1<java.lang.Object, java.lang.Object>);
    Code:
       0: getstatic     #16                 // Field scala/compat/java8/FunctionConverters/package$.MODULE$:Lscala/compat/java8/FunctionConverters/package$;
       3: aload_0
       4: invokevirtual #573                // Method scala/compat/java8/FunctionConverters/package$.asJavaDoubleToIntFunction:(Lscala/Function1;)Ljava/util/function/DoubleToIntFunction;
       7: areturn

  public static scala.Function1<java.lang.Object, java.lang.Object> asScalaFromDoubleToIntFunction(java.util.function.DoubleToIntFunction);
    Code:
       0: getstatic     #16                 // Field scala/compat/java8/FunctionConverters/package$.MODULE$:Lscala/compat/java8/FunctionConverters/package$;
       3: aload_0
       4: invokevirtual #577                // Method scala/compat/java8/FunctionConverters/package$.asScalaFromDoubleToIntFunction:(Ljava/util/function/DoubleToIntFunction;)Lscala/Function1;
       7: areturn

  public static java.util.function.DoubleSupplier asJavaDoubleSupplier(scala.Function0<java.lang.Object>);
    Code:
       0: getstatic     #16                 // Field scala/compat/java8/FunctionConverters/package$.MODULE$:Lscala/compat/java8/FunctionConverters/package$;
       3: aload_0
       4: invokevirtual #581                // Method scala/compat/java8/FunctionConverters/package$.asJavaDoubleSupplier:(Lscala/Function0;)Ljava/util/function/DoubleSupplier;
       7: areturn

  public static scala.Function0<java.lang.Object> asScalaFromDoubleSupplier(java.util.function.DoubleSupplier);
    Code:
       0: getstatic     #16                 // Field scala/compat/java8/FunctionConverters/package$.MODULE$:Lscala/compat/java8/FunctionConverters/package$;
       3: aload_0
       4: invokevirtual #585                // Method scala/compat/java8/FunctionConverters/package$.asScalaFromDoubleSupplier:(Ljava/util/function/DoubleSupplier;)Lscala/Function0;
       7: areturn

  public static java.util.function.DoublePredicate asJavaDoublePredicate(scala.Function1<java.lang.Object, java.lang.Object>);
    Code:
       0: getstatic     #16                 // Field scala/compat/java8/FunctionConverters/package$.MODULE$:Lscala/compat/java8/FunctionConverters/package$;
       3: aload_0
       4: invokevirtual #589                // Method scala/compat/java8/FunctionConverters/package$.asJavaDoublePredicate:(Lscala/Function1;)Ljava/util/function/DoublePredicate;
       7: areturn

  public static scala.Function1<java.lang.Object, java.lang.Object> asScalaFromDoublePredicate(java.util.function.DoublePredicate);
    Code:
       0: getstatic     #16                 // Field scala/compat/java8/FunctionConverters/package$.MODULE$:Lscala/compat/java8/FunctionConverters/package$;
       3: aload_0
       4: invokevirtual #593                // Method scala/compat/java8/FunctionConverters/package$.asScalaFromDoublePredicate:(Ljava/util/function/DoublePredicate;)Lscala/Function1;
       7: areturn

  public static <R> java.util.function.DoubleFunction<R> asJavaDoubleFunction(scala.Function1<java.lang.Object, R>);
    Code:
       0: getstatic     #16                 // Field scala/compat/java8/FunctionConverters/package$.MODULE$:Lscala/compat/java8/FunctionConverters/package$;
       3: aload_0
       4: invokevirtual #597                // Method scala/compat/java8/FunctionConverters/package$.asJavaDoubleFunction:(Lscala/Function1;)Ljava/util/function/DoubleFunction;
       7: areturn

  public static <R> scala.Function1<java.lang.Object, R> asScalaFromDoubleFunction(java.util.function.DoubleFunction<R>);
    Code:
       0: getstatic     #16                 // Field scala/compat/java8/FunctionConverters/package$.MODULE$:Lscala/compat/java8/FunctionConverters/package$;
       3: aload_0
       4: invokevirtual #601                // Method scala/compat/java8/FunctionConverters/package$.asScalaFromDoubleFunction:(Ljava/util/function/DoubleFunction;)Lscala/Function1;
       7: areturn

  public static java.util.function.DoubleConsumer asJavaDoubleConsumer(scala.Function1<java.lang.Object, scala.runtime.BoxedUnit>);
    Code:
       0: getstatic     #16                 // Field scala/compat/java8/FunctionConverters/package$.MODULE$:Lscala/compat/java8/FunctionConverters/package$;
       3: aload_0
       4: invokevirtual #605                // Method scala/compat/java8/FunctionConverters/package$.asJavaDoubleConsumer:(Lscala/Function1;)Ljava/util/function/DoubleConsumer;
       7: areturn

  public static scala.Function1<java.lang.Object, scala.runtime.BoxedUnit> asScalaFromDoubleConsumer(java.util.function.DoubleConsumer);
    Code:
       0: getstatic     #16                 // Field scala/compat/java8/FunctionConverters/package$.MODULE$:Lscala/compat/java8/FunctionConverters/package$;
       3: aload_0
       4: invokevirtual #609                // Method scala/compat/java8/FunctionConverters/package$.asScalaFromDoubleConsumer:(Ljava/util/function/DoubleConsumer;)Lscala/Function1;
       7: areturn

  public static java.util.function.DoubleBinaryOperator asJavaDoubleBinaryOperator(scala.Function2<java.lang.Object, java.lang.Object, java.lang.Object>);
    Code:
       0: getstatic     #16                 // Field scala/compat/java8/FunctionConverters/package$.MODULE$:Lscala/compat/java8/FunctionConverters/package$;
       3: aload_0
       4: invokevirtual #613                // Method scala/compat/java8/FunctionConverters/package$.asJavaDoubleBinaryOperator:(Lscala/Function2;)Ljava/util/function/DoubleBinaryOperator;
       7: areturn

  public static scala.Function2<java.lang.Object, java.lang.Object, java.lang.Object> asScalaFromDoubleBinaryOperator(java.util.function.DoubleBinaryOperator);
    Code:
       0: getstatic     #16                 // Field scala/compat/java8/FunctionConverters/package$.MODULE$:Lscala/compat/java8/FunctionConverters/package$;
       3: aload_0
       4: invokevirtual #617                // Method scala/compat/java8/FunctionConverters/package$.asScalaFromDoubleBinaryOperator:(Ljava/util/function/DoubleBinaryOperator;)Lscala/Function2;
       7: areturn

  public static <T> java.util.function.Consumer<T> asJavaConsumer(scala.Function1<T, scala.runtime.BoxedUnit>);
    Code:
       0: getstatic     #16                 // Field scala/compat/java8/FunctionConverters/package$.MODULE$:Lscala/compat/java8/FunctionConverters/package$;
       3: aload_0
       4: invokevirtual #621                // Method scala/compat/java8/FunctionConverters/package$.asJavaConsumer:(Lscala/Function1;)Ljava/util/function/Consumer;
       7: areturn

  public static <T> scala.Function1<T, scala.runtime.BoxedUnit> asScalaFromConsumer(java.util.function.Consumer<T>);
    Code:
       0: getstatic     #16                 // Field scala/compat/java8/FunctionConverters/package$.MODULE$:Lscala/compat/java8/FunctionConverters/package$;
       3: aload_0
       4: invokevirtual #625                // Method scala/compat/java8/FunctionConverters/package$.asScalaFromConsumer:(Ljava/util/function/Consumer;)Lscala/Function1;
       7: areturn

  public static java.util.function.BooleanSupplier asJavaBooleanSupplier(scala.Function0<java.lang.Object>);
    Code:
       0: getstatic     #16                 // Field scala/compat/java8/FunctionConverters/package$.MODULE$:Lscala/compat/java8/FunctionConverters/package$;
       3: aload_0
       4: invokevirtual #629                // Method scala/compat/java8/FunctionConverters/package$.asJavaBooleanSupplier:(Lscala/Function0;)Ljava/util/function/BooleanSupplier;
       7: areturn

  public static scala.Function0<java.lang.Object> asScalaFromBooleanSupplier(java.util.function.BooleanSupplier);
    Code:
       0: getstatic     #16                 // Field scala/compat/java8/FunctionConverters/package$.MODULE$:Lscala/compat/java8/FunctionConverters/package$;
       3: aload_0
       4: invokevirtual #633                // Method scala/compat/java8/FunctionConverters/package$.asScalaFromBooleanSupplier:(Ljava/util/function/BooleanSupplier;)Lscala/Function0;
       7: areturn

  public static <T> java.util.function.BinaryOperator<T> asJavaBinaryOperator(scala.Function2<T, T, T>);
    Code:
       0: getstatic     #16                 // Field scala/compat/java8/FunctionConverters/package$.MODULE$:Lscala/compat/java8/FunctionConverters/package$;
       3: aload_0
       4: invokevirtual #637                // Method scala/compat/java8/FunctionConverters/package$.asJavaBinaryOperator:(Lscala/Function2;)Ljava/util/function/BinaryOperator;
       7: areturn

  public static <T> scala.Function2<T, T, T> asScalaFromBinaryOperator(java.util.function.BinaryOperator<T>);
    Code:
       0: getstatic     #16                 // Field scala/compat/java8/FunctionConverters/package$.MODULE$:Lscala/compat/java8/FunctionConverters/package$;
       3: aload_0
       4: invokevirtual #641                // Method scala/compat/java8/FunctionConverters/package$.asScalaFromBinaryOperator:(Ljava/util/function/BinaryOperator;)Lscala/Function2;
       7: areturn

  public static <T, U> java.util.function.BiPredicate<T, U> asJavaBiPredicate(scala.Function2<T, U, java.lang.Object>);
    Code:
       0: getstatic     #16                 // Field scala/compat/java8/FunctionConverters/package$.MODULE$:Lscala/compat/java8/FunctionConverters/package$;
       3: aload_0
       4: invokevirtual #645                // Method scala/compat/java8/FunctionConverters/package$.asJavaBiPredicate:(Lscala/Function2;)Ljava/util/function/BiPredicate;
       7: areturn

  public static <T, U> scala.Function2<T, U, java.lang.Object> asScalaFromBiPredicate(java.util.function.BiPredicate<T, U>);
    Code:
       0: getstatic     #16                 // Field scala/compat/java8/FunctionConverters/package$.MODULE$:Lscala/compat/java8/FunctionConverters/package$;
       3: aload_0
       4: invokevirtual #649                // Method scala/compat/java8/FunctionConverters/package$.asScalaFromBiPredicate:(Ljava/util/function/BiPredicate;)Lscala/Function2;
       7: areturn

  public static <T, U, R> java.util.function.BiFunction<T, U, R> asJavaBiFunction(scala.Function2<T, U, R>);
    Code:
       0: getstatic     #16                 // Field scala/compat/java8/FunctionConverters/package$.MODULE$:Lscala/compat/java8/FunctionConverters/package$;
       3: aload_0
       4: invokevirtual #653                // Method scala/compat/java8/FunctionConverters/package$.asJavaBiFunction:(Lscala/Function2;)Ljava/util/function/BiFunction;
       7: areturn

  public static <T, U, R> scala.Function2<T, U, R> asScalaFromBiFunction(java.util.function.BiFunction<T, U, R>);
    Code:
       0: getstatic     #16                 // Field scala/compat/java8/FunctionConverters/package$.MODULE$:Lscala/compat/java8/FunctionConverters/package$;
       3: aload_0
       4: invokevirtual #657                // Method scala/compat/java8/FunctionConverters/package$.asScalaFromBiFunction:(Ljava/util/function/BiFunction;)Lscala/Function2;
       7: areturn

  public static <T, U> java.util.function.BiConsumer<T, U> asJavaBiConsumer(scala.Function2<T, U, scala.runtime.BoxedUnit>);
    Code:
       0: getstatic     #16                 // Field scala/compat/java8/FunctionConverters/package$.MODULE$:Lscala/compat/java8/FunctionConverters/package$;
       3: aload_0
       4: invokevirtual #661                // Method scala/compat/java8/FunctionConverters/package$.asJavaBiConsumer:(Lscala/Function2;)Ljava/util/function/BiConsumer;
       7: areturn

  public static <T, U> scala.Function2<T, U, scala.runtime.BoxedUnit> asScalaFromBiConsumer(java.util.function.BiConsumer<T, U>);
    Code:
       0: getstatic     #16                 // Field scala/compat/java8/FunctionConverters/package$.MODULE$:Lscala/compat/java8/FunctionConverters/package$;
       3: aload_0
       4: invokevirtual #665                // Method scala/compat/java8/FunctionConverters/package$.asScalaFromBiConsumer:(Ljava/util/function/BiConsumer;)Lscala/Function2;
       7: areturn
}
