Compiled from "JacksonJsonProvider.java"
public class org.codehaus.jackson.jaxrs.JacksonJsonProvider implements javax.ws.rs.ext.MessageBodyReader<java.lang.Object>, javax.ws.rs.ext.MessageBodyWriter<java.lang.Object>, org.codehaus.jackson.Versioned {
  public static final org.codehaus.jackson.jaxrs.Annotations[] BASIC_ANNOTATIONS;

  public static final java.util.HashSet<org.codehaus.jackson.map.type.ClassKey> _untouchables;

  public static final java.lang.Class<?>[] _unreadableClasses;

  public static final java.lang.Class<?>[] _unwritableClasses;

  protected final org.codehaus.jackson.jaxrs.MapperConfigurator _mapperConfig;

  protected java.util.HashSet<org.codehaus.jackson.map.type.ClassKey> _cfgCustomUntouchables;

  protected java.lang.String _jsonpFunctionName;

  protected javax.ws.rs.ext.Providers _providers;

  protected boolean _cfgCheckCanSerialize;

  protected boolean _cfgCheckCanDeserialize;

  public org.codehaus.jackson.jaxrs.JacksonJsonProvider();
    Code:
       0: aload_0
       1: aconst_null
       2: getstatic     #1                  // Field BASIC_ANNOTATIONS:[Lorg/codehaus/jackson/jaxrs/Annotations;
       5: invokespecial #2                  // Method "<init>":(Lorg/codehaus/jackson/map/ObjectMapper;[Lorg/codehaus/jackson/jaxrs/Annotations;)V
       8: return

  public org.codehaus.jackson.jaxrs.JacksonJsonProvider(org.codehaus.jackson.jaxrs.Annotations...);
    Code:
       0: aload_0
       1: aconst_null
       2: aload_1
       3: invokespecial #2                  // Method "<init>":(Lorg/codehaus/jackson/map/ObjectMapper;[Lorg/codehaus/jackson/jaxrs/Annotations;)V
       6: return

  public org.codehaus.jackson.jaxrs.JacksonJsonProvider(org.codehaus.jackson.map.ObjectMapper);
    Code:
       0: aload_0
       1: aload_1
       2: getstatic     #1                  // Field BASIC_ANNOTATIONS:[Lorg/codehaus/jackson/jaxrs/Annotations;
       5: invokespecial #2                  // Method "<init>":(Lorg/codehaus/jackson/map/ObjectMapper;[Lorg/codehaus/jackson/jaxrs/Annotations;)V
       8: return

  public org.codehaus.jackson.jaxrs.JacksonJsonProvider(org.codehaus.jackson.map.ObjectMapper, org.codehaus.jackson.jaxrs.Annotations[]);
    Code:
       0: aload_0
       1: invokespecial #3                  // Method java/lang/Object."<init>":()V
       4: aload_0
       5: iconst_0
       6: putfield      #4                  // Field _cfgCheckCanSerialize:Z
       9: aload_0
      10: iconst_0
      11: putfield      #5                  // Field _cfgCheckCanDeserialize:Z
      14: aload_0
      15: new           #6                  // class org/codehaus/jackson/jaxrs/MapperConfigurator
      18: dup
      19: aload_1
      20: aload_2
      21: invokespecial #7                  // Method org/codehaus/jackson/jaxrs/MapperConfigurator."<init>":(Lorg/codehaus/jackson/map/ObjectMapper;[Lorg/codehaus/jackson/jaxrs/Annotations;)V
      24: putfield      #8                  // Field _mapperConfig:Lorg/codehaus/jackson/jaxrs/MapperConfigurator;
      27: return

  public org.codehaus.jackson.Version version();
    Code:
       0: aload_0
       1: invokevirtual #9                  // Method java/lang/Object.getClass:()Ljava/lang/Class;
       4: invokestatic  #10                 // Method org/codehaus/jackson/util/VersionUtil.versionFor:(Ljava/lang/Class;)Lorg/codehaus/jackson/Version;
       7: areturn

  public void checkCanDeserialize(boolean);
    Code:
       0: aload_0
       1: iload_1
       2: putfield      #5                  // Field _cfgCheckCanDeserialize:Z
       5: return

  public void checkCanSerialize(boolean);
    Code:
       0: aload_0
       1: iload_1
       2: putfield      #4                  // Field _cfgCheckCanSerialize:Z
       5: return

  public void setAnnotationsToUse(org.codehaus.jackson.jaxrs.Annotations[]);
    Code:
       0: aload_0
       1: getfield      #8                  // Field _mapperConfig:Lorg/codehaus/jackson/jaxrs/MapperConfigurator;
       4: aload_1
       5: invokevirtual #11                 // Method org/codehaus/jackson/jaxrs/MapperConfigurator.setAnnotationsToUse:([Lorg/codehaus/jackson/jaxrs/Annotations;)V
       8: return

  public void setMapper(org.codehaus.jackson.map.ObjectMapper);
    Code:
       0: aload_0
       1: getfield      #8                  // Field _mapperConfig:Lorg/codehaus/jackson/jaxrs/MapperConfigurator;
       4: aload_1
       5: invokevirtual #12                 // Method org/codehaus/jackson/jaxrs/MapperConfigurator.setMapper:(Lorg/codehaus/jackson/map/ObjectMapper;)V
       8: return

  public org.codehaus.jackson.jaxrs.JacksonJsonProvider configure(org.codehaus.jackson.map.DeserializationConfig$Feature, boolean);
    Code:
       0: aload_0
       1: getfield      #8                  // Field _mapperConfig:Lorg/codehaus/jackson/jaxrs/MapperConfigurator;
       4: aload_1
       5: iload_2
       6: invokevirtual #13                 // Method org/codehaus/jackson/jaxrs/MapperConfigurator.configure:(Lorg/codehaus/jackson/map/DeserializationConfig$Feature;Z)V
       9: aload_0
      10: areturn

  public org.codehaus.jackson.jaxrs.JacksonJsonProvider configure(org.codehaus.jackson.map.SerializationConfig$Feature, boolean);
    Code:
       0: aload_0
       1: getfield      #8                  // Field _mapperConfig:Lorg/codehaus/jackson/jaxrs/MapperConfigurator;
       4: aload_1
       5: iload_2
       6: invokevirtual #14                 // Method org/codehaus/jackson/jaxrs/MapperConfigurator.configure:(Lorg/codehaus/jackson/map/SerializationConfig$Feature;Z)V
       9: aload_0
      10: areturn

  public org.codehaus.jackson.jaxrs.JacksonJsonProvider configure(org.codehaus.jackson.JsonParser$Feature, boolean);
    Code:
       0: aload_0
       1: getfield      #8                  // Field _mapperConfig:Lorg/codehaus/jackson/jaxrs/MapperConfigurator;
       4: aload_1
       5: iload_2
       6: invokevirtual #15                 // Method org/codehaus/jackson/jaxrs/MapperConfigurator.configure:(Lorg/codehaus/jackson/JsonParser$Feature;Z)V
       9: aload_0
      10: areturn

  public org.codehaus.jackson.jaxrs.JacksonJsonProvider configure(org.codehaus.jackson.JsonGenerator$Feature, boolean);
    Code:
       0: aload_0
       1: getfield      #8                  // Field _mapperConfig:Lorg/codehaus/jackson/jaxrs/MapperConfigurator;
       4: aload_1
       5: iload_2
       6: invokevirtual #16                 // Method org/codehaus/jackson/jaxrs/MapperConfigurator.configure:(Lorg/codehaus/jackson/JsonGenerator$Feature;Z)V
       9: aload_0
      10: areturn

  public org.codehaus.jackson.jaxrs.JacksonJsonProvider enable(org.codehaus.jackson.map.DeserializationConfig$Feature, boolean);
    Code:
       0: aload_0
       1: getfield      #8                  // Field _mapperConfig:Lorg/codehaus/jackson/jaxrs/MapperConfigurator;
       4: aload_1
       5: iconst_1
       6: invokevirtual #13                 // Method org/codehaus/jackson/jaxrs/MapperConfigurator.configure:(Lorg/codehaus/jackson/map/DeserializationConfig$Feature;Z)V
       9: aload_0
      10: areturn

  public org.codehaus.jackson.jaxrs.JacksonJsonProvider enable(org.codehaus.jackson.map.SerializationConfig$Feature, boolean);
    Code:
       0: aload_0
       1: getfield      #8                  // Field _mapperConfig:Lorg/codehaus/jackson/jaxrs/MapperConfigurator;
       4: aload_1
       5: iconst_1
       6: invokevirtual #14                 // Method org/codehaus/jackson/jaxrs/MapperConfigurator.configure:(Lorg/codehaus/jackson/map/SerializationConfig$Feature;Z)V
       9: aload_0
      10: areturn

  public org.codehaus.jackson.jaxrs.JacksonJsonProvider enable(org.codehaus.jackson.JsonParser$Feature, boolean);
    Code:
       0: aload_0
       1: getfield      #8                  // Field _mapperConfig:Lorg/codehaus/jackson/jaxrs/MapperConfigurator;
       4: aload_1
       5: iconst_1
       6: invokevirtual #15                 // Method org/codehaus/jackson/jaxrs/MapperConfigurator.configure:(Lorg/codehaus/jackson/JsonParser$Feature;Z)V
       9: aload_0
      10: areturn

  public org.codehaus.jackson.jaxrs.JacksonJsonProvider enable(org.codehaus.jackson.JsonGenerator$Feature, boolean);
    Code:
       0: aload_0
       1: getfield      #8                  // Field _mapperConfig:Lorg/codehaus/jackson/jaxrs/MapperConfigurator;
       4: aload_1
       5: iconst_1
       6: invokevirtual #16                 // Method org/codehaus/jackson/jaxrs/MapperConfigurator.configure:(Lorg/codehaus/jackson/JsonGenerator$Feature;Z)V
       9: aload_0
      10: areturn

  public org.codehaus.jackson.jaxrs.JacksonJsonProvider disable(org.codehaus.jackson.map.DeserializationConfig$Feature, boolean);
    Code:
       0: aload_0
       1: getfield      #8                  // Field _mapperConfig:Lorg/codehaus/jackson/jaxrs/MapperConfigurator;
       4: aload_1
       5: iconst_0
       6: invokevirtual #13                 // Method org/codehaus/jackson/jaxrs/MapperConfigurator.configure:(Lorg/codehaus/jackson/map/DeserializationConfig$Feature;Z)V
       9: aload_0
      10: areturn

  public org.codehaus.jackson.jaxrs.JacksonJsonProvider disable(org.codehaus.jackson.map.SerializationConfig$Feature, boolean);
    Code:
       0: aload_0
       1: getfield      #8                  // Field _mapperConfig:Lorg/codehaus/jackson/jaxrs/MapperConfigurator;
       4: aload_1
       5: iconst_0
       6: invokevirtual #14                 // Method org/codehaus/jackson/jaxrs/MapperConfigurator.configure:(Lorg/codehaus/jackson/map/SerializationConfig$Feature;Z)V
       9: aload_0
      10: areturn

  public org.codehaus.jackson.jaxrs.JacksonJsonProvider disable(org.codehaus.jackson.JsonParser$Feature, boolean);
    Code:
       0: aload_0
       1: getfield      #8                  // Field _mapperConfig:Lorg/codehaus/jackson/jaxrs/MapperConfigurator;
       4: aload_1
       5: iconst_0
       6: invokevirtual #15                 // Method org/codehaus/jackson/jaxrs/MapperConfigurator.configure:(Lorg/codehaus/jackson/JsonParser$Feature;Z)V
       9: aload_0
      10: areturn

  public org.codehaus.jackson.jaxrs.JacksonJsonProvider disable(org.codehaus.jackson.JsonGenerator$Feature, boolean);
    Code:
       0: aload_0
       1: getfield      #8                  // Field _mapperConfig:Lorg/codehaus/jackson/jaxrs/MapperConfigurator;
       4: aload_1
       5: iconst_0
       6: invokevirtual #16                 // Method org/codehaus/jackson/jaxrs/MapperConfigurator.configure:(Lorg/codehaus/jackson/JsonGenerator$Feature;Z)V
       9: aload_0
      10: areturn

  public void addUntouchable(java.lang.Class<?>);
    Code:
       0: aload_0
       1: getfield      #17                 // Field _cfgCustomUntouchables:Ljava/util/HashSet;
       4: ifnonnull     18
       7: aload_0
       8: new           #18                 // class java/util/HashSet
      11: dup
      12: invokespecial #19                 // Method java/util/HashSet."<init>":()V
      15: putfield      #17                 // Field _cfgCustomUntouchables:Ljava/util/HashSet;
      18: aload_0
      19: getfield      #17                 // Field _cfgCustomUntouchables:Ljava/util/HashSet;
      22: new           #20                 // class org/codehaus/jackson/map/type/ClassKey
      25: dup
      26: aload_1
      27: invokespecial #21                 // Method org/codehaus/jackson/map/type/ClassKey."<init>":(Ljava/lang/Class;)V
      30: invokevirtual #22                 // Method java/util/HashSet.add:(Ljava/lang/Object;)Z
      33: pop
      34: return

  public void setJSONPFunctionName(java.lang.String);
    Code:
       0: aload_0
       1: aload_1
       2: putfield      #23                 // Field _jsonpFunctionName:Ljava/lang/String;
       5: return

  public boolean isReadable(java.lang.Class<?>, java.lang.reflect.Type, java.lang.annotation.Annotation[], javax.ws.rs.core.MediaType);
    Code:
       0: aload_0
       1: aload         4
       3: invokevirtual #24                 // Method isJsonType:(Ljavax/ws/rs/core/MediaType;)Z
       6: ifne          11
       9: iconst_0
      10: ireturn
      11: getstatic     #25                 // Field _untouchables:Ljava/util/HashSet;
      14: new           #20                 // class org/codehaus/jackson/map/type/ClassKey
      17: dup
      18: aload_1
      19: invokespecial #21                 // Method org/codehaus/jackson/map/type/ClassKey."<init>":(Ljava/lang/Class;)V
      22: invokevirtual #26                 // Method java/util/HashSet.contains:(Ljava/lang/Object;)Z
      25: ifeq          30
      28: iconst_0
      29: ireturn
      30: getstatic     #27                 // Field _unreadableClasses:[Ljava/lang/Class;
      33: astore        5
      35: aload         5
      37: arraylength
      38: istore        6
      40: iconst_0
      41: istore        7
      43: iload         7
      45: iload         6
      47: if_icmpge     74
      50: aload         5
      52: iload         7
      54: aaload
      55: astore        8
      57: aload         8
      59: aload_1
      60: invokevirtual #28                 // Method java/lang/Class.isAssignableFrom:(Ljava/lang/Class;)Z
      63: ifeq          68
      66: iconst_0
      67: ireturn
      68: iinc          7, 1
      71: goto          43
      74: aload_1
      75: aload_0
      76: getfield      #17                 // Field _cfgCustomUntouchables:Ljava/util/HashSet;
      79: invokestatic  #29                 // Method _containedIn:(Ljava/lang/Class;Ljava/util/HashSet;)Z
      82: ifeq          87
      85: iconst_0
      86: ireturn
      87: aload_0
      88: getfield      #4                  // Field _cfgCheckCanSerialize:Z
      91: ifeq          119
      94: aload_0
      95: aload_1
      96: aload         4
      98: invokevirtual #30                 // Method locateMapper:(Ljava/lang/Class;Ljavax/ws/rs/core/MediaType;)Lorg/codehaus/jackson/map/ObjectMapper;
     101: astore        5
     103: aload         5
     105: aload         5
     107: aload_1
     108: invokevirtual #31                 // Method org/codehaus/jackson/map/ObjectMapper.constructType:(Ljava/lang/reflect/Type;)Lorg/codehaus/jackson/type/JavaType;
     111: invokevirtual #32                 // Method org/codehaus/jackson/map/ObjectMapper.canDeserialize:(Lorg/codehaus/jackson/type/JavaType;)Z
     114: ifne          119
     117: iconst_0
     118: ireturn
     119: iconst_1
     120: ireturn

  public java.lang.Object readFrom(java.lang.Class<java.lang.Object>, java.lang.reflect.Type, java.lang.annotation.Annotation[], javax.ws.rs.core.MediaType, javax.ws.rs.core.MultivaluedMap<java.lang.String, java.lang.String>, java.io.InputStream) throws java.io.IOException;
    Code:
       0: aload_0
       1: aload_1
       2: aload         4
       4: invokevirtual #30                 // Method locateMapper:(Ljava/lang/Class;Ljavax/ws/rs/core/MediaType;)Lorg/codehaus/jackson/map/ObjectMapper;
       7: astore        7
       9: aload         7
      11: invokevirtual #33                 // Method org/codehaus/jackson/map/ObjectMapper.getJsonFactory:()Lorg/codehaus/jackson/JsonFactory;
      14: aload         6
      16: invokevirtual #34                 // Method org/codehaus/jackson/JsonFactory.createJsonParser:(Ljava/io/InputStream;)Lorg/codehaus/jackson/JsonParser;
      19: astore        8
      21: aload         8
      23: getstatic     #35                 // Field org/codehaus/jackson/JsonParser$Feature.AUTO_CLOSE_SOURCE:Lorg/codehaus/jackson/JsonParser$Feature;
      26: invokevirtual #36                 // Method org/codehaus/jackson/JsonParser.disable:(Lorg/codehaus/jackson/JsonParser$Feature;)Lorg/codehaus/jackson/JsonParser;
      29: pop
      30: aload         7
      32: aload         8
      34: aload         7
      36: aload_2
      37: invokevirtual #31                 // Method org/codehaus/jackson/map/ObjectMapper.constructType:(Ljava/lang/reflect/Type;)Lorg/codehaus/jackson/type/JavaType;
      40: invokevirtual #37                 // Method org/codehaus/jackson/map/ObjectMapper.readValue:(Lorg/codehaus/jackson/JsonParser;Lorg/codehaus/jackson/type/JavaType;)Ljava/lang/Object;
      43: areturn

  public long getSize(java.lang.Object, java.lang.Class<?>, java.lang.reflect.Type, java.lang.annotation.Annotation[], javax.ws.rs.core.MediaType);
    Code:
       0: ldc2_w        #38                 // long -1l
       3: lreturn

  public boolean isWriteable(java.lang.Class<?>, java.lang.reflect.Type, java.lang.annotation.Annotation[], javax.ws.rs.core.MediaType);
    Code:
       0: aload_0
       1: aload         4
       3: invokevirtual #24                 // Method isJsonType:(Ljavax/ws/rs/core/MediaType;)Z
       6: ifne          11
       9: iconst_0
      10: ireturn
      11: getstatic     #25                 // Field _untouchables:Ljava/util/HashSet;
      14: new           #20                 // class org/codehaus/jackson/map/type/ClassKey
      17: dup
      18: aload_1
      19: invokespecial #21                 // Method org/codehaus/jackson/map/type/ClassKey."<init>":(Ljava/lang/Class;)V
      22: invokevirtual #26                 // Method java/util/HashSet.contains:(Ljava/lang/Object;)Z
      25: ifeq          30
      28: iconst_0
      29: ireturn
      30: getstatic     #40                 // Field _unwritableClasses:[Ljava/lang/Class;
      33: astore        5
      35: aload         5
      37: arraylength
      38: istore        6
      40: iconst_0
      41: istore        7
      43: iload         7
      45: iload         6
      47: if_icmpge     74
      50: aload         5
      52: iload         7
      54: aaload
      55: astore        8
      57: aload         8
      59: aload_1
      60: invokevirtual #28                 // Method java/lang/Class.isAssignableFrom:(Ljava/lang/Class;)Z
      63: ifeq          68
      66: iconst_0
      67: ireturn
      68: iinc          7, 1
      71: goto          43
      74: aload_1
      75: aload_0
      76: getfield      #17                 // Field _cfgCustomUntouchables:Ljava/util/HashSet;
      79: invokestatic  #29                 // Method _containedIn:(Ljava/lang/Class;Ljava/util/HashSet;)Z
      82: ifeq          87
      85: iconst_0
      86: ireturn
      87: aload_0
      88: getfield      #4                  // Field _cfgCheckCanSerialize:Z
      91: ifeq          110
      94: aload_0
      95: aload_1
      96: aload         4
      98: invokevirtual #30                 // Method locateMapper:(Ljava/lang/Class;Ljavax/ws/rs/core/MediaType;)Lorg/codehaus/jackson/map/ObjectMapper;
     101: aload_1
     102: invokevirtual #41                 // Method org/codehaus/jackson/map/ObjectMapper.canSerialize:(Ljava/lang/Class;)Z
     105: ifne          110
     108: iconst_0
     109: ireturn
     110: iconst_1
     111: ireturn

  public void writeTo(java.lang.Object, java.lang.Class<?>, java.lang.reflect.Type, java.lang.annotation.Annotation[], javax.ws.rs.core.MediaType, javax.ws.rs.core.MultivaluedMap<java.lang.String, java.lang.Object>, java.io.OutputStream) throws java.io.IOException;
    Code:
       0: aload_0
       1: aload_2
       2: aload         5
       4: invokevirtual #30                 // Method locateMapper:(Ljava/lang/Class;Ljavax/ws/rs/core/MediaType;)Lorg/codehaus/jackson/map/ObjectMapper;
       7: astore        8
       9: aload_0
      10: aload         5
      12: aload         6
      14: invokevirtual #42                 // Method findEncoding:(Ljavax/ws/rs/core/MediaType;Ljavax/ws/rs/core/MultivaluedMap;)Lorg/codehaus/jackson/JsonEncoding;
      17: astore        9
      19: aload         8
      21: invokevirtual #33                 // Method org/codehaus/jackson/map/ObjectMapper.getJsonFactory:()Lorg/codehaus/jackson/JsonFactory;
      24: aload         7
      26: aload         9
      28: invokevirtual #43                 // Method org/codehaus/jackson/JsonFactory.createJsonGenerator:(Ljava/io/OutputStream;Lorg/codehaus/jackson/JsonEncoding;)Lorg/codehaus/jackson/JsonGenerator;
      31: astore        10
      33: aload         10
      35: getstatic     #44                 // Field org/codehaus/jackson/JsonGenerator$Feature.AUTO_CLOSE_TARGET:Lorg/codehaus/jackson/JsonGenerator$Feature;
      38: invokevirtual #45                 // Method org/codehaus/jackson/JsonGenerator.disable:(Lorg/codehaus/jackson/JsonGenerator$Feature;)Lorg/codehaus/jackson/JsonGenerator;
      41: pop
      42: aload         8
      44: invokevirtual #46                 // Method org/codehaus/jackson/map/ObjectMapper.getSerializationConfig:()Lorg/codehaus/jackson/map/SerializationConfig;
      47: getstatic     #47                 // Field org/codehaus/jackson/map/SerializationConfig$Feature.INDENT_OUTPUT:Lorg/codehaus/jackson/map/SerializationConfig$Feature;
      50: invokevirtual #48                 // Method org/codehaus/jackson/map/SerializationConfig.isEnabled:(Lorg/codehaus/jackson/map/SerializationConfig$Feature;)Z
      53: ifeq          62
      56: aload         10
      58: invokevirtual #49                 // Method org/codehaus/jackson/JsonGenerator.useDefaultPrettyPrinter:()Lorg/codehaus/jackson/JsonGenerator;
      61: pop
      62: aconst_null
      63: astore        11
      65: aload_3
      66: ifnull        108
      69: aload_1
      70: ifnull        108
      73: aload_3
      74: invokevirtual #9                  // Method java/lang/Object.getClass:()Ljava/lang/Class;
      77: ldc_w         #50                 // class java/lang/Class
      80: if_acmpeq     108
      83: aload         8
      85: invokevirtual #51                 // Method org/codehaus/jackson/map/ObjectMapper.getTypeFactory:()Lorg/codehaus/jackson/map/type/TypeFactory;
      88: aload_3
      89: invokevirtual #52                 // Method org/codehaus/jackson/map/type/TypeFactory.constructType:(Ljava/lang/reflect/Type;)Lorg/codehaus/jackson/type/JavaType;
      92: astore        11
      94: aload         11
      96: invokevirtual #53                 // Method org/codehaus/jackson/type/JavaType.getRawClass:()Ljava/lang/Class;
      99: ldc_w         #54                 // class java/lang/Object
     102: if_acmpne     108
     105: aconst_null
     106: astore        11
     108: aconst_null
     109: astore        12
     111: aload         4
     113: ifnull        132
     116: aload         4
     118: arraylength
     119: ifle          132
     122: aload_0
     123: aload         8
     125: aload         4
     127: invokevirtual #55                 // Method _findView:(Lorg/codehaus/jackson/map/ObjectMapper;[Ljava/lang/annotation/Annotation;)Ljava/lang/Class;
     130: astore        12
     132: aload         12
     134: ifnull        214
     137: aload         8
     139: aload         12
     141: invokevirtual #56                 // Method org/codehaus/jackson/map/ObjectMapper.viewWriter:(Ljava/lang/Class;)Lorg/codehaus/jackson/map/ObjectWriter;
     144: astore        13
     146: aload_0
     147: getfield      #23                 // Field _jsonpFunctionName:Ljava/lang/String;
     150: ifnull        177
     153: aload         13
     155: aload         10
     157: new           #57                 // class org/codehaus/jackson/map/util/JSONPObject
     160: dup
     161: aload_0
     162: getfield      #23                 // Field _jsonpFunctionName:Ljava/lang/String;
     165: aload_1
     166: aload         11
     168: invokespecial #58                 // Method org/codehaus/jackson/map/util/JSONPObject."<init>":(Ljava/lang/String;Ljava/lang/Object;Lorg/codehaus/jackson/type/JavaType;)V
     171: invokevirtual #59                 // Method org/codehaus/jackson/map/ObjectWriter.writeValue:(Lorg/codehaus/jackson/JsonGenerator;Ljava/lang/Object;)V
     174: goto          211
     177: aload         11
     179: ifnull        203
     182: aload         8
     184: aload         11
     186: invokevirtual #60                 // Method org/codehaus/jackson/map/ObjectMapper.typedWriter:(Lorg/codehaus/jackson/type/JavaType;)Lorg/codehaus/jackson/map/ObjectWriter;
     189: aload         12
     191: invokevirtual #61                 // Method org/codehaus/jackson/map/ObjectWriter.withView:(Ljava/lang/Class;)Lorg/codehaus/jackson/map/ObjectWriter;
     194: aload         10
     196: aload_1
     197: invokevirtual #59                 // Method org/codehaus/jackson/map/ObjectWriter.writeValue:(Lorg/codehaus/jackson/JsonGenerator;Ljava/lang/Object;)V
     200: goto          211
     203: aload         13
     205: aload         10
     207: aload_1
     208: invokevirtual #59                 // Method org/codehaus/jackson/map/ObjectWriter.writeValue:(Lorg/codehaus/jackson/JsonGenerator;Ljava/lang/Object;)V
     211: goto          274
     214: aload_0
     215: getfield      #23                 // Field _jsonpFunctionName:Ljava/lang/String;
     218: ifnull        245
     221: aload         8
     223: aload         10
     225: new           #57                 // class org/codehaus/jackson/map/util/JSONPObject
     228: dup
     229: aload_0
     230: getfield      #23                 // Field _jsonpFunctionName:Ljava/lang/String;
     233: aload_1
     234: aload         11
     236: invokespecial #58                 // Method org/codehaus/jackson/map/util/JSONPObject."<init>":(Ljava/lang/String;Ljava/lang/Object;Lorg/codehaus/jackson/type/JavaType;)V
     239: invokevirtual #62                 // Method org/codehaus/jackson/map/ObjectMapper.writeValue:(Lorg/codehaus/jackson/JsonGenerator;Ljava/lang/Object;)V
     242: goto          274
     245: aload         11
     247: ifnull        266
     250: aload         8
     252: aload         11
     254: invokevirtual #60                 // Method org/codehaus/jackson/map/ObjectMapper.typedWriter:(Lorg/codehaus/jackson/type/JavaType;)Lorg/codehaus/jackson/map/ObjectWriter;
     257: aload         10
     259: aload_1
     260: invokevirtual #59                 // Method org/codehaus/jackson/map/ObjectWriter.writeValue:(Lorg/codehaus/jackson/JsonGenerator;Ljava/lang/Object;)V
     263: goto          274
     266: aload         8
     268: aload         10
     270: aload_1
     271: invokevirtual #62                 // Method org/codehaus/jackson/map/ObjectMapper.writeValue:(Lorg/codehaus/jackson/JsonGenerator;Ljava/lang/Object;)V
     274: return

  protected org.codehaus.jackson.JsonEncoding findEncoding(javax.ws.rs.core.MediaType, javax.ws.rs.core.MultivaluedMap<java.lang.String, java.lang.Object>);
    Code:
       0: getstatic     #63                 // Field org/codehaus/jackson/JsonEncoding.UTF8:Lorg/codehaus/jackson/JsonEncoding;
       3: areturn

  protected boolean isJsonType(javax.ws.rs.core.MediaType);
    Code:
       0: aload_1
       1: ifnull        33
       4: aload_1
       5: invokevirtual #64                 // Method javax/ws/rs/core/MediaType.getSubtype:()Ljava/lang/String;
       8: astore_2
       9: ldc           #65                 // String json
      11: aload_2
      12: invokevirtual #66                 // Method java/lang/String.equalsIgnoreCase:(Ljava/lang/String;)Z
      15: ifne          27
      18: aload_2
      19: ldc           #67                 // String +json
      21: invokevirtual #68                 // Method java/lang/String.endsWith:(Ljava/lang/String;)Z
      24: ifeq          31
      27: iconst_1
      28: goto          32
      31: iconst_0
      32: ireturn
      33: iconst_1
      34: ireturn

  public org.codehaus.jackson.map.ObjectMapper locateMapper(java.lang.Class<?>, javax.ws.rs.core.MediaType);
    Code:
       0: aload_0
       1: getfield      #8                  // Field _mapperConfig:Lorg/codehaus/jackson/jaxrs/MapperConfigurator;
       4: invokevirtual #69                 // Method org/codehaus/jackson/jaxrs/MapperConfigurator.getConfiguredMapper:()Lorg/codehaus/jackson/map/ObjectMapper;
       7: astore_3
       8: aload_3
       9: ifnonnull     83
      12: aload_0
      13: getfield      #70                 // Field _providers:Ljavax/ws/rs/ext/Providers;
      16: ifnull        71
      19: aload_0
      20: getfield      #70                 // Field _providers:Ljavax/ws/rs/ext/Providers;
      23: ldc_w         #71                 // class org/codehaus/jackson/map/ObjectMapper
      26: aload_2
      27: invokeinterface #72,  3           // InterfaceMethod javax/ws/rs/ext/Providers.getContextResolver:(Ljava/lang/Class;Ljavax/ws/rs/core/MediaType;)Ljavax/ws/rs/ext/ContextResolver;
      32: astore        4
      34: aload         4
      36: ifnonnull     54
      39: aload_0
      40: getfield      #70                 // Field _providers:Ljavax/ws/rs/ext/Providers;
      43: ldc_w         #71                 // class org/codehaus/jackson/map/ObjectMapper
      46: aconst_null
      47: invokeinterface #72,  3           // InterfaceMethod javax/ws/rs/ext/Providers.getContextResolver:(Ljava/lang/Class;Ljavax/ws/rs/core/MediaType;)Ljavax/ws/rs/ext/ContextResolver;
      52: astore        4
      54: aload         4
      56: ifnull        71
      59: aload         4
      61: aload_1
      62: invokeinterface #73,  2           // InterfaceMethod javax/ws/rs/ext/ContextResolver.getContext:(Ljava/lang/Class;)Ljava/lang/Object;
      67: checkcast     #71                 // class org/codehaus/jackson/map/ObjectMapper
      70: astore_3
      71: aload_3
      72: ifnonnull     83
      75: aload_0
      76: getfield      #8                  // Field _mapperConfig:Lorg/codehaus/jackson/jaxrs/MapperConfigurator;
      79: invokevirtual #74                 // Method org/codehaus/jackson/jaxrs/MapperConfigurator.getDefaultMapper:()Lorg/codehaus/jackson/map/ObjectMapper;
      82: astore_3
      83: aload_3
      84: areturn

  protected static boolean _containedIn(java.lang.Class<?>, java.util.HashSet<org.codehaus.jackson.map.type.ClassKey>);
    Code:
       0: aload_1
       1: ifnull        73
       4: new           #20                 // class org/codehaus/jackson/map/type/ClassKey
       7: dup
       8: aload_0
       9: invokespecial #21                 // Method org/codehaus/jackson/map/type/ClassKey."<init>":(Ljava/lang/Class;)V
      12: astore_2
      13: aload_1
      14: aload_2
      15: invokevirtual #26                 // Method java/util/HashSet.contains:(Ljava/lang/Object;)Z
      18: ifeq          23
      21: iconst_1
      22: ireturn
      23: aload_0
      24: aconst_null
      25: invokestatic  #75                 // Method org/codehaus/jackson/map/util/ClassUtil.findSuperTypes:(Ljava/lang/Class;Ljava/lang/Class;)Ljava/util/List;
      28: invokeinterface #76,  1           // InterfaceMethod java/util/List.iterator:()Ljava/util/Iterator;
      33: astore_3
      34: aload_3
      35: invokeinterface #77,  1           // InterfaceMethod java/util/Iterator.hasNext:()Z
      40: ifeq          73
      43: aload_3
      44: invokeinterface #78,  1           // InterfaceMethod java/util/Iterator.next:()Ljava/lang/Object;
      49: checkcast     #50                 // class java/lang/Class
      52: astore        4
      54: aload_2
      55: aload         4
      57: invokevirtual #79                 // Method org/codehaus/jackson/map/type/ClassKey.reset:(Ljava/lang/Class;)V
      60: aload_1
      61: aload_2
      62: invokevirtual #26                 // Method java/util/HashSet.contains:(Ljava/lang/Object;)Z
      65: ifeq          70
      68: iconst_1
      69: ireturn
      70: goto          34
      73: iconst_0
      74: ireturn

  protected java.lang.Class<?> _findView(org.codehaus.jackson.map.ObjectMapper, java.lang.annotation.Annotation[]) throws org.codehaus.jackson.map.JsonMappingException;
    Code:
       0: aload_2
       1: astore_3
       2: aload_3
       3: arraylength
       4: istore        4
       6: iconst_0
       7: istore        5
       9: iload         5
      11: iload         4
      13: if_icmpge     154
      16: aload_3
      17: iload         5
      19: aaload
      20: astore        6
      22: aload         6
      24: invokeinterface #80,  1           // InterfaceMethod java/lang/annotation/Annotation.annotationType:()Ljava/lang/Class;
      29: ldc_w         #81                 // class org/codehaus/jackson/map/annotate/JsonView
      32: invokevirtual #28                 // Method java/lang/Class.isAssignableFrom:(Ljava/lang/Class;)Z
      35: ifeq          148
      38: aload         6
      40: checkcast     #81                 // class org/codehaus/jackson/map/annotate/JsonView
      43: astore        7
      45: aload         7
      47: invokeinterface #82,  1           // InterfaceMethod org/codehaus/jackson/map/annotate/JsonView.value:()[Ljava/lang/Class;
      52: astore        8
      54: aload         8
      56: arraylength
      57: iconst_1
      58: if_icmple     143
      61: new           #83                 // class java/lang/StringBuilder
      64: dup
      65: ldc           #84                 // String Multiple @JsonView\'s can not be used on a JAX-RS method. Got
      67: invokespecial #85                 // Method java/lang/StringBuilder."<init>":(Ljava/lang/String;)V
      70: astore        9
      72: aload         9
      74: aload         8
      76: arraylength
      77: invokevirtual #86                 // Method java/lang/StringBuilder.append:(I)Ljava/lang/StringBuilder;
      80: ldc           #87                 // String  views:
      82: invokevirtual #88                 // Method java/lang/StringBuilder.append:(Ljava/lang/String;)Ljava/lang/StringBuilder;
      85: pop
      86: iconst_0
      87: istore        10
      89: iload         10
      91: aload         8
      93: arraylength
      94: if_icmpge     130
      97: iload         10
      99: ifle          110
     102: aload         9
     104: ldc           #89                 // String ,
     106: invokevirtual #88                 // Method java/lang/StringBuilder.append:(Ljava/lang/String;)Ljava/lang/StringBuilder;
     109: pop
     110: aload         9
     112: aload         8
     114: iload         10
     116: aaload
     117: invokevirtual #90                 // Method java/lang/Class.getName:()Ljava/lang/String;
     120: invokevirtual #88                 // Method java/lang/StringBuilder.append:(Ljava/lang/String;)Ljava/lang/StringBuilder;
     123: pop
     124: iinc          10, 1
     127: goto          89
     130: new           #91                 // class org/codehaus/jackson/map/JsonMappingException
     133: dup
     134: aload         9
     136: invokevirtual #92                 // Method java/lang/StringBuilder.toString:()Ljava/lang/String;
     139: invokespecial #93                 // Method org/codehaus/jackson/map/JsonMappingException."<init>":(Ljava/lang/String;)V
     142: athrow
     143: aload         8
     145: iconst_0
     146: aaload
     147: areturn
     148: iinc          5, 1
     151: goto          9
     154: aconst_null
     155: areturn

  static {};
    Code:
       0: iconst_1
       1: anewarray     #94                 // class org/codehaus/jackson/jaxrs/Annotations
       4: dup
       5: iconst_0
       6: getstatic     #95                 // Field org/codehaus/jackson/jaxrs/Annotations.JACKSON:Lorg/codehaus/jackson/jaxrs/Annotations;
       9: aastore
      10: putstatic     #1                  // Field BASIC_ANNOTATIONS:[Lorg/codehaus/jackson/jaxrs/Annotations;
      13: new           #18                 // class java/util/HashSet
      16: dup
      17: invokespecial #19                 // Method java/util/HashSet."<init>":()V
      20: putstatic     #25                 // Field _untouchables:Ljava/util/HashSet;
      23: getstatic     #25                 // Field _untouchables:Ljava/util/HashSet;
      26: new           #20                 // class org/codehaus/jackson/map/type/ClassKey
      29: dup
      30: ldc_w         #96                 // class java/io/InputStream
      33: invokespecial #21                 // Method org/codehaus/jackson/map/type/ClassKey."<init>":(Ljava/lang/Class;)V
      36: invokevirtual #22                 // Method java/util/HashSet.add:(Ljava/lang/Object;)Z
      39: pop
      40: getstatic     #25                 // Field _untouchables:Ljava/util/HashSet;
      43: new           #20                 // class org/codehaus/jackson/map/type/ClassKey
      46: dup
      47: ldc_w         #97                 // class java/io/Reader
      50: invokespecial #21                 // Method org/codehaus/jackson/map/type/ClassKey."<init>":(Ljava/lang/Class;)V
      53: invokevirtual #22                 // Method java/util/HashSet.add:(Ljava/lang/Object;)Z
      56: pop
      57: getstatic     #25                 // Field _untouchables:Ljava/util/HashSet;
      60: new           #20                 // class org/codehaus/jackson/map/type/ClassKey
      63: dup
      64: ldc_w         #98                 // class java/io/OutputStream
      67: invokespecial #21                 // Method org/codehaus/jackson/map/type/ClassKey."<init>":(Ljava/lang/Class;)V
      70: invokevirtual #22                 // Method java/util/HashSet.add:(Ljava/lang/Object;)Z
      73: pop
      74: getstatic     #25                 // Field _untouchables:Ljava/util/HashSet;
      77: new           #20                 // class org/codehaus/jackson/map/type/ClassKey
      80: dup
      81: ldc_w         #99                 // class java/io/Writer
      84: invokespecial #21                 // Method org/codehaus/jackson/map/type/ClassKey."<init>":(Ljava/lang/Class;)V
      87: invokevirtual #22                 // Method java/util/HashSet.add:(Ljava/lang/Object;)Z
      90: pop
      91: getstatic     #25                 // Field _untouchables:Ljava/util/HashSet;
      94: new           #20                 // class org/codehaus/jackson/map/type/ClassKey
      97: dup
      98: ldc_w         #100                // class "[B"
     101: invokespecial #21                 // Method org/codehaus/jackson/map/type/ClassKey."<init>":(Ljava/lang/Class;)V
     104: invokevirtual #22                 // Method java/util/HashSet.add:(Ljava/lang/Object;)Z
     107: pop
     108: getstatic     #25                 // Field _untouchables:Ljava/util/HashSet;
     111: new           #20                 // class org/codehaus/jackson/map/type/ClassKey
     114: dup
     115: ldc_w         #101                // class "[C"
     118: invokespecial #21                 // Method org/codehaus/jackson/map/type/ClassKey."<init>":(Ljava/lang/Class;)V
     121: invokevirtual #22                 // Method java/util/HashSet.add:(Ljava/lang/Object;)Z
     124: pop
     125: getstatic     #25                 // Field _untouchables:Ljava/util/HashSet;
     128: new           #20                 // class org/codehaus/jackson/map/type/ClassKey
     131: dup
     132: ldc_w         #102                // class java/lang/String
     135: invokespecial #21                 // Method org/codehaus/jackson/map/type/ClassKey."<init>":(Ljava/lang/Class;)V
     138: invokevirtual #22                 // Method java/util/HashSet.add:(Ljava/lang/Object;)Z
     141: pop
     142: getstatic     #25                 // Field _untouchables:Ljava/util/HashSet;
     145: new           #20                 // class org/codehaus/jackson/map/type/ClassKey
     148: dup
     149: ldc_w         #103                // class javax/ws/rs/core/StreamingOutput
     152: invokespecial #21                 // Method org/codehaus/jackson/map/type/ClassKey."<init>":(Ljava/lang/Class;)V
     155: invokevirtual #22                 // Method java/util/HashSet.add:(Ljava/lang/Object;)Z
     158: pop
     159: getstatic     #25                 // Field _untouchables:Ljava/util/HashSet;
     162: new           #20                 // class org/codehaus/jackson/map/type/ClassKey
     165: dup
     166: ldc_w         #104                // class javax/ws/rs/core/Response
     169: invokespecial #21                 // Method org/codehaus/jackson/map/type/ClassKey."<init>":(Ljava/lang/Class;)V
     172: invokevirtual #22                 // Method java/util/HashSet.add:(Ljava/lang/Object;)Z
     175: pop
     176: iconst_2
     177: anewarray     #50                 // class java/lang/Class
     180: dup
     181: iconst_0
     182: ldc_w         #96                 // class java/io/InputStream
     185: aastore
     186: dup
     187: iconst_1
     188: ldc_w         #97                 // class java/io/Reader
     191: aastore
     192: putstatic     #27                 // Field _unreadableClasses:[Ljava/lang/Class;
     195: iconst_4
     196: anewarray     #50                 // class java/lang/Class
     199: dup
     200: iconst_0
     201: ldc_w         #98                 // class java/io/OutputStream
     204: aastore
     205: dup
     206: iconst_1
     207: ldc_w         #99                 // class java/io/Writer
     210: aastore
     211: dup
     212: iconst_2
     213: ldc_w         #103                // class javax/ws/rs/core/StreamingOutput
     216: aastore
     217: dup
     218: iconst_3
     219: ldc_w         #104                // class javax/ws/rs/core/Response
     222: aastore
     223: putstatic     #40                 // Field _unwritableClasses:[Ljava/lang/Class;
     226: return
}
