Compiled from "MalformedClaimException.java"
public class org.jose4j.jwt.MalformedClaimException extends org.jose4j.jwt.GeneralJwtException {
  public org.jose4j.jwt.MalformedClaimException(java.lang.String);
    Code:
       0: aload_0
       1: aload_1
       2: invokespecial #1                  // Method org/jose4j/jwt/GeneralJwtException."<init>":(Ljava/lang/String;)V
       5: return

  public org.jose4j.jwt.MalformedClaimException(java.lang.String, java.lang.Throwable);
    Code:
       0: aload_0
       1: aload_1
       2: aload_2
       3: invokespecial #2                  // Method org/jose4j/jwt/GeneralJwtException."<init>":(Ljava/lang/String;Ljava/lang/Throwable;)V
       6: return
}
