Compiled from "CharGroup.java"
class com.google.re2j.CharGroup {
  final int sign;

  final int[] cls;

  private static final int[] code1;

  private static final int[] code2;

  private static final int[] code3;

  static final java.util.HashMap<java.lang.String, com.google.re2j.CharGroup> PERL_GROUPS;

  private static final int[] code4;

  private static final int[] code5;

  private static final int[] code6;

  private static final int[] code7;

  private static final int[] code8;

  private static final int[] code9;

  private static final int[] code10;

  private static final int[] code11;

  private static final int[] code12;

  private static final int[] code13;

  private static final int[] code14;

  private static final int[] code15;

  private static final int[] code16;

  private static final int[] code17;

  static final java.util.HashMap<java.lang.String, com.google.re2j.CharGroup> POSIX_GROUPS;

  private com.google.re2j.CharGroup(int, int[]);
    Code:
       0: aload_0
       1: invokespecial #1                  // Method java/lang/Object."<init>":()V
       4: aload_0
       5: iload_1
       6: putfield      #2                  // Field sign:I
       9: aload_0
      10: aload_2
      11: putfield      #3                  // Field cls:[I
      14: return

  static {};
    Code:
       0: iconst_2
       1: newarray       int
       3: dup
       4: iconst_0
       5: bipush        48
       7: iastore
       8: dup
       9: iconst_1
      10: bipush        57
      12: iastore
      13: putstatic     #4                  // Field code1:[I
      16: bipush        6
      18: newarray       int
      20: dup
      21: iconst_0
      22: bipush        9
      24: iastore
      25: dup
      26: iconst_1
      27: bipush        10
      29: iastore
      30: dup
      31: iconst_2
      32: bipush        12
      34: iastore
      35: dup
      36: iconst_3
      37: bipush        13
      39: iastore
      40: dup
      41: iconst_4
      42: bipush        32
      44: iastore
      45: dup
      46: iconst_5
      47: bipush        32
      49: iastore
      50: putstatic     #5                  // Field code2:[I
      53: bipush        8
      55: newarray       int
      57: dup
      58: iconst_0
      59: bipush        48
      61: iastore
      62: dup
      63: iconst_1
      64: bipush        57
      66: iastore
      67: dup
      68: iconst_2
      69: bipush        65
      71: iastore
      72: dup
      73: iconst_3
      74: bipush        90
      76: iastore
      77: dup
      78: iconst_4
      79: bipush        95
      81: iastore
      82: dup
      83: iconst_5
      84: bipush        95
      86: iastore
      87: dup
      88: bipush        6
      90: bipush        97
      92: iastore
      93: dup
      94: bipush        7
      96: bipush        122
      98: iastore
      99: putstatic     #6                  // Field code3:[I
     102: new           #7                  // class java/util/HashMap
     105: dup
     106: invokespecial #8                  // Method java/util/HashMap."<init>":()V
     109: putstatic     #9                  // Field PERL_GROUPS:Ljava/util/HashMap;
     112: getstatic     #9                  // Field PERL_GROUPS:Ljava/util/HashMap;
     115: ldc           #10                 // String \\d
     117: new           #11                 // class com/google/re2j/CharGroup
     120: dup
     121: iconst_1
     122: getstatic     #4                  // Field code1:[I
     125: invokespecial #12                 // Method "<init>":(I[I)V
     128: invokevirtual #13                 // Method java/util/HashMap.put:(Ljava/lang/Object;Ljava/lang/Object;)Ljava/lang/Object;
     131: pop
     132: getstatic     #9                  // Field PERL_GROUPS:Ljava/util/HashMap;
     135: ldc           #14                 // String \\D
     137: new           #11                 // class com/google/re2j/CharGroup
     140: dup
     141: iconst_m1
     142: getstatic     #4                  // Field code1:[I
     145: invokespecial #12                 // Method "<init>":(I[I)V
     148: invokevirtual #13                 // Method java/util/HashMap.put:(Ljava/lang/Object;Ljava/lang/Object;)Ljava/lang/Object;
     151: pop
     152: getstatic     #9                  // Field PERL_GROUPS:Ljava/util/HashMap;
     155: ldc           #15                 // String \\s
     157: new           #11                 // class com/google/re2j/CharGroup
     160: dup
     161: iconst_1
     162: getstatic     #5                  // Field code2:[I
     165: invokespecial #12                 // Method "<init>":(I[I)V
     168: invokevirtual #13                 // Method java/util/HashMap.put:(Ljava/lang/Object;Ljava/lang/Object;)Ljava/lang/Object;
     171: pop
     172: getstatic     #9                  // Field PERL_GROUPS:Ljava/util/HashMap;
     175: ldc           #16                 // String \\S
     177: new           #11                 // class com/google/re2j/CharGroup
     180: dup
     181: iconst_m1
     182: getstatic     #5                  // Field code2:[I
     185: invokespecial #12                 // Method "<init>":(I[I)V
     188: invokevirtual #13                 // Method java/util/HashMap.put:(Ljava/lang/Object;Ljava/lang/Object;)Ljava/lang/Object;
     191: pop
     192: getstatic     #9                  // Field PERL_GROUPS:Ljava/util/HashMap;
     195: ldc           #17                 // String \\w
     197: new           #11                 // class com/google/re2j/CharGroup
     200: dup
     201: iconst_1
     202: getstatic     #6                  // Field code3:[I
     205: invokespecial #12                 // Method "<init>":(I[I)V
     208: invokevirtual #13                 // Method java/util/HashMap.put:(Ljava/lang/Object;Ljava/lang/Object;)Ljava/lang/Object;
     211: pop
     212: getstatic     #9                  // Field PERL_GROUPS:Ljava/util/HashMap;
     215: ldc           #18                 // String \\W
     217: new           #11                 // class com/google/re2j/CharGroup
     220: dup
     221: iconst_m1
     222: getstatic     #6                  // Field code3:[I
     225: invokespecial #12                 // Method "<init>":(I[I)V
     228: invokevirtual #13                 // Method java/util/HashMap.put:(Ljava/lang/Object;Ljava/lang/Object;)Ljava/lang/Object;
     231: pop
     232: bipush        6
     234: newarray       int
     236: dup
     237: iconst_0
     238: bipush        48
     240: iastore
     241: dup
     242: iconst_1
     243: bipush        57
     245: iastore
     246: dup
     247: iconst_2
     248: bipush        65
     250: iastore
     251: dup
     252: iconst_3
     253: bipush        90
     255: iastore
     256: dup
     257: iconst_4
     258: bipush        97
     260: iastore
     261: dup
     262: iconst_5
     263: bipush        122
     265: iastore
     266: putstatic     #19                 // Field code4:[I
     269: iconst_4
     270: newarray       int
     272: dup
     273: iconst_0
     274: bipush        65
     276: iastore
     277: dup
     278: iconst_1
     279: bipush        90
     281: iastore
     282: dup
     283: iconst_2
     284: bipush        97
     286: iastore
     287: dup
     288: iconst_3
     289: bipush        122
     291: iastore
     292: putstatic     #20                 // Field code5:[I
     295: iconst_2
     296: newarray       int
     298: dup
     299: iconst_0
     300: iconst_0
     301: iastore
     302: dup
     303: iconst_1
     304: bipush        127
     306: iastore
     307: putstatic     #21                 // Field code6:[I
     310: iconst_4
     311: newarray       int
     313: dup
     314: iconst_0
     315: bipush        9
     317: iastore
     318: dup
     319: iconst_1
     320: bipush        9
     322: iastore
     323: dup
     324: iconst_2
     325: bipush        32
     327: iastore
     328: dup
     329: iconst_3
     330: bipush        32
     332: iastore
     333: putstatic     #22                 // Field code7:[I
     336: iconst_4
     337: newarray       int
     339: dup
     340: iconst_0
     341: iconst_0
     342: iastore
     343: dup
     344: iconst_1
     345: bipush        31
     347: iastore
     348: dup
     349: iconst_2
     350: bipush        127
     352: iastore
     353: dup
     354: iconst_3
     355: bipush        127
     357: iastore
     358: putstatic     #23                 // Field code8:[I
     361: iconst_2
     362: newarray       int
     364: dup
     365: iconst_0
     366: bipush        48
     368: iastore
     369: dup
     370: iconst_1
     371: bipush        57
     373: iastore
     374: putstatic     #24                 // Field code9:[I
     377: iconst_2
     378: newarray       int
     380: dup
     381: iconst_0
     382: bipush        33
     384: iastore
     385: dup
     386: iconst_1
     387: bipush        126
     389: iastore
     390: putstatic     #25                 // Field code10:[I
     393: iconst_2
     394: newarray       int
     396: dup
     397: iconst_0
     398: bipush        97
     400: iastore
     401: dup
     402: iconst_1
     403: bipush        122
     405: iastore
     406: putstatic     #26                 // Field code11:[I
     409: iconst_2
     410: newarray       int
     412: dup
     413: iconst_0
     414: bipush        32
     416: iastore
     417: dup
     418: iconst_1
     419: bipush        126
     421: iastore
     422: putstatic     #27                 // Field code12:[I
     425: bipush        8
     427: newarray       int
     429: dup
     430: iconst_0
     431: bipush        33
     433: iastore
     434: dup
     435: iconst_1
     436: bipush        47
     438: iastore
     439: dup
     440: iconst_2
     441: bipush        58
     443: iastore
     444: dup
     445: iconst_3
     446: bipush        64
     448: iastore
     449: dup
     450: iconst_4
     451: bipush        91
     453: iastore
     454: dup
     455: iconst_5
     456: bipush        96
     458: iastore
     459: dup
     460: bipush        6
     462: bipush        123
     464: iastore
     465: dup
     466: bipush        7
     468: bipush        126
     470: iastore
     471: putstatic     #28                 // Field code13:[I
     474: iconst_4
     475: newarray       int
     477: dup
     478: iconst_0
     479: bipush        9
     481: iastore
     482: dup
     483: iconst_1
     484: bipush        13
     486: iastore
     487: dup
     488: iconst_2
     489: bipush        32
     491: iastore
     492: dup
     493: iconst_3
     494: bipush        32
     496: iastore
     497: putstatic     #29                 // Field code14:[I
     500: iconst_2
     501: newarray       int
     503: dup
     504: iconst_0
     505: bipush        65
     507: iastore
     508: dup
     509: iconst_1
     510: bipush        90
     512: iastore
     513: putstatic     #30                 // Field code15:[I
     516: bipush        8
     518: newarray       int
     520: dup
     521: iconst_0
     522: bipush        48
     524: iastore
     525: dup
     526: iconst_1
     527: bipush        57
     529: iastore
     530: dup
     531: iconst_2
     532: bipush        65
     534: iastore
     535: dup
     536: iconst_3
     537: bipush        90
     539: iastore
     540: dup
     541: iconst_4
     542: bipush        95
     544: iastore
     545: dup
     546: iconst_5
     547: bipush        95
     549: iastore
     550: dup
     551: bipush        6
     553: bipush        97
     555: iastore
     556: dup
     557: bipush        7
     559: bipush        122
     561: iastore
     562: putstatic     #31                 // Field code16:[I
     565: bipush        6
     567: newarray       int
     569: dup
     570: iconst_0
     571: bipush        48
     573: iastore
     574: dup
     575: iconst_1
     576: bipush        57
     578: iastore
     579: dup
     580: iconst_2
     581: bipush        65
     583: iastore
     584: dup
     585: iconst_3
     586: bipush        70
     588: iastore
     589: dup
     590: iconst_4
     591: bipush        97
     593: iastore
     594: dup
     595: iconst_5
     596: bipush        102
     598: iastore
     599: putstatic     #32                 // Field code17:[I
     602: new           #7                  // class java/util/HashMap
     605: dup
     606: invokespecial #8                  // Method java/util/HashMap."<init>":()V
     609: putstatic     #33                 // Field POSIX_GROUPS:Ljava/util/HashMap;
     612: getstatic     #33                 // Field POSIX_GROUPS:Ljava/util/HashMap;
     615: ldc           #34                 // String [:alnum:]
     617: new           #11                 // class com/google/re2j/CharGroup
     620: dup
     621: iconst_1
     622: getstatic     #19                 // Field code4:[I
     625: invokespecial #12                 // Method "<init>":(I[I)V
     628: invokevirtual #13                 // Method java/util/HashMap.put:(Ljava/lang/Object;Ljava/lang/Object;)Ljava/lang/Object;
     631: pop
     632: getstatic     #33                 // Field POSIX_GROUPS:Ljava/util/HashMap;
     635: ldc           #35                 // String [:^alnum:]
     637: new           #11                 // class com/google/re2j/CharGroup
     640: dup
     641: iconst_m1
     642: getstatic     #19                 // Field code4:[I
     645: invokespecial #12                 // Method "<init>":(I[I)V
     648: invokevirtual #13                 // Method java/util/HashMap.put:(Ljava/lang/Object;Ljava/lang/Object;)Ljava/lang/Object;
     651: pop
     652: getstatic     #33                 // Field POSIX_GROUPS:Ljava/util/HashMap;
     655: ldc           #36                 // String [:alpha:]
     657: new           #11                 // class com/google/re2j/CharGroup
     660: dup
     661: iconst_1
     662: getstatic     #20                 // Field code5:[I
     665: invokespecial #12                 // Method "<init>":(I[I)V
     668: invokevirtual #13                 // Method java/util/HashMap.put:(Ljava/lang/Object;Ljava/lang/Object;)Ljava/lang/Object;
     671: pop
     672: getstatic     #33                 // Field POSIX_GROUPS:Ljava/util/HashMap;
     675: ldc           #37                 // String [:^alpha:]
     677: new           #11                 // class com/google/re2j/CharGroup
     680: dup
     681: iconst_m1
     682: getstatic     #20                 // Field code5:[I
     685: invokespecial #12                 // Method "<init>":(I[I)V
     688: invokevirtual #13                 // Method java/util/HashMap.put:(Ljava/lang/Object;Ljava/lang/Object;)Ljava/lang/Object;
     691: pop
     692: getstatic     #33                 // Field POSIX_GROUPS:Ljava/util/HashMap;
     695: ldc           #38                 // String [:ascii:]
     697: new           #11                 // class com/google/re2j/CharGroup
     700: dup
     701: iconst_1
     702: getstatic     #21                 // Field code6:[I
     705: invokespecial #12                 // Method "<init>":(I[I)V
     708: invokevirtual #13                 // Method java/util/HashMap.put:(Ljava/lang/Object;Ljava/lang/Object;)Ljava/lang/Object;
     711: pop
     712: getstatic     #33                 // Field POSIX_GROUPS:Ljava/util/HashMap;
     715: ldc           #39                 // String [:^ascii:]
     717: new           #11                 // class com/google/re2j/CharGroup
     720: dup
     721: iconst_m1
     722: getstatic     #21                 // Field code6:[I
     725: invokespecial #12                 // Method "<init>":(I[I)V
     728: invokevirtual #13                 // Method java/util/HashMap.put:(Ljava/lang/Object;Ljava/lang/Object;)Ljava/lang/Object;
     731: pop
     732: getstatic     #33                 // Field POSIX_GROUPS:Ljava/util/HashMap;
     735: ldc           #40                 // String [:blank:]
     737: new           #11                 // class com/google/re2j/CharGroup
     740: dup
     741: iconst_1
     742: getstatic     #22                 // Field code7:[I
     745: invokespecial #12                 // Method "<init>":(I[I)V
     748: invokevirtual #13                 // Method java/util/HashMap.put:(Ljava/lang/Object;Ljava/lang/Object;)Ljava/lang/Object;
     751: pop
     752: getstatic     #33                 // Field POSIX_GROUPS:Ljava/util/HashMap;
     755: ldc           #41                 // String [:^blank:]
     757: new           #11                 // class com/google/re2j/CharGroup
     760: dup
     761: iconst_m1
     762: getstatic     #22                 // Field code7:[I
     765: invokespecial #12                 // Method "<init>":(I[I)V
     768: invokevirtual #13                 // Method java/util/HashMap.put:(Ljava/lang/Object;Ljava/lang/Object;)Ljava/lang/Object;
     771: pop
     772: getstatic     #33                 // Field POSIX_GROUPS:Ljava/util/HashMap;
     775: ldc           #42                 // String [:cntrl:]
     777: new           #11                 // class com/google/re2j/CharGroup
     780: dup
     781: iconst_1
     782: getstatic     #23                 // Field code8:[I
     785: invokespecial #12                 // Method "<init>":(I[I)V
     788: invokevirtual #13                 // Method java/util/HashMap.put:(Ljava/lang/Object;Ljava/lang/Object;)Ljava/lang/Object;
     791: pop
     792: getstatic     #33                 // Field POSIX_GROUPS:Ljava/util/HashMap;
     795: ldc           #43                 // String [:^cntrl:]
     797: new           #11                 // class com/google/re2j/CharGroup
     800: dup
     801: iconst_m1
     802: getstatic     #23                 // Field code8:[I
     805: invokespecial #12                 // Method "<init>":(I[I)V
     808: invokevirtual #13                 // Method java/util/HashMap.put:(Ljava/lang/Object;Ljava/lang/Object;)Ljava/lang/Object;
     811: pop
     812: getstatic     #33                 // Field POSIX_GROUPS:Ljava/util/HashMap;
     815: ldc           #44                 // String [:digit:]
     817: new           #11                 // class com/google/re2j/CharGroup
     820: dup
     821: iconst_1
     822: getstatic     #24                 // Field code9:[I
     825: invokespecial #12                 // Method "<init>":(I[I)V
     828: invokevirtual #13                 // Method java/util/HashMap.put:(Ljava/lang/Object;Ljava/lang/Object;)Ljava/lang/Object;
     831: pop
     832: getstatic     #33                 // Field POSIX_GROUPS:Ljava/util/HashMap;
     835: ldc           #45                 // String [:^digit:]
     837: new           #11                 // class com/google/re2j/CharGroup
     840: dup
     841: iconst_m1
     842: getstatic     #24                 // Field code9:[I
     845: invokespecial #12                 // Method "<init>":(I[I)V
     848: invokevirtual #13                 // Method java/util/HashMap.put:(Ljava/lang/Object;Ljava/lang/Object;)Ljava/lang/Object;
     851: pop
     852: getstatic     #33                 // Field POSIX_GROUPS:Ljava/util/HashMap;
     855: ldc           #46                 // String [:graph:]
     857: new           #11                 // class com/google/re2j/CharGroup
     860: dup
     861: iconst_1
     862: getstatic     #25                 // Field code10:[I
     865: invokespecial #12                 // Method "<init>":(I[I)V
     868: invokevirtual #13                 // Method java/util/HashMap.put:(Ljava/lang/Object;Ljava/lang/Object;)Ljava/lang/Object;
     871: pop
     872: getstatic     #33                 // Field POSIX_GROUPS:Ljava/util/HashMap;
     875: ldc           #47                 // String [:^graph:]
     877: new           #11                 // class com/google/re2j/CharGroup
     880: dup
     881: iconst_m1
     882: getstatic     #25                 // Field code10:[I
     885: invokespecial #12                 // Method "<init>":(I[I)V
     888: invokevirtual #13                 // Method java/util/HashMap.put:(Ljava/lang/Object;Ljava/lang/Object;)Ljava/lang/Object;
     891: pop
     892: getstatic     #33                 // Field POSIX_GROUPS:Ljava/util/HashMap;
     895: ldc           #48                 // String [:lower:]
     897: new           #11                 // class com/google/re2j/CharGroup
     900: dup
     901: iconst_1
     902: getstatic     #26                 // Field code11:[I
     905: invokespecial #12                 // Method "<init>":(I[I)V
     908: invokevirtual #13                 // Method java/util/HashMap.put:(Ljava/lang/Object;Ljava/lang/Object;)Ljava/lang/Object;
     911: pop
     912: getstatic     #33                 // Field POSIX_GROUPS:Ljava/util/HashMap;
     915: ldc           #49                 // String [:^lower:]
     917: new           #11                 // class com/google/re2j/CharGroup
     920: dup
     921: iconst_m1
     922: getstatic     #26                 // Field code11:[I
     925: invokespecial #12                 // Method "<init>":(I[I)V
     928: invokevirtual #13                 // Method java/util/HashMap.put:(Ljava/lang/Object;Ljava/lang/Object;)Ljava/lang/Object;
     931: pop
     932: getstatic     #33                 // Field POSIX_GROUPS:Ljava/util/HashMap;
     935: ldc           #50                 // String [:print:]
     937: new           #11                 // class com/google/re2j/CharGroup
     940: dup
     941: iconst_1
     942: getstatic     #27                 // Field code12:[I
     945: invokespecial #12                 // Method "<init>":(I[I)V
     948: invokevirtual #13                 // Method java/util/HashMap.put:(Ljava/lang/Object;Ljava/lang/Object;)Ljava/lang/Object;
     951: pop
     952: getstatic     #33                 // Field POSIX_GROUPS:Ljava/util/HashMap;
     955: ldc           #51                 // String [:^print:]
     957: new           #11                 // class com/google/re2j/CharGroup
     960: dup
     961: iconst_m1
     962: getstatic     #27                 // Field code12:[I
     965: invokespecial #12                 // Method "<init>":(I[I)V
     968: invokevirtual #13                 // Method java/util/HashMap.put:(Ljava/lang/Object;Ljava/lang/Object;)Ljava/lang/Object;
     971: pop
     972: getstatic     #33                 // Field POSIX_GROUPS:Ljava/util/HashMap;
     975: ldc           #52                 // String [:punct:]
     977: new           #11                 // class com/google/re2j/CharGroup
     980: dup
     981: iconst_1
     982: getstatic     #28                 // Field code13:[I
     985: invokespecial #12                 // Method "<init>":(I[I)V
     988: invokevirtual #13                 // Method java/util/HashMap.put:(Ljava/lang/Object;Ljava/lang/Object;)Ljava/lang/Object;
     991: pop
     992: getstatic     #33                 // Field POSIX_GROUPS:Ljava/util/HashMap;
     995: ldc           #53                 // String [:^punct:]
     997: new           #11                 // class com/google/re2j/CharGroup
    1000: dup
    1001: iconst_m1
    1002: getstatic     #28                 // Field code13:[I
    1005: invokespecial #12                 // Method "<init>":(I[I)V
    1008: invokevirtual #13                 // Method java/util/HashMap.put:(Ljava/lang/Object;Ljava/lang/Object;)Ljava/lang/Object;
    1011: pop
    1012: getstatic     #33                 // Field POSIX_GROUPS:Ljava/util/HashMap;
    1015: ldc           #54                 // String [:space:]
    1017: new           #11                 // class com/google/re2j/CharGroup
    1020: dup
    1021: iconst_1
    1022: getstatic     #29                 // Field code14:[I
    1025: invokespecial #12                 // Method "<init>":(I[I)V
    1028: invokevirtual #13                 // Method java/util/HashMap.put:(Ljava/lang/Object;Ljava/lang/Object;)Ljava/lang/Object;
    1031: pop
    1032: getstatic     #33                 // Field POSIX_GROUPS:Ljava/util/HashMap;
    1035: ldc           #55                 // String [:^space:]
    1037: new           #11                 // class com/google/re2j/CharGroup
    1040: dup
    1041: iconst_m1
    1042: getstatic     #29                 // Field code14:[I
    1045: invokespecial #12                 // Method "<init>":(I[I)V
    1048: invokevirtual #13                 // Method java/util/HashMap.put:(Ljava/lang/Object;Ljava/lang/Object;)Ljava/lang/Object;
    1051: pop
    1052: getstatic     #33                 // Field POSIX_GROUPS:Ljava/util/HashMap;
    1055: ldc           #56                 // String [:upper:]
    1057: new           #11                 // class com/google/re2j/CharGroup
    1060: dup
    1061: iconst_1
    1062: getstatic     #30                 // Field code15:[I
    1065: invokespecial #12                 // Method "<init>":(I[I)V
    1068: invokevirtual #13                 // Method java/util/HashMap.put:(Ljava/lang/Object;Ljava/lang/Object;)Ljava/lang/Object;
    1071: pop
    1072: getstatic     #33                 // Field POSIX_GROUPS:Ljava/util/HashMap;
    1075: ldc           #57                 // String [:^upper:]
    1077: new           #11                 // class com/google/re2j/CharGroup
    1080: dup
    1081: iconst_m1
    1082: getstatic     #30                 // Field code15:[I
    1085: invokespecial #12                 // Method "<init>":(I[I)V
    1088: invokevirtual #13                 // Method java/util/HashMap.put:(Ljava/lang/Object;Ljava/lang/Object;)Ljava/lang/Object;
    1091: pop
    1092: getstatic     #33                 // Field POSIX_GROUPS:Ljava/util/HashMap;
    1095: ldc           #58                 // String [:word:]
    1097: new           #11                 // class com/google/re2j/CharGroup
    1100: dup
    1101: iconst_1
    1102: getstatic     #31                 // Field code16:[I
    1105: invokespecial #12                 // Method "<init>":(I[I)V
    1108: invokevirtual #13                 // Method java/util/HashMap.put:(Ljava/lang/Object;Ljava/lang/Object;)Ljava/lang/Object;
    1111: pop
    1112: getstatic     #33                 // Field POSIX_GROUPS:Ljava/util/HashMap;
    1115: ldc           #59                 // String [:^word:]
    1117: new           #11                 // class com/google/re2j/CharGroup
    1120: dup
    1121: iconst_m1
    1122: getstatic     #31                 // Field code16:[I
    1125: invokespecial #12                 // Method "<init>":(I[I)V
    1128: invokevirtual #13                 // Method java/util/HashMap.put:(Ljava/lang/Object;Ljava/lang/Object;)Ljava/lang/Object;
    1131: pop
    1132: getstatic     #33                 // Field POSIX_GROUPS:Ljava/util/HashMap;
    1135: ldc           #60                 // String [:xdigit:]
    1137: new           #11                 // class com/google/re2j/CharGroup
    1140: dup
    1141: iconst_1
    1142: getstatic     #32                 // Field code17:[I
    1145: invokespecial #12                 // Method "<init>":(I[I)V
    1148: invokevirtual #13                 // Method java/util/HashMap.put:(Ljava/lang/Object;Ljava/lang/Object;)Ljava/lang/Object;
    1151: pop
    1152: getstatic     #33                 // Field POSIX_GROUPS:Ljava/util/HashMap;
    1155: ldc           #61                 // String [:^xdigit:]
    1157: new           #11                 // class com/google/re2j/CharGroup
    1160: dup
    1161: iconst_m1
    1162: getstatic     #32                 // Field code17:[I
    1165: invokespecial #12                 // Method "<init>":(I[I)V
    1168: invokevirtual #13                 // Method java/util/HashMap.put:(Ljava/lang/Object;Ljava/lang/Object;)Ljava/lang/Object;
    1171: pop
    1172: return
}
