Compiled from "ELArithmetic.java"
public abstract class org.apache.el.lang.ELArithmetic {
  public static final org.apache.el.lang.ELArithmetic$BigDecimalDelegate BIGDECIMAL;

  public static final org.apache.el.lang.ELArithmetic$BigIntegerDelegate BIGINTEGER;

  public static final org.apache.el.lang.ELArithmetic$DoubleDelegate DOUBLE;

  public static final org.apache.el.lang.ELArithmetic$LongDelegate LONG;

  private static final java.lang.Long ZERO;

  public static final java.lang.Number add(java.lang.Object, java.lang.Object);
    Code:
       0: aload_0
       1: aload_1
       2: invokestatic  #1                  // Method findDelegate:(Ljava/lang/Object;Ljava/lang/Object;)Lorg/apache/el/lang/ELArithmetic;
       5: astore_2
       6: aload_2
       7: ifnonnull     15
      10: lconst_0
      11: invokestatic  #2                  // Method java/lang/Long.valueOf:(J)Ljava/lang/Long;
      14: areturn
      15: aload_2
      16: aload_0
      17: invokevirtual #3                  // Method coerce:(Ljava/lang/Object;)Ljava/lang/Number;
      20: astore_3
      21: aload_2
      22: aload_1
      23: invokevirtual #3                  // Method coerce:(Ljava/lang/Object;)Ljava/lang/Number;
      26: astore        4
      28: aload_2
      29: aload_3
      30: aload         4
      32: invokevirtual #4                  // Method add:(Ljava/lang/Number;Ljava/lang/Number;)Ljava/lang/Number;
      35: areturn

  public static final java.lang.Number mod(java.lang.Object, java.lang.Object);
    Code:
       0: aload_0
       1: ifnonnull     13
       4: aload_1
       5: ifnonnull     13
       8: lconst_0
       9: invokestatic  #2                  // Method java/lang/Long.valueOf:(J)Ljava/lang/Long;
      12: areturn
      13: getstatic     #5                  // Field BIGDECIMAL:Lorg/apache/el/lang/ELArithmetic$BigDecimalDelegate;
      16: aload_0
      17: aload_1
      18: invokevirtual #6                  // Method org/apache/el/lang/ELArithmetic$BigDecimalDelegate.matches:(Ljava/lang/Object;Ljava/lang/Object;)Z
      21: ifeq          31
      24: getstatic     #7                  // Field DOUBLE:Lorg/apache/el/lang/ELArithmetic$DoubleDelegate;
      27: astore_2
      28: goto          71
      31: getstatic     #7                  // Field DOUBLE:Lorg/apache/el/lang/ELArithmetic$DoubleDelegate;
      34: aload_0
      35: aload_1
      36: invokevirtual #8                  // Method org/apache/el/lang/ELArithmetic$DoubleDelegate.matches:(Ljava/lang/Object;Ljava/lang/Object;)Z
      39: ifeq          49
      42: getstatic     #7                  // Field DOUBLE:Lorg/apache/el/lang/ELArithmetic$DoubleDelegate;
      45: astore_2
      46: goto          71
      49: getstatic     #9                  // Field BIGINTEGER:Lorg/apache/el/lang/ELArithmetic$BigIntegerDelegate;
      52: aload_0
      53: aload_1
      54: invokevirtual #10                 // Method org/apache/el/lang/ELArithmetic$BigIntegerDelegate.matches:(Ljava/lang/Object;Ljava/lang/Object;)Z
      57: ifeq          67
      60: getstatic     #9                  // Field BIGINTEGER:Lorg/apache/el/lang/ELArithmetic$BigIntegerDelegate;
      63: astore_2
      64: goto          71
      67: getstatic     #11                 // Field LONG:Lorg/apache/el/lang/ELArithmetic$LongDelegate;
      70: astore_2
      71: aload_2
      72: aload_0
      73: invokevirtual #3                  // Method coerce:(Ljava/lang/Object;)Ljava/lang/Number;
      76: astore_3
      77: aload_2
      78: aload_1
      79: invokevirtual #3                  // Method coerce:(Ljava/lang/Object;)Ljava/lang/Number;
      82: astore        4
      84: aload_2
      85: aload_3
      86: aload         4
      88: invokevirtual #12                 // Method mod:(Ljava/lang/Number;Ljava/lang/Number;)Ljava/lang/Number;
      91: areturn

  public static final java.lang.Number subtract(java.lang.Object, java.lang.Object);
    Code:
       0: aload_0
       1: aload_1
       2: invokestatic  #1                  // Method findDelegate:(Ljava/lang/Object;Ljava/lang/Object;)Lorg/apache/el/lang/ELArithmetic;
       5: astore_2
       6: aload_2
       7: ifnonnull     15
      10: lconst_0
      11: invokestatic  #2                  // Method java/lang/Long.valueOf:(J)Ljava/lang/Long;
      14: areturn
      15: aload_2
      16: aload_0
      17: invokevirtual #3                  // Method coerce:(Ljava/lang/Object;)Ljava/lang/Number;
      20: astore_3
      21: aload_2
      22: aload_1
      23: invokevirtual #3                  // Method coerce:(Ljava/lang/Object;)Ljava/lang/Number;
      26: astore        4
      28: aload_2
      29: aload_3
      30: aload         4
      32: invokevirtual #13                 // Method subtract:(Ljava/lang/Number;Ljava/lang/Number;)Ljava/lang/Number;
      35: areturn

  public static final java.lang.Number divide(java.lang.Object, java.lang.Object);
    Code:
       0: aload_0
       1: ifnonnull     12
       4: aload_1
       5: ifnonnull     12
       8: getstatic     #14                 // Field ZERO:Ljava/lang/Long;
      11: areturn
      12: getstatic     #5                  // Field BIGDECIMAL:Lorg/apache/el/lang/ELArithmetic$BigDecimalDelegate;
      15: aload_0
      16: aload_1
      17: invokevirtual #6                  // Method org/apache/el/lang/ELArithmetic$BigDecimalDelegate.matches:(Ljava/lang/Object;Ljava/lang/Object;)Z
      20: ifeq          30
      23: getstatic     #5                  // Field BIGDECIMAL:Lorg/apache/el/lang/ELArithmetic$BigDecimalDelegate;
      26: astore_2
      27: goto          52
      30: getstatic     #9                  // Field BIGINTEGER:Lorg/apache/el/lang/ELArithmetic$BigIntegerDelegate;
      33: aload_0
      34: aload_1
      35: invokevirtual #10                 // Method org/apache/el/lang/ELArithmetic$BigIntegerDelegate.matches:(Ljava/lang/Object;Ljava/lang/Object;)Z
      38: ifeq          48
      41: getstatic     #5                  // Field BIGDECIMAL:Lorg/apache/el/lang/ELArithmetic$BigDecimalDelegate;
      44: astore_2
      45: goto          52
      48: getstatic     #7                  // Field DOUBLE:Lorg/apache/el/lang/ELArithmetic$DoubleDelegate;
      51: astore_2
      52: aload_2
      53: aload_0
      54: invokevirtual #3                  // Method coerce:(Ljava/lang/Object;)Ljava/lang/Number;
      57: astore_3
      58: aload_2
      59: aload_1
      60: invokevirtual #3                  // Method coerce:(Ljava/lang/Object;)Ljava/lang/Number;
      63: astore        4
      65: aload_2
      66: aload_3
      67: aload         4
      69: invokevirtual #15                 // Method divide:(Ljava/lang/Number;Ljava/lang/Number;)Ljava/lang/Number;
      72: areturn

  public static final java.lang.Number multiply(java.lang.Object, java.lang.Object);
    Code:
       0: aload_0
       1: aload_1
       2: invokestatic  #1                  // Method findDelegate:(Ljava/lang/Object;Ljava/lang/Object;)Lorg/apache/el/lang/ELArithmetic;
       5: astore_2
       6: aload_2
       7: ifnonnull     15
      10: lconst_0
      11: invokestatic  #2                  // Method java/lang/Long.valueOf:(J)Ljava/lang/Long;
      14: areturn
      15: aload_2
      16: aload_0
      17: invokevirtual #3                  // Method coerce:(Ljava/lang/Object;)Ljava/lang/Number;
      20: astore_3
      21: aload_2
      22: aload_1
      23: invokevirtual #3                  // Method coerce:(Ljava/lang/Object;)Ljava/lang/Number;
      26: astore        4
      28: aload_2
      29: aload_3
      30: aload         4
      32: invokevirtual #16                 // Method multiply:(Ljava/lang/Number;Ljava/lang/Number;)Ljava/lang/Number;
      35: areturn

  private static org.apache.el.lang.ELArithmetic findDelegate(java.lang.Object, java.lang.Object);
    Code:
       0: aload_0
       1: ifnonnull     10
       4: aload_1
       5: ifnonnull     10
       8: aconst_null
       9: areturn
      10: getstatic     #5                  // Field BIGDECIMAL:Lorg/apache/el/lang/ELArithmetic$BigDecimalDelegate;
      13: aload_0
      14: aload_1
      15: invokevirtual #6                  // Method org/apache/el/lang/ELArithmetic$BigDecimalDelegate.matches:(Ljava/lang/Object;Ljava/lang/Object;)Z
      18: ifeq          25
      21: getstatic     #5                  // Field BIGDECIMAL:Lorg/apache/el/lang/ELArithmetic$BigDecimalDelegate;
      24: areturn
      25: getstatic     #7                  // Field DOUBLE:Lorg/apache/el/lang/ELArithmetic$DoubleDelegate;
      28: aload_0
      29: aload_1
      30: invokevirtual #8                  // Method org/apache/el/lang/ELArithmetic$DoubleDelegate.matches:(Ljava/lang/Object;Ljava/lang/Object;)Z
      33: ifeq          55
      36: getstatic     #9                  // Field BIGINTEGER:Lorg/apache/el/lang/ELArithmetic$BigIntegerDelegate;
      39: aload_0
      40: aload_1
      41: invokevirtual #10                 // Method org/apache/el/lang/ELArithmetic$BigIntegerDelegate.matches:(Ljava/lang/Object;Ljava/lang/Object;)Z
      44: ifeq          51
      47: getstatic     #5                  // Field BIGDECIMAL:Lorg/apache/el/lang/ELArithmetic$BigDecimalDelegate;
      50: areturn
      51: getstatic     #7                  // Field DOUBLE:Lorg/apache/el/lang/ELArithmetic$DoubleDelegate;
      54: areturn
      55: getstatic     #9                  // Field BIGINTEGER:Lorg/apache/el/lang/ELArithmetic$BigIntegerDelegate;
      58: aload_0
      59: aload_1
      60: invokevirtual #10                 // Method org/apache/el/lang/ELArithmetic$BigIntegerDelegate.matches:(Ljava/lang/Object;Ljava/lang/Object;)Z
      63: ifeq          70
      66: getstatic     #9                  // Field BIGINTEGER:Lorg/apache/el/lang/ELArithmetic$BigIntegerDelegate;
      69: areturn
      70: getstatic     #11                 // Field LONG:Lorg/apache/el/lang/ELArithmetic$LongDelegate;
      73: areturn

  public static final boolean isNumber(java.lang.Object);
    Code:
       0: aload_0
       1: ifnull        18
       4: aload_0
       5: invokevirtual #17                 // Method java/lang/Object.getClass:()Ljava/lang/Class;
       8: invokestatic  #18                 // Method isNumberType:(Ljava/lang/Class;)Z
      11: ifeq          18
      14: iconst_1
      15: goto          19
      18: iconst_0
      19: ireturn

  public static final boolean isNumberType(java.lang.Class<?>);
    Code:
       0: aload_0
       1: getstatic     #19                 // Field java/lang/Long.TYPE:Ljava/lang/Class;
       4: if_acmpeq     52
       7: aload_0
       8: getstatic     #20                 // Field java/lang/Double.TYPE:Ljava/lang/Class;
      11: if_acmpeq     52
      14: aload_0
      15: getstatic     #21                 // Field java/lang/Byte.TYPE:Ljava/lang/Class;
      18: if_acmpeq     52
      21: aload_0
      22: getstatic     #22                 // Field java/lang/Short.TYPE:Ljava/lang/Class;
      25: if_acmpeq     52
      28: aload_0
      29: getstatic     #23                 // Field java/lang/Integer.TYPE:Ljava/lang/Class;
      32: if_acmpeq     52
      35: aload_0
      36: getstatic     #24                 // Field java/lang/Float.TYPE:Ljava/lang/Class;
      39: if_acmpeq     52
      42: ldc_w         #25                 // class java/lang/Number
      45: aload_0
      46: invokevirtual #26                 // Method java/lang/Class.isAssignableFrom:(Ljava/lang/Class;)Z
      49: ifeq          56
      52: iconst_1
      53: goto          57
      56: iconst_0
      57: ireturn

  protected org.apache.el.lang.ELArithmetic();
    Code:
       0: aload_0
       1: invokespecial #27                 // Method java/lang/Object."<init>":()V
       4: return

  protected abstract java.lang.Number add(java.lang.Number, java.lang.Number);

  protected abstract java.lang.Number multiply(java.lang.Number, java.lang.Number);

  protected abstract java.lang.Number subtract(java.lang.Number, java.lang.Number);

  protected abstract java.lang.Number mod(java.lang.Number, java.lang.Number);

  protected abstract java.lang.Number coerce(java.lang.Number);

  protected final java.lang.Number coerce(java.lang.Object);
    Code:
       0: aload_1
       1: invokestatic  #28                 // Method isNumber:(Ljava/lang/Object;)Z
       4: ifeq          16
       7: aload_0
       8: aload_1
       9: checkcast     #25                 // class java/lang/Number
      12: invokevirtual #29                 // Method coerce:(Ljava/lang/Number;)Ljava/lang/Number;
      15: areturn
      16: aload_1
      17: ifnull        29
      20: ldc           #30                 // String
      22: aload_1
      23: invokevirtual #31                 // Method java/lang/String.equals:(Ljava/lang/Object;)Z
      26: ifeq          37
      29: aload_0
      30: getstatic     #14                 // Field ZERO:Ljava/lang/Long;
      33: invokevirtual #29                 // Method coerce:(Ljava/lang/Number;)Ljava/lang/Number;
      36: areturn
      37: aload_1
      38: instanceof    #32                 // class java/lang/String
      41: ifeq          53
      44: aload_0
      45: aload_1
      46: checkcast     #32                 // class java/lang/String
      49: invokevirtual #33                 // Method coerce:(Ljava/lang/String;)Ljava/lang/Number;
      52: areturn
      53: aload_1
      54: instanceof    #34                 // class java/lang/Character
      57: ifeq          76
      60: aload_0
      61: aload_1
      62: checkcast     #34                 // class java/lang/Character
      65: invokevirtual #35                 // Method java/lang/Character.charValue:()C
      68: i2s
      69: invokestatic  #36                 // Method java/lang/Short.valueOf:(S)Ljava/lang/Short;
      72: invokevirtual #29                 // Method coerce:(Ljava/lang/Number;)Ljava/lang/Number;
      75: areturn
      76: new           #37                 // class java/lang/IllegalArgumentException
      79: dup
      80: ldc           #38                 // String error.convert
      82: iconst_3
      83: anewarray     #39                 // class java/lang/Object
      86: dup
      87: iconst_0
      88: aload_1
      89: aastore
      90: dup
      91: iconst_1
      92: aload_1
      93: invokevirtual #17                 // Method java/lang/Object.getClass:()Ljava/lang/Class;
      96: aastore
      97: dup
      98: iconst_2
      99: ldc           #40                 // String Number
     101: aastore
     102: invokestatic  #41                 // Method org/apache/el/util/MessageFactory.get:(Ljava/lang/String;[Ljava/lang/Object;)Ljava/lang/String;
     105: invokespecial #42                 // Method java/lang/IllegalArgumentException."<init>":(Ljava/lang/String;)V
     108: athrow

  protected abstract java.lang.Number coerce(java.lang.String);

  protected abstract java.lang.Number divide(java.lang.Number, java.lang.Number);

  protected abstract boolean matches(java.lang.Object, java.lang.Object);

  static {};
    Code:
       0: new           #43                 // class org/apache/el/lang/ELArithmetic$BigDecimalDelegate
       3: dup
       4: invokespecial #44                 // Method org/apache/el/lang/ELArithmetic$BigDecimalDelegate."<init>":()V
       7: putstatic     #5                  // Field BIGDECIMAL:Lorg/apache/el/lang/ELArithmetic$BigDecimalDelegate;
      10: new           #45                 // class org/apache/el/lang/ELArithmetic$BigIntegerDelegate
      13: dup
      14: invokespecial #46                 // Method org/apache/el/lang/ELArithmetic$BigIntegerDelegate."<init>":()V
      17: putstatic     #9                  // Field BIGINTEGER:Lorg/apache/el/lang/ELArithmetic$BigIntegerDelegate;
      20: new           #47                 // class org/apache/el/lang/ELArithmetic$DoubleDelegate
      23: dup
      24: invokespecial #48                 // Method org/apache/el/lang/ELArithmetic$DoubleDelegate."<init>":()V
      27: putstatic     #7                  // Field DOUBLE:Lorg/apache/el/lang/ELArithmetic$DoubleDelegate;
      30: new           #49                 // class org/apache/el/lang/ELArithmetic$LongDelegate
      33: dup
      34: invokespecial #50                 // Method org/apache/el/lang/ELArithmetic$LongDelegate."<init>":()V
      37: putstatic     #11                 // Field LONG:Lorg/apache/el/lang/ELArithmetic$LongDelegate;
      40: lconst_0
      41: invokestatic  #2                  // Method java/lang/Long.valueOf:(J)Ljava/lang/Long;
      44: putstatic     #14                 // Field ZERO:Ljava/lang/Long;
      47: return
}
