Compiled from "NonResolvingResourceDescriptionResolver.java"
class org.jboss.as.controller.descriptions.NonResolvingResourceDescriptionResolver$1 extends java.util.ResourceBundle {
  final org.jboss.as.controller.descriptions.NonResolvingResourceDescriptionResolver this$0;

  org.jboss.as.controller.descriptions.NonResolvingResourceDescriptionResolver$1(org.jboss.as.controller.descriptions.NonResolvingResourceDescriptionResolver);
    Code:
       0: aload_0
       1: aload_1
       2: putfield      #1                  // Field this$0:Lorg/jboss/as/controller/descriptions/NonResolvingResourceDescriptionResolver;
       5: aload_0
       6: invokespecial #2                  // Method java/util/ResourceBundle."<init>":()V
       9: return

  protected java.lang.Object handleGetObject(java.lang.String);
    Code:
       0: aload_1
       1: areturn

  public java.util.Enumeration<java.lang.String> getKeys();
    Code:
       0: new           #3                  // class java/util/HashSet
       3: dup
       4: invokespecial #4                  // Method java/util/HashSet."<init>":()V
       7: invokestatic  #5                  // Method java/util/Collections.enumeration:(Ljava/util/Collection;)Ljava/util/Enumeration;
      10: areturn
}
