Compiled from "EchoEncoder.java"
public class ch.qos.logback.core.encoder.EchoEncoder<E> extends ch.qos.logback.core.encoder.EncoderBase<E> {
  java.lang.String fileHeader;

  java.lang.String fileFooter;

  public ch.qos.logback.core.encoder.EchoEncoder();
    Code:
       0: aload_0
       1: invokespecial #1                  // Method ch/qos/logback/core/encoder/EncoderBase."<init>":()V
       4: return

  public void doEncode(E) throws java.io.IOException;
    Code:
       0: new           #2                  // class java/lang/StringBuilder
       3: dup
       4: invokespecial #3                  // Method java/lang/StringBuilder."<init>":()V
       7: aload_1
       8: invokevirtual #4                  // Method java/lang/StringBuilder.append:(Ljava/lang/Object;)Ljava/lang/StringBuilder;
      11: getstatic     #5                  // Field ch/qos/logback/core/CoreConstants.LINE_SEPARATOR:Ljava/lang/String;
      14: invokevirtual #6                  // Method java/lang/StringBuilder.append:(Ljava/lang/String;)Ljava/lang/StringBuilder;
      17: invokevirtual #7                  // Method java/lang/StringBuilder.toString:()Ljava/lang/String;
      20: astore_2
      21: aload_0
      22: getfield      #8                  // Field outputStream:Ljava/io/OutputStream;
      25: aload_2
      26: invokevirtual #9                  // Method java/lang/String.getBytes:()[B
      29: invokevirtual #10                 // Method java/io/OutputStream.write:([B)V
      32: aload_0
      33: getfield      #8                  // Field outputStream:Ljava/io/OutputStream;
      36: invokevirtual #11                 // Method java/io/OutputStream.flush:()V
      39: return

  public void close() throws java.io.IOException;
    Code:
       0: aload_0
       1: getfield      #12                 // Field fileFooter:Ljava/lang/String;
       4: ifnonnull     8
       7: return
       8: aload_0
       9: getfield      #8                  // Field outputStream:Ljava/io/OutputStream;
      12: aload_0
      13: getfield      #12                 // Field fileFooter:Ljava/lang/String;
      16: invokevirtual #9                  // Method java/lang/String.getBytes:()[B
      19: invokevirtual #10                 // Method java/io/OutputStream.write:([B)V
      22: return

  public void init(java.io.OutputStream) throws java.io.IOException;
    Code:
       0: aload_0
       1: aload_1
       2: invokespecial #13                 // Method ch/qos/logback/core/encoder/EncoderBase.init:(Ljava/io/OutputStream;)V
       5: aload_0
       6: getfield      #14                 // Field fileHeader:Ljava/lang/String;
       9: ifnonnull     13
      12: return
      13: aload_0
      14: getfield      #8                  // Field outputStream:Ljava/io/OutputStream;
      17: aload_0
      18: getfield      #14                 // Field fileHeader:Ljava/lang/String;
      21: invokevirtual #9                  // Method java/lang/String.getBytes:()[B
      24: invokevirtual #10                 // Method java/io/OutputStream.write:([B)V
      27: return
}
