Compiled from "Document.scala"
public abstract class scala.text.Document {
  public static scala.text.Document nest(int, scala.text.Document);
    Code:
       0: getstatic     #16                 // Field scala/text/Document$.MODULE$:Lscala/text/Document$;
       3: iload_0
       4: aload_1
       5: invokevirtual #18                 // Method scala/text/Document$.nest:(ILscala/text/Document;)Lscala/text/Document;
       8: areturn

  public static scala.text.Document group(scala.text.Document);
    Code:
       0: getstatic     #16                 // Field scala/text/Document$.MODULE$:Lscala/text/Document$;
       3: aload_0
       4: invokevirtual #22                 // Method scala/text/Document$.group:(Lscala/text/Document;)Lscala/text/Document;
       7: areturn

  public static scala.text.Document text(java.lang.String);
    Code:
       0: getstatic     #16                 // Field scala/text/Document$.MODULE$:Lscala/text/Document$;
       3: aload_0
       4: invokevirtual #26                 // Method scala/text/Document$.text:(Ljava/lang/String;)Lscala/text/Document;
       7: areturn

  public static scala.text.DocBreak$ break();
    Code:
       0: getstatic     #16                 // Field scala/text/Document$.MODULE$:Lscala/text/Document$;
       3: invokevirtual #30                 // Method scala/text/Document$.break:()Lscala/text/DocBreak$;
       6: areturn

  public static scala.text.DocNil$ empty();
    Code:
       0: getstatic     #16                 // Field scala/text/Document$.MODULE$:Lscala/text/Document$;
       3: invokevirtual #34                 // Method scala/text/Document$.empty:()Lscala/text/DocNil$;
       6: areturn

  public scala.text.Document $colon$colon(scala.text.Document);
    Code:
       0: new           #37                 // class scala/text/DocCons
       3: dup
       4: aload_1
       5: aload_0
       6: invokespecial #41                 // Method scala/text/DocCons."<init>":(Lscala/text/Document;Lscala/text/Document;)V
       9: areturn

  public scala.text.Document $colon$colon(java.lang.String);
    Code:
       0: new           #37                 // class scala/text/DocCons
       3: dup
       4: new           #46                 // class scala/text/DocText
       7: dup
       8: aload_1
       9: invokespecial #49                 // Method scala/text/DocText."<init>":(Ljava/lang/String;)V
      12: aload_0
      13: invokespecial #41                 // Method scala/text/DocCons."<init>":(Lscala/text/Document;Lscala/text/Document;)V
      16: areturn

  public scala.text.Document $colon$div$colon(scala.text.Document);
    Code:
       0: getstatic     #56                 // Field scala/text/DocBreak$.MODULE$:Lscala/text/DocBreak$;
       3: astore_2
       4: aload_0
       5: aload_2
       6: invokevirtual #58                 // Method $colon$colon:(Lscala/text/Document;)Lscala/text/Document;
       9: aload_1
      10: invokevirtual #58                 // Method $colon$colon:(Lscala/text/Document;)Lscala/text/Document;
      13: areturn

  public scala.text.Document $colon$div$colon(java.lang.String);
    Code:
       0: getstatic     #56                 // Field scala/text/DocBreak$.MODULE$:Lscala/text/DocBreak$;
       3: astore_2
       4: aload_0
       5: aload_2
       6: invokevirtual #58                 // Method $colon$colon:(Lscala/text/Document;)Lscala/text/Document;
       9: aload_1
      10: invokevirtual #60                 // Method $colon$colon:(Ljava/lang/String;)Lscala/text/Document;
      13: areturn

  public void format(int, java.io.Writer);
    Code:
       0: aload_0
       1: iconst_0
       2: new           #64                 // class scala/Tuple3
       5: dup
       6: iconst_0
       7: invokestatic  #70                 // Method scala/runtime/BoxesRunTime.boxToInteger:(I)Ljava/lang/Integer;
      10: iconst_0
      11: invokestatic  #74                 // Method scala/runtime/BoxesRunTime.boxToBoolean:(Z)Ljava/lang/Boolean;
      14: new           #76                 // class scala/text/DocGroup
      17: dup
      18: aload_0
      19: invokespecial #79                 // Method scala/text/DocGroup."<init>":(Lscala/text/Document;)V
      22: invokespecial #82                 // Method scala/Tuple3."<init>":(Ljava/lang/Object;Ljava/lang/Object;Ljava/lang/Object;)V
      25: astore_3
      26: getstatic     #87                 // Field scala/collection/immutable/Nil$.MODULE$:Lscala/collection/immutable/Nil$;
      29: aload_3
      30: invokevirtual #90                 // Method scala/collection/immutable/Nil$.$colon$colon:(Ljava/lang/Object;)Lscala/collection/immutable/List;
      33: iload_1
      34: aload_2
      35: invokespecial #94                 // Method fmt$1:(ILscala/collection/immutable/List;ILjava/io/Writer;)V
      38: return

  private final boolean fits$1(int, scala.collection.immutable.List);
    Code:
       0: iconst_0
       1: istore        11
       3: aconst_null
       4: astore        13
       6: iload_1
       7: iconst_0
       8: if_icmpge     17
      11: iconst_0
      12: istore        10
      14: goto          549
      17: getstatic     #105                // Field scala/collection/immutable/List$.MODULE$:Lscala/collection/immutable/List$;
      20: aload_2
      21: invokevirtual #109                // Method scala/collection/immutable/List$.unapplySeq:(Lscala/collection/Seq;)Lscala/Some;
      24: astore_3
      25: aload_3
      26: invokevirtual #115                // Method scala/Some.isEmpty:()Z
      29: ifne          62
      32: aload_3
      33: invokevirtual #119                // Method scala/Some.get:()Ljava/lang/Object;
      36: ifnull        62
      39: aload_3
      40: invokevirtual #119                // Method scala/Some.get:()Ljava/lang/Object;
      43: checkcast     #121                // class scala/collection/LinearSeqOptimized
      46: iconst_0
      47: invokeinterface #125,  2          // InterfaceMethod scala/collection/LinearSeqOptimized.lengthCompare:(I)I
      52: iconst_0
      53: if_icmpne     62
      56: iconst_1
      57: istore        10
      59: goto          549
      62: aload_2
      63: instanceof    #127                // class scala/collection/immutable/$colon$colon
      66: ifeq          116
      69: iconst_1
      70: istore        11
      72: aload_2
      73: checkcast     #127                // class scala/collection/immutable/$colon$colon
      76: dup
      77: astore        13
      79: invokevirtual #130                // Method scala/collection/immutable/$colon$colon.head:()Ljava/lang/Object;
      82: ifnull        116
      85: getstatic     #135                // Field scala/text/DocNil$.MODULE$:Lscala/text/DocNil$;
      88: aload         13
      90: invokevirtual #130                // Method scala/collection/immutable/$colon$colon.head:()Ljava/lang/Object;
      93: checkcast     #64                 // class scala/Tuple3
      96: invokevirtual #138                // Method scala/Tuple3._3:()Ljava/lang/Object;
      99: invokevirtual #142                // Method java/lang/Object.equals:(Ljava/lang/Object;)Z
     102: ifeq          116
     105: iload_1
     106: aload         13
     108: invokevirtual #146                // Method scala/collection/immutable/$colon$colon.tl$1:()Lscala/collection/immutable/List;
     111: astore_2
     112: istore_1
     113: goto          0
     116: iload         11
     118: ifeq          255
     121: aload         13
     123: invokevirtual #130                // Method scala/collection/immutable/$colon$colon.head:()Ljava/lang/Object;
     126: ifnull        255
     129: aload         13
     131: invokevirtual #130                // Method scala/collection/immutable/$colon$colon.head:()Ljava/lang/Object;
     134: checkcast     #64                 // class scala/Tuple3
     137: invokevirtual #138                // Method scala/Tuple3._3:()Ljava/lang/Object;
     140: instanceof    #37                 // class scala/text/DocCons
     143: ifeq          255
     146: aload         13
     148: invokevirtual #130                // Method scala/collection/immutable/$colon$colon.head:()Ljava/lang/Object;
     151: checkcast     #64                 // class scala/Tuple3
     154: invokevirtual #138                // Method scala/Tuple3._3:()Ljava/lang/Object;
     157: checkcast     #37                 // class scala/text/DocCons
     160: astore        4
     162: iload_1
     163: new           #64                 // class scala/Tuple3
     166: dup
     167: aload         13
     169: invokevirtual #130                // Method scala/collection/immutable/$colon$colon.head:()Ljava/lang/Object;
     172: checkcast     #64                 // class scala/Tuple3
     175: invokevirtual #149                // Method scala/Tuple3._1:()Ljava/lang/Object;
     178: aload         13
     180: invokevirtual #130                // Method scala/collection/immutable/$colon$colon.head:()Ljava/lang/Object;
     183: checkcast     #64                 // class scala/Tuple3
     186: invokevirtual #152                // Method scala/Tuple3._2:()Ljava/lang/Object;
     189: aload         4
     191: invokevirtual #155                // Method scala/text/DocCons.hd:()Lscala/text/Document;
     194: invokespecial #82                 // Method scala/Tuple3."<init>":(Ljava/lang/Object;Ljava/lang/Object;Ljava/lang/Object;)V
     197: astore        6
     199: new           #64                 // class scala/Tuple3
     202: dup
     203: aload         13
     205: invokevirtual #130                // Method scala/collection/immutable/$colon$colon.head:()Ljava/lang/Object;
     208: checkcast     #64                 // class scala/Tuple3
     211: invokevirtual #149                // Method scala/Tuple3._1:()Ljava/lang/Object;
     214: aload         13
     216: invokevirtual #130                // Method scala/collection/immutable/$colon$colon.head:()Ljava/lang/Object;
     219: checkcast     #64                 // class scala/Tuple3
     222: invokevirtual #152                // Method scala/Tuple3._2:()Ljava/lang/Object;
     225: aload         4
     227: invokevirtual #158                // Method scala/text/DocCons.tl:()Lscala/text/Document;
     230: invokespecial #82                 // Method scala/Tuple3."<init>":(Ljava/lang/Object;Ljava/lang/Object;Ljava/lang/Object;)V
     233: astore        5
     235: aload         13
     237: invokevirtual #146                // Method scala/collection/immutable/$colon$colon.tl$1:()Lscala/collection/immutable/List;
     240: aload         5
     242: invokevirtual #161                // Method scala/collection/immutable/List.$colon$colon:(Ljava/lang/Object;)Lscala/collection/immutable/List;
     245: aload         6
     247: invokevirtual #161                // Method scala/collection/immutable/List.$colon$colon:(Ljava/lang/Object;)Lscala/collection/immutable/List;
     250: astore_2
     251: istore_1
     252: goto          0
     255: iload         11
     257: ifeq          321
     260: aload         13
     262: invokevirtual #130                // Method scala/collection/immutable/$colon$colon.head:()Ljava/lang/Object;
     265: ifnull        321
     268: aload         13
     270: invokevirtual #130                // Method scala/collection/immutable/$colon$colon.head:()Ljava/lang/Object;
     273: checkcast     #64                 // class scala/Tuple3
     276: invokevirtual #138                // Method scala/Tuple3._3:()Ljava/lang/Object;
     279: instanceof    #46                 // class scala/text/DocText
     282: ifeq          321
     285: aload         13
     287: invokevirtual #130                // Method scala/collection/immutable/$colon$colon.head:()Ljava/lang/Object;
     290: checkcast     #64                 // class scala/Tuple3
     293: invokevirtual #138                // Method scala/Tuple3._3:()Ljava/lang/Object;
     296: checkcast     #46                 // class scala/text/DocText
     299: astore        7
     301: iload_1
     302: aload         7
     304: invokevirtual #165                // Method scala/text/DocText.txt:()Ljava/lang/String;
     307: invokevirtual #171                // Method java/lang/String.length:()I
     310: isub
     311: aload         13
     313: invokevirtual #146                // Method scala/collection/immutable/$colon$colon.tl$1:()Lscala/collection/immutable/List;
     316: astore_2
     317: istore_1
     318: goto          0
     321: iload         11
     323: ifeq          431
     326: aload         13
     328: invokevirtual #130                // Method scala/collection/immutable/$colon$colon.head:()Ljava/lang/Object;
     331: ifnull        431
     334: aload         13
     336: invokevirtual #130                // Method scala/collection/immutable/$colon$colon.head:()Ljava/lang/Object;
     339: checkcast     #64                 // class scala/Tuple3
     342: invokevirtual #138                // Method scala/Tuple3._3:()Ljava/lang/Object;
     345: instanceof    #173                // class scala/text/DocNest
     348: ifeq          431
     351: aload         13
     353: invokevirtual #130                // Method scala/collection/immutable/$colon$colon.head:()Ljava/lang/Object;
     356: checkcast     #64                 // class scala/Tuple3
     359: invokevirtual #138                // Method scala/Tuple3._3:()Ljava/lang/Object;
     362: checkcast     #173                // class scala/text/DocNest
     365: astore        8
     367: iload_1
     368: new           #64                 // class scala/Tuple3
     371: dup
     372: aload         13
     374: invokevirtual #130                // Method scala/collection/immutable/$colon$colon.head:()Ljava/lang/Object;
     377: checkcast     #64                 // class scala/Tuple3
     380: invokevirtual #149                // Method scala/Tuple3._1:()Ljava/lang/Object;
     383: invokestatic  #177                // Method scala/runtime/BoxesRunTime.unboxToInt:(Ljava/lang/Object;)I
     386: aload         8
     388: invokevirtual #180                // Method scala/text/DocNest.indent:()I
     391: iadd
     392: invokestatic  #70                 // Method scala/runtime/BoxesRunTime.boxToInteger:(I)Ljava/lang/Integer;
     395: aload         13
     397: invokevirtual #130                // Method scala/collection/immutable/$colon$colon.head:()Ljava/lang/Object;
     400: checkcast     #64                 // class scala/Tuple3
     403: invokevirtual #152                // Method scala/Tuple3._2:()Ljava/lang/Object;
     406: aload         8
     408: invokevirtual #183                // Method scala/text/DocNest.doc:()Lscala/text/Document;
     411: invokespecial #82                 // Method scala/Tuple3."<init>":(Ljava/lang/Object;Ljava/lang/Object;Ljava/lang/Object;)V
     414: astore        9
     416: aload         13
     418: invokevirtual #146                // Method scala/collection/immutable/$colon$colon.tl$1:()Lscala/collection/immutable/List;
     421: aload         9
     423: invokevirtual #161                // Method scala/collection/immutable/List.$colon$colon:(Ljava/lang/Object;)Lscala/collection/immutable/List;
     426: astore_2
     427: istore_1
     428: goto          0
     431: iload         11
     433: ifeq          495
     436: aload         13
     438: invokevirtual #130                // Method scala/collection/immutable/$colon$colon.head:()Ljava/lang/Object;
     441: ifnull        495
     444: iconst_0
     445: aload         13
     447: invokevirtual #130                // Method scala/collection/immutable/$colon$colon.head:()Ljava/lang/Object;
     450: checkcast     #64                 // class scala/Tuple3
     453: invokevirtual #152                // Method scala/Tuple3._2:()Ljava/lang/Object;
     456: invokestatic  #186                // Method scala/runtime/BoxesRunTime.unboxToBoolean:(Ljava/lang/Object;)Z
     459: if_icmpne     495
     462: getstatic     #56                 // Field scala/text/DocBreak$.MODULE$:Lscala/text/DocBreak$;
     465: aload         13
     467: invokevirtual #130                // Method scala/collection/immutable/$colon$colon.head:()Ljava/lang/Object;
     470: checkcast     #64                 // class scala/Tuple3
     473: invokevirtual #138                // Method scala/Tuple3._3:()Ljava/lang/Object;
     476: invokevirtual #142                // Method java/lang/Object.equals:(Ljava/lang/Object;)Z
     479: ifeq          495
     482: iload_1
     483: iconst_1
     484: isub
     485: aload         13
     487: invokevirtual #146                // Method scala/collection/immutable/$colon$colon.tl$1:()Lscala/collection/immutable/List;
     490: astore_2
     491: istore_1
     492: goto          0
     495: iload         11
     497: ifeq          552
     500: aload         13
     502: invokevirtual #130                // Method scala/collection/immutable/$colon$colon.head:()Ljava/lang/Object;
     505: ifnull        552
     508: iconst_1
     509: aload         13
     511: invokevirtual #130                // Method scala/collection/immutable/$colon$colon.head:()Ljava/lang/Object;
     514: checkcast     #64                 // class scala/Tuple3
     517: invokevirtual #152                // Method scala/Tuple3._2:()Ljava/lang/Object;
     520: invokestatic  #186                // Method scala/runtime/BoxesRunTime.unboxToBoolean:(Ljava/lang/Object;)Z
     523: if_icmpne     552
     526: getstatic     #56                 // Field scala/text/DocBreak$.MODULE$:Lscala/text/DocBreak$;
     529: aload         13
     531: invokevirtual #130                // Method scala/collection/immutable/$colon$colon.head:()Ljava/lang/Object;
     534: checkcast     #64                 // class scala/Tuple3
     537: invokevirtual #138                // Method scala/Tuple3._3:()Ljava/lang/Object;
     540: invokevirtual #142                // Method java/lang/Object.equals:(Ljava/lang/Object;)Z
     543: ifeq          552
     546: iconst_1
     547: istore        10
     549: iload         10
     551: ireturn
     552: iload         11
     554: ifeq          643
     557: aload         13
     559: invokevirtual #130                // Method scala/collection/immutable/$colon$colon.head:()Ljava/lang/Object;
     562: ifnull        643
     565: aload         13
     567: invokevirtual #130                // Method scala/collection/immutable/$colon$colon.head:()Ljava/lang/Object;
     570: checkcast     #64                 // class scala/Tuple3
     573: invokevirtual #138                // Method scala/Tuple3._3:()Ljava/lang/Object;
     576: instanceof    #76                 // class scala/text/DocGroup
     579: ifeq          643
     582: aload         13
     584: invokevirtual #130                // Method scala/collection/immutable/$colon$colon.head:()Ljava/lang/Object;
     587: checkcast     #64                 // class scala/Tuple3
     590: invokevirtual #138                // Method scala/Tuple3._3:()Ljava/lang/Object;
     593: checkcast     #76                 // class scala/text/DocGroup
     596: astore        12
     598: iload_1
     599: new           #64                 // class scala/Tuple3
     602: dup
     603: aload         13
     605: invokevirtual #130                // Method scala/collection/immutable/$colon$colon.head:()Ljava/lang/Object;
     608: checkcast     #64                 // class scala/Tuple3
     611: invokevirtual #149                // Method scala/Tuple3._1:()Ljava/lang/Object;
     614: iconst_0
     615: invokestatic  #74                 // Method scala/runtime/BoxesRunTime.boxToBoolean:(Z)Ljava/lang/Boolean;
     618: aload         12
     620: invokevirtual #187                // Method scala/text/DocGroup.doc:()Lscala/text/Document;
     623: invokespecial #82                 // Method scala/Tuple3."<init>":(Ljava/lang/Object;Ljava/lang/Object;Ljava/lang/Object;)V
     626: astore        14
     628: aload         13
     630: invokevirtual #146                // Method scala/collection/immutable/$colon$colon.tl$1:()Lscala/collection/immutable/List;
     633: aload         14
     635: invokevirtual #161                // Method scala/collection/immutable/List.$colon$colon:(Ljava/lang/Object;)Lscala/collection/immutable/List;
     638: astore_2
     639: istore_1
     640: goto          0
     643: new           #189                // class scala/MatchError
     646: dup
     647: aload_2
     648: invokespecial #192                // Method scala/MatchError."<init>":(Ljava/lang/Object;)V
     651: athrow

  private final void spaces$1(int, java.io.Writer);
    Code:
       0: iload_1
       1: istore_3
       2: iload_3
       3: bipush        16
       5: if_icmplt     22
       8: aload_2
       9: ldc           #198                // String
      11: invokevirtual #203                // Method java/io/Writer.write:(Ljava/lang/String;)V
      14: iload_3
      15: bipush        16
      17: isub
      18: istore_3
      19: goto          2
      22: iload_3
      23: bipush        8
      25: if_icmplt     39
      28: aload_2
      29: ldc           #205                // String
      31: invokevirtual #203                // Method java/io/Writer.write:(Ljava/lang/String;)V
      34: iload_3
      35: bipush        8
      37: isub
      38: istore_3
      39: iload_3
      40: iconst_4
      41: if_icmplt     54
      44: aload_2
      45: ldc           #207                // String
      47: invokevirtual #203                // Method java/io/Writer.write:(Ljava/lang/String;)V
      50: iload_3
      51: iconst_4
      52: isub
      53: istore_3
      54: iload_3
      55: iconst_2
      56: if_icmplt     69
      59: aload_2
      60: ldc           #209                // String
      62: invokevirtual #203                // Method java/io/Writer.write:(Ljava/lang/String;)V
      65: iload_3
      66: iconst_2
      67: isub
      68: istore_3
      69: iload_3
      70: iconst_1
      71: if_icmpne     80
      74: aload_2
      75: ldc           #211                // String
      77: invokevirtual #203                // Method java/io/Writer.write:(Ljava/lang/String;)V
      80: return

  private final void fmt$1(int, scala.collection.immutable.List, int, java.io.Writer);
    Code:
       0: iconst_0
       1: istore        12
       3: aconst_null
       4: astore        16
       6: getstatic     #105                // Field scala/collection/immutable/List$.MODULE$:Lscala/collection/immutable/List$;
       9: aload_2
      10: invokevirtual #109                // Method scala/collection/immutable/List$.unapplySeq:(Lscala/collection/Seq;)Lscala/Some;
      13: astore        5
      15: aload         5
      17: invokevirtual #115                // Method scala/Some.isEmpty:()Z
      20: ifne          56
      23: aload         5
      25: invokevirtual #119                // Method scala/Some.get:()Ljava/lang/Object;
      28: ifnull        56
      31: aload         5
      33: invokevirtual #119                // Method scala/Some.get:()Ljava/lang/Object;
      36: checkcast     #121                // class scala/collection/LinearSeqOptimized
      39: iconst_0
      40: invokeinterface #125,  2          // InterfaceMethod scala/collection/LinearSeqOptimized.lengthCompare:(I)I
      45: iconst_0
      46: if_icmpne     56
      49: getstatic     #220                // Field scala/runtime/BoxedUnit.UNIT:Lscala/runtime/BoxedUnit;
      52: pop
      53: goto          760
      56: aload_2
      57: instanceof    #127                // class scala/collection/immutable/$colon$colon
      60: ifeq          110
      63: iconst_1
      64: istore        12
      66: aload_2
      67: checkcast     #127                // class scala/collection/immutable/$colon$colon
      70: dup
      71: astore        16
      73: invokevirtual #130                // Method scala/collection/immutable/$colon$colon.head:()Ljava/lang/Object;
      76: ifnull        110
      79: getstatic     #135                // Field scala/text/DocNil$.MODULE$:Lscala/text/DocNil$;
      82: aload         16
      84: invokevirtual #130                // Method scala/collection/immutable/$colon$colon.head:()Ljava/lang/Object;
      87: checkcast     #64                 // class scala/Tuple3
      90: invokevirtual #138                // Method scala/Tuple3._3:()Ljava/lang/Object;
      93: invokevirtual #142                // Method java/lang/Object.equals:(Ljava/lang/Object;)Z
      96: ifeq          110
      99: iload_1
     100: aload         16
     102: invokevirtual #146                // Method scala/collection/immutable/$colon$colon.tl$1:()Lscala/collection/immutable/List;
     105: astore_2
     106: istore_1
     107: goto          0
     110: iload         12
     112: ifeq          249
     115: aload         16
     117: invokevirtual #130                // Method scala/collection/immutable/$colon$colon.head:()Ljava/lang/Object;
     120: ifnull        249
     123: aload         16
     125: invokevirtual #130                // Method scala/collection/immutable/$colon$colon.head:()Ljava/lang/Object;
     128: checkcast     #64                 // class scala/Tuple3
     131: invokevirtual #138                // Method scala/Tuple3._3:()Ljava/lang/Object;
     134: instanceof    #37                 // class scala/text/DocCons
     137: ifeq          249
     140: aload         16
     142: invokevirtual #130                // Method scala/collection/immutable/$colon$colon.head:()Ljava/lang/Object;
     145: checkcast     #64                 // class scala/Tuple3
     148: invokevirtual #138                // Method scala/Tuple3._3:()Ljava/lang/Object;
     151: checkcast     #37                 // class scala/text/DocCons
     154: astore        6
     156: iload_1
     157: new           #64                 // class scala/Tuple3
     160: dup
     161: aload         16
     163: invokevirtual #130                // Method scala/collection/immutable/$colon$colon.head:()Ljava/lang/Object;
     166: checkcast     #64                 // class scala/Tuple3
     169: invokevirtual #149                // Method scala/Tuple3._1:()Ljava/lang/Object;
     172: aload         16
     174: invokevirtual #130                // Method scala/collection/immutable/$colon$colon.head:()Ljava/lang/Object;
     177: checkcast     #64                 // class scala/Tuple3
     180: invokevirtual #152                // Method scala/Tuple3._2:()Ljava/lang/Object;
     183: aload         6
     185: invokevirtual #155                // Method scala/text/DocCons.hd:()Lscala/text/Document;
     188: invokespecial #82                 // Method scala/Tuple3."<init>":(Ljava/lang/Object;Ljava/lang/Object;Ljava/lang/Object;)V
     191: astore        8
     193: new           #64                 // class scala/Tuple3
     196: dup
     197: aload         16
     199: invokevirtual #130                // Method scala/collection/immutable/$colon$colon.head:()Ljava/lang/Object;
     202: checkcast     #64                 // class scala/Tuple3
     205: invokevirtual #149                // Method scala/Tuple3._1:()Ljava/lang/Object;
     208: aload         16
     210: invokevirtual #130                // Method scala/collection/immutable/$colon$colon.head:()Ljava/lang/Object;
     213: checkcast     #64                 // class scala/Tuple3
     216: invokevirtual #152                // Method scala/Tuple3._2:()Ljava/lang/Object;
     219: aload         6
     221: invokevirtual #158                // Method scala/text/DocCons.tl:()Lscala/text/Document;
     224: invokespecial #82                 // Method scala/Tuple3."<init>":(Ljava/lang/Object;Ljava/lang/Object;Ljava/lang/Object;)V
     227: astore        7
     229: aload         16
     231: invokevirtual #146                // Method scala/collection/immutable/$colon$colon.tl$1:()Lscala/collection/immutable/List;
     234: aload         7
     236: invokevirtual #161                // Method scala/collection/immutable/List.$colon$colon:(Ljava/lang/Object;)Lscala/collection/immutable/List;
     239: aload         8
     241: invokevirtual #161                // Method scala/collection/immutable/List.$colon$colon:(Ljava/lang/Object;)Lscala/collection/immutable/List;
     244: astore_2
     245: istore_1
     246: goto          0
     249: iload         12
     251: ifeq          325
     254: aload         16
     256: invokevirtual #130                // Method scala/collection/immutable/$colon$colon.head:()Ljava/lang/Object;
     259: ifnull        325
     262: aload         16
     264: invokevirtual #130                // Method scala/collection/immutable/$colon$colon.head:()Ljava/lang/Object;
     267: checkcast     #64                 // class scala/Tuple3
     270: invokevirtual #138                // Method scala/Tuple3._3:()Ljava/lang/Object;
     273: instanceof    #46                 // class scala/text/DocText
     276: ifeq          325
     279: aload         16
     281: invokevirtual #130                // Method scala/collection/immutable/$colon$colon.head:()Ljava/lang/Object;
     284: checkcast     #64                 // class scala/Tuple3
     287: invokevirtual #138                // Method scala/Tuple3._3:()Ljava/lang/Object;
     290: checkcast     #46                 // class scala/text/DocText
     293: astore        9
     295: aload         4
     297: aload         9
     299: invokevirtual #165                // Method scala/text/DocText.txt:()Ljava/lang/String;
     302: invokevirtual #203                // Method java/io/Writer.write:(Ljava/lang/String;)V
     305: iload_1
     306: aload         9
     308: invokevirtual #165                // Method scala/text/DocText.txt:()Ljava/lang/String;
     311: invokevirtual #171                // Method java/lang/String.length:()I
     314: iadd
     315: aload         16
     317: invokevirtual #146                // Method scala/collection/immutable/$colon$colon.tl$1:()Lscala/collection/immutable/List;
     320: astore_2
     321: istore_1
     322: goto          0
     325: iload         12
     327: ifeq          435
     330: aload         16
     332: invokevirtual #130                // Method scala/collection/immutable/$colon$colon.head:()Ljava/lang/Object;
     335: ifnull        435
     338: aload         16
     340: invokevirtual #130                // Method scala/collection/immutable/$colon$colon.head:()Ljava/lang/Object;
     343: checkcast     #64                 // class scala/Tuple3
     346: invokevirtual #138                // Method scala/Tuple3._3:()Ljava/lang/Object;
     349: instanceof    #173                // class scala/text/DocNest
     352: ifeq          435
     355: aload         16
     357: invokevirtual #130                // Method scala/collection/immutable/$colon$colon.head:()Ljava/lang/Object;
     360: checkcast     #64                 // class scala/Tuple3
     363: invokevirtual #138                // Method scala/Tuple3._3:()Ljava/lang/Object;
     366: checkcast     #173                // class scala/text/DocNest
     369: astore        10
     371: iload_1
     372: new           #64                 // class scala/Tuple3
     375: dup
     376: aload         16
     378: invokevirtual #130                // Method scala/collection/immutable/$colon$colon.head:()Ljava/lang/Object;
     381: checkcast     #64                 // class scala/Tuple3
     384: invokevirtual #149                // Method scala/Tuple3._1:()Ljava/lang/Object;
     387: invokestatic  #177                // Method scala/runtime/BoxesRunTime.unboxToInt:(Ljava/lang/Object;)I
     390: aload         10
     392: invokevirtual #180                // Method scala/text/DocNest.indent:()I
     395: iadd
     396: invokestatic  #70                 // Method scala/runtime/BoxesRunTime.boxToInteger:(I)Ljava/lang/Integer;
     399: aload         16
     401: invokevirtual #130                // Method scala/collection/immutable/$colon$colon.head:()Ljava/lang/Object;
     404: checkcast     #64                 // class scala/Tuple3
     407: invokevirtual #152                // Method scala/Tuple3._2:()Ljava/lang/Object;
     410: aload         10
     412: invokevirtual #183                // Method scala/text/DocNest.doc:()Lscala/text/Document;
     415: invokespecial #82                 // Method scala/Tuple3."<init>":(Ljava/lang/Object;Ljava/lang/Object;Ljava/lang/Object;)V
     418: astore        11
     420: aload         16
     422: invokevirtual #146                // Method scala/collection/immutable/$colon$colon.tl$1:()Lscala/collection/immutable/List;
     425: aload         11
     427: invokevirtual #161                // Method scala/collection/immutable/List.$colon$colon:(Ljava/lang/Object;)Lscala/collection/immutable/List;
     430: astore_2
     431: istore_1
     432: goto          0
     435: iload         12
     437: ifeq          537
     440: aload         16
     442: invokevirtual #130                // Method scala/collection/immutable/$colon$colon.head:()Ljava/lang/Object;
     445: ifnull        537
     448: iconst_1
     449: aload         16
     451: invokevirtual #130                // Method scala/collection/immutable/$colon$colon.head:()Ljava/lang/Object;
     454: checkcast     #64                 // class scala/Tuple3
     457: invokevirtual #152                // Method scala/Tuple3._2:()Ljava/lang/Object;
     460: invokestatic  #186                // Method scala/runtime/BoxesRunTime.unboxToBoolean:(Ljava/lang/Object;)Z
     463: if_icmpne     537
     466: getstatic     #56                 // Field scala/text/DocBreak$.MODULE$:Lscala/text/DocBreak$;
     469: aload         16
     471: invokevirtual #130                // Method scala/collection/immutable/$colon$colon.head:()Ljava/lang/Object;
     474: checkcast     #64                 // class scala/Tuple3
     477: invokevirtual #138                // Method scala/Tuple3._3:()Ljava/lang/Object;
     480: invokevirtual #142                // Method java/lang/Object.equals:(Ljava/lang/Object;)Z
     483: ifeq          537
     486: aload         4
     488: ldc           #222                // String \n
     490: invokevirtual #203                // Method java/io/Writer.write:(Ljava/lang/String;)V
     493: aload_0
     494: aload         16
     496: invokevirtual #130                // Method scala/collection/immutable/$colon$colon.head:()Ljava/lang/Object;
     499: checkcast     #64                 // class scala/Tuple3
     502: invokevirtual #149                // Method scala/Tuple3._1:()Ljava/lang/Object;
     505: invokestatic  #177                // Method scala/runtime/BoxesRunTime.unboxToInt:(Ljava/lang/Object;)I
     508: aload         4
     510: invokespecial #224                // Method spaces$1:(ILjava/io/Writer;)V
     513: aload         16
     515: invokevirtual #130                // Method scala/collection/immutable/$colon$colon.head:()Ljava/lang/Object;
     518: checkcast     #64                 // class scala/Tuple3
     521: invokevirtual #149                // Method scala/Tuple3._1:()Ljava/lang/Object;
     524: invokestatic  #177                // Method scala/runtime/BoxesRunTime.unboxToInt:(Ljava/lang/Object;)I
     527: aload         16
     529: invokevirtual #146                // Method scala/collection/immutable/$colon$colon.tl$1:()Lscala/collection/immutable/List;
     532: astore_2
     533: istore_1
     534: goto          0
     537: iload         12
     539: ifeq          608
     542: aload         16
     544: invokevirtual #130                // Method scala/collection/immutable/$colon$colon.head:()Ljava/lang/Object;
     547: ifnull        608
     550: iconst_0
     551: aload         16
     553: invokevirtual #130                // Method scala/collection/immutable/$colon$colon.head:()Ljava/lang/Object;
     556: checkcast     #64                 // class scala/Tuple3
     559: invokevirtual #152                // Method scala/Tuple3._2:()Ljava/lang/Object;
     562: invokestatic  #186                // Method scala/runtime/BoxesRunTime.unboxToBoolean:(Ljava/lang/Object;)Z
     565: if_icmpne     608
     568: getstatic     #56                 // Field scala/text/DocBreak$.MODULE$:Lscala/text/DocBreak$;
     571: aload         16
     573: invokevirtual #130                // Method scala/collection/immutable/$colon$colon.head:()Ljava/lang/Object;
     576: checkcast     #64                 // class scala/Tuple3
     579: invokevirtual #138                // Method scala/Tuple3._3:()Ljava/lang/Object;
     582: invokevirtual #142                // Method java/lang/Object.equals:(Ljava/lang/Object;)Z
     585: ifeq          608
     588: aload         4
     590: ldc           #211                // String
     592: invokevirtual #203                // Method java/io/Writer.write:(Ljava/lang/String;)V
     595: iload_1
     596: iconst_1
     597: iadd
     598: aload         16
     600: invokevirtual #146                // Method scala/collection/immutable/$colon$colon.tl$1:()Lscala/collection/immutable/List;
     603: astore_2
     604: istore_1
     605: goto          0
     608: iload         12
     610: ifeq          756
     613: aload         16
     615: invokevirtual #130                // Method scala/collection/immutable/$colon$colon.head:()Ljava/lang/Object;
     618: ifnull        756
     621: aload         16
     623: invokevirtual #130                // Method scala/collection/immutable/$colon$colon.head:()Ljava/lang/Object;
     626: checkcast     #64                 // class scala/Tuple3
     629: invokevirtual #138                // Method scala/Tuple3._3:()Ljava/lang/Object;
     632: instanceof    #76                 // class scala/text/DocGroup
     635: ifeq          756
     638: aload         16
     640: invokevirtual #130                // Method scala/collection/immutable/$colon$colon.head:()Ljava/lang/Object;
     643: checkcast     #64                 // class scala/Tuple3
     646: invokevirtual #138                // Method scala/Tuple3._3:()Ljava/lang/Object;
     649: checkcast     #76                 // class scala/text/DocGroup
     652: astore        15
     654: aload_0
     655: iload_3
     656: iload_1
     657: isub
     658: new           #64                 // class scala/Tuple3
     661: dup
     662: aload         16
     664: invokevirtual #130                // Method scala/collection/immutable/$colon$colon.head:()Ljava/lang/Object;
     667: checkcast     #64                 // class scala/Tuple3
     670: invokevirtual #149                // Method scala/Tuple3._1:()Ljava/lang/Object;
     673: iconst_0
     674: invokestatic  #74                 // Method scala/runtime/BoxesRunTime.boxToBoolean:(Z)Ljava/lang/Boolean;
     677: aload         15
     679: invokevirtual #187                // Method scala/text/DocGroup.doc:()Lscala/text/Document;
     682: invokespecial #82                 // Method scala/Tuple3."<init>":(Ljava/lang/Object;Ljava/lang/Object;Ljava/lang/Object;)V
     685: astore        13
     687: aload         16
     689: invokevirtual #146                // Method scala/collection/immutable/$colon$colon.tl$1:()Lscala/collection/immutable/List;
     692: aload         13
     694: invokevirtual #161                // Method scala/collection/immutable/List.$colon$colon:(Ljava/lang/Object;)Lscala/collection/immutable/List;
     697: invokespecial #226                // Method fits$1:(ILscala/collection/immutable/List;)Z
     700: istore        14
     702: iload_1
     703: new           #64                 // class scala/Tuple3
     706: dup
     707: aload         16
     709: invokevirtual #130                // Method scala/collection/immutable/$colon$colon.head:()Ljava/lang/Object;
     712: checkcast     #64                 // class scala/Tuple3
     715: invokevirtual #149                // Method scala/Tuple3._1:()Ljava/lang/Object;
     718: iload         14
     720: ifeq          727
     723: iconst_0
     724: goto          728
     727: iconst_1
     728: invokestatic  #74                 // Method scala/runtime/BoxesRunTime.boxToBoolean:(Z)Ljava/lang/Boolean;
     731: aload         15
     733: invokevirtual #187                // Method scala/text/DocGroup.doc:()Lscala/text/Document;
     736: invokespecial #82                 // Method scala/Tuple3."<init>":(Ljava/lang/Object;Ljava/lang/Object;Ljava/lang/Object;)V
     739: astore        17
     741: aload         16
     743: invokevirtual #146                // Method scala/collection/immutable/$colon$colon.tl$1:()Lscala/collection/immutable/List;
     746: aload         17
     748: invokevirtual #161                // Method scala/collection/immutable/List.$colon$colon:(Ljava/lang/Object;)Lscala/collection/immutable/List;
     751: astore_2
     752: istore_1
     753: goto          0
     756: getstatic     #220                // Field scala/runtime/BoxedUnit.UNIT:Lscala/runtime/BoxedUnit;
     759: pop
     760: getstatic     #220                // Field scala/runtime/BoxedUnit.UNIT:Lscala/runtime/BoxedUnit;
     763: pop
     764: return

  public scala.text.Document();
    Code:
       0: aload_0
       1: invokespecial #233                // Method java/lang/Object."<init>":()V
       4: return
}
