Compiled from "DbEntityReadHelper.java"
public final class ru.tinkoff.kora.database.annotation.processor.DbEntityReadHelper$ReadEntityCodeBlock extends java.lang.Record {
  private final com.squareup.javapoet.CodeBlock block;

  private final java.util.List<ru.tinkoff.kora.database.annotation.processor.DbEntityReadHelper$RequiredField> requiredFields;

  public ru.tinkoff.kora.database.annotation.processor.DbEntityReadHelper$ReadEntityCodeBlock(com.squareup.javapoet.CodeBlock, java.util.List<ru.tinkoff.kora.database.annotation.processor.DbEntityReadHelper$RequiredField>);
    Code:
       0: aload_0
       1: invokespecial #1                  // Method java/lang/Record."<init>":()V
       4: aload_0
       5: aload_1
       6: putfield      #7                  // Field block:Lcom/squareup/javapoet/CodeBlock;
       9: aload_0
      10: aload_2
      11: putfield      #13                 // Field requiredFields:Ljava/util/List;
      14: return

  public void enrich(com.squareup.javapoet.TypeSpec$Builder, com.squareup.javapoet.MethodSpec$Builder);
    Code:
       0: aload_0
       1: getfield      #13                 // Field requiredFields:Ljava/util/List;
       4: invokeinterface #17,  1           // InterfaceMethod java/util/List.iterator:()Ljava/util/Iterator;
       9: astore_3
      10: aload_3
      11: invokeinterface #23,  1           // InterfaceMethod java/util/Iterator.hasNext:()Z
      16: ifeq          94
      19: aload_3
      20: invokeinterface #29,  1           // InterfaceMethod java/util/Iterator.next:()Ljava/lang/Object;
      25: checkcast     #33                 // class ru/tinkoff/kora/database/annotation/processor/DbEntityReadHelper$RequiredField
      28: astore        4
      30: aload_1
      31: aload         4
      33: getfield      #35                 // Field ru/tinkoff/kora/database/annotation/processor/DbEntityReadHelper$RequiredField.field:Lcom/squareup/javapoet/FieldSpec;
      36: invokevirtual #39                 // Method com/squareup/javapoet/TypeSpec$Builder.addField:(Lcom/squareup/javapoet/FieldSpec;)Lcom/squareup/javapoet/TypeSpec$Builder;
      39: pop
      40: aload         4
      42: invokevirtual #45                 // Method ru/tinkoff/kora/database/annotation/processor/DbEntityReadHelper$RequiredField.constructorParam:()Lcom/squareup/javapoet/ParameterSpec;
      45: ifnull        91
      48: aload_2
      49: aload         4
      51: getfield      #49                 // Field ru/tinkoff/kora/database/annotation/processor/DbEntityReadHelper$RequiredField.constructorParam:Lcom/squareup/javapoet/ParameterSpec;
      54: invokevirtual #52                 // Method com/squareup/javapoet/MethodSpec$Builder.addParameter:(Lcom/squareup/javapoet/ParameterSpec;)Lcom/squareup/javapoet/MethodSpec$Builder;
      57: pop
      58: aload_2
      59: ldc           #58                 // String this.$L = $L;\n
      61: iconst_2
      62: anewarray     #60                 // class java/lang/Object
      65: dup
      66: iconst_0
      67: aload         4
      69: getfield      #35                 // Field ru/tinkoff/kora/database/annotation/processor/DbEntityReadHelper$RequiredField.field:Lcom/squareup/javapoet/FieldSpec;
      72: getfield      #62                 // Field com/squareup/javapoet/FieldSpec.name:Ljava/lang/String;
      75: aastore
      76: dup
      77: iconst_1
      78: aload         4
      80: invokevirtual #45                 // Method ru/tinkoff/kora/database/annotation/processor/DbEntityReadHelper$RequiredField.constructorParam:()Lcom/squareup/javapoet/ParameterSpec;
      83: getfield      #68                 // Field com/squareup/javapoet/ParameterSpec.name:Ljava/lang/String;
      86: aastore
      87: invokevirtual #71                 // Method com/squareup/javapoet/MethodSpec$Builder.addCode:(Ljava/lang/String;[Ljava/lang/Object;)Lcom/squareup/javapoet/MethodSpec$Builder;
      90: pop
      91: goto          10
      94: return

  public final java.lang.String toString();
    Code:
       0: aload_0
       1: invokedynamic #75,  0             // InvokeDynamic #0:toString:(Lru/tinkoff/kora/database/annotation/processor/DbEntityReadHelper$ReadEntityCodeBlock;)Ljava/lang/String;
       6: areturn

  public final int hashCode();
    Code:
       0: aload_0
       1: invokedynamic #79,  0             // InvokeDynamic #0:hashCode:(Lru/tinkoff/kora/database/annotation/processor/DbEntityReadHelper$ReadEntityCodeBlock;)I
       6: ireturn

  public final boolean equals(java.lang.Object);
    Code:
       0: aload_0
       1: aload_1
       2: invokedynamic #83,  0             // InvokeDynamic #0:equals:(Lru/tinkoff/kora/database/annotation/processor/DbEntityReadHelper$ReadEntityCodeBlock;Ljava/lang/Object;)Z
       7: ireturn

  public com.squareup.javapoet.CodeBlock block();
    Code:
       0: aload_0
       1: getfield      #7                  // Field block:Lcom/squareup/javapoet/CodeBlock;
       4: areturn

  public java.util.List<ru.tinkoff.kora.database.annotation.processor.DbEntityReadHelper$RequiredField> requiredFields();
    Code:
       0: aload_0
       1: getfield      #13                 // Field requiredFields:Ljava/util/List;
       4: areturn
}
