Compiled from "PageDataNode.java"
public class org.h2.index.PageDataNode extends org.h2.index.PageData {
  private int[] childPageIds;

  private int rowCountStored;

  private int rowCount;

  private int length;

  private org.h2.index.PageDataNode(org.h2.index.PageDataIndex, int, org.h2.store.Data);
    Code:
       0: aload_0
       1: aload_1
       2: iload_2
       3: aload_3
       4: invokespecial #1                  // Method org/h2/index/PageData."<init>":(Lorg/h2/index/PageDataIndex;ILorg/h2/store/Data;)V
       7: aload_0
       8: iconst_m1
       9: putfield      #2                  // Field rowCountStored:I
      12: aload_0
      13: iconst_m1
      14: putfield      #3                  // Field rowCount:I
      17: return

  static org.h2.index.PageDataNode create(org.h2.index.PageDataIndex, int, int);
    Code:
       0: new           #4                  // class org/h2/index/PageDataNode
       3: dup
       4: aload_0
       5: iload_1
       6: aload_0
       7: invokevirtual #5                  // Method org/h2/index/PageDataIndex.getPageStore:()Lorg/h2/store/PageStore;
      10: invokevirtual #6                  // Method org/h2/store/PageStore.createData:()Lorg/h2/store/Data;
      13: invokespecial #7                  // Method "<init>":(Lorg/h2/index/PageDataIndex;ILorg/h2/store/Data;)V
      16: astore_3
      17: aload_0
      18: invokevirtual #5                  // Method org/h2/index/PageDataIndex.getPageStore:()Lorg/h2/store/PageStore;
      21: aload_3
      22: aconst_null
      23: invokevirtual #8                  // Method org/h2/store/PageStore.logUndo:(Lorg/h2/store/Page;Lorg/h2/store/Data;)V
      26: aload_3
      27: iload_2
      28: putfield      #9                  // Field parentPageId:I
      31: aload_3
      32: invokespecial #10                 // Method writeHead:()V
      35: aload_3
      36: aload_3
      37: getfield      #11                 // Field data:Lorg/h2/store/Data;
      40: invokevirtual #12                 // Method org/h2/store/Data.length:()I
      43: iconst_4
      44: iadd
      45: putfield      #13                 // Field length:I
      48: aload_3
      49: areturn

  public static org.h2.store.Page read(org.h2.index.PageDataIndex, org.h2.store.Data, int);
    Code:
       0: new           #4                  // class org/h2/index/PageDataNode
       3: dup
       4: aload_0
       5: iload_2
       6: aload_1
       7: invokespecial #7                  // Method "<init>":(Lorg/h2/index/PageDataIndex;ILorg/h2/store/Data;)V
      10: astore_3
      11: aload_3
      12: invokespecial #14                 // Method read:()V
      15: aload_3
      16: areturn

  private void read();
    Code:
       0: aload_0
       1: getfield      #11                 // Field data:Lorg/h2/store/Data;
       4: invokevirtual #15                 // Method org/h2/store/Data.reset:()V
       7: aload_0
       8: getfield      #11                 // Field data:Lorg/h2/store/Data;
      11: invokevirtual #16                 // Method org/h2/store/Data.readByte:()B
      14: pop
      15: aload_0
      16: getfield      #11                 // Field data:Lorg/h2/store/Data;
      19: invokevirtual #17                 // Method org/h2/store/Data.readShortInt:()S
      22: pop
      23: aload_0
      24: aload_0
      25: getfield      #11                 // Field data:Lorg/h2/store/Data;
      28: invokevirtual #18                 // Method org/h2/store/Data.readInt:()I
      31: putfield      #9                  // Field parentPageId:I
      34: aload_0
      35: getfield      #11                 // Field data:Lorg/h2/store/Data;
      38: invokevirtual #19                 // Method org/h2/store/Data.readVarInt:()I
      41: istore_1
      42: iload_1
      43: aload_0
      44: getfield      #20                 // Field index:Lorg/h2/index/PageDataIndex;
      47: invokevirtual #21                 // Method org/h2/index/PageDataIndex.getId:()I
      50: if_icmpeq     105
      53: ldc           #22                 // int 90030
      55: new           #23                 // class java/lang/StringBuilder
      58: dup
      59: invokespecial #24                 // Method java/lang/StringBuilder."<init>":()V
      62: ldc           #25                 // String page:
      64: invokevirtual #26                 // Method java/lang/StringBuilder.append:(Ljava/lang/String;)Ljava/lang/StringBuilder;
      67: aload_0
      68: invokevirtual #27                 // Method getPos:()I
      71: invokevirtual #28                 // Method java/lang/StringBuilder.append:(I)Ljava/lang/StringBuilder;
      74: ldc           #29                 // String  expected index:
      76: invokevirtual #26                 // Method java/lang/StringBuilder.append:(Ljava/lang/String;)Ljava/lang/StringBuilder;
      79: aload_0
      80: getfield      #20                 // Field index:Lorg/h2/index/PageDataIndex;
      83: invokevirtual #21                 // Method org/h2/index/PageDataIndex.getId:()I
      86: invokevirtual #28                 // Method java/lang/StringBuilder.append:(I)Ljava/lang/StringBuilder;
      89: ldc           #30                 // String got:
      91: invokevirtual #26                 // Method java/lang/StringBuilder.append:(Ljava/lang/String;)Ljava/lang/StringBuilder;
      94: iload_1
      95: invokevirtual #28                 // Method java/lang/StringBuilder.append:(I)Ljava/lang/StringBuilder;
      98: invokevirtual #31                 // Method java/lang/StringBuilder.toString:()Ljava/lang/String;
     101: invokestatic  #32                 // Method org/h2/message/DbException.get:(ILjava/lang/String;)Lorg/h2/message/DbException;
     104: athrow
     105: aload_0
     106: aload_0
     107: aload_0
     108: getfield      #11                 // Field data:Lorg/h2/store/Data;
     111: invokevirtual #18                 // Method org/h2/store/Data.readInt:()I
     114: dup_x1
     115: putfield      #2                  // Field rowCountStored:I
     118: putfield      #3                  // Field rowCount:I
     121: aload_0
     122: aload_0
     123: getfield      #11                 // Field data:Lorg/h2/store/Data;
     126: invokevirtual #17                 // Method org/h2/store/Data.readShortInt:()S
     129: putfield      #33                 // Field entryCount:I
     132: aload_0
     133: aload_0
     134: getfield      #33                 // Field entryCount:I
     137: iconst_1
     138: iadd
     139: newarray       int
     141: putfield      #34                 // Field childPageIds:[I
     144: aload_0
     145: getfield      #34                 // Field childPageIds:[I
     148: aload_0
     149: getfield      #33                 // Field entryCount:I
     152: aload_0
     153: getfield      #11                 // Field data:Lorg/h2/store/Data;
     156: invokevirtual #18                 // Method org/h2/store/Data.readInt:()I
     159: iastore
     160: aload_0
     161: aload_0
     162: getfield      #33                 // Field entryCount:I
     165: invokestatic  #35                 // Method org/h2/util/Utils.newLongArray:(I)[J
     168: putfield      #36                 // Field keys:[J
     171: iconst_0
     172: istore_2
     173: iload_2
     174: aload_0
     175: getfield      #33                 // Field entryCount:I
     178: if_icmpge     213
     181: aload_0
     182: getfield      #34                 // Field childPageIds:[I
     185: iload_2
     186: aload_0
     187: getfield      #11                 // Field data:Lorg/h2/store/Data;
     190: invokevirtual #18                 // Method org/h2/store/Data.readInt:()I
     193: iastore
     194: aload_0
     195: getfield      #36                 // Field keys:[J
     198: iload_2
     199: aload_0
     200: getfield      #11                 // Field data:Lorg/h2/store/Data;
     203: invokevirtual #37                 // Method org/h2/store/Data.readVarLong:()J
     206: lastore
     207: iinc          2, 1
     210: goto          173
     213: aload_0
     214: aload_0
     215: getfield      #11                 // Field data:Lorg/h2/store/Data;
     218: invokevirtual #12                 // Method org/h2/store/Data.length:()I
     221: putfield      #13                 // Field length:I
     224: aload_0
     225: invokespecial #38                 // Method check:()V
     228: aload_0
     229: iconst_1
     230: putfield      #39                 // Field written:Z
     233: return

  private void addChild(int, int, long);
    Code:
       0: aload_0
       1: getfield      #20                 // Field index:Lorg/h2/index/PageDataIndex;
       4: invokevirtual #5                  // Method org/h2/index/PageDataIndex.getPageStore:()Lorg/h2/store/PageStore;
       7: aload_0
       8: aload_0
       9: getfield      #11                 // Field data:Lorg/h2/store/Data;
      12: invokevirtual #8                  // Method org/h2/store/PageStore.logUndo:(Lorg/h2/store/Page;Lorg/h2/store/Data;)V
      15: aload_0
      16: iconst_0
      17: putfield      #39                 // Field written:Z
      20: aload_0
      21: aload_0
      22: getfield      #20                 // Field index:Lorg/h2/index/PageDataIndex;
      25: invokevirtual #5                  // Method org/h2/index/PageDataIndex.getPageStore:()Lorg/h2/store/PageStore;
      28: invokevirtual #40                 // Method org/h2/store/PageStore.getChangeCount:()J
      31: putfield      #41                 // Field changeCount:J
      34: aload_0
      35: aload_0
      36: getfield      #34                 // Field childPageIds:[I
      39: aload_0
      40: getfield      #33                 // Field entryCount:I
      43: iconst_1
      44: iadd
      45: iload_1
      46: iconst_1
      47: iadd
      48: iload_2
      49: invokestatic  #42                 // Method insert:([IIII)[I
      52: putfield      #34                 // Field childPageIds:[I
      55: aload_0
      56: aload_0
      57: getfield      #36                 // Field keys:[J
      60: aload_0
      61: getfield      #33                 // Field entryCount:I
      64: iload_1
      65: lload_3
      66: invokestatic  #43                 // Method insert:([JIIJ)[J
      69: putfield      #36                 // Field keys:[J
      72: aload_0
      73: dup
      74: getfield      #33                 // Field entryCount:I
      77: iconst_1
      78: iadd
      79: putfield      #33                 // Field entryCount:I
      82: aload_0
      83: dup
      84: getfield      #13                 // Field length:I
      87: iconst_4
      88: lload_3
      89: invokestatic  #44                 // Method org/h2/store/Data.getVarLongLen:(J)I
      92: iadd
      93: iadd
      94: putfield      #13                 // Field length:I
      97: return

  int addRowTry(org.h2.result.Row);
    Code:
       0: aload_0
       1: getfield      #20                 // Field index:Lorg/h2/index/PageDataIndex;
       4: invokevirtual #5                  // Method org/h2/index/PageDataIndex.getPageStore:()Lorg/h2/store/PageStore;
       7: aload_0
       8: aload_0
       9: getfield      #11                 // Field data:Lorg/h2/store/Data;
      12: invokevirtual #8                  // Method org/h2/store/PageStore.logUndo:(Lorg/h2/store/Page;Lorg/h2/store/Data;)V
      15: iconst_4
      16: aload_1
      17: invokeinterface #45,  1           // InterfaceMethod org/h2/result/Row.getKey:()J
      22: invokestatic  #44                 // Method org/h2/store/Data.getVarLongLen:(J)I
      25: iadd
      26: istore_2
      27: aload_0
      28: aload_1
      29: invokeinterface #45,  1           // InterfaceMethod org/h2/result/Row.getKey:()J
      34: invokevirtual #46                 // Method find:(J)I
      37: istore_3
      38: aload_0
      39: getfield      #20                 // Field index:Lorg/h2/index/PageDataIndex;
      42: aload_0
      43: getfield      #34                 // Field childPageIds:[I
      46: iload_3
      47: iaload
      48: aload_0
      49: invokevirtual #27                 // Method getPos:()I
      52: invokevirtual #47                 // Method org/h2/index/PageDataIndex.getPage:(II)Lorg/h2/index/PageData;
      55: astore        4
      57: aload         4
      59: aload_1
      60: invokevirtual #48                 // Method org/h2/index/PageData.addRowTry:(Lorg/h2/result/Row;)I
      63: istore        5
      65: iload         5
      67: iconst_m1
      68: if_icmpne     74
      71: goto          184
      74: aload_0
      75: getfield      #13                 // Field length:I
      78: iload_2
      79: iadd
      80: aload_0
      81: getfield      #20                 // Field index:Lorg/h2/index/PageDataIndex;
      84: invokevirtual #5                  // Method org/h2/index/PageDataIndex.getPageStore:()Lorg/h2/store/PageStore;
      87: invokevirtual #49                 // Method org/h2/store/PageStore.getPageSize:()I
      90: if_icmple     100
      93: aload_0
      94: getfield      #33                 // Field entryCount:I
      97: iconst_2
      98: idiv
      99: ireturn
     100: iload         5
     102: ifne          114
     105: aload_1
     106: invokeinterface #45,  1           // InterfaceMethod org/h2/result/Row.getKey:()J
     111: goto          123
     114: aload         4
     116: iload         5
     118: iconst_1
     119: isub
     120: invokevirtual #50                 // Method org/h2/index/PageData.getKey:(I)J
     123: lstore        6
     125: aload         4
     127: iload         5
     129: invokevirtual #51                 // Method org/h2/index/PageData.split:(I)Lorg/h2/index/PageData;
     132: astore        8
     134: aload_0
     135: getfield      #20                 // Field index:Lorg/h2/index/PageDataIndex;
     138: invokevirtual #5                  // Method org/h2/index/PageDataIndex.getPageStore:()Lorg/h2/store/PageStore;
     141: aload         4
     143: invokevirtual #52                 // Method org/h2/store/PageStore.update:(Lorg/h2/store/Page;)V
     146: aload_0
     147: getfield      #20                 // Field index:Lorg/h2/index/PageDataIndex;
     150: invokevirtual #5                  // Method org/h2/index/PageDataIndex.getPageStore:()Lorg/h2/store/PageStore;
     153: aload         8
     155: invokevirtual #52                 // Method org/h2/store/PageStore.update:(Lorg/h2/store/Page;)V
     158: aload_0
     159: iload_3
     160: aload         8
     162: invokevirtual #53                 // Method org/h2/index/PageData.getPos:()I
     165: lload         6
     167: invokespecial #54                 // Method addChild:(IIJ)V
     170: aload_0
     171: getfield      #20                 // Field index:Lorg/h2/index/PageDataIndex;
     174: invokevirtual #5                  // Method org/h2/index/PageDataIndex.getPageStore:()Lorg/h2/store/PageStore;
     177: aload_0
     178: invokevirtual #52                 // Method org/h2/store/PageStore.update:(Lorg/h2/store/Page;)V
     181: goto          27
     184: aload_0
     185: iconst_1
     186: invokespecial #55                 // Method updateRowCount:(I)V
     189: iconst_m1
     190: ireturn

  private void updateRowCount(int);
    Code:
       0: aload_0
       1: getfield      #3                  // Field rowCount:I
       4: iconst_m1
       5: if_icmpeq     18
       8: aload_0
       9: dup
      10: getfield      #3                  // Field rowCount:I
      13: iload_1
      14: iadd
      15: putfield      #3                  // Field rowCount:I
      18: aload_0
      19: getfield      #2                  // Field rowCountStored:I
      22: iconst_m1
      23: if_icmpeq     68
      26: aload_0
      27: iconst_m1
      28: putfield      #2                  // Field rowCountStored:I
      31: aload_0
      32: getfield      #20                 // Field index:Lorg/h2/index/PageDataIndex;
      35: invokevirtual #5                  // Method org/h2/index/PageDataIndex.getPageStore:()Lorg/h2/store/PageStore;
      38: aload_0
      39: aload_0
      40: getfield      #11                 // Field data:Lorg/h2/store/Data;
      43: invokevirtual #8                  // Method org/h2/store/PageStore.logUndo:(Lorg/h2/store/Page;Lorg/h2/store/Data;)V
      46: aload_0
      47: getfield      #39                 // Field written:Z
      50: ifeq          57
      53: aload_0
      54: invokespecial #10                 // Method writeHead:()V
      57: aload_0
      58: getfield      #20                 // Field index:Lorg/h2/index/PageDataIndex;
      61: invokevirtual #5                  // Method org/h2/index/PageDataIndex.getPageStore:()Lorg/h2/store/PageStore;
      64: aload_0
      65: invokevirtual #52                 // Method org/h2/store/PageStore.update:(Lorg/h2/store/Page;)V
      68: return

  org.h2.index.Cursor find(org.h2.engine.Session, long, long, boolean);
    Code:
       0: aload_0
       1: lload_2
       2: invokevirtual #46                 // Method find:(J)I
       5: istore        7
       7: aload_0
       8: getfield      #34                 // Field childPageIds:[I
      11: iload         7
      13: iaload
      14: istore        8
      16: aload_0
      17: getfield      #20                 // Field index:Lorg/h2/index/PageDataIndex;
      20: iload         8
      22: aload_0
      23: invokevirtual #27                 // Method getPos:()I
      26: invokevirtual #47                 // Method org/h2/index/PageDataIndex.getPage:(II)Lorg/h2/index/PageData;
      29: aload_1
      30: lload_2
      31: lload         4
      33: iload         6
      35: invokevirtual #56                 // Method org/h2/index/PageData.find:(Lorg/h2/engine/Session;JJZ)Lorg/h2/index/Cursor;
      38: areturn

  org.h2.index.PageData split(int);
    Code:
       0: aload_0
       1: getfield      #20                 // Field index:Lorg/h2/index/PageDataIndex;
       4: invokevirtual #5                  // Method org/h2/index/PageDataIndex.getPageStore:()Lorg/h2/store/PageStore;
       7: invokevirtual #57                 // Method org/h2/store/PageStore.allocatePage:()I
      10: istore_2
      11: aload_0
      12: getfield      #20                 // Field index:Lorg/h2/index/PageDataIndex;
      15: iload_2
      16: aload_0
      17: getfield      #9                  // Field parentPageId:I
      20: invokestatic  #58                 // Method create:(Lorg/h2/index/PageDataIndex;II)Lorg/h2/index/PageDataNode;
      23: astore_3
      24: aload_0
      25: getfield      #34                 // Field childPageIds:[I
      28: iload_1
      29: iaload
      30: istore        4
      32: iload_1
      33: aload_0
      34: getfield      #33                 // Field entryCount:I
      37: if_icmpge     70
      40: aload_3
      41: aload_3
      42: getfield      #33                 // Field entryCount:I
      45: aload_0
      46: getfield      #34                 // Field childPageIds:[I
      49: iload_1
      50: iconst_1
      51: iadd
      52: iaload
      53: aload_0
      54: getfield      #36                 // Field keys:[J
      57: iload_1
      58: laload
      59: invokespecial #54                 // Method addChild:(IIJ)V
      62: aload_0
      63: iload_1
      64: invokespecial #59                 // Method removeChild:(I)V
      67: goto          32
      70: aload_0
      71: getfield      #34                 // Field childPageIds:[I
      74: iload_1
      75: iconst_1
      76: isub
      77: iaload
      78: istore        5
      80: aload_0
      81: iload_1
      82: iconst_1
      83: isub
      84: invokespecial #59                 // Method removeChild:(I)V
      87: aload_0
      88: getfield      #34                 // Field childPageIds:[I
      91: iload_1
      92: iconst_1
      93: isub
      94: iload         5
      96: iastore
      97: aload_3
      98: getfield      #34                 // Field childPageIds:[I
     101: iconst_0
     102: iload         4
     104: iastore
     105: aload_3
     106: aload_0
     107: invokevirtual #27                 // Method getPos:()I
     110: invokevirtual #60                 // Method remapChildren:(I)V
     113: aload_3
     114: areturn

  protected void remapChildren(int);
    Code:
       0: iconst_0
       1: istore_2
       2: iload_2
       3: aload_0
       4: getfield      #33                 // Field entryCount:I
       7: iconst_1
       8: iadd
       9: if_icmpge     57
      12: aload_0
      13: getfield      #34                 // Field childPageIds:[I
      16: iload_2
      17: iaload
      18: istore_3
      19: aload_0
      20: getfield      #20                 // Field index:Lorg/h2/index/PageDataIndex;
      23: iload_3
      24: iload_1
      25: invokevirtual #47                 // Method org/h2/index/PageDataIndex.getPage:(II)Lorg/h2/index/PageData;
      28: astore        4
      30: aload         4
      32: aload_0
      33: invokevirtual #27                 // Method getPos:()I
      36: invokevirtual #61                 // Method org/h2/index/PageData.setParentPageId:(I)V
      39: aload_0
      40: getfield      #20                 // Field index:Lorg/h2/index/PageDataIndex;
      43: invokevirtual #5                  // Method org/h2/index/PageDataIndex.getPageStore:()Lorg/h2/store/PageStore;
      46: aload         4
      48: invokevirtual #52                 // Method org/h2/store/PageStore.update:(Lorg/h2/store/Page;)V
      51: iinc          2, 1
      54: goto          2
      57: return

  void init(org.h2.index.PageData, long, org.h2.index.PageData);
    Code:
       0: aload_0
       1: iconst_1
       2: putfield      #33                 // Field entryCount:I
       5: aload_0
       6: iconst_2
       7: newarray       int
       9: dup
      10: iconst_0
      11: aload_1
      12: invokevirtual #53                 // Method org/h2/index/PageData.getPos:()I
      15: iastore
      16: dup
      17: iconst_1
      18: aload         4
      20: invokevirtual #53                 // Method org/h2/index/PageData.getPos:()I
      23: iastore
      24: putfield      #34                 // Field childPageIds:[I
      27: aload_0
      28: iconst_1
      29: newarray       long
      31: dup
      32: iconst_0
      33: lload_2
      34: lastore
      35: putfield      #36                 // Field keys:[J
      38: aload_0
      39: dup
      40: getfield      #13                 // Field length:I
      43: iconst_4
      44: lload_2
      45: invokestatic  #44                 // Method org/h2/store/Data.getVarLongLen:(J)I
      48: iadd
      49: iadd
      50: putfield      #13                 // Field length:I
      53: aload_0
      54: invokespecial #38                 // Method check:()V
      57: return

  long getLastKey();
    Code:
       0: aload_0
       1: getfield      #20                 // Field index:Lorg/h2/index/PageDataIndex;
       4: aload_0
       5: getfield      #34                 // Field childPageIds:[I
       8: aload_0
       9: getfield      #33                 // Field entryCount:I
      12: iaload
      13: aload_0
      14: invokevirtual #27                 // Method getPos:()I
      17: invokevirtual #47                 // Method org/h2/index/PageDataIndex.getPage:(II)Lorg/h2/index/PageData;
      20: invokevirtual #62                 // Method org/h2/index/PageData.getLastKey:()J
      23: lreturn

  org.h2.index.PageDataLeaf getNextPage(long);
    Code:
       0: aload_0
       1: lload_1
       2: invokevirtual #46                 // Method find:(J)I
       5: iconst_1
       6: iadd
       7: istore_3
       8: iload_3
       9: aload_0
      10: getfield      #33                 // Field entryCount:I
      13: if_icmple     49
      16: aload_0
      17: getfield      #9                  // Field parentPageId:I
      20: ifne          25
      23: aconst_null
      24: areturn
      25: aload_0
      26: getfield      #20                 // Field index:Lorg/h2/index/PageDataIndex;
      29: aload_0
      30: getfield      #9                  // Field parentPageId:I
      33: iconst_m1
      34: invokevirtual #47                 // Method org/h2/index/PageDataIndex.getPage:(II)Lorg/h2/index/PageData;
      37: checkcast     #4                  // class org/h2/index/PageDataNode
      40: astore        4
      42: aload         4
      44: lload_1
      45: invokevirtual #63                 // Method getNextPage:(J)Lorg/h2/index/PageDataLeaf;
      48: areturn
      49: aload_0
      50: getfield      #20                 // Field index:Lorg/h2/index/PageDataIndex;
      53: aload_0
      54: getfield      #34                 // Field childPageIds:[I
      57: iload_3
      58: iaload
      59: aload_0
      60: invokevirtual #27                 // Method getPos:()I
      63: invokevirtual #47                 // Method org/h2/index/PageDataIndex.getPage:(II)Lorg/h2/index/PageData;
      66: astore        4
      68: aload         4
      70: invokevirtual #64                 // Method org/h2/index/PageData.getFirstLeaf:()Lorg/h2/index/PageDataLeaf;
      73: areturn

  org.h2.index.PageDataLeaf getFirstLeaf();
    Code:
       0: aload_0
       1: getfield      #34                 // Field childPageIds:[I
       4: iconst_0
       5: iaload
       6: istore_1
       7: aload_0
       8: getfield      #20                 // Field index:Lorg/h2/index/PageDataIndex;
      11: iload_1
      12: aload_0
      13: invokevirtual #27                 // Method getPos:()I
      16: invokevirtual #47                 // Method org/h2/index/PageDataIndex.getPage:(II)Lorg/h2/index/PageData;
      19: invokevirtual #64                 // Method org/h2/index/PageData.getFirstLeaf:()Lorg/h2/index/PageDataLeaf;
      22: areturn

  boolean remove(long);
    Code:
       0: aload_0
       1: lload_1
       2: invokevirtual #46                 // Method find:(J)I
       5: istore_3
       6: aload_0
       7: getfield      #20                 // Field index:Lorg/h2/index/PageDataIndex;
      10: aload_0
      11: getfield      #34                 // Field childPageIds:[I
      14: iload_3
      15: iaload
      16: aload_0
      17: invokevirtual #27                 // Method getPos:()I
      20: invokevirtual #47                 // Method org/h2/index/PageDataIndex.getPage:(II)Lorg/h2/index/PageData;
      23: astore        4
      25: aload         4
      27: lload_1
      28: invokevirtual #65                 // Method org/h2/index/PageData.remove:(J)Z
      31: istore        5
      33: aload_0
      34: getfield      #20                 // Field index:Lorg/h2/index/PageDataIndex;
      37: invokevirtual #5                  // Method org/h2/index/PageDataIndex.getPageStore:()Lorg/h2/store/PageStore;
      40: aload_0
      41: aload_0
      42: getfield      #11                 // Field data:Lorg/h2/store/Data;
      45: invokevirtual #8                  // Method org/h2/store/PageStore.logUndo:(Lorg/h2/store/Page;Lorg/h2/store/Data;)V
      48: aload_0
      49: iconst_m1
      50: invokespecial #55                 // Method updateRowCount:(I)V
      53: iload         5
      55: ifne          60
      58: iconst_0
      59: ireturn
      60: aload_0
      61: getfield      #20                 // Field index:Lorg/h2/index/PageDataIndex;
      64: invokevirtual #5                  // Method org/h2/index/PageDataIndex.getPageStore:()Lorg/h2/store/PageStore;
      67: aload         4
      69: invokevirtual #53                 // Method org/h2/index/PageData.getPos:()I
      72: invokevirtual #66                 // Method org/h2/store/PageStore.free:(I)V
      75: aload_0
      76: getfield      #33                 // Field entryCount:I
      79: iconst_1
      80: if_icmpge     85
      83: iconst_1
      84: ireturn
      85: aload_0
      86: iload_3
      87: invokespecial #59                 // Method removeChild:(I)V
      90: aload_0
      91: getfield      #20                 // Field index:Lorg/h2/index/PageDataIndex;
      94: invokevirtual #5                  // Method org/h2/index/PageDataIndex.getPageStore:()Lorg/h2/store/PageStore;
      97: aload_0
      98: invokevirtual #52                 // Method org/h2/store/PageStore.update:(Lorg/h2/store/Page;)V
     101: iconst_0
     102: ireturn

  void freeRecursive();
    Code:
       0: aload_0
       1: getfield      #20                 // Field index:Lorg/h2/index/PageDataIndex;
       4: invokevirtual #5                  // Method org/h2/index/PageDataIndex.getPageStore:()Lorg/h2/store/PageStore;
       7: aload_0
       8: aload_0
       9: getfield      #11                 // Field data:Lorg/h2/store/Data;
      12: invokevirtual #8                  // Method org/h2/store/PageStore.logUndo:(Lorg/h2/store/Page;Lorg/h2/store/Data;)V
      15: aload_0
      16: getfield      #20                 // Field index:Lorg/h2/index/PageDataIndex;
      19: invokevirtual #5                  // Method org/h2/index/PageDataIndex.getPageStore:()Lorg/h2/store/PageStore;
      22: aload_0
      23: invokevirtual #27                 // Method getPos:()I
      26: invokevirtual #66                 // Method org/h2/store/PageStore.free:(I)V
      29: iconst_0
      30: istore_1
      31: iload_1
      32: aload_0
      33: getfield      #33                 // Field entryCount:I
      36: iconst_1
      37: iadd
      38: if_icmpge     69
      41: aload_0
      42: getfield      #34                 // Field childPageIds:[I
      45: iload_1
      46: iaload
      47: istore_2
      48: aload_0
      49: getfield      #20                 // Field index:Lorg/h2/index/PageDataIndex;
      52: iload_2
      53: aload_0
      54: invokevirtual #27                 // Method getPos:()I
      57: invokevirtual #47                 // Method org/h2/index/PageDataIndex.getPage:(II)Lorg/h2/index/PageData;
      60: invokevirtual #67                 // Method org/h2/index/PageData.freeRecursive:()V
      63: iinc          1, 1
      66: goto          31
      69: return

  org.h2.result.Row getRowWithKey(long);
    Code:
       0: aload_0
       1: lload_1
       2: invokevirtual #46                 // Method find:(J)I
       5: istore_3
       6: aload_0
       7: getfield      #20                 // Field index:Lorg/h2/index/PageDataIndex;
      10: aload_0
      11: getfield      #34                 // Field childPageIds:[I
      14: iload_3
      15: iaload
      16: aload_0
      17: invokevirtual #27                 // Method getPos:()I
      20: invokevirtual #47                 // Method org/h2/index/PageDataIndex.getPage:(II)Lorg/h2/index/PageData;
      23: astore        4
      25: aload         4
      27: lload_1
      28: invokevirtual #68                 // Method org/h2/index/PageData.getRowWithKey:(J)Lorg/h2/result/Row;
      31: areturn

  int getRowCount();
    Code:
       0: aload_0
       1: getfield      #3                  // Field rowCount:I
       4: iconst_m1
       5: if_icmpne     149
       8: iconst_0
       9: istore_1
      10: iconst_0
      11: istore_2
      12: iload_2
      13: aload_0
      14: getfield      #33                 // Field entryCount:I
      17: iconst_1
      18: iadd
      19: if_icmpge     144
      22: aload_0
      23: getfield      #34                 // Field childPageIds:[I
      26: iload_2
      27: iaload
      28: istore_3
      29: aload_0
      30: getfield      #20                 // Field index:Lorg/h2/index/PageDataIndex;
      33: iload_3
      34: aload_0
      35: invokevirtual #27                 // Method getPos:()I
      38: invokevirtual #47                 // Method org/h2/index/PageDataIndex.getPage:(II)Lorg/h2/index/PageData;
      41: astore        4
      43: aload_0
      44: invokevirtual #27                 // Method getPos:()I
      47: aload         4
      49: invokevirtual #53                 // Method org/h2/index/PageData.getPos:()I
      52: if_icmpne     81
      55: new           #23                 // class java/lang/StringBuilder
      58: dup
      59: invokespecial #24                 // Method java/lang/StringBuilder."<init>":()V
      62: ldc           #69                 // String Page is its own child:
      64: invokevirtual #26                 // Method java/lang/StringBuilder.append:(Ljava/lang/String;)Ljava/lang/StringBuilder;
      67: aload_0
      68: invokevirtual #27                 // Method getPos:()I
      71: invokevirtual #28                 // Method java/lang/StringBuilder.append:(I)Ljava/lang/StringBuilder;
      74: invokevirtual #31                 // Method java/lang/StringBuilder.toString:()Ljava/lang/String;
      77: invokestatic  #70                 // Method org/h2/message/DbException.throwInternalError:(Ljava/lang/String;)Ljava/lang/RuntimeException;
      80: athrow
      81: iload_1
      82: aload         4
      84: invokevirtual #71                 // Method org/h2/index/PageData.getRowCount:()I
      87: iadd
      88: istore_1
      89: aload_0
      90: getfield      #20                 // Field index:Lorg/h2/index/PageDataIndex;
      93: invokevirtual #72                 // Method org/h2/index/PageDataIndex.getDatabase:()Lorg/h2/engine/Database;
      96: iconst_0
      97: new           #23                 // class java/lang/StringBuilder
     100: dup
     101: invokespecial #24                 // Method java/lang/StringBuilder."<init>":()V
     104: aload_0
     105: getfield      #20                 // Field index:Lorg/h2/index/PageDataIndex;
     108: invokevirtual #73                 // Method org/h2/index/PageDataIndex.getTable:()Lorg/h2/table/Table;
     111: invokevirtual #74                 // Method java/lang/StringBuilder.append:(Ljava/lang/Object;)Ljava/lang/StringBuilder;
     114: ldc           #75                 // String .
     116: invokevirtual #26                 // Method java/lang/StringBuilder.append:(Ljava/lang/String;)Ljava/lang/StringBuilder;
     119: aload_0
     120: getfield      #20                 // Field index:Lorg/h2/index/PageDataIndex;
     123: invokevirtual #76                 // Method org/h2/index/PageDataIndex.getName:()Ljava/lang/String;
     126: invokevirtual #26                 // Method java/lang/StringBuilder.append:(Ljava/lang/String;)Ljava/lang/StringBuilder;
     129: invokevirtual #31                 // Method java/lang/StringBuilder.toString:()Ljava/lang/String;
     132: iload_1
     133: ldc           #77                 // int 2147483647
     135: invokevirtual #78                 // Method org/h2/engine/Database.setProgress:(ILjava/lang/String;II)V
     138: iinc          2, 1
     141: goto          12
     144: aload_0
     145: iload_1
     146: putfield      #3                  // Field rowCount:I
     149: aload_0
     150: getfield      #3                  // Field rowCount:I
     153: ireturn

  long getDiskSpaceUsed();
    Code:
       0: lconst_0
       1: lstore_1
       2: iconst_0
       3: istore_3
       4: iload_3
       5: aload_0
       6: getfield      #33                 // Field entryCount:I
       9: iconst_1
      10: iadd
      11: if_icmpge     142
      14: aload_0
      15: getfield      #34                 // Field childPageIds:[I
      18: iload_3
      19: iaload
      20: istore        4
      22: aload_0
      23: getfield      #20                 // Field index:Lorg/h2/index/PageDataIndex;
      26: iload         4
      28: aload_0
      29: invokevirtual #27                 // Method getPos:()I
      32: invokevirtual #47                 // Method org/h2/index/PageDataIndex.getPage:(II)Lorg/h2/index/PageData;
      35: astore        5
      37: aload_0
      38: invokevirtual #27                 // Method getPos:()I
      41: aload         5
      43: invokevirtual #53                 // Method org/h2/index/PageData.getPos:()I
      46: if_icmpne     75
      49: new           #23                 // class java/lang/StringBuilder
      52: dup
      53: invokespecial #24                 // Method java/lang/StringBuilder."<init>":()V
      56: ldc           #69                 // String Page is its own child:
      58: invokevirtual #26                 // Method java/lang/StringBuilder.append:(Ljava/lang/String;)Ljava/lang/StringBuilder;
      61: aload_0
      62: invokevirtual #27                 // Method getPos:()I
      65: invokevirtual #28                 // Method java/lang/StringBuilder.append:(I)Ljava/lang/StringBuilder;
      68: invokevirtual #31                 // Method java/lang/StringBuilder.toString:()Ljava/lang/String;
      71: invokestatic  #70                 // Method org/h2/message/DbException.throwInternalError:(Ljava/lang/String;)Ljava/lang/RuntimeException;
      74: athrow
      75: lload_1
      76: aload         5
      78: invokevirtual #79                 // Method org/h2/index/PageData.getDiskSpaceUsed:()J
      81: ladd
      82: lstore_1
      83: aload_0
      84: getfield      #20                 // Field index:Lorg/h2/index/PageDataIndex;
      87: invokevirtual #72                 // Method org/h2/index/PageDataIndex.getDatabase:()Lorg/h2/engine/Database;
      90: iconst_0
      91: new           #23                 // class java/lang/StringBuilder
      94: dup
      95: invokespecial #24                 // Method java/lang/StringBuilder."<init>":()V
      98: aload_0
      99: getfield      #20                 // Field index:Lorg/h2/index/PageDataIndex;
     102: invokevirtual #73                 // Method org/h2/index/PageDataIndex.getTable:()Lorg/h2/table/Table;
     105: invokevirtual #74                 // Method java/lang/StringBuilder.append:(Ljava/lang/Object;)Ljava/lang/StringBuilder;
     108: ldc           #75                 // String .
     110: invokevirtual #26                 // Method java/lang/StringBuilder.append:(Ljava/lang/String;)Ljava/lang/StringBuilder;
     113: aload_0
     114: getfield      #20                 // Field index:Lorg/h2/index/PageDataIndex;
     117: invokevirtual #76                 // Method org/h2/index/PageDataIndex.getName:()Ljava/lang/String;
     120: invokevirtual #26                 // Method java/lang/StringBuilder.append:(Ljava/lang/String;)Ljava/lang/StringBuilder;
     123: invokevirtual #31                 // Method java/lang/StringBuilder.toString:()Ljava/lang/String;
     126: lload_1
     127: bipush        16
     129: lshr
     130: l2i
     131: ldc           #77                 // int 2147483647
     133: invokevirtual #78                 // Method org/h2/engine/Database.setProgress:(ILjava/lang/String;II)V
     136: iinc          3, 1
     139: goto          4
     142: lload_1
     143: lreturn

  void setRowCountStored(int);
    Code:
       0: aload_0
       1: iload_1
       2: putfield      #3                  // Field rowCount:I
       5: aload_0
       6: getfield      #2                  // Field rowCountStored:I
       9: iload_1
      10: if_icmpeq     69
      13: aload_0
      14: iload_1
      15: putfield      #2                  // Field rowCountStored:I
      18: aload_0
      19: getfield      #20                 // Field index:Lorg/h2/index/PageDataIndex;
      22: invokevirtual #5                  // Method org/h2/index/PageDataIndex.getPageStore:()Lorg/h2/store/PageStore;
      25: aload_0
      26: aload_0
      27: getfield      #11                 // Field data:Lorg/h2/store/Data;
      30: invokevirtual #8                  // Method org/h2/store/PageStore.logUndo:(Lorg/h2/store/Page;Lorg/h2/store/Data;)V
      33: aload_0
      34: getfield      #39                 // Field written:Z
      37: ifeq          58
      40: aload_0
      41: aload_0
      42: getfield      #20                 // Field index:Lorg/h2/index/PageDataIndex;
      45: invokevirtual #5                  // Method org/h2/index/PageDataIndex.getPageStore:()Lorg/h2/store/PageStore;
      48: invokevirtual #40                 // Method org/h2/store/PageStore.getChangeCount:()J
      51: putfield      #41                 // Field changeCount:J
      54: aload_0
      55: invokespecial #10                 // Method writeHead:()V
      58: aload_0
      59: getfield      #20                 // Field index:Lorg/h2/index/PageDataIndex;
      62: invokevirtual #5                  // Method org/h2/index/PageDataIndex.getPageStore:()Lorg/h2/store/PageStore;
      65: aload_0
      66: invokevirtual #52                 // Method org/h2/store/PageStore.update:(Lorg/h2/store/Page;)V
      69: return

  private void check();
    Code:
       0: getstatic     #80                 // Field org/h2/engine/SysProperties.CHECK:Z
       3: ifeq          39
       6: iconst_0
       7: istore_1
       8: iload_1
       9: aload_0
      10: getfield      #33                 // Field entryCount:I
      13: iconst_1
      14: iadd
      15: if_icmpge     39
      18: aload_0
      19: getfield      #34                 // Field childPageIds:[I
      22: iload_1
      23: iaload
      24: istore_2
      25: iload_2
      26: ifne          33
      29: invokestatic  #81                 // Method org/h2/message/DbException.throwInternalError:()Ljava/lang/RuntimeException;
      32: pop
      33: iinc          1, 1
      36: goto          8
      39: return

  public void write();
    Code:
       0: aload_0
       1: invokespecial #82                 // Method writeData:()V
       4: aload_0
       5: getfield      #20                 // Field index:Lorg/h2/index/PageDataIndex;
       8: invokevirtual #5                  // Method org/h2/index/PageDataIndex.getPageStore:()Lorg/h2/store/PageStore;
      11: aload_0
      12: invokevirtual #27                 // Method getPos:()I
      15: aload_0
      16: getfield      #11                 // Field data:Lorg/h2/store/Data;
      19: invokevirtual #83                 // Method org/h2/store/PageStore.writePage:(ILorg/h2/store/Data;)V
      22: return

  private void writeHead();
    Code:
       0: aload_0
       1: getfield      #11                 // Field data:Lorg/h2/store/Data;
       4: invokevirtual #15                 // Method org/h2/store/Data.reset:()V
       7: aload_0
       8: getfield      #11                 // Field data:Lorg/h2/store/Data;
      11: iconst_2
      12: invokevirtual #84                 // Method org/h2/store/Data.writeByte:(B)V
      15: aload_0
      16: getfield      #11                 // Field data:Lorg/h2/store/Data;
      19: iconst_0
      20: invokevirtual #85                 // Method org/h2/store/Data.writeShortInt:(I)V
      23: getstatic     #86                 // Field org/h2/engine/SysProperties.CHECK2:Z
      26: ifeq          44
      29: aload_0
      30: getfield      #11                 // Field data:Lorg/h2/store/Data;
      33: invokevirtual #12                 // Method org/h2/store/Data.length:()I
      36: iconst_3
      37: if_icmpeq     44
      40: invokestatic  #81                 // Method org/h2/message/DbException.throwInternalError:()Ljava/lang/RuntimeException;
      43: pop
      44: aload_0
      45: getfield      #11                 // Field data:Lorg/h2/store/Data;
      48: aload_0
      49: getfield      #9                  // Field parentPageId:I
      52: invokevirtual #87                 // Method org/h2/store/Data.writeInt:(I)V
      55: aload_0
      56: getfield      #11                 // Field data:Lorg/h2/store/Data;
      59: aload_0
      60: getfield      #20                 // Field index:Lorg/h2/index/PageDataIndex;
      63: invokevirtual #21                 // Method org/h2/index/PageDataIndex.getId:()I
      66: invokevirtual #88                 // Method org/h2/store/Data.writeVarInt:(I)V
      69: aload_0
      70: getfield      #11                 // Field data:Lorg/h2/store/Data;
      73: aload_0
      74: getfield      #2                  // Field rowCountStored:I
      77: invokevirtual #87                 // Method org/h2/store/Data.writeInt:(I)V
      80: aload_0
      81: getfield      #11                 // Field data:Lorg/h2/store/Data;
      84: aload_0
      85: getfield      #33                 // Field entryCount:I
      88: invokevirtual #85                 // Method org/h2/store/Data.writeShortInt:(I)V
      91: return

  private void writeData();
    Code:
       0: aload_0
       1: getfield      #39                 // Field written:Z
       4: ifeq          8
       7: return
       8: aload_0
       9: invokespecial #38                 // Method check:()V
      12: aload_0
      13: invokespecial #10                 // Method writeHead:()V
      16: aload_0
      17: getfield      #11                 // Field data:Lorg/h2/store/Data;
      20: aload_0
      21: getfield      #34                 // Field childPageIds:[I
      24: aload_0
      25: getfield      #33                 // Field entryCount:I
      28: iaload
      29: invokevirtual #87                 // Method org/h2/store/Data.writeInt:(I)V
      32: iconst_0
      33: istore_1
      34: iload_1
      35: aload_0
      36: getfield      #33                 // Field entryCount:I
      39: if_icmpge     74
      42: aload_0
      43: getfield      #11                 // Field data:Lorg/h2/store/Data;
      46: aload_0
      47: getfield      #34                 // Field childPageIds:[I
      50: iload_1
      51: iaload
      52: invokevirtual #87                 // Method org/h2/store/Data.writeInt:(I)V
      55: aload_0
      56: getfield      #11                 // Field data:Lorg/h2/store/Data;
      59: aload_0
      60: getfield      #36                 // Field keys:[J
      63: iload_1
      64: laload
      65: invokevirtual #89                 // Method org/h2/store/Data.writeVarLong:(J)V
      68: iinc          1, 1
      71: goto          34
      74: aload_0
      75: getfield      #13                 // Field length:I
      78: aload_0
      79: getfield      #11                 // Field data:Lorg/h2/store/Data;
      82: invokevirtual #12                 // Method org/h2/store/Data.length:()I
      85: if_icmpeq     129
      88: new           #23                 // class java/lang/StringBuilder
      91: dup
      92: invokespecial #24                 // Method java/lang/StringBuilder."<init>":()V
      95: ldc           #90                 // String expected pos:
      97: invokevirtual #26                 // Method java/lang/StringBuilder.append:(Ljava/lang/String;)Ljava/lang/StringBuilder;
     100: aload_0
     101: getfield      #13                 // Field length:I
     104: invokevirtual #28                 // Method java/lang/StringBuilder.append:(I)Ljava/lang/StringBuilder;
     107: ldc           #91                 // String  got:
     109: invokevirtual #26                 // Method java/lang/StringBuilder.append:(Ljava/lang/String;)Ljava/lang/StringBuilder;
     112: aload_0
     113: getfield      #11                 // Field data:Lorg/h2/store/Data;
     116: invokevirtual #12                 // Method org/h2/store/Data.length:()I
     119: invokevirtual #28                 // Method java/lang/StringBuilder.append:(I)Ljava/lang/StringBuilder;
     122: invokevirtual #31                 // Method java/lang/StringBuilder.toString:()Ljava/lang/String;
     125: invokestatic  #70                 // Method org/h2/message/DbException.throwInternalError:(Ljava/lang/String;)Ljava/lang/RuntimeException;
     128: pop
     129: aload_0
     130: iconst_1
     131: putfield      #39                 // Field written:Z
     134: return

  private void removeChild(int);
    Code:
       0: aload_0
       1: getfield      #20                 // Field index:Lorg/h2/index/PageDataIndex;
       4: invokevirtual #5                  // Method org/h2/index/PageDataIndex.getPageStore:()Lorg/h2/store/PageStore;
       7: aload_0
       8: aload_0
       9: getfield      #11                 // Field data:Lorg/h2/store/Data;
      12: invokevirtual #8                  // Method org/h2/store/PageStore.logUndo:(Lorg/h2/store/Page;Lorg/h2/store/Data;)V
      15: aload_0
      16: iconst_0
      17: putfield      #39                 // Field written:Z
      20: aload_0
      21: aload_0
      22: getfield      #20                 // Field index:Lorg/h2/index/PageDataIndex;
      25: invokevirtual #5                  // Method org/h2/index/PageDataIndex.getPageStore:()Lorg/h2/store/PageStore;
      28: invokevirtual #40                 // Method org/h2/store/PageStore.getChangeCount:()J
      31: putfield      #41                 // Field changeCount:J
      34: iload_1
      35: aload_0
      36: getfield      #33                 // Field entryCount:I
      39: if_icmpge     46
      42: iload_1
      43: goto          49
      46: iload_1
      47: iconst_1
      48: isub
      49: istore_2
      50: aload_0
      51: dup
      52: getfield      #33                 // Field entryCount:I
      55: iconst_1
      56: isub
      57: putfield      #33                 // Field entryCount:I
      60: aload_0
      61: dup
      62: getfield      #13                 // Field length:I
      65: iconst_4
      66: aload_0
      67: getfield      #36                 // Field keys:[J
      70: iload_2
      71: laload
      72: invokestatic  #44                 // Method org/h2/store/Data.getVarLongLen:(J)I
      75: iadd
      76: isub
      77: putfield      #13                 // Field length:I
      80: aload_0
      81: getfield      #33                 // Field entryCount:I
      84: ifge          113
      87: new           #23                 // class java/lang/StringBuilder
      90: dup
      91: invokespecial #24                 // Method java/lang/StringBuilder."<init>":()V
      94: ldc           #92                 // String
      96: invokevirtual #26                 // Method java/lang/StringBuilder.append:(Ljava/lang/String;)Ljava/lang/StringBuilder;
      99: aload_0
     100: getfield      #33                 // Field entryCount:I
     103: invokevirtual #28                 // Method java/lang/StringBuilder.append:(I)Ljava/lang/StringBuilder;
     106: invokevirtual #31                 // Method java/lang/StringBuilder.toString:()Ljava/lang/String;
     109: invokestatic  #70                 // Method org/h2/message/DbException.throwInternalError:(Ljava/lang/String;)Ljava/lang/RuntimeException;
     112: pop
     113: aload_0
     114: aload_0
     115: getfield      #36                 // Field keys:[J
     118: aload_0
     119: getfield      #33                 // Field entryCount:I
     122: iconst_1
     123: iadd
     124: iload_2
     125: invokestatic  #93                 // Method remove:([JII)[J
     128: putfield      #36                 // Field keys:[J
     131: aload_0
     132: aload_0
     133: getfield      #34                 // Field childPageIds:[I
     136: aload_0
     137: getfield      #33                 // Field entryCount:I
     140: iconst_2
     141: iadd
     142: iload_1
     143: invokestatic  #94                 // Method remove:([III)[I
     146: putfield      #34                 // Field childPageIds:[I
     149: return

  public java.lang.String toString();
    Code:
       0: new           #23                 // class java/lang/StringBuilder
       3: dup
       4: invokespecial #24                 // Method java/lang/StringBuilder."<init>":()V
       7: ldc           #95                 // String page[
       9: invokevirtual #26                 // Method java/lang/StringBuilder.append:(Ljava/lang/String;)Ljava/lang/StringBuilder;
      12: aload_0
      13: invokevirtual #27                 // Method getPos:()I
      16: invokevirtual #28                 // Method java/lang/StringBuilder.append:(I)Ljava/lang/StringBuilder;
      19: ldc           #96                 // String ] data node table:
      21: invokevirtual #26                 // Method java/lang/StringBuilder.append:(Ljava/lang/String;)Ljava/lang/StringBuilder;
      24: aload_0
      25: getfield      #20                 // Field index:Lorg/h2/index/PageDataIndex;
      28: invokevirtual #21                 // Method org/h2/index/PageDataIndex.getId:()I
      31: invokevirtual #28                 // Method java/lang/StringBuilder.append:(I)Ljava/lang/StringBuilder;
      34: ldc           #97                 // String  entries:
      36: invokevirtual #26                 // Method java/lang/StringBuilder.append:(Ljava/lang/String;)Ljava/lang/StringBuilder;
      39: aload_0
      40: getfield      #33                 // Field entryCount:I
      43: invokevirtual #28                 // Method java/lang/StringBuilder.append:(I)Ljava/lang/StringBuilder;
      46: ldc           #98                 // String
      48: invokevirtual #26                 // Method java/lang/StringBuilder.append:(Ljava/lang/String;)Ljava/lang/StringBuilder;
      51: aload_0
      52: getfield      #34                 // Field childPageIds:[I
      55: invokestatic  #99                 // Method java/util/Arrays.toString:([I)Ljava/lang/String;
      58: invokevirtual #26                 // Method java/lang/StringBuilder.append:(Ljava/lang/String;)Ljava/lang/StringBuilder;
      61: invokevirtual #31                 // Method java/lang/StringBuilder.toString:()Ljava/lang/String;
      64: areturn

  public void moveTo(org.h2.engine.Session, int);
    Code:
       0: aload_0
       1: getfield      #20                 // Field index:Lorg/h2/index/PageDataIndex;
       4: invokevirtual #5                  // Method org/h2/index/PageDataIndex.getPageStore:()Lorg/h2/store/PageStore;
       7: astore_3
       8: iconst_0
       9: istore        4
      11: iload         4
      13: aload_0
      14: getfield      #33                 // Field entryCount:I
      17: iconst_1
      18: iadd
      19: if_icmpge     44
      22: aload_0
      23: getfield      #34                 // Field childPageIds:[I
      26: iload         4
      28: iaload
      29: istore        5
      31: aload_3
      32: iload         5
      34: invokevirtual #100                // Method org/h2/store/PageStore.getPage:(I)Lorg/h2/store/Page;
      37: pop
      38: iinc          4, 1
      41: goto          11
      44: aload_0
      45: getfield      #9                  // Field parentPageId:I
      48: ifeq          60
      51: aload_3
      52: aload_0
      53: getfield      #9                  // Field parentPageId:I
      56: invokevirtual #100                // Method org/h2/store/PageStore.getPage:(I)Lorg/h2/store/Page;
      59: pop
      60: aload_3
      61: aload_0
      62: aload_0
      63: getfield      #11                 // Field data:Lorg/h2/store/Data;
      66: invokevirtual #8                  // Method org/h2/store/PageStore.logUndo:(Lorg/h2/store/Page;Lorg/h2/store/Data;)V
      69: aload_0
      70: getfield      #20                 // Field index:Lorg/h2/index/PageDataIndex;
      73: iload_2
      74: aload_0
      75: getfield      #9                  // Field parentPageId:I
      78: invokestatic  #58                 // Method create:(Lorg/h2/index/PageDataIndex;II)Lorg/h2/index/PageDataNode;
      81: astore        4
      83: aload         4
      85: aload_0
      86: getfield      #2                  // Field rowCountStored:I
      89: putfield      #2                  // Field rowCountStored:I
      92: aload         4
      94: aload_0
      95: getfield      #3                  // Field rowCount:I
      98: putfield      #3                  // Field rowCount:I
     101: aload         4
     103: aload_0
     104: getfield      #34                 // Field childPageIds:[I
     107: putfield      #34                 // Field childPageIds:[I
     110: aload         4
     112: aload_0
     113: getfield      #36                 // Field keys:[J
     116: putfield      #36                 // Field keys:[J
     119: aload         4
     121: aload_0
     122: getfield      #33                 // Field entryCount:I
     125: putfield      #33                 // Field entryCount:I
     128: aload         4
     130: aload_0
     131: getfield      #13                 // Field length:I
     134: putfield      #13                 // Field length:I
     137: aload_3
     138: aload         4
     140: invokevirtual #52                 // Method org/h2/store/PageStore.update:(Lorg/h2/store/Page;)V
     143: aload_0
     144: getfield      #9                  // Field parentPageId:I
     147: ifne          162
     150: aload_0
     151: getfield      #20                 // Field index:Lorg/h2/index/PageDataIndex;
     154: aload_1
     155: iload_2
     156: invokevirtual #101                // Method org/h2/index/PageDataIndex.setRootPageId:(Lorg/h2/engine/Session;I)V
     159: goto          185
     162: aload_3
     163: aload_0
     164: getfield      #9                  // Field parentPageId:I
     167: invokevirtual #100                // Method org/h2/store/PageStore.getPage:(I)Lorg/h2/store/Page;
     170: checkcast     #4                  // class org/h2/index/PageDataNode
     173: astore        5
     175: aload         5
     177: aload_0
     178: invokevirtual #27                 // Method getPos:()I
     181: iload_2
     182: invokevirtual #102                // Method moveChild:(II)V
     185: iconst_0
     186: istore        5
     188: iload         5
     190: aload_0
     191: getfield      #33                 // Field entryCount:I
     194: iconst_1
     195: iadd
     196: if_icmpge     237
     199: aload_0
     200: getfield      #34                 // Field childPageIds:[I
     203: iload         5
     205: iaload
     206: istore        6
     208: aload_3
     209: iload         6
     211: invokevirtual #100                // Method org/h2/store/PageStore.getPage:(I)Lorg/h2/store/Page;
     214: checkcast     #103                // class org/h2/index/PageData
     217: astore        7
     219: aload         7
     221: iload_2
     222: invokevirtual #61                 // Method org/h2/index/PageData.setParentPageId:(I)V
     225: aload_3
     226: aload         7
     228: invokevirtual #52                 // Method org/h2/store/PageStore.update:(Lorg/h2/store/Page;)V
     231: iinc          5, 1
     234: goto          188
     237: aload_3
     238: aload_0
     239: invokevirtual #27                 // Method getPos:()I
     242: invokevirtual #66                 // Method org/h2/store/PageStore.free:(I)V
     245: return

  void moveChild(int, int);
    Code:
       0: iconst_0
       1: istore_3
       2: iload_3
       3: aload_0
       4: getfield      #33                 // Field entryCount:I
       7: iconst_1
       8: iadd
       9: if_icmpge     81
      12: aload_0
      13: getfield      #34                 // Field childPageIds:[I
      16: iload_3
      17: iaload
      18: iload_1
      19: if_icmpne     75
      22: aload_0
      23: getfield      #20                 // Field index:Lorg/h2/index/PageDataIndex;
      26: invokevirtual #5                  // Method org/h2/index/PageDataIndex.getPageStore:()Lorg/h2/store/PageStore;
      29: aload_0
      30: aload_0
      31: getfield      #11                 // Field data:Lorg/h2/store/Data;
      34: invokevirtual #8                  // Method org/h2/store/PageStore.logUndo:(Lorg/h2/store/Page;Lorg/h2/store/Data;)V
      37: aload_0
      38: iconst_0
      39: putfield      #39                 // Field written:Z
      42: aload_0
      43: aload_0
      44: getfield      #20                 // Field index:Lorg/h2/index/PageDataIndex;
      47: invokevirtual #5                  // Method org/h2/index/PageDataIndex.getPageStore:()Lorg/h2/store/PageStore;
      50: invokevirtual #40                 // Method org/h2/store/PageStore.getChangeCount:()J
      53: putfield      #41                 // Field changeCount:J
      56: aload_0
      57: getfield      #34                 // Field childPageIds:[I
      60: iload_3
      61: iload_2
      62: iastore
      63: aload_0
      64: getfield      #20                 // Field index:Lorg/h2/index/PageDataIndex;
      67: invokevirtual #5                  // Method org/h2/index/PageDataIndex.getPageStore:()Lorg/h2/store/PageStore;
      70: aload_0
      71: invokevirtual #52                 // Method org/h2/store/PageStore.update:(Lorg/h2/store/Page;)V
      74: return
      75: iinc          3, 1
      78: goto          2
      81: new           #23                 // class java/lang/StringBuilder
      84: dup
      85: invokespecial #24                 // Method java/lang/StringBuilder."<init>":()V
      88: iload_1
      89: invokevirtual #28                 // Method java/lang/StringBuilder.append:(I)Ljava/lang/StringBuilder;
      92: ldc           #98                 // String
      94: invokevirtual #26                 // Method java/lang/StringBuilder.append:(Ljava/lang/String;)Ljava/lang/StringBuilder;
      97: iload_2
      98: invokevirtual #28                 // Method java/lang/StringBuilder.append:(I)Ljava/lang/StringBuilder;
     101: invokevirtual #31                 // Method java/lang/StringBuilder.toString:()Ljava/lang/String;
     104: invokestatic  #70                 // Method org/h2/message/DbException.throwInternalError:(Ljava/lang/String;)Ljava/lang/RuntimeException;
     107: athrow

  public boolean canRemove();
    Code:
       0: aload_0
       1: invokespecial #104                // Method org/h2/index/PageData.canRemove:()Z
       4: ireturn

  public int getMemory();
    Code:
       0: aload_0
       1: invokespecial #105                // Method org/h2/index/PageData.getMemory:()I
       4: ireturn
}
