Compiled from "PageDataCursor.java"
class org.h2.index.PageDataCursor implements org.h2.index.Cursor {
  private org.h2.index.PageDataLeaf current;

  private int idx;

  private final long maxKey;

  private org.h2.result.Row row;

  private final boolean multiVersion;

  private final org.h2.engine.Session session;

  private java.util.Iterator<org.h2.result.Row> delta;

  org.h2.index.PageDataCursor(org.h2.engine.Session, org.h2.index.PageDataLeaf, int, long, boolean);
    Code:
       0: aload_0
       1: invokespecial #1                  // Method java/lang/Object."<init>":()V
       4: aload_0
       5: aload_2
       6: putfield      #2                  // Field current:Lorg/h2/index/PageDataLeaf;
       9: aload_0
      10: iload_3
      11: putfield      #3                  // Field idx:I
      14: aload_0
      15: lload         4
      17: putfield      #4                  // Field maxKey:J
      20: aload_0
      21: iload         6
      23: putfield      #5                  // Field multiVersion:Z
      26: aload_0
      27: aload_1
      28: putfield      #6                  // Field session:Lorg/h2/engine/Session;
      31: iload         6
      33: ifeq          47
      36: aload_0
      37: aload_2
      38: getfield      #7                  // Field org/h2/index/PageDataLeaf.index:Lorg/h2/index/PageDataIndex;
      41: invokevirtual #8                  // Method org/h2/index/PageDataIndex.getDelta:()Ljava/util/Iterator;
      44: putfield      #9                  // Field delta:Ljava/util/Iterator;
      47: return

  public org.h2.result.Row get();
    Code:
       0: aload_0
       1: getfield      #10                 // Field row:Lorg/h2/result/Row;
       4: areturn

  public org.h2.result.SearchRow getSearchRow();
    Code:
       0: aload_0
       1: invokevirtual #11                 // Method get:()Lorg/h2/result/Row;
       4: areturn

  public boolean next();
    Code:
       0: aload_0
       1: getfield      #5                  // Field multiVersion:Z
       4: ifne          16
       7: aload_0
       8: invokespecial #12                 // Method nextRow:()V
      11: aload_0
      12: invokespecial #13                 // Method checkMax:()Z
      15: ireturn
      16: aload_0
      17: getfield      #9                  // Field delta:Ljava/util/Iterator;
      20: ifnull        98
      23: aload_0
      24: getfield      #9                  // Field delta:Ljava/util/Iterator;
      27: invokeinterface #14,  1           // InterfaceMethod java/util/Iterator.hasNext:()Z
      32: ifne          48
      35: aload_0
      36: aconst_null
      37: putfield      #9                  // Field delta:Ljava/util/Iterator;
      40: aload_0
      41: aconst_null
      42: putfield      #10                 // Field row:Lorg/h2/result/Row;
      45: goto          16
      48: aload_0
      49: aload_0
      50: getfield      #9                  // Field delta:Ljava/util/Iterator;
      53: invokeinterface #15,  1           // InterfaceMethod java/util/Iterator.next:()Ljava/lang/Object;
      58: checkcast     #16                 // class org/h2/result/Row
      61: putfield      #10                 // Field row:Lorg/h2/result/Row;
      64: aload_0
      65: getfield      #10                 // Field row:Lorg/h2/result/Row;
      68: invokeinterface #17,  1           // InterfaceMethod org/h2/result/Row.isDeleted:()Z
      73: ifeq          16
      76: aload_0
      77: getfield      #10                 // Field row:Lorg/h2/result/Row;
      80: invokeinterface #18,  1           // InterfaceMethod org/h2/result/Row.getSessionId:()I
      85: aload_0
      86: getfield      #6                  // Field session:Lorg/h2/engine/Session;
      89: invokevirtual #19                 // Method org/h2/engine/Session.getId:()I
      92: if_icmpne     143
      95: goto          16
      98: aload_0
      99: invokespecial #12                 // Method nextRow:()V
     102: aload_0
     103: getfield      #10                 // Field row:Lorg/h2/result/Row;
     106: ifnull        143
     109: aload_0
     110: getfield      #10                 // Field row:Lorg/h2/result/Row;
     113: invokeinterface #18,  1           // InterfaceMethod org/h2/result/Row.getSessionId:()I
     118: ifeq          143
     121: aload_0
     122: getfield      #10                 // Field row:Lorg/h2/result/Row;
     125: invokeinterface #18,  1           // InterfaceMethod org/h2/result/Row.getSessionId:()I
     130: aload_0
     131: getfield      #6                  // Field session:Lorg/h2/engine/Session;
     134: invokevirtual #19                 // Method org/h2/engine/Session.getId:()I
     137: if_icmpeq     143
     140: goto          16
     143: aload_0
     144: invokespecial #13                 // Method checkMax:()Z
     147: ireturn

  private boolean checkMax();
    Code:
       0: aload_0
       1: getfield      #10                 // Field row:Lorg/h2/result/Row;
       4: ifnull        57
       7: aload_0
       8: getfield      #4                  // Field maxKey:J
      11: ldc2_w        #20                 // long 9223372036854775807l
      14: lcmp
      15: ifeq          55
      18: aload_0
      19: getfield      #2                  // Field current:Lorg/h2/index/PageDataLeaf;
      22: getfield      #7                  // Field org/h2/index/PageDataLeaf.index:Lorg/h2/index/PageDataIndex;
      25: aload_0
      26: getfield      #10                 // Field row:Lorg/h2/result/Row;
      29: ldc2_w        #20                 // long 9223372036854775807l
      32: ldc2_w        #20                 // long 9223372036854775807l
      35: invokevirtual #22                 // Method org/h2/index/PageDataIndex.getKey:(Lorg/h2/result/SearchRow;JJ)J
      38: lstore_1
      39: lload_1
      40: aload_0
      41: getfield      #4                  // Field maxKey:J
      44: lcmp
      45: ifle          55
      48: aload_0
      49: aconst_null
      50: putfield      #10                 // Field row:Lorg/h2/result/Row;
      53: iconst_0
      54: ireturn
      55: iconst_1
      56: ireturn
      57: iconst_0
      58: ireturn

  private void nextRow();
    Code:
       0: aload_0
       1: getfield      #3                  // Field idx:I
       4: aload_0
       5: getfield      #2                  // Field current:Lorg/h2/index/PageDataLeaf;
       8: invokevirtual #23                 // Method org/h2/index/PageDataLeaf.getEntryCount:()I
      11: if_icmplt     43
      14: aload_0
      15: aload_0
      16: getfield      #2                  // Field current:Lorg/h2/index/PageDataLeaf;
      19: invokevirtual #24                 // Method org/h2/index/PageDataLeaf.getNextPage:()Lorg/h2/index/PageDataLeaf;
      22: putfield      #2                  // Field current:Lorg/h2/index/PageDataLeaf;
      25: aload_0
      26: iconst_0
      27: putfield      #3                  // Field idx:I
      30: aload_0
      31: getfield      #2                  // Field current:Lorg/h2/index/PageDataLeaf;
      34: ifnonnull     43
      37: aload_0
      38: aconst_null
      39: putfield      #10                 // Field row:Lorg/h2/result/Row;
      42: return
      43: aload_0
      44: aload_0
      45: getfield      #2                  // Field current:Lorg/h2/index/PageDataLeaf;
      48: aload_0
      49: getfield      #3                  // Field idx:I
      52: invokevirtual #25                 // Method org/h2/index/PageDataLeaf.getRowAt:(I)Lorg/h2/result/Row;
      55: putfield      #10                 // Field row:Lorg/h2/result/Row;
      58: aload_0
      59: dup
      60: getfield      #3                  // Field idx:I
      63: iconst_1
      64: iadd
      65: putfield      #3                  // Field idx:I
      68: return

  public boolean previous();
    Code:
       0: aload_0
       1: invokevirtual #26                 // Method java/lang/Object.toString:()Ljava/lang/String;
       4: invokestatic  #27                 // Method org/h2/message/DbException.throwInternalError:(Ljava/lang/String;)Ljava/lang/RuntimeException;
       7: athrow
}
