Compiled from "BulkPaymentInitiationWithStatusResponse.java"
public class de.adorsys.psd2.model.BulkPaymentInitiationWithStatusResponse {
  private java.lang.Boolean batchBookingPreferred;

  private java.time.LocalDate requestedExecutionDate;

  private java.time.OffsetDateTime acceptorTransactionDateTime;

  private de.adorsys.psd2.model.AccountReference debtorAccount;

  private java.lang.String paymentInformationId;

  private java.util.List<de.adorsys.psd2.model.PaymentInitiationBulkElementJson> payments;

  private de.adorsys.psd2.model.TransactionStatus transactionStatus;

  public de.adorsys.psd2.model.BulkPaymentInitiationWithStatusResponse();
    Code:
       0: aload_0
       1: invokespecial #1                  // Method java/lang/Object."<init>":()V
       4: aload_0
       5: aconst_null
       6: putfield      #2                  // Field batchBookingPreferred:Ljava/lang/Boolean;
       9: aload_0
      10: aconst_null
      11: putfield      #3                  // Field requestedExecutionDate:Ljava/time/LocalDate;
      14: aload_0
      15: aconst_null
      16: putfield      #4                  // Field acceptorTransactionDateTime:Ljava/time/OffsetDateTime;
      19: aload_0
      20: aconst_null
      21: putfield      #5                  // Field debtorAccount:Lde/adorsys/psd2/model/AccountReference;
      24: aload_0
      25: aconst_null
      26: putfield      #6                  // Field paymentInformationId:Ljava/lang/String;
      29: aload_0
      30: new           #7                  // class java/util/ArrayList
      33: dup
      34: invokespecial #8                  // Method java/util/ArrayList."<init>":()V
      37: putfield      #9                  // Field payments:Ljava/util/List;
      40: aload_0
      41: aconst_null
      42: putfield      #10                 // Field transactionStatus:Lde/adorsys/psd2/model/TransactionStatus;
      45: return

  public de.adorsys.psd2.model.BulkPaymentInitiationWithStatusResponse batchBookingPreferred(java.lang.Boolean);
    Code:
       0: aload_0
       1: aload_1
       2: putfield      #2                  // Field batchBookingPreferred:Ljava/lang/Boolean;
       5: aload_0
       6: areturn

  public java.lang.Boolean getBatchBookingPreferred();
    Code:
       0: aload_0
       1: getfield      #2                  // Field batchBookingPreferred:Ljava/lang/Boolean;
       4: areturn

  public void setBatchBookingPreferred(java.lang.Boolean);
    Code:
       0: aload_0
       1: aload_1
       2: putfield      #2                  // Field batchBookingPreferred:Ljava/lang/Boolean;
       5: return

  public de.adorsys.psd2.model.BulkPaymentInitiationWithStatusResponse requestedExecutionDate(java.time.LocalDate);
    Code:
       0: aload_0
       1: aload_1
       2: putfield      #3                  // Field requestedExecutionDate:Ljava/time/LocalDate;
       5: aload_0
       6: areturn

  public java.time.LocalDate getRequestedExecutionDate();
    Code:
       0: aload_0
       1: getfield      #3                  // Field requestedExecutionDate:Ljava/time/LocalDate;
       4: areturn

  public void setRequestedExecutionDate(java.time.LocalDate);
    Code:
       0: aload_0
       1: aload_1
       2: putfield      #3                  // Field requestedExecutionDate:Ljava/time/LocalDate;
       5: return

  public de.adorsys.psd2.model.BulkPaymentInitiationWithStatusResponse acceptorTransactionDateTime(java.time.OffsetDateTime);
    Code:
       0: aload_0
       1: aload_1
       2: putfield      #4                  // Field acceptorTransactionDateTime:Ljava/time/OffsetDateTime;
       5: aload_0
       6: areturn

  public java.time.OffsetDateTime getAcceptorTransactionDateTime();
    Code:
       0: aload_0
       1: getfield      #4                  // Field acceptorTransactionDateTime:Ljava/time/OffsetDateTime;
       4: areturn

  public void setAcceptorTransactionDateTime(java.time.OffsetDateTime);
    Code:
       0: aload_0
       1: aload_1
       2: putfield      #4                  // Field acceptorTransactionDateTime:Ljava/time/OffsetDateTime;
       5: return

  public de.adorsys.psd2.model.BulkPaymentInitiationWithStatusResponse debtorAccount(de.adorsys.psd2.model.AccountReference);
    Code:
       0: aload_0
       1: aload_1
       2: putfield      #5                  // Field debtorAccount:Lde/adorsys/psd2/model/AccountReference;
       5: aload_0
       6: areturn

  public de.adorsys.psd2.model.AccountReference getDebtorAccount();
    Code:
       0: aload_0
       1: getfield      #5                  // Field debtorAccount:Lde/adorsys/psd2/model/AccountReference;
       4: areturn

  public void setDebtorAccount(de.adorsys.psd2.model.AccountReference);
    Code:
       0: aload_0
       1: aload_1
       2: putfield      #5                  // Field debtorAccount:Lde/adorsys/psd2/model/AccountReference;
       5: return

  public de.adorsys.psd2.model.BulkPaymentInitiationWithStatusResponse paymentInformationId(java.lang.String);
    Code:
       0: aload_0
       1: aload_1
       2: putfield      #6                  // Field paymentInformationId:Ljava/lang/String;
       5: aload_0
       6: areturn

  public java.lang.String getPaymentInformationId();
    Code:
       0: aload_0
       1: getfield      #6                  // Field paymentInformationId:Ljava/lang/String;
       4: areturn

  public void setPaymentInformationId(java.lang.String);
    Code:
       0: aload_0
       1: aload_1
       2: putfield      #6                  // Field paymentInformationId:Ljava/lang/String;
       5: return

  public de.adorsys.psd2.model.BulkPaymentInitiationWithStatusResponse payments(java.util.List<de.adorsys.psd2.model.PaymentInitiationBulkElementJson>);
    Code:
       0: aload_0
       1: aload_1
       2: putfield      #9                  // Field payments:Ljava/util/List;
       5: aload_0
       6: areturn

  public de.adorsys.psd2.model.BulkPaymentInitiationWithStatusResponse addPaymentsItem(de.adorsys.psd2.model.PaymentInitiationBulkElementJson);
    Code:
       0: aload_0
       1: getfield      #9                  // Field payments:Ljava/util/List;
       4: aload_1
       5: invokeinterface #11,  2           // InterfaceMethod java/util/List.add:(Ljava/lang/Object;)Z
      10: pop
      11: aload_0
      12: areturn

  public java.util.List<de.adorsys.psd2.model.PaymentInitiationBulkElementJson> getPayments();
    Code:
       0: aload_0
       1: getfield      #9                  // Field payments:Ljava/util/List;
       4: areturn

  public void setPayments(java.util.List<de.adorsys.psd2.model.PaymentInitiationBulkElementJson>);
    Code:
       0: aload_0
       1: aload_1
       2: putfield      #9                  // Field payments:Ljava/util/List;
       5: return

  public de.adorsys.psd2.model.BulkPaymentInitiationWithStatusResponse transactionStatus(de.adorsys.psd2.model.TransactionStatus);
    Code:
       0: aload_0
       1: aload_1
       2: putfield      #10                 // Field transactionStatus:Lde/adorsys/psd2/model/TransactionStatus;
       5: aload_0
       6: areturn

  public de.adorsys.psd2.model.TransactionStatus getTransactionStatus();
    Code:
       0: aload_0
       1: getfield      #10                 // Field transactionStatus:Lde/adorsys/psd2/model/TransactionStatus;
       4: areturn

  public void setTransactionStatus(de.adorsys.psd2.model.TransactionStatus);
    Code:
       0: aload_0
       1: aload_1
       2: putfield      #10                 // Field transactionStatus:Lde/adorsys/psd2/model/TransactionStatus;
       5: return

  public boolean equals(java.lang.Object);
    Code:
       0: aload_0
       1: aload_1
       2: if_acmpne     7
       5: iconst_1
       6: ireturn
       7: aload_1
       8: ifnull        22
      11: aload_0
      12: invokevirtual #12                 // Method java/lang/Object.getClass:()Ljava/lang/Class;
      15: aload_1
      16: invokevirtual #12                 // Method java/lang/Object.getClass:()Ljava/lang/Class;
      19: if_acmpeq     24
      22: iconst_0
      23: ireturn
      24: aload_1
      25: checkcast     #13                 // class de/adorsys/psd2/model/BulkPaymentInitiationWithStatusResponse
      28: astore_2
      29: aload_0
      30: getfield      #2                  // Field batchBookingPreferred:Ljava/lang/Boolean;
      33: aload_2
      34: getfield      #2                  // Field batchBookingPreferred:Ljava/lang/Boolean;
      37: invokestatic  #14                 // Method java/util/Objects.equals:(Ljava/lang/Object;Ljava/lang/Object;)Z
      40: ifeq          131
      43: aload_0
      44: getfield      #3                  // Field requestedExecutionDate:Ljava/time/LocalDate;
      47: aload_2
      48: getfield      #3                  // Field requestedExecutionDate:Ljava/time/LocalDate;
      51: invokestatic  #14                 // Method java/util/Objects.equals:(Ljava/lang/Object;Ljava/lang/Object;)Z
      54: ifeq          131
      57: aload_0
      58: getfield      #4                  // Field acceptorTransactionDateTime:Ljava/time/OffsetDateTime;
      61: aload_2
      62: getfield      #4                  // Field acceptorTransactionDateTime:Ljava/time/OffsetDateTime;
      65: invokestatic  #14                 // Method java/util/Objects.equals:(Ljava/lang/Object;Ljava/lang/Object;)Z
      68: ifeq          131
      71: aload_0
      72: getfield      #5                  // Field debtorAccount:Lde/adorsys/psd2/model/AccountReference;
      75: aload_2
      76: getfield      #5                  // Field debtorAccount:Lde/adorsys/psd2/model/AccountReference;
      79: invokestatic  #14                 // Method java/util/Objects.equals:(Ljava/lang/Object;Ljava/lang/Object;)Z
      82: ifeq          131
      85: aload_0
      86: getfield      #6                  // Field paymentInformationId:Ljava/lang/String;
      89: aload_2
      90: getfield      #6                  // Field paymentInformationId:Ljava/lang/String;
      93: invokestatic  #14                 // Method java/util/Objects.equals:(Ljava/lang/Object;Ljava/lang/Object;)Z
      96: ifeq          131
      99: aload_0
     100: getfield      #9                  // Field payments:Ljava/util/List;
     103: aload_2
     104: getfield      #9                  // Field payments:Ljava/util/List;
     107: invokestatic  #14                 // Method java/util/Objects.equals:(Ljava/lang/Object;Ljava/lang/Object;)Z
     110: ifeq          131
     113: aload_0
     114: getfield      #10                 // Field transactionStatus:Lde/adorsys/psd2/model/TransactionStatus;
     117: aload_2
     118: getfield      #10                 // Field transactionStatus:Lde/adorsys/psd2/model/TransactionStatus;
     121: invokestatic  #14                 // Method java/util/Objects.equals:(Ljava/lang/Object;Ljava/lang/Object;)Z
     124: ifeq          131
     127: iconst_1
     128: goto          132
     131: iconst_0
     132: ireturn

  public int hashCode();
    Code:
       0: bipush        7
       2: anewarray     #15                 // class java/lang/Object
       5: dup
       6: iconst_0
       7: aload_0
       8: getfield      #2                  // Field batchBookingPreferred:Ljava/lang/Boolean;
      11: aastore
      12: dup
      13: iconst_1
      14: aload_0
      15: getfield      #3                  // Field requestedExecutionDate:Ljava/time/LocalDate;
      18: aastore
      19: dup
      20: iconst_2
      21: aload_0
      22: getfield      #4                  // Field acceptorTransactionDateTime:Ljava/time/OffsetDateTime;
      25: aastore
      26: dup
      27: iconst_3
      28: aload_0
      29: getfield      #5                  // Field debtorAccount:Lde/adorsys/psd2/model/AccountReference;
      32: aastore
      33: dup
      34: iconst_4
      35: aload_0
      36: getfield      #6                  // Field paymentInformationId:Ljava/lang/String;
      39: aastore
      40: dup
      41: iconst_5
      42: aload_0
      43: getfield      #9                  // Field payments:Ljava/util/List;
      46: aastore
      47: dup
      48: bipush        6
      50: aload_0
      51: getfield      #10                 // Field transactionStatus:Lde/adorsys/psd2/model/TransactionStatus;
      54: aastore
      55: invokestatic  #16                 // Method java/util/Objects.hash:([Ljava/lang/Object;)I
      58: ireturn

  public java.lang.String toString();
    Code:
       0: new           #17                 // class java/lang/StringBuilder
       3: dup
       4: invokespecial #18                 // Method java/lang/StringBuilder."<init>":()V
       7: astore_1
       8: aload_1
       9: ldc           #19                 // String class BulkPaymentInitiationWithStatusResponse {\n
      11: invokevirtual #20                 // Method java/lang/StringBuilder.append:(Ljava/lang/String;)Ljava/lang/StringBuilder;
      14: pop
      15: aload_1
      16: ldc           #21                 // String     batchBookingPreferred:
      18: invokevirtual #20                 // Method java/lang/StringBuilder.append:(Ljava/lang/String;)Ljava/lang/StringBuilder;
      21: aload_0
      22: aload_0
      23: getfield      #2                  // Field batchBookingPreferred:Ljava/lang/Boolean;
      26: invokevirtual #22                 // Method toIndentedString:(Ljava/lang/Object;)Ljava/lang/String;
      29: invokevirtual #20                 // Method java/lang/StringBuilder.append:(Ljava/lang/String;)Ljava/lang/StringBuilder;
      32: ldc           #23                 // String \n
      34: invokevirtual #20                 // Method java/lang/StringBuilder.append:(Ljava/lang/String;)Ljava/lang/StringBuilder;
      37: pop
      38: aload_1
      39: ldc           #24                 // String     requestedExecutionDate:
      41: invokevirtual #20                 // Method java/lang/StringBuilder.append:(Ljava/lang/String;)Ljava/lang/StringBuilder;
      44: aload_0
      45: aload_0
      46: getfield      #3                  // Field requestedExecutionDate:Ljava/time/LocalDate;
      49: invokevirtual #22                 // Method toIndentedString:(Ljava/lang/Object;)Ljava/lang/String;
      52: invokevirtual #20                 // Method java/lang/StringBuilder.append:(Ljava/lang/String;)Ljava/lang/StringBuilder;
      55: ldc           #23                 // String \n
      57: invokevirtual #20                 // Method java/lang/StringBuilder.append:(Ljava/lang/String;)Ljava/lang/StringBuilder;
      60: pop
      61: aload_1
      62: ldc           #25                 // String     acceptorTransactionDateTime:
      64: invokevirtual #20                 // Method java/lang/StringBuilder.append:(Ljava/lang/String;)Ljava/lang/StringBuilder;
      67: aload_0
      68: aload_0
      69: getfield      #4                  // Field acceptorTransactionDateTime:Ljava/time/OffsetDateTime;
      72: invokevirtual #22                 // Method toIndentedString:(Ljava/lang/Object;)Ljava/lang/String;
      75: invokevirtual #20                 // Method java/lang/StringBuilder.append:(Ljava/lang/String;)Ljava/lang/StringBuilder;
      78: ldc           #23                 // String \n
      80: invokevirtual #20                 // Method java/lang/StringBuilder.append:(Ljava/lang/String;)Ljava/lang/StringBuilder;
      83: pop
      84: aload_1
      85: ldc           #26                 // String     debtorAccount:
      87: invokevirtual #20                 // Method java/lang/StringBuilder.append:(Ljava/lang/String;)Ljava/lang/StringBuilder;
      90: aload_0
      91: aload_0
      92: getfield      #5                  // Field debtorAccount:Lde/adorsys/psd2/model/AccountReference;
      95: invokevirtual #22                 // Method toIndentedString:(Ljava/lang/Object;)Ljava/lang/String;
      98: invokevirtual #20                 // Method java/lang/StringBuilder.append:(Ljava/lang/String;)Ljava/lang/StringBuilder;
     101: ldc           #23                 // String \n
     103: invokevirtual #20                 // Method java/lang/StringBuilder.append:(Ljava/lang/String;)Ljava/lang/StringBuilder;
     106: pop
     107: aload_1
     108: ldc           #27                 // String     paymentInformationId:
     110: invokevirtual #20                 // Method java/lang/StringBuilder.append:(Ljava/lang/String;)Ljava/lang/StringBuilder;
     113: aload_0
     114: aload_0
     115: getfield      #6                  // Field paymentInformationId:Ljava/lang/String;
     118: invokevirtual #22                 // Method toIndentedString:(Ljava/lang/Object;)Ljava/lang/String;
     121: invokevirtual #20                 // Method java/lang/StringBuilder.append:(Ljava/lang/String;)Ljava/lang/StringBuilder;
     124: ldc           #23                 // String \n
     126: invokevirtual #20                 // Method java/lang/StringBuilder.append:(Ljava/lang/String;)Ljava/lang/StringBuilder;
     129: pop
     130: aload_1
     131: ldc           #28                 // String     payments:
     133: invokevirtual #20                 // Method java/lang/StringBuilder.append:(Ljava/lang/String;)Ljava/lang/StringBuilder;
     136: aload_0
     137: aload_0
     138: getfield      #9                  // Field payments:Ljava/util/List;
     141: invokevirtual #22                 // Method toIndentedString:(Ljava/lang/Object;)Ljava/lang/String;
     144: invokevirtual #20                 // Method java/lang/StringBuilder.append:(Ljava/lang/String;)Ljava/lang/StringBuilder;
     147: ldc           #23                 // String \n
     149: invokevirtual #20                 // Method java/lang/StringBuilder.append:(Ljava/lang/String;)Ljava/lang/StringBuilder;
     152: pop
     153: aload_1
     154: ldc           #29                 // String     transactionStatus:
     156: invokevirtual #20                 // Method java/lang/StringBuilder.append:(Ljava/lang/String;)Ljava/lang/StringBuilder;
     159: aload_0
     160: aload_0
     161: getfield      #10                 // Field transactionStatus:Lde/adorsys/psd2/model/TransactionStatus;
     164: invokevirtual #22                 // Method toIndentedString:(Ljava/lang/Object;)Ljava/lang/String;
     167: invokevirtual #20                 // Method java/lang/StringBuilder.append:(Ljava/lang/String;)Ljava/lang/StringBuilder;
     170: ldc           #23                 // String \n
     172: invokevirtual #20                 // Method java/lang/StringBuilder.append:(Ljava/lang/String;)Ljava/lang/StringBuilder;
     175: pop
     176: aload_1
     177: ldc           #30                 // String }
     179: invokevirtual #20                 // Method java/lang/StringBuilder.append:(Ljava/lang/String;)Ljava/lang/StringBuilder;
     182: pop
     183: aload_1
     184: invokevirtual #31                 // Method java/lang/StringBuilder.toString:()Ljava/lang/String;
     187: areturn

  private java.lang.String toIndentedString(java.lang.Object);
    Code:
       0: aload_1
       1: ifnonnull     7
       4: ldc           #32                 // String null
       6: areturn
       7: aload_1
       8: invokevirtual #33                 // Method java/lang/Object.toString:()Ljava/lang/String;
      11: ldc           #23                 // String \n
      13: ldc           #34                 // String \n
      15: invokevirtual #35                 // Method java/lang/String.replace:(Ljava/lang/CharSequence;Ljava/lang/CharSequence;)Ljava/lang/String;
      18: areturn
}
