Compiled from "DayOfExecution.java"
public final class de.adorsys.psd2.model.DayOfExecution extends java.lang.Enum<de.adorsys.psd2.model.DayOfExecution> {
  public static final de.adorsys.psd2.model.DayOfExecution _1;

  public static final de.adorsys.psd2.model.DayOfExecution _2;

  public static final de.adorsys.psd2.model.DayOfExecution _3;

  public static final de.adorsys.psd2.model.DayOfExecution _4;

  public static final de.adorsys.psd2.model.DayOfExecution _5;

  public static final de.adorsys.psd2.model.DayOfExecution _6;

  public static final de.adorsys.psd2.model.DayOfExecution _7;

  public static final de.adorsys.psd2.model.DayOfExecution _8;

  public static final de.adorsys.psd2.model.DayOfExecution _9;

  public static final de.adorsys.psd2.model.DayOfExecution _10;

  public static final de.adorsys.psd2.model.DayOfExecution _11;

  public static final de.adorsys.psd2.model.DayOfExecution _12;

  public static final de.adorsys.psd2.model.DayOfExecution _13;

  public static final de.adorsys.psd2.model.DayOfExecution _14;

  public static final de.adorsys.psd2.model.DayOfExecution _15;

  public static final de.adorsys.psd2.model.DayOfExecution _16;

  public static final de.adorsys.psd2.model.DayOfExecution _17;

  public static final de.adorsys.psd2.model.DayOfExecution _18;

  public static final de.adorsys.psd2.model.DayOfExecution _19;

  public static final de.adorsys.psd2.model.DayOfExecution _20;

  public static final de.adorsys.psd2.model.DayOfExecution _21;

  public static final de.adorsys.psd2.model.DayOfExecution _22;

  public static final de.adorsys.psd2.model.DayOfExecution _23;

  public static final de.adorsys.psd2.model.DayOfExecution _24;

  public static final de.adorsys.psd2.model.DayOfExecution _25;

  public static final de.adorsys.psd2.model.DayOfExecution _26;

  public static final de.adorsys.psd2.model.DayOfExecution _27;

  public static final de.adorsys.psd2.model.DayOfExecution _28;

  public static final de.adorsys.psd2.model.DayOfExecution _29;

  public static final de.adorsys.psd2.model.DayOfExecution _30;

  public static final de.adorsys.psd2.model.DayOfExecution _31;

  private java.lang.String value;

  private static final de.adorsys.psd2.model.DayOfExecution[] $VALUES;

  public static de.adorsys.psd2.model.DayOfExecution[] values();
    Code:
       0: getstatic     #1                  // Field $VALUES:[Lde/adorsys/psd2/model/DayOfExecution;
       3: invokevirtual #2                  // Method "[Lde/adorsys/psd2/model/DayOfExecution;".clone:()Ljava/lang/Object;
       6: checkcast     #3                  // class "[Lde/adorsys/psd2/model/DayOfExecution;"
       9: areturn

  public static de.adorsys.psd2.model.DayOfExecution valueOf(java.lang.String);
    Code:
       0: ldc           #4                  // class de/adorsys/psd2/model/DayOfExecution
       2: aload_0
       3: invokestatic  #5                  // Method java/lang/Enum.valueOf:(Ljava/lang/Class;Ljava/lang/String;)Ljava/lang/Enum;
       6: checkcast     #4                  // class de/adorsys/psd2/model/DayOfExecution
       9: areturn

  private de.adorsys.psd2.model.DayOfExecution(java.lang.String);
    Code:
       0: aload_0
       1: aload_1
       2: iload_2
       3: invokespecial #6                  // Method java/lang/Enum."<init>":(Ljava/lang/String;I)V
       6: aload_0
       7: aload_3
       8: putfield      #7                  // Field value:Ljava/lang/String;
      11: return

  public java.lang.String toString();
    Code:
       0: aload_0
       1: getfield      #7                  // Field value:Ljava/lang/String;
       4: invokestatic  #8                  // Method java/lang/String.valueOf:(Ljava/lang/Object;)Ljava/lang/String;
       7: areturn

  public static de.adorsys.psd2.model.DayOfExecution fromValue(java.lang.String);
    Code:
       0: invokestatic  #9                  // Method values:()[Lde/adorsys/psd2/model/DayOfExecution;
       3: astore_1
       4: aload_1
       5: arraylength
       6: istore_2
       7: iconst_0
       8: istore_3
       9: iload_3
      10: iload_2
      11: if_icmpge     43
      14: aload_1
      15: iload_3
      16: aaload
      17: astore        4
      19: aload         4
      21: getfield      #7                  // Field value:Ljava/lang/String;
      24: invokestatic  #8                  // Method java/lang/String.valueOf:(Ljava/lang/Object;)Ljava/lang/String;
      27: aload_0
      28: invokevirtual #10                 // Method java/lang/String.equals:(Ljava/lang/Object;)Z
      31: ifeq          37
      34: aload         4
      36: areturn
      37: iinc          3, 1
      40: goto          9
      43: aconst_null
      44: areturn

  static {};
    Code:
       0: new           #4                  // class de/adorsys/psd2/model/DayOfExecution
       3: dup
       4: ldc           #11                 // String _1
       6: iconst_0
       7: ldc           #12                 // String 1
       9: invokespecial #13                 // Method "<init>":(Ljava/lang/String;ILjava/lang/String;)V
      12: putstatic     #14                 // Field _1:Lde/adorsys/psd2/model/DayOfExecution;
      15: new           #4                  // class de/adorsys/psd2/model/DayOfExecution
      18: dup
      19: ldc           #15                 // String _2
      21: iconst_1
      22: ldc           #16                 // String 2
      24: invokespecial #13                 // Method "<init>":(Ljava/lang/String;ILjava/lang/String;)V
      27: putstatic     #17                 // Field _2:Lde/adorsys/psd2/model/DayOfExecution;
      30: new           #4                  // class de/adorsys/psd2/model/DayOfExecution
      33: dup
      34: ldc           #18                 // String _3
      36: iconst_2
      37: ldc           #19                 // String 3
      39: invokespecial #13                 // Method "<init>":(Ljava/lang/String;ILjava/lang/String;)V
      42: putstatic     #20                 // Field _3:Lde/adorsys/psd2/model/DayOfExecution;
      45: new           #4                  // class de/adorsys/psd2/model/DayOfExecution
      48: dup
      49: ldc           #21                 // String _4
      51: iconst_3
      52: ldc           #22                 // String 4
      54: invokespecial #13                 // Method "<init>":(Ljava/lang/String;ILjava/lang/String;)V
      57: putstatic     #23                 // Field _4:Lde/adorsys/psd2/model/DayOfExecution;
      60: new           #4                  // class de/adorsys/psd2/model/DayOfExecution
      63: dup
      64: ldc           #24                 // String _5
      66: iconst_4
      67: ldc           #25                 // String 5
      69: invokespecial #13                 // Method "<init>":(Ljava/lang/String;ILjava/lang/String;)V
      72: putstatic     #26                 // Field _5:Lde/adorsys/psd2/model/DayOfExecution;
      75: new           #4                  // class de/adorsys/psd2/model/DayOfExecution
      78: dup
      79: ldc           #27                 // String _6
      81: iconst_5
      82: ldc           #28                 // String 6
      84: invokespecial #13                 // Method "<init>":(Ljava/lang/String;ILjava/lang/String;)V
      87: putstatic     #29                 // Field _6:Lde/adorsys/psd2/model/DayOfExecution;
      90: new           #4                  // class de/adorsys/psd2/model/DayOfExecution
      93: dup
      94: ldc           #30                 // String _7
      96: bipush        6
      98: ldc           #31                 // String 7
     100: invokespecial #13                 // Method "<init>":(Ljava/lang/String;ILjava/lang/String;)V
     103: putstatic     #32                 // Field _7:Lde/adorsys/psd2/model/DayOfExecution;
     106: new           #4                  // class de/adorsys/psd2/model/DayOfExecution
     109: dup
     110: ldc           #33                 // String _8
     112: bipush        7
     114: ldc           #34                 // String 8
     116: invokespecial #13                 // Method "<init>":(Ljava/lang/String;ILjava/lang/String;)V
     119: putstatic     #35                 // Field _8:Lde/adorsys/psd2/model/DayOfExecution;
     122: new           #4                  // class de/adorsys/psd2/model/DayOfExecution
     125: dup
     126: ldc           #36                 // String _9
     128: bipush        8
     130: ldc           #37                 // String 9
     132: invokespecial #13                 // Method "<init>":(Ljava/lang/String;ILjava/lang/String;)V
     135: putstatic     #38                 // Field _9:Lde/adorsys/psd2/model/DayOfExecution;
     138: new           #4                  // class de/adorsys/psd2/model/DayOfExecution
     141: dup
     142: ldc           #39                 // String _10
     144: bipush        9
     146: ldc           #40                 // String 10
     148: invokespecial #13                 // Method "<init>":(Ljava/lang/String;ILjava/lang/String;)V
     151: putstatic     #41                 // Field _10:Lde/adorsys/psd2/model/DayOfExecution;
     154: new           #4                  // class de/adorsys/psd2/model/DayOfExecution
     157: dup
     158: ldc           #42                 // String _11
     160: bipush        10
     162: ldc           #43                 // String 11
     164: invokespecial #13                 // Method "<init>":(Ljava/lang/String;ILjava/lang/String;)V
     167: putstatic     #44                 // Field _11:Lde/adorsys/psd2/model/DayOfExecution;
     170: new           #4                  // class de/adorsys/psd2/model/DayOfExecution
     173: dup
     174: ldc           #45                 // String _12
     176: bipush        11
     178: ldc           #46                 // String 12
     180: invokespecial #13                 // Method "<init>":(Ljava/lang/String;ILjava/lang/String;)V
     183: putstatic     #47                 // Field _12:Lde/adorsys/psd2/model/DayOfExecution;
     186: new           #4                  // class de/adorsys/psd2/model/DayOfExecution
     189: dup
     190: ldc           #48                 // String _13
     192: bipush        12
     194: ldc           #49                 // String 13
     196: invokespecial #13                 // Method "<init>":(Ljava/lang/String;ILjava/lang/String;)V
     199: putstatic     #50                 // Field _13:Lde/adorsys/psd2/model/DayOfExecution;
     202: new           #4                  // class de/adorsys/psd2/model/DayOfExecution
     205: dup
     206: ldc           #51                 // String _14
     208: bipush        13
     210: ldc           #52                 // String 14
     212: invokespecial #13                 // Method "<init>":(Ljava/lang/String;ILjava/lang/String;)V
     215: putstatic     #53                 // Field _14:Lde/adorsys/psd2/model/DayOfExecution;
     218: new           #4                  // class de/adorsys/psd2/model/DayOfExecution
     221: dup
     222: ldc           #54                 // String _15
     224: bipush        14
     226: ldc           #55                 // String 15
     228: invokespecial #13                 // Method "<init>":(Ljava/lang/String;ILjava/lang/String;)V
     231: putstatic     #56                 // Field _15:Lde/adorsys/psd2/model/DayOfExecution;
     234: new           #4                  // class de/adorsys/psd2/model/DayOfExecution
     237: dup
     238: ldc           #57                 // String _16
     240: bipush        15
     242: ldc           #58                 // String 16
     244: invokespecial #13                 // Method "<init>":(Ljava/lang/String;ILjava/lang/String;)V
     247: putstatic     #59                 // Field _16:Lde/adorsys/psd2/model/DayOfExecution;
     250: new           #4                  // class de/adorsys/psd2/model/DayOfExecution
     253: dup
     254: ldc           #60                 // String _17
     256: bipush        16
     258: ldc           #61                 // String 17
     260: invokespecial #13                 // Method "<init>":(Ljava/lang/String;ILjava/lang/String;)V
     263: putstatic     #62                 // Field _17:Lde/adorsys/psd2/model/DayOfExecution;
     266: new           #4                  // class de/adorsys/psd2/model/DayOfExecution
     269: dup
     270: ldc           #63                 // String _18
     272: bipush        17
     274: ldc           #64                 // String 18
     276: invokespecial #13                 // Method "<init>":(Ljava/lang/String;ILjava/lang/String;)V
     279: putstatic     #65                 // Field _18:Lde/adorsys/psd2/model/DayOfExecution;
     282: new           #4                  // class de/adorsys/psd2/model/DayOfExecution
     285: dup
     286: ldc           #66                 // String _19
     288: bipush        18
     290: ldc           #67                 // String 19
     292: invokespecial #13                 // Method "<init>":(Ljava/lang/String;ILjava/lang/String;)V
     295: putstatic     #68                 // Field _19:Lde/adorsys/psd2/model/DayOfExecution;
     298: new           #4                  // class de/adorsys/psd2/model/DayOfExecution
     301: dup
     302: ldc           #69                 // String _20
     304: bipush        19
     306: ldc           #70                 // String 20
     308: invokespecial #13                 // Method "<init>":(Ljava/lang/String;ILjava/lang/String;)V
     311: putstatic     #71                 // Field _20:Lde/adorsys/psd2/model/DayOfExecution;
     314: new           #4                  // class de/adorsys/psd2/model/DayOfExecution
     317: dup
     318: ldc           #72                 // String _21
     320: bipush        20
     322: ldc           #73                 // String 21
     324: invokespecial #13                 // Method "<init>":(Ljava/lang/String;ILjava/lang/String;)V
     327: putstatic     #74                 // Field _21:Lde/adorsys/psd2/model/DayOfExecution;
     330: new           #4                  // class de/adorsys/psd2/model/DayOfExecution
     333: dup
     334: ldc           #75                 // String _22
     336: bipush        21
     338: ldc           #76                 // String 22
     340: invokespecial #13                 // Method "<init>":(Ljava/lang/String;ILjava/lang/String;)V
     343: putstatic     #77                 // Field _22:Lde/adorsys/psd2/model/DayOfExecution;
     346: new           #4                  // class de/adorsys/psd2/model/DayOfExecution
     349: dup
     350: ldc           #78                 // String _23
     352: bipush        22
     354: ldc           #79                 // String 23
     356: invokespecial #13                 // Method "<init>":(Ljava/lang/String;ILjava/lang/String;)V
     359: putstatic     #80                 // Field _23:Lde/adorsys/psd2/model/DayOfExecution;
     362: new           #4                  // class de/adorsys/psd2/model/DayOfExecution
     365: dup
     366: ldc           #81                 // String _24
     368: bipush        23
     370: ldc           #82                 // String 24
     372: invokespecial #13                 // Method "<init>":(Ljava/lang/String;ILjava/lang/String;)V
     375: putstatic     #83                 // Field _24:Lde/adorsys/psd2/model/DayOfExecution;
     378: new           #4                  // class de/adorsys/psd2/model/DayOfExecution
     381: dup
     382: ldc           #84                 // String _25
     384: bipush        24
     386: ldc           #85                 // String 25
     388: invokespecial #13                 // Method "<init>":(Ljava/lang/String;ILjava/lang/String;)V
     391: putstatic     #86                 // Field _25:Lde/adorsys/psd2/model/DayOfExecution;
     394: new           #4                  // class de/adorsys/psd2/model/DayOfExecution
     397: dup
     398: ldc           #87                 // String _26
     400: bipush        25
     402: ldc           #88                 // String 26
     404: invokespecial #13                 // Method "<init>":(Ljava/lang/String;ILjava/lang/String;)V
     407: putstatic     #89                 // Field _26:Lde/adorsys/psd2/model/DayOfExecution;
     410: new           #4                  // class de/adorsys/psd2/model/DayOfExecution
     413: dup
     414: ldc           #90                 // String _27
     416: bipush        26
     418: ldc           #91                 // String 27
     420: invokespecial #13                 // Method "<init>":(Ljava/lang/String;ILjava/lang/String;)V
     423: putstatic     #92                 // Field _27:Lde/adorsys/psd2/model/DayOfExecution;
     426: new           #4                  // class de/adorsys/psd2/model/DayOfExecution
     429: dup
     430: ldc           #93                 // String _28
     432: bipush        27
     434: ldc           #94                 // String 28
     436: invokespecial #13                 // Method "<init>":(Ljava/lang/String;ILjava/lang/String;)V
     439: putstatic     #95                 // Field _28:Lde/adorsys/psd2/model/DayOfExecution;
     442: new           #4                  // class de/adorsys/psd2/model/DayOfExecution
     445: dup
     446: ldc           #96                 // String _29
     448: bipush        28
     450: ldc           #97                 // String 29
     452: invokespecial #13                 // Method "<init>":(Ljava/lang/String;ILjava/lang/String;)V
     455: putstatic     #98                 // Field _29:Lde/adorsys/psd2/model/DayOfExecution;
     458: new           #4                  // class de/adorsys/psd2/model/DayOfExecution
     461: dup
     462: ldc           #99                 // String _30
     464: bipush        29
     466: ldc           #100                // String 30
     468: invokespecial #13                 // Method "<init>":(Ljava/lang/String;ILjava/lang/String;)V
     471: putstatic     #101                // Field _30:Lde/adorsys/psd2/model/DayOfExecution;
     474: new           #4                  // class de/adorsys/psd2/model/DayOfExecution
     477: dup
     478: ldc           #102                // String _31
     480: bipush        30
     482: ldc           #103                // String 31
     484: invokespecial #13                 // Method "<init>":(Ljava/lang/String;ILjava/lang/String;)V
     487: putstatic     #104                // Field _31:Lde/adorsys/psd2/model/DayOfExecution;
     490: bipush        31
     492: anewarray     #4                  // class de/adorsys/psd2/model/DayOfExecution
     495: dup
     496: iconst_0
     497: getstatic     #14                 // Field _1:Lde/adorsys/psd2/model/DayOfExecution;
     500: aastore
     501: dup
     502: iconst_1
     503: getstatic     #17                 // Field _2:Lde/adorsys/psd2/model/DayOfExecution;
     506: aastore
     507: dup
     508: iconst_2
     509: getstatic     #20                 // Field _3:Lde/adorsys/psd2/model/DayOfExecution;
     512: aastore
     513: dup
     514: iconst_3
     515: getstatic     #23                 // Field _4:Lde/adorsys/psd2/model/DayOfExecution;
     518: aastore
     519: dup
     520: iconst_4
     521: getstatic     #26                 // Field _5:Lde/adorsys/psd2/model/DayOfExecution;
     524: aastore
     525: dup
     526: iconst_5
     527: getstatic     #29                 // Field _6:Lde/adorsys/psd2/model/DayOfExecution;
     530: aastore
     531: dup
     532: bipush        6
     534: getstatic     #32                 // Field _7:Lde/adorsys/psd2/model/DayOfExecution;
     537: aastore
     538: dup
     539: bipush        7
     541: getstatic     #35                 // Field _8:Lde/adorsys/psd2/model/DayOfExecution;
     544: aastore
     545: dup
     546: bipush        8
     548: getstatic     #38                 // Field _9:Lde/adorsys/psd2/model/DayOfExecution;
     551: aastore
     552: dup
     553: bipush        9
     555: getstatic     #41                 // Field _10:Lde/adorsys/psd2/model/DayOfExecution;
     558: aastore
     559: dup
     560: bipush        10
     562: getstatic     #44                 // Field _11:Lde/adorsys/psd2/model/DayOfExecution;
     565: aastore
     566: dup
     567: bipush        11
     569: getstatic     #47                 // Field _12:Lde/adorsys/psd2/model/DayOfExecution;
     572: aastore
     573: dup
     574: bipush        12
     576: getstatic     #50                 // Field _13:Lde/adorsys/psd2/model/DayOfExecution;
     579: aastore
     580: dup
     581: bipush        13
     583: getstatic     #53                 // Field _14:Lde/adorsys/psd2/model/DayOfExecution;
     586: aastore
     587: dup
     588: bipush        14
     590: getstatic     #56                 // Field _15:Lde/adorsys/psd2/model/DayOfExecution;
     593: aastore
     594: dup
     595: bipush        15
     597: getstatic     #59                 // Field _16:Lde/adorsys/psd2/model/DayOfExecution;
     600: aastore
     601: dup
     602: bipush        16
     604: getstatic     #62                 // Field _17:Lde/adorsys/psd2/model/DayOfExecution;
     607: aastore
     608: dup
     609: bipush        17
     611: getstatic     #65                 // Field _18:Lde/adorsys/psd2/model/DayOfExecution;
     614: aastore
     615: dup
     616: bipush        18
     618: getstatic     #68                 // Field _19:Lde/adorsys/psd2/model/DayOfExecution;
     621: aastore
     622: dup
     623: bipush        19
     625: getstatic     #71                 // Field _20:Lde/adorsys/psd2/model/DayOfExecution;
     628: aastore
     629: dup
     630: bipush        20
     632: getstatic     #74                 // Field _21:Lde/adorsys/psd2/model/DayOfExecution;
     635: aastore
     636: dup
     637: bipush        21
     639: getstatic     #77                 // Field _22:Lde/adorsys/psd2/model/DayOfExecution;
     642: aastore
     643: dup
     644: bipush        22
     646: getstatic     #80                 // Field _23:Lde/adorsys/psd2/model/DayOfExecution;
     649: aastore
     650: dup
     651: bipush        23
     653: getstatic     #83                 // Field _24:Lde/adorsys/psd2/model/DayOfExecution;
     656: aastore
     657: dup
     658: bipush        24
     660: getstatic     #86                 // Field _25:Lde/adorsys/psd2/model/DayOfExecution;
     663: aastore
     664: dup
     665: bipush        25
     667: getstatic     #89                 // Field _26:Lde/adorsys/psd2/model/DayOfExecution;
     670: aastore
     671: dup
     672: bipush        26
     674: getstatic     #92                 // Field _27:Lde/adorsys/psd2/model/DayOfExecution;
     677: aastore
     678: dup
     679: bipush        27
     681: getstatic     #95                 // Field _28:Lde/adorsys/psd2/model/DayOfExecution;
     684: aastore
     685: dup
     686: bipush        28
     688: getstatic     #98                 // Field _29:Lde/adorsys/psd2/model/DayOfExecution;
     691: aastore
     692: dup
     693: bipush        29
     695: getstatic     #101                // Field _30:Lde/adorsys/psd2/model/DayOfExecution;
     698: aastore
     699: dup
     700: bipush        30
     702: getstatic     #104                // Field _31:Lde/adorsys/psd2/model/DayOfExecution;
     705: aastore
     706: putstatic     #1                  // Field $VALUES:[Lde/adorsys/psd2/model/DayOfExecution;
     709: return
}
