Compiled from "ScaStatus.java"
public final class de.adorsys.psd2.model.ScaStatus extends java.lang.Enum<de.adorsys.psd2.model.ScaStatus> {
  public static final de.adorsys.psd2.model.ScaStatus RECEIVED;

  public static final de.adorsys.psd2.model.ScaStatus PSUIDENTIFIED;

  public static final de.adorsys.psd2.model.ScaStatus PSUAUTHENTICATED;

  public static final de.adorsys.psd2.model.ScaStatus SCAMETHODSELECTED;

  public static final de.adorsys.psd2.model.ScaStatus STARTED;

  public static final de.adorsys.psd2.model.ScaStatus UNCONFIRMED;

  public static final de.adorsys.psd2.model.ScaStatus FINALISED;

  public static final de.adorsys.psd2.model.ScaStatus FAILED;

  public static final de.adorsys.psd2.model.ScaStatus EXEMPTED;

  private java.lang.String value;

  private static final de.adorsys.psd2.model.ScaStatus[] $VALUES;

  public static de.adorsys.psd2.model.ScaStatus[] values();
    Code:
       0: getstatic     #1                  // Field $VALUES:[Lde/adorsys/psd2/model/ScaStatus;
       3: invokevirtual #2                  // Method "[Lde/adorsys/psd2/model/ScaStatus;".clone:()Ljava/lang/Object;
       6: checkcast     #3                  // class "[Lde/adorsys/psd2/model/ScaStatus;"
       9: areturn

  public static de.adorsys.psd2.model.ScaStatus valueOf(java.lang.String);
    Code:
       0: ldc           #4                  // class de/adorsys/psd2/model/ScaStatus
       2: aload_0
       3: invokestatic  #5                  // Method java/lang/Enum.valueOf:(Ljava/lang/Class;Ljava/lang/String;)Ljava/lang/Enum;
       6: checkcast     #4                  // class de/adorsys/psd2/model/ScaStatus
       9: areturn

  private de.adorsys.psd2.model.ScaStatus(java.lang.String);
    Code:
       0: aload_0
       1: aload_1
       2: iload_2
       3: invokespecial #6                  // Method java/lang/Enum."<init>":(Ljava/lang/String;I)V
       6: aload_0
       7: aload_3
       8: putfield      #7                  // Field value:Ljava/lang/String;
      11: return

  public java.lang.String toString();
    Code:
       0: aload_0
       1: getfield      #7                  // Field value:Ljava/lang/String;
       4: invokestatic  #8                  // Method java/lang/String.valueOf:(Ljava/lang/Object;)Ljava/lang/String;
       7: areturn

  public static de.adorsys.psd2.model.ScaStatus fromValue(java.lang.String);
    Code:
       0: invokestatic  #9                  // Method values:()[Lde/adorsys/psd2/model/ScaStatus;
       3: astore_1
       4: aload_1
       5: arraylength
       6: istore_2
       7: iconst_0
       8: istore_3
       9: iload_3
      10: iload_2
      11: if_icmpge     43
      14: aload_1
      15: iload_3
      16: aaload
      17: astore        4
      19: aload         4
      21: getfield      #7                  // Field value:Ljava/lang/String;
      24: invokestatic  #8                  // Method java/lang/String.valueOf:(Ljava/lang/Object;)Ljava/lang/String;
      27: aload_0
      28: invokevirtual #10                 // Method java/lang/String.equals:(Ljava/lang/Object;)Z
      31: ifeq          37
      34: aload         4
      36: areturn
      37: iinc          3, 1
      40: goto          9
      43: aconst_null
      44: areturn

  static {};
    Code:
       0: new           #4                  // class de/adorsys/psd2/model/ScaStatus
       3: dup
       4: ldc           #11                 // String RECEIVED
       6: iconst_0
       7: ldc           #12                 // String received
       9: invokespecial #13                 // Method "<init>":(Ljava/lang/String;ILjava/lang/String;)V
      12: putstatic     #14                 // Field RECEIVED:Lde/adorsys/psd2/model/ScaStatus;
      15: new           #4                  // class de/adorsys/psd2/model/ScaStatus
      18: dup
      19: ldc           #15                 // String PSUIDENTIFIED
      21: iconst_1
      22: ldc           #16                 // String psuIdentified
      24: invokespecial #13                 // Method "<init>":(Ljava/lang/String;ILjava/lang/String;)V
      27: putstatic     #17                 // Field PSUIDENTIFIED:Lde/adorsys/psd2/model/ScaStatus;
      30: new           #4                  // class de/adorsys/psd2/model/ScaStatus
      33: dup
      34: ldc           #18                 // String PSUAUTHENTICATED
      36: iconst_2
      37: ldc           #19                 // String psuAuthenticated
      39: invokespecial #13                 // Method "<init>":(Ljava/lang/String;ILjava/lang/String;)V
      42: putstatic     #20                 // Field PSUAUTHENTICATED:Lde/adorsys/psd2/model/ScaStatus;
      45: new           #4                  // class de/adorsys/psd2/model/ScaStatus
      48: dup
      49: ldc           #21                 // String SCAMETHODSELECTED
      51: iconst_3
      52: ldc           #22                 // String scaMethodSelected
      54: invokespecial #13                 // Method "<init>":(Ljava/lang/String;ILjava/lang/String;)V
      57: putstatic     #23                 // Field SCAMETHODSELECTED:Lde/adorsys/psd2/model/ScaStatus;
      60: new           #4                  // class de/adorsys/psd2/model/ScaStatus
      63: dup
      64: ldc           #24                 // String STARTED
      66: iconst_4
      67: ldc           #25                 // String started
      69: invokespecial #13                 // Method "<init>":(Ljava/lang/String;ILjava/lang/String;)V
      72: putstatic     #26                 // Field STARTED:Lde/adorsys/psd2/model/ScaStatus;
      75: new           #4                  // class de/adorsys/psd2/model/ScaStatus
      78: dup
      79: ldc           #27                 // String UNCONFIRMED
      81: iconst_5
      82: ldc           #28                 // String unconfirmed
      84: invokespecial #13                 // Method "<init>":(Ljava/lang/String;ILjava/lang/String;)V
      87: putstatic     #29                 // Field UNCONFIRMED:Lde/adorsys/psd2/model/ScaStatus;
      90: new           #4                  // class de/adorsys/psd2/model/ScaStatus
      93: dup
      94: ldc           #30                 // String FINALISED
      96: bipush        6
      98: ldc           #31                 // String finalised
     100: invokespecial #13                 // Method "<init>":(Ljava/lang/String;ILjava/lang/String;)V
     103: putstatic     #32                 // Field FINALISED:Lde/adorsys/psd2/model/ScaStatus;
     106: new           #4                  // class de/adorsys/psd2/model/ScaStatus
     109: dup
     110: ldc           #33                 // String FAILED
     112: bipush        7
     114: ldc           #34                 // String failed
     116: invokespecial #13                 // Method "<init>":(Ljava/lang/String;ILjava/lang/String;)V
     119: putstatic     #35                 // Field FAILED:Lde/adorsys/psd2/model/ScaStatus;
     122: new           #4                  // class de/adorsys/psd2/model/ScaStatus
     125: dup
     126: ldc           #36                 // String EXEMPTED
     128: bipush        8
     130: ldc           #37                 // String exempted
     132: invokespecial #13                 // Method "<init>":(Ljava/lang/String;ILjava/lang/String;)V
     135: putstatic     #38                 // Field EXEMPTED:Lde/adorsys/psd2/model/ScaStatus;
     138: bipush        9
     140: anewarray     #4                  // class de/adorsys/psd2/model/ScaStatus
     143: dup
     144: iconst_0
     145: getstatic     #14                 // Field RECEIVED:Lde/adorsys/psd2/model/ScaStatus;
     148: aastore
     149: dup
     150: iconst_1
     151: getstatic     #17                 // Field PSUIDENTIFIED:Lde/adorsys/psd2/model/ScaStatus;
     154: aastore
     155: dup
     156: iconst_2
     157: getstatic     #20                 // Field PSUAUTHENTICATED:Lde/adorsys/psd2/model/ScaStatus;
     160: aastore
     161: dup
     162: iconst_3
     163: getstatic     #23                 // Field SCAMETHODSELECTED:Lde/adorsys/psd2/model/ScaStatus;
     166: aastore
     167: dup
     168: iconst_4
     169: getstatic     #26                 // Field STARTED:Lde/adorsys/psd2/model/ScaStatus;
     172: aastore
     173: dup
     174: iconst_5
     175: getstatic     #29                 // Field UNCONFIRMED:Lde/adorsys/psd2/model/ScaStatus;
     178: aastore
     179: dup
     180: bipush        6
     182: getstatic     #32                 // Field FINALISED:Lde/adorsys/psd2/model/ScaStatus;
     185: aastore
     186: dup
     187: bipush        7
     189: getstatic     #35                 // Field FAILED:Lde/adorsys/psd2/model/ScaStatus;
     192: aastore
     193: dup
     194: bipush        8
     196: getstatic     #38                 // Field EXEMPTED:Lde/adorsys/psd2/model/ScaStatus;
     199: aastore
     200: putstatic     #1                  // Field $VALUES:[Lde/adorsys/psd2/model/ScaStatus;
     203: return
}
