Compiled from "BenchmarkResult.java"
class org.hpccsystems.commons.benchmarking.BenchmarkResult$MetricInfo {
  public org.hpccsystems.commons.benchmarking.IMetric metric;

  public org.hpccsystems.commons.benchmarking.Units$Scale desiredScale;

  final org.hpccsystems.commons.benchmarking.BenchmarkResult this$0;

  public org.hpccsystems.commons.benchmarking.BenchmarkResult$MetricInfo(org.hpccsystems.commons.benchmarking.BenchmarkResult, org.hpccsystems.commons.benchmarking.IMetric);
    Code:
       0: aload_0
       1: aload_1
       2: putfield      #1                  // Field this$0:Lorg/hpccsystems/commons/benchmarking/BenchmarkResult;
       5: aload_0
       6: invokespecial #2                  // Method java/lang/Object."<init>":()V
       9: aload_0
      10: aconst_null
      11: putfield      #3                  // Field metric:Lorg/hpccsystems/commons/benchmarking/IMetric;
      14: aload_0
      15: aconst_null
      16: putfield      #4                  // Field desiredScale:Lorg/hpccsystems/commons/benchmarking/Units$Scale;
      19: aload_0
      20: aload_2
      21: putfield      #3                  // Field metric:Lorg/hpccsystems/commons/benchmarking/IMetric;
      24: return
}
