Compiled from "BenchmarkResult.java"
public class org.hpccsystems.commons.benchmarking.BenchmarkResult {
  private java.lang.String testGroup;

  private java.lang.String testName;

  private java.lang.String testDescription;

  private java.util.ArrayList<org.hpccsystems.commons.benchmarking.BenchmarkParam> parameters;

  private java.util.HashMap<java.lang.String, org.hpccsystems.commons.benchmarking.BenchmarkResult$MetricInfo> metrics;

  public org.hpccsystems.commons.benchmarking.BenchmarkResult(java.lang.String, java.lang.String);
    Code:
       0: aload_0
       1: invokespecial #1                  // Method java/lang/Object."<init>":()V
       4: aload_0
       5: ldc           #2                  // String
       7: putfield      #3                  // Field testGroup:Ljava/lang/String;
      10: aload_0
      11: ldc           #2                  // String
      13: putfield      #4                  // Field testName:Ljava/lang/String;
      16: aload_0
      17: ldc           #2                  // String
      19: putfield      #5                  // Field testDescription:Ljava/lang/String;
      22: aload_0
      23: new           #6                  // class java/util/ArrayList
      26: dup
      27: invokespecial #7                  // Method java/util/ArrayList."<init>":()V
      30: putfield      #8                  // Field parameters:Ljava/util/ArrayList;
      33: aload_0
      34: new           #9                  // class java/util/HashMap
      37: dup
      38: invokespecial #10                 // Method java/util/HashMap."<init>":()V
      41: putfield      #11                 // Field metrics:Ljava/util/HashMap;
      44: aload_0
      45: aload_1
      46: putfield      #3                  // Field testGroup:Ljava/lang/String;
      49: aload_0
      50: aload_2
      51: putfield      #4                  // Field testName:Ljava/lang/String;
      54: return

  public org.hpccsystems.commons.benchmarking.BenchmarkResult(java.lang.String, java.lang.String, java.lang.String);
    Code:
       0: aload_0
       1: invokespecial #1                  // Method java/lang/Object."<init>":()V
       4: aload_0
       5: ldc           #2                  // String
       7: putfield      #3                  // Field testGroup:Ljava/lang/String;
      10: aload_0
      11: ldc           #2                  // String
      13: putfield      #4                  // Field testName:Ljava/lang/String;
      16: aload_0
      17: ldc           #2                  // String
      19: putfield      #5                  // Field testDescription:Ljava/lang/String;
      22: aload_0
      23: new           #6                  // class java/util/ArrayList
      26: dup
      27: invokespecial #7                  // Method java/util/ArrayList."<init>":()V
      30: putfield      #8                  // Field parameters:Ljava/util/ArrayList;
      33: aload_0
      34: new           #9                  // class java/util/HashMap
      37: dup
      38: invokespecial #10                 // Method java/util/HashMap."<init>":()V
      41: putfield      #11                 // Field metrics:Ljava/util/HashMap;
      44: aload_0
      45: aload_1
      46: putfield      #3                  // Field testGroup:Ljava/lang/String;
      49: aload_0
      50: aload_2
      51: putfield      #4                  // Field testName:Ljava/lang/String;
      54: aload_0
      55: aload_3
      56: putfield      #5                  // Field testDescription:Ljava/lang/String;
      59: return

  public org.hpccsystems.commons.benchmarking.IMetric getMetric(java.lang.String);
    Code:
       0: aload_0
       1: getfield      #11                 // Field metrics:Ljava/util/HashMap;
       4: aload_1
       5: invokevirtual #12                 // Method java/util/HashMap.get:(Ljava/lang/Object;)Ljava/lang/Object;
       8: checkcast     #13                 // class org/hpccsystems/commons/benchmarking/BenchmarkResult$MetricInfo
      11: astore_2
      12: aload_2
      13: ifnonnull     18
      16: aconst_null
      17: areturn
      18: aload_2
      19: getfield      #14                 // Field org/hpccsystems/commons/benchmarking/BenchmarkResult$MetricInfo.metric:Lorg/hpccsystems/commons/benchmarking/IMetric;
      22: areturn

  public void addMetric(org.hpccsystems.commons.benchmarking.IMetric);
    Code:
       0: aload_1
       1: ifnonnull     14
       4: new           #15                 // class java/lang/RuntimeException
       7: dup
       8: ldc           #16                 // String BenchmarkResult: Error: A null IMetric was provided to addMetric.
      10: invokespecial #17                 // Method java/lang/RuntimeException."<init>":(Ljava/lang/String;)V
      13: athrow
      14: aload_0
      15: getfield      #11                 // Field metrics:Ljava/util/HashMap;
      18: aload_1
      19: invokeinterface #18,  1           // InterfaceMethod org/hpccsystems/commons/benchmarking/IMetric.getName:()Ljava/lang/String;
      24: invokevirtual #12                 // Method java/util/HashMap.get:(Ljava/lang/Object;)Ljava/lang/Object;
      27: checkcast     #13                 // class org/hpccsystems/commons/benchmarking/BenchmarkResult$MetricInfo
      30: astore_2
      31: aload_2
      32: ifnonnull     61
      35: aload_0
      36: getfield      #11                 // Field metrics:Ljava/util/HashMap;
      39: aload_1
      40: invokeinterface #18,  1           // InterfaceMethod org/hpccsystems/commons/benchmarking/IMetric.getName:()Ljava/lang/String;
      45: new           #13                 // class org/hpccsystems/commons/benchmarking/BenchmarkResult$MetricInfo
      48: dup
      49: aload_0
      50: aload_1
      51: invokespecial #19                 // Method org/hpccsystems/commons/benchmarking/BenchmarkResult$MetricInfo."<init>":(Lorg/hpccsystems/commons/benchmarking/BenchmarkResult;Lorg/hpccsystems/commons/benchmarking/IMetric;)V
      54: invokevirtual #20                 // Method java/util/HashMap.put:(Ljava/lang/Object;Ljava/lang/Object;)Ljava/lang/Object;
      57: pop
      58: goto          66
      61: aload_2
      62: aload_1
      63: putfield      #14                 // Field org/hpccsystems/commons/benchmarking/BenchmarkResult$MetricInfo.metric:Lorg/hpccsystems/commons/benchmarking/IMetric;
      66: return

  public void addMetrics(java.util.List<org.hpccsystems.commons.benchmarking.IMetric>);
    Code:
       0: iconst_0
       1: istore_2
       2: iload_2
       3: aload_1
       4: invokeinterface #21,  1           // InterfaceMethod java/util/List.size:()I
       9: if_icmpge     32
      12: aload_0
      13: aload_1
      14: iload_2
      15: invokeinterface #22,  2           // InterfaceMethod java/util/List.get:(I)Ljava/lang/Object;
      20: checkcast     #23                 // class org/hpccsystems/commons/benchmarking/IMetric
      23: invokevirtual #24                 // Method addMetric:(Lorg/hpccsystems/commons/benchmarking/IMetric;)V
      26: iinc          2, 1
      29: goto          2
      32: return

  public void addParameter(org.hpccsystems.commons.benchmarking.BenchmarkParam);
    Code:
       0: aload_0
       1: getfield      #8                  // Field parameters:Ljava/util/ArrayList;
       4: aload_1
       5: invokevirtual #25                 // Method java/util/ArrayList.add:(Ljava/lang/Object;)Z
       8: pop
       9: return

  public void setMetricDesiredUnitScale(java.lang.String, org.hpccsystems.commons.benchmarking.Units$Scale);
    Code:
       0: aload_0
       1: getfield      #11                 // Field metrics:Ljava/util/HashMap;
       4: aload_1
       5: invokevirtual #12                 // Method java/util/HashMap.get:(Ljava/lang/Object;)Ljava/lang/Object;
       8: checkcast     #13                 // class org/hpccsystems/commons/benchmarking/BenchmarkResult$MetricInfo
      11: astore_3
      12: aload_3
      13: ifnonnull     36
      16: new           #13                 // class org/hpccsystems/commons/benchmarking/BenchmarkResult$MetricInfo
      19: dup
      20: aload_0
      21: aconst_null
      22: invokespecial #19                 // Method org/hpccsystems/commons/benchmarking/BenchmarkResult$MetricInfo."<init>":(Lorg/hpccsystems/commons/benchmarking/BenchmarkResult;Lorg/hpccsystems/commons/benchmarking/IMetric;)V
      25: astore_3
      26: aload_0
      27: getfield      #11                 // Field metrics:Ljava/util/HashMap;
      30: aload_1
      31: aload_3
      32: invokevirtual #20                 // Method java/util/HashMap.put:(Ljava/lang/Object;Ljava/lang/Object;)Ljava/lang/Object;
      35: pop
      36: aload_3
      37: aload_2
      38: putfield      #26                 // Field org/hpccsystems/commons/benchmarking/BenchmarkResult$MetricInfo.desiredScale:Lorg/hpccsystems/commons/benchmarking/Units$Scale;
      41: return

  public org.json.JSONObject toJson();
    Code:
       0: aload_0
       1: aconst_null
       2: invokevirtual #27                 // Method toJson:([Ljava/lang/String;)Lorg/json/JSONObject;
       5: areturn

  private org.json.JSONObject serializeMetric(org.hpccsystems.commons.benchmarking.BenchmarkResult$MetricInfo, boolean);
    Code:
       0: aload_1
       1: getfield      #14                 // Field org/hpccsystems/commons/benchmarking/BenchmarkResult$MetricInfo.metric:Lorg/hpccsystems/commons/benchmarking/IMetric;
       4: astore_3
       5: getstatic     #28                 // Field org/hpccsystems/commons/benchmarking/Units$Scale.UNIT:Lorg/hpccsystems/commons/benchmarking/Units$Scale;
       8: astore        4
      10: aload_1
      11: getfield      #26                 // Field org/hpccsystems/commons/benchmarking/BenchmarkResult$MetricInfo.desiredScale:Lorg/hpccsystems/commons/benchmarking/Units$Scale;
      14: ifnull        26
      17: aload_1
      18: getfield      #26                 // Field org/hpccsystems/commons/benchmarking/BenchmarkResult$MetricInfo.desiredScale:Lorg/hpccsystems/commons/benchmarking/Units$Scale;
      21: astore        4
      23: goto          46
      26: aload_3
      27: invokeinterface #29,  1           // InterfaceMethod org/hpccsystems/commons/benchmarking/IMetric.getUnits:()Lorg/hpccsystems/commons/benchmarking/Units;
      32: ifnull        46
      35: aload_3
      36: invokeinterface #29,  1           // InterfaceMethod org/hpccsystems/commons/benchmarking/IMetric.getUnits:()Lorg/hpccsystems/commons/benchmarking/Units;
      41: getfield      #30                 // Field org/hpccsystems/commons/benchmarking/Units.scale:Lorg/hpccsystems/commons/benchmarking/Units$Scale;
      44: astore        4
      46: aload_3
      47: invokeinterface #31,  1           // InterfaceMethod org/hpccsystems/commons/benchmarking/IMetric.getValue:()D
      52: aload_3
      53: invokeinterface #29,  1           // InterfaceMethod org/hpccsystems/commons/benchmarking/IMetric.getUnits:()Lorg/hpccsystems/commons/benchmarking/Units;
      58: getfield      #30                 // Field org/hpccsystems/commons/benchmarking/Units.scale:Lorg/hpccsystems/commons/benchmarking/Units$Scale;
      61: aload         4
      63: invokestatic  #32                 // Method org/hpccsystems/commons/benchmarking/Units.calculateScaleConversion:(Lorg/hpccsystems/commons/benchmarking/Units$Scale;Lorg/hpccsystems/commons/benchmarking/Units$Scale;)D
      66: dmul
      67: d2f
      68: fstore        5
      70: iload_2
      71: ifeq          250
      74: new           #33                 // class org/json/JSONObject
      77: dup
      78: invokespecial #34                 // Method org/json/JSONObject."<init>":()V
      81: astore        6
      83: aload         6
      85: ldc           #35                 // String group
      87: aload_0
      88: getfield      #3                  // Field testGroup:Ljava/lang/String;
      91: invokevirtual #36                 // Method org/json/JSONObject.put:(Ljava/lang/String;Ljava/lang/Object;)Lorg/json/JSONObject;
      94: pop
      95: aload         6
      97: ldc           #37                 // String test
      99: aload_0
     100: getfield      #4                  // Field testName:Ljava/lang/String;
     103: invokevirtual #36                 // Method org/json/JSONObject.put:(Ljava/lang/String;Ljava/lang/Object;)Lorg/json/JSONObject;
     106: pop
     107: aload         6
     109: ldc           #38                 // String result
     111: aload_3
     112: invokeinterface #18,  1           // InterfaceMethod org/hpccsystems/commons/benchmarking/IMetric.getName:()Ljava/lang/String;
     117: invokevirtual #36                 // Method org/json/JSONObject.put:(Ljava/lang/String;Ljava/lang/Object;)Lorg/json/JSONObject;
     120: pop
     121: aload         6
     123: ldc           #39                 // String value
     125: fload         5
     127: invokevirtual #40                 // Method org/json/JSONObject.put:(Ljava/lang/String;F)Lorg/json/JSONObject;
     130: pop
     131: iconst_0
     132: istore        7
     134: iload         7
     136: aload_0
     137: getfield      #8                  // Field parameters:Ljava/util/ArrayList;
     140: invokevirtual #41                 // Method java/util/ArrayList.size:()I
     143: if_icmpge     182
     146: aload_0
     147: getfield      #8                  // Field parameters:Ljava/util/ArrayList;
     150: iload         7
     152: invokevirtual #42                 // Method java/util/ArrayList.get:(I)Ljava/lang/Object;
     155: checkcast     #43                 // class org/hpccsystems/commons/benchmarking/BenchmarkParam
     158: astore        8
     160: aload         6
     162: aload         8
     164: getfield      #44                 // Field org/hpccsystems/commons/benchmarking/BenchmarkParam.name:Ljava/lang/String;
     167: aload         8
     169: getfield      #45                 // Field org/hpccsystems/commons/benchmarking/BenchmarkParam.value:Ljava/lang/String;
     172: invokevirtual #36                 // Method org/json/JSONObject.put:(Ljava/lang/String;Ljava/lang/Object;)Lorg/json/JSONObject;
     175: pop
     176: iinc          7, 1
     179: goto          134
     182: aload_3
     183: invokeinterface #29,  1           // InterfaceMethod org/hpccsystems/commons/benchmarking/IMetric.getUnits:()Lorg/hpccsystems/commons/benchmarking/Units;
     188: astore        7
     190: aload         7
     192: ifnull        224
     195: new           #46                 // class org/hpccsystems/commons/benchmarking/Units
     198: dup
     199: aload         7
     201: getfield      #47                 // Field org/hpccsystems/commons/benchmarking/Units.type:Lorg/hpccsystems/commons/benchmarking/Units$Type;
     204: aload         4
     206: invokespecial #48                 // Method org/hpccsystems/commons/benchmarking/Units."<init>":(Lorg/hpccsystems/commons/benchmarking/Units$Type;Lorg/hpccsystems/commons/benchmarking/Units$Scale;)V
     209: astore        8
     211: aload         6
     213: ldc           #49                 // String units
     215: aload         8
     217: invokevirtual #50                 // Method org/hpccsystems/commons/benchmarking/Units.toString:()Ljava/lang/String;
     220: invokevirtual #36                 // Method org/json/JSONObject.put:(Ljava/lang/String;Ljava/lang/Object;)Lorg/json/JSONObject;
     223: pop
     224: aload_3
     225: invokeinterface #51,  1           // InterfaceMethod org/hpccsystems/commons/benchmarking/IMetric.getDescription:()Ljava/lang/String;
     230: astore        8
     232: aload         8
     234: ifnull        247
     237: aload         6
     239: ldc           #52                 // String description
     241: aload         8
     243: invokevirtual #36                 // Method org/json/JSONObject.put:(Ljava/lang/String;Ljava/lang/Object;)Lorg/json/JSONObject;
     246: pop
     247: aload         6
     249: areturn
     250: new           #33                 // class org/json/JSONObject
     253: dup
     254: invokespecial #34                 // Method org/json/JSONObject."<init>":()V
     257: astore        6
     259: aload         6
     261: ldc           #53                 // String name
     263: aload_3
     264: invokeinterface #18,  1           // InterfaceMethod org/hpccsystems/commons/benchmarking/IMetric.getName:()Ljava/lang/String;
     269: invokevirtual #36                 // Method org/json/JSONObject.put:(Ljava/lang/String;Ljava/lang/Object;)Lorg/json/JSONObject;
     272: pop
     273: aload_3
     274: invokeinterface #29,  1           // InterfaceMethod org/hpccsystems/commons/benchmarking/IMetric.getUnits:()Lorg/hpccsystems/commons/benchmarking/Units;
     279: astore        7
     281: aload         7
     283: ifnull        315
     286: new           #46                 // class org/hpccsystems/commons/benchmarking/Units
     289: dup
     290: aload         7
     292: getfield      #47                 // Field org/hpccsystems/commons/benchmarking/Units.type:Lorg/hpccsystems/commons/benchmarking/Units$Type;
     295: aload         4
     297: invokespecial #48                 // Method org/hpccsystems/commons/benchmarking/Units."<init>":(Lorg/hpccsystems/commons/benchmarking/Units$Type;Lorg/hpccsystems/commons/benchmarking/Units$Scale;)V
     300: astore        8
     302: aload         6
     304: ldc           #49                 // String units
     306: aload         8
     308: invokevirtual #50                 // Method org/hpccsystems/commons/benchmarking/Units.toString:()Ljava/lang/String;
     311: invokevirtual #36                 // Method org/json/JSONObject.put:(Ljava/lang/String;Ljava/lang/Object;)Lorg/json/JSONObject;
     314: pop
     315: aload_3
     316: invokeinterface #51,  1           // InterfaceMethod org/hpccsystems/commons/benchmarking/IMetric.getDescription:()Ljava/lang/String;
     321: astore        8
     323: aload         8
     325: ifnull        338
     328: aload         6
     330: ldc           #52                 // String description
     332: aload         8
     334: invokevirtual #36                 // Method org/json/JSONObject.put:(Ljava/lang/String;Ljava/lang/Object;)Lorg/json/JSONObject;
     337: pop
     338: aload         6
     340: ldc           #39                 // String value
     342: fload         5
     344: invokevirtual #40                 // Method org/json/JSONObject.put:(Ljava/lang/String;F)Lorg/json/JSONObject;
     347: pop
     348: aload         6
     350: areturn

  public org.json.JSONObject toJson(java.lang.String[]);
    Code:
       0: new           #33                 // class org/json/JSONObject
       3: dup
       4: invokespecial #34                 // Method org/json/JSONObject."<init>":()V
       7: astore_2
       8: aload_2
       9: ldc           #53                 // String name
      11: aload_0
      12: getfield      #4                  // Field testName:Ljava/lang/String;
      15: invokevirtual #36                 // Method org/json/JSONObject.put:(Ljava/lang/String;Ljava/lang/Object;)Lorg/json/JSONObject;
      18: pop
      19: aload_2
      20: ldc           #52                 // String description
      22: aload_0
      23: getfield      #5                  // Field testDescription:Ljava/lang/String;
      26: invokevirtual #36                 // Method org/json/JSONObject.put:(Ljava/lang/String;Ljava/lang/Object;)Lorg/json/JSONObject;
      29: pop
      30: new           #54                 // class org/json/JSONArray
      33: dup
      34: invokespecial #55                 // Method org/json/JSONArray."<init>":()V
      37: astore_3
      38: iconst_0
      39: istore        4
      41: iload         4
      43: aload_0
      44: getfield      #8                  // Field parameters:Ljava/util/ArrayList;
      47: invokevirtual #41                 // Method java/util/ArrayList.size:()I
      50: if_icmpge     83
      53: aload_0
      54: getfield      #8                  // Field parameters:Ljava/util/ArrayList;
      57: iload         4
      59: invokevirtual #42                 // Method java/util/ArrayList.get:(I)Ljava/lang/Object;
      62: checkcast     #43                 // class org/hpccsystems/commons/benchmarking/BenchmarkParam
      65: invokevirtual #56                 // Method org/hpccsystems/commons/benchmarking/BenchmarkParam.toJson:()Lorg/json/JSONObject;
      68: astore        5
      70: aload_3
      71: aload         5
      73: invokevirtual #57                 // Method org/json/JSONArray.put:(Ljava/lang/Object;)Lorg/json/JSONArray;
      76: pop
      77: iinc          4, 1
      80: goto          41
      83: aload_2
      84: ldc           #58                 // String parameters
      86: aload_0
      87: getfield      #8                  // Field parameters:Ljava/util/ArrayList;
      90: invokevirtual #59                 // Method org/json/JSONObject.put:(Ljava/lang/String;Ljava/util/Collection;)Lorg/json/JSONObject;
      93: pop
      94: new           #54                 // class org/json/JSONArray
      97: dup
      98: invokespecial #55                 // Method org/json/JSONArray."<init>":()V
     101: astore        4
     103: aload_1
     104: ifnull        112
     107: aload_1
     108: arraylength
     109: ifne          199
     112: aload_0
     113: getfield      #11                 // Field metrics:Ljava/util/HashMap;
     116: invokevirtual #60                 // Method java/util/HashMap.entrySet:()Ljava/util/Set;
     119: invokeinterface #61,  1           // InterfaceMethod java/util/Set.iterator:()Ljava/util/Iterator;
     124: astore        5
     126: aload         5
     128: invokeinterface #62,  1           // InterfaceMethod java/util/Iterator.hasNext:()Z
     133: ifeq          196
     136: aload         5
     138: invokeinterface #63,  1           // InterfaceMethod java/util/Iterator.next:()Ljava/lang/Object;
     143: checkcast     #64                 // class java/util/Map$Entry
     146: astore        6
     148: aload         6
     150: invokeinterface #65,  1           // InterfaceMethod java/util/Map$Entry.getValue:()Ljava/lang/Object;
     155: checkcast     #13                 // class org/hpccsystems/commons/benchmarking/BenchmarkResult$MetricInfo
     158: astore        7
     160: aload         7
     162: ifnull        126
     165: aload         7
     167: getfield      #14                 // Field org/hpccsystems/commons/benchmarking/BenchmarkResult$MetricInfo.metric:Lorg/hpccsystems/commons/benchmarking/IMetric;
     170: ifnonnull     176
     173: goto          126
     176: aload_0
     177: aload         7
     179: iconst_0
     180: invokespecial #66                 // Method serializeMetric:(Lorg/hpccsystems/commons/benchmarking/BenchmarkResult$MetricInfo;Z)Lorg/json/JSONObject;
     183: astore        8
     185: aload         4
     187: aload         8
     189: invokevirtual #57                 // Method org/json/JSONArray.put:(Ljava/lang/Object;)Lorg/json/JSONArray;
     192: pop
     193: goto          126
     196: goto          264
     199: iconst_0
     200: istore        5
     202: iload         5
     204: aload_1
     205: arraylength
     206: if_icmpge     264
     209: aload_0
     210: getfield      #11                 // Field metrics:Ljava/util/HashMap;
     213: aload_1
     214: iload         5
     216: aaload
     217: invokevirtual #12                 // Method java/util/HashMap.get:(Ljava/lang/Object;)Ljava/lang/Object;
     220: checkcast     #13                 // class org/hpccsystems/commons/benchmarking/BenchmarkResult$MetricInfo
     223: astore        6
     225: aload         6
     227: ifnull        258
     230: aload         6
     232: getfield      #14                 // Field org/hpccsystems/commons/benchmarking/BenchmarkResult$MetricInfo.metric:Lorg/hpccsystems/commons/benchmarking/IMetric;
     235: ifnonnull     241
     238: goto          258
     241: aload_0
     242: aload         6
     244: iconst_0
     245: invokespecial #66                 // Method serializeMetric:(Lorg/hpccsystems/commons/benchmarking/BenchmarkResult$MetricInfo;Z)Lorg/json/JSONObject;
     248: astore        7
     250: aload         4
     252: aload         7
     254: invokevirtual #57                 // Method org/json/JSONArray.put:(Ljava/lang/Object;)Lorg/json/JSONArray;
     257: pop
     258: iinc          5, 1
     261: goto          202
     264: aload_2
     265: ldc           #67                 // String results
     267: aload         4
     269: invokevirtual #36                 // Method org/json/JSONObject.put:(Ljava/lang/String;Ljava/lang/Object;)Lorg/json/JSONObject;
     272: pop
     273: aload_2
     274: areturn

  public org.json.JSONArray toFlatJson();
    Code:
       0: aload_0
       1: aconst_null
       2: invokevirtual #68                 // Method toFlatJson:([Ljava/lang/String;)Lorg/json/JSONArray;
       5: areturn

  public org.json.JSONArray toFlatJson(java.lang.String[]);
    Code:
       0: new           #54                 // class org/json/JSONArray
       3: dup
       4: invokespecial #55                 // Method org/json/JSONArray."<init>":()V
       7: astore_2
       8: aload_1
       9: ifnull        17
      12: aload_1
      13: arraylength
      14: ifne          100
      17: aload_0
      18: getfield      #11                 // Field metrics:Ljava/util/HashMap;
      21: invokevirtual #60                 // Method java/util/HashMap.entrySet:()Ljava/util/Set;
      24: invokeinterface #61,  1           // InterfaceMethod java/util/Set.iterator:()Ljava/util/Iterator;
      29: astore_3
      30: aload_3
      31: invokeinterface #62,  1           // InterfaceMethod java/util/Iterator.hasNext:()Z
      36: ifeq          97
      39: aload_3
      40: invokeinterface #63,  1           // InterfaceMethod java/util/Iterator.next:()Ljava/lang/Object;
      45: checkcast     #64                 // class java/util/Map$Entry
      48: astore        4
      50: aload         4
      52: invokeinterface #65,  1           // InterfaceMethod java/util/Map$Entry.getValue:()Ljava/lang/Object;
      57: checkcast     #13                 // class org/hpccsystems/commons/benchmarking/BenchmarkResult$MetricInfo
      60: astore        5
      62: aload         5
      64: ifnull        30
      67: aload         5
      69: getfield      #14                 // Field org/hpccsystems/commons/benchmarking/BenchmarkResult$MetricInfo.metric:Lorg/hpccsystems/commons/benchmarking/IMetric;
      72: ifnonnull     78
      75: goto          30
      78: aload_0
      79: aload         5
      81: iconst_1
      82: invokespecial #66                 // Method serializeMetric:(Lorg/hpccsystems/commons/benchmarking/BenchmarkResult$MetricInfo;Z)Lorg/json/JSONObject;
      85: astore        6
      87: aload_2
      88: aload         6
      90: invokevirtual #57                 // Method org/json/JSONArray.put:(Ljava/lang/Object;)Lorg/json/JSONArray;
      93: pop
      94: goto          30
      97: goto          161
     100: iconst_0
     101: istore_3
     102: iload_3
     103: aload_1
     104: arraylength
     105: if_icmpge     161
     108: aload_0
     109: getfield      #11                 // Field metrics:Ljava/util/HashMap;
     112: aload_1
     113: iload_3
     114: aaload
     115: invokevirtual #12                 // Method java/util/HashMap.get:(Ljava/lang/Object;)Ljava/lang/Object;
     118: checkcast     #13                 // class org/hpccsystems/commons/benchmarking/BenchmarkResult$MetricInfo
     121: astore        4
     123: aload         4
     125: ifnull        155
     128: aload         4
     130: getfield      #14                 // Field org/hpccsystems/commons/benchmarking/BenchmarkResult$MetricInfo.metric:Lorg/hpccsystems/commons/benchmarking/IMetric;
     133: ifnonnull     139
     136: goto          155
     139: aload_0
     140: aload         4
     142: iconst_1
     143: invokespecial #66                 // Method serializeMetric:(Lorg/hpccsystems/commons/benchmarking/BenchmarkResult$MetricInfo;Z)Lorg/json/JSONObject;
     146: astore        5
     148: aload_2
     149: aload         5
     151: invokevirtual #57                 // Method org/json/JSONArray.put:(Ljava/lang/Object;)Lorg/json/JSONArray;
     154: pop
     155: iinc          3, 1
     158: goto          102
     161: aload_2
     162: areturn
}
