Compiled from "LogStoreConstants.java"
final class org.jboss.as.txn.subsystem.LogStoreConstants$2 extends java.util.HashMap<java.lang.String, java.lang.String> {
  private static final long serialVersionUID;

  org.jboss.as.txn.subsystem.LogStoreConstants$2();
    Code:
       0: aload_0
       1: invokespecial #2                  // Method java/util/HashMap."<init>":()V
       4: aload_0
       5: ldc           #3                  // String jmx-name
       7: aconst_null
       8: invokevirtual #4                  // Method put:(Ljava/lang/Object;Ljava/lang/Object;)Ljava/lang/Object;
      11: pop
      12: aload_0
      13: ldc           #5                  // String type
      15: ldc           #6                  // String Type
      17: invokevirtual #4                  // Method put:(Ljava/lang/Object;Ljava/lang/Object;)Ljava/lang/Object;
      20: pop
      21: aload_0
      22: ldc           #7                  // String status
      24: ldc           #8                  // String Status
      26: invokevirtual #4                  // Method put:(Ljava/lang/Object;Ljava/lang/Object;)Ljava/lang/Object;
      29: pop
      30: aload_0
      31: ldc           #9                  // String jndi-name
      33: ldc           #10                 // String JndiName
      35: invokevirtual #4                  // Method put:(Ljava/lang/Object;Ljava/lang/Object;)Ljava/lang/Object;
      38: pop
      39: aload_0
      40: ldc           #11                 // String eis-product-name
      42: ldc           #12                 // String EisProductName
      44: invokevirtual #4                  // Method put:(Ljava/lang/Object;Ljava/lang/Object;)Ljava/lang/Object;
      47: pop
      48: aload_0
      49: ldc           #13                 // String eis-product-version
      51: ldc           #14                 // String EisProductVersion
      53: invokevirtual #4                  // Method put:(Ljava/lang/Object;Ljava/lang/Object;)Ljava/lang/Object;
      56: pop
      57: return
}
