Compiled from "LogStoreConstants.java"
class org.jboss.as.txn.subsystem.LogStoreConstants {
  static final java.lang.String PROBE;

  static final java.lang.String RECOVER;

  static final java.lang.String DELETE;

  static final java.lang.String REFRESH;

  public static final java.lang.String LOG_STORE;

  public static final java.lang.String TRANSACTIONS;

  public static final java.lang.String PARTICIPANTS;

  static final java.lang.String JMX_ON_ATTRIBUTE;

  static final java.lang.String JNDI_ATTRIBUTE;

  static final java.lang.String LOG_STORE_TYPE_ATTRIBUTE;

  static final java.lang.String EXPOSE_ALL_LOGS_ATTRIBUTE;

  static final java.util.Map<java.lang.String, java.lang.String> MODEL_TO_JMX_TXN_NAMES;

  static final java.util.Map<java.lang.String, java.lang.String> MODEL_TO_JMX_PARTICIPANT_NAMES;

  static final java.lang.String[] TXN_JMX_NAMES;

  static final java.lang.String[] PARTICIPANT_JMX_NAMES;

  static org.jboss.as.controller.SimpleAttributeDefinition LOG_STORE_TYPE;

  static final org.jboss.as.controller.SimpleAttributeDefinition EXPOSE_ALL_LOGS;

  static org.jboss.as.controller.SimpleAttributeDefinition JMX_NAME;

  static org.jboss.as.controller.SimpleAttributeDefinition TRANSACTION_AGE;

  static org.jboss.as.controller.SimpleAttributeDefinition TRANSACTION_ID;

  static org.jboss.as.controller.SimpleAttributeDefinition PARTICIPANT_STATUS;

  static org.jboss.as.controller.SimpleAttributeDefinition PARTICIPANT_JNDI_NAME;

  static org.jboss.as.controller.SimpleAttributeDefinition EIS_NAME;

  static org.jboss.as.controller.SimpleAttributeDefinition EIS_VERSION;

  static org.jboss.as.controller.SimpleAttributeDefinition RECORD_TYPE;

  org.jboss.as.txn.subsystem.LogStoreConstants();
    Code:
       0: aload_0
       1: invokespecial #1                  // Method java/lang/Object."<init>":()V
       4: return

  static java.lang.String jmxNameToModelName(java.util.Map<java.lang.String, java.lang.String>, java.lang.String);
    Code:
       0: aload_0
       1: invokeinterface #2,  1            // InterfaceMethod java/util/Map.entrySet:()Ljava/util/Set;
       6: invokeinterface #3,  1            // InterfaceMethod java/util/Set.iterator:()Ljava/util/Iterator;
      11: astore_2
      12: aload_2
      13: invokeinterface #4,  1            // InterfaceMethod java/util/Iterator.hasNext:()Z
      18: ifeq          57
      21: aload_2
      22: invokeinterface #5,  1            // InterfaceMethod java/util/Iterator.next:()Ljava/lang/Object;
      27: checkcast     #6                  // class java/util/Map$Entry
      30: astore_3
      31: aload_1
      32: aload_3
      33: invokeinterface #7,  1            // InterfaceMethod java/util/Map$Entry.getValue:()Ljava/lang/Object;
      38: invokevirtual #8                  // Method java/lang/String.equals:(Ljava/lang/Object;)Z
      41: ifeq          54
      44: aload_3
      45: invokeinterface #9,  1            // InterfaceMethod java/util/Map$Entry.getKey:()Ljava/lang/Object;
      50: checkcast     #10                 // class java/lang/String
      53: areturn
      54: goto          12
      57: aconst_null
      58: areturn

  static {};
    Code:
       0: new           #11                 // class org/jboss/as/txn/subsystem/LogStoreConstants$1
       3: dup
       4: invokespecial #12                 // Method org/jboss/as/txn/subsystem/LogStoreConstants$1."<init>":()V
       7: invokestatic  #13                 // Method java/util/Collections.unmodifiableMap:(Ljava/util/Map;)Ljava/util/Map;
      10: putstatic     #14                 // Field MODEL_TO_JMX_TXN_NAMES:Ljava/util/Map;
      13: new           #15                 // class org/jboss/as/txn/subsystem/LogStoreConstants$2
      16: dup
      17: invokespecial #16                 // Method org/jboss/as/txn/subsystem/LogStoreConstants$2."<init>":()V
      20: invokestatic  #13                 // Method java/util/Collections.unmodifiableMap:(Ljava/util/Map;)Ljava/util/Map;
      23: putstatic     #17                 // Field MODEL_TO_JMX_PARTICIPANT_NAMES:Ljava/util/Map;
      26: getstatic     #14                 // Field MODEL_TO_JMX_TXN_NAMES:Ljava/util/Map;
      29: invokeinterface #18,  1           // InterfaceMethod java/util/Map.values:()Ljava/util/Collection;
      34: getstatic     #14                 // Field MODEL_TO_JMX_TXN_NAMES:Ljava/util/Map;
      37: invokeinterface #19,  1           // InterfaceMethod java/util/Map.size:()I
      42: anewarray     #10                 // class java/lang/String
      45: invokeinterface #20,  2           // InterfaceMethod java/util/Collection.toArray:([Ljava/lang/Object;)[Ljava/lang/Object;
      50: checkcast     #21                 // class "[Ljava/lang/String;"
      53: putstatic     #22                 // Field TXN_JMX_NAMES:[Ljava/lang/String;
      56: getstatic     #17                 // Field MODEL_TO_JMX_PARTICIPANT_NAMES:Ljava/util/Map;
      59: invokeinterface #18,  1           // InterfaceMethod java/util/Map.values:()Ljava/util/Collection;
      64: getstatic     #17                 // Field MODEL_TO_JMX_PARTICIPANT_NAMES:Ljava/util/Map;
      67: invokeinterface #19,  1           // InterfaceMethod java/util/Map.size:()I
      72: anewarray     #10                 // class java/lang/String
      75: invokeinterface #20,  2           // InterfaceMethod java/util/Collection.toArray:([Ljava/lang/Object;)[Ljava/lang/Object;
      80: checkcast     #21                 // class "[Ljava/lang/String;"
      83: putstatic     #23                 // Field PARTICIPANT_JMX_NAMES:[Ljava/lang/String;
      86: new           #24                 // class org/jboss/as/controller/SimpleAttributeDefinitionBuilder
      89: dup
      90: ldc           #26                 // String type
      92: getstatic     #27                 // Field org/jboss/dmr/ModelType.STRING:Lorg/jboss/dmr/ModelType;
      95: invokespecial #28                 // Method org/jboss/as/controller/SimpleAttributeDefinitionBuilder."<init>":(Ljava/lang/String;Lorg/jboss/dmr/ModelType;)V
      98: iconst_0
      99: invokevirtual #29                 // Method org/jboss/as/controller/SimpleAttributeDefinitionBuilder.setAllowExpression:(Z)Lorg/jboss/as/controller/AbstractAttributeDefinitionBuilder;
     102: checkcast     #24                 // class org/jboss/as/controller/SimpleAttributeDefinitionBuilder
     105: iconst_1
     106: invokevirtual #30                 // Method org/jboss/as/controller/SimpleAttributeDefinitionBuilder.setAllowNull:(Z)Lorg/jboss/as/controller/AbstractAttributeDefinitionBuilder;
     109: checkcast     #24                 // class org/jboss/as/controller/SimpleAttributeDefinitionBuilder
     112: new           #31                 // class org/jboss/dmr/ModelNode
     115: dup
     116: ldc           #32                 // String default
     118: invokespecial #33                 // Method org/jboss/dmr/ModelNode."<init>":(Ljava/lang/String;)V
     121: invokevirtual #34                 // Method org/jboss/as/controller/SimpleAttributeDefinitionBuilder.setDefaultValue:(Lorg/jboss/dmr/ModelNode;)Lorg/jboss/as/controller/AbstractAttributeDefinitionBuilder;
     124: checkcast     #24                 // class org/jboss/as/controller/SimpleAttributeDefinitionBuilder
     127: getstatic     #35                 // Field org/jboss/as/controller/client/helpers/MeasurementUnit.NONE:Lorg/jboss/as/controller/client/helpers/MeasurementUnit;
     130: invokevirtual #36                 // Method org/jboss/as/controller/SimpleAttributeDefinitionBuilder.setMeasurementUnit:(Lorg/jboss/as/controller/client/helpers/MeasurementUnit;)Lorg/jboss/as/controller/AbstractAttributeDefinitionBuilder;
     133: checkcast     #24                 // class org/jboss/as/controller/SimpleAttributeDefinitionBuilder
     136: invokevirtual #37                 // Method org/jboss/as/controller/SimpleAttributeDefinitionBuilder.build:()Lorg/jboss/as/controller/SimpleAttributeDefinition;
     139: putstatic     #38                 // Field LOG_STORE_TYPE:Lorg/jboss/as/controller/SimpleAttributeDefinition;
     142: new           #24                 // class org/jboss/as/controller/SimpleAttributeDefinitionBuilder
     145: dup
     146: ldc           #39                 // String expose-all-logs
     148: getstatic     #40                 // Field org/jboss/dmr/ModelType.BOOLEAN:Lorg/jboss/dmr/ModelType;
     151: invokespecial #28                 // Method org/jboss/as/controller/SimpleAttributeDefinitionBuilder."<init>":(Ljava/lang/String;Lorg/jboss/dmr/ModelType;)V
     154: iconst_1
     155: invokevirtual #29                 // Method org/jboss/as/controller/SimpleAttributeDefinitionBuilder.setAllowExpression:(Z)Lorg/jboss/as/controller/AbstractAttributeDefinitionBuilder;
     158: checkcast     #24                 // class org/jboss/as/controller/SimpleAttributeDefinitionBuilder
     161: iconst_1
     162: invokevirtual #30                 // Method org/jboss/as/controller/SimpleAttributeDefinitionBuilder.setAllowNull:(Z)Lorg/jboss/as/controller/AbstractAttributeDefinitionBuilder;
     165: checkcast     #24                 // class org/jboss/as/controller/SimpleAttributeDefinitionBuilder
     168: new           #31                 // class org/jboss/dmr/ModelNode
     171: dup
     172: invokespecial #41                 // Method org/jboss/dmr/ModelNode."<init>":()V
     175: iconst_0
     176: invokevirtual #42                 // Method org/jboss/dmr/ModelNode.set:(Z)Lorg/jboss/dmr/ModelNode;
     179: invokevirtual #34                 // Method org/jboss/as/controller/SimpleAttributeDefinitionBuilder.setDefaultValue:(Lorg/jboss/dmr/ModelNode;)Lorg/jboss/as/controller/AbstractAttributeDefinitionBuilder;
     182: checkcast     #24                 // class org/jboss/as/controller/SimpleAttributeDefinitionBuilder
     185: getstatic     #35                 // Field org/jboss/as/controller/client/helpers/MeasurementUnit.NONE:Lorg/jboss/as/controller/client/helpers/MeasurementUnit;
     188: invokevirtual #36                 // Method org/jboss/as/controller/SimpleAttributeDefinitionBuilder.setMeasurementUnit:(Lorg/jboss/as/controller/client/helpers/MeasurementUnit;)Lorg/jboss/as/controller/AbstractAttributeDefinitionBuilder;
     191: checkcast     #24                 // class org/jboss/as/controller/SimpleAttributeDefinitionBuilder
     194: invokevirtual #43                 // Method org/jboss/as/controller/SimpleAttributeDefinitionBuilder.setStorageRuntime:()Lorg/jboss/as/controller/AbstractAttributeDefinitionBuilder;
     197: checkcast     #24                 // class org/jboss/as/controller/SimpleAttributeDefinitionBuilder
     200: invokevirtual #37                 // Method org/jboss/as/controller/SimpleAttributeDefinitionBuilder.build:()Lorg/jboss/as/controller/SimpleAttributeDefinition;
     203: putstatic     #44                 // Field EXPOSE_ALL_LOGS:Lorg/jboss/as/controller/SimpleAttributeDefinition;
     206: new           #24                 // class org/jboss/as/controller/SimpleAttributeDefinitionBuilder
     209: dup
     210: ldc           #45                 // String jmx-name
     212: getstatic     #27                 // Field org/jboss/dmr/ModelType.STRING:Lorg/jboss/dmr/ModelType;
     215: invokespecial #28                 // Method org/jboss/as/controller/SimpleAttributeDefinitionBuilder."<init>":(Ljava/lang/String;Lorg/jboss/dmr/ModelType;)V
     218: iconst_0
     219: invokevirtual #29                 // Method org/jboss/as/controller/SimpleAttributeDefinitionBuilder.setAllowExpression:(Z)Lorg/jboss/as/controller/AbstractAttributeDefinitionBuilder;
     222: checkcast     #24                 // class org/jboss/as/controller/SimpleAttributeDefinitionBuilder
     225: iconst_1
     226: invokevirtual #30                 // Method org/jboss/as/controller/SimpleAttributeDefinitionBuilder.setAllowNull:(Z)Lorg/jboss/as/controller/AbstractAttributeDefinitionBuilder;
     229: checkcast     #24                 // class org/jboss/as/controller/SimpleAttributeDefinitionBuilder
     232: new           #31                 // class org/jboss/dmr/ModelNode
     235: dup
     236: invokespecial #41                 // Method org/jboss/dmr/ModelNode."<init>":()V
     239: invokevirtual #34                 // Method org/jboss/as/controller/SimpleAttributeDefinitionBuilder.setDefaultValue:(Lorg/jboss/dmr/ModelNode;)Lorg/jboss/as/controller/AbstractAttributeDefinitionBuilder;
     242: checkcast     #24                 // class org/jboss/as/controller/SimpleAttributeDefinitionBuilder
     245: getstatic     #35                 // Field org/jboss/as/controller/client/helpers/MeasurementUnit.NONE:Lorg/jboss/as/controller/client/helpers/MeasurementUnit;
     248: invokevirtual #36                 // Method org/jboss/as/controller/SimpleAttributeDefinitionBuilder.setMeasurementUnit:(Lorg/jboss/as/controller/client/helpers/MeasurementUnit;)Lorg/jboss/as/controller/AbstractAttributeDefinitionBuilder;
     251: checkcast     #24                 // class org/jboss/as/controller/SimpleAttributeDefinitionBuilder
     254: new           #46                 // class org/jboss/as/controller/operations/validation/StringLengthValidator
     257: dup
     258: iconst_0
     259: iconst_1
     260: invokespecial #47                 // Method org/jboss/as/controller/operations/validation/StringLengthValidator."<init>":(IZ)V
     263: invokevirtual #48                 // Method org/jboss/as/controller/SimpleAttributeDefinitionBuilder.setValidator:(Lorg/jboss/as/controller/operations/validation/ParameterValidator;)Lorg/jboss/as/controller/AbstractAttributeDefinitionBuilder;
     266: checkcast     #24                 // class org/jboss/as/controller/SimpleAttributeDefinitionBuilder
     269: invokevirtual #37                 // Method org/jboss/as/controller/SimpleAttributeDefinitionBuilder.build:()Lorg/jboss/as/controller/SimpleAttributeDefinition;
     272: putstatic     #49                 // Field JMX_NAME:Lorg/jboss/as/controller/SimpleAttributeDefinition;
     275: new           #24                 // class org/jboss/as/controller/SimpleAttributeDefinitionBuilder
     278: dup
     279: ldc           #50                 // String age-in-seconds
     281: getstatic     #51                 // Field org/jboss/dmr/ModelType.LONG:Lorg/jboss/dmr/ModelType;
     284: invokespecial #28                 // Method org/jboss/as/controller/SimpleAttributeDefinitionBuilder."<init>":(Ljava/lang/String;Lorg/jboss/dmr/ModelType;)V
     287: iconst_0
     288: invokevirtual #29                 // Method org/jboss/as/controller/SimpleAttributeDefinitionBuilder.setAllowExpression:(Z)Lorg/jboss/as/controller/AbstractAttributeDefinitionBuilder;
     291: checkcast     #24                 // class org/jboss/as/controller/SimpleAttributeDefinitionBuilder
     294: iconst_1
     295: invokevirtual #30                 // Method org/jboss/as/controller/SimpleAttributeDefinitionBuilder.setAllowNull:(Z)Lorg/jboss/as/controller/AbstractAttributeDefinitionBuilder;
     298: checkcast     #24                 // class org/jboss/as/controller/SimpleAttributeDefinitionBuilder
     301: new           #31                 // class org/jboss/dmr/ModelNode
     304: dup
     305: invokespecial #41                 // Method org/jboss/dmr/ModelNode."<init>":()V
     308: invokevirtual #34                 // Method org/jboss/as/controller/SimpleAttributeDefinitionBuilder.setDefaultValue:(Lorg/jboss/dmr/ModelNode;)Lorg/jboss/as/controller/AbstractAttributeDefinitionBuilder;
     311: checkcast     #24                 // class org/jboss/as/controller/SimpleAttributeDefinitionBuilder
     314: getstatic     #52                 // Field org/jboss/as/controller/client/helpers/MeasurementUnit.SECONDS:Lorg/jboss/as/controller/client/helpers/MeasurementUnit;
     317: invokevirtual #36                 // Method org/jboss/as/controller/SimpleAttributeDefinitionBuilder.setMeasurementUnit:(Lorg/jboss/as/controller/client/helpers/MeasurementUnit;)Lorg/jboss/as/controller/AbstractAttributeDefinitionBuilder;
     320: checkcast     #24                 // class org/jboss/as/controller/SimpleAttributeDefinitionBuilder
     323: invokevirtual #37                 // Method org/jboss/as/controller/SimpleAttributeDefinitionBuilder.build:()Lorg/jboss/as/controller/SimpleAttributeDefinition;
     326: putstatic     #53                 // Field TRANSACTION_AGE:Lorg/jboss/as/controller/SimpleAttributeDefinition;
     329: new           #24                 // class org/jboss/as/controller/SimpleAttributeDefinitionBuilder
     332: dup
     333: ldc           #54                 // String id
     335: getstatic     #27                 // Field org/jboss/dmr/ModelType.STRING:Lorg/jboss/dmr/ModelType;
     338: invokespecial #28                 // Method org/jboss/as/controller/SimpleAttributeDefinitionBuilder."<init>":(Ljava/lang/String;Lorg/jboss/dmr/ModelType;)V
     341: iconst_0
     342: invokevirtual #29                 // Method org/jboss/as/controller/SimpleAttributeDefinitionBuilder.setAllowExpression:(Z)Lorg/jboss/as/controller/AbstractAttributeDefinitionBuilder;
     345: checkcast     #24                 // class org/jboss/as/controller/SimpleAttributeDefinitionBuilder
     348: iconst_1
     349: invokevirtual #30                 // Method org/jboss/as/controller/SimpleAttributeDefinitionBuilder.setAllowNull:(Z)Lorg/jboss/as/controller/AbstractAttributeDefinitionBuilder;
     352: checkcast     #24                 // class org/jboss/as/controller/SimpleAttributeDefinitionBuilder
     355: new           #31                 // class org/jboss/dmr/ModelNode
     358: dup
     359: invokespecial #41                 // Method org/jboss/dmr/ModelNode."<init>":()V
     362: invokevirtual #34                 // Method org/jboss/as/controller/SimpleAttributeDefinitionBuilder.setDefaultValue:(Lorg/jboss/dmr/ModelNode;)Lorg/jboss/as/controller/AbstractAttributeDefinitionBuilder;
     365: checkcast     #24                 // class org/jboss/as/controller/SimpleAttributeDefinitionBuilder
     368: getstatic     #35                 // Field org/jboss/as/controller/client/helpers/MeasurementUnit.NONE:Lorg/jboss/as/controller/client/helpers/MeasurementUnit;
     371: invokevirtual #36                 // Method org/jboss/as/controller/SimpleAttributeDefinitionBuilder.setMeasurementUnit:(Lorg/jboss/as/controller/client/helpers/MeasurementUnit;)Lorg/jboss/as/controller/AbstractAttributeDefinitionBuilder;
     374: checkcast     #24                 // class org/jboss/as/controller/SimpleAttributeDefinitionBuilder
     377: invokevirtual #37                 // Method org/jboss/as/controller/SimpleAttributeDefinitionBuilder.build:()Lorg/jboss/as/controller/SimpleAttributeDefinition;
     380: putstatic     #55                 // Field TRANSACTION_ID:Lorg/jboss/as/controller/SimpleAttributeDefinition;
     383: new           #24                 // class org/jboss/as/controller/SimpleAttributeDefinitionBuilder
     386: dup
     387: ldc           #56                 // String status
     389: getstatic     #27                 // Field org/jboss/dmr/ModelType.STRING:Lorg/jboss/dmr/ModelType;
     392: invokespecial #28                 // Method org/jboss/as/controller/SimpleAttributeDefinitionBuilder."<init>":(Ljava/lang/String;Lorg/jboss/dmr/ModelType;)V
     395: iconst_0
     396: invokevirtual #29                 // Method org/jboss/as/controller/SimpleAttributeDefinitionBuilder.setAllowExpression:(Z)Lorg/jboss/as/controller/AbstractAttributeDefinitionBuilder;
     399: checkcast     #24                 // class org/jboss/as/controller/SimpleAttributeDefinitionBuilder
     402: iconst_1
     403: invokevirtual #30                 // Method org/jboss/as/controller/SimpleAttributeDefinitionBuilder.setAllowNull:(Z)Lorg/jboss/as/controller/AbstractAttributeDefinitionBuilder;
     406: checkcast     #24                 // class org/jboss/as/controller/SimpleAttributeDefinitionBuilder
     409: new           #31                 // class org/jboss/dmr/ModelNode
     412: dup
     413: invokespecial #41                 // Method org/jboss/dmr/ModelNode."<init>":()V
     416: invokevirtual #34                 // Method org/jboss/as/controller/SimpleAttributeDefinitionBuilder.setDefaultValue:(Lorg/jboss/dmr/ModelNode;)Lorg/jboss/as/controller/AbstractAttributeDefinitionBuilder;
     419: checkcast     #24                 // class org/jboss/as/controller/SimpleAttributeDefinitionBuilder
     422: getstatic     #35                 // Field org/jboss/as/controller/client/helpers/MeasurementUnit.NONE:Lorg/jboss/as/controller/client/helpers/MeasurementUnit;
     425: invokevirtual #36                 // Method org/jboss/as/controller/SimpleAttributeDefinitionBuilder.setMeasurementUnit:(Lorg/jboss/as/controller/client/helpers/MeasurementUnit;)Lorg/jboss/as/controller/AbstractAttributeDefinitionBuilder;
     428: checkcast     #24                 // class org/jboss/as/controller/SimpleAttributeDefinitionBuilder
     431: new           #57                 // class org/jboss/as/controller/operations/validation/EnumValidator
     434: dup
     435: ldc           #58                 // class org/jboss/as/txn/subsystem/LogStoreConstants$ParticipantStatus
     437: iconst_1
     438: iconst_0
     439: invokespecial #59                 // Method org/jboss/as/controller/operations/validation/EnumValidator."<init>":(Ljava/lang/Class;ZZ)V
     442: invokevirtual #48                 // Method org/jboss/as/controller/SimpleAttributeDefinitionBuilder.setValidator:(Lorg/jboss/as/controller/operations/validation/ParameterValidator;)Lorg/jboss/as/controller/AbstractAttributeDefinitionBuilder;
     445: checkcast     #24                 // class org/jboss/as/controller/SimpleAttributeDefinitionBuilder
     448: invokevirtual #37                 // Method org/jboss/as/controller/SimpleAttributeDefinitionBuilder.build:()Lorg/jboss/as/controller/SimpleAttributeDefinition;
     451: putstatic     #60                 // Field PARTICIPANT_STATUS:Lorg/jboss/as/controller/SimpleAttributeDefinition;
     454: new           #24                 // class org/jboss/as/controller/SimpleAttributeDefinitionBuilder
     457: dup
     458: ldc           #61                 // String jndi-name
     460: getstatic     #27                 // Field org/jboss/dmr/ModelType.STRING:Lorg/jboss/dmr/ModelType;
     463: invokespecial #28                 // Method org/jboss/as/controller/SimpleAttributeDefinitionBuilder."<init>":(Ljava/lang/String;Lorg/jboss/dmr/ModelType;)V
     466: iconst_0
     467: invokevirtual #29                 // Method org/jboss/as/controller/SimpleAttributeDefinitionBuilder.setAllowExpression:(Z)Lorg/jboss/as/controller/AbstractAttributeDefinitionBuilder;
     470: checkcast     #24                 // class org/jboss/as/controller/SimpleAttributeDefinitionBuilder
     473: iconst_1
     474: invokevirtual #30                 // Method org/jboss/as/controller/SimpleAttributeDefinitionBuilder.setAllowNull:(Z)Lorg/jboss/as/controller/AbstractAttributeDefinitionBuilder;
     477: checkcast     #24                 // class org/jboss/as/controller/SimpleAttributeDefinitionBuilder
     480: new           #31                 // class org/jboss/dmr/ModelNode
     483: dup
     484: invokespecial #41                 // Method org/jboss/dmr/ModelNode."<init>":()V
     487: invokevirtual #34                 // Method org/jboss/as/controller/SimpleAttributeDefinitionBuilder.setDefaultValue:(Lorg/jboss/dmr/ModelNode;)Lorg/jboss/as/controller/AbstractAttributeDefinitionBuilder;
     490: checkcast     #24                 // class org/jboss/as/controller/SimpleAttributeDefinitionBuilder
     493: getstatic     #35                 // Field org/jboss/as/controller/client/helpers/MeasurementUnit.NONE:Lorg/jboss/as/controller/client/helpers/MeasurementUnit;
     496: invokevirtual #36                 // Method org/jboss/as/controller/SimpleAttributeDefinitionBuilder.setMeasurementUnit:(Lorg/jboss/as/controller/client/helpers/MeasurementUnit;)Lorg/jboss/as/controller/AbstractAttributeDefinitionBuilder;
     499: checkcast     #24                 // class org/jboss/as/controller/SimpleAttributeDefinitionBuilder
     502: invokevirtual #37                 // Method org/jboss/as/controller/SimpleAttributeDefinitionBuilder.build:()Lorg/jboss/as/controller/SimpleAttributeDefinition;
     505: putstatic     #62                 // Field PARTICIPANT_JNDI_NAME:Lorg/jboss/as/controller/SimpleAttributeDefinition;
     508: new           #24                 // class org/jboss/as/controller/SimpleAttributeDefinitionBuilder
     511: dup
     512: ldc           #63                 // String eis-product-name
     514: getstatic     #27                 // Field org/jboss/dmr/ModelType.STRING:Lorg/jboss/dmr/ModelType;
     517: invokespecial #28                 // Method org/jboss/as/controller/SimpleAttributeDefinitionBuilder."<init>":(Ljava/lang/String;Lorg/jboss/dmr/ModelType;)V
     520: iconst_0
     521: invokevirtual #29                 // Method org/jboss/as/controller/SimpleAttributeDefinitionBuilder.setAllowExpression:(Z)Lorg/jboss/as/controller/AbstractAttributeDefinitionBuilder;
     524: checkcast     #24                 // class org/jboss/as/controller/SimpleAttributeDefinitionBuilder
     527: iconst_1
     528: invokevirtual #30                 // Method org/jboss/as/controller/SimpleAttributeDefinitionBuilder.setAllowNull:(Z)Lorg/jboss/as/controller/AbstractAttributeDefinitionBuilder;
     531: checkcast     #24                 // class org/jboss/as/controller/SimpleAttributeDefinitionBuilder
     534: new           #31                 // class org/jboss/dmr/ModelNode
     537: dup
     538: invokespecial #41                 // Method org/jboss/dmr/ModelNode."<init>":()V
     541: invokevirtual #34                 // Method org/jboss/as/controller/SimpleAttributeDefinitionBuilder.setDefaultValue:(Lorg/jboss/dmr/ModelNode;)Lorg/jboss/as/controller/AbstractAttributeDefinitionBuilder;
     544: checkcast     #24                 // class org/jboss/as/controller/SimpleAttributeDefinitionBuilder
     547: getstatic     #35                 // Field org/jboss/as/controller/client/helpers/MeasurementUnit.NONE:Lorg/jboss/as/controller/client/helpers/MeasurementUnit;
     550: invokevirtual #36                 // Method org/jboss/as/controller/SimpleAttributeDefinitionBuilder.setMeasurementUnit:(Lorg/jboss/as/controller/client/helpers/MeasurementUnit;)Lorg/jboss/as/controller/AbstractAttributeDefinitionBuilder;
     553: checkcast     #24                 // class org/jboss/as/controller/SimpleAttributeDefinitionBuilder
     556: new           #46                 // class org/jboss/as/controller/operations/validation/StringLengthValidator
     559: dup
     560: iconst_0
     561: iconst_1
     562: invokespecial #47                 // Method org/jboss/as/controller/operations/validation/StringLengthValidator."<init>":(IZ)V
     565: invokevirtual #48                 // Method org/jboss/as/controller/SimpleAttributeDefinitionBuilder.setValidator:(Lorg/jboss/as/controller/operations/validation/ParameterValidator;)Lorg/jboss/as/controller/AbstractAttributeDefinitionBuilder;
     568: checkcast     #24                 // class org/jboss/as/controller/SimpleAttributeDefinitionBuilder
     571: invokevirtual #37                 // Method org/jboss/as/controller/SimpleAttributeDefinitionBuilder.build:()Lorg/jboss/as/controller/SimpleAttributeDefinition;
     574: putstatic     #64                 // Field EIS_NAME:Lorg/jboss/as/controller/SimpleAttributeDefinition;
     577: new           #24                 // class org/jboss/as/controller/SimpleAttributeDefinitionBuilder
     580: dup
     581: ldc           #65                 // String eis-product-version
     583: getstatic     #27                 // Field org/jboss/dmr/ModelType.STRING:Lorg/jboss/dmr/ModelType;
     586: invokespecial #28                 // Method org/jboss/as/controller/SimpleAttributeDefinitionBuilder."<init>":(Ljava/lang/String;Lorg/jboss/dmr/ModelType;)V
     589: iconst_0
     590: invokevirtual #29                 // Method org/jboss/as/controller/SimpleAttributeDefinitionBuilder.setAllowExpression:(Z)Lorg/jboss/as/controller/AbstractAttributeDefinitionBuilder;
     593: checkcast     #24                 // class org/jboss/as/controller/SimpleAttributeDefinitionBuilder
     596: iconst_1
     597: invokevirtual #30                 // Method org/jboss/as/controller/SimpleAttributeDefinitionBuilder.setAllowNull:(Z)Lorg/jboss/as/controller/AbstractAttributeDefinitionBuilder;
     600: checkcast     #24                 // class org/jboss/as/controller/SimpleAttributeDefinitionBuilder
     603: new           #31                 // class org/jboss/dmr/ModelNode
     606: dup
     607: invokespecial #41                 // Method org/jboss/dmr/ModelNode."<init>":()V
     610: invokevirtual #34                 // Method org/jboss/as/controller/SimpleAttributeDefinitionBuilder.setDefaultValue:(Lorg/jboss/dmr/ModelNode;)Lorg/jboss/as/controller/AbstractAttributeDefinitionBuilder;
     613: checkcast     #24                 // class org/jboss/as/controller/SimpleAttributeDefinitionBuilder
     616: getstatic     #35                 // Field org/jboss/as/controller/client/helpers/MeasurementUnit.NONE:Lorg/jboss/as/controller/client/helpers/MeasurementUnit;
     619: invokevirtual #36                 // Method org/jboss/as/controller/SimpleAttributeDefinitionBuilder.setMeasurementUnit:(Lorg/jboss/as/controller/client/helpers/MeasurementUnit;)Lorg/jboss/as/controller/AbstractAttributeDefinitionBuilder;
     622: checkcast     #24                 // class org/jboss/as/controller/SimpleAttributeDefinitionBuilder
     625: new           #46                 // class org/jboss/as/controller/operations/validation/StringLengthValidator
     628: dup
     629: iconst_0
     630: iconst_1
     631: invokespecial #47                 // Method org/jboss/as/controller/operations/validation/StringLengthValidator."<init>":(IZ)V
     634: invokevirtual #48                 // Method org/jboss/as/controller/SimpleAttributeDefinitionBuilder.setValidator:(Lorg/jboss/as/controller/operations/validation/ParameterValidator;)Lorg/jboss/as/controller/AbstractAttributeDefinitionBuilder;
     637: checkcast     #24                 // class org/jboss/as/controller/SimpleAttributeDefinitionBuilder
     640: invokevirtual #37                 // Method org/jboss/as/controller/SimpleAttributeDefinitionBuilder.build:()Lorg/jboss/as/controller/SimpleAttributeDefinition;
     643: putstatic     #66                 // Field EIS_VERSION:Lorg/jboss/as/controller/SimpleAttributeDefinition;
     646: new           #24                 // class org/jboss/as/controller/SimpleAttributeDefinitionBuilder
     649: dup
     650: ldc           #26                 // String type
     652: getstatic     #27                 // Field org/jboss/dmr/ModelType.STRING:Lorg/jboss/dmr/ModelType;
     655: invokespecial #28                 // Method org/jboss/as/controller/SimpleAttributeDefinitionBuilder."<init>":(Ljava/lang/String;Lorg/jboss/dmr/ModelType;)V
     658: iconst_0
     659: invokevirtual #29                 // Method org/jboss/as/controller/SimpleAttributeDefinitionBuilder.setAllowExpression:(Z)Lorg/jboss/as/controller/AbstractAttributeDefinitionBuilder;
     662: checkcast     #24                 // class org/jboss/as/controller/SimpleAttributeDefinitionBuilder
     665: iconst_1
     666: invokevirtual #30                 // Method org/jboss/as/controller/SimpleAttributeDefinitionBuilder.setAllowNull:(Z)Lorg/jboss/as/controller/AbstractAttributeDefinitionBuilder;
     669: checkcast     #24                 // class org/jboss/as/controller/SimpleAttributeDefinitionBuilder
     672: new           #31                 // class org/jboss/dmr/ModelNode
     675: dup
     676: invokespecial #41                 // Method org/jboss/dmr/ModelNode."<init>":()V
     679: invokevirtual #34                 // Method org/jboss/as/controller/SimpleAttributeDefinitionBuilder.setDefaultValue:(Lorg/jboss/dmr/ModelNode;)Lorg/jboss/as/controller/AbstractAttributeDefinitionBuilder;
     682: checkcast     #24                 // class org/jboss/as/controller/SimpleAttributeDefinitionBuilder
     685: getstatic     #35                 // Field org/jboss/as/controller/client/helpers/MeasurementUnit.NONE:Lorg/jboss/as/controller/client/helpers/MeasurementUnit;
     688: invokevirtual #36                 // Method org/jboss/as/controller/SimpleAttributeDefinitionBuilder.setMeasurementUnit:(Lorg/jboss/as/controller/client/helpers/MeasurementUnit;)Lorg/jboss/as/controller/AbstractAttributeDefinitionBuilder;
     691: checkcast     #24                 // class org/jboss/as/controller/SimpleAttributeDefinitionBuilder
     694: invokevirtual #37                 // Method org/jboss/as/controller/SimpleAttributeDefinitionBuilder.build:()Lorg/jboss/as/controller/SimpleAttributeDefinition;
     697: putstatic     #67                 // Field RECORD_TYPE:Lorg/jboss/as/controller/SimpleAttributeDefinition;
     700: return
}
