Compiled from "LogStoreProbeHandler.java"
public class org.jboss.as.txn.subsystem.LogStoreProbeHandler implements org.jboss.as.controller.OperationStepHandler {
  static final org.jboss.as.txn.subsystem.LogStoreProbeHandler INSTANCE;

  static final java.lang.String osMBeanName;

  static final java.lang.String JNDI_PROPNAME;

  static final boolean $assertionsDisabled;

  public org.jboss.as.txn.subsystem.LogStoreProbeHandler();
    Code:
       0: aload_0
       1: invokespecial #1                  // Method java/lang/Object."<init>":()V
       4: return

  private java.util.Map<java.lang.String, java.lang.String> getMBeanValues(javax.management.MBeanServerConnection, javax.management.ObjectName, java.lang.String...) throws javax.management.InstanceNotFoundException, java.io.IOException, javax.management.ReflectionException, javax.management.IntrospectionException;
    Code:
       0: aload_3
       1: ifnonnull     74
       4: aload_1
       5: aload_2
       6: invokeinterface #2,  2            // InterfaceMethod javax/management/MBeanServerConnection.getMBeanInfo:(Ljavax/management/ObjectName;)Ljavax/management/MBeanInfo;
      11: astore        4
      13: aload         4
      15: invokevirtual #3                  // Method javax/management/MBeanInfo.getAttributes:()[Ljavax/management/MBeanAttributeInfo;
      18: astore        5
      20: iconst_0
      21: istore        6
      23: aload         5
      25: arraylength
      26: anewarray     #4                  // class java/lang/String
      29: astore_3
      30: aload         5
      32: astore        7
      34: aload         7
      36: arraylength
      37: istore        8
      39: iconst_0
      40: istore        9
      42: iload         9
      44: iload         8
      46: if_icmpge     74
      49: aload         7
      51: iload         9
      53: aaload
      54: astore        10
      56: aload_3
      57: iload         6
      59: iinc          6, 1
      62: aload         10
      64: invokevirtual #5                  // Method javax/management/MBeanAttributeInfo.getName:()Ljava/lang/String;
      67: aastore
      68: iinc          9, 1
      71: goto          42
      74: aload_1
      75: aload_2
      76: aload_3
      77: invokeinterface #6,  3            // InterfaceMethod javax/management/MBeanServerConnection.getAttributes:(Ljavax/management/ObjectName;[Ljava/lang/String;)Ljavax/management/AttributeList;
      82: astore        4
      84: new           #7                  // class java/util/HashMap
      87: dup
      88: invokespecial #8                  // Method java/util/HashMap."<init>":()V
      91: astore        5
      93: aload         4
      95: invokevirtual #9                  // Method javax/management/AttributeList.asList:()Ljava/util/List;
      98: invokeinterface #10,  1           // InterfaceMethod java/util/List.iterator:()Ljava/util/Iterator;
     103: astore        6
     105: aload         6
     107: invokeinterface #11,  1           // InterfaceMethod java/util/Iterator.hasNext:()Z
     112: ifeq          165
     115: aload         6
     117: invokeinterface #12,  1           // InterfaceMethod java/util/Iterator.next:()Ljava/lang/Object;
     122: checkcast     #13                 // class javax/management/Attribute
     125: astore        7
     127: aload         7
     129: invokevirtual #14                 // Method javax/management/Attribute.getValue:()Ljava/lang/Object;
     132: astore        8
     134: aload         5
     136: aload         7
     138: invokevirtual #15                 // Method javax/management/Attribute.getName:()Ljava/lang/String;
     141: aload         8
     143: ifnonnull     151
     146: ldc           #16                 // String
     148: goto          156
     151: aload         8
     153: invokevirtual #17                 // Method java/lang/Object.toString:()Ljava/lang/String;
     156: invokeinterface #18,  3           // InterfaceMethod java/util/Map.put:(Ljava/lang/Object;Ljava/lang/Object;)Ljava/lang/Object;
     161: pop
     162: goto          105
     165: aload         5
     167: areturn

  private void addAttributes(org.jboss.dmr.ModelNode, java.util.Map<java.lang.String, java.lang.String>, java.util.Map<java.lang.String, java.lang.String>);
    Code:
       0: aload_2
       1: invokeinterface #19,  1           // InterfaceMethod java/util/Map.entrySet:()Ljava/util/Set;
       6: invokeinterface #20,  1           // InterfaceMethod java/util/Set.iterator:()Ljava/util/Iterator;
      11: astore        4
      13: aload         4
      15: invokeinterface #11,  1           // InterfaceMethod java/util/Iterator.hasNext:()Z
      20: ifeq          81
      23: aload         4
      25: invokeinterface #12,  1           // InterfaceMethod java/util/Iterator.next:()Ljava/lang/Object;
      30: checkcast     #21                 // class java/util/Map$Entry
      33: astore        5
      35: aload_3
      36: aload         5
      38: invokeinterface #22,  1           // InterfaceMethod java/util/Map$Entry.getValue:()Ljava/lang/Object;
      43: invokeinterface #23,  2           // InterfaceMethod java/util/Map.get:(Ljava/lang/Object;)Ljava/lang/Object;
      48: checkcast     #4                  // class java/lang/String
      51: astore        6
      53: aload         6
      55: ifnull        78
      58: aload_1
      59: aload         5
      61: invokeinterface #24,  1           // InterfaceMethod java/util/Map$Entry.getKey:()Ljava/lang/Object;
      66: checkcast     #4                  // class java/lang/String
      69: invokevirtual #25                 // Method org/jboss/dmr/ModelNode.get:(Ljava/lang/String;)Lorg/jboss/dmr/ModelNode;
      72: aload         6
      74: invokevirtual #26                 // Method org/jboss/dmr/ModelNode.set:(Ljava/lang/String;)Lorg/jboss/dmr/ModelNode;
      77: pop
      78: goto          13
      81: return

  private void addParticipants(org.jboss.as.controller.registry.Resource, java.util.Set<javax.management.ObjectInstance>, javax.management.MBeanServer) throws javax.management.IntrospectionException, javax.management.InstanceNotFoundException, java.io.IOException, javax.management.ReflectionException;
    Code:
       0: iconst_1
       1: istore        4
       3: aload_2
       4: invokeinterface #20,  1           // InterfaceMethod java/util/Set.iterator:()Ljava/util/Iterator;
       9: astore        5
      11: aload         5
      13: invokeinterface #11,  1           // InterfaceMethod java/util/Iterator.hasNext:()Z
      18: ifeq          166
      21: aload         5
      23: invokeinterface #12,  1           // InterfaceMethod java/util/Iterator.next:()Ljava/lang/Object;
      28: checkcast     #27                 // class javax/management/ObjectInstance
      31: astore        6
      33: new           #28                 // class org/jboss/as/txn/subsystem/LogStoreResource$LogStoreRuntimeResource
      36: dup
      37: aload         6
      39: invokevirtual #29                 // Method javax/management/ObjectInstance.getObjectName:()Ljavax/management/ObjectName;
      42: invokespecial #30                 // Method org/jboss/as/txn/subsystem/LogStoreResource$LogStoreRuntimeResource."<init>":(Ljavax/management/ObjectName;)V
      45: astore        7
      47: aload         7
      49: invokeinterface #31,  1           // InterfaceMethod org/jboss/as/controller/registry/Resource.getModel:()Lorg/jboss/dmr/ModelNode;
      54: astore        8
      56: aload_0
      57: aload_3
      58: aload         6
      60: invokevirtual #29                 // Method javax/management/ObjectInstance.getObjectName:()Ljavax/management/ObjectName;
      63: getstatic     #32                 // Field org/jboss/as/txn/subsystem/LogStoreConstants.PARTICIPANT_JMX_NAMES:[Ljava/lang/String;
      66: invokespecial #33                 // Method getMBeanValues:(Ljavax/management/MBeanServerConnection;Ljavax/management/ObjectName;[Ljava/lang/String;)Ljava/util/Map;
      69: astore        9
      71: aload         9
      73: getstatic     #34                 // Field JNDI_PROPNAME:Ljava/lang/String;
      76: invokeinterface #23,  2           // InterfaceMethod java/util/Map.get:(Ljava/lang/Object;)Ljava/lang/Object;
      81: checkcast     #4                  // class java/lang/String
      84: astore        10
      86: aload         10
      88: ifnull        99
      91: aload         10
      93: invokevirtual #35                 // Method java/lang/String.length:()I
      96: ifne          133
      99: aload         9
     101: getstatic     #34                 // Field JNDI_PROPNAME:Ljava/lang/String;
     104: iload         4
     106: iinc          4, 1
     109: invokestatic  #36                 // Method java/lang/String.valueOf:(I)Ljava/lang/String;
     112: invokeinterface #18,  3           // InterfaceMethod java/util/Map.put:(Ljava/lang/Object;Ljava/lang/Object;)Ljava/lang/Object;
     117: pop
     118: aload         9
     120: getstatic     #34                 // Field JNDI_PROPNAME:Ljava/lang/String;
     123: invokeinterface #23,  2           // InterfaceMethod java/util/Map.get:(Ljava/lang/Object;)Ljava/lang/Object;
     128: checkcast     #4                  // class java/lang/String
     131: astore        10
     133: aload_0
     134: aload         8
     136: getstatic     #37                 // Field org/jboss/as/txn/subsystem/LogStoreConstants.MODEL_TO_JMX_PARTICIPANT_NAMES:Ljava/util/Map;
     139: aload         9
     141: invokespecial #38                 // Method addAttributes:(Lorg/jboss/dmr/ModelNode;Ljava/util/Map;Ljava/util/Map;)V
     144: ldc           #40                 // String participants
     146: aload         10
     148: invokestatic  #41                 // Method org/jboss/as/controller/PathElement.pathElement:(Ljava/lang/String;Ljava/lang/String;)Lorg/jboss/as/controller/PathElement;
     151: astore        11
     153: aload_1
     154: aload         11
     156: aload         7
     158: invokeinterface #42,  3           // InterfaceMethod org/jboss/as/controller/registry/Resource.registerChild:(Lorg/jboss/as/controller/PathElement;Lorg/jboss/as/controller/registry/Resource;)V
     163: goto          11
     166: return

  private void addTransactions(org.jboss.as.controller.registry.Resource, java.util.Set<javax.management.ObjectInstance>, javax.management.MBeanServer) throws javax.management.IntrospectionException, javax.management.InstanceNotFoundException, java.io.IOException, javax.management.ReflectionException, javax.management.MalformedObjectNameException;
    Code:
       0: aload_2
       1: invokeinterface #20,  1           // InterfaceMethod java/util/Set.iterator:()Ljava/util/Iterator;
       6: astore        4
       8: aload         4
      10: invokeinterface #11,  1           // InterfaceMethod java/util/Iterator.hasNext:()Z
      15: ifeq          194
      18: aload         4
      20: invokeinterface #12,  1           // InterfaceMethod java/util/Iterator.next:()Ljava/lang/Object;
      25: checkcast     #27                 // class javax/management/ObjectInstance
      28: astore        5
      30: aload         5
      32: invokevirtual #29                 // Method javax/management/ObjectInstance.getObjectName:()Ljavax/management/ObjectName;
      35: invokevirtual #43                 // Method javax/management/ObjectName.getCanonicalName:()Ljava/lang/String;
      38: astore        6
      40: aload         6
      42: ldc           #44                 // String puid
      44: invokevirtual #45                 // Method java/lang/String.contains:(Ljava/lang/CharSequence;)Z
      47: ifne          191
      50: aload         6
      52: ldc           #46                 // String itype
      54: invokevirtual #45                 // Method java/lang/String.contains:(Ljava/lang/CharSequence;)Z
      57: ifeq          191
      60: new           #28                 // class org/jboss/as/txn/subsystem/LogStoreResource$LogStoreRuntimeResource
      63: dup
      64: aload         5
      66: invokevirtual #29                 // Method javax/management/ObjectInstance.getObjectName:()Ljavax/management/ObjectName;
      69: invokespecial #30                 // Method org/jboss/as/txn/subsystem/LogStoreResource$LogStoreRuntimeResource."<init>":(Ljavax/management/ObjectName;)V
      72: astore        7
      74: aload         7
      76: invokeinterface #31,  1           // InterfaceMethod org/jboss/as/controller/registry/Resource.getModel:()Lorg/jboss/dmr/ModelNode;
      81: astore        8
      83: aload_0
      84: aload_3
      85: aload         5
      87: invokevirtual #29                 // Method javax/management/ObjectInstance.getObjectName:()Ljavax/management/ObjectName;
      90: getstatic     #47                 // Field org/jboss/as/txn/subsystem/LogStoreConstants.TXN_JMX_NAMES:[Ljava/lang/String;
      93: invokespecial #33                 // Method getMBeanValues:(Ljavax/management/MBeanServerConnection;Ljavax/management/ObjectName;[Ljava/lang/String;)Ljava/util/Map;
      96: astore        9
      98: aload         9
     100: ldc           #48                 // String Id
     102: invokeinterface #23,  2           // InterfaceMethod java/util/Map.get:(Ljava/lang/Object;)Ljava/lang/Object;
     107: checkcast     #4                  // class java/lang/String
     110: astore        10
     112: aload_0
     113: aload         8
     115: getstatic     #49                 // Field org/jboss/as/txn/subsystem/LogStoreConstants.MODEL_TO_JMX_TXN_NAMES:Ljava/util/Map;
     118: aload         9
     120: invokespecial #38                 // Method addAttributes:(Lorg/jboss/dmr/ModelNode;Ljava/util/Map;Ljava/util/Map;)V
     123: new           #50                 // class java/lang/StringBuilder
     126: dup
     127: invokespecial #51                 // Method java/lang/StringBuilder."<init>":()V
     130: aload         6
     132: invokevirtual #52                 // Method java/lang/StringBuilder.append:(Ljava/lang/String;)Ljava/lang/StringBuilder;
     135: ldc           #53                 // String ,puid=*
     137: invokevirtual #52                 // Method java/lang/StringBuilder.append:(Ljava/lang/String;)Ljava/lang/StringBuilder;
     140: invokevirtual #54                 // Method java/lang/StringBuilder.toString:()Ljava/lang/String;
     143: astore        11
     145: aload_3
     146: new           #55                 // class javax/management/ObjectName
     149: dup
     150: aload         11
     152: invokespecial #56                 // Method javax/management/ObjectName."<init>":(Ljava/lang/String;)V
     155: aconst_null
     156: invokeinterface #57,  3           // InterfaceMethod javax/management/MBeanServer.queryMBeans:(Ljavax/management/ObjectName;Ljavax/management/QueryExp;)Ljava/util/Set;
     161: astore        12
     163: aload_0
     164: aload         7
     166: aload         12
     168: aload_3
     169: invokespecial #58                 // Method addParticipants:(Lorg/jboss/as/controller/registry/Resource;Ljava/util/Set;Ljavax/management/MBeanServer;)V
     172: ldc           #59                 // String transactions
     174: aload         10
     176: invokestatic  #41                 // Method org/jboss/as/controller/PathElement.pathElement:(Ljava/lang/String;Ljava/lang/String;)Lorg/jboss/as/controller/PathElement;
     179: astore        13
     181: aload_1
     182: aload         13
     184: aload         7
     186: invokeinterface #42,  3           // InterfaceMethod org/jboss/as/controller/registry/Resource.registerChild:(Lorg/jboss/as/controller/PathElement;Lorg/jboss/as/controller/registry/Resource;)V
     191: goto          8
     194: return

  private org.jboss.as.controller.registry.Resource probeTransactions(javax.management.MBeanServer, boolean) throws org.jboss.as.controller.OperationFailedException;
    Code:
       0: new           #55                 // class javax/management/ObjectName
       3: dup
       4: ldc           #61                 // String jboss.jta:type=ObjectStore
       6: invokespecial #56                 // Method javax/management/ObjectName."<init>":(Ljava/lang/String;)V
       9: astore_3
      10: aload_1
      11: aload_3
      12: new           #13                 // class javax/management/Attribute
      15: dup
      16: ldc           #62                 // String ExposeAllRecordsAsMBeans
      18: iload_2
      19: invokestatic  #63                 // Method java/lang/Boolean.valueOf:(Z)Ljava/lang/Boolean;
      22: invokespecial #64                 // Method javax/management/Attribute."<init>":(Ljava/lang/String;Ljava/lang/Object;)V
      25: invokeinterface #65,  3           // InterfaceMethod javax/management/MBeanServer.setAttribute:(Ljavax/management/ObjectName;Ljavax/management/Attribute;)V
      30: aload_1
      31: aload_3
      32: ldc           #66                 // String probe
      34: aconst_null
      35: aconst_null
      36: invokeinterface #67,  5           // InterfaceMethod javax/management/MBeanServer.invoke:(Ljavax/management/ObjectName;Ljava/lang/String;[Ljava/lang/Object;[Ljava/lang/String;)Ljava/lang/Object;
      41: pop
      42: aload_1
      43: new           #55                 // class javax/management/ObjectName
      46: dup
      47: ldc           #68                 // String jboss.jta:type=ObjectStore,*
      49: invokespecial #56                 // Method javax/management/ObjectName."<init>":(Ljava/lang/String;)V
      52: aconst_null
      53: invokeinterface #57,  3           // InterfaceMethod javax/management/MBeanServer.queryMBeans:(Ljavax/management/ObjectName;Ljavax/management/QueryExp;)Ljava/util/Set;
      58: astore        4
      60: invokestatic  #69                 // Method org/jboss/as/controller/registry/Resource$Factory.create:()Lorg/jboss/as/controller/registry/Resource;
      63: astore        5
      65: aload_0
      66: aload         5
      68: aload         4
      70: aload_1
      71: invokespecial #70                 // Method addTransactions:(Lorg/jboss/as/controller/registry/Resource;Ljava/util/Set;Ljavax/management/MBeanServer;)V
      74: aload         5
      76: areturn
      77: astore_3
      78: new           #72                 // class org/jboss/as/controller/OperationFailedException
      81: dup
      82: ldc           #73                 // String Transaction discovery error:
      84: aload_3
      85: invokespecial #74                 // Method org/jboss/as/controller/OperationFailedException."<init>":(Ljava/lang/String;Ljava/lang/Throwable;)V
      88: athrow
      89: astore_3
      90: new           #72                 // class org/jboss/as/controller/OperationFailedException
      93: dup
      94: ldc           #73                 // String Transaction discovery error:
      96: aload_3
      97: invokespecial #74                 // Method org/jboss/as/controller/OperationFailedException."<init>":(Ljava/lang/String;Ljava/lang/Throwable;)V
     100: athrow
    Exception table:
       from    to  target type
           0    76    77   Class javax/management/JMException
           0    76    89   Class java/io/IOException

  public void execute(org.jboss.as.controller.OperationContext, org.jboss.dmr.ModelNode) throws org.jboss.as.controller.OperationFailedException;
    Code:
       0: aload_1
       1: invokeinterface #76,  1           // InterfaceMethod org/jboss/as/controller/OperationContext.isNormalServer:()Z
       6: ifne          19
       9: aload_1
      10: getstatic     #77                 // Field org/jboss/as/controller/OperationContext$RollbackHandler.NOOP_ROLLBACK_HANDLER:Lorg/jboss/as/controller/OperationContext$RollbackHandler;
      13: invokeinterface #78,  2           // InterfaceMethod org/jboss/as/controller/OperationContext.completeStep:(Lorg/jboss/as/controller/OperationContext$RollbackHandler;)V
      18: return
      19: aload_1
      20: invokestatic  #79                 // Method org/jboss/as/txn/subsystem/TransactionExtension.getMBeanServer:(Lorg/jboss/as/controller/OperationContext;)Ljavax/management/MBeanServer;
      23: astore_3
      24: aload_3
      25: ifnull        132
      28: aload_1
      29: getstatic     #80                 // Field org/jboss/as/controller/PathAddress.EMPTY_ADDRESS:Lorg/jboss/as/controller/PathAddress;
      32: invokeinterface #81,  2           // InterfaceMethod org/jboss/as/controller/OperationContext.readResource:(Lorg/jboss/as/controller/PathAddress;)Lorg/jboss/as/controller/registry/Resource;
      37: astore        4
      39: getstatic     #82                 // Field $assertionsDisabled:Z
      42: ifne          61
      45: aload         4
      47: instanceof    #83                 // class org/jboss/as/txn/subsystem/LogStoreResource
      50: ifne          61
      53: new           #84                 // class java/lang/AssertionError
      56: dup
      57: invokespecial #85                 // Method java/lang/AssertionError."<init>":()V
      60: athrow
      61: aload         4
      63: checkcast     #83                 // class org/jboss/as/txn/subsystem/LogStoreResource
      66: astore        5
      68: aload_1
      69: getstatic     #80                 // Field org/jboss/as/controller/PathAddress.EMPTY_ADDRESS:Lorg/jboss/as/controller/PathAddress;
      72: invokeinterface #81,  2           // InterfaceMethod org/jboss/as/controller/OperationContext.readResource:(Lorg/jboss/as/controller/PathAddress;)Lorg/jboss/as/controller/registry/Resource;
      77: invokeinterface #31,  1           // InterfaceMethod org/jboss/as/controller/registry/Resource.getModel:()Lorg/jboss/dmr/ModelNode;
      82: astore        6
      84: getstatic     #86                 // Field org/jboss/as/txn/subsystem/LogStoreConstants.EXPOSE_ALL_LOGS:Lorg/jboss/as/controller/SimpleAttributeDefinition;
      87: aload_1
      88: aload         6
      90: invokevirtual #87                 // Method org/jboss/as/controller/SimpleAttributeDefinition.resolveModelAttribute:(Lorg/jboss/as/controller/OperationContext;Lorg/jboss/dmr/ModelNode;)Lorg/jboss/dmr/ModelNode;
      93: invokevirtual #88                 // Method org/jboss/dmr/ModelNode.asBoolean:()Z
      96: istore        7
      98: aload_0
      99: aload_3
     100: iload         7
     102: invokespecial #89                 // Method probeTransactions:(Ljavax/management/MBeanServer;Z)Lorg/jboss/as/controller/registry/Resource;
     105: astore        8
     107: aload_1
     108: invokeinterface #90,  1           // InterfaceMethod org/jboss/as/controller/OperationContext.acquireControllerLock:()V
     113: aload         8
     115: aload         5
     117: invokevirtual #91                 // Method org/jboss/as/txn/subsystem/LogStoreResource.getModel:()Lorg/jboss/dmr/ModelNode;
     120: invokeinterface #92,  2           // InterfaceMethod org/jboss/as/controller/registry/Resource.writeModel:(Lorg/jboss/dmr/ModelNode;)V
     125: aload         5
     127: aload         8
     129: invokevirtual #93                 // Method org/jboss/as/txn/subsystem/LogStoreResource.update:(Lorg/jboss/as/controller/registry/Resource;)V
     132: aload_1
     133: getstatic     #77                 // Field org/jboss/as/controller/OperationContext$RollbackHandler.NOOP_ROLLBACK_HANDLER:Lorg/jboss/as/controller/OperationContext$RollbackHandler;
     136: invokeinterface #78,  2           // InterfaceMethod org/jboss/as/controller/OperationContext.completeStep:(Lorg/jboss/as/controller/OperationContext$RollbackHandler;)V
     141: return

  static {};
    Code:
       0: ldc           #60                 // class org/jboss/as/txn/subsystem/LogStoreProbeHandler
       2: invokevirtual #94                 // Method java/lang/Class.desiredAssertionStatus:()Z
       5: ifne          12
       8: iconst_1
       9: goto          13
      12: iconst_0
      13: putstatic     #82                 // Field $assertionsDisabled:Z
      16: new           #60                 // class org/jboss/as/txn/subsystem/LogStoreProbeHandler
      19: dup
      20: invokespecial #95                 // Method "<init>":()V
      23: putstatic     #96                 // Field INSTANCE:Lorg/jboss/as/txn/subsystem/LogStoreProbeHandler;
      26: getstatic     #37                 // Field org/jboss/as/txn/subsystem/LogStoreConstants.MODEL_TO_JMX_PARTICIPANT_NAMES:Ljava/util/Map;
      29: ldc           #97                 // String jndi-name
      31: invokeinterface #23,  2           // InterfaceMethod java/util/Map.get:(Ljava/lang/Object;)Ljava/lang/Object;
      36: checkcast     #4                  // class java/lang/String
      39: putstatic     #34                 // Field JNDI_PROPNAME:Ljava/lang/String;
      42: return
}
