public class org.bouncycastle.pqc.crypto.xmss.XMSSUtil {
  public org.bouncycastle.pqc.crypto.xmss.XMSSUtil();
    Code:
       0: aload_0
       1: invokespecial #184                // Method java/lang/Object."<init>":()V
       4: return

  public static int log2(int);
    Code:
       0: iconst_0
       1: istore_1
       2: iload_0
       3: iconst_1
       4: ishr
       5: dup
       6: istore_0
       7: ifeq          16
      10: iinc          1, 1
      13: goto          2
      16: iload_1
      17: ireturn

  public static byte[] toBytesBigEndian(long, int);
    Code:
       0: iload_2
       1: newarray       byte
       3: astore_3
       4: iload_2
       5: iconst_1
       6: isub
       7: istore        4
       9: iload         4
      11: iflt          32
      14: aload_3
      15: iload         4
      17: lload_0
      18: l2i
      19: i2b
      20: bastore
      21: lload_0
      22: bipush        8
      24: lushr
      25: lstore_0
      26: iinc          4, -1
      29: goto          9
      32: aload_3
      33: areturn

  public static void longToBigEndian(long, byte[], int);
    Code:
       0: aload_2
       1: ifnonnull     14
       4: new           #125                // class java/lang/NullPointerException
       7: dup
       8: ldc           #6                  // String in == null
      10: invokespecial #183                // Method java/lang/NullPointerException."<init>":(Ljava/lang/String;)V
      13: athrow
      14: aload_2
      15: arraylength
      16: iload_3
      17: isub
      18: bipush        8
      20: if_icmpge     33
      23: new           #122                // class java/lang/IllegalArgumentException
      26: dup
      27: ldc           #10                 // String not enough space in array
      29: invokespecial #180                // Method java/lang/IllegalArgumentException."<init>":(Ljava/lang/String;)V
      32: athrow
      33: aload_2
      34: iload_3
      35: lload_0
      36: bipush        56
      38: lshr
      39: ldc2_w        #111                // long 255l
      42: land
      43: l2i
      44: i2b
      45: bastore
      46: aload_2
      47: iload_3
      48: iconst_1
      49: iadd
      50: lload_0
      51: bipush        48
      53: lshr
      54: ldc2_w        #111                // long 255l
      57: land
      58: l2i
      59: i2b
      60: bastore
      61: aload_2
      62: iload_3
      63: iconst_2
      64: iadd
      65: lload_0
      66: bipush        40
      68: lshr
      69: ldc2_w        #111                // long 255l
      72: land
      73: l2i
      74: i2b
      75: bastore
      76: aload_2
      77: iload_3
      78: iconst_3
      79: iadd
      80: lload_0
      81: bipush        32
      83: lshr
      84: ldc2_w        #111                // long 255l
      87: land
      88: l2i
      89: i2b
      90: bastore
      91: aload_2
      92: iload_3
      93: iconst_4
      94: iadd
      95: lload_0
      96: bipush        24
      98: lshr
      99: ldc2_w        #111                // long 255l
     102: land
     103: l2i
     104: i2b
     105: bastore
     106: aload_2
     107: iload_3
     108: iconst_5
     109: iadd
     110: lload_0
     111: bipush        16
     113: lshr
     114: ldc2_w        #111                // long 255l
     117: land
     118: l2i
     119: i2b
     120: bastore
     121: aload_2
     122: iload_3
     123: bipush        6
     125: iadd
     126: lload_0
     127: bipush        8
     129: lshr
     130: ldc2_w        #111                // long 255l
     133: land
     134: l2i
     135: i2b
     136: bastore
     137: aload_2
     138: iload_3
     139: bipush        7
     141: iadd
     142: lload_0
     143: ldc2_w        #111                // long 255l
     146: land
     147: l2i
     148: i2b
     149: bastore
     150: return

  public static long bytesToXBigEndian(byte[], int, int);
    Code:
       0: aload_0
       1: ifnonnull     14
       4: new           #125                // class java/lang/NullPointerException
       7: dup
       8: ldc           #6                  // String in == null
      10: invokespecial #183                // Method java/lang/NullPointerException."<init>":(Ljava/lang/String;)V
      13: athrow
      14: lconst_0
      15: lstore_3
      16: iload_1
      17: istore        5
      19: iload         5
      21: iload_1
      22: iload_2
      23: iadd
      24: if_icmpge     48
      27: lload_3
      28: bipush        8
      30: lshl
      31: aload_0
      32: iload         5
      34: baload
      35: sipush        255
      38: iand
      39: i2l
      40: lor
      41: lstore_3
      42: iinc          5, 1
      45: goto          19
      48: lload_3
      49: lreturn

  public static byte[] cloneArray(byte[]);
    Code:
       0: aload_0
       1: ifnonnull     14
       4: new           #125                // class java/lang/NullPointerException
       7: dup
       8: ldc           #6                  // String in == null
      10: invokespecial #183                // Method java/lang/NullPointerException."<init>":(Ljava/lang/String;)V
      13: athrow
      14: aload_0
      15: arraylength
      16: newarray       byte
      18: astore_1
      19: aload_0
      20: iconst_0
      21: aload_1
      22: iconst_0
      23: aload_0
      24: arraylength
      25: invokestatic  #186                // Method java/lang/System.arraycopy:(Ljava/lang/Object;ILjava/lang/Object;II)V
      28: aload_1
      29: areturn

  public static byte[][] cloneArray(byte[][]);
    Code:
       0: aload_0
       1: invokestatic  #187                // Method hasNullPointer:([[B)Z
       4: ifeq          17
       7: new           #125                // class java/lang/NullPointerException
      10: dup
      11: ldc           #7                  // String in has null pointers
      13: invokespecial #183                // Method java/lang/NullPointerException."<init>":(Ljava/lang/String;)V
      16: athrow
      17: aload_0
      18: arraylength
      19: anewarray     #113                // class "[B"
      22: astore_1
      23: iconst_0
      24: istore_2
      25: iload_2
      26: aload_0
      27: arraylength
      28: if_icmpge     61
      31: aload_1
      32: iload_2
      33: aload_0
      34: iload_2
      35: aaload
      36: arraylength
      37: newarray       byte
      39: aastore
      40: aload_0
      41: iload_2
      42: aaload
      43: iconst_0
      44: aload_1
      45: iload_2
      46: aaload
      47: iconst_0
      48: aload_0
      49: iload_2
      50: aaload
      51: arraylength
      52: invokestatic  #186                // Method java/lang/System.arraycopy:(Ljava/lang/Object;ILjava/lang/Object;II)V
      55: iinc          2, 1
      58: goto          25
      61: aload_1
      62: areturn

  public static boolean areEqual(byte[][], byte[][]);
    Code:
       0: aload_0
       1: invokestatic  #187                // Method hasNullPointer:([[B)Z
       4: ifne          14
       7: aload_1
       8: invokestatic  #187                // Method hasNullPointer:([[B)Z
      11: ifeq          24
      14: new           #125                // class java/lang/NullPointerException
      17: dup
      18: ldc           #3                  // String a or b == null
      20: invokespecial #183                // Method java/lang/NullPointerException."<init>":(Ljava/lang/String;)V
      23: athrow
      24: iconst_0
      25: istore_2
      26: iload_2
      27: aload_0
      28: arraylength
      29: if_icmpge     52
      32: aload_0
      33: iload_2
      34: aaload
      35: aload_1
      36: iload_2
      37: aaload
      38: invokestatic  #189                // Method org/bouncycastle/util/Arrays.areEqual:([B[B)Z
      41: ifne          46
      44: iconst_0
      45: ireturn
      46: iinc          2, 1
      49: goto          26
      52: iconst_1
      53: ireturn

  public static void dumpByteArray(byte[][]);
    Code:
       0: aload_0
       1: invokestatic  #187                // Method hasNullPointer:([[B)Z
       4: ifeq          17
       7: new           #125                // class java/lang/NullPointerException
      10: dup
      11: ldc           #17                 // String x has null pointers
      13: invokespecial #183                // Method java/lang/NullPointerException."<init>":(Ljava/lang/String;)V
      16: athrow
      17: iconst_0
      18: istore_1
      19: iload_1
      20: aload_0
      21: arraylength
      22: if_icmpge     43
      25: getstatic     #168                // Field java/lang/System.out:Ljava/io/PrintStream;
      28: aload_0
      29: iload_1
      30: aaload
      31: invokestatic  #190                // Method org/bouncycastle/util/encoders/Hex.toHexString:([B)Ljava/lang/String;
      34: invokevirtual #178                // Method java/io/PrintStream.println:(Ljava/lang/String;)V
      37: iinc          1, 1
      40: goto          19
      43: return

  public static boolean hasNullPointer(byte[][]);
    Code:
       0: aload_0
       1: ifnonnull     6
       4: iconst_1
       5: ireturn
       6: iconst_0
       7: istore_1
       8: iload_1
       9: aload_0
      10: arraylength
      11: if_icmpge     28
      14: aload_0
      15: iload_1
      16: aaload
      17: ifnonnull     22
      20: iconst_1
      21: ireturn
      22: iinc          1, 1
      25: goto          8
      28: iconst_0
      29: ireturn

  public static void copyBytesAtOffset(byte[], byte[], int);
    Code:
       0: aload_0
       1: ifnonnull     14
       4: new           #125                // class java/lang/NullPointerException
       7: dup
       8: ldc           #5                  // String dst == null
      10: invokespecial #183                // Method java/lang/NullPointerException."<init>":(Ljava/lang/String;)V
      13: athrow
      14: aload_1
      15: ifnonnull     28
      18: new           #125                // class java/lang/NullPointerException
      21: dup
      22: ldc           #13                 // String src == null
      24: invokespecial #183                // Method java/lang/NullPointerException."<init>":(Ljava/lang/String;)V
      27: athrow
      28: iload_2
      29: ifge          42
      32: new           #122                // class java/lang/IllegalArgumentException
      35: dup
      36: ldc           #12                 // String offset hast to be >= 0
      38: invokespecial #180                // Method java/lang/IllegalArgumentException."<init>":(Ljava/lang/String;)V
      41: athrow
      42: aload_1
      43: arraylength
      44: iload_2
      45: iadd
      46: aload_0
      47: arraylength
      48: if_icmple     61
      51: new           #122                // class java/lang/IllegalArgumentException
      54: dup
      55: ldc           #14                 // String src length + offset must not be greater than size of destination
      57: invokespecial #180                // Method java/lang/IllegalArgumentException."<init>":(Ljava/lang/String;)V
      60: athrow
      61: iconst_0
      62: istore_3
      63: iload_3
      64: aload_1
      65: arraylength
      66: if_icmpge     83
      69: aload_0
      70: iload_2
      71: iload_3
      72: iadd
      73: aload_1
      74: iload_3
      75: baload
      76: bastore
      77: iinc          3, 1
      80: goto          63
      83: return

  public static byte[] extractBytesAtOffset(byte[], int, int);
    Code:
       0: aload_0
       1: ifnonnull     14
       4: new           #125                // class java/lang/NullPointerException
       7: dup
       8: ldc           #13                 // String src == null
      10: invokespecial #183                // Method java/lang/NullPointerException."<init>":(Ljava/lang/String;)V
      13: athrow
      14: iload_1
      15: ifge          28
      18: new           #122                // class java/lang/IllegalArgumentException
      21: dup
      22: ldc           #12                 // String offset hast to be >= 0
      24: invokespecial #180                // Method java/lang/IllegalArgumentException."<init>":(Ljava/lang/String;)V
      27: athrow
      28: iload_2
      29: ifge          42
      32: new           #122                // class java/lang/IllegalArgumentException
      35: dup
      36: ldc           #9                  // String length hast to be >= 0
      38: invokespecial #180                // Method java/lang/IllegalArgumentException."<init>":(Ljava/lang/String;)V
      41: athrow
      42: iload_1
      43: iload_2
      44: iadd
      45: aload_0
      46: arraylength
      47: if_icmple     60
      50: new           #122                // class java/lang/IllegalArgumentException
      53: dup
      54: ldc           #11                 // String offset + length must not be greater then size of source array
      56: invokespecial #180                // Method java/lang/IllegalArgumentException."<init>":(Ljava/lang/String;)V
      59: athrow
      60: iload_2
      61: newarray       byte
      63: astore_3
      64: iconst_0
      65: istore        4
      67: iload         4
      69: aload_3
      70: arraylength
      71: if_icmpge     90
      74: aload_3
      75: iload         4
      77: aload_0
      78: iload_1
      79: iload         4
      81: iadd
      82: baload
      83: bastore
      84: iinc          4, 1
      87: goto          67
      90: aload_3
      91: areturn

  public static boolean isIndexValid(int, long);
    Code:
       0: lload_1
       1: lconst_0
       2: lcmp
       3: ifge          16
       6: new           #123                // class java/lang/IllegalStateException
       9: dup
      10: ldc           #8                  // String index must not be negative
      12: invokespecial #181                // Method java/lang/IllegalStateException."<init>":(Ljava/lang/String;)V
      15: athrow
      16: lload_1
      17: lconst_1
      18: iload_0
      19: lshl
      20: lcmp
      21: ifge          28
      24: iconst_1
      25: goto          29
      28: iconst_0
      29: ireturn

  public static int getDigestSize(org.bouncycastle.crypto.Digest);
    Code:
       0: aload_0
       1: ifnonnull     14
       4: new           #125                // class java/lang/NullPointerException
       7: dup
       8: ldc           #4                  // String digest == null
      10: invokespecial #183                // Method java/lang/NullPointerException."<init>":(Ljava/lang/String;)V
      13: athrow
      14: aload_0
      15: invokeinterface #192,  1          // InterfaceMethod org/bouncycastle/crypto/Digest.getAlgorithmName:()Ljava/lang/String;
      20: astore_1
      21: aload_1
      22: ldc           #1                  // String SHAKE128
      24: invokevirtual #185                // Method java/lang/String.equals:(Ljava/lang/Object;)Z
      27: ifeq          33
      30: bipush        32
      32: ireturn
      33: aload_1
      34: ldc           #2                  // String SHAKE256
      36: invokevirtual #185                // Method java/lang/String.equals:(Ljava/lang/Object;)Z
      39: ifeq          45
      42: bipush        64
      44: ireturn
      45: aload_0
      46: invokeinterface #191,  1          // InterfaceMethod org/bouncycastle/crypto/Digest.getDigestSize:()I
      51: ireturn

  public static long getTreeIndex(long, int);
    Code:
       0: lload_0
       1: iload_2
       2: lshr
       3: lreturn

  public static int getLeafIndex(long, int);
    Code:
       0: lload_0
       1: lconst_1
       2: iload_2
       3: lshl
       4: lconst_1
       5: lsub
       6: land
       7: l2i
       8: ireturn

  public static byte[] serialize(java.lang.Object) throws java.io.IOException;
    Code:
       0: new           #115                // class java/io/ByteArrayOutputStream
       3: dup
       4: invokespecial #170                // Method java/io/ByteArrayOutputStream."<init>":()V
       7: astore_1
       8: new           #118                // class java/io/ObjectOutputStream
      11: dup
      12: aload_1
      13: invokespecial #176                // Method java/io/ObjectOutputStream."<init>":(Ljava/io/OutputStream;)V
      16: astore_2
      17: aload_2
      18: aload_0
      19: invokevirtual #177                // Method java/io/ObjectOutputStream.writeObject:(Ljava/lang/Object;)V
      22: aload_2
      23: invokevirtual #175                // Method java/io/ObjectOutputStream.flush:()V
      26: aload_1
      27: invokevirtual #171                // Method java/io/ByteArrayOutputStream.toByteArray:()[B
      30: areturn

  public static java.lang.Object deserialize(byte[], java.lang.Class) throws java.io.IOException, java.lang.ClassNotFoundException;
    Code:
       0: new           #114                // class java/io/ByteArrayInputStream
       3: dup
       4: aload_0
       5: invokespecial #169                // Method java/io/ByteArrayInputStream."<init>":([B)V
       8: astore_2
       9: new           #131                // class org/bouncycastle/pqc/crypto/xmss/XMSSUtil$CheckingStream
      12: dup
      13: aload_1
      14: aload_2
      15: invokespecial #188                // Method org/bouncycastle/pqc/crypto/xmss/XMSSUtil$CheckingStream."<init>":(Ljava/lang/Class;Ljava/io/InputStream;)V
      18: astore_3
      19: aload_3
      20: invokevirtual #174                // Method java/io/ObjectInputStream.readObject:()Ljava/lang/Object;
      23: astore        4
      25: aload_3
      26: invokevirtual #173                // Method java/io/ObjectInputStream.available:()I
      29: ifeq          42
      32: new           #116                // class java/io/IOException
      35: dup
      36: ldc           #16                 // String unexpected data found at end of ObjectInputStream
      38: invokespecial #172                // Method java/io/IOException."<init>":(Ljava/lang/String;)V
      41: athrow
      42: aload_1
      43: aload         4
      45: invokevirtual #179                // Method java/lang/Class.isInstance:(Ljava/lang/Object;)Z
      48: ifeq          54
      51: aload         4
      53: areturn
      54: new           #116                // class java/io/IOException
      57: dup
      58: ldc           #15                 // String unexpected class found in ObjectInputStream
      60: invokespecial #172                // Method java/io/IOException."<init>":(Ljava/lang/String;)V
      63: athrow

  public static int calculateTau(int, int);
    Code:
       0: iconst_0
       1: istore_2
       2: iconst_0
       3: istore_3
       4: iload_3
       5: iload_1
       6: if_icmpge     28
       9: iload_0
      10: iload_3
      11: ishr
      12: iconst_1
      13: iand
      14: ifne          22
      17: iload_3
      18: istore_2
      19: goto          28
      22: iinc          3, 1
      25: goto          4
      28: iload_2
      29: ireturn

  public static boolean isNewBDSInitNeeded(long, int, int);
    Code:
       0: lload_0
       1: lconst_0
       2: lcmp
       3: ifne          8
       6: iconst_0
       7: ireturn
       8: lload_0
       9: iconst_1
      10: iload_2
      11: ishl
      12: i2d
      13: iload_3
      14: iconst_1
      15: iadd
      16: i2d
      17: invokestatic  #182                // Method java/lang/Math.pow:(DD)D
      20: d2l
      21: lrem
      22: lconst_0
      23: lcmp
      24: ifne          31
      27: iconst_1
      28: goto          32
      31: iconst_0
      32: ireturn

  public static boolean isNewAuthenticationPathNeeded(long, int, int);
    Code:
       0: lload_0
       1: lconst_0
       2: lcmp
       3: ifne          8
       6: iconst_0
       7: ireturn
       8: lload_0
       9: lconst_1
      10: ladd
      11: iconst_1
      12: iload_2
      13: ishl
      14: i2d
      15: iload_3
      16: i2d
      17: invokestatic  #182                // Method java/lang/Math.pow:(DD)D
      20: d2l
      21: lrem
      22: lconst_0
      23: lcmp
      24: ifne          31
      27: iconst_1
      28: goto          32
      31: iconst_0
      32: ireturn
}
