Compiled from "SQLQuery.java"
public interface org.hibernate.SQLQuery<T> extends org.hibernate.Query<T>, org.hibernate.SynchronizeableQuery<T> {
  public abstract org.hibernate.query.NativeQuery<T> setResultSetMapping(java.lang.String);

  public abstract boolean isCallable();

  public abstract java.util.List<org.hibernate.engine.query.spi.sql.NativeSQLQueryReturn> getQueryReturns();

  public abstract org.hibernate.query.NativeQuery<T> addScalar(java.lang.String);

  public abstract org.hibernate.query.NativeQuery<T> addScalar(java.lang.String, org.hibernate.type.Type);

  public abstract org.hibernate.SQLQuery$RootReturn addRoot(java.lang.String, java.lang.String);

  public abstract org.hibernate.SQLQuery$RootReturn addRoot(java.lang.String, java.lang.Class);

  public abstract org.hibernate.query.NativeQuery<T> addEntity(java.lang.String);

  public abstract org.hibernate.query.NativeQuery<T> addEntity(java.lang.String, java.lang.String);

  public abstract org.hibernate.query.NativeQuery<T> addEntity(java.lang.String, java.lang.String, org.hibernate.LockMode);

  public abstract org.hibernate.query.NativeQuery<T> addEntity(java.lang.Class);

  public abstract org.hibernate.query.NativeQuery<T> addEntity(java.lang.String, java.lang.Class);

  public abstract org.hibernate.query.NativeQuery<T> addEntity(java.lang.String, java.lang.Class, org.hibernate.LockMode);

  public abstract org.hibernate.SQLQuery$FetchReturn addFetch(java.lang.String, java.lang.String, java.lang.String);

  public abstract org.hibernate.query.NativeQuery<T> addJoin(java.lang.String, java.lang.String);

  public abstract org.hibernate.query.NativeQuery<T> addJoin(java.lang.String, java.lang.String, java.lang.String);

  public abstract org.hibernate.query.NativeQuery<T> addJoin(java.lang.String, java.lang.String, org.hibernate.LockMode);

  public abstract org.hibernate.query.NativeQuery<T> setHibernateFlushMode(org.hibernate.FlushMode);

  public abstract org.hibernate.query.NativeQuery<T> setFlushMode(javax.persistence.FlushModeType);

  public abstract org.hibernate.query.NativeQuery<T> setCacheMode(org.hibernate.CacheMode);

  public abstract org.hibernate.query.NativeQuery<T> setCacheable(boolean);

  public abstract org.hibernate.query.NativeQuery<T> setCacheRegion(java.lang.String);

  public abstract org.hibernate.query.NativeQuery<T> setTimeout(int);

  public abstract org.hibernate.query.NativeQuery<T> setFetchSize(int);

  public abstract org.hibernate.query.NativeQuery<T> setReadOnly(boolean);

  public abstract org.hibernate.query.NativeQuery<T> setLockOptions(org.hibernate.LockOptions);

  public abstract org.hibernate.query.NativeQuery<T> setLockMode(java.lang.String, org.hibernate.LockMode);

  public abstract org.hibernate.query.NativeQuery<T> setComment(java.lang.String);

  public abstract org.hibernate.query.NativeQuery<T> addQueryHint(java.lang.String);

  public abstract <P> org.hibernate.query.NativeQuery<T> setParameter(org.hibernate.query.QueryParameter<P>, P);

  public abstract <P> org.hibernate.query.NativeQuery<T> setParameter(javax.persistence.Parameter<P>, P);

  public abstract org.hibernate.query.NativeQuery<T> setParameter(java.lang.String, java.lang.Object);

  public abstract org.hibernate.query.NativeQuery<T> setParameter(int, java.lang.Object);

  public abstract <P> org.hibernate.query.NativeQuery<T> setParameter(org.hibernate.query.QueryParameter<P>, P, org.hibernate.type.Type);

  public abstract org.hibernate.query.NativeQuery<T> setParameter(java.lang.String, java.lang.Object, org.hibernate.type.Type);

  public abstract org.hibernate.query.NativeQuery<T> setParameter(int, java.lang.Object, org.hibernate.type.Type);

  public abstract <P> org.hibernate.query.NativeQuery<T> setParameter(org.hibernate.query.QueryParameter<P>, P, javax.persistence.TemporalType);

  public abstract <P> org.hibernate.query.NativeQuery<T> setParameter(java.lang.String, P, javax.persistence.TemporalType);

  public abstract <P> org.hibernate.query.NativeQuery<T> setParameter(int, P, javax.persistence.TemporalType);

  public abstract <P> org.hibernate.query.NativeQuery<T> setParameterList(org.hibernate.query.QueryParameter<P>, java.util.Collection<P>);

  public abstract org.hibernate.query.NativeQuery<T> setParameterList(java.lang.String, java.util.Collection);

  public abstract org.hibernate.query.NativeQuery<T> setParameterList(java.lang.String, java.util.Collection, org.hibernate.type.Type);

  public abstract org.hibernate.query.NativeQuery<T> setParameterList(java.lang.String, java.lang.Object[], org.hibernate.type.Type);

  public abstract org.hibernate.query.NativeQuery<T> setParameterList(java.lang.String, java.lang.Object[]);

  public abstract org.hibernate.query.NativeQuery<T> setProperties(java.lang.Object);

  public abstract org.hibernate.query.NativeQuery<T> setProperties(java.util.Map);

  public abstract org.hibernate.query.NativeQuery<T> setParameter(javax.persistence.Parameter<java.util.Calendar>, java.util.Calendar, javax.persistence.TemporalType);

  public abstract org.hibernate.query.NativeQuery<T> setParameter(javax.persistence.Parameter<java.util.Date>, java.util.Date, javax.persistence.TemporalType);

  public abstract org.hibernate.query.NativeQuery<T> setParameter(java.lang.String, java.util.Calendar, javax.persistence.TemporalType);

  public abstract org.hibernate.query.NativeQuery<T> setParameter(java.lang.String, java.util.Date, javax.persistence.TemporalType);

  public abstract org.hibernate.query.NativeQuery<T> setParameter(int, java.util.Calendar, javax.persistence.TemporalType);

  public abstract org.hibernate.query.NativeQuery<T> setParameter(int, java.util.Date, javax.persistence.TemporalType);

  public abstract org.hibernate.query.NativeQuery<T> addSynchronizedQuerySpace(java.lang.String);

  public abstract org.hibernate.query.NativeQuery<T> addSynchronizedEntityName(java.lang.String) throws org.hibernate.MappingException;

  public abstract org.hibernate.query.NativeQuery<T> addSynchronizedEntityClass(java.lang.Class) throws org.hibernate.MappingException;

  public abstract org.hibernate.query.NativeQuery<T> setFlushMode(org.hibernate.FlushMode);

  public default org.hibernate.Query setFlushMode(javax.persistence.FlushModeType);
    Code:
       0: aload_0
       1: aload_1
       2: invokeinterface #1,  2            // InterfaceMethod setFlushMode:(Ljavax/persistence/FlushModeType;)Lorg/hibernate/query/NativeQuery;
       7: areturn

  public default org.hibernate.Query setParameter(int, java.util.Date, javax.persistence.TemporalType);
    Code:
       0: aload_0
       1: iload_1
       2: aload_2
       3: aload_3
       4: invokeinterface #2,  4            // InterfaceMethod setParameter:(ILjava/util/Date;Ljavax/persistence/TemporalType;)Lorg/hibernate/query/NativeQuery;
       9: areturn

  public default org.hibernate.Query setParameter(int, java.util.Calendar, javax.persistence.TemporalType);
    Code:
       0: aload_0
       1: iload_1
       2: aload_2
       3: aload_3
       4: invokeinterface #3,  4            // InterfaceMethod setParameter:(ILjava/util/Calendar;Ljavax/persistence/TemporalType;)Lorg/hibernate/query/NativeQuery;
       9: areturn

  public default org.hibernate.Query setParameter(java.lang.String, java.util.Date, javax.persistence.TemporalType);
    Code:
       0: aload_0
       1: aload_1
       2: aload_2
       3: aload_3
       4: invokeinterface #4,  4            // InterfaceMethod setParameter:(Ljava/lang/String;Ljava/util/Date;Ljavax/persistence/TemporalType;)Lorg/hibernate/query/NativeQuery;
       9: areturn

  public default org.hibernate.Query setParameter(java.lang.String, java.util.Calendar, javax.persistence.TemporalType);
    Code:
       0: aload_0
       1: aload_1
       2: aload_2
       3: aload_3
       4: invokeinterface #5,  4            // InterfaceMethod setParameter:(Ljava/lang/String;Ljava/util/Calendar;Ljavax/persistence/TemporalType;)Lorg/hibernate/query/NativeQuery;
       9: areturn

  public default org.hibernate.Query setParameter(javax.persistence.Parameter, java.util.Date, javax.persistence.TemporalType);
    Code:
       0: aload_0
       1: aload_1
       2: aload_2
       3: aload_3
       4: invokeinterface #6,  4            // InterfaceMethod setParameter:(Ljavax/persistence/Parameter;Ljava/util/Date;Ljavax/persistence/TemporalType;)Lorg/hibernate/query/NativeQuery;
       9: areturn

  public default org.hibernate.Query setParameter(javax.persistence.Parameter, java.util.Calendar, javax.persistence.TemporalType);
    Code:
       0: aload_0
       1: aload_1
       2: aload_2
       3: aload_3
       4: invokeinterface #7,  4            // InterfaceMethod setParameter:(Ljavax/persistence/Parameter;Ljava/util/Calendar;Ljavax/persistence/TemporalType;)Lorg/hibernate/query/NativeQuery;
       9: areturn

  public default org.hibernate.Query setProperties(java.util.Map);
    Code:
       0: aload_0
       1: aload_1
       2: invokeinterface #8,  2            // InterfaceMethod setProperties:(Ljava/util/Map;)Lorg/hibernate/query/NativeQuery;
       7: areturn

  public default org.hibernate.Query setProperties(java.lang.Object);
    Code:
       0: aload_0
       1: aload_1
       2: invokeinterface #9,  2            // InterfaceMethod setProperties:(Ljava/lang/Object;)Lorg/hibernate/query/NativeQuery;
       7: areturn

  public default org.hibernate.Query setParameterList(java.lang.String, java.lang.Object[]);
    Code:
       0: aload_0
       1: aload_1
       2: aload_2
       3: invokeinterface #10,  3           // InterfaceMethod setParameterList:(Ljava/lang/String;[Ljava/lang/Object;)Lorg/hibernate/query/NativeQuery;
       8: areturn

  public default org.hibernate.Query setParameterList(java.lang.String, java.lang.Object[], org.hibernate.type.Type);
    Code:
       0: aload_0
       1: aload_1
       2: aload_2
       3: aload_3
       4: invokeinterface #11,  4           // InterfaceMethod setParameterList:(Ljava/lang/String;[Ljava/lang/Object;Lorg/hibernate/type/Type;)Lorg/hibernate/query/NativeQuery;
       9: areturn

  public default org.hibernate.Query setParameterList(java.lang.String, java.util.Collection, org.hibernate.type.Type);
    Code:
       0: aload_0
       1: aload_1
       2: aload_2
       3: aload_3
       4: invokeinterface #12,  4           // InterfaceMethod setParameterList:(Ljava/lang/String;Ljava/util/Collection;Lorg/hibernate/type/Type;)Lorg/hibernate/query/NativeQuery;
       9: areturn

  public default org.hibernate.Query setParameterList(java.lang.String, java.util.Collection);
    Code:
       0: aload_0
       1: aload_1
       2: aload_2
       3: invokeinterface #13,  3           // InterfaceMethod setParameterList:(Ljava/lang/String;Ljava/util/Collection;)Lorg/hibernate/query/NativeQuery;
       8: areturn

  public default org.hibernate.Query setParameterList(org.hibernate.query.QueryParameter, java.util.Collection);
    Code:
       0: aload_0
       1: aload_1
       2: aload_2
       3: invokeinterface #14,  3           // InterfaceMethod setParameterList:(Lorg/hibernate/query/QueryParameter;Ljava/util/Collection;)Lorg/hibernate/query/NativeQuery;
       8: areturn

  public default org.hibernate.Query setParameter(int, java.lang.Object, javax.persistence.TemporalType);
    Code:
       0: aload_0
       1: iload_1
       2: aload_2
       3: aload_3
       4: invokeinterface #15,  4           // InterfaceMethod setParameter:(ILjava/lang/Object;Ljavax/persistence/TemporalType;)Lorg/hibernate/query/NativeQuery;
       9: areturn

  public default org.hibernate.Query setParameter(java.lang.String, java.lang.Object, javax.persistence.TemporalType);
    Code:
       0: aload_0
       1: aload_1
       2: aload_2
       3: aload_3
       4: invokeinterface #16,  4           // InterfaceMethod setParameter:(Ljava/lang/String;Ljava/lang/Object;Ljavax/persistence/TemporalType;)Lorg/hibernate/query/NativeQuery;
       9: areturn

  public default org.hibernate.Query setParameter(org.hibernate.query.QueryParameter, java.lang.Object, javax.persistence.TemporalType);
    Code:
       0: aload_0
       1: aload_1
       2: aload_2
       3: aload_3
       4: invokeinterface #17,  4           // InterfaceMethod setParameter:(Lorg/hibernate/query/QueryParameter;Ljava/lang/Object;Ljavax/persistence/TemporalType;)Lorg/hibernate/query/NativeQuery;
       9: areturn

  public default org.hibernate.Query setParameter(int, java.lang.Object, org.hibernate.type.Type);
    Code:
       0: aload_0
       1: iload_1
       2: aload_2
       3: aload_3
       4: invokeinterface #18,  4           // InterfaceMethod setParameter:(ILjava/lang/Object;Lorg/hibernate/type/Type;)Lorg/hibernate/query/NativeQuery;
       9: areturn

  public default org.hibernate.Query setParameter(java.lang.String, java.lang.Object, org.hibernate.type.Type);
    Code:
       0: aload_0
       1: aload_1
       2: aload_2
       3: aload_3
       4: invokeinterface #19,  4           // InterfaceMethod setParameter:(Ljava/lang/String;Ljava/lang/Object;Lorg/hibernate/type/Type;)Lorg/hibernate/query/NativeQuery;
       9: areturn

  public default org.hibernate.Query setParameter(org.hibernate.query.QueryParameter, java.lang.Object, org.hibernate.type.Type);
    Code:
       0: aload_0
       1: aload_1
       2: aload_2
       3: aload_3
       4: invokeinterface #20,  4           // InterfaceMethod setParameter:(Lorg/hibernate/query/QueryParameter;Ljava/lang/Object;Lorg/hibernate/type/Type;)Lorg/hibernate/query/NativeQuery;
       9: areturn

  public default org.hibernate.Query setParameter(int, java.lang.Object);
    Code:
       0: aload_0
       1: iload_1
       2: aload_2
       3: invokeinterface #21,  3           // InterfaceMethod setParameter:(ILjava/lang/Object;)Lorg/hibernate/query/NativeQuery;
       8: areturn

  public default org.hibernate.Query setParameter(java.lang.String, java.lang.Object);
    Code:
       0: aload_0
       1: aload_1
       2: aload_2
       3: invokeinterface #22,  3           // InterfaceMethod setParameter:(Ljava/lang/String;Ljava/lang/Object;)Lorg/hibernate/query/NativeQuery;
       8: areturn

  public default org.hibernate.Query setParameter(javax.persistence.Parameter, java.lang.Object);
    Code:
       0: aload_0
       1: aload_1
       2: aload_2
       3: invokeinterface #23,  3           // InterfaceMethod setParameter:(Ljavax/persistence/Parameter;Ljava/lang/Object;)Lorg/hibernate/query/NativeQuery;
       8: areturn

  public default org.hibernate.Query setParameter(org.hibernate.query.QueryParameter, java.lang.Object);
    Code:
       0: aload_0
       1: aload_1
       2: aload_2
       3: invokeinterface #24,  3           // InterfaceMethod setParameter:(Lorg/hibernate/query/QueryParameter;Ljava/lang/Object;)Lorg/hibernate/query/NativeQuery;
       8: areturn

  public default org.hibernate.Query addQueryHint(java.lang.String);
    Code:
       0: aload_0
       1: aload_1
       2: invokeinterface #25,  2           // InterfaceMethod addQueryHint:(Ljava/lang/String;)Lorg/hibernate/query/NativeQuery;
       7: areturn

  public default org.hibernate.Query setComment(java.lang.String);
    Code:
       0: aload_0
       1: aload_1
       2: invokeinterface #26,  2           // InterfaceMethod setComment:(Ljava/lang/String;)Lorg/hibernate/query/NativeQuery;
       7: areturn

  public default org.hibernate.Query setLockMode(java.lang.String, org.hibernate.LockMode);
    Code:
       0: aload_0
       1: aload_1
       2: aload_2
       3: invokeinterface #27,  3           // InterfaceMethod setLockMode:(Ljava/lang/String;Lorg/hibernate/LockMode;)Lorg/hibernate/query/NativeQuery;
       8: areturn

  public default org.hibernate.Query setLockOptions(org.hibernate.LockOptions);
    Code:
       0: aload_0
       1: aload_1
       2: invokeinterface #28,  2           // InterfaceMethod setLockOptions:(Lorg/hibernate/LockOptions;)Lorg/hibernate/query/NativeQuery;
       7: areturn

  public default org.hibernate.Query setReadOnly(boolean);
    Code:
       0: aload_0
       1: iload_1
       2: invokeinterface #29,  2           // InterfaceMethod setReadOnly:(Z)Lorg/hibernate/query/NativeQuery;
       7: areturn

  public default org.hibernate.Query setFetchSize(int);
    Code:
       0: aload_0
       1: iload_1
       2: invokeinterface #30,  2           // InterfaceMethod setFetchSize:(I)Lorg/hibernate/query/NativeQuery;
       7: areturn

  public default org.hibernate.Query setTimeout(int);
    Code:
       0: aload_0
       1: iload_1
       2: invokeinterface #31,  2           // InterfaceMethod setTimeout:(I)Lorg/hibernate/query/NativeQuery;
       7: areturn

  public default org.hibernate.Query setCacheRegion(java.lang.String);
    Code:
       0: aload_0
       1: aload_1
       2: invokeinterface #32,  2           // InterfaceMethod setCacheRegion:(Ljava/lang/String;)Lorg/hibernate/query/NativeQuery;
       7: areturn

  public default org.hibernate.Query setCacheable(boolean);
    Code:
       0: aload_0
       1: iload_1
       2: invokeinterface #33,  2           // InterfaceMethod setCacheable:(Z)Lorg/hibernate/query/NativeQuery;
       7: areturn

  public default org.hibernate.Query setCacheMode(org.hibernate.CacheMode);
    Code:
       0: aload_0
       1: aload_1
       2: invokeinterface #34,  2           // InterfaceMethod setCacheMode:(Lorg/hibernate/CacheMode;)Lorg/hibernate/query/NativeQuery;
       7: areturn

  public default org.hibernate.Query setFlushMode(org.hibernate.FlushMode);
    Code:
       0: aload_0
       1: aload_1
       2: invokeinterface #35,  2           // InterfaceMethod setFlushMode:(Lorg/hibernate/FlushMode;)Lorg/hibernate/query/NativeQuery;
       7: areturn

  public default org.hibernate.Query setHibernateFlushMode(org.hibernate.FlushMode);
    Code:
       0: aload_0
       1: aload_1
       2: invokeinterface #36,  2           // InterfaceMethod setHibernateFlushMode:(Lorg/hibernate/FlushMode;)Lorg/hibernate/query/NativeQuery;
       7: areturn

  public default javax.persistence.TypedQuery setFlushMode(javax.persistence.FlushModeType);
    Code:
       0: aload_0
       1: aload_1
       2: invokeinterface #1,  2            // InterfaceMethod setFlushMode:(Ljavax/persistence/FlushModeType;)Lorg/hibernate/query/NativeQuery;
       7: areturn

  public default javax.persistence.TypedQuery setParameter(int, java.util.Date, javax.persistence.TemporalType);
    Code:
       0: aload_0
       1: iload_1
       2: aload_2
       3: aload_3
       4: invokeinterface #2,  4            // InterfaceMethod setParameter:(ILjava/util/Date;Ljavax/persistence/TemporalType;)Lorg/hibernate/query/NativeQuery;
       9: areturn

  public default javax.persistence.TypedQuery setParameter(int, java.util.Calendar, javax.persistence.TemporalType);
    Code:
       0: aload_0
       1: iload_1
       2: aload_2
       3: aload_3
       4: invokeinterface #3,  4            // InterfaceMethod setParameter:(ILjava/util/Calendar;Ljavax/persistence/TemporalType;)Lorg/hibernate/query/NativeQuery;
       9: areturn

  public default javax.persistence.TypedQuery setParameter(int, java.lang.Object);
    Code:
       0: aload_0
       1: iload_1
       2: aload_2
       3: invokeinterface #21,  3           // InterfaceMethod setParameter:(ILjava/lang/Object;)Lorg/hibernate/query/NativeQuery;
       8: areturn

  public default javax.persistence.TypedQuery setParameter(java.lang.String, java.util.Date, javax.persistence.TemporalType);
    Code:
       0: aload_0
       1: aload_1
       2: aload_2
       3: aload_3
       4: invokeinterface #4,  4            // InterfaceMethod setParameter:(Ljava/lang/String;Ljava/util/Date;Ljavax/persistence/TemporalType;)Lorg/hibernate/query/NativeQuery;
       9: areturn

  public default javax.persistence.TypedQuery setParameter(java.lang.String, java.util.Calendar, javax.persistence.TemporalType);
    Code:
       0: aload_0
       1: aload_1
       2: aload_2
       3: aload_3
       4: invokeinterface #5,  4            // InterfaceMethod setParameter:(Ljava/lang/String;Ljava/util/Calendar;Ljavax/persistence/TemporalType;)Lorg/hibernate/query/NativeQuery;
       9: areturn

  public default javax.persistence.TypedQuery setParameter(java.lang.String, java.lang.Object);
    Code:
       0: aload_0
       1: aload_1
       2: aload_2
       3: invokeinterface #22,  3           // InterfaceMethod setParameter:(Ljava/lang/String;Ljava/lang/Object;)Lorg/hibernate/query/NativeQuery;
       8: areturn

  public default javax.persistence.TypedQuery setParameter(javax.persistence.Parameter, java.util.Date, javax.persistence.TemporalType);
    Code:
       0: aload_0
       1: aload_1
       2: aload_2
       3: aload_3
       4: invokeinterface #6,  4            // InterfaceMethod setParameter:(Ljavax/persistence/Parameter;Ljava/util/Date;Ljavax/persistence/TemporalType;)Lorg/hibernate/query/NativeQuery;
       9: areturn

  public default javax.persistence.TypedQuery setParameter(javax.persistence.Parameter, java.util.Calendar, javax.persistence.TemporalType);
    Code:
       0: aload_0
       1: aload_1
       2: aload_2
       3: aload_3
       4: invokeinterface #7,  4            // InterfaceMethod setParameter:(Ljavax/persistence/Parameter;Ljava/util/Calendar;Ljavax/persistence/TemporalType;)Lorg/hibernate/query/NativeQuery;
       9: areturn

  public default javax.persistence.TypedQuery setParameter(javax.persistence.Parameter, java.lang.Object);
    Code:
       0: aload_0
       1: aload_1
       2: aload_2
       3: invokeinterface #23,  3           // InterfaceMethod setParameter:(Ljavax/persistence/Parameter;Ljava/lang/Object;)Lorg/hibernate/query/NativeQuery;
       8: areturn

  public default javax.persistence.Query setFlushMode(javax.persistence.FlushModeType);
    Code:
       0: aload_0
       1: aload_1
       2: invokeinterface #1,  2            // InterfaceMethod setFlushMode:(Ljavax/persistence/FlushModeType;)Lorg/hibernate/query/NativeQuery;
       7: areturn

  public default javax.persistence.Query setParameter(int, java.util.Date, javax.persistence.TemporalType);
    Code:
       0: aload_0
       1: iload_1
       2: aload_2
       3: aload_3
       4: invokeinterface #2,  4            // InterfaceMethod setParameter:(ILjava/util/Date;Ljavax/persistence/TemporalType;)Lorg/hibernate/query/NativeQuery;
       9: areturn

  public default javax.persistence.Query setParameter(int, java.util.Calendar, javax.persistence.TemporalType);
    Code:
       0: aload_0
       1: iload_1
       2: aload_2
       3: aload_3
       4: invokeinterface #3,  4            // InterfaceMethod setParameter:(ILjava/util/Calendar;Ljavax/persistence/TemporalType;)Lorg/hibernate/query/NativeQuery;
       9: areturn

  public default javax.persistence.Query setParameter(int, java.lang.Object);
    Code:
       0: aload_0
       1: iload_1
       2: aload_2
       3: invokeinterface #21,  3           // InterfaceMethod setParameter:(ILjava/lang/Object;)Lorg/hibernate/query/NativeQuery;
       8: areturn

  public default javax.persistence.Query setParameter(java.lang.String, java.util.Date, javax.persistence.TemporalType);
    Code:
       0: aload_0
       1: aload_1
       2: aload_2
       3: aload_3
       4: invokeinterface #4,  4            // InterfaceMethod setParameter:(Ljava/lang/String;Ljava/util/Date;Ljavax/persistence/TemporalType;)Lorg/hibernate/query/NativeQuery;
       9: areturn

  public default javax.persistence.Query setParameter(java.lang.String, java.util.Calendar, javax.persistence.TemporalType);
    Code:
       0: aload_0
       1: aload_1
       2: aload_2
       3: aload_3
       4: invokeinterface #5,  4            // InterfaceMethod setParameter:(Ljava/lang/String;Ljava/util/Calendar;Ljavax/persistence/TemporalType;)Lorg/hibernate/query/NativeQuery;
       9: areturn

  public default javax.persistence.Query setParameter(java.lang.String, java.lang.Object);
    Code:
       0: aload_0
       1: aload_1
       2: aload_2
       3: invokeinterface #22,  3           // InterfaceMethod setParameter:(Ljava/lang/String;Ljava/lang/Object;)Lorg/hibernate/query/NativeQuery;
       8: areturn

  public default javax.persistence.Query setParameter(javax.persistence.Parameter, java.util.Date, javax.persistence.TemporalType);
    Code:
       0: aload_0
       1: aload_1
       2: aload_2
       3: aload_3
       4: invokeinterface #6,  4            // InterfaceMethod setParameter:(Ljavax/persistence/Parameter;Ljava/util/Date;Ljavax/persistence/TemporalType;)Lorg/hibernate/query/NativeQuery;
       9: areturn

  public default javax.persistence.Query setParameter(javax.persistence.Parameter, java.util.Calendar, javax.persistence.TemporalType);
    Code:
       0: aload_0
       1: aload_1
       2: aload_2
       3: aload_3
       4: invokeinterface #7,  4            // InterfaceMethod setParameter:(Ljavax/persistence/Parameter;Ljava/util/Calendar;Ljavax/persistence/TemporalType;)Lorg/hibernate/query/NativeQuery;
       9: areturn

  public default javax.persistence.Query setParameter(javax.persistence.Parameter, java.lang.Object);
    Code:
       0: aload_0
       1: aload_1
       2: aload_2
       3: invokeinterface #23,  3           // InterfaceMethod setParameter:(Ljavax/persistence/Parameter;Ljava/lang/Object;)Lorg/hibernate/query/NativeQuery;
       8: areturn

  public default org.hibernate.query.CommonQueryContract setReadOnly(boolean);
    Code:
       0: aload_0
       1: iload_1
       2: invokeinterface #29,  2           // InterfaceMethod setReadOnly:(Z)Lorg/hibernate/query/NativeQuery;
       7: areturn

  public default org.hibernate.query.CommonQueryContract setFetchSize(int);
    Code:
       0: aload_0
       1: iload_1
       2: invokeinterface #30,  2           // InterfaceMethod setFetchSize:(I)Lorg/hibernate/query/NativeQuery;
       7: areturn

  public default org.hibernate.query.CommonQueryContract setTimeout(int);
    Code:
       0: aload_0
       1: iload_1
       2: invokeinterface #31,  2           // InterfaceMethod setTimeout:(I)Lorg/hibernate/query/NativeQuery;
       7: areturn

  public default org.hibernate.query.CommonQueryContract setCacheRegion(java.lang.String);
    Code:
       0: aload_0
       1: aload_1
       2: invokeinterface #32,  2           // InterfaceMethod setCacheRegion:(Ljava/lang/String;)Lorg/hibernate/query/NativeQuery;
       7: areturn

  public default org.hibernate.query.CommonQueryContract setCacheable(boolean);
    Code:
       0: aload_0
       1: iload_1
       2: invokeinterface #33,  2           // InterfaceMethod setCacheable:(Z)Lorg/hibernate/query/NativeQuery;
       7: areturn

  public default org.hibernate.query.CommonQueryContract setCacheMode(org.hibernate.CacheMode);
    Code:
       0: aload_0
       1: aload_1
       2: invokeinterface #34,  2           // InterfaceMethod setCacheMode:(Lorg/hibernate/CacheMode;)Lorg/hibernate/query/NativeQuery;
       7: areturn

  public default org.hibernate.query.CommonQueryContract setHibernateFlushMode(org.hibernate.FlushMode);
    Code:
       0: aload_0
       1: aload_1
       2: invokeinterface #36,  2           // InterfaceMethod setHibernateFlushMode:(Lorg/hibernate/FlushMode;)Lorg/hibernate/query/NativeQuery;
       7: areturn

  public default org.hibernate.query.CommonQueryContract setFlushMode(org.hibernate.FlushMode);
    Code:
       0: aload_0
       1: aload_1
       2: invokeinterface #35,  2           // InterfaceMethod setFlushMode:(Lorg/hibernate/FlushMode;)Lorg/hibernate/query/NativeQuery;
       7: areturn

  public default org.hibernate.SynchronizeableQuery addSynchronizedEntityClass(java.lang.Class) throws org.hibernate.MappingException;
    Code:
       0: aload_0
       1: aload_1
       2: invokeinterface #37,  2           // InterfaceMethod addSynchronizedEntityClass:(Ljava/lang/Class;)Lorg/hibernate/query/NativeQuery;
       7: areturn

  public default org.hibernate.SynchronizeableQuery addSynchronizedEntityName(java.lang.String) throws org.hibernate.MappingException;
    Code:
       0: aload_0
       1: aload_1
       2: invokeinterface #38,  2           // InterfaceMethod addSynchronizedEntityName:(Ljava/lang/String;)Lorg/hibernate/query/NativeQuery;
       7: areturn

  public default org.hibernate.SynchronizeableQuery addSynchronizedQuerySpace(java.lang.String);
    Code:
       0: aload_0
       1: aload_1
       2: invokeinterface #39,  2           // InterfaceMethod addSynchronizedQuerySpace:(Ljava/lang/String;)Lorg/hibernate/query/NativeQuery;
       7: areturn
}
