Compiled from "SockJSHandlerOptions.java"
public class io.vertx.ext.web.handler.sockjs.SockJSHandlerOptions {
  public static final long DEFAULT_SESSION_TIMEOUT;

  public static final boolean DEFAULT_INSERT_JSESSIONID;

  public static final long DEFAULT_HEARTBEAT_INTERVAL;

  public static final int DEFAULT_MAX_BYTES_STREAMING;

  public static final java.lang.String DEFAULT_LIBRARY_URL;

  public static final boolean DEFAULT_REGISTER_WRITE_HANDLER;

  public static final boolean DEFAULT_LOCAL_WRITE_HANDLER;

  private long sessionTimeout;

  private boolean insertJSESSIONID;

  private long heartbeatInterval;

  private int maxBytesStreaming;

  private java.lang.String libraryURL;

  private final java.util.Set<java.lang.String> disabledTransports;

  private boolean registerWriteHandler;

  private boolean localWriteHandler;

  private java.lang.String origin;

  public io.vertx.ext.web.handler.sockjs.SockJSHandlerOptions(io.vertx.ext.web.handler.sockjs.SockJSHandlerOptions);
    Code:
       0: aload_0
       1: invokespecial #1                  // Method java/lang/Object."<init>":()V
       4: aload_0
       5: new           #2                  // class java/util/HashSet
       8: dup
       9: invokespecial #3                  // Method java/util/HashSet."<init>":()V
      12: putfield      #4                  // Field disabledTransports:Ljava/util/Set;
      15: aload_0
      16: aload_1
      17: getfield      #5                  // Field sessionTimeout:J
      20: putfield      #5                  // Field sessionTimeout:J
      23: aload_0
      24: aload_1
      25: getfield      #6                  // Field insertJSESSIONID:Z
      28: putfield      #6                  // Field insertJSESSIONID:Z
      31: aload_0
      32: aload_1
      33: getfield      #7                  // Field heartbeatInterval:J
      36: putfield      #7                  // Field heartbeatInterval:J
      39: aload_0
      40: aload_1
      41: getfield      #8                  // Field maxBytesStreaming:I
      44: putfield      #8                  // Field maxBytesStreaming:I
      47: aload_0
      48: aload_1
      49: getfield      #9                  // Field libraryURL:Ljava/lang/String;
      52: putfield      #9                  // Field libraryURL:Ljava/lang/String;
      55: aload_0
      56: getfield      #4                  // Field disabledTransports:Ljava/util/Set;
      59: aload_1
      60: getfield      #4                  // Field disabledTransports:Ljava/util/Set;
      63: invokeinterface #10,  2           // InterfaceMethod java/util/Set.addAll:(Ljava/util/Collection;)Z
      68: pop
      69: aload_0
      70: aload_1
      71: getfield      #11                 // Field registerWriteHandler:Z
      74: putfield      #11                 // Field registerWriteHandler:Z
      77: aload_0
      78: aload_1
      79: getfield      #12                 // Field localWriteHandler:Z
      82: putfield      #12                 // Field localWriteHandler:Z
      85: aload_0
      86: aload_1
      87: getfield      #13                 // Field origin:Ljava/lang/String;
      90: putfield      #13                 // Field origin:Ljava/lang/String;
      93: return

  public io.vertx.ext.web.handler.sockjs.SockJSHandlerOptions();
    Code:
       0: aload_0
       1: invokespecial #1                  // Method java/lang/Object."<init>":()V
       4: aload_0
       5: new           #2                  // class java/util/HashSet
       8: dup
       9: invokespecial #3                  // Method java/util/HashSet."<init>":()V
      12: putfield      #4                  // Field disabledTransports:Ljava/util/Set;
      15: aload_0
      16: ldc2_w        #15                 // long 5000l
      19: putfield      #5                  // Field sessionTimeout:J
      22: aload_0
      23: iconst_1
      24: putfield      #6                  // Field insertJSESSIONID:Z
      27: aload_0
      28: ldc2_w        #17                 // long 25000l
      31: putfield      #7                  // Field heartbeatInterval:J
      34: aload_0
      35: ldc           #19                 // int 131072
      37: putfield      #8                  // Field maxBytesStreaming:I
      40: aload_0
      41: ldc           #20                 // String //cdn.jsdelivr.net/npm/sockjs-client@1/dist/sockjs.min.js
      43: putfield      #9                  // Field libraryURL:Ljava/lang/String;
      46: aload_0
      47: iconst_0
      48: putfield      #11                 // Field registerWriteHandler:Z
      51: aload_0
      52: iconst_1
      53: putfield      #12                 // Field localWriteHandler:Z
      56: return

  public io.vertx.ext.web.handler.sockjs.SockJSHandlerOptions(io.vertx.core.json.JsonObject);
    Code:
       0: aload_0
       1: invokespecial #1                  // Method java/lang/Object."<init>":()V
       4: aload_0
       5: new           #2                  // class java/util/HashSet
       8: dup
       9: invokespecial #3                  // Method java/util/HashSet."<init>":()V
      12: putfield      #4                  // Field disabledTransports:Ljava/util/Set;
      15: aload_0
      16: aload_1
      17: ldc           #21                 // String sessionTimeout
      19: ldc2_w        #15                 // long 5000l
      22: invokestatic  #22                 // Method java/lang/Long.valueOf:(J)Ljava/lang/Long;
      25: invokevirtual #23                 // Method io/vertx/core/json/JsonObject.getLong:(Ljava/lang/String;Ljava/lang/Long;)Ljava/lang/Long;
      28: invokevirtual #24                 // Method java/lang/Long.longValue:()J
      31: putfield      #5                  // Field sessionTimeout:J
      34: aload_0
      35: aload_1
      36: ldc           #25                 // String insertJSESSIONID
      38: iconst_1
      39: invokestatic  #26                 // Method java/lang/Boolean.valueOf:(Z)Ljava/lang/Boolean;
      42: invokevirtual #27                 // Method io/vertx/core/json/JsonObject.getBoolean:(Ljava/lang/String;Ljava/lang/Boolean;)Ljava/lang/Boolean;
      45: invokevirtual #28                 // Method java/lang/Boolean.booleanValue:()Z
      48: putfield      #6                  // Field insertJSESSIONID:Z
      51: aload_0
      52: aload_1
      53: ldc           #29                 // String heartbeatInterval
      55: ldc2_w        #17                 // long 25000l
      58: invokestatic  #22                 // Method java/lang/Long.valueOf:(J)Ljava/lang/Long;
      61: invokevirtual #23                 // Method io/vertx/core/json/JsonObject.getLong:(Ljava/lang/String;Ljava/lang/Long;)Ljava/lang/Long;
      64: invokevirtual #24                 // Method java/lang/Long.longValue:()J
      67: putfield      #7                  // Field heartbeatInterval:J
      70: aload_0
      71: aload_1
      72: ldc           #30                 // String maxBytesStreaming
      74: ldc           #19                 // int 131072
      76: invokestatic  #31                 // Method java/lang/Integer.valueOf:(I)Ljava/lang/Integer;
      79: invokevirtual #32                 // Method io/vertx/core/json/JsonObject.getInteger:(Ljava/lang/String;Ljava/lang/Integer;)Ljava/lang/Integer;
      82: invokevirtual #33                 // Method java/lang/Integer.intValue:()I
      85: putfield      #8                  // Field maxBytesStreaming:I
      88: aload_0
      89: aload_1
      90: ldc           #34                 // String libraryURL
      92: ldc           #20                 // String //cdn.jsdelivr.net/npm/sockjs-client@1/dist/sockjs.min.js
      94: invokevirtual #35                 // Method io/vertx/core/json/JsonObject.getString:(Ljava/lang/String;Ljava/lang/String;)Ljava/lang/String;
      97: putfield      #9                  // Field libraryURL:Ljava/lang/String;
     100: aload_1
     101: ldc           #36                 // String disabledTransports
     103: invokevirtual #37                 // Method io/vertx/core/json/JsonObject.getJsonArray:(Ljava/lang/String;)Lio/vertx/core/json/JsonArray;
     106: astore_2
     107: aload_2
     108: ifnull        202
     111: aload_2
     112: invokevirtual #38                 // Method io/vertx/core/json/JsonArray.iterator:()Ljava/util/Iterator;
     115: astore_3
     116: aload_3
     117: invokeinterface #39,  1           // InterfaceMethod java/util/Iterator.hasNext:()Z
     122: ifeq          202
     125: aload_3
     126: invokeinterface #40,  1           // InterfaceMethod java/util/Iterator.next:()Ljava/lang/Object;
     131: astore        4
     133: aload         4
     135: instanceof    #41                 // class java/lang/String
     138: ifeq          163
     141: aload         4
     143: checkcast     #41                 // class java/lang/String
     146: astore        5
     148: aload_0
     149: getfield      #4                  // Field disabledTransports:Ljava/util/Set;
     152: aload         5
     154: invokeinterface #42,  2           // InterfaceMethod java/util/Set.add:(Ljava/lang/Object;)Z
     159: pop
     160: goto          199
     163: new           #43                 // class java/lang/IllegalArgumentException
     166: dup
     167: new           #44                 // class java/lang/StringBuilder
     170: dup
     171: invokespecial #45                 // Method java/lang/StringBuilder."<init>":()V
     174: ldc           #46                 // String Invalid type
     176: invokevirtual #47                 // Method java/lang/StringBuilder.append:(Ljava/lang/String;)Ljava/lang/StringBuilder;
     179: aload         4
     181: invokevirtual #48                 // Method java/lang/Object.getClass:()Ljava/lang/Class;
     184: invokevirtual #49                 // Method java/lang/StringBuilder.append:(Ljava/lang/Object;)Ljava/lang/StringBuilder;
     187: ldc           #50                 // String  in disabledTransports array
     189: invokevirtual #47                 // Method java/lang/StringBuilder.append:(Ljava/lang/String;)Ljava/lang/StringBuilder;
     192: invokevirtual #51                 // Method java/lang/StringBuilder.toString:()Ljava/lang/String;
     195: invokespecial #52                 // Method java/lang/IllegalArgumentException."<init>":(Ljava/lang/String;)V
     198: athrow
     199: goto          116
     202: aload_0
     203: aload_1
     204: ldc           #53                 // String registerWriteHandler
     206: iconst_0
     207: invokestatic  #26                 // Method java/lang/Boolean.valueOf:(Z)Ljava/lang/Boolean;
     210: invokevirtual #27                 // Method io/vertx/core/json/JsonObject.getBoolean:(Ljava/lang/String;Ljava/lang/Boolean;)Ljava/lang/Boolean;
     213: invokevirtual #28                 // Method java/lang/Boolean.booleanValue:()Z
     216: putfield      #11                 // Field registerWriteHandler:Z
     219: aload_0
     220: aload_1
     221: ldc           #54                 // String localWriteHandler
     223: iconst_1
     224: invokestatic  #26                 // Method java/lang/Boolean.valueOf:(Z)Ljava/lang/Boolean;
     227: invokevirtual #27                 // Method io/vertx/core/json/JsonObject.getBoolean:(Ljava/lang/String;Ljava/lang/Boolean;)Ljava/lang/Boolean;
     230: invokevirtual #28                 // Method java/lang/Boolean.booleanValue:()Z
     233: putfield      #12                 // Field localWriteHandler:Z
     236: aload_0
     237: aload_1
     238: ldc           #55                 // String origin
     240: invokevirtual #56                 // Method io/vertx/core/json/JsonObject.getString:(Ljava/lang/String;)Ljava/lang/String;
     243: putfield      #13                 // Field origin:Ljava/lang/String;
     246: return

  public long getSessionTimeout();
    Code:
       0: aload_0
       1: getfield      #5                  // Field sessionTimeout:J
       4: lreturn

  public io.vertx.ext.web.handler.sockjs.SockJSHandlerOptions setSessionTimeout(long);
    Code:
       0: lload_1
       1: lconst_1
       2: lcmp
       3: ifge          16
       6: new           #43                 // class java/lang/IllegalArgumentException
       9: dup
      10: ldc           #57                 // String sessionTimeout must be > 0
      12: invokespecial #52                 // Method java/lang/IllegalArgumentException."<init>":(Ljava/lang/String;)V
      15: athrow
      16: aload_0
      17: lload_1
      18: putfield      #5                  // Field sessionTimeout:J
      21: aload_0
      22: areturn

  public boolean isInsertJSESSIONID();
    Code:
       0: aload_0
       1: getfield      #6                  // Field insertJSESSIONID:Z
       4: ireturn

  public io.vertx.ext.web.handler.sockjs.SockJSHandlerOptions setInsertJSESSIONID(boolean);
    Code:
       0: aload_0
       1: iload_1
       2: putfield      #6                  // Field insertJSESSIONID:Z
       5: aload_0
       6: areturn

  public long getHeartbeatInterval();
    Code:
       0: aload_0
       1: getfield      #7                  // Field heartbeatInterval:J
       4: lreturn

  public io.vertx.ext.web.handler.sockjs.SockJSHandlerOptions setHeartbeatInterval(long);
    Code:
       0: lload_1
       1: lconst_1
       2: lcmp
       3: ifge          16
       6: new           #43                 // class java/lang/IllegalArgumentException
       9: dup
      10: ldc           #58                 // String heartbeatInterval must be > 0
      12: invokespecial #52                 // Method java/lang/IllegalArgumentException."<init>":(Ljava/lang/String;)V
      15: athrow
      16: aload_0
      17: lload_1
      18: putfield      #7                  // Field heartbeatInterval:J
      21: aload_0
      22: areturn

  public int getMaxBytesStreaming();
    Code:
       0: aload_0
       1: getfield      #8                  // Field maxBytesStreaming:I
       4: ireturn

  public io.vertx.ext.web.handler.sockjs.SockJSHandlerOptions setMaxBytesStreaming(int);
    Code:
       0: iload_1
       1: iconst_1
       2: if_icmpge     15
       5: new           #43                 // class java/lang/IllegalArgumentException
       8: dup
       9: ldc           #59                 // String maxBytesStreaming must be > 0
      11: invokespecial #52                 // Method java/lang/IllegalArgumentException."<init>":(Ljava/lang/String;)V
      14: athrow
      15: aload_0
      16: iload_1
      17: putfield      #8                  // Field maxBytesStreaming:I
      20: aload_0
      21: areturn

  public java.lang.String getLibraryURL();
    Code:
       0: aload_0
       1: getfield      #9                  // Field libraryURL:Ljava/lang/String;
       4: areturn

  public io.vertx.ext.web.handler.sockjs.SockJSHandlerOptions setLibraryURL(java.lang.String);
    Code:
       0: aload_0
       1: aload_1
       2: putfield      #9                  // Field libraryURL:Ljava/lang/String;
       5: aload_0
       6: areturn

  public io.vertx.ext.web.handler.sockjs.SockJSHandlerOptions addDisabledTransport(java.lang.String);
    Code:
       0: aload_0
       1: getfield      #4                  // Field disabledTransports:Ljava/util/Set;
       4: aload_1
       5: invokeinterface #42,  2           // InterfaceMethod java/util/Set.add:(Ljava/lang/Object;)Z
      10: pop
      11: aload_0
      12: areturn

  public java.util.Set<java.lang.String> getDisabledTransports();
    Code:
       0: aload_0
       1: getfield      #4                  // Field disabledTransports:Ljava/util/Set;
       4: areturn

  public boolean isRegisterWriteHandler();
    Code:
       0: aload_0
       1: getfield      #11                 // Field registerWriteHandler:Z
       4: ireturn

  public io.vertx.ext.web.handler.sockjs.SockJSHandlerOptions setRegisterWriteHandler(boolean);
    Code:
       0: aload_0
       1: iload_1
       2: putfield      #11                 // Field registerWriteHandler:Z
       5: aload_0
       6: areturn

  public boolean isLocalWriteHandler();
    Code:
       0: aload_0
       1: getfield      #12                 // Field localWriteHandler:Z
       4: ireturn

  public io.vertx.ext.web.handler.sockjs.SockJSHandlerOptions setLocalWriteHandler(boolean);
    Code:
       0: aload_0
       1: iload_1
       2: putfield      #12                 // Field localWriteHandler:Z
       5: aload_0
       6: areturn

  public java.lang.String getOrigin();
    Code:
       0: aload_0
       1: getfield      #13                 // Field origin:Ljava/lang/String;
       4: areturn

  public io.vertx.ext.web.handler.sockjs.SockJSHandlerOptions setOrigin(java.lang.String);
    Code:
       0: aload_0
       1: aload_1
       2: putfield      #13                 // Field origin:Ljava/lang/String;
       5: aload_0
       6: areturn
}
