Compiled from "ConfigurationSidecarsResponse.java"
public abstract class org.graylog.plugins.sidecar.rest.responses.ConfigurationSidecarsResponse {
  public org.graylog.plugins.sidecar.rest.responses.ConfigurationSidecarsResponse();
    Code:
       0: aload_0
       1: invokespecial #1                  // Method java/lang/Object."<init>":()V
       4: return

  public abstract java.lang.String configurationId();

  public abstract java.util.Collection<java.lang.String> sidecarIds();

  public static org.graylog.plugins.sidecar.rest.responses.ConfigurationSidecarsResponse create(java.lang.String, java.util.Collection<java.lang.String>);
    Code:
       0: new           #2                  // class org/graylog/plugins/sidecar/rest/responses/AutoValue_ConfigurationSidecarsResponse
       3: dup
       4: aload_0
       5: aload_1
       6: invokespecial #3                  // Method org/graylog/plugins/sidecar/rest/responses/AutoValue_ConfigurationSidecarsResponse."<init>":(Ljava/lang/String;Ljava/util/Collection;)V
       9: areturn
}
