Compiled from "Cluster.java"
public final class io.grpc.xds.shaded.io.envoyproxy.envoy.api.v2.Cluster$LbSubsetConfig$LbSubsetSelector$Builder extends com.google.protobuf.GeneratedMessageV3$Builder<io.grpc.xds.shaded.io.envoyproxy.envoy.api.v2.Cluster$LbSubsetConfig$LbSubsetSelector$Builder> implements io.grpc.xds.shaded.io.envoyproxy.envoy.api.v2.Cluster$LbSubsetConfig$LbSubsetSelectorOrBuilder {
  private int bitField0_;

  private com.google.protobuf.LazyStringList keys_;

  private int fallbackPolicy_;

  private com.google.protobuf.LazyStringList fallbackKeysSubset_;

  public static final com.google.protobuf.Descriptors$Descriptor getDescriptor();
    Code:
       0: getstatic     #72                 // Field io/grpc/xds/shaded/io/envoyproxy/envoy/api/v2/ClusterProto.internal_static_envoy_api_v2_Cluster_LbSubsetConfig_LbSubsetSelector_descriptor:Lcom/google/protobuf/Descriptors$Descriptor;
       3: areturn

  protected com.google.protobuf.GeneratedMessageV3$FieldAccessorTable internalGetFieldAccessorTable();
    Code:
       0: getstatic     #78                 // Field io/grpc/xds/shaded/io/envoyproxy/envoy/api/v2/ClusterProto.internal_static_envoy_api_v2_Cluster_LbSubsetConfig_LbSubsetSelector_fieldAccessorTable:Lcom/google/protobuf/GeneratedMessageV3$FieldAccessorTable;
       3: ldc           #25                 // class io/grpc/xds/shaded/io/envoyproxy/envoy/api/v2/Cluster$LbSubsetConfig$LbSubsetSelector
       5: ldc           #2                  // class io/grpc/xds/shaded/io/envoyproxy/envoy/api/v2/Cluster$LbSubsetConfig$LbSubsetSelector$Builder
       7: invokevirtual #82                 // Method com/google/protobuf/GeneratedMessageV3$FieldAccessorTable.ensureFieldAccessorsInitialized:(Ljava/lang/Class;Ljava/lang/Class;)Lcom/google/protobuf/GeneratedMessageV3$FieldAccessorTable;
      10: areturn

  private io.grpc.xds.shaded.io.envoyproxy.envoy.api.v2.Cluster$LbSubsetConfig$LbSubsetSelector$Builder();
    Code:
       0: aload_0
       1: invokespecial #88                 // Method com/google/protobuf/GeneratedMessageV3$Builder."<init>":()V
       4: aload_0
       5: getstatic     #93                 // Field com/google/protobuf/LazyStringArrayList.EMPTY:Lcom/google/protobuf/LazyStringList;
       8: putfield      #95                 // Field keys_:Lcom/google/protobuf/LazyStringList;
      11: aload_0
      12: iconst_0
      13: putfield      #97                 // Field fallbackPolicy_:I
      16: aload_0
      17: getstatic     #93                 // Field com/google/protobuf/LazyStringArrayList.EMPTY:Lcom/google/protobuf/LazyStringList;
      20: putfield      #99                 // Field fallbackKeysSubset_:Lcom/google/protobuf/LazyStringList;
      23: aload_0
      24: invokespecial #102                // Method maybeForceBuilderInitialization:()V
      27: return

  private io.grpc.xds.shaded.io.envoyproxy.envoy.api.v2.Cluster$LbSubsetConfig$LbSubsetSelector$Builder(com.google.protobuf.GeneratedMessageV3$BuilderParent);
    Code:
       0: aload_0
       1: aload_1
       2: invokespecial #105                // Method com/google/protobuf/GeneratedMessageV3$Builder."<init>":(Lcom/google/protobuf/GeneratedMessageV3$BuilderParent;)V
       5: aload_0
       6: getstatic     #93                 // Field com/google/protobuf/LazyStringArrayList.EMPTY:Lcom/google/protobuf/LazyStringList;
       9: putfield      #95                 // Field keys_:Lcom/google/protobuf/LazyStringList;
      12: aload_0
      13: iconst_0
      14: putfield      #97                 // Field fallbackPolicy_:I
      17: aload_0
      18: getstatic     #93                 // Field com/google/protobuf/LazyStringArrayList.EMPTY:Lcom/google/protobuf/LazyStringList;
      21: putfield      #99                 // Field fallbackKeysSubset_:Lcom/google/protobuf/LazyStringList;
      24: aload_0
      25: invokespecial #102                // Method maybeForceBuilderInitialization:()V
      28: return

  private void maybeForceBuilderInitialization();
    Code:
       0: invokestatic  #111                // Method io/grpc/xds/shaded/io/envoyproxy/envoy/api/v2/Cluster$LbSubsetConfig$LbSubsetSelector.access$3300:()Z
       3: ifeq          6
       6: return

  public io.grpc.xds.shaded.io.envoyproxy.envoy.api.v2.Cluster$LbSubsetConfig$LbSubsetSelector$Builder clear();
    Code:
       0: aload_0
       1: invokespecial #116                // Method com/google/protobuf/GeneratedMessageV3$Builder.clear:()Lcom/google/protobuf/GeneratedMessageV3$Builder;
       4: pop
       5: aload_0
       6: getstatic     #93                 // Field com/google/protobuf/LazyStringArrayList.EMPTY:Lcom/google/protobuf/LazyStringList;
       9: putfield      #95                 // Field keys_:Lcom/google/protobuf/LazyStringList;
      12: aload_0
      13: aload_0
      14: getfield      #118                // Field bitField0_:I
      17: bipush        -2
      19: iand
      20: putfield      #118                // Field bitField0_:I
      23: aload_0
      24: iconst_0
      25: putfield      #97                 // Field fallbackPolicy_:I
      28: aload_0
      29: getstatic     #93                 // Field com/google/protobuf/LazyStringArrayList.EMPTY:Lcom/google/protobuf/LazyStringList;
      32: putfield      #99                 // Field fallbackKeysSubset_:Lcom/google/protobuf/LazyStringList;
      35: aload_0
      36: aload_0
      37: getfield      #118                // Field bitField0_:I
      40: bipush        -3
      42: iand
      43: putfield      #118                // Field bitField0_:I
      46: aload_0
      47: areturn

  public com.google.protobuf.Descriptors$Descriptor getDescriptorForType();
    Code:
       0: getstatic     #72                 // Field io/grpc/xds/shaded/io/envoyproxy/envoy/api/v2/ClusterProto.internal_static_envoy_api_v2_Cluster_LbSubsetConfig_LbSubsetSelector_descriptor:Lcom/google/protobuf/Descriptors$Descriptor;
       3: areturn

  public io.grpc.xds.shaded.io.envoyproxy.envoy.api.v2.Cluster$LbSubsetConfig$LbSubsetSelector getDefaultInstanceForType();
    Code:
       0: invokestatic  #124                // Method io/grpc/xds/shaded/io/envoyproxy/envoy/api/v2/Cluster$LbSubsetConfig$LbSubsetSelector.getDefaultInstance:()Lio/grpc/xds/shaded/io/envoyproxy/envoy/api/v2/Cluster$LbSubsetConfig$LbSubsetSelector;
       3: areturn

  public io.grpc.xds.shaded.io.envoyproxy.envoy.api.v2.Cluster$LbSubsetConfig$LbSubsetSelector build();
    Code:
       0: aload_0
       1: invokevirtual #128                // Method buildPartial:()Lio/grpc/xds/shaded/io/envoyproxy/envoy/api/v2/Cluster$LbSubsetConfig$LbSubsetSelector;
       4: astore_1
       5: aload_1
       6: invokevirtual #131                // Method io/grpc/xds/shaded/io/envoyproxy/envoy/api/v2/Cluster$LbSubsetConfig$LbSubsetSelector.isInitialized:()Z
       9: ifne          17
      12: aload_1
      13: invokestatic  #135                // Method newUninitializedMessageException:(Lcom/google/protobuf/Message;)Lcom/google/protobuf/UninitializedMessageException;
      16: athrow
      17: aload_1
      18: areturn

  public io.grpc.xds.shaded.io.envoyproxy.envoy.api.v2.Cluster$LbSubsetConfig$LbSubsetSelector buildPartial();
    Code:
       0: new           #25                 // class io/grpc/xds/shaded/io/envoyproxy/envoy/api/v2/Cluster$LbSubsetConfig$LbSubsetSelector
       3: dup
       4: aload_0
       5: aconst_null
       6: invokespecial #140                // Method io/grpc/xds/shaded/io/envoyproxy/envoy/api/v2/Cluster$LbSubsetConfig$LbSubsetSelector."<init>":(Lcom/google/protobuf/GeneratedMessageV3$Builder;Lio/grpc/xds/shaded/io/envoyproxy/envoy/api/v2/Cluster$1;)V
       9: astore_1
      10: aload_0
      11: getfield      #118                // Field bitField0_:I
      14: istore_2
      15: aload_0
      16: getfield      #118                // Field bitField0_:I
      19: iconst_1
      20: iand
      21: ifeq          48
      24: aload_0
      25: aload_0
      26: getfield      #95                 // Field keys_:Lcom/google/protobuf/LazyStringList;
      29: invokeinterface #146,  1          // InterfaceMethod com/google/protobuf/LazyStringList.getUnmodifiableView:()Lcom/google/protobuf/LazyStringList;
      34: putfield      #95                 // Field keys_:Lcom/google/protobuf/LazyStringList;
      37: aload_0
      38: aload_0
      39: getfield      #118                // Field bitField0_:I
      42: bipush        -2
      44: iand
      45: putfield      #118                // Field bitField0_:I
      48: aload_1
      49: aload_0
      50: getfield      #95                 // Field keys_:Lcom/google/protobuf/LazyStringList;
      53: invokestatic  #150                // Method io/grpc/xds/shaded/io/envoyproxy/envoy/api/v2/Cluster$LbSubsetConfig$LbSubsetSelector.access$3502:(Lio/grpc/xds/shaded/io/envoyproxy/envoy/api/v2/Cluster$LbSubsetConfig$LbSubsetSelector;Lcom/google/protobuf/LazyStringList;)Lcom/google/protobuf/LazyStringList;
      56: pop
      57: aload_1
      58: aload_0
      59: getfield      #97                 // Field fallbackPolicy_:I
      62: invokestatic  #154                // Method io/grpc/xds/shaded/io/envoyproxy/envoy/api/v2/Cluster$LbSubsetConfig$LbSubsetSelector.access$3602:(Lio/grpc/xds/shaded/io/envoyproxy/envoy/api/v2/Cluster$LbSubsetConfig$LbSubsetSelector;I)I
      65: pop
      66: aload_0
      67: getfield      #118                // Field bitField0_:I
      70: iconst_2
      71: iand
      72: ifeq          99
      75: aload_0
      76: aload_0
      77: getfield      #99                 // Field fallbackKeysSubset_:Lcom/google/protobuf/LazyStringList;
      80: invokeinterface #146,  1          // InterfaceMethod com/google/protobuf/LazyStringList.getUnmodifiableView:()Lcom/google/protobuf/LazyStringList;
      85: putfield      #99                 // Field fallbackKeysSubset_:Lcom/google/protobuf/LazyStringList;
      88: aload_0
      89: aload_0
      90: getfield      #118                // Field bitField0_:I
      93: bipush        -3
      95: iand
      96: putfield      #118                // Field bitField0_:I
      99: aload_1
     100: aload_0
     101: getfield      #99                 // Field fallbackKeysSubset_:Lcom/google/protobuf/LazyStringList;
     104: invokestatic  #157                // Method io/grpc/xds/shaded/io/envoyproxy/envoy/api/v2/Cluster$LbSubsetConfig$LbSubsetSelector.access$3702:(Lio/grpc/xds/shaded/io/envoyproxy/envoy/api/v2/Cluster$LbSubsetConfig$LbSubsetSelector;Lcom/google/protobuf/LazyStringList;)Lcom/google/protobuf/LazyStringList;
     107: pop
     108: aload_0
     109: invokevirtual #160                // Method onBuilt:()V
     112: aload_1
     113: areturn

  public io.grpc.xds.shaded.io.envoyproxy.envoy.api.v2.Cluster$LbSubsetConfig$LbSubsetSelector$Builder clone();
    Code:
       0: aload_0
       1: invokespecial #164                // Method com/google/protobuf/GeneratedMessageV3$Builder.clone:()Lcom/google/protobuf/GeneratedMessageV3$Builder;
       4: checkcast     #2                  // class io/grpc/xds/shaded/io/envoyproxy/envoy/api/v2/Cluster$LbSubsetConfig$LbSubsetSelector$Builder
       7: areturn

  public io.grpc.xds.shaded.io.envoyproxy.envoy.api.v2.Cluster$LbSubsetConfig$LbSubsetSelector$Builder setField(com.google.protobuf.Descriptors$FieldDescriptor, java.lang.Object);
    Code:
       0: aload_0
       1: aload_1
       2: aload_2
       3: invokespecial #169                // Method com/google/protobuf/GeneratedMessageV3$Builder.setField:(Lcom/google/protobuf/Descriptors$FieldDescriptor;Ljava/lang/Object;)Lcom/google/protobuf/GeneratedMessageV3$Builder;
       6: checkcast     #2                  // class io/grpc/xds/shaded/io/envoyproxy/envoy/api/v2/Cluster$LbSubsetConfig$LbSubsetSelector$Builder
       9: areturn

  public io.grpc.xds.shaded.io.envoyproxy.envoy.api.v2.Cluster$LbSubsetConfig$LbSubsetSelector$Builder clearField(com.google.protobuf.Descriptors$FieldDescriptor);
    Code:
       0: aload_0
       1: aload_1
       2: invokespecial #178                // Method com/google/protobuf/GeneratedMessageV3$Builder.clearField:(Lcom/google/protobuf/Descriptors$FieldDescriptor;)Lcom/google/protobuf/GeneratedMessageV3$Builder;
       5: checkcast     #2                  // class io/grpc/xds/shaded/io/envoyproxy/envoy/api/v2/Cluster$LbSubsetConfig$LbSubsetSelector$Builder
       8: areturn

  public io.grpc.xds.shaded.io.envoyproxy.envoy.api.v2.Cluster$LbSubsetConfig$LbSubsetSelector$Builder clearOneof(com.google.protobuf.Descriptors$OneofDescriptor);
    Code:
       0: aload_0
       1: aload_1
       2: invokespecial #183                // Method com/google/protobuf/GeneratedMessageV3$Builder.clearOneof:(Lcom/google/protobuf/Descriptors$OneofDescriptor;)Lcom/google/protobuf/GeneratedMessageV3$Builder;
       5: checkcast     #2                  // class io/grpc/xds/shaded/io/envoyproxy/envoy/api/v2/Cluster$LbSubsetConfig$LbSubsetSelector$Builder
       8: areturn

  public io.grpc.xds.shaded.io.envoyproxy.envoy.api.v2.Cluster$LbSubsetConfig$LbSubsetSelector$Builder setRepeatedField(com.google.protobuf.Descriptors$FieldDescriptor, int, java.lang.Object);
    Code:
       0: aload_0
       1: aload_1
       2: iload_2
       3: aload_3
       4: invokespecial #190                // Method com/google/protobuf/GeneratedMessageV3$Builder.setRepeatedField:(Lcom/google/protobuf/Descriptors$FieldDescriptor;ILjava/lang/Object;)Lcom/google/protobuf/GeneratedMessageV3$Builder;
       7: checkcast     #2                  // class io/grpc/xds/shaded/io/envoyproxy/envoy/api/v2/Cluster$LbSubsetConfig$LbSubsetSelector$Builder
      10: areturn

  public io.grpc.xds.shaded.io.envoyproxy.envoy.api.v2.Cluster$LbSubsetConfig$LbSubsetSelector$Builder addRepeatedField(com.google.protobuf.Descriptors$FieldDescriptor, java.lang.Object);
    Code:
       0: aload_0
       1: aload_1
       2: aload_2
       3: invokespecial #194                // Method com/google/protobuf/GeneratedMessageV3$Builder.addRepeatedField:(Lcom/google/protobuf/Descriptors$FieldDescriptor;Ljava/lang/Object;)Lcom/google/protobuf/GeneratedMessageV3$Builder;
       6: checkcast     #2                  // class io/grpc/xds/shaded/io/envoyproxy/envoy/api/v2/Cluster$LbSubsetConfig$LbSubsetSelector$Builder
       9: areturn

  public io.grpc.xds.shaded.io.envoyproxy.envoy.api.v2.Cluster$LbSubsetConfig$LbSubsetSelector$Builder mergeFrom(com.google.protobuf.Message);
    Code:
       0: aload_1
       1: instanceof    #25                 // class io/grpc/xds/shaded/io/envoyproxy/envoy/api/v2/Cluster$LbSubsetConfig$LbSubsetSelector
       4: ifeq          16
       7: aload_0
       8: aload_1
       9: checkcast     #25                 // class io/grpc/xds/shaded/io/envoyproxy/envoy/api/v2/Cluster$LbSubsetConfig$LbSubsetSelector
      12: invokevirtual #199                // Method mergeFrom:(Lio/grpc/xds/shaded/io/envoyproxy/envoy/api/v2/Cluster$LbSubsetConfig$LbSubsetSelector;)Lio/grpc/xds/shaded/io/envoyproxy/envoy/api/v2/Cluster$LbSubsetConfig$LbSubsetSelector$Builder;
      15: areturn
      16: aload_0
      17: aload_1
      18: invokespecial #202                // Method com/google/protobuf/GeneratedMessageV3$Builder.mergeFrom:(Lcom/google/protobuf/Message;)Lcom/google/protobuf/AbstractMessage$Builder;
      21: pop
      22: aload_0
      23: areturn

  public io.grpc.xds.shaded.io.envoyproxy.envoy.api.v2.Cluster$LbSubsetConfig$LbSubsetSelector$Builder mergeFrom(io.grpc.xds.shaded.io.envoyproxy.envoy.api.v2.Cluster$LbSubsetConfig$LbSubsetSelector);
    Code:
       0: aload_1
       1: invokestatic  #124                // Method io/grpc/xds/shaded/io/envoyproxy/envoy/api/v2/Cluster$LbSubsetConfig$LbSubsetSelector.getDefaultInstance:()Lio/grpc/xds/shaded/io/envoyproxy/envoy/api/v2/Cluster$LbSubsetConfig$LbSubsetSelector;
       4: if_acmpne     9
       7: aload_0
       8: areturn
       9: aload_1
      10: invokestatic  #208                // Method io/grpc/xds/shaded/io/envoyproxy/envoy/api/v2/Cluster$LbSubsetConfig$LbSubsetSelector.access$3500:(Lio/grpc/xds/shaded/io/envoyproxy/envoy/api/v2/Cluster$LbSubsetConfig$LbSubsetSelector;)Lcom/google/protobuf/LazyStringList;
      13: invokeinterface #211,  1          // InterfaceMethod com/google/protobuf/LazyStringList.isEmpty:()Z
      18: ifne          77
      21: aload_0
      22: getfield      #95                 // Field keys_:Lcom/google/protobuf/LazyStringList;
      25: invokeinterface #211,  1          // InterfaceMethod com/google/protobuf/LazyStringList.isEmpty:()Z
      30: ifeq          55
      33: aload_0
      34: aload_1
      35: invokestatic  #208                // Method io/grpc/xds/shaded/io/envoyproxy/envoy/api/v2/Cluster$LbSubsetConfig$LbSubsetSelector.access$3500:(Lio/grpc/xds/shaded/io/envoyproxy/envoy/api/v2/Cluster$LbSubsetConfig$LbSubsetSelector;)Lcom/google/protobuf/LazyStringList;
      38: putfield      #95                 // Field keys_:Lcom/google/protobuf/LazyStringList;
      41: aload_0
      42: aload_0
      43: getfield      #118                // Field bitField0_:I
      46: bipush        -2
      48: iand
      49: putfield      #118                // Field bitField0_:I
      52: goto          73
      55: aload_0
      56: invokespecial #214                // Method ensureKeysIsMutable:()V
      59: aload_0
      60: getfield      #95                 // Field keys_:Lcom/google/protobuf/LazyStringList;
      63: aload_1
      64: invokestatic  #208                // Method io/grpc/xds/shaded/io/envoyproxy/envoy/api/v2/Cluster$LbSubsetConfig$LbSubsetSelector.access$3500:(Lio/grpc/xds/shaded/io/envoyproxy/envoy/api/v2/Cluster$LbSubsetConfig$LbSubsetSelector;)Lcom/google/protobuf/LazyStringList;
      67: invokeinterface #218,  2          // InterfaceMethod com/google/protobuf/LazyStringList.addAll:(Ljava/util/Collection;)Z
      72: pop
      73: aload_0
      74: invokevirtual #221                // Method onChanged:()V
      77: aload_1
      78: invokestatic  #225                // Method io/grpc/xds/shaded/io/envoyproxy/envoy/api/v2/Cluster$LbSubsetConfig$LbSubsetSelector.access$3600:(Lio/grpc/xds/shaded/io/envoyproxy/envoy/api/v2/Cluster$LbSubsetConfig$LbSubsetSelector;)I
      81: ifeq          93
      84: aload_0
      85: aload_1
      86: invokevirtual #229                // Method io/grpc/xds/shaded/io/envoyproxy/envoy/api/v2/Cluster$LbSubsetConfig$LbSubsetSelector.getFallbackPolicyValue:()I
      89: invokevirtual #233                // Method setFallbackPolicyValue:(I)Lio/grpc/xds/shaded/io/envoyproxy/envoy/api/v2/Cluster$LbSubsetConfig$LbSubsetSelector$Builder;
      92: pop
      93: aload_1
      94: invokestatic  #236                // Method io/grpc/xds/shaded/io/envoyproxy/envoy/api/v2/Cluster$LbSubsetConfig$LbSubsetSelector.access$3700:(Lio/grpc/xds/shaded/io/envoyproxy/envoy/api/v2/Cluster$LbSubsetConfig$LbSubsetSelector;)Lcom/google/protobuf/LazyStringList;
      97: invokeinterface #211,  1          // InterfaceMethod com/google/protobuf/LazyStringList.isEmpty:()Z
     102: ifne          161
     105: aload_0
     106: getfield      #99                 // Field fallbackKeysSubset_:Lcom/google/protobuf/LazyStringList;
     109: invokeinterface #211,  1          // InterfaceMethod com/google/protobuf/LazyStringList.isEmpty:()Z
     114: ifeq          139
     117: aload_0
     118: aload_1
     119: invokestatic  #236                // Method io/grpc/xds/shaded/io/envoyproxy/envoy/api/v2/Cluster$LbSubsetConfig$LbSubsetSelector.access$3700:(Lio/grpc/xds/shaded/io/envoyproxy/envoy/api/v2/Cluster$LbSubsetConfig$LbSubsetSelector;)Lcom/google/protobuf/LazyStringList;
     122: putfield      #99                 // Field fallbackKeysSubset_:Lcom/google/protobuf/LazyStringList;
     125: aload_0
     126: aload_0
     127: getfield      #118                // Field bitField0_:I
     130: bipush        -3
     132: iand
     133: putfield      #118                // Field bitField0_:I
     136: goto          157
     139: aload_0
     140: invokespecial #239                // Method ensureFallbackKeysSubsetIsMutable:()V
     143: aload_0
     144: getfield      #99                 // Field fallbackKeysSubset_:Lcom/google/protobuf/LazyStringList;
     147: aload_1
     148: invokestatic  #236                // Method io/grpc/xds/shaded/io/envoyproxy/envoy/api/v2/Cluster$LbSubsetConfig$LbSubsetSelector.access$3700:(Lio/grpc/xds/shaded/io/envoyproxy/envoy/api/v2/Cluster$LbSubsetConfig$LbSubsetSelector;)Lcom/google/protobuf/LazyStringList;
     151: invokeinterface #218,  2          // InterfaceMethod com/google/protobuf/LazyStringList.addAll:(Ljava/util/Collection;)Z
     156: pop
     157: aload_0
     158: invokevirtual #221                // Method onChanged:()V
     161: aload_0
     162: aload_1
     163: invokestatic  #243                // Method io/grpc/xds/shaded/io/envoyproxy/envoy/api/v2/Cluster$LbSubsetConfig$LbSubsetSelector.access$3800:(Lio/grpc/xds/shaded/io/envoyproxy/envoy/api/v2/Cluster$LbSubsetConfig$LbSubsetSelector;)Lcom/google/protobuf/UnknownFieldSet;
     166: invokevirtual #247                // Method mergeUnknownFields:(Lcom/google/protobuf/UnknownFieldSet;)Lio/grpc/xds/shaded/io/envoyproxy/envoy/api/v2/Cluster$LbSubsetConfig$LbSubsetSelector$Builder;
     169: pop
     170: aload_0
     171: invokevirtual #221                // Method onChanged:()V
     174: aload_0
     175: areturn

  public final boolean isInitialized();
    Code:
       0: iconst_1
       1: ireturn

  public io.grpc.xds.shaded.io.envoyproxy.envoy.api.v2.Cluster$LbSubsetConfig$LbSubsetSelector$Builder mergeFrom(com.google.protobuf.CodedInputStream, com.google.protobuf.ExtensionRegistryLite) throws java.io.IOException;
    Code:
       0: aconst_null
       1: astore_3
       2: invokestatic  #256                // Method io/grpc/xds/shaded/io/envoyproxy/envoy/api/v2/Cluster$LbSubsetConfig$LbSubsetSelector.access$3900:()Lcom/google/protobuf/Parser;
       5: aload_1
       6: aload_2
       7: invokeinterface #262,  3          // InterfaceMethod com/google/protobuf/Parser.parsePartialFrom:(Lcom/google/protobuf/CodedInputStream;Lcom/google/protobuf/ExtensionRegistryLite;)Ljava/lang/Object;
      12: checkcast     #25                 // class io/grpc/xds/shaded/io/envoyproxy/envoy/api/v2/Cluster$LbSubsetConfig$LbSubsetSelector
      15: astore_3
      16: aload_3
      17: ifnull        61
      20: aload_0
      21: aload_3
      22: invokevirtual #199                // Method mergeFrom:(Lio/grpc/xds/shaded/io/envoyproxy/envoy/api/v2/Cluster$LbSubsetConfig$LbSubsetSelector;)Lio/grpc/xds/shaded/io/envoyproxy/envoy/api/v2/Cluster$LbSubsetConfig$LbSubsetSelector$Builder;
      25: pop
      26: goto          61
      29: astore        4
      31: aload         4
      33: invokevirtual #270                // Method com/google/protobuf/InvalidProtocolBufferException.getUnfinishedMessage:()Lcom/google/protobuf/MessageLite;
      36: checkcast     #25                 // class io/grpc/xds/shaded/io/envoyproxy/envoy/api/v2/Cluster$LbSubsetConfig$LbSubsetSelector
      39: astore_3
      40: aload         4
      42: invokevirtual #274                // Method com/google/protobuf/InvalidProtocolBufferException.unwrapIOException:()Ljava/io/IOException;
      45: athrow
      46: astore        5
      48: aload_3
      49: ifnull        58
      52: aload_0
      53: aload_3
      54: invokevirtual #199                // Method mergeFrom:(Lio/grpc/xds/shaded/io/envoyproxy/envoy/api/v2/Cluster$LbSubsetConfig$LbSubsetSelector;)Lio/grpc/xds/shaded/io/envoyproxy/envoy/api/v2/Cluster$LbSubsetConfig$LbSubsetSelector$Builder;
      57: pop
      58: aload         5
      60: athrow
      61: aload_0
      62: areturn
    Exception table:
       from    to  target type
           2    16    29   Class com/google/protobuf/InvalidProtocolBufferException
           2    16    46   any
          29    48    46   any

  private void ensureKeysIsMutable();
    Code:
       0: aload_0
       1: getfield      #118                // Field bitField0_:I
       4: iconst_1
       5: iand
       6: ifne          34
       9: aload_0
      10: new           #90                 // class com/google/protobuf/LazyStringArrayList
      13: dup
      14: aload_0
      15: getfield      #95                 // Field keys_:Lcom/google/protobuf/LazyStringList;
      18: invokespecial #286                // Method com/google/protobuf/LazyStringArrayList."<init>":(Lcom/google/protobuf/LazyStringList;)V
      21: putfield      #95                 // Field keys_:Lcom/google/protobuf/LazyStringList;
      24: aload_0
      25: dup
      26: getfield      #118                // Field bitField0_:I
      29: iconst_1
      30: ior
      31: putfield      #118                // Field bitField0_:I
      34: return

  public com.google.protobuf.ProtocolStringList getKeysList();
    Code:
       0: aload_0
       1: getfield      #95                 // Field keys_:Lcom/google/protobuf/LazyStringList;
       4: invokeinterface #146,  1          // InterfaceMethod com/google/protobuf/LazyStringList.getUnmodifiableView:()Lcom/google/protobuf/LazyStringList;
       9: areturn

  public int getKeysCount();
    Code:
       0: aload_0
       1: getfield      #95                 // Field keys_:Lcom/google/protobuf/LazyStringList;
       4: invokeinterface #292,  1          // InterfaceMethod com/google/protobuf/LazyStringList.size:()I
       9: ireturn

  public java.lang.String getKeys(int);
    Code:
       0: aload_0
       1: getfield      #95                 // Field keys_:Lcom/google/protobuf/LazyStringList;
       4: iload_1
       5: invokeinterface #298,  2          // InterfaceMethod com/google/protobuf/LazyStringList.get:(I)Ljava/lang/Object;
      10: checkcast     #300                // class java/lang/String
      13: areturn

  public com.google.protobuf.ByteString getKeysBytes(int);
    Code:
       0: aload_0
       1: getfield      #95                 // Field keys_:Lcom/google/protobuf/LazyStringList;
       4: iload_1
       5: invokeinterface #305,  2          // InterfaceMethod com/google/protobuf/LazyStringList.getByteString:(I)Lcom/google/protobuf/ByteString;
      10: areturn

  public io.grpc.xds.shaded.io.envoyproxy.envoy.api.v2.Cluster$LbSubsetConfig$LbSubsetSelector$Builder setKeys(int, java.lang.String);
    Code:
       0: aload_2
       1: ifnonnull     12
       4: new           #309                // class java/lang/NullPointerException
       7: dup
       8: invokespecial #310                // Method java/lang/NullPointerException."<init>":()V
      11: athrow
      12: aload_0
      13: invokespecial #214                // Method ensureKeysIsMutable:()V
      16: aload_0
      17: getfield      #95                 // Field keys_:Lcom/google/protobuf/LazyStringList;
      20: iload_1
      21: aload_2
      22: invokeinterface #314,  3          // InterfaceMethod com/google/protobuf/LazyStringList.set:(ILjava/lang/Object;)Ljava/lang/Object;
      27: pop
      28: aload_0
      29: invokevirtual #221                // Method onChanged:()V
      32: aload_0
      33: areturn

  public io.grpc.xds.shaded.io.envoyproxy.envoy.api.v2.Cluster$LbSubsetConfig$LbSubsetSelector$Builder addKeys(java.lang.String);
    Code:
       0: aload_1
       1: ifnonnull     12
       4: new           #309                // class java/lang/NullPointerException
       7: dup
       8: invokespecial #310                // Method java/lang/NullPointerException."<init>":()V
      11: athrow
      12: aload_0
      13: invokespecial #214                // Method ensureKeysIsMutable:()V
      16: aload_0
      17: getfield      #95                 // Field keys_:Lcom/google/protobuf/LazyStringList;
      20: aload_1
      21: invokeinterface #321,  2          // InterfaceMethod com/google/protobuf/LazyStringList.add:(Ljava/lang/Object;)Z
      26: pop
      27: aload_0
      28: invokevirtual #221                // Method onChanged:()V
      31: aload_0
      32: areturn

  public io.grpc.xds.shaded.io.envoyproxy.envoy.api.v2.Cluster$LbSubsetConfig$LbSubsetSelector$Builder addAllKeys(java.lang.Iterable<java.lang.String>);
    Code:
       0: aload_0
       1: invokespecial #214                // Method ensureKeysIsMutable:()V
       4: aload_1
       5: aload_0
       6: getfield      #95                 // Field keys_:Lcom/google/protobuf/LazyStringList;
       9: invokestatic  #327                // Method com/google/protobuf/AbstractMessageLite$Builder.addAll:(Ljava/lang/Iterable;Ljava/util/List;)V
      12: aload_0
      13: invokevirtual #221                // Method onChanged:()V
      16: aload_0
      17: areturn

  public io.grpc.xds.shaded.io.envoyproxy.envoy.api.v2.Cluster$LbSubsetConfig$LbSubsetSelector$Builder clearKeys();
    Code:
       0: aload_0
       1: getstatic     #93                 // Field com/google/protobuf/LazyStringArrayList.EMPTY:Lcom/google/protobuf/LazyStringList;
       4: putfield      #95                 // Field keys_:Lcom/google/protobuf/LazyStringList;
       7: aload_0
       8: aload_0
       9: getfield      #118                // Field bitField0_:I
      12: bipush        -2
      14: iand
      15: putfield      #118                // Field bitField0_:I
      18: aload_0
      19: invokevirtual #221                // Method onChanged:()V
      22: aload_0
      23: areturn

  public io.grpc.xds.shaded.io.envoyproxy.envoy.api.v2.Cluster$LbSubsetConfig$LbSubsetSelector$Builder addKeysBytes(com.google.protobuf.ByteString);
    Code:
       0: aload_1
       1: ifnonnull     12
       4: new           #309                // class java/lang/NullPointerException
       7: dup
       8: invokespecial #310                // Method java/lang/NullPointerException."<init>":()V
      11: athrow
      12: aload_1
      13: invokestatic  #337                // Method io/grpc/xds/shaded/io/envoyproxy/envoy/api/v2/Cluster$LbSubsetConfig$LbSubsetSelector.access$4000:(Lcom/google/protobuf/ByteString;)V
      16: aload_0
      17: invokespecial #214                // Method ensureKeysIsMutable:()V
      20: aload_0
      21: getfield      #95                 // Field keys_:Lcom/google/protobuf/LazyStringList;
      24: aload_1
      25: invokeinterface #339,  2          // InterfaceMethod com/google/protobuf/LazyStringList.add:(Lcom/google/protobuf/ByteString;)V
      30: aload_0
      31: invokevirtual #221                // Method onChanged:()V
      34: aload_0
      35: areturn

  public int getFallbackPolicyValue();
    Code:
       0: aload_0
       1: getfield      #97                 // Field fallbackPolicy_:I
       4: ireturn

  public io.grpc.xds.shaded.io.envoyproxy.envoy.api.v2.Cluster$LbSubsetConfig$LbSubsetSelector$Builder setFallbackPolicyValue(int);
    Code:
       0: aload_0
       1: iload_1
       2: putfield      #97                 // Field fallbackPolicy_:I
       5: aload_0
       6: invokevirtual #221                // Method onChanged:()V
       9: aload_0
      10: areturn

  public io.grpc.xds.shaded.io.envoyproxy.envoy.api.v2.Cluster$LbSubsetConfig$LbSubsetSelector$LbSubsetSelectorFallbackPolicy getFallbackPolicy();
    Code:
       0: aload_0
       1: getfield      #97                 // Field fallbackPolicy_:I
       4: invokestatic  #346                // Method io/grpc/xds/shaded/io/envoyproxy/envoy/api/v2/Cluster$LbSubsetConfig$LbSubsetSelector$LbSubsetSelectorFallbackPolicy.valueOf:(I)Lio/grpc/xds/shaded/io/envoyproxy/envoy/api/v2/Cluster$LbSubsetConfig$LbSubsetSelector$LbSubsetSelectorFallbackPolicy;
       7: astore_1
       8: aload_1
       9: ifnonnull     18
      12: getstatic     #350                // Field io/grpc/xds/shaded/io/envoyproxy/envoy/api/v2/Cluster$LbSubsetConfig$LbSubsetSelector$LbSubsetSelectorFallbackPolicy.UNRECOGNIZED:Lio/grpc/xds/shaded/io/envoyproxy/envoy/api/v2/Cluster$LbSubsetConfig$LbSubsetSelector$LbSubsetSelectorFallbackPolicy;
      15: goto          19
      18: aload_1
      19: areturn

  public io.grpc.xds.shaded.io.envoyproxy.envoy.api.v2.Cluster$LbSubsetConfig$LbSubsetSelector$Builder setFallbackPolicy(io.grpc.xds.shaded.io.envoyproxy.envoy.api.v2.Cluster$LbSubsetConfig$LbSubsetSelector$LbSubsetSelectorFallbackPolicy);
    Code:
       0: aload_1
       1: ifnonnull     12
       4: new           #309                // class java/lang/NullPointerException
       7: dup
       8: invokespecial #310                // Method java/lang/NullPointerException."<init>":()V
      11: athrow
      12: aload_0
      13: aload_1
      14: invokevirtual #355                // Method io/grpc/xds/shaded/io/envoyproxy/envoy/api/v2/Cluster$LbSubsetConfig$LbSubsetSelector$LbSubsetSelectorFallbackPolicy.getNumber:()I
      17: putfield      #97                 // Field fallbackPolicy_:I
      20: aload_0
      21: invokevirtual #221                // Method onChanged:()V
      24: aload_0
      25: areturn

  public io.grpc.xds.shaded.io.envoyproxy.envoy.api.v2.Cluster$LbSubsetConfig$LbSubsetSelector$Builder clearFallbackPolicy();
    Code:
       0: aload_0
       1: iconst_0
       2: putfield      #97                 // Field fallbackPolicy_:I
       5: aload_0
       6: invokevirtual #221                // Method onChanged:()V
       9: aload_0
      10: areturn

  private void ensureFallbackKeysSubsetIsMutable();
    Code:
       0: aload_0
       1: getfield      #118                // Field bitField0_:I
       4: iconst_2
       5: iand
       6: ifne          34
       9: aload_0
      10: new           #90                 // class com/google/protobuf/LazyStringArrayList
      13: dup
      14: aload_0
      15: getfield      #99                 // Field fallbackKeysSubset_:Lcom/google/protobuf/LazyStringList;
      18: invokespecial #286                // Method com/google/protobuf/LazyStringArrayList."<init>":(Lcom/google/protobuf/LazyStringList;)V
      21: putfield      #99                 // Field fallbackKeysSubset_:Lcom/google/protobuf/LazyStringList;
      24: aload_0
      25: dup
      26: getfield      #118                // Field bitField0_:I
      29: iconst_2
      30: ior
      31: putfield      #118                // Field bitField0_:I
      34: return

  public com.google.protobuf.ProtocolStringList getFallbackKeysSubsetList();
    Code:
       0: aload_0
       1: getfield      #99                 // Field fallbackKeysSubset_:Lcom/google/protobuf/LazyStringList;
       4: invokeinterface #146,  1          // InterfaceMethod com/google/protobuf/LazyStringList.getUnmodifiableView:()Lcom/google/protobuf/LazyStringList;
       9: areturn

  public int getFallbackKeysSubsetCount();
    Code:
       0: aload_0
       1: getfield      #99                 // Field fallbackKeysSubset_:Lcom/google/protobuf/LazyStringList;
       4: invokeinterface #292,  1          // InterfaceMethod com/google/protobuf/LazyStringList.size:()I
       9: ireturn

  public java.lang.String getFallbackKeysSubset(int);
    Code:
       0: aload_0
       1: getfield      #99                 // Field fallbackKeysSubset_:Lcom/google/protobuf/LazyStringList;
       4: iload_1
       5: invokeinterface #298,  2          // InterfaceMethod com/google/protobuf/LazyStringList.get:(I)Ljava/lang/Object;
      10: checkcast     #300                // class java/lang/String
      13: areturn

  public com.google.protobuf.ByteString getFallbackKeysSubsetBytes(int);
    Code:
       0: aload_0
       1: getfield      #99                 // Field fallbackKeysSubset_:Lcom/google/protobuf/LazyStringList;
       4: iload_1
       5: invokeinterface #305,  2          // InterfaceMethod com/google/protobuf/LazyStringList.getByteString:(I)Lcom/google/protobuf/ByteString;
      10: areturn

  public io.grpc.xds.shaded.io.envoyproxy.envoy.api.v2.Cluster$LbSubsetConfig$LbSubsetSelector$Builder setFallbackKeysSubset(int, java.lang.String);
    Code:
       0: aload_2
       1: ifnonnull     12
       4: new           #309                // class java/lang/NullPointerException
       7: dup
       8: invokespecial #310                // Method java/lang/NullPointerException."<init>":()V
      11: athrow
      12: aload_0
      13: invokespecial #239                // Method ensureFallbackKeysSubsetIsMutable:()V
      16: aload_0
      17: getfield      #99                 // Field fallbackKeysSubset_:Lcom/google/protobuf/LazyStringList;
      20: iload_1
      21: aload_2
      22: invokeinterface #314,  3          // InterfaceMethod com/google/protobuf/LazyStringList.set:(ILjava/lang/Object;)Ljava/lang/Object;
      27: pop
      28: aload_0
      29: invokevirtual #221                // Method onChanged:()V
      32: aload_0
      33: areturn

  public io.grpc.xds.shaded.io.envoyproxy.envoy.api.v2.Cluster$LbSubsetConfig$LbSubsetSelector$Builder addFallbackKeysSubset(java.lang.String);
    Code:
       0: aload_1
       1: ifnonnull     12
       4: new           #309                // class java/lang/NullPointerException
       7: dup
       8: invokespecial #310                // Method java/lang/NullPointerException."<init>":()V
      11: athrow
      12: aload_0
      13: invokespecial #239                // Method ensureFallbackKeysSubsetIsMutable:()V
      16: aload_0
      17: getfield      #99                 // Field fallbackKeysSubset_:Lcom/google/protobuf/LazyStringList;
      20: aload_1
      21: invokeinterface #321,  2          // InterfaceMethod com/google/protobuf/LazyStringList.add:(Ljava/lang/Object;)Z
      26: pop
      27: aload_0
      28: invokevirtual #221                // Method onChanged:()V
      31: aload_0
      32: areturn

  public io.grpc.xds.shaded.io.envoyproxy.envoy.api.v2.Cluster$LbSubsetConfig$LbSubsetSelector$Builder addAllFallbackKeysSubset(java.lang.Iterable<java.lang.String>);
    Code:
       0: aload_0
       1: invokespecial #239                // Method ensureFallbackKeysSubsetIsMutable:()V
       4: aload_1
       5: aload_0
       6: getfield      #99                 // Field fallbackKeysSubset_:Lcom/google/protobuf/LazyStringList;
       9: invokestatic  #327                // Method com/google/protobuf/AbstractMessageLite$Builder.addAll:(Ljava/lang/Iterable;Ljava/util/List;)V
      12: aload_0
      13: invokevirtual #221                // Method onChanged:()V
      16: aload_0
      17: areturn

  public io.grpc.xds.shaded.io.envoyproxy.envoy.api.v2.Cluster$LbSubsetConfig$LbSubsetSelector$Builder clearFallbackKeysSubset();
    Code:
       0: aload_0
       1: getstatic     #93                 // Field com/google/protobuf/LazyStringArrayList.EMPTY:Lcom/google/protobuf/LazyStringList;
       4: putfield      #99                 // Field fallbackKeysSubset_:Lcom/google/protobuf/LazyStringList;
       7: aload_0
       8: aload_0
       9: getfield      #118                // Field bitField0_:I
      12: bipush        -3
      14: iand
      15: putfield      #118                // Field bitField0_:I
      18: aload_0
      19: invokevirtual #221                // Method onChanged:()V
      22: aload_0
      23: areturn

  public io.grpc.xds.shaded.io.envoyproxy.envoy.api.v2.Cluster$LbSubsetConfig$LbSubsetSelector$Builder addFallbackKeysSubsetBytes(com.google.protobuf.ByteString);
    Code:
       0: aload_1
       1: ifnonnull     12
       4: new           #309                // class java/lang/NullPointerException
       7: dup
       8: invokespecial #310                // Method java/lang/NullPointerException."<init>":()V
      11: athrow
      12: aload_1
      13: invokestatic  #368                // Method io/grpc/xds/shaded/io/envoyproxy/envoy/api/v2/Cluster$LbSubsetConfig$LbSubsetSelector.access$4100:(Lcom/google/protobuf/ByteString;)V
      16: aload_0
      17: invokespecial #239                // Method ensureFallbackKeysSubsetIsMutable:()V
      20: aload_0
      21: getfield      #99                 // Field fallbackKeysSubset_:Lcom/google/protobuf/LazyStringList;
      24: aload_1
      25: invokeinterface #339,  2          // InterfaceMethod com/google/protobuf/LazyStringList.add:(Lcom/google/protobuf/ByteString;)V
      30: aload_0
      31: invokevirtual #221                // Method onChanged:()V
      34: aload_0
      35: areturn

  public final io.grpc.xds.shaded.io.envoyproxy.envoy.api.v2.Cluster$LbSubsetConfig$LbSubsetSelector$Builder setUnknownFields(com.google.protobuf.UnknownFieldSet);
    Code:
       0: aload_0
       1: aload_1
       2: invokespecial #372                // Method com/google/protobuf/GeneratedMessageV3$Builder.setUnknownFields:(Lcom/google/protobuf/UnknownFieldSet;)Lcom/google/protobuf/GeneratedMessageV3$Builder;
       5: checkcast     #2                  // class io/grpc/xds/shaded/io/envoyproxy/envoy/api/v2/Cluster$LbSubsetConfig$LbSubsetSelector$Builder
       8: areturn

  public final io.grpc.xds.shaded.io.envoyproxy.envoy.api.v2.Cluster$LbSubsetConfig$LbSubsetSelector$Builder mergeUnknownFields(com.google.protobuf.UnknownFieldSet);
    Code:
       0: aload_0
       1: aload_1
       2: invokespecial #376                // Method com/google/protobuf/GeneratedMessageV3$Builder.mergeUnknownFields:(Lcom/google/protobuf/UnknownFieldSet;)Lcom/google/protobuf/GeneratedMessageV3$Builder;
       5: checkcast     #2                  // class io/grpc/xds/shaded/io/envoyproxy/envoy/api/v2/Cluster$LbSubsetConfig$LbSubsetSelector$Builder
       8: areturn

  public com.google.protobuf.GeneratedMessageV3$Builder mergeUnknownFields(com.google.protobuf.UnknownFieldSet);
    Code:
       0: aload_0
       1: aload_1
       2: invokevirtual #247                // Method mergeUnknownFields:(Lcom/google/protobuf/UnknownFieldSet;)Lio/grpc/xds/shaded/io/envoyproxy/envoy/api/v2/Cluster$LbSubsetConfig$LbSubsetSelector$Builder;
       5: areturn

  public com.google.protobuf.GeneratedMessageV3$Builder setUnknownFields(com.google.protobuf.UnknownFieldSet);
    Code:
       0: aload_0
       1: aload_1
       2: invokevirtual #378                // Method setUnknownFields:(Lcom/google/protobuf/UnknownFieldSet;)Lio/grpc/xds/shaded/io/envoyproxy/envoy/api/v2/Cluster$LbSubsetConfig$LbSubsetSelector$Builder;
       5: areturn

  public com.google.protobuf.GeneratedMessageV3$Builder addRepeatedField(com.google.protobuf.Descriptors$FieldDescriptor, java.lang.Object);
    Code:
       0: aload_0
       1: aload_1
       2: aload_2
       3: invokevirtual #380                // Method addRepeatedField:(Lcom/google/protobuf/Descriptors$FieldDescriptor;Ljava/lang/Object;)Lio/grpc/xds/shaded/io/envoyproxy/envoy/api/v2/Cluster$LbSubsetConfig$LbSubsetSelector$Builder;
       6: areturn

  public com.google.protobuf.GeneratedMessageV3$Builder setRepeatedField(com.google.protobuf.Descriptors$FieldDescriptor, int, java.lang.Object);
    Code:
       0: aload_0
       1: aload_1
       2: iload_2
       3: aload_3
       4: invokevirtual #382                // Method setRepeatedField:(Lcom/google/protobuf/Descriptors$FieldDescriptor;ILjava/lang/Object;)Lio/grpc/xds/shaded/io/envoyproxy/envoy/api/v2/Cluster$LbSubsetConfig$LbSubsetSelector$Builder;
       7: areturn

  public com.google.protobuf.GeneratedMessageV3$Builder clearOneof(com.google.protobuf.Descriptors$OneofDescriptor);
    Code:
       0: aload_0
       1: aload_1
       2: invokevirtual #384                // Method clearOneof:(Lcom/google/protobuf/Descriptors$OneofDescriptor;)Lio/grpc/xds/shaded/io/envoyproxy/envoy/api/v2/Cluster$LbSubsetConfig$LbSubsetSelector$Builder;
       5: areturn

  public com.google.protobuf.GeneratedMessageV3$Builder clearField(com.google.protobuf.Descriptors$FieldDescriptor);
    Code:
       0: aload_0
       1: aload_1
       2: invokevirtual #386                // Method clearField:(Lcom/google/protobuf/Descriptors$FieldDescriptor;)Lio/grpc/xds/shaded/io/envoyproxy/envoy/api/v2/Cluster$LbSubsetConfig$LbSubsetSelector$Builder;
       5: areturn

  public com.google.protobuf.GeneratedMessageV3$Builder setField(com.google.protobuf.Descriptors$FieldDescriptor, java.lang.Object);
    Code:
       0: aload_0
       1: aload_1
       2: aload_2
       3: invokevirtual #388                // Method setField:(Lcom/google/protobuf/Descriptors$FieldDescriptor;Ljava/lang/Object;)Lio/grpc/xds/shaded/io/envoyproxy/envoy/api/v2/Cluster$LbSubsetConfig$LbSubsetSelector$Builder;
       6: areturn

  public com.google.protobuf.GeneratedMessageV3$Builder clear();
    Code:
       0: aload_0
       1: invokevirtual #390                // Method clear:()Lio/grpc/xds/shaded/io/envoyproxy/envoy/api/v2/Cluster$LbSubsetConfig$LbSubsetSelector$Builder;
       4: areturn

  public com.google.protobuf.GeneratedMessageV3$Builder clone();
    Code:
       0: aload_0
       1: invokevirtual #392                // Method clone:()Lio/grpc/xds/shaded/io/envoyproxy/envoy/api/v2/Cluster$LbSubsetConfig$LbSubsetSelector$Builder;
       4: areturn

  public com.google.protobuf.AbstractMessage$Builder mergeUnknownFields(com.google.protobuf.UnknownFieldSet);
    Code:
       0: aload_0
       1: aload_1
       2: invokevirtual #247                // Method mergeUnknownFields:(Lcom/google/protobuf/UnknownFieldSet;)Lio/grpc/xds/shaded/io/envoyproxy/envoy/api/v2/Cluster$LbSubsetConfig$LbSubsetSelector$Builder;
       5: areturn

  public com.google.protobuf.AbstractMessage$Builder mergeFrom(com.google.protobuf.CodedInputStream, com.google.protobuf.ExtensionRegistryLite) throws java.io.IOException;
    Code:
       0: aload_0
       1: aload_1
       2: aload_2
       3: invokevirtual #396                // Method mergeFrom:(Lcom/google/protobuf/CodedInputStream;Lcom/google/protobuf/ExtensionRegistryLite;)Lio/grpc/xds/shaded/io/envoyproxy/envoy/api/v2/Cluster$LbSubsetConfig$LbSubsetSelector$Builder;
       6: areturn

  public com.google.protobuf.AbstractMessage$Builder mergeFrom(com.google.protobuf.Message);
    Code:
       0: aload_0
       1: aload_1
       2: invokevirtual #398                // Method mergeFrom:(Lcom/google/protobuf/Message;)Lio/grpc/xds/shaded/io/envoyproxy/envoy/api/v2/Cluster$LbSubsetConfig$LbSubsetSelector$Builder;
       5: areturn

  public com.google.protobuf.AbstractMessage$Builder clear();
    Code:
       0: aload_0
       1: invokevirtual #390                // Method clear:()Lio/grpc/xds/shaded/io/envoyproxy/envoy/api/v2/Cluster$LbSubsetConfig$LbSubsetSelector$Builder;
       4: areturn

  public com.google.protobuf.AbstractMessage$Builder clearOneof(com.google.protobuf.Descriptors$OneofDescriptor);
    Code:
       0: aload_0
       1: aload_1
       2: invokevirtual #384                // Method clearOneof:(Lcom/google/protobuf/Descriptors$OneofDescriptor;)Lio/grpc/xds/shaded/io/envoyproxy/envoy/api/v2/Cluster$LbSubsetConfig$LbSubsetSelector$Builder;
       5: areturn

  public com.google.protobuf.AbstractMessage$Builder clone();
    Code:
       0: aload_0
       1: invokevirtual #392                // Method clone:()Lio/grpc/xds/shaded/io/envoyproxy/envoy/api/v2/Cluster$LbSubsetConfig$LbSubsetSelector$Builder;
       4: areturn

  public com.google.protobuf.Message$Builder mergeUnknownFields(com.google.protobuf.UnknownFieldSet);
    Code:
       0: aload_0
       1: aload_1
       2: invokevirtual #247                // Method mergeUnknownFields:(Lcom/google/protobuf/UnknownFieldSet;)Lio/grpc/xds/shaded/io/envoyproxy/envoy/api/v2/Cluster$LbSubsetConfig$LbSubsetSelector$Builder;
       5: areturn

  public com.google.protobuf.Message$Builder setUnknownFields(com.google.protobuf.UnknownFieldSet);
    Code:
       0: aload_0
       1: aload_1
       2: invokevirtual #378                // Method setUnknownFields:(Lcom/google/protobuf/UnknownFieldSet;)Lio/grpc/xds/shaded/io/envoyproxy/envoy/api/v2/Cluster$LbSubsetConfig$LbSubsetSelector$Builder;
       5: areturn

  public com.google.protobuf.Message$Builder addRepeatedField(com.google.protobuf.Descriptors$FieldDescriptor, java.lang.Object);
    Code:
       0: aload_0
       1: aload_1
       2: aload_2
       3: invokevirtual #380                // Method addRepeatedField:(Lcom/google/protobuf/Descriptors$FieldDescriptor;Ljava/lang/Object;)Lio/grpc/xds/shaded/io/envoyproxy/envoy/api/v2/Cluster$LbSubsetConfig$LbSubsetSelector$Builder;
       6: areturn

  public com.google.protobuf.Message$Builder setRepeatedField(com.google.protobuf.Descriptors$FieldDescriptor, int, java.lang.Object);
    Code:
       0: aload_0
       1: aload_1
       2: iload_2
       3: aload_3
       4: invokevirtual #382                // Method setRepeatedField:(Lcom/google/protobuf/Descriptors$FieldDescriptor;ILjava/lang/Object;)Lio/grpc/xds/shaded/io/envoyproxy/envoy/api/v2/Cluster$LbSubsetConfig$LbSubsetSelector$Builder;
       7: areturn

  public com.google.protobuf.Message$Builder clearOneof(com.google.protobuf.Descriptors$OneofDescriptor);
    Code:
       0: aload_0
       1: aload_1
       2: invokevirtual #384                // Method clearOneof:(Lcom/google/protobuf/Descriptors$OneofDescriptor;)Lio/grpc/xds/shaded/io/envoyproxy/envoy/api/v2/Cluster$LbSubsetConfig$LbSubsetSelector$Builder;
       5: areturn

  public com.google.protobuf.Message$Builder clearField(com.google.protobuf.Descriptors$FieldDescriptor);
    Code:
       0: aload_0
       1: aload_1
       2: invokevirtual #386                // Method clearField:(Lcom/google/protobuf/Descriptors$FieldDescriptor;)Lio/grpc/xds/shaded/io/envoyproxy/envoy/api/v2/Cluster$LbSubsetConfig$LbSubsetSelector$Builder;
       5: areturn

  public com.google.protobuf.Message$Builder setField(com.google.protobuf.Descriptors$FieldDescriptor, java.lang.Object);
    Code:
       0: aload_0
       1: aload_1
       2: aload_2
       3: invokevirtual #388                // Method setField:(Lcom/google/protobuf/Descriptors$FieldDescriptor;Ljava/lang/Object;)Lio/grpc/xds/shaded/io/envoyproxy/envoy/api/v2/Cluster$LbSubsetConfig$LbSubsetSelector$Builder;
       6: areturn

  public com.google.protobuf.Message$Builder mergeFrom(com.google.protobuf.CodedInputStream, com.google.protobuf.ExtensionRegistryLite) throws java.io.IOException;
    Code:
       0: aload_0
       1: aload_1
       2: aload_2
       3: invokevirtual #396                // Method mergeFrom:(Lcom/google/protobuf/CodedInputStream;Lcom/google/protobuf/ExtensionRegistryLite;)Lio/grpc/xds/shaded/io/envoyproxy/envoy/api/v2/Cluster$LbSubsetConfig$LbSubsetSelector$Builder;
       6: areturn

  public com.google.protobuf.Message$Builder clone();
    Code:
       0: aload_0
       1: invokevirtual #392                // Method clone:()Lio/grpc/xds/shaded/io/envoyproxy/envoy/api/v2/Cluster$LbSubsetConfig$LbSubsetSelector$Builder;
       4: areturn

  public com.google.protobuf.Message buildPartial();
    Code:
       0: aload_0
       1: invokevirtual #128                // Method buildPartial:()Lio/grpc/xds/shaded/io/envoyproxy/envoy/api/v2/Cluster$LbSubsetConfig$LbSubsetSelector;
       4: areturn

  public com.google.protobuf.Message build();
    Code:
       0: aload_0
       1: invokevirtual #410                // Method build:()Lio/grpc/xds/shaded/io/envoyproxy/envoy/api/v2/Cluster$LbSubsetConfig$LbSubsetSelector;
       4: areturn

  public com.google.protobuf.Message$Builder mergeFrom(com.google.protobuf.Message);
    Code:
       0: aload_0
       1: aload_1
       2: invokevirtual #398                // Method mergeFrom:(Lcom/google/protobuf/Message;)Lio/grpc/xds/shaded/io/envoyproxy/envoy/api/v2/Cluster$LbSubsetConfig$LbSubsetSelector$Builder;
       5: areturn

  public com.google.protobuf.Message$Builder clear();
    Code:
       0: aload_0
       1: invokevirtual #390                // Method clear:()Lio/grpc/xds/shaded/io/envoyproxy/envoy/api/v2/Cluster$LbSubsetConfig$LbSubsetSelector$Builder;
       4: areturn

  public com.google.protobuf.MessageLite$Builder mergeFrom(com.google.protobuf.CodedInputStream, com.google.protobuf.ExtensionRegistryLite) throws java.io.IOException;
    Code:
       0: aload_0
       1: aload_1
       2: aload_2
       3: invokevirtual #396                // Method mergeFrom:(Lcom/google/protobuf/CodedInputStream;Lcom/google/protobuf/ExtensionRegistryLite;)Lio/grpc/xds/shaded/io/envoyproxy/envoy/api/v2/Cluster$LbSubsetConfig$LbSubsetSelector$Builder;
       6: areturn

  public com.google.protobuf.MessageLite$Builder clone();
    Code:
       0: aload_0
       1: invokevirtual #392                // Method clone:()Lio/grpc/xds/shaded/io/envoyproxy/envoy/api/v2/Cluster$LbSubsetConfig$LbSubsetSelector$Builder;
       4: areturn

  public com.google.protobuf.MessageLite buildPartial();
    Code:
       0: aload_0
       1: invokevirtual #128                // Method buildPartial:()Lio/grpc/xds/shaded/io/envoyproxy/envoy/api/v2/Cluster$LbSubsetConfig$LbSubsetSelector;
       4: areturn

  public com.google.protobuf.MessageLite build();
    Code:
       0: aload_0
       1: invokevirtual #410                // Method build:()Lio/grpc/xds/shaded/io/envoyproxy/envoy/api/v2/Cluster$LbSubsetConfig$LbSubsetSelector;
       4: areturn

  public com.google.protobuf.MessageLite$Builder clear();
    Code:
       0: aload_0
       1: invokevirtual #390                // Method clear:()Lio/grpc/xds/shaded/io/envoyproxy/envoy/api/v2/Cluster$LbSubsetConfig$LbSubsetSelector$Builder;
       4: areturn

  public com.google.protobuf.MessageLite getDefaultInstanceForType();
    Code:
       0: aload_0
       1: invokevirtual #415                // Method getDefaultInstanceForType:()Lio/grpc/xds/shaded/io/envoyproxy/envoy/api/v2/Cluster$LbSubsetConfig$LbSubsetSelector;
       4: areturn

  public com.google.protobuf.Message getDefaultInstanceForType();
    Code:
       0: aload_0
       1: invokevirtual #415                // Method getDefaultInstanceForType:()Lio/grpc/xds/shaded/io/envoyproxy/envoy/api/v2/Cluster$LbSubsetConfig$LbSubsetSelector;
       4: areturn

  public com.google.protobuf.AbstractMessageLite$Builder mergeFrom(com.google.protobuf.CodedInputStream, com.google.protobuf.ExtensionRegistryLite) throws java.io.IOException;
    Code:
       0: aload_0
       1: aload_1
       2: aload_2
       3: invokevirtual #396                // Method mergeFrom:(Lcom/google/protobuf/CodedInputStream;Lcom/google/protobuf/ExtensionRegistryLite;)Lio/grpc/xds/shaded/io/envoyproxy/envoy/api/v2/Cluster$LbSubsetConfig$LbSubsetSelector$Builder;
       6: areturn

  public com.google.protobuf.AbstractMessageLite$Builder clone();
    Code:
       0: aload_0
       1: invokevirtual #392                // Method clone:()Lio/grpc/xds/shaded/io/envoyproxy/envoy/api/v2/Cluster$LbSubsetConfig$LbSubsetSelector$Builder;
       4: areturn

  public java.lang.Object clone() throws java.lang.CloneNotSupportedException;
    Code:
       0: aload_0
       1: invokevirtual #392                // Method clone:()Lio/grpc/xds/shaded/io/envoyproxy/envoy/api/v2/Cluster$LbSubsetConfig$LbSubsetSelector$Builder;
       4: areturn

  public java.util.List getFallbackKeysSubsetList();
    Code:
       0: aload_0
       1: invokevirtual #423                // Method getFallbackKeysSubsetList:()Lcom/google/protobuf/ProtocolStringList;
       4: areturn

  public java.util.List getKeysList();
    Code:
       0: aload_0
       1: invokevirtual #425                // Method getKeysList:()Lcom/google/protobuf/ProtocolStringList;
       4: areturn

  io.grpc.xds.shaded.io.envoyproxy.envoy.api.v2.Cluster$LbSubsetConfig$LbSubsetSelector$Builder(io.grpc.xds.shaded.io.envoyproxy.envoy.api.v2.Cluster$1);
    Code:
       0: aload_0
       1: invokespecial #427                // Method "<init>":()V
       4: return

  io.grpc.xds.shaded.io.envoyproxy.envoy.api.v2.Cluster$LbSubsetConfig$LbSubsetSelector$Builder(com.google.protobuf.GeneratedMessageV3$BuilderParent, io.grpc.xds.shaded.io.envoyproxy.envoy.api.v2.Cluster$1);
    Code:
       0: aload_0
       1: aload_1
       2: invokespecial #431                // Method "<init>":(Lcom/google/protobuf/GeneratedMessageV3$BuilderParent;)V
       5: return
}
