Compiled from "GarbageCollectionWarningThread.java"
class org.graylog2.periodical.GarbageCollectionWarningThread$1 implements javax.management.NotificationListener {
  final java.lang.management.GarbageCollectorMXBean val$gc;

  final org.graylog2.periodical.GarbageCollectionWarningThread this$0;

  org.graylog2.periodical.GarbageCollectionWarningThread$1(org.graylog2.periodical.GarbageCollectionWarningThread, java.lang.management.GarbageCollectorMXBean);
    Code:
       0: aload_0
       1: aload_1
       2: putfield      #1                  // Field this$0:Lorg/graylog2/periodical/GarbageCollectionWarningThread;
       5: aload_0
       6: aload_2
       7: putfield      #2                  // Field val$gc:Ljava/lang/management/GarbageCollectorMXBean;
      10: aload_0
      11: invokespecial #3                  // Method java/lang/Object."<init>":()V
      14: return

  public void handleNotification(javax.management.Notification, java.lang.Object);
    Code:
       0: ldc           #5                  // String com.sun.management.gc.notification
       2: aload_1
       3: invokevirtual #6                  // Method javax/management/Notification.getType:()Ljava/lang/String;
       6: invokevirtual #7                  // Method java/lang/String.equals:(Ljava/lang/Object;)Z
       9: ifeq          261
      12: aload_1
      13: invokevirtual #8                  // Method javax/management/Notification.getUserData:()Ljava/lang/Object;
      16: checkcast     #9                  // class javax/management/openmbean/CompositeData
      19: invokestatic  #10                 // Method com/sun/management/GarbageCollectionNotificationInfo.from:(Ljavax/management/openmbean/CompositeData;)Lcom/sun/management/GarbageCollectionNotificationInfo;
      22: invokevirtual #11                 // Method com/sun/management/GarbageCollectionNotificationInfo.getGcInfo:()Lcom/sun/management/GcInfo;
      25: astore_3
      26: aload_3
      27: invokevirtual #12                 // Method com/sun/management/GcInfo.getDuration:()J
      30: invokestatic  #13                 // Method com/github/joschi/jadconfig/util/Duration.milliseconds:(J)Lcom/github/joschi/jadconfig/util/Duration;
      33: astore        4
      35: aload         4
      37: aload_0
      38: getfield      #1                  // Field this$0:Lorg/graylog2/periodical/GarbageCollectionWarningThread;
      41: invokestatic  #14                 // Method org/graylog2/periodical/GarbageCollectionWarningThread.access$000:(Lorg/graylog2/periodical/GarbageCollectionWarningThread;)Lcom/github/joschi/jadconfig/util/Duration;
      44: invokevirtual #15                 // Method com/github/joschi/jadconfig/util/Duration.compareTo:(Lcom/github/joschi/jadconfig/util/Duration;)I
      47: ifle          261
      50: invokestatic  #16                 // Method org/graylog2/periodical/GarbageCollectionWarningThread.access$100:()Lorg/slf4j/Logger;
      53: ldc           #17                 // String Last GC run with {} took longer than {} (last duration={})
      55: iconst_3
      56: anewarray     #18                 // class java/lang/Object
      59: dup
      60: iconst_0
      61: aload_0
      62: getfield      #2                  // Field val$gc:Ljava/lang/management/GarbageCollectorMXBean;
      65: invokeinterface #19,  1           // InterfaceMethod java/lang/management/GarbageCollectorMXBean.getName:()Ljava/lang/String;
      70: aastore
      71: dup
      72: iconst_1
      73: aload_0
      74: getfield      #1                  // Field this$0:Lorg/graylog2/periodical/GarbageCollectionWarningThread;
      77: invokestatic  #14                 // Method org/graylog2/periodical/GarbageCollectionWarningThread.access$000:(Lorg/graylog2/periodical/GarbageCollectionWarningThread;)Lcom/github/joschi/jadconfig/util/Duration;
      80: aastore
      81: dup
      82: iconst_2
      83: aload         4
      85: aastore
      86: invokeinterface #20,  3           // InterfaceMethod org/slf4j/Logger.warn:(Ljava/lang/String;[Ljava/lang/Object;)V
      91: aload_0
      92: getfield      #1                  // Field this$0:Lorg/graylog2/periodical/GarbageCollectionWarningThread;
      95: invokestatic  #21                 // Method org/graylog2/periodical/GarbageCollectionWarningThread.access$300:(Lorg/graylog2/periodical/GarbageCollectionWarningThread;)Lorg/graylog2/notifications/NotificationService;
      98: invokeinterface #22,  1           // InterfaceMethod org/graylog2/notifications/NotificationService.buildNow:()Lorg/graylog2/notifications/Notification;
     103: aload_0
     104: getfield      #1                  // Field this$0:Lorg/graylog2/periodical/GarbageCollectionWarningThread;
     107: invokestatic  #23                 // Method org/graylog2/periodical/GarbageCollectionWarningThread.access$200:(Lorg/graylog2/periodical/GarbageCollectionWarningThread;)Lorg/graylog2/plugin/system/NodeId;
     110: invokevirtual #24                 // Method org/graylog2/plugin/system/NodeId.toString:()Ljava/lang/String;
     113: invokeinterface #25,  2           // InterfaceMethod org/graylog2/notifications/Notification.addNode:(Ljava/lang/String;)Lorg/graylog2/notifications/Notification;
     118: invokestatic  #26                 // Method org/graylog2/plugin/Tools.nowUTC:()Lorg/joda/time/DateTime;
     121: invokeinterface #27,  2           // InterfaceMethod org/graylog2/notifications/Notification.addTimestamp:(Lorg/joda/time/DateTime;)Lorg/graylog2/notifications/Notification;
     126: getstatic     #28                 // Field org/graylog2/notifications/Notification$Severity.URGENT:Lorg/graylog2/notifications/Notification$Severity;
     129: invokeinterface #29,  2           // InterfaceMethod org/graylog2/notifications/Notification.addSeverity:(Lorg/graylog2/notifications/Notification$Severity;)Lorg/graylog2/notifications/Notification;
     134: getstatic     #30                 // Field org/graylog2/notifications/Notification$Type.GC_TOO_LONG:Lorg/graylog2/notifications/Notification$Type;
     137: invokeinterface #31,  2           // InterfaceMethod org/graylog2/notifications/Notification.addType:(Lorg/graylog2/notifications/Notification$Type;)Lorg/graylog2/notifications/Notification;
     142: ldc           #32                 // String gc_name
     144: aload_0
     145: getfield      #2                  // Field val$gc:Ljava/lang/management/GarbageCollectorMXBean;
     148: invokeinterface #19,  1           // InterfaceMethod java/lang/management/GarbageCollectorMXBean.getName:()Ljava/lang/String;
     153: invokeinterface #33,  3           // InterfaceMethod org/graylog2/notifications/Notification.addDetail:(Ljava/lang/String;Ljava/lang/Object;)Lorg/graylog2/notifications/Notification;
     158: ldc           #34                 // String gc_duration_ms
     160: aload         4
     162: invokevirtual #35                 // Method com/github/joschi/jadconfig/util/Duration.toMilliseconds:()J
     165: invokestatic  #36                 // Method java/lang/Long.valueOf:(J)Ljava/lang/Long;
     168: invokeinterface #33,  3           // InterfaceMethod org/graylog2/notifications/Notification.addDetail:(Ljava/lang/String;Ljava/lang/Object;)Lorg/graylog2/notifications/Notification;
     173: ldc           #37                 // String gc_threshold_ms
     175: aload_0
     176: getfield      #1                  // Field this$0:Lorg/graylog2/periodical/GarbageCollectionWarningThread;
     179: invokestatic  #14                 // Method org/graylog2/periodical/GarbageCollectionWarningThread.access$000:(Lorg/graylog2/periodical/GarbageCollectionWarningThread;)Lcom/github/joschi/jadconfig/util/Duration;
     182: invokevirtual #35                 // Method com/github/joschi/jadconfig/util/Duration.toMilliseconds:()J
     185: invokestatic  #36                 // Method java/lang/Long.valueOf:(J)Ljava/lang/Long;
     188: invokeinterface #33,  3           // InterfaceMethod org/graylog2/notifications/Notification.addDetail:(Ljava/lang/String;Ljava/lang/Object;)Lorg/graylog2/notifications/Notification;
     193: ldc           #38                 // String gc_collection_count
     195: aload_0
     196: getfield      #2                  // Field val$gc:Ljava/lang/management/GarbageCollectorMXBean;
     199: invokeinterface #39,  1           // InterfaceMethod java/lang/management/GarbageCollectorMXBean.getCollectionCount:()J
     204: invokestatic  #36                 // Method java/lang/Long.valueOf:(J)Ljava/lang/Long;
     207: invokeinterface #33,  3           // InterfaceMethod org/graylog2/notifications/Notification.addDetail:(Ljava/lang/String;Ljava/lang/Object;)Lorg/graylog2/notifications/Notification;
     212: ldc           #40                 // String gc_collection_time
     214: aload_0
     215: getfield      #2                  // Field val$gc:Ljava/lang/management/GarbageCollectorMXBean;
     218: invokeinterface #41,  1           // InterfaceMethod java/lang/management/GarbageCollectorMXBean.getCollectionTime:()J
     223: invokestatic  #36                 // Method java/lang/Long.valueOf:(J)Ljava/lang/Long;
     226: invokeinterface #33,  3           // InterfaceMethod org/graylog2/notifications/Notification.addDetail:(Ljava/lang/String;Ljava/lang/Object;)Lorg/graylog2/notifications/Notification;
     231: astore        5
     233: aload_0
     234: getfield      #1                  // Field this$0:Lorg/graylog2/periodical/GarbageCollectionWarningThread;
     237: invokestatic  #21                 // Method org/graylog2/periodical/GarbageCollectionWarningThread.access$300:(Lorg/graylog2/periodical/GarbageCollectionWarningThread;)Lorg/graylog2/notifications/NotificationService;
     240: aload         5
     242: invokeinterface #42,  2           // InterfaceMethod org/graylog2/notifications/NotificationService.publishIfFirst:(Lorg/graylog2/notifications/Notification;)Z
     247: ifne          261
     250: invokestatic  #16                 // Method org/graylog2/periodical/GarbageCollectionWarningThread.access$100:()Lorg/slf4j/Logger;
     253: ldc           #43                 // String Couldn\'t publish notification: {}
     255: aload_1
     256: invokeinterface #44,  3           // InterfaceMethod org/slf4j/Logger.debug:(Ljava/lang/String;Ljava/lang/Object;)V
     261: return
}
