Compiled from "DefaultFTPFileEntryParserFactory.java"
public class org.apache.commons.net.ftp.parser.DefaultFTPFileEntryParserFactory implements org.apache.commons.net.ftp.parser.FTPFileEntryParserFactory {
  private static final java.lang.String JAVA_IDENTIFIER;

  private static final java.lang.String JAVA_QUALIFIED_NAME;

  private static final java.util.regex.Pattern JAVA_QUALIFIED_NAME_PATTERN;

  public org.apache.commons.net.ftp.parser.DefaultFTPFileEntryParserFactory();
    Code:
       0: aload_0
       1: invokespecial #2                  // Method java/lang/Object."<init>":()V
       4: return

  public org.apache.commons.net.ftp.FTPFileEntryParser createFileEntryParser(org.apache.commons.net.ftp.FTPClientConfig) throws org.apache.commons.net.ftp.parser.ParserInitializationException;
    Code:
       0: aload_1
       1: invokevirtual #3                  // Method org/apache/commons/net/ftp/FTPClientConfig.getServerSystemKey:()Ljava/lang/String;
       4: astore_2
       5: aload_0
       6: aload_2
       7: aload_1
       8: invokespecial #4                  // Method createFileEntryParser:(Ljava/lang/String;Lorg/apache/commons/net/ftp/FTPClientConfig;)Lorg/apache/commons/net/ftp/FTPFileEntryParser;
      11: areturn

  public org.apache.commons.net.ftp.FTPFileEntryParser createFileEntryParser(java.lang.String);
    Code:
       0: aload_1
       1: ifnonnull     14
       4: new           #5                  // class org/apache/commons/net/ftp/parser/ParserInitializationException
       7: dup
       8: ldc           #6                  // String Parser key cannot be null
      10: invokespecial #7                  // Method org/apache/commons/net/ftp/parser/ParserInitializationException."<init>":(Ljava/lang/String;)V
      13: athrow
      14: aload_0
      15: aload_1
      16: aconst_null
      17: invokespecial #4                  // Method createFileEntryParser:(Ljava/lang/String;Lorg/apache/commons/net/ftp/FTPClientConfig;)Lorg/apache/commons/net/ftp/FTPFileEntryParser;
      20: areturn

  private org.apache.commons.net.ftp.FTPFileEntryParser createFileEntryParser(java.lang.String, org.apache.commons.net.ftp.FTPClientConfig);
    Code:
       0: aconst_null
       1: astore_3
       2: getstatic     #8                  // Field JAVA_QUALIFIED_NAME_PATTERN:Ljava/util/regex/Pattern;
       5: aload_1
       6: invokevirtual #9                  // Method java/util/regex/Pattern.matcher:(Ljava/lang/CharSequence;)Ljava/util/regex/Matcher;
       9: invokevirtual #10                 // Method java/util/regex/Matcher.matches:()Z
      12: ifeq          87
      15: aload_1
      16: invokestatic  #11                 // Method java/lang/Class.forName:(Ljava/lang/String;)Ljava/lang/Class;
      19: astore        4
      21: aload         4
      23: invokevirtual #12                 // Method java/lang/Class.newInstance:()Ljava/lang/Object;
      26: checkcast     #13                 // class org/apache/commons/net/ftp/FTPFileEntryParser
      29: astore_3
      30: goto          82
      33: astore        5
      35: new           #5                  // class org/apache/commons/net/ftp/parser/ParserInitializationException
      38: dup
      39: new           #15                 // class java/lang/StringBuilder
      42: dup
      43: invokespecial #16                 // Method java/lang/StringBuilder."<init>":()V
      46: aload         4
      48: invokevirtual #17                 // Method java/lang/Class.getName:()Ljava/lang/String;
      51: invokevirtual #18                 // Method java/lang/StringBuilder.append:(Ljava/lang/String;)Ljava/lang/StringBuilder;
      54: ldc           #19                 // String  does not implement the interface org.apache.commons.net.ftp.FTPFileEntryParser.
      56: invokevirtual #18                 // Method java/lang/StringBuilder.append:(Ljava/lang/String;)Ljava/lang/StringBuilder;
      59: invokevirtual #20                 // Method java/lang/StringBuilder.toString:()Ljava/lang/String;
      62: aload         5
      64: invokespecial #21                 // Method org/apache/commons/net/ftp/parser/ParserInitializationException."<init>":(Ljava/lang/String;Ljava/lang/Throwable;)V
      67: athrow
      68: astore        5
      70: new           #5                  // class org/apache/commons/net/ftp/parser/ParserInitializationException
      73: dup
      74: ldc           #24                 // String Error initializing parser
      76: aload         5
      78: invokespecial #21                 // Method org/apache/commons/net/ftp/parser/ParserInitializationException."<init>":(Ljava/lang/String;Ljava/lang/Throwable;)V
      81: athrow
      82: goto          87
      85: astore        4
      87: aload_3
      88: ifnonnull     352
      91: aload_1
      92: getstatic     #26                 // Field java/util/Locale.ENGLISH:Ljava/util/Locale;
      95: invokevirtual #27                 // Method java/lang/String.toUpperCase:(Ljava/util/Locale;)Ljava/lang/String;
      98: astore        4
     100: aload         4
     102: ldc           #29                 // String UNIX_LTRIM
     104: invokevirtual #30                 // Method java/lang/String.contains:(Ljava/lang/CharSequence;)Z
     107: ifeq          123
     110: new           #31                 // class org/apache/commons/net/ftp/parser/UnixFTPEntryParser
     113: dup
     114: aload_2
     115: iconst_1
     116: invokespecial #32                 // Method org/apache/commons/net/ftp/parser/UnixFTPEntryParser."<init>":(Lorg/apache/commons/net/ftp/FTPClientConfig;Z)V
     119: astore_3
     120: goto          352
     123: aload         4
     125: ldc           #33                 // String UNIX
     127: invokevirtual #30                 // Method java/lang/String.contains:(Ljava/lang/CharSequence;)Z
     130: ifeq          146
     133: new           #31                 // class org/apache/commons/net/ftp/parser/UnixFTPEntryParser
     136: dup
     137: aload_2
     138: iconst_0
     139: invokespecial #32                 // Method org/apache/commons/net/ftp/parser/UnixFTPEntryParser."<init>":(Lorg/apache/commons/net/ftp/FTPClientConfig;Z)V
     142: astore_3
     143: goto          352
     146: aload         4
     148: ldc           #34                 // String VMS
     150: invokevirtual #30                 // Method java/lang/String.contains:(Ljava/lang/CharSequence;)Z
     153: ifeq          168
     156: new           #35                 // class org/apache/commons/net/ftp/parser/VMSVersioningFTPEntryParser
     159: dup
     160: aload_2
     161: invokespecial #36                 // Method org/apache/commons/net/ftp/parser/VMSVersioningFTPEntryParser."<init>":(Lorg/apache/commons/net/ftp/FTPClientConfig;)V
     164: astore_3
     165: goto          352
     168: aload         4
     170: ldc           #37                 // String WINDOWS
     172: invokevirtual #30                 // Method java/lang/String.contains:(Ljava/lang/CharSequence;)Z
     175: ifeq          187
     178: aload_0
     179: aload_2
     180: invokespecial #38                 // Method createNTFTPEntryParser:(Lorg/apache/commons/net/ftp/FTPClientConfig;)Lorg/apache/commons/net/ftp/FTPFileEntryParser;
     183: astore_3
     184: goto          352
     187: aload         4
     189: ldc           #39                 // String OS/2
     191: invokevirtual #30                 // Method java/lang/String.contains:(Ljava/lang/CharSequence;)Z
     194: ifeq          209
     197: new           #40                 // class org/apache/commons/net/ftp/parser/OS2FTPEntryParser
     200: dup
     201: aload_2
     202: invokespecial #41                 // Method org/apache/commons/net/ftp/parser/OS2FTPEntryParser."<init>":(Lorg/apache/commons/net/ftp/FTPClientConfig;)V
     205: astore_3
     206: goto          352
     209: aload         4
     211: ldc           #42                 // String OS/400
     213: invokevirtual #30                 // Method java/lang/String.contains:(Ljava/lang/CharSequence;)Z
     216: ifne          229
     219: aload         4
     221: ldc           #43                 // String AS/400
     223: invokevirtual #30                 // Method java/lang/String.contains:(Ljava/lang/CharSequence;)Z
     226: ifeq          238
     229: aload_0
     230: aload_2
     231: invokespecial #44                 // Method createOS400FTPEntryParser:(Lorg/apache/commons/net/ftp/FTPClientConfig;)Lorg/apache/commons/net/ftp/FTPFileEntryParser;
     234: astore_3
     235: goto          352
     238: aload         4
     240: ldc           #45                 // String MVS
     242: invokevirtual #30                 // Method java/lang/String.contains:(Ljava/lang/CharSequence;)Z
     245: ifeq          259
     248: new           #46                 // class org/apache/commons/net/ftp/parser/MVSFTPEntryParser
     251: dup
     252: invokespecial #47                 // Method org/apache/commons/net/ftp/parser/MVSFTPEntryParser."<init>":()V
     255: astore_3
     256: goto          352
     259: aload         4
     261: ldc           #48                 // String NETWARE
     263: invokevirtual #30                 // Method java/lang/String.contains:(Ljava/lang/CharSequence;)Z
     266: ifeq          281
     269: new           #49                 // class org/apache/commons/net/ftp/parser/NetwareFTPEntryParser
     272: dup
     273: aload_2
     274: invokespecial #50                 // Method org/apache/commons/net/ftp/parser/NetwareFTPEntryParser."<init>":(Lorg/apache/commons/net/ftp/FTPClientConfig;)V
     277: astore_3
     278: goto          352
     281: aload         4
     283: ldc           #51                 // String MACOS PETER
     285: invokevirtual #30                 // Method java/lang/String.contains:(Ljava/lang/CharSequence;)Z
     288: ifeq          303
     291: new           #52                 // class org/apache/commons/net/ftp/parser/MacOsPeterFTPEntryParser
     294: dup
     295: aload_2
     296: invokespecial #53                 // Method org/apache/commons/net/ftp/parser/MacOsPeterFTPEntryParser."<init>":(Lorg/apache/commons/net/ftp/FTPClientConfig;)V
     299: astore_3
     300: goto          352
     303: aload         4
     305: ldc           #54                 // String TYPE: L8
     307: invokevirtual #30                 // Method java/lang/String.contains:(Ljava/lang/CharSequence;)Z
     310: ifeq          325
     313: new           #31                 // class org/apache/commons/net/ftp/parser/UnixFTPEntryParser
     316: dup
     317: aload_2
     318: invokespecial #55                 // Method org/apache/commons/net/ftp/parser/UnixFTPEntryParser."<init>":(Lorg/apache/commons/net/ftp/FTPClientConfig;)V
     321: astore_3
     322: goto          352
     325: new           #5                  // class org/apache/commons/net/ftp/parser/ParserInitializationException
     328: dup
     329: new           #15                 // class java/lang/StringBuilder
     332: dup
     333: invokespecial #16                 // Method java/lang/StringBuilder."<init>":()V
     336: ldc           #56                 // String Unknown parser type:
     338: invokevirtual #18                 // Method java/lang/StringBuilder.append:(Ljava/lang/String;)Ljava/lang/StringBuilder;
     341: aload_1
     342: invokevirtual #18                 // Method java/lang/StringBuilder.append:(Ljava/lang/String;)Ljava/lang/StringBuilder;
     345: invokevirtual #20                 // Method java/lang/StringBuilder.toString:()Ljava/lang/String;
     348: invokespecial #7                  // Method org/apache/commons/net/ftp/parser/ParserInitializationException."<init>":(Ljava/lang/String;)V
     351: athrow
     352: aload_3
     353: instanceof    #57                 // class org/apache/commons/net/ftp/Configurable
     356: ifeq          369
     359: aload_3
     360: checkcast     #57                 // class org/apache/commons/net/ftp/Configurable
     363: aload_2
     364: invokeinterface #58,  2           // InterfaceMethod org/apache/commons/net/ftp/Configurable.configure:(Lorg/apache/commons/net/ftp/FTPClientConfig;)V
     369: aload_3
     370: areturn
    Exception table:
       from    to  target type
          21    30    33   Class java/lang/ClassCastException
          21    30    68   Class java/lang/Exception
          21    30    68   Class java/lang/ExceptionInInitializerError
          15    82    85   Class java/lang/ClassNotFoundException

  public org.apache.commons.net.ftp.FTPFileEntryParser createMVSEntryParser();
    Code:
       0: new           #46                 // class org/apache/commons/net/ftp/parser/MVSFTPEntryParser
       3: dup
       4: invokespecial #47                 // Method org/apache/commons/net/ftp/parser/MVSFTPEntryParser."<init>":()V
       7: areturn

  public org.apache.commons.net.ftp.FTPFileEntryParser createNetwareFTPEntryParser();
    Code:
       0: new           #49                 // class org/apache/commons/net/ftp/parser/NetwareFTPEntryParser
       3: dup
       4: invokespecial #59                 // Method org/apache/commons/net/ftp/parser/NetwareFTPEntryParser."<init>":()V
       7: areturn

  public org.apache.commons.net.ftp.FTPFileEntryParser createNTFTPEntryParser();
    Code:
       0: aload_0
       1: aconst_null
       2: invokespecial #38                 // Method createNTFTPEntryParser:(Lorg/apache/commons/net/ftp/FTPClientConfig;)Lorg/apache/commons/net/ftp/FTPFileEntryParser;
       5: areturn

  private org.apache.commons.net.ftp.FTPFileEntryParser createNTFTPEntryParser(org.apache.commons.net.ftp.FTPClientConfig);
    Code:
       0: aload_1
       1: ifnull        25
       4: ldc           #37                 // String WINDOWS
       6: aload_1
       7: invokevirtual #3                  // Method org/apache/commons/net/ftp/FTPClientConfig.getServerSystemKey:()Ljava/lang/String;
      10: invokevirtual #60                 // Method java/lang/String.equals:(Ljava/lang/Object;)Z
      13: ifeq          25
      16: new           #61                 // class org/apache/commons/net/ftp/parser/NTFTPEntryParser
      19: dup
      20: aload_1
      21: invokespecial #62                 // Method org/apache/commons/net/ftp/parser/NTFTPEntryParser."<init>":(Lorg/apache/commons/net/ftp/FTPClientConfig;)V
      24: areturn
      25: aload_1
      26: ifnull        40
      29: new           #28                 // class org/apache/commons/net/ftp/FTPClientConfig
      32: dup
      33: aload_1
      34: invokespecial #63                 // Method org/apache/commons/net/ftp/FTPClientConfig."<init>":(Lorg/apache/commons/net/ftp/FTPClientConfig;)V
      37: goto          41
      40: aconst_null
      41: astore_2
      42: new           #64                 // class org/apache/commons/net/ftp/parser/CompositeFileEntryParser
      45: dup
      46: iconst_2
      47: anewarray     #13                 // class org/apache/commons/net/ftp/FTPFileEntryParser
      50: dup
      51: iconst_0
      52: new           #61                 // class org/apache/commons/net/ftp/parser/NTFTPEntryParser
      55: dup
      56: aload_1
      57: invokespecial #62                 // Method org/apache/commons/net/ftp/parser/NTFTPEntryParser."<init>":(Lorg/apache/commons/net/ftp/FTPClientConfig;)V
      60: aastore
      61: dup
      62: iconst_1
      63: new           #31                 // class org/apache/commons/net/ftp/parser/UnixFTPEntryParser
      66: dup
      67: aload_2
      68: aload_2
      69: ifnull        88
      72: ldc           #29                 // String UNIX_LTRIM
      74: aload_2
      75: invokevirtual #3                  // Method org/apache/commons/net/ftp/FTPClientConfig.getServerSystemKey:()Ljava/lang/String;
      78: invokevirtual #60                 // Method java/lang/String.equals:(Ljava/lang/Object;)Z
      81: ifeq          88
      84: iconst_1
      85: goto          89
      88: iconst_0
      89: invokespecial #32                 // Method org/apache/commons/net/ftp/parser/UnixFTPEntryParser."<init>":(Lorg/apache/commons/net/ftp/FTPClientConfig;Z)V
      92: aastore
      93: invokespecial #65                 // Method org/apache/commons/net/ftp/parser/CompositeFileEntryParser."<init>":([Lorg/apache/commons/net/ftp/FTPFileEntryParser;)V
      96: areturn

  public org.apache.commons.net.ftp.FTPFileEntryParser createOS2FTPEntryParser();
    Code:
       0: new           #40                 // class org/apache/commons/net/ftp/parser/OS2FTPEntryParser
       3: dup
       4: invokespecial #66                 // Method org/apache/commons/net/ftp/parser/OS2FTPEntryParser."<init>":()V
       7: areturn

  public org.apache.commons.net.ftp.FTPFileEntryParser createOS400FTPEntryParser();
    Code:
       0: aload_0
       1: aconst_null
       2: invokespecial #44                 // Method createOS400FTPEntryParser:(Lorg/apache/commons/net/ftp/FTPClientConfig;)Lorg/apache/commons/net/ftp/FTPFileEntryParser;
       5: areturn

  private org.apache.commons.net.ftp.FTPFileEntryParser createOS400FTPEntryParser(org.apache.commons.net.ftp.FTPClientConfig);
    Code:
       0: aload_1
       1: ifnull        25
       4: ldc           #42                 // String OS/400
       6: aload_1
       7: invokevirtual #3                  // Method org/apache/commons/net/ftp/FTPClientConfig.getServerSystemKey:()Ljava/lang/String;
      10: invokevirtual #60                 // Method java/lang/String.equals:(Ljava/lang/Object;)Z
      13: ifeq          25
      16: new           #67                 // class org/apache/commons/net/ftp/parser/OS400FTPEntryParser
      19: dup
      20: aload_1
      21: invokespecial #68                 // Method org/apache/commons/net/ftp/parser/OS400FTPEntryParser."<init>":(Lorg/apache/commons/net/ftp/FTPClientConfig;)V
      24: areturn
      25: aload_1
      26: ifnull        40
      29: new           #28                 // class org/apache/commons/net/ftp/FTPClientConfig
      32: dup
      33: aload_1
      34: invokespecial #63                 // Method org/apache/commons/net/ftp/FTPClientConfig."<init>":(Lorg/apache/commons/net/ftp/FTPClientConfig;)V
      37: goto          41
      40: aconst_null
      41: astore_2
      42: new           #64                 // class org/apache/commons/net/ftp/parser/CompositeFileEntryParser
      45: dup
      46: iconst_2
      47: anewarray     #13                 // class org/apache/commons/net/ftp/FTPFileEntryParser
      50: dup
      51: iconst_0
      52: new           #67                 // class org/apache/commons/net/ftp/parser/OS400FTPEntryParser
      55: dup
      56: aload_1
      57: invokespecial #68                 // Method org/apache/commons/net/ftp/parser/OS400FTPEntryParser."<init>":(Lorg/apache/commons/net/ftp/FTPClientConfig;)V
      60: aastore
      61: dup
      62: iconst_1
      63: new           #31                 // class org/apache/commons/net/ftp/parser/UnixFTPEntryParser
      66: dup
      67: aload_2
      68: aload_2
      69: ifnull        88
      72: ldc           #29                 // String UNIX_LTRIM
      74: aload_2
      75: invokevirtual #3                  // Method org/apache/commons/net/ftp/FTPClientConfig.getServerSystemKey:()Ljava/lang/String;
      78: invokevirtual #60                 // Method java/lang/String.equals:(Ljava/lang/Object;)Z
      81: ifeq          88
      84: iconst_1
      85: goto          89
      88: iconst_0
      89: invokespecial #32                 // Method org/apache/commons/net/ftp/parser/UnixFTPEntryParser."<init>":(Lorg/apache/commons/net/ftp/FTPClientConfig;Z)V
      92: aastore
      93: invokespecial #65                 // Method org/apache/commons/net/ftp/parser/CompositeFileEntryParser."<init>":([Lorg/apache/commons/net/ftp/FTPFileEntryParser;)V
      96: areturn

  public org.apache.commons.net.ftp.FTPFileEntryParser createUnixFTPEntryParser();
    Code:
       0: new           #31                 // class org/apache/commons/net/ftp/parser/UnixFTPEntryParser
       3: dup
       4: invokespecial #69                 // Method org/apache/commons/net/ftp/parser/UnixFTPEntryParser."<init>":()V
       7: areturn

  public org.apache.commons.net.ftp.FTPFileEntryParser createVMSVersioningFTPEntryParser();
    Code:
       0: new           #35                 // class org/apache/commons/net/ftp/parser/VMSVersioningFTPEntryParser
       3: dup
       4: invokespecial #70                 // Method org/apache/commons/net/ftp/parser/VMSVersioningFTPEntryParser."<init>":()V
       7: areturn

  static {};
    Code:
       0: ldc           #71                 // String (\\p{javaJavaIdentifierStart}(\\p{javaJavaIdentifierPart})*\\.)+\\p{javaJavaIdentifierStart}(\\p{javaJavaIdentifierPart})*
       2: invokestatic  #72                 // Method java/util/regex/Pattern.compile:(Ljava/lang/String;)Ljava/util/regex/Pattern;
       5: putstatic     #8                  // Field JAVA_QUALIFIED_NAME_PATTERN:Ljava/util/regex/Pattern;
       8: return
}
