Compiled from "UnixFTPEntryParser.java"
public class org.apache.commons.net.ftp.parser.UnixFTPEntryParser extends org.apache.commons.net.ftp.parser.ConfigurableFTPFileEntryParserImpl {
  static final java.lang.String DEFAULT_DATE_FORMAT;

  static final java.lang.String DEFAULT_RECENT_DATE_FORMAT;

  static final java.lang.String NUMERIC_DATE_FORMAT;

  private static final java.lang.String JA_MONTH;

  private static final java.lang.String JA_DAY;

  private static final java.lang.String JA_YEAR;

  private static final java.lang.String DEFAULT_DATE_FORMAT_JA;

  private static final java.lang.String DEFAULT_RECENT_DATE_FORMAT_JA;

  public static final org.apache.commons.net.ftp.FTPClientConfig NUMERIC_DATE_CONFIG;

  private static final java.lang.String REGEX;

  final boolean trimLeadingSpaces;

  public org.apache.commons.net.ftp.parser.UnixFTPEntryParser();
    Code:
       0: aload_0
       1: aconst_null
       2: invokespecial #2                  // Method "<init>":(Lorg/apache/commons/net/ftp/FTPClientConfig;)V
       5: return

  public org.apache.commons.net.ftp.parser.UnixFTPEntryParser(org.apache.commons.net.ftp.FTPClientConfig);
    Code:
       0: aload_0
       1: aload_1
       2: iconst_0
       3: invokespecial #3                  // Method "<init>":(Lorg/apache/commons/net/ftp/FTPClientConfig;Z)V
       6: return

  public org.apache.commons.net.ftp.parser.UnixFTPEntryParser(org.apache.commons.net.ftp.FTPClientConfig, boolean);
    Code:
       0: aload_0
       1: ldc           #4                  // String ([bcdelfmpSs-])(((r|-)(w|-)([xsStTL-]))((r|-)(w|-)([xsStTL-]))((r|-)(w|-)([xsStTL-])))\\+?\\s*(\\d+)\\s+(?:(\\S+(?:\\s\\S+)*?)\\s+)?(?:(\\S+(?:\\s\\S+)*)\\s+)?(\\d+(?:,\\s*\\d+)?)\\s+((?:\\d+[-/]\\d+[-/]\\d+)|(?:\\S{3}\\s+\\d{1,2})|(?:\\d{1,2}\\s+\\S{3})|(?:\\d{1,2}月\\s+\\d{1,2}日))\\s+((?:\\d+(?::\\d+)?)|(?:\\d{4}年))\\s(.*)
       3: invokespecial #5                  // Method org/apache/commons/net/ftp/parser/ConfigurableFTPFileEntryParserImpl."<init>":(Ljava/lang/String;)V
       6: aload_0
       7: aload_1
       8: invokevirtual #6                  // Method configure:(Lorg/apache/commons/net/ftp/FTPClientConfig;)V
      11: aload_0
      12: iload_2
      13: putfield      #7                  // Field trimLeadingSpaces:Z
      16: return

  protected org.apache.commons.net.ftp.FTPClientConfig getDefaultConfiguration();
    Code:
       0: new           #8                  // class org/apache/commons/net/ftp/FTPClientConfig
       3: dup
       4: ldc           #9                  // String UNIX
       6: ldc           #10                 // String MMM d yyyy
       8: ldc           #11                 // String MMM d HH:mm
      10: invokespecial #12                 // Method org/apache/commons/net/ftp/FTPClientConfig."<init>":(Ljava/lang/String;Ljava/lang/String;Ljava/lang/String;)V
      13: areturn

  public org.apache.commons.net.ftp.FTPFile parseFTPEntry(java.lang.String);
    Code:
       0: new           #13                 // class org/apache/commons/net/ftp/FTPFile
       3: dup
       4: invokespecial #14                 // Method org/apache/commons/net/ftp/FTPFile."<init>":()V
       7: astore_2
       8: aload_2
       9: aload_1
      10: invokevirtual #15                 // Method org/apache/commons/net/ftp/FTPFile.setRawListing:(Ljava/lang/String;)V
      13: iconst_0
      14: istore        4
      16: aload_0
      17: aload_1
      18: invokevirtual #16                 // Method matches:(Ljava/lang/String;)Z
      21: ifeq          532
      24: aload_0
      25: iconst_1
      26: invokevirtual #17                 // Method group:(I)Ljava/lang/String;
      29: astore        5
      31: aload_0
      32: bipush        15
      34: invokevirtual #17                 // Method group:(I)Ljava/lang/String;
      37: astore        6
      39: aload_0
      40: bipush        16
      42: invokevirtual #17                 // Method group:(I)Ljava/lang/String;
      45: astore        7
      47: aload_0
      48: bipush        17
      50: invokevirtual #17                 // Method group:(I)Ljava/lang/String;
      53: astore        8
      55: aload_0
      56: bipush        18
      58: invokevirtual #17                 // Method group:(I)Ljava/lang/String;
      61: astore        9
      63: new           #18                 // class java/lang/StringBuilder
      66: dup
      67: invokespecial #19                 // Method java/lang/StringBuilder."<init>":()V
      70: aload_0
      71: bipush        19
      73: invokevirtual #17                 // Method group:(I)Ljava/lang/String;
      76: invokevirtual #20                 // Method java/lang/StringBuilder.append:(Ljava/lang/String;)Ljava/lang/StringBuilder;
      79: ldc           #21                 // String
      81: invokevirtual #20                 // Method java/lang/StringBuilder.append:(Ljava/lang/String;)Ljava/lang/StringBuilder;
      84: aload_0
      85: bipush        20
      87: invokevirtual #17                 // Method group:(I)Ljava/lang/String;
      90: invokevirtual #20                 // Method java/lang/StringBuilder.append:(Ljava/lang/String;)Ljava/lang/StringBuilder;
      93: invokevirtual #22                 // Method java/lang/StringBuilder.toString:()Ljava/lang/String;
      96: astore        10
      98: aload_0
      99: bipush        21
     101: invokevirtual #17                 // Method group:(I)Ljava/lang/String;
     104: astore        11
     106: aload_0
     107: getfield      #7                  // Field trimLeadingSpaces:Z
     110: ifeq          124
     113: aload         11
     115: ldc           #23                 // String ^\\s+
     117: ldc           #24                 // String
     119: invokevirtual #25                 // Method java/lang/String.replaceFirst:(Ljava/lang/String;Ljava/lang/String;)Ljava/lang/String;
     122: astore        11
     124: aload_0
     125: bipush        19
     127: invokevirtual #17                 // Method group:(I)Ljava/lang/String;
     130: ldc           #26                 // String 月
     132: invokevirtual #27                 // Method java/lang/String.contains:(Ljava/lang/CharSequence;)Z
     135: ifeq          179
     138: new           #28                 // class org/apache/commons/net/ftp/parser/FTPTimestampParserImpl
     141: dup
     142: invokespecial #29                 // Method org/apache/commons/net/ftp/parser/FTPTimestampParserImpl."<init>":()V
     145: astore        12
     147: aload         12
     149: new           #8                  // class org/apache/commons/net/ftp/FTPClientConfig
     152: dup
     153: ldc           #9                  // String UNIX
     155: ldc           #30                 // String M\'月\' d\'日\' yyyy\'年\'
     157: ldc           #31                 // String M\'月\' d\'日\' HH:mm
     159: invokespecial #12                 // Method org/apache/commons/net/ftp/FTPClientConfig."<init>":(Ljava/lang/String;Ljava/lang/String;Ljava/lang/String;)V
     162: invokevirtual #32                 // Method org/apache/commons/net/ftp/parser/FTPTimestampParserImpl.configure:(Lorg/apache/commons/net/ftp/FTPClientConfig;)V
     165: aload_2
     166: aload         12
     168: aload         10
     170: invokevirtual #33                 // Method org/apache/commons/net/ftp/parser/FTPTimestampParserImpl.parseTimestamp:(Ljava/lang/String;)Ljava/util/Calendar;
     173: invokevirtual #34                 // Method org/apache/commons/net/ftp/FTPFile.setTimestamp:(Ljava/util/Calendar;)V
     176: goto          189
     179: aload_2
     180: aload_0
     181: aload         10
     183: invokespecial #35                 // Method org/apache/commons/net/ftp/parser/ConfigurableFTPFileEntryParserImpl.parseTimestamp:(Ljava/lang/String;)Ljava/util/Calendar;
     186: invokevirtual #34                 // Method org/apache/commons/net/ftp/FTPFile.setTimestamp:(Ljava/util/Calendar;)V
     189: goto          194
     192: astore        12
     194: aload         5
     196: iconst_0
     197: invokevirtual #37                 // Method java/lang/String.charAt:(I)C
     200: lookupswitch  { // 7
                    45: 291
                    98: 283
                    99: 283
                   100: 268
                   101: 273
                   102: 291
                   108: 278
               default: 296
          }
     268: iconst_1
     269: istore_3
     270: goto          298
     273: iconst_2
     274: istore_3
     275: goto          298
     278: iconst_2
     279: istore_3
     280: goto          298
     283: iconst_1
     284: istore        4
     286: iconst_0
     287: istore_3
     288: goto          298
     291: iconst_0
     292: istore_3
     293: goto          298
     296: iconst_3
     297: istore_3
     298: aload_2
     299: iload_3
     300: invokevirtual #38                 // Method org/apache/commons/net/ftp/FTPFile.setType:(I)V
     303: iconst_4
     304: istore        12
     306: iconst_0
     307: istore        13
     309: iload         13
     311: iconst_3
     312: if_icmpge     422
     315: aload_2
     316: iload         13
     318: iconst_0
     319: aload_0
     320: iload         12
     322: invokevirtual #17                 // Method group:(I)Ljava/lang/String;
     325: ldc           #39                 // String -
     327: invokevirtual #40                 // Method java/lang/String.equals:(Ljava/lang/Object;)Z
     330: ifne          337
     333: iconst_1
     334: goto          338
     337: iconst_0
     338: invokevirtual #41                 // Method org/apache/commons/net/ftp/FTPFile.setPermission:(IIZ)V
     341: aload_2
     342: iload         13
     344: iconst_1
     345: aload_0
     346: iload         12
     348: iconst_1
     349: iadd
     350: invokevirtual #17                 // Method group:(I)Ljava/lang/String;
     353: ldc           #39                 // String -
     355: invokevirtual #40                 // Method java/lang/String.equals:(Ljava/lang/Object;)Z
     358: ifne          365
     361: iconst_1
     362: goto          366
     365: iconst_0
     366: invokevirtual #41                 // Method org/apache/commons/net/ftp/FTPFile.setPermission:(IIZ)V
     369: aload_0
     370: iload         12
     372: iconst_2
     373: iadd
     374: invokevirtual #17                 // Method group:(I)Ljava/lang/String;
     377: astore        14
     379: aload_2
     380: iload         13
     382: iconst_2
     383: aload         14
     385: ldc           #39                 // String -
     387: invokevirtual #40                 // Method java/lang/String.equals:(Ljava/lang/Object;)Z
     390: ifne          409
     393: aload         14
     395: iconst_0
     396: invokevirtual #37                 // Method java/lang/String.charAt:(I)C
     399: invokestatic  #42                 // Method java/lang/Character.isUpperCase:(C)Z
     402: ifne          409
     405: iconst_1
     406: goto          410
     409: iconst_0
     410: invokevirtual #41                 // Method org/apache/commons/net/ftp/FTPFile.setPermission:(IIZ)V
     413: iinc          13, 1
     416: iinc          12, 4
     419: goto          309
     422: iload         4
     424: ifne          441
     427: aload_2
     428: aload         6
     430: invokestatic  #43                 // Method java/lang/Integer.parseInt:(Ljava/lang/String;)I
     433: invokevirtual #44                 // Method org/apache/commons/net/ftp/FTPFile.setHardLinkCount:(I)V
     436: goto          441
     439: astore        13
     441: aload_2
     442: aload         7
     444: invokevirtual #46                 // Method org/apache/commons/net/ftp/FTPFile.setUser:(Ljava/lang/String;)V
     447: aload_2
     448: aload         8
     450: invokevirtual #47                 // Method org/apache/commons/net/ftp/FTPFile.setGroup:(Ljava/lang/String;)V
     453: aload_2
     454: aload         9
     456: invokestatic  #48                 // Method java/lang/Long.parseLong:(Ljava/lang/String;)J
     459: invokevirtual #49                 // Method org/apache/commons/net/ftp/FTPFile.setSize:(J)V
     462: goto          467
     465: astore        13
     467: iload_3
     468: iconst_2
     469: if_icmpne     524
     472: aload         11
     474: ldc           #50                 // String  ->
     476: invokevirtual #51                 // Method java/lang/String.indexOf:(Ljava/lang/String;)I
     479: istore        13
     481: iload         13
     483: iconst_m1
     484: if_icmpne     496
     487: aload_2
     488: aload         11
     490: invokevirtual #52                 // Method org/apache/commons/net/ftp/FTPFile.setName:(Ljava/lang/String;)V
     493: goto          521
     496: aload_2
     497: aload         11
     499: iconst_0
     500: iload         13
     502: invokevirtual #53                 // Method java/lang/String.substring:(II)Ljava/lang/String;
     505: invokevirtual #52                 // Method org/apache/commons/net/ftp/FTPFile.setName:(Ljava/lang/String;)V
     508: aload_2
     509: aload         11
     511: iload         13
     513: iconst_4
     514: iadd
     515: invokevirtual #54                 // Method java/lang/String.substring:(I)Ljava/lang/String;
     518: invokevirtual #55                 // Method org/apache/commons/net/ftp/FTPFile.setLink:(Ljava/lang/String;)V
     521: goto          530
     524: aload_2
     525: aload         11
     527: invokevirtual #52                 // Method org/apache/commons/net/ftp/FTPFile.setName:(Ljava/lang/String;)V
     530: aload_2
     531: areturn
     532: aconst_null
     533: areturn
    Exception table:
       from    to  target type
         124   189   192   Class java/text/ParseException
         427   436   439   Class java/lang/NumberFormatException
         453   462   465   Class java/lang/NumberFormatException

  public java.util.List<java.lang.String> preParse(java.util.List<java.lang.String>);
    Code:
       0: aload_1
       1: invokedynamic #56,  0             // InvokeDynamic #0:test:()Ljava/util/function/Predicate;
       6: invokeinterface #57,  2           // InterfaceMethod java/util/List.removeIf:(Ljava/util/function/Predicate;)Z
      11: pop
      12: aload_1
      13: areturn

  private static boolean lambda$preParse$0(java.lang.String);
    Code:
       0: aload_0
       1: ldc           #58                 // String ^total \\d+$
       3: invokevirtual #59                 // Method java/lang/String.matches:(Ljava/lang/String;)Z
       6: ireturn

  static {};
    Code:
       0: new           #8                  // class org/apache/commons/net/ftp/FTPClientConfig
       3: dup
       4: ldc           #9                  // String UNIX
       6: ldc           #60                 // String yyyy-MM-dd HH:mm
       8: aconst_null
       9: invokespecial #12                 // Method org/apache/commons/net/ftp/FTPClientConfig."<init>":(Ljava/lang/String;Ljava/lang/String;Ljava/lang/String;)V
      12: putstatic     #61                 // Field NUMERIC_DATE_CONFIG:Lorg/apache/commons/net/ftp/FTPClientConfig;
      15: return
}
