Compiled from "NativeManagementServices.java"
public class org.jboss.as.host.controller.operations.NativeManagementServices {
  private static final int heartbeatInterval;

  private static final org.xnio.OptionMap SERVICE_OPTIONS;

  public static final org.xnio.OptionMap CONNECTION_OPTIONS;

  public org.jboss.as.host.controller.operations.NativeManagementServices();
    Code:
       0: aload_0
       1: invokespecial #1                  // Method java/lang/Object."<init>":()V
       4: return

  static synchronized void installManagementWorkerService(org.jboss.msc.service.ServiceTarget, org.jboss.msc.service.ServiceRegistry);
    Code:
       0: aload_1
       1: getstatic     #2                  // Field org/jboss/as/server/mgmt/ManagementWorkerService.SERVICE_NAME:Lorg/jboss/msc/service/ServiceName;
       4: invokeinterface #3,  2            // InterfaceMethod org/jboss/msc/service/ServiceRegistry.getService:(Lorg/jboss/msc/service/ServiceName;)Lorg/jboss/msc/service/ServiceController;
       9: ifnonnull     16
      12: aload_0
      13: invokestatic  #4                  // Method org/jboss/as/server/mgmt/ManagementWorkerService.installService:(Lorg/jboss/msc/service/ServiceTarget;)V
      16: return

  static synchronized void installRemotingServicesIfNotInstalled(org.jboss.msc.service.ServiceTarget, java.lang.String, org.jboss.msc.service.ServiceRegistry, boolean);
    Code:
       0: aload_2
       1: getstatic     #5                  // Field org/jboss/as/remoting/management/ManagementRemotingServices.MANAGEMENT_ENDPOINT:Lorg/jboss/msc/service/ServiceName;
       4: invokeinterface #3,  2            // InterfaceMethod org/jboss/msc/service/ServiceRegistry.getService:(Lorg/jboss/msc/service/ServiceName;)Lorg/jboss/msc/service/ServiceController;
       9: ifnonnull     74
      12: aload_0
      13: getstatic     #5                  // Field org/jboss/as/remoting/management/ManagementRemotingServices.MANAGEMENT_ENDPOINT:Lorg/jboss/msc/service/ServiceName;
      16: invokestatic  #6                  // Method org/jboss/as/remoting/management/ManagementChannelRegistryService.addService:(Lorg/jboss/msc/service/ServiceTarget;Lorg/jboss/msc/service/ServiceName;)V
      19: aload_0
      20: getstatic     #5                  // Field org/jboss/as/remoting/management/ManagementRemotingServices.MANAGEMENT_ENDPOINT:Lorg/jboss/msc/service/ServiceName;
      23: aload_1
      24: getstatic     #7                  // Field org/jboss/as/remoting/EndpointService$EndpointType.MANAGEMENT:Lorg/jboss/as/remoting/EndpointService$EndpointType;
      27: getstatic     #8                  // Field CONNECTION_OPTIONS:Lorg/xnio/OptionMap;
      30: invokestatic  #9                  // Method org/jboss/as/remoting/management/ManagementRemotingServices.installRemotingManagementEndpoint:(Lorg/jboss/msc/service/ServiceTarget;Lorg/jboss/msc/service/ServiceName;Ljava/lang/String;Lorg/jboss/as/remoting/EndpointService$EndpointType;Lorg/xnio/OptionMap;)V
      33: aload_0
      34: getstatic     #5                  // Field org/jboss/as/remoting/management/ManagementRemotingServices.MANAGEMENT_ENDPOINT:Lorg/jboss/msc/service/ServiceName;
      37: ldc           #11                 // String server
      39: getstatic     #12                 // Field org/jboss/as/host/controller/mgmt/ServerToHostOperationHandlerFactoryService.SERVICE_NAME:Lorg/jboss/msc/service/ServiceName;
      42: getstatic     #13                 // Field SERVICE_OPTIONS:Lorg/xnio/OptionMap;
      45: iload_3
      46: invokestatic  #14                 // Method org/jboss/as/remoting/management/ManagementRemotingServices.installManagementChannelOpenListenerService:(Lorg/jboss/msc/service/ServiceTarget;Lorg/jboss/msc/service/ServiceName;Ljava/lang/String;Lorg/jboss/msc/service/ServiceName;Lorg/xnio/OptionMap;Z)V
      49: aload_0
      50: getstatic     #5                  // Field org/jboss/as/remoting/management/ManagementRemotingServices.MANAGEMENT_ENDPOINT:Lorg/jboss/msc/service/ServiceName;
      53: new           #15                 // class org/jboss/as/controller/remote/ModelControllerClientOperationHandlerFactoryService
      56: dup
      57: invokespecial #16                 // Method org/jboss/as/controller/remote/ModelControllerClientOperationHandlerFactoryService."<init>":()V
      60: getstatic     #17                 // Field org/jboss/as/host/controller/DomainModelControllerService.SERVICE_NAME:Lorg/jboss/msc/service/ServiceName;
      63: ldc           #18                 // String management
      65: getstatic     #19                 // Field org/jboss/as/host/controller/HostControllerService.HC_EXECUTOR_SERVICE_NAME:Lorg/jboss/msc/service/ServiceName;
      68: getstatic     #20                 // Field org/jboss/as/host/controller/HostControllerService.HC_SCHEDULED_EXECUTOR_SERVICE_NAME:Lorg/jboss/msc/service/ServiceName;
      71: invokestatic  #21                 // Method org/jboss/as/remoting/management/ManagementRemotingServices.installManagementChannelServices:(Lorg/jboss/msc/service/ServiceTarget;Lorg/jboss/msc/service/ServiceName;Lorg/jboss/as/controller/remote/AbstractModelControllerOperationHandlerFactoryService;Lorg/jboss/msc/service/ServiceName;Ljava/lang/String;Lorg/jboss/msc/service/ServiceName;Lorg/jboss/msc/service/ServiceName;)V
      74: return

  static {};
    Code:
       0: getstatic     #22                 // Field org/xnio/OptionMap.EMPTY:Lorg/xnio/OptionMap;
       3: putstatic     #13                 // Field SERVICE_OPTIONS:Lorg/xnio/OptionMap;
       6: getstatic     #23                 // Field org/jboss/remoting3/RemotingOptions.HEARTBEAT_INTERVAL:Lorg/xnio/Option;
       9: sipush        15000
      12: invokestatic  #25                 // Method java/lang/Integer.valueOf:(I)Ljava/lang/Integer;
      15: getstatic     #26                 // Field org/xnio/Options.READ_TIMEOUT:Lorg/xnio/Option;
      18: ldc           #27                 // int 45000
      20: invokestatic  #25                 // Method java/lang/Integer.valueOf:(I)Ljava/lang/Integer;
      23: invokestatic  #28                 // Method org/xnio/OptionMap.create:(Lorg/xnio/Option;Ljava/lang/Object;Lorg/xnio/Option;Ljava/lang/Object;)Lorg/xnio/OptionMap;
      26: putstatic     #8                  // Field CONNECTION_OPTIONS:Lorg/xnio/OptionMap;
      29: return
}
