Compiled from "MethodInfo.java"
final class org.apache.camel.component.bean.MethodInfo$DynamicRouterExpression extends org.apache.camel.support.ExpressionAdapter {
  private final java.lang.Object pojo;

  final org.apache.camel.component.bean.MethodInfo this$0;

  private org.apache.camel.component.bean.MethodInfo$DynamicRouterExpression(org.apache.camel.component.bean.MethodInfo, java.lang.Object);
    Code:
       0: aload_0
       1: aload_1
       2: putfield      #18                 // Field this$0:Lorg/apache/camel/component/bean/MethodInfo;
       5: aload_0
       6: invokespecial #21                 // Method org/apache/camel/support/ExpressionAdapter."<init>":()V
       9: aload_0
      10: aload_2
      11: putfield      #23                 // Field pojo:Ljava/lang/Object;
      14: return

  public java.lang.Object evaluate(org.apache.camel.Exchange);
    Code:
       0: aload_0
       1: getfield      #18                 // Field this$0:Lorg/apache/camel/component/bean/MethodInfo;
       4: invokestatic  #33                 // Method org/apache/camel/component/bean/MethodInfo.access$000:(Lorg/apache/camel/component/bean/MethodInfo;)Lorg/apache/camel/Expression;
       7: aload_1
       8: ldc           #35                 // class "[Ljava/lang/Object;"
      10: invokeinterface #40,  3           // InterfaceMethod org/apache/camel/Expression.evaluate:(Lorg/apache/camel/Exchange;Ljava/lang/Class;)Ljava/lang/Object;
      15: checkcast     #35                 // class "[Ljava/lang/Object;"
      18: astore_2
      19: aload_0
      20: getfield      #18                 // Field this$0:Lorg/apache/camel/component/bean/MethodInfo;
      23: aload_0
      24: getfield      #18                 // Field this$0:Lorg/apache/camel/component/bean/MethodInfo;
      27: invokestatic  #44                 // Method org/apache/camel/component/bean/MethodInfo.access$100:(Lorg/apache/camel/component/bean/MethodInfo;)Ljava/lang/reflect/Method;
      30: aload_0
      31: getfield      #23                 // Field pojo:Ljava/lang/Object;
      34: aload_2
      35: aload_1
      36: invokevirtual #48                 // Method org/apache/camel/component/bean/MethodInfo.invoke:(Ljava/lang/reflect/Method;Ljava/lang/Object;[Ljava/lang/Object;Lorg/apache/camel/Exchange;)Ljava/lang/Object;
      39: areturn
      40: astore_3
      41: aload_3
      42: invokestatic  #56                 // Method org/apache/camel/util/ObjectHelper.wrapRuntimeCamelException:(Ljava/lang/Throwable;)Lorg/apache/camel/RuntimeCamelException;
      45: athrow
    Exception table:
       from    to  target type
          19    39    40   Class java/lang/Exception

  public java.lang.String toString();
    Code:
       0: new           #65                 // class java/lang/StringBuilder
       3: dup
       4: invokespecial #66                 // Method java/lang/StringBuilder."<init>":()V
       7: ldc           #68                 // String DynamicRouter[invoking:
       9: invokevirtual #72                 // Method java/lang/StringBuilder.append:(Ljava/lang/String;)Ljava/lang/StringBuilder;
      12: aload_0
      13: getfield      #18                 // Field this$0:Lorg/apache/camel/component/bean/MethodInfo;
      16: invokestatic  #44                 // Method org/apache/camel/component/bean/MethodInfo.access$100:(Lorg/apache/camel/component/bean/MethodInfo;)Ljava/lang/reflect/Method;
      19: invokevirtual #75                 // Method java/lang/StringBuilder.append:(Ljava/lang/Object;)Ljava/lang/StringBuilder;
      22: ldc           #77                 // String  on bean:
      24: invokevirtual #72                 // Method java/lang/StringBuilder.append:(Ljava/lang/String;)Ljava/lang/StringBuilder;
      27: aload_0
      28: getfield      #23                 // Field pojo:Ljava/lang/Object;
      31: invokevirtual #75                 // Method java/lang/StringBuilder.append:(Ljava/lang/Object;)Ljava/lang/StringBuilder;
      34: ldc           #79                 // String ]
      36: invokevirtual #72                 // Method java/lang/StringBuilder.append:(Ljava/lang/String;)Ljava/lang/StringBuilder;
      39: invokevirtual #81                 // Method java/lang/StringBuilder.toString:()Ljava/lang/String;
      42: areturn

  org.apache.camel.component.bean.MethodInfo$DynamicRouterExpression(org.apache.camel.component.bean.MethodInfo, java.lang.Object, org.apache.camel.component.bean.MethodInfo$1);
    Code:
       0: aload_0
       1: aload_1
       2: aload_2
       3: invokespecial #84                 // Method "<init>":(Lorg/apache/camel/component/bean/MethodInfo;Ljava/lang/Object;)V
       6: return
}
