Compiled from "AuditLogHandler.java"
class org.jboss.as.controller.audit.AuditLogHandler$StandardFailureCountHandler implements org.jboss.as.controller.audit.AuditLogHandler$FailureCountHandler {
  final org.jboss.as.controller.audit.AuditLogHandler this$0;

  org.jboss.as.controller.audit.AuditLogHandler$StandardFailureCountHandler(org.jboss.as.controller.audit.AuditLogHandler);
    Code:
       0: aload_0
       1: aload_1
       2: putfield      #1                  // Field this$0:Lorg/jboss/as/controller/audit/AuditLogHandler;
       5: aload_0
       6: invokespecial #2                  // Method java/lang/Object."<init>":()V
       9: return

  public void success();
    Code:
       0: aload_0
       1: getfield      #1                  // Field this$0:Lorg/jboss/as/controller/audit/AuditLogHandler;
       4: iconst_0
       5: invokestatic  #3                  // Method org/jboss/as/controller/audit/AuditLogHandler.access$002:(Lorg/jboss/as/controller/audit/AuditLogHandler;I)I
       8: pop
       9: return

  public void failure(java.lang.Throwable);
    Code:
       0: aload_0
       1: getfield      #1                  // Field this$0:Lorg/jboss/as/controller/audit/AuditLogHandler;
       4: invokestatic  #4                  // Method org/jboss/as/controller/audit/AuditLogHandler.access$008:(Lorg/jboss/as/controller/audit/AuditLogHandler;)I
       7: pop
       8: getstatic     #5                  // Field org/jboss/as/controller/logging/ControllerLogger.MGMT_OP_LOGGER:Lorg/jboss/as/controller/logging/ControllerLogger;
      11: aload_1
      12: aload_0
      13: getfield      #1                  // Field this$0:Lorg/jboss/as/controller/audit/AuditLogHandler;
      16: getfield      #6                  // Field org/jboss/as/controller/audit/AuditLogHandler.name:Ljava/lang/String;
      19: invokeinterface #7,  3            // InterfaceMethod org/jboss/as/controller/logging/ControllerLogger.logHandlerWriteFailed:(Ljava/lang/Throwable;Ljava/lang/String;)V
      24: aload_0
      25: getfield      #1                  // Field this$0:Lorg/jboss/as/controller/audit/AuditLogHandler;
      28: invokevirtual #8                  // Method org/jboss/as/controller/audit/AuditLogHandler.hasTooManyFailures:()Z
      31: ifeq          56
      34: getstatic     #5                  // Field org/jboss/as/controller/logging/ControllerLogger.MGMT_OP_LOGGER:Lorg/jboss/as/controller/logging/ControllerLogger;
      37: aload_0
      38: getfield      #1                  // Field this$0:Lorg/jboss/as/controller/audit/AuditLogHandler;
      41: invokestatic  #9                  // Method org/jboss/as/controller/audit/AuditLogHandler.access$000:(Lorg/jboss/as/controller/audit/AuditLogHandler;)I
      44: aload_0
      45: getfield      #1                  // Field this$0:Lorg/jboss/as/controller/audit/AuditLogHandler;
      48: getfield      #6                  // Field org/jboss/as/controller/audit/AuditLogHandler.name:Ljava/lang/String;
      51: invokeinterface #10,  3           // InterfaceMethod org/jboss/as/controller/logging/ControllerLogger.disablingLogHandlerDueToFailures:(ILjava/lang/String;)V
      56: return
}
