Compiled from "TestDecorator.java"
public class junit.extensions.TestDecorator extends junit.framework.Assert implements junit.framework.Test {
  protected junit.framework.Test fTest;

  public junit.extensions.TestDecorator(junit.framework.Test);
    Code:
       0: aload_0
       1: invokespecial #1                  // Method junit/framework/Assert."<init>":()V
       4: aload_0
       5: aload_1
       6: putfield      #2                  // Field fTest:Ljunit/framework/Test;
       9: return

  public void basicRun(junit.framework.TestResult);
    Code:
       0: aload_0
       1: getfield      #2                  // Field fTest:Ljunit/framework/Test;
       4: aload_1
       5: invokeinterface #3,  2            // InterfaceMethod junit/framework/Test.run:(Ljunit/framework/TestResult;)V
      10: return

  public int countTestCases();
    Code:
       0: aload_0
       1: getfield      #2                  // Field fTest:Ljunit/framework/Test;
       4: invokeinterface #4,  1            // InterfaceMethod junit/framework/Test.countTestCases:()I
       9: ireturn

  public void run(junit.framework.TestResult);
    Code:
       0: aload_0
       1: aload_1
       2: invokevirtual #5                  // Method basicRun:(Ljunit/framework/TestResult;)V
       5: return

  public java.lang.String toString();
    Code:
       0: aload_0
       1: getfield      #2                  // Field fTest:Ljunit/framework/Test;
       4: invokevirtual #6                  // Method java/lang/Object.toString:()Ljava/lang/String;
       7: areturn

  public junit.framework.Test getTest();
    Code:
       0: aload_0
       1: getfield      #2                  // Field fTest:Ljunit/framework/Test;
       4: areturn
}
