Compiled from "ClientRegistrationsBeanDefinitionParser.java"
public final class org.springframework.security.config.oauth2.client.ClientRegistrationsBeanDefinitionParser implements org.springframework.beans.factory.xml.BeanDefinitionParser {
  private static final java.lang.String ELT_CLIENT_REGISTRATION;

  private static final java.lang.String ELT_PROVIDER;

  private static final java.lang.String ATT_REGISTRATION_ID;

  private static final java.lang.String ATT_CLIENT_ID;

  private static final java.lang.String ATT_CLIENT_SECRET;

  private static final java.lang.String ATT_CLIENT_AUTHENTICATION_METHOD;

  private static final java.lang.String ATT_AUTHORIZATION_GRANT_TYPE;

  private static final java.lang.String ATT_REDIRECT_URI;

  private static final java.lang.String ATT_SCOPE;

  private static final java.lang.String ATT_CLIENT_NAME;

  private static final java.lang.String ATT_PROVIDER_ID;

  private static final java.lang.String ATT_AUTHORIZATION_URI;

  private static final java.lang.String ATT_TOKEN_URI;

  private static final java.lang.String ATT_USER_INFO_URI;

  private static final java.lang.String ATT_USER_INFO_AUTHENTICATION_METHOD;

  private static final java.lang.String ATT_USER_INFO_USER_NAME_ATTRIBUTE;

  private static final java.lang.String ATT_JWK_SET_URI;

  private static final java.lang.String ATT_ISSUER_URI;

  public org.springframework.security.config.oauth2.client.ClientRegistrationsBeanDefinitionParser();
    Code:
       0: aload_0
       1: invokespecial #1                  // Method java/lang/Object."<init>":()V
       4: return

  public org.springframework.beans.factory.config.BeanDefinition parse(org.w3c.dom.Element, org.springframework.beans.factory.xml.ParserContext);
    Code:
       0: new           #2                  // class org/springframework/beans/factory/parsing/CompositeComponentDefinition
       3: dup
       4: aload_1
       5: invokeinterface #3,  1            // InterfaceMethod org/w3c/dom/Element.getTagName:()Ljava/lang/String;
      10: aload_2
      11: aload_1
      12: invokevirtual #4                  // Method org/springframework/beans/factory/xml/ParserContext.extractSource:(Ljava/lang/Object;)Ljava/lang/Object;
      15: invokespecial #5                  // Method org/springframework/beans/factory/parsing/CompositeComponentDefinition."<init>":(Ljava/lang/String;Ljava/lang/Object;)V
      18: astore_3
      19: aload_2
      20: aload_3
      21: invokevirtual #6                  // Method org/springframework/beans/factory/xml/ParserContext.pushContainingComponent:(Lorg/springframework/beans/factory/parsing/CompositeComponentDefinition;)V
      24: aload_0
      25: aload_1
      26: invokespecial #7                  // Method getProviders:(Lorg/w3c/dom/Element;)Ljava/util/Map;
      29: astore        4
      31: aload_0
      32: aload_1
      33: aload_2
      34: aload         4
      36: invokespecial #8                  // Method getClientRegistrations:(Lorg/w3c/dom/Element;Lorg/springframework/beans/factory/xml/ParserContext;Ljava/util/Map;)Ljava/util/List;
      39: astore        5
      41: ldc           #9                  // class org/springframework/security/oauth2/client/registration/InMemoryClientRegistrationRepository
      43: invokestatic  #10                 // Method org/springframework/beans/factory/support/BeanDefinitionBuilder.rootBeanDefinition:(Ljava/lang/Class;)Lorg/springframework/beans/factory/support/BeanDefinitionBuilder;
      46: aload         5
      48: invokevirtual #11                 // Method org/springframework/beans/factory/support/BeanDefinitionBuilder.addConstructorArgValue:(Ljava/lang/Object;)Lorg/springframework/beans/factory/support/BeanDefinitionBuilder;
      51: invokevirtual #12                 // Method org/springframework/beans/factory/support/BeanDefinitionBuilder.getBeanDefinition:()Lorg/springframework/beans/factory/support/AbstractBeanDefinition;
      54: astore        6
      56: aload_2
      57: invokevirtual #13                 // Method org/springframework/beans/factory/xml/ParserContext.getReaderContext:()Lorg/springframework/beans/factory/xml/XmlReaderContext;
      60: aload         6
      62: invokevirtual #14                 // Method org/springframework/beans/factory/xml/XmlReaderContext.generateBeanName:(Lorg/springframework/beans/factory/config/BeanDefinition;)Ljava/lang/String;
      65: astore        7
      67: aload_2
      68: new           #15                 // class org/springframework/beans/factory/parsing/BeanComponentDefinition
      71: dup
      72: aload         6
      74: aload         7
      76: invokespecial #16                 // Method org/springframework/beans/factory/parsing/BeanComponentDefinition."<init>":(Lorg/springframework/beans/factory/config/BeanDefinition;Ljava/lang/String;)V
      79: invokevirtual #17                 // Method org/springframework/beans/factory/xml/ParserContext.registerBeanComponent:(Lorg/springframework/beans/factory/parsing/BeanComponentDefinition;)V
      82: aload_2
      83: invokevirtual #18                 // Method org/springframework/beans/factory/xml/ParserContext.popAndRegisterContainingComponent:()V
      86: aconst_null
      87: areturn

  private java.util.List<org.springframework.security.oauth2.client.registration.ClientRegistration> getClientRegistrations(org.w3c.dom.Element, org.springframework.beans.factory.xml.ParserContext, java.util.Map<java.lang.String, java.util.Map<java.lang.String, java.lang.String>>);
    Code:
       0: aload_1
       1: ldc           #20                 // String client-registration
       3: invokestatic  #21                 // Method org/springframework/util/xml/DomUtils.getChildElementsByTagName:(Lorg/w3c/dom/Element;Ljava/lang/String;)Ljava/util/List;
       6: astore        4
       8: new           #22                 // class java/util/ArrayList
      11: dup
      12: invokespecial #23                 // Method java/util/ArrayList."<init>":()V
      15: astore        5
      17: aload         4
      19: invokeinterface #24,  1           // InterfaceMethod java/util/List.iterator:()Ljava/util/Iterator;
      24: astore        6
      26: aload         6
      28: invokeinterface #25,  1           // InterfaceMethod java/util/Iterator.hasNext:()Z
      33: ifeq          355
      36: aload         6
      38: invokeinterface #26,  1           // InterfaceMethod java/util/Iterator.next:()Ljava/lang/Object;
      43: checkcast     #27                 // class org/w3c/dom/Element
      46: astore        7
      48: aload         7
      50: ldc           #28                 // String registration-id
      52: invokeinterface #29,  2           // InterfaceMethod org/w3c/dom/Element.getAttribute:(Ljava/lang/String;)Ljava/lang/String;
      57: astore        8
      59: aload         7
      61: ldc           #30                 // String provider-id
      63: invokeinterface #29,  2           // InterfaceMethod org/w3c/dom/Element.getAttribute:(Ljava/lang/String;)Ljava/lang/String;
      68: astore        9
      70: aload         8
      72: aload         9
      74: aload_3
      75: invokestatic  #31                 // Method getBuilderFromIssuerIfPossible:(Ljava/lang/String;Ljava/lang/String;Ljava/util/Map;)Lorg/springframework/security/oauth2/client/registration/ClientRegistration$Builder;
      78: astore        10
      80: aload         10
      82: ifnonnull     126
      85: aload         8
      87: aload         9
      89: aload_3
      90: invokestatic  #32                 // Method getBuilder:(Ljava/lang/String;Ljava/lang/String;Ljava/util/Map;)Lorg/springframework/security/oauth2/client/registration/ClientRegistration$Builder;
      93: astore        10
      95: aload         10
      97: ifnonnull     126
     100: aload_2
     101: aload_1
     102: invokevirtual #4                  // Method org/springframework/beans/factory/xml/ParserContext.extractSource:(Ljava/lang/Object;)Ljava/lang/Object;
     105: astore        11
     107: aload_2
     108: invokevirtual #13                 // Method org/springframework/beans/factory/xml/ParserContext.getReaderContext:()Lorg/springframework/beans/factory/xml/XmlReaderContext;
     111: aload         9
     113: aload         8
     115: invokestatic  #33                 // Method getErrorMessage:(Ljava/lang/String;Ljava/lang/String;)Ljava/lang/String;
     118: aload         11
     120: invokevirtual #34                 // Method org/springframework/beans/factory/xml/XmlReaderContext.error:(Ljava/lang/String;Ljava/lang/Object;)V
     123: goto          26
     126: aload         7
     128: ldc           #35                 // String client-id
     130: invokeinterface #29,  2           // InterfaceMethod org/w3c/dom/Element.getAttribute:(Ljava/lang/String;)Ljava/lang/String;
     135: invokestatic  #36                 // Method getOptionalIfNotEmpty:(Ljava/lang/String;)Ljava/util/Optional;
     138: aload         10
     140: dup
     141: invokevirtual #37                 // Method java/lang/Object.getClass:()Ljava/lang/Class;
     144: pop
     145: invokedynamic #38,  0             // InvokeDynamic #0:accept:(Lorg/springframework/security/oauth2/client/registration/ClientRegistration$Builder;)Ljava/util/function/Consumer;
     150: invokevirtual #39                 // Method java/util/Optional.ifPresent:(Ljava/util/function/Consumer;)V
     153: aload         7
     155: ldc           #40                 // String client-secret
     157: invokeinterface #29,  2           // InterfaceMethod org/w3c/dom/Element.getAttribute:(Ljava/lang/String;)Ljava/lang/String;
     162: invokestatic  #36                 // Method getOptionalIfNotEmpty:(Ljava/lang/String;)Ljava/util/Optional;
     165: aload         10
     167: dup
     168: invokevirtual #37                 // Method java/lang/Object.getClass:()Ljava/lang/Class;
     171: pop
     172: invokedynamic #41,  0             // InvokeDynamic #1:accept:(Lorg/springframework/security/oauth2/client/registration/ClientRegistration$Builder;)Ljava/util/function/Consumer;
     177: invokevirtual #39                 // Method java/util/Optional.ifPresent:(Ljava/util/function/Consumer;)V
     180: aload         7
     182: ldc           #42                 // String client-authentication-method
     184: invokeinterface #29,  2           // InterfaceMethod org/w3c/dom/Element.getAttribute:(Ljava/lang/String;)Ljava/lang/String;
     189: invokestatic  #36                 // Method getOptionalIfNotEmpty:(Ljava/lang/String;)Ljava/util/Optional;
     192: invokedynamic #43,  0             // InvokeDynamic #2:apply:()Ljava/util/function/Function;
     197: invokevirtual #44                 // Method java/util/Optional.map:(Ljava/util/function/Function;)Ljava/util/Optional;
     200: aload         10
     202: dup
     203: invokevirtual #37                 // Method java/lang/Object.getClass:()Ljava/lang/Class;
     206: pop
     207: invokedynamic #45,  0             // InvokeDynamic #3:accept:(Lorg/springframework/security/oauth2/client/registration/ClientRegistration$Builder;)Ljava/util/function/Consumer;
     212: invokevirtual #39                 // Method java/util/Optional.ifPresent:(Ljava/util/function/Consumer;)V
     215: aload         7
     217: ldc           #46                 // String authorization-grant-type
     219: invokeinterface #29,  2           // InterfaceMethod org/w3c/dom/Element.getAttribute:(Ljava/lang/String;)Ljava/lang/String;
     224: invokestatic  #36                 // Method getOptionalIfNotEmpty:(Ljava/lang/String;)Ljava/util/Optional;
     227: invokedynamic #47,  0             // InvokeDynamic #4:apply:()Ljava/util/function/Function;
     232: invokevirtual #44                 // Method java/util/Optional.map:(Ljava/util/function/Function;)Ljava/util/Optional;
     235: aload         10
     237: dup
     238: invokevirtual #37                 // Method java/lang/Object.getClass:()Ljava/lang/Class;
     241: pop
     242: invokedynamic #48,  0             // InvokeDynamic #5:accept:(Lorg/springframework/security/oauth2/client/registration/ClientRegistration$Builder;)Ljava/util/function/Consumer;
     247: invokevirtual #39                 // Method java/util/Optional.ifPresent:(Ljava/util/function/Consumer;)V
     250: aload         7
     252: ldc           #49                 // String redirect-uri
     254: invokeinterface #29,  2           // InterfaceMethod org/w3c/dom/Element.getAttribute:(Ljava/lang/String;)Ljava/lang/String;
     259: invokestatic  #36                 // Method getOptionalIfNotEmpty:(Ljava/lang/String;)Ljava/util/Optional;
     262: aload         10
     264: dup
     265: invokevirtual #37                 // Method java/lang/Object.getClass:()Ljava/lang/Class;
     268: pop
     269: invokedynamic #50,  0             // InvokeDynamic #6:accept:(Lorg/springframework/security/oauth2/client/registration/ClientRegistration$Builder;)Ljava/util/function/Consumer;
     274: invokevirtual #39                 // Method java/util/Optional.ifPresent:(Ljava/util/function/Consumer;)V
     277: aload         7
     279: ldc           #51                 // String scope
     281: invokeinterface #29,  2           // InterfaceMethod org/w3c/dom/Element.getAttribute:(Ljava/lang/String;)Ljava/lang/String;
     286: invokestatic  #36                 // Method getOptionalIfNotEmpty:(Ljava/lang/String;)Ljava/util/Optional;
     289: invokedynamic #52,  0             // InvokeDynamic #7:apply:()Ljava/util/function/Function;
     294: invokevirtual #44                 // Method java/util/Optional.map:(Ljava/util/function/Function;)Ljava/util/Optional;
     297: aload         10
     299: dup
     300: invokevirtual #37                 // Method java/lang/Object.getClass:()Ljava/lang/Class;
     303: pop
     304: invokedynamic #53,  0             // InvokeDynamic #8:accept:(Lorg/springframework/security/oauth2/client/registration/ClientRegistration$Builder;)Ljava/util/function/Consumer;
     309: invokevirtual #39                 // Method java/util/Optional.ifPresent:(Ljava/util/function/Consumer;)V
     312: aload         7
     314: ldc           #54                 // String client-name
     316: invokeinterface #29,  2           // InterfaceMethod org/w3c/dom/Element.getAttribute:(Ljava/lang/String;)Ljava/lang/String;
     321: invokestatic  #36                 // Method getOptionalIfNotEmpty:(Ljava/lang/String;)Ljava/util/Optional;
     324: aload         10
     326: dup
     327: invokevirtual #37                 // Method java/lang/Object.getClass:()Ljava/lang/Class;
     330: pop
     331: invokedynamic #55,  0             // InvokeDynamic #9:accept:(Lorg/springframework/security/oauth2/client/registration/ClientRegistration$Builder;)Ljava/util/function/Consumer;
     336: invokevirtual #39                 // Method java/util/Optional.ifPresent:(Ljava/util/function/Consumer;)V
     339: aload         5
     341: aload         10
     343: invokevirtual #56                 // Method org/springframework/security/oauth2/client/registration/ClientRegistration$Builder.build:()Lorg/springframework/security/oauth2/client/registration/ClientRegistration;
     346: invokeinterface #57,  2           // InterfaceMethod java/util/List.add:(Ljava/lang/Object;)Z
     351: pop
     352: goto          26
     355: aload         5
     357: areturn

  private java.util.Map<java.lang.String, java.util.Map<java.lang.String, java.lang.String>> getProviders(org.w3c.dom.Element);
    Code:
       0: aload_1
       1: ldc           #58                 // String provider
       3: invokestatic  #21                 // Method org/springframework/util/xml/DomUtils.getChildElementsByTagName:(Lorg/w3c/dom/Element;Ljava/lang/String;)Ljava/util/List;
       6: astore_2
       7: new           #59                 // class java/util/HashMap
      10: dup
      11: invokespecial #60                 // Method java/util/HashMap."<init>":()V
      14: astore_3
      15: aload_2
      16: invokeinterface #24,  1           // InterfaceMethod java/util/List.iterator:()Ljava/util/Iterator;
      21: astore        4
      23: aload         4
      25: invokeinterface #25,  1           // InterfaceMethod java/util/Iterator.hasNext:()Z
      30: ifeq          245
      33: aload         4
      35: invokeinterface #26,  1           // InterfaceMethod java/util/Iterator.next:()Ljava/lang/Object;
      40: checkcast     #27                 // class org/w3c/dom/Element
      43: astore        5
      45: new           #59                 // class java/util/HashMap
      48: dup
      49: invokespecial #60                 // Method java/util/HashMap."<init>":()V
      52: astore        6
      54: aload         5
      56: ldc           #30                 // String provider-id
      58: invokeinterface #29,  2           // InterfaceMethod org/w3c/dom/Element.getAttribute:(Ljava/lang/String;)Ljava/lang/String;
      63: astore        7
      65: aload         6
      67: ldc           #30                 // String provider-id
      69: aload         7
      71: invokeinterface #61,  3           // InterfaceMethod java/util/Map.put:(Ljava/lang/Object;Ljava/lang/Object;)Ljava/lang/Object;
      76: pop
      77: aload         5
      79: ldc           #62                 // String authorization-uri
      81: invokeinterface #29,  2           // InterfaceMethod org/w3c/dom/Element.getAttribute:(Ljava/lang/String;)Ljava/lang/String;
      86: invokestatic  #36                 // Method getOptionalIfNotEmpty:(Ljava/lang/String;)Ljava/util/Optional;
      89: aload         6
      91: invokedynamic #63,  0             // InvokeDynamic #10:accept:(Ljava/util/Map;)Ljava/util/function/Consumer;
      96: invokevirtual #39                 // Method java/util/Optional.ifPresent:(Ljava/util/function/Consumer;)V
      99: aload         5
     101: ldc           #64                 // String token-uri
     103: invokeinterface #29,  2           // InterfaceMethod org/w3c/dom/Element.getAttribute:(Ljava/lang/String;)Ljava/lang/String;
     108: invokestatic  #36                 // Method getOptionalIfNotEmpty:(Ljava/lang/String;)Ljava/util/Optional;
     111: aload         6
     113: invokedynamic #65,  0             // InvokeDynamic #11:accept:(Ljava/util/Map;)Ljava/util/function/Consumer;
     118: invokevirtual #39                 // Method java/util/Optional.ifPresent:(Ljava/util/function/Consumer;)V
     121: aload         5
     123: ldc           #66                 // String user-info-uri
     125: invokeinterface #29,  2           // InterfaceMethod org/w3c/dom/Element.getAttribute:(Ljava/lang/String;)Ljava/lang/String;
     130: invokestatic  #36                 // Method getOptionalIfNotEmpty:(Ljava/lang/String;)Ljava/util/Optional;
     133: aload         6
     135: invokedynamic #67,  0             // InvokeDynamic #12:accept:(Ljava/util/Map;)Ljava/util/function/Consumer;
     140: invokevirtual #39                 // Method java/util/Optional.ifPresent:(Ljava/util/function/Consumer;)V
     143: aload         5
     145: ldc           #68                 // String user-info-authentication-method
     147: invokeinterface #29,  2           // InterfaceMethod org/w3c/dom/Element.getAttribute:(Ljava/lang/String;)Ljava/lang/String;
     152: invokestatic  #36                 // Method getOptionalIfNotEmpty:(Ljava/lang/String;)Ljava/util/Optional;
     155: aload         6
     157: invokedynamic #69,  0             // InvokeDynamic #13:accept:(Ljava/util/Map;)Ljava/util/function/Consumer;
     162: invokevirtual #39                 // Method java/util/Optional.ifPresent:(Ljava/util/function/Consumer;)V
     165: aload         5
     167: ldc           #70                 // String user-info-user-name-attribute
     169: invokeinterface #29,  2           // InterfaceMethod org/w3c/dom/Element.getAttribute:(Ljava/lang/String;)Ljava/lang/String;
     174: invokestatic  #36                 // Method getOptionalIfNotEmpty:(Ljava/lang/String;)Ljava/util/Optional;
     177: aload         6
     179: invokedynamic #71,  0             // InvokeDynamic #14:accept:(Ljava/util/Map;)Ljava/util/function/Consumer;
     184: invokevirtual #39                 // Method java/util/Optional.ifPresent:(Ljava/util/function/Consumer;)V
     187: aload         5
     189: ldc           #72                 // String jwk-set-uri
     191: invokeinterface #29,  2           // InterfaceMethod org/w3c/dom/Element.getAttribute:(Ljava/lang/String;)Ljava/lang/String;
     196: invokestatic  #36                 // Method getOptionalIfNotEmpty:(Ljava/lang/String;)Ljava/util/Optional;
     199: aload         6
     201: invokedynamic #73,  0             // InvokeDynamic #15:accept:(Ljava/util/Map;)Ljava/util/function/Consumer;
     206: invokevirtual #39                 // Method java/util/Optional.ifPresent:(Ljava/util/function/Consumer;)V
     209: aload         5
     211: ldc           #74                 // String issuer-uri
     213: invokeinterface #29,  2           // InterfaceMethod org/w3c/dom/Element.getAttribute:(Ljava/lang/String;)Ljava/lang/String;
     218: invokestatic  #36                 // Method getOptionalIfNotEmpty:(Ljava/lang/String;)Ljava/util/Optional;
     221: aload         6
     223: invokedynamic #75,  0             // InvokeDynamic #16:accept:(Ljava/util/Map;)Ljava/util/function/Consumer;
     228: invokevirtual #39                 // Method java/util/Optional.ifPresent:(Ljava/util/function/Consumer;)V
     231: aload_3
     232: aload         7
     234: aload         6
     236: invokeinterface #61,  3           // InterfaceMethod java/util/Map.put:(Ljava/lang/Object;Ljava/lang/Object;)Ljava/lang/Object;
     241: pop
     242: goto          23
     245: aload_3
     246: areturn

  private static org.springframework.security.oauth2.client.registration.ClientRegistration$Builder getBuilderFromIssuerIfPossible(java.lang.String, java.lang.String, java.util.Map<java.lang.String, java.util.Map<java.lang.String, java.lang.String>>);
    Code:
       0: aload_1
       1: ifnull        8
       4: aload_1
       5: goto          9
       8: aload_0
       9: astore_3
      10: aload_2
      11: aload_3
      12: invokeinterface #76,  2           // InterfaceMethod java/util/Map.containsKey:(Ljava/lang/Object;)Z
      17: ifeq          73
      20: aload_2
      21: aload_3
      22: invokeinterface #77,  2           // InterfaceMethod java/util/Map.get:(Ljava/lang/Object;)Ljava/lang/Object;
      27: checkcast     #78                 // class java/util/Map
      30: astore        4
      32: aload         4
      34: ldc           #74                 // String issuer-uri
      36: invokeinterface #77,  2           // InterfaceMethod java/util/Map.get:(Ljava/lang/Object;)Ljava/lang/Object;
      41: checkcast     #79                 // class java/lang/String
      44: astore        5
      46: aload         5
      48: invokestatic  #80                 // Method org/springframework/util/StringUtils.isEmpty:(Ljava/lang/Object;)Z
      51: ifne          73
      54: aload         5
      56: invokestatic  #81                 // Method org/springframework/security/oauth2/client/registration/ClientRegistrations.fromIssuerLocation:(Ljava/lang/String;)Lorg/springframework/security/oauth2/client/registration/ClientRegistration$Builder;
      59: aload_0
      60: invokevirtual #82                 // Method org/springframework/security/oauth2/client/registration/ClientRegistration$Builder.registrationId:(Ljava/lang/String;)Lorg/springframework/security/oauth2/client/registration/ClientRegistration$Builder;
      63: astore        6
      65: aload         6
      67: aload         4
      69: invokestatic  #83                 // Method getBuilder:(Lorg/springframework/security/oauth2/client/registration/ClientRegistration$Builder;Ljava/util/Map;)Lorg/springframework/security/oauth2/client/registration/ClientRegistration$Builder;
      72: areturn
      73: aconst_null
      74: areturn

  private static org.springframework.security.oauth2.client.registration.ClientRegistration$Builder getBuilder(java.lang.String, java.lang.String, java.util.Map<java.lang.String, java.util.Map<java.lang.String, java.lang.String>>);
    Code:
       0: aload_1
       1: ifnull        8
       4: aload_1
       5: goto          9
       8: aload_0
       9: astore_3
      10: aload_3
      11: invokestatic  #84                 // Method getCommonProvider:(Ljava/lang/String;)Lorg/springframework/security/config/oauth2/client/CommonOAuth2Provider;
      14: astore        4
      16: aload         4
      18: ifnonnull     33
      21: aload_2
      22: aload_3
      23: invokeinterface #76,  2           // InterfaceMethod java/util/Map.containsKey:(Ljava/lang/Object;)Z
      28: ifne          33
      31: aconst_null
      32: areturn
      33: aload         4
      35: ifnull        47
      38: aload         4
      40: aload_0
      41: invokevirtual #85                 // Method org/springframework/security/config/oauth2/client/CommonOAuth2Provider.getBuilder:(Ljava/lang/String;)Lorg/springframework/security/oauth2/client/registration/ClientRegistration$Builder;
      44: goto          51
      47: aload_0
      48: invokestatic  #86                 // Method org/springframework/security/oauth2/client/registration/ClientRegistration.withRegistrationId:(Ljava/lang/String;)Lorg/springframework/security/oauth2/client/registration/ClientRegistration$Builder;
      51: astore        5
      53: aload_2
      54: aload_3
      55: invokeinterface #76,  2           // InterfaceMethod java/util/Map.containsKey:(Ljava/lang/Object;)Z
      60: ifeq          79
      63: aload         5
      65: aload_2
      66: aload_3
      67: invokeinterface #77,  2           // InterfaceMethod java/util/Map.get:(Ljava/lang/Object;)Ljava/lang/Object;
      72: checkcast     #78                 // class java/util/Map
      75: invokestatic  #83                 // Method getBuilder:(Lorg/springframework/security/oauth2/client/registration/ClientRegistration$Builder;Ljava/util/Map;)Lorg/springframework/security/oauth2/client/registration/ClientRegistration$Builder;
      78: areturn
      79: aload         5
      81: areturn

  private static org.springframework.security.oauth2.client.registration.ClientRegistration$Builder getBuilder(org.springframework.security.oauth2.client.registration.ClientRegistration$Builder, java.util.Map<java.lang.String, java.lang.String>);
    Code:
       0: aload_1
       1: ldc           #62                 // String authorization-uri
       3: invokeinterface #77,  2           // InterfaceMethod java/util/Map.get:(Ljava/lang/Object;)Ljava/lang/Object;
       8: checkcast     #79                 // class java/lang/String
      11: invokestatic  #36                 // Method getOptionalIfNotEmpty:(Ljava/lang/String;)Ljava/util/Optional;
      14: aload_0
      15: dup
      16: invokevirtual #37                 // Method java/lang/Object.getClass:()Ljava/lang/Class;
      19: pop
      20: invokedynamic #87,  0             // InvokeDynamic #17:accept:(Lorg/springframework/security/oauth2/client/registration/ClientRegistration$Builder;)Ljava/util/function/Consumer;
      25: invokevirtual #39                 // Method java/util/Optional.ifPresent:(Ljava/util/function/Consumer;)V
      28: aload_1
      29: ldc           #64                 // String token-uri
      31: invokeinterface #77,  2           // InterfaceMethod java/util/Map.get:(Ljava/lang/Object;)Ljava/lang/Object;
      36: checkcast     #79                 // class java/lang/String
      39: invokestatic  #36                 // Method getOptionalIfNotEmpty:(Ljava/lang/String;)Ljava/util/Optional;
      42: aload_0
      43: dup
      44: invokevirtual #37                 // Method java/lang/Object.getClass:()Ljava/lang/Class;
      47: pop
      48: invokedynamic #88,  0             // InvokeDynamic #18:accept:(Lorg/springframework/security/oauth2/client/registration/ClientRegistration$Builder;)Ljava/util/function/Consumer;
      53: invokevirtual #39                 // Method java/util/Optional.ifPresent:(Ljava/util/function/Consumer;)V
      56: aload_1
      57: ldc           #66                 // String user-info-uri
      59: invokeinterface #77,  2           // InterfaceMethod java/util/Map.get:(Ljava/lang/Object;)Ljava/lang/Object;
      64: checkcast     #79                 // class java/lang/String
      67: invokestatic  #36                 // Method getOptionalIfNotEmpty:(Ljava/lang/String;)Ljava/util/Optional;
      70: aload_0
      71: dup
      72: invokevirtual #37                 // Method java/lang/Object.getClass:()Ljava/lang/Class;
      75: pop
      76: invokedynamic #89,  0             // InvokeDynamic #19:accept:(Lorg/springframework/security/oauth2/client/registration/ClientRegistration$Builder;)Ljava/util/function/Consumer;
      81: invokevirtual #39                 // Method java/util/Optional.ifPresent:(Ljava/util/function/Consumer;)V
      84: aload_1
      85: ldc           #68                 // String user-info-authentication-method
      87: invokeinterface #77,  2           // InterfaceMethod java/util/Map.get:(Ljava/lang/Object;)Ljava/lang/Object;
      92: checkcast     #79                 // class java/lang/String
      95: invokestatic  #36                 // Method getOptionalIfNotEmpty:(Ljava/lang/String;)Ljava/util/Optional;
      98: invokedynamic #90,  0             // InvokeDynamic #20:apply:()Ljava/util/function/Function;
     103: invokevirtual #44                 // Method java/util/Optional.map:(Ljava/util/function/Function;)Ljava/util/Optional;
     106: aload_0
     107: dup
     108: invokevirtual #37                 // Method java/lang/Object.getClass:()Ljava/lang/Class;
     111: pop
     112: invokedynamic #91,  0             // InvokeDynamic #21:accept:(Lorg/springframework/security/oauth2/client/registration/ClientRegistration$Builder;)Ljava/util/function/Consumer;
     117: invokevirtual #39                 // Method java/util/Optional.ifPresent:(Ljava/util/function/Consumer;)V
     120: aload_1
     121: ldc           #72                 // String jwk-set-uri
     123: invokeinterface #77,  2           // InterfaceMethod java/util/Map.get:(Ljava/lang/Object;)Ljava/lang/Object;
     128: checkcast     #79                 // class java/lang/String
     131: invokestatic  #36                 // Method getOptionalIfNotEmpty:(Ljava/lang/String;)Ljava/util/Optional;
     134: aload_0
     135: dup
     136: invokevirtual #37                 // Method java/lang/Object.getClass:()Ljava/lang/Class;
     139: pop
     140: invokedynamic #92,  0             // InvokeDynamic #22:accept:(Lorg/springframework/security/oauth2/client/registration/ClientRegistration$Builder;)Ljava/util/function/Consumer;
     145: invokevirtual #39                 // Method java/util/Optional.ifPresent:(Ljava/util/function/Consumer;)V
     148: aload_1
     149: ldc           #70                 // String user-info-user-name-attribute
     151: invokeinterface #77,  2           // InterfaceMethod java/util/Map.get:(Ljava/lang/Object;)Ljava/lang/Object;
     156: checkcast     #79                 // class java/lang/String
     159: invokestatic  #36                 // Method getOptionalIfNotEmpty:(Ljava/lang/String;)Ljava/util/Optional;
     162: aload_0
     163: dup
     164: invokevirtual #37                 // Method java/lang/Object.getClass:()Ljava/lang/Class;
     167: pop
     168: invokedynamic #93,  0             // InvokeDynamic #23:accept:(Lorg/springframework/security/oauth2/client/registration/ClientRegistration$Builder;)Ljava/util/function/Consumer;
     173: invokevirtual #39                 // Method java/util/Optional.ifPresent:(Ljava/util/function/Consumer;)V
     176: aload_0
     177: areturn

  private static java.util.Optional<java.lang.String> getOptionalIfNotEmpty(java.lang.String);
    Code:
       0: aload_0
       1: invokestatic  #94                 // Method java/util/Optional.ofNullable:(Ljava/lang/Object;)Ljava/util/Optional;
       4: invokedynamic #95,  0             // InvokeDynamic #24:test:()Ljava/util/function/Predicate;
       9: invokevirtual #96                 // Method java/util/Optional.filter:(Ljava/util/function/Predicate;)Ljava/util/Optional;
      12: areturn

  private static org.springframework.security.config.oauth2.client.CommonOAuth2Provider getCommonProvider(java.lang.String);
    Code:
       0: aload_0
       1: invokevirtual #97                 // Method java/lang/String.trim:()Ljava/lang/String;
       4: astore_1
       5: aload_1
       6: invokevirtual #98                 // Method java/lang/String.isEmpty:()Z
       9: ifeq          14
      12: aconst_null
      13: areturn
      14: aload_1
      15: invokestatic  #99                 // Method org/springframework/security/config/oauth2/client/CommonOAuth2Provider.valueOf:(Ljava/lang/String;)Lorg/springframework/security/config/oauth2/client/CommonOAuth2Provider;
      18: areturn
      19: astore_2
      20: aload_1
      21: invokestatic  #101                // Method findEnum:(Ljava/lang/String;)Lorg/springframework/security/config/oauth2/client/CommonOAuth2Provider;
      24: areturn
      25: astore_1
      26: aconst_null
      27: areturn
    Exception table:
       from    to  target type
          14    18    19   Class java/lang/Exception
           0    13    25   Class java/lang/Exception
          14    18    25   Class java/lang/Exception
          19    24    25   Class java/lang/Exception

  private static org.springframework.security.config.oauth2.client.CommonOAuth2Provider findEnum(java.lang.String);
    Code:
       0: aload_0
       1: invokestatic  #102                // Method getCanonicalName:(Ljava/lang/String;)Ljava/lang/String;
       4: astore_1
       5: ldc           #103                // class org/springframework/security/config/oauth2/client/CommonOAuth2Provider
       7: invokestatic  #104                // Method java/util/EnumSet.allOf:(Ljava/lang/Class;)Ljava/util/EnumSet;
      10: invokevirtual #105                // Method java/util/EnumSet.iterator:()Ljava/util/Iterator;
      13: astore_2
      14: aload_2
      15: invokeinterface #25,  1           // InterfaceMethod java/util/Iterator.hasNext:()Z
      20: ifeq          56
      23: aload_2
      24: invokeinterface #26,  1           // InterfaceMethod java/util/Iterator.next:()Ljava/lang/Object;
      29: checkcast     #103                // class org/springframework/security/config/oauth2/client/CommonOAuth2Provider
      32: astore_3
      33: aload_3
      34: invokevirtual #106                // Method org/springframework/security/config/oauth2/client/CommonOAuth2Provider.name:()Ljava/lang/String;
      37: invokestatic  #102                // Method getCanonicalName:(Ljava/lang/String;)Ljava/lang/String;
      40: astore        4
      42: aload_1
      43: aload         4
      45: invokevirtual #107                // Method java/lang/String.equals:(Ljava/lang/Object;)Z
      48: ifeq          53
      51: aload_3
      52: areturn
      53: goto          14
      56: new           #108                // class java/lang/IllegalArgumentException
      59: dup
      60: new           #109                // class java/lang/StringBuilder
      63: dup
      64: invokespecial #110                // Method java/lang/StringBuilder."<init>":()V
      67: ldc           #111                // String No enum constant
      69: invokevirtual #112                // Method java/lang/StringBuilder.append:(Ljava/lang/String;)Ljava/lang/StringBuilder;
      72: ldc           #103                // class org/springframework/security/config/oauth2/client/CommonOAuth2Provider
      74: invokevirtual #113                // Method java/lang/Class.getCanonicalName:()Ljava/lang/String;
      77: invokevirtual #112                // Method java/lang/StringBuilder.append:(Ljava/lang/String;)Ljava/lang/StringBuilder;
      80: ldc           #114                // String .
      82: invokevirtual #112                // Method java/lang/StringBuilder.append:(Ljava/lang/String;)Ljava/lang/StringBuilder;
      85: aload_0
      86: invokevirtual #112                // Method java/lang/StringBuilder.append:(Ljava/lang/String;)Ljava/lang/StringBuilder;
      89: invokevirtual #115                // Method java/lang/StringBuilder.toString:()Ljava/lang/String;
      92: invokespecial #116                // Method java/lang/IllegalArgumentException."<init>":(Ljava/lang/String;)V
      95: athrow

  private static java.lang.String getCanonicalName(java.lang.String);
    Code:
       0: new           #109                // class java/lang/StringBuilder
       3: dup
       4: aload_0
       5: invokevirtual #117                // Method java/lang/String.length:()I
       8: invokespecial #118                // Method java/lang/StringBuilder."<init>":(I)V
      11: astore_1
      12: aload_0
      13: invokevirtual #119                // Method java/lang/String.chars:()Ljava/util/stream/IntStream;
      16: invokedynamic #120,  0            // InvokeDynamic #25:test:()Ljava/util/function/IntPredicate;
      21: invokeinterface #121,  2          // InterfaceMethod java/util/stream/IntStream.filter:(Ljava/util/function/IntPredicate;)Ljava/util/stream/IntStream;
      26: invokedynamic #122,  0            // InvokeDynamic #26:applyAsInt:()Ljava/util/function/IntUnaryOperator;
      31: invokeinterface #123,  2          // InterfaceMethod java/util/stream/IntStream.map:(Ljava/util/function/IntUnaryOperator;)Ljava/util/stream/IntStream;
      36: aload_1
      37: invokedynamic #124,  0            // InvokeDynamic #27:accept:(Ljava/lang/StringBuilder;)Ljava/util/function/IntConsumer;
      42: invokeinterface #125,  2          // InterfaceMethod java/util/stream/IntStream.forEach:(Ljava/util/function/IntConsumer;)V
      47: aload_1
      48: invokevirtual #115                // Method java/lang/StringBuilder.toString:()Ljava/lang/String;
      51: areturn

  private static java.lang.String getErrorMessage(java.lang.String, java.lang.String);
    Code:
       0: aload_0
       1: ifnull        31
       4: new           #109                // class java/lang/StringBuilder
       7: dup
       8: invokespecial #110                // Method java/lang/StringBuilder."<init>":()V
      11: ldc           #126                // String Unknown provider ID \'
      13: invokevirtual #112                // Method java/lang/StringBuilder.append:(Ljava/lang/String;)Ljava/lang/StringBuilder;
      16: aload_0
      17: invokevirtual #112                // Method java/lang/StringBuilder.append:(Ljava/lang/String;)Ljava/lang/StringBuilder;
      20: ldc           #127                // String \'
      22: invokevirtual #112                // Method java/lang/StringBuilder.append:(Ljava/lang/String;)Ljava/lang/StringBuilder;
      25: invokevirtual #115                // Method java/lang/StringBuilder.toString:()Ljava/lang/String;
      28: goto          55
      31: new           #109                // class java/lang/StringBuilder
      34: dup
      35: invokespecial #110                // Method java/lang/StringBuilder."<init>":()V
      38: ldc           #128                // String Provider ID must be specified for client registration \'
      40: invokevirtual #112                // Method java/lang/StringBuilder.append:(Ljava/lang/String;)Ljava/lang/StringBuilder;
      43: aload_1
      44: invokevirtual #112                // Method java/lang/StringBuilder.append:(Ljava/lang/String;)Ljava/lang/StringBuilder;
      47: ldc           #127                // String \'
      49: invokevirtual #112                // Method java/lang/StringBuilder.append:(Ljava/lang/String;)Ljava/lang/StringBuilder;
      52: invokevirtual #115                // Method java/lang/StringBuilder.toString:()Ljava/lang/String;
      55: areturn

  private static void lambda$getCanonicalName$8(java.lang.StringBuilder, int);
    Code:
       0: aload_0
       1: iload_1
       2: i2c
       3: invokevirtual #129                // Method java/lang/StringBuilder.append:(C)Ljava/lang/StringBuilder;
       6: pop
       7: return

  private static boolean lambda$getOptionalIfNotEmpty$7(java.lang.String);
    Code:
       0: aload_0
       1: invokevirtual #98                 // Method java/lang/String.isEmpty:()Z
       4: ifne          11
       7: iconst_1
       8: goto          12
      11: iconst_0
      12: ireturn

  private static void lambda$getProviders$6(java.util.Map, java.lang.String);
    Code:
       0: aload_0
       1: ldc           #74                 // String issuer-uri
       3: aload_1
       4: invokeinterface #61,  3           // InterfaceMethod java/util/Map.put:(Ljava/lang/Object;Ljava/lang/Object;)Ljava/lang/Object;
       9: checkcast     #79                 // class java/lang/String
      12: pop
      13: return

  private static void lambda$getProviders$5(java.util.Map, java.lang.String);
    Code:
       0: aload_0
       1: ldc           #72                 // String jwk-set-uri
       3: aload_1
       4: invokeinterface #61,  3           // InterfaceMethod java/util/Map.put:(Ljava/lang/Object;Ljava/lang/Object;)Ljava/lang/Object;
       9: checkcast     #79                 // class java/lang/String
      12: pop
      13: return

  private static void lambda$getProviders$4(java.util.Map, java.lang.String);
    Code:
       0: aload_0
       1: ldc           #70                 // String user-info-user-name-attribute
       3: aload_1
       4: invokeinterface #61,  3           // InterfaceMethod java/util/Map.put:(Ljava/lang/Object;Ljava/lang/Object;)Ljava/lang/Object;
       9: checkcast     #79                 // class java/lang/String
      12: pop
      13: return

  private static void lambda$getProviders$3(java.util.Map, java.lang.String);
    Code:
       0: aload_0
       1: ldc           #68                 // String user-info-authentication-method
       3: aload_1
       4: invokeinterface #61,  3           // InterfaceMethod java/util/Map.put:(Ljava/lang/Object;Ljava/lang/Object;)Ljava/lang/Object;
       9: checkcast     #79                 // class java/lang/String
      12: pop
      13: return

  private static void lambda$getProviders$2(java.util.Map, java.lang.String);
    Code:
       0: aload_0
       1: ldc           #66                 // String user-info-uri
       3: aload_1
       4: invokeinterface #61,  3           // InterfaceMethod java/util/Map.put:(Ljava/lang/Object;Ljava/lang/Object;)Ljava/lang/Object;
       9: checkcast     #79                 // class java/lang/String
      12: pop
      13: return

  private static void lambda$getProviders$1(java.util.Map, java.lang.String);
    Code:
       0: aload_0
       1: ldc           #64                 // String token-uri
       3: aload_1
       4: invokeinterface #61,  3           // InterfaceMethod java/util/Map.put:(Ljava/lang/Object;Ljava/lang/Object;)Ljava/lang/Object;
       9: checkcast     #79                 // class java/lang/String
      12: pop
      13: return

  private static void lambda$getProviders$0(java.util.Map, java.lang.String);
    Code:
       0: aload_0
       1: ldc           #62                 // String authorization-uri
       3: aload_1
       4: invokeinterface #61,  3           // InterfaceMethod java/util/Map.put:(Ljava/lang/Object;Ljava/lang/Object;)Ljava/lang/Object;
       9: checkcast     #79                 // class java/lang/String
      12: pop
      13: return
}
