Compiled from "CamelCaseAbbreviatingFieldNamingStrategy.java"
public class org.springframework.data.mapping.model.CamelCaseAbbreviatingFieldNamingStrategy extends org.springframework.data.mapping.model.CamelCaseSplittingFieldNamingStrategy {
  public org.springframework.data.mapping.model.CamelCaseAbbreviatingFieldNamingStrategy();
    Code:
       0: aload_0
       1: ldc           #1                  // String
       3: invokespecial #2                  // Method org/springframework/data/mapping/model/CamelCaseSplittingFieldNamingStrategy."<init>":(Ljava/lang/String;)V
       6: return

  protected java.lang.String preparePart(java.lang.String);
    Code:
       0: aload_1
       1: iconst_0
       2: iconst_1
       3: invokevirtual #3                  // Method java/lang/String.substring:(II)Ljava/lang/String;
       6: areturn
}
