Compiled from "GraphUnionRead.java"
public class org.apache.jena.sparql.graph.GraphUnionRead extends org.apache.jena.graph.impl.GraphBase {
  private final org.apache.jena.sparql.core.DatasetGraph dataset;

  private final java.util.Collection<org.apache.jena.graph.Node> graphs;

  public org.apache.jena.sparql.graph.GraphUnionRead(org.apache.jena.sparql.core.DatasetGraph);
    Code:
       0: aload_0
       1: aload_1
       2: aconst_null
       3: invokespecial #1                  // Method "<init>":(Lorg/apache/jena/sparql/core/DatasetGraph;Ljava/util/Collection;)V
       6: return

  public org.apache.jena.sparql.graph.GraphUnionRead(org.apache.jena.sparql.core.DatasetGraph, java.util.Collection<org.apache.jena.graph.Node>);
    Code:
       0: aload_0
       1: invokespecial #2                  // Method org/apache/jena/graph/impl/GraphBase."<init>":()V
       4: aload_0
       5: aload_1
       6: putfield      #3                  // Field dataset:Lorg/apache/jena/sparql/core/DatasetGraph;
       9: aload_0
      10: aload_2
      11: putfield      #4                  // Field graphs:Ljava/util/Collection;
      14: return

  protected org.apache.jena.shared.PrefixMapping createPrefixMapping();
    Code:
       0: new           #5                  // class org/apache/jena/shared/impl/PrefixMappingImpl
       3: dup
       4: invokespecial #6                  // Method org/apache/jena/shared/impl/PrefixMappingImpl."<init>":()V
       7: astore_1
       8: aload_0
       9: aload_1
      10: invokedynamic #7,  0              // InvokeDynamic #0:accept:(Lorg/apache/jena/shared/PrefixMapping;)Ljava/util/function/Consumer;
      15: invokespecial #8                  // Method forEachGraph:(Ljava/util/function/Consumer;)V
      18: aload_1
      19: areturn

  protected org.apache.jena.util.iterator.ExtendedIterator<org.apache.jena.graph.Triple> graphBaseFind(org.apache.jena.graph.Triple);
    Code:
       0: aload_0
       1: getfield      #4                  // Field graphs:Ljava/util/Collection;
       4: ifnonnull     47
       7: aload_0
       8: getfield      #3                  // Field dataset:Lorg/apache/jena/sparql/core/DatasetGraph;
      11: getstatic     #9                  // Field org/apache/jena/sparql/core/Quad.unionGraph:Lorg/apache/jena/graph/Node;
      14: aload_1
      15: invokevirtual #10                 // Method org/apache/jena/graph/Triple.getSubject:()Lorg/apache/jena/graph/Node;
      18: aload_1
      19: invokevirtual #11                 // Method org/apache/jena/graph/Triple.getPredicate:()Lorg/apache/jena/graph/Node;
      22: aload_1
      23: invokevirtual #12                 // Method org/apache/jena/graph/Triple.getObject:()Lorg/apache/jena/graph/Node;
      26: invokeinterface #13,  5           // InterfaceMethod org/apache/jena/sparql/core/DatasetGraph.findNG:(Lorg/apache/jena/graph/Node;Lorg/apache/jena/graph/Node;Lorg/apache/jena/graph/Node;Lorg/apache/jena/graph/Node;)Ljava/util/Iterator;
      31: astore_2
      32: aload_2
      33: invokedynamic #14,  0             // InvokeDynamic #1:apply:()Ljava/util/function/Function;
      38: invokestatic  #15                 // Method org/apache/jena/atlas/iterator/Iter.map:(Ljava/util/Iterator;Ljava/util/function/Function;)Ljava/util/Iterator;
      41: astore_3
      42: aload_3
      43: invokestatic  #16                 // Method org/apache/jena/util/iterator/WrappedIterator.createNoRemove:(Ljava/util/Iterator;)Lorg/apache/jena/util/iterator/WrappedIterator;
      46: areturn
      47: new           #17                 // class org/apache/jena/atlas/iterator/IteratorConcat
      50: dup
      51: invokespecial #18                 // Method org/apache/jena/atlas/iterator/IteratorConcat."<init>":()V
      54: astore_2
      55: aload_0
      56: aload_2
      57: aload_1
      58: invokedynamic #19,  0             // InvokeDynamic #2:accept:(Lorg/apache/jena/atlas/iterator/IteratorConcat;Lorg/apache/jena/graph/Triple;)Ljava/util/function/Consumer;
      63: invokespecial #8                  // Method forEachGraph:(Ljava/util/function/Consumer;)V
      66: aload_2
      67: invokestatic  #20                 // Method org/apache/jena/atlas/iterator/Iter.distinct:(Ljava/util/Iterator;)Ljava/util/Iterator;
      70: invokestatic  #16                 // Method org/apache/jena/util/iterator/WrappedIterator.createNoRemove:(Ljava/util/Iterator;)Lorg/apache/jena/util/iterator/WrappedIterator;
      73: areturn

  private void forEachGraph(java.util.function.Consumer<org.apache.jena.graph.Graph>);
    Code:
       0: aload_0
       1: getfield      #4                  // Field graphs:Ljava/util/Collection;
       4: ifnonnull     29
       7: aload_0
       8: getfield      #3                  // Field dataset:Lorg/apache/jena/sparql/core/DatasetGraph;
      11: invokeinterface #21,  1           // InterfaceMethod org/apache/jena/sparql/core/DatasetGraph.listGraphNodes:()Ljava/util/Iterator;
      16: aload_0
      17: aload_1
      18: invokedynamic #22,  0             // InvokeDynamic #3:accept:(Lorg/apache/jena/sparql/graph/GraphUnionRead;Ljava/util/function/Consumer;)Ljava/util/function/Consumer;
      23: invokeinterface #23,  2           // InterfaceMethod java/util/Iterator.forEachRemaining:(Ljava/util/function/Consumer;)V
      28: return
      29: aload_0
      30: getfield      #4                  // Field graphs:Ljava/util/Collection;
      33: invokeinterface #24,  1           // InterfaceMethod java/util/Collection.stream:()Ljava/util/stream/Stream;
      38: aload_0
      39: invokedynamic #25,  0             // InvokeDynamic #4:test:(Lorg/apache/jena/sparql/graph/GraphUnionRead;)Ljava/util/function/Predicate;
      44: invokeinterface #26,  2           // InterfaceMethod java/util/stream/Stream.filter:(Ljava/util/function/Predicate;)Ljava/util/stream/Stream;
      49: aload_0
      50: invokedynamic #27,  0             // InvokeDynamic #5:apply:(Lorg/apache/jena/sparql/graph/GraphUnionRead;)Ljava/util/function/Function;
      55: invokeinterface #28,  2           // InterfaceMethod java/util/stream/Stream.map:(Ljava/util/function/Function;)Ljava/util/stream/Stream;
      60: aload_1
      61: invokeinterface #29,  2           // InterfaceMethod java/util/stream/Stream.forEach:(Ljava/util/function/Consumer;)V
      66: return

  public void performAdd(org.apache.jena.graph.Triple);
    Code:
       0: new           #30                 // class org/apache/jena/shared/AddDeniedException
       3: dup
       4: ldc           #31                 // String GraphUnionRead::performAdd - Read-only graph
       6: invokespecial #32                 // Method org/apache/jena/shared/AddDeniedException."<init>":(Ljava/lang/String;)V
       9: athrow

  public void performDelete(org.apache.jena.graph.Triple);
    Code:
       0: new           #33                 // class org/apache/jena/shared/DeleteDeniedException
       3: dup
       4: ldc           #34                 // String GraphUnionRead::performDelete - Read-only graph
       6: invokespecial #35                 // Method org/apache/jena/shared/DeleteDeniedException."<init>":(Ljava/lang/String;)V
       9: athrow

  private org.apache.jena.graph.Graph lambda$forEachGraph$5(org.apache.jena.graph.Node);
    Code:
       0: aload_1
       1: invokestatic  #36                 // Method org/apache/jena/sparql/core/Quad.isDefaultGraph:(Lorg/apache/jena/graph/Node;)Z
       4: ifeq          19
       7: aload_0
       8: getfield      #3                  // Field dataset:Lorg/apache/jena/sparql/core/DatasetGraph;
      11: invokeinterface #37,  1           // InterfaceMethod org/apache/jena/sparql/core/DatasetGraph.getDefaultGraph:()Lorg/apache/jena/graph/Graph;
      16: goto          29
      19: aload_0
      20: getfield      #3                  // Field dataset:Lorg/apache/jena/sparql/core/DatasetGraph;
      23: aload_1
      24: invokeinterface #38,  2           // InterfaceMethod org/apache/jena/sparql/core/DatasetGraph.getGraph:(Lorg/apache/jena/graph/Node;)Lorg/apache/jena/graph/Graph;
      29: areturn

  private boolean lambda$forEachGraph$4(org.apache.jena.graph.Node);
    Code:
       0: aload_0
       1: getfield      #3                  // Field dataset:Lorg/apache/jena/sparql/core/DatasetGraph;
       4: aload_1
       5: invokeinterface #39,  2           // InterfaceMethod org/apache/jena/sparql/core/DatasetGraph.containsGraph:(Lorg/apache/jena/graph/Node;)Z
      10: ireturn

  private void lambda$forEachGraph$3(java.util.function.Consumer, org.apache.jena.graph.Node);
    Code:
       0: aload_1
       1: aload_0
       2: getfield      #3                  // Field dataset:Lorg/apache/jena/sparql/core/DatasetGraph;
       5: aload_2
       6: invokeinterface #38,  2           // InterfaceMethod org/apache/jena/sparql/core/DatasetGraph.getGraph:(Lorg/apache/jena/graph/Node;)Lorg/apache/jena/graph/Graph;
      11: invokeinterface #40,  2           // InterfaceMethod java/util/function/Consumer.accept:(Ljava/lang/Object;)V
      16: return

  private static void lambda$graphBaseFind$2(org.apache.jena.atlas.iterator.IteratorConcat, org.apache.jena.graph.Triple, org.apache.jena.graph.Graph);
    Code:
       0: aload_0
       1: aload_2
       2: aload_1
       3: invokeinterface #41,  2           // InterfaceMethod org/apache/jena/graph/Graph.find:(Lorg/apache/jena/graph/Triple;)Lorg/apache/jena/util/iterator/ExtendedIterator;
       8: invokevirtual #42                 // Method org/apache/jena/atlas/iterator/IteratorConcat.add:(Ljava/util/Iterator;)V
      11: return

  private static org.apache.jena.graph.Triple lambda$graphBaseFind$1(org.apache.jena.sparql.core.Quad);
    Code:
       0: aload_0
       1: invokevirtual #43                 // Method org/apache/jena/sparql/core/Quad.asTriple:()Lorg/apache/jena/graph/Triple;
       4: areturn

  private static void lambda$createPrefixMapping$0(org.apache.jena.shared.PrefixMapping, org.apache.jena.graph.Graph);
    Code:
       0: aload_1
       1: invokeinterface #44,  1           // InterfaceMethod org/apache/jena/graph/Graph.getPrefixMapping:()Lorg/apache/jena/shared/PrefixMapping;
       6: astore_2
       7: aload_0
       8: aload_2
       9: invokeinterface #45,  2           // InterfaceMethod org/apache/jena/shared/PrefixMapping.setNsPrefixes:(Lorg/apache/jena/shared/PrefixMapping;)Lorg/apache/jena/shared/PrefixMapping;
      14: pop
      15: return
}
