Compiled from "PojoEndpointServer.java"
public class org.apache.tomcat.websocket.pojo.PojoEndpointServer extends org.apache.tomcat.websocket.pojo.PojoEndpointBase {
  private static final org.apache.tomcat.util.res.StringManager sm;

  public org.apache.tomcat.websocket.pojo.PojoEndpointServer();
    Code:
       0: aload_0
       1: invokespecial #1                  // Method org/apache/tomcat/websocket/pojo/PojoEndpointBase."<init>":()V
       4: return

  public void onOpen(javax.websocket.Session, javax.websocket.EndpointConfig);
    Code:
       0: aload_2
       1: checkcast     #2                  // class javax/websocket/server/ServerEndpointConfig
       4: astore_3
       5: aload_3
       6: invokeinterface #3,  1            // InterfaceMethod javax/websocket/server/ServerEndpointConfig.getConfigurator:()Ljavax/websocket/server/ServerEndpointConfig$Configurator;
      11: aload_3
      12: invokeinterface #4,  1            // InterfaceMethod javax/websocket/server/ServerEndpointConfig.getEndpointClass:()Ljava/lang/Class;
      17: invokevirtual #5                  // Method javax/websocket/server/ServerEndpointConfig$Configurator.getEndpointInstance:(Ljava/lang/Class;)Ljava/lang/Object;
      20: astore        4
      22: goto          61
      25: astore        5
      27: new           #7                  // class java/lang/IllegalArgumentException
      30: dup
      31: getstatic     #8                  // Field sm:Lorg/apache/tomcat/util/res/StringManager;
      34: ldc           #9                  // String pojoEndpointServer.getPojoInstanceFail
      36: iconst_1
      37: anewarray     #10                 // class java/lang/Object
      40: dup
      41: iconst_0
      42: aload_3
      43: invokeinterface #4,  1            // InterfaceMethod javax/websocket/server/ServerEndpointConfig.getEndpointClass:()Ljava/lang/Class;
      48: invokevirtual #11                 // Method java/lang/Class.getName:()Ljava/lang/String;
      51: aastore
      52: invokevirtual #12                 // Method org/apache/tomcat/util/res/StringManager.getString:(Ljava/lang/String;[Ljava/lang/Object;)Ljava/lang/String;
      55: aload         5
      57: invokespecial #13                 // Method java/lang/IllegalArgumentException."<init>":(Ljava/lang/String;Ljava/lang/Throwable;)V
      60: athrow
      61: aload_0
      62: aload         4
      64: invokevirtual #14                 // Method setPojo:(Ljava/lang/Object;)V
      67: aload_3
      68: invokeinterface #15,  1           // InterfaceMethod javax/websocket/server/ServerEndpointConfig.getUserProperties:()Ljava/util/Map;
      73: ldc           #17                 // String org.apache.tomcat.websocket.pojo.PojoEndpoint.pathParams
      75: invokeinterface #18,  2           // InterfaceMethod java/util/Map.get:(Ljava/lang/Object;)Ljava/lang/Object;
      80: checkcast     #19                 // class java/util/Map
      83: astore        5
      85: aload_0
      86: aload         5
      88: invokevirtual #20                 // Method setPathParameters:(Ljava/util/Map;)V
      91: aload_3
      92: invokeinterface #15,  1           // InterfaceMethod javax/websocket/server/ServerEndpointConfig.getUserProperties:()Ljava/util/Map;
      97: ldc           #21                 // String org.apache.tomcat.websocket.pojo.PojoEndpoint.methodMapping
      99: invokeinterface #18,  2           // InterfaceMethod java/util/Map.get:(Ljava/lang/Object;)Ljava/lang/Object;
     104: checkcast     #22                 // class org/apache/tomcat/websocket/pojo/PojoMethodMapping
     107: astore        6
     109: aload_0
     110: aload         6
     112: invokevirtual #23                 // Method setMethodMapping:(Lorg/apache/tomcat/websocket/pojo/PojoMethodMapping;)V
     115: aload_0
     116: aload_1
     117: aload_2
     118: invokevirtual #24                 // Method doOnOpen:(Ljavax/websocket/Session;Ljavax/websocket/EndpointConfig;)V
     121: return
    Exception table:
       from    to  target type
           5    22    25   Class java/lang/InstantiationException

  static {};
    Code:
       0: ldc           #25                 // class org/apache/tomcat/websocket/pojo/PojoEndpointServer
       2: invokestatic  #26                 // Method org/apache/tomcat/util/res/StringManager.getManager:(Ljava/lang/Class;)Lorg/apache/tomcat/util/res/StringManager;
       5: putstatic     #8                  // Field sm:Lorg/apache/tomcat/util/res/StringManager;
       8: return
}
