Compiled from "ConversionUtils.java"
abstract class org.springframework.core.convert.support.ConversionUtils {
  org.springframework.core.convert.support.ConversionUtils();
    Code:
       0: aload_0
       1: invokespecial #1                  // Method java/lang/Object."<init>":()V
       4: return

  public static java.lang.Object invokeConverter(org.springframework.core.convert.converter.GenericConverter, java.lang.Object, org.springframework.core.convert.TypeDescriptor, org.springframework.core.convert.TypeDescriptor);
    Code:
       0: aload_0
       1: aload_1
       2: aload_2
       3: aload_3
       4: invokeinterface #2,  4            // InterfaceMethod org/springframework/core/convert/converter/GenericConverter.convert:(Ljava/lang/Object;Lorg/springframework/core/convert/TypeDescriptor;Lorg/springframework/core/convert/TypeDescriptor;)Ljava/lang/Object;
       9: areturn
      10: astore        4
      12: aload         4
      14: athrow
      15: astore        4
      17: new           #3                  // class org/springframework/core/convert/ConversionFailedException
      20: dup
      21: aload_2
      22: aload_3
      23: aload_1
      24: aload         4
      26: invokespecial #5                  // Method org/springframework/core/convert/ConversionFailedException."<init>":(Lorg/springframework/core/convert/TypeDescriptor;Lorg/springframework/core/convert/TypeDescriptor;Ljava/lang/Object;Ljava/lang/Throwable;)V
      29: athrow
    Exception table:
       from    to  target type
           0     9    10   Class org/springframework/core/convert/ConversionFailedException
           0     9    15   Class java/lang/Throwable

  public static boolean canConvertElements(org.springframework.core.convert.TypeDescriptor, org.springframework.core.convert.TypeDescriptor, org.springframework.core.convert.ConversionService);
    Code:
       0: aload_1
       1: ifnonnull     6
       4: iconst_1
       5: ireturn
       6: aload_0
       7: ifnonnull     12
      10: iconst_1
      11: ireturn
      12: aload_2
      13: aload_0
      14: aload_1
      15: invokeinterface #6,  3            // InterfaceMethod org/springframework/core/convert/ConversionService.canConvert:(Lorg/springframework/core/convert/TypeDescriptor;Lorg/springframework/core/convert/TypeDescriptor;)Z
      20: ifeq          25
      23: iconst_1
      24: ireturn
      25: aload_0
      26: invokevirtual #7                  // Method org/springframework/core/convert/TypeDescriptor.getType:()Ljava/lang/Class;
      29: aload_1
      30: invokevirtual #7                  // Method org/springframework/core/convert/TypeDescriptor.getType:()Ljava/lang/Class;
      33: invokestatic  #8                  // Method org/springframework/util/ClassUtils.isAssignable:(Ljava/lang/Class;Ljava/lang/Class;)Z
      36: ifeq          41
      39: iconst_1
      40: ireturn
      41: iconst_0
      42: ireturn

  public static java.lang.Class<?> getEnumType(java.lang.Class<?>);
    Code:
       0: aload_0
       1: astore_1
       2: aload_1
       3: ifnull        21
       6: aload_1
       7: invokevirtual #9                  // Method java/lang/Class.isEnum:()Z
      10: ifne          21
      13: aload_1
      14: invokevirtual #10                 // Method java/lang/Class.getSuperclass:()Ljava/lang/Class;
      17: astore_1
      18: goto          2
      21: aload_1
      22: aload_0
      23: invokedynamic #11,  0             // InvokeDynamic #0:get:(Ljava/lang/Class;)Ljava/util/function/Supplier;
      28: invokestatic  #12                 // Method org/springframework/util/Assert.notNull:(Ljava/lang/Object;Ljava/util/function/Supplier;)V
      31: aload_1
      32: areturn

  private static java.lang.String lambda$getEnumType$0(java.lang.Class);
    Code:
       0: new           #13                 // class java/lang/StringBuilder
       3: dup
       4: invokespecial #14                 // Method java/lang/StringBuilder."<init>":()V
       7: ldc           #15                 // String The target type
       9: invokevirtual #16                 // Method java/lang/StringBuilder.append:(Ljava/lang/String;)Ljava/lang/StringBuilder;
      12: aload_0
      13: invokevirtual #17                 // Method java/lang/Class.getName:()Ljava/lang/String;
      16: invokevirtual #16                 // Method java/lang/StringBuilder.append:(Ljava/lang/String;)Ljava/lang/StringBuilder;
      19: ldc           #18                 // String  does not refer to an enum
      21: invokevirtual #16                 // Method java/lang/StringBuilder.append:(Ljava/lang/String;)Ljava/lang/StringBuilder;
      24: invokevirtual #19                 // Method java/lang/StringBuilder.toString:()Ljava/lang/String;
      27: areturn
}
