Compiled from "FXCollections.java"
class javafx.collections.FXCollections$SingletonObservableList<E> extends java.util.AbstractList<E> implements javafx.collections.ObservableList<E> {
  private final E element;

  public javafx.collections.FXCollections$SingletonObservableList(E);
    Code:
       0: aload_0
       1: invokespecial #1                  // Method java/util/AbstractList."<init>":()V
       4: aload_1
       5: ifnonnull     16
       8: new           #2                  // class java/lang/NullPointerException
      11: dup
      12: invokespecial #3                  // Method java/lang/NullPointerException."<init>":()V
      15: athrow
      16: aload_0
      17: aload_1
      18: putfield      #4                  // Field element:Ljava/lang/Object;
      21: return

  public boolean addAll(E...);
    Code:
       0: new           #5                  // class java/lang/UnsupportedOperationException
       3: dup
       4: invokespecial #6                  // Method java/lang/UnsupportedOperationException."<init>":()V
       7: athrow

  public boolean setAll(E...);
    Code:
       0: new           #5                  // class java/lang/UnsupportedOperationException
       3: dup
       4: invokespecial #6                  // Method java/lang/UnsupportedOperationException."<init>":()V
       7: athrow

  public boolean setAll(java.util.Collection<? extends E>);
    Code:
       0: new           #5                  // class java/lang/UnsupportedOperationException
       3: dup
       4: invokespecial #6                  // Method java/lang/UnsupportedOperationException."<init>":()V
       7: athrow

  public boolean removeAll(E...);
    Code:
       0: new           #5                  // class java/lang/UnsupportedOperationException
       3: dup
       4: invokespecial #6                  // Method java/lang/UnsupportedOperationException."<init>":()V
       7: athrow

  public boolean retainAll(E...);
    Code:
       0: new           #5                  // class java/lang/UnsupportedOperationException
       3: dup
       4: invokespecial #6                  // Method java/lang/UnsupportedOperationException."<init>":()V
       7: athrow

  public void remove(int, int);
    Code:
       0: new           #5                  // class java/lang/UnsupportedOperationException
       3: dup
       4: invokespecial #6                  // Method java/lang/UnsupportedOperationException."<init>":()V
       7: athrow

  public void addListener(javafx.beans.InvalidationListener);
    Code:
       0: return

  public void removeListener(javafx.beans.InvalidationListener);
    Code:
       0: return

  public void addListener(javafx.collections.ListChangeListener<? super E>);
    Code:
       0: return

  public void removeListener(javafx.collections.ListChangeListener<? super E>);
    Code:
       0: return

  public int size();
    Code:
       0: iconst_1
       1: ireturn

  public boolean isEmpty();
    Code:
       0: iconst_0
       1: ireturn

  public boolean contains(java.lang.Object);
    Code:
       0: aload_0
       1: getfield      #4                  // Field element:Ljava/lang/Object;
       4: aload_1
       5: invokevirtual #7                  // Method java/lang/Object.equals:(Ljava/lang/Object;)Z
       8: ireturn

  public E get(int);
    Code:
       0: iload_1
       1: ifeq          12
       4: new           #8                  // class java/lang/IndexOutOfBoundsException
       7: dup
       8: invokespecial #9                  // Method java/lang/IndexOutOfBoundsException."<init>":()V
      11: athrow
      12: aload_0
      13: getfield      #4                  // Field element:Ljava/lang/Object;
      16: areturn
}
