Compiled from "Activator.java"
public class org.apache.activemq.util.osgi.Activator implements org.osgi.framework.BundleActivator,org.osgi.framework.SynchronousBundleListener,org.apache.activemq.util.FactoryFinder$ObjectFactory {
  private static final org.slf4j.Logger LOG;

  private final java.util.concurrent.ConcurrentHashMap<java.lang.String, java.lang.Class> serviceCache;

  private final java.util.concurrent.ConcurrentMap<java.lang.Long, org.apache.activemq.util.osgi.Activator$BundleWrapper> bundleWrappers;

  private org.osgi.framework.BundleContext bundleContext;

  public org.apache.activemq.util.osgi.Activator();
    Code:
       0: aload_0
       1: invokespecial #1                  // Method java/lang/Object."<init>":()V
       4: aload_0
       5: new           #2                  // class java/util/concurrent/ConcurrentHashMap
       8: dup
       9: invokespecial #3                  // Method java/util/concurrent/ConcurrentHashMap."<init>":()V
      12: putfield      #4                  // Field serviceCache:Ljava/util/concurrent/ConcurrentHashMap;
      15: aload_0
      16: new           #2                  // class java/util/concurrent/ConcurrentHashMap
      19: dup
      20: invokespecial #3                  // Method java/util/concurrent/ConcurrentHashMap."<init>":()V
      23: putfield      #5                  // Field bundleWrappers:Ljava/util/concurrent/ConcurrentMap;
      26: return

  public synchronized void start(org.osgi.framework.BundleContext) throws java.lang.Exception;
    Code:
       0: aload_0
       1: invokestatic  #6                  // Method org/apache/activemq/util/FactoryFinder.setObjectFactory:(Lorg/apache/activemq/util/FactoryFinder$ObjectFactory;)V
       4: aload_0
       5: ldc           #7                  // String activating
       7: invokespecial #8                  // Method debug:(Ljava/lang/Object;)V
      10: aload_0
      11: aload_1
      12: putfield      #9                  // Field bundleContext:Lorg/osgi/framework/BundleContext;
      15: aload_0
      16: ldc           #10                 // String checking existing bundles
      18: invokespecial #8                  // Method debug:(Ljava/lang/Object;)V
      21: aload_1
      22: aload_0
      23: invokeinterface #11,  2           // InterfaceMethod org/osgi/framework/BundleContext.addBundleListener:(Lorg/osgi/framework/BundleListener;)V
      28: aload_1
      29: invokeinterface #12,  1           // InterfaceMethod org/osgi/framework/BundleContext.getBundles:()[Lorg/osgi/framework/Bundle;
      34: astore_2
      35: aload_2
      36: arraylength
      37: istore_3
      38: iconst_0
      39: istore        4
      41: iload         4
      43: iload_3
      44: if_icmpge     112
      47: aload_2
      48: iload         4
      50: aaload
      51: astore        5
      53: aload         5
      55: invokeinterface #13,  1           // InterfaceMethod org/osgi/framework/Bundle.getState:()I
      60: iconst_4
      61: if_icmpeq     100
      64: aload         5
      66: invokeinterface #13,  1           // InterfaceMethod org/osgi/framework/Bundle.getState:()I
      71: bipush        8
      73: if_icmpeq     100
      76: aload         5
      78: invokeinterface #13,  1           // InterfaceMethod org/osgi/framework/Bundle.getState:()I
      83: bipush        32
      85: if_icmpeq     100
      88: aload         5
      90: invokeinterface #13,  1           // InterfaceMethod org/osgi/framework/Bundle.getState:()I
      95: bipush        16
      97: if_icmpne     106
     100: aload_0
     101: aload         5
     103: invokevirtual #14                 // Method register:(Lorg/osgi/framework/Bundle;)V
     106: iinc          4, 1
     109: goto          41
     112: aload_0
     113: ldc           #15                 // String activated
     115: invokespecial #8                  // Method debug:(Ljava/lang/Object;)V
     118: return

  public synchronized void stop(org.osgi.framework.BundleContext) throws java.lang.Exception;
    Code:
       0: aload_0
       1: ldc           #16                 // String deactivating
       3: invokespecial #8                  // Method debug:(Ljava/lang/Object;)V
       6: aload_1
       7: aload_0
       8: invokeinterface #17,  2           // InterfaceMethod org/osgi/framework/BundleContext.removeBundleListener:(Lorg/osgi/framework/BundleListener;)V
      13: aload_0
      14: getfield      #5                  // Field bundleWrappers:Ljava/util/concurrent/ConcurrentMap;
      17: invokeinterface #18,  1           // InterfaceMethod java/util/concurrent/ConcurrentMap.isEmpty:()Z
      22: ifne          57
      25: aload_0
      26: aload_0
      27: getfield      #5                  // Field bundleWrappers:Ljava/util/concurrent/ConcurrentMap;
      30: invokeinterface #19,  1           // InterfaceMethod java/util/concurrent/ConcurrentMap.keySet:()Ljava/util/Set;
      35: invokeinterface #20,  1           // InterfaceMethod java/util/Set.iterator:()Ljava/util/Iterator;
      40: invokeinterface #21,  1           // InterfaceMethod java/util/Iterator.next:()Ljava/lang/Object;
      45: checkcast     #22                 // class java/lang/Long
      48: invokevirtual #23                 // Method java/lang/Long.longValue:()J
      51: invokevirtual #24                 // Method unregister:(J)V
      54: goto          13
      57: aload_0
      58: ldc           #25                 // String deactivated
      60: invokespecial #8                  // Method debug:(Ljava/lang/Object;)V
      63: aload_0
      64: aconst_null
      65: putfield      #9                  // Field bundleContext:Lorg/osgi/framework/BundleContext;
      68: return

  public void bundleChanged(org.osgi.framework.BundleEvent);
    Code:
       0: aload_1
       1: invokevirtual #26                 // Method org/osgi/framework/BundleEvent.getType:()I
       4: bipush        32
       6: if_icmpne     20
       9: aload_0
      10: aload_1
      11: invokevirtual #27                 // Method org/osgi/framework/BundleEvent.getBundle:()Lorg/osgi/framework/Bundle;
      14: invokevirtual #14                 // Method register:(Lorg/osgi/framework/Bundle;)V
      17: goto          51
      20: aload_1
      21: invokevirtual #26                 // Method org/osgi/framework/BundleEvent.getType:()I
      24: bipush        64
      26: if_icmpeq     38
      29: aload_1
      30: invokevirtual #26                 // Method org/osgi/framework/BundleEvent.getType:()I
      33: bipush        16
      35: if_icmpne     51
      38: aload_0
      39: aload_1
      40: invokevirtual #27                 // Method org/osgi/framework/BundleEvent.getBundle:()Lorg/osgi/framework/Bundle;
      43: invokeinterface #28,  1           // InterfaceMethod org/osgi/framework/Bundle.getBundleId:()J
      48: invokevirtual #24                 // Method unregister:(J)V
      51: return

  protected void register(org.osgi.framework.Bundle);
    Code:
       0: aload_0
       1: new           #29                 // class java/lang/StringBuilder
       4: dup
       5: invokespecial #30                 // Method java/lang/StringBuilder."<init>":()V
       8: ldc           #31                 // String checking bundle
      10: invokevirtual #32                 // Method java/lang/StringBuilder.append:(Ljava/lang/String;)Ljava/lang/StringBuilder;
      13: aload_1
      14: invokeinterface #28,  1           // InterfaceMethod org/osgi/framework/Bundle.getBundleId:()J
      19: invokevirtual #33                 // Method java/lang/StringBuilder.append:(J)Ljava/lang/StringBuilder;
      22: invokevirtual #34                 // Method java/lang/StringBuilder.toString:()Ljava/lang/String;
      25: invokespecial #8                  // Method debug:(Ljava/lang/Object;)V
      28: aload_0
      29: aload_1
      30: invokespecial #35                 // Method isImportingUs:(Lorg/osgi/framework/Bundle;)Z
      33: ifne          65
      36: aload_0
      37: new           #29                 // class java/lang/StringBuilder
      40: dup
      41: invokespecial #30                 // Method java/lang/StringBuilder."<init>":()V
      44: ldc           #36                 // String The bundle does not import us:
      46: invokevirtual #32                 // Method java/lang/StringBuilder.append:(Ljava/lang/String;)Ljava/lang/StringBuilder;
      49: aload_1
      50: invokeinterface #28,  1           // InterfaceMethod org/osgi/framework/Bundle.getBundleId:()J
      55: invokevirtual #33                 // Method java/lang/StringBuilder.append:(J)Ljava/lang/StringBuilder;
      58: invokevirtual #34                 // Method java/lang/StringBuilder.toString:()Ljava/lang/String;
      61: invokespecial #8                  // Method debug:(Ljava/lang/Object;)V
      64: return
      65: aload_0
      66: getfield      #5                  // Field bundleWrappers:Ljava/util/concurrent/ConcurrentMap;
      69: aload_1
      70: invokeinterface #28,  1           // InterfaceMethod org/osgi/framework/Bundle.getBundleId:()J
      75: invokestatic  #37                 // Method java/lang/Long.valueOf:(J)Ljava/lang/Long;
      78: new           #38                 // class org/apache/activemq/util/osgi/Activator$BundleWrapper
      81: dup
      82: aload_1
      83: invokespecial #39                 // Method org/apache/activemq/util/osgi/Activator$BundleWrapper."<init>":(Lorg/osgi/framework/Bundle;)V
      86: invokeinterface #40,  3           // InterfaceMethod java/util/concurrent/ConcurrentMap.put:(Ljava/lang/Object;Ljava/lang/Object;)Ljava/lang/Object;
      91: pop
      92: return

  protected void unregister(long);
    Code:
       0: aload_0
       1: getfield      #5                  // Field bundleWrappers:Ljava/util/concurrent/ConcurrentMap;
       4: lload_1
       5: invokestatic  #37                 // Method java/lang/Long.valueOf:(J)Ljava/lang/Long;
       8: invokeinterface #41,  2           // InterfaceMethod java/util/concurrent/ConcurrentMap.remove:(Ljava/lang/Object;)Ljava/lang/Object;
      13: checkcast     #38                 // class org/apache/activemq/util/osgi/Activator$BundleWrapper
      16: astore_3
      17: aload_3
      18: ifnull        91
      21: aload_3
      22: invokestatic  #42                 // Method org/apache/activemq/util/osgi/Activator$BundleWrapper.access$000:(Lorg/apache/activemq/util/osgi/Activator$BundleWrapper;)Ljava/util/List;
      25: invokeinterface #43,  1           // InterfaceMethod java/util/List.iterator:()Ljava/util/Iterator;
      30: astore        4
      32: aload         4
      34: invokeinterface #44,  1           // InterfaceMethod java/util/Iterator.hasNext:()Z
      39: ifeq          91
      42: aload         4
      44: invokeinterface #21,  1           // InterfaceMethod java/util/Iterator.next:()Ljava/lang/Object;
      49: checkcast     #45                 // class java/lang/String
      52: astore        5
      54: aload_0
      55: new           #29                 // class java/lang/StringBuilder
      58: dup
      59: invokespecial #30                 // Method java/lang/StringBuilder."<init>":()V
      62: ldc           #46                 // String unregistering service for key:
      64: invokevirtual #32                 // Method java/lang/StringBuilder.append:(Ljava/lang/String;)Ljava/lang/StringBuilder;
      67: aload         5
      69: invokevirtual #32                 // Method java/lang/StringBuilder.append:(Ljava/lang/String;)Ljava/lang/StringBuilder;
      72: invokevirtual #34                 // Method java/lang/StringBuilder.toString:()Ljava/lang/String;
      75: invokespecial #8                  // Method debug:(Ljava/lang/Object;)V
      78: aload_0
      79: getfield      #4                  // Field serviceCache:Ljava/util/concurrent/ConcurrentHashMap;
      82: aload         5
      84: invokevirtual #47                 // Method java/util/concurrent/ConcurrentHashMap.remove:(Ljava/lang/Object;)Ljava/lang/Object;
      87: pop
      88: goto          32
      91: return

  public java.lang.Object create(java.lang.String) throws java.lang.IllegalAccessException, java.lang.InstantiationException, java.io.IOException, java.lang.ClassNotFoundException;
    Code:
       0: aload_0
       1: getfield      #4                  // Field serviceCache:Ljava/util/concurrent/ConcurrentHashMap;
       4: aload_1
       5: invokevirtual #48                 // Method java/util/concurrent/ConcurrentHashMap.get:(Ljava/lang/Object;)Ljava/lang/Object;
       8: checkcast     #49                 // class java/lang/Class
      11: astore_2
      12: aload_2
      13: ifnonnull     331
      16: new           #50                 // class java/lang/StringBuffer
      19: dup
      20: invokespecial #51                 // Method java/lang/StringBuffer."<init>":()V
      23: astore_3
      24: iconst_1
      25: istore        4
      27: aload_0
      28: getfield      #5                  // Field bundleWrappers:Ljava/util/concurrent/ConcurrentMap;
      31: invokeinterface #52,  1           // InterfaceMethod java/util/concurrent/ConcurrentMap.values:()Ljava/util/Collection;
      36: invokeinterface #53,  1           // InterfaceMethod java/util/Collection.iterator:()Ljava/util/Iterator;
      41: astore        5
      43: aload         5
      45: invokeinterface #44,  1           // InterfaceMethod java/util/Iterator.hasNext:()Z
      50: ifeq          258
      53: aload         5
      55: invokeinterface #21,  1           // InterfaceMethod java/util/Iterator.next:()Ljava/lang/Object;
      60: checkcast     #38                 // class org/apache/activemq/util/osgi/Activator$BundleWrapper
      63: astore        6
      65: aload         6
      67: invokestatic  #54                 // Method org/apache/activemq/util/osgi/Activator$BundleWrapper.access$100:(Lorg/apache/activemq/util/osgi/Activator$BundleWrapper;)Lorg/osgi/framework/Bundle;
      70: aload_1
      71: invokeinterface #55,  2           // InterfaceMethod org/osgi/framework/Bundle.getResource:(Ljava/lang/String;)Ljava/net/URL;
      76: astore        7
      78: aload         7
      80: ifnonnull     86
      83: goto          43
      86: aload_0
      87: aload         7
      89: invokespecial #56                 // Method loadProperties:(Ljava/net/URL;)Ljava/util/Properties;
      92: astore        8
      94: aload         8
      96: ldc           #57                 // String class
      98: invokevirtual #58                 // Method java/util/Properties.getProperty:(Ljava/lang/String;)Ljava/lang/String;
     101: astore        9
     103: aload         9
     105: ifnonnull     154
     108: aload_3
     109: new           #29                 // class java/lang/StringBuilder
     112: dup
     113: invokespecial #30                 // Method java/lang/StringBuilder."<init>":()V
     116: ldc           #59                 // String (
     118: invokevirtual #32                 // Method java/lang/StringBuilder.append:(Ljava/lang/String;)Ljava/lang/StringBuilder;
     121: iload         4
     123: iinc          4, 1
     126: invokevirtual #60                 // Method java/lang/StringBuilder.append:(I)Ljava/lang/StringBuilder;
     129: ldc           #61                 // String ) Invalid service file in bundle
     131: invokevirtual #32                 // Method java/lang/StringBuilder.append:(Ljava/lang/String;)Ljava/lang/StringBuilder;
     134: aload         6
     136: invokevirtual #62                 // Method java/lang/StringBuilder.append:(Ljava/lang/Object;)Ljava/lang/StringBuilder;
     139: ldc           #63                 // String : \'class\' property not defined.
     141: invokevirtual #32                 // Method java/lang/StringBuilder.append:(Ljava/lang/String;)Ljava/lang/StringBuilder;
     144: invokevirtual #34                 // Method java/lang/StringBuilder.toString:()Ljava/lang/String;
     147: invokevirtual #64                 // Method java/lang/StringBuffer.append:(Ljava/lang/String;)Ljava/lang/StringBuffer;
     150: pop
     151: goto          43
     154: aload         6
     156: invokestatic  #54                 // Method org/apache/activemq/util/osgi/Activator$BundleWrapper.access$100:(Lorg/apache/activemq/util/osgi/Activator$BundleWrapper;)Lorg/osgi/framework/Bundle;
     159: aload         9
     161: invokeinterface #65,  2           // InterfaceMethod org/osgi/framework/Bundle.loadClass:(Ljava/lang/String;)Ljava/lang/Class;
     166: astore_2
     167: goto          233
     170: astore        10
     172: aload_3
     173: new           #29                 // class java/lang/StringBuilder
     176: dup
     177: invokespecial #30                 // Method java/lang/StringBuilder."<init>":()V
     180: ldc           #59                 // String (
     182: invokevirtual #32                 // Method java/lang/StringBuilder.append:(Ljava/lang/String;)Ljava/lang/StringBuilder;
     185: iload         4
     187: iinc          4, 1
     190: invokevirtual #60                 // Method java/lang/StringBuilder.append:(I)Ljava/lang/StringBuilder;
     193: ldc           #67                 // String ) Bundle
     195: invokevirtual #32                 // Method java/lang/StringBuilder.append:(Ljava/lang/String;)Ljava/lang/StringBuilder;
     198: aload         6
     200: invokevirtual #62                 // Method java/lang/StringBuilder.append:(Ljava/lang/Object;)Ljava/lang/StringBuilder;
     203: ldc           #68                 // String  could not load
     205: invokevirtual #32                 // Method java/lang/StringBuilder.append:(Ljava/lang/String;)Ljava/lang/StringBuilder;
     208: aload         9
     210: invokevirtual #32                 // Method java/lang/StringBuilder.append:(Ljava/lang/String;)Ljava/lang/StringBuilder;
     213: ldc           #69                 // String :
     215: invokevirtual #32                 // Method java/lang/StringBuilder.append:(Ljava/lang/String;)Ljava/lang/StringBuilder;
     218: aload         10
     220: invokevirtual #62                 // Method java/lang/StringBuilder.append:(Ljava/lang/Object;)Ljava/lang/StringBuilder;
     223: invokevirtual #34                 // Method java/lang/StringBuilder.toString:()Ljava/lang/String;
     226: invokevirtual #64                 // Method java/lang/StringBuffer.append:(Ljava/lang/String;)Ljava/lang/StringBuffer;
     229: pop
     230: goto          43
     233: aload_0
     234: getfield      #4                  // Field serviceCache:Ljava/util/concurrent/ConcurrentHashMap;
     237: aload_1
     238: aload_2
     239: invokevirtual #70                 // Method java/util/concurrent/ConcurrentHashMap.put:(Ljava/lang/Object;Ljava/lang/Object;)Ljava/lang/Object;
     242: pop
     243: aload         6
     245: invokestatic  #42                 // Method org/apache/activemq/util/osgi/Activator$BundleWrapper.access$000:(Lorg/apache/activemq/util/osgi/Activator$BundleWrapper;)Ljava/util/List;
     248: aload_1
     249: invokeinterface #71,  2           // InterfaceMethod java/util/List.add:(Ljava/lang/Object;)Z
     254: pop
     255: goto          258
     258: aload_2
     259: ifnonnull     331
     262: new           #29                 // class java/lang/StringBuilder
     265: dup
     266: invokespecial #30                 // Method java/lang/StringBuilder."<init>":()V
     269: ldc           #72                 // String Service not found: \'
     271: invokevirtual #32                 // Method java/lang/StringBuilder.append:(Ljava/lang/String;)Ljava/lang/StringBuilder;
     274: aload_1
     275: invokevirtual #32                 // Method java/lang/StringBuilder.append:(Ljava/lang/String;)Ljava/lang/StringBuilder;
     278: ldc           #73                 // String \'
     280: invokevirtual #32                 // Method java/lang/StringBuilder.append:(Ljava/lang/String;)Ljava/lang/StringBuilder;
     283: invokevirtual #34                 // Method java/lang/StringBuilder.toString:()Ljava/lang/String;
     286: astore        5
     288: aload_3
     289: invokevirtual #74                 // Method java/lang/StringBuffer.length:()I
     292: ifeq          321
     295: new           #29                 // class java/lang/StringBuilder
     298: dup
     299: invokespecial #30                 // Method java/lang/StringBuilder."<init>":()V
     302: aload         5
     304: invokevirtual #32                 // Method java/lang/StringBuilder.append:(Ljava/lang/String;)Ljava/lang/StringBuilder;
     307: ldc           #75                 // String ,
     309: invokevirtual #32                 // Method java/lang/StringBuilder.append:(Ljava/lang/String;)Ljava/lang/StringBuilder;
     312: aload_3
     313: invokevirtual #62                 // Method java/lang/StringBuilder.append:(Ljava/lang/Object;)Ljava/lang/StringBuilder;
     316: invokevirtual #34                 // Method java/lang/StringBuilder.toString:()Ljava/lang/String;
     319: astore        5
     321: new           #76                 // class java/io/IOException
     324: dup
     325: aload         5
     327: invokespecial #77                 // Method java/io/IOException."<init>":(Ljava/lang/String;)V
     330: athrow
     331: aload_2
     332: invokevirtual #78                 // Method java/lang/Class.newInstance:()Ljava/lang/Object;
     335: areturn
    Exception table:
       from    to  target type
         154   167   170   Class java/lang/ClassNotFoundException

  private void debug(java.lang.Object);
    Code:
       0: getstatic     #79                 // Field LOG:Lorg/slf4j/Logger;
       3: aload_1
       4: invokevirtual #80                 // Method java/lang/Object.toString:()Ljava/lang/String;
       7: invokeinterface #81,  2           // InterfaceMethod org/slf4j/Logger.debug:(Ljava/lang/String;)V
      12: return

  private java.util.Properties loadProperties(java.net.URL) throws java.io.IOException;
    Code:
       0: aload_1
       1: invokevirtual #82                 // Method java/net/URL.openStream:()Ljava/io/InputStream;
       4: astore_2
       5: new           #83                 // class java/io/BufferedReader
       8: dup
       9: new           #84                 // class java/io/InputStreamReader
      12: dup
      13: aload_2
      14: ldc           #85                 // String UTF-8
      16: invokespecial #86                 // Method java/io/InputStreamReader."<init>":(Ljava/io/InputStream;Ljava/lang/String;)V
      19: invokespecial #87                 // Method java/io/BufferedReader."<init>":(Ljava/io/Reader;)V
      22: astore_3
      23: new           #88                 // class java/util/Properties
      26: dup
      27: invokespecial #89                 // Method java/util/Properties."<init>":()V
      30: astore        4
      32: aload         4
      34: aload_2
      35: invokevirtual #90                 // Method java/util/Properties.load:(Ljava/io/InputStream;)V
      38: aload         4
      40: astore        5
      42: aload_2
      43: invokevirtual #91                 // Method java/io/InputStream.close:()V
      46: goto          51
      49: astore        6
      51: aload         5
      53: areturn
      54: astore        7
      56: aload_2
      57: invokevirtual #91                 // Method java/io/InputStream.close:()V
      60: goto          65
      63: astore        8
      65: aload         7
      67: athrow
    Exception table:
       from    to  target type
          42    46    49   Class java/lang/Exception
           5    42    54   any
          56    60    63   Class java/lang/Exception
          54    56    54   any

  private boolean isImportingUs(org.osgi.framework.Bundle);
    Code:
       0: aload_0
       1: aload_1
       2: ldc_w         #93                 // class org/apache/activemq/Service
       5: invokespecial #94                 // Method isImportingClass:(Lorg/osgi/framework/Bundle;Ljava/lang/Class;)Z
       8: ifne          44
      11: aload_0
      12: aload_1
      13: ldc_w         #95                 // class org/apache/activemq/transport/Transport
      16: invokespecial #94                 // Method isImportingClass:(Lorg/osgi/framework/Bundle;Ljava/lang/Class;)Z
      19: ifne          44
      22: aload_0
      23: aload_1
      24: ldc_w         #96                 // class org/apache/activemq/transport/discovery/DiscoveryAgent
      27: invokespecial #94                 // Method isImportingClass:(Lorg/osgi/framework/Bundle;Ljava/lang/Class;)Z
      30: ifne          44
      33: aload_0
      34: aload_1
      35: ldc_w         #97                 // class org/apache/activemq/store/PersistenceAdapter
      38: invokespecial #94                 // Method isImportingClass:(Lorg/osgi/framework/Bundle;Ljava/lang/Class;)Z
      41: ifeq          48
      44: iconst_1
      45: goto          49
      48: iconst_0
      49: ireturn

  private boolean isImportingClass(org.osgi.framework.Bundle, java.lang.Class);
    Code:
       0: aload_1
       1: aload_2
       2: invokevirtual #98                 // Method java/lang/Class.getName:()Ljava/lang/String;
       5: invokeinterface #65,  2           // InterfaceMethod org/osgi/framework/Bundle.loadClass:(Ljava/lang/String;)Ljava/lang/Class;
      10: aload_2
      11: if_acmpne     18
      14: iconst_1
      15: goto          19
      18: iconst_0
      19: ireturn
      20: astore_3
      21: iconst_0
      22: ireturn
    Exception table:
       from    to  target type
           0    19    20   Class java/lang/ClassNotFoundException

  static {};
    Code:
       0: ldc_w         #99                 // class org/apache/activemq/util/osgi/Activator
       3: invokestatic  #100                // Method org/slf4j/LoggerFactory.getLogger:(Ljava/lang/Class;)Lorg/slf4j/Logger;
       6: putstatic     #79                 // Field LOG:Lorg/slf4j/Logger;
       9: return
}
