Compiled from "DeserializerFactoryConfig.java"
public class org.apache.htrace.shaded.fasterxml.jackson.databind.cfg.DeserializerFactoryConfig implements java.io.Serializable {
  private static final long serialVersionUID;

  protected static final org.apache.htrace.shaded.fasterxml.jackson.databind.deser.Deserializers[] NO_DESERIALIZERS;

  protected static final org.apache.htrace.shaded.fasterxml.jackson.databind.deser.BeanDeserializerModifier[] NO_MODIFIERS;

  protected static final org.apache.htrace.shaded.fasterxml.jackson.databind.AbstractTypeResolver[] NO_ABSTRACT_TYPE_RESOLVERS;

  protected static final org.apache.htrace.shaded.fasterxml.jackson.databind.deser.ValueInstantiators[] NO_VALUE_INSTANTIATORS;

  protected static final org.apache.htrace.shaded.fasterxml.jackson.databind.deser.KeyDeserializers[] DEFAULT_KEY_DESERIALIZERS;

  protected final org.apache.htrace.shaded.fasterxml.jackson.databind.deser.Deserializers[] _additionalDeserializers;

  protected final org.apache.htrace.shaded.fasterxml.jackson.databind.deser.KeyDeserializers[] _additionalKeyDeserializers;

  protected final org.apache.htrace.shaded.fasterxml.jackson.databind.deser.BeanDeserializerModifier[] _modifiers;

  protected final org.apache.htrace.shaded.fasterxml.jackson.databind.AbstractTypeResolver[] _abstractTypeResolvers;

  protected final org.apache.htrace.shaded.fasterxml.jackson.databind.deser.ValueInstantiators[] _valueInstantiators;

  public org.apache.htrace.shaded.fasterxml.jackson.databind.cfg.DeserializerFactoryConfig();
    Code:
       0: aload_0
       1: aconst_null
       2: aconst_null
       3: aconst_null
       4: aconst_null
       5: aconst_null
       6: invokespecial #31                 // Method "<init>":([Lorg/apache/htrace/shaded/fasterxml/jackson/databind/deser/Deserializers;[Lorg/apache/htrace/shaded/fasterxml/jackson/databind/deser/KeyDeserializers;[Lorg/apache/htrace/shaded/fasterxml/jackson/databind/deser/BeanDeserializerModifier;[Lorg/apache/htrace/shaded/fasterxml/jackson/databind/AbstractTypeResolver;[Lorg/apache/htrace/shaded/fasterxml/jackson/databind/deser/ValueInstantiators;)V
       9: return

  protected org.apache.htrace.shaded.fasterxml.jackson.databind.cfg.DeserializerFactoryConfig(org.apache.htrace.shaded.fasterxml.jackson.databind.deser.Deserializers[], org.apache.htrace.shaded.fasterxml.jackson.databind.deser.KeyDeserializers[], org.apache.htrace.shaded.fasterxml.jackson.databind.deser.BeanDeserializerModifier[], org.apache.htrace.shaded.fasterxml.jackson.databind.AbstractTypeResolver[], org.apache.htrace.shaded.fasterxml.jackson.databind.deser.ValueInstantiators[]);
    Code:
       0: aload_0
       1: invokespecial #35                 // Method java/lang/Object."<init>":()V
       4: aload_0
       5: aload_1
       6: ifnonnull     15
       9: getstatic     #37                 // Field NO_DESERIALIZERS:[Lorg/apache/htrace/shaded/fasterxml/jackson/databind/deser/Deserializers;
      12: goto          16
      15: aload_1
      16: putfield      #44                 // Field _additionalDeserializers:[Lorg/apache/htrace/shaded/fasterxml/jackson/databind/deser/Deserializers;
      19: aload_0
      20: aload_2
      21: ifnonnull     30
      24: getstatic     #46                 // Field DEFAULT_KEY_DESERIALIZERS:[Lorg/apache/htrace/shaded/fasterxml/jackson/databind/deser/KeyDeserializers;
      27: goto          31
      30: aload_2
      31: putfield      #48                 // Field _additionalKeyDeserializers:[Lorg/apache/htrace/shaded/fasterxml/jackson/databind/deser/KeyDeserializers;
      34: aload_0
      35: aload_3
      36: ifnonnull     45
      39: getstatic     #50                 // Field NO_MODIFIERS:[Lorg/apache/htrace/shaded/fasterxml/jackson/databind/deser/BeanDeserializerModifier;
      42: goto          46
      45: aload_3
      46: putfield      #52                 // Field _modifiers:[Lorg/apache/htrace/shaded/fasterxml/jackson/databind/deser/BeanDeserializerModifier;
      49: aload_0
      50: aload         4
      52: ifnonnull     61
      55: getstatic     #54                 // Field NO_ABSTRACT_TYPE_RESOLVERS:[Lorg/apache/htrace/shaded/fasterxml/jackson/databind/AbstractTypeResolver;
      58: goto          63
      61: aload         4
      63: putfield      #56                 // Field _abstractTypeResolvers:[Lorg/apache/htrace/shaded/fasterxml/jackson/databind/AbstractTypeResolver;
      66: aload_0
      67: aload         5
      69: ifnonnull     78
      72: getstatic     #58                 // Field NO_VALUE_INSTANTIATORS:[Lorg/apache/htrace/shaded/fasterxml/jackson/databind/deser/ValueInstantiators;
      75: goto          80
      78: aload         5
      80: putfield      #60                 // Field _valueInstantiators:[Lorg/apache/htrace/shaded/fasterxml/jackson/databind/deser/ValueInstantiators;
      83: return

  public org.apache.htrace.shaded.fasterxml.jackson.databind.cfg.DeserializerFactoryConfig withAdditionalDeserializers(org.apache.htrace.shaded.fasterxml.jackson.databind.deser.Deserializers);
    Code:
       0: aload_1
       1: ifnonnull     14
       4: new           #69                 // class java/lang/IllegalArgumentException
       7: dup
       8: ldc           #71                 // String Can not pass null Deserializers
      10: invokespecial #74                 // Method java/lang/IllegalArgumentException."<init>":(Ljava/lang/String;)V
      13: athrow
      14: aload_0
      15: getfield      #44                 // Field _additionalDeserializers:[Lorg/apache/htrace/shaded/fasterxml/jackson/databind/deser/Deserializers;
      18: aload_1
      19: invokestatic  #80                 // Method org/apache/htrace/shaded/fasterxml/jackson/databind/util/ArrayBuilders.insertInListNoDup:([Ljava/lang/Object;Ljava/lang/Object;)[Ljava/lang/Object;
      22: checkcast     #38                 // class "[Lorg/apache/htrace/shaded/fasterxml/jackson/databind/deser/Deserializers;"
      25: astore_2
      26: new           #2                  // class org/apache/htrace/shaded/fasterxml/jackson/databind/cfg/DeserializerFactoryConfig
      29: dup
      30: aload_2
      31: aload_0
      32: getfield      #48                 // Field _additionalKeyDeserializers:[Lorg/apache/htrace/shaded/fasterxml/jackson/databind/deser/KeyDeserializers;
      35: aload_0
      36: getfield      #52                 // Field _modifiers:[Lorg/apache/htrace/shaded/fasterxml/jackson/databind/deser/BeanDeserializerModifier;
      39: aload_0
      40: getfield      #56                 // Field _abstractTypeResolvers:[Lorg/apache/htrace/shaded/fasterxml/jackson/databind/AbstractTypeResolver;
      43: aload_0
      44: getfield      #60                 // Field _valueInstantiators:[Lorg/apache/htrace/shaded/fasterxml/jackson/databind/deser/ValueInstantiators;
      47: invokespecial #31                 // Method "<init>":([Lorg/apache/htrace/shaded/fasterxml/jackson/databind/deser/Deserializers;[Lorg/apache/htrace/shaded/fasterxml/jackson/databind/deser/KeyDeserializers;[Lorg/apache/htrace/shaded/fasterxml/jackson/databind/deser/BeanDeserializerModifier;[Lorg/apache/htrace/shaded/fasterxml/jackson/databind/AbstractTypeResolver;[Lorg/apache/htrace/shaded/fasterxml/jackson/databind/deser/ValueInstantiators;)V
      50: areturn

  public org.apache.htrace.shaded.fasterxml.jackson.databind.cfg.DeserializerFactoryConfig withAdditionalKeyDeserializers(org.apache.htrace.shaded.fasterxml.jackson.databind.deser.KeyDeserializers);
    Code:
       0: aload_1
       1: ifnonnull     14
       4: new           #69                 // class java/lang/IllegalArgumentException
       7: dup
       8: ldc           #87                 // String Can not pass null KeyDeserializers
      10: invokespecial #74                 // Method java/lang/IllegalArgumentException."<init>":(Ljava/lang/String;)V
      13: athrow
      14: aload_0
      15: getfield      #48                 // Field _additionalKeyDeserializers:[Lorg/apache/htrace/shaded/fasterxml/jackson/databind/deser/KeyDeserializers;
      18: aload_1
      19: invokestatic  #80                 // Method org/apache/htrace/shaded/fasterxml/jackson/databind/util/ArrayBuilders.insertInListNoDup:([Ljava/lang/Object;Ljava/lang/Object;)[Ljava/lang/Object;
      22: checkcast     #39                 // class "[Lorg/apache/htrace/shaded/fasterxml/jackson/databind/deser/KeyDeserializers;"
      25: astore_2
      26: new           #2                  // class org/apache/htrace/shaded/fasterxml/jackson/databind/cfg/DeserializerFactoryConfig
      29: dup
      30: aload_0
      31: getfield      #44                 // Field _additionalDeserializers:[Lorg/apache/htrace/shaded/fasterxml/jackson/databind/deser/Deserializers;
      34: aload_2
      35: aload_0
      36: getfield      #52                 // Field _modifiers:[Lorg/apache/htrace/shaded/fasterxml/jackson/databind/deser/BeanDeserializerModifier;
      39: aload_0
      40: getfield      #56                 // Field _abstractTypeResolvers:[Lorg/apache/htrace/shaded/fasterxml/jackson/databind/AbstractTypeResolver;
      43: aload_0
      44: getfield      #60                 // Field _valueInstantiators:[Lorg/apache/htrace/shaded/fasterxml/jackson/databind/deser/ValueInstantiators;
      47: invokespecial #31                 // Method "<init>":([Lorg/apache/htrace/shaded/fasterxml/jackson/databind/deser/Deserializers;[Lorg/apache/htrace/shaded/fasterxml/jackson/databind/deser/KeyDeserializers;[Lorg/apache/htrace/shaded/fasterxml/jackson/databind/deser/BeanDeserializerModifier;[Lorg/apache/htrace/shaded/fasterxml/jackson/databind/AbstractTypeResolver;[Lorg/apache/htrace/shaded/fasterxml/jackson/databind/deser/ValueInstantiators;)V
      50: areturn

  public org.apache.htrace.shaded.fasterxml.jackson.databind.cfg.DeserializerFactoryConfig withDeserializerModifier(org.apache.htrace.shaded.fasterxml.jackson.databind.deser.BeanDeserializerModifier);
    Code:
       0: aload_1
       1: ifnonnull     14
       4: new           #69                 // class java/lang/IllegalArgumentException
       7: dup
       8: ldc           #92                 // String Can not pass null modifier
      10: invokespecial #74                 // Method java/lang/IllegalArgumentException."<init>":(Ljava/lang/String;)V
      13: athrow
      14: aload_0
      15: getfield      #52                 // Field _modifiers:[Lorg/apache/htrace/shaded/fasterxml/jackson/databind/deser/BeanDeserializerModifier;
      18: aload_1
      19: invokestatic  #80                 // Method org/apache/htrace/shaded/fasterxml/jackson/databind/util/ArrayBuilders.insertInListNoDup:([Ljava/lang/Object;Ljava/lang/Object;)[Ljava/lang/Object;
      22: checkcast     #40                 // class "[Lorg/apache/htrace/shaded/fasterxml/jackson/databind/deser/BeanDeserializerModifier;"
      25: astore_2
      26: new           #2                  // class org/apache/htrace/shaded/fasterxml/jackson/databind/cfg/DeserializerFactoryConfig
      29: dup
      30: aload_0
      31: getfield      #44                 // Field _additionalDeserializers:[Lorg/apache/htrace/shaded/fasterxml/jackson/databind/deser/Deserializers;
      34: aload_0
      35: getfield      #48                 // Field _additionalKeyDeserializers:[Lorg/apache/htrace/shaded/fasterxml/jackson/databind/deser/KeyDeserializers;
      38: aload_2
      39: aload_0
      40: getfield      #56                 // Field _abstractTypeResolvers:[Lorg/apache/htrace/shaded/fasterxml/jackson/databind/AbstractTypeResolver;
      43: aload_0
      44: getfield      #60                 // Field _valueInstantiators:[Lorg/apache/htrace/shaded/fasterxml/jackson/databind/deser/ValueInstantiators;
      47: invokespecial #31                 // Method "<init>":([Lorg/apache/htrace/shaded/fasterxml/jackson/databind/deser/Deserializers;[Lorg/apache/htrace/shaded/fasterxml/jackson/databind/deser/KeyDeserializers;[Lorg/apache/htrace/shaded/fasterxml/jackson/databind/deser/BeanDeserializerModifier;[Lorg/apache/htrace/shaded/fasterxml/jackson/databind/AbstractTypeResolver;[Lorg/apache/htrace/shaded/fasterxml/jackson/databind/deser/ValueInstantiators;)V
      50: areturn

  public org.apache.htrace.shaded.fasterxml.jackson.databind.cfg.DeserializerFactoryConfig withAbstractTypeResolver(org.apache.htrace.shaded.fasterxml.jackson.databind.AbstractTypeResolver);
    Code:
       0: aload_1
       1: ifnonnull     14
       4: new           #69                 // class java/lang/IllegalArgumentException
       7: dup
       8: ldc           #98                 // String Can not pass null resolver
      10: invokespecial #74                 // Method java/lang/IllegalArgumentException."<init>":(Ljava/lang/String;)V
      13: athrow
      14: aload_0
      15: getfield      #56                 // Field _abstractTypeResolvers:[Lorg/apache/htrace/shaded/fasterxml/jackson/databind/AbstractTypeResolver;
      18: aload_1
      19: invokestatic  #80                 // Method org/apache/htrace/shaded/fasterxml/jackson/databind/util/ArrayBuilders.insertInListNoDup:([Ljava/lang/Object;Ljava/lang/Object;)[Ljava/lang/Object;
      22: checkcast     #41                 // class "[Lorg/apache/htrace/shaded/fasterxml/jackson/databind/AbstractTypeResolver;"
      25: astore_2
      26: new           #2                  // class org/apache/htrace/shaded/fasterxml/jackson/databind/cfg/DeserializerFactoryConfig
      29: dup
      30: aload_0
      31: getfield      #44                 // Field _additionalDeserializers:[Lorg/apache/htrace/shaded/fasterxml/jackson/databind/deser/Deserializers;
      34: aload_0
      35: getfield      #48                 // Field _additionalKeyDeserializers:[Lorg/apache/htrace/shaded/fasterxml/jackson/databind/deser/KeyDeserializers;
      38: aload_0
      39: getfield      #52                 // Field _modifiers:[Lorg/apache/htrace/shaded/fasterxml/jackson/databind/deser/BeanDeserializerModifier;
      42: aload_2
      43: aload_0
      44: getfield      #60                 // Field _valueInstantiators:[Lorg/apache/htrace/shaded/fasterxml/jackson/databind/deser/ValueInstantiators;
      47: invokespecial #31                 // Method "<init>":([Lorg/apache/htrace/shaded/fasterxml/jackson/databind/deser/Deserializers;[Lorg/apache/htrace/shaded/fasterxml/jackson/databind/deser/KeyDeserializers;[Lorg/apache/htrace/shaded/fasterxml/jackson/databind/deser/BeanDeserializerModifier;[Lorg/apache/htrace/shaded/fasterxml/jackson/databind/AbstractTypeResolver;[Lorg/apache/htrace/shaded/fasterxml/jackson/databind/deser/ValueInstantiators;)V
      50: areturn

  public org.apache.htrace.shaded.fasterxml.jackson.databind.cfg.DeserializerFactoryConfig withValueInstantiators(org.apache.htrace.shaded.fasterxml.jackson.databind.deser.ValueInstantiators);
    Code:
       0: aload_1
       1: ifnonnull     14
       4: new           #69                 // class java/lang/IllegalArgumentException
       7: dup
       8: ldc           #98                 // String Can not pass null resolver
      10: invokespecial #74                 // Method java/lang/IllegalArgumentException."<init>":(Ljava/lang/String;)V
      13: athrow
      14: aload_0
      15: getfield      #60                 // Field _valueInstantiators:[Lorg/apache/htrace/shaded/fasterxml/jackson/databind/deser/ValueInstantiators;
      18: aload_1
      19: invokestatic  #80                 // Method org/apache/htrace/shaded/fasterxml/jackson/databind/util/ArrayBuilders.insertInListNoDup:([Ljava/lang/Object;Ljava/lang/Object;)[Ljava/lang/Object;
      22: checkcast     #42                 // class "[Lorg/apache/htrace/shaded/fasterxml/jackson/databind/deser/ValueInstantiators;"
      25: astore_2
      26: new           #2                  // class org/apache/htrace/shaded/fasterxml/jackson/databind/cfg/DeserializerFactoryConfig
      29: dup
      30: aload_0
      31: getfield      #44                 // Field _additionalDeserializers:[Lorg/apache/htrace/shaded/fasterxml/jackson/databind/deser/Deserializers;
      34: aload_0
      35: getfield      #48                 // Field _additionalKeyDeserializers:[Lorg/apache/htrace/shaded/fasterxml/jackson/databind/deser/KeyDeserializers;
      38: aload_0
      39: getfield      #52                 // Field _modifiers:[Lorg/apache/htrace/shaded/fasterxml/jackson/databind/deser/BeanDeserializerModifier;
      42: aload_0
      43: getfield      #56                 // Field _abstractTypeResolvers:[Lorg/apache/htrace/shaded/fasterxml/jackson/databind/AbstractTypeResolver;
      46: aload_2
      47: invokespecial #31                 // Method "<init>":([Lorg/apache/htrace/shaded/fasterxml/jackson/databind/deser/Deserializers;[Lorg/apache/htrace/shaded/fasterxml/jackson/databind/deser/KeyDeserializers;[Lorg/apache/htrace/shaded/fasterxml/jackson/databind/deser/BeanDeserializerModifier;[Lorg/apache/htrace/shaded/fasterxml/jackson/databind/AbstractTypeResolver;[Lorg/apache/htrace/shaded/fasterxml/jackson/databind/deser/ValueInstantiators;)V
      50: areturn

  public boolean hasDeserializers();
    Code:
       0: aload_0
       1: getfield      #44                 // Field _additionalDeserializers:[Lorg/apache/htrace/shaded/fasterxml/jackson/databind/deser/Deserializers;
       4: arraylength
       5: ifle          12
       8: iconst_1
       9: goto          13
      12: iconst_0
      13: ireturn

  public boolean hasKeyDeserializers();
    Code:
       0: aload_0
       1: getfield      #48                 // Field _additionalKeyDeserializers:[Lorg/apache/htrace/shaded/fasterxml/jackson/databind/deser/KeyDeserializers;
       4: arraylength
       5: ifle          12
       8: iconst_1
       9: goto          13
      12: iconst_0
      13: ireturn

  public boolean hasDeserializerModifiers();
    Code:
       0: aload_0
       1: getfield      #52                 // Field _modifiers:[Lorg/apache/htrace/shaded/fasterxml/jackson/databind/deser/BeanDeserializerModifier;
       4: arraylength
       5: ifle          12
       8: iconst_1
       9: goto          13
      12: iconst_0
      13: ireturn

  public boolean hasAbstractTypeResolvers();
    Code:
       0: aload_0
       1: getfield      #56                 // Field _abstractTypeResolvers:[Lorg/apache/htrace/shaded/fasterxml/jackson/databind/AbstractTypeResolver;
       4: arraylength
       5: ifle          12
       8: iconst_1
       9: goto          13
      12: iconst_0
      13: ireturn

  public boolean hasValueInstantiators();
    Code:
       0: aload_0
       1: getfield      #60                 // Field _valueInstantiators:[Lorg/apache/htrace/shaded/fasterxml/jackson/databind/deser/ValueInstantiators;
       4: arraylength
       5: ifle          12
       8: iconst_1
       9: goto          13
      12: iconst_0
      13: ireturn

  public java.lang.Iterable<org.apache.htrace.shaded.fasterxml.jackson.databind.deser.Deserializers> deserializers();
    Code:
       0: new           #114                // class org/apache/htrace/shaded/fasterxml/jackson/databind/util/ArrayIterator
       3: dup
       4: aload_0
       5: getfield      #44                 // Field _additionalDeserializers:[Lorg/apache/htrace/shaded/fasterxml/jackson/databind/deser/Deserializers;
       8: invokespecial #117                // Method org/apache/htrace/shaded/fasterxml/jackson/databind/util/ArrayIterator."<init>":([Ljava/lang/Object;)V
      11: areturn

  public java.lang.Iterable<org.apache.htrace.shaded.fasterxml.jackson.databind.deser.KeyDeserializers> keyDeserializers();
    Code:
       0: new           #114                // class org/apache/htrace/shaded/fasterxml/jackson/databind/util/ArrayIterator
       3: dup
       4: aload_0
       5: getfield      #48                 // Field _additionalKeyDeserializers:[Lorg/apache/htrace/shaded/fasterxml/jackson/databind/deser/KeyDeserializers;
       8: invokespecial #117                // Method org/apache/htrace/shaded/fasterxml/jackson/databind/util/ArrayIterator."<init>":([Ljava/lang/Object;)V
      11: areturn

  public java.lang.Iterable<org.apache.htrace.shaded.fasterxml.jackson.databind.deser.BeanDeserializerModifier> deserializerModifiers();
    Code:
       0: new           #114                // class org/apache/htrace/shaded/fasterxml/jackson/databind/util/ArrayIterator
       3: dup
       4: aload_0
       5: getfield      #52                 // Field _modifiers:[Lorg/apache/htrace/shaded/fasterxml/jackson/databind/deser/BeanDeserializerModifier;
       8: invokespecial #117                // Method org/apache/htrace/shaded/fasterxml/jackson/databind/util/ArrayIterator."<init>":([Ljava/lang/Object;)V
      11: areturn

  public java.lang.Iterable<org.apache.htrace.shaded.fasterxml.jackson.databind.AbstractTypeResolver> abstractTypeResolvers();
    Code:
       0: new           #114                // class org/apache/htrace/shaded/fasterxml/jackson/databind/util/ArrayIterator
       3: dup
       4: aload_0
       5: getfield      #56                 // Field _abstractTypeResolvers:[Lorg/apache/htrace/shaded/fasterxml/jackson/databind/AbstractTypeResolver;
       8: invokespecial #117                // Method org/apache/htrace/shaded/fasterxml/jackson/databind/util/ArrayIterator."<init>":([Ljava/lang/Object;)V
      11: areturn

  public java.lang.Iterable<org.apache.htrace.shaded.fasterxml.jackson.databind.deser.ValueInstantiators> valueInstantiators();
    Code:
       0: new           #114                // class org/apache/htrace/shaded/fasterxml/jackson/databind/util/ArrayIterator
       3: dup
       4: aload_0
       5: getfield      #60                 // Field _valueInstantiators:[Lorg/apache/htrace/shaded/fasterxml/jackson/databind/deser/ValueInstantiators;
       8: invokespecial #117                // Method org/apache/htrace/shaded/fasterxml/jackson/databind/util/ArrayIterator."<init>":([Ljava/lang/Object;)V
      11: areturn

  static {};
    Code:
       0: iconst_0
       1: anewarray     #124                // class org/apache/htrace/shaded/fasterxml/jackson/databind/deser/Deserializers
       4: putstatic     #37                 // Field NO_DESERIALIZERS:[Lorg/apache/htrace/shaded/fasterxml/jackson/databind/deser/Deserializers;
       7: iconst_0
       8: anewarray     #126                // class org/apache/htrace/shaded/fasterxml/jackson/databind/deser/BeanDeserializerModifier
      11: putstatic     #50                 // Field NO_MODIFIERS:[Lorg/apache/htrace/shaded/fasterxml/jackson/databind/deser/BeanDeserializerModifier;
      14: iconst_0
      15: anewarray     #128                // class org/apache/htrace/shaded/fasterxml/jackson/databind/AbstractTypeResolver
      18: putstatic     #54                 // Field NO_ABSTRACT_TYPE_RESOLVERS:[Lorg/apache/htrace/shaded/fasterxml/jackson/databind/AbstractTypeResolver;
      21: iconst_0
      22: anewarray     #130                // class org/apache/htrace/shaded/fasterxml/jackson/databind/deser/ValueInstantiators
      25: putstatic     #58                 // Field NO_VALUE_INSTANTIATORS:[Lorg/apache/htrace/shaded/fasterxml/jackson/databind/deser/ValueInstantiators;
      28: iconst_1
      29: anewarray     #132                // class org/apache/htrace/shaded/fasterxml/jackson/databind/deser/KeyDeserializers
      32: dup
      33: iconst_0
      34: new           #134                // class org/apache/htrace/shaded/fasterxml/jackson/databind/deser/std/StdKeyDeserializers
      37: dup
      38: invokespecial #135                // Method org/apache/htrace/shaded/fasterxml/jackson/databind/deser/std/StdKeyDeserializers."<init>":()V
      41: aastore
      42: putstatic     #46                 // Field DEFAULT_KEY_DESERIALIZERS:[Lorg/apache/htrace/shaded/fasterxml/jackson/databind/deser/KeyDeserializers;
      45: return
}
