Compiled from "CLI.scala"
public final class laserdisc.cli.CLI$impl$$anonfun$mkStream$2$$anonfun$apply$7$$anonfun$apply$8$$anonfun$apply$9 extends scala.runtime.AbstractFunction1<laserdisc.fs2.RedisClient<cats.effect.IO>, cats.effect.IO<cats.effect.ExitCode>> implements scala.Serializable {
  public static final long serialVersionUID;

  private final laserdisc.cli.CLI$impl$$anonfun$mkStream$2$$anonfun$apply$7$$anonfun$apply$8 $outer;

  private laserdisc.cli.CLI$impl$$anonfun$mkStream$2$$anonfun$apply$7$$anonfun$apply$8$$anonfun$apply$9$ToMillis$2$ laserdisc$cli$CLI$impl$$anonfun$$anonfun$$anonfun$$anonfun$$ToMillis$1$lzycompute(scala.runtime.VolatileObjectRef);
    Code:
       0: aload_0
       1: dup
       2: astore_2
       3: monitorenter
       4: aload_1
       5: getfield      #24                 // Field scala/runtime/VolatileObjectRef.elem:Ljava/lang/Object;
       8: ifnonnull     23
      11: aload_1
      12: new           #26                 // class laserdisc/cli/CLI$impl$$anonfun$mkStream$2$$anonfun$apply$7$$anonfun$apply$8$$anonfun$apply$9$ToMillis$2$
      15: dup
      16: aload_0
      17: invokespecial #30                 // Method laserdisc/cli/CLI$impl$$anonfun$mkStream$2$$anonfun$apply$7$$anonfun$apply$8$$anonfun$apply$9$ToMillis$2$."<init>":(Llaserdisc/cli/CLI$impl$$anonfun$mkStream$2$$anonfun$apply$7$$anonfun$apply$8$$anonfun$apply$9;)V
      20: putfield      #24                 // Field scala/runtime/VolatileObjectRef.elem:Ljava/lang/Object;
      23: getstatic     #36                 // Field scala/runtime/BoxedUnit.UNIT:Lscala/runtime/BoxedUnit;
      26: pop
      27: aload_2
      28: monitorexit
      29: aconst_null
      30: pop
      31: aload_1
      32: getfield      #24                 // Field scala/runtime/VolatileObjectRef.elem:Ljava/lang/Object;
      35: checkcast     #26                 // class laserdisc/cli/CLI$impl$$anonfun$mkStream$2$$anonfun$apply$7$$anonfun$apply$8$$anonfun$apply$9$ToMillis$2$
      38: areturn
      39: aload_2
      40: monitorexit
      41: athrow
    Exception table:
       from    to  target type
           4    29    39   any

  public final cats.effect.IO<cats.effect.ExitCode> apply(laserdisc.fs2.RedisClient<cats.effect.IO>);
    Code:
       0: invokestatic  #48                 // Method scala/runtime/VolatileObjectRef.zero:()Lscala/runtime/VolatileObjectRef;
       3: astore_2
       4: getstatic     #54                 // Field fs2/Stream$.MODULE$:Lfs2/Stream$;
       7: getstatic     #59                 // Field laserdisc/fs2/package$.MODULE$:Llaserdisc/fs2/package$;
      10: invokevirtual #63                 // Method laserdisc/fs2/package$.Stream:()Lfs2/Stream$;
      13: new           #65                 // class scala/StringContext
      16: dup
      17: getstatic     #70                 // Field scala/Predef$.MODULE$:Lscala/Predef$;
      20: iconst_3
      21: anewarray     #72                 // class java/lang/String
      24: dup
      25: iconst_0
      26: ldc           #74                 // String
      28: aastore
      29: dup
      30: iconst_1
      31: ldc           #76                 // String :
      33: aastore
      34: dup
      35: iconst_2
      36: ldc           #78                 // String >
      38: aastore
      39: checkcast     #80                 // class "[Ljava/lang/Object;"
      42: invokevirtual #84                 // Method scala/Predef$.wrapRefArray:([Ljava/lang/Object;)Lscala/collection/mutable/WrappedArray;
      45: invokespecial #87                 // Method scala/StringContext."<init>":(Lscala/collection/Seq;)V
      48: getstatic     #70                 // Field scala/Predef$.MODULE$:Lscala/Predef$;
      51: iconst_2
      52: anewarray     #89                 // class java/lang/Object
      55: dup
      56: iconst_0
      57: new           #91                 // class eu/timepit/refined/api/Refined
      60: dup
      61: aload_0
      62: getfield      #93                 // Field $outer:Llaserdisc/cli/CLI$impl$$anonfun$mkStream$2$$anonfun$apply$7$$anonfun$apply$8;
      65: invokevirtual #97                 // Method laserdisc/cli/CLI$impl$$anonfun$mkStream$2$$anonfun$apply$7$$anonfun$apply$8.laserdisc$cli$CLI$impl$$anonfun$$anonfun$$anonfun$$$outer:()Llaserdisc/cli/CLI$impl$$anonfun$mkStream$2$$anonfun$apply$7;
      68: invokevirtual #103                // Method laserdisc/cli/CLI$impl$$anonfun$mkStream$2$$anonfun$apply$7.laserdisc$cli$CLI$impl$$anonfun$$anonfun$$$outer:()Llaserdisc/cli/CLI$impl$$anonfun$mkStream$2;
      71: getfield      #109                // Field laserdisc/cli/CLI$impl$$anonfun$mkStream$2.host$1:Ljava/lang/String;
      74: invokespecial #112                // Method eu/timepit/refined/api/Refined."<init>":(Ljava/lang/Object;)V
      77: aastore
      78: dup
      79: iconst_1
      80: new           #91                 // class eu/timepit/refined/api/Refined
      83: dup
      84: aload_0
      85: getfield      #93                 // Field $outer:Llaserdisc/cli/CLI$impl$$anonfun$mkStream$2$$anonfun$apply$7$$anonfun$apply$8;
      88: invokevirtual #97                 // Method laserdisc/cli/CLI$impl$$anonfun$mkStream$2$$anonfun$apply$7$$anonfun$apply$8.laserdisc$cli$CLI$impl$$anonfun$$anonfun$$anonfun$$$outer:()Llaserdisc/cli/CLI$impl$$anonfun$mkStream$2$$anonfun$apply$7;
      91: invokevirtual #103                // Method laserdisc/cli/CLI$impl$$anonfun$mkStream$2$$anonfun$apply$7.laserdisc$cli$CLI$impl$$anonfun$$anonfun$$$outer:()Llaserdisc/cli/CLI$impl$$anonfun$mkStream$2;
      94: getfield      #116                // Field laserdisc/cli/CLI$impl$$anonfun$mkStream$2.port$1:Ljava/lang/Integer;
      97: invokespecial #112                // Method eu/timepit/refined/api/Refined."<init>":(Ljava/lang/Object;)V
     100: aastore
     101: invokevirtual #120                // Method scala/Predef$.genericWrapArray:(Ljava/lang/Object;)Lscala/collection/mutable/WrappedArray;
     104: invokevirtual #124                // Method scala/StringContext.s:(Lscala/collection/Seq;)Ljava/lang/String;
     107: invokevirtual #128                // Method fs2/Stream$.emit:(Ljava/lang/Object;)Lfs2/internal/FreeC;
     110: invokevirtual #132                // Method fs2/Stream$.repeat$extension:(Lfs2/internal/FreeC;)Lfs2/internal/FreeC;
     113: astore_3
     114: getstatic     #54                 // Field fs2/Stream$.MODULE$:Lfs2/Stream$;
     117: getstatic     #54                 // Field fs2/Stream$.MODULE$:Lfs2/Stream$;
     120: getstatic     #54                 // Field fs2/Stream$.MODULE$:Lfs2/Stream$;
     123: getstatic     #54                 // Field fs2/Stream$.MODULE$:Lfs2/Stream$;
     126: aload_3
     127: invokevirtual #135                // Method fs2/Stream$.head$extension:(Lfs2/internal/FreeC;)Lfs2/internal/FreeC;
     130: getstatic     #140                // Field fs2/text$.MODULE$:Lfs2/text$;
     133: invokevirtual #144                // Method fs2/text$.utf8Encode:()Lscala/Function1;
     136: invokevirtual #148                // Method fs2/Stream$.through$extension:(Lfs2/internal/FreeC;Lscala/Function1;)Lfs2/internal/FreeC;
     139: getstatic     #153                // Field fs2/io/package$.MODULE$:Lfs2/io/package$;
     142: aload_0
     143: getfield      #93                 // Field $outer:Llaserdisc/cli/CLI$impl$$anonfun$mkStream$2$$anonfun$apply$7$$anonfun$apply$8;
     146: getfield      #157                // Field laserdisc/cli/CLI$impl$$anonfun$mkStream$2$$anonfun$apply$7$$anonfun$apply$8.blockingEC$1:Lscala/concurrent/ExecutionContextExecutorService;
     149: getstatic     #162                // Field cats/effect/IO$.MODULE$:Lcats/effect/IO$;
     152: getstatic     #167                // Field laserdisc/cli/CLI$.MODULE$:Llaserdisc/cli/CLI$;
     155: invokevirtual #171                // Method laserdisc/cli/CLI$.contextShift:()Lcats/effect/ContextShift;
     158: invokevirtual #175                // Method cats/effect/IO$.ioConcurrentEffect:(Lcats/effect/ContextShift;)Lcats/effect/ConcurrentEffect;
     161: getstatic     #167                // Field laserdisc/cli/CLI$.MODULE$:Llaserdisc/cli/CLI$;
     164: invokevirtual #171                // Method laserdisc/cli/CLI$.contextShift:()Lcats/effect/ContextShift;
     167: invokevirtual #179                // Method fs2/io/package$.stdout:(Lscala/concurrent/ExecutionContext;Lcats/effect/Sync;Lcats/effect/ContextShift;)Lscala/Function1;
     170: invokevirtual #182                // Method fs2/Stream$.to$extension:(Lfs2/internal/FreeC;Lscala/Function1;)Lfs2/internal/FreeC;
     173: getstatic     #187                // Field fs2/Stream$Compiler$.MODULE$:Lfs2/Stream$Compiler$;
     176: getstatic     #162                // Field cats/effect/IO$.MODULE$:Lcats/effect/IO$;
     179: getstatic     #167                // Field laserdisc/cli/CLI$.MODULE$:Llaserdisc/cli/CLI$;
     182: invokevirtual #171                // Method laserdisc/cli/CLI$.contextShift:()Lcats/effect/ContextShift;
     185: invokevirtual #175                // Method cats/effect/IO$.ioConcurrentEffect:(Lcats/effect/ContextShift;)Lcats/effect/ConcurrentEffect;
     188: invokevirtual #191                // Method fs2/Stream$Compiler$.syncInstance:(Lcats/effect/Sync;)Lfs2/Stream$Compiler;
     191: invokevirtual #195                // Method fs2/Stream$.compile$extension:(Lfs2/internal/FreeC;Lfs2/Stream$Compiler;)Lfs2/Stream$CompileOps;
     194: invokevirtual #201                // Method fs2/Stream$CompileOps.drain:()Ljava/lang/Object;
     197: checkcast     #203                // class cats/effect/IO
     200: astore        4
     202: new           #205                // class laserdisc/cli/CLI$impl$$anonfun$mkStream$2$$anonfun$apply$7$$anonfun$apply$8$$anonfun$apply$9$$anonfun$4
     205: dup
     206: aload_0
     207: aload_3
     208: invokespecial #208                // Method laserdisc/cli/CLI$impl$$anonfun$mkStream$2$$anonfun$apply$7$$anonfun$apply$8$$anonfun$apply$9$$anonfun$4."<init>":(Llaserdisc/cli/CLI$impl$$anonfun$mkStream$2$$anonfun$apply$7$$anonfun$apply$8$$anonfun$apply$9;Lfs2/internal/FreeC;)V
     211: astore        5
     213: getstatic     #213                // Field cats/syntax/FlatMapOps$.MODULE$:Lcats/syntax/FlatMapOps$;
     216: getstatic     #218                // Field cats/syntax/package$all$.MODULE$:Lcats/syntax/package$all$;
     219: aload         4
     221: getstatic     #162                // Field cats/effect/IO$.MODULE$:Lcats/effect/IO$;
     224: getstatic     #167                // Field laserdisc/cli/CLI$.MODULE$:Llaserdisc/cli/CLI$;
     227: invokevirtual #171                // Method laserdisc/cli/CLI$.contextShift:()Lcats/effect/ContextShift;
     230: invokevirtual #175                // Method cats/effect/IO$.ioConcurrentEffect:(Lcats/effect/ContextShift;)Lcats/effect/ConcurrentEffect;
     233: invokevirtual #222                // Method cats/syntax/package$all$.catsSyntaxFlatMapOps:(Ljava/lang/Object;Lcats/FlatMap;)Ljava/lang/Object;
     236: new           #224                // class laserdisc/cli/CLI$impl$$anonfun$mkStream$2$$anonfun$apply$7$$anonfun$apply$8$$anonfun$apply$9$$anonfun$apply$12
     239: dup
     240: aload_0
     241: aload_3
     242: aload         5
     244: aload_2
     245: aload_1
     246: invokespecial #227                // Method laserdisc/cli/CLI$impl$$anonfun$mkStream$2$$anonfun$apply$7$$anonfun$apply$8$$anonfun$apply$9$$anonfun$apply$12."<init>":(Llaserdisc/cli/CLI$impl$$anonfun$mkStream$2$$anonfun$apply$7$$anonfun$apply$8$$anonfun$apply$9;Lfs2/internal/FreeC;Lscala/Function1;Lscala/runtime/VolatileObjectRef;Llaserdisc/fs2/RedisClient;)V
     249: getstatic     #162                // Field cats/effect/IO$.MODULE$:Lcats/effect/IO$;
     252: getstatic     #167                // Field laserdisc/cli/CLI$.MODULE$:Llaserdisc/cli/CLI$;
     255: invokevirtual #171                // Method laserdisc/cli/CLI$.contextShift:()Lcats/effect/ContextShift;
     258: invokevirtual #175                // Method cats/effect/IO$.ioConcurrentEffect:(Lcats/effect/ContextShift;)Lcats/effect/ConcurrentEffect;
     261: invokevirtual #231                // Method cats/syntax/FlatMapOps$.$greater$greater$extension:(Ljava/lang/Object;Lscala/Function0;Lcats/FlatMap;)Ljava/lang/Object;
     264: checkcast     #203                // class cats/effect/IO
     267: areturn

  public laserdisc.cli.CLI$impl$$anonfun$mkStream$2$$anonfun$apply$7$$anonfun$apply$8 laserdisc$cli$CLI$impl$$anonfun$$anonfun$$anonfun$$anonfun$$$outer();
    Code:
       0: aload_0
       1: getfield      #93                 // Field $outer:Llaserdisc/cli/CLI$impl$$anonfun$mkStream$2$$anonfun$apply$7$$anonfun$apply$8;
       4: areturn

  public final java.lang.Object apply(java.lang.Object);
    Code:
       0: aload_0
       1: aload_1
       2: checkcast     #245                // class laserdisc/fs2/RedisClient
       5: invokevirtual #247                // Method apply:(Llaserdisc/fs2/RedisClient;)Lcats/effect/IO;
       8: areturn

  public final cats.effect.IO laserdisc$cli$CLI$impl$$anonfun$$anonfun$$anonfun$$anonfun$$prompt$1(java.lang.String, fs2.internal.FreeC);
    Code:
       0: getstatic     #54                 // Field fs2/Stream$.MODULE$:Lfs2/Stream$;
       3: getstatic     #54                 // Field fs2/Stream$.MODULE$:Lfs2/Stream$;
       6: getstatic     #54                 // Field fs2/Stream$.MODULE$:Lfs2/Stream$;
       9: getstatic     #54                 // Field fs2/Stream$.MODULE$:Lfs2/Stream$;
      12: getstatic     #59                 // Field laserdisc/fs2/package$.MODULE$:Llaserdisc/fs2/package$;
      15: invokevirtual #63                 // Method laserdisc/fs2/package$.Stream:()Lfs2/Stream$;
      18: aload_1
      19: invokevirtual #128                // Method fs2/Stream$.emit:(Ljava/lang/Object;)Lfs2/internal/FreeC;
      22: new           #252                // class laserdisc/cli/CLI$impl$$anonfun$mkStream$2$$anonfun$apply$7$$anonfun$apply$8$$anonfun$apply$9$$anonfun$laserdisc$cli$CLI$impl$$anonfun$$anonfun$$anonfun$$anonfun$$prompt$1$1
      25: dup
      26: aload_0
      27: aload_2
      28: invokespecial #253                // Method laserdisc/cli/CLI$impl$$anonfun$mkStream$2$$anonfun$apply$7$$anonfun$apply$8$$anonfun$apply$9$$anonfun$laserdisc$cli$CLI$impl$$anonfun$$anonfun$$anonfun$$anonfun$$prompt$1$1."<init>":(Llaserdisc/cli/CLI$impl$$anonfun$mkStream$2$$anonfun$apply$7$$anonfun$apply$8$$anonfun$apply$9;Lfs2/internal/FreeC;)V
      31: invokevirtual #257                // Method fs2/Stream$.append$extension:(Lfs2/internal/FreeC;Lscala/Function0;)Lfs2/internal/FreeC;
      34: getstatic     #140                // Field fs2/text$.MODULE$:Lfs2/text$;
      37: invokevirtual #144                // Method fs2/text$.utf8Encode:()Lscala/Function1;
      40: invokevirtual #148                // Method fs2/Stream$.through$extension:(Lfs2/internal/FreeC;Lscala/Function1;)Lfs2/internal/FreeC;
      43: getstatic     #153                // Field fs2/io/package$.MODULE$:Lfs2/io/package$;
      46: aload_0
      47: getfield      #93                 // Field $outer:Llaserdisc/cli/CLI$impl$$anonfun$mkStream$2$$anonfun$apply$7$$anonfun$apply$8;
      50: getfield      #157                // Field laserdisc/cli/CLI$impl$$anonfun$mkStream$2$$anonfun$apply$7$$anonfun$apply$8.blockingEC$1:Lscala/concurrent/ExecutionContextExecutorService;
      53: getstatic     #162                // Field cats/effect/IO$.MODULE$:Lcats/effect/IO$;
      56: getstatic     #167                // Field laserdisc/cli/CLI$.MODULE$:Llaserdisc/cli/CLI$;
      59: invokevirtual #171                // Method laserdisc/cli/CLI$.contextShift:()Lcats/effect/ContextShift;
      62: invokevirtual #175                // Method cats/effect/IO$.ioConcurrentEffect:(Lcats/effect/ContextShift;)Lcats/effect/ConcurrentEffect;
      65: getstatic     #167                // Field laserdisc/cli/CLI$.MODULE$:Llaserdisc/cli/CLI$;
      68: invokevirtual #171                // Method laserdisc/cli/CLI$.contextShift:()Lcats/effect/ContextShift;
      71: invokevirtual #179                // Method fs2/io/package$.stdout:(Lscala/concurrent/ExecutionContext;Lcats/effect/Sync;Lcats/effect/ContextShift;)Lscala/Function1;
      74: invokevirtual #182                // Method fs2/Stream$.to$extension:(Lfs2/internal/FreeC;Lscala/Function1;)Lfs2/internal/FreeC;
      77: getstatic     #187                // Field fs2/Stream$Compiler$.MODULE$:Lfs2/Stream$Compiler$;
      80: getstatic     #162                // Field cats/effect/IO$.MODULE$:Lcats/effect/IO$;
      83: getstatic     #167                // Field laserdisc/cli/CLI$.MODULE$:Llaserdisc/cli/CLI$;
      86: invokevirtual #171                // Method laserdisc/cli/CLI$.contextShift:()Lcats/effect/ContextShift;
      89: invokevirtual #175                // Method cats/effect/IO$.ioConcurrentEffect:(Lcats/effect/ContextShift;)Lcats/effect/ConcurrentEffect;
      92: invokevirtual #191                // Method fs2/Stream$Compiler$.syncInstance:(Lcats/effect/Sync;)Lfs2/Stream$Compiler;
      95: invokevirtual #195                // Method fs2/Stream$.compile$extension:(Lfs2/internal/FreeC;Lfs2/Stream$Compiler;)Lfs2/Stream$CompileOps;
      98: invokevirtual #201                // Method fs2/Stream$CompileOps.drain:()Ljava/lang/Object;
     101: checkcast     #203                // class cats/effect/IO
     104: areturn

  public final laserdisc.cli.CLI$impl$$anonfun$mkStream$2$$anonfun$apply$7$$anonfun$apply$8$$anonfun$apply$9$ToMillis$2$ laserdisc$cli$CLI$impl$$anonfun$$anonfun$$anonfun$$anonfun$$ToMillis$1(scala.runtime.VolatileObjectRef);
    Code:
       0: aload_1
       1: getfield      #24                 // Field scala/runtime/VolatileObjectRef.elem:Ljava/lang/Object;
       4: ifnonnull     15
       7: aload_0
       8: aload_1
       9: invokespecial #262                // Method laserdisc$cli$CLI$impl$$anonfun$$anonfun$$anonfun$$anonfun$$ToMillis$1$lzycompute:(Lscala/runtime/VolatileObjectRef;)Llaserdisc/cli/CLI$impl$$anonfun$mkStream$2$$anonfun$apply$7$$anonfun$apply$8$$anonfun$apply$9$ToMillis$2$;
      12: goto          22
      15: aload_1
      16: getfield      #24                 // Field scala/runtime/VolatileObjectRef.elem:Ljava/lang/Object;
      19: checkcast     #26                 // class laserdisc/cli/CLI$impl$$anonfun$mkStream$2$$anonfun$apply$7$$anonfun$apply$8$$anonfun$apply$9$ToMillis$2$
      22: areturn

  public final cats.effect.IO laserdisc$cli$CLI$impl$$anonfun$$anonfun$$anonfun$$anonfun$$mkProtocol$1(java.lang.String);
    Code:
       0: getstatic     #162                // Field cats/effect/IO$.MODULE$:Lcats/effect/IO$;
       3: new           #267                // class laserdisc/cli/CLI$impl$$anonfun$mkStream$2$$anonfun$apply$7$$anonfun$apply$8$$anonfun$apply$9$$anonfun$laserdisc$cli$CLI$impl$$anonfun$$anonfun$$anonfun$$anonfun$$mkProtocol$1$1
       6: dup
       7: aload_0
       8: aload_1
       9: invokespecial #270                // Method laserdisc/cli/CLI$impl$$anonfun$mkStream$2$$anonfun$apply$7$$anonfun$apply$8$$anonfun$apply$9$$anonfun$laserdisc$cli$CLI$impl$$anonfun$$anonfun$$anonfun$$anonfun$$mkProtocol$1$1."<init>":(Llaserdisc/cli/CLI$impl$$anonfun$mkStream$2$$anonfun$apply$7$$anonfun$apply$8$$anonfun$apply$9;Ljava/lang/String;)V
      12: invokevirtual #274                // Method cats/effect/IO$.delay:(Lscala/Function0;)Lcats/effect/IO;
      15: invokevirtual #278                // Method cats/effect/IO.attempt:()Lcats/effect/IO;
      18: areturn

  public laserdisc.cli.CLI$impl$$anonfun$mkStream$2$$anonfun$apply$7$$anonfun$apply$8$$anonfun$apply$9(laserdisc.cli.CLI$impl$$anonfun$mkStream$2$$anonfun$apply$7$$anonfun$apply$8);
    Code:
       0: aload_1
       1: ifnonnull     6
       4: aconst_null
       5: athrow
       6: aload_0
       7: aload_1
       8: putfield      #93                 // Field $outer:Llaserdisc/cli/CLI$impl$$anonfun$mkStream$2$$anonfun$apply$7$$anonfun$apply$8;
      11: aload_0
      12: invokespecial #283                // Method scala/runtime/AbstractFunction1."<init>":()V
      15: return
}
