Compiled from "CLI.scala"
public final class laserdisc.cli.CLI$impl$$anonfun$mkStream$1$$anonfun$apply$4 extends scala.runtime.AbstractFunction0<java.nio.channels.AsynchronousChannelGroup> implements scala.Serializable {
  public static final long serialVersionUID;

  public final java.nio.channels.AsynchronousChannelGroup apply();
    Code:
       0: bipush        8
       2: invokestatic  #24                 // Method java/util/concurrent/Executors.newFixedThreadPool:(I)Ljava/util/concurrent/ExecutorService;
       5: invokestatic  #30                 // Method java/nio/channels/AsynchronousChannelGroup.withThreadPool:(Ljava/util/concurrent/ExecutorService;)Ljava/nio/channels/AsynchronousChannelGroup;
       8: areturn

  public final java.lang.Object apply();
    Code:
       0: aload_0
       1: invokevirtual #35                 // Method apply:()Ljava/nio/channels/AsynchronousChannelGroup;
       4: areturn

  public laserdisc.cli.CLI$impl$$anonfun$mkStream$1$$anonfun$apply$4(laserdisc.cli.CLI$impl$$anonfun$mkStream$1);
    Code:
       0: aload_0
       1: invokespecial #40                 // Method scala/runtime/AbstractFunction0."<init>":()V
       4: return
}
