Compiled from "ProjectMetaDataValidator.java"
public class org.sklsft.generator.components.validation.ProjectMetaDataValidator {
  public org.sklsft.generator.components.validation.ProjectMetaDataValidator();
    Code:
       0: aload_0
       1: invokespecial #1                  // Method java/lang/Object."<init>":()V
       4: return

  public org.sklsft.generator.model.metadata.validation.ProjectValidationReport validate(org.sklsft.generator.model.metadata.ProjectMetaData);
    Code:
       0: new           #2                  // class org/sklsft/generator/model/metadata/validation/ProjectValidationReport
       3: dup
       4: invokespecial #3                  // Method org/sklsft/generator/model/metadata/validation/ProjectValidationReport."<init>":()V
       7: astore_2
       8: invokestatic  #4                  // Method org/sklsft/generator/components/validation/rules/impl/Rules.values:()[Lorg/sklsft/generator/components/validation/rules/impl/Rules;
      11: astore_3
      12: aload_3
      13: arraylength
      14: istore        4
      16: iconst_0
      17: istore        5
      19: iload         5
      21: iload         4
      23: if_icmpge     98
      26: aload_3
      27: iload         5
      29: aaload
      30: astore        6
      32: aload         6
      34: invokevirtual #5                  // Method org/sklsft/generator/components/validation/rules/impl/Rules.getCheckerClass:()Ljava/lang/Class;
      37: invokevirtual #6                  // Method java/lang/Class.newInstance:()Ljava/lang/Object;
      40: checkcast     #7                  // class org/sklsft/generator/components/validation/rules/ProjectMetaDataRuleChecker
      43: aload_1
      44: aload_2
      45: invokeinterface #8,  3            // InterfaceMethod org/sklsft/generator/components/validation/rules/ProjectMetaDataRuleChecker.checkRules:(Lorg/sklsft/generator/model/metadata/ProjectMetaData;Lorg/sklsft/generator/model/metadata/validation/ProjectValidationReport;)Lorg/sklsft/generator/model/metadata/validation/ProjectValidationReport;
      50: astore_2
      51: goto          92
      54: astore        7
      56: new           #11                 // class java/lang/Error
      59: dup
      60: new           #12                 // class java/lang/StringBuilder
      63: dup
      64: invokespecial #13                 // Method java/lang/StringBuilder."<init>":()V
      67: ldc           #14                 // String Could not instantiate :
      69: invokevirtual #15                 // Method java/lang/StringBuilder.append:(Ljava/lang/String;)Ljava/lang/StringBuilder;
      72: aload         6
      74: invokevirtual #5                  // Method org/sklsft/generator/components/validation/rules/impl/Rules.getCheckerClass:()Ljava/lang/Class;
      77: invokevirtual #16                 // Method java/lang/Class.getName:()Ljava/lang/String;
      80: invokevirtual #15                 // Method java/lang/StringBuilder.append:(Ljava/lang/String;)Ljava/lang/StringBuilder;
      83: invokevirtual #17                 // Method java/lang/StringBuilder.toString:()Ljava/lang/String;
      86: aload         7
      88: invokespecial #18                 // Method java/lang/Error."<init>":(Ljava/lang/String;Ljava/lang/Throwable;)V
      91: athrow
      92: iinc          5, 1
      95: goto          19
      98: aload_2
      99: areturn
    Exception table:
       from    to  target type
          32    51    54   Class java/lang/InstantiationException
          32    51    54   Class java/lang/IllegalAccessException
}
