Compiled from "ApplicationTimeoutPBImpl.java"
public class org.apache.hadoop.yarn.api.records.impl.pb.ApplicationTimeoutPBImpl extends org.apache.hadoop.yarn.api.records.ApplicationTimeout {
  private org.apache.hadoop.yarn.proto.YarnProtos$ApplicationTimeoutProto proto;

  private org.apache.hadoop.yarn.proto.YarnProtos$ApplicationTimeoutProto$Builder builder;

  private boolean viaProto;

  public org.apache.hadoop.yarn.api.records.impl.pb.ApplicationTimeoutPBImpl();
    Code:
       0: aload_0
       1: invokespecial #1                  // Method org/apache/hadoop/yarn/api/records/ApplicationTimeout."<init>":()V
       4: aload_0
       5: invokestatic  #2                  // Method org/apache/hadoop/yarn/proto/YarnProtos$ApplicationTimeoutProto.getDefaultInstance:()Lorg/apache/hadoop/yarn/proto/YarnProtos$ApplicationTimeoutProto;
       8: putfield      #3                  // Field proto:Lorg/apache/hadoop/yarn/proto/YarnProtos$ApplicationTimeoutProto;
      11: aload_0
      12: aconst_null
      13: putfield      #4                  // Field builder:Lorg/apache/hadoop/yarn/proto/YarnProtos$ApplicationTimeoutProto$Builder;
      16: aload_0
      17: iconst_0
      18: putfield      #5                  // Field viaProto:Z
      21: aload_0
      22: invokestatic  #6                  // Method org/apache/hadoop/yarn/proto/YarnProtos$ApplicationTimeoutProto.newBuilder:()Lorg/apache/hadoop/yarn/proto/YarnProtos$ApplicationTimeoutProto$Builder;
      25: putfield      #4                  // Field builder:Lorg/apache/hadoop/yarn/proto/YarnProtos$ApplicationTimeoutProto$Builder;
      28: return

  public org.apache.hadoop.yarn.api.records.impl.pb.ApplicationTimeoutPBImpl(org.apache.hadoop.yarn.proto.YarnProtos$ApplicationTimeoutProto);
    Code:
       0: aload_0
       1: invokespecial #1                  // Method org/apache/hadoop/yarn/api/records/ApplicationTimeout."<init>":()V
       4: aload_0
       5: invokestatic  #2                  // Method org/apache/hadoop/yarn/proto/YarnProtos$ApplicationTimeoutProto.getDefaultInstance:()Lorg/apache/hadoop/yarn/proto/YarnProtos$ApplicationTimeoutProto;
       8: putfield      #3                  // Field proto:Lorg/apache/hadoop/yarn/proto/YarnProtos$ApplicationTimeoutProto;
      11: aload_0
      12: aconst_null
      13: putfield      #4                  // Field builder:Lorg/apache/hadoop/yarn/proto/YarnProtos$ApplicationTimeoutProto$Builder;
      16: aload_0
      17: iconst_0
      18: putfield      #5                  // Field viaProto:Z
      21: aload_0
      22: aload_1
      23: putfield      #3                  // Field proto:Lorg/apache/hadoop/yarn/proto/YarnProtos$ApplicationTimeoutProto;
      26: aload_0
      27: iconst_1
      28: putfield      #5                  // Field viaProto:Z
      31: return

  public org.apache.hadoop.yarn.proto.YarnProtos$ApplicationTimeoutProto getProto();
    Code:
       0: aload_0
       1: aload_0
       2: getfield      #5                  // Field viaProto:Z
       5: ifeq          15
       8: aload_0
       9: getfield      #3                  // Field proto:Lorg/apache/hadoop/yarn/proto/YarnProtos$ApplicationTimeoutProto;
      12: goto          22
      15: aload_0
      16: getfield      #4                  // Field builder:Lorg/apache/hadoop/yarn/proto/YarnProtos$ApplicationTimeoutProto$Builder;
      19: invokevirtual #7                  // Method org/apache/hadoop/yarn/proto/YarnProtos$ApplicationTimeoutProto$Builder.build:()Lorg/apache/hadoop/yarn/proto/YarnProtos$ApplicationTimeoutProto;
      22: putfield      #3                  // Field proto:Lorg/apache/hadoop/yarn/proto/YarnProtos$ApplicationTimeoutProto;
      25: aload_0
      26: iconst_1
      27: putfield      #5                  // Field viaProto:Z
      30: aload_0
      31: getfield      #3                  // Field proto:Lorg/apache/hadoop/yarn/proto/YarnProtos$ApplicationTimeoutProto;
      34: areturn

  private void maybeInitBuilder();
    Code:
       0: aload_0
       1: getfield      #5                  // Field viaProto:Z
       4: ifne          14
       7: aload_0
       8: getfield      #4                  // Field builder:Lorg/apache/hadoop/yarn/proto/YarnProtos$ApplicationTimeoutProto$Builder;
      11: ifnonnull     25
      14: aload_0
      15: aload_0
      16: getfield      #3                  // Field proto:Lorg/apache/hadoop/yarn/proto/YarnProtos$ApplicationTimeoutProto;
      19: invokestatic  #8                  // Method org/apache/hadoop/yarn/proto/YarnProtos$ApplicationTimeoutProto.newBuilder:(Lorg/apache/hadoop/yarn/proto/YarnProtos$ApplicationTimeoutProto;)Lorg/apache/hadoop/yarn/proto/YarnProtos$ApplicationTimeoutProto$Builder;
      22: putfield      #4                  // Field builder:Lorg/apache/hadoop/yarn/proto/YarnProtos$ApplicationTimeoutProto$Builder;
      25: aload_0
      26: iconst_0
      27: putfield      #5                  // Field viaProto:Z
      30: return

  public org.apache.hadoop.yarn.api.records.ApplicationTimeoutType getTimeoutType();
    Code:
       0: aload_0
       1: getfield      #5                  // Field viaProto:Z
       4: ifeq          14
       7: aload_0
       8: getfield      #3                  // Field proto:Lorg/apache/hadoop/yarn/proto/YarnProtos$ApplicationTimeoutProto;
      11: goto          18
      14: aload_0
      15: getfield      #4                  // Field builder:Lorg/apache/hadoop/yarn/proto/YarnProtos$ApplicationTimeoutProto$Builder;
      18: astore_1
      19: aload_1
      20: invokeinterface #9,  1            // InterfaceMethod org/apache/hadoop/yarn/proto/YarnProtos$ApplicationTimeoutProtoOrBuilder.hasApplicationTimeoutType:()Z
      25: ifne          30
      28: aconst_null
      29: areturn
      30: aload_1
      31: invokeinterface #10,  1           // InterfaceMethod org/apache/hadoop/yarn/proto/YarnProtos$ApplicationTimeoutProtoOrBuilder.getApplicationTimeoutType:()Lorg/apache/hadoop/yarn/proto/YarnProtos$ApplicationTimeoutTypeProto;
      36: invokestatic  #11                 // Method org/apache/hadoop/yarn/api/records/impl/pb/ProtoUtils.convertFromProtoFormat:(Lorg/apache/hadoop/yarn/proto/YarnProtos$ApplicationTimeoutTypeProto;)Lorg/apache/hadoop/yarn/api/records/ApplicationTimeoutType;
      39: areturn

  public void setTimeoutType(org.apache.hadoop.yarn.api.records.ApplicationTimeoutType);
    Code:
       0: aload_0
       1: invokespecial #12                 // Method maybeInitBuilder:()V
       4: aload_1
       5: ifnonnull     17
       8: aload_0
       9: getfield      #4                  // Field builder:Lorg/apache/hadoop/yarn/proto/YarnProtos$ApplicationTimeoutProto$Builder;
      12: invokevirtual #13                 // Method org/apache/hadoop/yarn/proto/YarnProtos$ApplicationTimeoutProto$Builder.clearApplicationTimeoutType:()Lorg/apache/hadoop/yarn/proto/YarnProtos$ApplicationTimeoutProto$Builder;
      15: pop
      16: return
      17: aload_0
      18: getfield      #4                  // Field builder:Lorg/apache/hadoop/yarn/proto/YarnProtos$ApplicationTimeoutProto$Builder;
      21: aload_1
      22: invokestatic  #14                 // Method org/apache/hadoop/yarn/api/records/impl/pb/ProtoUtils.convertToProtoFormat:(Lorg/apache/hadoop/yarn/api/records/ApplicationTimeoutType;)Lorg/apache/hadoop/yarn/proto/YarnProtos$ApplicationTimeoutTypeProto;
      25: invokevirtual #15                 // Method org/apache/hadoop/yarn/proto/YarnProtos$ApplicationTimeoutProto$Builder.setApplicationTimeoutType:(Lorg/apache/hadoop/yarn/proto/YarnProtos$ApplicationTimeoutTypeProto;)Lorg/apache/hadoop/yarn/proto/YarnProtos$ApplicationTimeoutProto$Builder;
      28: pop
      29: return

  public java.lang.String getExpiryTime();
    Code:
       0: aload_0
       1: getfield      #5                  // Field viaProto:Z
       4: ifeq          14
       7: aload_0
       8: getfield      #3                  // Field proto:Lorg/apache/hadoop/yarn/proto/YarnProtos$ApplicationTimeoutProto;
      11: goto          18
      14: aload_0
      15: getfield      #4                  // Field builder:Lorg/apache/hadoop/yarn/proto/YarnProtos$ApplicationTimeoutProto$Builder;
      18: astore_1
      19: aload_1
      20: invokeinterface #16,  1           // InterfaceMethod org/apache/hadoop/yarn/proto/YarnProtos$ApplicationTimeoutProtoOrBuilder.hasExpireTime:()Z
      25: ifne          30
      28: aconst_null
      29: areturn
      30: aload_1
      31: invokeinterface #17,  1           // InterfaceMethod org/apache/hadoop/yarn/proto/YarnProtos$ApplicationTimeoutProtoOrBuilder.getExpireTime:()Ljava/lang/String;
      36: areturn

  public void setExpiryTime(java.lang.String);
    Code:
       0: aload_0
       1: invokespecial #12                 // Method maybeInitBuilder:()V
       4: aload_1
       5: ifnonnull     17
       8: aload_0
       9: getfield      #4                  // Field builder:Lorg/apache/hadoop/yarn/proto/YarnProtos$ApplicationTimeoutProto$Builder;
      12: invokevirtual #18                 // Method org/apache/hadoop/yarn/proto/YarnProtos$ApplicationTimeoutProto$Builder.clearExpireTime:()Lorg/apache/hadoop/yarn/proto/YarnProtos$ApplicationTimeoutProto$Builder;
      15: pop
      16: return
      17: aload_0
      18: getfield      #4                  // Field builder:Lorg/apache/hadoop/yarn/proto/YarnProtos$ApplicationTimeoutProto$Builder;
      21: aload_1
      22: invokevirtual #19                 // Method org/apache/hadoop/yarn/proto/YarnProtos$ApplicationTimeoutProto$Builder.setExpireTime:(Ljava/lang/String;)Lorg/apache/hadoop/yarn/proto/YarnProtos$ApplicationTimeoutProto$Builder;
      25: pop
      26: return

  public long getRemainingTime();
    Code:
       0: aload_0
       1: getfield      #5                  // Field viaProto:Z
       4: ifeq          14
       7: aload_0
       8: getfield      #3                  // Field proto:Lorg/apache/hadoop/yarn/proto/YarnProtos$ApplicationTimeoutProto;
      11: goto          18
      14: aload_0
      15: getfield      #4                  // Field builder:Lorg/apache/hadoop/yarn/proto/YarnProtos$ApplicationTimeoutProto$Builder;
      18: astore_1
      19: aload_1
      20: invokeinterface #20,  1           // InterfaceMethod org/apache/hadoop/yarn/proto/YarnProtos$ApplicationTimeoutProtoOrBuilder.getRemainingTime:()J
      25: lreturn

  public void setRemainingTime(long);
    Code:
       0: aload_0
       1: invokespecial #12                 // Method maybeInitBuilder:()V
       4: aload_0
       5: getfield      #4                  // Field builder:Lorg/apache/hadoop/yarn/proto/YarnProtos$ApplicationTimeoutProto$Builder;
       8: lload_1
       9: invokevirtual #21                 // Method org/apache/hadoop/yarn/proto/YarnProtos$ApplicationTimeoutProto$Builder.setRemainingTime:(J)Lorg/apache/hadoop/yarn/proto/YarnProtos$ApplicationTimeoutProto$Builder;
      12: pop
      13: return

  public int hashCode();
    Code:
       0: aload_0
       1: invokevirtual #22                 // Method getProto:()Lorg/apache/hadoop/yarn/proto/YarnProtos$ApplicationTimeoutProto;
       4: invokevirtual #23                 // Method org/apache/hadoop/yarn/proto/YarnProtos$ApplicationTimeoutProto.hashCode:()I
       7: ireturn

  public boolean equals(java.lang.Object);
    Code:
       0: aload_1
       1: ifnonnull     6
       4: iconst_0
       5: ireturn
       6: aload_1
       7: invokevirtual #24                 // Method java/lang/Object.getClass:()Ljava/lang/Class;
      10: aload_0
      11: invokevirtual #24                 // Method java/lang/Object.getClass:()Ljava/lang/Class;
      14: invokevirtual #25                 // Method java/lang/Class.isAssignableFrom:(Ljava/lang/Class;)Z
      17: ifeq          42
      20: aload_0
      21: invokevirtual #22                 // Method getProto:()Lorg/apache/hadoop/yarn/proto/YarnProtos$ApplicationTimeoutProto;
      24: aload_0
      25: invokevirtual #24                 // Method java/lang/Object.getClass:()Ljava/lang/Class;
      28: aload_1
      29: invokevirtual #26                 // Method java/lang/Class.cast:(Ljava/lang/Object;)Ljava/lang/Object;
      32: checkcast     #27                 // class org/apache/hadoop/yarn/api/records/impl/pb/ApplicationTimeoutPBImpl
      35: invokevirtual #22                 // Method getProto:()Lorg/apache/hadoop/yarn/proto/YarnProtos$ApplicationTimeoutProto;
      38: invokevirtual #28                 // Method org/apache/hadoop/yarn/proto/YarnProtos$ApplicationTimeoutProto.equals:(Ljava/lang/Object;)Z
      41: ireturn
      42: iconst_0
      43: ireturn

  public java.lang.String toString();
    Code:
       0: aload_0
       1: invokevirtual #22                 // Method getProto:()Lorg/apache/hadoop/yarn/proto/YarnProtos$ApplicationTimeoutProto;
       4: invokestatic  #29                 // Method com/google/protobuf/TextFormat.shortDebugString:(Lcom/google/protobuf/MessageOrBuilder;)Ljava/lang/String;
       7: areturn
}
