Compiled from "ResourcePBImpl.java"
public class org.apache.hadoop.yarn.api.records.impl.pb.ResourcePBImpl extends org.apache.hadoop.yarn.api.records.Resource {
  private static final org.apache.commons.logging.Log LOG;

  org.apache.hadoop.yarn.proto.YarnProtos$ResourceProto proto;

  org.apache.hadoop.yarn.proto.YarnProtos$ResourceProto$Builder builder;

  boolean viaProto;

  static org.apache.hadoop.yarn.proto.YarnProtos$ResourceProto getProto(org.apache.hadoop.yarn.api.records.Resource);
    Code:
       0: aload_0
       1: instanceof    #1                  // class org/apache/hadoop/yarn/api/records/impl/pb/ResourcePBImpl
       4: ifeq          15
       7: aload_0
       8: checkcast     #1                  // class org/apache/hadoop/yarn/api/records/impl/pb/ResourcePBImpl
      11: astore_1
      12: goto          79
      15: new           #1                  // class org/apache/hadoop/yarn/api/records/impl/pb/ResourcePBImpl
      18: dup
      19: invokespecial #2                  // Method "<init>":()V
      22: astore_1
      23: aload_1
      24: aload_0
      25: invokevirtual #3                  // Method org/apache/hadoop/yarn/api/records/Resource.getMemorySize:()J
      28: invokevirtual #4                  // Method setMemorySize:(J)V
      31: aload_1
      32: aload_0
      33: invokevirtual #5                  // Method org/apache/hadoop/yarn/api/records/Resource.getVirtualCores:()I
      36: invokevirtual #6                  // Method setVirtualCores:(I)V
      39: aload_0
      40: invokevirtual #7                  // Method org/apache/hadoop/yarn/api/records/Resource.getResources:()[Lorg/apache/hadoop/yarn/api/records/ResourceInformation;
      43: astore_2
      44: aload_2
      45: arraylength
      46: istore_3
      47: iconst_0
      48: istore        4
      50: iload         4
      52: iload_3
      53: if_icmpge     79
      56: aload_2
      57: iload         4
      59: aaload
      60: astore        5
      62: aload_1
      63: aload         5
      65: invokevirtual #8                  // Method org/apache/hadoop/yarn/api/records/ResourceInformation.getName:()Ljava/lang/String;
      68: aload         5
      70: invokevirtual #9                  // Method setResourceInformation:(Ljava/lang/String;Lorg/apache/hadoop/yarn/api/records/ResourceInformation;)V
      73: iinc          4, 1
      76: goto          50
      79: aload_1
      80: invokevirtual #10                 // Method getProto:()Lorg/apache/hadoop/yarn/proto/YarnProtos$ResourceProto;
      83: areturn

  public org.apache.hadoop.yarn.api.records.impl.pb.ResourcePBImpl();
    Code:
       0: aload_0
       1: invokespecial #11                 // Method org/apache/hadoop/yarn/api/records/Resource."<init>":()V
       4: aload_0
       5: invokestatic  #12                 // Method org/apache/hadoop/yarn/proto/YarnProtos$ResourceProto.getDefaultInstance:()Lorg/apache/hadoop/yarn/proto/YarnProtos$ResourceProto;
       8: putfield      #13                 // Field proto:Lorg/apache/hadoop/yarn/proto/YarnProtos$ResourceProto;
      11: aload_0
      12: aconst_null
      13: putfield      #14                 // Field builder:Lorg/apache/hadoop/yarn/proto/YarnProtos$ResourceProto$Builder;
      16: aload_0
      17: iconst_0
      18: putfield      #15                 // Field viaProto:Z
      21: aload_0
      22: invokestatic  #16                 // Method org/apache/hadoop/yarn/proto/YarnProtos$ResourceProto.newBuilder:()Lorg/apache/hadoop/yarn/proto/YarnProtos$ResourceProto$Builder;
      25: putfield      #14                 // Field builder:Lorg/apache/hadoop/yarn/proto/YarnProtos$ResourceProto$Builder;
      28: aload_0
      29: invokespecial #17                 // Method initResources:()V
      32: return

  public org.apache.hadoop.yarn.api.records.impl.pb.ResourcePBImpl(org.apache.hadoop.yarn.proto.YarnProtos$ResourceProto);
    Code:
       0: aload_0
       1: invokespecial #11                 // Method org/apache/hadoop/yarn/api/records/Resource."<init>":()V
       4: aload_0
       5: invokestatic  #12                 // Method org/apache/hadoop/yarn/proto/YarnProtos$ResourceProto.getDefaultInstance:()Lorg/apache/hadoop/yarn/proto/YarnProtos$ResourceProto;
       8: putfield      #13                 // Field proto:Lorg/apache/hadoop/yarn/proto/YarnProtos$ResourceProto;
      11: aload_0
      12: aconst_null
      13: putfield      #14                 // Field builder:Lorg/apache/hadoop/yarn/proto/YarnProtos$ResourceProto$Builder;
      16: aload_0
      17: iconst_0
      18: putfield      #15                 // Field viaProto:Z
      21: aload_0
      22: aload_1
      23: putfield      #13                 // Field proto:Lorg/apache/hadoop/yarn/proto/YarnProtos$ResourceProto;
      26: aload_0
      27: iconst_1
      28: putfield      #15                 // Field viaProto:Z
      31: aload_0
      32: invokespecial #17                 // Method initResources:()V
      35: return

  public synchronized org.apache.hadoop.yarn.proto.YarnProtos$ResourceProto getProto();
    Code:
       0: aload_0
       1: invokespecial #18                 // Method mergeLocalToProto:()V
       4: aload_0
       5: aload_0
       6: getfield      #15                 // Field viaProto:Z
       9: ifeq          19
      12: aload_0
      13: getfield      #13                 // Field proto:Lorg/apache/hadoop/yarn/proto/YarnProtos$ResourceProto;
      16: goto          26
      19: aload_0
      20: getfield      #14                 // Field builder:Lorg/apache/hadoop/yarn/proto/YarnProtos$ResourceProto$Builder;
      23: invokevirtual #19                 // Method org/apache/hadoop/yarn/proto/YarnProtos$ResourceProto$Builder.build:()Lorg/apache/hadoop/yarn/proto/YarnProtos$ResourceProto;
      26: putfield      #13                 // Field proto:Lorg/apache/hadoop/yarn/proto/YarnProtos$ResourceProto;
      29: aload_0
      30: iconst_1
      31: putfield      #15                 // Field viaProto:Z
      34: aload_0
      35: getfield      #13                 // Field proto:Lorg/apache/hadoop/yarn/proto/YarnProtos$ResourceProto;
      38: areturn

  private synchronized void maybeInitBuilder();
    Code:
       0: aload_0
       1: getfield      #15                 // Field viaProto:Z
       4: ifne          14
       7: aload_0
       8: getfield      #14                 // Field builder:Lorg/apache/hadoop/yarn/proto/YarnProtos$ResourceProto$Builder;
      11: ifnonnull     25
      14: aload_0
      15: aload_0
      16: getfield      #13                 // Field proto:Lorg/apache/hadoop/yarn/proto/YarnProtos$ResourceProto;
      19: invokestatic  #20                 // Method org/apache/hadoop/yarn/proto/YarnProtos$ResourceProto.newBuilder:(Lorg/apache/hadoop/yarn/proto/YarnProtos$ResourceProto;)Lorg/apache/hadoop/yarn/proto/YarnProtos$ResourceProto$Builder;
      22: putfield      #14                 // Field builder:Lorg/apache/hadoop/yarn/proto/YarnProtos$ResourceProto$Builder;
      25: aload_0
      26: iconst_0
      27: putfield      #15                 // Field viaProto:Z
      30: return

  public int getMemory();
    Code:
       0: aload_0
       1: invokevirtual #21                 // Method getMemorySize:()J
       4: invokestatic  #22                 // Method castToIntSafely:(J)I
       7: ireturn

  public long getMemorySize();
    Code:
       0: aload_0
       1: getfield      #23                 // Field resources:[Lorg/apache/hadoop/yarn/api/records/ResourceInformation;
       4: iconst_0
       5: aaload
       6: astore_1
       7: aload_1
       8: invokevirtual #25                 // Method org/apache/hadoop/yarn/api/records/ResourceInformation.getUnits:()Ljava/lang/String;
      11: invokevirtual #26                 // Method java/lang/String.isEmpty:()Z
      14: ifeq          22
      17: aload_1
      18: invokevirtual #27                 // Method org/apache/hadoop/yarn/api/records/ResourceInformation.getValue:()J
      21: lreturn
      22: aload_1
      23: invokevirtual #25                 // Method org/apache/hadoop/yarn/api/records/ResourceInformation.getUnits:()Ljava/lang/String;
      26: getstatic     #28                 // Field org/apache/hadoop/yarn/api/records/ResourceInformation.MEMORY_MB:Lorg/apache/hadoop/yarn/api/records/ResourceInformation;
      29: invokevirtual #25                 // Method org/apache/hadoop/yarn/api/records/ResourceInformation.getUnits:()Ljava/lang/String;
      32: aload_1
      33: invokevirtual #27                 // Method org/apache/hadoop/yarn/api/records/ResourceInformation.getValue:()J
      36: invokestatic  #29                 // Method org/apache/hadoop/yarn/util/UnitsConversionUtil.convert:(Ljava/lang/String;Ljava/lang/String;J)J
      39: lreturn

  public void setMemory(int);
    Code:
       0: aload_0
       1: iload_1
       2: i2l
       3: invokevirtual #4                  // Method setMemorySize:(J)V
       6: return

  public void setMemorySize(long);
    Code:
       0: aload_0
       1: invokespecial #30                 // Method maybeInitBuilder:()V
       4: aload_0
       5: getfield      #23                 // Field resources:[Lorg/apache/hadoop/yarn/api/records/ResourceInformation;
       8: iconst_0
       9: aaload
      10: lload_1
      11: invokevirtual #31                 // Method org/apache/hadoop/yarn/api/records/ResourceInformation.setValue:(J)V
      14: return

  public int getVirtualCores();
    Code:
       0: aload_0
       1: getfield      #23                 // Field resources:[Lorg/apache/hadoop/yarn/api/records/ResourceInformation;
       4: iconst_1
       5: aaload
       6: invokevirtual #27                 // Method org/apache/hadoop/yarn/api/records/ResourceInformation.getValue:()J
       9: invokestatic  #22                 // Method castToIntSafely:(J)I
      12: ireturn

  public void setVirtualCores(int);
    Code:
       0: aload_0
       1: invokespecial #30                 // Method maybeInitBuilder:()V
       4: aload_0
       5: getfield      #23                 // Field resources:[Lorg/apache/hadoop/yarn/api/records/ResourceInformation;
       8: iconst_1
       9: aaload
      10: iload_1
      11: i2l
      12: invokevirtual #31                 // Method org/apache/hadoop/yarn/api/records/ResourceInformation.setValue:(J)V
      15: return

  private synchronized void initResources();
    Code:
       0: aload_0
       1: getfield      #23                 // Field resources:[Lorg/apache/hadoop/yarn/api/records/ResourceInformation;
       4: ifnull        8
       7: return
       8: aload_0
       9: getfield      #15                 // Field viaProto:Z
      12: ifeq          22
      15: aload_0
      16: getfield      #13                 // Field proto:Lorg/apache/hadoop/yarn/proto/YarnProtos$ResourceProto;
      19: goto          26
      22: aload_0
      23: getfield      #14                 // Field builder:Lorg/apache/hadoop/yarn/proto/YarnProtos$ResourceProto$Builder;
      26: astore_1
      27: invokestatic  #32                 // Method org/apache/hadoop/yarn/util/resource/ResourceUtils.getResourceTypesArray:()[Lorg/apache/hadoop/yarn/api/records/ResourceInformation;
      30: astore_2
      31: invokestatic  #33                 // Method org/apache/hadoop/yarn/util/resource/ResourceUtils.getResourceTypeIndex:()Ljava/util/Map;
      34: astore_3
      35: aload_0
      36: aload_2
      37: arraylength
      38: anewarray     #34                 // class org/apache/hadoop/yarn/api/records/ResourceInformation
      41: putfield      #23                 // Field resources:[Lorg/apache/hadoop/yarn/api/records/ResourceInformation;
      44: aload_1
      45: invokeinterface #35,  1           // InterfaceMethod org/apache/hadoop/yarn/proto/YarnProtos$ResourceProtoOrBuilder.getResourceValueMapList:()Ljava/util/List;
      50: invokeinterface #36,  1           // InterfaceMethod java/util/List.iterator:()Ljava/util/Iterator;
      55: astore        4
      57: aload         4
      59: invokeinterface #37,  1           // InterfaceMethod java/util/Iterator.hasNext:()Z
      64: ifeq          164
      67: aload         4
      69: invokeinterface #38,  1           // InterfaceMethod java/util/Iterator.next:()Ljava/lang/Object;
      74: checkcast     #39                 // class org/apache/hadoop/yarn/proto/YarnProtos$ResourceInformationProto
      77: astore        5
      79: aload_3
      80: aload         5
      82: invokevirtual #40                 // Method org/apache/hadoop/yarn/proto/YarnProtos$ResourceInformationProto.getKey:()Ljava/lang/String;
      85: invokeinterface #41,  2           // InterfaceMethod java/util/Map.get:(Ljava/lang/Object;)Ljava/lang/Object;
      90: checkcast     #42                 // class java/lang/Integer
      93: astore        6
      95: aload         6
      97: ifnonnull     139
     100: getstatic     #43                 // Field LOG:Lorg/apache/commons/logging/Log;
     103: new           #44                 // class java/lang/StringBuilder
     106: dup
     107: invokespecial #45                 // Method java/lang/StringBuilder."<init>":()V
     110: ldc           #46                 // String Got unknown resource type:
     112: invokevirtual #47                 // Method java/lang/StringBuilder.append:(Ljava/lang/String;)Ljava/lang/StringBuilder;
     115: aload         5
     117: invokevirtual #40                 // Method org/apache/hadoop/yarn/proto/YarnProtos$ResourceInformationProto.getKey:()Ljava/lang/String;
     120: invokevirtual #47                 // Method java/lang/StringBuilder.append:(Ljava/lang/String;)Ljava/lang/StringBuilder;
     123: ldc           #48                 // String ; skipping
     125: invokevirtual #47                 // Method java/lang/StringBuilder.append:(Ljava/lang/String;)Ljava/lang/StringBuilder;
     128: invokevirtual #49                 // Method java/lang/StringBuilder.toString:()Ljava/lang/String;
     131: invokeinterface #50,  2           // InterfaceMethod org/apache/commons/logging/Log.warn:(Ljava/lang/Object;)V
     136: goto          161
     139: aload_0
     140: getfield      #23                 // Field resources:[Lorg/apache/hadoop/yarn/api/records/ResourceInformation;
     143: aload         6
     145: invokevirtual #51                 // Method java/lang/Integer.intValue:()I
     148: aload_2
     149: aload         6
     151: invokevirtual #51                 // Method java/lang/Integer.intValue:()I
     154: aaload
     155: aload         5
     157: invokestatic  #52                 // Method newDefaultInformation:(Lorg/apache/hadoop/yarn/api/records/ResourceInformation;Lorg/apache/hadoop/yarn/proto/YarnProtos$ResourceInformationProto;)Lorg/apache/hadoop/yarn/api/records/ResourceInformation;
     160: aastore
     161: goto          57
     164: aload_0
     165: getfield      #23                 // Field resources:[Lorg/apache/hadoop/yarn/api/records/ResourceInformation;
     168: iconst_0
     169: getstatic     #28                 // Field org/apache/hadoop/yarn/api/records/ResourceInformation.MEMORY_MB:Lorg/apache/hadoop/yarn/api/records/ResourceInformation;
     172: invokestatic  #53                 // Method org/apache/hadoop/yarn/api/records/ResourceInformation.newInstance:(Lorg/apache/hadoop/yarn/api/records/ResourceInformation;)Lorg/apache/hadoop/yarn/api/records/ResourceInformation;
     175: aastore
     176: aload_0
     177: getfield      #23                 // Field resources:[Lorg/apache/hadoop/yarn/api/records/ResourceInformation;
     180: iconst_1
     181: getstatic     #54                 // Field org/apache/hadoop/yarn/api/records/ResourceInformation.VCORES:Lorg/apache/hadoop/yarn/api/records/ResourceInformation;
     184: invokestatic  #53                 // Method org/apache/hadoop/yarn/api/records/ResourceInformation.newInstance:(Lorg/apache/hadoop/yarn/api/records/ResourceInformation;)Lorg/apache/hadoop/yarn/api/records/ResourceInformation;
     187: aastore
     188: aload_0
     189: aload_1
     190: invokeinterface #55,  1           // InterfaceMethod org/apache/hadoop/yarn/proto/YarnProtos$ResourceProtoOrBuilder.getMemory:()J
     195: invokevirtual #4                  // Method setMemorySize:(J)V
     198: aload_0
     199: aload_1
     200: invokeinterface #56,  1           // InterfaceMethod org/apache/hadoop/yarn/proto/YarnProtos$ResourceProtoOrBuilder.getVirtualCores:()I
     205: invokevirtual #6                  // Method setVirtualCores:(I)V
     208: aload_0
     209: aload_2
     210: invokespecial #57                 // Method updateResourceInformationMap:([Lorg/apache/hadoop/yarn/api/records/ResourceInformation;)V
     213: return

  private void updateResourceInformationMap(org.apache.hadoop.yarn.api.records.ResourceInformation[]);
    Code:
       0: iconst_0
       1: istore_2
       2: iload_2
       3: aload_1
       4: arraylength
       5: if_icmpge     35
       8: aload_0
       9: getfield      #23                 // Field resources:[Lorg/apache/hadoop/yarn/api/records/ResourceInformation;
      12: iload_2
      13: aaload
      14: ifnonnull     29
      17: aload_0
      18: getfield      #23                 // Field resources:[Lorg/apache/hadoop/yarn/api/records/ResourceInformation;
      21: iload_2
      22: aload_1
      23: iload_2
      24: aaload
      25: invokestatic  #53                 // Method org/apache/hadoop/yarn/api/records/ResourceInformation.newInstance:(Lorg/apache/hadoop/yarn/api/records/ResourceInformation;)Lorg/apache/hadoop/yarn/api/records/ResourceInformation;
      28: aastore
      29: iinc          2, 1
      32: goto          2
      35: return

  private static org.apache.hadoop.yarn.api.records.ResourceInformation newDefaultInformation(org.apache.hadoop.yarn.api.records.ResourceInformation, org.apache.hadoop.yarn.proto.YarnProtos$ResourceInformationProto);
    Code:
       0: new           #34                 // class org/apache/hadoop/yarn/api/records/ResourceInformation
       3: dup
       4: invokespecial #58                 // Method org/apache/hadoop/yarn/api/records/ResourceInformation."<init>":()V
       7: astore_2
       8: aload_2
       9: aload_0
      10: invokevirtual #8                  // Method org/apache/hadoop/yarn/api/records/ResourceInformation.getName:()Ljava/lang/String;
      13: invokevirtual #59                 // Method org/apache/hadoop/yarn/api/records/ResourceInformation.setName:(Ljava/lang/String;)V
      16: aload_2
      17: aload_0
      18: invokevirtual #60                 // Method org/apache/hadoop/yarn/api/records/ResourceInformation.getMinimumAllocation:()J
      21: invokevirtual #61                 // Method org/apache/hadoop/yarn/api/records/ResourceInformation.setMinimumAllocation:(J)V
      24: aload_2
      25: aload_0
      26: invokevirtual #62                 // Method org/apache/hadoop/yarn/api/records/ResourceInformation.getMaximumAllocation:()J
      29: invokevirtual #63                 // Method org/apache/hadoop/yarn/api/records/ResourceInformation.setMaximumAllocation:(J)V
      32: aload_2
      33: aload_1
      34: invokevirtual #64                 // Method org/apache/hadoop/yarn/proto/YarnProtos$ResourceInformationProto.hasType:()Z
      37: ifeq          50
      40: aload_1
      41: invokevirtual #65                 // Method org/apache/hadoop/yarn/proto/YarnProtos$ResourceInformationProto.getType:()Lorg/apache/hadoop/yarn/proto/YarnProtos$ResourceTypesProto;
      44: invokestatic  #66                 // Method org/apache/hadoop/yarn/api/records/impl/pb/ProtoUtils.convertFromProtoFormat:(Lorg/apache/hadoop/yarn/proto/YarnProtos$ResourceTypesProto;)Lorg/apache/hadoop/yarn/api/protocolrecords/ResourceTypes;
      47: goto          53
      50: getstatic     #67                 // Field org/apache/hadoop/yarn/api/protocolrecords/ResourceTypes.COUNTABLE:Lorg/apache/hadoop/yarn/api/protocolrecords/ResourceTypes;
      53: invokevirtual #68                 // Method org/apache/hadoop/yarn/api/records/ResourceInformation.setResourceType:(Lorg/apache/hadoop/yarn/api/protocolrecords/ResourceTypes;)V
      56: aload_1
      57: invokevirtual #69                 // Method org/apache/hadoop/yarn/proto/YarnProtos$ResourceInformationProto.hasUnits:()Z
      60: ifeq          70
      63: aload_1
      64: invokevirtual #70                 // Method org/apache/hadoop/yarn/proto/YarnProtos$ResourceInformationProto.getUnits:()Ljava/lang/String;
      67: goto          77
      70: aload_1
      71: invokevirtual #40                 // Method org/apache/hadoop/yarn/proto/YarnProtos$ResourceInformationProto.getKey:()Ljava/lang/String;
      74: invokestatic  #71                 // Method org/apache/hadoop/yarn/util/resource/ResourceUtils.getDefaultUnit:(Ljava/lang/String;)Ljava/lang/String;
      77: astore_3
      78: aload_1
      79: invokevirtual #72                 // Method org/apache/hadoop/yarn/proto/YarnProtos$ResourceInformationProto.hasValue:()Z
      82: ifeq          92
      85: aload_1
      86: invokevirtual #73                 // Method org/apache/hadoop/yarn/proto/YarnProtos$ResourceInformationProto.getValue:()J
      89: goto          93
      92: lconst_0
      93: lstore        4
      95: aload_1
      96: invokevirtual #40                 // Method org/apache/hadoop/yarn/proto/YarnProtos$ResourceInformationProto.getKey:()Ljava/lang/String;
      99: invokestatic  #71                 // Method org/apache/hadoop/yarn/util/resource/ResourceUtils.getDefaultUnit:(Ljava/lang/String;)Ljava/lang/String;
     102: astore        6
     104: aload_3
     105: aload         6
     107: invokevirtual #74                 // Method java/lang/String.equals:(Ljava/lang/Object;)Z
     110: ifne          134
     113: aload_2
     114: aload_3
     115: aload         6
     117: lload         4
     119: invokestatic  #29                 // Method org/apache/hadoop/yarn/util/UnitsConversionUtil.convert:(Ljava/lang/String;Ljava/lang/String;J)J
     122: invokevirtual #31                 // Method org/apache/hadoop/yarn/api/records/ResourceInformation.setValue:(J)V
     125: aload_2
     126: aload         6
     128: invokevirtual #75                 // Method org/apache/hadoop/yarn/api/records/ResourceInformation.setUnits:(Ljava/lang/String;)V
     131: goto          145
     134: aload_2
     135: aload_3
     136: invokevirtual #75                 // Method org/apache/hadoop/yarn/api/records/ResourceInformation.setUnits:(Ljava/lang/String;)V
     139: aload_2
     140: lload         4
     142: invokevirtual #31                 // Method org/apache/hadoop/yarn/api/records/ResourceInformation.setValue:(J)V
     145: aload_2
     146: areturn

  public void setResourceInformation(java.lang.String, org.apache.hadoop.yarn.api.records.ResourceInformation);
    Code:
       0: aload_0
       1: invokespecial #30                 // Method maybeInitBuilder:()V
       4: aload_1
       5: ifnull        12
       8: aload_2
       9: ifnonnull     22
      12: new           #76                 // class java/lang/IllegalArgumentException
      15: dup
      16: ldc           #77                 // String resource and/or resourceInformation cannot be null
      18: invokespecial #78                 // Method java/lang/IllegalArgumentException."<init>":(Ljava/lang/String;)V
      21: athrow
      22: aload_0
      23: aload_1
      24: invokespecial #79                 // Method org/apache/hadoop/yarn/api/records/Resource.getResourceInformation:(Ljava/lang/String;)Lorg/apache/hadoop/yarn/api/records/ResourceInformation;
      27: astore_3
      28: aload_2
      29: aload_3
      30: invokestatic  #80                 // Method org/apache/hadoop/yarn/api/records/ResourceInformation.copy:(Lorg/apache/hadoop/yarn/api/records/ResourceInformation;Lorg/apache/hadoop/yarn/api/records/ResourceInformation;)V
      33: return

  public void setResourceValue(java.lang.String, long);
    Code:
       0: aload_0
       1: invokespecial #30                 // Method maybeInitBuilder:()V
       4: aload_1
       5: ifnonnull     18
       8: new           #76                 // class java/lang/IllegalArgumentException
      11: dup
      12: ldc           #81                 // String resource type object cannot be null
      14: invokespecial #78                 // Method java/lang/IllegalArgumentException."<init>":(Ljava/lang/String;)V
      17: athrow
      18: aload_0
      19: aload_1
      20: invokevirtual #82                 // Method getResourceInformation:(Ljava/lang/String;)Lorg/apache/hadoop/yarn/api/records/ResourceInformation;
      23: lload_2
      24: invokevirtual #31                 // Method org/apache/hadoop/yarn/api/records/ResourceInformation.setValue:(J)V
      27: return

  public org.apache.hadoop.yarn.api.records.ResourceInformation getResourceInformation(java.lang.String);
    Code:
       0: aload_0
       1: invokespecial #17                 // Method initResources:()V
       4: aload_0
       5: aload_1
       6: invokespecial #79                 // Method org/apache/hadoop/yarn/api/records/Resource.getResourceInformation:(Ljava/lang/String;)Lorg/apache/hadoop/yarn/api/records/ResourceInformation;
       9: areturn

  public long getResourceValue(java.lang.String);
    Code:
       0: aload_0
       1: aload_1
       2: invokespecial #83                 // Method org/apache/hadoop/yarn/api/records/Resource.getResourceValue:(Ljava/lang/String;)J
       5: lreturn

  private synchronized void mergeLocalToBuilder();
    Code:
       0: aload_0
       1: getfield      #14                 // Field builder:Lorg/apache/hadoop/yarn/proto/YarnProtos$ResourceProto$Builder;
       4: invokevirtual #84                 // Method org/apache/hadoop/yarn/proto/YarnProtos$ResourceProto$Builder.clearResourceValueMap:()Lorg/apache/hadoop/yarn/proto/YarnProtos$ResourceProto$Builder;
       7: pop
       8: aload_0
       9: getfield      #23                 // Field resources:[Lorg/apache/hadoop/yarn/api/records/ResourceInformation;
      12: ifnull        111
      15: aload_0
      16: getfield      #23                 // Field resources:[Lorg/apache/hadoop/yarn/api/records/ResourceInformation;
      19: arraylength
      20: ifeq          111
      23: aload_0
      24: getfield      #23                 // Field resources:[Lorg/apache/hadoop/yarn/api/records/ResourceInformation;
      27: astore_1
      28: aload_1
      29: arraylength
      30: istore_2
      31: iconst_0
      32: istore_3
      33: iload_3
      34: iload_2
      35: if_icmpge     111
      38: aload_1
      39: iload_3
      40: aaload
      41: astore        4
      43: invokestatic  #85                 // Method org/apache/hadoop/yarn/proto/YarnProtos$ResourceInformationProto.newBuilder:()Lorg/apache/hadoop/yarn/proto/YarnProtos$ResourceInformationProto$Builder;
      46: astore        5
      48: aload         5
      50: aload         4
      52: invokevirtual #8                  // Method org/apache/hadoop/yarn/api/records/ResourceInformation.getName:()Ljava/lang/String;
      55: invokevirtual #86                 // Method org/apache/hadoop/yarn/proto/YarnProtos$ResourceInformationProto$Builder.setKey:(Ljava/lang/String;)Lorg/apache/hadoop/yarn/proto/YarnProtos$ResourceInformationProto$Builder;
      58: pop
      59: aload         5
      61: aload         4
      63: invokevirtual #25                 // Method org/apache/hadoop/yarn/api/records/ResourceInformation.getUnits:()Ljava/lang/String;
      66: invokevirtual #87                 // Method org/apache/hadoop/yarn/proto/YarnProtos$ResourceInformationProto$Builder.setUnits:(Ljava/lang/String;)Lorg/apache/hadoop/yarn/proto/YarnProtos$ResourceInformationProto$Builder;
      69: pop
      70: aload         5
      72: aload         4
      74: invokevirtual #88                 // Method org/apache/hadoop/yarn/api/records/ResourceInformation.getResourceType:()Lorg/apache/hadoop/yarn/api/protocolrecords/ResourceTypes;
      77: invokestatic  #89                 // Method org/apache/hadoop/yarn/api/records/impl/pb/ProtoUtils.converToProtoFormat:(Lorg/apache/hadoop/yarn/api/protocolrecords/ResourceTypes;)Lorg/apache/hadoop/yarn/proto/YarnProtos$ResourceTypesProto;
      80: invokevirtual #90                 // Method org/apache/hadoop/yarn/proto/YarnProtos$ResourceInformationProto$Builder.setType:(Lorg/apache/hadoop/yarn/proto/YarnProtos$ResourceTypesProto;)Lorg/apache/hadoop/yarn/proto/YarnProtos$ResourceInformationProto$Builder;
      83: pop
      84: aload         5
      86: aload         4
      88: invokevirtual #27                 // Method org/apache/hadoop/yarn/api/records/ResourceInformation.getValue:()J
      91: invokevirtual #91                 // Method org/apache/hadoop/yarn/proto/YarnProtos$ResourceInformationProto$Builder.setValue:(J)Lorg/apache/hadoop/yarn/proto/YarnProtos$ResourceInformationProto$Builder;
      94: pop
      95: aload_0
      96: getfield      #14                 // Field builder:Lorg/apache/hadoop/yarn/proto/YarnProtos$ResourceProto$Builder;
      99: aload         5
     101: invokevirtual #92                 // Method org/apache/hadoop/yarn/proto/YarnProtos$ResourceProto$Builder.addResourceValueMap:(Lorg/apache/hadoop/yarn/proto/YarnProtos$ResourceInformationProto$Builder;)Lorg/apache/hadoop/yarn/proto/YarnProtos$ResourceProto$Builder;
     104: pop
     105: iinc          3, 1
     108: goto          33
     111: aload_0
     112: getfield      #14                 // Field builder:Lorg/apache/hadoop/yarn/proto/YarnProtos$ResourceProto$Builder;
     115: aload_0
     116: invokevirtual #21                 // Method getMemorySize:()J
     119: invokevirtual #93                 // Method org/apache/hadoop/yarn/proto/YarnProtos$ResourceProto$Builder.setMemory:(J)Lorg/apache/hadoop/yarn/proto/YarnProtos$ResourceProto$Builder;
     122: pop
     123: aload_0
     124: getfield      #14                 // Field builder:Lorg/apache/hadoop/yarn/proto/YarnProtos$ResourceProto$Builder;
     127: aload_0
     128: invokevirtual #94                 // Method getVirtualCores:()I
     131: invokevirtual #95                 // Method org/apache/hadoop/yarn/proto/YarnProtos$ResourceProto$Builder.setVirtualCores:(I)Lorg/apache/hadoop/yarn/proto/YarnProtos$ResourceProto$Builder;
     134: pop
     135: return

  private void mergeLocalToProto();
    Code:
       0: aload_0
       1: getfield      #15                 // Field viaProto:Z
       4: ifeq          11
       7: aload_0
       8: invokespecial #30                 // Method maybeInitBuilder:()V
      11: aload_0
      12: invokespecial #96                 // Method mergeLocalToBuilder:()V
      15: aload_0
      16: aload_0
      17: getfield      #14                 // Field builder:Lorg/apache/hadoop/yarn/proto/YarnProtos$ResourceProto$Builder;
      20: invokevirtual #19                 // Method org/apache/hadoop/yarn/proto/YarnProtos$ResourceProto$Builder.build:()Lorg/apache/hadoop/yarn/proto/YarnProtos$ResourceProto;
      23: putfield      #13                 // Field proto:Lorg/apache/hadoop/yarn/proto/YarnProtos$ResourceProto;
      26: aload_0
      27: iconst_1
      28: putfield      #15                 // Field viaProto:Z
      31: return

  static {};
    Code:
       0: ldc           #1                  // class org/apache/hadoop/yarn/api/records/impl/pb/ResourcePBImpl
       2: invokestatic  #97                 // Method org/apache/commons/logging/LogFactory.getLog:(Ljava/lang/Class;)Lorg/apache/commons/logging/Log;
       5: putstatic     #43                 // Field LOG:Lorg/apache/commons/logging/Log;
       8: return
}
