Compiled from "ResourceAllocationRequestPBImpl.java"
public class org.apache.hadoop.yarn.api.records.impl.pb.ResourceAllocationRequestPBImpl extends org.apache.hadoop.yarn.api.records.ResourceAllocationRequest {
  private org.apache.hadoop.yarn.proto.YarnProtos$ResourceAllocationRequestProto proto;

  private org.apache.hadoop.yarn.proto.YarnProtos$ResourceAllocationRequestProto$Builder builder;

  private boolean viaProto;

  private org.apache.hadoop.yarn.api.records.Resource capability;

  public org.apache.hadoop.yarn.api.records.impl.pb.ResourceAllocationRequestPBImpl();
    Code:
       0: aload_0
       1: invokespecial #1                  // Method org/apache/hadoop/yarn/api/records/ResourceAllocationRequest."<init>":()V
       4: aload_0
       5: invokestatic  #2                  // Method org/apache/hadoop/yarn/proto/YarnProtos$ResourceAllocationRequestProto.getDefaultInstance:()Lorg/apache/hadoop/yarn/proto/YarnProtos$ResourceAllocationRequestProto;
       8: putfield      #3                  // Field proto:Lorg/apache/hadoop/yarn/proto/YarnProtos$ResourceAllocationRequestProto;
      11: aload_0
      12: aconst_null
      13: putfield      #4                  // Field builder:Lorg/apache/hadoop/yarn/proto/YarnProtos$ResourceAllocationRequestProto$Builder;
      16: aload_0
      17: iconst_0
      18: putfield      #5                  // Field viaProto:Z
      21: aload_0
      22: aconst_null
      23: putfield      #6                  // Field capability:Lorg/apache/hadoop/yarn/api/records/Resource;
      26: aload_0
      27: invokestatic  #7                  // Method org/apache/hadoop/yarn/proto/YarnProtos$ResourceAllocationRequestProto.newBuilder:()Lorg/apache/hadoop/yarn/proto/YarnProtos$ResourceAllocationRequestProto$Builder;
      30: putfield      #4                  // Field builder:Lorg/apache/hadoop/yarn/proto/YarnProtos$ResourceAllocationRequestProto$Builder;
      33: return

  public org.apache.hadoop.yarn.api.records.impl.pb.ResourceAllocationRequestPBImpl(org.apache.hadoop.yarn.proto.YarnProtos$ResourceAllocationRequestProto);
    Code:
       0: aload_0
       1: invokespecial #1                  // Method org/apache/hadoop/yarn/api/records/ResourceAllocationRequest."<init>":()V
       4: aload_0
       5: invokestatic  #2                  // Method org/apache/hadoop/yarn/proto/YarnProtos$ResourceAllocationRequestProto.getDefaultInstance:()Lorg/apache/hadoop/yarn/proto/YarnProtos$ResourceAllocationRequestProto;
       8: putfield      #3                  // Field proto:Lorg/apache/hadoop/yarn/proto/YarnProtos$ResourceAllocationRequestProto;
      11: aload_0
      12: aconst_null
      13: putfield      #4                  // Field builder:Lorg/apache/hadoop/yarn/proto/YarnProtos$ResourceAllocationRequestProto$Builder;
      16: aload_0
      17: iconst_0
      18: putfield      #5                  // Field viaProto:Z
      21: aload_0
      22: aconst_null
      23: putfield      #6                  // Field capability:Lorg/apache/hadoop/yarn/api/records/Resource;
      26: aload_0
      27: aload_1
      28: putfield      #3                  // Field proto:Lorg/apache/hadoop/yarn/proto/YarnProtos$ResourceAllocationRequestProto;
      31: aload_0
      32: iconst_1
      33: putfield      #5                  // Field viaProto:Z
      36: return

  public org.apache.hadoop.yarn.proto.YarnProtos$ResourceAllocationRequestProto getProto();
    Code:
       0: aload_0
       1: invokespecial #8                  // Method mergeLocalToProto:()V
       4: aload_0
       5: aload_0
       6: getfield      #5                  // Field viaProto:Z
       9: ifeq          19
      12: aload_0
      13: getfield      #3                  // Field proto:Lorg/apache/hadoop/yarn/proto/YarnProtos$ResourceAllocationRequestProto;
      16: goto          26
      19: aload_0
      20: getfield      #4                  // Field builder:Lorg/apache/hadoop/yarn/proto/YarnProtos$ResourceAllocationRequestProto$Builder;
      23: invokevirtual #9                  // Method org/apache/hadoop/yarn/proto/YarnProtos$ResourceAllocationRequestProto$Builder.build:()Lorg/apache/hadoop/yarn/proto/YarnProtos$ResourceAllocationRequestProto;
      26: putfield      #3                  // Field proto:Lorg/apache/hadoop/yarn/proto/YarnProtos$ResourceAllocationRequestProto;
      29: aload_0
      30: iconst_1
      31: putfield      #5                  // Field viaProto:Z
      34: aload_0
      35: getfield      #3                  // Field proto:Lorg/apache/hadoop/yarn/proto/YarnProtos$ResourceAllocationRequestProto;
      38: areturn

  private void maybeInitBuilder();
    Code:
       0: aload_0
       1: getfield      #5                  // Field viaProto:Z
       4: ifne          14
       7: aload_0
       8: getfield      #4                  // Field builder:Lorg/apache/hadoop/yarn/proto/YarnProtos$ResourceAllocationRequestProto$Builder;
      11: ifnonnull     25
      14: aload_0
      15: aload_0
      16: getfield      #3                  // Field proto:Lorg/apache/hadoop/yarn/proto/YarnProtos$ResourceAllocationRequestProto;
      19: invokestatic  #10                 // Method org/apache/hadoop/yarn/proto/YarnProtos$ResourceAllocationRequestProto.newBuilder:(Lorg/apache/hadoop/yarn/proto/YarnProtos$ResourceAllocationRequestProto;)Lorg/apache/hadoop/yarn/proto/YarnProtos$ResourceAllocationRequestProto$Builder;
      22: putfield      #4                  // Field builder:Lorg/apache/hadoop/yarn/proto/YarnProtos$ResourceAllocationRequestProto$Builder;
      25: aload_0
      26: iconst_0
      27: putfield      #5                  // Field viaProto:Z
      30: return

  public org.apache.hadoop.yarn.api.records.Resource getCapability();
    Code:
       0: aload_0
       1: getfield      #5                  // Field viaProto:Z
       4: ifeq          14
       7: aload_0
       8: getfield      #3                  // Field proto:Lorg/apache/hadoop/yarn/proto/YarnProtos$ResourceAllocationRequestProto;
      11: goto          18
      14: aload_0
      15: getfield      #4                  // Field builder:Lorg/apache/hadoop/yarn/proto/YarnProtos$ResourceAllocationRequestProto$Builder;
      18: astore_1
      19: aload_0
      20: getfield      #6                  // Field capability:Lorg/apache/hadoop/yarn/api/records/Resource;
      23: ifnull        31
      26: aload_0
      27: getfield      #6                  // Field capability:Lorg/apache/hadoop/yarn/api/records/Resource;
      30: areturn
      31: aload_1
      32: invokeinterface #11,  1           // InterfaceMethod org/apache/hadoop/yarn/proto/YarnProtos$ResourceAllocationRequestProtoOrBuilder.hasResource:()Z
      37: ifne          42
      40: aconst_null
      41: areturn
      42: aload_0
      43: aload_0
      44: aload_1
      45: invokeinterface #12,  1           // InterfaceMethod org/apache/hadoop/yarn/proto/YarnProtos$ResourceAllocationRequestProtoOrBuilder.getResource:()Lorg/apache/hadoop/yarn/proto/YarnProtos$ResourceProto;
      50: invokespecial #13                 // Method convertFromProtoFormat:(Lorg/apache/hadoop/yarn/proto/YarnProtos$ResourceProto;)Lorg/apache/hadoop/yarn/api/records/impl/pb/ResourcePBImpl;
      53: putfield      #6                  // Field capability:Lorg/apache/hadoop/yarn/api/records/Resource;
      56: aload_0
      57: getfield      #6                  // Field capability:Lorg/apache/hadoop/yarn/api/records/Resource;
      60: areturn

  public void setCapability(org.apache.hadoop.yarn.api.records.Resource);
    Code:
       0: aload_0
       1: invokespecial #14                 // Method maybeInitBuilder:()V
       4: aload_1
       5: ifnonnull     17
       8: aload_0
       9: getfield      #4                  // Field builder:Lorg/apache/hadoop/yarn/proto/YarnProtos$ResourceAllocationRequestProto$Builder;
      12: invokevirtual #15                 // Method org/apache/hadoop/yarn/proto/YarnProtos$ResourceAllocationRequestProto$Builder.clearResource:()Lorg/apache/hadoop/yarn/proto/YarnProtos$ResourceAllocationRequestProto$Builder;
      15: pop
      16: return
      17: aload_0
      18: aload_1
      19: putfield      #6                  // Field capability:Lorg/apache/hadoop/yarn/api/records/Resource;
      22: return

  public long getStartTime();
    Code:
       0: aload_0
       1: getfield      #5                  // Field viaProto:Z
       4: ifeq          14
       7: aload_0
       8: getfield      #3                  // Field proto:Lorg/apache/hadoop/yarn/proto/YarnProtos$ResourceAllocationRequestProto;
      11: goto          18
      14: aload_0
      15: getfield      #4                  // Field builder:Lorg/apache/hadoop/yarn/proto/YarnProtos$ResourceAllocationRequestProto$Builder;
      18: astore_1
      19: aload_1
      20: invokeinterface #16,  1           // InterfaceMethod org/apache/hadoop/yarn/proto/YarnProtos$ResourceAllocationRequestProtoOrBuilder.hasStartTime:()Z
      25: ifne          30
      28: lconst_0
      29: lreturn
      30: aload_1
      31: invokeinterface #17,  1           // InterfaceMethod org/apache/hadoop/yarn/proto/YarnProtos$ResourceAllocationRequestProtoOrBuilder.getStartTime:()J
      36: lreturn

  public void setStartTime(long);
    Code:
       0: aload_0
       1: invokespecial #14                 // Method maybeInitBuilder:()V
       4: lload_1
       5: lconst_0
       6: lcmp
       7: ifgt          19
      10: aload_0
      11: getfield      #4                  // Field builder:Lorg/apache/hadoop/yarn/proto/YarnProtos$ResourceAllocationRequestProto$Builder;
      14: invokevirtual #18                 // Method org/apache/hadoop/yarn/proto/YarnProtos$ResourceAllocationRequestProto$Builder.clearStartTime:()Lorg/apache/hadoop/yarn/proto/YarnProtos$ResourceAllocationRequestProto$Builder;
      17: pop
      18: return
      19: aload_0
      20: getfield      #4                  // Field builder:Lorg/apache/hadoop/yarn/proto/YarnProtos$ResourceAllocationRequestProto$Builder;
      23: lload_1
      24: invokevirtual #19                 // Method org/apache/hadoop/yarn/proto/YarnProtos$ResourceAllocationRequestProto$Builder.setStartTime:(J)Lorg/apache/hadoop/yarn/proto/YarnProtos$ResourceAllocationRequestProto$Builder;
      27: pop
      28: return

  public long getEndTime();
    Code:
       0: aload_0
       1: getfield      #5                  // Field viaProto:Z
       4: ifeq          14
       7: aload_0
       8: getfield      #3                  // Field proto:Lorg/apache/hadoop/yarn/proto/YarnProtos$ResourceAllocationRequestProto;
      11: goto          18
      14: aload_0
      15: getfield      #4                  // Field builder:Lorg/apache/hadoop/yarn/proto/YarnProtos$ResourceAllocationRequestProto$Builder;
      18: astore_1
      19: aload_1
      20: invokeinterface #20,  1           // InterfaceMethod org/apache/hadoop/yarn/proto/YarnProtos$ResourceAllocationRequestProtoOrBuilder.hasEndTime:()Z
      25: ifne          30
      28: lconst_0
      29: lreturn
      30: aload_1
      31: invokeinterface #21,  1           // InterfaceMethod org/apache/hadoop/yarn/proto/YarnProtos$ResourceAllocationRequestProtoOrBuilder.getEndTime:()J
      36: lreturn

  public void setEndTime(long);
    Code:
       0: aload_0
       1: invokespecial #14                 // Method maybeInitBuilder:()V
       4: lload_1
       5: lconst_0
       6: lcmp
       7: ifgt          19
      10: aload_0
      11: getfield      #4                  // Field builder:Lorg/apache/hadoop/yarn/proto/YarnProtos$ResourceAllocationRequestProto$Builder;
      14: invokevirtual #22                 // Method org/apache/hadoop/yarn/proto/YarnProtos$ResourceAllocationRequestProto$Builder.clearEndTime:()Lorg/apache/hadoop/yarn/proto/YarnProtos$ResourceAllocationRequestProto$Builder;
      17: pop
      18: return
      19: aload_0
      20: getfield      #4                  // Field builder:Lorg/apache/hadoop/yarn/proto/YarnProtos$ResourceAllocationRequestProto$Builder;
      23: lload_1
      24: invokevirtual #23                 // Method org/apache/hadoop/yarn/proto/YarnProtos$ResourceAllocationRequestProto$Builder.setEndTime:(J)Lorg/apache/hadoop/yarn/proto/YarnProtos$ResourceAllocationRequestProto$Builder;
      27: pop
      28: return

  private org.apache.hadoop.yarn.api.records.impl.pb.ResourcePBImpl convertFromProtoFormat(org.apache.hadoop.yarn.proto.YarnProtos$ResourceProto);
    Code:
       0: new           #24                 // class org/apache/hadoop/yarn/api/records/impl/pb/ResourcePBImpl
       3: dup
       4: aload_1
       5: invokespecial #25                 // Method org/apache/hadoop/yarn/api/records/impl/pb/ResourcePBImpl."<init>":(Lorg/apache/hadoop/yarn/proto/YarnProtos$ResourceProto;)V
       8: areturn

  private org.apache.hadoop.yarn.proto.YarnProtos$ResourceProto convertToProtoFormat(org.apache.hadoop.yarn.api.records.Resource);
    Code:
       0: aload_1
       1: invokestatic  #26                 // Method org/apache/hadoop/yarn/api/records/impl/pb/ProtoUtils.convertToProtoFormat:(Lorg/apache/hadoop/yarn/api/records/Resource;)Lorg/apache/hadoop/yarn/proto/YarnProtos$ResourceProto;
       4: areturn

  private void mergeLocalToBuilder();
    Code:
       0: aload_0
       1: getfield      #6                  // Field capability:Lorg/apache/hadoop/yarn/api/records/Resource;
       4: ifnull        23
       7: aload_0
       8: getfield      #4                  // Field builder:Lorg/apache/hadoop/yarn/proto/YarnProtos$ResourceAllocationRequestProto$Builder;
      11: aload_0
      12: aload_0
      13: getfield      #6                  // Field capability:Lorg/apache/hadoop/yarn/api/records/Resource;
      16: invokespecial #27                 // Method convertToProtoFormat:(Lorg/apache/hadoop/yarn/api/records/Resource;)Lorg/apache/hadoop/yarn/proto/YarnProtos$ResourceProto;
      19: invokevirtual #28                 // Method org/apache/hadoop/yarn/proto/YarnProtos$ResourceAllocationRequestProto$Builder.setResource:(Lorg/apache/hadoop/yarn/proto/YarnProtos$ResourceProto;)Lorg/apache/hadoop/yarn/proto/YarnProtos$ResourceAllocationRequestProto$Builder;
      22: pop
      23: return

  private void mergeLocalToProto();
    Code:
       0: aload_0
       1: getfield      #5                  // Field viaProto:Z
       4: ifeq          11
       7: aload_0
       8: invokespecial #14                 // Method maybeInitBuilder:()V
      11: aload_0
      12: invokespecial #29                 // Method mergeLocalToBuilder:()V
      15: aload_0
      16: aload_0
      17: getfield      #4                  // Field builder:Lorg/apache/hadoop/yarn/proto/YarnProtos$ResourceAllocationRequestProto$Builder;
      20: invokevirtual #9                  // Method org/apache/hadoop/yarn/proto/YarnProtos$ResourceAllocationRequestProto$Builder.build:()Lorg/apache/hadoop/yarn/proto/YarnProtos$ResourceAllocationRequestProto;
      23: putfield      #3                  // Field proto:Lorg/apache/hadoop/yarn/proto/YarnProtos$ResourceAllocationRequestProto;
      26: aload_0
      27: iconst_1
      28: putfield      #5                  // Field viaProto:Z
      31: return

  public java.lang.String toString();
    Code:
       0: new           #30                 // class java/lang/StringBuilder
       3: dup
       4: invokespecial #31                 // Method java/lang/StringBuilder."<init>":()V
       7: ldc           #32                 // String {Resource:
       9: invokevirtual #33                 // Method java/lang/StringBuilder.append:(Ljava/lang/String;)Ljava/lang/StringBuilder;
      12: aload_0
      13: invokevirtual #34                 // Method getCapability:()Lorg/apache/hadoop/yarn/api/records/Resource;
      16: invokevirtual #35                 // Method java/lang/StringBuilder.append:(Ljava/lang/Object;)Ljava/lang/StringBuilder;
      19: ldc           #36                 // String , # Start Time:
      21: invokevirtual #33                 // Method java/lang/StringBuilder.append:(Ljava/lang/String;)Ljava/lang/StringBuilder;
      24: aload_0
      25: invokevirtual #37                 // Method getStartTime:()J
      28: invokevirtual #38                 // Method java/lang/StringBuilder.append:(J)Ljava/lang/StringBuilder;
      31: ldc           #39                 // String , End Time:
      33: invokevirtual #33                 // Method java/lang/StringBuilder.append:(Ljava/lang/String;)Ljava/lang/StringBuilder;
      36: aload_0
      37: invokevirtual #40                 // Method getEndTime:()J
      40: invokevirtual #38                 // Method java/lang/StringBuilder.append:(J)Ljava/lang/StringBuilder;
      43: ldc           #41                 // String }
      45: invokevirtual #33                 // Method java/lang/StringBuilder.append:(Ljava/lang/String;)Ljava/lang/StringBuilder;
      48: invokevirtual #42                 // Method java/lang/StringBuilder.toString:()Ljava/lang/String;
      51: areturn

  public boolean equals(java.lang.Object);
    Code:
       0: aload_1
       1: ifnonnull     6
       4: iconst_0
       5: ireturn
       6: aload_1
       7: invokevirtual #43                 // Method java/lang/Object.getClass:()Ljava/lang/Class;
      10: aload_0
      11: invokevirtual #43                 // Method java/lang/Object.getClass:()Ljava/lang/Class;
      14: invokevirtual #44                 // Method java/lang/Class.isAssignableFrom:(Ljava/lang/Class;)Z
      17: ifeq          42
      20: aload_0
      21: invokevirtual #45                 // Method getProto:()Lorg/apache/hadoop/yarn/proto/YarnProtos$ResourceAllocationRequestProto;
      24: aload_0
      25: invokevirtual #43                 // Method java/lang/Object.getClass:()Ljava/lang/Class;
      28: aload_1
      29: invokevirtual #46                 // Method java/lang/Class.cast:(Ljava/lang/Object;)Ljava/lang/Object;
      32: checkcast     #47                 // class org/apache/hadoop/yarn/api/records/impl/pb/ResourceAllocationRequestPBImpl
      35: invokevirtual #45                 // Method getProto:()Lorg/apache/hadoop/yarn/proto/YarnProtos$ResourceAllocationRequestProto;
      38: invokevirtual #48                 // Method org/apache/hadoop/yarn/proto/YarnProtos$ResourceAllocationRequestProto.equals:(Ljava/lang/Object;)Z
      41: ireturn
      42: iconst_0
      43: ireturn

  public int hashCode();
    Code:
       0: aload_0
       1: invokevirtual #45                 // Method getProto:()Lorg/apache/hadoop/yarn/proto/YarnProtos$ResourceAllocationRequestProto;
       4: invokevirtual #49                 // Method org/apache/hadoop/yarn/proto/YarnProtos$ResourceAllocationRequestProto.hashCode:()I
       7: ireturn
}
