Compiled from "TokenPBImpl.java"
public class org.apache.hadoop.yarn.api.records.impl.pb.TokenPBImpl extends org.apache.hadoop.yarn.api.records.Token {
  private org.apache.hadoop.security.proto.SecurityProtos$TokenProto proto;

  private org.apache.hadoop.security.proto.SecurityProtos$TokenProto$Builder builder;

  private boolean viaProto;

  private java.nio.ByteBuffer identifier;

  private java.nio.ByteBuffer password;

  public org.apache.hadoop.yarn.api.records.impl.pb.TokenPBImpl();
    Code:
       0: aload_0
       1: invokespecial #1                  // Method org/apache/hadoop/yarn/api/records/Token."<init>":()V
       4: aload_0
       5: invokestatic  #2                  // Method org/apache/hadoop/security/proto/SecurityProtos$TokenProto.getDefaultInstance:()Lorg/apache/hadoop/security/proto/SecurityProtos$TokenProto;
       8: putfield      #3                  // Field proto:Lorg/apache/hadoop/security/proto/SecurityProtos$TokenProto;
      11: aload_0
      12: aconst_null
      13: putfield      #4                  // Field builder:Lorg/apache/hadoop/security/proto/SecurityProtos$TokenProto$Builder;
      16: aload_0
      17: iconst_0
      18: putfield      #5                  // Field viaProto:Z
      21: aload_0
      22: invokestatic  #6                  // Method org/apache/hadoop/security/proto/SecurityProtos$TokenProto.newBuilder:()Lorg/apache/hadoop/security/proto/SecurityProtos$TokenProto$Builder;
      25: putfield      #4                  // Field builder:Lorg/apache/hadoop/security/proto/SecurityProtos$TokenProto$Builder;
      28: return

  public org.apache.hadoop.yarn.api.records.impl.pb.TokenPBImpl(org.apache.hadoop.security.proto.SecurityProtos$TokenProto);
    Code:
       0: aload_0
       1: invokespecial #1                  // Method org/apache/hadoop/yarn/api/records/Token."<init>":()V
       4: aload_0
       5: invokestatic  #2                  // Method org/apache/hadoop/security/proto/SecurityProtos$TokenProto.getDefaultInstance:()Lorg/apache/hadoop/security/proto/SecurityProtos$TokenProto;
       8: putfield      #3                  // Field proto:Lorg/apache/hadoop/security/proto/SecurityProtos$TokenProto;
      11: aload_0
      12: aconst_null
      13: putfield      #4                  // Field builder:Lorg/apache/hadoop/security/proto/SecurityProtos$TokenProto$Builder;
      16: aload_0
      17: iconst_0
      18: putfield      #5                  // Field viaProto:Z
      21: aload_0
      22: aload_1
      23: putfield      #3                  // Field proto:Lorg/apache/hadoop/security/proto/SecurityProtos$TokenProto;
      26: aload_0
      27: iconst_1
      28: putfield      #5                  // Field viaProto:Z
      31: return

  public synchronized org.apache.hadoop.security.proto.SecurityProtos$TokenProto getProto();
    Code:
       0: aload_0
       1: invokespecial #7                  // Method mergeLocalToProto:()V
       4: aload_0
       5: aload_0
       6: getfield      #5                  // Field viaProto:Z
       9: ifeq          19
      12: aload_0
      13: getfield      #3                  // Field proto:Lorg/apache/hadoop/security/proto/SecurityProtos$TokenProto;
      16: goto          26
      19: aload_0
      20: getfield      #4                  // Field builder:Lorg/apache/hadoop/security/proto/SecurityProtos$TokenProto$Builder;
      23: invokevirtual #8                  // Method org/apache/hadoop/security/proto/SecurityProtos$TokenProto$Builder.build:()Lorg/apache/hadoop/security/proto/SecurityProtos$TokenProto;
      26: putfield      #3                  // Field proto:Lorg/apache/hadoop/security/proto/SecurityProtos$TokenProto;
      29: aload_0
      30: iconst_1
      31: putfield      #5                  // Field viaProto:Z
      34: aload_0
      35: getfield      #3                  // Field proto:Lorg/apache/hadoop/security/proto/SecurityProtos$TokenProto;
      38: areturn

  public int hashCode();
    Code:
       0: aload_0
       1: invokevirtual #9                  // Method getProto:()Lorg/apache/hadoop/security/proto/SecurityProtos$TokenProto;
       4: invokevirtual #10                 // Method org/apache/hadoop/security/proto/SecurityProtos$TokenProto.hashCode:()I
       7: ireturn

  public boolean equals(java.lang.Object);
    Code:
       0: aload_1
       1: ifnonnull     6
       4: iconst_0
       5: ireturn
       6: aload_1
       7: invokevirtual #11                 // Method java/lang/Object.getClass:()Ljava/lang/Class;
      10: aload_0
      11: invokevirtual #11                 // Method java/lang/Object.getClass:()Ljava/lang/Class;
      14: invokevirtual #12                 // Method java/lang/Class.isAssignableFrom:(Ljava/lang/Class;)Z
      17: ifeq          42
      20: aload_0
      21: invokevirtual #9                  // Method getProto:()Lorg/apache/hadoop/security/proto/SecurityProtos$TokenProto;
      24: aload_0
      25: invokevirtual #11                 // Method java/lang/Object.getClass:()Ljava/lang/Class;
      28: aload_1
      29: invokevirtual #13                 // Method java/lang/Class.cast:(Ljava/lang/Object;)Ljava/lang/Object;
      32: checkcast     #14                 // class org/apache/hadoop/yarn/api/records/impl/pb/TokenPBImpl
      35: invokevirtual #9                  // Method getProto:()Lorg/apache/hadoop/security/proto/SecurityProtos$TokenProto;
      38: invokevirtual #15                 // Method org/apache/hadoop/security/proto/SecurityProtos$TokenProto.equals:(Ljava/lang/Object;)Z
      41: ireturn
      42: iconst_0
      43: ireturn

  protected final java.nio.ByteBuffer convertFromProtoFormat(com.google.protobuf.ByteString);
    Code:
       0: aload_1
       1: invokestatic  #16                 // Method org/apache/hadoop/yarn/api/records/impl/pb/ProtoUtils.convertFromProtoFormat:(Lcom/google/protobuf/ByteString;)Ljava/nio/ByteBuffer;
       4: areturn

  protected final com.google.protobuf.ByteString convertToProtoFormat(java.nio.ByteBuffer);
    Code:
       0: aload_1
       1: invokestatic  #17                 // Method org/apache/hadoop/yarn/api/records/impl/pb/ProtoUtils.convertToProtoFormat:(Ljava/nio/ByteBuffer;)Lcom/google/protobuf/ByteString;
       4: areturn

  private synchronized void mergeLocalToBuilder();
    Code:
       0: aload_0
       1: getfield      #18                 // Field identifier:Ljava/nio/ByteBuffer;
       4: ifnull        23
       7: aload_0
       8: getfield      #4                  // Field builder:Lorg/apache/hadoop/security/proto/SecurityProtos$TokenProto$Builder;
      11: aload_0
      12: aload_0
      13: getfield      #18                 // Field identifier:Ljava/nio/ByteBuffer;
      16: invokevirtual #19                 // Method convertToProtoFormat:(Ljava/nio/ByteBuffer;)Lcom/google/protobuf/ByteString;
      19: invokevirtual #20                 // Method org/apache/hadoop/security/proto/SecurityProtos$TokenProto$Builder.setIdentifier:(Lcom/google/protobuf/ByteString;)Lorg/apache/hadoop/security/proto/SecurityProtos$TokenProto$Builder;
      22: pop
      23: aload_0
      24: getfield      #21                 // Field password:Ljava/nio/ByteBuffer;
      27: ifnull        46
      30: aload_0
      31: getfield      #4                  // Field builder:Lorg/apache/hadoop/security/proto/SecurityProtos$TokenProto$Builder;
      34: aload_0
      35: aload_0
      36: getfield      #21                 // Field password:Ljava/nio/ByteBuffer;
      39: invokevirtual #19                 // Method convertToProtoFormat:(Ljava/nio/ByteBuffer;)Lcom/google/protobuf/ByteString;
      42: invokevirtual #22                 // Method org/apache/hadoop/security/proto/SecurityProtos$TokenProto$Builder.setPassword:(Lcom/google/protobuf/ByteString;)Lorg/apache/hadoop/security/proto/SecurityProtos$TokenProto$Builder;
      45: pop
      46: return

  private synchronized void mergeLocalToProto();
    Code:
       0: aload_0
       1: getfield      #5                  // Field viaProto:Z
       4: ifeq          11
       7: aload_0
       8: invokespecial #23                 // Method maybeInitBuilder:()V
      11: aload_0
      12: invokespecial #24                 // Method mergeLocalToBuilder:()V
      15: aload_0
      16: aload_0
      17: getfield      #4                  // Field builder:Lorg/apache/hadoop/security/proto/SecurityProtos$TokenProto$Builder;
      20: invokevirtual #8                  // Method org/apache/hadoop/security/proto/SecurityProtos$TokenProto$Builder.build:()Lorg/apache/hadoop/security/proto/SecurityProtos$TokenProto;
      23: putfield      #3                  // Field proto:Lorg/apache/hadoop/security/proto/SecurityProtos$TokenProto;
      26: aload_0
      27: iconst_1
      28: putfield      #5                  // Field viaProto:Z
      31: return

  private synchronized void maybeInitBuilder();
    Code:
       0: aload_0
       1: getfield      #5                  // Field viaProto:Z
       4: ifne          14
       7: aload_0
       8: getfield      #4                  // Field builder:Lorg/apache/hadoop/security/proto/SecurityProtos$TokenProto$Builder;
      11: ifnonnull     25
      14: aload_0
      15: aload_0
      16: getfield      #3                  // Field proto:Lorg/apache/hadoop/security/proto/SecurityProtos$TokenProto;
      19: invokestatic  #25                 // Method org/apache/hadoop/security/proto/SecurityProtos$TokenProto.newBuilder:(Lorg/apache/hadoop/security/proto/SecurityProtos$TokenProto;)Lorg/apache/hadoop/security/proto/SecurityProtos$TokenProto$Builder;
      22: putfield      #4                  // Field builder:Lorg/apache/hadoop/security/proto/SecurityProtos$TokenProto$Builder;
      25: aload_0
      26: iconst_0
      27: putfield      #5                  // Field viaProto:Z
      30: return

  public synchronized java.nio.ByteBuffer getIdentifier();
    Code:
       0: aload_0
       1: getfield      #5                  // Field viaProto:Z
       4: ifeq          14
       7: aload_0
       8: getfield      #3                  // Field proto:Lorg/apache/hadoop/security/proto/SecurityProtos$TokenProto;
      11: goto          18
      14: aload_0
      15: getfield      #4                  // Field builder:Lorg/apache/hadoop/security/proto/SecurityProtos$TokenProto$Builder;
      18: astore_1
      19: aload_0
      20: getfield      #18                 // Field identifier:Ljava/nio/ByteBuffer;
      23: ifnull        31
      26: aload_0
      27: getfield      #18                 // Field identifier:Ljava/nio/ByteBuffer;
      30: areturn
      31: aload_1
      32: invokeinterface #26,  1           // InterfaceMethod org/apache/hadoop/security/proto/SecurityProtos$TokenProtoOrBuilder.hasIdentifier:()Z
      37: ifne          42
      40: aconst_null
      41: areturn
      42: aload_0
      43: aload_0
      44: aload_1
      45: invokeinterface #27,  1           // InterfaceMethod org/apache/hadoop/security/proto/SecurityProtos$TokenProtoOrBuilder.getIdentifier:()Lcom/google/protobuf/ByteString;
      50: invokevirtual #28                 // Method convertFromProtoFormat:(Lcom/google/protobuf/ByteString;)Ljava/nio/ByteBuffer;
      53: putfield      #18                 // Field identifier:Ljava/nio/ByteBuffer;
      56: aload_0
      57: getfield      #18                 // Field identifier:Ljava/nio/ByteBuffer;
      60: areturn

  public synchronized void setIdentifier(java.nio.ByteBuffer);
    Code:
       0: aload_0
       1: invokespecial #23                 // Method maybeInitBuilder:()V
       4: aload_1
       5: ifnonnull     16
       8: aload_0
       9: getfield      #4                  // Field builder:Lorg/apache/hadoop/security/proto/SecurityProtos$TokenProto$Builder;
      12: invokevirtual #29                 // Method org/apache/hadoop/security/proto/SecurityProtos$TokenProto$Builder.clearIdentifier:()Lorg/apache/hadoop/security/proto/SecurityProtos$TokenProto$Builder;
      15: pop
      16: aload_0
      17: aload_1
      18: putfield      #18                 // Field identifier:Ljava/nio/ByteBuffer;
      21: return

  public synchronized java.nio.ByteBuffer getPassword();
    Code:
       0: aload_0
       1: getfield      #5                  // Field viaProto:Z
       4: ifeq          14
       7: aload_0
       8: getfield      #3                  // Field proto:Lorg/apache/hadoop/security/proto/SecurityProtos$TokenProto;
      11: goto          18
      14: aload_0
      15: getfield      #4                  // Field builder:Lorg/apache/hadoop/security/proto/SecurityProtos$TokenProto$Builder;
      18: astore_1
      19: aload_0
      20: getfield      #21                 // Field password:Ljava/nio/ByteBuffer;
      23: ifnull        31
      26: aload_0
      27: getfield      #21                 // Field password:Ljava/nio/ByteBuffer;
      30: areturn
      31: aload_1
      32: invokeinterface #30,  1           // InterfaceMethod org/apache/hadoop/security/proto/SecurityProtos$TokenProtoOrBuilder.hasPassword:()Z
      37: ifne          42
      40: aconst_null
      41: areturn
      42: aload_0
      43: aload_0
      44: aload_1
      45: invokeinterface #31,  1           // InterfaceMethod org/apache/hadoop/security/proto/SecurityProtos$TokenProtoOrBuilder.getPassword:()Lcom/google/protobuf/ByteString;
      50: invokevirtual #28                 // Method convertFromProtoFormat:(Lcom/google/protobuf/ByteString;)Ljava/nio/ByteBuffer;
      53: putfield      #21                 // Field password:Ljava/nio/ByteBuffer;
      56: aload_0
      57: getfield      #21                 // Field password:Ljava/nio/ByteBuffer;
      60: areturn

  public synchronized void setPassword(java.nio.ByteBuffer);
    Code:
       0: aload_0
       1: invokespecial #23                 // Method maybeInitBuilder:()V
       4: aload_1
       5: ifnonnull     16
       8: aload_0
       9: getfield      #4                  // Field builder:Lorg/apache/hadoop/security/proto/SecurityProtos$TokenProto$Builder;
      12: invokevirtual #32                 // Method org/apache/hadoop/security/proto/SecurityProtos$TokenProto$Builder.clearPassword:()Lorg/apache/hadoop/security/proto/SecurityProtos$TokenProto$Builder;
      15: pop
      16: aload_0
      17: aload_1
      18: putfield      #21                 // Field password:Ljava/nio/ByteBuffer;
      21: return

  public synchronized java.lang.String getKind();
    Code:
       0: aload_0
       1: getfield      #5                  // Field viaProto:Z
       4: ifeq          14
       7: aload_0
       8: getfield      #3                  // Field proto:Lorg/apache/hadoop/security/proto/SecurityProtos$TokenProto;
      11: goto          18
      14: aload_0
      15: getfield      #4                  // Field builder:Lorg/apache/hadoop/security/proto/SecurityProtos$TokenProto$Builder;
      18: astore_1
      19: aload_1
      20: invokeinterface #33,  1           // InterfaceMethod org/apache/hadoop/security/proto/SecurityProtos$TokenProtoOrBuilder.hasKind:()Z
      25: ifne          30
      28: aconst_null
      29: areturn
      30: aload_1
      31: invokeinterface #34,  1           // InterfaceMethod org/apache/hadoop/security/proto/SecurityProtos$TokenProtoOrBuilder.getKind:()Ljava/lang/String;
      36: areturn

  public synchronized void setKind(java.lang.String);
    Code:
       0: aload_0
       1: invokespecial #23                 // Method maybeInitBuilder:()V
       4: aload_1
       5: ifnonnull     17
       8: aload_0
       9: getfield      #4                  // Field builder:Lorg/apache/hadoop/security/proto/SecurityProtos$TokenProto$Builder;
      12: invokevirtual #35                 // Method org/apache/hadoop/security/proto/SecurityProtos$TokenProto$Builder.clearKind:()Lorg/apache/hadoop/security/proto/SecurityProtos$TokenProto$Builder;
      15: pop
      16: return
      17: aload_0
      18: getfield      #4                  // Field builder:Lorg/apache/hadoop/security/proto/SecurityProtos$TokenProto$Builder;
      21: aload_1
      22: invokevirtual #36                 // Method org/apache/hadoop/security/proto/SecurityProtos$TokenProto$Builder.setKind:(Ljava/lang/String;)Lorg/apache/hadoop/security/proto/SecurityProtos$TokenProto$Builder;
      25: pop
      26: return

  public synchronized java.lang.String getService();
    Code:
       0: aload_0
       1: getfield      #5                  // Field viaProto:Z
       4: ifeq          14
       7: aload_0
       8: getfield      #3                  // Field proto:Lorg/apache/hadoop/security/proto/SecurityProtos$TokenProto;
      11: goto          18
      14: aload_0
      15: getfield      #4                  // Field builder:Lorg/apache/hadoop/security/proto/SecurityProtos$TokenProto$Builder;
      18: astore_1
      19: aload_1
      20: invokeinterface #37,  1           // InterfaceMethod org/apache/hadoop/security/proto/SecurityProtos$TokenProtoOrBuilder.hasService:()Z
      25: ifne          30
      28: aconst_null
      29: areturn
      30: aload_1
      31: invokeinterface #38,  1           // InterfaceMethod org/apache/hadoop/security/proto/SecurityProtos$TokenProtoOrBuilder.getService:()Ljava/lang/String;
      36: areturn

  public synchronized void setService(java.lang.String);
    Code:
       0: aload_0
       1: invokespecial #23                 // Method maybeInitBuilder:()V
       4: aload_1
       5: ifnonnull     17
       8: aload_0
       9: getfield      #4                  // Field builder:Lorg/apache/hadoop/security/proto/SecurityProtos$TokenProto$Builder;
      12: invokevirtual #39                 // Method org/apache/hadoop/security/proto/SecurityProtos$TokenProto$Builder.clearService:()Lorg/apache/hadoop/security/proto/SecurityProtos$TokenProto$Builder;
      15: pop
      16: return
      17: aload_0
      18: getfield      #4                  // Field builder:Lorg/apache/hadoop/security/proto/SecurityProtos$TokenProto$Builder;
      21: aload_1
      22: invokevirtual #40                 // Method org/apache/hadoop/security/proto/SecurityProtos$TokenProto$Builder.setService:(Ljava/lang/String;)Lorg/apache/hadoop/security/proto/SecurityProtos$TokenProto$Builder;
      25: pop
      26: return

  public java.lang.String toString();
    Code:
       0: new           #41                 // class java/lang/StringBuilder
       3: dup
       4: invokespecial #42                 // Method java/lang/StringBuilder."<init>":()V
       7: astore_1
       8: aload_1
       9: ldc           #43                 // String Token {
      11: invokevirtual #44                 // Method java/lang/StringBuilder.append:(Ljava/lang/String;)Ljava/lang/StringBuilder;
      14: pop
      15: aload_1
      16: ldc           #45                 // String kind:
      18: invokevirtual #44                 // Method java/lang/StringBuilder.append:(Ljava/lang/String;)Ljava/lang/StringBuilder;
      21: aload_0
      22: invokevirtual #46                 // Method getKind:()Ljava/lang/String;
      25: invokevirtual #44                 // Method java/lang/StringBuilder.append:(Ljava/lang/String;)Ljava/lang/StringBuilder;
      28: ldc           #47                 // String ,
      30: invokevirtual #44                 // Method java/lang/StringBuilder.append:(Ljava/lang/String;)Ljava/lang/StringBuilder;
      33: pop
      34: aload_1
      35: ldc           #48                 // String service:
      37: invokevirtual #44                 // Method java/lang/StringBuilder.append:(Ljava/lang/String;)Ljava/lang/StringBuilder;
      40: aload_0
      41: invokevirtual #49                 // Method getService:()Ljava/lang/String;
      44: invokevirtual #44                 // Method java/lang/StringBuilder.append:(Ljava/lang/String;)Ljava/lang/StringBuilder;
      47: ldc           #50                 // String  }
      49: invokevirtual #44                 // Method java/lang/StringBuilder.append:(Ljava/lang/String;)Ljava/lang/StringBuilder;
      52: pop
      53: aload_1
      54: invokevirtual #51                 // Method java/lang/StringBuilder.toString:()Ljava/lang/String;
      57: areturn
}
