Compiled from "dig.java"
final class org.xbill.DNS.tools.dig$1 implements org.xbill.DNS.ZoneTransferIn$ZoneTransferHandler {
  org.xbill.DNS.tools.dig$1();
    Code:
       0: aload_0
       1: invokespecial #1                  // Method java/lang/Object."<init>":()V
       4: return

  public void startAXFR();
    Code:
       0: return

  public void startIXFR();
    Code:
       0: return

  public void startIXFRDeletes(org.xbill.DNS.Record);
    Code:
       0: return

  public void startIXFRAdds(org.xbill.DNS.Record);
    Code:
       0: return

  public void handleRecord(org.xbill.DNS.Record);
    Code:
       0: getstatic     #2                  // Field java/lang/System.out:Ljava/io/PrintStream;
       3: aload_1
       4: invokevirtual #3                  // Method java/io/PrintStream.println:(Ljava/lang/Object;)V
       7: return
}
