Compiled from "jnamed.java"
public class org.xbill.DNS.tools.jnamed {
  static final int FLAG_DNSSECOK;

  static final int FLAG_SIGONLY;

  java.util.Map<java.lang.Integer, org.xbill.DNS.Cache> caches;

  java.util.Map<org.xbill.DNS.Name, org.xbill.DNS.Zone> znames;

  java.util.Map<org.xbill.DNS.Name, org.xbill.DNS.TSIG> TSIGs;

  private static java.lang.String addrport(java.net.InetAddress, int);
    Code:
       0: new           #1                  // class java/lang/StringBuilder
       3: dup
       4: invokespecial #2                  // Method java/lang/StringBuilder."<init>":()V
       7: aload_0
       8: invokevirtual #3                  // Method java/net/InetAddress.getHostAddress:()Ljava/lang/String;
      11: invokevirtual #4                  // Method java/lang/StringBuilder.append:(Ljava/lang/String;)Ljava/lang/StringBuilder;
      14: ldc           #5                  // String #
      16: invokevirtual #4                  // Method java/lang/StringBuilder.append:(Ljava/lang/String;)Ljava/lang/StringBuilder;
      19: iload_1
      20: invokevirtual #6                  // Method java/lang/StringBuilder.append:(I)Ljava/lang/StringBuilder;
      23: invokevirtual #7                  // Method java/lang/StringBuilder.toString:()Ljava/lang/String;
      26: areturn

  public org.xbill.DNS.tools.jnamed(java.lang.String) throws java.io.IOException, org.xbill.DNS.ZoneTransferException;
    Code:
       0: aload_0
       1: invokespecial #8                  // Method java/lang/Object."<init>":()V
       4: new           #9                  // class java/util/ArrayList
       7: dup
       8: invokespecial #10                 // Method java/util/ArrayList."<init>":()V
      11: astore        5
      13: new           #9                  // class java/util/ArrayList
      16: dup
      17: invokespecial #10                 // Method java/util/ArrayList."<init>":()V
      20: astore        6
      22: new           #11                 // class java/io/FileInputStream
      25: dup
      26: aload_1
      27: invokespecial #12                 // Method java/io/FileInputStream."<init>":(Ljava/lang/String;)V
      30: astore_2
      31: new           #13                 // class java/io/InputStreamReader
      34: dup
      35: aload_2
      36: invokespecial #14                 // Method java/io/InputStreamReader."<init>":(Ljava/io/InputStream;)V
      39: astore_3
      40: new           #15                 // class java/io/BufferedReader
      43: dup
      44: aload_3
      45: invokespecial #16                 // Method java/io/BufferedReader."<init>":(Ljava/io/Reader;)V
      48: astore        4
      50: goto          81
      53: astore        7
      55: getstatic     #18                 // Field java/lang/System.out:Ljava/io/PrintStream;
      58: new           #1                  // class java/lang/StringBuilder
      61: dup
      62: invokespecial #2                  // Method java/lang/StringBuilder."<init>":()V
      65: ldc           #19                 // String Cannot open
      67: invokevirtual #4                  // Method java/lang/StringBuilder.append:(Ljava/lang/String;)Ljava/lang/StringBuilder;
      70: aload_1
      71: invokevirtual #4                  // Method java/lang/StringBuilder.append:(Ljava/lang/String;)Ljava/lang/StringBuilder;
      74: invokevirtual #7                  // Method java/lang/StringBuilder.toString:()Ljava/lang/String;
      77: invokevirtual #20                 // Method java/io/PrintStream.println:(Ljava/lang/String;)V
      80: return
      81: aload_0
      82: new           #21                 // class java/util/HashMap
      85: dup
      86: invokespecial #22                 // Method java/util/HashMap."<init>":()V
      89: putfield      #23                 // Field caches:Ljava/util/Map;
      92: aload_0
      93: new           #21                 // class java/util/HashMap
      96: dup
      97: invokespecial #22                 // Method java/util/HashMap."<init>":()V
     100: putfield      #24                 // Field znames:Ljava/util/Map;
     103: aload_0
     104: new           #21                 // class java/util/HashMap
     107: dup
     108: invokespecial #22                 // Method java/util/HashMap."<init>":()V
     111: putfield      #25                 // Field TSIGs:Ljava/util/Map;
     114: aload         4
     116: invokevirtual #26                 // Method java/io/BufferedReader.readLine:()Ljava/lang/String;
     119: dup
     120: astore        7
     122: ifnull        597
     125: new           #27                 // class java/util/StringTokenizer
     128: dup
     129: aload         7
     131: invokespecial #28                 // Method java/util/StringTokenizer."<init>":(Ljava/lang/String;)V
     134: astore        8
     136: aload         8
     138: invokevirtual #29                 // Method java/util/StringTokenizer.hasMoreTokens:()Z
     141: ifne          147
     144: goto          114
     147: aload         8
     149: invokevirtual #30                 // Method java/util/StringTokenizer.nextToken:()Ljava/lang/String;
     152: astore        9
     154: aload         8
     156: invokevirtual #29                 // Method java/util/StringTokenizer.hasMoreTokens:()Z
     159: ifne          191
     162: getstatic     #18                 // Field java/lang/System.out:Ljava/io/PrintStream;
     165: new           #1                  // class java/lang/StringBuilder
     168: dup
     169: invokespecial #2                  // Method java/lang/StringBuilder."<init>":()V
     172: ldc           #31                 // String Invalid line:
     174: invokevirtual #4                  // Method java/lang/StringBuilder.append:(Ljava/lang/String;)Ljava/lang/StringBuilder;
     177: aload         7
     179: invokevirtual #4                  // Method java/lang/StringBuilder.append:(Ljava/lang/String;)Ljava/lang/StringBuilder;
     182: invokevirtual #7                  // Method java/lang/StringBuilder.toString:()Ljava/lang/String;
     185: invokevirtual #20                 // Method java/io/PrintStream.println:(Ljava/lang/String;)V
     188: goto          114
     191: aload         9
     193: iconst_0
     194: invokevirtual #32                 // Method java/lang/String.charAt:(I)C
     197: bipush        35
     199: if_icmpne     205
     202: goto          114
     205: aload         9
     207: astore        10
     209: iconst_m1
     210: istore        11
     212: aload         10
     214: invokevirtual #33                 // Method java/lang/String.hashCode:()I
     217: lookupswitch  { // 6
           -1147692044: 356
            -817598092: 292
            -314765822: 276
                106079: 324
               3446913: 340
              94416770: 308
               default: 369
          }
     276: aload         10
     278: ldc           #34                 // String primary
     280: invokevirtual #35                 // Method java/lang/String.equals:(Ljava/lang/Object;)Z
     283: ifeq          369
     286: iconst_0
     287: istore        11
     289: goto          369
     292: aload         10
     294: ldc           #36                 // String secondary
     296: invokevirtual #35                 // Method java/lang/String.equals:(Ljava/lang/Object;)Z
     299: ifeq          369
     302: iconst_1
     303: istore        11
     305: goto          369
     308: aload         10
     310: ldc           #37                 // String cache
     312: invokevirtual #35                 // Method java/lang/String.equals:(Ljava/lang/Object;)Z
     315: ifeq          369
     318: iconst_2
     319: istore        11
     321: goto          369
     324: aload         10
     326: ldc           #38                 // String key
     328: invokevirtual #35                 // Method java/lang/String.equals:(Ljava/lang/Object;)Z
     331: ifeq          369
     334: iconst_3
     335: istore        11
     337: goto          369
     340: aload         10
     342: ldc           #39                 // String port
     344: invokevirtual #35                 // Method java/lang/String.equals:(Ljava/lang/Object;)Z
     347: ifeq          369
     350: iconst_4
     351: istore        11
     353: goto          369
     356: aload         10
     358: ldc           #40                 // String address
     360: invokevirtual #35                 // Method java/lang/String.equals:(Ljava/lang/Object;)Z
     363: ifeq          369
     366: iconst_5
     367: istore        11
     369: iload         11
     371: tableswitch   { // 0 to 5
                     0: 408
                     1: 425
                     2: 442
                     3: 475
                     4: 526
                     5: 545
               default: 568
          }
     408: aload_0
     409: aload         8
     411: invokevirtual #30                 // Method java/util/StringTokenizer.nextToken:()Ljava/lang/String;
     414: aload         8
     416: invokevirtual #30                 // Method java/util/StringTokenizer.nextToken:()Ljava/lang/String;
     419: invokevirtual #41                 // Method addPrimaryZone:(Ljava/lang/String;Ljava/lang/String;)V
     422: goto          594
     425: aload_0
     426: aload         8
     428: invokevirtual #30                 // Method java/util/StringTokenizer.nextToken:()Ljava/lang/String;
     431: aload         8
     433: invokevirtual #30                 // Method java/util/StringTokenizer.nextToken:()Ljava/lang/String;
     436: invokevirtual #42                 // Method addSecondaryZone:(Ljava/lang/String;Ljava/lang/String;)V
     439: goto          594
     442: new           #43                 // class org/xbill/DNS/Cache
     445: dup
     446: aload         8
     448: invokevirtual #30                 // Method java/util/StringTokenizer.nextToken:()Ljava/lang/String;
     451: invokespecial #44                 // Method org/xbill/DNS/Cache."<init>":(Ljava/lang/String;)V
     454: astore        12
     456: aload_0
     457: getfield      #23                 // Field caches:Ljava/util/Map;
     460: iconst_1
     461: invokestatic  #46                 // Method java/lang/Integer.valueOf:(I)Ljava/lang/Integer;
     464: aload         12
     466: invokeinterface #47,  3           // InterfaceMethod java/util/Map.put:(Ljava/lang/Object;Ljava/lang/Object;)Ljava/lang/Object;
     471: pop
     472: goto          594
     475: aload         8
     477: invokevirtual #30                 // Method java/util/StringTokenizer.nextToken:()Ljava/lang/String;
     480: astore        13
     482: aload         8
     484: invokevirtual #30                 // Method java/util/StringTokenizer.nextToken:()Ljava/lang/String;
     487: astore        14
     489: aload         8
     491: invokevirtual #29                 // Method java/util/StringTokenizer.hasMoreTokens:()Z
     494: ifeq          513
     497: aload_0
     498: aload         13
     500: aload         14
     502: aload         8
     504: invokevirtual #30                 // Method java/util/StringTokenizer.nextToken:()Ljava/lang/String;
     507: invokevirtual #48                 // Method addTSIG:(Ljava/lang/String;Ljava/lang/String;Ljava/lang/String;)V
     510: goto          594
     513: aload_0
     514: ldc           #49                 // String hmac-md5
     516: aload         13
     518: aload         14
     520: invokevirtual #48                 // Method addTSIG:(Ljava/lang/String;Ljava/lang/String;Ljava/lang/String;)V
     523: goto          594
     526: aload         5
     528: aload         8
     530: invokevirtual #30                 // Method java/util/StringTokenizer.nextToken:()Ljava/lang/String;
     533: invokestatic  #50                 // Method java/lang/Integer.valueOf:(Ljava/lang/String;)Ljava/lang/Integer;
     536: invokeinterface #51,  2           // InterfaceMethod java/util/List.add:(Ljava/lang/Object;)Z
     541: pop
     542: goto          594
     545: aload         8
     547: invokevirtual #30                 // Method java/util/StringTokenizer.nextToken:()Ljava/lang/String;
     550: astore        15
     552: aload         6
     554: aload         15
     556: invokestatic  #52                 // Method org/xbill/DNS/Address.getByAddress:(Ljava/lang/String;)Ljava/net/InetAddress;
     559: invokeinterface #51,  2           // InterfaceMethod java/util/List.add:(Ljava/lang/Object;)Z
     564: pop
     565: goto          594
     568: getstatic     #18                 // Field java/lang/System.out:Ljava/io/PrintStream;
     571: new           #1                  // class java/lang/StringBuilder
     574: dup
     575: invokespecial #2                  // Method java/lang/StringBuilder."<init>":()V
     578: ldc           #53                 // String unknown keyword:
     580: invokevirtual #4                  // Method java/lang/StringBuilder.append:(Ljava/lang/String;)Ljava/lang/StringBuilder;
     583: aload         9
     585: invokevirtual #4                  // Method java/lang/StringBuilder.append:(Ljava/lang/String;)Ljava/lang/StringBuilder;
     588: invokevirtual #7                  // Method java/lang/StringBuilder.toString:()Ljava/lang/String;
     591: invokevirtual #20                 // Method java/io/PrintStream.println:(Ljava/lang/String;)V
     594: goto          114
     597: aload         5
     599: invokeinterface #54,  1           // InterfaceMethod java/util/List.isEmpty:()Z
     604: ifeq          620
     607: aload         5
     609: bipush        53
     611: invokestatic  #46                 // Method java/lang/Integer.valueOf:(I)Ljava/lang/Integer;
     614: invokeinterface #51,  2           // InterfaceMethod java/util/List.add:(Ljava/lang/Object;)Z
     619: pop
     620: aload         6
     622: invokeinterface #54,  1           // InterfaceMethod java/util/List.isEmpty:()Z
     627: ifeq          643
     630: aload         6
     632: ldc           #55                 // String 0.0.0.0
     634: invokestatic  #52                 // Method org/xbill/DNS/Address.getByAddress:(Ljava/lang/String;)Ljava/net/InetAddress;
     637: invokeinterface #51,  2           // InterfaceMethod java/util/List.add:(Ljava/lang/Object;)Z
     642: pop
     643: aload         6
     645: invokeinterface #56,  1           // InterfaceMethod java/util/List.iterator:()Ljava/util/Iterator;
     650: astore        8
     652: aload         8
     654: invokeinterface #57,  1           // InterfaceMethod java/util/Iterator.hasNext:()Z
     659: ifeq          765
     662: aload         8
     664: invokeinterface #58,  1           // InterfaceMethod java/util/Iterator.next:()Ljava/lang/Object;
     669: checkcast     #59                 // class java/net/InetAddress
     672: astore        9
     674: aload         5
     676: invokeinterface #56,  1           // InterfaceMethod java/util/List.iterator:()Ljava/util/Iterator;
     681: astore        10
     683: aload         10
     685: invokeinterface #57,  1           // InterfaceMethod java/util/Iterator.hasNext:()Z
     690: ifeq          762
     693: aload         10
     695: invokeinterface #58,  1           // InterfaceMethod java/util/Iterator.next:()Ljava/lang/Object;
     700: checkcast     #60                 // class java/lang/Integer
     703: astore        11
     705: aload         11
     707: invokevirtual #61                 // Method java/lang/Integer.intValue:()I
     710: istore        12
     712: aload_0
     713: aload         9
     715: iload         12
     717: invokevirtual #62                 // Method addUDP:(Ljava/net/InetAddress;I)V
     720: aload_0
     721: aload         9
     723: iload         12
     725: invokevirtual #63                 // Method addTCP:(Ljava/net/InetAddress;I)V
     728: getstatic     #18                 // Field java/lang/System.out:Ljava/io/PrintStream;
     731: new           #1                  // class java/lang/StringBuilder
     734: dup
     735: invokespecial #2                  // Method java/lang/StringBuilder."<init>":()V
     738: ldc           #64                 // String jnamed: listening on
     740: invokevirtual #4                  // Method java/lang/StringBuilder.append:(Ljava/lang/String;)Ljava/lang/StringBuilder;
     743: aload         9
     745: iload         12
     747: invokestatic  #65                 // Method addrport:(Ljava/net/InetAddress;I)Ljava/lang/String;
     750: invokevirtual #4                  // Method java/lang/StringBuilder.append:(Ljava/lang/String;)Ljava/lang/StringBuilder;
     753: invokevirtual #7                  // Method java/lang/StringBuilder.toString:()Ljava/lang/String;
     756: invokevirtual #20                 // Method java/io/PrintStream.println:(Ljava/lang/String;)V
     759: goto          683
     762: goto          652
     765: getstatic     #18                 // Field java/lang/System.out:Ljava/io/PrintStream;
     768: ldc           #66                 // String jnamed: running
     770: invokevirtual #20                 // Method java/io/PrintStream.println:(Ljava/lang/String;)V
     773: aload         4
     775: invokevirtual #67                 // Method java/io/BufferedReader.close:()V
     778: goto          791
     781: astore        16
     783: aload         4
     785: invokevirtual #67                 // Method java/io/BufferedReader.close:()V
     788: aload         16
     790: athrow
     791: return
    Exception table:
       from    to  target type
          22    50    53   Class java/lang/Exception
          81   773   781   any
         781   783   781   any

  public void addPrimaryZone(java.lang.String, java.lang.String) throws java.io.IOException;
    Code:
       0: aconst_null
       1: astore_3
       2: aload_1
       3: ifnull        14
       6: aload_1
       7: getstatic     #68                 // Field org/xbill/DNS/Name.root:Lorg/xbill/DNS/Name;
      10: invokestatic  #69                 // Method org/xbill/DNS/Name.fromString:(Ljava/lang/String;Lorg/xbill/DNS/Name;)Lorg/xbill/DNS/Name;
      13: astore_3
      14: new           #70                 // class org/xbill/DNS/Zone
      17: dup
      18: aload_3
      19: aload_2
      20: invokespecial #71                 // Method org/xbill/DNS/Zone."<init>":(Lorg/xbill/DNS/Name;Ljava/lang/String;)V
      23: astore        4
      25: aload_0
      26: getfield      #24                 // Field znames:Ljava/util/Map;
      29: aload         4
      31: invokevirtual #72                 // Method org/xbill/DNS/Zone.getOrigin:()Lorg/xbill/DNS/Name;
      34: aload         4
      36: invokeinterface #47,  3           // InterfaceMethod java/util/Map.put:(Ljava/lang/Object;Ljava/lang/Object;)Ljava/lang/Object;
      41: pop
      42: return

  public void addSecondaryZone(java.lang.String, java.lang.String) throws java.io.IOException, org.xbill.DNS.ZoneTransferException;
    Code:
       0: aload_1
       1: getstatic     #68                 // Field org/xbill/DNS/Name.root:Lorg/xbill/DNS/Name;
       4: invokestatic  #69                 // Method org/xbill/DNS/Name.fromString:(Ljava/lang/String;Lorg/xbill/DNS/Name;)Lorg/xbill/DNS/Name;
       7: astore_3
       8: new           #70                 // class org/xbill/DNS/Zone
      11: dup
      12: aload_3
      13: iconst_1
      14: aload_2
      15: invokespecial #73                 // Method org/xbill/DNS/Zone."<init>":(Lorg/xbill/DNS/Name;ILjava/lang/String;)V
      18: astore        4
      20: aload_0
      21: getfield      #24                 // Field znames:Ljava/util/Map;
      24: aload_3
      25: aload         4
      27: invokeinterface #47,  3           // InterfaceMethod java/util/Map.put:(Ljava/lang/Object;Ljava/lang/Object;)Ljava/lang/Object;
      32: pop
      33: return

  public void addTSIG(java.lang.String, java.lang.String, java.lang.String) throws java.io.IOException;
    Code:
       0: aload_2
       1: getstatic     #68                 // Field org/xbill/DNS/Name.root:Lorg/xbill/DNS/Name;
       4: invokestatic  #69                 // Method org/xbill/DNS/Name.fromString:(Ljava/lang/String;Lorg/xbill/DNS/Name;)Lorg/xbill/DNS/Name;
       7: astore        4
       9: aload_0
      10: getfield      #25                 // Field TSIGs:Ljava/util/Map;
      13: aload         4
      15: new           #74                 // class org/xbill/DNS/TSIG
      18: dup
      19: aload_1
      20: aload_2
      21: aload_3
      22: invokespecial #75                 // Method org/xbill/DNS/TSIG."<init>":(Ljava/lang/String;Ljava/lang/String;Ljava/lang/String;)V
      25: invokeinterface #47,  3           // InterfaceMethod java/util/Map.put:(Ljava/lang/Object;Ljava/lang/Object;)Ljava/lang/Object;
      30: pop
      31: return

  public org.xbill.DNS.Cache getCache(int);
    Code:
       0: aload_0
       1: getfield      #23                 // Field caches:Ljava/util/Map;
       4: iload_1
       5: invokestatic  #46                 // Method java/lang/Integer.valueOf:(I)Ljava/lang/Integer;
       8: invokedynamic #76,  0             // InvokeDynamic #0:apply:()Ljava/util/function/Function;
      13: invokeinterface #77,  3           // InterfaceMethod java/util/Map.computeIfAbsent:(Ljava/lang/Object;Ljava/util/function/Function;)Ljava/lang/Object;
      18: checkcast     #43                 // class org/xbill/DNS/Cache
      21: areturn

  public org.xbill.DNS.Zone findBestZone(org.xbill.DNS.Name);
    Code:
       0: aload_0
       1: getfield      #24                 // Field znames:Ljava/util/Map;
       4: aload_1
       5: invokeinterface #78,  2           // InterfaceMethod java/util/Map.get:(Ljava/lang/Object;)Ljava/lang/Object;
      10: checkcast     #70                 // class org/xbill/DNS/Zone
      13: astore_2
      14: aload_2
      15: ifnull        20
      18: aload_2
      19: areturn
      20: aload_1
      21: invokevirtual #79                 // Method org/xbill/DNS/Name.labels:()I
      24: istore_3
      25: iconst_1
      26: istore        4
      28: iload         4
      30: iload_3
      31: if_icmpge     73
      34: new           #80                 // class org/xbill/DNS/Name
      37: dup
      38: aload_1
      39: iload         4
      41: invokespecial #81                 // Method org/xbill/DNS/Name."<init>":(Lorg/xbill/DNS/Name;I)V
      44: astore        5
      46: aload_0
      47: getfield      #24                 // Field znames:Ljava/util/Map;
      50: aload         5
      52: invokeinterface #78,  2           // InterfaceMethod java/util/Map.get:(Ljava/lang/Object;)Ljava/lang/Object;
      57: checkcast     #70                 // class org/xbill/DNS/Zone
      60: astore_2
      61: aload_2
      62: ifnull        67
      65: aload_2
      66: areturn
      67: iinc          4, 1
      70: goto          28
      73: aconst_null
      74: areturn

  public org.xbill.DNS.RRset findExactMatch(org.xbill.DNS.Name, int, int, boolean);
    Code:
       0: aload_0
       1: aload_1
       2: invokevirtual #82                 // Method findBestZone:(Lorg/xbill/DNS/Name;)Lorg/xbill/DNS/Zone;
       5: astore        5
       7: aload         5
       9: ifnull        20
      12: aload         5
      14: aload_1
      15: iload_2
      16: invokevirtual #83                 // Method org/xbill/DNS/Zone.findExactMatch:(Lorg/xbill/DNS/Name;I)Lorg/xbill/DNS/RRset;
      19: areturn
      20: aload_0
      21: iload_3
      22: invokevirtual #84                 // Method getCache:(I)Lorg/xbill/DNS/Cache;
      25: astore        7
      27: iload         4
      29: ifeq          44
      32: aload         7
      34: aload_1
      35: iload_2
      36: invokevirtual #85                 // Method org/xbill/DNS/Cache.findAnyRecords:(Lorg/xbill/DNS/Name;I)Ljava/util/List;
      39: astore        6
      41: goto          53
      44: aload         7
      46: aload_1
      47: iload_2
      48: invokevirtual #86                 // Method org/xbill/DNS/Cache.findRecords:(Lorg/xbill/DNS/Name;I)Ljava/util/List;
      51: astore        6
      53: aload         6
      55: ifnonnull     60
      58: aconst_null
      59: areturn
      60: aload         6
      62: iconst_0
      63: invokeinterface #87,  2           // InterfaceMethod java/util/List.get:(I)Ljava/lang/Object;
      68: checkcast     #88                 // class org/xbill/DNS/RRset
      71: areturn

  void addRRset(org.xbill.DNS.Name, org.xbill.DNS.Message, org.xbill.DNS.RRset, int, int);
    Code:
       0: iconst_1
       1: istore        6
       3: iload         6
       5: iload         4
       7: if_icmpgt     31
      10: aload_2
      11: aload_1
      12: aload_3
      13: invokevirtual #89                 // Method org/xbill/DNS/RRset.getType:()I
      16: iload         6
      18: invokevirtual #90                 // Method org/xbill/DNS/Message.findRRset:(Lorg/xbill/DNS/Name;II)Z
      21: ifeq          25
      24: return
      25: iinc          6, 1
      28: goto          3
      31: iload         5
      33: iconst_2
      34: iand
      35: ifne          108
      38: aload_3
      39: invokevirtual #92                 // Method org/xbill/DNS/RRset.rrs:()Ljava/util/List;
      42: invokeinterface #56,  1           // InterfaceMethod java/util/List.iterator:()Ljava/util/Iterator;
      47: astore        6
      49: aload         6
      51: invokeinterface #57,  1           // InterfaceMethod java/util/Iterator.hasNext:()Z
      56: ifeq          108
      59: aload         6
      61: invokeinterface #58,  1           // InterfaceMethod java/util/Iterator.next:()Ljava/lang/Object;
      66: checkcast     #93                 // class org/xbill/DNS/Record
      69: astore        7
      71: aload         7
      73: invokevirtual #94                 // Method org/xbill/DNS/Record.getName:()Lorg/xbill/DNS/Name;
      76: invokevirtual #95                 // Method org/xbill/DNS/Name.isWild:()Z
      79: ifeq          97
      82: aload_1
      83: invokevirtual #95                 // Method org/xbill/DNS/Name.isWild:()Z
      86: ifne          97
      89: aload         7
      91: aload_1
      92: invokevirtual #96                 // Method org/xbill/DNS/Record.withName:(Lorg/xbill/DNS/Name;)Lorg/xbill/DNS/Record;
      95: astore        7
      97: aload_2
      98: aload         7
     100: iload         4
     102: invokevirtual #97                 // Method org/xbill/DNS/Message.addRecord:(Lorg/xbill/DNS/Record;I)V
     105: goto          49
     108: iload         5
     110: iconst_3
     111: iand
     112: ifeq          185
     115: aload_3
     116: invokevirtual #98                 // Method org/xbill/DNS/RRset.sigs:()Ljava/util/List;
     119: invokeinterface #56,  1           // InterfaceMethod java/util/List.iterator:()Ljava/util/Iterator;
     124: astore        6
     126: aload         6
     128: invokeinterface #57,  1           // InterfaceMethod java/util/Iterator.hasNext:()Z
     133: ifeq          185
     136: aload         6
     138: invokeinterface #58,  1           // InterfaceMethod java/util/Iterator.next:()Ljava/lang/Object;
     143: checkcast     #93                 // class org/xbill/DNS/Record
     146: astore        7
     148: aload         7
     150: invokevirtual #94                 // Method org/xbill/DNS/Record.getName:()Lorg/xbill/DNS/Name;
     153: invokevirtual #95                 // Method org/xbill/DNS/Name.isWild:()Z
     156: ifeq          174
     159: aload_1
     160: invokevirtual #95                 // Method org/xbill/DNS/Name.isWild:()Z
     163: ifne          174
     166: aload         7
     168: aload_1
     169: invokevirtual #96                 // Method org/xbill/DNS/Record.withName:(Lorg/xbill/DNS/Name;)Lorg/xbill/DNS/Record;
     172: astore        7
     174: aload_2
     175: aload         7
     177: iload         4
     179: invokevirtual #97                 // Method org/xbill/DNS/Message.addRecord:(Lorg/xbill/DNS/Record;I)V
     182: goto          126
     185: return

  private void addSOA(org.xbill.DNS.Message, org.xbill.DNS.Zone);
    Code:
       0: aload_1
       1: aload_2
       2: invokevirtual #99                 // Method org/xbill/DNS/Zone.getSOA:()Lorg/xbill/DNS/SOARecord;
       5: iconst_2
       6: invokevirtual #97                 // Method org/xbill/DNS/Message.addRecord:(Lorg/xbill/DNS/Record;I)V
       9: return

  private void addNS(org.xbill.DNS.Message, org.xbill.DNS.Zone, int);
    Code:
       0: aload_2
       1: invokevirtual #101                // Method org/xbill/DNS/Zone.getNS:()Lorg/xbill/DNS/RRset;
       4: astore        4
       6: aload_0
       7: aload         4
       9: invokevirtual #102                // Method org/xbill/DNS/RRset.getName:()Lorg/xbill/DNS/Name;
      12: aload_1
      13: aload         4
      15: iconst_2
      16: iload_3
      17: invokevirtual #103                // Method addRRset:(Lorg/xbill/DNS/Name;Lorg/xbill/DNS/Message;Lorg/xbill/DNS/RRset;II)V
      20: return

  private void addCacheNS(org.xbill.DNS.Message, org.xbill.DNS.Cache, org.xbill.DNS.Name);
    Code:
       0: aload_2
       1: aload_3
       2: iconst_2
       3: iconst_0
       4: invokevirtual #106                // Method org/xbill/DNS/Cache.lookupRecords:(Lorg/xbill/DNS/Name;II)Lorg/xbill/DNS/SetResponse;
       7: astore        4
       9: aload         4
      11: invokevirtual #107                // Method org/xbill/DNS/SetResponse.isDelegation:()Z
      14: ifne          18
      17: return
      18: aload         4
      20: invokevirtual #108                // Method org/xbill/DNS/SetResponse.getNS:()Lorg/xbill/DNS/RRset;
      23: astore        5
      25: aload         5
      27: invokevirtual #92                 // Method org/xbill/DNS/RRset.rrs:()Ljava/util/List;
      30: invokeinterface #56,  1           // InterfaceMethod java/util/List.iterator:()Ljava/util/Iterator;
      35: astore        6
      37: aload         6
      39: invokeinterface #57,  1           // InterfaceMethod java/util/Iterator.hasNext:()Z
      44: ifeq          69
      47: aload         6
      49: invokeinterface #58,  1           // InterfaceMethod java/util/Iterator.next:()Ljava/lang/Object;
      54: checkcast     #93                 // class org/xbill/DNS/Record
      57: astore        7
      59: aload_1
      60: aload         7
      62: iconst_2
      63: invokevirtual #97                 // Method org/xbill/DNS/Message.addRecord:(Lorg/xbill/DNS/Record;I)V
      66: goto          37
      69: return

  private void addGlue(org.xbill.DNS.Message, org.xbill.DNS.Name, int);
    Code:
       0: aload_0
       1: aload_2
       2: iconst_1
       3: iconst_1
       4: iconst_1
       5: invokevirtual #109                // Method findExactMatch:(Lorg/xbill/DNS/Name;IIZ)Lorg/xbill/DNS/RRset;
       8: astore        4
      10: aload         4
      12: ifnonnull     16
      15: return
      16: aload_0
      17: aload_2
      18: aload_1
      19: aload         4
      21: iconst_3
      22: iload_3
      23: invokevirtual #103                // Method addRRset:(Lorg/xbill/DNS/Name;Lorg/xbill/DNS/Message;Lorg/xbill/DNS/RRset;II)V
      26: return

  private void addAdditional2(org.xbill.DNS.Message, int, int);
    Code:
       0: aload_1
       1: iload_2
       2: invokevirtual #110                // Method org/xbill/DNS/Message.getSection:(I)Ljava/util/List;
       5: invokeinterface #56,  1           // InterfaceMethod java/util/List.iterator:()Ljava/util/Iterator;
      10: astore        4
      12: aload         4
      14: invokeinterface #57,  1           // InterfaceMethod java/util/Iterator.hasNext:()Z
      19: ifeq          57
      22: aload         4
      24: invokeinterface #58,  1           // InterfaceMethod java/util/Iterator.next:()Ljava/lang/Object;
      29: checkcast     #93                 // class org/xbill/DNS/Record
      32: astore        5
      34: aload         5
      36: invokevirtual #111                // Method org/xbill/DNS/Record.getAdditionalName:()Lorg/xbill/DNS/Name;
      39: astore        6
      41: aload         6
      43: ifnull        54
      46: aload_0
      47: aload_1
      48: aload         6
      50: iload_3
      51: invokespecial #112                // Method addGlue:(Lorg/xbill/DNS/Message;Lorg/xbill/DNS/Name;I)V
      54: goto          12
      57: return

  private void addAdditional(org.xbill.DNS.Message, int);
    Code:
       0: aload_0
       1: aload_1
       2: iconst_1
       3: iload_2
       4: invokespecial #113                // Method addAdditional2:(Lorg/xbill/DNS/Message;II)V
       7: aload_0
       8: aload_1
       9: iconst_2
      10: iload_2
      11: invokespecial #113                // Method addAdditional2:(Lorg/xbill/DNS/Message;II)V
      14: return

  byte addAnswer(org.xbill.DNS.Message, org.xbill.DNS.Name, int, int, int, int);
    Code:
       0: iconst_0
       1: istore        8
       3: iload         5
       5: bipush        6
       7: if_icmple     12
      10: iconst_0
      11: ireturn
      12: iload_3
      13: bipush        24
      15: if_icmpeq     24
      18: iload_3
      19: bipush        46
      21: if_icmpne     34
      24: sipush        255
      27: istore_3
      28: iload         6
      30: iconst_2
      31: ior
      32: istore        6
      34: aload_0
      35: aload_2
      36: invokevirtual #82                 // Method findBestZone:(Lorg/xbill/DNS/Name;)Lorg/xbill/DNS/Zone;
      39: astore        9
      41: aload         9
      43: ifnull        58
      46: aload         9
      48: aload_2
      49: iload_3
      50: invokevirtual #115                // Method org/xbill/DNS/Zone.findRecords:(Lorg/xbill/DNS/Name;I)Lorg/xbill/DNS/SetResponse;
      53: astore        7
      55: goto          76
      58: aload_0
      59: iload         4
      61: invokevirtual #84                 // Method getCache:(I)Lorg/xbill/DNS/Cache;
      64: astore        10
      66: aload         10
      68: aload_2
      69: iload_3
      70: iconst_3
      71: invokevirtual #106                // Method org/xbill/DNS/Cache.lookupRecords:(Lorg/xbill/DNS/Name;II)Lorg/xbill/DNS/SetResponse;
      74: astore        7
      76: aload         7
      78: invokevirtual #116                // Method org/xbill/DNS/SetResponse.isUnknown:()Z
      81: ifeq          96
      84: aload_0
      85: aload_1
      86: aload_0
      87: iload         4
      89: invokevirtual #84                 // Method getCache:(I)Lorg/xbill/DNS/Cache;
      92: aload_2
      93: invokespecial #117                // Method addCacheNS:(Lorg/xbill/DNS/Message;Lorg/xbill/DNS/Cache;Lorg/xbill/DNS/Name;)V
      96: aload         7
      98: invokevirtual #118                // Method org/xbill/DNS/SetResponse.isNXDOMAIN:()Z
     101: ifeq          143
     104: aload_1
     105: invokevirtual #119                // Method org/xbill/DNS/Message.getHeader:()Lorg/xbill/DNS/Header;
     108: iconst_3
     109: invokevirtual #120                // Method org/xbill/DNS/Header.setRcode:(I)V
     112: aload         9
     114: ifnull        137
     117: aload_0
     118: aload_1
     119: aload         9
     121: invokespecial #121                // Method addSOA:(Lorg/xbill/DNS/Message;Lorg/xbill/DNS/Zone;)V
     124: iload         5
     126: ifne          137
     129: aload_1
     130: invokevirtual #119                // Method org/xbill/DNS/Message.getHeader:()Lorg/xbill/DNS/Header;
     133: iconst_5
     134: invokevirtual #123                // Method org/xbill/DNS/Header.setFlag:(I)V
     137: iconst_3
     138: istore        8
     140: goto          522
     143: aload         7
     145: invokevirtual #124                // Method org/xbill/DNS/SetResponse.isNXRRSET:()Z
     148: ifeq          179
     151: aload         9
     153: ifnull        522
     156: aload_0
     157: aload_1
     158: aload         9
     160: invokespecial #121                // Method addSOA:(Lorg/xbill/DNS/Message;Lorg/xbill/DNS/Zone;)V
     163: iload         5
     165: ifne          522
     168: aload_1
     169: invokevirtual #119                // Method org/xbill/DNS/Message.getHeader:()Lorg/xbill/DNS/Header;
     172: iconst_5
     173: invokevirtual #123                // Method org/xbill/DNS/Header.setFlag:(I)V
     176: goto          522
     179: aload         7
     181: invokevirtual #107                // Method org/xbill/DNS/SetResponse.isDelegation:()Z
     184: ifeq          212
     187: aload         7
     189: invokevirtual #108                // Method org/xbill/DNS/SetResponse.getNS:()Lorg/xbill/DNS/RRset;
     192: astore        10
     194: aload_0
     195: aload         10
     197: invokevirtual #102                // Method org/xbill/DNS/RRset.getName:()Lorg/xbill/DNS/Name;
     200: aload_1
     201: aload         10
     203: iconst_2
     204: iload         6
     206: invokevirtual #103                // Method addRRset:(Lorg/xbill/DNS/Name;Lorg/xbill/DNS/Message;Lorg/xbill/DNS/RRset;II)V
     209: goto          522
     212: aload         7
     214: invokevirtual #125                // Method org/xbill/DNS/SetResponse.isCNAME:()Z
     217: ifeq          291
     220: aload         7
     222: invokevirtual #126                // Method org/xbill/DNS/SetResponse.getCNAME:()Lorg/xbill/DNS/CNAMERecord;
     225: astore        10
     227: new           #88                 // class org/xbill/DNS/RRset
     230: dup
     231: aload         10
     233: invokespecial #127                // Method org/xbill/DNS/RRset."<init>":(Lorg/xbill/DNS/Record;)V
     236: astore        11
     238: aload_0
     239: aload_2
     240: aload_1
     241: aload         11
     243: iconst_1
     244: iload         6
     246: invokevirtual #103                // Method addRRset:(Lorg/xbill/DNS/Name;Lorg/xbill/DNS/Message;Lorg/xbill/DNS/RRset;II)V
     249: aload         9
     251: ifnull        267
     254: iload         5
     256: ifne          267
     259: aload_1
     260: invokevirtual #119                // Method org/xbill/DNS/Message.getHeader:()Lorg/xbill/DNS/Header;
     263: iconst_5
     264: invokevirtual #123                // Method org/xbill/DNS/Header.setFlag:(I)V
     267: aload_0
     268: aload_1
     269: aload         10
     271: invokevirtual #128                // Method org/xbill/DNS/CNAMERecord.getTarget:()Lorg/xbill/DNS/Name;
     274: iload_3
     275: iload         4
     277: iload         5
     279: iconst_1
     280: iadd
     281: iload         6
     283: invokevirtual #129                // Method addAnswer:(Lorg/xbill/DNS/Message;Lorg/xbill/DNS/Name;IIII)B
     286: istore        8
     288: goto          522
     291: aload         7
     293: invokevirtual #130                // Method org/xbill/DNS/SetResponse.isDNAME:()Z
     296: ifeq          420
     299: aload         7
     301: invokevirtual #131                // Method org/xbill/DNS/SetResponse.getDNAME:()Lorg/xbill/DNS/DNAMERecord;
     304: astore        10
     306: new           #88                 // class org/xbill/DNS/RRset
     309: dup
     310: aload         10
     312: invokespecial #127                // Method org/xbill/DNS/RRset."<init>":(Lorg/xbill/DNS/Record;)V
     315: astore        11
     317: aload_0
     318: aload_2
     319: aload_1
     320: aload         11
     322: iconst_1
     323: iload         6
     325: invokevirtual #103                // Method addRRset:(Lorg/xbill/DNS/Name;Lorg/xbill/DNS/Message;Lorg/xbill/DNS/RRset;II)V
     328: aload_2
     329: aload         10
     331: invokevirtual #132                // Method org/xbill/DNS/Name.fromDNAME:(Lorg/xbill/DNS/DNAMERecord;)Lorg/xbill/DNS/Name;
     334: astore        12
     336: goto          344
     339: astore        13
     341: bipush        6
     343: ireturn
     344: new           #134                // class org/xbill/DNS/CNAMERecord
     347: dup
     348: aload_2
     349: iload         4
     351: lconst_0
     352: aload         12
     354: invokespecial #135                // Method org/xbill/DNS/CNAMERecord."<init>":(Lorg/xbill/DNS/Name;IJLorg/xbill/DNS/Name;)V
     357: astore        13
     359: new           #88                 // class org/xbill/DNS/RRset
     362: dup
     363: aload         13
     365: invokespecial #127                // Method org/xbill/DNS/RRset."<init>":(Lorg/xbill/DNS/Record;)V
     368: astore        14
     370: aload_0
     371: aload_2
     372: aload_1
     373: aload         14
     375: iconst_1
     376: iload         6
     378: invokevirtual #103                // Method addRRset:(Lorg/xbill/DNS/Name;Lorg/xbill/DNS/Message;Lorg/xbill/DNS/RRset;II)V
     381: aload         9
     383: ifnull        399
     386: iload         5
     388: ifne          399
     391: aload_1
     392: invokevirtual #119                // Method org/xbill/DNS/Message.getHeader:()Lorg/xbill/DNS/Header;
     395: iconst_5
     396: invokevirtual #123                // Method org/xbill/DNS/Header.setFlag:(I)V
     399: aload_0
     400: aload_1
     401: aload         12
     403: iload_3
     404: iload         4
     406: iload         5
     408: iconst_1
     409: iadd
     410: iload         6
     412: invokevirtual #129                // Method addAnswer:(Lorg/xbill/DNS/Message;Lorg/xbill/DNS/Name;IIII)B
     415: istore        8
     417: goto          522
     420: aload         7
     422: invokevirtual #136                // Method org/xbill/DNS/SetResponse.isSuccessful:()Z
     425: ifeq          522
     428: aload         7
     430: invokevirtual #137                // Method org/xbill/DNS/SetResponse.answers:()Ljava/util/List;
     433: astore        10
     435: aload         10
     437: invokeinterface #56,  1           // InterfaceMethod java/util/List.iterator:()Ljava/util/Iterator;
     442: astore        11
     444: aload         11
     446: invokeinterface #57,  1           // InterfaceMethod java/util/Iterator.hasNext:()Z
     451: ifeq          480
     454: aload         11
     456: invokeinterface #58,  1           // InterfaceMethod java/util/Iterator.next:()Ljava/lang/Object;
     461: checkcast     #88                 // class org/xbill/DNS/RRset
     464: astore        12
     466: aload_0
     467: aload_2
     468: aload_1
     469: aload         12
     471: iconst_1
     472: iload         6
     474: invokevirtual #103                // Method addRRset:(Lorg/xbill/DNS/Name;Lorg/xbill/DNS/Message;Lorg/xbill/DNS/RRset;II)V
     477: goto          444
     480: aload         9
     482: ifnull        510
     485: aload_0
     486: aload_1
     487: aload         9
     489: iload         6
     491: invokespecial #138                // Method addNS:(Lorg/xbill/DNS/Message;Lorg/xbill/DNS/Zone;I)V
     494: iload         5
     496: ifne          522
     499: aload_1
     500: invokevirtual #119                // Method org/xbill/DNS/Message.getHeader:()Lorg/xbill/DNS/Header;
     503: iconst_5
     504: invokevirtual #123                // Method org/xbill/DNS/Header.setFlag:(I)V
     507: goto          522
     510: aload_0
     511: aload_1
     512: aload_0
     513: iload         4
     515: invokevirtual #84                 // Method getCache:(I)Lorg/xbill/DNS/Cache;
     518: aload_2
     519: invokespecial #117                // Method addCacheNS:(Lorg/xbill/DNS/Message;Lorg/xbill/DNS/Cache;Lorg/xbill/DNS/Name;)V
     522: iload         8
     524: ireturn
    Exception table:
       from    to  target type
         328   336   339   Class org/xbill/DNS/NameTooLongException

  byte[] doAXFR(org.xbill.DNS.Name, org.xbill.DNS.Message, org.xbill.DNS.TSIG, org.xbill.DNS.TSIGRecord, java.net.Socket);
    Code:
       0: aload_0
       1: getfield      #24                 // Field znames:Ljava/util/Map;
       4: aload_1
       5: invokeinterface #78,  2           // InterfaceMethod java/util/Map.get:(Ljava/lang/Object;)Ljava/lang/Object;
      10: checkcast     #70                 // class org/xbill/DNS/Zone
      13: astore        6
      15: iconst_1
      16: istore        7
      18: aload         6
      20: ifnonnull     30
      23: aload_0
      24: aload_2
      25: iconst_5
      26: invokevirtual #139                // Method errorMessage:(Lorg/xbill/DNS/Message;I)[B
      29: areturn
      30: new           #140                // class java/io/DataOutputStream
      33: dup
      34: aload         5
      36: invokevirtual #141                // Method java/net/Socket.getOutputStream:()Ljava/io/OutputStream;
      39: invokespecial #142                // Method java/io/DataOutputStream."<init>":(Ljava/io/OutputStream;)V
      42: astore        8
      44: aload_2
      45: invokevirtual #119                // Method org/xbill/DNS/Message.getHeader:()Lorg/xbill/DNS/Header;
      48: invokevirtual #143                // Method org/xbill/DNS/Header.getID:()I
      51: istore        9
      53: aload         6
      55: invokevirtual #144                // Method org/xbill/DNS/Zone.AXFR:()Ljava/util/Iterator;
      58: astore        10
      60: aload         10
      62: invokeinterface #57,  1           // InterfaceMethod java/util/Iterator.hasNext:()Z
      67: ifeq          176
      70: aload         10
      72: invokeinterface #58,  1           // InterfaceMethod java/util/Iterator.next:()Ljava/lang/Object;
      77: checkcast     #88                 // class org/xbill/DNS/RRset
      80: astore        11
      82: new           #145                // class org/xbill/DNS/Message
      85: dup
      86: iload         9
      88: invokespecial #146                // Method org/xbill/DNS/Message."<init>":(I)V
      91: astore        12
      93: aload         12
      95: invokevirtual #119                // Method org/xbill/DNS/Message.getHeader:()Lorg/xbill/DNS/Header;
      98: astore        13
     100: aload         13
     102: iconst_0
     103: invokevirtual #123                // Method org/xbill/DNS/Header.setFlag:(I)V
     106: aload         13
     108: iconst_5
     109: invokevirtual #123                // Method org/xbill/DNS/Header.setFlag:(I)V
     112: aload_0
     113: aload         11
     115: invokevirtual #102                // Method org/xbill/DNS/RRset.getName:()Lorg/xbill/DNS/Name;
     118: aload         12
     120: aload         11
     122: iconst_1
     123: iconst_1
     124: invokevirtual #103                // Method addRRset:(Lorg/xbill/DNS/Name;Lorg/xbill/DNS/Message;Lorg/xbill/DNS/RRset;II)V
     127: aload_3
     128: ifnull        148
     131: aload_3
     132: aload         12
     134: aload         4
     136: iload         7
     138: invokevirtual #147                // Method org/xbill/DNS/TSIG.apply:(Lorg/xbill/DNS/Message;Lorg/xbill/DNS/TSIGRecord;Z)V
     141: aload         12
     143: invokevirtual #148                // Method org/xbill/DNS/Message.getTSIG:()Lorg/xbill/DNS/TSIGRecord;
     146: astore        4
     148: iconst_0
     149: istore        7
     151: aload         12
     153: invokevirtual #149                // Method org/xbill/DNS/Message.toWire:()[B
     156: astore        14
     158: aload         8
     160: aload         14
     162: arraylength
     163: invokevirtual #150                // Method java/io/DataOutputStream.writeShort:(I)V
     166: aload         8
     168: aload         14
     170: invokevirtual #151                // Method java/io/DataOutputStream.write:([B)V
     173: goto          60
     176: goto          189
     179: astore        8
     181: getstatic     #18                 // Field java/lang/System.out:Ljava/io/PrintStream;
     184: ldc           #153                // String AXFR failed
     186: invokevirtual #20                 // Method java/io/PrintStream.println:(Ljava/lang/String;)V
     189: aload         5
     191: invokevirtual #154                // Method java/net/Socket.close:()V
     194: goto          199
     197: astore        8
     199: aconst_null
     200: areturn
    Exception table:
       from    to  target type
          30   176   179   Class java/io/IOException
         189   194   197   Class java/io/IOException

  byte[] generateReply(org.xbill.DNS.Message, byte[], java.net.Socket);
    Code:
       0: iconst_0
       1: istore        6
       3: aload_1
       4: invokevirtual #119                // Method org/xbill/DNS/Message.getHeader:()Lorg/xbill/DNS/Header;
       7: astore        4
       9: aload         4
      11: iconst_0
      12: invokevirtual #155                // Method org/xbill/DNS/Header.getFlag:(I)Z
      15: ifeq          20
      18: aconst_null
      19: areturn
      20: aload         4
      22: invokevirtual #156                // Method org/xbill/DNS/Header.getRcode:()I
      25: ifeq          35
      28: aload_0
      29: aload_1
      30: iconst_1
      31: invokevirtual #139                // Method errorMessage:(Lorg/xbill/DNS/Message;I)[B
      34: areturn
      35: aload         4
      37: invokevirtual #157                // Method org/xbill/DNS/Header.getOpcode:()I
      40: ifeq          50
      43: aload_0
      44: aload_1
      45: iconst_4
      46: invokevirtual #139                // Method errorMessage:(Lorg/xbill/DNS/Message;I)[B
      49: areturn
      50: aload_1
      51: invokevirtual #158                // Method org/xbill/DNS/Message.getQuestion:()Lorg/xbill/DNS/Record;
      54: astore        7
      56: aload_1
      57: invokevirtual #148                // Method org/xbill/DNS/Message.getTSIG:()Lorg/xbill/DNS/TSIGRecord;
      60: astore        8
      62: aconst_null
      63: astore        9
      65: aload         8
      67: ifnull        111
      70: aload_0
      71: getfield      #25                 // Field TSIGs:Ljava/util/Map;
      74: aload         8
      76: invokevirtual #159                // Method org/xbill/DNS/TSIGRecord.getName:()Lorg/xbill/DNS/Name;
      79: invokeinterface #78,  2           // InterfaceMethod java/util/Map.get:(Ljava/lang/Object;)Ljava/lang/Object;
      84: checkcast     #74                 // class org/xbill/DNS/TSIG
      87: astore        9
      89: aload         9
      91: ifnull        105
      94: aload         9
      96: aload_1
      97: aload_2
      98: aconst_null
      99: invokevirtual #160                // Method org/xbill/DNS/TSIG.verify:(Lorg/xbill/DNS/Message;[BLorg/xbill/DNS/TSIGRecord;)I
     102: ifeq          111
     105: aload_0
     106: aload_2
     107: invokevirtual #161                // Method formerrMessage:([B)[B
     110: areturn
     111: aload_1
     112: invokevirtual #162                // Method org/xbill/DNS/Message.getOPT:()Lorg/xbill/DNS/OPTRecord;
     115: astore        10
     117: aload_3
     118: ifnull        128
     121: ldc           #163                // int 65535
     123: istore        5
     125: goto          154
     128: aload         10
     130: ifnull        149
     133: aload         10
     135: invokevirtual #164                // Method org/xbill/DNS/OPTRecord.getPayloadSize:()I
     138: sipush        512
     141: invokestatic  #165                // Method java/lang/Math.max:(II)I
     144: istore        5
     146: goto          154
     149: sipush        512
     152: istore        5
     154: aload         10
     156: ifnull        173
     159: aload         10
     161: invokevirtual #166                // Method org/xbill/DNS/OPTRecord.getFlags:()I
     164: ldc           #168                // int 32768
     166: iand
     167: ifeq          173
     170: iconst_1
     171: istore        6
     173: new           #145                // class org/xbill/DNS/Message
     176: dup
     177: aload_1
     178: invokevirtual #119                // Method org/xbill/DNS/Message.getHeader:()Lorg/xbill/DNS/Header;
     181: invokevirtual #143                // Method org/xbill/DNS/Header.getID:()I
     184: invokespecial #146                // Method org/xbill/DNS/Message."<init>":(I)V
     187: astore        11
     189: aload         11
     191: invokevirtual #119                // Method org/xbill/DNS/Message.getHeader:()Lorg/xbill/DNS/Header;
     194: iconst_0
     195: invokevirtual #123                // Method org/xbill/DNS/Header.setFlag:(I)V
     198: aload_1
     199: invokevirtual #119                // Method org/xbill/DNS/Message.getHeader:()Lorg/xbill/DNS/Header;
     202: bipush        7
     204: invokevirtual #155                // Method org/xbill/DNS/Header.getFlag:(I)Z
     207: ifeq          220
     210: aload         11
     212: invokevirtual #119                // Method org/xbill/DNS/Message.getHeader:()Lorg/xbill/DNS/Header;
     215: bipush        7
     217: invokevirtual #123                // Method org/xbill/DNS/Header.setFlag:(I)V
     220: aload         11
     222: aload         7
     224: iconst_0
     225: invokevirtual #97                 // Method org/xbill/DNS/Message.addRecord:(Lorg/xbill/DNS/Record;I)V
     228: aload         7
     230: invokevirtual #94                 // Method org/xbill/DNS/Record.getName:()Lorg/xbill/DNS/Name;
     233: astore        12
     235: aload         7
     237: invokevirtual #169                // Method org/xbill/DNS/Record.getType:()I
     240: istore        13
     242: aload         7
     244: invokevirtual #170                // Method org/xbill/DNS/Record.getDClass:()I
     247: istore        14
     249: iload         13
     251: sipush        252
     254: if_icmpne     274
     257: aload_3
     258: ifnull        274
     261: aload_0
     262: aload         12
     264: aload_1
     265: aload         9
     267: aload         8
     269: aload_3
     270: invokevirtual #171                // Method doAXFR:(Lorg/xbill/DNS/Name;Lorg/xbill/DNS/Message;Lorg/xbill/DNS/TSIG;Lorg/xbill/DNS/TSIGRecord;Ljava/net/Socket;)[B
     273: areturn
     274: iload         13
     276: invokestatic  #172                // Method org/xbill/DNS/Type.isRR:(I)Z
     279: ifne          297
     282: iload         13
     284: sipush        255
     287: if_icmpeq     297
     290: aload_0
     291: aload_1
     292: iconst_4
     293: invokevirtual #139                // Method errorMessage:(Lorg/xbill/DNS/Message;I)[B
     296: areturn
     297: aload_0
     298: aload         11
     300: aload         12
     302: iload         13
     304: iload         14
     306: iconst_0
     307: iload         6
     309: invokevirtual #129                // Method addAnswer:(Lorg/xbill/DNS/Message;Lorg/xbill/DNS/Name;IIII)B
     312: istore        15
     314: iload         15
     316: ifeq          333
     319: iload         15
     321: iconst_3
     322: if_icmpeq     333
     325: aload_0
     326: aload_1
     327: iload         15
     329: invokevirtual #139                // Method errorMessage:(Lorg/xbill/DNS/Message;I)[B
     332: areturn
     333: aload_0
     334: aload         11
     336: iload         6
     338: invokespecial #173                // Method addAdditional:(Lorg/xbill/DNS/Message;I)V
     341: aload         10
     343: ifnull        385
     346: iload         6
     348: iconst_1
     349: if_icmpne     357
     352: ldc           #168                // int 32768
     354: goto          358
     357: iconst_0
     358: istore        16
     360: new           #174                // class org/xbill/DNS/OPTRecord
     363: dup
     364: sipush        4096
     367: iload         15
     369: iconst_0
     370: iload         16
     372: invokespecial #175                // Method org/xbill/DNS/OPTRecord."<init>":(IIII)V
     375: astore        17
     377: aload         11
     379: aload         17
     381: iconst_3
     382: invokevirtual #97                 // Method org/xbill/DNS/Message.addRecord:(Lorg/xbill/DNS/Record;I)V
     385: aload         11
     387: aload         9
     389: iconst_0
     390: aload         8
     392: invokevirtual #176                // Method org/xbill/DNS/Message.setTSIG:(Lorg/xbill/DNS/TSIG;ILorg/xbill/DNS/TSIGRecord;)V
     395: aload         11
     397: iload         5
     399: invokevirtual #177                // Method org/xbill/DNS/Message.toWire:(I)[B
     402: areturn

  byte[] buildErrorMessage(org.xbill.DNS.Header, int, org.xbill.DNS.Record);
    Code:
       0: new           #145                // class org/xbill/DNS/Message
       3: dup
       4: invokespecial #178                // Method org/xbill/DNS/Message."<init>":()V
       7: astore        4
       9: aload         4
      11: aload_1
      12: invokevirtual #179                // Method org/xbill/DNS/Message.setHeader:(Lorg/xbill/DNS/Header;)V
      15: iconst_0
      16: istore        5
      18: iload         5
      20: iconst_4
      21: if_icmpge     37
      24: aload         4
      26: iload         5
      28: invokevirtual #180                // Method org/xbill/DNS/Message.removeAllRecords:(I)V
      31: iinc          5, 1
      34: goto          18
      37: iload_2
      38: iconst_2
      39: if_icmpne     49
      42: aload         4
      44: aload_3
      45: iconst_0
      46: invokevirtual #97                 // Method org/xbill/DNS/Message.addRecord:(Lorg/xbill/DNS/Record;I)V
      49: aload_1
      50: iload_2
      51: invokevirtual #120                // Method org/xbill/DNS/Header.setRcode:(I)V
      54: aload         4
      56: invokevirtual #149                // Method org/xbill/DNS/Message.toWire:()[B
      59: areturn

  public byte[] formerrMessage(byte[]);
    Code:
       0: new           #181                // class org/xbill/DNS/Header
       3: dup
       4: aload_1
       5: invokespecial #182                // Method org/xbill/DNS/Header."<init>":([B)V
       8: astore_2
       9: goto          15
      12: astore_3
      13: aconst_null
      14: areturn
      15: aload_0
      16: aload_2
      17: iconst_1
      18: aconst_null
      19: invokevirtual #183                // Method buildErrorMessage:(Lorg/xbill/DNS/Header;ILorg/xbill/DNS/Record;)[B
      22: areturn
    Exception table:
       from    to  target type
           0     9    12   Class java/io/IOException

  public byte[] errorMessage(org.xbill.DNS.Message, int);
    Code:
       0: aload_0
       1: aload_1
       2: invokevirtual #119                // Method org/xbill/DNS/Message.getHeader:()Lorg/xbill/DNS/Header;
       5: iload_2
       6: aload_1
       7: invokevirtual #158                // Method org/xbill/DNS/Message.getQuestion:()Lorg/xbill/DNS/Record;
      10: invokevirtual #183                // Method buildErrorMessage:(Lorg/xbill/DNS/Header;ILorg/xbill/DNS/Record;)[B
      13: areturn

  public void TCPclient(java.net.Socket);
    Code:
       0: aload_1
       1: invokevirtual #184                // Method java/net/Socket.getInputStream:()Ljava/io/InputStream;
       4: astore_2
       5: aconst_null
       6: astore_3
       7: new           #185                // class java/io/DataInputStream
      10: dup
      11: aload_2
      12: invokespecial #186                // Method java/io/DataInputStream."<init>":(Ljava/io/InputStream;)V
      15: astore        5
      17: aload         5
      19: invokevirtual #187                // Method java/io/DataInputStream.readUnsignedShort:()I
      22: istore        4
      24: iload         4
      26: newarray       byte
      28: astore        7
      30: aload         5
      32: aload         7
      34: invokevirtual #188                // Method java/io/DataInputStream.readFully:([B)V
      37: new           #145                // class org/xbill/DNS/Message
      40: dup
      41: aload         7
      43: invokespecial #189                // Method org/xbill/DNS/Message."<init>":([B)V
      46: astore        8
      48: aload_0
      49: aload         8
      51: aload         7
      53: aload_1
      54: invokevirtual #190                // Method generateReply:(Lorg/xbill/DNS/Message;[BLjava/net/Socket;)[B
      57: astore        9
      59: aload         9
      61: ifnonnull     95
      64: aload_2
      65: ifnull        94
      68: aload_3
      69: ifnull        90
      72: aload_2
      73: invokevirtual #191                // Method java/io/InputStream.close:()V
      76: goto          94
      79: astore        10
      81: aload_3
      82: aload         10
      84: invokevirtual #193                // Method java/lang/Throwable.addSuppressed:(Ljava/lang/Throwable;)V
      87: goto          94
      90: aload_2
      91: invokevirtual #191                // Method java/io/InputStream.close:()V
      94: return
      95: goto          108
      98: astore        10
     100: aload_0
     101: aload         7
     103: invokevirtual #161                // Method formerrMessage:([B)[B
     106: astore        9
     108: new           #140                // class java/io/DataOutputStream
     111: dup
     112: aload_1
     113: invokevirtual #141                // Method java/net/Socket.getOutputStream:()Ljava/io/OutputStream;
     116: invokespecial #142                // Method java/io/DataOutputStream."<init>":(Ljava/io/OutputStream;)V
     119: astore        6
     121: aload         6
     123: aload         9
     125: arraylength
     126: invokevirtual #150                // Method java/io/DataOutputStream.writeShort:(I)V
     129: aload         6
     131: aload         9
     133: invokevirtual #151                // Method java/io/DataOutputStream.write:([B)V
     136: aload_2
     137: ifnull        212
     140: aload_3
     141: ifnull        162
     144: aload_2
     145: invokevirtual #191                // Method java/io/InputStream.close:()V
     148: goto          212
     151: astore        4
     153: aload_3
     154: aload         4
     156: invokevirtual #193                // Method java/lang/Throwable.addSuppressed:(Ljava/lang/Throwable;)V
     159: goto          212
     162: aload_2
     163: invokevirtual #191                // Method java/io/InputStream.close:()V
     166: goto          212
     169: astore        4
     171: aload         4
     173: astore_3
     174: aload         4
     176: athrow
     177: astore        11
     179: aload_2
     180: ifnull        209
     183: aload_3
     184: ifnull        205
     187: aload_2
     188: invokevirtual #191                // Method java/io/InputStream.close:()V
     191: goto          209
     194: astore        12
     196: aload_3
     197: aload         12
     199: invokevirtual #193                // Method java/lang/Throwable.addSuppressed:(Ljava/lang/Throwable;)V
     202: goto          209
     205: aload_2
     206: invokevirtual #191                // Method java/io/InputStream.close:()V
     209: aload         11
     211: athrow
     212: goto          260
     215: astore_2
     216: getstatic     #18                 // Field java/lang/System.out:Ljava/io/PrintStream;
     219: new           #1                  // class java/lang/StringBuilder
     222: dup
     223: invokespecial #2                  // Method java/lang/StringBuilder."<init>":()V
     226: ldc           #194                // String TCPclient(
     228: invokevirtual #4                  // Method java/lang/StringBuilder.append:(Ljava/lang/String;)Ljava/lang/StringBuilder;
     231: aload_1
     232: invokevirtual #195                // Method java/net/Socket.getLocalAddress:()Ljava/net/InetAddress;
     235: aload_1
     236: invokevirtual #196                // Method java/net/Socket.getLocalPort:()I
     239: invokestatic  #65                 // Method addrport:(Ljava/net/InetAddress;I)Ljava/lang/String;
     242: invokevirtual #4                  // Method java/lang/StringBuilder.append:(Ljava/lang/String;)Ljava/lang/StringBuilder;
     245: ldc           #197                // String ):
     247: invokevirtual #4                  // Method java/lang/StringBuilder.append:(Ljava/lang/String;)Ljava/lang/StringBuilder;
     250: aload_2
     251: invokevirtual #198                // Method java/lang/StringBuilder.append:(Ljava/lang/Object;)Ljava/lang/StringBuilder;
     254: invokevirtual #7                  // Method java/lang/StringBuilder.toString:()Ljava/lang/String;
     257: invokevirtual #20                 // Method java/io/PrintStream.println:(Ljava/lang/String;)V
     260: return
    Exception table:
       from    to  target type
          72    76    79   Class java/lang/Throwable
          37    64    98   Class java/io/IOException
         144   148   151   Class java/lang/Throwable
           7    64   169   Class java/lang/Throwable
          95   136   169   Class java/lang/Throwable
           7    64   177   any
          95   136   177   any
         187   191   194   Class java/lang/Throwable
         169   179   177   any
           0    94   215   Class java/io/IOException
          95   212   215   Class java/io/IOException

  public void serveTCP(java.net.InetAddress, int);
    Code:
       0: new           #199                // class java/net/ServerSocket
       3: dup
       4: iload_2
       5: sipush        128
       8: aload_1
       9: invokespecial #200                // Method java/net/ServerSocket."<init>":(IILjava/net/InetAddress;)V
      12: astore_3
      13: aconst_null
      14: astore        4
      16: aload_3
      17: invokevirtual #201                // Method java/net/ServerSocket.accept:()Ljava/net/Socket;
      20: astore        5
      22: new           #202                // class java/lang/Thread
      25: dup
      26: aload_0
      27: aload         5
      29: invokedynamic #203,  0            // InvokeDynamic #1:run:(Lorg/xbill/DNS/tools/jnamed;Ljava/net/Socket;)Ljava/lang/Runnable;
      34: invokespecial #204                // Method java/lang/Thread."<init>":(Ljava/lang/Runnable;)V
      37: astore        6
      39: aload         6
      41: invokevirtual #205                // Method java/lang/Thread.start:()V
      44: goto          16
      47: astore        5
      49: aload         5
      51: astore        4
      53: aload         5
      55: athrow
      56: astore        7
      58: aload_3
      59: ifnull        90
      62: aload         4
      64: ifnull        86
      67: aload_3
      68: invokevirtual #206                // Method java/net/ServerSocket.close:()V
      71: goto          90
      74: astore        8
      76: aload         4
      78: aload         8
      80: invokevirtual #193                // Method java/lang/Throwable.addSuppressed:(Ljava/lang/Throwable;)V
      83: goto          90
      86: aload_3
      87: invokevirtual #206                // Method java/net/ServerSocket.close:()V
      90: aload         7
      92: athrow
      93: astore_3
      94: getstatic     #18                 // Field java/lang/System.out:Ljava/io/PrintStream;
      97: new           #1                  // class java/lang/StringBuilder
     100: dup
     101: invokespecial #2                  // Method java/lang/StringBuilder."<init>":()V
     104: ldc           #207                // String serveTCP(
     106: invokevirtual #4                  // Method java/lang/StringBuilder.append:(Ljava/lang/String;)Ljava/lang/StringBuilder;
     109: aload_1
     110: iload_2
     111: invokestatic  #65                 // Method addrport:(Ljava/net/InetAddress;I)Ljava/lang/String;
     114: invokevirtual #4                  // Method java/lang/StringBuilder.append:(Ljava/lang/String;)Ljava/lang/StringBuilder;
     117: ldc           #197                // String ):
     119: invokevirtual #4                  // Method java/lang/StringBuilder.append:(Ljava/lang/String;)Ljava/lang/StringBuilder;
     122: aload_3
     123: invokevirtual #198                // Method java/lang/StringBuilder.append:(Ljava/lang/Object;)Ljava/lang/StringBuilder;
     126: invokevirtual #7                  // Method java/lang/StringBuilder.toString:()Ljava/lang/String;
     129: invokevirtual #20                 // Method java/io/PrintStream.println:(Ljava/lang/String;)V
     132: return
    Exception table:
       from    to  target type
          16    47    47   Class java/lang/Throwable
          67    71    74   Class java/lang/Throwable
          16    58    56   any
           0    93    93   Class java/io/IOException

  public void serveUDP(java.net.InetAddress, int);
    Code:
       0: new           #208                // class java/net/DatagramSocket
       3: dup
       4: iload_2
       5: aload_1
       6: invokespecial #209                // Method java/net/DatagramSocket."<init>":(ILjava/net/InetAddress;)V
       9: astore_3
      10: aconst_null
      11: astore        4
      13: sipush        512
      16: istore        5
      18: sipush        512
      21: newarray       byte
      23: astore        6
      25: new           #210                // class java/net/DatagramPacket
      28: dup
      29: aload         6
      31: aload         6
      33: arraylength
      34: invokespecial #211                // Method java/net/DatagramPacket."<init>":([BI)V
      37: astore        7
      39: aconst_null
      40: astore        8
      42: aload         7
      44: aload         6
      46: arraylength
      47: invokevirtual #212                // Method java/net/DatagramPacket.setLength:(I)V
      50: aload_3
      51: aload         7
      53: invokevirtual #213                // Method java/net/DatagramSocket.receive:(Ljava/net/DatagramPacket;)V
      56: goto          64
      59: astore        9
      61: goto          42
      64: new           #145                // class org/xbill/DNS/Message
      67: dup
      68: aload         6
      70: invokespecial #189                // Method org/xbill/DNS/Message."<init>":([B)V
      73: astore        9
      75: aload_0
      76: aload         9
      78: aload         6
      80: aconst_null
      81: invokevirtual #190                // Method generateReply:(Lorg/xbill/DNS/Message;[BLjava/net/Socket;)[B
      84: astore        10
      86: aload         10
      88: ifnonnull     94
      91: goto          42
      94: goto          107
      97: astore        11
      99: aload_0
     100: aload         6
     102: invokevirtual #161                // Method formerrMessage:([B)[B
     105: astore        10
     107: aload         8
     109: ifnonnull     139
     112: new           #210                // class java/net/DatagramPacket
     115: dup
     116: aload         10
     118: aload         10
     120: arraylength
     121: aload         7
     123: invokevirtual #215                // Method java/net/DatagramPacket.getAddress:()Ljava/net/InetAddress;
     126: aload         7
     128: invokevirtual #216                // Method java/net/DatagramPacket.getPort:()I
     131: invokespecial #217                // Method java/net/DatagramPacket."<init>":([BILjava/net/InetAddress;I)V
     134: astore        8
     136: goto          174
     139: aload         8
     141: aload         10
     143: invokevirtual #218                // Method java/net/DatagramPacket.setData:([B)V
     146: aload         8
     148: aload         10
     150: arraylength
     151: invokevirtual #212                // Method java/net/DatagramPacket.setLength:(I)V
     154: aload         8
     156: aload         7
     158: invokevirtual #215                // Method java/net/DatagramPacket.getAddress:()Ljava/net/InetAddress;
     161: invokevirtual #219                // Method java/net/DatagramPacket.setAddress:(Ljava/net/InetAddress;)V
     164: aload         8
     166: aload         7
     168: invokevirtual #216                // Method java/net/DatagramPacket.getPort:()I
     171: invokevirtual #220                // Method java/net/DatagramPacket.setPort:(I)V
     174: aload_3
     175: aload         8
     177: invokevirtual #221                // Method java/net/DatagramSocket.send:(Ljava/net/DatagramPacket;)V
     180: goto          42
     183: astore        5
     185: aload         5
     187: astore        4
     189: aload         5
     191: athrow
     192: astore        12
     194: aload_3
     195: ifnull        226
     198: aload         4
     200: ifnull        222
     203: aload_3
     204: invokevirtual #222                // Method java/net/DatagramSocket.close:()V
     207: goto          226
     210: astore        13
     212: aload         4
     214: aload         13
     216: invokevirtual #193                // Method java/lang/Throwable.addSuppressed:(Ljava/lang/Throwable;)V
     219: goto          226
     222: aload_3
     223: invokevirtual #222                // Method java/net/DatagramSocket.close:()V
     226: aload         12
     228: athrow
     229: astore_3
     230: getstatic     #18                 // Field java/lang/System.out:Ljava/io/PrintStream;
     233: new           #1                  // class java/lang/StringBuilder
     236: dup
     237: invokespecial #2                  // Method java/lang/StringBuilder."<init>":()V
     240: ldc           #223                // String serveUDP(
     242: invokevirtual #4                  // Method java/lang/StringBuilder.append:(Ljava/lang/String;)Ljava/lang/StringBuilder;
     245: aload_1
     246: iload_2
     247: invokestatic  #65                 // Method addrport:(Ljava/net/InetAddress;I)Ljava/lang/String;
     250: invokevirtual #4                  // Method java/lang/StringBuilder.append:(Ljava/lang/String;)Ljava/lang/StringBuilder;
     253: ldc           #197                // String ):
     255: invokevirtual #4                  // Method java/lang/StringBuilder.append:(Ljava/lang/String;)Ljava/lang/StringBuilder;
     258: aload_3
     259: invokevirtual #198                // Method java/lang/StringBuilder.append:(Ljava/lang/Object;)Ljava/lang/StringBuilder;
     262: invokevirtual #7                  // Method java/lang/StringBuilder.toString:()Ljava/lang/String;
     265: invokevirtual #20                 // Method java/io/PrintStream.println:(Ljava/lang/String;)V
     268: return
    Exception table:
       from    to  target type
          50    56    59   Class java/io/InterruptedIOException
          64    91    97   Class java/io/IOException
          13   183   183   Class java/lang/Throwable
         203   207   210   Class java/lang/Throwable
          13   194   192   any
           0   229   229   Class java/io/IOException

  public void addTCP(java.net.InetAddress, int);
    Code:
       0: new           #202                // class java/lang/Thread
       3: dup
       4: aload_0
       5: aload_1
       6: iload_2
       7: invokedynamic #224,  0            // InvokeDynamic #2:run:(Lorg/xbill/DNS/tools/jnamed;Ljava/net/InetAddress;I)Ljava/lang/Runnable;
      12: invokespecial #204                // Method java/lang/Thread."<init>":(Ljava/lang/Runnable;)V
      15: astore_3
      16: aload_3
      17: invokevirtual #205                // Method java/lang/Thread.start:()V
      20: return

  public void addUDP(java.net.InetAddress, int);
    Code:
       0: new           #202                // class java/lang/Thread
       3: dup
       4: aload_0
       5: aload_1
       6: iload_2
       7: invokedynamic #225,  0            // InvokeDynamic #3:run:(Lorg/xbill/DNS/tools/jnamed;Ljava/net/InetAddress;I)Ljava/lang/Runnable;
      12: invokespecial #204                // Method java/lang/Thread."<init>":(Ljava/lang/Runnable;)V
      15: astore_3
      16: aload_3
      17: invokevirtual #205                // Method java/lang/Thread.start:()V
      20: return

  public static void main(java.lang.String[]);
    Code:
       0: aload_0
       1: arraylength
       2: iconst_1
       3: if_icmple     18
       6: getstatic     #18                 // Field java/lang/System.out:Ljava/io/PrintStream;
       9: ldc           #226                // String usage: jnamed [conf]
      11: invokevirtual #20                 // Method java/io/PrintStream.println:(Ljava/lang/String;)V
      14: iconst_0
      15: invokestatic  #227                // Method java/lang/System.exit:(I)V
      18: aload_0
      19: arraylength
      20: iconst_1
      21: if_icmpne     31
      24: aload_0
      25: iconst_0
      26: aaload
      27: astore_1
      28: goto          34
      31: ldc           #228                // String jnamed.conf
      33: astore_1
      34: new           #91                 // class org/xbill/DNS/tools/jnamed
      37: dup
      38: aload_1
      39: invokespecial #229                // Method "<init>":(Ljava/lang/String;)V
      42: pop
      43: goto          54
      46: astore_1
      47: getstatic     #18                 // Field java/lang/System.out:Ljava/io/PrintStream;
      50: aload_1
      51: invokevirtual #231                // Method java/io/PrintStream.println:(Ljava/lang/Object;)V
      54: return
    Exception table:
       from    to  target type
          18    43    46   Class java/io/IOException
          18    43    46   Class org/xbill/DNS/ZoneTransferException

  private void lambda$addUDP$2(java.net.InetAddress, int);
    Code:
       0: aload_0
       1: aload_1
       2: iload_2
       3: invokevirtual #232                // Method serveUDP:(Ljava/net/InetAddress;I)V
       6: return

  private void lambda$addTCP$1(java.net.InetAddress, int);
    Code:
       0: aload_0
       1: aload_1
       2: iload_2
       3: invokevirtual #233                // Method serveTCP:(Ljava/net/InetAddress;I)V
       6: return

  private void lambda$serveTCP$0(java.net.Socket);
    Code:
       0: aload_0
       1: aload_1
       2: invokevirtual #234                // Method TCPclient:(Ljava/net/Socket;)V
       5: return
}
