Compiled from "ActivitySchedulingOptions.java"
public class com.amazonaws.services.simpleworkflow.flow.ActivitySchedulingOptions {
  private java.lang.Long heartbeatTimeoutSeconds;

  private java.lang.Long scheduleToCloseTimeoutSeconds;

  private java.lang.Long scheduleToStartTimeoutSeconds;

  private java.lang.Long startToCloseTimeoutSeconds;

  private java.lang.String taskList;

  private java.lang.Integer taskPriority;

  public com.amazonaws.services.simpleworkflow.flow.ActivitySchedulingOptions();
    Code:
       0: aload_0
       1: invokespecial #17                 // Method java/lang/Object."<init>":()V
       4: return

  public java.lang.Long getHeartbeatTimeoutSeconds();
    Code:
       0: aload_0
       1: getfield      #26                 // Field heartbeatTimeoutSeconds:Ljava/lang/Long;
       4: areturn

  public void setHeartbeatTimeoutSeconds(java.lang.Long);
    Code:
       0: aload_0
       1: aload_1
       2: putfield      #26                 // Field heartbeatTimeoutSeconds:Ljava/lang/Long;
       5: return

  public com.amazonaws.services.simpleworkflow.flow.ActivitySchedulingOptions withHeartbeatTimeoutSeconds(java.lang.Long);
    Code:
       0: aload_0
       1: aload_1
       2: putfield      #26                 // Field heartbeatTimeoutSeconds:Ljava/lang/Long;
       5: aload_0
       6: areturn

  public java.lang.Long getScheduleToCloseTimeoutSeconds();
    Code:
       0: aload_0
       1: getfield      #33                 // Field scheduleToCloseTimeoutSeconds:Ljava/lang/Long;
       4: areturn

  public void setScheduleToCloseTimeoutSeconds(java.lang.Long);
    Code:
       0: aload_0
       1: aload_1
       2: putfield      #33                 // Field scheduleToCloseTimeoutSeconds:Ljava/lang/Long;
       5: return

  public com.amazonaws.services.simpleworkflow.flow.ActivitySchedulingOptions withScheduleToCloseTimeoutSeconds(java.lang.Long);
    Code:
       0: aload_0
       1: aload_1
       2: putfield      #33                 // Field scheduleToCloseTimeoutSeconds:Ljava/lang/Long;
       5: aload_0
       6: areturn

  public java.lang.Long getScheduleToStartTimeoutSeconds();
    Code:
       0: aload_0
       1: getfield      #38                 // Field scheduleToStartTimeoutSeconds:Ljava/lang/Long;
       4: areturn

  public void setScheduleToStartTimeoutSeconds(java.lang.Long);
    Code:
       0: aload_0
       1: aload_1
       2: putfield      #38                 // Field scheduleToStartTimeoutSeconds:Ljava/lang/Long;
       5: return

  public com.amazonaws.services.simpleworkflow.flow.ActivitySchedulingOptions withScheduleToStartTimeoutSeconds(java.lang.Long);
    Code:
       0: aload_0
       1: aload_1
       2: putfield      #38                 // Field scheduleToStartTimeoutSeconds:Ljava/lang/Long;
       5: aload_0
       6: areturn

  public java.lang.Long getStartToCloseTimeoutSeconds();
    Code:
       0: aload_0
       1: getfield      #43                 // Field startToCloseTimeoutSeconds:Ljava/lang/Long;
       4: areturn

  public void setStartToCloseTimeoutSeconds(java.lang.Long);
    Code:
       0: aload_0
       1: aload_1
       2: putfield      #43                 // Field startToCloseTimeoutSeconds:Ljava/lang/Long;
       5: return

  public com.amazonaws.services.simpleworkflow.flow.ActivitySchedulingOptions withStartToCloseTimeoutSeconds(java.lang.Long);
    Code:
       0: aload_0
       1: aload_1
       2: putfield      #43                 // Field startToCloseTimeoutSeconds:Ljava/lang/Long;
       5: aload_0
       6: areturn

  public java.lang.String getTaskList();
    Code:
       0: aload_0
       1: getfield      #49                 // Field taskList:Ljava/lang/String;
       4: areturn

  public void setTaskList(java.lang.String);
    Code:
       0: aload_0
       1: aload_1
       2: putfield      #49                 // Field taskList:Ljava/lang/String;
       5: return

  public com.amazonaws.services.simpleworkflow.flow.ActivitySchedulingOptions withTaskList(java.lang.String);
    Code:
       0: aload_0
       1: aload_1
       2: putfield      #49                 // Field taskList:Ljava/lang/String;
       5: aload_0
       6: areturn

  public java.lang.Integer getTaskPriority();
    Code:
       0: aload_0
       1: getfield      #57                 // Field taskPriority:Ljava/lang/Integer;
       4: areturn

  public void setTaskPriority(java.lang.Integer);
    Code:
       0: aload_0
       1: aload_1
       2: putfield      #57                 // Field taskPriority:Ljava/lang/Integer;
       5: return

  public com.amazonaws.services.simpleworkflow.flow.ActivitySchedulingOptions withTaskPriority(java.lang.Integer);
    Code:
       0: aload_0
       1: aload_1
       2: putfield      #57                 // Field taskPriority:Ljava/lang/Integer;
       5: aload_0
       6: areturn
}
