Compiled from "LambdaFunctionException.java"
public class com.amazonaws.services.simpleworkflow.flow.LambdaFunctionException extends com.amazonaws.services.simpleworkflow.flow.DecisionException {
  private java.lang.String functionName;

  private java.lang.String functionId;

  public com.amazonaws.services.simpleworkflow.flow.LambdaFunctionException(java.lang.String);
    Code:
       0: aload_0
       1: aload_1
       2: invokespecial #12                 // Method com/amazonaws/services/simpleworkflow/flow/DecisionException."<init>":(Ljava/lang/String;)V
       5: return

  public com.amazonaws.services.simpleworkflow.flow.LambdaFunctionException(java.lang.String, java.lang.Throwable);
    Code:
       0: aload_0
       1: aload_1
       2: aload_2
       3: invokespecial #20                 // Method com/amazonaws/services/simpleworkflow/flow/DecisionException."<init>":(Ljava/lang/String;Ljava/lang/Throwable;)V
       6: return

  public com.amazonaws.services.simpleworkflow.flow.LambdaFunctionException(java.lang.String, long, java.lang.String, java.lang.String);
    Code:
       0: aload_0
       1: new           #25                 // class java/lang/StringBuilder
       4: dup
       5: aload_1
       6: invokestatic  #27                 // Method java/lang/String.valueOf:(Ljava/lang/Object;)Ljava/lang/String;
       9: invokespecial #33                 // Method java/lang/StringBuilder."<init>":(Ljava/lang/String;)V
      12: ldc           #34                 // String  for functionId=\"
      14: invokevirtual #36                 // Method java/lang/StringBuilder.append:(Ljava/lang/String;)Ljava/lang/StringBuilder;
      17: aload         5
      19: invokevirtual #36                 // Method java/lang/StringBuilder.append:(Ljava/lang/String;)Ljava/lang/StringBuilder;
      22: ldc           #40                 // String \" of functionName=
      24: invokevirtual #36                 // Method java/lang/StringBuilder.append:(Ljava/lang/String;)Ljava/lang/StringBuilder;
      27: aload         4
      29: invokevirtual #36                 // Method java/lang/StringBuilder.append:(Ljava/lang/String;)Ljava/lang/StringBuilder;
      32: invokevirtual #42                 // Method java/lang/StringBuilder.toString:()Ljava/lang/String;
      35: lload_2
      36: invokespecial #46                 // Method com/amazonaws/services/simpleworkflow/flow/DecisionException."<init>":(Ljava/lang/String;J)V
      39: aload_0
      40: aload         4
      42: putfield      #49                 // Field functionName:Ljava/lang/String;
      45: aload_0
      46: aload         5
      48: putfield      #51                 // Field functionId:Ljava/lang/String;
      51: return

  public java.lang.String getFunctionName();
    Code:
       0: aload_0
       1: getfield      #49                 // Field functionName:Ljava/lang/String;
       4: areturn

  public void setFunctionName(java.lang.String);
    Code:
       0: aload_0
       1: aload_1
       2: putfield      #49                 // Field functionName:Ljava/lang/String;
       5: return

  public java.lang.String getFunctionId();
    Code:
       0: aload_0
       1: getfield      #51                 // Field functionId:Ljava/lang/String;
       4: areturn

  public void setFunctionId(java.lang.String);
    Code:
       0: aload_0
       1: aload_1
       2: putfield      #51                 // Field functionId:Ljava/lang/String;
       5: return
}
