Compiled from "Delete.java"
public class org.hibernate.sql.Delete {
  private java.lang.String tableName;

  private java.lang.String versionColumnName;

  private java.lang.String where;

  private java.util.Map primaryKeyColumns;

  private java.lang.String comment;

  public org.hibernate.sql.Delete();
    Code:
       0: aload_0
       1: invokespecial #1                  // Method java/lang/Object."<init>":()V
       4: aload_0
       5: new           #2                  // class java/util/LinkedHashMap
       8: dup
       9: invokespecial #3                  // Method java/util/LinkedHashMap."<init>":()V
      12: putfield      #4                  // Field primaryKeyColumns:Ljava/util/Map;
      15: return

  public org.hibernate.sql.Delete setComment(java.lang.String);
    Code:
       0: aload_0
       1: aload_1
       2: putfield      #5                  // Field comment:Ljava/lang/String;
       5: aload_0
       6: areturn

  public org.hibernate.sql.Delete setTableName(java.lang.String);
    Code:
       0: aload_0
       1: aload_1
       2: putfield      #6                  // Field tableName:Ljava/lang/String;
       5: aload_0
       6: areturn

  public java.lang.String toStatementString();
    Code:
       0: new           #7                  // class java/lang/StringBuilder
       3: dup
       4: aload_0
       5: getfield      #6                  // Field tableName:Ljava/lang/String;
       8: invokevirtual #8                  // Method java/lang/String.length:()I
      11: bipush        10
      13: iadd
      14: invokespecial #9                  // Method java/lang/StringBuilder."<init>":(I)V
      17: astore_1
      18: aload_0
      19: getfield      #5                  // Field comment:Ljava/lang/String;
      22: ifnull        44
      25: aload_1
      26: ldc           #10                 // String /*
      28: invokevirtual #11                 // Method java/lang/StringBuilder.append:(Ljava/lang/String;)Ljava/lang/StringBuilder;
      31: aload_0
      32: getfield      #5                  // Field comment:Ljava/lang/String;
      35: invokevirtual #11                 // Method java/lang/StringBuilder.append:(Ljava/lang/String;)Ljava/lang/StringBuilder;
      38: ldc           #12                 // String  */
      40: invokevirtual #11                 // Method java/lang/StringBuilder.append:(Ljava/lang/String;)Ljava/lang/StringBuilder;
      43: pop
      44: aload_1
      45: ldc           #13                 // String delete from
      47: invokevirtual #11                 // Method java/lang/StringBuilder.append:(Ljava/lang/String;)Ljava/lang/StringBuilder;
      50: aload_0
      51: getfield      #6                  // Field tableName:Ljava/lang/String;
      54: invokevirtual #11                 // Method java/lang/StringBuilder.append:(Ljava/lang/String;)Ljava/lang/StringBuilder;
      57: pop
      58: aload_0
      59: getfield      #14                 // Field where:Ljava/lang/String;
      62: ifnonnull     84
      65: aload_0
      66: getfield      #4                  // Field primaryKeyColumns:Ljava/util/Map;
      69: invokeinterface #15,  1           // InterfaceMethod java/util/Map.isEmpty:()Z
      74: ifeq          84
      77: aload_0
      78: getfield      #16                 // Field versionColumnName:Ljava/lang/String;
      81: ifnull        91
      84: aload_1
      85: ldc           #17                 // String  where
      87: invokevirtual #11                 // Method java/lang/StringBuilder.append:(Ljava/lang/String;)Ljava/lang/StringBuilder;
      90: pop
      91: iconst_0
      92: istore_2
      93: aload_0
      94: getfield      #4                  // Field primaryKeyColumns:Ljava/util/Map;
      97: invokeinterface #18,  1           // InterfaceMethod java/util/Map.entrySet:()Ljava/util/Set;
     102: invokeinterface #19,  1           // InterfaceMethod java/util/Set.iterator:()Ljava/util/Iterator;
     107: astore_3
     108: aload_3
     109: invokeinterface #20,  1           // InterfaceMethod java/util/Iterator.hasNext:()Z
     114: ifeq          176
     117: aload_3
     118: invokeinterface #21,  1           // InterfaceMethod java/util/Iterator.next:()Ljava/lang/Object;
     123: checkcast     #22                 // class java/util/Map$Entry
     126: astore        4
     128: aload_1
     129: aload         4
     131: invokeinterface #23,  1           // InterfaceMethod java/util/Map$Entry.getKey:()Ljava/lang/Object;
     136: invokevirtual #24                 // Method java/lang/StringBuilder.append:(Ljava/lang/Object;)Ljava/lang/StringBuilder;
     139: bipush        61
     141: invokevirtual #25                 // Method java/lang/StringBuilder.append:(C)Ljava/lang/StringBuilder;
     144: aload         4
     146: invokeinterface #26,  1           // InterfaceMethod java/util/Map$Entry.getValue:()Ljava/lang/Object;
     151: invokevirtual #24                 // Method java/lang/StringBuilder.append:(Ljava/lang/Object;)Ljava/lang/StringBuilder;
     154: pop
     155: aload_3
     156: invokeinterface #20,  1           // InterfaceMethod java/util/Iterator.hasNext:()Z
     161: ifeq          171
     164: aload_1
     165: ldc           #27                 // String  and
     167: invokevirtual #11                 // Method java/lang/StringBuilder.append:(Ljava/lang/String;)Ljava/lang/StringBuilder;
     170: pop
     171: iconst_1
     172: istore_2
     173: goto          108
     176: aload_0
     177: getfield      #14                 // Field where:Ljava/lang/String;
     180: ifnull        205
     183: iload_2
     184: ifeq          194
     187: aload_1
     188: ldc           #27                 // String  and
     190: invokevirtual #11                 // Method java/lang/StringBuilder.append:(Ljava/lang/String;)Ljava/lang/StringBuilder;
     193: pop
     194: aload_1
     195: aload_0
     196: getfield      #14                 // Field where:Ljava/lang/String;
     199: invokevirtual #11                 // Method java/lang/StringBuilder.append:(Ljava/lang/String;)Ljava/lang/StringBuilder;
     202: pop
     203: iconst_1
     204: istore_2
     205: aload_0
     206: getfield      #16                 // Field versionColumnName:Ljava/lang/String;
     209: ifnull        237
     212: iload_2
     213: ifeq          223
     216: aload_1
     217: ldc           #27                 // String  and
     219: invokevirtual #11                 // Method java/lang/StringBuilder.append:(Ljava/lang/String;)Ljava/lang/StringBuilder;
     222: pop
     223: aload_1
     224: aload_0
     225: getfield      #16                 // Field versionColumnName:Ljava/lang/String;
     228: invokevirtual #11                 // Method java/lang/StringBuilder.append:(Ljava/lang/String;)Ljava/lang/StringBuilder;
     231: ldc           #28                 // String =?
     233: invokevirtual #11                 // Method java/lang/StringBuilder.append:(Ljava/lang/String;)Ljava/lang/StringBuilder;
     236: pop
     237: aload_1
     238: invokevirtual #29                 // Method java/lang/StringBuilder.toString:()Ljava/lang/String;
     241: areturn

  public org.hibernate.sql.Delete setWhere(java.lang.String);
    Code:
       0: aload_0
       1: aload_1
       2: putfield      #14                 // Field where:Ljava/lang/String;
       5: aload_0
       6: areturn

  public org.hibernate.sql.Delete addWhereFragment(java.lang.String);
    Code:
       0: aload_0
       1: getfield      #14                 // Field where:Ljava/lang/String;
       4: ifnonnull     15
       7: aload_0
       8: aload_1
       9: putfield      #14                 // Field where:Ljava/lang/String;
      12: goto          45
      15: new           #7                  // class java/lang/StringBuilder
      18: dup
      19: invokespecial #30                 // Method java/lang/StringBuilder."<init>":()V
      22: aload_0
      23: dup_x1
      24: getfield      #14                 // Field where:Ljava/lang/String;
      27: invokevirtual #11                 // Method java/lang/StringBuilder.append:(Ljava/lang/String;)Ljava/lang/StringBuilder;
      30: ldc           #27                 // String  and
      32: invokevirtual #11                 // Method java/lang/StringBuilder.append:(Ljava/lang/String;)Ljava/lang/StringBuilder;
      35: aload_1
      36: invokevirtual #11                 // Method java/lang/StringBuilder.append:(Ljava/lang/String;)Ljava/lang/StringBuilder;
      39: invokevirtual #29                 // Method java/lang/StringBuilder.toString:()Ljava/lang/String;
      42: putfield      #14                 // Field where:Ljava/lang/String;
      45: aload_0
      46: areturn

  public org.hibernate.sql.Delete setPrimaryKeyColumnNames(java.lang.String[]);
    Code:
       0: aload_0
       1: getfield      #4                  // Field primaryKeyColumns:Ljava/util/Map;
       4: invokeinterface #31,  1           // InterfaceMethod java/util/Map.clear:()V
       9: aload_0
      10: aload_1
      11: invokevirtual #32                 // Method addPrimaryKeyColumns:([Ljava/lang/String;)Lorg/hibernate/sql/Delete;
      14: pop
      15: aload_0
      16: areturn

  public org.hibernate.sql.Delete addPrimaryKeyColumns(java.lang.String[]);
    Code:
       0: aload_1
       1: astore_2
       2: aload_2
       3: arraylength
       4: istore_3
       5: iconst_0
       6: istore        4
       8: iload         4
      10: iload_3
      11: if_icmpge     35
      14: aload_2
      15: iload         4
      17: aaload
      18: astore        5
      20: aload_0
      21: aload         5
      23: ldc           #33                 // String ?
      25: invokevirtual #34                 // Method addPrimaryKeyColumn:(Ljava/lang/String;Ljava/lang/String;)Lorg/hibernate/sql/Delete;
      28: pop
      29: iinc          4, 1
      32: goto          8
      35: aload_0
      36: areturn

  public org.hibernate.sql.Delete addPrimaryKeyColumns(java.lang.String[], boolean[], java.lang.String[]);
    Code:
       0: iconst_0
       1: istore        4
       3: iload         4
       5: aload_1
       6: arraylength
       7: if_icmpge     36
      10: aload_2
      11: iload         4
      13: baload
      14: ifeq          30
      17: aload_0
      18: aload_1
      19: iload         4
      21: aaload
      22: aload_3
      23: iload         4
      25: aaload
      26: invokevirtual #34                 // Method addPrimaryKeyColumn:(Ljava/lang/String;Ljava/lang/String;)Lorg/hibernate/sql/Delete;
      29: pop
      30: iinc          4, 1
      33: goto          3
      36: aload_0
      37: areturn

  public org.hibernate.sql.Delete addPrimaryKeyColumns(java.lang.String[], java.lang.String[]);
    Code:
       0: iconst_0
       1: istore_3
       2: iload_3
       3: aload_1
       4: arraylength
       5: if_icmpge     25
       8: aload_0
       9: aload_1
      10: iload_3
      11: aaload
      12: aload_2
      13: iload_3
      14: aaload
      15: invokevirtual #34                 // Method addPrimaryKeyColumn:(Ljava/lang/String;Ljava/lang/String;)Lorg/hibernate/sql/Delete;
      18: pop
      19: iinc          3, 1
      22: goto          2
      25: aload_0
      26: areturn

  public org.hibernate.sql.Delete addPrimaryKeyColumn(java.lang.String, java.lang.String);
    Code:
       0: aload_0
       1: getfield      #4                  // Field primaryKeyColumns:Ljava/util/Map;
       4: aload_1
       5: aload_2
       6: invokeinterface #35,  3           // InterfaceMethod java/util/Map.put:(Ljava/lang/Object;Ljava/lang/Object;)Ljava/lang/Object;
      11: pop
      12: aload_0
      13: areturn

  public org.hibernate.sql.Delete setVersionColumnName(java.lang.String);
    Code:
       0: aload_0
       1: aload_1
       2: putfield      #16                 // Field versionColumnName:Ljava/lang/String;
       5: aload_0
       6: areturn
}
