Compiled from "SamlServiceProperties.java"
public final class org.springframework.security.cas.SamlServiceProperties extends org.springframework.security.cas.ServiceProperties {
  public static final java.lang.String DEFAULT_SAML_ARTIFACT_PARAMETER;

  public static final java.lang.String DEFAULT_SAML_SERVICE_PARAMETER;

  public org.springframework.security.cas.SamlServiceProperties();
    Code:
       0: aload_0
       1: invokespecial #1                  // Method org/springframework/security/cas/ServiceProperties."<init>":()V
       4: aload_0
       5: ldc           #3                  // String SAMLart
       7: invokespecial #4                  // Method org/springframework/security/cas/ServiceProperties.setArtifactParameter:(Ljava/lang/String;)V
      10: aload_0
      11: ldc           #5                  // String TARGET
      13: invokespecial #6                  // Method org/springframework/security/cas/ServiceProperties.setServiceParameter:(Ljava/lang/String;)V
      16: return
}
