Compiled from "ZManaged.scala"
public final class zio.managed.ZManaged$ServiceWithManagedPartiallyApplied<Service> {
  private final boolean dummy;

  public static <Service> boolean $lessinit$greater$default$1();
    Code:
       0: getstatic     #26                 // Field zio/managed/ZManaged$ServiceWithManagedPartiallyApplied$.MODULE$:Lzio/managed/ZManaged$ServiceWithManagedPartiallyApplied$;
       3: invokevirtual #28                 // Method zio/managed/ZManaged$ServiceWithManagedPartiallyApplied$.$lessinit$greater$default$1:()Z
       6: ireturn

  public static <R extends Service, E, A, Service> zio.managed.ZManaged<R, E, A> apply$extension(boolean, scala.Function1<Service, zio.managed.ZManaged<R, E, A>>, zio.package$Tag<Service>, java.lang.Object);
    Code:
       0: getstatic     #26                 // Field zio/managed/ZManaged$ServiceWithManagedPartiallyApplied$.MODULE$:Lzio/managed/ZManaged$ServiceWithManagedPartiallyApplied$;
       3: iload_0
       4: aload_1
       5: aload_2
       6: aload_3
       7: invokevirtual #33                 // Method zio/managed/ZManaged$ServiceWithManagedPartiallyApplied$.apply$extension:(ZLscala/Function1;Lzio/package$Tag;Ljava/lang/Object;)Lzio/managed/ZManaged;
      10: areturn

  public static <Service> boolean equals$extension(boolean, java.lang.Object);
    Code:
       0: getstatic     #26                 // Field zio/managed/ZManaged$ServiceWithManagedPartiallyApplied$.MODULE$:Lzio/managed/ZManaged$ServiceWithManagedPartiallyApplied$;
       3: iload_0
       4: aload_1
       5: invokevirtual #38                 // Method zio/managed/ZManaged$ServiceWithManagedPartiallyApplied$.equals$extension:(ZLjava/lang/Object;)Z
       8: ireturn

  public static <Service> int hashCode$extension(boolean);
    Code:
       0: getstatic     #26                 // Field zio/managed/ZManaged$ServiceWithManagedPartiallyApplied$.MODULE$:Lzio/managed/ZManaged$ServiceWithManagedPartiallyApplied$;
       3: iload_0
       4: invokevirtual #43                 // Method zio/managed/ZManaged$ServiceWithManagedPartiallyApplied$.hashCode$extension:(Z)I
       7: ireturn

  public zio.managed.ZManaged$ServiceWithManagedPartiallyApplied(boolean);
    Code:
       0: aload_0
       1: iload_1
       2: putfield      #47                 // Field dummy:Z
       5: aload_0
       6: invokespecial #50                 // Method java/lang/Object."<init>":()V
       9: return

  public int hashCode();
    Code:
       0: getstatic     #26                 // Field zio/managed/ZManaged$ServiceWithManagedPartiallyApplied$.MODULE$:Lzio/managed/ZManaged$ServiceWithManagedPartiallyApplied$;
       3: aload_0
       4: invokevirtual #57                 // Method zio$managed$ZManaged$ServiceWithManagedPartiallyApplied$$dummy:()Z
       7: invokevirtual #43                 // Method zio/managed/ZManaged$ServiceWithManagedPartiallyApplied$.hashCode$extension:(Z)I
      10: ireturn

  public boolean equals(java.lang.Object);
    Code:
       0: getstatic     #26                 // Field zio/managed/ZManaged$ServiceWithManagedPartiallyApplied$.MODULE$:Lzio/managed/ZManaged$ServiceWithManagedPartiallyApplied$;
       3: aload_0
       4: invokevirtual #57                 // Method zio$managed$ZManaged$ServiceWithManagedPartiallyApplied$$dummy:()Z
       7: aload_1
       8: invokevirtual #38                 // Method zio/managed/ZManaged$ServiceWithManagedPartiallyApplied$.equals$extension:(ZLjava/lang/Object;)Z
      11: ireturn

  public boolean zio$managed$ZManaged$ServiceWithManagedPartiallyApplied$$dummy();
    Code:
       0: aload_0
       1: getfield      #47                 // Field dummy:Z
       4: ireturn

  public <R extends Service, E, A> zio.managed.ZManaged<R, E, A> apply(scala.Function1<Service, zio.managed.ZManaged<R, E, A>>, zio.package$Tag<Service>, java.lang.Object);
    Code:
       0: getstatic     #26                 // Field zio/managed/ZManaged$ServiceWithManagedPartiallyApplied$.MODULE$:Lzio/managed/ZManaged$ServiceWithManagedPartiallyApplied$;
       3: aload_0
       4: invokevirtual #57                 // Method zio$managed$ZManaged$ServiceWithManagedPartiallyApplied$$dummy:()Z
       7: aload_1
       8: aload_2
       9: aload_3
      10: invokevirtual #33                 // Method zio/managed/ZManaged$ServiceWithManagedPartiallyApplied$.apply$extension:(ZLscala/Function1;Lzio/package$Tag;Ljava/lang/Object;)Lzio/managed/ZManaged;
      13: areturn
}
