Compiled from "ZManagedCompatPlatformSpecific.scala"
public interface zio.managed.ZManagedCompatPlatformSpecific {
  public static zio.managed.ZManagedCompatPlatformSpecific$ZManagedZStreamCompanionPlatformSpecificSyntax ZManagedZStreamCompanionPlatformSpecificSyntax$(zio.managed.ZManagedCompatPlatformSpecific, zio.stream.ZStream$);
    Code:
       0: aload_0
       1: aload_1
       2: invokespecial #15                 // InterfaceMethod ZManagedZStreamCompanionPlatformSpecificSyntax:(Lzio/stream/ZStream$;)Lzio/managed/ZManagedCompatPlatformSpecific$ZManagedZStreamCompanionPlatformSpecificSyntax;
       5: areturn

  public default zio.managed.ZManagedCompatPlatformSpecific$ZManagedZStreamCompanionPlatformSpecificSyntax ZManagedZStreamCompanionPlatformSpecificSyntax(zio.stream.ZStream$);
    Code:
       0: new           #7                  // class zio/managed/ZManagedCompatPlatformSpecific$ZManagedZStreamCompanionPlatformSpecificSyntax
       3: dup
       4: aload_0
       5: aload_1
       6: invokespecial #21                 // Method zio/managed/ZManagedCompatPlatformSpecific$ZManagedZStreamCompanionPlatformSpecificSyntax."<init>":(Lzio/managed/ZManagedCompatPlatformSpecific;Lzio/stream/ZStream$;)V
       9: areturn

  public static zio.ZIO zio$managed$ZManagedCompatPlatformSpecific$ZManagedZStreamCompanionPlatformSpecificSyntax$$_$asyncManaged$$anonfun$1(scala.Function1, java.lang.Object, scala.Function1);
    Code:
       0: aload_0
       1: aload_2
       2: invokeinterface #33,  2           // InterfaceMethod scala/Function1.apply:(Ljava/lang/Object;)Ljava/lang/Object;
       7: checkcast     #35                 // class zio/managed/ZManaged
      10: aload_1
      11: invokevirtual #39                 // Method zio/managed/ZManaged.scoped:(Ljava/lang/Object;)Lzio/ZIO;
      14: areturn
}
