Compiled from "CallerDataConverter.java"
public class ch.qos.logback.classic.pattern.CallerDataConverter extends ch.qos.logback.classic.pattern.ClassicConverter {
  public static final java.lang.String DEFAULT_CALLER_LINE_PREFIX;

  public static final java.lang.String DEFAULT_RANGE_DELIMITER;

  private int depthStart;

  private int depthEnd;

  java.util.List<ch.qos.logback.core.boolex.EventEvaluator<ch.qos.logback.classic.spi.ILoggingEvent>> evaluatorList;

  final int MAX_ERROR_COUNT;

  int errorCount;

  public ch.qos.logback.classic.pattern.CallerDataConverter();
    Code:
       0: aload_0
       1: invokespecial #1                  // Method ch/qos/logback/classic/pattern/ClassicConverter."<init>":()V
       4: aload_0
       5: iconst_0
       6: putfield      #2                  // Field depthStart:I
       9: aload_0
      10: iconst_5
      11: putfield      #3                  // Field depthEnd:I
      14: aload_0
      15: aconst_null
      16: putfield      #4                  // Field evaluatorList:Ljava/util/List;
      19: aload_0
      20: iconst_4
      21: putfield      #5                  // Field MAX_ERROR_COUNT:I
      24: aload_0
      25: iconst_0
      26: putfield      #6                  // Field errorCount:I
      29: return

  public void start();
    Code:
       0: aload_0
       1: invokevirtual #7                  // Method getFirstOption:()Ljava/lang/String;
       4: astore_1
       5: aload_1
       6: ifnonnull     10
       9: return
      10: aload_0
      11: aload_1
      12: invokespecial #8                  // Method isRange:(Ljava/lang/String;)Z
      15: ifeq          88
      18: aload_0
      19: aload_1
      20: invokespecial #9                  // Method splitRange:(Ljava/lang/String;)[Ljava/lang/String;
      23: astore_2
      24: aload_2
      25: arraylength
      26: iconst_2
      27: if_icmpne     57
      30: aload_0
      31: aload_2
      32: iconst_0
      33: aaload
      34: invokestatic  #10                 // Method java/lang/Integer.parseInt:(Ljava/lang/String;)I
      37: putfield      #2                  // Field depthStart:I
      40: aload_0
      41: aload_2
      42: iconst_1
      43: aaload
      44: invokestatic  #10                 // Method java/lang/Integer.parseInt:(Ljava/lang/String;)I
      47: putfield      #3                  // Field depthEnd:I
      50: aload_0
      51: invokespecial #11                 // Method checkRange:()V
      54: goto          85
      57: aload_0
      58: new           #12                 // class java/lang/StringBuilder
      61: dup
      62: invokespecial #13                 // Method java/lang/StringBuilder."<init>":()V
      65: ldc           #14                 // String Failed to parse depth option as range [
      67: invokevirtual #15                 // Method java/lang/StringBuilder.append:(Ljava/lang/String;)Ljava/lang/StringBuilder;
      70: aload_1
      71: invokevirtual #15                 // Method java/lang/StringBuilder.append:(Ljava/lang/String;)Ljava/lang/StringBuilder;
      74: ldc           #16                 // String ]
      76: invokevirtual #15                 // Method java/lang/StringBuilder.append:(Ljava/lang/String;)Ljava/lang/StringBuilder;
      79: invokevirtual #17                 // Method java/lang/StringBuilder.toString:()Ljava/lang/String;
      82: invokevirtual #18                 // Method addError:(Ljava/lang/String;)V
      85: goto          96
      88: aload_0
      89: aload_1
      90: invokestatic  #10                 // Method java/lang/Integer.parseInt:(Ljava/lang/String;)I
      93: putfield      #3                  // Field depthEnd:I
      96: goto          129
      99: astore_2
     100: aload_0
     101: new           #12                 // class java/lang/StringBuilder
     104: dup
     105: invokespecial #13                 // Method java/lang/StringBuilder."<init>":()V
     108: ldc           #20                 // String Failed to parse depth option [
     110: invokevirtual #15                 // Method java/lang/StringBuilder.append:(Ljava/lang/String;)Ljava/lang/StringBuilder;
     113: aload_1
     114: invokevirtual #15                 // Method java/lang/StringBuilder.append:(Ljava/lang/String;)Ljava/lang/StringBuilder;
     117: ldc           #16                 // String ]
     119: invokevirtual #15                 // Method java/lang/StringBuilder.append:(Ljava/lang/String;)Ljava/lang/StringBuilder;
     122: invokevirtual #17                 // Method java/lang/StringBuilder.toString:()Ljava/lang/String;
     125: aload_2
     126: invokevirtual #21                 // Method addError:(Ljava/lang/String;Ljava/lang/Throwable;)V
     129: aload_0
     130: invokevirtual #22                 // Method getOptionList:()Ljava/util/List;
     133: astore_2
     134: aload_2
     135: ifnull        233
     138: aload_2
     139: invokeinterface #23,  1           // InterfaceMethod java/util/List.size:()I
     144: iconst_1
     145: if_icmple     233
     148: aload_2
     149: invokeinterface #23,  1           // InterfaceMethod java/util/List.size:()I
     154: istore_3
     155: iconst_1
     156: istore        4
     158: iload         4
     160: iload_3
     161: if_icmpge     233
     164: aload_2
     165: iload         4
     167: invokeinterface #24,  2           // InterfaceMethod java/util/List.get:(I)Ljava/lang/Object;
     172: checkcast     #25                 // class java/lang/String
     175: astore        5
     177: aload_0
     178: invokevirtual #26                 // Method getContext:()Lch/qos/logback/core/Context;
     181: astore        6
     183: aload         6
     185: ifnull        227
     188: aload         6
     190: ldc           #27                 // String EVALUATOR_MAP
     192: invokeinterface #28,  2           // InterfaceMethod ch/qos/logback/core/Context.getObject:(Ljava/lang/String;)Ljava/lang/Object;
     197: checkcast     #29                 // class java/util/Map
     200: astore        7
     202: aload         7
     204: aload         5
     206: invokeinterface #30,  2           // InterfaceMethod java/util/Map.get:(Ljava/lang/Object;)Ljava/lang/Object;
     211: checkcast     #31                 // class ch/qos/logback/core/boolex/EventEvaluator
     214: astore        8
     216: aload         8
     218: ifnull        227
     221: aload_0
     222: aload         8
     224: invokespecial #32                 // Method addEvaluator:(Lch/qos/logback/core/boolex/EventEvaluator;)V
     227: iinc          4, 1
     230: goto          158
     233: return
    Exception table:
       from    to  target type
          10    96    99   Class java/lang/NumberFormatException

  private boolean isRange(java.lang.String);
    Code:
       0: aload_1
       1: aload_0
       2: invokevirtual #33                 // Method getDefaultRangeDelimiter:()Ljava/lang/String;
       5: invokevirtual #34                 // Method java/lang/String.contains:(Ljava/lang/CharSequence;)Z
       8: ireturn

  private java.lang.String[] splitRange(java.lang.String);
    Code:
       0: aload_1
       1: aload_0
       2: invokevirtual #33                 // Method getDefaultRangeDelimiter:()Ljava/lang/String;
       5: invokestatic  #35                 // Method java/util/regex/Pattern.quote:(Ljava/lang/String;)Ljava/lang/String;
       8: iconst_2
       9: invokevirtual #36                 // Method java/lang/String.split:(Ljava/lang/String;I)[Ljava/lang/String;
      12: areturn

  private void checkRange();
    Code:
       0: aload_0
       1: getfield      #2                  // Field depthStart:I
       4: iflt          14
       7: aload_0
       8: getfield      #3                  // Field depthEnd:I
      11: ifge          60
      14: aload_0
      15: new           #12                 // class java/lang/StringBuilder
      18: dup
      19: invokespecial #13                 // Method java/lang/StringBuilder."<init>":()V
      22: ldc           #37                 // String Invalid depthStart/depthEnd range [
      24: invokevirtual #15                 // Method java/lang/StringBuilder.append:(Ljava/lang/String;)Ljava/lang/StringBuilder;
      27: aload_0
      28: getfield      #2                  // Field depthStart:I
      31: invokevirtual #38                 // Method java/lang/StringBuilder.append:(I)Ljava/lang/StringBuilder;
      34: ldc           #39                 // String ,
      36: invokevirtual #15                 // Method java/lang/StringBuilder.append:(Ljava/lang/String;)Ljava/lang/StringBuilder;
      39: aload_0
      40: getfield      #3                  // Field depthEnd:I
      43: invokevirtual #38                 // Method java/lang/StringBuilder.append:(I)Ljava/lang/StringBuilder;
      46: ldc           #40                 // String ] (negative values are not allowed)
      48: invokevirtual #15                 // Method java/lang/StringBuilder.append:(Ljava/lang/String;)Ljava/lang/StringBuilder;
      51: invokevirtual #17                 // Method java/lang/StringBuilder.toString:()Ljava/lang/String;
      54: invokevirtual #18                 // Method addError:(Ljava/lang/String;)V
      57: goto          114
      60: aload_0
      61: getfield      #2                  // Field depthStart:I
      64: aload_0
      65: getfield      #3                  // Field depthEnd:I
      68: if_icmplt     114
      71: aload_0
      72: new           #12                 // class java/lang/StringBuilder
      75: dup
      76: invokespecial #13                 // Method java/lang/StringBuilder."<init>":()V
      79: ldc           #41                 // String Invalid depthEnd range [
      81: invokevirtual #15                 // Method java/lang/StringBuilder.append:(Ljava/lang/String;)Ljava/lang/StringBuilder;
      84: aload_0
      85: getfield      #2                  // Field depthStart:I
      88: invokevirtual #38                 // Method java/lang/StringBuilder.append:(I)Ljava/lang/StringBuilder;
      91: ldc           #39                 // String ,
      93: invokevirtual #15                 // Method java/lang/StringBuilder.append:(Ljava/lang/String;)Ljava/lang/StringBuilder;
      96: aload_0
      97: getfield      #3                  // Field depthEnd:I
     100: invokevirtual #38                 // Method java/lang/StringBuilder.append:(I)Ljava/lang/StringBuilder;
     103: ldc           #42                 // String ] (start greater or equal to end)
     105: invokevirtual #15                 // Method java/lang/StringBuilder.append:(Ljava/lang/String;)Ljava/lang/StringBuilder;
     108: invokevirtual #17                 // Method java/lang/StringBuilder.toString:()Ljava/lang/String;
     111: invokevirtual #18                 // Method addError:(Ljava/lang/String;)V
     114: return

  private void addEvaluator(ch.qos.logback.core.boolex.EventEvaluator<ch.qos.logback.classic.spi.ILoggingEvent>);
    Code:
       0: aload_0
       1: getfield      #4                  // Field evaluatorList:Ljava/util/List;
       4: ifnonnull     18
       7: aload_0
       8: new           #43                 // class java/util/ArrayList
      11: dup
      12: invokespecial #44                 // Method java/util/ArrayList."<init>":()V
      15: putfield      #4                  // Field evaluatorList:Ljava/util/List;
      18: aload_0
      19: getfield      #4                  // Field evaluatorList:Ljava/util/List;
      22: aload_1
      23: invokeinterface #45,  2           // InterfaceMethod java/util/List.add:(Ljava/lang/Object;)Z
      28: pop
      29: return

  public java.lang.String convert(ch.qos.logback.classic.spi.ILoggingEvent);
    Code:
       0: new           #12                 // class java/lang/StringBuilder
       3: dup
       4: invokespecial #13                 // Method java/lang/StringBuilder."<init>":()V
       7: astore_2
       8: aload_0
       9: getfield      #4                  // Field evaluatorList:Ljava/util/List;
      12: ifnull        212
      15: iconst_0
      16: istore_3
      17: iconst_0
      18: istore        4
      20: iload         4
      22: aload_0
      23: getfield      #4                  // Field evaluatorList:Ljava/util/List;
      26: invokeinterface #23,  1           // InterfaceMethod java/util/List.size:()I
      31: if_icmpge     205
      34: aload_0
      35: getfield      #4                  // Field evaluatorList:Ljava/util/List;
      38: iload         4
      40: invokeinterface #24,  2           // InterfaceMethod java/util/List.get:(I)Ljava/lang/Object;
      45: checkcast     #31                 // class ch/qos/logback/core/boolex/EventEvaluator
      48: astore        5
      50: aload         5
      52: aload_1
      53: invokeinterface #46,  2           // InterfaceMethod ch/qos/logback/core/boolex/EventEvaluator.evaluate:(Ljava/lang/Object;)Z
      58: ifeq          66
      61: iconst_1
      62: istore_3
      63: goto          205
      66: goto          199
      69: astore        6
      71: aload_0
      72: dup
      73: getfield      #6                  // Field errorCount:I
      76: iconst_1
      77: iadd
      78: putfield      #6                  // Field errorCount:I
      81: aload_0
      82: getfield      #6                  // Field errorCount:I
      85: iconst_4
      86: if_icmpge     128
      89: aload_0
      90: new           #12                 // class java/lang/StringBuilder
      93: dup
      94: invokespecial #13                 // Method java/lang/StringBuilder."<init>":()V
      97: ldc           #48                 // String Exception thrown for evaluator named [
      99: invokevirtual #15                 // Method java/lang/StringBuilder.append:(Ljava/lang/String;)Ljava/lang/StringBuilder;
     102: aload         5
     104: invokeinterface #49,  1           // InterfaceMethod ch/qos/logback/core/boolex/EventEvaluator.getName:()Ljava/lang/String;
     109: invokevirtual #15                 // Method java/lang/StringBuilder.append:(Ljava/lang/String;)Ljava/lang/StringBuilder;
     112: ldc           #16                 // String ]
     114: invokevirtual #15                 // Method java/lang/StringBuilder.append:(Ljava/lang/String;)Ljava/lang/StringBuilder;
     117: invokevirtual #17                 // Method java/lang/StringBuilder.toString:()Ljava/lang/String;
     120: aload         6
     122: invokevirtual #21                 // Method addError:(Ljava/lang/String;Ljava/lang/Throwable;)V
     125: goto          199
     128: aload_0
     129: getfield      #6                  // Field errorCount:I
     132: iconst_4
     133: if_icmpne     199
     136: new           #50                 // class ch/qos/logback/core/status/ErrorStatus
     139: dup
     140: new           #12                 // class java/lang/StringBuilder
     143: dup
     144: invokespecial #13                 // Method java/lang/StringBuilder."<init>":()V
     147: ldc           #48                 // String Exception thrown for evaluator named [
     149: invokevirtual #15                 // Method java/lang/StringBuilder.append:(Ljava/lang/String;)Ljava/lang/StringBuilder;
     152: aload         5
     154: invokeinterface #49,  1           // InterfaceMethod ch/qos/logback/core/boolex/EventEvaluator.getName:()Ljava/lang/String;
     159: invokevirtual #15                 // Method java/lang/StringBuilder.append:(Ljava/lang/String;)Ljava/lang/StringBuilder;
     162: ldc           #51                 // String ].
     164: invokevirtual #15                 // Method java/lang/StringBuilder.append:(Ljava/lang/String;)Ljava/lang/StringBuilder;
     167: invokevirtual #17                 // Method java/lang/StringBuilder.toString:()Ljava/lang/String;
     170: aload_0
     171: aload         6
     173: invokespecial #52                 // Method ch/qos/logback/core/status/ErrorStatus."<init>":(Ljava/lang/String;Ljava/lang/Object;Ljava/lang/Throwable;)V
     176: astore        7
     178: aload         7
     180: new           #50                 // class ch/qos/logback/core/status/ErrorStatus
     183: dup
     184: ldc           #53                 // String This was the last warning about this evaluator\'s errors.We don\'t want the StatusManager to get flooded.
     186: aload_0
     187: invokespecial #54                 // Method ch/qos/logback/core/status/ErrorStatus."<init>":(Ljava/lang/String;Ljava/lang/Object;)V
     190: invokevirtual #55                 // Method ch/qos/logback/core/status/ErrorStatus.add:(Lch/qos/logback/core/status/Status;)V
     193: aload_0
     194: aload         7
     196: invokevirtual #56                 // Method addStatus:(Lch/qos/logback/core/status/Status;)V
     199: iinc          4, 1
     202: goto          20
     205: iload_3
     206: ifne          212
     209: ldc           #57                 // String
     211: areturn
     212: aload_1
     213: invokeinterface #58,  1           // InterfaceMethod ch/qos/logback/classic/spi/ILoggingEvent.getCallerData:()[Ljava/lang/StackTraceElement;
     218: astore_3
     219: aload_3
     220: ifnull        316
     223: aload_3
     224: arraylength
     225: aload_0
     226: getfield      #2                  // Field depthStart:I
     229: if_icmple     316
     232: aload_0
     233: getfield      #3                  // Field depthEnd:I
     236: aload_3
     237: arraylength
     238: if_icmpge     248
     241: aload_0
     242: getfield      #3                  // Field depthEnd:I
     245: goto          250
     248: aload_3
     249: arraylength
     250: istore        4
     252: aload_0
     253: getfield      #2                  // Field depthStart:I
     256: istore        5
     258: iload         5
     260: iload         4
     262: if_icmpge     311
     265: aload_2
     266: aload_0
     267: invokevirtual #59                 // Method getCallerLinePrefix:()Ljava/lang/String;
     270: invokevirtual #15                 // Method java/lang/StringBuilder.append:(Ljava/lang/String;)Ljava/lang/StringBuilder;
     273: pop
     274: aload_2
     275: iload         5
     277: invokevirtual #38                 // Method java/lang/StringBuilder.append:(I)Ljava/lang/StringBuilder;
     280: pop
     281: aload_2
     282: ldc           #60                 // String \t at
     284: invokevirtual #15                 // Method java/lang/StringBuilder.append:(Ljava/lang/String;)Ljava/lang/StringBuilder;
     287: pop
     288: aload_2
     289: aload_3
     290: iload         5
     292: aaload
     293: invokevirtual #61                 // Method java/lang/StringBuilder.append:(Ljava/lang/Object;)Ljava/lang/StringBuilder;
     296: pop
     297: aload_2
     298: getstatic     #62                 // Field ch/qos/logback/core/CoreConstants.LINE_SEPARATOR:Ljava/lang/String;
     301: invokevirtual #15                 // Method java/lang/StringBuilder.append:(Ljava/lang/String;)Ljava/lang/StringBuilder;
     304: pop
     305: iinc          5, 1
     308: goto          258
     311: aload_2
     312: invokevirtual #17                 // Method java/lang/StringBuilder.toString:()Ljava/lang/String;
     315: areturn
     316: getstatic     #63                 // Field ch/qos/logback/classic/spi/CallerData.CALLER_DATA_NA:Ljava/lang/String;
     319: areturn
    Exception table:
       from    to  target type
          50    63    69   Class ch/qos/logback/core/boolex/EvaluationException

  protected java.lang.String getCallerLinePrefix();
    Code:
       0: ldc           #64                 // String Caller+
       2: areturn

  protected java.lang.String getDefaultRangeDelimiter();
    Code:
       0: ldc           #65                 // String ..
       2: areturn

  public java.lang.String convert(java.lang.Object);
    Code:
       0: aload_0
       1: aload_1
       2: checkcast     #66                 // class ch/qos/logback/classic/spi/ILoggingEvent
       5: invokevirtual #67                 // Method convert:(Lch/qos/logback/classic/spi/ILoggingEvent;)Ljava/lang/String;
       8: areturn
}
