Compiled from "TestType.java"
public final class de.tum.in.test.api.context.TestType extends java.lang.Enum<de.tum.in.test.api.context.TestType> {
  public static final de.tum.in.test.api.context.TestType PUBLIC;

  public static final de.tum.in.test.api.context.TestType HIDDEN;

  private static final de.tum.in.test.api.context.TestType[] $VALUES;

  public static de.tum.in.test.api.context.TestType[] values();
    Code:
       0: getstatic     #1                  // Field $VALUES:[Lde/tum/in/test/api/context/TestType;
       3: invokevirtual #2                  // Method "[Lde/tum/in/test/api/context/TestType;".clone:()Ljava/lang/Object;
       6: checkcast     #3                  // class "[Lde/tum/in/test/api/context/TestType;"
       9: areturn

  public static de.tum.in.test.api.context.TestType valueOf(java.lang.String);
    Code:
       0: ldc           #4                  // class de/tum/in/test/api/context/TestType
       2: aload_0
       3: invokestatic  #5                  // Method java/lang/Enum.valueOf:(Ljava/lang/Class;Ljava/lang/String;)Ljava/lang/Enum;
       6: checkcast     #4                  // class de/tum/in/test/api/context/TestType
       9: areturn

  private de.tum.in.test.api.context.TestType();
    Code:
       0: aload_0
       1: aload_1
       2: iload_2
       3: invokespecial #6                  // Method java/lang/Enum."<init>":(Ljava/lang/String;I)V
       6: return

  static {};
    Code:
       0: new           #4                  // class de/tum/in/test/api/context/TestType
       3: dup
       4: ldc           #7                  // String PUBLIC
       6: iconst_0
       7: invokespecial #8                  // Method "<init>":(Ljava/lang/String;I)V
      10: putstatic     #9                  // Field PUBLIC:Lde/tum/in/test/api/context/TestType;
      13: new           #4                  // class de/tum/in/test/api/context/TestType
      16: dup
      17: ldc           #10                 // String HIDDEN
      19: iconst_1
      20: invokespecial #8                  // Method "<init>":(Ljava/lang/String;I)V
      23: putstatic     #11                 // Field HIDDEN:Lde/tum/in/test/api/context/TestType;
      26: iconst_2
      27: anewarray     #4                  // class de/tum/in/test/api/context/TestType
      30: dup
      31: iconst_0
      32: getstatic     #9                  // Field PUBLIC:Lde/tum/in/test/api/context/TestType;
      35: aastore
      36: dup
      37: iconst_1
      38: getstatic     #11                 // Field HIDDEN:Lde/tum/in/test/api/context/TestType;
      41: aastore
      42: putstatic     #1                  // Field $VALUES:[Lde/tum/in/test/api/context/TestType;
      45: return
}
