Compiled from "Assembly.java"
public class coldsrc.coldlib.util.Assembly$Builder<I, T, O> {
  final java.lang.Class<I> intermediateType;

  final java.lang.Class<T> resultType;

  final java.lang.Class<O> optionsType;

  java.util.function.Supplier<O> defaultOptionsProvider;

  java.util.function.Function<I, T> finalizer;

  coldsrc.coldlib.util.Assembly$InstanceFactory<I, O> instanceFactory;

  java.util.List<coldsrc.coldlib.util.Assembly$Transformer<I, O>> intermediateTransformers;

  java.util.List<coldsrc.coldlib.util.Assembly$Transformer<T, O>> resultTransformers;

  coldsrc.coldlib.util.Assembly$Builder(java.lang.Class<I>, java.lang.Class<T>, java.lang.Class<O>);
    Code:
       0: aload_0
       1: invokespecial #1                  // Method java/lang/Object."<init>":()V
       4: aload_0
       5: new           #7                  // class java/util/ArrayList
       8: dup
       9: invokespecial #9                  // Method java/util/ArrayList."<init>":()V
      12: putfield      #10                 // Field intermediateTransformers:Ljava/util/List;
      15: aload_0
      16: new           #7                  // class java/util/ArrayList
      19: dup
      20: invokespecial #9                  // Method java/util/ArrayList."<init>":()V
      23: putfield      #16                 // Field resultTransformers:Ljava/util/List;
      26: aload_1
      27: ldc           #19                 // String Intermediate type can not be null
      29: invokestatic  #21                 // Method java/util/Objects.requireNonNull:(Ljava/lang/Object;Ljava/lang/String;)Ljava/lang/Object;
      32: pop
      33: aload_2
      34: ldc           #27                 // String Result type can not be null
      36: invokestatic  #21                 // Method java/util/Objects.requireNonNull:(Ljava/lang/Object;Ljava/lang/String;)Ljava/lang/Object;
      39: pop
      40: aload_3
      41: ifnonnull     47
      44: ldc           #2                  // class java/lang/Object
      46: astore_3
      47: aload_0
      48: aload_1
      49: putfield      #29                 // Field intermediateType:Ljava/lang/Class;
      52: aload_0
      53: aload_2
      54: putfield      #33                 // Field resultType:Ljava/lang/Class;
      57: aload_0
      58: aload_3
      59: putfield      #36                 // Field optionsType:Ljava/lang/Class;
      62: return

  public coldsrc.coldlib.util.Assembly<I, T, O> build();
    Code:
       0: new           #39                 // class coldsrc/coldlib/util/Assembly
       3: dup
       4: aload_0
       5: getfield      #29                 // Field intermediateType:Ljava/lang/Class;
       8: aload_0
       9: getfield      #33                 // Field resultType:Ljava/lang/Class;
      12: aload_0
      13: getfield      #36                 // Field optionsType:Ljava/lang/Class;
      16: aload_0
      17: getfield      #41                 // Field defaultOptionsProvider:Ljava/util/function/Supplier;
      20: aload_0
      21: getfield      #45                 // Field instanceFactory:Lcoldsrc/coldlib/util/Assembly$InstanceFactory;
      24: new           #49                 // class coldsrc/coldlib/util/Assembly$Line
      27: dup
      28: aload_0
      29: getfield      #10                 // Field intermediateTransformers:Ljava/util/List;
      32: invokespecial #51                 // Method coldsrc/coldlib/util/Assembly$Line."<init>":(Ljava/util/List;)V
      35: aload_0
      36: getfield      #54                 // Field finalizer:Ljava/util/function/Function;
      39: new           #49                 // class coldsrc/coldlib/util/Assembly$Line
      42: dup
      43: aload_0
      44: getfield      #16                 // Field resultTransformers:Ljava/util/List;
      47: invokespecial #51                 // Method coldsrc/coldlib/util/Assembly$Line."<init>":(Ljava/util/List;)V
      50: invokespecial #58                 // Method coldsrc/coldlib/util/Assembly."<init>":(Ljava/lang/Class;Ljava/lang/Class;Ljava/lang/Class;Ljava/util/function/Supplier;Lcoldsrc/coldlib/util/Assembly$InstanceFactory;Lcoldsrc/coldlib/util/Assembly$Line;Ljava/util/function/Function;Lcoldsrc/coldlib/util/Assembly$Line;)V
      53: areturn

  private <V> coldsrc.coldlib.util.Assembly$Transformer<V, O> makeTransformer(java.util.function.BiConsumer<V, O>);
    Code:
       0: aload_1
       1: invokedynamic #61,  0             // InvokeDynamic #0:transform:(Ljava/util/function/BiConsumer;)Lcoldsrc/coldlib/util/Assembly$Transformer;
       6: areturn

  public java.util.function.Supplier<O> getDefaultOptionsProvider();
    Code:
       0: aload_0
       1: getfield      #41                 // Field defaultOptionsProvider:Ljava/util/function/Supplier;
       4: areturn

  public coldsrc.coldlib.util.Assembly$Builder<I, T, O> setDefaultOptionsProvider(java.util.function.Supplier<O>);
    Code:
       0: aload_0
       1: aload_1
       2: putfield      #41                 // Field defaultOptionsProvider:Ljava/util/function/Supplier;
       5: aload_0
       6: areturn

  public coldsrc.coldlib.util.Assembly$Builder<I, T, O> setDefaultOptions(O);
    Code:
       0: aload_0
       1: aload_1
       2: invokedynamic #65,  0             // InvokeDynamic #1:get:(Ljava/lang/Object;)Ljava/util/function/Supplier;
       7: invokevirtual #69                 // Method setDefaultOptionsProvider:(Ljava/util/function/Supplier;)Lcoldsrc/coldlib/util/Assembly$Builder;
      10: areturn

  public java.util.function.Function<I, T> getFinalizer();
    Code:
       0: aload_0
       1: getfield      #54                 // Field finalizer:Ljava/util/function/Function;
       4: areturn

  public coldsrc.coldlib.util.Assembly$Builder<I, T, O> setFinalizer(java.util.function.Function<I, T>);
    Code:
       0: aload_0
       1: aload_1
       2: putfield      #54                 // Field finalizer:Ljava/util/function/Function;
       5: aload_0
       6: areturn

  public coldsrc.coldlib.util.Assembly$InstanceFactory<I, O> getInstanceFactory();
    Code:
       0: aload_0
       1: getfield      #45                 // Field instanceFactory:Lcoldsrc/coldlib/util/Assembly$InstanceFactory;
       4: areturn

  public coldsrc.coldlib.util.Assembly$Builder<I, T, O> setInstanceFactory(coldsrc.coldlib.util.Assembly$InstanceFactory<I, O>);
    Code:
       0: aload_0
       1: aload_1
       2: putfield      #45                 // Field instanceFactory:Lcoldsrc/coldlib/util/Assembly$InstanceFactory;
       5: aload_0
       6: areturn

  public java.util.List<coldsrc.coldlib.util.Assembly$Transformer<I, O>> getIntermediateTransformers();
    Code:
       0: aload_0
       1: getfield      #10                 // Field intermediateTransformers:Ljava/util/List;
       4: areturn

  public coldsrc.coldlib.util.Assembly$Builder<I, T, O> setIntermediateTransformers(java.util.List<coldsrc.coldlib.util.Assembly$Transformer<I, O>>);
    Code:
       0: aload_0
       1: aload_1
       2: putfield      #10                 // Field intermediateTransformers:Ljava/util/List;
       5: aload_0
       6: areturn

  public coldsrc.coldlib.util.Assembly$Builder<I, T, O> addIntermediateTransformer(coldsrc.coldlib.util.Assembly$Transformer<I, O>);
    Code:
       0: aload_0
       1: getfield      #10                 // Field intermediateTransformers:Ljava/util/List;
       4: aload_1
       5: invokeinterface #73,  2           // InterfaceMethod java/util/List.add:(Ljava/lang/Object;)Z
      10: pop
      11: aload_0
      12: areturn

  public coldsrc.coldlib.util.Assembly$Builder<I, T, O> addIntermediateConsumer(java.util.function.BiConsumer<I, O>);
    Code:
       0: aload_0
       1: aload_0
       2: aload_1
       3: invokevirtual #79                 // Method makeTransformer:(Ljava/util/function/BiConsumer;)Lcoldsrc/coldlib/util/Assembly$Transformer;
       6: invokevirtual #82                 // Method addIntermediateTransformer:(Lcoldsrc/coldlib/util/Assembly$Transformer;)Lcoldsrc/coldlib/util/Assembly$Builder;
       9: areturn

  public java.util.List<coldsrc.coldlib.util.Assembly$Transformer<T, O>> getResultTransformers();
    Code:
       0: aload_0
       1: getfield      #16                 // Field resultTransformers:Ljava/util/List;
       4: areturn

  public coldsrc.coldlib.util.Assembly$Builder<I, T, O> setResultTransformers(java.util.List<coldsrc.coldlib.util.Assembly$Transformer<T, O>>);
    Code:
       0: aload_0
       1: aload_1
       2: putfield      #16                 // Field resultTransformers:Ljava/util/List;
       5: aload_0
       6: areturn

  public coldsrc.coldlib.util.Assembly$Builder<I, T, O> addResultTransformer(coldsrc.coldlib.util.Assembly$Transformer<T, O>);
    Code:
       0: aload_0
       1: getfield      #16                 // Field resultTransformers:Ljava/util/List;
       4: aload_1
       5: invokeinterface #73,  2           // InterfaceMethod java/util/List.add:(Ljava/lang/Object;)Z
      10: pop
      11: aload_0
      12: areturn

  public coldsrc.coldlib.util.Assembly$Builder<I, T, O> addResultConsumer(java.util.function.BiConsumer<T, O>);
    Code:
       0: aload_0
       1: aload_0
       2: aload_1
       3: invokevirtual #79                 // Method makeTransformer:(Ljava/util/function/BiConsumer;)Lcoldsrc/coldlib/util/Assembly$Transformer;
       6: invokevirtual #86                 // Method addResultTransformer:(Lcoldsrc/coldlib/util/Assembly$Transformer;)Lcoldsrc/coldlib/util/Assembly$Builder;
       9: areturn

  private static java.lang.Object lambda$setDefaultOptions$1(java.lang.Object);
    Code:
       0: aload_0
       1: areturn

  private static java.lang.Object lambda$makeTransformer$0(java.util.function.BiConsumer, java.lang.Object, java.lang.Object);
    Code:
       0: aload_0
       1: aload_1
       2: aload_2
       3: invokeinterface #89,  3           // InterfaceMethod java/util/function/BiConsumer.accept:(Ljava/lang/Object;Ljava/lang/Object;)V
       8: aload_1
       9: areturn
}
