Compiled from "FrontEnd.java"
public class org.apache.cxf.tools.plugin.FrontEnd {
  protected org.apache.cxf.tools.plugin.Generators generators;

  protected org.apache.cxf.tools.plugin.Processor processor;

  protected org.apache.cxf.tools.plugin.Container container;

  protected org.apache.cxf.tools.plugin.Builder builder;

  protected java.lang.String name;

  protected java.lang.String _package;

  protected java.lang.String profile;

  public org.apache.cxf.tools.plugin.FrontEnd();
    Code:
       0: aload_0
       1: invokespecial #1                  // Method java/lang/Object."<init>":()V
       4: return

  public org.apache.cxf.tools.plugin.Generators getGenerators();
    Code:
       0: aload_0
       1: getfield      #2                  // Field generators:Lorg/apache/cxf/tools/plugin/Generators;
       4: areturn

  public void setGenerators(org.apache.cxf.tools.plugin.Generators);
    Code:
       0: aload_0
       1: aload_1
       2: putfield      #2                  // Field generators:Lorg/apache/cxf/tools/plugin/Generators;
       5: return

  public org.apache.cxf.tools.plugin.Processor getProcessor();
    Code:
       0: aload_0
       1: getfield      #3                  // Field processor:Lorg/apache/cxf/tools/plugin/Processor;
       4: areturn

  public void setProcessor(org.apache.cxf.tools.plugin.Processor);
    Code:
       0: aload_0
       1: aload_1
       2: putfield      #3                  // Field processor:Lorg/apache/cxf/tools/plugin/Processor;
       5: return

  public org.apache.cxf.tools.plugin.Container getContainer();
    Code:
       0: aload_0
       1: getfield      #4                  // Field container:Lorg/apache/cxf/tools/plugin/Container;
       4: areturn

  public void setContainer(org.apache.cxf.tools.plugin.Container);
    Code:
       0: aload_0
       1: aload_1
       2: putfield      #4                  // Field container:Lorg/apache/cxf/tools/plugin/Container;
       5: return

  public org.apache.cxf.tools.plugin.Builder getBuilder();
    Code:
       0: aload_0
       1: getfield      #5                  // Field builder:Lorg/apache/cxf/tools/plugin/Builder;
       4: areturn

  public void setBuilder(org.apache.cxf.tools.plugin.Builder);
    Code:
       0: aload_0
       1: aload_1
       2: putfield      #5                  // Field builder:Lorg/apache/cxf/tools/plugin/Builder;
       5: return

  public java.lang.String getName();
    Code:
       0: aload_0
       1: getfield      #6                  // Field name:Ljava/lang/String;
       4: areturn

  public void setName(java.lang.String);
    Code:
       0: aload_0
       1: aload_1
       2: putfield      #6                  // Field name:Ljava/lang/String;
       5: return

  public java.lang.String getPackage();
    Code:
       0: aload_0
       1: getfield      #7                  // Field _package:Ljava/lang/String;
       4: areturn

  public void setPackage(java.lang.String);
    Code:
       0: aload_0
       1: aload_1
       2: putfield      #7                  // Field _package:Ljava/lang/String;
       5: return

  public java.lang.String getProfile();
    Code:
       0: aload_0
       1: getfield      #8                  // Field profile:Ljava/lang/String;
       4: areturn

  public void setProfile(java.lang.String);
    Code:
       0: aload_0
       1: aload_1
       2: putfield      #8                  // Field profile:Ljava/lang/String;
       5: return
}
