Compiled from "LoadBalancingKMSClientProvider.java"
public class org.apache.hadoop.crypto.key.kms.LoadBalancingKMSClientProvider extends org.apache.hadoop.crypto.key.KeyProvider implements org.apache.hadoop.crypto.key.KeyProviderCryptoExtension$CryptoExtension,org.apache.hadoop.crypto.key.KeyProviderDelegationTokenExtension$DelegationTokenExtension {
  public static org.slf4j.Logger LOG;

  private final org.apache.hadoop.crypto.key.kms.KMSClientProvider[] providers;

  private final java.util.concurrent.atomic.AtomicInteger currentIdx;

  private final org.apache.hadoop.io.Text dtService;

  private final org.apache.hadoop.io.Text canonicalService;

  private org.apache.hadoop.io.retry.RetryPolicy retryPolicy;

  public org.apache.hadoop.crypto.key.kms.LoadBalancingKMSClientProvider(java.net.URI, org.apache.hadoop.crypto.key.kms.KMSClientProvider[], org.apache.hadoop.conf.Configuration);
    Code:
       0: aload_0
       1: aload_1
       2: aload_2
       3: invokestatic  #2                  // Method org/apache/hadoop/util/Time.monotonicNow:()J
       6: aload_3
       7: invokespecial #3                  // Method "<init>":(Ljava/net/URI;[Lorg/apache/hadoop/crypto/key/kms/KMSClientProvider;JLorg/apache/hadoop/conf/Configuration;)V
      10: return

  org.apache.hadoop.crypto.key.kms.LoadBalancingKMSClientProvider(org.apache.hadoop.crypto.key.kms.KMSClientProvider[], long, org.apache.hadoop.conf.Configuration);
    Code:
       0: aload_0
       1: ldc           #4                  // String kms://testing
       3: invokestatic  #5                  // Method java/net/URI.create:(Ljava/lang/String;)Ljava/net/URI;
       6: aload_1
       7: lload_2
       8: aload         4
      10: invokespecial #3                  // Method "<init>":(Ljava/net/URI;[Lorg/apache/hadoop/crypto/key/kms/KMSClientProvider;JLorg/apache/hadoop/conf/Configuration;)V
      13: return

  private org.apache.hadoop.crypto.key.kms.LoadBalancingKMSClientProvider(java.net.URI, org.apache.hadoop.crypto.key.kms.KMSClientProvider[], long, org.apache.hadoop.conf.Configuration);
    Code:
       0: aload_0
       1: aload         5
       3: invokespecial #6                  // Method org/apache/hadoop/crypto/key/KeyProvider."<init>":(Lorg/apache/hadoop/conf/Configuration;)V
       6: aload_0
       7: aconst_null
       8: putfield      #7                  // Field retryPolicy:Lorg/apache/hadoop/io/retry/RetryPolicy;
      11: aload_0
      12: aload_1
      13: invokestatic  #8                  // Method org/apache/hadoop/crypto/key/kms/KMSClientProvider.getDtService:(Ljava/net/URI;)Lorg/apache/hadoop/io/Text;
      16: putfield      #1                  // Field dtService:Lorg/apache/hadoop/io/Text;
      19: aload         5
      21: invokestatic  #9                  // Method org/apache/hadoop/util/KMSUtil.getKeyProviderUri:(Lorg/apache/hadoop/conf/Configuration;)Ljava/net/URI;
      24: ifnonnull     38
      27: aload_0
      28: aload_0
      29: getfield      #1                  // Field dtService:Lorg/apache/hadoop/io/Text;
      32: putfield      #10                 // Field canonicalService:Lorg/apache/hadoop/io/Text;
      35: goto          55
      38: aload_0
      39: new           #11                 // class org/apache/hadoop/io/Text
      42: dup
      43: aload_2
      44: iconst_0
      45: aaload
      46: invokevirtual #12                 // Method org/apache/hadoop/crypto/key/kms/KMSClientProvider.getCanonicalServiceName:()Ljava/lang/String;
      49: invokespecial #13                 // Method org/apache/hadoop/io/Text."<init>":(Ljava/lang/String;)V
      52: putfield      #10                 // Field canonicalService:Lorg/apache/hadoop/io/Text;
      55: aload_0
      56: lload_3
      57: lconst_0
      58: lcmp
      59: ifeq          69
      62: aload_2
      63: invokestatic  #14                 // Method shuffle:([Lorg/apache/hadoop/crypto/key/kms/KMSClientProvider;)[Lorg/apache/hadoop/crypto/key/kms/KMSClientProvider;
      66: goto          70
      69: aload_2
      70: putfield      #15                 // Field providers:[Lorg/apache/hadoop/crypto/key/kms/KMSClientProvider;
      73: aload_2
      74: astore        6
      76: aload         6
      78: arraylength
      79: istore        7
      81: iconst_0
      82: istore        8
      84: iload         8
      86: iload         7
      88: if_icmpge     110
      91: aload         6
      93: iload         8
      95: aaload
      96: astore        9
      98: aload         9
     100: aload_0
     101: invokevirtual #16                 // Method org/apache/hadoop/crypto/key/kms/KMSClientProvider.setClientTokenProvider:(Lorg/apache/hadoop/crypto/key/KeyProviderDelegationTokenExtension$DelegationTokenExtension;)V
     104: iinc          8, 1
     107: goto          84
     110: aload_0
     111: new           #17                 // class java/util/concurrent/atomic/AtomicInteger
     114: dup
     115: lload_3
     116: aload_2
     117: arraylength
     118: i2l
     119: lrem
     120: l2i
     121: invokespecial #18                 // Method java/util/concurrent/atomic/AtomicInteger."<init>":(I)V
     124: putfield      #19                 // Field currentIdx:Ljava/util/concurrent/atomic/AtomicInteger;
     127: aload         5
     129: ldc           #21                 // String hadoop.security.kms.client.failover.max.retries
     131: aload_2
     132: arraylength
     133: invokevirtual #22                 // Method org/apache/hadoop/conf/Configuration.getInt:(Ljava/lang/String;I)I
     136: istore        6
     138: aload         5
     140: ldc           #23                 // String hadoop.security.kms.client.failover.sleep.base.millis
     142: bipush        100
     144: invokevirtual #22                 // Method org/apache/hadoop/conf/Configuration.getInt:(Ljava/lang/String;I)I
     147: istore        7
     149: aload         5
     151: ldc           #24                 // String hadoop.security.kms.client.failover.sleep.max.millis
     153: sipush        2000
     156: invokevirtual #22                 // Method org/apache/hadoop/conf/Configuration.getInt:(Ljava/lang/String;I)I
     159: istore        8
     161: iload         6
     163: iflt          170
     166: iconst_1
     167: goto          171
     170: iconst_0
     171: invokestatic  #25                 // Method com/google/common/base/Preconditions.checkState:(Z)V
     174: iload         7
     176: iflt          183
     179: iconst_1
     180: goto          184
     183: iconst_0
     184: invokestatic  #25                 // Method com/google/common/base/Preconditions.checkState:(Z)V
     187: iload         8
     189: iflt          196
     192: iconst_1
     193: goto          197
     196: iconst_0
     197: invokestatic  #25                 // Method com/google/common/base/Preconditions.checkState:(Z)V
     200: aload_0
     201: getstatic     #26                 // Field org/apache/hadoop/io/retry/RetryPolicies.TRY_ONCE_THEN_FAIL:Lorg/apache/hadoop/io/retry/RetryPolicy;
     204: iload         6
     206: iconst_0
     207: iload         7
     209: i2l
     210: iload         8
     212: i2l
     213: invokestatic  #27                 // Method org/apache/hadoop/io/retry/RetryPolicies.failoverOnNetworkException:(Lorg/apache/hadoop/io/retry/RetryPolicy;IIJJ)Lorg/apache/hadoop/io/retry/RetryPolicy;
     216: putfield      #7                  // Field retryPolicy:Lorg/apache/hadoop/io/retry/RetryPolicy;
     219: getstatic     #28                 // Field LOG:Lorg/slf4j/Logger;
     222: ldc           #29                 // String Created LoadBalancingKMSClientProvider for KMS url: {} with {} providers. delegation token service: {}, canonical service: {}
     224: iconst_4
     225: anewarray     #30                 // class java/lang/Object
     228: dup
     229: iconst_0
     230: aload_1
     231: aastore
     232: dup
     233: iconst_1
     234: aload_2
     235: arraylength
     236: invokestatic  #31                 // Method java/lang/Integer.valueOf:(I)Ljava/lang/Integer;
     239: aastore
     240: dup
     241: iconst_2
     242: aload_0
     243: getfield      #1                  // Field dtService:Lorg/apache/hadoop/io/Text;
     246: aastore
     247: dup
     248: iconst_3
     249: aload_0
     250: getfield      #10                 // Field canonicalService:Lorg/apache/hadoop/io/Text;
     253: aastore
     254: invokeinterface #32,  3           // InterfaceMethod org/slf4j/Logger.debug:(Ljava/lang/String;[Ljava/lang/Object;)V
     259: return

  public org.apache.hadoop.crypto.key.kms.KMSClientProvider[] getProviders();
    Code:
       0: aload_0
       1: getfield      #15                 // Field providers:[Lorg/apache/hadoop/crypto/key/kms/KMSClientProvider;
       4: areturn

  public org.apache.hadoop.security.token.Token<? extends org.apache.hadoop.security.token.TokenIdentifier> selectDelegationToken(org.apache.hadoop.security.Credentials);
    Code:
       0: aload_1
       1: aload_0
       2: getfield      #10                 // Field canonicalService:Lorg/apache/hadoop/io/Text;
       5: invokestatic  #33                 // Method org/apache/hadoop/crypto/key/kms/KMSClientProvider.selectDelegationToken:(Lorg/apache/hadoop/security/Credentials;Lorg/apache/hadoop/io/Text;)Lorg/apache/hadoop/security/token/Token;
       8: astore_2
       9: aload_2
      10: ifnonnull     58
      13: aload_0
      14: invokevirtual #34                 // Method getProviders:()[Lorg/apache/hadoop/crypto/key/kms/KMSClientProvider;
      17: astore_3
      18: aload_3
      19: arraylength
      20: istore        4
      22: iconst_0
      23: istore        5
      25: iload         5
      27: iload         4
      29: if_icmpge     58
      32: aload_3
      33: iload         5
      35: aaload
      36: astore        6
      38: aload         6
      40: aload_1
      41: invokevirtual #35                 // Method org/apache/hadoop/crypto/key/kms/KMSClientProvider.selectDelegationToken:(Lorg/apache/hadoop/security/Credentials;)Lorg/apache/hadoop/security/token/Token;
      44: astore_2
      45: aload_2
      46: ifnull        52
      49: goto          58
      52: iinc          5, 1
      55: goto          25
      58: aload_2
      59: areturn

  private <T> T doOp(org.apache.hadoop.crypto.key.kms.LoadBalancingKMSClientProvider$ProviderCallable<T>, int, boolean) throws java.io.IOException;
    Code:
       0: aload_0
       1: getfield      #15                 // Field providers:[Lorg/apache/hadoop/crypto/key/kms/KMSClientProvider;
       4: arraylength
       5: ifne          18
       8: new           #36                 // class java/io/IOException
      11: dup
      12: ldc           #37                 // String No providers configured !
      14: invokespecial #38                 // Method java/io/IOException."<init>":(Ljava/lang/String;)V
      17: athrow
      18: iconst_0
      19: istore        4
      21: iconst_0
      22: istore        5
      24: aload_0
      25: getfield      #15                 // Field providers:[Lorg/apache/hadoop/crypto/key/kms/KMSClientProvider;
      28: iload_2
      29: iload         5
      31: iadd
      32: aload_0
      33: getfield      #15                 // Field providers:[Lorg/apache/hadoop/crypto/key/kms/KMSClientProvider;
      36: arraylength
      37: irem
      38: aaload
      39: astore        6
      41: aload_1
      42: aload         6
      44: invokeinterface #39,  2           // InterfaceMethod org/apache/hadoop/crypto/key/kms/LoadBalancingKMSClientProvider$ProviderCallable.call:(Lorg/apache/hadoop/crypto/key/kms/KMSClientProvider;)Ljava/lang/Object;
      49: areturn
      50: astore        7
      52: aload         7
      54: athrow
      55: astore        7
      57: getstatic     #28                 // Field LOG:Lorg/slf4j/Logger;
      60: ldc           #41                 // String KMS provider at [{}] threw an IOException:
      62: aload         6
      64: invokevirtual #42                 // Method org/apache/hadoop/crypto/key/kms/KMSClientProvider.getKMSUrl:()Ljava/lang/String;
      67: aload         7
      69: invokeinterface #43,  4           // InterfaceMethod org/slf4j/Logger.warn:(Ljava/lang/String;Ljava/lang/Object;Ljava/lang/Object;)V
      74: aload         7
      76: instanceof    #44                 // class javax/net/ssl/SSLHandshakeException
      79: ifeq          126
      82: aload         7
      84: astore        8
      86: new           #45                 // class java/net/ConnectException
      89: dup
      90: new           #46                 // class java/lang/StringBuilder
      93: dup
      94: invokespecial #47                 // Method java/lang/StringBuilder."<init>":()V
      97: ldc           #48                 // String SSLHandshakeException:
      99: invokevirtual #49                 // Method java/lang/StringBuilder.append:(Ljava/lang/String;)Ljava/lang/StringBuilder;
     102: aload         8
     104: invokevirtual #50                 // Method java/lang/Exception.getMessage:()Ljava/lang/String;
     107: invokevirtual #49                 // Method java/lang/StringBuilder.append:(Ljava/lang/String;)Ljava/lang/StringBuilder;
     110: invokevirtual #51                 // Method java/lang/StringBuilder.toString:()Ljava/lang/String;
     113: invokespecial #52                 // Method java/net/ConnectException."<init>":(Ljava/lang/String;)V
     116: astore        7
     118: aload         7
     120: aload         8
     122: invokevirtual #53                 // Method java/io/IOException.initCause:(Ljava/lang/Throwable;)Ljava/lang/Throwable;
     125: pop
     126: aconst_null
     127: astore        8
     129: aload_0
     130: getfield      #7                  // Field retryPolicy:Lorg/apache/hadoop/io/retry/RetryPolicy;
     133: aload         7
     135: iconst_0
     136: iload         4
     138: iload_3
     139: invokeinterface #54,  5           // InterfaceMethod org/apache/hadoop/io/retry/RetryPolicy.shouldRetry:(Ljava/lang/Exception;IIZ)Lorg/apache/hadoop/io/retry/RetryPolicy$RetryAction;
     144: astore        8
     146: goto          175
     149: astore        9
     151: aload         9
     153: instanceof    #36                 // class java/io/IOException
     156: ifeq          165
     159: aload         9
     161: checkcast     #36                 // class java/io/IOException
     164: athrow
     165: new           #36                 // class java/io/IOException
     168: dup
     169: aload         9
     171: invokespecial #56                 // Method java/io/IOException."<init>":(Ljava/lang/Throwable;)V
     174: athrow
     175: aload         8
     177: getfield      #57                 // Field org/apache/hadoop/io/retry/RetryPolicy$RetryAction.action:Lorg/apache/hadoop/io/retry/RetryPolicy$RetryAction$RetryDecision;
     180: getstatic     #58                 // Field org/apache/hadoop/io/retry/RetryPolicy$RetryAction$RetryDecision.FAIL:Lorg/apache/hadoop/io/retry/RetryPolicy$RetryAction$RetryDecision;
     183: if_acmpne     251
     186: iload         4
     188: aload_0
     189: getfield      #15                 // Field providers:[Lorg/apache/hadoop/crypto/key/kms/KMSClientProvider;
     192: arraylength
     193: iconst_1
     194: isub
     195: if_icmplt     251
     198: getstatic     #28                 // Field LOG:Lorg/slf4j/Logger;
     201: ldc           #59                 // String Aborting since the Request has failed with all KMS providers(depending on {}={} setting and numProviders={}) in the group OR the exception is not recoverable
     203: iconst_3
     204: anewarray     #30                 // class java/lang/Object
     207: dup
     208: iconst_0
     209: ldc           #21                 // String hadoop.security.kms.client.failover.max.retries
     211: aastore
     212: dup
     213: iconst_1
     214: aload_0
     215: invokevirtual #60                 // Method getConf:()Lorg/apache/hadoop/conf/Configuration;
     218: ldc           #21                 // String hadoop.security.kms.client.failover.max.retries
     220: aload_0
     221: getfield      #15                 // Field providers:[Lorg/apache/hadoop/crypto/key/kms/KMSClientProvider;
     224: arraylength
     225: invokevirtual #22                 // Method org/apache/hadoop/conf/Configuration.getInt:(Ljava/lang/String;I)I
     228: invokestatic  #31                 // Method java/lang/Integer.valueOf:(I)Ljava/lang/Integer;
     231: aastore
     232: dup
     233: iconst_2
     234: aload_0
     235: getfield      #15                 // Field providers:[Lorg/apache/hadoop/crypto/key/kms/KMSClientProvider;
     238: arraylength
     239: invokestatic  #31                 // Method java/lang/Integer.valueOf:(I)Ljava/lang/Integer;
     242: aastore
     243: invokeinterface #61,  3           // InterfaceMethod org/slf4j/Logger.error:(Ljava/lang/String;[Ljava/lang/Object;)V
     248: aload         7
     250: athrow
     251: iload         4
     253: iconst_1
     254: iadd
     255: aload_0
     256: getfield      #15                 // Field providers:[Lorg/apache/hadoop/crypto/key/kms/KMSClientProvider;
     259: arraylength
     260: irem
     261: ifne          287
     264: aload         8
     266: getfield      #62                 // Field org/apache/hadoop/io/retry/RetryPolicy$RetryAction.delayMillis:J
     269: invokestatic  #63                 // Method java/lang/Thread.sleep:(J)V
     272: goto          287
     275: astore        9
     277: new           #65                 // class java/io/InterruptedIOException
     280: dup
     281: ldc           #66                 // String Thread Interrupted
     283: invokespecial #67                 // Method java/io/InterruptedIOException."<init>":(Ljava/lang/String;)V
     286: athrow
     287: goto          316
     290: astore        7
     292: aload         7
     294: instanceof    #68                 // class java/lang/RuntimeException
     297: ifeq          306
     300: aload         7
     302: checkcast     #68                 // class java/lang/RuntimeException
     305: athrow
     306: new           #69                 // class org/apache/hadoop/crypto/key/kms/LoadBalancingKMSClientProvider$WrapperException
     309: dup
     310: aload         7
     312: invokespecial #70                 // Method org/apache/hadoop/crypto/key/kms/LoadBalancingKMSClientProvider$WrapperException."<init>":(Ljava/lang/Throwable;)V
     315: athrow
     316: iinc          5, 1
     319: iinc          4, 1
     322: goto          24
    Exception table:
       from    to  target type
          41    49    50   Class org/apache/hadoop/security/AccessControlException
          41    49    55   Class java/io/IOException
         129   146   149   Class java/lang/Exception
         264   272   275   Class java/lang/InterruptedException
          41    49   290   Class java/lang/Exception

  private int nextIdx();
    Code:
       0: aload_0
       1: getfield      #19                 // Field currentIdx:Ljava/util/concurrent/atomic/AtomicInteger;
       4: invokevirtual #71                 // Method java/util/concurrent/atomic/AtomicInteger.get:()I
       7: istore_1
       8: iload_1
       9: iconst_1
      10: iadd
      11: aload_0
      12: getfield      #15                 // Field providers:[Lorg/apache/hadoop/crypto/key/kms/KMSClientProvider;
      15: arraylength
      16: irem
      17: istore_2
      18: aload_0
      19: getfield      #19                 // Field currentIdx:Ljava/util/concurrent/atomic/AtomicInteger;
      22: iload_1
      23: iload_2
      24: invokevirtual #72                 // Method java/util/concurrent/atomic/AtomicInteger.compareAndSet:(II)Z
      27: ifeq          32
      30: iload_1
      31: ireturn
      32: goto          0

  public java.lang.String getCanonicalServiceName();
    Code:
       0: aload_0
       1: getfield      #10                 // Field canonicalService:Lorg/apache/hadoop/io/Text;
       4: invokevirtual #73                 // Method org/apache/hadoop/io/Text.toString:()Ljava/lang/String;
       7: areturn

  public org.apache.hadoop.security.token.Token<?> getDelegationToken(java.lang.String) throws java.io.IOException;
    Code:
       0: aload_0
       1: new           #74                 // class org/apache/hadoop/crypto/key/kms/LoadBalancingKMSClientProvider$1
       4: dup
       5: aload_0
       6: aload_1
       7: invokespecial #75                 // Method org/apache/hadoop/crypto/key/kms/LoadBalancingKMSClientProvider$1."<init>":(Lorg/apache/hadoop/crypto/key/kms/LoadBalancingKMSClientProvider;Ljava/lang/String;)V
      10: aload_0
      11: invokespecial #76                 // Method nextIdx:()I
      14: iconst_0
      15: invokespecial #77                 // Method doOp:(Lorg/apache/hadoop/crypto/key/kms/LoadBalancingKMSClientProvider$ProviderCallable;IZ)Ljava/lang/Object;
      18: checkcast     #78                 // class org/apache/hadoop/security/token/Token
      21: areturn

  public long renewDelegationToken(org.apache.hadoop.security.token.Token<?>) throws java.io.IOException;
    Code:
       0: aload_0
       1: new           #79                 // class org/apache/hadoop/crypto/key/kms/LoadBalancingKMSClientProvider$2
       4: dup
       5: aload_0
       6: aload_1
       7: invokespecial #80                 // Method org/apache/hadoop/crypto/key/kms/LoadBalancingKMSClientProvider$2."<init>":(Lorg/apache/hadoop/crypto/key/kms/LoadBalancingKMSClientProvider;Lorg/apache/hadoop/security/token/Token;)V
      10: aload_0
      11: invokespecial #76                 // Method nextIdx:()I
      14: iconst_0
      15: invokespecial #77                 // Method doOp:(Lorg/apache/hadoop/crypto/key/kms/LoadBalancingKMSClientProvider$ProviderCallable;IZ)Ljava/lang/Object;
      18: checkcast     #81                 // class java/lang/Long
      21: invokevirtual #82                 // Method java/lang/Long.longValue:()J
      24: lreturn

  public java.lang.Void cancelDelegationToken(org.apache.hadoop.security.token.Token<?>) throws java.io.IOException;
    Code:
       0: aload_0
       1: new           #83                 // class org/apache/hadoop/crypto/key/kms/LoadBalancingKMSClientProvider$3
       4: dup
       5: aload_0
       6: aload_1
       7: invokespecial #84                 // Method org/apache/hadoop/crypto/key/kms/LoadBalancingKMSClientProvider$3."<init>":(Lorg/apache/hadoop/crypto/key/kms/LoadBalancingKMSClientProvider;Lorg/apache/hadoop/security/token/Token;)V
      10: aload_0
      11: invokespecial #76                 // Method nextIdx:()I
      14: iconst_0
      15: invokespecial #77                 // Method doOp:(Lorg/apache/hadoop/crypto/key/kms/LoadBalancingKMSClientProvider$ProviderCallable;IZ)Ljava/lang/Object;
      18: checkcast     #85                 // class java/lang/Void
      21: areturn

  public void warmUpEncryptedKeys(java.lang.String...) throws java.io.IOException;
    Code:
       0: aload_0
       1: getfield      #15                 // Field providers:[Lorg/apache/hadoop/crypto/key/kms/KMSClientProvider;
       4: arraylength
       5: ifle          12
       8: iconst_1
       9: goto          13
      12: iconst_0
      13: ldc           #86                 // String No providers are configured
      15: invokestatic  #87                 // Method com/google/common/base/Preconditions.checkArgument:(ZLjava/lang/Object;)V
      18: iconst_0
      19: istore_2
      20: aconst_null
      21: astore_3
      22: aload_0
      23: getfield      #15                 // Field providers:[Lorg/apache/hadoop/crypto/key/kms/KMSClientProvider;
      26: astore        4
      28: aload         4
      30: arraylength
      31: istore        5
      33: iconst_0
      34: istore        6
      36: iload         6
      38: iload         5
      40: if_icmpge     110
      43: aload         4
      45: iload         6
      47: aaload
      48: astore        7
      50: aload         7
      52: aload_1
      53: invokevirtual #88                 // Method org/apache/hadoop/crypto/key/kms/KMSClientProvider.warmUpEncryptedKeys:([Ljava/lang/String;)V
      56: iconst_1
      57: istore_2
      58: goto          104
      61: astore        8
      63: aload         8
      65: astore_3
      66: getstatic     #28                 // Field LOG:Lorg/slf4j/Logger;
      69: new           #46                 // class java/lang/StringBuilder
      72: dup
      73: invokespecial #47                 // Method java/lang/StringBuilder."<init>":()V
      76: ldc           #89                 // String Error warming up keys for provider with url[
      78: invokevirtual #49                 // Method java/lang/StringBuilder.append:(Ljava/lang/String;)Ljava/lang/StringBuilder;
      81: aload         7
      83: invokevirtual #42                 // Method org/apache/hadoop/crypto/key/kms/KMSClientProvider.getKMSUrl:()Ljava/lang/String;
      86: invokevirtual #49                 // Method java/lang/StringBuilder.append:(Ljava/lang/String;)Ljava/lang/StringBuilder;
      89: ldc           #90                 // String ]
      91: invokevirtual #49                 // Method java/lang/StringBuilder.append:(Ljava/lang/String;)Ljava/lang/StringBuilder;
      94: invokevirtual #51                 // Method java/lang/StringBuilder.toString:()Ljava/lang/String;
      97: aload         8
      99: invokeinterface #91,  3           // InterfaceMethod org/slf4j/Logger.error:(Ljava/lang/String;Ljava/lang/Throwable;)V
     104: iinc          6, 1
     107: goto          36
     110: iload_2
     111: ifne          120
     114: aload_3
     115: ifnull        120
     118: aload_3
     119: athrow
     120: return
    Exception table:
       from    to  target type
          50    58    61   Class java/io/IOException

  public void drain(java.lang.String);
    Code:
       0: aload_0
       1: getfield      #15                 // Field providers:[Lorg/apache/hadoop/crypto/key/kms/KMSClientProvider;
       4: astore_2
       5: aload_2
       6: arraylength
       7: istore_3
       8: iconst_0
       9: istore        4
      11: iload         4
      13: iload_3
      14: if_icmpge     35
      17: aload_2
      18: iload         4
      20: aaload
      21: astore        5
      23: aload         5
      25: aload_1
      26: invokevirtual #92                 // Method org/apache/hadoop/crypto/key/kms/KMSClientProvider.drain:(Ljava/lang/String;)V
      29: iinc          4, 1
      32: goto          11
      35: return

  public void invalidateCache(java.lang.String) throws java.io.IOException;
    Code:
       0: aload_0
       1: getfield      #15                 // Field providers:[Lorg/apache/hadoop/crypto/key/kms/KMSClientProvider;
       4: astore_2
       5: aload_2
       6: arraylength
       7: istore_3
       8: iconst_0
       9: istore        4
      11: iload         4
      13: iload_3
      14: if_icmpge     35
      17: aload_2
      18: iload         4
      20: aaload
      21: astore        5
      23: aload         5
      25: aload_1
      26: invokevirtual #93                 // Method org/apache/hadoop/crypto/key/kms/KMSClientProvider.invalidateCache:(Ljava/lang/String;)V
      29: iinc          4, 1
      32: goto          11
      35: return

  public org.apache.hadoop.crypto.key.KeyProviderCryptoExtension$EncryptedKeyVersion generateEncryptedKey(java.lang.String) throws java.io.IOException, java.security.GeneralSecurityException;
    Code:
       0: aload_0
       1: new           #94                 // class org/apache/hadoop/crypto/key/kms/LoadBalancingKMSClientProvider$4
       4: dup
       5: aload_0
       6: aload_1
       7: invokespecial #95                 // Method org/apache/hadoop/crypto/key/kms/LoadBalancingKMSClientProvider$4."<init>":(Lorg/apache/hadoop/crypto/key/kms/LoadBalancingKMSClientProvider;Ljava/lang/String;)V
      10: aload_0
      11: invokespecial #76                 // Method nextIdx:()I
      14: iconst_1
      15: invokespecial #77                 // Method doOp:(Lorg/apache/hadoop/crypto/key/kms/LoadBalancingKMSClientProvider$ProviderCallable;IZ)Ljava/lang/Object;
      18: checkcast     #96                 // class org/apache/hadoop/crypto/key/KeyProviderCryptoExtension$EncryptedKeyVersion
      21: areturn
      22: astore_2
      23: aload_2
      24: invokevirtual #97                 // Method org/apache/hadoop/crypto/key/kms/LoadBalancingKMSClientProvider$WrapperException.getCause:()Ljava/lang/Throwable;
      27: instanceof    #98                 // class java/security/GeneralSecurityException
      30: ifeq          41
      33: aload_2
      34: invokevirtual #97                 // Method org/apache/hadoop/crypto/key/kms/LoadBalancingKMSClientProvider$WrapperException.getCause:()Ljava/lang/Throwable;
      37: checkcast     #98                 // class java/security/GeneralSecurityException
      40: athrow
      41: new           #36                 // class java/io/IOException
      44: dup
      45: aload_2
      46: invokevirtual #97                 // Method org/apache/hadoop/crypto/key/kms/LoadBalancingKMSClientProvider$WrapperException.getCause:()Ljava/lang/Throwable;
      49: invokespecial #56                 // Method java/io/IOException."<init>":(Ljava/lang/Throwable;)V
      52: athrow
    Exception table:
       from    to  target type
           0    21    22   Class org/apache/hadoop/crypto/key/kms/LoadBalancingKMSClientProvider$WrapperException

  public org.apache.hadoop.crypto.key.KeyProvider$KeyVersion decryptEncryptedKey(org.apache.hadoop.crypto.key.KeyProviderCryptoExtension$EncryptedKeyVersion) throws java.io.IOException, java.security.GeneralSecurityException;
    Code:
       0: aload_0
       1: new           #99                 // class org/apache/hadoop/crypto/key/kms/LoadBalancingKMSClientProvider$5
       4: dup
       5: aload_0
       6: aload_1
       7: invokespecial #100                // Method org/apache/hadoop/crypto/key/kms/LoadBalancingKMSClientProvider$5."<init>":(Lorg/apache/hadoop/crypto/key/kms/LoadBalancingKMSClientProvider;Lorg/apache/hadoop/crypto/key/KeyProviderCryptoExtension$EncryptedKeyVersion;)V
      10: aload_0
      11: invokespecial #76                 // Method nextIdx:()I
      14: iconst_1
      15: invokespecial #77                 // Method doOp:(Lorg/apache/hadoop/crypto/key/kms/LoadBalancingKMSClientProvider$ProviderCallable;IZ)Ljava/lang/Object;
      18: checkcast     #101                // class org/apache/hadoop/crypto/key/KeyProvider$KeyVersion
      21: areturn
      22: astore_2
      23: aload_2
      24: invokevirtual #97                 // Method org/apache/hadoop/crypto/key/kms/LoadBalancingKMSClientProvider$WrapperException.getCause:()Ljava/lang/Throwable;
      27: instanceof    #98                 // class java/security/GeneralSecurityException
      30: ifeq          41
      33: aload_2
      34: invokevirtual #97                 // Method org/apache/hadoop/crypto/key/kms/LoadBalancingKMSClientProvider$WrapperException.getCause:()Ljava/lang/Throwable;
      37: checkcast     #98                 // class java/security/GeneralSecurityException
      40: athrow
      41: new           #36                 // class java/io/IOException
      44: dup
      45: aload_2
      46: invokevirtual #97                 // Method org/apache/hadoop/crypto/key/kms/LoadBalancingKMSClientProvider$WrapperException.getCause:()Ljava/lang/Throwable;
      49: invokespecial #56                 // Method java/io/IOException."<init>":(Ljava/lang/Throwable;)V
      52: athrow
    Exception table:
       from    to  target type
           0    21    22   Class org/apache/hadoop/crypto/key/kms/LoadBalancingKMSClientProvider$WrapperException

  public org.apache.hadoop.crypto.key.KeyProviderCryptoExtension$EncryptedKeyVersion reencryptEncryptedKey(org.apache.hadoop.crypto.key.KeyProviderCryptoExtension$EncryptedKeyVersion) throws java.io.IOException, java.security.GeneralSecurityException;
    Code:
       0: aload_0
       1: new           #102                // class org/apache/hadoop/crypto/key/kms/LoadBalancingKMSClientProvider$6
       4: dup
       5: aload_0
       6: aload_1
       7: invokespecial #103                // Method org/apache/hadoop/crypto/key/kms/LoadBalancingKMSClientProvider$6."<init>":(Lorg/apache/hadoop/crypto/key/kms/LoadBalancingKMSClientProvider;Lorg/apache/hadoop/crypto/key/KeyProviderCryptoExtension$EncryptedKeyVersion;)V
      10: aload_0
      11: invokespecial #76                 // Method nextIdx:()I
      14: iconst_1
      15: invokespecial #77                 // Method doOp:(Lorg/apache/hadoop/crypto/key/kms/LoadBalancingKMSClientProvider$ProviderCallable;IZ)Ljava/lang/Object;
      18: checkcast     #96                 // class org/apache/hadoop/crypto/key/KeyProviderCryptoExtension$EncryptedKeyVersion
      21: areturn
      22: astore_2
      23: aload_2
      24: invokevirtual #97                 // Method org/apache/hadoop/crypto/key/kms/LoadBalancingKMSClientProvider$WrapperException.getCause:()Ljava/lang/Throwable;
      27: instanceof    #98                 // class java/security/GeneralSecurityException
      30: ifeq          41
      33: aload_2
      34: invokevirtual #97                 // Method org/apache/hadoop/crypto/key/kms/LoadBalancingKMSClientProvider$WrapperException.getCause:()Ljava/lang/Throwable;
      37: checkcast     #98                 // class java/security/GeneralSecurityException
      40: athrow
      41: new           #36                 // class java/io/IOException
      44: dup
      45: aload_2
      46: invokevirtual #97                 // Method org/apache/hadoop/crypto/key/kms/LoadBalancingKMSClientProvider$WrapperException.getCause:()Ljava/lang/Throwable;
      49: invokespecial #56                 // Method java/io/IOException."<init>":(Ljava/lang/Throwable;)V
      52: athrow
    Exception table:
       from    to  target type
           0    21    22   Class org/apache/hadoop/crypto/key/kms/LoadBalancingKMSClientProvider$WrapperException

  public void reencryptEncryptedKeys(java.util.List<org.apache.hadoop.crypto.key.KeyProviderCryptoExtension$EncryptedKeyVersion>) throws java.io.IOException, java.security.GeneralSecurityException;
    Code:
       0: aload_0
       1: new           #104                // class org/apache/hadoop/crypto/key/kms/LoadBalancingKMSClientProvider$7
       4: dup
       5: aload_0
       6: aload_1
       7: invokespecial #105                // Method org/apache/hadoop/crypto/key/kms/LoadBalancingKMSClientProvider$7."<init>":(Lorg/apache/hadoop/crypto/key/kms/LoadBalancingKMSClientProvider;Ljava/util/List;)V
      10: aload_0
      11: invokespecial #76                 // Method nextIdx:()I
      14: iconst_1
      15: invokespecial #77                 // Method doOp:(Lorg/apache/hadoop/crypto/key/kms/LoadBalancingKMSClientProvider$ProviderCallable;IZ)Ljava/lang/Object;
      18: pop
      19: goto          53
      22: astore_2
      23: aload_2
      24: invokevirtual #97                 // Method org/apache/hadoop/crypto/key/kms/LoadBalancingKMSClientProvider$WrapperException.getCause:()Ljava/lang/Throwable;
      27: instanceof    #98                 // class java/security/GeneralSecurityException
      30: ifeq          41
      33: aload_2
      34: invokevirtual #97                 // Method org/apache/hadoop/crypto/key/kms/LoadBalancingKMSClientProvider$WrapperException.getCause:()Ljava/lang/Throwable;
      37: checkcast     #98                 // class java/security/GeneralSecurityException
      40: athrow
      41: new           #36                 // class java/io/IOException
      44: dup
      45: aload_2
      46: invokevirtual #97                 // Method org/apache/hadoop/crypto/key/kms/LoadBalancingKMSClientProvider$WrapperException.getCause:()Ljava/lang/Throwable;
      49: invokespecial #56                 // Method java/io/IOException."<init>":(Ljava/lang/Throwable;)V
      52: athrow
      53: return
    Exception table:
       from    to  target type
           0    19    22   Class org/apache/hadoop/crypto/key/kms/LoadBalancingKMSClientProvider$WrapperException

  public org.apache.hadoop.crypto.key.KeyProvider$KeyVersion getKeyVersion(java.lang.String) throws java.io.IOException;
    Code:
       0: aload_0
       1: new           #106                // class org/apache/hadoop/crypto/key/kms/LoadBalancingKMSClientProvider$8
       4: dup
       5: aload_0
       6: aload_1
       7: invokespecial #107                // Method org/apache/hadoop/crypto/key/kms/LoadBalancingKMSClientProvider$8."<init>":(Lorg/apache/hadoop/crypto/key/kms/LoadBalancingKMSClientProvider;Ljava/lang/String;)V
      10: aload_0
      11: invokespecial #76                 // Method nextIdx:()I
      14: iconst_1
      15: invokespecial #77                 // Method doOp:(Lorg/apache/hadoop/crypto/key/kms/LoadBalancingKMSClientProvider$ProviderCallable;IZ)Ljava/lang/Object;
      18: checkcast     #101                // class org/apache/hadoop/crypto/key/KeyProvider$KeyVersion
      21: areturn

  public java.util.List<java.lang.String> getKeys() throws java.io.IOException;
    Code:
       0: aload_0
       1: new           #108                // class org/apache/hadoop/crypto/key/kms/LoadBalancingKMSClientProvider$9
       4: dup
       5: aload_0
       6: invokespecial #109                // Method org/apache/hadoop/crypto/key/kms/LoadBalancingKMSClientProvider$9."<init>":(Lorg/apache/hadoop/crypto/key/kms/LoadBalancingKMSClientProvider;)V
       9: aload_0
      10: invokespecial #76                 // Method nextIdx:()I
      13: iconst_1
      14: invokespecial #77                 // Method doOp:(Lorg/apache/hadoop/crypto/key/kms/LoadBalancingKMSClientProvider$ProviderCallable;IZ)Ljava/lang/Object;
      17: checkcast     #110                // class java/util/List
      20: areturn

  public org.apache.hadoop.crypto.key.KeyProvider$Metadata[] getKeysMetadata(java.lang.String...) throws java.io.IOException;
    Code:
       0: aload_0
       1: new           #111                // class org/apache/hadoop/crypto/key/kms/LoadBalancingKMSClientProvider$10
       4: dup
       5: aload_0
       6: aload_1
       7: invokespecial #112                // Method org/apache/hadoop/crypto/key/kms/LoadBalancingKMSClientProvider$10."<init>":(Lorg/apache/hadoop/crypto/key/kms/LoadBalancingKMSClientProvider;[Ljava/lang/String;)V
      10: aload_0
      11: invokespecial #76                 // Method nextIdx:()I
      14: iconst_1
      15: invokespecial #77                 // Method doOp:(Lorg/apache/hadoop/crypto/key/kms/LoadBalancingKMSClientProvider$ProviderCallable;IZ)Ljava/lang/Object;
      18: checkcast     #113                // class "[Lorg/apache/hadoop/crypto/key/KeyProvider$Metadata;"
      21: areturn

  public java.util.List<org.apache.hadoop.crypto.key.KeyProvider$KeyVersion> getKeyVersions(java.lang.String) throws java.io.IOException;
    Code:
       0: aload_0
       1: new           #114                // class org/apache/hadoop/crypto/key/kms/LoadBalancingKMSClientProvider$11
       4: dup
       5: aload_0
       6: aload_1
       7: invokespecial #115                // Method org/apache/hadoop/crypto/key/kms/LoadBalancingKMSClientProvider$11."<init>":(Lorg/apache/hadoop/crypto/key/kms/LoadBalancingKMSClientProvider;Ljava/lang/String;)V
      10: aload_0
      11: invokespecial #76                 // Method nextIdx:()I
      14: iconst_1
      15: invokespecial #77                 // Method doOp:(Lorg/apache/hadoop/crypto/key/kms/LoadBalancingKMSClientProvider$ProviderCallable;IZ)Ljava/lang/Object;
      18: checkcast     #110                // class java/util/List
      21: areturn

  public org.apache.hadoop.crypto.key.KeyProvider$KeyVersion getCurrentKey(java.lang.String) throws java.io.IOException;
    Code:
       0: aload_0
       1: new           #116                // class org/apache/hadoop/crypto/key/kms/LoadBalancingKMSClientProvider$12
       4: dup
       5: aload_0
       6: aload_1
       7: invokespecial #117                // Method org/apache/hadoop/crypto/key/kms/LoadBalancingKMSClientProvider$12."<init>":(Lorg/apache/hadoop/crypto/key/kms/LoadBalancingKMSClientProvider;Ljava/lang/String;)V
      10: aload_0
      11: invokespecial #76                 // Method nextIdx:()I
      14: iconst_1
      15: invokespecial #77                 // Method doOp:(Lorg/apache/hadoop/crypto/key/kms/LoadBalancingKMSClientProvider$ProviderCallable;IZ)Ljava/lang/Object;
      18: checkcast     #101                // class org/apache/hadoop/crypto/key/KeyProvider$KeyVersion
      21: areturn

  public org.apache.hadoop.crypto.key.KeyProvider$Metadata getMetadata(java.lang.String) throws java.io.IOException;
    Code:
       0: aload_0
       1: new           #118                // class org/apache/hadoop/crypto/key/kms/LoadBalancingKMSClientProvider$13
       4: dup
       5: aload_0
       6: aload_1
       7: invokespecial #119                // Method org/apache/hadoop/crypto/key/kms/LoadBalancingKMSClientProvider$13."<init>":(Lorg/apache/hadoop/crypto/key/kms/LoadBalancingKMSClientProvider;Ljava/lang/String;)V
      10: aload_0
      11: invokespecial #76                 // Method nextIdx:()I
      14: iconst_1
      15: invokespecial #77                 // Method doOp:(Lorg/apache/hadoop/crypto/key/kms/LoadBalancingKMSClientProvider$ProviderCallable;IZ)Ljava/lang/Object;
      18: checkcast     #120                // class org/apache/hadoop/crypto/key/KeyProvider$Metadata
      21: areturn

  public org.apache.hadoop.crypto.key.KeyProvider$KeyVersion createKey(java.lang.String, byte[], org.apache.hadoop.crypto.key.KeyProvider$Options) throws java.io.IOException;
    Code:
       0: aload_0
       1: new           #121                // class org/apache/hadoop/crypto/key/kms/LoadBalancingKMSClientProvider$14
       4: dup
       5: aload_0
       6: aload_1
       7: aload_2
       8: aload_3
       9: invokespecial #122                // Method org/apache/hadoop/crypto/key/kms/LoadBalancingKMSClientProvider$14."<init>":(Lorg/apache/hadoop/crypto/key/kms/LoadBalancingKMSClientProvider;Ljava/lang/String;[BLorg/apache/hadoop/crypto/key/KeyProvider$Options;)V
      12: aload_0
      13: invokespecial #76                 // Method nextIdx:()I
      16: iconst_0
      17: invokespecial #77                 // Method doOp:(Lorg/apache/hadoop/crypto/key/kms/LoadBalancingKMSClientProvider$ProviderCallable;IZ)Ljava/lang/Object;
      20: checkcast     #101                // class org/apache/hadoop/crypto/key/KeyProvider$KeyVersion
      23: areturn

  public org.apache.hadoop.crypto.key.KeyProvider$KeyVersion createKey(java.lang.String, org.apache.hadoop.crypto.key.KeyProvider$Options) throws java.security.NoSuchAlgorithmException, java.io.IOException;
    Code:
       0: aload_0
       1: new           #123                // class org/apache/hadoop/crypto/key/kms/LoadBalancingKMSClientProvider$15
       4: dup
       5: aload_0
       6: aload_1
       7: aload_2
       8: invokespecial #124                // Method org/apache/hadoop/crypto/key/kms/LoadBalancingKMSClientProvider$15."<init>":(Lorg/apache/hadoop/crypto/key/kms/LoadBalancingKMSClientProvider;Ljava/lang/String;Lorg/apache/hadoop/crypto/key/KeyProvider$Options;)V
      11: aload_0
      12: invokespecial #76                 // Method nextIdx:()I
      15: iconst_0
      16: invokespecial #77                 // Method doOp:(Lorg/apache/hadoop/crypto/key/kms/LoadBalancingKMSClientProvider$ProviderCallable;IZ)Ljava/lang/Object;
      19: checkcast     #101                // class org/apache/hadoop/crypto/key/KeyProvider$KeyVersion
      22: areturn
      23: astore_3
      24: aload_3
      25: invokevirtual #97                 // Method org/apache/hadoop/crypto/key/kms/LoadBalancingKMSClientProvider$WrapperException.getCause:()Ljava/lang/Throwable;
      28: instanceof    #98                 // class java/security/GeneralSecurityException
      31: ifeq          42
      34: aload_3
      35: invokevirtual #97                 // Method org/apache/hadoop/crypto/key/kms/LoadBalancingKMSClientProvider$WrapperException.getCause:()Ljava/lang/Throwable;
      38: checkcast     #125                // class java/security/NoSuchAlgorithmException
      41: athrow
      42: new           #36                 // class java/io/IOException
      45: dup
      46: aload_3
      47: invokevirtual #97                 // Method org/apache/hadoop/crypto/key/kms/LoadBalancingKMSClientProvider$WrapperException.getCause:()Ljava/lang/Throwable;
      50: invokespecial #56                 // Method java/io/IOException."<init>":(Ljava/lang/Throwable;)V
      53: athrow
    Exception table:
       from    to  target type
           0    22    23   Class org/apache/hadoop/crypto/key/kms/LoadBalancingKMSClientProvider$WrapperException

  public void deleteKey(java.lang.String) throws java.io.IOException;
    Code:
       0: aload_0
       1: new           #126                // class org/apache/hadoop/crypto/key/kms/LoadBalancingKMSClientProvider$16
       4: dup
       5: aload_0
       6: aload_1
       7: invokespecial #127                // Method org/apache/hadoop/crypto/key/kms/LoadBalancingKMSClientProvider$16."<init>":(Lorg/apache/hadoop/crypto/key/kms/LoadBalancingKMSClientProvider;Ljava/lang/String;)V
      10: aload_0
      11: invokespecial #76                 // Method nextIdx:()I
      14: iconst_0
      15: invokespecial #77                 // Method doOp:(Lorg/apache/hadoop/crypto/key/kms/LoadBalancingKMSClientProvider$ProviderCallable;IZ)Ljava/lang/Object;
      18: pop
      19: return

  public org.apache.hadoop.crypto.key.KeyProvider$KeyVersion rollNewVersion(java.lang.String, byte[]) throws java.io.IOException;
    Code:
       0: aload_0
       1: new           #128                // class org/apache/hadoop/crypto/key/kms/LoadBalancingKMSClientProvider$17
       4: dup
       5: aload_0
       6: aload_1
       7: aload_2
       8: invokespecial #129                // Method org/apache/hadoop/crypto/key/kms/LoadBalancingKMSClientProvider$17."<init>":(Lorg/apache/hadoop/crypto/key/kms/LoadBalancingKMSClientProvider;Ljava/lang/String;[B)V
      11: aload_0
      12: invokespecial #76                 // Method nextIdx:()I
      15: iconst_0
      16: invokespecial #77                 // Method doOp:(Lorg/apache/hadoop/crypto/key/kms/LoadBalancingKMSClientProvider$ProviderCallable;IZ)Ljava/lang/Object;
      19: checkcast     #101                // class org/apache/hadoop/crypto/key/KeyProvider$KeyVersion
      22: astore_3
      23: aload_0
      24: aload_1
      25: invokevirtual #130                // Method invalidateCache:(Ljava/lang/String;)V
      28: aload_3
      29: areturn

  public org.apache.hadoop.crypto.key.KeyProvider$KeyVersion rollNewVersion(java.lang.String) throws java.security.NoSuchAlgorithmException, java.io.IOException;
    Code:
       0: aload_0
       1: new           #131                // class org/apache/hadoop/crypto/key/kms/LoadBalancingKMSClientProvider$18
       4: dup
       5: aload_0
       6: aload_1
       7: invokespecial #132                // Method org/apache/hadoop/crypto/key/kms/LoadBalancingKMSClientProvider$18."<init>":(Lorg/apache/hadoop/crypto/key/kms/LoadBalancingKMSClientProvider;Ljava/lang/String;)V
      10: aload_0
      11: invokespecial #76                 // Method nextIdx:()I
      14: iconst_0
      15: invokespecial #77                 // Method doOp:(Lorg/apache/hadoop/crypto/key/kms/LoadBalancingKMSClientProvider$ProviderCallable;IZ)Ljava/lang/Object;
      18: checkcast     #101                // class org/apache/hadoop/crypto/key/KeyProvider$KeyVersion
      21: astore_2
      22: aload_0
      23: aload_1
      24: invokevirtual #130                // Method invalidateCache:(Ljava/lang/String;)V
      27: aload_2
      28: areturn
      29: astore_2
      30: aload_2
      31: invokevirtual #97                 // Method org/apache/hadoop/crypto/key/kms/LoadBalancingKMSClientProvider$WrapperException.getCause:()Ljava/lang/Throwable;
      34: instanceof    #98                 // class java/security/GeneralSecurityException
      37: ifeq          48
      40: aload_2
      41: invokevirtual #97                 // Method org/apache/hadoop/crypto/key/kms/LoadBalancingKMSClientProvider$WrapperException.getCause:()Ljava/lang/Throwable;
      44: checkcast     #125                // class java/security/NoSuchAlgorithmException
      47: athrow
      48: new           #36                 // class java/io/IOException
      51: dup
      52: aload_2
      53: invokevirtual #97                 // Method org/apache/hadoop/crypto/key/kms/LoadBalancingKMSClientProvider$WrapperException.getCause:()Ljava/lang/Throwable;
      56: invokespecial #56                 // Method java/io/IOException."<init>":(Ljava/lang/Throwable;)V
      59: athrow
    Exception table:
       from    to  target type
           0    28    29   Class org/apache/hadoop/crypto/key/kms/LoadBalancingKMSClientProvider$WrapperException

  public void close() throws java.io.IOException;
    Code:
       0: aload_0
       1: getfield      #15                 // Field providers:[Lorg/apache/hadoop/crypto/key/kms/KMSClientProvider;
       4: astore_1
       5: aload_1
       6: arraylength
       7: istore_2
       8: iconst_0
       9: istore_3
      10: iload_3
      11: iload_2
      12: if_icmpge     72
      15: aload_1
      16: iload_3
      17: aaload
      18: astore        4
      20: aload         4
      22: invokevirtual #133                // Method org/apache/hadoop/crypto/key/kms/KMSClientProvider.close:()V
      25: goto          66
      28: astore        5
      30: getstatic     #28                 // Field LOG:Lorg/slf4j/Logger;
      33: new           #46                 // class java/lang/StringBuilder
      36: dup
      37: invokespecial #47                 // Method java/lang/StringBuilder."<init>":()V
      40: ldc           #134                // String Error closing provider with url[
      42: invokevirtual #49                 // Method java/lang/StringBuilder.append:(Ljava/lang/String;)Ljava/lang/StringBuilder;
      45: aload         4
      47: invokevirtual #42                 // Method org/apache/hadoop/crypto/key/kms/KMSClientProvider.getKMSUrl:()Ljava/lang/String;
      50: invokevirtual #49                 // Method java/lang/StringBuilder.append:(Ljava/lang/String;)Ljava/lang/StringBuilder;
      53: ldc           #90                 // String ]
      55: invokevirtual #49                 // Method java/lang/StringBuilder.append:(Ljava/lang/String;)Ljava/lang/StringBuilder;
      58: invokevirtual #51                 // Method java/lang/StringBuilder.toString:()Ljava/lang/String;
      61: invokeinterface #135,  2          // InterfaceMethod org/slf4j/Logger.error:(Ljava/lang/String;)V
      66: iinc          3, 1
      69: goto          10
      72: return
    Exception table:
       from    to  target type
          20    25    28   Class java/io/IOException

  public void flush() throws java.io.IOException;
    Code:
       0: aload_0
       1: getfield      #15                 // Field providers:[Lorg/apache/hadoop/crypto/key/kms/KMSClientProvider;
       4: astore_1
       5: aload_1
       6: arraylength
       7: istore_2
       8: iconst_0
       9: istore_3
      10: iload_3
      11: iload_2
      12: if_icmpge     72
      15: aload_1
      16: iload_3
      17: aaload
      18: astore        4
      20: aload         4
      22: invokevirtual #136                // Method org/apache/hadoop/crypto/key/kms/KMSClientProvider.flush:()V
      25: goto          66
      28: astore        5
      30: getstatic     #28                 // Field LOG:Lorg/slf4j/Logger;
      33: new           #46                 // class java/lang/StringBuilder
      36: dup
      37: invokespecial #47                 // Method java/lang/StringBuilder."<init>":()V
      40: ldc           #137                // String Error flushing provider with url[
      42: invokevirtual #49                 // Method java/lang/StringBuilder.append:(Ljava/lang/String;)Ljava/lang/StringBuilder;
      45: aload         4
      47: invokevirtual #42                 // Method org/apache/hadoop/crypto/key/kms/KMSClientProvider.getKMSUrl:()Ljava/lang/String;
      50: invokevirtual #49                 // Method java/lang/StringBuilder.append:(Ljava/lang/String;)Ljava/lang/StringBuilder;
      53: ldc           #90                 // String ]
      55: invokevirtual #49                 // Method java/lang/StringBuilder.append:(Ljava/lang/String;)Ljava/lang/StringBuilder;
      58: invokevirtual #51                 // Method java/lang/StringBuilder.toString:()Ljava/lang/String;
      61: invokeinterface #135,  2          // InterfaceMethod org/slf4j/Logger.error:(Ljava/lang/String;)V
      66: iinc          3, 1
      69: goto          10
      72: return
    Exception table:
       from    to  target type
          20    25    28   Class java/io/IOException

  private static org.apache.hadoop.crypto.key.kms.KMSClientProvider[] shuffle(org.apache.hadoop.crypto.key.kms.KMSClientProvider[]);
    Code:
       0: aload_0
       1: invokestatic  #138                // Method java/util/Arrays.asList:([Ljava/lang/Object;)Ljava/util/List;
       4: astore_1
       5: aload_1
       6: invokestatic  #139                // Method java/util/Collections.shuffle:(Ljava/util/List;)V
       9: aload_1
      10: aload_0
      11: invokeinterface #140,  2          // InterfaceMethod java/util/List.toArray:([Ljava/lang/Object;)[Ljava/lang/Object;
      16: checkcast     #141                // class "[Lorg/apache/hadoop/crypto/key/kms/KMSClientProvider;"
      19: areturn

  static org.apache.hadoop.io.Text access$000(org.apache.hadoop.crypto.key.kms.LoadBalancingKMSClientProvider);
    Code:
       0: aload_0
       1: getfield      #1                  // Field dtService:Lorg/apache/hadoop/io/Text;
       4: areturn

  static {};
    Code:
       0: ldc           #142                // class org/apache/hadoop/crypto/key/kms/LoadBalancingKMSClientProvider
       2: invokestatic  #143                // Method org/slf4j/LoggerFactory.getLogger:(Ljava/lang/Class;)Lorg/slf4j/Logger;
       5: putstatic     #28                 // Field LOG:Lorg/slf4j/Logger;
       8: return
}
