Compiled from "OccupationBuilder.java"
public final class cn.nothinghere.brook.builder.OccupationBuilder implements cn.nothinghere.brook.Builder {
  private final cn.nothinghere.brook.value.occupation.Occupation occupation;

  protected cn.nothinghere.brook.builder.OccupationBuilder();
    Code:
       0: aload_0
       1: invokespecial #1                  // Method java/lang/Object."<init>":()V
       4: aload_0
       5: new           #2                  // class cn/nothinghere/brook/value/occupation/Occupation
       8: dup
       9: invokespecial #3                  // Method cn/nothinghere/brook/value/occupation/Occupation."<init>":()V
      12: putfield      #4                  // Field occupation:Lcn/nothinghere/brook/value/occupation/Occupation;
      15: return

  public cn.nothinghere.brook.builder.OccupationBuilder withType(cn.nothinghere.brook.value.occupation.MajorType);
    Code:
       0: aload_0
       1: getfield      #4                  // Field occupation:Lcn/nothinghere/brook/value/occupation/Occupation;
       4: aload_1
       5: invokevirtual #5                  // Method cn/nothinghere/brook/value/occupation/Occupation.setMajorType:(Lcn/nothinghere/brook/value/occupation/MajorType;)V
       8: aload_0
       9: areturn

  public java.lang.String build();
    Code:
       0: aload_0
       1: getfield      #4                  // Field occupation:Lcn/nothinghere/brook/value/occupation/Occupation;
       4: invokevirtual #6                  // Method cn/nothinghere/brook/value/occupation/Occupation.randomIfNull:()V
       7: aload_0
       8: getfield      #4                  // Field occupation:Lcn/nothinghere/brook/value/occupation/Occupation;
      11: invokevirtual #7                  // Method cn/nothinghere/brook/value/occupation/Occupation.verify:()V
      14: aload_0
      15: getfield      #4                  // Field occupation:Lcn/nothinghere/brook/value/occupation/Occupation;
      18: invokevirtual #8                  // Method cn/nothinghere/brook/value/occupation/Occupation.asString:()Ljava/lang/String;
      21: areturn
}
