Compiled from "PhoneBuilder.java"
public class cn.nothinghere.brook.builder.PhoneBuilder$Mac implements cn.nothinghere.brook.Field,cn.nothinghere.brook.Randomize,java.io.Serializable {
  private static final long serialVersionUID;

  private static final java.util.Map<java.lang.String, java.util.List<java.lang.Integer>> MAC_MAP;

  private cn.nothinghere.brook.value.Operator operator;

  public cn.nothinghere.brook.builder.PhoneBuilder$Mac();
    Code:
       0: aload_0
       1: invokespecial #1                  // Method java/lang/Object."<init>":()V
       4: return

  public cn.nothinghere.brook.value.Operator getOperator();
    Code:
       0: aload_0
       1: getfield      #2                  // Field operator:Lcn/nothinghere/brook/value/Operator;
       4: areturn

  public void setOperator(cn.nothinghere.brook.value.Operator);
    Code:
       0: aload_0
       1: aload_1
       2: putfield      #2                  // Field operator:Lcn/nothinghere/brook/value/Operator;
       5: return

  public java.lang.String asString();
    Code:
       0: aload_0
       1: getfield      #2                  // Field operator:Lcn/nothinghere/brook/value/Operator;
       4: invokevirtual #3                  // Method cn/nothinghere/brook/value/Operator.name:()Ljava/lang/String;
       7: invokevirtual #4                  // Method java/lang/String.toLowerCase:()Ljava/lang/String;
      10: astore_1
      11: getstatic     #5                  // Field MAC_MAP:Ljava/util/Map;
      14: aload_1
      15: invokeinterface #6,  2            // InterfaceMethod java/util/Map.get:(Ljava/lang/Object;)Ljava/lang/Object;
      20: checkcast     #7                  // class java/util/List
      23: astore_2
      24: aload_2
      25: invokestatic  #8                  // Method cn/nothinghere/brook/util/RandomUtils.choice:(Ljava/util/List;)Ljava/lang/Object;
      28: checkcast     #9                  // class java/lang/Integer
      31: invokevirtual #10                 // Method java/lang/Integer.toString:()Ljava/lang/String;
      34: areturn

  public void randomIfNull();
    Code:
       0: aconst_null
       1: aload_0
       2: getfield      #2                  // Field operator:Lcn/nothinghere/brook/value/Operator;
       5: if_acmpne     21
       8: aload_0
       9: invokestatic  #11                 // Method cn/nothinghere/brook/value/Operator.values:()[Lcn/nothinghere/brook/value/Operator;
      12: invokestatic  #12                 // Method cn/nothinghere/brook/util/RandomUtils.choice:([Ljava/lang/Object;)Ljava/lang/Object;
      15: checkcast     #13                 // class cn/nothinghere/brook/value/Operator
      18: putfield      #2                  // Field operator:Lcn/nothinghere/brook/value/Operator;
      21: return

  static {};
    Code:
       0: ldc           #14                 // String mac.yml
       2: invokestatic  #15                 // Method cn/nothinghere/brook/util/YamlUtils.load:(Ljava/lang/String;)Ljava/lang/Object;
       5: checkcast     #16                 // class java/util/Map
       8: invokestatic  #17                 // Method java/util/Collections.unmodifiableMap:(Ljava/util/Map;)Ljava/util/Map;
      11: putstatic     #5                  // Field MAC_MAP:Ljava/util/Map;
      14: return
}
