Compiled from "PermissionActions.java"
final class org.wildfly.security.permission.PermissionActions$TrieNode<E> {
  private static final char[] C_EMPTY;

  private static final org.wildfly.security.permission.PermissionActions$TrieNode[] T_EMPTY;

  private E result;

  private char[] matches;

  private org.wildfly.security.permission.PermissionActions$TrieNode<E>[] children;

  org.wildfly.security.permission.PermissionActions$TrieNode();
    Code:
       0: aload_0
       1: invokespecial #1                  // Method java/lang/Object."<init>":()V
       4: aload_0
       5: getstatic     #2                  // Field C_EMPTY:[C
       8: putfield      #3                  // Field matches:[C
      11: aload_0
      12: getstatic     #4                  // Field T_EMPTY:[Lorg/wildfly/security/permission/PermissionActions$TrieNode;
      15: putfield      #5                  // Field children:[Lorg/wildfly/security/permission/PermissionActions$TrieNode;
      18: return

  void put(java.lang.String, int, E);
    Code:
       0: iload_2
       1: aload_1
       2: invokevirtual #6                  // Method java/lang/String.length:()I
       5: if_icmpne     14
       8: aload_0
       9: aload_3
      10: putfield      #7                  // Field result:Ljava/lang/Object;
      13: return
      14: aload_1
      15: iload_2
      16: invokevirtual #8                  // Method java/lang/String.charAt:(I)C
      19: istore        4
      21: aload_0
      22: getfield      #3                  // Field matches:[C
      25: iload         4
      27: invokestatic  #9                  // Method java/util/Arrays.binarySearch:([CC)I
      30: istore        5
      32: iload         5
      34: ifge          164
      37: aload_0
      38: getfield      #3                  // Field matches:[C
      41: arraylength
      42: istore        6
      44: aload_0
      45: getfield      #3                  // Field matches:[C
      48: iload         6
      50: iconst_1
      51: iadd
      52: invokestatic  #10                 // Method java/util/Arrays.copyOf:([CI)[C
      55: astore        7
      57: aload_0
      58: getfield      #5                  // Field children:[Lorg/wildfly/security/permission/PermissionActions$TrieNode;
      61: iload         6
      63: iconst_1
      64: iadd
      65: invokestatic  #11                 // Method java/util/Arrays.copyOf:([Ljava/lang/Object;I)[Ljava/lang/Object;
      68: checkcast     #12                 // class "[Lorg/wildfly/security/permission/PermissionActions$TrieNode;"
      71: astore        8
      73: iload         5
      75: ineg
      76: iconst_1
      77: isub
      78: istore        9
      80: aload         7
      82: iload         9
      84: aload         7
      86: iload         9
      88: iconst_1
      89: iadd
      90: iload         6
      92: iload         9
      94: isub
      95: invokestatic  #13                 // Method java/lang/System.arraycopy:(Ljava/lang/Object;ILjava/lang/Object;II)V
      98: aload         8
     100: iload         9
     102: aload         8
     104: iload         9
     106: iconst_1
     107: iadd
     108: iload         6
     110: iload         9
     112: isub
     113: invokestatic  #13                 // Method java/lang/System.arraycopy:(Ljava/lang/Object;ILjava/lang/Object;II)V
     116: aload         7
     118: iload         9
     120: iload         4
     122: castore
     123: new           #14                 // class org/wildfly/security/permission/PermissionActions$TrieNode
     126: dup
     127: invokespecial #15                 // Method "<init>":()V
     130: astore        10
     132: aload         8
     134: iload         9
     136: aload         10
     138: aastore
     139: aload_0
     140: aload         7
     142: putfield      #3                  // Field matches:[C
     145: aload_0
     146: aload         8
     148: putfield      #5                  // Field children:[Lorg/wildfly/security/permission/PermissionActions$TrieNode;
     151: aload         10
     153: aload_1
     154: iload_2
     155: iconst_1
     156: iadd
     157: aload_3
     158: invokevirtual #16                 // Method put:(Ljava/lang/String;ILjava/lang/Object;)V
     161: goto          179
     164: aload_0
     165: getfield      #5                  // Field children:[Lorg/wildfly/security/permission/PermissionActions$TrieNode;
     168: iload         5
     170: aaload
     171: aload_1
     172: iload_2
     173: iconst_1
     174: iadd
     175: aload_3
     176: invokevirtual #16                 // Method put:(Ljava/lang/String;ILjava/lang/Object;)V
     179: return

  E get(java.lang.String, int, int);
    Code:
       0: iload_2
       1: iload_3
       2: if_icmpne     10
       5: aload_0
       6: getfield      #7                  // Field result:Ljava/lang/Object;
       9: areturn
      10: aload_1
      11: iload_2
      12: invokevirtual #8                  // Method java/lang/String.charAt:(I)C
      15: istore        4
      17: aload_0
      18: getfield      #3                  // Field matches:[C
      21: iload         4
      23: invokestatic  #9                  // Method java/util/Arrays.binarySearch:([CC)I
      26: istore        5
      28: iload         5
      30: ifge          35
      33: aconst_null
      34: areturn
      35: aload_0
      36: getfield      #5                  // Field children:[Lorg/wildfly/security/permission/PermissionActions$TrieNode;
      39: iload         5
      41: aaload
      42: aload_1
      43: iload_2
      44: iconst_1
      45: iadd
      46: iload_3
      47: invokevirtual #17                 // Method get:(Ljava/lang/String;II)Ljava/lang/Object;
      50: areturn

  static {};
    Code:
       0: iconst_0
       1: newarray       char
       3: putstatic     #2                  // Field C_EMPTY:[C
       6: iconst_0
       7: anewarray     #14                 // class org/wildfly/security/permission/PermissionActions$TrieNode
      10: putstatic     #4                  // Field T_EMPTY:[Lorg/wildfly/security/permission/PermissionActions$TrieNode;
      13: return
}
