Compiled from "DoneableCertificateSigningRequest.java"
class io.dekorate.deps.kubernetes.api.model.certificates.DoneableCertificateSigningRequest$1 implements io.dekorate.deps.kubernetes.api.builder.Function<io.dekorate.deps.kubernetes.api.model.certificates.CertificateSigningRequest, io.dekorate.deps.kubernetes.api.model.certificates.CertificateSigningRequest> {
  final io.dekorate.deps.kubernetes.api.model.certificates.DoneableCertificateSigningRequest this$0;

  io.dekorate.deps.kubernetes.api.model.certificates.DoneableCertificateSigningRequest$1(io.dekorate.deps.kubernetes.api.model.certificates.DoneableCertificateSigningRequest);
    Code:
       0: aload_0
       1: aload_1
       2: putfield      #18                 // Field this$0:Lio/dekorate/deps/kubernetes/api/model/certificates/DoneableCertificateSigningRequest;
       5: aload_0
       6: invokespecial #21                 // Method java/lang/Object."<init>":()V
       9: return

  public io.dekorate.deps.kubernetes.api.model.certificates.CertificateSigningRequest apply(io.dekorate.deps.kubernetes.api.model.certificates.CertificateSigningRequest);
    Code:
       0: aload_1
       1: areturn

  public java.lang.Object apply(java.lang.Object);
    Code:
       0: aload_0
       1: aload_1
       2: checkcast     #30                 // class io/dekorate/deps/kubernetes/api/model/certificates/CertificateSigningRequest
       5: invokevirtual #32                 // Method apply:(Lio/dekorate/deps/kubernetes/api/model/certificates/CertificateSigningRequest;)Lio/dekorate/deps/kubernetes/api/model/certificates/CertificateSigningRequest;
       8: areturn
}
