Compiled from "NotificationChannel.java"
public abstract class org.sonar.api.notifications.NotificationChannel {
  public org.sonar.api.notifications.NotificationChannel();
    Code:
       0: aload_0
       1: invokespecial #13                 // Method java/lang/Object."<init>":()V
       4: return

  public java.lang.String getKey();
    Code:
       0: aload_0
       1: invokevirtual #21                 // Method java/lang/Object.getClass:()Ljava/lang/Class;
       4: invokevirtual #26                 // Method java/lang/Class.getSimpleName:()Ljava/lang/String;
       7: areturn

  public abstract boolean deliver(org.sonar.api.notifications.Notification, java.lang.String);

  public java.lang.String toString();
    Code:
       0: aload_0
       1: invokevirtual #31                 // Method getKey:()Ljava/lang/String;
       4: areturn
}
