Compiled from "JaxpSourceXmlSource.java"
public class org.hibernate.boot.jaxb.internal.JaxpSourceXmlSource extends org.hibernate.boot.jaxb.spi.XmlSource {
  private final javax.xml.transform.Source jaxpSource;

  public org.hibernate.boot.jaxb.internal.JaxpSourceXmlSource(org.hibernate.boot.jaxb.Origin, javax.xml.transform.Source);
    Code:
       0: aload_0
       1: aload_1
       2: invokespecial #1                  // Method org/hibernate/boot/jaxb/spi/XmlSource."<init>":(Lorg/hibernate/boot/jaxb/Origin;)V
       5: aload_0
       6: aload_2
       7: putfield      #2                  // Field jaxpSource:Ljavax/xml/transform/Source;
      10: return

  public org.hibernate.boot.jaxb.spi.Binding doBind(org.hibernate.boot.jaxb.spi.Binder);
    Code:
       0: aload_1
       1: aload_0
       2: getfield      #2                  // Field jaxpSource:Ljavax/xml/transform/Source;
       5: aload_0
       6: invokevirtual #3                  // Method getOrigin:()Lorg/hibernate/boot/jaxb/Origin;
       9: invokeinterface #4,  3            // InterfaceMethod org/hibernate/boot/jaxb/spi/Binder.bind:(Ljavax/xml/transform/Source;Lorg/hibernate/boot/jaxb/Origin;)Lorg/hibernate/boot/jaxb/spi/Binding;
      14: areturn
}
