Compiled from "ApacheHttpClient4Executor.java"
final class org.jboss.resteasy.client.core.executors.ApacheHttpClient4Executor$MemoryUnit extends java.lang.Enum<org.jboss.resteasy.client.core.executors.ApacheHttpClient4Executor$MemoryUnit> {
  public static final org.jboss.resteasy.client.core.executors.ApacheHttpClient4Executor$MemoryUnit BY;

  public static final org.jboss.resteasy.client.core.executors.ApacheHttpClient4Executor$MemoryUnit KB;

  public static final org.jboss.resteasy.client.core.executors.ApacheHttpClient4Executor$MemoryUnit MB;

  public static final org.jboss.resteasy.client.core.executors.ApacheHttpClient4Executor$MemoryUnit GB;

  private static final org.jboss.resteasy.client.core.executors.ApacheHttpClient4Executor$MemoryUnit[] $VALUES;

  public static org.jboss.resteasy.client.core.executors.ApacheHttpClient4Executor$MemoryUnit[] values();
    Code:
       0: getstatic     #1                  // Field $VALUES:[Lorg/jboss/resteasy/client/core/executors/ApacheHttpClient4Executor$MemoryUnit;
       3: invokevirtual #2                  // Method "[Lorg/jboss/resteasy/client/core/executors/ApacheHttpClient4Executor$MemoryUnit;".clone:()Ljava/lang/Object;
       6: checkcast     #3                  // class "[Lorg/jboss/resteasy/client/core/executors/ApacheHttpClient4Executor$MemoryUnit;"
       9: areturn

  public static org.jboss.resteasy.client.core.executors.ApacheHttpClient4Executor$MemoryUnit valueOf(java.lang.String);
    Code:
       0: ldc           #4                  // class org/jboss/resteasy/client/core/executors/ApacheHttpClient4Executor$MemoryUnit
       2: aload_0
       3: invokestatic  #5                  // Method java/lang/Enum.valueOf:(Ljava/lang/Class;Ljava/lang/String;)Ljava/lang/Enum;
       6: checkcast     #4                  // class org/jboss/resteasy/client/core/executors/ApacheHttpClient4Executor$MemoryUnit
       9: areturn

  private org.jboss.resteasy.client.core.executors.ApacheHttpClient4Executor$MemoryUnit();
    Code:
       0: aload_0
       1: aload_1
       2: iload_2
       3: invokespecial #6                  // Method java/lang/Enum."<init>":(Ljava/lang/String;I)V
       6: return

  static {};
    Code:
       0: new           #4                  // class org/jboss/resteasy/client/core/executors/ApacheHttpClient4Executor$MemoryUnit
       3: dup
       4: ldc           #7                  // String BY
       6: iconst_0
       7: invokespecial #8                  // Method "<init>":(Ljava/lang/String;I)V
      10: putstatic     #9                  // Field BY:Lorg/jboss/resteasy/client/core/executors/ApacheHttpClient4Executor$MemoryUnit;
      13: new           #4                  // class org/jboss/resteasy/client/core/executors/ApacheHttpClient4Executor$MemoryUnit
      16: dup
      17: ldc           #10                 // String KB
      19: iconst_1
      20: invokespecial #8                  // Method "<init>":(Ljava/lang/String;I)V
      23: putstatic     #11                 // Field KB:Lorg/jboss/resteasy/client/core/executors/ApacheHttpClient4Executor$MemoryUnit;
      26: new           #4                  // class org/jboss/resteasy/client/core/executors/ApacheHttpClient4Executor$MemoryUnit
      29: dup
      30: ldc           #12                 // String MB
      32: iconst_2
      33: invokespecial #8                  // Method "<init>":(Ljava/lang/String;I)V
      36: putstatic     #13                 // Field MB:Lorg/jboss/resteasy/client/core/executors/ApacheHttpClient4Executor$MemoryUnit;
      39: new           #4                  // class org/jboss/resteasy/client/core/executors/ApacheHttpClient4Executor$MemoryUnit
      42: dup
      43: ldc           #14                 // String GB
      45: iconst_3
      46: invokespecial #8                  // Method "<init>":(Ljava/lang/String;I)V
      49: putstatic     #15                 // Field GB:Lorg/jboss/resteasy/client/core/executors/ApacheHttpClient4Executor$MemoryUnit;
      52: iconst_4
      53: anewarray     #4                  // class org/jboss/resteasy/client/core/executors/ApacheHttpClient4Executor$MemoryUnit
      56: dup
      57: iconst_0
      58: getstatic     #9                  // Field BY:Lorg/jboss/resteasy/client/core/executors/ApacheHttpClient4Executor$MemoryUnit;
      61: aastore
      62: dup
      63: iconst_1
      64: getstatic     #11                 // Field KB:Lorg/jboss/resteasy/client/core/executors/ApacheHttpClient4Executor$MemoryUnit;
      67: aastore
      68: dup
      69: iconst_2
      70: getstatic     #13                 // Field MB:Lorg/jboss/resteasy/client/core/executors/ApacheHttpClient4Executor$MemoryUnit;
      73: aastore
      74: dup
      75: iconst_3
      76: getstatic     #15                 // Field GB:Lorg/jboss/resteasy/client/core/executors/ApacheHttpClient4Executor$MemoryUnit;
      79: aastore
      80: putstatic     #1                  // Field $VALUES:[Lorg/jboss/resteasy/client/core/executors/ApacheHttpClient4Executor$MemoryUnit;
      83: return
}
