Compiled from "ResourceHandlerFunction.java"
class org.springframework.web.servlet.function.ResourceHandlerFunction implements org.springframework.web.servlet.function.HandlerFunction<org.springframework.web.servlet.function.ServerResponse> {
  private static final java.util.Set<org.springframework.http.HttpMethod> SUPPORTED_METHODS;

  private final org.springframework.core.io.Resource resource;

  public org.springframework.web.servlet.function.ResourceHandlerFunction(org.springframework.core.io.Resource);
    Code:
       0: aload_0
       1: invokespecial #1                  // Method java/lang/Object."<init>":()V
       4: aload_0
       5: aload_1
       6: putfield      #2                  // Field resource:Lorg/springframework/core/io/Resource;
       9: return

  public org.springframework.web.servlet.function.ServerResponse handle(org.springframework.web.servlet.function.ServerRequest);
    Code:
       0: aload_1
       1: invokeinterface #3,  1            // InterfaceMethod org/springframework/web/servlet/function/ServerRequest.method:()Lorg/springframework/http/HttpMethod;
       6: astore_2
       7: aload_2
       8: ifnull        99
      11: getstatic     #4                  // Field org/springframework/web/servlet/function/ResourceHandlerFunction$1.$SwitchMap$org$springframework$http$HttpMethod:[I
      14: aload_2
      15: invokevirtual #5                  // Method org/springframework/http/HttpMethod.ordinal:()I
      18: iaload
      19: tableswitch   { // 1 to 3
                     1: 44
                     2: 57
                     3: 79
               default: 99
          }
      44: aload_0
      45: getfield      #2                  // Field resource:Lorg/springframework/core/io/Resource;
      48: invokestatic  #6                  // InterfaceMethod org/springframework/web/servlet/function/EntityResponse.fromObject:(Ljava/lang/Object;)Lorg/springframework/web/servlet/function/EntityResponse$Builder;
      51: invokeinterface #7,  1            // InterfaceMethod org/springframework/web/servlet/function/EntityResponse$Builder.build:()Lorg/springframework/web/servlet/function/EntityResponse;
      56: areturn
      57: new           #8                  // class org/springframework/web/servlet/function/ResourceHandlerFunction$HeadMethodResource
      60: dup
      61: aload_0
      62: getfield      #2                  // Field resource:Lorg/springframework/core/io/Resource;
      65: invokespecial #9                  // Method org/springframework/web/servlet/function/ResourceHandlerFunction$HeadMethodResource."<init>":(Lorg/springframework/core/io/Resource;)V
      68: astore_3
      69: aload_3
      70: invokestatic  #6                  // InterfaceMethod org/springframework/web/servlet/function/EntityResponse.fromObject:(Ljava/lang/Object;)Lorg/springframework/web/servlet/function/EntityResponse$Builder;
      73: invokeinterface #7,  1            // InterfaceMethod org/springframework/web/servlet/function/EntityResponse$Builder.build:()Lorg/springframework/web/servlet/function/EntityResponse;
      78: areturn
      79: invokestatic  #10                 // InterfaceMethod org/springframework/web/servlet/function/ServerResponse.ok:()Lorg/springframework/web/servlet/function/ServerResponse$BodyBuilder;
      82: getstatic     #11                 // Field SUPPORTED_METHODS:Ljava/util/Set;
      85: invokeinterface #12,  2           // InterfaceMethod org/springframework/web/servlet/function/ServerResponse$BodyBuilder.allow:(Ljava/util/Set;)Lorg/springframework/web/servlet/function/ServerResponse$HeadersBuilder;
      90: checkcast     #13                 // class org/springframework/web/servlet/function/ServerResponse$BodyBuilder
      93: invokeinterface #14,  1           // InterfaceMethod org/springframework/web/servlet/function/ServerResponse$BodyBuilder.build:()Lorg/springframework/web/servlet/function/ServerResponse;
      98: areturn
      99: getstatic     #15                 // Field org/springframework/http/HttpStatus.METHOD_NOT_ALLOWED:Lorg/springframework/http/HttpStatus;
     102: invokestatic  #16                 // InterfaceMethod org/springframework/web/servlet/function/ServerResponse.status:(Lorg/springframework/http/HttpStatus;)Lorg/springframework/web/servlet/function/ServerResponse$BodyBuilder;
     105: getstatic     #11                 // Field SUPPORTED_METHODS:Ljava/util/Set;
     108: invokeinterface #12,  2           // InterfaceMethod org/springframework/web/servlet/function/ServerResponse$BodyBuilder.allow:(Ljava/util/Set;)Lorg/springframework/web/servlet/function/ServerResponse$HeadersBuilder;
     113: checkcast     #13                 // class org/springframework/web/servlet/function/ServerResponse$BodyBuilder
     116: invokeinterface #14,  1           // InterfaceMethod org/springframework/web/servlet/function/ServerResponse$BodyBuilder.build:()Lorg/springframework/web/servlet/function/ServerResponse;
     121: areturn

  static {};
    Code:
       0: getstatic     #17                 // Field org/springframework/http/HttpMethod.GET:Lorg/springframework/http/HttpMethod;
       3: getstatic     #18                 // Field org/springframework/http/HttpMethod.HEAD:Lorg/springframework/http/HttpMethod;
       6: getstatic     #19                 // Field org/springframework/http/HttpMethod.OPTIONS:Lorg/springframework/http/HttpMethod;
       9: invokestatic  #20                 // Method java/util/EnumSet.of:(Ljava/lang/Enum;Ljava/lang/Enum;Ljava/lang/Enum;)Ljava/util/EnumSet;
      12: putstatic     #11                 // Field SUPPORTED_METHODS:Ljava/util/Set;
      15: return
}
