Compiled from "ServerResponse.java"
public interface org.springframework.web.servlet.function.ServerResponse {
  public abstract org.springframework.http.HttpStatus statusCode();

  public abstract int rawStatusCode();

  public abstract org.springframework.http.HttpHeaders headers();

  public abstract org.springframework.util.MultiValueMap<java.lang.String, javax.servlet.http.Cookie> cookies();

  public abstract org.springframework.web.servlet.ModelAndView writeTo(javax.servlet.http.HttpServletRequest, javax.servlet.http.HttpServletResponse, org.springframework.web.servlet.function.ServerResponse$Context) throws javax.servlet.ServletException, java.io.IOException;

  public static org.springframework.web.servlet.function.ServerResponse$BodyBuilder from(org.springframework.web.servlet.function.ServerResponse);
    Code:
       0: new           #1                  // class org/springframework/web/servlet/function/DefaultServerResponseBuilder
       3: dup
       4: aload_0
       5: invokespecial #2                  // Method org/springframework/web/servlet/function/DefaultServerResponseBuilder."<init>":(Lorg/springframework/web/servlet/function/ServerResponse;)V
       8: areturn

  public static org.springframework.web.servlet.function.ServerResponse$BodyBuilder status(org.springframework.http.HttpStatus);
    Code:
       0: new           #1                  // class org/springframework/web/servlet/function/DefaultServerResponseBuilder
       3: dup
       4: aload_0
       5: invokespecial #3                  // Method org/springframework/web/servlet/function/DefaultServerResponseBuilder."<init>":(Lorg/springframework/http/HttpStatus;)V
       8: areturn

  public static org.springframework.web.servlet.function.ServerResponse$BodyBuilder status(int);
    Code:
       0: new           #1                  // class org/springframework/web/servlet/function/DefaultServerResponseBuilder
       3: dup
       4: iload_0
       5: invokespecial #4                  // Method org/springframework/web/servlet/function/DefaultServerResponseBuilder."<init>":(I)V
       8: areturn

  public static org.springframework.web.servlet.function.ServerResponse$BodyBuilder ok();
    Code:
       0: getstatic     #5                  // Field org/springframework/http/HttpStatus.OK:Lorg/springframework/http/HttpStatus;
       3: invokestatic  #6                  // InterfaceMethod status:(Lorg/springframework/http/HttpStatus;)Lorg/springframework/web/servlet/function/ServerResponse$BodyBuilder;
       6: areturn

  public static org.springframework.web.servlet.function.ServerResponse$BodyBuilder created(java.net.URI);
    Code:
       0: getstatic     #7                  // Field org/springframework/http/HttpStatus.CREATED:Lorg/springframework/http/HttpStatus;
       3: invokestatic  #6                  // InterfaceMethod status:(Lorg/springframework/http/HttpStatus;)Lorg/springframework/web/servlet/function/ServerResponse$BodyBuilder;
       6: astore_1
       7: aload_1
       8: aload_0
       9: invokeinterface #8,  2            // InterfaceMethod org/springframework/web/servlet/function/ServerResponse$BodyBuilder.location:(Ljava/net/URI;)Lorg/springframework/web/servlet/function/ServerResponse$HeadersBuilder;
      14: checkcast     #9                  // class org/springframework/web/servlet/function/ServerResponse$BodyBuilder
      17: areturn

  public static org.springframework.web.servlet.function.ServerResponse$BodyBuilder accepted();
    Code:
       0: getstatic     #10                 // Field org/springframework/http/HttpStatus.ACCEPTED:Lorg/springframework/http/HttpStatus;
       3: invokestatic  #6                  // InterfaceMethod status:(Lorg/springframework/http/HttpStatus;)Lorg/springframework/web/servlet/function/ServerResponse$BodyBuilder;
       6: areturn

  public static org.springframework.web.servlet.function.ServerResponse$HeadersBuilder<?> noContent();
    Code:
       0: getstatic     #11                 // Field org/springframework/http/HttpStatus.NO_CONTENT:Lorg/springframework/http/HttpStatus;
       3: invokestatic  #6                  // InterfaceMethod status:(Lorg/springframework/http/HttpStatus;)Lorg/springframework/web/servlet/function/ServerResponse$BodyBuilder;
       6: areturn

  public static org.springframework.web.servlet.function.ServerResponse$BodyBuilder seeOther(java.net.URI);
    Code:
       0: getstatic     #12                 // Field org/springframework/http/HttpStatus.SEE_OTHER:Lorg/springframework/http/HttpStatus;
       3: invokestatic  #6                  // InterfaceMethod status:(Lorg/springframework/http/HttpStatus;)Lorg/springframework/web/servlet/function/ServerResponse$BodyBuilder;
       6: astore_1
       7: aload_1
       8: aload_0
       9: invokeinterface #8,  2            // InterfaceMethod org/springframework/web/servlet/function/ServerResponse$BodyBuilder.location:(Ljava/net/URI;)Lorg/springframework/web/servlet/function/ServerResponse$HeadersBuilder;
      14: checkcast     #9                  // class org/springframework/web/servlet/function/ServerResponse$BodyBuilder
      17: areturn

  public static org.springframework.web.servlet.function.ServerResponse$BodyBuilder temporaryRedirect(java.net.URI);
    Code:
       0: getstatic     #13                 // Field org/springframework/http/HttpStatus.TEMPORARY_REDIRECT:Lorg/springframework/http/HttpStatus;
       3: invokestatic  #6                  // InterfaceMethod status:(Lorg/springframework/http/HttpStatus;)Lorg/springframework/web/servlet/function/ServerResponse$BodyBuilder;
       6: astore_1
       7: aload_1
       8: aload_0
       9: invokeinterface #8,  2            // InterfaceMethod org/springframework/web/servlet/function/ServerResponse$BodyBuilder.location:(Ljava/net/URI;)Lorg/springframework/web/servlet/function/ServerResponse$HeadersBuilder;
      14: checkcast     #9                  // class org/springframework/web/servlet/function/ServerResponse$BodyBuilder
      17: areturn

  public static org.springframework.web.servlet.function.ServerResponse$BodyBuilder permanentRedirect(java.net.URI);
    Code:
       0: getstatic     #14                 // Field org/springframework/http/HttpStatus.PERMANENT_REDIRECT:Lorg/springframework/http/HttpStatus;
       3: invokestatic  #6                  // InterfaceMethod status:(Lorg/springframework/http/HttpStatus;)Lorg/springframework/web/servlet/function/ServerResponse$BodyBuilder;
       6: astore_1
       7: aload_1
       8: aload_0
       9: invokeinterface #8,  2            // InterfaceMethod org/springframework/web/servlet/function/ServerResponse$BodyBuilder.location:(Ljava/net/URI;)Lorg/springframework/web/servlet/function/ServerResponse$HeadersBuilder;
      14: checkcast     #9                  // class org/springframework/web/servlet/function/ServerResponse$BodyBuilder
      17: areturn

  public static org.springframework.web.servlet.function.ServerResponse$BodyBuilder badRequest();
    Code:
       0: getstatic     #15                 // Field org/springframework/http/HttpStatus.BAD_REQUEST:Lorg/springframework/http/HttpStatus;
       3: invokestatic  #6                  // InterfaceMethod status:(Lorg/springframework/http/HttpStatus;)Lorg/springframework/web/servlet/function/ServerResponse$BodyBuilder;
       6: areturn

  public static org.springframework.web.servlet.function.ServerResponse$HeadersBuilder<?> notFound();
    Code:
       0: getstatic     #16                 // Field org/springframework/http/HttpStatus.NOT_FOUND:Lorg/springframework/http/HttpStatus;
       3: invokestatic  #6                  // InterfaceMethod status:(Lorg/springframework/http/HttpStatus;)Lorg/springframework/web/servlet/function/ServerResponse$BodyBuilder;
       6: areturn

  public static org.springframework.web.servlet.function.ServerResponse$BodyBuilder unprocessableEntity();
    Code:
       0: getstatic     #17                 // Field org/springframework/http/HttpStatus.UNPROCESSABLE_ENTITY:Lorg/springframework/http/HttpStatus;
       3: invokestatic  #6                  // InterfaceMethod status:(Lorg/springframework/http/HttpStatus;)Lorg/springframework/web/servlet/function/ServerResponse$BodyBuilder;
       6: areturn
}
