Compiled from "WebSocketProcessor.java"
public final class org.atmosphere.websocket.WebSocketProcessor$WebSocketException extends java.lang.Exception {
  private final org.atmosphere.cpr.AtmosphereResponse r;

  public org.atmosphere.websocket.WebSocketProcessor$WebSocketException(java.lang.String, org.atmosphere.cpr.AtmosphereResponse);
    Code:
       0: aload_0
       1: aload_1
       2: invokespecial #1                  // Method java/lang/Exception."<init>":(Ljava/lang/String;)V
       5: aload_0
       6: aload_2
       7: putfield      #2                  // Field r:Lorg/atmosphere/cpr/AtmosphereResponse;
      10: return

  public org.atmosphere.websocket.WebSocketProcessor$WebSocketException(java.lang.Throwable, org.atmosphere.cpr.AtmosphereResponse);
    Code:
       0: aload_0
       1: aload_1
       2: invokespecial #3                  // Method java/lang/Exception."<init>":(Ljava/lang/Throwable;)V
       5: aload_0
       6: aload_2
       7: putfield      #2                  // Field r:Lorg/atmosphere/cpr/AtmosphereResponse;
      10: return

  public org.atmosphere.cpr.AtmosphereResponse response();
    Code:
       0: aload_0
       1: getfield      #2                  // Field r:Lorg/atmosphere/cpr/AtmosphereResponse;
       4: areturn
}
