Compiled from "WebSocketProcessorAdapter.java"
public class org.atmosphere.websocket.WebSocketProcessorAdapter implements org.atmosphere.websocket.WebSocketProcessor {
  public org.atmosphere.websocket.WebSocketProcessorAdapter();
    Code:
       0: aload_0
       1: invokespecial #1                  // Method java/lang/Object."<init>":()V
       4: return

  public org.atmosphere.websocket.WebSocketProcessor configure(org.atmosphere.cpr.AtmosphereConfig);
    Code:
       0: aload_0
       1: areturn

  public boolean handshake(javax.servlet.http.HttpServletRequest);
    Code:
       0: iconst_1
       1: ireturn

  public org.atmosphere.websocket.WebSocketProcessor registerWebSocketHandler(java.lang.String, org.atmosphere.websocket.WebSocketProcessor$WebSocketHandlerProxy);
    Code:
       0: aload_0
       1: areturn

  public void open(org.atmosphere.websocket.WebSocket, org.atmosphere.cpr.AtmosphereRequest, org.atmosphere.cpr.AtmosphereResponse) throws java.io.IOException;
    Code:
       0: return

  public void invokeWebSocketProtocol(org.atmosphere.websocket.WebSocket, java.lang.String);
    Code:
       0: return

  public void invokeWebSocketProtocol(org.atmosphere.websocket.WebSocket, java.io.InputStream);
    Code:
       0: return

  public void invokeWebSocketProtocol(org.atmosphere.websocket.WebSocket, java.io.Reader);
    Code:
       0: return

  public void invokeWebSocketProtocol(org.atmosphere.websocket.WebSocket, byte[], int, int);
    Code:
       0: return

  public void close(org.atmosphere.websocket.WebSocket, int);
    Code:
       0: return

  public void notifyListener(org.atmosphere.websocket.WebSocket, org.atmosphere.websocket.WebSocketEventListener$WebSocketEvent);
    Code:
       0: return

  public void destroy();
    Code:
       0: return
}
