Compiled from "PersistS3.java"
class water.persist.PersistS3$KeyCache extends water.persist.PersistS3$Cache {
  private final java.lang.String _keyPrefix;

  private final java.lang.String _bucket;

  public water.persist.PersistS3$KeyCache(java.lang.String);
    Code:
       0: aload_0
       1: aconst_null
       2: invokespecial #1                  // Method water/persist/PersistS3$Cache."<init>":(Lwater/persist/PersistS3$1;)V
       5: aload_0
       6: aload_1
       7: putfield      #2                  // Field _bucket:Ljava/lang/String;
      10: aload_0
      11: new           #3                  // class java/lang/StringBuilder
      14: dup
      15: invokespecial #4                  // Method java/lang/StringBuilder."<init>":()V
      18: aload_0
      19: aload_1
      20: invokespecial #5                  // Method water/persist/PersistS3$Cache.wrapKey:(Ljava/lang/String;)Ljava/lang/String;
      23: invokevirtual #6                  // Method java/lang/StringBuilder.append:(Ljava/lang/String;)Ljava/lang/StringBuilder;
      26: ldc           #7                  // String /
      28: invokevirtual #6                  // Method java/lang/StringBuilder.append:(Ljava/lang/String;)Ljava/lang/StringBuilder;
      31: invokevirtual #8                  // Method java/lang/StringBuilder.toString:()Ljava/lang/String;
      34: putfield      #9                  // Field _keyPrefix:Ljava/lang/String;
      37: return

  protected java.lang.String[] update();
    Code:
       0: invokestatic  #10                 // Method water/persist/PersistS3.getClient:()Lcom/amazonaws/services/s3/AmazonS3;
       3: astore_1
       4: aload_1
       5: aload_0
       6: getfield      #2                  // Field _bucket:Ljava/lang/String;
       9: ldc           #11                 // String
      11: invokeinterface #12,  3           // InterfaceMethod com/amazonaws/services/s3/AmazonS3.listObjects:(Ljava/lang/String;Ljava/lang/String;)Lcom/amazonaws/services/s3/model/ObjectListing;
      16: astore_2
      17: new           #13                 // class java/util/ArrayList
      20: dup
      21: invokespecial #14                 // Method java/util/ArrayList."<init>":()V
      24: astore_3
      25: aload_2
      26: aload_3
      27: aconst_null
      28: iconst_0
      29: invokestatic  #15                 // Method water/persist/PersistS3.access$100:(Lcom/amazonaws/services/s3/model/ObjectListing;Ljava/util/ArrayList;Ljava/util/ArrayList;Z)V
      32: aload_2
      33: invokevirtual #16                 // Method com/amazonaws/services/s3/model/ObjectListing.isTruncated:()Z
      36: ifeq          57
      39: aload_1
      40: aload_2
      41: invokeinterface #17,  2           // InterfaceMethod com/amazonaws/services/s3/AmazonS3.listNextBatchOfObjects:(Lcom/amazonaws/services/s3/model/ObjectListing;)Lcom/amazonaws/services/s3/model/ObjectListing;
      46: astore_2
      47: aload_2
      48: aload_3
      49: aconst_null
      50: iconst_0
      51: invokestatic  #15                 // Method water/persist/PersistS3.access$100:(Lcom/amazonaws/services/s3/model/ObjectListing;Ljava/util/ArrayList;Ljava/util/ArrayList;Z)V
      54: goto          32
      57: aload_3
      58: invokestatic  #18                 // Method java/util/Collections.sort:(Ljava/util/List;)V
      61: aload_0
      62: aload_3
      63: aload_3
      64: invokevirtual #19                 // Method java/util/ArrayList.size:()I
      67: anewarray     #20                 // class java/lang/String
      70: invokevirtual #21                 // Method java/util/ArrayList.toArray:([Ljava/lang/Object;)[Ljava/lang/Object;
      73: checkcast     #22                 // class "[Ljava/lang/String;"
      76: dup_x1
      77: putfield      #23                 // Field _cache:[Ljava/lang/String;
      80: areturn

  protected java.lang.String wrapKey(java.lang.String);
    Code:
       0: new           #3                  // class java/lang/StringBuilder
       3: dup
       4: invokespecial #4                  // Method java/lang/StringBuilder."<init>":()V
       7: aload_0
       8: getfield      #9                  // Field _keyPrefix:Ljava/lang/String;
      11: invokevirtual #6                  // Method java/lang/StringBuilder.append:(Ljava/lang/String;)Ljava/lang/StringBuilder;
      14: aload_1
      15: invokevirtual #6                  // Method java/lang/StringBuilder.append:(Ljava/lang/String;)Ljava/lang/StringBuilder;
      18: invokevirtual #8                  // Method java/lang/StringBuilder.toString:()Ljava/lang/String;
      21: areturn
}
