Compiled from "RetryUntilElapsed.java"
public class org.apache.curator.retry.RetryUntilElapsed extends org.apache.curator.retry.SleepingRetry {
  private final int maxElapsedTimeMs;

  private final int sleepMsBetweenRetries;

  public org.apache.curator.retry.RetryUntilElapsed(int, int);
    Code:
       0: aload_0
       1: ldc           #11                 // int 2147483647
       3: invokespecial #14                 // Method org/apache/curator/retry/SleepingRetry."<init>":(I)V
       6: aload_0
       7: iload_1
       8: putfield      #16                 // Field maxElapsedTimeMs:I
      11: aload_0
      12: iload_2
      13: putfield      #18                 // Field sleepMsBetweenRetries:I
      16: return

  public boolean allowRetry(int, long, org.apache.curator.RetrySleeper);
    Code:
       0: aload_0
       1: iload_1
       2: lload_2
       3: aload         4
       5: invokespecial #24                 // Method org/apache/curator/retry/SleepingRetry.allowRetry:(IJLorg/apache/curator/RetrySleeper;)Z
       8: ifeq          25
      11: lload_2
      12: aload_0
      13: getfield      #16                 // Field maxElapsedTimeMs:I
      16: i2l
      17: lcmp
      18: ifge          25
      21: iconst_1
      22: goto          26
      25: iconst_0
      26: ireturn

  protected long getSleepTimeMs(int, long);
    Code:
       0: aload_0
       1: getfield      #18                 // Field sleepMsBetweenRetries:I
       4: i2l
       5: lreturn

  public int getN();
    Code:
       0: aload_0
       1: invokespecial #35                 // Method org/apache/curator/retry/SleepingRetry.getN:()I
       4: ireturn
}
