Compiled from "HttpException.java"
public class org.apache.jena.atlas.web.HttpException extends java.lang.RuntimeException {
  private static final long serialVersionUID;

  private int responseCode;

  private java.lang.String statusLine;

  private java.lang.String response;

  public org.apache.jena.atlas.web.HttpException(int, java.lang.String, java.lang.String);
    Code:
       0: aload_0
       1: new           #1                  // class java/lang/StringBuilder
       4: dup
       5: invokespecial #2                  // Method java/lang/StringBuilder."<init>":()V
       8: iload_1
       9: invokevirtual #3                  // Method java/lang/StringBuilder.append:(I)Ljava/lang/StringBuilder;
      12: ldc           #4                  // String  -
      14: invokevirtual #5                  // Method java/lang/StringBuilder.append:(Ljava/lang/String;)Ljava/lang/StringBuilder;
      17: aload_2
      18: invokevirtual #5                  // Method java/lang/StringBuilder.append:(Ljava/lang/String;)Ljava/lang/StringBuilder;
      21: invokevirtual #6                  // Method java/lang/StringBuilder.toString:()Ljava/lang/String;
      24: invokespecial #7                  // Method java/lang/RuntimeException."<init>":(Ljava/lang/String;)V
      27: aload_0
      28: iconst_m1
      29: putfield      #8                  // Field responseCode:I
      32: aload_0
      33: aconst_null
      34: putfield      #9                  // Field statusLine:Ljava/lang/String;
      37: aload_0
      38: iload_1
      39: putfield      #8                  // Field responseCode:I
      42: aload_0
      43: aload_2
      44: putfield      #9                  // Field statusLine:Ljava/lang/String;
      47: aload_0
      48: aload_3
      49: putfield      #10                 // Field response:Ljava/lang/String;
      52: return

  public org.apache.jena.atlas.web.HttpException(java.lang.String);
    Code:
       0: aload_0
       1: aload_1
       2: invokespecial #7                  // Method java/lang/RuntimeException."<init>":(Ljava/lang/String;)V
       5: aload_0
       6: iconst_m1
       7: putfield      #8                  // Field responseCode:I
      10: aload_0
      11: aconst_null
      12: putfield      #9                  // Field statusLine:Ljava/lang/String;
      15: return

  public org.apache.jena.atlas.web.HttpException(java.lang.String, java.lang.Throwable);
    Code:
       0: aload_0
       1: aload_1
       2: aload_2
       3: invokespecial #11                 // Method java/lang/RuntimeException."<init>":(Ljava/lang/String;Ljava/lang/Throwable;)V
       6: aload_0
       7: iconst_m1
       8: putfield      #8                  // Field responseCode:I
      11: aload_0
      12: aconst_null
      13: putfield      #9                  // Field statusLine:Ljava/lang/String;
      16: return

  public org.apache.jena.atlas.web.HttpException(java.lang.Throwable);
    Code:
       0: aload_0
       1: aload_1
       2: invokespecial #12                 // Method java/lang/RuntimeException."<init>":(Ljava/lang/Throwable;)V
       5: aload_0
       6: iconst_m1
       7: putfield      #8                  // Field responseCode:I
      10: aload_0
      11: aconst_null
      12: putfield      #9                  // Field statusLine:Ljava/lang/String;
      15: return

  public int getResponseCode();
    Code:
       0: aload_0
       1: getfield      #8                  // Field responseCode:I
       4: ireturn

  public java.lang.String getStatusLine();
    Code:
       0: aload_0
       1: getfield      #9                  // Field statusLine:Ljava/lang/String;
       4: areturn

  public java.lang.String getResponse();
    Code:
       0: aload_0
       1: getfield      #10                 // Field response:Ljava/lang/String;
       4: areturn
}
