Compiled from "Properties.scala"
public final class almond.api.Properties {
  public static java.lang.String actualScalaVersion();
    Code:
       0: getstatic     #16                 // Field almond/api/Properties$.MODULE$:Lalmond/api/Properties$;
       3: invokevirtual #18                 // Method almond/api/Properties$.actualScalaVersion:()Ljava/lang/String;
       6: areturn

  public static scala.Option<java.lang.String> defaultScalafmtVersionOpt();
    Code:
       0: getstatic     #16                 // Field almond/api/Properties$.MODULE$:Lalmond/api/Properties$;
       3: invokevirtual #23                 // Method almond/api/Properties$.defaultScalafmtVersionOpt:()Lscala/Option;
       6: areturn

  public static java.lang.String ammoniteSparkVersion();
    Code:
       0: getstatic     #16                 // Field almond/api/Properties$.MODULE$:Lalmond/api/Properties$;
       3: invokevirtual #26                 // Method almond/api/Properties$.ammoniteSparkVersion:()Ljava/lang/String;
       6: areturn

  public static java.lang.String commitHash();
    Code:
       0: getstatic     #16                 // Field almond/api/Properties$.MODULE$:Lalmond/api/Properties$;
       3: invokevirtual #29                 // Method almond/api/Properties$.commitHash:()Ljava/lang/String;
       6: areturn

  public static java.lang.String version();
    Code:
       0: getstatic     #16                 // Field almond/api/Properties$.MODULE$:Lalmond/api/Properties$;
       3: invokevirtual #32                 // Method almond/api/Properties$.version:()Ljava/lang/String;
       6: areturn
}
