Compiled from "TokenBuffer.java"
public final class com.fasterxml.jackson.databind.util.TokenBuffer$Parser extends com.fasterxml.jackson.core.base.ParserMinimalBase {
  protected com.fasterxml.jackson.core.ObjectCodec _codec;

  protected final boolean _hasNativeTypeIds;

  protected final boolean _hasNativeObjectIds;

  protected final boolean _hasNativeIds;

  protected com.fasterxml.jackson.databind.util.TokenBuffer$Segment _segment;

  protected int _segmentPtr;

  protected com.fasterxml.jackson.core.json.JsonReadContext _parsingContext;

  protected boolean _closed;

  protected transient com.fasterxml.jackson.core.util.ByteArrayBuilder _byteBuilder;

  protected com.fasterxml.jackson.core.JsonLocation _location;

  public com.fasterxml.jackson.databind.util.TokenBuffer$Parser(com.fasterxml.jackson.databind.util.TokenBuffer$Segment, com.fasterxml.jackson.core.ObjectCodec, boolean, boolean);
    Code:
       0: aload_0
       1: iconst_0
       2: invokespecial #1                  // Method com/fasterxml/jackson/core/base/ParserMinimalBase."<init>":(I)V
       5: aload_0
       6: aconst_null
       7: putfield      #2                  // Field _location:Lcom/fasterxml/jackson/core/JsonLocation;
      10: aload_0
      11: aload_1
      12: putfield      #3                  // Field _segment:Lcom/fasterxml/jackson/databind/util/TokenBuffer$Segment;
      15: aload_0
      16: iconst_m1
      17: putfield      #4                  // Field _segmentPtr:I
      20: aload_0
      21: aload_2
      22: putfield      #5                  // Field _codec:Lcom/fasterxml/jackson/core/ObjectCodec;
      25: aload_0
      26: aconst_null
      27: invokestatic  #6                  // Method com/fasterxml/jackson/core/json/JsonReadContext.createRootContext:(Lcom/fasterxml/jackson/core/json/DupDetector;)Lcom/fasterxml/jackson/core/json/JsonReadContext;
      30: putfield      #7                  // Field _parsingContext:Lcom/fasterxml/jackson/core/json/JsonReadContext;
      33: aload_0
      34: iload_3
      35: putfield      #8                  // Field _hasNativeTypeIds:Z
      38: aload_0
      39: iload         4
      41: putfield      #9                  // Field _hasNativeObjectIds:Z
      44: aload_0
      45: iload_3
      46: iload         4
      48: ior
      49: putfield      #10                 // Field _hasNativeIds:Z
      52: return

  public void setLocation(com.fasterxml.jackson.core.JsonLocation);
    Code:
       0: aload_0
       1: aload_1
       2: putfield      #2                  // Field _location:Lcom/fasterxml/jackson/core/JsonLocation;
       5: return

  public com.fasterxml.jackson.core.ObjectCodec getCodec();
    Code:
       0: aload_0
       1: getfield      #5                  // Field _codec:Lcom/fasterxml/jackson/core/ObjectCodec;
       4: areturn

  public void setCodec(com.fasterxml.jackson.core.ObjectCodec);
    Code:
       0: aload_0
       1: aload_1
       2: putfield      #5                  // Field _codec:Lcom/fasterxml/jackson/core/ObjectCodec;
       5: return

  public com.fasterxml.jackson.core.Version version();
    Code:
       0: getstatic     #11                 // Field com/fasterxml/jackson/databind/cfg/PackageVersion.VERSION:Lcom/fasterxml/jackson/core/Version;
       3: areturn

  public com.fasterxml.jackson.core.JsonToken peekNextToken() throws java.io.IOException;
    Code:
       0: aload_0
       1: getfield      #12                 // Field _closed:Z
       4: ifeq          9
       7: aconst_null
       8: areturn
       9: aload_0
      10: getfield      #3                  // Field _segment:Lcom/fasterxml/jackson/databind/util/TokenBuffer$Segment;
      13: astore_1
      14: aload_0
      15: getfield      #4                  // Field _segmentPtr:I
      18: iconst_1
      19: iadd
      20: istore_2
      21: iload_2
      22: bipush        16
      24: if_icmplt     42
      27: iconst_0
      28: istore_2
      29: aload_1
      30: ifnonnull     37
      33: aconst_null
      34: goto          41
      37: aload_1
      38: invokevirtual #13                 // Method com/fasterxml/jackson/databind/util/TokenBuffer$Segment.next:()Lcom/fasterxml/jackson/databind/util/TokenBuffer$Segment;
      41: astore_1
      42: aload_1
      43: ifnonnull     50
      46: aconst_null
      47: goto          55
      50: aload_1
      51: iload_2
      52: invokevirtual #14                 // Method com/fasterxml/jackson/databind/util/TokenBuffer$Segment.type:(I)Lcom/fasterxml/jackson/core/JsonToken;
      55: areturn

  public void close() throws java.io.IOException;
    Code:
       0: aload_0
       1: getfield      #12                 // Field _closed:Z
       4: ifne          12
       7: aload_0
       8: iconst_1
       9: putfield      #12                 // Field _closed:Z
      12: return

  public com.fasterxml.jackson.core.JsonToken nextToken() throws java.io.IOException;
    Code:
       0: aload_0
       1: getfield      #12                 // Field _closed:Z
       4: ifne          14
       7: aload_0
       8: getfield      #3                  // Field _segment:Lcom/fasterxml/jackson/databind/util/TokenBuffer$Segment;
      11: ifnonnull     16
      14: aconst_null
      15: areturn
      16: aload_0
      17: dup
      18: getfield      #4                  // Field _segmentPtr:I
      21: iconst_1
      22: iadd
      23: dup_x1
      24: putfield      #4                  // Field _segmentPtr:I
      27: bipush        16
      29: if_icmplt     57
      32: aload_0
      33: iconst_0
      34: putfield      #4                  // Field _segmentPtr:I
      37: aload_0
      38: aload_0
      39: getfield      #3                  // Field _segment:Lcom/fasterxml/jackson/databind/util/TokenBuffer$Segment;
      42: invokevirtual #13                 // Method com/fasterxml/jackson/databind/util/TokenBuffer$Segment.next:()Lcom/fasterxml/jackson/databind/util/TokenBuffer$Segment;
      45: putfield      #3                  // Field _segment:Lcom/fasterxml/jackson/databind/util/TokenBuffer$Segment;
      48: aload_0
      49: getfield      #3                  // Field _segment:Lcom/fasterxml/jackson/databind/util/TokenBuffer$Segment;
      52: ifnonnull     57
      55: aconst_null
      56: areturn
      57: aload_0
      58: aload_0
      59: getfield      #3                  // Field _segment:Lcom/fasterxml/jackson/databind/util/TokenBuffer$Segment;
      62: aload_0
      63: getfield      #4                  // Field _segmentPtr:I
      66: invokevirtual #14                 // Method com/fasterxml/jackson/databind/util/TokenBuffer$Segment.type:(I)Lcom/fasterxml/jackson/core/JsonToken;
      69: putfield      #15                 // Field _currToken:Lcom/fasterxml/jackson/core/JsonToken;
      72: aload_0
      73: getfield      #15                 // Field _currToken:Lcom/fasterxml/jackson/core/JsonToken;
      76: getstatic     #16                 // Field com/fasterxml/jackson/core/JsonToken.FIELD_NAME:Lcom/fasterxml/jackson/core/JsonToken;
      79: if_acmpne     117
      82: aload_0
      83: invokevirtual #17                 // Method _currentObject:()Ljava/lang/Object;
      86: astore_1
      87: aload_1
      88: instanceof    #18                 // class java/lang/String
      91: ifeq          101
      94: aload_1
      95: checkcast     #18                 // class java/lang/String
      98: goto          105
     101: aload_1
     102: invokevirtual #19                 // Method java/lang/Object.toString:()Ljava/lang/String;
     105: astore_2
     106: aload_0
     107: getfield      #7                  // Field _parsingContext:Lcom/fasterxml/jackson/core/json/JsonReadContext;
     110: aload_2
     111: invokevirtual #20                 // Method com/fasterxml/jackson/core/json/JsonReadContext.setCurrentName:(Ljava/lang/String;)V
     114: goto          215
     117: aload_0
     118: getfield      #15                 // Field _currToken:Lcom/fasterxml/jackson/core/JsonToken;
     121: getstatic     #21                 // Field com/fasterxml/jackson/core/JsonToken.START_OBJECT:Lcom/fasterxml/jackson/core/JsonToken;
     124: if_acmpne     143
     127: aload_0
     128: aload_0
     129: getfield      #7                  // Field _parsingContext:Lcom/fasterxml/jackson/core/json/JsonReadContext;
     132: iconst_m1
     133: iconst_m1
     134: invokevirtual #22                 // Method com/fasterxml/jackson/core/json/JsonReadContext.createChildObjectContext:(II)Lcom/fasterxml/jackson/core/json/JsonReadContext;
     137: putfield      #7                  // Field _parsingContext:Lcom/fasterxml/jackson/core/json/JsonReadContext;
     140: goto          215
     143: aload_0
     144: getfield      #15                 // Field _currToken:Lcom/fasterxml/jackson/core/JsonToken;
     147: getstatic     #23                 // Field com/fasterxml/jackson/core/JsonToken.START_ARRAY:Lcom/fasterxml/jackson/core/JsonToken;
     150: if_acmpne     169
     153: aload_0
     154: aload_0
     155: getfield      #7                  // Field _parsingContext:Lcom/fasterxml/jackson/core/json/JsonReadContext;
     158: iconst_m1
     159: iconst_m1
     160: invokevirtual #24                 // Method com/fasterxml/jackson/core/json/JsonReadContext.createChildArrayContext:(II)Lcom/fasterxml/jackson/core/json/JsonReadContext;
     163: putfield      #7                  // Field _parsingContext:Lcom/fasterxml/jackson/core/json/JsonReadContext;
     166: goto          215
     169: aload_0
     170: getfield      #15                 // Field _currToken:Lcom/fasterxml/jackson/core/JsonToken;
     173: getstatic     #25                 // Field com/fasterxml/jackson/core/JsonToken.END_OBJECT:Lcom/fasterxml/jackson/core/JsonToken;
     176: if_acmpeq     189
     179: aload_0
     180: getfield      #15                 // Field _currToken:Lcom/fasterxml/jackson/core/JsonToken;
     183: getstatic     #26                 // Field com/fasterxml/jackson/core/JsonToken.END_ARRAY:Lcom/fasterxml/jackson/core/JsonToken;
     186: if_acmpne     215
     189: aload_0
     190: aload_0
     191: getfield      #7                  // Field _parsingContext:Lcom/fasterxml/jackson/core/json/JsonReadContext;
     194: invokevirtual #27                 // Method com/fasterxml/jackson/core/json/JsonReadContext.getParent:()Lcom/fasterxml/jackson/core/json/JsonReadContext;
     197: putfield      #7                  // Field _parsingContext:Lcom/fasterxml/jackson/core/json/JsonReadContext;
     200: aload_0
     201: getfield      #7                  // Field _parsingContext:Lcom/fasterxml/jackson/core/json/JsonReadContext;
     204: ifnonnull     215
     207: aload_0
     208: aconst_null
     209: invokestatic  #6                  // Method com/fasterxml/jackson/core/json/JsonReadContext.createRootContext:(Lcom/fasterxml/jackson/core/json/DupDetector;)Lcom/fasterxml/jackson/core/json/JsonReadContext;
     212: putfield      #7                  // Field _parsingContext:Lcom/fasterxml/jackson/core/json/JsonReadContext;
     215: aload_0
     216: getfield      #15                 // Field _currToken:Lcom/fasterxml/jackson/core/JsonToken;
     219: areturn

  public java.lang.String nextFieldName() throws java.io.IOException;
    Code:
       0: aload_0
       1: getfield      #12                 // Field _closed:Z
       4: ifne          14
       7: aload_0
       8: getfield      #3                  // Field _segment:Lcom/fasterxml/jackson/databind/util/TokenBuffer$Segment;
      11: ifnonnull     16
      14: aconst_null
      15: areturn
      16: aload_0
      17: getfield      #4                  // Field _segmentPtr:I
      20: iconst_1
      21: iadd
      22: istore_1
      23: iload_1
      24: bipush        16
      26: if_icmpge     86
      29: aload_0
      30: getfield      #3                  // Field _segment:Lcom/fasterxml/jackson/databind/util/TokenBuffer$Segment;
      33: iload_1
      34: invokevirtual #14                 // Method com/fasterxml/jackson/databind/util/TokenBuffer$Segment.type:(I)Lcom/fasterxml/jackson/core/JsonToken;
      37: getstatic     #16                 // Field com/fasterxml/jackson/core/JsonToken.FIELD_NAME:Lcom/fasterxml/jackson/core/JsonToken;
      40: if_acmpne     86
      43: aload_0
      44: iload_1
      45: putfield      #4                  // Field _segmentPtr:I
      48: aload_0
      49: getfield      #3                  // Field _segment:Lcom/fasterxml/jackson/databind/util/TokenBuffer$Segment;
      52: iload_1
      53: invokevirtual #28                 // Method com/fasterxml/jackson/databind/util/TokenBuffer$Segment.get:(I)Ljava/lang/Object;
      56: astore_2
      57: aload_2
      58: instanceof    #18                 // class java/lang/String
      61: ifeq          71
      64: aload_2
      65: checkcast     #18                 // class java/lang/String
      68: goto          75
      71: aload_2
      72: invokevirtual #19                 // Method java/lang/Object.toString:()Ljava/lang/String;
      75: astore_3
      76: aload_0
      77: getfield      #7                  // Field _parsingContext:Lcom/fasterxml/jackson/core/json/JsonReadContext;
      80: aload_3
      81: invokevirtual #20                 // Method com/fasterxml/jackson/core/json/JsonReadContext.setCurrentName:(Ljava/lang/String;)V
      84: aload_3
      85: areturn
      86: aload_0
      87: invokevirtual #29                 // Method nextToken:()Lcom/fasterxml/jackson/core/JsonToken;
      90: getstatic     #16                 // Field com/fasterxml/jackson/core/JsonToken.FIELD_NAME:Lcom/fasterxml/jackson/core/JsonToken;
      93: if_acmpne     103
      96: aload_0
      97: invokevirtual #30                 // Method getCurrentName:()Ljava/lang/String;
     100: goto          104
     103: aconst_null
     104: areturn

  public boolean isClosed();
    Code:
       0: aload_0
       1: getfield      #12                 // Field _closed:Z
       4: ireturn

  public com.fasterxml.jackson.core.JsonStreamContext getParsingContext();
    Code:
       0: aload_0
       1: getfield      #7                  // Field _parsingContext:Lcom/fasterxml/jackson/core/json/JsonReadContext;
       4: areturn

  public com.fasterxml.jackson.core.JsonLocation getTokenLocation();
    Code:
       0: aload_0
       1: invokevirtual #31                 // Method getCurrentLocation:()Lcom/fasterxml/jackson/core/JsonLocation;
       4: areturn

  public com.fasterxml.jackson.core.JsonLocation getCurrentLocation();
    Code:
       0: aload_0
       1: getfield      #2                  // Field _location:Lcom/fasterxml/jackson/core/JsonLocation;
       4: ifnonnull     13
       7: getstatic     #32                 // Field com/fasterxml/jackson/core/JsonLocation.NA:Lcom/fasterxml/jackson/core/JsonLocation;
      10: goto          17
      13: aload_0
      14: getfield      #2                  // Field _location:Lcom/fasterxml/jackson/core/JsonLocation;
      17: areturn

  public java.lang.String getCurrentName();
    Code:
       0: aload_0
       1: getfield      #15                 // Field _currToken:Lcom/fasterxml/jackson/core/JsonToken;
       4: getstatic     #21                 // Field com/fasterxml/jackson/core/JsonToken.START_OBJECT:Lcom/fasterxml/jackson/core/JsonToken;
       7: if_acmpeq     20
      10: aload_0
      11: getfield      #15                 // Field _currToken:Lcom/fasterxml/jackson/core/JsonToken;
      14: getstatic     #23                 // Field com/fasterxml/jackson/core/JsonToken.START_ARRAY:Lcom/fasterxml/jackson/core/JsonToken;
      17: if_acmpne     33
      20: aload_0
      21: getfield      #7                  // Field _parsingContext:Lcom/fasterxml/jackson/core/json/JsonReadContext;
      24: invokevirtual #27                 // Method com/fasterxml/jackson/core/json/JsonReadContext.getParent:()Lcom/fasterxml/jackson/core/json/JsonReadContext;
      27: astore_1
      28: aload_1
      29: invokevirtual #33                 // Method com/fasterxml/jackson/core/json/JsonReadContext.getCurrentName:()Ljava/lang/String;
      32: areturn
      33: aload_0
      34: getfield      #7                  // Field _parsingContext:Lcom/fasterxml/jackson/core/json/JsonReadContext;
      37: invokevirtual #33                 // Method com/fasterxml/jackson/core/json/JsonReadContext.getCurrentName:()Ljava/lang/String;
      40: areturn

  public void overrideCurrentName(java.lang.String);
    Code:
       0: aload_0
       1: getfield      #7                  // Field _parsingContext:Lcom/fasterxml/jackson/core/json/JsonReadContext;
       4: astore_2
       5: aload_0
       6: getfield      #15                 // Field _currToken:Lcom/fasterxml/jackson/core/JsonToken;
       9: getstatic     #21                 // Field com/fasterxml/jackson/core/JsonToken.START_OBJECT:Lcom/fasterxml/jackson/core/JsonToken;
      12: if_acmpeq     25
      15: aload_0
      16: getfield      #15                 // Field _currToken:Lcom/fasterxml/jackson/core/JsonToken;
      19: getstatic     #23                 // Field com/fasterxml/jackson/core/JsonToken.START_ARRAY:Lcom/fasterxml/jackson/core/JsonToken;
      22: if_acmpne     30
      25: aload_2
      26: invokevirtual #27                 // Method com/fasterxml/jackson/core/json/JsonReadContext.getParent:()Lcom/fasterxml/jackson/core/json/JsonReadContext;
      29: astore_2
      30: aload_2
      31: aload_1
      32: invokevirtual #20                 // Method com/fasterxml/jackson/core/json/JsonReadContext.setCurrentName:(Ljava/lang/String;)V
      35: goto          48
      38: astore_3
      39: new           #35                 // class java/lang/RuntimeException
      42: dup
      43: aload_3
      44: invokespecial #36                 // Method java/lang/RuntimeException."<init>":(Ljava/lang/Throwable;)V
      47: athrow
      48: return
    Exception table:
       from    to  target type
          30    35    38   Class java/io/IOException

  public java.lang.String getText();
    Code:
       0: aload_0
       1: getfield      #15                 // Field _currToken:Lcom/fasterxml/jackson/core/JsonToken;
       4: getstatic     #37                 // Field com/fasterxml/jackson/core/JsonToken.VALUE_STRING:Lcom/fasterxml/jackson/core/JsonToken;
       7: if_acmpeq     20
      10: aload_0
      11: getfield      #15                 // Field _currToken:Lcom/fasterxml/jackson/core/JsonToken;
      14: getstatic     #16                 // Field com/fasterxml/jackson/core/JsonToken.FIELD_NAME:Lcom/fasterxml/jackson/core/JsonToken;
      17: if_acmpne     50
      20: aload_0
      21: invokevirtual #17                 // Method _currentObject:()Ljava/lang/Object;
      24: astore_1
      25: aload_1
      26: instanceof    #18                 // class java/lang/String
      29: ifeq          37
      32: aload_1
      33: checkcast     #18                 // class java/lang/String
      36: areturn
      37: aload_1
      38: ifnonnull     45
      41: aconst_null
      42: goto          49
      45: aload_1
      46: invokevirtual #19                 // Method java/lang/Object.toString:()Ljava/lang/String;
      49: areturn
      50: aload_0
      51: getfield      #15                 // Field _currToken:Lcom/fasterxml/jackson/core/JsonToken;
      54: ifnonnull     59
      57: aconst_null
      58: areturn
      59: getstatic     #38                 // Field com/fasterxml/jackson/databind/util/TokenBuffer$1.$SwitchMap$com$fasterxml$jackson$core$JsonToken:[I
      62: aload_0
      63: getfield      #15                 // Field _currToken:Lcom/fasterxml/jackson/core/JsonToken;
      66: invokevirtual #39                 // Method com/fasterxml/jackson/core/JsonToken.ordinal:()I
      69: iaload
      70: lookupswitch  { // 2
                     7: 96
                     8: 96
               default: 114
          }
      96: aload_0
      97: invokevirtual #17                 // Method _currentObject:()Ljava/lang/Object;
     100: astore_1
     101: aload_1
     102: ifnonnull     109
     105: aconst_null
     106: goto          113
     109: aload_1
     110: invokevirtual #19                 // Method java/lang/Object.toString:()Ljava/lang/String;
     113: areturn
     114: aload_0
     115: getfield      #15                 // Field _currToken:Lcom/fasterxml/jackson/core/JsonToken;
     118: invokevirtual #40                 // Method com/fasterxml/jackson/core/JsonToken.asString:()Ljava/lang/String;
     121: areturn

  public char[] getTextCharacters();
    Code:
       0: aload_0
       1: invokevirtual #41                 // Method getText:()Ljava/lang/String;
       4: astore_1
       5: aload_1
       6: ifnonnull     13
       9: aconst_null
      10: goto          17
      13: aload_1
      14: invokevirtual #42                 // Method java/lang/String.toCharArray:()[C
      17: areturn

  public int getTextLength();
    Code:
       0: aload_0
       1: invokevirtual #41                 // Method getText:()Ljava/lang/String;
       4: astore_1
       5: aload_1
       6: ifnonnull     13
       9: iconst_0
      10: goto          17
      13: aload_1
      14: invokevirtual #43                 // Method java/lang/String.length:()I
      17: ireturn

  public int getTextOffset();
    Code:
       0: iconst_0
       1: ireturn

  public boolean hasTextCharacters();
    Code:
       0: iconst_0
       1: ireturn

  public java.math.BigInteger getBigIntegerValue() throws java.io.IOException;
    Code:
       0: aload_0
       1: invokevirtual #44                 // Method getNumberValue:()Ljava/lang/Number;
       4: astore_1
       5: aload_1
       6: instanceof    #45                 // class java/math/BigInteger
       9: ifeq          17
      12: aload_1
      13: checkcast     #45                 // class java/math/BigInteger
      16: areturn
      17: aload_0
      18: invokevirtual #46                 // Method getNumberType:()Lcom/fasterxml/jackson/core/JsonParser$NumberType;
      21: getstatic     #47                 // Field com/fasterxml/jackson/core/JsonParser$NumberType.BIG_DECIMAL:Lcom/fasterxml/jackson/core/JsonParser$NumberType;
      24: if_acmpne     35
      27: aload_1
      28: checkcast     #48                 // class java/math/BigDecimal
      31: invokevirtual #49                 // Method java/math/BigDecimal.toBigInteger:()Ljava/math/BigInteger;
      34: areturn
      35: aload_1
      36: invokevirtual #50                 // Method java/lang/Number.longValue:()J
      39: invokestatic  #51                 // Method java/math/BigInteger.valueOf:(J)Ljava/math/BigInteger;
      42: areturn

  public java.math.BigDecimal getDecimalValue() throws java.io.IOException;
    Code:
       0: aload_0
       1: invokevirtual #44                 // Method getNumberValue:()Ljava/lang/Number;
       4: astore_1
       5: aload_1
       6: instanceof    #48                 // class java/math/BigDecimal
       9: ifeq          17
      12: aload_1
      13: checkcast     #48                 // class java/math/BigDecimal
      16: areturn
      17: getstatic     #52                 // Field com/fasterxml/jackson/databind/util/TokenBuffer$1.$SwitchMap$com$fasterxml$jackson$core$JsonParser$NumberType:[I
      20: aload_0
      21: invokevirtual #46                 // Method getNumberType:()Lcom/fasterxml/jackson/core/JsonParser$NumberType;
      24: invokevirtual #53                 // Method com/fasterxml/jackson/core/JsonParser$NumberType.ordinal:()I
      27: iaload
      28: tableswitch   { // 1 to 5
                     1: 64
                     2: 72
                     3: 84
                     4: 84
                     5: 64
               default: 84
          }
      64: aload_1
      65: invokevirtual #50                 // Method java/lang/Number.longValue:()J
      68: invokestatic  #54                 // Method java/math/BigDecimal.valueOf:(J)Ljava/math/BigDecimal;
      71: areturn
      72: new           #48                 // class java/math/BigDecimal
      75: dup
      76: aload_1
      77: checkcast     #45                 // class java/math/BigInteger
      80: invokespecial #55                 // Method java/math/BigDecimal."<init>":(Ljava/math/BigInteger;)V
      83: areturn
      84: aload_1
      85: invokevirtual #56                 // Method java/lang/Number.doubleValue:()D
      88: invokestatic  #57                 // Method java/math/BigDecimal.valueOf:(D)Ljava/math/BigDecimal;
      91: areturn

  public double getDoubleValue() throws java.io.IOException;
    Code:
       0: aload_0
       1: invokevirtual #44                 // Method getNumberValue:()Ljava/lang/Number;
       4: invokevirtual #56                 // Method java/lang/Number.doubleValue:()D
       7: dreturn

  public float getFloatValue() throws java.io.IOException;
    Code:
       0: aload_0
       1: invokevirtual #44                 // Method getNumberValue:()Ljava/lang/Number;
       4: invokevirtual #58                 // Method java/lang/Number.floatValue:()F
       7: freturn

  public int getIntValue() throws java.io.IOException;
    Code:
       0: aload_0
       1: getfield      #15                 // Field _currToken:Lcom/fasterxml/jackson/core/JsonToken;
       4: getstatic     #59                 // Field com/fasterxml/jackson/core/JsonToken.VALUE_NUMBER_INT:Lcom/fasterxml/jackson/core/JsonToken;
       7: if_acmpne     21
      10: aload_0
      11: invokevirtual #17                 // Method _currentObject:()Ljava/lang/Object;
      14: checkcast     #60                 // class java/lang/Number
      17: invokevirtual #61                 // Method java/lang/Number.intValue:()I
      20: ireturn
      21: aload_0
      22: invokevirtual #44                 // Method getNumberValue:()Ljava/lang/Number;
      25: invokevirtual #61                 // Method java/lang/Number.intValue:()I
      28: ireturn

  public long getLongValue() throws java.io.IOException;
    Code:
       0: aload_0
       1: invokevirtual #44                 // Method getNumberValue:()Ljava/lang/Number;
       4: invokevirtual #50                 // Method java/lang/Number.longValue:()J
       7: lreturn

  public com.fasterxml.jackson.core.JsonParser$NumberType getNumberType() throws java.io.IOException;
    Code:
       0: aload_0
       1: invokevirtual #44                 // Method getNumberValue:()Ljava/lang/Number;
       4: astore_1
       5: aload_1
       6: instanceof    #62                 // class java/lang/Integer
       9: ifeq          16
      12: getstatic     #63                 // Field com/fasterxml/jackson/core/JsonParser$NumberType.INT:Lcom/fasterxml/jackson/core/JsonParser$NumberType;
      15: areturn
      16: aload_1
      17: instanceof    #64                 // class java/lang/Long
      20: ifeq          27
      23: getstatic     #65                 // Field com/fasterxml/jackson/core/JsonParser$NumberType.LONG:Lcom/fasterxml/jackson/core/JsonParser$NumberType;
      26: areturn
      27: aload_1
      28: instanceof    #66                 // class java/lang/Double
      31: ifeq          38
      34: getstatic     #67                 // Field com/fasterxml/jackson/core/JsonParser$NumberType.DOUBLE:Lcom/fasterxml/jackson/core/JsonParser$NumberType;
      37: areturn
      38: aload_1
      39: instanceof    #48                 // class java/math/BigDecimal
      42: ifeq          49
      45: getstatic     #47                 // Field com/fasterxml/jackson/core/JsonParser$NumberType.BIG_DECIMAL:Lcom/fasterxml/jackson/core/JsonParser$NumberType;
      48: areturn
      49: aload_1
      50: instanceof    #45                 // class java/math/BigInteger
      53: ifeq          60
      56: getstatic     #68                 // Field com/fasterxml/jackson/core/JsonParser$NumberType.BIG_INTEGER:Lcom/fasterxml/jackson/core/JsonParser$NumberType;
      59: areturn
      60: aload_1
      61: instanceof    #69                 // class java/lang/Float
      64: ifeq          71
      67: getstatic     #70                 // Field com/fasterxml/jackson/core/JsonParser$NumberType.FLOAT:Lcom/fasterxml/jackson/core/JsonParser$NumberType;
      70: areturn
      71: aload_1
      72: instanceof    #71                 // class java/lang/Short
      75: ifeq          82
      78: getstatic     #63                 // Field com/fasterxml/jackson/core/JsonParser$NumberType.INT:Lcom/fasterxml/jackson/core/JsonParser$NumberType;
      81: areturn
      82: aconst_null
      83: areturn

  public final java.lang.Number getNumberValue() throws java.io.IOException;
    Code:
       0: aload_0
       1: invokevirtual #72                 // Method _checkIsNumber:()V
       4: aload_0
       5: invokevirtual #17                 // Method _currentObject:()Ljava/lang/Object;
       8: astore_1
       9: aload_1
      10: instanceof    #60                 // class java/lang/Number
      13: ifeq          21
      16: aload_1
      17: checkcast     #60                 // class java/lang/Number
      20: areturn
      21: aload_1
      22: instanceof    #18                 // class java/lang/String
      25: ifeq          58
      28: aload_1
      29: checkcast     #18                 // class java/lang/String
      32: astore_2
      33: aload_2
      34: bipush        46
      36: invokevirtual #73                 // Method java/lang/String.indexOf:(I)I
      39: iflt          50
      42: aload_2
      43: invokestatic  #74                 // Method java/lang/Double.parseDouble:(Ljava/lang/String;)D
      46: invokestatic  #75                 // Method java/lang/Double.valueOf:(D)Ljava/lang/Double;
      49: areturn
      50: aload_2
      51: invokestatic  #76                 // Method java/lang/Long.parseLong:(Ljava/lang/String;)J
      54: invokestatic  #77                 // Method java/lang/Long.valueOf:(J)Ljava/lang/Long;
      57: areturn
      58: aload_1
      59: ifnonnull     64
      62: aconst_null
      63: areturn
      64: new           #78                 // class java/lang/IllegalStateException
      67: dup
      68: new           #79                 // class java/lang/StringBuilder
      71: dup
      72: invokespecial #80                 // Method java/lang/StringBuilder."<init>":()V
      75: ldc           #81                 // String Internal error: entry should be a Number, but is of type
      77: invokevirtual #82                 // Method java/lang/StringBuilder.append:(Ljava/lang/String;)Ljava/lang/StringBuilder;
      80: aload_1
      81: invokevirtual #83                 // Method java/lang/Object.getClass:()Ljava/lang/Class;
      84: invokevirtual #84                 // Method java/lang/Class.getName:()Ljava/lang/String;
      87: invokevirtual #82                 // Method java/lang/StringBuilder.append:(Ljava/lang/String;)Ljava/lang/StringBuilder;
      90: invokevirtual #85                 // Method java/lang/StringBuilder.toString:()Ljava/lang/String;
      93: invokespecial #86                 // Method java/lang/IllegalStateException."<init>":(Ljava/lang/String;)V
      96: athrow

  public java.lang.Object getEmbeddedObject();
    Code:
       0: aload_0
       1: getfield      #15                 // Field _currToken:Lcom/fasterxml/jackson/core/JsonToken;
       4: getstatic     #87                 // Field com/fasterxml/jackson/core/JsonToken.VALUE_EMBEDDED_OBJECT:Lcom/fasterxml/jackson/core/JsonToken;
       7: if_acmpne     15
      10: aload_0
      11: invokevirtual #17                 // Method _currentObject:()Ljava/lang/Object;
      14: areturn
      15: aconst_null
      16: areturn

  public byte[] getBinaryValue(com.fasterxml.jackson.core.Base64Variant) throws java.io.IOException, com.fasterxml.jackson.core.JsonParseException;
    Code:
       0: aload_0
       1: getfield      #15                 // Field _currToken:Lcom/fasterxml/jackson/core/JsonToken;
       4: getstatic     #87                 // Field com/fasterxml/jackson/core/JsonToken.VALUE_EMBEDDED_OBJECT:Lcom/fasterxml/jackson/core/JsonToken;
       7: if_acmpne     30
      10: aload_0
      11: invokevirtual #17                 // Method _currentObject:()Ljava/lang/Object;
      14: astore_2
      15: aload_2
      16: instanceof    #88                 // class "[B"
      19: ifeq          30
      22: aload_2
      23: checkcast     #88                 // class "[B"
      26: checkcast     #88                 // class "[B"
      29: areturn
      30: aload_0
      31: getfield      #15                 // Field _currToken:Lcom/fasterxml/jackson/core/JsonToken;
      34: getstatic     #37                 // Field com/fasterxml/jackson/core/JsonToken.VALUE_STRING:Lcom/fasterxml/jackson/core/JsonToken;
      37: if_acmpeq     72
      40: aload_0
      41: new           #79                 // class java/lang/StringBuilder
      44: dup
      45: invokespecial #80                 // Method java/lang/StringBuilder."<init>":()V
      48: ldc           #89                 // String Current token (
      50: invokevirtual #82                 // Method java/lang/StringBuilder.append:(Ljava/lang/String;)Ljava/lang/StringBuilder;
      53: aload_0
      54: getfield      #15                 // Field _currToken:Lcom/fasterxml/jackson/core/JsonToken;
      57: invokevirtual #90                 // Method java/lang/StringBuilder.append:(Ljava/lang/Object;)Ljava/lang/StringBuilder;
      60: ldc           #91                 // String ) not VALUE_STRING (or VALUE_EMBEDDED_OBJECT with byte[]), can not access as binary
      62: invokevirtual #82                 // Method java/lang/StringBuilder.append:(Ljava/lang/String;)Ljava/lang/StringBuilder;
      65: invokevirtual #85                 // Method java/lang/StringBuilder.toString:()Ljava/lang/String;
      68: invokevirtual #92                 // Method _constructError:(Ljava/lang/String;)Lcom/fasterxml/jackson/core/JsonParseException;
      71: athrow
      72: aload_0
      73: invokevirtual #41                 // Method getText:()Ljava/lang/String;
      76: astore_2
      77: aload_2
      78: ifnonnull     83
      81: aconst_null
      82: areturn
      83: aload_0
      84: getfield      #93                 // Field _byteBuilder:Lcom/fasterxml/jackson/core/util/ByteArrayBuilder;
      87: astore_3
      88: aload_3
      89: ifnonnull     110
      92: aload_0
      93: new           #94                 // class com/fasterxml/jackson/core/util/ByteArrayBuilder
      96: dup
      97: bipush        100
      99: invokespecial #95                 // Method com/fasterxml/jackson/core/util/ByteArrayBuilder."<init>":(I)V
     102: dup
     103: astore_3
     104: putfield      #93                 // Field _byteBuilder:Lcom/fasterxml/jackson/core/util/ByteArrayBuilder;
     107: goto          117
     110: aload_0
     111: getfield      #93                 // Field _byteBuilder:Lcom/fasterxml/jackson/core/util/ByteArrayBuilder;
     114: invokevirtual #96                 // Method com/fasterxml/jackson/core/util/ByteArrayBuilder.reset:()V
     117: aload_0
     118: aload_2
     119: aload_3
     120: aload_1
     121: invokevirtual #97                 // Method _decodeBase64:(Ljava/lang/String;Lcom/fasterxml/jackson/core/util/ByteArrayBuilder;Lcom/fasterxml/jackson/core/Base64Variant;)V
     124: aload_3
     125: invokevirtual #98                 // Method com/fasterxml/jackson/core/util/ByteArrayBuilder.toByteArray:()[B
     128: areturn

  public int readBinaryValue(com.fasterxml.jackson.core.Base64Variant, java.io.OutputStream) throws java.io.IOException;
    Code:
       0: aload_0
       1: aload_1
       2: invokevirtual #99                 // Method getBinaryValue:(Lcom/fasterxml/jackson/core/Base64Variant;)[B
       5: astore_3
       6: aload_3
       7: ifnull        21
      10: aload_2
      11: aload_3
      12: iconst_0
      13: aload_3
      14: arraylength
      15: invokevirtual #100                // Method java/io/OutputStream.write:([BII)V
      18: aload_3
      19: arraylength
      20: ireturn
      21: iconst_0
      22: ireturn

  public boolean canReadObjectId();
    Code:
       0: aload_0
       1: getfield      #9                  // Field _hasNativeObjectIds:Z
       4: ireturn

  public boolean canReadTypeId();
    Code:
       0: aload_0
       1: getfield      #8                  // Field _hasNativeTypeIds:Z
       4: ireturn

  public java.lang.Object getTypeId();
    Code:
       0: aload_0
       1: getfield      #3                  // Field _segment:Lcom/fasterxml/jackson/databind/util/TokenBuffer$Segment;
       4: aload_0
       5: getfield      #4                  // Field _segmentPtr:I
       8: invokevirtual #101                // Method com/fasterxml/jackson/databind/util/TokenBuffer$Segment.findTypeId:(I)Ljava/lang/Object;
      11: areturn

  public java.lang.Object getObjectId();
    Code:
       0: aload_0
       1: getfield      #3                  // Field _segment:Lcom/fasterxml/jackson/databind/util/TokenBuffer$Segment;
       4: aload_0
       5: getfield      #4                  // Field _segmentPtr:I
       8: invokevirtual #102                // Method com/fasterxml/jackson/databind/util/TokenBuffer$Segment.findObjectId:(I)Ljava/lang/Object;
      11: areturn

  protected final java.lang.Object _currentObject();
    Code:
       0: aload_0
       1: getfield      #3                  // Field _segment:Lcom/fasterxml/jackson/databind/util/TokenBuffer$Segment;
       4: aload_0
       5: getfield      #4                  // Field _segmentPtr:I
       8: invokevirtual #28                 // Method com/fasterxml/jackson/databind/util/TokenBuffer$Segment.get:(I)Ljava/lang/Object;
      11: areturn

  protected final void _checkIsNumber() throws com.fasterxml.jackson.core.JsonParseException;
    Code:
       0: aload_0
       1: getfield      #15                 // Field _currToken:Lcom/fasterxml/jackson/core/JsonToken;
       4: ifnull        17
       7: aload_0
       8: getfield      #15                 // Field _currToken:Lcom/fasterxml/jackson/core/JsonToken;
      11: invokevirtual #103                // Method com/fasterxml/jackson/core/JsonToken.isNumeric:()Z
      14: ifne          49
      17: aload_0
      18: new           #79                 // class java/lang/StringBuilder
      21: dup
      22: invokespecial #80                 // Method java/lang/StringBuilder."<init>":()V
      25: ldc           #89                 // String Current token (
      27: invokevirtual #82                 // Method java/lang/StringBuilder.append:(Ljava/lang/String;)Ljava/lang/StringBuilder;
      30: aload_0
      31: getfield      #15                 // Field _currToken:Lcom/fasterxml/jackson/core/JsonToken;
      34: invokevirtual #90                 // Method java/lang/StringBuilder.append:(Ljava/lang/Object;)Ljava/lang/StringBuilder;
      37: ldc           #104                // String ) not numeric, can not use numeric value accessors
      39: invokevirtual #82                 // Method java/lang/StringBuilder.append:(Ljava/lang/String;)Ljava/lang/StringBuilder;
      42: invokevirtual #85                 // Method java/lang/StringBuilder.toString:()Ljava/lang/String;
      45: invokevirtual #92                 // Method _constructError:(Ljava/lang/String;)Lcom/fasterxml/jackson/core/JsonParseException;
      48: athrow
      49: return

  protected void _handleEOF() throws com.fasterxml.jackson.core.JsonParseException;
    Code:
       0: aload_0
       1: invokevirtual #105                // Method _throwInternal:()V
       4: return
}
