Compiled from "CloudFunctionConfiguration.java"
public class io.minio.messages.CloudFunctionConfiguration extends io.minio.messages.XmlEntity {
  private java.lang.String id;

  private java.lang.String cloudFunction;

  private java.util.List<java.lang.String> events;

  private io.minio.messages.Filter filter;

  public io.minio.messages.CloudFunctionConfiguration() throws org.xmlpull.v1.XmlPullParserException;
    Code:
       0: aload_0
       1: invokespecial #1                  // Method io/minio/messages/XmlEntity."<init>":()V
       4: aload_0
       5: new           #2                  // class java/util/LinkedList
       8: dup
       9: invokespecial #3                  // Method java/util/LinkedList."<init>":()V
      12: putfield      #4                  // Field events:Ljava/util/List;
      15: aload_0
      16: ldc           #5                  // String CloudFunctionConfiguration
      18: putfield      #6                  // Field io/minio/messages/XmlEntity.name:Ljava/lang/String;
      21: return

  public java.lang.String id();
    Code:
       0: aload_0
       1: getfield      #7                  // Field id:Ljava/lang/String;
       4: areturn

  public void setId(java.lang.String);
    Code:
       0: aload_0
       1: aload_1
       2: putfield      #7                  // Field id:Ljava/lang/String;
       5: return

  public java.lang.String cloudFunction();
    Code:
       0: aload_0
       1: getfield      #8                  // Field cloudFunction:Ljava/lang/String;
       4: areturn

  public void setCloudFunction(java.lang.String);
    Code:
       0: aload_0
       1: aload_1
       2: putfield      #8                  // Field cloudFunction:Ljava/lang/String;
       5: return

  public java.util.List<io.minio.messages.EventType> events() throws io.minio.errors.InvalidArgumentException;
    Code:
       0: aload_0
       1: getfield      #4                  // Field events:Ljava/util/List;
       4: invokestatic  #9                  // Method io/minio/messages/EventType.fromStringList:(Ljava/util/List;)Ljava/util/List;
       7: areturn

  public void setEvents(java.util.List<io.minio.messages.EventType>);
    Code:
       0: aload_0
       1: aload_1
       2: invokestatic  #10                 // Method io/minio/messages/EventType.toStringList:(Ljava/util/List;)Ljava/util/List;
       5: putfield      #4                  // Field events:Ljava/util/List;
       8: return

  public io.minio.messages.Filter filter();
    Code:
       0: aload_0
       1: getfield      #11                 // Field filter:Lio/minio/messages/Filter;
       4: areturn

  public void setFilter(io.minio.messages.Filter);
    Code:
       0: aload_0
       1: aload_1
       2: putfield      #11                 // Field filter:Lio/minio/messages/Filter;
       5: return
}
