Compiled from "CacheNamespaceHandler.java"
public class org.springframework.cache.config.CacheNamespaceHandler extends org.springframework.beans.factory.xml.NamespaceHandlerSupport {
  static final java.lang.String CACHE_MANAGER_ATTRIBUTE;

  static final java.lang.String DEFAULT_CACHE_MANAGER_BEAN_NAME;

  public org.springframework.cache.config.CacheNamespaceHandler();
    Code:
       0: aload_0
       1: invokespecial #1                  // Method org/springframework/beans/factory/xml/NamespaceHandlerSupport."<init>":()V
       4: return

  static java.lang.String extractCacheManager(org.w3c.dom.Element);
    Code:
       0: aload_0
       1: ldc           #3                  // String cache-manager
       3: invokeinterface #4,  2            // InterfaceMethod org/w3c/dom/Element.hasAttribute:(Ljava/lang/String;)Z
       8: ifeq          22
      11: aload_0
      12: ldc           #3                  // String cache-manager
      14: invokeinterface #5,  2            // InterfaceMethod org/w3c/dom/Element.getAttribute:(Ljava/lang/String;)Ljava/lang/String;
      19: goto          24
      22: ldc           #6                  // String cacheManager
      24: areturn

  static org.springframework.beans.factory.config.BeanDefinition parseKeyGenerator(org.w3c.dom.Element, org.springframework.beans.factory.config.BeanDefinition);
    Code:
       0: aload_0
       1: ldc           #7                  // String key-generator
       3: invokeinterface #5,  2            // InterfaceMethod org/w3c/dom/Element.getAttribute:(Ljava/lang/String;)Ljava/lang/String;
       8: astore_2
       9: aload_2
      10: invokestatic  #8                  // Method org/springframework/util/StringUtils.hasText:(Ljava/lang/String;)Z
      13: ifeq          39
      16: aload_1
      17: invokeinterface #9,  1            // InterfaceMethod org/springframework/beans/factory/config/BeanDefinition.getPropertyValues:()Lorg/springframework/beans/MutablePropertyValues;
      22: ldc           #10                 // String keyGenerator
      24: new           #11                 // class org/springframework/beans/factory/config/RuntimeBeanReference
      27: dup
      28: aload_2
      29: invokevirtual #12                 // Method java/lang/String.trim:()Ljava/lang/String;
      32: invokespecial #13                 // Method org/springframework/beans/factory/config/RuntimeBeanReference."<init>":(Ljava/lang/String;)V
      35: invokevirtual #14                 // Method org/springframework/beans/MutablePropertyValues.add:(Ljava/lang/String;Ljava/lang/Object;)Lorg/springframework/beans/MutablePropertyValues;
      38: pop
      39: aload_1
      40: areturn

  public void init();
    Code:
       0: aload_0
       1: ldc           #15                 // String annotation-driven
       3: new           #16                 // class org/springframework/cache/config/AnnotationDrivenCacheBeanDefinitionParser
       6: dup
       7: invokespecial #17                 // Method org/springframework/cache/config/AnnotationDrivenCacheBeanDefinitionParser."<init>":()V
      10: invokevirtual #18                 // Method registerBeanDefinitionParser:(Ljava/lang/String;Lorg/springframework/beans/factory/xml/BeanDefinitionParser;)V
      13: aload_0
      14: ldc           #19                 // String advice
      16: new           #20                 // class org/springframework/cache/config/CacheAdviceParser
      19: dup
      20: invokespecial #21                 // Method org/springframework/cache/config/CacheAdviceParser."<init>":()V
      23: invokevirtual #18                 // Method registerBeanDefinitionParser:(Ljava/lang/String;Lorg/springframework/beans/factory/xml/BeanDefinitionParser;)V
      26: return
}
