Compiled from "DefaultTransferResource.java"
public class org.sonatype.aether.util.listener.DefaultTransferResource implements org.sonatype.aether.transfer.TransferResource {
  private final java.lang.String repositoryUrl;

  private final java.lang.String resourceName;

  private final java.io.File file;

  private final long startTime;

  private final org.sonatype.aether.RequestTrace trace;

  private long contentLength;

  public org.sonatype.aether.util.listener.DefaultTransferResource(java.lang.String, java.lang.String, java.io.File);
    Code:
       0: aload_0
       1: aload_1
       2: aload_2
       3: aload_3
       4: aconst_null
       5: invokespecial #1                  // Method "<init>":(Ljava/lang/String;Ljava/lang/String;Ljava/io/File;Lorg/sonatype/aether/RequestTrace;)V
       8: return

  public org.sonatype.aether.util.listener.DefaultTransferResource(java.lang.String, java.lang.String, java.io.File, org.sonatype.aether.RequestTrace);
    Code:
       0: aload_0
       1: invokespecial #2                  // Method java/lang/Object."<init>":()V
       4: aload_0
       5: ldc2_w        #3                  // long -1l
       8: putfield      #5                  // Field contentLength:J
      11: aload_1
      12: ifnull        22
      15: aload_1
      16: invokevirtual #6                  // Method java/lang/String.length:()I
      19: ifgt          31
      22: aload_0
      23: ldc           #7                  // String
      25: putfield      #8                  // Field repositoryUrl:Ljava/lang/String;
      28: goto          71
      31: aload_1
      32: ldc           #9                  // String /
      34: invokevirtual #10                 // Method java/lang/String.endsWith:(Ljava/lang/String;)Z
      37: ifeq          48
      40: aload_0
      41: aload_1
      42: putfield      #8                  // Field repositoryUrl:Ljava/lang/String;
      45: goto          71
      48: aload_0
      49: new           #11                 // class java/lang/StringBuilder
      52: dup
      53: invokespecial #12                 // Method java/lang/StringBuilder."<init>":()V
      56: aload_1
      57: invokevirtual #13                 // Method java/lang/StringBuilder.append:(Ljava/lang/String;)Ljava/lang/StringBuilder;
      60: bipush        47
      62: invokevirtual #14                 // Method java/lang/StringBuilder.append:(C)Ljava/lang/StringBuilder;
      65: invokevirtual #15                 // Method java/lang/StringBuilder.toString:()Ljava/lang/String;
      68: putfield      #8                  // Field repositoryUrl:Ljava/lang/String;
      71: aload_2
      72: ifnull        82
      75: aload_2
      76: invokevirtual #6                  // Method java/lang/String.length:()I
      79: ifgt          91
      82: aload_0
      83: ldc           #7                  // String
      85: putfield      #16                 // Field resourceName:Ljava/lang/String;
      88: goto          117
      91: aload_2
      92: ldc           #9                  // String /
      94: invokevirtual #17                 // Method java/lang/String.startsWith:(Ljava/lang/String;)Z
      97: ifeq          112
     100: aload_0
     101: aload_2
     102: iconst_1
     103: invokevirtual #18                 // Method java/lang/String.substring:(I)Ljava/lang/String;
     106: putfield      #16                 // Field resourceName:Ljava/lang/String;
     109: goto          117
     112: aload_0
     113: aload_2
     114: putfield      #16                 // Field resourceName:Ljava/lang/String;
     117: aload_0
     118: aload_3
     119: putfield      #19                 // Field file:Ljava/io/File;
     122: aload_0
     123: aload         4
     125: putfield      #20                 // Field trace:Lorg/sonatype/aether/RequestTrace;
     128: aload_0
     129: invokestatic  #21                 // Method java/lang/System.currentTimeMillis:()J
     132: putfield      #22                 // Field startTime:J
     135: return

  public java.lang.String getRepositoryUrl();
    Code:
       0: aload_0
       1: getfield      #8                  // Field repositoryUrl:Ljava/lang/String;
       4: areturn

  public java.lang.String getResourceName();
    Code:
       0: aload_0
       1: getfield      #16                 // Field resourceName:Ljava/lang/String;
       4: areturn

  public java.io.File getFile();
    Code:
       0: aload_0
       1: getfield      #19                 // Field file:Ljava/io/File;
       4: areturn

  public long getContentLength();
    Code:
       0: aload_0
       1: getfield      #5                  // Field contentLength:J
       4: lreturn

  public org.sonatype.aether.util.listener.DefaultTransferResource setContentLength(long);
    Code:
       0: aload_0
       1: lload_1
       2: putfield      #5                  // Field contentLength:J
       5: aload_0
       6: areturn

  public long getTransferStartTime();
    Code:
       0: aload_0
       1: getfield      #22                 // Field startTime:J
       4: lreturn

  public org.sonatype.aether.RequestTrace getTrace();
    Code:
       0: aload_0
       1: getfield      #20                 // Field trace:Lorg/sonatype/aether/RequestTrace;
       4: areturn

  public java.lang.String toString();
    Code:
       0: new           #11                 // class java/lang/StringBuilder
       3: dup
       4: invokespecial #12                 // Method java/lang/StringBuilder."<init>":()V
       7: aload_0
       8: invokevirtual #23                 // Method getRepositoryUrl:()Ljava/lang/String;
      11: invokevirtual #13                 // Method java/lang/StringBuilder.append:(Ljava/lang/String;)Ljava/lang/StringBuilder;
      14: aload_0
      15: invokevirtual #24                 // Method getResourceName:()Ljava/lang/String;
      18: invokevirtual #13                 // Method java/lang/StringBuilder.append:(Ljava/lang/String;)Ljava/lang/StringBuilder;
      21: ldc           #25                 // String  <>
      23: invokevirtual #13                 // Method java/lang/StringBuilder.append:(Ljava/lang/String;)Ljava/lang/StringBuilder;
      26: aload_0
      27: invokevirtual #26                 // Method getFile:()Ljava/io/File;
      30: invokevirtual #27                 // Method java/lang/StringBuilder.append:(Ljava/lang/Object;)Ljava/lang/StringBuilder;
      33: invokevirtual #15                 // Method java/lang/StringBuilder.toString:()Ljava/lang/String;
      36: areturn
}
