Compiled from "WildcardRefFluentImpl.java"
public class io.sundr.codegen.model.WildcardRefFluentImpl$WildcardRefBoundsNestedImpl<N> extends io.sundr.codegen.model.WildcardRefFluentImpl<io.sundr.codegen.model.WildcardRefFluent$WildcardRefBoundsNested<N>> implements io.sundr.codegen.model.WildcardRefFluent$WildcardRefBoundsNested<N>, io.sundr.builder.Nested<N> {
  private final io.sundr.codegen.model.WildcardRefBuilder builder;

  private final int index;

  final io.sundr.codegen.model.WildcardRefFluentImpl this$0;

  io.sundr.codegen.model.WildcardRefFluentImpl$WildcardRefBoundsNestedImpl(io.sundr.codegen.model.WildcardRefFluentImpl, int, io.sundr.codegen.model.WildcardRef);
    Code:
       0: aload_0
       1: aload_1
       2: putfield      #24                 // Field this$0:Lio/sundr/codegen/model/WildcardRefFluentImpl;
       5: aload_0
       6: invokespecial #27                 // Method io/sundr/codegen/model/WildcardRefFluentImpl."<init>":()V
       9: aload_0
      10: iload_2
      11: putfield      #29                 // Field index:I
      14: aload_0
      15: new           #31                 // class io/sundr/codegen/model/WildcardRefBuilder
      18: dup
      19: aload_0
      20: aload_3
      21: invokespecial #34                 // Method io/sundr/codegen/model/WildcardRefBuilder."<init>":(Lio/sundr/codegen/model/WildcardRefFluent;Lio/sundr/codegen/model/WildcardRef;)V
      24: putfield      #36                 // Field builder:Lio/sundr/codegen/model/WildcardRefBuilder;
      27: return

  io.sundr.codegen.model.WildcardRefFluentImpl$WildcardRefBoundsNestedImpl(io.sundr.codegen.model.WildcardRefFluentImpl);
    Code:
       0: aload_0
       1: aload_1
       2: putfield      #24                 // Field this$0:Lio/sundr/codegen/model/WildcardRefFluentImpl;
       5: aload_0
       6: invokespecial #27                 // Method io/sundr/codegen/model/WildcardRefFluentImpl."<init>":()V
       9: aload_0
      10: iconst_m1
      11: putfield      #29                 // Field index:I
      14: aload_0
      15: new           #31                 // class io/sundr/codegen/model/WildcardRefBuilder
      18: dup
      19: aload_0
      20: invokespecial #45                 // Method io/sundr/codegen/model/WildcardRefBuilder."<init>":(Lio/sundr/codegen/model/WildcardRefFluent;)V
      23: putfield      #36                 // Field builder:Lio/sundr/codegen/model/WildcardRefBuilder;
      26: return

  public N and();
    Code:
       0: aload_0
       1: getfield      #24                 // Field this$0:Lio/sundr/codegen/model/WildcardRefFluentImpl;
       4: aload_0
       5: getfield      #29                 // Field index:I
       8: aload_0
       9: getfield      #36                 // Field builder:Lio/sundr/codegen/model/WildcardRefBuilder;
      12: invokevirtual #51                 // Method io/sundr/codegen/model/WildcardRefBuilder.build:()Lio/sundr/codegen/model/EditableWildcardRef;
      15: invokevirtual #55                 // Method io/sundr/codegen/model/WildcardRefFluentImpl.setToBounds:(ILio/sundr/codegen/model/TypeRef;)Lio/sundr/codegen/model/WildcardRefFluent;
      18: areturn

  public N endWildcardRefBound();
    Code:
       0: aload_0
       1: invokevirtual #58                 // Method and:()Ljava/lang/Object;
       4: areturn
}
