Compiled from "TransactionalProtocolOperationHandler.java"
class org.jboss.as.controller.remote.TransactionalProtocolOperationHandler$ProxyOperationTransactionControl implements org.jboss.as.controller.ModelController$OperationTransactionControl {
  private final org.jboss.as.controller.remote.TransactionalProtocolOperationHandler$ExecuteRequestContext requestContext;

  org.jboss.as.controller.remote.TransactionalProtocolOperationHandler$ProxyOperationTransactionControl(org.jboss.as.controller.remote.TransactionalProtocolOperationHandler$ExecuteRequestContext);
    Code:
       0: aload_0
       1: invokespecial #1                  // Method java/lang/Object."<init>":()V
       4: aload_0
       5: aload_1
       6: putfield      #2                  // Field requestContext:Lorg/jboss/as/controller/remote/TransactionalProtocolOperationHandler$ExecuteRequestContext;
       9: return

  public void operationPrepared(org.jboss.as.controller.ModelController$OperationTransaction, org.jboss.dmr.ModelNode);
    Code:
       0: aload_0
       1: getfield      #2                  // Field requestContext:Lorg/jboss/as/controller/remote/TransactionalProtocolOperationHandler$ExecuteRequestContext;
       4: aload_1
       5: aload_2
       6: invokevirtual #3                  // Method org/jboss/as/controller/remote/TransactionalProtocolOperationHandler$ExecuteRequestContext.prepare:(Lorg/jboss/as/controller/ModelController$OperationTransaction;Lorg/jboss/dmr/ModelNode;)V
       9: aload_0
      10: getfield      #2                  // Field requestContext:Lorg/jboss/as/controller/remote/TransactionalProtocolOperationHandler$ExecuteRequestContext;
      13: invokestatic  #4                  // Method org/jboss/as/controller/remote/TransactionalProtocolOperationHandler$ExecuteRequestContext.access$1000:(Lorg/jboss/as/controller/remote/TransactionalProtocolOperationHandler$ExecuteRequestContext;)Ljava/util/concurrent/CountDownLatch;
      16: invokevirtual #5                  // Method java/util/concurrent/CountDownLatch.await:()V
      19: goto          46
      22: astore_3
      23: getstatic     #7                  // Field org/jboss/as/controller/logging/ControllerLogger.ROOT_LOGGER:Lorg/jboss/as/controller/logging/ControllerLogger;
      26: ldc           #8                  // String Clearing interrupted status from client request %d
      28: aload_0
      29: getfield      #2                  // Field requestContext:Lorg/jboss/as/controller/remote/TransactionalProtocolOperationHandler$ExecuteRequestContext;
      32: invokevirtual #9                  // Method org/jboss/as/controller/remote/TransactionalProtocolOperationHandler$ExecuteRequestContext.getOperationId:()Ljava/lang/Integer;
      35: invokeinterface #10,  3           // InterfaceMethod org/jboss/as/controller/logging/ControllerLogger.tracef:(Ljava/lang/String;Ljava/lang/Object;)V
      40: invokestatic  #11                 // Method java/lang/Thread.currentThread:()Ljava/lang/Thread;
      43: invokevirtual #12                 // Method java/lang/Thread.interrupt:()V
      46: return
    Exception table:
       from    to  target type
           9    19    22   Class java/lang/InterruptedException
}
