Compiled from "ContextFactory.java"
public class org.apache.hadoop.mapreduce.ContextFactory {
  private static final java.lang.reflect.Constructor<?> JOB_CONTEXT_CONSTRUCTOR;

  private static final java.lang.reflect.Constructor<?> TASK_CONTEXT_CONSTRUCTOR;

  private static final java.lang.reflect.Constructor<?> MAP_CONTEXT_CONSTRUCTOR;

  private static final java.lang.reflect.Constructor<?> MAP_CONTEXT_IMPL_CONSTRUCTOR;

  private static final boolean useV21;

  private static final java.lang.reflect.Field REPORTER_FIELD;

  private static final java.lang.reflect.Field READER_FIELD;

  private static final java.lang.reflect.Field WRITER_FIELD;

  private static final java.lang.reflect.Field OUTER_MAP_FIELD;

  private static final java.lang.reflect.Field WRAPPED_CONTEXT_FIELD;

  public org.apache.hadoop.mapreduce.ContextFactory();
    Code:
       0: aload_0
       1: invokespecial #1                  // Method java/lang/Object."<init>":()V
       4: return

  public static org.apache.hadoop.mapreduce.JobContext cloneContext(org.apache.hadoop.mapreduce.JobContext, org.apache.hadoop.conf.Configuration) throws java.io.IOException, java.lang.InterruptedException;
    Code:
       0: aload_0
       1: instanceof    #2                  // class org/apache/hadoop/mapreduce/MapContext
       4: ifeq          18
       7: aload_0
       8: checkcast     #3                  // class org/apache/hadoop/mapreduce/Mapper$Context
      11: aload_1
      12: aconst_null
      13: aconst_null
      14: invokestatic  #4                  // Method cloneMapContext:(Lorg/apache/hadoop/mapreduce/MapContext;Lorg/apache/hadoop/conf/Configuration;Lorg/apache/hadoop/mapreduce/RecordReader;Lorg/apache/hadoop/mapreduce/RecordWriter;)Lorg/apache/hadoop/mapreduce/Mapper$Context;
      17: areturn
      18: aload_0
      19: instanceof    #5                  // class org/apache/hadoop/mapreduce/ReduceContext
      22: ifeq          35
      25: new           #6                  // class java/lang/IllegalArgumentException
      28: dup
      29: ldc           #7                  // String can\'t clone ReduceContext
      31: invokespecial #8                  // Method java/lang/IllegalArgumentException."<init>":(Ljava/lang/String;)V
      34: athrow
      35: aload_0
      36: instanceof    #9                  // class org/apache/hadoop/mapreduce/TaskAttemptContext
      39: ifeq          74
      42: aload_0
      43: checkcast     #9                  // class org/apache/hadoop/mapreduce/TaskAttemptContext
      46: astore_2
      47: getstatic     #10                 // Field TASK_CONTEXT_CONSTRUCTOR:Ljava/lang/reflect/Constructor;
      50: iconst_2
      51: anewarray     #11                 // class java/lang/Object
      54: dup
      55: iconst_0
      56: aload_1
      57: aastore
      58: dup
      59: iconst_1
      60: aload_2
      61: invokeinterface #12,  1           // InterfaceMethod org/apache/hadoop/mapreduce/TaskAttemptContext.getTaskAttemptID:()Lorg/apache/hadoop/mapreduce/TaskAttemptID;
      66: aastore
      67: invokevirtual #13                 // Method java/lang/reflect/Constructor.newInstance:([Ljava/lang/Object;)Ljava/lang/Object;
      70: checkcast     #14                 // class org/apache/hadoop/mapreduce/JobContext
      73: areturn
      74: getstatic     #15                 // Field JOB_CONTEXT_CONSTRUCTOR:Ljava/lang/reflect/Constructor;
      77: iconst_2
      78: anewarray     #11                 // class java/lang/Object
      81: dup
      82: iconst_0
      83: aload_1
      84: aastore
      85: dup
      86: iconst_1
      87: aload_0
      88: invokeinterface #16,  1           // InterfaceMethod org/apache/hadoop/mapreduce/JobContext.getJobID:()Lorg/apache/hadoop/mapreduce/JobID;
      93: aastore
      94: invokevirtual #13                 // Method java/lang/reflect/Constructor.newInstance:([Ljava/lang/Object;)Ljava/lang/Object;
      97: checkcast     #14                 // class org/apache/hadoop/mapreduce/JobContext
     100: areturn
     101: astore_2
     102: new           #6                  // class java/lang/IllegalArgumentException
     105: dup
     106: ldc           #18                 // String Can\'t clone object
     108: aload_2
     109: invokespecial #19                 // Method java/lang/IllegalArgumentException."<init>":(Ljava/lang/String;Ljava/lang/Throwable;)V
     112: athrow
     113: astore_2
     114: new           #6                  // class java/lang/IllegalArgumentException
     117: dup
     118: ldc           #18                 // String Can\'t clone object
     120: aload_2
     121: invokespecial #19                 // Method java/lang/IllegalArgumentException."<init>":(Ljava/lang/String;Ljava/lang/Throwable;)V
     124: athrow
     125: astore_2
     126: new           #6                  // class java/lang/IllegalArgumentException
     129: dup
     130: ldc           #18                 // String Can\'t clone object
     132: aload_2
     133: invokespecial #19                 // Method java/lang/IllegalArgumentException."<init>":(Ljava/lang/String;Ljava/lang/Throwable;)V
     136: athrow
    Exception table:
       from    to  target type
           0    17   101   Class java/lang/InstantiationException
          18    73   101   Class java/lang/InstantiationException
          74   100   101   Class java/lang/InstantiationException
           0    17   113   Class java/lang/IllegalAccessException
          18    73   113   Class java/lang/IllegalAccessException
          74   100   113   Class java/lang/IllegalAccessException
           0    17   125   Class java/lang/reflect/InvocationTargetException
          18    73   125   Class java/lang/reflect/InvocationTargetException
          74   100   125   Class java/lang/reflect/InvocationTargetException

  public static <K1, V1, K2, V2> org.apache.hadoop.mapreduce.Mapper<K1, V1, K2, V2>.Context cloneMapContext(org.apache.hadoop.mapreduce.MapContext<K1, V1, K2, V2>, org.apache.hadoop.conf.Configuration, org.apache.hadoop.mapreduce.RecordReader<K1, V1>, org.apache.hadoop.mapreduce.RecordWriter<K2, V2>) throws java.io.IOException, java.lang.InterruptedException;
    Code:
       0: getstatic     #22                 // Field OUTER_MAP_FIELD:Ljava/lang/reflect/Field;
       3: aload_0
       4: invokevirtual #23                 // Method java/lang/reflect/Field.get:(Ljava/lang/Object;)Ljava/lang/Object;
       7: astore        4
       9: ldc           #24                 // String org.apache.hadoop.mapreduce.lib.map.WrappedMapper$Context
      11: aload_0
      12: invokevirtual #25                 // Method java/lang/Object.getClass:()Ljava/lang/Class;
      15: invokevirtual #26                 // Method java/lang/Class.getName:()Ljava/lang/String;
      18: invokevirtual #27                 // Method java/lang/String.equals:(Ljava/lang/Object;)Z
      21: ifeq          35
      24: getstatic     #28                 // Field WRAPPED_CONTEXT_FIELD:Ljava/lang/reflect/Field;
      27: aload_0
      28: invokevirtual #23                 // Method java/lang/reflect/Field.get:(Ljava/lang/Object;)Ljava/lang/Object;
      31: checkcast     #2                  // class org/apache/hadoop/mapreduce/MapContext
      34: astore_0
      35: aload_2
      36: ifnonnull     50
      39: getstatic     #29                 // Field READER_FIELD:Ljava/lang/reflect/Field;
      42: aload_0
      43: invokevirtual #23                 // Method java/lang/reflect/Field.get:(Ljava/lang/Object;)Ljava/lang/Object;
      46: checkcast     #30                 // class org/apache/hadoop/mapreduce/RecordReader
      49: astore_2
      50: aload_3
      51: ifnonnull     65
      54: getstatic     #31                 // Field WRITER_FIELD:Ljava/lang/reflect/Field;
      57: aload_0
      58: invokevirtual #23                 // Method java/lang/reflect/Field.get:(Ljava/lang/Object;)Ljava/lang/Object;
      61: checkcast     #32                 // class org/apache/hadoop/mapreduce/RecordWriter
      64: astore_3
      65: getstatic     #33                 // Field useV21:Z
      68: ifeq          158
      71: getstatic     #34                 // Field MAP_CONTEXT_IMPL_CONSTRUCTOR:Ljava/lang/reflect/Constructor;
      74: bipush        7
      76: anewarray     #11                 // class java/lang/Object
      79: dup
      80: iconst_0
      81: aload_1
      82: aastore
      83: dup
      84: iconst_1
      85: aload_0
      86: invokeinterface #35,  1           // InterfaceMethod org/apache/hadoop/mapreduce/MapContext.getTaskAttemptID:()Lorg/apache/hadoop/mapreduce/TaskAttemptID;
      91: aastore
      92: dup
      93: iconst_2
      94: aload_2
      95: aastore
      96: dup
      97: iconst_3
      98: aload_3
      99: aastore
     100: dup
     101: iconst_4
     102: aload_0
     103: invokeinterface #36,  1           // InterfaceMethod org/apache/hadoop/mapreduce/MapContext.getOutputCommitter:()Lorg/apache/hadoop/mapreduce/OutputCommitter;
     108: aastore
     109: dup
     110: iconst_5
     111: getstatic     #37                 // Field REPORTER_FIELD:Ljava/lang/reflect/Field;
     114: aload_0
     115: invokevirtual #23                 // Method java/lang/reflect/Field.get:(Ljava/lang/Object;)Ljava/lang/Object;
     118: aastore
     119: dup
     120: bipush        6
     122: aload_0
     123: invokeinterface #38,  1           // InterfaceMethod org/apache/hadoop/mapreduce/MapContext.getInputSplit:()Lorg/apache/hadoop/mapreduce/InputSplit;
     128: aastore
     129: invokevirtual #13                 // Method java/lang/reflect/Constructor.newInstance:([Ljava/lang/Object;)Ljava/lang/Object;
     132: astore        5
     134: getstatic     #39                 // Field MAP_CONTEXT_CONSTRUCTOR:Ljava/lang/reflect/Constructor;
     137: iconst_2
     138: anewarray     #11                 // class java/lang/Object
     141: dup
     142: iconst_0
     143: aload         4
     145: aastore
     146: dup
     147: iconst_1
     148: aload         5
     150: aastore
     151: invokevirtual #13                 // Method java/lang/reflect/Constructor.newInstance:([Ljava/lang/Object;)Ljava/lang/Object;
     154: checkcast     #3                  // class org/apache/hadoop/mapreduce/Mapper$Context
     157: areturn
     158: getstatic     #39                 // Field MAP_CONTEXT_CONSTRUCTOR:Ljava/lang/reflect/Constructor;
     161: bipush        8
     163: anewarray     #11                 // class java/lang/Object
     166: dup
     167: iconst_0
     168: aload         4
     170: aastore
     171: dup
     172: iconst_1
     173: aload_1
     174: aastore
     175: dup
     176: iconst_2
     177: aload_0
     178: invokeinterface #35,  1           // InterfaceMethod org/apache/hadoop/mapreduce/MapContext.getTaskAttemptID:()Lorg/apache/hadoop/mapreduce/TaskAttemptID;
     183: aastore
     184: dup
     185: iconst_3
     186: aload_2
     187: aastore
     188: dup
     189: iconst_4
     190: aload_3
     191: aastore
     192: dup
     193: iconst_5
     194: aload_0
     195: invokeinterface #36,  1           // InterfaceMethod org/apache/hadoop/mapreduce/MapContext.getOutputCommitter:()Lorg/apache/hadoop/mapreduce/OutputCommitter;
     200: aastore
     201: dup
     202: bipush        6
     204: getstatic     #37                 // Field REPORTER_FIELD:Ljava/lang/reflect/Field;
     207: aload_0
     208: invokevirtual #23                 // Method java/lang/reflect/Field.get:(Ljava/lang/Object;)Ljava/lang/Object;
     211: aastore
     212: dup
     213: bipush        7
     215: aload_0
     216: invokeinterface #38,  1           // InterfaceMethod org/apache/hadoop/mapreduce/MapContext.getInputSplit:()Lorg/apache/hadoop/mapreduce/InputSplit;
     221: aastore
     222: invokevirtual #13                 // Method java/lang/reflect/Constructor.newInstance:([Ljava/lang/Object;)Ljava/lang/Object;
     225: checkcast     #3                  // class org/apache/hadoop/mapreduce/Mapper$Context
     228: areturn
     229: astore        4
     231: new           #6                  // class java/lang/IllegalArgumentException
     234: dup
     235: ldc           #40                 // String Can\'t access field
     237: aload         4
     239: invokespecial #19                 // Method java/lang/IllegalArgumentException."<init>":(Ljava/lang/String;Ljava/lang/Throwable;)V
     242: athrow
     243: astore        4
     245: new           #6                  // class java/lang/IllegalArgumentException
     248: dup
     249: ldc           #41                 // String Can\'t create object
     251: aload         4
     253: invokespecial #19                 // Method java/lang/IllegalArgumentException."<init>":(Ljava/lang/String;Ljava/lang/Throwable;)V
     256: athrow
     257: astore        4
     259: new           #6                  // class java/lang/IllegalArgumentException
     262: dup
     263: ldc           #42                 // String Can\'t invoke constructor
     265: aload         4
     267: invokespecial #19                 // Method java/lang/IllegalArgumentException."<init>":(Ljava/lang/String;Ljava/lang/Throwable;)V
     270: athrow
    Exception table:
       from    to  target type
           0   157   229   Class java/lang/IllegalAccessException
         158   228   229   Class java/lang/IllegalAccessException
           0   157   243   Class java/lang/InstantiationException
         158   228   243   Class java/lang/InstantiationException
           0   157   257   Class java/lang/reflect/InvocationTargetException
         158   228   257   Class java/lang/reflect/InvocationTargetException

  static {};
    Code:
       0: iconst_1
       1: istore_0
       2: ldc           #43                 // String org.apache.hadoop.mapreduce
       4: astore_1
       5: ldc           #44                 // String org.apache.hadoop.mapreduce.task.JobContextImpl
       7: invokestatic  #45                 // Method java/lang/Class.forName:(Ljava/lang/String;)Ljava/lang/Class;
      10: pop
      11: goto          17
      14: astore_2
      15: iconst_0
      16: istore_0
      17: iload_0
      18: putstatic     #33                 // Field useV21:Z
      21: iload_0
      22: ifeq          68
      25: ldc           #44                 // String org.apache.hadoop.mapreduce.task.JobContextImpl
      27: invokestatic  #45                 // Method java/lang/Class.forName:(Ljava/lang/String;)Ljava/lang/Class;
      30: astore_2
      31: ldc           #47                 // String org.apache.hadoop.mapreduce.task.TaskAttemptContextImpl
      33: invokestatic  #45                 // Method java/lang/Class.forName:(Ljava/lang/String;)Ljava/lang/Class;
      36: astore_3
      37: ldc           #48                 // String org.apache.hadoop.mapreduce.task.TaskInputOutputContextImpl
      39: invokestatic  #45                 // Method java/lang/Class.forName:(Ljava/lang/String;)Ljava/lang/Class;
      42: astore        4
      44: ldc           #49                 // String org.apache.hadoop.mapreduce.task.MapContextImpl
      46: invokestatic  #45                 // Method java/lang/Class.forName:(Ljava/lang/String;)Ljava/lang/Class;
      49: astore        6
      51: ldc           #50                 // String org.apache.hadoop.mapreduce.lib.map.WrappedMapper
      53: invokestatic  #45                 // Method java/lang/Class.forName:(Ljava/lang/String;)Ljava/lang/Class;
      56: astore        5
      58: ldc           #24                 // String org.apache.hadoop.mapreduce.lib.map.WrappedMapper$Context
      60: invokestatic  #45                 // Method java/lang/Class.forName:(Ljava/lang/String;)Ljava/lang/Class;
      63: astore        7
      65: goto          108
      68: ldc           #51                 // String org.apache.hadoop.mapreduce.JobContext
      70: invokestatic  #45                 // Method java/lang/Class.forName:(Ljava/lang/String;)Ljava/lang/Class;
      73: astore_2
      74: ldc           #52                 // String org.apache.hadoop.mapreduce.TaskAttemptContext
      76: invokestatic  #45                 // Method java/lang/Class.forName:(Ljava/lang/String;)Ljava/lang/Class;
      79: astore_3
      80: ldc           #53                 // String org.apache.hadoop.mapreduce.TaskInputOutputContext
      82: invokestatic  #45                 // Method java/lang/Class.forName:(Ljava/lang/String;)Ljava/lang/Class;
      85: astore        4
      87: ldc           #54                 // String org.apache.hadoop.mapreduce.MapContext
      89: invokestatic  #45                 // Method java/lang/Class.forName:(Ljava/lang/String;)Ljava/lang/Class;
      92: astore        6
      94: ldc           #55                 // String org.apache.hadoop.mapreduce.Mapper
      96: invokestatic  #45                 // Method java/lang/Class.forName:(Ljava/lang/String;)Ljava/lang/Class;
      99: astore        5
     101: ldc           #56                 // String org.apache.hadoop.mapreduce.Mapper$Context
     103: invokestatic  #45                 // Method java/lang/Class.forName:(Ljava/lang/String;)Ljava/lang/Class;
     106: astore        7
     108: goto          125
     111: astore        8
     113: new           #6                  // class java/lang/IllegalArgumentException
     116: dup
     117: ldc           #57                 // String Can\'t find class
     119: aload         8
     121: invokespecial #19                 // Method java/lang/IllegalArgumentException."<init>":(Ljava/lang/String;Ljava/lang/Throwable;)V
     124: athrow
     125: aload_2
     126: iconst_2
     127: anewarray     #58                 // class java/lang/Class
     130: dup
     131: iconst_0
     132: ldc           #59                 // class org/apache/hadoop/conf/Configuration
     134: aastore
     135: dup
     136: iconst_1
     137: ldc           #60                 // class org/apache/hadoop/mapreduce/JobID
     139: aastore
     140: invokevirtual #61                 // Method java/lang/Class.getConstructor:([Ljava/lang/Class;)Ljava/lang/reflect/Constructor;
     143: putstatic     #15                 // Field JOB_CONTEXT_CONSTRUCTOR:Ljava/lang/reflect/Constructor;
     146: getstatic     #15                 // Field JOB_CONTEXT_CONSTRUCTOR:Ljava/lang/reflect/Constructor;
     149: iconst_1
     150: invokevirtual #62                 // Method java/lang/reflect/Constructor.setAccessible:(Z)V
     153: aload_3
     154: iconst_2
     155: anewarray     #58                 // class java/lang/Class
     158: dup
     159: iconst_0
     160: ldc           #59                 // class org/apache/hadoop/conf/Configuration
     162: aastore
     163: dup
     164: iconst_1
     165: ldc           #63                 // class org/apache/hadoop/mapreduce/TaskAttemptID
     167: aastore
     168: invokevirtual #61                 // Method java/lang/Class.getConstructor:([Ljava/lang/Class;)Ljava/lang/reflect/Constructor;
     171: putstatic     #10                 // Field TASK_CONTEXT_CONSTRUCTOR:Ljava/lang/reflect/Constructor;
     174: getstatic     #10                 // Field TASK_CONTEXT_CONSTRUCTOR:Ljava/lang/reflect/Constructor;
     177: iconst_1
     178: invokevirtual #62                 // Method java/lang/reflect/Constructor.setAccessible:(Z)V
     181: getstatic     #33                 // Field useV21:Z
     184: ifeq          285
     187: aload         7
     189: iconst_2
     190: anewarray     #58                 // class java/lang/Class
     193: dup
     194: iconst_0
     195: aload         5
     197: aastore
     198: dup
     199: iconst_1
     200: ldc           #2                  // class org/apache/hadoop/mapreduce/MapContext
     202: aastore
     203: invokevirtual #61                 // Method java/lang/Class.getConstructor:([Ljava/lang/Class;)Ljava/lang/reflect/Constructor;
     206: putstatic     #39                 // Field MAP_CONTEXT_CONSTRUCTOR:Ljava/lang/reflect/Constructor;
     209: aload         6
     211: bipush        7
     213: anewarray     #58                 // class java/lang/Class
     216: dup
     217: iconst_0
     218: ldc           #59                 // class org/apache/hadoop/conf/Configuration
     220: aastore
     221: dup
     222: iconst_1
     223: ldc           #63                 // class org/apache/hadoop/mapreduce/TaskAttemptID
     225: aastore
     226: dup
     227: iconst_2
     228: ldc           #30                 // class org/apache/hadoop/mapreduce/RecordReader
     230: aastore
     231: dup
     232: iconst_3
     233: ldc           #32                 // class org/apache/hadoop/mapreduce/RecordWriter
     235: aastore
     236: dup
     237: iconst_4
     238: ldc           #64                 // class org/apache/hadoop/mapreduce/OutputCommitter
     240: aastore
     241: dup
     242: iconst_5
     243: ldc           #65                 // class org/apache/hadoop/mapreduce/StatusReporter
     245: aastore
     246: dup
     247: bipush        6
     249: ldc           #66                 // class org/apache/hadoop/mapreduce/InputSplit
     251: aastore
     252: invokevirtual #67                 // Method java/lang/Class.getDeclaredConstructor:([Ljava/lang/Class;)Ljava/lang/reflect/Constructor;
     255: putstatic     #34                 // Field MAP_CONTEXT_IMPL_CONSTRUCTOR:Ljava/lang/reflect/Constructor;
     258: getstatic     #34                 // Field MAP_CONTEXT_IMPL_CONSTRUCTOR:Ljava/lang/reflect/Constructor;
     261: iconst_1
     262: invokevirtual #62                 // Method java/lang/reflect/Constructor.setAccessible:(Z)V
     265: aload         7
     267: ldc           #68                 // String mapContext
     269: invokevirtual #69                 // Method java/lang/Class.getDeclaredField:(Ljava/lang/String;)Ljava/lang/reflect/Field;
     272: putstatic     #28                 // Field WRAPPED_CONTEXT_FIELD:Ljava/lang/reflect/Field;
     275: getstatic     #28                 // Field WRAPPED_CONTEXT_FIELD:Ljava/lang/reflect/Field;
     278: iconst_1
     279: invokevirtual #70                 // Method java/lang/reflect/Field.setAccessible:(Z)V
     282: goto          348
     285: aload         7
     287: bipush        8
     289: anewarray     #58                 // class java/lang/Class
     292: dup
     293: iconst_0
     294: aload         5
     296: aastore
     297: dup
     298: iconst_1
     299: ldc           #59                 // class org/apache/hadoop/conf/Configuration
     301: aastore
     302: dup
     303: iconst_2
     304: ldc           #63                 // class org/apache/hadoop/mapreduce/TaskAttemptID
     306: aastore
     307: dup
     308: iconst_3
     309: ldc           #30                 // class org/apache/hadoop/mapreduce/RecordReader
     311: aastore
     312: dup
     313: iconst_4
     314: ldc           #32                 // class org/apache/hadoop/mapreduce/RecordWriter
     316: aastore
     317: dup
     318: iconst_5
     319: ldc           #64                 // class org/apache/hadoop/mapreduce/OutputCommitter
     321: aastore
     322: dup
     323: bipush        6
     325: ldc           #65                 // class org/apache/hadoop/mapreduce/StatusReporter
     327: aastore
     328: dup
     329: bipush        7
     331: ldc           #66                 // class org/apache/hadoop/mapreduce/InputSplit
     333: aastore
     334: invokevirtual #61                 // Method java/lang/Class.getConstructor:([Ljava/lang/Class;)Ljava/lang/reflect/Constructor;
     337: putstatic     #39                 // Field MAP_CONTEXT_CONSTRUCTOR:Ljava/lang/reflect/Constructor;
     340: aconst_null
     341: putstatic     #34                 // Field MAP_CONTEXT_IMPL_CONSTRUCTOR:Ljava/lang/reflect/Constructor;
     344: aconst_null
     345: putstatic     #28                 // Field WRAPPED_CONTEXT_FIELD:Ljava/lang/reflect/Field;
     348: getstatic     #39                 // Field MAP_CONTEXT_CONSTRUCTOR:Ljava/lang/reflect/Constructor;
     351: iconst_1
     352: invokevirtual #62                 // Method java/lang/reflect/Constructor.setAccessible:(Z)V
     355: aload_3
     356: ldc           #71                 // String reporter
     358: invokevirtual #69                 // Method java/lang/Class.getDeclaredField:(Ljava/lang/String;)Ljava/lang/reflect/Field;
     361: putstatic     #37                 // Field REPORTER_FIELD:Ljava/lang/reflect/Field;
     364: getstatic     #37                 // Field REPORTER_FIELD:Ljava/lang/reflect/Field;
     367: iconst_1
     368: invokevirtual #70                 // Method java/lang/reflect/Field.setAccessible:(Z)V
     371: aload         6
     373: ldc           #72                 // String reader
     375: invokevirtual #69                 // Method java/lang/Class.getDeclaredField:(Ljava/lang/String;)Ljava/lang/reflect/Field;
     378: putstatic     #29                 // Field READER_FIELD:Ljava/lang/reflect/Field;
     381: getstatic     #29                 // Field READER_FIELD:Ljava/lang/reflect/Field;
     384: iconst_1
     385: invokevirtual #70                 // Method java/lang/reflect/Field.setAccessible:(Z)V
     388: aload         4
     390: ldc           #73                 // String output
     392: invokevirtual #69                 // Method java/lang/Class.getDeclaredField:(Ljava/lang/String;)Ljava/lang/reflect/Field;
     395: putstatic     #31                 // Field WRITER_FIELD:Ljava/lang/reflect/Field;
     398: getstatic     #31                 // Field WRITER_FIELD:Ljava/lang/reflect/Field;
     401: iconst_1
     402: invokevirtual #70                 // Method java/lang/reflect/Field.setAccessible:(Z)V
     405: aload         7
     407: ldc           #74                 // String this$0
     409: invokevirtual #69                 // Method java/lang/Class.getDeclaredField:(Ljava/lang/String;)Ljava/lang/reflect/Field;
     412: putstatic     #22                 // Field OUTER_MAP_FIELD:Ljava/lang/reflect/Field;
     415: getstatic     #22                 // Field OUTER_MAP_FIELD:Ljava/lang/reflect/Field;
     418: iconst_1
     419: invokevirtual #70                 // Method java/lang/reflect/Field.setAccessible:(Z)V
     422: goto          467
     425: astore        8
     427: new           #6                  // class java/lang/IllegalArgumentException
     430: dup
     431: ldc           #76                 // String Can\'t run constructor
     433: aload         8
     435: invokespecial #19                 // Method java/lang/IllegalArgumentException."<init>":(Ljava/lang/String;Ljava/lang/Throwable;)V
     438: athrow
     439: astore        8
     441: new           #6                  // class java/lang/IllegalArgumentException
     444: dup
     445: ldc           #78                 // String Can\'t find constructor
     447: aload         8
     449: invokespecial #19                 // Method java/lang/IllegalArgumentException."<init>":(Ljava/lang/String;Ljava/lang/Throwable;)V
     452: athrow
     453: astore        8
     455: new           #6                  // class java/lang/IllegalArgumentException
     458: dup
     459: ldc           #80                 // String Can\'t find field
     461: aload         8
     463: invokespecial #19                 // Method java/lang/IllegalArgumentException."<init>":(Ljava/lang/String;Ljava/lang/Throwable;)V
     466: athrow
     467: return
    Exception table:
       from    to  target type
           5    11    14   Class java/lang/ClassNotFoundException
          21   108   111   Class java/lang/ClassNotFoundException
         125   422   425   Class java/lang/SecurityException
         125   422   439   Class java/lang/NoSuchMethodException
         125   422   453   Class java/lang/NoSuchFieldException
}
