Compiled from "JobID.java"
public class org.apache.hadoop.mapreduce.JobID extends org.apache.hadoop.mapred.ID implements java.lang.Comparable<org.apache.hadoop.mapreduce.ID> {
  public static final java.lang.String JOB;

  public static final java.lang.String JOBID_REGEX;

  private final org.apache.hadoop.io.Text jtIdentifier;

  protected static final java.text.NumberFormat idFormat;

  public org.apache.hadoop.mapreduce.JobID(java.lang.String, int);
    Code:
       0: aload_0
       1: iload_2
       2: invokespecial #3                  // Method org/apache/hadoop/mapred/ID."<init>":(I)V
       5: aload_0
       6: new           #4                  // class org/apache/hadoop/io/Text
       9: dup
      10: aload_1
      11: invokespecial #5                  // Method org/apache/hadoop/io/Text."<init>":(Ljava/lang/String;)V
      14: putfield      #6                  // Field jtIdentifier:Lorg/apache/hadoop/io/Text;
      17: return

  public org.apache.hadoop.mapreduce.JobID();
    Code:
       0: aload_0
       1: invokespecial #7                  // Method org/apache/hadoop/mapred/ID."<init>":()V
       4: aload_0
       5: new           #4                  // class org/apache/hadoop/io/Text
       8: dup
       9: invokespecial #8                  // Method org/apache/hadoop/io/Text."<init>":()V
      12: putfield      #6                  // Field jtIdentifier:Lorg/apache/hadoop/io/Text;
      15: return

  public java.lang.String getJtIdentifier();
    Code:
       0: aload_0
       1: getfield      #6                  // Field jtIdentifier:Lorg/apache/hadoop/io/Text;
       4: invokevirtual #9                  // Method org/apache/hadoop/io/Text.toString:()Ljava/lang/String;
       7: areturn

  public boolean equals(java.lang.Object);
    Code:
       0: aload_0
       1: aload_1
       2: invokespecial #10                 // Method org/apache/hadoop/mapred/ID.equals:(Ljava/lang/Object;)Z
       5: ifne          10
       8: iconst_0
       9: ireturn
      10: aload_1
      11: checkcast     #1                  // class org/apache/hadoop/mapreduce/JobID
      14: astore_2
      15: aload_0
      16: getfield      #6                  // Field jtIdentifier:Lorg/apache/hadoop/io/Text;
      19: aload_2
      20: getfield      #6                  // Field jtIdentifier:Lorg/apache/hadoop/io/Text;
      23: invokevirtual #11                 // Method org/apache/hadoop/io/Text.equals:(Ljava/lang/Object;)Z
      26: ireturn

  public int compareTo(org.apache.hadoop.mapreduce.ID);
    Code:
       0: aload_1
       1: checkcast     #1                  // class org/apache/hadoop/mapreduce/JobID
       4: astore_2
       5: aload_0
       6: getfield      #6                  // Field jtIdentifier:Lorg/apache/hadoop/io/Text;
       9: aload_2
      10: getfield      #6                  // Field jtIdentifier:Lorg/apache/hadoop/io/Text;
      13: invokevirtual #12                 // Method org/apache/hadoop/io/Text.compareTo:(Lorg/apache/hadoop/io/BinaryComparable;)I
      16: istore_3
      17: iload_3
      18: ifne          31
      21: aload_0
      22: getfield      #13                 // Field id:I
      25: aload_2
      26: getfield      #13                 // Field id:I
      29: isub
      30: ireturn
      31: iload_3
      32: ireturn

  public java.lang.StringBuilder appendTo(java.lang.StringBuilder);
    Code:
       0: aload_1
       1: bipush        95
       3: invokevirtual #14                 // Method java/lang/StringBuilder.append:(C)Ljava/lang/StringBuilder;
       6: pop
       7: aload_1
       8: aload_0
       9: getfield      #6                  // Field jtIdentifier:Lorg/apache/hadoop/io/Text;
      12: invokevirtual #15                 // Method java/lang/StringBuilder.append:(Ljava/lang/Object;)Ljava/lang/StringBuilder;
      15: pop
      16: aload_1
      17: bipush        95
      19: invokevirtual #14                 // Method java/lang/StringBuilder.append:(C)Ljava/lang/StringBuilder;
      22: pop
      23: aload_1
      24: getstatic     #16                 // Field idFormat:Ljava/text/NumberFormat;
      27: aload_0
      28: getfield      #13                 // Field id:I
      31: i2l
      32: invokevirtual #17                 // Method java/text/NumberFormat.format:(J)Ljava/lang/String;
      35: invokevirtual #18                 // Method java/lang/StringBuilder.append:(Ljava/lang/String;)Ljava/lang/StringBuilder;
      38: pop
      39: aload_1
      40: areturn

  public int hashCode();
    Code:
       0: aload_0
       1: getfield      #6                  // Field jtIdentifier:Lorg/apache/hadoop/io/Text;
       4: invokevirtual #19                 // Method org/apache/hadoop/io/Text.hashCode:()I
       7: aload_0
       8: getfield      #13                 // Field id:I
      11: iadd
      12: ireturn

  public java.lang.String toString();
    Code:
       0: aload_0
       1: new           #20                 // class java/lang/StringBuilder
       4: dup
       5: ldc           #21                 // String job
       7: invokespecial #22                 // Method java/lang/StringBuilder."<init>":(Ljava/lang/String;)V
      10: invokevirtual #23                 // Method appendTo:(Ljava/lang/StringBuilder;)Ljava/lang/StringBuilder;
      13: invokevirtual #24                 // Method java/lang/StringBuilder.toString:()Ljava/lang/String;
      16: areturn

  public void readFields(java.io.DataInput) throws java.io.IOException;
    Code:
       0: aload_0
       1: aload_1
       2: invokespecial #25                 // Method org/apache/hadoop/mapred/ID.readFields:(Ljava/io/DataInput;)V
       5: aload_0
       6: getfield      #6                  // Field jtIdentifier:Lorg/apache/hadoop/io/Text;
       9: aload_1
      10: invokevirtual #26                 // Method org/apache/hadoop/io/Text.readFields:(Ljava/io/DataInput;)V
      13: return

  public void write(java.io.DataOutput) throws java.io.IOException;
    Code:
       0: aload_0
       1: aload_1
       2: invokespecial #27                 // Method org/apache/hadoop/mapred/ID.write:(Ljava/io/DataOutput;)V
       5: aload_0
       6: getfield      #6                  // Field jtIdentifier:Lorg/apache/hadoop/io/Text;
       9: aload_1
      10: invokevirtual #28                 // Method org/apache/hadoop/io/Text.write:(Ljava/io/DataOutput;)V
      13: return

  public static org.apache.hadoop.mapreduce.JobID forName(java.lang.String) throws java.lang.IllegalArgumentException;
    Code:
       0: aload_0
       1: ifnonnull     6
       4: aconst_null
       5: areturn
       6: aload_0
       7: ldc           #29                 // String _
       9: invokevirtual #30                 // Method java/lang/String.split:(Ljava/lang/String;)[Ljava/lang/String;
      12: astore_1
      13: aload_1
      14: arraylength
      15: iconst_3
      16: if_icmpne     47
      19: aload_1
      20: iconst_0
      21: aaload
      22: ldc           #21                 // String job
      24: invokevirtual #31                 // Method java/lang/String.equals:(Ljava/lang/Object;)Z
      27: ifeq          47
      30: new           #32                 // class org/apache/hadoop/mapred/JobID
      33: dup
      34: aload_1
      35: iconst_1
      36: aaload
      37: aload_1
      38: iconst_2
      39: aaload
      40: invokestatic  #33                 // Method java/lang/Integer.parseInt:(Ljava/lang/String;)I
      43: invokespecial #34                 // Method org/apache/hadoop/mapred/JobID."<init>":(Ljava/lang/String;I)V
      46: areturn
      47: goto          51
      50: astore_1
      51: new           #36                 // class java/lang/IllegalArgumentException
      54: dup
      55: new           #20                 // class java/lang/StringBuilder
      58: dup
      59: invokespecial #37                 // Method java/lang/StringBuilder."<init>":()V
      62: ldc           #38                 // String JobId string :
      64: invokevirtual #18                 // Method java/lang/StringBuilder.append:(Ljava/lang/String;)Ljava/lang/StringBuilder;
      67: aload_0
      68: invokevirtual #18                 // Method java/lang/StringBuilder.append:(Ljava/lang/String;)Ljava/lang/StringBuilder;
      71: ldc           #39                 // String  is not properly formed
      73: invokevirtual #18                 // Method java/lang/StringBuilder.append:(Ljava/lang/String;)Ljava/lang/StringBuilder;
      76: invokevirtual #24                 // Method java/lang/StringBuilder.toString:()Ljava/lang/String;
      79: invokespecial #40                 // Method java/lang/IllegalArgumentException."<init>":(Ljava/lang/String;)V
      82: athrow
    Exception table:
       from    to  target type
           6    46    50   Class java/lang/Exception

  public int compareTo(java.lang.Object);
    Code:
       0: aload_0
       1: aload_1
       2: checkcast     #2                  // class org/apache/hadoop/mapreduce/ID
       5: invokevirtual #41                 // Method compareTo:(Lorg/apache/hadoop/mapreduce/ID;)I
       8: ireturn

  static {};
    Code:
       0: invokestatic  #42                 // Method java/text/NumberFormat.getInstance:()Ljava/text/NumberFormat;
       3: putstatic     #16                 // Field idFormat:Ljava/text/NumberFormat;
       6: getstatic     #16                 // Field idFormat:Ljava/text/NumberFormat;
       9: iconst_0
      10: invokevirtual #43                 // Method java/text/NumberFormat.setGroupingUsed:(Z)V
      13: getstatic     #16                 // Field idFormat:Ljava/text/NumberFormat;
      16: iconst_4
      17: invokevirtual #44                 // Method java/text/NumberFormat.setMinimumIntegerDigits:(I)V
      20: return
}
