Compiled from "JobSubmitter.java"
class org.apache.hadoop.mapreduce.JobSubmitter {
  protected static final org.slf4j.Logger LOG;

  private static final java.lang.String SHUFFLE_KEYGEN_ALGORITHM;

  private static final int SHUFFLE_KEY_LENGTH;

  private org.apache.hadoop.fs.FileSystem jtFs;

  private org.apache.hadoop.mapreduce.protocol.ClientProtocol submitClient;

  private java.lang.String submitHostName;

  private java.lang.String submitHostAddress;

  org.apache.hadoop.mapreduce.JobSubmitter(org.apache.hadoop.fs.FileSystem, org.apache.hadoop.mapreduce.protocol.ClientProtocol) throws java.io.IOException;
    Code:
       0: aload_0
       1: invokespecial #1                  // Method java/lang/Object."<init>":()V
       4: aload_0
       5: aload_2
       6: putfield      #2                  // Field submitClient:Lorg/apache/hadoop/mapreduce/protocol/ClientProtocol;
       9: aload_0
      10: aload_1
      11: putfield      #3                  // Field jtFs:Lorg/apache/hadoop/fs/FileSystem;
      14: return

  private void copyAndConfigureFiles(org.apache.hadoop.mapreduce.Job, org.apache.hadoop.fs.Path) throws java.io.IOException;
    Code:
       0: aload_1
       1: invokevirtual #4                  // Method org/apache/hadoop/mapreduce/Job.getConfiguration:()Lorg/apache/hadoop/conf/Configuration;
       4: astore_3
       5: aload_3
       6: ldc           #6                  // String mapreduce.client.libjars.wildcard
       8: iconst_1
       9: invokevirtual #7                  // Method org/apache/hadoop/conf/Configuration.getBoolean:(Ljava/lang/String;Z)Z
      12: istore        4
      14: new           #8                  // class org/apache/hadoop/mapreduce/JobResourceUploader
      17: dup
      18: aload_0
      19: getfield      #3                  // Field jtFs:Lorg/apache/hadoop/fs/FileSystem;
      22: iload         4
      24: invokespecial #9                  // Method org/apache/hadoop/mapreduce/JobResourceUploader."<init>":(Lorg/apache/hadoop/fs/FileSystem;Z)V
      27: astore        5
      29: aload         5
      31: aload_1
      32: aload_2
      33: invokevirtual #10                 // Method org/apache/hadoop/mapreduce/JobResourceUploader.uploadResources:(Lorg/apache/hadoop/mapreduce/Job;Lorg/apache/hadoop/fs/Path;)V
      36: aload_1
      37: invokevirtual #11                 // Method org/apache/hadoop/mapreduce/Job.getWorkingDirectory:()Lorg/apache/hadoop/fs/Path;
      40: pop
      41: return

  org.apache.hadoop.mapreduce.JobStatus submitJobInternal(org.apache.hadoop.mapreduce.Job, org.apache.hadoop.mapreduce.Cluster) throws java.lang.ClassNotFoundException, java.lang.InterruptedException, java.io.IOException;
    Code:
       0: aload_0
       1: aload_1
       2: invokespecial #12                 // Method checkSpecs:(Lorg/apache/hadoop/mapreduce/Job;)V
       5: aload_1
       6: invokevirtual #4                  // Method org/apache/hadoop/mapreduce/Job.getConfiguration:()Lorg/apache/hadoop/conf/Configuration;
       9: astore_3
      10: aload_3
      11: invokestatic  #13                 // Method addMRFrameworkToDistributedCache:(Lorg/apache/hadoop/conf/Configuration;)V
      14: aload_2
      15: aload_3
      16: invokestatic  #14                 // Method org/apache/hadoop/mapreduce/JobSubmissionFiles.getStagingDir:(Lorg/apache/hadoop/mapreduce/Cluster;Lorg/apache/hadoop/conf/Configuration;)Lorg/apache/hadoop/fs/Path;
      19: astore        4
      21: invokestatic  #15                 // Method java/net/InetAddress.getLocalHost:()Ljava/net/InetAddress;
      24: astore        5
      26: aload         5
      28: ifnull        69
      31: aload_0
      32: aload         5
      34: invokevirtual #16                 // Method java/net/InetAddress.getHostAddress:()Ljava/lang/String;
      37: putfield      #17                 // Field submitHostAddress:Ljava/lang/String;
      40: aload_0
      41: aload         5
      43: invokevirtual #18                 // Method java/net/InetAddress.getHostName:()Ljava/lang/String;
      46: putfield      #19                 // Field submitHostName:Ljava/lang/String;
      49: aload_3
      50: ldc           #21                 // String mapreduce.job.submithostname
      52: aload_0
      53: getfield      #19                 // Field submitHostName:Ljava/lang/String;
      56: invokevirtual #22                 // Method org/apache/hadoop/conf/Configuration.set:(Ljava/lang/String;Ljava/lang/String;)V
      59: aload_3
      60: ldc           #23                 // String mapreduce.job.submithostaddress
      62: aload_0
      63: getfield      #17                 // Field submitHostAddress:Ljava/lang/String;
      66: invokevirtual #22                 // Method org/apache/hadoop/conf/Configuration.set:(Ljava/lang/String;Ljava/lang/String;)V
      69: aload_0
      70: getfield      #2                  // Field submitClient:Lorg/apache/hadoop/mapreduce/protocol/ClientProtocol;
      73: invokeinterface #24,  1           // InterfaceMethod org/apache/hadoop/mapreduce/protocol/ClientProtocol.getNewJobID:()Lorg/apache/hadoop/mapreduce/JobID;
      78: astore        6
      80: aload_1
      81: aload         6
      83: invokevirtual #25                 // Method org/apache/hadoop/mapreduce/Job.setJobID:(Lorg/apache/hadoop/mapreduce/JobID;)V
      86: new           #26                 // class org/apache/hadoop/fs/Path
      89: dup
      90: aload         4
      92: aload         6
      94: invokevirtual #27                 // Method org/apache/hadoop/mapreduce/JobID.toString:()Ljava/lang/String;
      97: invokespecial #28                 // Method org/apache/hadoop/fs/Path."<init>":(Lorg/apache/hadoop/fs/Path;Ljava/lang/String;)V
     100: astore        7
     102: aconst_null
     103: astore        8
     105: aload_3
     106: ldc           #29                 // String mapreduce.job.user.name
     108: invokestatic  #30                 // Method org/apache/hadoop/security/UserGroupInformation.getCurrentUser:()Lorg/apache/hadoop/security/UserGroupInformation;
     111: invokevirtual #31                 // Method org/apache/hadoop/security/UserGroupInformation.getShortUserName:()Ljava/lang/String;
     114: invokevirtual #22                 // Method org/apache/hadoop/conf/Configuration.set:(Ljava/lang/String;Ljava/lang/String;)V
     117: aload_3
     118: ldc           #32                 // String hadoop.http.filter.initializers
     120: ldc           #33                 // String org.apache.hadoop.yarn.server.webproxy.amfilter.AmFilterInitializer
     122: invokevirtual #22                 // Method org/apache/hadoop/conf/Configuration.set:(Ljava/lang/String;Ljava/lang/String;)V
     125: aload_3
     126: ldc           #34                 // String mapreduce.job.dir
     128: aload         7
     130: invokevirtual #35                 // Method org/apache/hadoop/fs/Path.toString:()Ljava/lang/String;
     133: invokevirtual #22                 // Method org/apache/hadoop/conf/Configuration.set:(Ljava/lang/String;Ljava/lang/String;)V
     136: getstatic     #36                 // Field LOG:Lorg/slf4j/Logger;
     139: new           #37                 // class java/lang/StringBuilder
     142: dup
     143: invokespecial #38                 // Method java/lang/StringBuilder."<init>":()V
     146: ldc           #39                 // String Configuring job
     148: invokevirtual #40                 // Method java/lang/StringBuilder.append:(Ljava/lang/String;)Ljava/lang/StringBuilder;
     151: aload         6
     153: invokevirtual #41                 // Method java/lang/StringBuilder.append:(Ljava/lang/Object;)Ljava/lang/StringBuilder;
     156: ldc           #42                 // String  with
     158: invokevirtual #40                 // Method java/lang/StringBuilder.append:(Ljava/lang/String;)Ljava/lang/StringBuilder;
     161: aload         7
     163: invokevirtual #41                 // Method java/lang/StringBuilder.append:(Ljava/lang/Object;)Ljava/lang/StringBuilder;
     166: ldc           #43                 // String  as the submit dir
     168: invokevirtual #40                 // Method java/lang/StringBuilder.append:(Ljava/lang/String;)Ljava/lang/StringBuilder;
     171: invokevirtual #44                 // Method java/lang/StringBuilder.toString:()Ljava/lang/String;
     174: invokeinterface #45,  2           // InterfaceMethod org/slf4j/Logger.debug:(Ljava/lang/String;)V
     179: aload_1
     180: invokevirtual #46                 // Method org/apache/hadoop/mapreduce/Job.getCredentials:()Lorg/apache/hadoop/security/Credentials;
     183: iconst_1
     184: anewarray     #26                 // class org/apache/hadoop/fs/Path
     187: dup
     188: iconst_0
     189: aload         7
     191: aastore
     192: aload_3
     193: invokestatic  #47                 // Method org/apache/hadoop/mapreduce/security/TokenCache.obtainTokensForNamenodes:(Lorg/apache/hadoop/security/Credentials;[Lorg/apache/hadoop/fs/Path;Lorg/apache/hadoop/conf/Configuration;)V
     196: aload_0
     197: aload_3
     198: aload_1
     199: invokevirtual #46                 // Method org/apache/hadoop/mapreduce/Job.getCredentials:()Lorg/apache/hadoop/security/Credentials;
     202: invokespecial #48                 // Method populateTokenCache:(Lorg/apache/hadoop/conf/Configuration;Lorg/apache/hadoop/security/Credentials;)V
     205: aload_1
     206: invokevirtual #46                 // Method org/apache/hadoop/mapreduce/Job.getCredentials:()Lorg/apache/hadoop/security/Credentials;
     209: invokestatic  #49                 // Method org/apache/hadoop/mapreduce/security/TokenCache.getShuffleSecretKey:(Lorg/apache/hadoop/security/Credentials;)[B
     212: ifnonnull     267
     215: ldc           #51                 // String HmacSHA1
     217: invokestatic  #52                 // Method javax/crypto/KeyGenerator.getInstance:(Ljava/lang/String;)Ljavax/crypto/KeyGenerator;
     220: astore        9
     222: aload         9
     224: bipush        64
     226: invokevirtual #53                 // Method javax/crypto/KeyGenerator.init:(I)V
     229: goto          246
     232: astore        10
     234: new           #55                 // class java/io/IOException
     237: dup
     238: ldc           #56                 // String Error generating shuffle secret key
     240: aload         10
     242: invokespecial #57                 // Method java/io/IOException."<init>":(Ljava/lang/String;Ljava/lang/Throwable;)V
     245: athrow
     246: aload         9
     248: invokevirtual #58                 // Method javax/crypto/KeyGenerator.generateKey:()Ljavax/crypto/SecretKey;
     251: astore        10
     253: aload         10
     255: invokeinterface #59,  1           // InterfaceMethod javax/crypto/SecretKey.getEncoded:()[B
     260: aload_1
     261: invokevirtual #46                 // Method org/apache/hadoop/mapreduce/Job.getCredentials:()Lorg/apache/hadoop/security/Credentials;
     264: invokestatic  #60                 // Method org/apache/hadoop/mapreduce/security/TokenCache.setShuffleSecretKey:([BLorg/apache/hadoop/security/Credentials;)V
     267: aload_3
     268: invokestatic  #61                 // Method org/apache/hadoop/mapreduce/CryptoUtils.isEncryptedSpillEnabled:(Lorg/apache/hadoop/conf/Configuration;)Z
     271: ifeq          291
     274: aload_3
     275: ldc           #62                 // String mapreduce.am.max-attempts
     277: iconst_1
     278: invokevirtual #63                 // Method org/apache/hadoop/conf/Configuration.setInt:(Ljava/lang/String;I)V
     281: getstatic     #36                 // Field LOG:Lorg/slf4j/Logger;
     284: ldc           #64                 // String Max job attempts set to 1 since encrypted intermediatedata spill is enabled
     286: invokeinterface #65,  2           // InterfaceMethod org/slf4j/Logger.warn:(Ljava/lang/String;)V
     291: aload_0
     292: aload_1
     293: aload         7
     295: invokespecial #66                 // Method copyAndConfigureFiles:(Lorg/apache/hadoop/mapreduce/Job;Lorg/apache/hadoop/fs/Path;)V
     298: aload         7
     300: invokestatic  #67                 // Method org/apache/hadoop/mapreduce/JobSubmissionFiles.getJobConfPath:(Lorg/apache/hadoop/fs/Path;)Lorg/apache/hadoop/fs/Path;
     303: astore        9
     305: getstatic     #36                 // Field LOG:Lorg/slf4j/Logger;
     308: new           #37                 // class java/lang/StringBuilder
     311: dup
     312: invokespecial #38                 // Method java/lang/StringBuilder."<init>":()V
     315: ldc           #68                 // String Creating splits at
     317: invokevirtual #40                 // Method java/lang/StringBuilder.append:(Ljava/lang/String;)Ljava/lang/StringBuilder;
     320: aload_0
     321: getfield      #3                  // Field jtFs:Lorg/apache/hadoop/fs/FileSystem;
     324: aload         7
     326: invokevirtual #69                 // Method org/apache/hadoop/fs/FileSystem.makeQualified:(Lorg/apache/hadoop/fs/Path;)Lorg/apache/hadoop/fs/Path;
     329: invokevirtual #41                 // Method java/lang/StringBuilder.append:(Ljava/lang/Object;)Ljava/lang/StringBuilder;
     332: invokevirtual #44                 // Method java/lang/StringBuilder.toString:()Ljava/lang/String;
     335: invokeinterface #45,  2           // InterfaceMethod org/slf4j/Logger.debug:(Ljava/lang/String;)V
     340: aload_0
     341: aload_1
     342: aload         7
     344: invokespecial #70                 // Method writeSplits:(Lorg/apache/hadoop/mapreduce/JobContext;Lorg/apache/hadoop/fs/Path;)I
     347: istore        10
     349: aload_3
     350: ldc           #71                 // String mapreduce.job.maps
     352: iload         10
     354: invokevirtual #63                 // Method org/apache/hadoop/conf/Configuration.setInt:(Ljava/lang/String;I)V
     357: getstatic     #36                 // Field LOG:Lorg/slf4j/Logger;
     360: new           #37                 // class java/lang/StringBuilder
     363: dup
     364: invokespecial #38                 // Method java/lang/StringBuilder."<init>":()V
     367: ldc           #72                 // String number of splits:
     369: invokevirtual #40                 // Method java/lang/StringBuilder.append:(Ljava/lang/String;)Ljava/lang/StringBuilder;
     372: iload         10
     374: invokevirtual #73                 // Method java/lang/StringBuilder.append:(I)Ljava/lang/StringBuilder;
     377: invokevirtual #44                 // Method java/lang/StringBuilder.toString:()Ljava/lang/String;
     380: invokeinterface #74,  2           // InterfaceMethod org/slf4j/Logger.info:(Ljava/lang/String;)V
     385: aload_3
     386: ldc           #75                 // String mapreduce.job.max.map
     388: iconst_m1
     389: invokevirtual #76                 // Method org/apache/hadoop/conf/Configuration.getInt:(Ljava/lang/String;I)I
     392: istore        11
     394: iload         11
     396: iflt          444
     399: iload         11
     401: iload         10
     403: if_icmpge     444
     406: new           #77                 // class java/lang/IllegalArgumentException
     409: dup
     410: new           #37                 // class java/lang/StringBuilder
     413: dup
     414: invokespecial #38                 // Method java/lang/StringBuilder."<init>":()V
     417: ldc           #78                 // String The number of map tasks
     419: invokevirtual #40                 // Method java/lang/StringBuilder.append:(Ljava/lang/String;)Ljava/lang/StringBuilder;
     422: iload         10
     424: invokevirtual #73                 // Method java/lang/StringBuilder.append:(I)Ljava/lang/StringBuilder;
     427: ldc           #79                 // String  exceeded limit
     429: invokevirtual #40                 // Method java/lang/StringBuilder.append:(Ljava/lang/String;)Ljava/lang/StringBuilder;
     432: iload         11
     434: invokevirtual #73                 // Method java/lang/StringBuilder.append:(I)Ljava/lang/StringBuilder;
     437: invokevirtual #44                 // Method java/lang/StringBuilder.toString:()Ljava/lang/String;
     440: invokespecial #80                 // Method java/lang/IllegalArgumentException."<init>":(Ljava/lang/String;)V
     443: athrow
     444: aload_3
     445: ldc           #81                 // String mapreduce.job.queuename
     447: ldc           #83                 // String default
     449: invokevirtual #84                 // Method org/apache/hadoop/conf/Configuration.get:(Ljava/lang/String;Ljava/lang/String;)Ljava/lang/String;
     452: astore        12
     454: aload_0
     455: getfield      #2                  // Field submitClient:Lorg/apache/hadoop/mapreduce/protocol/ClientProtocol;
     458: aload         12
     460: invokeinterface #85,  2           // InterfaceMethod org/apache/hadoop/mapreduce/protocol/ClientProtocol.getQueueAdmins:(Ljava/lang/String;)Lorg/apache/hadoop/security/authorize/AccessControlList;
     465: astore        13
     467: aload_3
     468: aload         12
     470: getstatic     #86                 // Field org/apache/hadoop/mapred/QueueACL.ADMINISTER_JOBS:Lorg/apache/hadoop/mapred/QueueACL;
     473: invokevirtual #87                 // Method org/apache/hadoop/mapred/QueueACL.getAclName:()Ljava/lang/String;
     476: invokestatic  #88                 // Method org/apache/hadoop/mapred/QueueManager.toFullPropertyName:(Ljava/lang/String;Ljava/lang/String;)Ljava/lang/String;
     479: aload         13
     481: invokevirtual #89                 // Method org/apache/hadoop/security/authorize/AccessControlList.getAclString:()Ljava/lang/String;
     484: invokevirtual #22                 // Method org/apache/hadoop/conf/Configuration.set:(Ljava/lang/String;Ljava/lang/String;)V
     487: aload_3
     488: invokestatic  #90                 // Method org/apache/hadoop/mapreduce/security/TokenCache.cleanUpTokenReferral:(Lorg/apache/hadoop/conf/Configuration;)V
     491: aload_3
     492: ldc           #91                 // String mapreduce.job.token.tracking.ids.enabled
     494: iconst_0
     495: invokevirtual #7                  // Method org/apache/hadoop/conf/Configuration.getBoolean:(Ljava/lang/String;Z)Z
     498: ifeq          585
     501: new           #92                 // class java/util/ArrayList
     504: dup
     505: invokespecial #93                 // Method java/util/ArrayList."<init>":()V
     508: astore        14
     510: aload_1
     511: invokevirtual #46                 // Method org/apache/hadoop/mapreduce/Job.getCredentials:()Lorg/apache/hadoop/security/Credentials;
     514: invokevirtual #94                 // Method org/apache/hadoop/security/Credentials.getAllTokens:()Ljava/util/Collection;
     517: invokeinterface #95,  1           // InterfaceMethod java/util/Collection.iterator:()Ljava/util/Iterator;
     522: astore        15
     524: aload         15
     526: invokeinterface #96,  1           // InterfaceMethod java/util/Iterator.hasNext:()Z
     531: ifeq          563
     534: aload         15
     536: invokeinterface #97,  1           // InterfaceMethod java/util/Iterator.next:()Ljava/lang/Object;
     541: checkcast     #98                 // class org/apache/hadoop/security/token/Token
     544: astore        16
     546: aload         14
     548: aload         16
     550: invokevirtual #99                 // Method org/apache/hadoop/security/token/Token.decodeIdentifier:()Lorg/apache/hadoop/security/token/TokenIdentifier;
     553: invokevirtual #100                // Method org/apache/hadoop/security/token/TokenIdentifier.getTrackingId:()Ljava/lang/String;
     556: invokevirtual #101                // Method java/util/ArrayList.add:(Ljava/lang/Object;)Z
     559: pop
     560: goto          524
     563: aload_3
     564: ldc           #102                // String mapreduce.job.token.tracking.ids
     566: aload         14
     568: aload         14
     570: invokevirtual #103                // Method java/util/ArrayList.size:()I
     573: anewarray     #104                // class java/lang/String
     576: invokevirtual #105                // Method java/util/ArrayList.toArray:([Ljava/lang/Object;)[Ljava/lang/Object;
     579: checkcast     #106                // class "[Ljava/lang/String;"
     582: invokevirtual #107                // Method org/apache/hadoop/conf/Configuration.setStrings:(Ljava/lang/String;[Ljava/lang/String;)V
     585: aload_1
     586: invokevirtual #108                // Method org/apache/hadoop/mapreduce/Job.getReservationId:()Lorg/apache/hadoop/yarn/api/records/ReservationId;
     589: astore        14
     591: aload         14
     593: ifnull        607
     596: aload_3
     597: ldc           #109                // String mapreduce.job.reservation.id
     599: aload         14
     601: invokevirtual #110                // Method org/apache/hadoop/yarn/api/records/ReservationId.toString:()Ljava/lang/String;
     604: invokevirtual #22                 // Method org/apache/hadoop/conf/Configuration.set:(Ljava/lang/String;Ljava/lang/String;)V
     607: aload_0
     608: aload_3
     609: aload         9
     611: invokespecial #111                // Method writeConf:(Lorg/apache/hadoop/conf/Configuration;Lorg/apache/hadoop/fs/Path;)V
     614: aload_0
     615: aload         6
     617: aload_1
     618: invokevirtual #46                 // Method org/apache/hadoop/mapreduce/Job.getCredentials:()Lorg/apache/hadoop/security/Credentials;
     621: invokespecial #112                // Method printTokens:(Lorg/apache/hadoop/mapreduce/JobID;Lorg/apache/hadoop/security/Credentials;)V
     624: aload_0
     625: getfield      #2                  // Field submitClient:Lorg/apache/hadoop/mapreduce/protocol/ClientProtocol;
     628: aload         6
     630: aload         7
     632: invokevirtual #35                 // Method org/apache/hadoop/fs/Path.toString:()Ljava/lang/String;
     635: aload_1
     636: invokevirtual #46                 // Method org/apache/hadoop/mapreduce/Job.getCredentials:()Lorg/apache/hadoop/security/Credentials;
     639: invokeinterface #113,  4          // InterfaceMethod org/apache/hadoop/mapreduce/protocol/ClientProtocol.submitJob:(Lorg/apache/hadoop/mapreduce/JobID;Ljava/lang/String;Lorg/apache/hadoop/security/Credentials;)Lorg/apache/hadoop/mapreduce/JobStatus;
     644: astore        8
     646: aload         8
     648: ifnull        714
     651: aload         8
     653: astore        15
     655: aload         8
     657: ifnonnull     711
     660: getstatic     #36                 // Field LOG:Lorg/slf4j/Logger;
     663: new           #37                 // class java/lang/StringBuilder
     666: dup
     667: invokespecial #38                 // Method java/lang/StringBuilder."<init>":()V
     670: ldc           #114                // String Cleaning up the staging area
     672: invokevirtual #40                 // Method java/lang/StringBuilder.append:(Ljava/lang/String;)Ljava/lang/StringBuilder;
     675: aload         7
     677: invokevirtual #41                 // Method java/lang/StringBuilder.append:(Ljava/lang/Object;)Ljava/lang/StringBuilder;
     680: invokevirtual #44                 // Method java/lang/StringBuilder.toString:()Ljava/lang/String;
     683: invokeinterface #74,  2           // InterfaceMethod org/slf4j/Logger.info:(Ljava/lang/String;)V
     688: aload_0
     689: getfield      #3                  // Field jtFs:Lorg/apache/hadoop/fs/FileSystem;
     692: ifnull        711
     695: aload         7
     697: ifnull        711
     700: aload_0
     701: getfield      #3                  // Field jtFs:Lorg/apache/hadoop/fs/FileSystem;
     704: aload         7
     706: iconst_1
     707: invokevirtual #115                // Method org/apache/hadoop/fs/FileSystem.delete:(Lorg/apache/hadoop/fs/Path;Z)Z
     710: pop
     711: aload         15
     713: areturn
     714: new           #55                 // class java/io/IOException
     717: dup
     718: ldc           #116                // String Could not launch job
     720: invokespecial #117                // Method java/io/IOException."<init>":(Ljava/lang/String;)V
     723: athrow
     724: astore        17
     726: aload         8
     728: ifnonnull     782
     731: getstatic     #36                 // Field LOG:Lorg/slf4j/Logger;
     734: new           #37                 // class java/lang/StringBuilder
     737: dup
     738: invokespecial #38                 // Method java/lang/StringBuilder."<init>":()V
     741: ldc           #114                // String Cleaning up the staging area
     743: invokevirtual #40                 // Method java/lang/StringBuilder.append:(Ljava/lang/String;)Ljava/lang/StringBuilder;
     746: aload         7
     748: invokevirtual #41                 // Method java/lang/StringBuilder.append:(Ljava/lang/Object;)Ljava/lang/StringBuilder;
     751: invokevirtual #44                 // Method java/lang/StringBuilder.toString:()Ljava/lang/String;
     754: invokeinterface #74,  2           // InterfaceMethod org/slf4j/Logger.info:(Ljava/lang/String;)V
     759: aload_0
     760: getfield      #3                  // Field jtFs:Lorg/apache/hadoop/fs/FileSystem;
     763: ifnull        782
     766: aload         7
     768: ifnull        782
     771: aload_0
     772: getfield      #3                  // Field jtFs:Lorg/apache/hadoop/fs/FileSystem;
     775: aload         7
     777: iconst_1
     778: invokevirtual #115                // Method org/apache/hadoop/fs/FileSystem.delete:(Lorg/apache/hadoop/fs/Path;Z)Z
     781: pop
     782: aload         17
     784: athrow
    Exception table:
       from    to  target type
         215   229   232   Class java/security/NoSuchAlgorithmException
         105   655   724   any
         714   726   724   any

  private void checkSpecs(org.apache.hadoop.mapreduce.Job) throws java.lang.ClassNotFoundException, java.lang.InterruptedException, java.io.IOException;
    Code:
       0: aload_1
       1: invokevirtual #4                  // Method org/apache/hadoop/mapreduce/Job.getConfiguration:()Lorg/apache/hadoop/conf/Configuration;
       4: checkcast     #82                 // class org/apache/hadoop/mapred/JobConf
       7: astore_2
       8: aload_2
       9: invokevirtual #118                // Method org/apache/hadoop/mapred/JobConf.getNumReduceTasks:()I
      12: ifne          25
      15: aload_2
      16: invokevirtual #119                // Method org/apache/hadoop/mapred/JobConf.getUseNewMapper:()Z
      19: ifeq          55
      22: goto          32
      25: aload_2
      26: invokevirtual #120                // Method org/apache/hadoop/mapred/JobConf.getUseNewReducer:()Z
      29: ifeq          55
      32: aload_1
      33: invokevirtual #121                // Method org/apache/hadoop/mapreduce/Job.getOutputFormatClass:()Ljava/lang/Class;
      36: aload_1
      37: invokevirtual #4                  // Method org/apache/hadoop/mapreduce/Job.getConfiguration:()Lorg/apache/hadoop/conf/Configuration;
      40: invokestatic  #122                // Method org/apache/hadoop/util/ReflectionUtils.newInstance:(Ljava/lang/Class;Lorg/apache/hadoop/conf/Configuration;)Ljava/lang/Object;
      43: checkcast     #123                // class org/apache/hadoop/mapreduce/OutputFormat
      46: astore_3
      47: aload_3
      48: aload_1
      49: invokevirtual #124                // Method org/apache/hadoop/mapreduce/OutputFormat.checkOutputSpecs:(Lorg/apache/hadoop/mapreduce/JobContext;)V
      52: goto          69
      55: aload_2
      56: invokevirtual #125                // Method org/apache/hadoop/mapred/JobConf.getOutputFormat:()Lorg/apache/hadoop/mapred/OutputFormat;
      59: aload_0
      60: getfield      #3                  // Field jtFs:Lorg/apache/hadoop/fs/FileSystem;
      63: aload_2
      64: invokeinterface #126,  3          // InterfaceMethod org/apache/hadoop/mapred/OutputFormat.checkOutputSpecs:(Lorg/apache/hadoop/fs/FileSystem;Lorg/apache/hadoop/mapred/JobConf;)V
      69: return

  private void writeConf(org.apache.hadoop.conf.Configuration, org.apache.hadoop.fs.Path) throws java.io.IOException;
    Code:
       0: aload_0
       1: getfield      #3                  // Field jtFs:Lorg/apache/hadoop/fs/FileSystem;
       4: aload_2
       5: new           #127                // class org/apache/hadoop/fs/permission/FsPermission
       8: dup
       9: getstatic     #128                // Field org/apache/hadoop/mapreduce/JobSubmissionFiles.JOB_FILE_PERMISSION:Lorg/apache/hadoop/fs/permission/FsPermission;
      12: invokespecial #129                // Method org/apache/hadoop/fs/permission/FsPermission."<init>":(Lorg/apache/hadoop/fs/permission/FsPermission;)V
      15: invokestatic  #130                // Method org/apache/hadoop/fs/FileSystem.create:(Lorg/apache/hadoop/fs/FileSystem;Lorg/apache/hadoop/fs/Path;Lorg/apache/hadoop/fs/permission/FsPermission;)Lorg/apache/hadoop/fs/FSDataOutputStream;
      18: astore_3
      19: aload_1
      20: aload_3
      21: invokevirtual #131                // Method org/apache/hadoop/conf/Configuration.writeXml:(Ljava/io/OutputStream;)V
      24: aload_3
      25: invokevirtual #132                // Method org/apache/hadoop/fs/FSDataOutputStream.close:()V
      28: goto          40
      31: astore        4
      33: aload_3
      34: invokevirtual #132                // Method org/apache/hadoop/fs/FSDataOutputStream.close:()V
      37: aload         4
      39: athrow
      40: return
    Exception table:
       from    to  target type
          19    24    31   any
          31    33    31   any

  private void printTokens(org.apache.hadoop.mapreduce.JobID, org.apache.hadoop.security.Credentials) throws java.io.IOException;
    Code:
       0: getstatic     #36                 // Field LOG:Lorg/slf4j/Logger;
       3: new           #37                 // class java/lang/StringBuilder
       6: dup
       7: invokespecial #38                 // Method java/lang/StringBuilder."<init>":()V
      10: ldc           #133                // String Submitting tokens for job:
      12: invokevirtual #40                 // Method java/lang/StringBuilder.append:(Ljava/lang/String;)Ljava/lang/StringBuilder;
      15: aload_1
      16: invokevirtual #41                 // Method java/lang/StringBuilder.append:(Ljava/lang/Object;)Ljava/lang/StringBuilder;
      19: invokevirtual #44                 // Method java/lang/StringBuilder.toString:()Ljava/lang/String;
      22: invokeinterface #74,  2           // InterfaceMethod org/slf4j/Logger.info:(Ljava/lang/String;)V
      27: getstatic     #36                 // Field LOG:Lorg/slf4j/Logger;
      30: ldc           #134                // String Executing with tokens: {}
      32: aload_2
      33: invokevirtual #94                 // Method org/apache/hadoop/security/Credentials.getAllTokens:()Ljava/util/Collection;
      36: invokeinterface #135,  3          // InterfaceMethod org/slf4j/Logger.info:(Ljava/lang/String;Ljava/lang/Object;)V
      41: return

  private <T extends org.apache.hadoop.mapreduce.InputSplit> int writeNewSplits(org.apache.hadoop.mapreduce.JobContext, org.apache.hadoop.fs.Path) throws java.io.IOException, java.lang.InterruptedException, java.lang.ClassNotFoundException;
    Code:
       0: aload_1
       1: invokeinterface #136,  1          // InterfaceMethod org/apache/hadoop/mapreduce/JobContext.getConfiguration:()Lorg/apache/hadoop/conf/Configuration;
       6: astore_3
       7: aload_1
       8: invokeinterface #137,  1          // InterfaceMethod org/apache/hadoop/mapreduce/JobContext.getInputFormatClass:()Ljava/lang/Class;
      13: aload_3
      14: invokestatic  #122                // Method org/apache/hadoop/util/ReflectionUtils.newInstance:(Ljava/lang/Class;Lorg/apache/hadoop/conf/Configuration;)Ljava/lang/Object;
      17: checkcast     #138                // class org/apache/hadoop/mapreduce/InputFormat
      20: astore        4
      22: aload         4
      24: aload_1
      25: invokevirtual #139                // Method org/apache/hadoop/mapreduce/InputFormat.getSplits:(Lorg/apache/hadoop/mapreduce/JobContext;)Ljava/util/List;
      28: astore        5
      30: aload         5
      32: aload         5
      34: invokeinterface #140,  1          // InterfaceMethod java/util/List.size:()I
      39: anewarray     #141                // class org/apache/hadoop/mapreduce/InputSplit
      42: invokeinterface #142,  2          // InterfaceMethod java/util/List.toArray:([Ljava/lang/Object;)[Ljava/lang/Object;
      47: checkcast     #143                // class "[Lorg/apache/hadoop/mapreduce/InputSplit;"
      50: checkcast     #143                // class "[Lorg/apache/hadoop/mapreduce/InputSplit;"
      53: astore        6
      55: aload         6
      57: new           #144                // class org/apache/hadoop/mapreduce/JobSubmitter$SplitComparator
      60: dup
      61: aconst_null
      62: invokespecial #145                // Method org/apache/hadoop/mapreduce/JobSubmitter$SplitComparator."<init>":(Lorg/apache/hadoop/mapreduce/JobSubmitter$1;)V
      65: invokestatic  #146                // Method java/util/Arrays.sort:([Ljava/lang/Object;Ljava/util/Comparator;)V
      68: aload_2
      69: aload_3
      70: aload_2
      71: aload_3
      72: invokevirtual #147                // Method org/apache/hadoop/fs/Path.getFileSystem:(Lorg/apache/hadoop/conf/Configuration;)Lorg/apache/hadoop/fs/FileSystem;
      75: aload         6
      77: invokestatic  #148                // Method org/apache/hadoop/mapreduce/split/JobSplitWriter.createSplitFiles:(Lorg/apache/hadoop/fs/Path;Lorg/apache/hadoop/conf/Configuration;Lorg/apache/hadoop/fs/FileSystem;[Lorg/apache/hadoop/mapreduce/InputSplit;)V
      80: aload         6
      82: arraylength
      83: ireturn

  private int writeSplits(org.apache.hadoop.mapreduce.JobContext, org.apache.hadoop.fs.Path) throws java.io.IOException, java.lang.InterruptedException, java.lang.ClassNotFoundException;
    Code:
       0: aload_1
       1: invokeinterface #136,  1          // InterfaceMethod org/apache/hadoop/mapreduce/JobContext.getConfiguration:()Lorg/apache/hadoop/conf/Configuration;
       6: checkcast     #82                 // class org/apache/hadoop/mapred/JobConf
       9: astore_3
      10: aload_3
      11: invokevirtual #119                // Method org/apache/hadoop/mapred/JobConf.getUseNewMapper:()Z
      14: ifeq          28
      17: aload_0
      18: aload_1
      19: aload_2
      20: invokespecial #149                // Method writeNewSplits:(Lorg/apache/hadoop/mapreduce/JobContext;Lorg/apache/hadoop/fs/Path;)I
      23: istore        4
      25: goto          36
      28: aload_0
      29: aload_3
      30: aload_2
      31: invokespecial #150                // Method writeOldSplits:(Lorg/apache/hadoop/mapred/JobConf;Lorg/apache/hadoop/fs/Path;)I
      34: istore        4
      36: iload         4
      38: ireturn

  private int writeOldSplits(org.apache.hadoop.mapred.JobConf, org.apache.hadoop.fs.Path) throws java.io.IOException;
    Code:
       0: aload_1
       1: invokevirtual #151                // Method org/apache/hadoop/mapred/JobConf.getInputFormat:()Lorg/apache/hadoop/mapred/InputFormat;
       4: aload_1
       5: aload_1
       6: invokevirtual #152                // Method org/apache/hadoop/mapred/JobConf.getNumMapTasks:()I
       9: invokeinterface #153,  3          // InterfaceMethod org/apache/hadoop/mapred/InputFormat.getSplits:(Lorg/apache/hadoop/mapred/JobConf;I)[Lorg/apache/hadoop/mapred/InputSplit;
      14: astore_3
      15: aload_3
      16: new           #154                // class org/apache/hadoop/mapreduce/JobSubmitter$1
      19: dup
      20: aload_0
      21: invokespecial #155                // Method org/apache/hadoop/mapreduce/JobSubmitter$1."<init>":(Lorg/apache/hadoop/mapreduce/JobSubmitter;)V
      24: invokestatic  #146                // Method java/util/Arrays.sort:([Ljava/lang/Object;Ljava/util/Comparator;)V
      27: aload_2
      28: aload_1
      29: aload_2
      30: aload_1
      31: invokevirtual #147                // Method org/apache/hadoop/fs/Path.getFileSystem:(Lorg/apache/hadoop/conf/Configuration;)Lorg/apache/hadoop/fs/FileSystem;
      34: aload_3
      35: invokestatic  #156                // Method org/apache/hadoop/mapreduce/split/JobSplitWriter.createSplitFiles:(Lorg/apache/hadoop/fs/Path;Lorg/apache/hadoop/conf/Configuration;Lorg/apache/hadoop/fs/FileSystem;[Lorg/apache/hadoop/mapred/InputSplit;)V
      38: aload_3
      39: arraylength
      40: ireturn

  private void readTokensFromFiles(org.apache.hadoop.conf.Configuration, org.apache.hadoop.security.Credentials) throws java.io.IOException;
    Code:
       0: aload_1
       1: ldc           #157                // String mapreduce.job.credentials.binary
       3: invokevirtual #158                // Method org/apache/hadoop/conf/Configuration.get:(Ljava/lang/String;)Ljava/lang/String;
       6: astore_3
       7: aload_3
       8: ifnull        38
      11: aload_1
      12: invokestatic  #159                // Method org/apache/hadoop/fs/FileSystem.getLocal:(Lorg/apache/hadoop/conf/Configuration;)Lorg/apache/hadoop/fs/LocalFileSystem;
      15: new           #26                 // class org/apache/hadoop/fs/Path
      18: dup
      19: aload_3
      20: invokespecial #160                // Method org/apache/hadoop/fs/Path."<init>":(Ljava/lang/String;)V
      23: invokevirtual #161                // Method org/apache/hadoop/fs/LocalFileSystem.makeQualified:(Lorg/apache/hadoop/fs/Path;)Lorg/apache/hadoop/fs/Path;
      26: aload_1
      27: invokestatic  #162                // Method org/apache/hadoop/security/Credentials.readTokenStorageFile:(Lorg/apache/hadoop/fs/Path;Lorg/apache/hadoop/conf/Configuration;)Lorg/apache/hadoop/security/Credentials;
      30: astore        4
      32: aload_2
      33: aload         4
      35: invokevirtual #163                // Method org/apache/hadoop/security/Credentials.addAll:(Lorg/apache/hadoop/security/Credentials;)V
      38: aload_1
      39: ldc           #164                // String mapreduce.job.credentials.json
      41: invokevirtual #158                // Method org/apache/hadoop/conf/Configuration.get:(Ljava/lang/String;)Ljava/lang/String;
      44: astore        4
      46: aload         4
      48: ifnull        207
      51: getstatic     #36                 // Field LOG:Lorg/slf4j/Logger;
      54: new           #37                 // class java/lang/StringBuilder
      57: dup
      58: invokespecial #38                 // Method java/lang/StringBuilder."<init>":()V
      61: ldc           #165                // String loading user\'s secret keys from
      63: invokevirtual #40                 // Method java/lang/StringBuilder.append:(Ljava/lang/String;)Ljava/lang/StringBuilder;
      66: aload         4
      68: invokevirtual #40                 // Method java/lang/StringBuilder.append:(Ljava/lang/String;)Ljava/lang/StringBuilder;
      71: invokevirtual #44                 // Method java/lang/StringBuilder.toString:()Ljava/lang/String;
      74: invokeinterface #74,  2           // InterfaceMethod org/slf4j/Logger.info:(Ljava/lang/String;)V
      79: new           #26                 // class org/apache/hadoop/fs/Path
      82: dup
      83: aload         4
      85: invokespecial #160                // Method org/apache/hadoop/fs/Path."<init>":(Ljava/lang/String;)V
      88: invokevirtual #166                // Method org/apache/hadoop/fs/Path.toUri:()Ljava/net/URI;
      91: invokevirtual #167                // Method java/net/URI.getPath:()Ljava/lang/String;
      94: astore        5
      96: invokestatic  #168                // Method org/apache/hadoop/util/JsonSerialization.mapReader:()Lcom/fasterxml/jackson/databind/ObjectReader;
      99: new           #169                // class java/io/File
     102: dup
     103: aload         5
     105: invokespecial #170                // Method java/io/File."<init>":(Ljava/lang/String;)V
     108: invokevirtual #171                // Method com/fasterxml/jackson/databind/ObjectReader.readValue:(Ljava/io/File;)Ljava/lang/Object;
     111: checkcast     #172                // class java/util/Map
     114: astore        6
     116: aload         6
     118: invokeinterface #173,  1          // InterfaceMethod java/util/Map.entrySet:()Ljava/util/Set;
     123: invokeinterface #174,  1          // InterfaceMethod java/util/Set.iterator:()Ljava/util/Iterator;
     128: astore        7
     130: aload         7
     132: invokeinterface #96,  1           // InterfaceMethod java/util/Iterator.hasNext:()Z
     137: ifeq          192
     140: aload         7
     142: invokeinterface #97,  1           // InterfaceMethod java/util/Iterator.next:()Ljava/lang/Object;
     147: checkcast     #175                // class java/util/Map$Entry
     150: astore        8
     152: aload_2
     153: new           #176                // class org/apache/hadoop/io/Text
     156: dup
     157: aload         8
     159: invokeinterface #177,  1          // InterfaceMethod java/util/Map$Entry.getKey:()Ljava/lang/Object;
     164: checkcast     #104                // class java/lang/String
     167: invokespecial #178                // Method org/apache/hadoop/io/Text."<init>":(Ljava/lang/String;)V
     170: aload         8
     172: invokeinterface #179,  1          // InterfaceMethod java/util/Map$Entry.getValue:()Ljava/lang/Object;
     177: checkcast     #104                // class java/lang/String
     180: getstatic     #180                // Field com/google/common/base/Charsets.UTF_8:Ljava/nio/charset/Charset;
     183: invokevirtual #181                // Method java/lang/String.getBytes:(Ljava/nio/charset/Charset;)[B
     186: invokevirtual #182                // Method org/apache/hadoop/security/Credentials.addSecretKey:(Lorg/apache/hadoop/io/Text;[B)V
     189: goto          130
     192: goto          207
     195: astore        6
     197: getstatic     #36                 // Field LOG:Lorg/slf4j/Logger;
     200: ldc           #185                // String couldn\'t parse Token Cache JSON file with user secret keys
     202: invokeinterface #65,  2           // InterfaceMethod org/slf4j/Logger.warn:(Ljava/lang/String;)V
     207: return
    Exception table:
       from    to  target type
          96   192   195   Class com/fasterxml/jackson/databind/JsonMappingException
          96   192   195   Class com/fasterxml/jackson/core/JsonParseException

  private void populateTokenCache(org.apache.hadoop.conf.Configuration, org.apache.hadoop.security.Credentials) throws java.io.IOException;
    Code:
       0: aload_0
       1: aload_1
       2: aload_2
       3: invokespecial #186                // Method readTokensFromFiles:(Lorg/apache/hadoop/conf/Configuration;Lorg/apache/hadoop/security/Credentials;)V
       6: aload_1
       7: ldc           #187                // String mapreduce.job.hdfs-servers
       9: invokevirtual #188                // Method org/apache/hadoop/conf/Configuration.getStrings:(Ljava/lang/String;)[Ljava/lang/String;
      12: astore_3
      13: getstatic     #36                 // Field LOG:Lorg/slf4j/Logger;
      16: new           #37                 // class java/lang/StringBuilder
      19: dup
      20: invokespecial #38                 // Method java/lang/StringBuilder."<init>":()V
      23: ldc           #189                // String adding the following namenodes\' delegation tokens:
      25: invokevirtual #40                 // Method java/lang/StringBuilder.append:(Ljava/lang/String;)Ljava/lang/StringBuilder;
      28: aload_3
      29: invokestatic  #190                // Method java/util/Arrays.toString:([Ljava/lang/Object;)Ljava/lang/String;
      32: invokevirtual #40                 // Method java/lang/StringBuilder.append:(Ljava/lang/String;)Ljava/lang/StringBuilder;
      35: invokevirtual #44                 // Method java/lang/StringBuilder.toString:()Ljava/lang/String;
      38: invokeinterface #45,  2           // InterfaceMethod org/slf4j/Logger.debug:(Ljava/lang/String;)V
      43: aload_3
      44: ifnull        93
      47: aload_3
      48: arraylength
      49: anewarray     #26                 // class org/apache/hadoop/fs/Path
      52: astore        4
      54: iconst_0
      55: istore        5
      57: iload         5
      59: aload_3
      60: arraylength
      61: if_icmpge     86
      64: aload         4
      66: iload         5
      68: new           #26                 // class org/apache/hadoop/fs/Path
      71: dup
      72: aload_3
      73: iload         5
      75: aaload
      76: invokespecial #160                // Method org/apache/hadoop/fs/Path."<init>":(Ljava/lang/String;)V
      79: aastore
      80: iinc          5, 1
      83: goto          57
      86: aload_2
      87: aload         4
      89: aload_1
      90: invokestatic  #47                 // Method org/apache/hadoop/mapreduce/security/TokenCache.obtainTokensForNamenodes:(Lorg/apache/hadoop/security/Credentials;[Lorg/apache/hadoop/fs/Path;Lorg/apache/hadoop/conf/Configuration;)V
      93: return

  private static void addMRFrameworkToDistributedCache(org.apache.hadoop.conf.Configuration) throws java.io.IOException;
    Code:
       0: aload_0
       1: ldc           #191                // String mapreduce.application.framework.path
       3: ldc           #192                // String
       5: invokevirtual #84                 // Method org/apache/hadoop/conf/Configuration.get:(Ljava/lang/String;Ljava/lang/String;)Ljava/lang/String;
       8: astore_1
       9: aload_1
      10: invokevirtual #193                // Method java/lang/String.isEmpty:()Z
      13: ifne          173
      16: new           #194                // class java/net/URI
      19: dup
      20: aload_1
      21: invokespecial #195                // Method java/net/URI."<init>":(Ljava/lang/String;)V
      24: astore_2
      25: goto          67
      28: astore_3
      29: new           #77                 // class java/lang/IllegalArgumentException
      32: dup
      33: new           #37                 // class java/lang/StringBuilder
      36: dup
      37: invokespecial #38                 // Method java/lang/StringBuilder."<init>":()V
      40: ldc           #197                // String Unable to parse \'
      42: invokevirtual #40                 // Method java/lang/StringBuilder.append:(Ljava/lang/String;)Ljava/lang/StringBuilder;
      45: aload_1
      46: invokevirtual #40                 // Method java/lang/StringBuilder.append:(Ljava/lang/String;)Ljava/lang/StringBuilder;
      49: ldc           #198                // String \' as a URI, check the setting for
      51: invokevirtual #40                 // Method java/lang/StringBuilder.append:(Ljava/lang/String;)Ljava/lang/StringBuilder;
      54: ldc           #191                // String mapreduce.application.framework.path
      56: invokevirtual #40                 // Method java/lang/StringBuilder.append:(Ljava/lang/String;)Ljava/lang/StringBuilder;
      59: invokevirtual #44                 // Method java/lang/StringBuilder.toString:()Ljava/lang/String;
      62: aload_3
      63: invokespecial #199                // Method java/lang/IllegalArgumentException."<init>":(Ljava/lang/String;Ljava/lang/Throwable;)V
      66: athrow
      67: aload_2
      68: invokevirtual #200                // Method java/net/URI.getFragment:()Ljava/lang/String;
      71: astore_3
      72: aload_2
      73: aload_0
      74: invokestatic  #201                // Method org/apache/hadoop/fs/FileSystem.get:(Ljava/net/URI;Lorg/apache/hadoop/conf/Configuration;)Lorg/apache/hadoop/fs/FileSystem;
      77: astore        4
      79: aload         4
      81: new           #26                 // class org/apache/hadoop/fs/Path
      84: dup
      85: aload_2
      86: invokevirtual #202                // Method java/net/URI.getScheme:()Ljava/lang/String;
      89: aload_2
      90: invokevirtual #203                // Method java/net/URI.getAuthority:()Ljava/lang/String;
      93: aload_2
      94: invokevirtual #167                // Method java/net/URI.getPath:()Ljava/lang/String;
      97: invokespecial #204                // Method org/apache/hadoop/fs/Path."<init>":(Ljava/lang/String;Ljava/lang/String;Ljava/lang/String;)V
     100: invokevirtual #69                 // Method org/apache/hadoop/fs/FileSystem.makeQualified:(Lorg/apache/hadoop/fs/Path;)Lorg/apache/hadoop/fs/Path;
     103: astore        5
     105: aload         5
     107: invokevirtual #166                // Method org/apache/hadoop/fs/Path.toUri:()Ljava/net/URI;
     110: aload_0
     111: invokestatic  #205                // Method org/apache/hadoop/fs/FileContext.getFileContext:(Ljava/net/URI;Lorg/apache/hadoop/conf/Configuration;)Lorg/apache/hadoop/fs/FileContext;
     114: astore        6
     116: aload         6
     118: aload         5
     120: invokevirtual #206                // Method org/apache/hadoop/fs/FileContext.resolvePath:(Lorg/apache/hadoop/fs/Path;)Lorg/apache/hadoop/fs/Path;
     123: astore        5
     125: aload         5
     127: invokevirtual #166                // Method org/apache/hadoop/fs/Path.toUri:()Ljava/net/URI;
     130: astore_2
     131: new           #194                // class java/net/URI
     134: dup
     135: aload_2
     136: invokevirtual #202                // Method java/net/URI.getScheme:()Ljava/lang/String;
     139: aload_2
     140: invokevirtual #203                // Method java/net/URI.getAuthority:()Ljava/lang/String;
     143: aload_2
     144: invokevirtual #167                // Method java/net/URI.getPath:()Ljava/lang/String;
     147: aconst_null
     148: aload_3
     149: invokespecial #207                // Method java/net/URI."<init>":(Ljava/lang/String;Ljava/lang/String;Ljava/lang/String;Ljava/lang/String;Ljava/lang/String;)V
     152: astore_2
     153: goto          168
     156: astore        7
     158: new           #77                 // class java/lang/IllegalArgumentException
     161: dup
     162: aload         7
     164: invokespecial #208                // Method java/lang/IllegalArgumentException."<init>":(Ljava/lang/Throwable;)V
     167: athrow
     168: aload_2
     169: aload_0
     170: invokestatic  #209                // Method org/apache/hadoop/mapreduce/filecache/DistributedCache.addCacheArchive:(Ljava/net/URI;Lorg/apache/hadoop/conf/Configuration;)V
     173: return
    Exception table:
       from    to  target type
          16    25    28   Class java/net/URISyntaxException
         131   153   156   Class java/net/URISyntaxException

  static {};
    Code:
       0: ldc           #50                 // class org/apache/hadoop/mapreduce/JobSubmitter
       2: invokestatic  #210                // Method org/slf4j/LoggerFactory.getLogger:(Ljava/lang/Class;)Lorg/slf4j/Logger;
       5: putstatic     #36                 // Field LOG:Lorg/slf4j/Logger;
       8: return
}
