Compiled from "TaskCompletionEvent.java"
public class org.apache.hadoop.mapreduce.TaskCompletionEvent implements org.apache.hadoop.io.Writable {
  private int eventId;

  private java.lang.String taskTrackerHttp;

  private int taskRunTime;

  private org.apache.hadoop.mapreduce.TaskAttemptID taskId;

  org.apache.hadoop.mapreduce.TaskCompletionEvent$Status status;

  boolean isMap;

  private int idWithinJob;

  public static final org.apache.hadoop.mapreduce.TaskCompletionEvent[] EMPTY_ARRAY;

  public org.apache.hadoop.mapreduce.TaskCompletionEvent();
    Code:
       0: aload_0
       1: invokespecial #1                  // Method java/lang/Object."<init>":()V
       4: aload_0
       5: iconst_0
       6: putfield      #2                  // Field isMap:Z
       9: aload_0
      10: new           #3                  // class org/apache/hadoop/mapreduce/TaskAttemptID
      13: dup
      14: invokespecial #4                  // Method org/apache/hadoop/mapreduce/TaskAttemptID."<init>":()V
      17: putfield      #5                  // Field taskId:Lorg/apache/hadoop/mapreduce/TaskAttemptID;
      20: return

  public org.apache.hadoop.mapreduce.TaskCompletionEvent(int, org.apache.hadoop.mapreduce.TaskAttemptID, int, boolean, org.apache.hadoop.mapreduce.TaskCompletionEvent$Status, java.lang.String);
    Code:
       0: aload_0
       1: invokespecial #1                  // Method java/lang/Object."<init>":()V
       4: aload_0
       5: iconst_0
       6: putfield      #2                  // Field isMap:Z
       9: aload_0
      10: aload_2
      11: putfield      #5                  // Field taskId:Lorg/apache/hadoop/mapreduce/TaskAttemptID;
      14: aload_0
      15: iload_3
      16: putfield      #6                  // Field idWithinJob:I
      19: aload_0
      20: iload         4
      22: putfield      #2                  // Field isMap:Z
      25: aload_0
      26: iload_1
      27: putfield      #7                  // Field eventId:I
      30: aload_0
      31: aload         5
      33: putfield      #8                  // Field status:Lorg/apache/hadoop/mapreduce/TaskCompletionEvent$Status;
      36: aload_0
      37: aload         6
      39: putfield      #9                  // Field taskTrackerHttp:Ljava/lang/String;
      42: return

  public int getEventId();
    Code:
       0: aload_0
       1: getfield      #7                  // Field eventId:I
       4: ireturn

  public org.apache.hadoop.mapreduce.TaskAttemptID getTaskAttemptId();
    Code:
       0: aload_0
       1: getfield      #5                  // Field taskId:Lorg/apache/hadoop/mapreduce/TaskAttemptID;
       4: areturn

  public org.apache.hadoop.mapreduce.TaskCompletionEvent$Status getStatus();
    Code:
       0: aload_0
       1: getfield      #8                  // Field status:Lorg/apache/hadoop/mapreduce/TaskCompletionEvent$Status;
       4: areturn

  public java.lang.String getTaskTrackerHttp();
    Code:
       0: aload_0
       1: getfield      #9                  // Field taskTrackerHttp:Ljava/lang/String;
       4: areturn

  public int getTaskRunTime();
    Code:
       0: aload_0
       1: getfield      #10                 // Field taskRunTime:I
       4: ireturn

  protected void setTaskRunTime(int);
    Code:
       0: aload_0
       1: iload_1
       2: putfield      #10                 // Field taskRunTime:I
       5: return

  protected void setEventId(int);
    Code:
       0: aload_0
       1: iload_1
       2: putfield      #7                  // Field eventId:I
       5: return

  protected void setTaskAttemptId(org.apache.hadoop.mapreduce.TaskAttemptID);
    Code:
       0: aload_0
       1: aload_1
       2: putfield      #5                  // Field taskId:Lorg/apache/hadoop/mapreduce/TaskAttemptID;
       5: return

  protected void setTaskStatus(org.apache.hadoop.mapreduce.TaskCompletionEvent$Status);
    Code:
       0: aload_0
       1: aload_1
       2: putfield      #8                  // Field status:Lorg/apache/hadoop/mapreduce/TaskCompletionEvent$Status;
       5: return

  protected void setTaskTrackerHttp(java.lang.String);
    Code:
       0: aload_0
       1: aload_1
       2: putfield      #9                  // Field taskTrackerHttp:Ljava/lang/String;
       5: return

  public java.lang.String toString();
    Code:
       0: new           #11                 // class java/lang/StringBuffer
       3: dup
       4: invokespecial #12                 // Method java/lang/StringBuffer."<init>":()V
       7: astore_1
       8: aload_1
       9: ldc           #13                 // String Task Id :
      11: invokevirtual #14                 // Method java/lang/StringBuffer.append:(Ljava/lang/String;)Ljava/lang/StringBuffer;
      14: pop
      15: aload_1
      16: aload_0
      17: getfield      #5                  // Field taskId:Lorg/apache/hadoop/mapreduce/TaskAttemptID;
      20: invokevirtual #15                 // Method java/lang/StringBuffer.append:(Ljava/lang/Object;)Ljava/lang/StringBuffer;
      23: pop
      24: aload_1
      25: ldc           #16                 // String , Status :
      27: invokevirtual #14                 // Method java/lang/StringBuffer.append:(Ljava/lang/String;)Ljava/lang/StringBuffer;
      30: pop
      31: aload_1
      32: aload_0
      33: getfield      #8                  // Field status:Lorg/apache/hadoop/mapreduce/TaskCompletionEvent$Status;
      36: invokevirtual #17                 // Method org/apache/hadoop/mapreduce/TaskCompletionEvent$Status.name:()Ljava/lang/String;
      39: invokevirtual #14                 // Method java/lang/StringBuffer.append:(Ljava/lang/String;)Ljava/lang/StringBuffer;
      42: pop
      43: aload_1
      44: invokevirtual #18                 // Method java/lang/StringBuffer.toString:()Ljava/lang/String;
      47: areturn

  public boolean equals(java.lang.Object);
    Code:
       0: aload_1
       1: ifnonnull     6
       4: iconst_0
       5: ireturn
       6: aload_1
       7: invokevirtual #19                 // Method java/lang/Object.getClass:()Ljava/lang/Class;
      10: aload_0
      11: invokevirtual #19                 // Method java/lang/Object.getClass:()Ljava/lang/Class;
      14: invokevirtual #20                 // Method java/lang/Object.equals:(Ljava/lang/Object;)Z
      17: ifeq          117
      20: aload_1
      21: checkcast     #21                 // class org/apache/hadoop/mapreduce/TaskCompletionEvent
      24: astore_2
      25: aload_0
      26: getfield      #2                  // Field isMap:Z
      29: aload_2
      30: invokevirtual #22                 // Method isMapTask:()Z
      33: if_icmpne     115
      36: aload_0
      37: getfield      #7                  // Field eventId:I
      40: aload_2
      41: invokevirtual #23                 // Method getEventId:()I
      44: if_icmpne     115
      47: aload_0
      48: getfield      #6                  // Field idWithinJob:I
      51: aload_2
      52: invokevirtual #24                 // Method idWithinJob:()I
      55: if_icmpne     115
      58: aload_0
      59: getfield      #8                  // Field status:Lorg/apache/hadoop/mapreduce/TaskCompletionEvent$Status;
      62: aload_2
      63: invokevirtual #25                 // Method getStatus:()Lorg/apache/hadoop/mapreduce/TaskCompletionEvent$Status;
      66: invokevirtual #26                 // Method org/apache/hadoop/mapreduce/TaskCompletionEvent$Status.equals:(Ljava/lang/Object;)Z
      69: ifeq          115
      72: aload_0
      73: getfield      #5                  // Field taskId:Lorg/apache/hadoop/mapreduce/TaskAttemptID;
      76: aload_2
      77: invokevirtual #27                 // Method getTaskAttemptId:()Lorg/apache/hadoop/mapreduce/TaskAttemptID;
      80: invokevirtual #28                 // Method org/apache/hadoop/mapreduce/TaskAttemptID.equals:(Ljava/lang/Object;)Z
      83: ifeq          115
      86: aload_0
      87: getfield      #10                 // Field taskRunTime:I
      90: aload_2
      91: invokevirtual #29                 // Method getTaskRunTime:()I
      94: if_icmpne     115
      97: aload_0
      98: getfield      #9                  // Field taskTrackerHttp:Ljava/lang/String;
     101: aload_2
     102: invokevirtual #30                 // Method getTaskTrackerHttp:()Ljava/lang/String;
     105: invokevirtual #31                 // Method java/lang/String.equals:(Ljava/lang/Object;)Z
     108: ifeq          115
     111: iconst_1
     112: goto          116
     115: iconst_0
     116: ireturn
     117: iconst_0
     118: ireturn

  public int hashCode();
    Code:
       0: aload_0
       1: invokevirtual #32                 // Method toString:()Ljava/lang/String;
       4: invokevirtual #33                 // Method java/lang/String.hashCode:()I
       7: ireturn

  public boolean isMapTask();
    Code:
       0: aload_0
       1: getfield      #2                  // Field isMap:Z
       4: ireturn

  public int idWithinJob();
    Code:
       0: aload_0
       1: getfield      #6                  // Field idWithinJob:I
       4: ireturn

  public void write(java.io.DataOutput) throws java.io.IOException;
    Code:
       0: aload_0
       1: getfield      #5                  // Field taskId:Lorg/apache/hadoop/mapreduce/TaskAttemptID;
       4: aload_1
       5: invokevirtual #34                 // Method org/apache/hadoop/mapreduce/TaskAttemptID.write:(Ljava/io/DataOutput;)V
       8: aload_1
       9: aload_0
      10: getfield      #6                  // Field idWithinJob:I
      13: invokestatic  #35                 // Method org/apache/hadoop/io/WritableUtils.writeVInt:(Ljava/io/DataOutput;I)V
      16: aload_1
      17: aload_0
      18: getfield      #2                  // Field isMap:Z
      21: invokeinterface #36,  2           // InterfaceMethod java/io/DataOutput.writeBoolean:(Z)V
      26: aload_1
      27: aload_0
      28: getfield      #8                  // Field status:Lorg/apache/hadoop/mapreduce/TaskCompletionEvent$Status;
      31: invokestatic  #37                 // Method org/apache/hadoop/io/WritableUtils.writeEnum:(Ljava/io/DataOutput;Ljava/lang/Enum;)V
      34: aload_1
      35: aload_0
      36: getfield      #9                  // Field taskTrackerHttp:Ljava/lang/String;
      39: invokestatic  #38                 // Method org/apache/hadoop/io/WritableUtils.writeString:(Ljava/io/DataOutput;Ljava/lang/String;)V
      42: aload_1
      43: aload_0
      44: getfield      #10                 // Field taskRunTime:I
      47: invokestatic  #35                 // Method org/apache/hadoop/io/WritableUtils.writeVInt:(Ljava/io/DataOutput;I)V
      50: aload_1
      51: aload_0
      52: getfield      #7                  // Field eventId:I
      55: invokestatic  #35                 // Method org/apache/hadoop/io/WritableUtils.writeVInt:(Ljava/io/DataOutput;I)V
      58: return

  public void readFields(java.io.DataInput) throws java.io.IOException;
    Code:
       0: aload_0
       1: getfield      #5                  // Field taskId:Lorg/apache/hadoop/mapreduce/TaskAttemptID;
       4: aload_1
       5: invokevirtual #39                 // Method org/apache/hadoop/mapreduce/TaskAttemptID.readFields:(Ljava/io/DataInput;)V
       8: aload_0
       9: aload_1
      10: invokestatic  #40                 // Method org/apache/hadoop/io/WritableUtils.readVInt:(Ljava/io/DataInput;)I
      13: putfield      #6                  // Field idWithinJob:I
      16: aload_0
      17: aload_1
      18: invokeinterface #41,  1           // InterfaceMethod java/io/DataInput.readBoolean:()Z
      23: putfield      #2                  // Field isMap:Z
      26: aload_0
      27: aload_1
      28: ldc           #42                 // class org/apache/hadoop/mapreduce/TaskCompletionEvent$Status
      30: invokestatic  #43                 // Method org/apache/hadoop/io/WritableUtils.readEnum:(Ljava/io/DataInput;Ljava/lang/Class;)Ljava/lang/Enum;
      33: checkcast     #42                 // class org/apache/hadoop/mapreduce/TaskCompletionEvent$Status
      36: putfield      #8                  // Field status:Lorg/apache/hadoop/mapreduce/TaskCompletionEvent$Status;
      39: aload_0
      40: aload_1
      41: invokestatic  #44                 // Method org/apache/hadoop/io/WritableUtils.readString:(Ljava/io/DataInput;)Ljava/lang/String;
      44: putfield      #9                  // Field taskTrackerHttp:Ljava/lang/String;
      47: aload_0
      48: aload_1
      49: invokestatic  #40                 // Method org/apache/hadoop/io/WritableUtils.readVInt:(Ljava/io/DataInput;)I
      52: putfield      #10                 // Field taskRunTime:I
      55: aload_0
      56: aload_1
      57: invokestatic  #40                 // Method org/apache/hadoop/io/WritableUtils.readVInt:(Ljava/io/DataInput;)I
      60: putfield      #7                  // Field eventId:I
      63: return

  static {};
    Code:
       0: iconst_0
       1: anewarray     #21                 // class org/apache/hadoop/mapreduce/TaskCompletionEvent
       4: putstatic     #45                 // Field EMPTY_ARRAY:[Lorg/apache/hadoop/mapreduce/TaskCompletionEvent;
       7: return
}
