Compiled from "ProxyWriter.java"
public class org.sonar.api.internal.apachecommons.io.output.ProxyWriter extends java.io.FilterWriter {
  public org.sonar.api.internal.apachecommons.io.output.ProxyWriter(java.io.Writer);
    Code:
       0: aload_0
       1: aload_1
       2: invokespecial #9                  // Method java/io/FilterWriter."<init>":(Ljava/io/Writer;)V
       5: return

  public java.io.Writer append(char) throws java.io.IOException;
    Code:
       0: aload_0
       1: iconst_1
       2: invokevirtual #21                 // Method beforeWrite:(I)V
       5: aload_0
       6: getfield      #24                 // Field out:Ljava/io/Writer;
       9: iload_1
      10: invokevirtual #28                 // Method java/io/Writer.append:(C)Ljava/io/Writer;
      13: pop
      14: aload_0
      15: iconst_1
      16: invokevirtual #31                 // Method afterWrite:(I)V
      19: goto          28
      22: astore_2
      23: aload_0
      24: aload_2
      25: invokevirtual #35                 // Method handleIOException:(Ljava/io/IOException;)V
      28: aload_0
      29: areturn
    Exception table:
       from    to  target type
           0    19    22   Class java/io/IOException

  public java.io.Writer append(java.lang.CharSequence, int, int) throws java.io.IOException;
    Code:
       0: aload_0
       1: iload_3
       2: iload_2
       3: isub
       4: invokevirtual #21                 // Method beforeWrite:(I)V
       7: aload_0
       8: getfield      #24                 // Field out:Ljava/io/Writer;
      11: aload_1
      12: iload_2
      13: iload_3
      14: invokevirtual #42                 // Method java/io/Writer.append:(Ljava/lang/CharSequence;II)Ljava/io/Writer;
      17: pop
      18: aload_0
      19: iload_3
      20: iload_2
      21: isub
      22: invokevirtual #31                 // Method afterWrite:(I)V
      25: goto          36
      28: astore        4
      30: aload_0
      31: aload         4
      33: invokevirtual #35                 // Method handleIOException:(Ljava/io/IOException;)V
      36: aload_0
      37: areturn
    Exception table:
       from    to  target type
           0    25    28   Class java/io/IOException

  public java.io.Writer append(java.lang.CharSequence) throws java.io.IOException;
    Code:
       0: iconst_0
       1: istore_2
       2: aload_1
       3: ifnull        13
       6: aload_1
       7: invokeinterface #54,  1           // InterfaceMethod java/lang/CharSequence.length:()I
      12: istore_2
      13: aload_0
      14: iload_2
      15: invokevirtual #21                 // Method beforeWrite:(I)V
      18: aload_0
      19: getfield      #24                 // Field out:Ljava/io/Writer;
      22: aload_1
      23: invokevirtual #56                 // Method java/io/Writer.append:(Ljava/lang/CharSequence;)Ljava/io/Writer;
      26: pop
      27: aload_0
      28: iload_2
      29: invokevirtual #31                 // Method afterWrite:(I)V
      32: goto          41
      35: astore_2
      36: aload_0
      37: aload_2
      38: invokevirtual #35                 // Method handleIOException:(Ljava/io/IOException;)V
      41: aload_0
      42: areturn
    Exception table:
       from    to  target type
           0    32    35   Class java/io/IOException

  public void write(int) throws java.io.IOException;
    Code:
       0: aload_0
       1: iconst_1
       2: invokevirtual #21                 // Method beforeWrite:(I)V
       5: aload_0
       6: getfield      #24                 // Field out:Ljava/io/Writer;
       9: iload_1
      10: invokevirtual #60                 // Method java/io/Writer.write:(I)V
      13: aload_0
      14: iconst_1
      15: invokevirtual #31                 // Method afterWrite:(I)V
      18: goto          27
      21: astore_2
      22: aload_0
      23: aload_2
      24: invokevirtual #35                 // Method handleIOException:(Ljava/io/IOException;)V
      27: return
    Exception table:
       from    to  target type
           0    18    21   Class java/io/IOException

  public void write(char[]) throws java.io.IOException;
    Code:
       0: iconst_0
       1: istore_2
       2: aload_1
       3: ifnull        9
       6: aload_1
       7: arraylength
       8: istore_2
       9: aload_0
      10: iload_2
      11: invokevirtual #21                 // Method beforeWrite:(I)V
      14: aload_0
      15: getfield      #24                 // Field out:Ljava/io/Writer;
      18: aload_1
      19: invokevirtual #64                 // Method java/io/Writer.write:([C)V
      22: aload_0
      23: iload_2
      24: invokevirtual #31                 // Method afterWrite:(I)V
      27: goto          36
      30: astore_2
      31: aload_0
      32: aload_2
      33: invokevirtual #35                 // Method handleIOException:(Ljava/io/IOException;)V
      36: return
    Exception table:
       from    to  target type
           0    27    30   Class java/io/IOException

  public void write(char[], int, int) throws java.io.IOException;
    Code:
       0: aload_0
       1: iload_3
       2: invokevirtual #21                 // Method beforeWrite:(I)V
       5: aload_0
       6: getfield      #24                 // Field out:Ljava/io/Writer;
       9: aload_1
      10: iload_2
      11: iload_3
      12: invokevirtual #70                 // Method java/io/Writer.write:([CII)V
      15: aload_0
      16: iload_3
      17: invokevirtual #31                 // Method afterWrite:(I)V
      20: goto          31
      23: astore        4
      25: aload_0
      26: aload         4
      28: invokevirtual #35                 // Method handleIOException:(Ljava/io/IOException;)V
      31: return
    Exception table:
       from    to  target type
           0    20    23   Class java/io/IOException

  public void write(java.lang.String) throws java.io.IOException;
    Code:
       0: iconst_0
       1: istore_2
       2: aload_1
       3: ifnull        11
       6: aload_1
       7: invokevirtual #75                 // Method java/lang/String.length:()I
      10: istore_2
      11: aload_0
      12: iload_2
      13: invokevirtual #21                 // Method beforeWrite:(I)V
      16: aload_0
      17: getfield      #24                 // Field out:Ljava/io/Writer;
      20: aload_1
      21: invokevirtual #77                 // Method java/io/Writer.write:(Ljava/lang/String;)V
      24: aload_0
      25: iload_2
      26: invokevirtual #31                 // Method afterWrite:(I)V
      29: goto          38
      32: astore_2
      33: aload_0
      34: aload_2
      35: invokevirtual #35                 // Method handleIOException:(Ljava/io/IOException;)V
      38: return
    Exception table:
       from    to  target type
           0    29    32   Class java/io/IOException

  public void write(java.lang.String, int, int) throws java.io.IOException;
    Code:
       0: aload_0
       1: iload_3
       2: invokevirtual #21                 // Method beforeWrite:(I)V
       5: aload_0
       6: getfield      #24                 // Field out:Ljava/io/Writer;
       9: aload_1
      10: iload_2
      11: iload_3
      12: invokevirtual #82                 // Method java/io/Writer.write:(Ljava/lang/String;II)V
      15: aload_0
      16: iload_3
      17: invokevirtual #31                 // Method afterWrite:(I)V
      20: goto          31
      23: astore        4
      25: aload_0
      26: aload         4
      28: invokevirtual #35                 // Method handleIOException:(Ljava/io/IOException;)V
      31: return
    Exception table:
       from    to  target type
           0    20    23   Class java/io/IOException

  public void flush() throws java.io.IOException;
    Code:
       0: aload_0
       1: getfield      #24                 // Field out:Ljava/io/Writer;
       4: invokevirtual #86                 // Method java/io/Writer.flush:()V
       7: goto          16
      10: astore_1
      11: aload_0
      12: aload_1
      13: invokevirtual #35                 // Method handleIOException:(Ljava/io/IOException;)V
      16: return
    Exception table:
       from    to  target type
           0     7    10   Class java/io/IOException

  public void close() throws java.io.IOException;
    Code:
       0: aload_0
       1: getfield      #24                 // Field out:Ljava/io/Writer;
       4: invokevirtual #89                 // Method java/io/Writer.close:()V
       7: goto          16
      10: astore_1
      11: aload_0
      12: aload_1
      13: invokevirtual #35                 // Method handleIOException:(Ljava/io/IOException;)V
      16: return
    Exception table:
       from    to  target type
           0     7    10   Class java/io/IOException

  protected void beforeWrite(int) throws java.io.IOException;
    Code:
       0: return

  protected void afterWrite(int) throws java.io.IOException;
    Code:
       0: return

  protected void handleIOException(java.io.IOException) throws java.io.IOException;
    Code:
       0: aload_1
       1: athrow

  public java.lang.Appendable append(char) throws java.io.IOException;
    Code:
       0: aload_0
       1: iload_1
       2: invokevirtual #92                 // Method append:(C)Ljava/io/Writer;
       5: areturn

  public java.lang.Appendable append(java.lang.CharSequence, int, int) throws java.io.IOException;
    Code:
       0: aload_0
       1: aload_1
       2: iload_2
       3: iload_3
       4: invokevirtual #95                 // Method append:(Ljava/lang/CharSequence;II)Ljava/io/Writer;
       7: areturn

  public java.lang.Appendable append(java.lang.CharSequence) throws java.io.IOException;
    Code:
       0: aload_0
       1: aload_1
       2: invokevirtual #99                 // Method append:(Ljava/lang/CharSequence;)Ljava/io/Writer;
       5: areturn
}
