Compiled from "XmlStreamWriter.java"
public class org.sonar.api.internal.apachecommons.io.output.XmlStreamWriter extends java.io.Writer {
  private static final int BUFFER_SIZE;

  private final java.io.OutputStream out;

  private final java.lang.String defaultEncoding;

  private java.io.StringWriter xmlPrologWriter;

  private java.io.Writer writer;

  private java.lang.String encoding;

  static final java.util.regex.Pattern ENCODING_PATTERN;

  public org.sonar.api.internal.apachecommons.io.output.XmlStreamWriter(java.io.OutputStream);
    Code:
       0: aload_0
       1: aload_1
       2: aconst_null
       3: invokespecial #24                 // Method "<init>":(Ljava/io/OutputStream;Ljava/lang/String;)V
       6: return

  public org.sonar.api.internal.apachecommons.io.output.XmlStreamWriter(java.io.OutputStream, java.lang.String);
    Code:
       0: aload_0
       1: invokespecial #29                 // Method java/io/Writer."<init>":()V
       4: aload_0
       5: new           #31                 // class java/io/StringWriter
       8: dup
       9: sipush        4096
      12: invokespecial #34                 // Method java/io/StringWriter."<init>":(I)V
      15: putfield      #36                 // Field xmlPrologWriter:Ljava/io/StringWriter;
      18: aload_0
      19: aload_1
      20: putfield      #38                 // Field out:Ljava/io/OutputStream;
      23: aload_0
      24: aload_2
      25: ifnull        32
      28: aload_2
      29: goto          34
      32: ldc           #44                 // String UTF-8
      34: putfield      #46                 // Field defaultEncoding:Ljava/lang/String;
      37: return

  public org.sonar.api.internal.apachecommons.io.output.XmlStreamWriter(java.io.File) throws java.io.FileNotFoundException;
    Code:
       0: aload_0
       1: aload_1
       2: aconst_null
       3: invokespecial #52                 // Method "<init>":(Ljava/io/File;Ljava/lang/String;)V
       6: return

  public org.sonar.api.internal.apachecommons.io.output.XmlStreamWriter(java.io.File, java.lang.String) throws java.io.FileNotFoundException;
    Code:
       0: aload_0
       1: new           #56                 // class java/io/FileOutputStream
       4: dup
       5: aload_1
       6: invokespecial #58                 // Method java/io/FileOutputStream."<init>":(Ljava/io/File;)V
       9: aload_2
      10: invokespecial #24                 // Method "<init>":(Ljava/io/OutputStream;Ljava/lang/String;)V
      13: return

  public java.lang.String getEncoding();
    Code:
       0: aload_0
       1: getfield      #62                 // Field encoding:Ljava/lang/String;
       4: areturn

  public java.lang.String getDefaultEncoding();
    Code:
       0: aload_0
       1: getfield      #46                 // Field defaultEncoding:Ljava/lang/String;
       4: areturn

  public void close() throws java.io.IOException;
    Code:
       0: aload_0
       1: getfield      #68                 // Field writer:Ljava/io/Writer;
       4: ifnonnull     48
       7: aload_0
       8: aload_0
       9: getfield      #46                 // Field defaultEncoding:Ljava/lang/String;
      12: putfield      #62                 // Field encoding:Ljava/lang/String;
      15: aload_0
      16: new           #70                 // class java/io/OutputStreamWriter
      19: dup
      20: aload_0
      21: getfield      #38                 // Field out:Ljava/io/OutputStream;
      24: aload_0
      25: getfield      #62                 // Field encoding:Ljava/lang/String;
      28: invokespecial #71                 // Method java/io/OutputStreamWriter."<init>":(Ljava/io/OutputStream;Ljava/lang/String;)V
      31: putfield      #68                 // Field writer:Ljava/io/Writer;
      34: aload_0
      35: getfield      #68                 // Field writer:Ljava/io/Writer;
      38: aload_0
      39: getfield      #36                 // Field xmlPrologWriter:Ljava/io/StringWriter;
      42: invokevirtual #74                 // Method java/io/StringWriter.toString:()Ljava/lang/String;
      45: invokevirtual #78                 // Method java/io/Writer.write:(Ljava/lang/String;)V
      48: aload_0
      49: getfield      #68                 // Field writer:Ljava/io/Writer;
      52: invokevirtual #80                 // Method java/io/Writer.close:()V
      55: return

  public void flush() throws java.io.IOException;
    Code:
       0: aload_0
       1: getfield      #68                 // Field writer:Ljava/io/Writer;
       4: ifnull        14
       7: aload_0
       8: getfield      #68                 // Field writer:Ljava/io/Writer;
      11: invokevirtual #83                 // Method java/io/Writer.flush:()V
      14: return

  private void detectEncoding(char[], int, int) throws java.io.IOException;
    Code:
       0: iload_3
       1: istore        4
       3: aload_0
       4: getfield      #36                 // Field xmlPrologWriter:Ljava/io/StringWriter;
       7: invokevirtual #89                 // Method java/io/StringWriter.getBuffer:()Ljava/lang/StringBuffer;
      10: astore        5
      12: aload         5
      14: invokevirtual #95                 // Method java/lang/StringBuffer.length:()I
      17: iload_3
      18: iadd
      19: sipush        4096
      22: if_icmple     36
      25: sipush        4096
      28: aload         5
      30: invokevirtual #95                 // Method java/lang/StringBuffer.length:()I
      33: isub
      34: istore        4
      36: aload_0
      37: getfield      #36                 // Field xmlPrologWriter:Ljava/io/StringWriter;
      40: aload_1
      41: iload_2
      42: iload         4
      44: invokevirtual #97                 // Method java/io/StringWriter.write:([CII)V
      47: aload         5
      49: invokevirtual #95                 // Method java/lang/StringBuffer.length:()I
      52: iconst_5
      53: if_icmplt     252
      56: aload         5
      58: iconst_0
      59: iconst_5
      60: invokevirtual #101                // Method java/lang/StringBuffer.substring:(II)Ljava/lang/String;
      63: ldc           #103                // String <?xml
      65: invokevirtual #107                // Method java/lang/String.equals:(Ljava/lang/Object;)Z
      68: ifeq          179
      71: aload         5
      73: ldc           #109                // String ?>
      75: invokevirtual #113                // Method java/lang/StringBuffer.indexOf:(Ljava/lang/String;)I
      78: istore        6
      80: iload         6
      82: ifle          157
      85: getstatic     #115                // Field ENCODING_PATTERN:Ljava/util/regex/Pattern;
      88: aload         5
      90: iconst_0
      91: iload         6
      93: invokevirtual #101                // Method java/lang/StringBuffer.substring:(II)Ljava/lang/String;
      96: invokevirtual #121                // Method java/util/regex/Pattern.matcher:(Ljava/lang/CharSequence;)Ljava/util/regex/Matcher;
      99: astore        7
     101: aload         7
     103: invokevirtual #127                // Method java/util/regex/Matcher.find:()Z
     106: ifeq          146
     109: aload_0
     110: aload         7
     112: iconst_1
     113: invokevirtual #131                // Method java/util/regex/Matcher.group:(I)Ljava/lang/String;
     116: invokevirtual #134                // Method java/lang/String.toUpperCase:()Ljava/lang/String;
     119: putfield      #62                 // Field encoding:Ljava/lang/String;
     122: aload_0
     123: aload_0
     124: getfield      #62                 // Field encoding:Ljava/lang/String;
     127: iconst_1
     128: aload_0
     129: getfield      #62                 // Field encoding:Ljava/lang/String;
     132: invokevirtual #135                // Method java/lang/String.length:()I
     135: iconst_1
     136: isub
     137: invokevirtual #136                // Method java/lang/String.substring:(II)Ljava/lang/String;
     140: putfield      #62                 // Field encoding:Ljava/lang/String;
     143: goto          154
     146: aload_0
     147: aload_0
     148: getfield      #46                 // Field defaultEncoding:Ljava/lang/String;
     151: putfield      #62                 // Field encoding:Ljava/lang/String;
     154: goto          176
     157: aload         5
     159: invokevirtual #95                 // Method java/lang/StringBuffer.length:()I
     162: sipush        4096
     165: if_icmplt     176
     168: aload_0
     169: aload_0
     170: getfield      #46                 // Field defaultEncoding:Ljava/lang/String;
     173: putfield      #62                 // Field encoding:Ljava/lang/String;
     176: goto          187
     179: aload_0
     180: aload_0
     181: getfield      #46                 // Field defaultEncoding:Ljava/lang/String;
     184: putfield      #62                 // Field encoding:Ljava/lang/String;
     187: aload_0
     188: getfield      #62                 // Field encoding:Ljava/lang/String;
     191: ifnull        252
     194: aload_0
     195: aconst_null
     196: putfield      #36                 // Field xmlPrologWriter:Ljava/io/StringWriter;
     199: aload_0
     200: new           #70                 // class java/io/OutputStreamWriter
     203: dup
     204: aload_0
     205: getfield      #38                 // Field out:Ljava/io/OutputStream;
     208: aload_0
     209: getfield      #62                 // Field encoding:Ljava/lang/String;
     212: invokespecial #71                 // Method java/io/OutputStreamWriter."<init>":(Ljava/io/OutputStream;Ljava/lang/String;)V
     215: putfield      #68                 // Field writer:Ljava/io/Writer;
     218: aload_0
     219: getfield      #68                 // Field writer:Ljava/io/Writer;
     222: aload         5
     224: invokevirtual #137                // Method java/lang/StringBuffer.toString:()Ljava/lang/String;
     227: invokevirtual #78                 // Method java/io/Writer.write:(Ljava/lang/String;)V
     230: iload_3
     231: iload         4
     233: if_icmple     252
     236: aload_0
     237: getfield      #68                 // Field writer:Ljava/io/Writer;
     240: aload_1
     241: iload_2
     242: iload         4
     244: iadd
     245: iload_3
     246: iload         4
     248: isub
     249: invokevirtual #138                // Method java/io/Writer.write:([CII)V
     252: return

  public void write(char[], int, int) throws java.io.IOException;
    Code:
       0: aload_0
       1: getfield      #36                 // Field xmlPrologWriter:Ljava/io/StringWriter;
       4: ifnull        17
       7: aload_0
       8: aload_1
       9: iload_2
      10: iload_3
      11: invokespecial #150                // Method detectEncoding:([CII)V
      14: goto          27
      17: aload_0
      18: getfield      #68                 // Field writer:Ljava/io/Writer;
      21: aload_1
      22: iload_2
      23: iload_3
      24: invokevirtual #138                // Method java/io/Writer.write:([CII)V
      27: return

  static {};
    Code:
       0: getstatic     #154                // Field org/sonar/api/internal/apachecommons/io/input/XmlStreamReader.ENCODING_PATTERN:Ljava/util/regex/Pattern;
       3: putstatic     #115                // Field ENCODING_PATTERN:Ljava/util/regex/Pattern;
       6: return
}
