Compiled from "WebSocketClient.java"
class org.wso2.transport.http.netty.contractimpl.sender.websocket.WebSocketClient$WebSocketClientSSLHandshakeCompletionHandler extends io.netty.channel.ChannelInboundHandlerAdapter {
  private final org.wso2.transport.http.netty.contractimpl.websocket.DefaultClientHandshakeFuture clientHandshakeFuture;

  final org.wso2.transport.http.netty.contractimpl.sender.websocket.WebSocketClient this$0;

  private org.wso2.transport.http.netty.contractimpl.sender.websocket.WebSocketClient$WebSocketClientSSLHandshakeCompletionHandler(org.wso2.transport.http.netty.contractimpl.sender.websocket.WebSocketClient, org.wso2.transport.http.netty.contractimpl.websocket.DefaultClientHandshakeFuture);
    Code:
       0: aload_0
       1: aload_1
       2: putfield      #2                  // Field this$0:Lorg/wso2/transport/http/netty/contractimpl/sender/websocket/WebSocketClient;
       5: aload_0
       6: invokespecial #3                  // Method io/netty/channel/ChannelInboundHandlerAdapter."<init>":()V
       9: aload_0
      10: aload_2
      11: putfield      #4                  // Field clientHandshakeFuture:Lorg/wso2/transport/http/netty/contractimpl/websocket/DefaultClientHandshakeFuture;
      14: return

  public void userEventTriggered(io.netty.channel.ChannelHandlerContext, java.lang.Object);
    Code:
       0: aload_2
       1: instanceof    #5                  // class io/netty/handler/ssl/SslHandshakeCompletionEvent
       4: ifeq          80
       7: aload_2
       8: checkcast     #5                  // class io/netty/handler/ssl/SslHandshakeCompletionEvent
      11: astore_3
      12: aload_3
      13: invokevirtual #6                  // Method io/netty/handler/ssl/SslHandshakeCompletionEvent.isSuccess:()Z
      16: ifeq          68
      19: aload_3
      20: invokevirtual #7                  // Method io/netty/handler/ssl/SslHandshakeCompletionEvent.cause:()Ljava/lang/Throwable;
      23: ifnonnull     68
      26: aload_0
      27: getfield      #2                  // Field this$0:Lorg/wso2/transport/http/netty/contractimpl/sender/websocket/WebSocketClient;
      30: aload_1
      31: invokeinterface #8,  1            // InterfaceMethod io/netty/channel/ChannelHandlerContext.channel:()Lio/netty/channel/Channel;
      36: invokeinterface #9,  1            // InterfaceMethod io/netty/channel/Channel.pipeline:()Lio/netty/channel/ChannelPipeline;
      41: invokestatic  #10                 // Method org/wso2/transport/http/netty/contractimpl/sender/websocket/WebSocketClient.access$100:(Lorg/wso2/transport/http/netty/contractimpl/sender/websocket/WebSocketClient;Lio/netty/channel/ChannelPipeline;)V
      44: aload_1
      45: invokeinterface #11,  1           // InterfaceMethod io/netty/channel/ChannelHandlerContext.pipeline:()Lio/netty/channel/ChannelPipeline;
      50: ldc           #13                 // String sslHandshakeCompletionHandler
      52: invokeinterface #14,  2           // InterfaceMethod io/netty/channel/ChannelPipeline.remove:(Ljava/lang/String;)Lio/netty/channel/ChannelHandler;
      57: pop
      58: aload_1
      59: invokeinterface #15,  1           // InterfaceMethod io/netty/channel/ChannelHandlerContext.fireChannelActive:()Lio/netty/channel/ChannelHandlerContext;
      64: pop
      65: goto          80
      68: aload_0
      69: getfield      #4                  // Field clientHandshakeFuture:Lorg/wso2/transport/http/netty/contractimpl/websocket/DefaultClientHandshakeFuture;
      72: aload_3
      73: invokevirtual #7                  // Method io/netty/handler/ssl/SslHandshakeCompletionEvent.cause:()Ljava/lang/Throwable;
      76: aconst_null
      77: invokevirtual #16                 // Method org/wso2/transport/http/netty/contractimpl/websocket/DefaultClientHandshakeFuture.notifyError:(Ljava/lang/Throwable;Lorg/wso2/transport/http/netty/message/HttpCarbonResponse;)V
      80: return

  org.wso2.transport.http.netty.contractimpl.sender.websocket.WebSocketClient$WebSocketClientSSLHandshakeCompletionHandler(org.wso2.transport.http.netty.contractimpl.sender.websocket.WebSocketClient, org.wso2.transport.http.netty.contractimpl.websocket.DefaultClientHandshakeFuture, org.wso2.transport.http.netty.contractimpl.sender.websocket.WebSocketClient$1);
    Code:
       0: aload_0
       1: aload_1
       2: aload_2
       3: invokespecial #1                  // Method "<init>":(Lorg/wso2/transport/http/netty/contractimpl/sender/websocket/WebSocketClient;Lorg/wso2/transport/http/netty/contractimpl/websocket/DefaultClientHandshakeFuture;)V
       6: return
}
