Compiled from "SpyAnnotationEngine.java"
public class org.mockito.internal.configuration.SpyAnnotationEngine implements org.mockito.configuration.AnnotationEngine {
  public org.mockito.internal.configuration.SpyAnnotationEngine();
    Code:
       0: aload_0
       1: invokespecial #1                  // Method java/lang/Object."<init>":()V
       4: return

  public void process(java.lang.Class<?>, java.lang.Object);
    Code:
       0: aload_1
       1: invokevirtual #2                  // Method java/lang/Class.getDeclaredFields:()[Ljava/lang/reflect/Field;
       4: astore_3
       5: aload_3
       6: astore        4
       8: aload         4
      10: arraylength
      11: istore        5
      13: iconst_0
      14: istore        6
      16: iload         6
      18: iload         5
      20: if_icmpge     243
      23: aload         4
      25: iload         6
      27: aaload
      28: astore        7
      30: aload         7
      32: ldc_w         #3                  // class org/mockito/Spy
      35: invokevirtual #4                  // Method java/lang/reflect/Field.isAnnotationPresent:(Ljava/lang/Class;)Z
      38: ifeq          237
      41: aload         7
      43: ldc_w         #5                  // class org/mockito/InjectMocks
      46: invokevirtual #4                  // Method java/lang/reflect/Field.isAnnotationPresent:(Ljava/lang/Class;)Z
      49: ifne          237
      52: aload_0
      53: ldc_w         #3                  // class org/mockito/Spy
      56: aload         7
      58: iconst_2
      59: anewarray     #6                  // class java/lang/Class
      62: dup
      63: iconst_0
      64: ldc_w         #7                  // class org/mockito/Mock
      67: aastore
      68: dup
      69: iconst_1
      70: ldc_w         #8                  // class org/mockito/Captor
      73: aastore
      74: invokespecial #9                  // Method assertNoIncompatibleAnnotations:(Ljava/lang/Class;Ljava/lang/reflect/Field;[Ljava/lang/Class;)V
      77: aload         7
      79: iconst_1
      80: invokevirtual #10                 // Method java/lang/reflect/Field.setAccessible:(Z)V
      83: aload         7
      85: aload_2
      86: invokevirtual #11                 // Method java/lang/reflect/Field.get:(Ljava/lang/Object;)Ljava/lang/Object;
      89: astore        8
      91: aload         8
      93: aload         7
      95: invokevirtual #12                 // Method java/lang/reflect/Field.getType:()Ljava/lang/Class;
      98: invokestatic  #13                 // Method assertNotInterface:(Ljava/lang/Object;Ljava/lang/Class;)V
     101: aload         8
     103: invokestatic  #14                 // Method org/mockito/internal/util/MockUtil.isMock:(Ljava/lang/Object;)Z
     106: ifeq          124
     109: iconst_1
     110: anewarray     #15                 // class java/lang/Object
     113: dup
     114: iconst_0
     115: aload         8
     117: aastore
     118: invokestatic  #16                 // Method org/mockito/Mockito.reset:([Ljava/lang/Object;)V
     121: goto          186
     124: aload         8
     126: ifnull        174
     129: aload         7
     131: aload_2
     132: aload         8
     134: invokevirtual #17                 // Method java/lang/Object.getClass:()Ljava/lang/Class;
     137: invokestatic  #18                 // Method org/mockito/Mockito.withSettings:()Lorg/mockito/MockSettings;
     140: aload         8
     142: invokeinterface #19,  2           // InterfaceMethod org/mockito/MockSettings.spiedInstance:(Ljava/lang/Object;)Lorg/mockito/MockSettings;
     147: getstatic     #20                 // Field org/mockito/Mockito.CALLS_REAL_METHODS:Lorg/mockito/stubbing/Answer;
     150: invokeinterface #21,  2           // InterfaceMethod org/mockito/MockSettings.defaultAnswer:(Lorg/mockito/stubbing/Answer;)Lorg/mockito/MockSettings;
     155: aload         7
     157: invokevirtual #22                 // Method java/lang/reflect/Field.getName:()Ljava/lang/String;
     160: invokeinterface #23,  2           // InterfaceMethod org/mockito/MockSettings.name:(Ljava/lang/String;)Lorg/mockito/MockSettings;
     165: invokestatic  #24                 // Method org/mockito/Mockito.mock:(Ljava/lang/Class;Lorg/mockito/MockSettings;)Ljava/lang/Object;
     168: invokevirtual #25                 // Method java/lang/reflect/Field.set:(Ljava/lang/Object;Ljava/lang/Object;)V
     171: goto          186
     174: aload         7
     176: aload_2
     177: aload_2
     178: aload         7
     180: invokestatic  #26                 // Method newSpyInstance:(Ljava/lang/Object;Ljava/lang/reflect/Field;)Ljava/lang/Object;
     183: invokevirtual #25                 // Method java/lang/reflect/Field.set:(Ljava/lang/Object;Ljava/lang/Object;)V
     186: goto          237
     189: astore        9
     191: new           #28                 // class org/mockito/exceptions/base/MockitoException
     194: dup
     195: new           #29                 // class java/lang/StringBuilder
     198: dup
     199: invokespecial #30                 // Method java/lang/StringBuilder."<init>":()V
     202: ldc           #31                 // String Unable to initialize @Spy annotated field \'
     204: invokevirtual #32                 // Method java/lang/StringBuilder.append:(Ljava/lang/String;)Ljava/lang/StringBuilder;
     207: aload         7
     209: invokevirtual #22                 // Method java/lang/reflect/Field.getName:()Ljava/lang/String;
     212: invokevirtual #32                 // Method java/lang/StringBuilder.append:(Ljava/lang/String;)Ljava/lang/StringBuilder;
     215: ldc           #33                 // String \'.\n
     217: invokevirtual #32                 // Method java/lang/StringBuilder.append:(Ljava/lang/String;)Ljava/lang/StringBuilder;
     220: aload         9
     222: invokevirtual #34                 // Method java/lang/Exception.getMessage:()Ljava/lang/String;
     225: invokevirtual #32                 // Method java/lang/StringBuilder.append:(Ljava/lang/String;)Ljava/lang/StringBuilder;
     228: invokevirtual #35                 // Method java/lang/StringBuilder.toString:()Ljava/lang/String;
     231: aload         9
     233: invokespecial #36                 // Method org/mockito/exceptions/base/MockitoException."<init>":(Ljava/lang/String;Ljava/lang/Throwable;)V
     236: athrow
     237: iinc          6, 1
     240: goto          16
     243: return
    Exception table:
       from    to  target type
          83   186   189   Class java/lang/Exception

  private static void assertNotInterface(java.lang.Object, java.lang.Class<?>);
    Code:
       0: aload_0
       1: ifnull        11
       4: aload_0
       5: invokevirtual #17                 // Method java/lang/Object.getClass:()Ljava/lang/Class;
       8: goto          12
      11: aload_1
      12: astore_1
      13: aload_1
      14: invokevirtual #37                 // Method java/lang/Class.isInterface:()Z
      17: ifeq          55
      20: new           #28                 // class org/mockito/exceptions/base/MockitoException
      23: dup
      24: new           #29                 // class java/lang/StringBuilder
      27: dup
      28: invokespecial #30                 // Method java/lang/StringBuilder."<init>":()V
      31: ldc           #38                 // String Type \'
      33: invokevirtual #32                 // Method java/lang/StringBuilder.append:(Ljava/lang/String;)Ljava/lang/StringBuilder;
      36: aload_1
      37: invokevirtual #39                 // Method java/lang/Class.getSimpleName:()Ljava/lang/String;
      40: invokevirtual #32                 // Method java/lang/StringBuilder.append:(Ljava/lang/String;)Ljava/lang/StringBuilder;
      43: ldc           #40                 // String \' is an interface and it cannot be spied on.
      45: invokevirtual #32                 // Method java/lang/StringBuilder.append:(Ljava/lang/String;)Ljava/lang/StringBuilder;
      48: invokevirtual #35                 // Method java/lang/StringBuilder.toString:()Ljava/lang/String;
      51: invokespecial #41                 // Method org/mockito/exceptions/base/MockitoException."<init>":(Ljava/lang/String;)V
      54: athrow
      55: return

  private static java.lang.Object newSpyInstance(java.lang.Object, java.lang.reflect.Field) throws java.lang.InstantiationException, java.lang.IllegalAccessException, java.lang.reflect.InvocationTargetException;
    Code:
       0: invokestatic  #18                 // Method org/mockito/Mockito.withSettings:()Lorg/mockito/MockSettings;
       3: getstatic     #20                 // Field org/mockito/Mockito.CALLS_REAL_METHODS:Lorg/mockito/stubbing/Answer;
       6: invokeinterface #21,  2           // InterfaceMethod org/mockito/MockSettings.defaultAnswer:(Lorg/mockito/stubbing/Answer;)Lorg/mockito/MockSettings;
      11: aload_1
      12: invokevirtual #22                 // Method java/lang/reflect/Field.getName:()Ljava/lang/String;
      15: invokeinterface #23,  2           // InterfaceMethod org/mockito/MockSettings.name:(Ljava/lang/String;)Lorg/mockito/MockSettings;
      20: astore_2
      21: aload_1
      22: invokevirtual #12                 // Method java/lang/reflect/Field.getType:()Ljava/lang/Class;
      25: astore_3
      26: aload_3
      27: invokevirtual #37                 // Method java/lang/Class.isInterface:()Z
      30: ifeq          44
      33: aload_3
      34: aload_2
      35: invokeinterface #42,  1           // InterfaceMethod org/mockito/MockSettings.useConstructor:()Lorg/mockito/MockSettings;
      40: invokestatic  #24                 // Method org/mockito/Mockito.mock:(Ljava/lang/Class;Lorg/mockito/MockSettings;)Ljava/lang/Object;
      43: areturn
      44: aload_3
      45: invokevirtual #43                 // Method java/lang/Class.getModifiers:()I
      48: invokestatic  #44                 // Method java/lang/reflect/Modifier.isStatic:(I)Z
      51: ifne          144
      54: aload_3
      55: invokevirtual #45                 // Method java/lang/Class.getEnclosingClass:()Ljava/lang/Class;
      58: astore        4
      60: aload         4
      62: ifnull        144
      65: aload         4
      67: aload_0
      68: invokevirtual #46                 // Method java/lang/Class.isInstance:(Ljava/lang/Object;)Z
      71: ifne          127
      74: new           #28                 // class org/mockito/exceptions/base/MockitoException
      77: dup
      78: new           #29                 // class java/lang/StringBuilder
      81: dup
      82: invokespecial #30                 // Method java/lang/StringBuilder."<init>":()V
      85: ldc           #47                 // String @Spy annotation can only initialize inner classes declared in the test. Inner class: \'
      87: invokevirtual #32                 // Method java/lang/StringBuilder.append:(Ljava/lang/String;)Ljava/lang/StringBuilder;
      90: aload_3
      91: invokevirtual #39                 // Method java/lang/Class.getSimpleName:()Ljava/lang/String;
      94: invokevirtual #32                 // Method java/lang/StringBuilder.append:(Ljava/lang/String;)Ljava/lang/StringBuilder;
      97: ldc           #48                 // String \',
      99: invokevirtual #32                 // Method java/lang/StringBuilder.append:(Ljava/lang/String;)Ljava/lang/StringBuilder;
     102: ldc           #49                 // String outer class: \'
     104: invokevirtual #32                 // Method java/lang/StringBuilder.append:(Ljava/lang/String;)Ljava/lang/StringBuilder;
     107: aload         4
     109: invokevirtual #39                 // Method java/lang/Class.getSimpleName:()Ljava/lang/String;
     112: invokevirtual #32                 // Method java/lang/StringBuilder.append:(Ljava/lang/String;)Ljava/lang/StringBuilder;
     115: ldc           #50                 // String \'.
     117: invokevirtual #32                 // Method java/lang/StringBuilder.append:(Ljava/lang/String;)Ljava/lang/StringBuilder;
     120: invokevirtual #35                 // Method java/lang/StringBuilder.toString:()Ljava/lang/String;
     123: invokespecial #41                 // Method org/mockito/exceptions/base/MockitoException."<init>":(Ljava/lang/String;)V
     126: athrow
     127: aload_3
     128: aload_2
     129: invokeinterface #42,  1           // InterfaceMethod org/mockito/MockSettings.useConstructor:()Lorg/mockito/MockSettings;
     134: aload_0
     135: invokeinterface #51,  2           // InterfaceMethod org/mockito/MockSettings.outerInstance:(Ljava/lang/Object;)Lorg/mockito/MockSettings;
     140: invokestatic  #24                 // Method org/mockito/Mockito.mock:(Ljava/lang/Class;Lorg/mockito/MockSettings;)Ljava/lang/Object;
     143: areturn
     144: aload_3
     145: iconst_0
     146: anewarray     #6                  // class java/lang/Class
     149: invokevirtual #52                 // Method java/lang/Class.getDeclaredConstructor:([Ljava/lang/Class;)Ljava/lang/reflect/Constructor;
     152: astore        4
     154: goto          194
     157: astore        5
     159: new           #28                 // class org/mockito/exceptions/base/MockitoException
     162: dup
     163: new           #29                 // class java/lang/StringBuilder
     166: dup
     167: invokespecial #30                 // Method java/lang/StringBuilder."<init>":()V
     170: ldc           #54                 // String Please ensure that the type \'
     172: invokevirtual #32                 // Method java/lang/StringBuilder.append:(Ljava/lang/String;)Ljava/lang/StringBuilder;
     175: aload_3
     176: invokevirtual #39                 // Method java/lang/Class.getSimpleName:()Ljava/lang/String;
     179: invokevirtual #32                 // Method java/lang/StringBuilder.append:(Ljava/lang/String;)Ljava/lang/StringBuilder;
     182: ldc           #55                 // String \' has 0-arg constructor.
     184: invokevirtual #32                 // Method java/lang/StringBuilder.append:(Ljava/lang/String;)Ljava/lang/StringBuilder;
     187: invokevirtual #35                 // Method java/lang/StringBuilder.toString:()Ljava/lang/String;
     190: invokespecial #41                 // Method org/mockito/exceptions/base/MockitoException."<init>":(Ljava/lang/String;)V
     193: athrow
     194: aload         4
     196: invokevirtual #56                 // Method java/lang/reflect/Constructor.getModifiers:()I
     199: invokestatic  #57                 // Method java/lang/reflect/Modifier.isPrivate:(I)Z
     202: ifeq          231
     205: aload         4
     207: iconst_1
     208: invokevirtual #58                 // Method java/lang/reflect/Constructor.setAccessible:(Z)V
     211: aload_3
     212: aload_2
     213: aload         4
     215: iconst_0
     216: anewarray     #15                 // class java/lang/Object
     219: invokevirtual #59                 // Method java/lang/reflect/Constructor.newInstance:([Ljava/lang/Object;)Ljava/lang/Object;
     222: invokeinterface #19,  2           // InterfaceMethod org/mockito/MockSettings.spiedInstance:(Ljava/lang/Object;)Lorg/mockito/MockSettings;
     227: invokestatic  #24                 // Method org/mockito/Mockito.mock:(Ljava/lang/Class;Lorg/mockito/MockSettings;)Ljava/lang/Object;
     230: areturn
     231: aload_3
     232: aload_2
     233: invokeinterface #42,  1           // InterfaceMethod org/mockito/MockSettings.useConstructor:()Lorg/mockito/MockSettings;
     238: invokestatic  #24                 // Method org/mockito/Mockito.mock:(Ljava/lang/Class;Lorg/mockito/MockSettings;)Ljava/lang/Object;
     241: areturn
    Exception table:
       from    to  target type
         144   154   157   Class java/lang/NoSuchMethodException

  private void assertNoIncompatibleAnnotations(java.lang.Class<? extends java.lang.annotation.Annotation>, java.lang.reflect.Field, java.lang.Class<? extends java.lang.annotation.Annotation>...);
    Code:
       0: aload_3
       1: astore        4
       3: aload         4
       5: arraylength
       6: istore        5
       8: iconst_0
       9: istore        6
      11: iload         6
      13: iload         5
      15: if_icmpge     55
      18: aload         4
      20: iload         6
      22: aaload
      23: astore        7
      25: aload_2
      26: aload         7
      28: invokevirtual #4                  // Method java/lang/reflect/Field.isAnnotationPresent:(Ljava/lang/Class;)Z
      31: ifeq          49
      34: aload_1
      35: invokevirtual #39                 // Method java/lang/Class.getSimpleName:()Ljava/lang/String;
      38: aload_1
      39: invokevirtual #17                 // Method java/lang/Object.getClass:()Ljava/lang/Class;
      42: invokevirtual #39                 // Method java/lang/Class.getSimpleName:()Ljava/lang/String;
      45: invokestatic  #60                 // Method org/mockito/internal/exceptions/Reporter.unsupportedCombinationOfAnnotations:(Ljava/lang/String;Ljava/lang/String;)Lorg/mockito/exceptions/base/MockitoException;
      48: athrow
      49: iinc          6, 1
      52: goto          11
      55: return
}
