Compiled from "EnvironmentLookup.java"
public class org.apache.commons.configuration.interpol.EnvironmentLookup extends org.apache.commons.lang.text.StrLookup {
  private final org.apache.commons.configuration.EnvironmentConfiguration environmentConfig;

  public org.apache.commons.configuration.interpol.EnvironmentLookup();
    Code:
       0: aload_0
       1: invokespecial #1                  // Method org/apache/commons/lang/text/StrLookup."<init>":()V
       4: aload_0
       5: new           #2                  // class org/apache/commons/configuration/EnvironmentConfiguration
       8: dup
       9: invokespecial #3                  // Method org/apache/commons/configuration/EnvironmentConfiguration."<init>":()V
      12: putfield      #4                  // Field environmentConfig:Lorg/apache/commons/configuration/EnvironmentConfiguration;
      15: return

  public java.lang.String lookup(java.lang.String);
    Code:
       0: aload_0
       1: getfield      #4                  // Field environmentConfig:Lorg/apache/commons/configuration/EnvironmentConfiguration;
       4: aload_1
       5: invokevirtual #5                  // Method org/apache/commons/configuration/EnvironmentConfiguration.getString:(Ljava/lang/String;)Ljava/lang/String;
       8: areturn
}
