Compiled from "WhatsAroundQueryFactory.java"
public class won.matcher.solr.query.factory.WhatsAroundQueryFactory extends won.matcher.solr.query.factory.BasicAtomQueryFactory {
  private static final java.lang.String ATOM_TYPE_DUMMY_FIELD;

  private static final java.lang.String ATOM_TYPE_DUMMY_FIELD_CONTENT;

  public won.matcher.solr.query.factory.WhatsAroundQueryFactory(org.apache.jena.query.Dataset);
    Code:
       0: aload_0
       1: aload_1
       2: invokespecial #1                  // Method won/matcher/solr/query/factory/BasicAtomQueryFactory."<init>":(Lorg/apache/jena/query/Dataset;)V
       5: aload_0
       6: getfield      #2                  // Field atomModelWrapper:Lwon/protocol/util/DefaultAtomModelWrapper;
       9: invokevirtual #3                  // Method won/protocol/util/DefaultAtomModelWrapper.getAtomContentNode:()Lorg/apache/jena/rdf/model/Resource;
      12: astore_2
      13: aload_0
      14: aload_2
      15: getstatic     #4                  // Field won/matcher/solr/utils/MatcherAtomContentPropertyType.SEEKS:Lwon/matcher/solr/utils/MatcherAtomContentPropertyType;
      18: invokevirtual #5                  // Method addLocationFilters:(Lorg/apache/jena/rdf/model/Resource;Lwon/matcher/solr/utils/MatcherAtomContentPropertyType;)V
      21: aload_0
      22: getfield      #2                  // Field atomModelWrapper:Lwon/protocol/util/DefaultAtomModelWrapper;
      25: invokevirtual #6                  // Method won/protocol/util/DefaultAtomModelWrapper.getSeeksNodes:()Ljava/util/Collection;
      28: invokeinterface #7,  1            // InterfaceMethod java/util/Collection.iterator:()Ljava/util/Iterator;
      33: astore_3
      34: aload_3
      35: invokeinterface #8,  1            // InterfaceMethod java/util/Iterator.hasNext:()Z
      40: ifeq          75
      43: aload_3
      44: invokeinterface #9,  1            // InterfaceMethod java/util/Iterator.next:()Ljava/lang/Object;
      49: checkcast     #10                 // class org/apache/jena/rdf/model/Resource
      52: astore        4
      54: aload_0
      55: aload         4
      57: getstatic     #11                 // Field won/matcher/solr/utils/MatcherAtomContentPropertyType.IS:Lwon/matcher/solr/utils/MatcherAtomContentPropertyType;
      60: invokevirtual #5                  // Method addLocationFilters:(Lorg/apache/jena/rdf/model/Resource;Lwon/matcher/solr/utils/MatcherAtomContentPropertyType;)V
      63: aload_0
      64: aload         4
      66: getstatic     #12                 // Field won/matcher/solr/utils/MatcherAtomContentPropertyType.SEEKS_SEEKS:Lwon/matcher/solr/utils/MatcherAtomContentPropertyType;
      69: invokevirtual #5                  // Method addLocationFilters:(Lorg/apache/jena/rdf/model/Resource;Lwon/matcher/solr/utils/MatcherAtomContentPropertyType;)V
      72: goto          34
      75: aload_0
      76: getfield      #2                  // Field atomModelWrapper:Lwon/protocol/util/DefaultAtomModelWrapper;
      79: invokevirtual #13                 // Method won/protocol/util/DefaultAtomModelWrapper.getSeeksSeeksNodes:()Ljava/util/Collection;
      82: invokeinterface #7,  1            // InterfaceMethod java/util/Collection.iterator:()Ljava/util/Iterator;
      87: astore_3
      88: aload_3
      89: invokeinterface #8,  1            // InterfaceMethod java/util/Iterator.hasNext:()Z
      94: ifeq          120
      97: aload_3
      98: invokeinterface #9,  1            // InterfaceMethod java/util/Iterator.next:()Ljava/lang/Object;
     103: checkcast     #10                 // class org/apache/jena/rdf/model/Resource
     106: astore        4
     108: aload_0
     109: aload         4
     111: getstatic     #4                  // Field won/matcher/solr/utils/MatcherAtomContentPropertyType.SEEKS:Lwon/matcher/solr/utils/MatcherAtomContentPropertyType;
     114: invokevirtual #5                  // Method addLocationFilters:(Lorg/apache/jena/rdf/model/Resource;Lwon/matcher/solr/utils/MatcherAtomContentPropertyType;)V
     117: goto          88
     120: new           #14                 // class won/matcher/solr/query/factory/MatchFieldQueryFactory
     123: dup
     124: ldc           #16                 // String _graph._type
     126: ldc           #17                 // String http\\://purl.org/webofneeds/model#Atom
     128: invokespecial #18                 // Method won/matcher/solr/query/factory/MatchFieldQueryFactory."<init>":(Ljava/lang/String;Ljava/lang/String;)V
     131: astore_3
     132: aload_0
     133: getfield      #19                 // Field contentFactories:Ljava/util/ArrayList;
     136: aload_3
     137: invokevirtual #20                 // Method java/util/ArrayList.add:(Ljava/lang/Object;)Z
     140: pop
     141: return
}
