Compiled from "MeasuresFilters.java"
public final class org.sonar.api.measures.MeasuresFilters {
  private org.sonar.api.measures.MeasuresFilters();
    Code:
       0: aload_0
       1: invokespecial #27                 // Method java/lang/Object."<init>":()V
       4: return

  public static org.sonar.api.measures.MeasuresFilter<java.util.Collection<org.sonar.api.measures.Measure>> all();
    Code:
       0: new           #23                 // class org/sonar/api/measures/MeasuresFilters$1
       3: dup
       4: invokespecial #32                 // Method org/sonar/api/measures/MeasuresFilters$1."<init>":()V
       7: areturn

  public static org.sonar.api.measures.MeasuresFilter<org.sonar.api.measures.Measure> metric(org.sonar.api.batch.measure.Metric<?>);
    Code:
       0: aload_0
       1: invokeinterface #40,  1           // InterfaceMethod org/sonar/api/batch/measure/Metric.key:()Ljava/lang/String;
       6: invokestatic  #43                 // Method metric:(Ljava/lang/String;)Lorg/sonar/api/measures/MeasuresFilter;
       9: areturn

  public static org.sonar.api.measures.MeasuresFilter<org.sonar.api.measures.Measure> metric(java.lang.String);
    Code:
       0: new           #21                 // class org/sonar/api/measures/MeasuresFilters$2
       3: dup
       4: aload_0
       5: aload_0
       6: invokespecial #48                 // Method org/sonar/api/measures/MeasuresFilters$2."<init>":(Ljava/lang/String;Ljava/lang/String;)V
       9: areturn

  public static org.sonar.api.measures.MeasuresFilter<org.sonar.api.measures.Measure> measure(org.sonar.api.measures.Measure);
    Code:
       0: new           #19                 // class org/sonar/api/measures/MeasuresFilters$3
       3: dup
       4: aload_0
       5: invokespecial #55                 // Method org/sonar/api/measures/MeasuresFilters$3."<init>":(Lorg/sonar/api/measures/Measure;)V
       8: areturn

  public static org.sonar.api.measures.MeasuresFilter<org.sonar.api.measures.RuleMeasure> rule(org.sonar.api.measures.Metric, org.sonar.api.rule.RuleKey);
    Code:
       0: new           #8                  // class org/sonar/api/measures/MeasuresFilters$RuleFilter
       3: dup
       4: aload_0
       5: aload_1
       6: invokespecial #61                 // Method org/sonar/api/measures/MeasuresFilters$RuleFilter."<init>":(Lorg/sonar/api/measures/Metric;Lorg/sonar/api/rule/RuleKey;)V
       9: areturn

  public static org.sonar.api.measures.MeasuresFilter<org.sonar.api.measures.RuleMeasure> rule(org.sonar.api.measures.Metric, org.sonar.api.rules.Rule);
    Code:
       0: aload_0
       1: aload_1
       2: invokevirtual #70                 // Method org/sonar/api/rules/Rule.ruleKey:()Lorg/sonar/api/rule/RuleKey;
       5: invokestatic  #72                 // Method rule:(Lorg/sonar/api/measures/Metric;Lorg/sonar/api/rule/RuleKey;)Lorg/sonar/api/measures/MeasuresFilter;
       8: areturn

  public static org.sonar.api.measures.MeasuresFilter<java.util.Collection<org.sonar.api.measures.RuleMeasure>> rules(org.sonar.api.measures.Metric);
    Code:
       0: new           #17                 // class org/sonar/api/measures/MeasuresFilters$4
       3: dup
       4: aload_0
       5: aload_0
       6: invokespecial #78                 // Method org/sonar/api/measures/MeasuresFilters$4."<init>":(Lorg/sonar/api/measures/Metric;Lorg/sonar/api/measures/Metric;)V
       9: areturn
}
