Compiled from "PersistenceMode.java"
public final class org.sonar.api.measures.PersistenceMode extends java.lang.Enum<org.sonar.api.measures.PersistenceMode> {
  public static final org.sonar.api.measures.PersistenceMode MEMORY;

  public static final org.sonar.api.measures.PersistenceMode DATABASE;

  public static final org.sonar.api.measures.PersistenceMode FULL;

  private static final org.sonar.api.measures.PersistenceMode[] $VALUES;

  public static org.sonar.api.measures.PersistenceMode[] values();
    Code:
       0: getstatic     #17                 // Field $VALUES:[Lorg/sonar/api/measures/PersistenceMode;
       3: invokevirtual #22                 // Method "[Lorg/sonar/api/measures/PersistenceMode;".clone:()Ljava/lang/Object;
       6: checkcast     #18                 // class "[Lorg/sonar/api/measures/PersistenceMode;"
       9: areturn

  public static org.sonar.api.measures.PersistenceMode valueOf(java.lang.String);
    Code:
       0: ldc           #2                  // class org/sonar/api/measures/PersistenceMode
       2: aload_0
       3: invokestatic  #27                 // Method java/lang/Enum.valueOf:(Ljava/lang/Class;Ljava/lang/String;)Ljava/lang/Enum;
       6: checkcast     #2                  // class org/sonar/api/measures/PersistenceMode
       9: areturn

  private org.sonar.api.measures.PersistenceMode();
    Code:
       0: aload_0
       1: aload_1
       2: iload_2
       3: invokespecial #33                 // Method java/lang/Enum."<init>":(Ljava/lang/String;I)V
       6: return

  public boolean useMemory();
    Code:
       0: aload_0
       1: getstatic     #38                 // Field MEMORY:Lorg/sonar/api/measures/PersistenceMode;
       4: invokevirtual #42                 // Method equals:(Ljava/lang/Object;)Z
       7: ifne          20
      10: aload_0
      11: getstatic     #44                 // Field FULL:Lorg/sonar/api/measures/PersistenceMode;
      14: invokevirtual #42                 // Method equals:(Ljava/lang/Object;)Z
      17: ifeq          24
      20: iconst_1
      21: goto          25
      24: iconst_0
      25: ireturn

  public boolean useDatabase();
    Code:
       0: aload_0
       1: getstatic     #47                 // Field DATABASE:Lorg/sonar/api/measures/PersistenceMode;
       4: invokevirtual #42                 // Method equals:(Ljava/lang/Object;)Z
       7: ifne          20
      10: aload_0
      11: getstatic     #44                 // Field FULL:Lorg/sonar/api/measures/PersistenceMode;
      14: invokevirtual #42                 // Method equals:(Ljava/lang/Object;)Z
      17: ifeq          24
      20: iconst_1
      21: goto          25
      24: iconst_0
      25: ireturn

  static {};
    Code:
       0: new           #2                  // class org/sonar/api/measures/PersistenceMode
       3: dup
       4: ldc           #50                 // String MEMORY
       6: iconst_0
       7: invokespecial #51                 // Method "<init>":(Ljava/lang/String;I)V
      10: putstatic     #38                 // Field MEMORY:Lorg/sonar/api/measures/PersistenceMode;
      13: new           #2                  // class org/sonar/api/measures/PersistenceMode
      16: dup
      17: ldc           #52                 // String DATABASE
      19: iconst_1
      20: invokespecial #51                 // Method "<init>":(Ljava/lang/String;I)V
      23: putstatic     #47                 // Field DATABASE:Lorg/sonar/api/measures/PersistenceMode;
      26: new           #2                  // class org/sonar/api/measures/PersistenceMode
      29: dup
      30: ldc           #53                 // String FULL
      32: iconst_2
      33: invokespecial #51                 // Method "<init>":(Ljava/lang/String;I)V
      36: putstatic     #44                 // Field FULL:Lorg/sonar/api/measures/PersistenceMode;
      39: iconst_3
      40: anewarray     #2                  // class org/sonar/api/measures/PersistenceMode
      43: dup
      44: iconst_0
      45: getstatic     #38                 // Field MEMORY:Lorg/sonar/api/measures/PersistenceMode;
      48: aastore
      49: dup
      50: iconst_1
      51: getstatic     #47                 // Field DATABASE:Lorg/sonar/api/measures/PersistenceMode;
      54: aastore
      55: dup
      56: iconst_2
      57: getstatic     #44                 // Field FULL:Lorg/sonar/api/measures/PersistenceMode;
      60: aastore
      61: putstatic     #17                 // Field $VALUES:[Lorg/sonar/api/measures/PersistenceMode;
      64: return
}
