Compiled from "Filter.java"
public abstract class org.apache.jena.util.iterator.Filter<T> implements java.util.function.Predicate<T> {
  public static final org.apache.jena.util.iterator.Filter any;

  public org.apache.jena.util.iterator.Filter();
    Code:
       0: aload_0
       1: invokespecial #1                  // Method java/lang/Object."<init>":()V
       4: return

  public boolean test(T);
    Code:
       0: aload_0
       1: aload_1
       2: invokevirtual #2                  // Method accept:(Ljava/lang/Object;)Z
       5: ireturn

  public abstract boolean accept(T);

  public org.apache.jena.util.iterator.ExtendedIterator<T> filterKeep(java.util.Iterator<T>);
    Code:
       0: new           #3                  // class org/apache/jena/util/iterator/FilterIterator
       3: dup
       4: aload_0
       5: aload_1
       6: invokespecial #4                  // Method org/apache/jena/util/iterator/FilterIterator."<init>":(Ljava/util/function/Predicate;Ljava/util/Iterator;)V
       9: areturn

  public org.apache.jena.util.iterator.Filter<T> and(org.apache.jena.util.iterator.Filter<T>);
    Code:
       0: aload_1
       1: invokevirtual #5                  // Method isAny:()Z
       4: ifeq          11
       7: aload_0
       8: goto          20
      11: new           #6                  // class org/apache/jena/util/iterator/Filter$1
      14: dup
      15: aload_0
      16: aload_1
      17: invokespecial #7                  // Method org/apache/jena/util/iterator/Filter$1."<init>":(Lorg/apache/jena/util/iterator/Filter;Lorg/apache/jena/util/iterator/Filter;)V
      20: areturn

  public boolean isAny();
    Code:
       0: iconst_0
       1: ireturn

  public static <T> org.apache.jena.util.iterator.Filter<T> any();
    Code:
       0: new           #8                  // class org/apache/jena/util/iterator/Filter$3
       3: dup
       4: invokespecial #9                  // Method org/apache/jena/util/iterator/Filter$3."<init>":()V
       7: areturn

  static {};
    Code:
       0: new           #10                 // class org/apache/jena/util/iterator/Filter$2
       3: dup
       4: invokespecial #11                 // Method org/apache/jena/util/iterator/Filter$2."<init>":()V
       7: putstatic     #12                 // Field any:Lorg/apache/jena/util/iterator/Filter;
      10: return
}
