Compiled from "ComposingConstraintTree.java"
final class org.hibernate.validator.internal.engine.constraintvalidation.ComposingConstraintTree$CompositionResult {
  private boolean allTrue;

  private boolean atLeastOneTrue;

  org.hibernate.validator.internal.engine.constraintvalidation.ComposingConstraintTree$CompositionResult(boolean, boolean);
    Code:
       0: aload_0
       1: invokespecial #1                  // Method java/lang/Object."<init>":()V
       4: aload_0
       5: iload_1
       6: putfield      #7                  // Field allTrue:Z
       9: aload_0
      10: iload_2
      11: putfield      #13                 // Field atLeastOneTrue:Z
      14: return

  public boolean isAllTrue();
    Code:
       0: aload_0
       1: getfield      #7                  // Field allTrue:Z
       4: ireturn

  public boolean isAtLeastOneTrue();
    Code:
       0: aload_0
       1: getfield      #13                 // Field atLeastOneTrue:Z
       4: ireturn

  public void setAllTrue(boolean);
    Code:
       0: aload_0
       1: iload_1
       2: putfield      #7                  // Field allTrue:Z
       5: return

  public void setAtLeastOneTrue(boolean);
    Code:
       0: aload_0
       1: iload_1
       2: putfield      #13                 // Field atLeastOneTrue:Z
       5: return
}
