Compiled from "ExprEditor.java"
final class javassist.expr.ExprEditor$NewOp {
  javassist.expr.ExprEditor$NewOp next;

  int pos;

  java.lang.String type;

  javassist.expr.ExprEditor$NewOp(javassist.expr.ExprEditor$NewOp, int, java.lang.String);
    Code:
       0: aload_0
       1: invokespecial #1                  // Method java/lang/Object."<init>":()V
       4: aload_0
       5: aload_1
       6: putfield      #2                  // Field next:Ljavassist/expr/ExprEditor$NewOp;
       9: aload_0
      10: iload_2
      11: putfield      #3                  // Field pos:I
      14: aload_0
      15: aload_3
      16: putfield      #4                  // Field type:Ljava/lang/String;
      19: return
}
