Compiled from "NewExpr.java"
public class javassist.expr.NewExpr extends javassist.expr.Expr {
  java.lang.String newTypeName;

  int newPos;

  protected javassist.expr.NewExpr(int, javassist.bytecode.CodeIterator, javassist.CtClass, javassist.bytecode.MethodInfo, java.lang.String, int);
    Code:
       0: aload_0
       1: iload_1
       2: aload_2
       3: aload_3
       4: aload         4
       6: invokespecial #1                  // Method javassist/expr/Expr."<init>":(ILjavassist/bytecode/CodeIterator;Ljavassist/CtClass;Ljavassist/bytecode/MethodInfo;)V
       9: aload_0
      10: aload         5
      12: putfield      #2                  // Field newTypeName:Ljava/lang/String;
      15: aload_0
      16: iload         6
      18: putfield      #3                  // Field newPos:I
      21: return

  public javassist.CtBehavior where();
    Code:
       0: aload_0
       1: invokespecial #4                  // Method javassist/expr/Expr.where:()Ljavassist/CtBehavior;
       4: areturn

  public int getLineNumber();
    Code:
       0: aload_0
       1: invokespecial #5                  // Method javassist/expr/Expr.getLineNumber:()I
       4: ireturn

  public java.lang.String getFileName();
    Code:
       0: aload_0
       1: invokespecial #6                  // Method javassist/expr/Expr.getFileName:()Ljava/lang/String;
       4: areturn

  private javassist.CtClass getCtClass() throws javassist.NotFoundException;
    Code:
       0: aload_0
       1: getfield      #7                  // Field thisClass:Ljavassist/CtClass;
       4: invokevirtual #8                  // Method javassist/CtClass.getClassPool:()Ljavassist/ClassPool;
       7: aload_0
       8: getfield      #2                  // Field newTypeName:Ljava/lang/String;
      11: invokevirtual #9                  // Method javassist/ClassPool.get:(Ljava/lang/String;)Ljavassist/CtClass;
      14: areturn

  public java.lang.String getClassName();
    Code:
       0: aload_0
       1: getfield      #2                  // Field newTypeName:Ljava/lang/String;
       4: areturn

  public java.lang.String getSignature();
    Code:
       0: aload_0
       1: invokevirtual #10                 // Method getConstPool:()Ljavassist/bytecode/ConstPool;
       4: astore_1
       5: aload_0
       6: getfield      #11                 // Field iterator:Ljavassist/bytecode/CodeIterator;
       9: aload_0
      10: getfield      #12                 // Field currentPos:I
      13: iconst_1
      14: iadd
      15: invokevirtual #13                 // Method javassist/bytecode/CodeIterator.u16bitAt:(I)I
      18: istore_2
      19: aload_1
      20: iload_2
      21: invokevirtual #14                 // Method javassist/bytecode/ConstPool.getMethodrefType:(I)Ljava/lang/String;
      24: areturn

  public javassist.CtConstructor getConstructor() throws javassist.NotFoundException;
    Code:
       0: aload_0
       1: invokevirtual #10                 // Method getConstPool:()Ljavassist/bytecode/ConstPool;
       4: astore_1
       5: aload_0
       6: getfield      #11                 // Field iterator:Ljavassist/bytecode/CodeIterator;
       9: aload_0
      10: getfield      #12                 // Field currentPos:I
      13: iconst_1
      14: iadd
      15: invokevirtual #13                 // Method javassist/bytecode/CodeIterator.u16bitAt:(I)I
      18: istore_2
      19: aload_1
      20: iload_2
      21: invokevirtual #14                 // Method javassist/bytecode/ConstPool.getMethodrefType:(I)Ljava/lang/String;
      24: astore_3
      25: aload_0
      26: invokespecial #15                 // Method getCtClass:()Ljavassist/CtClass;
      29: aload_3
      30: invokevirtual #16                 // Method javassist/CtClass.getConstructor:(Ljava/lang/String;)Ljavassist/CtConstructor;
      33: areturn

  public javassist.CtClass[] mayThrow();
    Code:
       0: aload_0
       1: invokespecial #17                 // Method javassist/expr/Expr.mayThrow:()[Ljavassist/CtClass;
       4: areturn

  private int canReplace() throws javassist.CannotCompileException;
    Code:
       0: aload_0
       1: getfield      #11                 // Field iterator:Ljavassist/bytecode/CodeIterator;
       4: aload_0
       5: getfield      #3                  // Field newPos:I
       8: iconst_3
       9: iadd
      10: invokevirtual #18                 // Method javassist/bytecode/CodeIterator.byteAt:(I)I
      13: istore_1
      14: iload_1
      15: bipush        89
      17: if_icmpne     63
      20: aload_0
      21: getfield      #11                 // Field iterator:Ljavassist/bytecode/CodeIterator;
      24: aload_0
      25: getfield      #3                  // Field newPos:I
      28: iconst_4
      29: iadd
      30: invokevirtual #18                 // Method javassist/bytecode/CodeIterator.byteAt:(I)I
      33: bipush        94
      35: if_icmpne     61
      38: aload_0
      39: getfield      #11                 // Field iterator:Ljavassist/bytecode/CodeIterator;
      42: aload_0
      43: getfield      #3                  // Field newPos:I
      46: iconst_5
      47: iadd
      48: invokevirtual #18                 // Method javassist/bytecode/CodeIterator.byteAt:(I)I
      51: bipush        88
      53: if_icmpne     61
      56: bipush        6
      58: goto          62
      61: iconst_4
      62: ireturn
      63: iload_1
      64: bipush        90
      66: if_icmpne     89
      69: aload_0
      70: getfield      #11                 // Field iterator:Ljavassist/bytecode/CodeIterator;
      73: aload_0
      74: getfield      #3                  // Field newPos:I
      77: iconst_4
      78: iadd
      79: invokevirtual #18                 // Method javassist/bytecode/CodeIterator.byteAt:(I)I
      82: bipush        95
      84: if_icmpne     89
      87: iconst_5
      88: ireturn
      89: iconst_3
      90: ireturn

  public void replace(java.lang.String) throws javassist.CannotCompileException;
    Code:
       0: aload_0
       1: getfield      #7                  // Field thisClass:Ljavassist/CtClass;
       4: invokevirtual #20                 // Method javassist/CtClass.getClassFile:()Ljavassist/bytecode/ClassFile;
       7: pop
       8: iconst_3
       9: istore_2
      10: aload_0
      11: getfield      #3                  // Field newPos:I
      14: istore_3
      15: aload_0
      16: getfield      #11                 // Field iterator:Ljavassist/bytecode/CodeIterator;
      19: iload_3
      20: iconst_1
      21: iadd
      22: invokevirtual #13                 // Method javassist/bytecode/CodeIterator.u16bitAt:(I)I
      25: istore        4
      27: aload_0
      28: invokespecial #21                 // Method canReplace:()I
      31: istore        5
      33: iload_3
      34: iload         5
      36: iadd
      37: istore        6
      39: iload_3
      40: istore        7
      42: iload         7
      44: iload         6
      46: if_icmpge     65
      49: aload_0
      50: getfield      #11                 // Field iterator:Ljavassist/bytecode/CodeIterator;
      53: iconst_0
      54: iload         7
      56: invokevirtual #22                 // Method javassist/bytecode/CodeIterator.writeByte:(II)V
      59: iinc          7, 1
      62: goto          42
      65: aload_0
      66: invokevirtual #10                 // Method getConstPool:()Ljavassist/bytecode/ConstPool;
      69: astore        7
      71: aload_0
      72: getfield      #12                 // Field currentPos:I
      75: istore_3
      76: aload_0
      77: getfield      #11                 // Field iterator:Ljavassist/bytecode/CodeIterator;
      80: iload_3
      81: iconst_1
      82: iadd
      83: invokevirtual #13                 // Method javassist/bytecode/CodeIterator.u16bitAt:(I)I
      86: istore        8
      88: aload         7
      90: iload         8
      92: invokevirtual #14                 // Method javassist/bytecode/ConstPool.getMethodrefType:(I)Ljava/lang/String;
      95: astore        9
      97: new           #23                 // class javassist/compiler/Javac
     100: dup
     101: aload_0
     102: getfield      #7                  // Field thisClass:Ljavassist/CtClass;
     105: invokespecial #24                 // Method javassist/compiler/Javac."<init>":(Ljavassist/CtClass;)V
     108: astore        10
     110: aload_0
     111: getfield      #7                  // Field thisClass:Ljavassist/CtClass;
     114: invokevirtual #8                  // Method javassist/CtClass.getClassPool:()Ljavassist/ClassPool;
     117: astore        11
     119: aload_0
     120: getfield      #11                 // Field iterator:Ljavassist/bytecode/CodeIterator;
     123: invokevirtual #25                 // Method javassist/bytecode/CodeIterator.get:()Ljavassist/bytecode/CodeAttribute;
     126: astore        12
     128: aload         9
     130: aload         11
     132: invokestatic  #26                 // Method javassist/bytecode/Descriptor.getParameterTypes:(Ljava/lang/String;Ljavassist/ClassPool;)[Ljavassist/CtClass;
     135: astore        13
     137: aload         11
     139: aload_0
     140: getfield      #2                  // Field newTypeName:Ljava/lang/String;
     143: invokevirtual #9                  // Method javassist/ClassPool.get:(Ljava/lang/String;)Ljavassist/CtClass;
     146: astore        14
     148: aload         12
     150: invokevirtual #27                 // Method javassist/bytecode/CodeAttribute.getMaxLocals:()I
     153: istore        15
     155: aload         10
     157: aload_0
     158: getfield      #2                  // Field newTypeName:Ljava/lang/String;
     161: aload         13
     163: iconst_1
     164: iload         15
     166: aload_0
     167: invokevirtual #28                 // Method withinStatic:()Z
     170: invokevirtual #29                 // Method javassist/compiler/Javac.recordParams:(Ljava/lang/String;[Ljavassist/CtClass;ZIZ)I
     173: pop
     174: aload         10
     176: aload         14
     178: iconst_1
     179: invokevirtual #30                 // Method javassist/compiler/Javac.recordReturnType:(Ljavassist/CtClass;Z)I
     182: istore        16
     184: aload         10
     186: new           #31                 // class javassist/expr/NewExpr$ProceedForNew
     189: dup
     190: aload         14
     192: iload         4
     194: iload         8
     196: invokespecial #32                 // Method javassist/expr/NewExpr$ProceedForNew."<init>":(Ljavassist/CtClass;II)V
     199: invokevirtual #33                 // Method javassist/compiler/Javac.recordProceed:(Ljavassist/compiler/ProceedHandler;)V
     202: aload         14
     204: aload_1
     205: invokestatic  #34                 // Method checkResultValue:(Ljavassist/CtClass;Ljava/lang/String;)Z
     208: pop
     209: aload         10
     211: invokevirtual #35                 // Method javassist/compiler/Javac.getBytecode:()Ljavassist/bytecode/Bytecode;
     214: astore        17
     216: aload         13
     218: iconst_1
     219: iload         15
     221: aload         17
     223: invokestatic  #36                 // Method storeStack:([Ljavassist/CtClass;ZILjavassist/bytecode/Bytecode;)V
     226: aload         10
     228: aload         12
     230: iload_3
     231: invokevirtual #37                 // Method javassist/compiler/Javac.recordLocalVariables:(Ljavassist/bytecode/CodeAttribute;I)Z
     234: pop
     235: aload         17
     237: aload         14
     239: invokevirtual #38                 // Method javassist/bytecode/Bytecode.addConstZero:(Ljavassist/CtClass;)V
     242: aload         17
     244: iload         16
     246: aload         14
     248: invokevirtual #39                 // Method javassist/bytecode/Bytecode.addStore:(ILjavassist/CtClass;)I
     251: pop
     252: aload         10
     254: aload_1
     255: invokevirtual #40                 // Method javassist/compiler/Javac.compileStmnt:(Ljava/lang/String;)V
     258: iload         5
     260: iconst_3
     261: if_icmple     271
     264: aload         17
     266: iload         16
     268: invokevirtual #41                 // Method javassist/bytecode/Bytecode.addAload:(I)V
     271: aload_0
     272: iload_3
     273: aload         17
     275: iconst_3
     276: invokevirtual #42                 // Method replace0:(ILjavassist/bytecode/Bytecode;I)V
     279: goto          318
     282: astore        13
     284: new           #44                 // class javassist/CannotCompileException
     287: dup
     288: aload         13
     290: invokespecial #45                 // Method javassist/CannotCompileException."<init>":(Ljavassist/compiler/CompileError;)V
     293: athrow
     294: astore        13
     296: new           #44                 // class javassist/CannotCompileException
     299: dup
     300: aload         13
     302: invokespecial #47                 // Method javassist/CannotCompileException."<init>":(Ljavassist/NotFoundException;)V
     305: athrow
     306: astore        13
     308: new           #44                 // class javassist/CannotCompileException
     311: dup
     312: ldc           #49                 // String broken method
     314: invokespecial #50                 // Method javassist/CannotCompileException."<init>":(Ljava/lang/String;)V
     317: athrow
     318: return
    Exception table:
       from    to  target type
         128   279   282   Class javassist/compiler/CompileError
         128   279   294   Class javassist/NotFoundException
         128   279   306   Class javassist/bytecode/BadBytecode
}
