Compiled from "DeliveryMode.java"
public class com.amazonaws.event.DeliveryMode$Check {
  public com.amazonaws.event.DeliveryMode$Check();
    Code:
       0: aload_0
       1: invokespecial #1                  // Method java/lang/Object."<init>":()V
       4: return

  public static boolean isSyncCallSafe(com.amazonaws.event.ProgressListener);
    Code:
       0: aload_0
       1: instanceof    #2                  // class com/amazonaws/event/DeliveryMode
       4: ifeq          19
       7: aload_0
       8: checkcast     #2                  // class com/amazonaws/event/DeliveryMode
      11: astore_1
      12: aload_1
      13: invokeinterface #3,  1            // InterfaceMethod com/amazonaws/event/DeliveryMode.isSyncCallSafe:()Z
      18: ireturn
      19: aload_0
      20: ifnonnull     27
      23: iconst_1
      24: goto          28
      27: iconst_0
      28: ireturn
}
