Compiled from "BinaryPredicateSupport.java"
public abstract class org.apache.camel.builder.BinaryPredicateSupport implements org.apache.camel.BinaryPredicate {
  private final org.apache.camel.Expression left;

  private final org.apache.camel.Expression right;

  protected org.apache.camel.builder.BinaryPredicateSupport(org.apache.camel.Expression, org.apache.camel.Expression);
    Code:
       0: aload_0
       1: invokespecial #15                 // Method java/lang/Object."<init>":()V
       4: aload_1
       5: ldc           #16                 // String left
       7: invokestatic  #22                 // Method org/apache/camel/util/ObjectHelper.notNull:(Ljava/lang/Object;Ljava/lang/String;)Ljava/lang/Object;
      10: pop
      11: aload_2
      12: ldc           #23                 // String right
      14: invokestatic  #22                 // Method org/apache/camel/util/ObjectHelper.notNull:(Ljava/lang/Object;Ljava/lang/String;)Ljava/lang/Object;
      17: pop
      18: aload_0
      19: aload_1
      20: putfield      #25                 // Field left:Lorg/apache/camel/Expression;
      23: aload_0
      24: aload_2
      25: putfield      #27                 // Field right:Lorg/apache/camel/Expression;
      28: return

  public java.lang.String toString();
    Code:
       0: new           #33                 // class java/lang/StringBuilder
       3: dup
       4: invokespecial #34                 // Method java/lang/StringBuilder."<init>":()V
       7: aload_0
       8: getfield      #25                 // Field left:Lorg/apache/camel/Expression;
      11: invokevirtual #38                 // Method java/lang/StringBuilder.append:(Ljava/lang/Object;)Ljava/lang/StringBuilder;
      14: ldc           #40                 // String
      16: invokevirtual #43                 // Method java/lang/StringBuilder.append:(Ljava/lang/String;)Ljava/lang/StringBuilder;
      19: aload_0
      20: invokevirtual #46                 // Method getOperationText:()Ljava/lang/String;
      23: invokevirtual #43                 // Method java/lang/StringBuilder.append:(Ljava/lang/String;)Ljava/lang/StringBuilder;
      26: ldc           #40                 // String
      28: invokevirtual #43                 // Method java/lang/StringBuilder.append:(Ljava/lang/String;)Ljava/lang/StringBuilder;
      31: aload_0
      32: getfield      #27                 // Field right:Lorg/apache/camel/Expression;
      35: invokevirtual #38                 // Method java/lang/StringBuilder.append:(Ljava/lang/Object;)Ljava/lang/StringBuilder;
      38: invokevirtual #48                 // Method java/lang/StringBuilder.toString:()Ljava/lang/String;
      41: areturn

  public boolean matches(org.apache.camel.Exchange);
    Code:
       0: aload_0
       1: aload_1
       2: invokevirtual #54                 // Method matchesReturningFailureMessage:(Lorg/apache/camel/Exchange;)Ljava/lang/String;
       5: ifnonnull     12
       8: iconst_1
       9: goto          13
      12: iconst_0
      13: ireturn

  public java.lang.String matchesReturningFailureMessage(org.apache.camel.Exchange);
    Code:
       0: aconst_null
       1: astore_2
       2: aload_0
       3: getfield      #25                 // Field left:Lorg/apache/camel/Expression;
       6: aload_1
       7: ldc           #4                  // class java/lang/Object
       9: invokeinterface #62,  3           // InterfaceMethod org/apache/camel/Expression.evaluate:(Lorg/apache/camel/Exchange;Ljava/lang/Class;)Ljava/lang/Object;
      14: astore_3
      15: aload_0
      16: getfield      #27                 // Field right:Lorg/apache/camel/Expression;
      19: aload_1
      20: ldc           #4                  // class java/lang/Object
      22: invokeinterface #62,  3           // InterfaceMethod org/apache/camel/Expression.evaluate:(Lorg/apache/camel/Exchange;Ljava/lang/Class;)Ljava/lang/Object;
      27: astore        4
      29: aload_0
      30: aload_1
      31: aload_3
      32: aload         4
      34: invokevirtual #65                 // Method matches:(Lorg/apache/camel/Exchange;Ljava/lang/Object;Ljava/lang/Object;)Z
      37: ifne          77
      40: new           #33                 // class java/lang/StringBuilder
      43: dup
      44: invokespecial #34                 // Method java/lang/StringBuilder."<init>":()V
      47: aload_3
      48: invokevirtual #38                 // Method java/lang/StringBuilder.append:(Ljava/lang/Object;)Ljava/lang/StringBuilder;
      51: ldc           #40                 // String
      53: invokevirtual #43                 // Method java/lang/StringBuilder.append:(Ljava/lang/String;)Ljava/lang/StringBuilder;
      56: aload_0
      57: invokevirtual #68                 // Method getOperator:()Ljava/lang/String;
      60: invokevirtual #43                 // Method java/lang/StringBuilder.append:(Ljava/lang/String;)Ljava/lang/StringBuilder;
      63: ldc           #40                 // String
      65: invokevirtual #43                 // Method java/lang/StringBuilder.append:(Ljava/lang/String;)Ljava/lang/StringBuilder;
      68: aload         4
      70: invokevirtual #38                 // Method java/lang/StringBuilder.append:(Ljava/lang/Object;)Ljava/lang/StringBuilder;
      73: invokevirtual #48                 // Method java/lang/StringBuilder.toString:()Ljava/lang/String;
      76: astore_2
      77: aload_2
      78: areturn

  protected abstract boolean matches(org.apache.camel.Exchange, java.lang.Object, java.lang.Object);

  protected abstract java.lang.String getOperationText();

  public org.apache.camel.Expression getLeft();
    Code:
       0: aload_0
       1: getfield      #25                 // Field left:Lorg/apache/camel/Expression;
       4: areturn

  public org.apache.camel.Expression getRight();
    Code:
       0: aload_0
       1: getfield      #27                 // Field right:Lorg/apache/camel/Expression;
       4: areturn

  public java.lang.String getOperator();
    Code:
       0: aload_0
       1: invokevirtual #46                 // Method getOperationText:()Ljava/lang/String;
       4: areturn
}
