Compiled from "NotifyBuilder.java"
final class org.apache.camel.builder.NotifyBuilder$CompoundEventPredicate implements org.apache.camel.builder.NotifyBuilder$EventPredicate {
  private java.util.List<org.apache.camel.builder.NotifyBuilder$EventPredicate> predicates;

  final org.apache.camel.builder.NotifyBuilder this$0;

  private org.apache.camel.builder.NotifyBuilder$CompoundEventPredicate(java.util.List<org.apache.camel.builder.NotifyBuilder$EventPredicate>);
    Code:
       0: aload_0
       1: aload_1
       2: putfield      #22                 // Field this$0:Lorg/apache/camel/builder/NotifyBuilder;
       5: aload_0
       6: invokespecial #25                 // Method java/lang/Object."<init>":()V
       9: aload_0
      10: new           #27                 // class java/util/ArrayList
      13: dup
      14: invokespecial #28                 // Method java/util/ArrayList."<init>":()V
      17: putfield      #30                 // Field predicates:Ljava/util/List;
      20: aload_0
      21: getfield      #30                 // Field predicates:Ljava/util/List;
      24: aload_2
      25: invokeinterface #36,  2           // InterfaceMethod java/util/List.addAll:(Ljava/util/Collection;)Z
      30: pop
      31: return

  public boolean isAbstract();
    Code:
       0: iconst_0
       1: ireturn

  public boolean matches();
    Code:
       0: aload_0
       1: getfield      #30                 // Field predicates:Ljava/util/List;
       4: invokeinterface #45,  1           // InterfaceMethod java/util/List.iterator:()Ljava/util/Iterator;
       9: astore_1
      10: aload_1
      11: invokeinterface #50,  1           // InterfaceMethod java/util/Iterator.hasNext:()Z
      16: ifeq          60
      19: aload_1
      20: invokeinterface #54,  1           // InterfaceMethod java/util/Iterator.next:()Ljava/lang/Object;
      25: checkcast     #6                  // class org/apache/camel/builder/NotifyBuilder$EventPredicate
      28: astore_2
      29: aload_2
      30: invokeinterface #56,  1           // InterfaceMethod org/apache/camel/builder/NotifyBuilder$EventPredicate.matches:()Z
      35: istore_3
      36: invokestatic  #60                 // Method org/apache/camel/builder/NotifyBuilder.access$800:()Lorg/slf4j/Logger;
      39: ldc           #62                 // String matches() {} -> {}
      41: aload_2
      42: iload_3
      43: invokestatic  #68                 // Method java/lang/Boolean.valueOf:(Z)Ljava/lang/Boolean;
      46: invokeinterface #74,  4           // InterfaceMethod org/slf4j/Logger.trace:(Ljava/lang/String;Ljava/lang/Object;Ljava/lang/Object;)V
      51: iload_3
      52: ifne          57
      55: iconst_0
      56: ireturn
      57: goto          10
      60: iconst_1
      61: ireturn

  public void reset();
    Code:
       0: aload_0
       1: getfield      #30                 // Field predicates:Ljava/util/List;
       4: invokeinterface #45,  1           // InterfaceMethod java/util/List.iterator:()Ljava/util/Iterator;
       9: astore_1
      10: aload_1
      11: invokeinterface #50,  1           // InterfaceMethod java/util/Iterator.hasNext:()Z
      16: ifeq          49
      19: aload_1
      20: invokeinterface #54,  1           // InterfaceMethod java/util/Iterator.next:()Ljava/lang/Object;
      25: checkcast     #6                  // class org/apache/camel/builder/NotifyBuilder$EventPredicate
      28: astore_2
      29: invokestatic  #60                 // Method org/apache/camel/builder/NotifyBuilder.access$800:()Lorg/slf4j/Logger;
      32: ldc           #83                 // String reset() {}
      34: aload_2
      35: invokeinterface #86,  3           // InterfaceMethod org/slf4j/Logger.trace:(Ljava/lang/String;Ljava/lang/Object;)V
      40: aload_2
      41: invokeinterface #88,  1           // InterfaceMethod org/apache/camel/builder/NotifyBuilder$EventPredicate.reset:()V
      46: goto          10
      49: return

  public boolean onExchangeCreated(org.apache.camel.Exchange);
    Code:
       0: aload_0
       1: getfield      #30                 // Field predicates:Ljava/util/List;
       4: invokeinterface #45,  1           // InterfaceMethod java/util/List.iterator:()Ljava/util/Iterator;
       9: astore_2
      10: aload_2
      11: invokeinterface #50,  1           // InterfaceMethod java/util/Iterator.hasNext:()Z
      16: ifeq          64
      19: aload_2
      20: invokeinterface #54,  1           // InterfaceMethod java/util/Iterator.next:()Ljava/lang/Object;
      25: checkcast     #6                  // class org/apache/camel/builder/NotifyBuilder$EventPredicate
      28: astore_3
      29: aload_3
      30: aload_1
      31: invokeinterface #92,  2           // InterfaceMethod org/apache/camel/builder/NotifyBuilder$EventPredicate.onExchangeCreated:(Lorg/apache/camel/Exchange;)Z
      36: istore        4
      38: invokestatic  #60                 // Method org/apache/camel/builder/NotifyBuilder.access$800:()Lorg/slf4j/Logger;
      41: ldc           #94                 // String onExchangeCreated() {} -> {}
      43: aload_3
      44: iload         4
      46: invokestatic  #68                 // Method java/lang/Boolean.valueOf:(Z)Ljava/lang/Boolean;
      49: invokeinterface #74,  4           // InterfaceMethod org/slf4j/Logger.trace:(Ljava/lang/String;Ljava/lang/Object;Ljava/lang/Object;)V
      54: iload         4
      56: ifne          61
      59: iconst_0
      60: ireturn
      61: goto          10
      64: iconst_1
      65: ireturn

  public boolean onExchangeCompleted(org.apache.camel.Exchange);
    Code:
       0: aload_0
       1: getfield      #30                 // Field predicates:Ljava/util/List;
       4: invokeinterface #45,  1           // InterfaceMethod java/util/List.iterator:()Ljava/util/Iterator;
       9: astore_2
      10: aload_2
      11: invokeinterface #50,  1           // InterfaceMethod java/util/Iterator.hasNext:()Z
      16: ifeq          64
      19: aload_2
      20: invokeinterface #54,  1           // InterfaceMethod java/util/Iterator.next:()Ljava/lang/Object;
      25: checkcast     #6                  // class org/apache/camel/builder/NotifyBuilder$EventPredicate
      28: astore_3
      29: aload_3
      30: aload_1
      31: invokeinterface #99,  2           // InterfaceMethod org/apache/camel/builder/NotifyBuilder$EventPredicate.onExchangeCompleted:(Lorg/apache/camel/Exchange;)Z
      36: istore        4
      38: invokestatic  #60                 // Method org/apache/camel/builder/NotifyBuilder.access$800:()Lorg/slf4j/Logger;
      41: ldc           #101                // String onExchangeCompleted() {} -> {}
      43: aload_3
      44: iload         4
      46: invokestatic  #68                 // Method java/lang/Boolean.valueOf:(Z)Ljava/lang/Boolean;
      49: invokeinterface #74,  4           // InterfaceMethod org/slf4j/Logger.trace:(Ljava/lang/String;Ljava/lang/Object;Ljava/lang/Object;)V
      54: iload         4
      56: ifne          61
      59: iconst_0
      60: ireturn
      61: goto          10
      64: iconst_1
      65: ireturn

  public boolean onExchangeFailed(org.apache.camel.Exchange);
    Code:
       0: aload_0
       1: getfield      #30                 // Field predicates:Ljava/util/List;
       4: invokeinterface #45,  1           // InterfaceMethod java/util/List.iterator:()Ljava/util/Iterator;
       9: astore_2
      10: aload_2
      11: invokeinterface #50,  1           // InterfaceMethod java/util/Iterator.hasNext:()Z
      16: ifeq          64
      19: aload_2
      20: invokeinterface #54,  1           // InterfaceMethod java/util/Iterator.next:()Ljava/lang/Object;
      25: checkcast     #6                  // class org/apache/camel/builder/NotifyBuilder$EventPredicate
      28: astore_3
      29: aload_3
      30: aload_1
      31: invokeinterface #104,  2          // InterfaceMethod org/apache/camel/builder/NotifyBuilder$EventPredicate.onExchangeFailed:(Lorg/apache/camel/Exchange;)Z
      36: istore        4
      38: invokestatic  #60                 // Method org/apache/camel/builder/NotifyBuilder.access$800:()Lorg/slf4j/Logger;
      41: ldc           #106                // String onExchangeFailed() {} -> {}
      43: aload_3
      44: iload         4
      46: invokestatic  #68                 // Method java/lang/Boolean.valueOf:(Z)Ljava/lang/Boolean;
      49: invokeinterface #74,  4           // InterfaceMethod org/slf4j/Logger.trace:(Ljava/lang/String;Ljava/lang/Object;Ljava/lang/Object;)V
      54: iload         4
      56: ifne          61
      59: iconst_0
      60: ireturn
      61: goto          10
      64: iconst_1
      65: ireturn

  public boolean onExchangeSent(org.apache.camel.Exchange, org.apache.camel.Endpoint, long);
    Code:
       0: aload_0
       1: getfield      #30                 // Field predicates:Ljava/util/List;
       4: invokeinterface #45,  1           // InterfaceMethod java/util/List.iterator:()Ljava/util/Iterator;
       9: astore        5
      11: aload         5
      13: invokeinterface #50,  1           // InterfaceMethod java/util/Iterator.hasNext:()Z
      18: ifeq          86
      21: aload         5
      23: invokeinterface #54,  1           // InterfaceMethod java/util/Iterator.next:()Ljava/lang/Object;
      28: checkcast     #6                  // class org/apache/camel/builder/NotifyBuilder$EventPredicate
      31: astore        6
      33: aload         6
      35: aload_1
      36: aload_2
      37: lload_3
      38: invokeinterface #110,  5          // InterfaceMethod org/apache/camel/builder/NotifyBuilder$EventPredicate.onExchangeSent:(Lorg/apache/camel/Exchange;Lorg/apache/camel/Endpoint;J)Z
      43: istore        7
      45: invokestatic  #60                 // Method org/apache/camel/builder/NotifyBuilder.access$800:()Lorg/slf4j/Logger;
      48: ldc           #112                // String onExchangeSent() {} {} -> {}
      50: iconst_3
      51: anewarray     #4                  // class java/lang/Object
      54: dup
      55: iconst_0
      56: aload_2
      57: aastore
      58: dup
      59: iconst_1
      60: aload         6
      62: aastore
      63: dup
      64: iconst_2
      65: iload         7
      67: invokestatic  #68                 // Method java/lang/Boolean.valueOf:(Z)Ljava/lang/Boolean;
      70: aastore
      71: invokeinterface #115,  3          // InterfaceMethod org/slf4j/Logger.trace:(Ljava/lang/String;[Ljava/lang/Object;)V
      76: iload         7
      78: ifne          83
      81: iconst_0
      82: ireturn
      83: goto          11
      86: iconst_1
      87: ireturn

  public java.lang.String toString();
    Code:
       0: new           #123                // class java/lang/StringBuilder
       3: dup
       4: invokespecial #124                // Method java/lang/StringBuilder."<init>":()V
       7: astore_1
       8: aload_0
       9: getfield      #30                 // Field predicates:Ljava/util/List;
      12: invokeinterface #45,  1           // InterfaceMethod java/util/List.iterator:()Ljava/util/Iterator;
      17: astore_2
      18: aload_2
      19: invokeinterface #50,  1           // InterfaceMethod java/util/Iterator.hasNext:()Z
      24: ifeq          63
      27: aload_2
      28: invokeinterface #54,  1           // InterfaceMethod java/util/Iterator.next:()Ljava/lang/Object;
      33: checkcast     #6                  // class org/apache/camel/builder/NotifyBuilder$EventPredicate
      36: astore_3
      37: aload_1
      38: invokevirtual #128                // Method java/lang/StringBuilder.length:()I
      41: ifle          51
      44: aload_1
      45: ldc           #130                // String .
      47: invokevirtual #134                // Method java/lang/StringBuilder.append:(Ljava/lang/String;)Ljava/lang/StringBuilder;
      50: pop
      51: aload_1
      52: aload_3
      53: invokevirtual #136                // Method java/lang/Object.toString:()Ljava/lang/String;
      56: invokevirtual #134                // Method java/lang/StringBuilder.append:(Ljava/lang/String;)Ljava/lang/StringBuilder;
      59: pop
      60: goto          18
      63: aload_1
      64: invokevirtual #137                // Method java/lang/StringBuilder.toString:()Ljava/lang/String;
      67: areturn

  org.apache.camel.builder.NotifyBuilder$CompoundEventPredicate(org.apache.camel.builder.NotifyBuilder, java.util.List, org.apache.camel.builder.NotifyBuilder$1);
    Code:
       0: aload_0
       1: aload_1
       2: aload_2
       3: invokespecial #143                // Method "<init>":(Lorg/apache/camel/builder/NotifyBuilder;Ljava/util/List;)V
       6: return
}
