Compiled from "TrinoThriftDomain.java"
public final class io.trino.plugin.thrift.api.TrinoThriftDomain {
  private final io.trino.plugin.thrift.api.valuesets.TrinoThriftValueSet valueSet;

  private final boolean nullAllowed;

  public io.trino.plugin.thrift.api.TrinoThriftDomain(io.trino.plugin.thrift.api.valuesets.TrinoThriftValueSet, boolean);
    Code:
       0: aload_0
       1: invokespecial #1                  // Method java/lang/Object."<init>":()V
       4: aload_0
       5: aload_1
       6: ldc           #7                  // String valueSet is null
       8: invokestatic  #9                  // Method java/util/Objects.requireNonNull:(Ljava/lang/Object;Ljava/lang/String;)Ljava/lang/Object;
      11: checkcast     #15                 // class io/trino/plugin/thrift/api/valuesets/TrinoThriftValueSet
      14: putfield      #17                 // Field valueSet:Lio/trino/plugin/thrift/api/valuesets/TrinoThriftValueSet;
      17: aload_0
      18: iload_2
      19: putfield      #23                 // Field nullAllowed:Z
      22: return

  public io.trino.plugin.thrift.api.valuesets.TrinoThriftValueSet getValueSet();
    Code:
       0: aload_0
       1: getfield      #17                 // Field valueSet:Lio/trino/plugin/thrift/api/valuesets/TrinoThriftValueSet;
       4: areturn

  public boolean isNullAllowed();
    Code:
       0: aload_0
       1: getfield      #23                 // Field nullAllowed:Z
       4: ireturn

  public boolean equals(java.lang.Object);
    Code:
       0: aload_0
       1: aload_1
       2: if_acmpne     7
       5: iconst_1
       6: ireturn
       7: aload_1
       8: ifnull        22
      11: aload_0
      12: invokevirtual #27                 // Method java/lang/Object.getClass:()Ljava/lang/Class;
      15: aload_1
      16: invokevirtual #27                 // Method java/lang/Object.getClass:()Ljava/lang/Class;
      19: if_acmpeq     24
      22: iconst_0
      23: ireturn
      24: aload_1
      25: checkcast     #18                 // class io/trino/plugin/thrift/api/TrinoThriftDomain
      28: astore_2
      29: aload_0
      30: getfield      #17                 // Field valueSet:Lio/trino/plugin/thrift/api/valuesets/TrinoThriftValueSet;
      33: aload_2
      34: getfield      #17                 // Field valueSet:Lio/trino/plugin/thrift/api/valuesets/TrinoThriftValueSet;
      37: invokestatic  #31                 // Method java/util/Objects.equals:(Ljava/lang/Object;Ljava/lang/Object;)Z
      40: ifeq          58
      43: aload_0
      44: getfield      #23                 // Field nullAllowed:Z
      47: aload_2
      48: getfield      #23                 // Field nullAllowed:Z
      51: if_icmpne     58
      54: iconst_1
      55: goto          59
      58: iconst_0
      59: ireturn

  public int hashCode();
    Code:
       0: iconst_2
       1: anewarray     #2                  // class java/lang/Object
       4: dup
       5: iconst_0
       6: aload_0
       7: getfield      #17                 // Field valueSet:Lio/trino/plugin/thrift/api/valuesets/TrinoThriftValueSet;
      10: aastore
      11: dup
      12: iconst_1
      13: aload_0
      14: getfield      #23                 // Field nullAllowed:Z
      17: invokestatic  #35                 // Method java/lang/Boolean.valueOf:(Z)Ljava/lang/Boolean;
      20: aastore
      21: invokestatic  #41                 // Method java/util/Objects.hash:([Ljava/lang/Object;)I
      24: ireturn

  public java.lang.String toString();
    Code:
       0: aload_0
       1: invokestatic  #45                 // Method com/google/common/base/MoreObjects.toStringHelper:(Ljava/lang/Object;)Lcom/google/common/base/MoreObjects$ToStringHelper;
       4: ldc           #51                 // String valueSet
       6: aload_0
       7: getfield      #17                 // Field valueSet:Lio/trino/plugin/thrift/api/valuesets/TrinoThriftValueSet;
      10: invokevirtual #52                 // Method com/google/common/base/MoreObjects$ToStringHelper.add:(Ljava/lang/String;Ljava/lang/Object;)Lcom/google/common/base/MoreObjects$ToStringHelper;
      13: ldc           #58                 // String nullAllowed
      15: aload_0
      16: getfield      #23                 // Field nullAllowed:Z
      19: invokevirtual #59                 // Method com/google/common/base/MoreObjects$ToStringHelper.add:(Ljava/lang/String;Z)Lcom/google/common/base/MoreObjects$ToStringHelper;
      22: invokevirtual #62                 // Method com/google/common/base/MoreObjects$ToStringHelper.toString:()Ljava/lang/String;
      25: areturn

  public static io.trino.plugin.thrift.api.TrinoThriftDomain fromDomain(io.trino.spi.predicate.Domain);
    Code:
       0: new           #18                 // class io/trino/plugin/thrift/api/TrinoThriftDomain
       3: dup
       4: aload_0
       5: invokevirtual #66                 // Method io/trino/spi/predicate/Domain.getValues:()Lio/trino/spi/predicate/ValueSet;
       8: invokestatic  #72                 // Method io/trino/plugin/thrift/api/valuesets/TrinoThriftValueSet.fromValueSet:(Lio/trino/spi/predicate/ValueSet;)Lio/trino/plugin/thrift/api/valuesets/TrinoThriftValueSet;
      11: aload_0
      12: invokevirtual #76                 // Method io/trino/spi/predicate/Domain.isNullAllowed:()Z
      15: invokespecial #80                 // Method "<init>":(Lio/trino/plugin/thrift/api/valuesets/TrinoThriftValueSet;Z)V
      18: areturn
}
