Compiled from "LoaderConfiguration.java"
public class org.codehaus.groovy.tools.LoaderConfiguration {
  private static final java.lang.String MAIN_PREFIX;

  private static final java.lang.String LOAD_PREFIX;

  private static final java.lang.String GRAB_PREFIX;

  private static final java.lang.String PROP_PREFIX;

  private java.util.List<java.net.URL> classPath;

  private java.lang.String main;

  private boolean requireMain;

  private static final char WILDCARD;

  private static final java.lang.String ALL_WILDCARD;

  private static final java.lang.String MATCH_FILE_NAME;

  private static final java.lang.String MATCH_ALL;

  private final java.util.List<java.lang.String> grabList;

  public org.codehaus.groovy.tools.LoaderConfiguration();
    Code:
       0: aload_0
       1: invokespecial #42                 // Method java/lang/Object."<init>":()V
       4: aload_0
       5: new           #44                 // class java/util/ArrayList
       8: dup
       9: invokespecial #45                 // Method java/util/ArrayList."<init>":()V
      12: putfield      #47                 // Field classPath:Ljava/util/List;
      15: aload_0
      16: new           #44                 // class java/util/ArrayList
      19: dup
      20: invokespecial #45                 // Method java/util/ArrayList."<init>":()V
      23: putfield      #49                 // Field grabList:Ljava/util/List;
      26: aload_0
      27: iconst_1
      28: putfield      #51                 // Field requireMain:Z
      31: return

  public void configure(java.io.InputStream) throws java.io.IOException;
    Code:
       0: new           #59                 // class java/io/BufferedReader
       3: dup
       4: new           #61                 // class java/io/InputStreamReader
       7: dup
       8: aload_1
       9: invokespecial #63                 // Method java/io/InputStreamReader."<init>":(Ljava/io/InputStream;)V
      12: invokespecial #66                 // Method java/io/BufferedReader."<init>":(Ljava/io/Reader;)V
      15: astore_2
      16: iconst_0
      17: istore_3
      18: aload_2
      19: invokevirtual #70                 // Method java/io/BufferedReader.readLine:()Ljava/lang/String;
      22: astore        4
      24: aload         4
      26: ifnonnull     32
      29: goto          310
      32: aload         4
      34: invokevirtual #75                 // Method java/lang/String.trim:()Ljava/lang/String;
      37: astore        4
      39: iinc          3, 1
      42: aload         4
      44: ldc           #77                 // String #
      46: invokevirtual #81                 // Method java/lang/String.startsWith:(Ljava/lang/String;)Z
      49: ifne          18
      52: aload         4
      54: invokevirtual #85                 // Method java/lang/String.length:()I
      57: ifne          63
      60: goto          18
      63: aload         4
      65: ldc           #12                 // String load
      67: invokevirtual #81                 // Method java/lang/String.startsWith:(Ljava/lang/String;)Z
      70: ifeq          104
      73: aload         4
      75: ldc           #12                 // String load
      77: invokevirtual #85                 // Method java/lang/String.length:()I
      80: invokevirtual #89                 // Method java/lang/String.substring:(I)Ljava/lang/String;
      83: invokevirtual #75                 // Method java/lang/String.trim:()Ljava/lang/String;
      86: astore        5
      88: aload         5
      90: invokestatic  #93                 // Method assignProperties:(Ljava/lang/String;)Ljava/lang/String;
      93: astore        5
      95: aload_0
      96: aload         5
      98: invokespecial #97                 // Method loadFilteredPath:(Ljava/lang/String;)V
     101: goto          307
     104: aload         4
     106: ldc           #15                 // String grab
     108: invokevirtual #81                 // Method java/lang/String.startsWith:(Ljava/lang/String;)Z
     111: ifeq          147
     114: aload         4
     116: ldc           #15                 // String grab
     118: invokevirtual #85                 // Method java/lang/String.length:()I
     121: invokevirtual #89                 // Method java/lang/String.substring:(I)Ljava/lang/String;
     124: invokevirtual #75                 // Method java/lang/String.trim:()Ljava/lang/String;
     127: astore        5
     129: aload_0
     130: getfield      #49                 // Field grabList:Ljava/util/List;
     133: aload         5
     135: invokestatic  #93                 // Method assignProperties:(Ljava/lang/String;)Ljava/lang/String;
     138: invokeinterface #103,  2          // InterfaceMethod java/util/List.add:(Ljava/lang/Object;)Z
     143: pop
     144: goto          307
     147: aload         4
     149: ldc           #9                  // String main is
     151: invokevirtual #81                 // Method java/lang/String.startsWith:(Ljava/lang/String;)Z
     154: ifeq          221
     157: aload_0
     158: getfield      #105                // Field main:Ljava/lang/String;
     161: ifnull        201
     164: new           #57                 // class java/io/IOException
     167: dup
     168: new           #107                // class java/lang/StringBuilder
     171: dup
     172: invokespecial #108                // Method java/lang/StringBuilder."<init>":()V
     175: ldc           #110                // String duplicate definition of main in line
     177: invokevirtual #114                // Method java/lang/StringBuilder.append:(Ljava/lang/String;)Ljava/lang/StringBuilder;
     180: iload_3
     181: invokevirtual #117                // Method java/lang/StringBuilder.append:(I)Ljava/lang/StringBuilder;
     184: ldc           #119                // String  :
     186: invokevirtual #114                // Method java/lang/StringBuilder.append:(Ljava/lang/String;)Ljava/lang/StringBuilder;
     189: aload         4
     191: invokevirtual #114                // Method java/lang/StringBuilder.append:(Ljava/lang/String;)Ljava/lang/StringBuilder;
     194: invokevirtual #122                // Method java/lang/StringBuilder.toString:()Ljava/lang/String;
     197: invokespecial #124                // Method java/io/IOException."<init>":(Ljava/lang/String;)V
     200: athrow
     201: aload_0
     202: aload         4
     204: ldc           #9                  // String main is
     206: invokevirtual #85                 // Method java/lang/String.length:()I
     209: invokevirtual #89                 // Method java/lang/String.substring:(I)Ljava/lang/String;
     212: invokevirtual #75                 // Method java/lang/String.trim:()Ljava/lang/String;
     215: putfield      #105                // Field main:Ljava/lang/String;
     218: goto          307
     221: aload         4
     223: ldc           #18                 // String property
     225: invokevirtual #81                 // Method java/lang/String.startsWith:(Ljava/lang/String;)Z
     228: ifeq          270
     231: aload         4
     233: ldc           #18                 // String property
     235: invokevirtual #85                 // Method java/lang/String.length:()I
     238: invokevirtual #89                 // Method java/lang/String.substring:(I)Ljava/lang/String;
     241: invokevirtual #75                 // Method java/lang/String.trim:()Ljava/lang/String;
     244: astore        5
     246: aload         5
     248: invokestatic  #129                // Method org/apache/groovy/util/SystemUtil.setSystemPropertyFrom:(Ljava/lang/String;)Ljava/lang/String;
     251: astore        6
     253: aload         6
     255: aload         6
     257: invokestatic  #134                // Method java/lang/System.getProperty:(Ljava/lang/String;)Ljava/lang/String;
     260: invokestatic  #93                 // Method assignProperties:(Ljava/lang/String;)Ljava/lang/String;
     263: invokestatic  #138                // Method java/lang/System.setProperty:(Ljava/lang/String;Ljava/lang/String;)Ljava/lang/String;
     266: pop
     267: goto          307
     270: new           #57                 // class java/io/IOException
     273: dup
     274: new           #107                // class java/lang/StringBuilder
     277: dup
     278: invokespecial #108                // Method java/lang/StringBuilder."<init>":()V
     281: ldc           #140                // String unexpected line in
     283: invokevirtual #114                // Method java/lang/StringBuilder.append:(Ljava/lang/String;)Ljava/lang/StringBuilder;
     286: iload_3
     287: invokevirtual #117                // Method java/lang/StringBuilder.append:(I)Ljava/lang/StringBuilder;
     290: ldc           #119                // String  :
     292: invokevirtual #114                // Method java/lang/StringBuilder.append:(Ljava/lang/String;)Ljava/lang/StringBuilder;
     295: aload         4
     297: invokevirtual #114                // Method java/lang/StringBuilder.append:(Ljava/lang/String;)Ljava/lang/StringBuilder;
     300: invokevirtual #122                // Method java/lang/StringBuilder.toString:()Ljava/lang/String;
     303: invokespecial #124                // Method java/io/IOException."<init>":(Ljava/lang/String;)V
     306: athrow
     307: goto          18
     310: aload_2
     311: invokevirtual #143                // Method java/io/BufferedReader.close:()V
     314: goto          326
     317: astore        7
     319: aload_2
     320: invokevirtual #143                // Method java/io/BufferedReader.close:()V
     323: aload         7
     325: athrow
     326: aload_0
     327: getfield      #51                 // Field requireMain:Z
     330: ifeq          350
     333: aload_0
     334: getfield      #105                // Field main:Ljava/lang/String;
     337: ifnonnull     350
     340: new           #57                 // class java/io/IOException
     343: dup
     344: ldc           #147                // String missing main class definition in config file
     346: invokespecial #124                // Method java/io/IOException."<init>":(Ljava/lang/String;)V
     349: athrow
     350: return
    Exception table:
       from    to  target type
          16   310   317   any
         317   319   317   any

  private static java.lang.String assignProperties(java.lang.String);
    Code:
       0: iconst_0
       1: istore_1
       2: iconst_0
       3: istore_2
       4: new           #107                // class java/lang/StringBuilder
       7: dup
       8: invokespecial #108                // Method java/lang/StringBuilder."<init>":()V
      11: astore_3
      12: iload_1
      13: aload_0
      14: invokevirtual #85                 // Method java/lang/String.length:()I
      17: if_icmpge     221
      20: aload_0
      21: ldc           #160                // String ${
      23: iload_1
      24: invokevirtual #164                // Method java/lang/String.indexOf:(Ljava/lang/String;I)I
      27: istore        4
      29: aload_0
      30: ldc           #166                // String !{
      32: iload_1
      33: invokevirtual #164                // Method java/lang/String.indexOf:(Ljava/lang/String;I)I
      36: istore        5
      38: iload         4
      40: iconst_m1
      41: if_icmpne     50
      44: iload         5
      46: istore_1
      47: goto          70
      50: iload         5
      52: iconst_m1
      53: if_icmpne     62
      56: iload         4
      58: istore_1
      59: goto          70
      62: iload         4
      64: iload         5
      66: invokestatic  #172                // Method java/lang/Math.min:(II)I
      69: istore_1
      70: iload_1
      71: iload         5
      73: if_icmpne     80
      76: iconst_1
      77: goto          81
      80: iconst_0
      81: istore        6
      83: iload_1
      84: iconst_m1
      85: if_icmpne     91
      88: goto          221
      91: aload_3
      92: aload_0
      93: iload_2
      94: iload_1
      95: invokevirtual #175                // Method java/lang/String.substring:(II)Ljava/lang/String;
      98: invokevirtual #114                // Method java/lang/StringBuilder.append:(Ljava/lang/String;)Ljava/lang/StringBuilder;
     101: pop
     102: aload_0
     103: ldc           #177                // String }
     105: iload_1
     106: invokevirtual #164                // Method java/lang/String.indexOf:(Ljava/lang/String;I)I
     109: istore_2
     110: iload_2
     111: iconst_m1
     112: if_icmpne     118
     115: goto          221
     118: aload_0
     119: iload_1
     120: iconst_2
     121: iadd
     122: iload_2
     123: invokevirtual #175                // Method java/lang/String.substring:(II)Ljava/lang/String;
     126: astore        4
     128: aload         4
     130: invokestatic  #134                // Method java/lang/System.getProperty:(Ljava/lang/String;)Ljava/lang/String;
     133: astore        5
     135: aload         5
     137: ifnonnull     190
     140: iload         6
     142: ifeq          188
     145: new           #179                // class java/lang/IllegalArgumentException
     148: dup
     149: new           #107                // class java/lang/StringBuilder
     152: dup
     153: invokespecial #108                // Method java/lang/StringBuilder."<init>":()V
     156: ldc           #181                // String Variable
     158: invokevirtual #114                // Method java/lang/StringBuilder.append:(Ljava/lang/String;)Ljava/lang/StringBuilder;
     161: aload         4
     163: invokevirtual #114                // Method java/lang/StringBuilder.append:(Ljava/lang/String;)Ljava/lang/StringBuilder;
     166: ldc           #183                // String  in groovy-starter.conf references a non-existent System property! Try passing the property to the VM using -D
     168: invokevirtual #114                // Method java/lang/StringBuilder.append:(Ljava/lang/String;)Ljava/lang/StringBuilder;
     171: aload         4
     173: invokevirtual #114                // Method java/lang/StringBuilder.append:(Ljava/lang/String;)Ljava/lang/StringBuilder;
     176: ldc           #185                // String =myValue in JAVA_OPTS
     178: invokevirtual #114                // Method java/lang/StringBuilder.append:(Ljava/lang/String;)Ljava/lang/StringBuilder;
     181: invokevirtual #122                // Method java/lang/StringBuilder.toString:()Ljava/lang/String;
     184: invokespecial #186                // Method java/lang/IllegalArgumentException."<init>":(Ljava/lang/String;)V
     187: athrow
     188: aconst_null
     189: areturn
     190: aload         5
     192: invokestatic  #189                // Method getSlashyPath:(Ljava/lang/String;)Ljava/lang/String;
     195: astore        5
     197: aload         5
     199: iload_2
     200: aload_0
     201: invokestatic  #193                // Method correctDoubleSlash:(Ljava/lang/String;ILjava/lang/String;)Ljava/lang/String;
     204: astore        5
     206: aload_3
     207: aload         5
     209: invokevirtual #114                // Method java/lang/StringBuilder.append:(Ljava/lang/String;)Ljava/lang/StringBuilder;
     212: pop
     213: iinc          2, 1
     216: iload_2
     217: istore_1
     218: goto          12
     221: iload_1
     222: iconst_m1
     223: if_icmpeq     234
     226: iload_1
     227: aload_0
     228: invokevirtual #85                 // Method java/lang/String.length:()I
     231: if_icmplt     247
     234: aload_3
     235: aload_0
     236: iload_2
     237: invokevirtual #89                 // Method java/lang/String.substring:(I)Ljava/lang/String;
     240: invokevirtual #114                // Method java/lang/StringBuilder.append:(Ljava/lang/String;)Ljava/lang/StringBuilder;
     243: pop
     244: goto          262
     247: iload_2
     248: iconst_m1
     249: if_icmpne     262
     252: aload_3
     253: aload_0
     254: iload_1
     255: invokevirtual #89                 // Method java/lang/String.substring:(I)Ljava/lang/String;
     258: invokevirtual #114                // Method java/lang/StringBuilder.append:(Ljava/lang/String;)Ljava/lang/StringBuilder;
     261: pop
     262: aload_3
     263: invokevirtual #122                // Method java/lang/StringBuilder.toString:()Ljava/lang/String;
     266: areturn

  private static java.lang.String correctDoubleSlash(java.lang.String, int, java.lang.String);
    Code:
       0: iload_1
       1: iconst_1
       2: iadd
       3: istore_3
       4: iload_3
       5: aload_2
       6: invokevirtual #85                 // Method java/lang/String.length:()I
       9: if_icmpge     50
      12: aload_2
      13: iload_3
      14: invokevirtual #207                // Method java/lang/String.charAt:(I)C
      17: bipush        47
      19: if_icmpne     50
      22: aload_0
      23: ldc           #209                // String /
      25: invokevirtual #212                // Method java/lang/String.endsWith:(Ljava/lang/String;)Z
      28: ifeq          50
      31: aload_0
      32: invokevirtual #85                 // Method java/lang/String.length:()I
      35: ifle          50
      38: aload_0
      39: iconst_0
      40: aload_0
      41: invokevirtual #85                 // Method java/lang/String.length:()I
      44: iconst_1
      45: isub
      46: invokevirtual #175                // Method java/lang/String.substring:(II)Ljava/lang/String;
      49: astore_0
      50: aload_0
      51: areturn

  private void loadFilteredPath(java.lang.String);
    Code:
       0: aload_1
       1: ifnonnull     5
       4: return
       5: aload_1
       6: invokestatic  #189                // Method getSlashyPath:(Ljava/lang/String;)Ljava/lang/String;
       9: astore_1
      10: aload_1
      11: bipush        42
      13: invokevirtual #216                // Method java/lang/String.indexOf:(I)I
      16: istore_2
      17: iload_2
      18: iconst_m1
      19: if_icmpne     35
      22: aload_0
      23: new           #218                // class java/io/File
      26: dup
      27: aload_1
      28: invokespecial #219                // Method java/io/File."<init>":(Ljava/lang/String;)V
      31: invokevirtual #223                // Method addFile:(Ljava/io/File;)V
      34: return
      35: aload_1
      36: ldc           #30                 // String **
      38: invokevirtual #227                // Method java/lang/String.contains:(Ljava/lang/CharSequence;)Z
      41: istore_3
      42: aload_1
      43: bipush        47
      45: invokevirtual #230                // Method java/lang/String.lastIndexOf:(I)I
      48: iload_2
      49: if_icmpge     61
      52: aload_1
      53: bipush        47
      55: invokevirtual #230                // Method java/lang/String.lastIndexOf:(I)I
      58: iconst_1
      59: iadd
      60: istore_2
      61: aload_1
      62: iconst_0
      63: iload_2
      64: iconst_1
      65: isub
      66: invokevirtual #175                // Method java/lang/String.substring:(II)Ljava/lang/String;
      69: astore        4
      71: new           #218                // class java/io/File
      74: dup
      75: aload         4
      77: invokespecial #219                // Method java/io/File."<init>":(Ljava/lang/String;)V
      80: astore        5
      82: aload_1
      83: invokestatic  #235                // Method java/util/regex/Pattern.quote:(Ljava/lang/String;)Ljava/lang/String;
      86: astore_1
      87: aload_1
      88: ldc           #237                // String \\*\\*
      90: ldc           #36                 // String \\\\E.+?\\\\Q
      92: invokevirtual #240                // Method java/lang/String.replaceAll:(Ljava/lang/String;Ljava/lang/String;)Ljava/lang/String;
      95: astore_1
      96: aload_1
      97: ldc           #242                // String \\*
      99: ldc           #33                 // String \\\\E[^/]+?\\\\Q
     101: invokevirtual #240                // Method java/lang/String.replaceAll:(Ljava/lang/String;Ljava/lang/String;)Ljava/lang/String;
     104: astore_1
     105: aload_1
     106: invokestatic  #246                // Method java/util/regex/Pattern.compile:(Ljava/lang/String;)Ljava/util/regex/Pattern;
     109: astore        6
     111: aload         5
     113: invokevirtual #250                // Method java/io/File.listFiles:()[Ljava/io/File;
     116: astore        7
     118: aload         7
     120: ifnull        132
     123: aload_0
     124: aload         7
     126: aload         6
     128: iload_3
     129: invokespecial #254                // Method findMatchingFiles:([Ljava/io/File;Ljava/util/regex/Pattern;Z)V
     132: return

  private void findMatchingFiles(java.io.File[], java.util.regex.Pattern, boolean);
    Code:
       0: aload_1
       1: astore        4
       3: aload         4
       5: arraylength
       6: istore        5
       8: iconst_0
       9: istore        6
      11: iload         6
      13: iload         5
      15: if_icmpge     103
      18: aload         4
      20: iload         6
      22: aaload
      23: astore        7
      25: aload         7
      27: invokevirtual #268                // Method java/io/File.getPath:()Ljava/lang/String;
      30: invokestatic  #189                // Method getSlashyPath:(Ljava/lang/String;)Ljava/lang/String;
      33: astore        8
      35: aload_2
      36: aload         8
      38: invokevirtual #272                // Method java/util/regex/Pattern.matcher:(Ljava/lang/CharSequence;)Ljava/util/regex/Matcher;
      41: astore        9
      43: aload         9
      45: invokevirtual #278                // Method java/util/regex/Matcher.matches:()Z
      48: ifeq          65
      51: aload         7
      53: invokevirtual #281                // Method java/io/File.isFile:()Z
      56: ifeq          65
      59: aload_0
      60: aload         7
      62: invokevirtual #223                // Method addFile:(Ljava/io/File;)V
      65: aload         7
      67: invokevirtual #284                // Method java/io/File.isDirectory:()Z
      70: ifeq          97
      73: iload_3
      74: ifeq          97
      77: aload         7
      79: invokevirtual #250                // Method java/io/File.listFiles:()[Ljava/io/File;
      82: astore        10
      84: aload         10
      86: ifnull        97
      89: aload_0
      90: aload         10
      92: aload_2
      93: iconst_1
      94: invokespecial #254                // Method findMatchingFiles:([Ljava/io/File;Ljava/util/regex/Pattern;Z)V
      97: iinc          6, 1
     100: goto          11
     103: return

  private static java.lang.String getSlashyPath(java.lang.String);
    Code:
       0: aload_0
       1: astore_1
       2: getstatic     #292                // Field java/io/File.separatorChar:C
       5: bipush        47
       7: if_icmpeq     20
      10: aload_1
      11: getstatic     #292                // Field java/io/File.separatorChar:C
      14: bipush        47
      16: invokevirtual #296                // Method java/lang/String.replace:(CC)Ljava/lang/String;
      19: astore_1
      20: aload_1
      21: areturn

  public void addFile(java.io.File);
    Code:
       0: aload_1
       1: ifnull        43
       4: aload_1
       5: invokevirtual #303                // Method java/io/File.exists:()Z
       8: ifeq          43
      11: aload_0
      12: getfield      #47                 // Field classPath:Ljava/util/List;
      15: aload_1
      16: invokevirtual #307                // Method java/io/File.toURI:()Ljava/net/URI;
      19: invokevirtual #313                // Method java/net/URI.toURL:()Ljava/net/URL;
      22: invokeinterface #103,  2          // InterfaceMethod java/util/List.add:(Ljava/lang/Object;)Z
      27: pop
      28: goto          43
      31: astore_2
      32: new           #315                // class java/lang/AssertionError
      35: dup
      36: ldc_w         #317                // String converting an existing file to an url should have never thrown an exception!
      39: invokespecial #320                // Method java/lang/AssertionError."<init>":(Ljava/lang/Object;)V
      42: athrow
      43: return
    Exception table:
       from    to  target type
          11    28    31   Class java/net/MalformedURLException

  public void addFile(java.lang.String);
    Code:
       0: aload_1
       1: ifnull        16
       4: aload_0
       5: new           #218                // class java/io/File
       8: dup
       9: aload_1
      10: invokespecial #219                // Method java/io/File."<init>":(Ljava/lang/String;)V
      13: invokevirtual #223                // Method addFile:(Ljava/io/File;)V
      16: return

  public void addClassPath(java.lang.String);
    Code:
       0: aload_1
       1: getstatic     #327                // Field java/io/File.pathSeparator:Ljava/lang/String;
       4: invokevirtual #331                // Method java/lang/String.split:(Ljava/lang/String;)[Ljava/lang/String;
       7: astore_2
       8: aload_2
       9: astore_3
      10: aload_3
      11: arraylength
      12: istore        4
      14: iconst_0
      15: istore        5
      17: iload         5
      19: iload         4
      21: if_icmpge     157
      24: aload_3
      25: iload         5
      27: aaload
      28: astore        6
      30: aload         6
      32: ldc_w         #335                // String *
      35: invokevirtual #212                // Method java/lang/String.endsWith:(Ljava/lang/String;)Z
      38: ifeq          138
      41: new           #218                // class java/io/File
      44: dup
      45: aload         6
      47: iconst_0
      48: aload         6
      50: invokevirtual #85                 // Method java/lang/String.length:()I
      53: iconst_1
      54: isub
      55: invokevirtual #175                // Method java/lang/String.substring:(II)Ljava/lang/String;
      58: invokespecial #219                // Method java/io/File."<init>":(Ljava/lang/String;)V
      61: astore        7
      63: aload         7
      65: invokevirtual #250                // Method java/io/File.listFiles:()[Ljava/io/File;
      68: astore        8
      70: aload         8
      72: ifnull        135
      75: aload         8
      77: astore        9
      79: aload         9
      81: arraylength
      82: istore        10
      84: iconst_0
      85: istore        11
      87: iload         11
      89: iload         10
      91: if_icmpge     135
      94: aload         9
      96: iload         11
      98: aaload
      99: astore        12
     101: aload         12
     103: invokevirtual #281                // Method java/io/File.isFile:()Z
     106: ifeq          129
     109: aload         12
     111: invokevirtual #338                // Method java/io/File.getName:()Ljava/lang/String;
     114: ldc_w         #340                // String .jar
     117: invokevirtual #212                // Method java/lang/String.endsWith:(Ljava/lang/String;)Z
     120: ifeq          129
     123: aload_0
     124: aload         12
     126: invokevirtual #223                // Method addFile:(Ljava/io/File;)V
     129: iinc          11, 1
     132: goto          87
     135: goto          151
     138: aload_0
     139: new           #218                // class java/io/File
     142: dup
     143: aload         6
     145: invokespecial #219                // Method java/io/File."<init>":(Ljava/lang/String;)V
     148: invokevirtual #223                // Method addFile:(Ljava/io/File;)V
     151: iinc          5, 1
     154: goto          17
     157: return

  public java.net.URL[] getClassPathUrls();
    Code:
       0: aload_0
       1: getfield      #47                 // Field classPath:Ljava/util/List;
       4: aload_0
       5: getfield      #47                 // Field classPath:Ljava/util/List;
       8: invokeinterface #348,  1          // InterfaceMethod java/util/List.size:()I
      13: anewarray     #350                // class java/net/URL
      16: invokeinterface #354,  2          // InterfaceMethod java/util/List.toArray:([Ljava/lang/Object;)[Ljava/lang/Object;
      21: checkcast     #356                // class "[Ljava/net/URL;"
      24: areturn

  public java.util.List<java.lang.String> getGrabUrls();
    Code:
       0: aload_0
       1: getfield      #49                 // Field grabList:Ljava/util/List;
       4: areturn

  public java.lang.String getMainClass();
    Code:
       0: aload_0
       1: getfield      #105                // Field main:Ljava/lang/String;
       4: areturn

  public void setMainClass(java.lang.String);
    Code:
       0: aload_0
       1: aload_1
       2: putfield      #105                // Field main:Ljava/lang/String;
       5: aload_0
       6: iconst_0
       7: putfield      #51                 // Field requireMain:Z
      10: return

  public void setRequireMain(boolean);
    Code:
       0: aload_0
       1: iload_1
       2: putfield      #51                 // Field requireMain:Z
       5: return
}
