Compiled from "DbMigrate.java"
class org.flywaydb.core.internal.command.DbMigrate$2 implements org.flywaydb.core.internal.util.jdbc.TransactionCallback<java.lang.Boolean> {
  final boolean val$firstRun;

  final org.flywaydb.core.internal.command.DbMigrate this$0;

  org.flywaydb.core.internal.command.DbMigrate$2(org.flywaydb.core.internal.command.DbMigrate, boolean);
    Code:
       0: aload_0
       1: aload_1
       2: putfield      #1                  // Field this$0:Lorg/flywaydb/core/internal/command/DbMigrate;
       5: aload_0
       6: iload_2
       7: putfield      #2                  // Field val$firstRun:Z
      10: aload_0
      11: invokespecial #3                  // Method java/lang/Object."<init>":()V
      14: return

  public java.lang.Boolean doInTransaction();
    Code:
       0: aload_0
       1: getfield      #1                  // Field this$0:Lorg/flywaydb/core/internal/command/DbMigrate;
       4: invokestatic  #4                  // Method org/flywaydb/core/internal/command/DbMigrate.access$300:(Lorg/flywaydb/core/internal/command/DbMigrate;)Lorg/flywaydb/core/internal/metadatatable/MetaDataTable;
       7: invokeinterface #5,  1            // InterfaceMethod org/flywaydb/core/internal/metadatatable/MetaDataTable.lock:()V
      12: new           #6                  // class org/flywaydb/core/internal/info/MigrationInfoServiceImpl
      15: dup
      16: aload_0
      17: getfield      #1                  // Field this$0:Lorg/flywaydb/core/internal/command/DbMigrate;
      20: invokestatic  #7                  // Method org/flywaydb/core/internal/command/DbMigrate.access$400:(Lorg/flywaydb/core/internal/command/DbMigrate;)Lorg/flywaydb/core/api/resolver/MigrationResolver;
      23: aload_0
      24: getfield      #1                  // Field this$0:Lorg/flywaydb/core/internal/command/DbMigrate;
      27: invokestatic  #4                  // Method org/flywaydb/core/internal/command/DbMigrate.access$300:(Lorg/flywaydb/core/internal/command/DbMigrate;)Lorg/flywaydb/core/internal/metadatatable/MetaDataTable;
      30: aload_0
      31: getfield      #1                  // Field this$0:Lorg/flywaydb/core/internal/command/DbMigrate;
      34: invokestatic  #8                  // Method org/flywaydb/core/internal/command/DbMigrate.access$500:(Lorg/flywaydb/core/internal/command/DbMigrate;)Lorg/flywaydb/core/api/MigrationVersion;
      37: aload_0
      38: getfield      #1                  // Field this$0:Lorg/flywaydb/core/internal/command/DbMigrate;
      41: invokestatic  #9                  // Method org/flywaydb/core/internal/command/DbMigrate.access$600:(Lorg/flywaydb/core/internal/command/DbMigrate;)Z
      44: iconst_1
      45: iconst_1
      46: invokespecial #10                 // Method org/flywaydb/core/internal/info/MigrationInfoServiceImpl."<init>":(Lorg/flywaydb/core/api/resolver/MigrationResolver;Lorg/flywaydb/core/internal/metadatatable/MetaDataTable;Lorg/flywaydb/core/api/MigrationVersion;ZZZ)V
      49: astore_1
      50: aload_1
      51: invokevirtual #11                 // Method org/flywaydb/core/internal/info/MigrationInfoServiceImpl.refresh:()V
      54: getstatic     #12                 // Field org/flywaydb/core/api/MigrationVersion.EMPTY:Lorg/flywaydb/core/api/MigrationVersion;
      57: astore_2
      58: aload_1
      59: invokevirtual #13                 // Method org/flywaydb/core/internal/info/MigrationInfoServiceImpl.current:()Lorg/flywaydb/core/api/MigrationInfo;
      62: ifnull        75
      65: aload_1
      66: invokevirtual #13                 // Method org/flywaydb/core/internal/info/MigrationInfoServiceImpl.current:()Lorg/flywaydb/core/api/MigrationInfo;
      69: invokeinterface #14,  1           // InterfaceMethod org/flywaydb/core/api/MigrationInfo.getVersion:()Lorg/flywaydb/core/api/MigrationVersion;
      74: astore_2
      75: aload_0
      76: getfield      #2                  // Field val$firstRun:Z
      79: ifeq          172
      82: invokestatic  #15                 // Method org/flywaydb/core/internal/command/DbMigrate.access$700:()Lorg/flywaydb/core/internal/util/logging/Log;
      85: new           #16                 // class java/lang/StringBuilder
      88: dup
      89: invokespecial #17                 // Method java/lang/StringBuilder."<init>":()V
      92: ldc           #18                 // String Current version of schema
      94: invokevirtual #19                 // Method java/lang/StringBuilder.append:(Ljava/lang/String;)Ljava/lang/StringBuilder;
      97: aload_0
      98: getfield      #1                  // Field this$0:Lorg/flywaydb/core/internal/command/DbMigrate;
     101: invokestatic  #20                 // Method org/flywaydb/core/internal/command/DbMigrate.access$000:(Lorg/flywaydb/core/internal/command/DbMigrate;)Lorg/flywaydb/core/internal/dbsupport/Schema;
     104: invokevirtual #21                 // Method java/lang/StringBuilder.append:(Ljava/lang/Object;)Ljava/lang/StringBuilder;
     107: ldc           #22                 // String :
     109: invokevirtual #19                 // Method java/lang/StringBuilder.append:(Ljava/lang/String;)Ljava/lang/StringBuilder;
     112: aload_2
     113: invokevirtual #21                 // Method java/lang/StringBuilder.append:(Ljava/lang/Object;)Ljava/lang/StringBuilder;
     116: invokevirtual #23                 // Method java/lang/StringBuilder.toString:()Ljava/lang/String;
     119: invokeinterface #24,  2           // InterfaceMethod org/flywaydb/core/internal/util/logging/Log.info:(Ljava/lang/String;)V
     124: aload_0
     125: getfield      #1                  // Field this$0:Lorg/flywaydb/core/internal/command/DbMigrate;
     128: invokestatic  #9                  // Method org/flywaydb/core/internal/command/DbMigrate.access$600:(Lorg/flywaydb/core/internal/command/DbMigrate;)Z
     131: ifeq          172
     134: invokestatic  #15                 // Method org/flywaydb/core/internal/command/DbMigrate.access$700:()Lorg/flywaydb/core/internal/util/logging/Log;
     137: new           #16                 // class java/lang/StringBuilder
     140: dup
     141: invokespecial #17                 // Method java/lang/StringBuilder."<init>":()V
     144: ldc           #25                 // String outOfOrder mode is active. Migration of schema
     146: invokevirtual #19                 // Method java/lang/StringBuilder.append:(Ljava/lang/String;)Ljava/lang/StringBuilder;
     149: aload_0
     150: getfield      #1                  // Field this$0:Lorg/flywaydb/core/internal/command/DbMigrate;
     153: invokestatic  #20                 // Method org/flywaydb/core/internal/command/DbMigrate.access$000:(Lorg/flywaydb/core/internal/command/DbMigrate;)Lorg/flywaydb/core/internal/dbsupport/Schema;
     156: invokevirtual #21                 // Method java/lang/StringBuilder.append:(Ljava/lang/Object;)Ljava/lang/StringBuilder;
     159: ldc           #26                 // String  may not be reproducible.
     161: invokevirtual #19                 // Method java/lang/StringBuilder.append:(Ljava/lang/String;)Ljava/lang/StringBuilder;
     164: invokevirtual #23                 // Method java/lang/StringBuilder.toString:()Ljava/lang/String;
     167: invokeinterface #27,  2           // InterfaceMethod org/flywaydb/core/internal/util/logging/Log.warn:(Ljava/lang/String;)V
     172: aload_1
     173: invokevirtual #28                 // Method org/flywaydb/core/internal/info/MigrationInfoServiceImpl.future:()[Lorg/flywaydb/core/api/MigrationInfo;
     176: astore_3
     177: aload_3
     178: arraylength
     179: ifle          335
     182: aload_1
     183: invokevirtual #29                 // Method org/flywaydb/core/internal/info/MigrationInfoServiceImpl.resolved:()[Lorg/flywaydb/core/api/MigrationInfo;
     186: astore        4
     188: aload         4
     190: arraylength
     191: ifne          244
     194: invokestatic  #15                 // Method org/flywaydb/core/internal/command/DbMigrate.access$700:()Lorg/flywaydb/core/internal/util/logging/Log;
     197: new           #16                 // class java/lang/StringBuilder
     200: dup
     201: invokespecial #17                 // Method java/lang/StringBuilder."<init>":()V
     204: ldc           #30                 // String Schema
     206: invokevirtual #19                 // Method java/lang/StringBuilder.append:(Ljava/lang/String;)Ljava/lang/StringBuilder;
     209: aload_0
     210: getfield      #1                  // Field this$0:Lorg/flywaydb/core/internal/command/DbMigrate;
     213: invokestatic  #20                 // Method org/flywaydb/core/internal/command/DbMigrate.access$000:(Lorg/flywaydb/core/internal/command/DbMigrate;)Lorg/flywaydb/core/internal/dbsupport/Schema;
     216: invokevirtual #21                 // Method java/lang/StringBuilder.append:(Ljava/lang/Object;)Ljava/lang/StringBuilder;
     219: ldc           #31                 // String  has version
     221: invokevirtual #19                 // Method java/lang/StringBuilder.append:(Ljava/lang/String;)Ljava/lang/StringBuilder;
     224: aload_2
     225: invokevirtual #21                 // Method java/lang/StringBuilder.append:(Ljava/lang/Object;)Ljava/lang/StringBuilder;
     228: ldc           #32                 // String , but no migration could be resolved in the configured locations !
     230: invokevirtual #19                 // Method java/lang/StringBuilder.append:(Ljava/lang/String;)Ljava/lang/StringBuilder;
     233: invokevirtual #23                 // Method java/lang/StringBuilder.toString:()Ljava/lang/String;
     236: invokeinterface #27,  2           // InterfaceMethod org/flywaydb/core/internal/util/logging/Log.warn:(Ljava/lang/String;)V
     241: goto          335
     244: aload         4
     246: arraylength
     247: iconst_1
     248: isub
     249: istore        5
     251: aload         4
     253: iload         5
     255: aaload
     256: invokeinterface #14,  1           // InterfaceMethod org/flywaydb/core/api/MigrationInfo.getVersion:()Lorg/flywaydb/core/api/MigrationVersion;
     261: ifnonnull     270
     264: iinc          5, -1
     267: goto          251
     270: invokestatic  #15                 // Method org/flywaydb/core/internal/command/DbMigrate.access$700:()Lorg/flywaydb/core/internal/util/logging/Log;
     273: new           #16                 // class java/lang/StringBuilder
     276: dup
     277: invokespecial #17                 // Method java/lang/StringBuilder."<init>":()V
     280: ldc           #30                 // String Schema
     282: invokevirtual #19                 // Method java/lang/StringBuilder.append:(Ljava/lang/String;)Ljava/lang/StringBuilder;
     285: aload_0
     286: getfield      #1                  // Field this$0:Lorg/flywaydb/core/internal/command/DbMigrate;
     289: invokestatic  #20                 // Method org/flywaydb/core/internal/command/DbMigrate.access$000:(Lorg/flywaydb/core/internal/command/DbMigrate;)Lorg/flywaydb/core/internal/dbsupport/Schema;
     292: invokevirtual #21                 // Method java/lang/StringBuilder.append:(Ljava/lang/Object;)Ljava/lang/StringBuilder;
     295: ldc           #33                 // String  has a version (
     297: invokevirtual #19                 // Method java/lang/StringBuilder.append:(Ljava/lang/String;)Ljava/lang/StringBuilder;
     300: aload_2
     301: invokevirtual #21                 // Method java/lang/StringBuilder.append:(Ljava/lang/Object;)Ljava/lang/StringBuilder;
     304: ldc           #34                 // String ) that is newer than the latest available migration (
     306: invokevirtual #19                 // Method java/lang/StringBuilder.append:(Ljava/lang/String;)Ljava/lang/StringBuilder;
     309: aload         4
     311: iload         5
     313: aaload
     314: invokeinterface #14,  1           // InterfaceMethod org/flywaydb/core/api/MigrationInfo.getVersion:()Lorg/flywaydb/core/api/MigrationVersion;
     319: invokevirtual #21                 // Method java/lang/StringBuilder.append:(Ljava/lang/Object;)Ljava/lang/StringBuilder;
     322: ldc           #35                 // String ) !
     324: invokevirtual #19                 // Method java/lang/StringBuilder.append:(Ljava/lang/String;)Ljava/lang/StringBuilder;
     327: invokevirtual #23                 // Method java/lang/StringBuilder.toString:()Ljava/lang/String;
     330: invokeinterface #27,  2           // InterfaceMethod org/flywaydb/core/internal/util/logging/Log.warn:(Ljava/lang/String;)V
     335: aload_1
     336: invokevirtual #36                 // Method org/flywaydb/core/internal/info/MigrationInfoServiceImpl.failed:()[Lorg/flywaydb/core/api/MigrationInfo;
     339: astore        4
     341: aload         4
     343: arraylength
     344: ifle          502
     347: aload         4
     349: arraylength
     350: iconst_1
     351: if_icmpne     447
     354: aload         4
     356: iconst_0
     357: aaload
     358: invokeinterface #37,  1           // InterfaceMethod org/flywaydb/core/api/MigrationInfo.getState:()Lorg/flywaydb/core/api/MigrationState;
     363: getstatic     #38                 // Field org/flywaydb/core/api/MigrationState.FUTURE_FAILED:Lorg/flywaydb/core/api/MigrationState;
     366: if_acmpne     447
     369: aload_0
     370: getfield      #1                  // Field this$0:Lorg/flywaydb/core/internal/command/DbMigrate;
     373: invokestatic  #39                 // Method org/flywaydb/core/internal/command/DbMigrate.access$800:(Lorg/flywaydb/core/internal/command/DbMigrate;)Z
     376: ifne          389
     379: aload_0
     380: getfield      #1                  // Field this$0:Lorg/flywaydb/core/internal/command/DbMigrate;
     383: invokestatic  #40                 // Method org/flywaydb/core/internal/command/DbMigrate.access$900:(Lorg/flywaydb/core/internal/command/DbMigrate;)Z
     386: ifeq          447
     389: invokestatic  #15                 // Method org/flywaydb/core/internal/command/DbMigrate.access$700:()Lorg/flywaydb/core/internal/util/logging/Log;
     392: new           #16                 // class java/lang/StringBuilder
     395: dup
     396: invokespecial #17                 // Method java/lang/StringBuilder."<init>":()V
     399: ldc           #30                 // String Schema
     401: invokevirtual #19                 // Method java/lang/StringBuilder.append:(Ljava/lang/String;)Ljava/lang/StringBuilder;
     404: aload_0
     405: getfield      #1                  // Field this$0:Lorg/flywaydb/core/internal/command/DbMigrate;
     408: invokestatic  #20                 // Method org/flywaydb/core/internal/command/DbMigrate.access$000:(Lorg/flywaydb/core/internal/command/DbMigrate;)Lorg/flywaydb/core/internal/dbsupport/Schema;
     411: invokevirtual #21                 // Method java/lang/StringBuilder.append:(Ljava/lang/Object;)Ljava/lang/StringBuilder;
     414: ldc           #41                 // String  contains a failed future migration to version
     416: invokevirtual #19                 // Method java/lang/StringBuilder.append:(Ljava/lang/String;)Ljava/lang/StringBuilder;
     419: aload         4
     421: iconst_0
     422: aaload
     423: invokeinterface #14,  1           // InterfaceMethod org/flywaydb/core/api/MigrationInfo.getVersion:()Lorg/flywaydb/core/api/MigrationVersion;
     428: invokevirtual #21                 // Method java/lang/StringBuilder.append:(Ljava/lang/Object;)Ljava/lang/StringBuilder;
     431: ldc           #42                 // String  !
     433: invokevirtual #19                 // Method java/lang/StringBuilder.append:(Ljava/lang/String;)Ljava/lang/StringBuilder;
     436: invokevirtual #23                 // Method java/lang/StringBuilder.toString:()Ljava/lang/String;
     439: invokeinterface #27,  2           // InterfaceMethod org/flywaydb/core/internal/util/logging/Log.warn:(Ljava/lang/String;)V
     444: goto          502
     447: new           #43                 // class org/flywaydb/core/api/FlywayException
     450: dup
     451: new           #16                 // class java/lang/StringBuilder
     454: dup
     455: invokespecial #17                 // Method java/lang/StringBuilder."<init>":()V
     458: ldc           #30                 // String Schema
     460: invokevirtual #19                 // Method java/lang/StringBuilder.append:(Ljava/lang/String;)Ljava/lang/StringBuilder;
     463: aload_0
     464: getfield      #1                  // Field this$0:Lorg/flywaydb/core/internal/command/DbMigrate;
     467: invokestatic  #20                 // Method org/flywaydb/core/internal/command/DbMigrate.access$000:(Lorg/flywaydb/core/internal/command/DbMigrate;)Lorg/flywaydb/core/internal/dbsupport/Schema;
     470: invokevirtual #21                 // Method java/lang/StringBuilder.append:(Ljava/lang/Object;)Ljava/lang/StringBuilder;
     473: ldc           #44                 // String  contains a failed migration to version
     475: invokevirtual #19                 // Method java/lang/StringBuilder.append:(Ljava/lang/String;)Ljava/lang/StringBuilder;
     478: aload         4
     480: iconst_0
     481: aaload
     482: invokeinterface #14,  1           // InterfaceMethod org/flywaydb/core/api/MigrationInfo.getVersion:()Lorg/flywaydb/core/api/MigrationVersion;
     487: invokevirtual #21                 // Method java/lang/StringBuilder.append:(Ljava/lang/Object;)Ljava/lang/StringBuilder;
     490: ldc           #42                 // String  !
     492: invokevirtual #19                 // Method java/lang/StringBuilder.append:(Ljava/lang/String;)Ljava/lang/StringBuilder;
     495: invokevirtual #23                 // Method java/lang/StringBuilder.toString:()Ljava/lang/String;
     498: invokespecial #45                 // Method org/flywaydb/core/api/FlywayException."<init>":(Ljava/lang/String;)V
     501: athrow
     502: aload_1
     503: invokevirtual #46                 // Method org/flywaydb/core/internal/info/MigrationInfoServiceImpl.pending:()[Lorg/flywaydb/core/internal/info/MigrationInfoImpl;
     506: astore        5
     508: aload         5
     510: arraylength
     511: ifne          519
     514: iconst_1
     515: invokestatic  #47                 // Method java/lang/Boolean.valueOf:(Z)Ljava/lang/Boolean;
     518: areturn
     519: aload         5
     521: iconst_0
     522: aaload
     523: invokevirtual #48                 // Method org/flywaydb/core/internal/info/MigrationInfoImpl.getVersion:()Lorg/flywaydb/core/api/MigrationVersion;
     526: ifnull        547
     529: aload         5
     531: iconst_0
     532: aaload
     533: invokevirtual #48                 // Method org/flywaydb/core/internal/info/MigrationInfoImpl.getVersion:()Lorg/flywaydb/core/api/MigrationVersion;
     536: aload_2
     537: invokevirtual #49                 // Method org/flywaydb/core/api/MigrationVersion.compareTo:(Lorg/flywaydb/core/api/MigrationVersion;)I
     540: ifge          547
     543: iconst_1
     544: goto          548
     547: iconst_0
     548: istore        6
     550: aload_0
     551: getfield      #1                  // Field this$0:Lorg/flywaydb/core/internal/command/DbMigrate;
     554: aload         5
     556: iconst_0
     557: aaload
     558: iload         6
     560: invokestatic  #50                 // Method org/flywaydb/core/internal/command/DbMigrate.access$1000:(Lorg/flywaydb/core/internal/command/DbMigrate;Lorg/flywaydb/core/internal/info/MigrationInfoImpl;Z)Ljava/lang/Boolean;
     563: areturn

  public java.lang.Object doInTransaction() throws java.sql.SQLException;
    Code:
       0: aload_0
       1: invokevirtual #51                 // Method doInTransaction:()Ljava/lang/Boolean;
       4: areturn
}
