Compiled from "InterProcessMutex.java"
public class org.apache.curator.framework.recipes.locks.InterProcessMutex implements org.apache.curator.framework.recipes.locks.InterProcessLock, org.apache.curator.framework.recipes.locks.Revocable<org.apache.curator.framework.recipes.locks.InterProcessMutex> {
  private final org.apache.curator.framework.recipes.locks.LockInternals internals;

  private final java.lang.String basePath;

  private final java.util.concurrent.ConcurrentMap<java.lang.Thread, org.apache.curator.framework.recipes.locks.InterProcessMutex$LockData> threadData;

  private static final java.lang.String LOCK_NAME;

  public org.apache.curator.framework.recipes.locks.InterProcessMutex(org.apache.curator.framework.CuratorFramework, java.lang.String);
    Code:
       0: aload_0
       1: aload_1
       2: aload_2
       3: new           #29                 // class org/apache/curator/framework/recipes/locks/StandardLockInternalsDriver
       6: dup
       7: invokespecial #32                 // Method org/apache/curator/framework/recipes/locks/StandardLockInternalsDriver."<init>":()V
      10: invokespecial #35                 // Method "<init>":(Lorg/apache/curator/framework/CuratorFramework;Ljava/lang/String;Lorg/apache/curator/framework/recipes/locks/LockInternalsDriver;)V
      13: return

  public org.apache.curator.framework.recipes.locks.InterProcessMutex(org.apache.curator.framework.CuratorFramework, java.lang.String, org.apache.curator.framework.recipes.locks.LockInternalsDriver);
    Code:
       0: aload_0
       1: aload_1
       2: aload_2
       3: ldc           #25                 // String lock-
       5: iconst_1
       6: aload_3
       7: invokespecial #43                 // Method "<init>":(Lorg/apache/curator/framework/CuratorFramework;Ljava/lang/String;Ljava/lang/String;ILorg/apache/curator/framework/recipes/locks/LockInternalsDriver;)V
      10: return

  public void acquire() throws java.lang.Exception;
    Code:
       0: aload_0
       1: ldc2_w        #49                 // long -1l
       4: aconst_null
       5: invokespecial #54                 // Method internalLock:(JLjava/util/concurrent/TimeUnit;)Z
       8: ifne          41
      11: new           #56                 // class java/io/IOException
      14: dup
      15: new           #58                 // class java/lang/StringBuilder
      18: dup
      19: invokespecial #59                 // Method java/lang/StringBuilder."<init>":()V
      22: ldc           #61                 // String Lost connection while trying to acquire lock:
      24: invokevirtual #65                 // Method java/lang/StringBuilder.append:(Ljava/lang/String;)Ljava/lang/StringBuilder;
      27: aload_0
      28: getfield      #67                 // Field basePath:Ljava/lang/String;
      31: invokevirtual #65                 // Method java/lang/StringBuilder.append:(Ljava/lang/String;)Ljava/lang/StringBuilder;
      34: invokevirtual #71                 // Method java/lang/StringBuilder.toString:()Ljava/lang/String;
      37: invokespecial #74                 // Method java/io/IOException."<init>":(Ljava/lang/String;)V
      40: athrow
      41: return

  public boolean acquire(long, java.util.concurrent.TimeUnit) throws java.lang.Exception;
    Code:
       0: aload_0
       1: lload_1
       2: aload_3
       3: invokespecial #54                 // Method internalLock:(JLjava/util/concurrent/TimeUnit;)Z
       6: ireturn

  public boolean isAcquiredInThisProcess();
    Code:
       0: aload_0
       1: getfield      #82                 // Field threadData:Ljava/util/concurrent/ConcurrentMap;
       4: invokeinterface #88,  1           // InterfaceMethod java/util/concurrent/ConcurrentMap.size:()I
       9: ifle          16
      12: iconst_1
      13: goto          17
      16: iconst_0
      17: ireturn

  public void release() throws java.lang.Exception;
    Code:
       0: invokestatic  #95                 // Method java/lang/Thread.currentThread:()Ljava/lang/Thread;
       3: astore_1
       4: aload_0
       5: getfield      #82                 // Field threadData:Ljava/util/concurrent/ConcurrentMap;
       8: aload_1
       9: invokeinterface #99,  2           // InterfaceMethod java/util/concurrent/ConcurrentMap.get:(Ljava/lang/Object;)Ljava/lang/Object;
      14: checkcast     #12                 // class org/apache/curator/framework/recipes/locks/InterProcessMutex$LockData
      17: astore_2
      18: aload_2
      19: ifnonnull     52
      22: new           #101                // class java/lang/IllegalMonitorStateException
      25: dup
      26: new           #58                 // class java/lang/StringBuilder
      29: dup
      30: invokespecial #59                 // Method java/lang/StringBuilder."<init>":()V
      33: ldc           #103                // String You do not own the lock:
      35: invokevirtual #65                 // Method java/lang/StringBuilder.append:(Ljava/lang/String;)Ljava/lang/StringBuilder;
      38: aload_0
      39: getfield      #67                 // Field basePath:Ljava/lang/String;
      42: invokevirtual #65                 // Method java/lang/StringBuilder.append:(Ljava/lang/String;)Ljava/lang/StringBuilder;
      45: invokevirtual #71                 // Method java/lang/StringBuilder.toString:()Ljava/lang/String;
      48: invokespecial #104                // Method java/lang/IllegalMonitorStateException."<init>":(Ljava/lang/String;)V
      51: athrow
      52: aload_2
      53: getfield      #108                // Field org/apache/curator/framework/recipes/locks/InterProcessMutex$LockData.lockCount:Ljava/util/concurrent/atomic/AtomicInteger;
      56: invokevirtual #113                // Method java/util/concurrent/atomic/AtomicInteger.decrementAndGet:()I
      59: istore_3
      60: iload_3
      61: ifle          65
      64: return
      65: iload_3
      66: ifge          99
      69: new           #101                // class java/lang/IllegalMonitorStateException
      72: dup
      73: new           #58                 // class java/lang/StringBuilder
      76: dup
      77: invokespecial #59                 // Method java/lang/StringBuilder."<init>":()V
      80: ldc           #115                // String Lock count has gone negative for lock:
      82: invokevirtual #65                 // Method java/lang/StringBuilder.append:(Ljava/lang/String;)Ljava/lang/StringBuilder;
      85: aload_0
      86: getfield      #67                 // Field basePath:Ljava/lang/String;
      89: invokevirtual #65                 // Method java/lang/StringBuilder.append:(Ljava/lang/String;)Ljava/lang/StringBuilder;
      92: invokevirtual #71                 // Method java/lang/StringBuilder.toString:()Ljava/lang/String;
      95: invokespecial #104                // Method java/lang/IllegalMonitorStateException."<init>":(Ljava/lang/String;)V
      98: athrow
      99: aload_0
     100: getfield      #117                // Field internals:Lorg/apache/curator/framework/recipes/locks/LockInternals;
     103: aload_2
     104: getfield      #120                // Field org/apache/curator/framework/recipes/locks/InterProcessMutex$LockData.lockPath:Ljava/lang/String;
     107: invokevirtual #125                // Method org/apache/curator/framework/recipes/locks/LockInternals.releaseLock:(Ljava/lang/String;)V
     110: aload_0
     111: getfield      #82                 // Field threadData:Ljava/util/concurrent/ConcurrentMap;
     114: aload_1
     115: invokeinterface #128,  2          // InterfaceMethod java/util/concurrent/ConcurrentMap.remove:(Ljava/lang/Object;)Ljava/lang/Object;
     120: pop
     121: goto          140
     124: astore        4
     126: aload_0
     127: getfield      #82                 // Field threadData:Ljava/util/concurrent/ConcurrentMap;
     130: aload_1
     131: invokeinterface #128,  2          // InterfaceMethod java/util/concurrent/ConcurrentMap.remove:(Ljava/lang/Object;)Ljava/lang/Object;
     136: pop
     137: aload         4
     139: athrow
     140: return
    Exception table:
       from    to  target type
          99   110   124   any
         124   126   124   any

  public java.util.Collection<java.lang.String> getParticipantNodes() throws java.lang.Exception;
    Code:
       0: aload_0
       1: getfield      #117                // Field internals:Lorg/apache/curator/framework/recipes/locks/LockInternals;
       4: invokevirtual #142                // Method org/apache/curator/framework/recipes/locks/LockInternals.getClient:()Lorg/apache/curator/framework/CuratorFramework;
       7: aload_0
       8: getfield      #67                 // Field basePath:Ljava/lang/String;
      11: aload_0
      12: getfield      #117                // Field internals:Lorg/apache/curator/framework/recipes/locks/LockInternals;
      15: invokevirtual #145                // Method org/apache/curator/framework/recipes/locks/LockInternals.getLockName:()Ljava/lang/String;
      18: aload_0
      19: getfield      #117                // Field internals:Lorg/apache/curator/framework/recipes/locks/LockInternals;
      22: invokevirtual #149                // Method org/apache/curator/framework/recipes/locks/LockInternals.getDriver:()Lorg/apache/curator/framework/recipes/locks/LockInternalsDriver;
      25: invokestatic  #152                // Method org/apache/curator/framework/recipes/locks/LockInternals.getParticipantNodes:(Lorg/apache/curator/framework/CuratorFramework;Ljava/lang/String;Ljava/lang/String;Lorg/apache/curator/framework/recipes/locks/LockInternalsSorter;)Ljava/util/Collection;
      28: areturn

  public void makeRevocable(org.apache.curator.framework.recipes.locks.RevocationListener<org.apache.curator.framework.recipes.locks.InterProcessMutex>);
    Code:
       0: aload_0
       1: aload_1
       2: invokestatic  #161                // Method org/apache/curator/shaded/com/google/common/util/concurrent/MoreExecutors.directExecutor:()Ljava/util/concurrent/Executor;
       5: invokevirtual #164                // Method makeRevocable:(Lorg/apache/curator/framework/recipes/locks/RevocationListener;Ljava/util/concurrent/Executor;)V
       8: return

  public void makeRevocable(org.apache.curator.framework.recipes.locks.RevocationListener<org.apache.curator.framework.recipes.locks.InterProcessMutex>, java.util.concurrent.Executor);
    Code:
       0: aload_0
       1: getfield      #117                // Field internals:Lorg/apache/curator/framework/recipes/locks/LockInternals;
       4: new           #170                // class org/apache/curator/framework/recipes/locks/RevocationSpec
       7: dup
       8: aload_2
       9: new           #15                 // class org/apache/curator/framework/recipes/locks/InterProcessMutex$1
      12: dup
      13: aload_0
      14: aload_1
      15: invokespecial #173                // Method org/apache/curator/framework/recipes/locks/InterProcessMutex$1."<init>":(Lorg/apache/curator/framework/recipes/locks/InterProcessMutex;Lorg/apache/curator/framework/recipes/locks/RevocationListener;)V
      18: invokespecial #176                // Method org/apache/curator/framework/recipes/locks/RevocationSpec."<init>":(Ljava/util/concurrent/Executor;Ljava/lang/Runnable;)V
      21: invokevirtual #179                // Method org/apache/curator/framework/recipes/locks/LockInternals.makeRevocable:(Lorg/apache/curator/framework/recipes/locks/RevocationSpec;)V
      24: return

  org.apache.curator.framework.recipes.locks.InterProcessMutex(org.apache.curator.framework.CuratorFramework, java.lang.String, java.lang.String, int, org.apache.curator.framework.recipes.locks.LockInternalsDriver);
    Code:
       0: aload_0
       1: invokespecial #182                // Method java/lang/Object."<init>":()V
       4: aload_0
       5: invokestatic  #188                // Method org/apache/curator/shaded/com/google/common/collect/Maps.newConcurrentMap:()Ljava/util/concurrent/ConcurrentMap;
       8: putfield      #82                 // Field threadData:Ljava/util/concurrent/ConcurrentMap;
      11: aload_0
      12: aload_2
      13: invokestatic  #194                // Method org/apache/curator/utils/PathUtils.validatePath:(Ljava/lang/String;)Ljava/lang/String;
      16: putfield      #67                 // Field basePath:Ljava/lang/String;
      19: aload_0
      20: new           #122                // class org/apache/curator/framework/recipes/locks/LockInternals
      23: dup
      24: aload_1
      25: aload         5
      27: aload_2
      28: aload_3
      29: iload         4
      31: invokespecial #197                // Method org/apache/curator/framework/recipes/locks/LockInternals."<init>":(Lorg/apache/curator/framework/CuratorFramework;Lorg/apache/curator/framework/recipes/locks/LockInternalsDriver;Ljava/lang/String;Ljava/lang/String;I)V
      34: putfield      #117                // Field internals:Lorg/apache/curator/framework/recipes/locks/LockInternals;
      37: return

  public boolean isOwnedByCurrentThread();
    Code:
       0: aload_0
       1: getfield      #82                 // Field threadData:Ljava/util/concurrent/ConcurrentMap;
       4: invokestatic  #95                 // Method java/lang/Thread.currentThread:()Ljava/lang/Thread;
       7: invokeinterface #99,  2           // InterfaceMethod java/util/concurrent/ConcurrentMap.get:(Ljava/lang/Object;)Ljava/lang/Object;
      12: checkcast     #12                 // class org/apache/curator/framework/recipes/locks/InterProcessMutex$LockData
      15: astore_1
      16: aload_1
      17: ifnull        34
      20: aload_1
      21: getfield      #108                // Field org/apache/curator/framework/recipes/locks/InterProcessMutex$LockData.lockCount:Ljava/util/concurrent/atomic/AtomicInteger;
      24: invokevirtual #202                // Method java/util/concurrent/atomic/AtomicInteger.get:()I
      27: ifle          34
      30: iconst_1
      31: goto          35
      34: iconst_0
      35: ireturn

  protected byte[] getLockNodeBytes();
    Code:
       0: aconst_null
       1: areturn

  protected java.lang.String getLockPath();
    Code:
       0: aload_0
       1: getfield      #82                 // Field threadData:Ljava/util/concurrent/ConcurrentMap;
       4: invokestatic  #95                 // Method java/lang/Thread.currentThread:()Ljava/lang/Thread;
       7: invokeinterface #99,  2           // InterfaceMethod java/util/concurrent/ConcurrentMap.get:(Ljava/lang/Object;)Ljava/lang/Object;
      12: checkcast     #12                 // class org/apache/curator/framework/recipes/locks/InterProcessMutex$LockData
      15: astore_1
      16: aload_1
      17: ifnull        27
      20: aload_1
      21: getfield      #120                // Field org/apache/curator/framework/recipes/locks/InterProcessMutex$LockData.lockPath:Ljava/lang/String;
      24: goto          28
      27: aconst_null
      28: areturn

  private boolean internalLock(long, java.util.concurrent.TimeUnit) throws java.lang.Exception;
    Code:
       0: invokestatic  #95                 // Method java/lang/Thread.currentThread:()Ljava/lang/Thread;
       3: astore        4
       5: aload_0
       6: getfield      #82                 // Field threadData:Ljava/util/concurrent/ConcurrentMap;
       9: aload         4
      11: invokeinterface #99,  2           // InterfaceMethod java/util/concurrent/ConcurrentMap.get:(Ljava/lang/Object;)Ljava/lang/Object;
      16: checkcast     #12                 // class org/apache/curator/framework/recipes/locks/InterProcessMutex$LockData
      19: astore        5
      21: aload         5
      23: ifnull        37
      26: aload         5
      28: getfield      #108                // Field org/apache/curator/framework/recipes/locks/InterProcessMutex$LockData.lockCount:Ljava/util/concurrent/atomic/AtomicInteger;
      31: invokevirtual #210                // Method java/util/concurrent/atomic/AtomicInteger.incrementAndGet:()I
      34: pop
      35: iconst_1
      36: ireturn
      37: aload_0
      38: getfield      #117                // Field internals:Lorg/apache/curator/framework/recipes/locks/LockInternals;
      41: lload_1
      42: aload_3
      43: aload_0
      44: invokevirtual #212                // Method getLockNodeBytes:()[B
      47: invokevirtual #216                // Method org/apache/curator/framework/recipes/locks/LockInternals.attemptLock:(JLjava/util/concurrent/TimeUnit;[B)Ljava/lang/String;
      50: astore        6
      52: aload         6
      54: ifnull        87
      57: new           #12                 // class org/apache/curator/framework/recipes/locks/InterProcessMutex$LockData
      60: dup
      61: aload         4
      63: aload         6
      65: aconst_null
      66: invokespecial #219                // Method org/apache/curator/framework/recipes/locks/InterProcessMutex$LockData."<init>":(Ljava/lang/Thread;Ljava/lang/String;Lorg/apache/curator/framework/recipes/locks/InterProcessMutex$1;)V
      69: astore        7
      71: aload_0
      72: getfield      #82                 // Field threadData:Ljava/util/concurrent/ConcurrentMap;
      75: aload         4
      77: aload         7
      79: invokeinterface #223,  3          // InterfaceMethod java/util/concurrent/ConcurrentMap.put:(Ljava/lang/Object;Ljava/lang/Object;)Ljava/lang/Object;
      84: pop
      85: iconst_1
      86: ireturn
      87: iconst_0
      88: ireturn
}
