Compiled from "HttpMethodBase.java"
public abstract class org.elasticsearch.hadoop.thirdparty.apache.commons.httpclient.HttpMethodBase implements org.elasticsearch.hadoop.thirdparty.apache.commons.httpclient.HttpMethod {
  private static final org.apache.commons.logging.Log LOG;

  private org.elasticsearch.hadoop.thirdparty.apache.commons.httpclient.HeaderGroup requestHeaders;

  private org.elasticsearch.hadoop.thirdparty.apache.commons.httpclient.StatusLine statusLine;

  private org.elasticsearch.hadoop.thirdparty.apache.commons.httpclient.HeaderGroup responseHeaders;

  private org.elasticsearch.hadoop.thirdparty.apache.commons.httpclient.HeaderGroup responseTrailerHeaders;

  private java.lang.String path;

  private java.lang.String queryString;

  private java.io.InputStream responseStream;

  private org.elasticsearch.hadoop.thirdparty.apache.commons.httpclient.HttpConnection responseConnection;

  private byte[] responseBody;

  private boolean followRedirects;

  private boolean doAuthentication;

  private org.elasticsearch.hadoop.thirdparty.apache.commons.httpclient.params.HttpMethodParams params;

  private org.elasticsearch.hadoop.thirdparty.apache.commons.httpclient.auth.AuthState hostAuthState;

  private org.elasticsearch.hadoop.thirdparty.apache.commons.httpclient.auth.AuthState proxyAuthState;

  private boolean used;

  private int recoverableExceptionCount;

  private org.elasticsearch.hadoop.thirdparty.apache.commons.httpclient.HttpHost httphost;

  private org.elasticsearch.hadoop.thirdparty.apache.commons.httpclient.MethodRetryHandler methodRetryHandler;

  private boolean connectionCloseForced;

  private static final int RESPONSE_WAIT_TIME_MS;

  private org.elasticsearch.hadoop.thirdparty.apache.commons.httpclient.HttpVersion effectiveVersion;

  private transient boolean aborted;

  private boolean requestSent;

  private org.elasticsearch.hadoop.thirdparty.apache.commons.httpclient.cookie.CookieSpec cookiespec;

  private static final int DEFAULT_INITIAL_BUFFER_SIZE;

  static java.lang.Class class$org$apache$commons$httpclient$HttpMethodBase;

  public org.elasticsearch.hadoop.thirdparty.apache.commons.httpclient.HttpMethodBase();
    Code:
       0: aload_0
       1: invokespecial #58                 // Method java/lang/Object."<init>":()V
       4: aload_0
       5: new           #60                 // class org/elasticsearch/hadoop/thirdparty/apache/commons/httpclient/HeaderGroup
       8: dup
       9: invokespecial #61                 // Method org/elasticsearch/hadoop/thirdparty/apache/commons/httpclient/HeaderGroup."<init>":()V
      12: putfield      #63                 // Field requestHeaders:Lorg/elasticsearch/hadoop/thirdparty/apache/commons/httpclient/HeaderGroup;
      15: aload_0
      16: aconst_null
      17: putfield      #65                 // Field statusLine:Lorg/elasticsearch/hadoop/thirdparty/apache/commons/httpclient/StatusLine;
      20: aload_0
      21: new           #60                 // class org/elasticsearch/hadoop/thirdparty/apache/commons/httpclient/HeaderGroup
      24: dup
      25: invokespecial #61                 // Method org/elasticsearch/hadoop/thirdparty/apache/commons/httpclient/HeaderGroup."<init>":()V
      28: putfield      #67                 // Field responseHeaders:Lorg/elasticsearch/hadoop/thirdparty/apache/commons/httpclient/HeaderGroup;
      31: aload_0
      32: new           #60                 // class org/elasticsearch/hadoop/thirdparty/apache/commons/httpclient/HeaderGroup
      35: dup
      36: invokespecial #61                 // Method org/elasticsearch/hadoop/thirdparty/apache/commons/httpclient/HeaderGroup."<init>":()V
      39: putfield      #69                 // Field responseTrailerHeaders:Lorg/elasticsearch/hadoop/thirdparty/apache/commons/httpclient/HeaderGroup;
      42: aload_0
      43: aconst_null
      44: putfield      #71                 // Field path:Ljava/lang/String;
      47: aload_0
      48: aconst_null
      49: putfield      #73                 // Field queryString:Ljava/lang/String;
      52: aload_0
      53: aconst_null
      54: putfield      #75                 // Field responseStream:Ljava/io/InputStream;
      57: aload_0
      58: aconst_null
      59: putfield      #77                 // Field responseConnection:Lorg/elasticsearch/hadoop/thirdparty/apache/commons/httpclient/HttpConnection;
      62: aload_0
      63: aconst_null
      64: putfield      #79                 // Field responseBody:[B
      67: aload_0
      68: iconst_0
      69: putfield      #81                 // Field followRedirects:Z
      72: aload_0
      73: iconst_1
      74: putfield      #83                 // Field doAuthentication:Z
      77: aload_0
      78: new           #85                 // class org/elasticsearch/hadoop/thirdparty/apache/commons/httpclient/params/HttpMethodParams
      81: dup
      82: invokespecial #86                 // Method org/elasticsearch/hadoop/thirdparty/apache/commons/httpclient/params/HttpMethodParams."<init>":()V
      85: putfield      #88                 // Field params:Lorg/elasticsearch/hadoop/thirdparty/apache/commons/httpclient/params/HttpMethodParams;
      88: aload_0
      89: new           #90                 // class org/elasticsearch/hadoop/thirdparty/apache/commons/httpclient/auth/AuthState
      92: dup
      93: invokespecial #91                 // Method org/elasticsearch/hadoop/thirdparty/apache/commons/httpclient/auth/AuthState."<init>":()V
      96: putfield      #93                 // Field hostAuthState:Lorg/elasticsearch/hadoop/thirdparty/apache/commons/httpclient/auth/AuthState;
      99: aload_0
     100: new           #90                 // class org/elasticsearch/hadoop/thirdparty/apache/commons/httpclient/auth/AuthState
     103: dup
     104: invokespecial #91                 // Method org/elasticsearch/hadoop/thirdparty/apache/commons/httpclient/auth/AuthState."<init>":()V
     107: putfield      #95                 // Field proxyAuthState:Lorg/elasticsearch/hadoop/thirdparty/apache/commons/httpclient/auth/AuthState;
     110: aload_0
     111: iconst_0
     112: putfield      #97                 // Field used:Z
     115: aload_0
     116: iconst_0
     117: putfield      #99                 // Field recoverableExceptionCount:I
     120: aload_0
     121: aconst_null
     122: putfield      #101                // Field httphost:Lorg/elasticsearch/hadoop/thirdparty/apache/commons/httpclient/HttpHost;
     125: aload_0
     126: iconst_0
     127: putfield      #103                // Field connectionCloseForced:Z
     130: aload_0
     131: aconst_null
     132: putfield      #105                // Field effectiveVersion:Lorg/elasticsearch/hadoop/thirdparty/apache/commons/httpclient/HttpVersion;
     135: aload_0
     136: iconst_0
     137: putfield      #107                // Field aborted:Z
     140: aload_0
     141: iconst_0
     142: putfield      #109                // Field requestSent:Z
     145: aload_0
     146: aconst_null
     147: putfield      #111                // Field cookiespec:Lorg/elasticsearch/hadoop/thirdparty/apache/commons/httpclient/cookie/CookieSpec;
     150: return

  public org.elasticsearch.hadoop.thirdparty.apache.commons.httpclient.HttpMethodBase(java.lang.String) throws java.lang.IllegalArgumentException, java.lang.IllegalStateException;
    Code:
       0: aload_0
       1: invokespecial #58                 // Method java/lang/Object."<init>":()V
       4: aload_0
       5: new           #60                 // class org/elasticsearch/hadoop/thirdparty/apache/commons/httpclient/HeaderGroup
       8: dup
       9: invokespecial #61                 // Method org/elasticsearch/hadoop/thirdparty/apache/commons/httpclient/HeaderGroup."<init>":()V
      12: putfield      #63                 // Field requestHeaders:Lorg/elasticsearch/hadoop/thirdparty/apache/commons/httpclient/HeaderGroup;
      15: aload_0
      16: aconst_null
      17: putfield      #65                 // Field statusLine:Lorg/elasticsearch/hadoop/thirdparty/apache/commons/httpclient/StatusLine;
      20: aload_0
      21: new           #60                 // class org/elasticsearch/hadoop/thirdparty/apache/commons/httpclient/HeaderGroup
      24: dup
      25: invokespecial #61                 // Method org/elasticsearch/hadoop/thirdparty/apache/commons/httpclient/HeaderGroup."<init>":()V
      28: putfield      #67                 // Field responseHeaders:Lorg/elasticsearch/hadoop/thirdparty/apache/commons/httpclient/HeaderGroup;
      31: aload_0
      32: new           #60                 // class org/elasticsearch/hadoop/thirdparty/apache/commons/httpclient/HeaderGroup
      35: dup
      36: invokespecial #61                 // Method org/elasticsearch/hadoop/thirdparty/apache/commons/httpclient/HeaderGroup."<init>":()V
      39: putfield      #69                 // Field responseTrailerHeaders:Lorg/elasticsearch/hadoop/thirdparty/apache/commons/httpclient/HeaderGroup;
      42: aload_0
      43: aconst_null
      44: putfield      #71                 // Field path:Ljava/lang/String;
      47: aload_0
      48: aconst_null
      49: putfield      #73                 // Field queryString:Ljava/lang/String;
      52: aload_0
      53: aconst_null
      54: putfield      #75                 // Field responseStream:Ljava/io/InputStream;
      57: aload_0
      58: aconst_null
      59: putfield      #77                 // Field responseConnection:Lorg/elasticsearch/hadoop/thirdparty/apache/commons/httpclient/HttpConnection;
      62: aload_0
      63: aconst_null
      64: putfield      #79                 // Field responseBody:[B
      67: aload_0
      68: iconst_0
      69: putfield      #81                 // Field followRedirects:Z
      72: aload_0
      73: iconst_1
      74: putfield      #83                 // Field doAuthentication:Z
      77: aload_0
      78: new           #85                 // class org/elasticsearch/hadoop/thirdparty/apache/commons/httpclient/params/HttpMethodParams
      81: dup
      82: invokespecial #86                 // Method org/elasticsearch/hadoop/thirdparty/apache/commons/httpclient/params/HttpMethodParams."<init>":()V
      85: putfield      #88                 // Field params:Lorg/elasticsearch/hadoop/thirdparty/apache/commons/httpclient/params/HttpMethodParams;
      88: aload_0
      89: new           #90                 // class org/elasticsearch/hadoop/thirdparty/apache/commons/httpclient/auth/AuthState
      92: dup
      93: invokespecial #91                 // Method org/elasticsearch/hadoop/thirdparty/apache/commons/httpclient/auth/AuthState."<init>":()V
      96: putfield      #93                 // Field hostAuthState:Lorg/elasticsearch/hadoop/thirdparty/apache/commons/httpclient/auth/AuthState;
      99: aload_0
     100: new           #90                 // class org/elasticsearch/hadoop/thirdparty/apache/commons/httpclient/auth/AuthState
     103: dup
     104: invokespecial #91                 // Method org/elasticsearch/hadoop/thirdparty/apache/commons/httpclient/auth/AuthState."<init>":()V
     107: putfield      #95                 // Field proxyAuthState:Lorg/elasticsearch/hadoop/thirdparty/apache/commons/httpclient/auth/AuthState;
     110: aload_0
     111: iconst_0
     112: putfield      #97                 // Field used:Z
     115: aload_0
     116: iconst_0
     117: putfield      #99                 // Field recoverableExceptionCount:I
     120: aload_0
     121: aconst_null
     122: putfield      #101                // Field httphost:Lorg/elasticsearch/hadoop/thirdparty/apache/commons/httpclient/HttpHost;
     125: aload_0
     126: iconst_0
     127: putfield      #103                // Field connectionCloseForced:Z
     130: aload_0
     131: aconst_null
     132: putfield      #105                // Field effectiveVersion:Lorg/elasticsearch/hadoop/thirdparty/apache/commons/httpclient/HttpVersion;
     135: aload_0
     136: iconst_0
     137: putfield      #107                // Field aborted:Z
     140: aload_0
     141: iconst_0
     142: putfield      #109                // Field requestSent:Z
     145: aload_0
     146: aconst_null
     147: putfield      #111                // Field cookiespec:Lorg/elasticsearch/hadoop/thirdparty/apache/commons/httpclient/cookie/CookieSpec;
     150: aload_1
     151: ifnull        163
     154: aload_1
     155: ldc           #122                // String
     157: invokevirtual #128                // Method java/lang/String.equals:(Ljava/lang/Object;)Z
     160: ifeq          166
     163: ldc           #130                // String /
     165: astore_1
     166: aload_0
     167: new           #132                // class org/elasticsearch/hadoop/thirdparty/apache/commons/httpclient/URI
     170: dup
     171: aload_1
     172: iconst_1
     173: invokespecial #135                // Method org/elasticsearch/hadoop/thirdparty/apache/commons/httpclient/URI."<init>":(Ljava/lang/String;Z)V
     176: invokevirtual #139                // Method setURI:(Lorg/elasticsearch/hadoop/thirdparty/apache/commons/httpclient/URI;)V
     179: goto          222
     182: astore_2
     183: new           #116                // class java/lang/IllegalArgumentException
     186: dup
     187: new           #141                // class java/lang/StringBuffer
     190: dup
     191: invokespecial #142                // Method java/lang/StringBuffer."<init>":()V
     194: ldc           #144                // String Invalid uri \'
     196: invokevirtual #148                // Method java/lang/StringBuffer.append:(Ljava/lang/String;)Ljava/lang/StringBuffer;
     199: aload_1
     200: invokevirtual #148                // Method java/lang/StringBuffer.append:(Ljava/lang/String;)Ljava/lang/StringBuffer;
     203: ldc           #150                // String \':
     205: invokevirtual #148                // Method java/lang/StringBuffer.append:(Ljava/lang/String;)Ljava/lang/StringBuffer;
     208: aload_2
     209: invokevirtual #156                // Method java/lang/Throwable.getMessage:()Ljava/lang/String;
     212: invokevirtual #148                // Method java/lang/StringBuffer.append:(Ljava/lang/String;)Ljava/lang/StringBuffer;
     215: invokevirtual #159                // Method java/lang/StringBuffer.toString:()Ljava/lang/String;
     218: invokespecial #161                // Method java/lang/IllegalArgumentException."<init>":(Ljava/lang/String;)V
     221: athrow
     222: return
    Exception table:
       from    to  target type
         150   179   182   Class org/elasticsearch/hadoop/thirdparty/apache/commons/httpclient/URIException

  public abstract java.lang.String getName();

  public org.elasticsearch.hadoop.thirdparty.apache.commons.httpclient.URI getURI() throws org.elasticsearch.hadoop.thirdparty.apache.commons.httpclient.URIException;
    Code:
       0: new           #141                // class java/lang/StringBuffer
       3: dup
       4: invokespecial #142                // Method java/lang/StringBuffer."<init>":()V
       7: astore_1
       8: aload_0
       9: getfield      #101                // Field httphost:Lorg/elasticsearch/hadoop/thirdparty/apache/commons/httpclient/HttpHost;
      12: ifnull        89
      15: aload_1
      16: aload_0
      17: getfield      #101                // Field httphost:Lorg/elasticsearch/hadoop/thirdparty/apache/commons/httpclient/HttpHost;
      20: invokevirtual #173                // Method org/elasticsearch/hadoop/thirdparty/apache/commons/httpclient/HttpHost.getProtocol:()Lorg/elasticsearch/hadoop/thirdparty/apache/commons/httpclient/protocol/Protocol;
      23: invokevirtual #178                // Method org/elasticsearch/hadoop/thirdparty/apache/commons/httpclient/protocol/Protocol.getScheme:()Ljava/lang/String;
      26: invokevirtual #148                // Method java/lang/StringBuffer.append:(Ljava/lang/String;)Ljava/lang/StringBuffer;
      29: pop
      30: aload_1
      31: ldc           #180                // String ://
      33: invokevirtual #148                // Method java/lang/StringBuffer.append:(Ljava/lang/String;)Ljava/lang/StringBuffer;
      36: pop
      37: aload_1
      38: aload_0
      39: getfield      #101                // Field httphost:Lorg/elasticsearch/hadoop/thirdparty/apache/commons/httpclient/HttpHost;
      42: invokevirtual #183                // Method org/elasticsearch/hadoop/thirdparty/apache/commons/httpclient/HttpHost.getHostName:()Ljava/lang/String;
      45: invokevirtual #148                // Method java/lang/StringBuffer.append:(Ljava/lang/String;)Ljava/lang/StringBuffer;
      48: pop
      49: aload_0
      50: getfield      #101                // Field httphost:Lorg/elasticsearch/hadoop/thirdparty/apache/commons/httpclient/HttpHost;
      53: invokevirtual #187                // Method org/elasticsearch/hadoop/thirdparty/apache/commons/httpclient/HttpHost.getPort:()I
      56: istore_2
      57: iload_2
      58: iconst_m1
      59: if_icmpeq     89
      62: iload_2
      63: aload_0
      64: getfield      #101                // Field httphost:Lorg/elasticsearch/hadoop/thirdparty/apache/commons/httpclient/HttpHost;
      67: invokevirtual #173                // Method org/elasticsearch/hadoop/thirdparty/apache/commons/httpclient/HttpHost.getProtocol:()Lorg/elasticsearch/hadoop/thirdparty/apache/commons/httpclient/protocol/Protocol;
      70: invokevirtual #190                // Method org/elasticsearch/hadoop/thirdparty/apache/commons/httpclient/protocol/Protocol.getDefaultPort:()I
      73: if_icmpeq     89
      76: aload_1
      77: ldc           #192                // String :
      79: invokevirtual #148                // Method java/lang/StringBuffer.append:(Ljava/lang/String;)Ljava/lang/StringBuffer;
      82: pop
      83: aload_1
      84: iload_2
      85: invokevirtual #195                // Method java/lang/StringBuffer.append:(I)Ljava/lang/StringBuffer;
      88: pop
      89: aload_1
      90: aload_0
      91: getfield      #71                 // Field path:Ljava/lang/String;
      94: invokevirtual #148                // Method java/lang/StringBuffer.append:(Ljava/lang/String;)Ljava/lang/StringBuffer;
      97: pop
      98: aload_0
      99: getfield      #73                 // Field queryString:Ljava/lang/String;
     102: ifnull        121
     105: aload_1
     106: bipush        63
     108: invokevirtual #198                // Method java/lang/StringBuffer.append:(C)Ljava/lang/StringBuffer;
     111: pop
     112: aload_1
     113: aload_0
     114: getfield      #73                 // Field queryString:Ljava/lang/String;
     117: invokevirtual #148                // Method java/lang/StringBuffer.append:(Ljava/lang/String;)Ljava/lang/StringBuffer;
     120: pop
     121: new           #132                // class org/elasticsearch/hadoop/thirdparty/apache/commons/httpclient/URI
     124: dup
     125: aload_1
     126: invokevirtual #159                // Method java/lang/StringBuffer.toString:()Ljava/lang/String;
     129: iconst_1
     130: invokespecial #135                // Method org/elasticsearch/hadoop/thirdparty/apache/commons/httpclient/URI."<init>":(Ljava/lang/String;Z)V
     133: areturn

  public void setURI(org.elasticsearch.hadoop.thirdparty.apache.commons.httpclient.URI) throws org.elasticsearch.hadoop.thirdparty.apache.commons.httpclient.URIException;
    Code:
       0: aload_1
       1: invokevirtual #205                // Method org/elasticsearch/hadoop/thirdparty/apache/commons/httpclient/URI.isAbsoluteURI:()Z
       4: ifeq          19
       7: aload_0
       8: new           #169                // class org/elasticsearch/hadoop/thirdparty/apache/commons/httpclient/HttpHost
      11: dup
      12: aload_1
      13: invokespecial #207                // Method org/elasticsearch/hadoop/thirdparty/apache/commons/httpclient/HttpHost."<init>":(Lorg/elasticsearch/hadoop/thirdparty/apache/commons/httpclient/URI;)V
      16: putfield      #101                // Field httphost:Lorg/elasticsearch/hadoop/thirdparty/apache/commons/httpclient/HttpHost;
      19: aload_0
      20: aload_1
      21: invokevirtual #210                // Method org/elasticsearch/hadoop/thirdparty/apache/commons/httpclient/URI.getPath:()Ljava/lang/String;
      24: ifnonnull     32
      27: ldc           #130                // String /
      29: goto          36
      32: aload_1
      33: invokevirtual #213                // Method org/elasticsearch/hadoop/thirdparty/apache/commons/httpclient/URI.getEscapedPath:()Ljava/lang/String;
      36: invokevirtual #216                // Method setPath:(Ljava/lang/String;)V
      39: aload_0
      40: aload_1
      41: invokevirtual #219                // Method org/elasticsearch/hadoop/thirdparty/apache/commons/httpclient/URI.getEscapedQuery:()Ljava/lang/String;
      44: invokevirtual #222                // Method setQueryString:(Ljava/lang/String;)V
      47: return

  public void setFollowRedirects(boolean);
    Code:
       0: aload_0
       1: iload_1
       2: putfield      #81                 // Field followRedirects:Z
       5: return

  public boolean getFollowRedirects();
    Code:
       0: aload_0
       1: getfield      #81                 // Field followRedirects:Z
       4: ireturn

  public void setHttp11(boolean);
    Code:
       0: iload_1
       1: ifeq          17
       4: aload_0
       5: getfield      #88                 // Field params:Lorg/elasticsearch/hadoop/thirdparty/apache/commons/httpclient/params/HttpMethodParams;
       8: getstatic     #232                // Field org/elasticsearch/hadoop/thirdparty/apache/commons/httpclient/HttpVersion.HTTP_1_1:Lorg/elasticsearch/hadoop/thirdparty/apache/commons/httpclient/HttpVersion;
      11: invokevirtual #236                // Method org/elasticsearch/hadoop/thirdparty/apache/commons/httpclient/params/HttpMethodParams.setVersion:(Lorg/elasticsearch/hadoop/thirdparty/apache/commons/httpclient/HttpVersion;)V
      14: goto          27
      17: aload_0
      18: getfield      #88                 // Field params:Lorg/elasticsearch/hadoop/thirdparty/apache/commons/httpclient/params/HttpMethodParams;
      21: getstatic     #239                // Field org/elasticsearch/hadoop/thirdparty/apache/commons/httpclient/HttpVersion.HTTP_1_0:Lorg/elasticsearch/hadoop/thirdparty/apache/commons/httpclient/HttpVersion;
      24: invokevirtual #236                // Method org/elasticsearch/hadoop/thirdparty/apache/commons/httpclient/params/HttpMethodParams.setVersion:(Lorg/elasticsearch/hadoop/thirdparty/apache/commons/httpclient/HttpVersion;)V
      27: return

  public boolean getDoAuthentication();
    Code:
       0: aload_0
       1: getfield      #83                 // Field doAuthentication:Z
       4: ireturn

  public void setDoAuthentication(boolean);
    Code:
       0: aload_0
       1: iload_1
       2: putfield      #83                 // Field doAuthentication:Z
       5: return

  public boolean isHttp11();
    Code:
       0: aload_0
       1: getfield      #88                 // Field params:Lorg/elasticsearch/hadoop/thirdparty/apache/commons/httpclient/params/HttpMethodParams;
       4: invokevirtual #247                // Method org/elasticsearch/hadoop/thirdparty/apache/commons/httpclient/params/HttpMethodParams.getVersion:()Lorg/elasticsearch/hadoop/thirdparty/apache/commons/httpclient/HttpVersion;
       7: getstatic     #232                // Field org/elasticsearch/hadoop/thirdparty/apache/commons/httpclient/HttpVersion.HTTP_1_1:Lorg/elasticsearch/hadoop/thirdparty/apache/commons/httpclient/HttpVersion;
      10: invokevirtual #250                // Method org/elasticsearch/hadoop/thirdparty/apache/commons/httpclient/HttpVersion.equals:(Lorg/elasticsearch/hadoop/thirdparty/apache/commons/httpclient/HttpVersion;)Z
      13: ireturn

  public void setPath(java.lang.String);
    Code:
       0: aload_0
       1: aload_1
       2: putfield      #71                 // Field path:Ljava/lang/String;
       5: return

  public void addRequestHeader(org.elasticsearch.hadoop.thirdparty.apache.commons.httpclient.Header);
    Code:
       0: getstatic     #254                // Field LOG:Lorg/apache/commons/logging/Log;
       3: ldc_w         #256                // String HttpMethodBase.addRequestHeader(Header)
       6: invokeinterface #262,  2          // InterfaceMethod org/apache/commons/logging/Log.trace:(Ljava/lang/Object;)V
      11: aload_1
      12: ifnonnull     29
      15: getstatic     #254                // Field LOG:Lorg/apache/commons/logging/Log;
      18: ldc_w         #264                // String null header value ignored
      21: invokeinterface #267,  2          // InterfaceMethod org/apache/commons/logging/Log.debug:(Ljava/lang/Object;)V
      26: goto          37
      29: aload_0
      30: invokevirtual #271                // Method getRequestHeaderGroup:()Lorg/elasticsearch/hadoop/thirdparty/apache/commons/httpclient/HeaderGroup;
      33: aload_1
      34: invokevirtual #274                // Method org/elasticsearch/hadoop/thirdparty/apache/commons/httpclient/HeaderGroup.addHeader:(Lorg/elasticsearch/hadoop/thirdparty/apache/commons/httpclient/Header;)V
      37: return

  public void addResponseFooter(org.elasticsearch.hadoop.thirdparty.apache.commons.httpclient.Header);
    Code:
       0: aload_0
       1: invokevirtual #280                // Method getResponseTrailerHeaderGroup:()Lorg/elasticsearch/hadoop/thirdparty/apache/commons/httpclient/HeaderGroup;
       4: aload_1
       5: invokevirtual #274                // Method org/elasticsearch/hadoop/thirdparty/apache/commons/httpclient/HeaderGroup.addHeader:(Lorg/elasticsearch/hadoop/thirdparty/apache/commons/httpclient/Header;)V
       8: return

  public java.lang.String getPath();
    Code:
       0: aload_0
       1: getfield      #71                 // Field path:Ljava/lang/String;
       4: ifnull        19
       7: aload_0
       8: getfield      #71                 // Field path:Ljava/lang/String;
      11: ldc           #122                // String
      13: invokevirtual #128                // Method java/lang/String.equals:(Ljava/lang/Object;)Z
      16: ifeq          24
      19: ldc           #130                // String /
      21: goto          28
      24: aload_0
      25: getfield      #71                 // Field path:Ljava/lang/String;
      28: areturn

  public void setQueryString(java.lang.String);
    Code:
       0: aload_0
       1: aload_1
       2: putfield      #73                 // Field queryString:Ljava/lang/String;
       5: return

  public void setQueryString(org.elasticsearch.hadoop.thirdparty.apache.commons.httpclient.NameValuePair[]);
    Code:
       0: getstatic     #254                // Field LOG:Lorg/apache/commons/logging/Log;
       3: ldc_w         #284                // String enter HttpMethodBase.setQueryString(NameValuePair[])
       6: invokeinterface #262,  2          // InterfaceMethod org/apache/commons/logging/Log.trace:(Ljava/lang/Object;)V
      11: aload_0
      12: aload_1
      13: ldc_w         #286                // String UTF-8
      16: invokestatic  #292                // Method org/elasticsearch/hadoop/thirdparty/apache/commons/httpclient/util/EncodingUtil.formUrlEncode:([Lorg/elasticsearch/hadoop/thirdparty/apache/commons/httpclient/NameValuePair;Ljava/lang/String;)Ljava/lang/String;
      19: putfield      #73                 // Field queryString:Ljava/lang/String;
      22: return

  public java.lang.String getQueryString();
    Code:
       0: aload_0
       1: getfield      #73                 // Field queryString:Ljava/lang/String;
       4: areturn

  public void setRequestHeader(java.lang.String, java.lang.String);
    Code:
       0: new           #298                // class org/elasticsearch/hadoop/thirdparty/apache/commons/httpclient/Header
       3: dup
       4: aload_1
       5: aload_2
       6: invokespecial #300                // Method org/elasticsearch/hadoop/thirdparty/apache/commons/httpclient/Header."<init>":(Ljava/lang/String;Ljava/lang/String;)V
       9: astore_3
      10: aload_0
      11: aload_3
      12: invokevirtual #302                // Method setRequestHeader:(Lorg/elasticsearch/hadoop/thirdparty/apache/commons/httpclient/Header;)V
      15: return

  public void setRequestHeader(org.elasticsearch.hadoop.thirdparty.apache.commons.httpclient.Header);
    Code:
       0: aload_0
       1: invokevirtual #271                // Method getRequestHeaderGroup:()Lorg/elasticsearch/hadoop/thirdparty/apache/commons/httpclient/HeaderGroup;
       4: aload_1
       5: invokevirtual #308                // Method org/elasticsearch/hadoop/thirdparty/apache/commons/httpclient/NameValuePair.getName:()Ljava/lang/String;
       8: invokevirtual #312                // Method org/elasticsearch/hadoop/thirdparty/apache/commons/httpclient/HeaderGroup.getHeaders:(Ljava/lang/String;)[Lorg/elasticsearch/hadoop/thirdparty/apache/commons/httpclient/Header;
      11: astore_2
      12: iconst_0
      13: istore_3
      14: goto          30
      17: aload_0
      18: invokevirtual #271                // Method getRequestHeaderGroup:()Lorg/elasticsearch/hadoop/thirdparty/apache/commons/httpclient/HeaderGroup;
      21: aload_2
      22: iload_3
      23: aaload
      24: invokevirtual #315                // Method org/elasticsearch/hadoop/thirdparty/apache/commons/httpclient/HeaderGroup.removeHeader:(Lorg/elasticsearch/hadoop/thirdparty/apache/commons/httpclient/Header;)V
      27: iinc          3, 1
      30: iload_3
      31: aload_2
      32: arraylength
      33: if_icmplt     17
      36: aload_0
      37: invokevirtual #271                // Method getRequestHeaderGroup:()Lorg/elasticsearch/hadoop/thirdparty/apache/commons/httpclient/HeaderGroup;
      40: aload_1
      41: invokevirtual #274                // Method org/elasticsearch/hadoop/thirdparty/apache/commons/httpclient/HeaderGroup.addHeader:(Lorg/elasticsearch/hadoop/thirdparty/apache/commons/httpclient/Header;)V
      44: return

  public org.elasticsearch.hadoop.thirdparty.apache.commons.httpclient.Header getRequestHeader(java.lang.String);
    Code:
       0: aload_1
       1: ifnonnull     6
       4: aconst_null
       5: areturn
       6: aload_0
       7: invokevirtual #271                // Method getRequestHeaderGroup:()Lorg/elasticsearch/hadoop/thirdparty/apache/commons/httpclient/HeaderGroup;
      10: aload_1
      11: invokevirtual #323                // Method org/elasticsearch/hadoop/thirdparty/apache/commons/httpclient/HeaderGroup.getCondensedHeader:(Ljava/lang/String;)Lorg/elasticsearch/hadoop/thirdparty/apache/commons/httpclient/Header;
      14: areturn

  public org.elasticsearch.hadoop.thirdparty.apache.commons.httpclient.Header[] getRequestHeaders();
    Code:
       0: aload_0
       1: invokevirtual #271                // Method getRequestHeaderGroup:()Lorg/elasticsearch/hadoop/thirdparty/apache/commons/httpclient/HeaderGroup;
       4: invokevirtual #328                // Method org/elasticsearch/hadoop/thirdparty/apache/commons/httpclient/HeaderGroup.getAllHeaders:()[Lorg/elasticsearch/hadoop/thirdparty/apache/commons/httpclient/Header;
       7: areturn

  public org.elasticsearch.hadoop.thirdparty.apache.commons.httpclient.Header[] getRequestHeaders(java.lang.String);
    Code:
       0: aload_0
       1: invokevirtual #271                // Method getRequestHeaderGroup:()Lorg/elasticsearch/hadoop/thirdparty/apache/commons/httpclient/HeaderGroup;
       4: aload_1
       5: invokevirtual #312                // Method org/elasticsearch/hadoop/thirdparty/apache/commons/httpclient/HeaderGroup.getHeaders:(Ljava/lang/String;)[Lorg/elasticsearch/hadoop/thirdparty/apache/commons/httpclient/Header;
       8: areturn

  protected org.elasticsearch.hadoop.thirdparty.apache.commons.httpclient.HeaderGroup getRequestHeaderGroup();
    Code:
       0: aload_0
       1: getfield      #63                 // Field requestHeaders:Lorg/elasticsearch/hadoop/thirdparty/apache/commons/httpclient/HeaderGroup;
       4: areturn

  protected org.elasticsearch.hadoop.thirdparty.apache.commons.httpclient.HeaderGroup getResponseTrailerHeaderGroup();
    Code:
       0: aload_0
       1: getfield      #69                 // Field responseTrailerHeaders:Lorg/elasticsearch/hadoop/thirdparty/apache/commons/httpclient/HeaderGroup;
       4: areturn

  protected org.elasticsearch.hadoop.thirdparty.apache.commons.httpclient.HeaderGroup getResponseHeaderGroup();
    Code:
       0: aload_0
       1: getfield      #67                 // Field responseHeaders:Lorg/elasticsearch/hadoop/thirdparty/apache/commons/httpclient/HeaderGroup;
       4: areturn

  public org.elasticsearch.hadoop.thirdparty.apache.commons.httpclient.Header[] getResponseHeaders(java.lang.String);
    Code:
       0: aload_0
       1: invokevirtual #332                // Method getResponseHeaderGroup:()Lorg/elasticsearch/hadoop/thirdparty/apache/commons/httpclient/HeaderGroup;
       4: aload_1
       5: invokevirtual #312                // Method org/elasticsearch/hadoop/thirdparty/apache/commons/httpclient/HeaderGroup.getHeaders:(Ljava/lang/String;)[Lorg/elasticsearch/hadoop/thirdparty/apache/commons/httpclient/Header;
       8: areturn

  public int getStatusCode();
    Code:
       0: aload_0
       1: getfield      #65                 // Field statusLine:Lorg/elasticsearch/hadoop/thirdparty/apache/commons/httpclient/StatusLine;
       4: invokevirtual #337                // Method org/elasticsearch/hadoop/thirdparty/apache/commons/httpclient/StatusLine.getStatusCode:()I
       7: ireturn

  public org.elasticsearch.hadoop.thirdparty.apache.commons.httpclient.StatusLine getStatusLine();
    Code:
       0: aload_0
       1: getfield      #65                 // Field statusLine:Lorg/elasticsearch/hadoop/thirdparty/apache/commons/httpclient/StatusLine;
       4: areturn

  private boolean responseAvailable();
    Code:
       0: aload_0
       1: getfield      #79                 // Field responseBody:[B
       4: ifnonnull     14
       7: aload_0
       8: getfield      #75                 // Field responseStream:Ljava/io/InputStream;
      11: ifnull        18
      14: iconst_1
      15: goto          19
      18: iconst_0
      19: ireturn

  public org.elasticsearch.hadoop.thirdparty.apache.commons.httpclient.Header[] getResponseHeaders();
    Code:
       0: aload_0
       1: invokevirtual #332                // Method getResponseHeaderGroup:()Lorg/elasticsearch/hadoop/thirdparty/apache/commons/httpclient/HeaderGroup;
       4: invokevirtual #328                // Method org/elasticsearch/hadoop/thirdparty/apache/commons/httpclient/HeaderGroup.getAllHeaders:()[Lorg/elasticsearch/hadoop/thirdparty/apache/commons/httpclient/Header;
       7: areturn

  public org.elasticsearch.hadoop.thirdparty.apache.commons.httpclient.Header getResponseHeader(java.lang.String);
    Code:
       0: aload_1
       1: ifnonnull     6
       4: aconst_null
       5: areturn
       6: aload_0
       7: invokevirtual #332                // Method getResponseHeaderGroup:()Lorg/elasticsearch/hadoop/thirdparty/apache/commons/httpclient/HeaderGroup;
      10: aload_1
      11: invokevirtual #323                // Method org/elasticsearch/hadoop/thirdparty/apache/commons/httpclient/HeaderGroup.getCondensedHeader:(Ljava/lang/String;)Lorg/elasticsearch/hadoop/thirdparty/apache/commons/httpclient/Header;
      14: areturn

  public long getResponseContentLength();
    Code:
       0: aload_0
       1: invokevirtual #332                // Method getResponseHeaderGroup:()Lorg/elasticsearch/hadoop/thirdparty/apache/commons/httpclient/HeaderGroup;
       4: ldc_w         #347                // String Content-Length
       7: invokevirtual #312                // Method org/elasticsearch/hadoop/thirdparty/apache/commons/httpclient/HeaderGroup.getHeaders:(Ljava/lang/String;)[Lorg/elasticsearch/hadoop/thirdparty/apache/commons/httpclient/Header;
      10: astore_1
      11: aload_1
      12: arraylength
      13: ifne          20
      16: ldc2_w        #348                // long -1l
      19: lreturn
      20: aload_1
      21: arraylength
      22: iconst_1
      23: if_icmple     37
      26: getstatic     #254                // Field LOG:Lorg/apache/commons/logging/Log;
      29: ldc_w         #351                // String Multiple content-length headers detected
      32: invokeinterface #354,  2          // InterfaceMethod org/apache/commons/logging/Log.warn:(Ljava/lang/Object;)V
      37: aload_1
      38: arraylength
      39: iconst_1
      40: isub
      41: istore_2
      42: goto          105
      45: aload_1
      46: iload_2
      47: aaload
      48: astore_3
      49: aload_3
      50: invokevirtual #357                // Method org/elasticsearch/hadoop/thirdparty/apache/commons/httpclient/NameValuePair.getValue:()Ljava/lang/String;
      53: invokestatic  #363                // Method java/lang/Long.parseLong:(Ljava/lang/String;)J
      56: lreturn
      57: astore        4
      59: getstatic     #254                // Field LOG:Lorg/apache/commons/logging/Log;
      62: invokeinterface #366,  1          // InterfaceMethod org/apache/commons/logging/Log.isWarnEnabled:()Z
      67: ifeq          102
      70: getstatic     #254                // Field LOG:Lorg/apache/commons/logging/Log;
      73: new           #141                // class java/lang/StringBuffer
      76: dup
      77: invokespecial #142                // Method java/lang/StringBuffer."<init>":()V
      80: ldc_w         #368                // String Invalid content-length value:
      83: invokevirtual #148                // Method java/lang/StringBuffer.append:(Ljava/lang/String;)Ljava/lang/StringBuffer;
      86: aload         4
      88: invokevirtual #156                // Method java/lang/Throwable.getMessage:()Ljava/lang/String;
      91: invokevirtual #148                // Method java/lang/StringBuffer.append:(Ljava/lang/String;)Ljava/lang/StringBuffer;
      94: invokevirtual #159                // Method java/lang/StringBuffer.toString:()Ljava/lang/String;
      97: invokeinterface #354,  2          // InterfaceMethod org/apache/commons/logging/Log.warn:(Ljava/lang/Object;)V
     102: iinc          2, -1
     105: iload_2
     106: ifge          45
     109: ldc2_w        #348                // long -1l
     112: lreturn
    Exception table:
       from    to  target type
          49    57    57   Class java/lang/NumberFormatException

  public byte[] getResponseBody() throws java.io.IOException;
    Code:
       0: aload_0
       1: getfield      #79                 // Field responseBody:[B
       4: ifnonnull     190
       7: aload_0
       8: invokevirtual #377                // Method getResponseBodyAsStream:()Ljava/io/InputStream;
      11: astore_1
      12: aload_1
      13: ifnull        190
      16: aload_0
      17: invokevirtual #379                // Method getResponseContentLength:()J
      20: lstore_2
      21: lload_2
      22: ldc2_w        #380                // long 2147483647l
      25: lcmp
      26: ifle          63
      29: new           #373                // class java/io/IOException
      32: dup
      33: new           #141                // class java/lang/StringBuffer
      36: dup
      37: invokespecial #142                // Method java/lang/StringBuffer."<init>":()V
      40: ldc_w         #383                // String Content too large to be buffered:
      43: invokevirtual #148                // Method java/lang/StringBuffer.append:(Ljava/lang/String;)Ljava/lang/StringBuffer;
      46: lload_2
      47: invokevirtual #386                // Method java/lang/StringBuffer.append:(J)Ljava/lang/StringBuffer;
      50: ldc_w         #388                // String  bytes
      53: invokevirtual #148                // Method java/lang/StringBuffer.append:(Ljava/lang/String;)Ljava/lang/StringBuffer;
      56: invokevirtual #159                // Method java/lang/StringBuffer.toString:()Ljava/lang/String;
      59: invokespecial #389                // Method java/io/IOException."<init>":(Ljava/lang/String;)V
      62: athrow
      63: aload_0
      64: invokevirtual #393                // Method getParams:()Lorg/elasticsearch/hadoop/thirdparty/apache/commons/httpclient/params/HttpMethodParams;
      67: ldc_w         #395                // String http.method.response.buffer.warnlimit
      70: ldc_w         #396                // int 1048576
      73: invokevirtual #402                // Method org/elasticsearch/hadoop/thirdparty/apache/commons/httpclient/params/DefaultHttpParams.getIntParameter:(Ljava/lang/String;I)I
      76: istore        4
      78: lload_2
      79: ldc2_w        #348                // long -1l
      82: lcmp
      83: ifeq          94
      86: lload_2
      87: iload         4
      89: i2l
      90: lcmp
      91: ifle          105
      94: getstatic     #254                // Field LOG:Lorg/apache/commons/logging/Log;
      97: ldc_w         #404                // String Going to buffer response body of large or unknown size. Using getResponseBodyAsStream instead is recommended.
     100: invokeinterface #354,  2          // InterfaceMethod org/apache/commons/logging/Log.warn:(Ljava/lang/Object;)V
     105: getstatic     #254                // Field LOG:Lorg/apache/commons/logging/Log;
     108: ldc_w         #406                // String Buffering response body
     111: invokeinterface #267,  2          // InterfaceMethod org/apache/commons/logging/Log.debug:(Ljava/lang/Object;)V
     116: new           #408                // class java/io/ByteArrayOutputStream
     119: dup
     120: lload_2
     121: lconst_0
     122: lcmp
     123: ifle          131
     126: lload_2
     127: l2i
     128: goto          134
     131: sipush        4096
     134: invokespecial #411                // Method java/io/ByteArrayOutputStream."<init>":(I)V
     137: astore        5
     139: sipush        4096
     142: newarray       byte
     144: astore        6
     146: goto          159
     149: aload         5
     151: aload         6
     153: iconst_0
     154: iload         7
     156: invokevirtual #415                // Method java/io/ByteArrayOutputStream.write:([BII)V
     159: aload_1
     160: aload         6
     162: invokevirtual #421                // Method java/io/InputStream.read:([B)I
     165: dup
     166: istore        7
     168: ifgt          149
     171: aload         5
     173: invokevirtual #424                // Method java/io/ByteArrayOutputStream.close:()V
     176: aload_0
     177: aconst_null
     178: invokevirtual #428                // Method setResponseStream:(Ljava/io/InputStream;)V
     181: aload_0
     182: aload         5
     184: invokevirtual #431                // Method java/io/ByteArrayOutputStream.toByteArray:()[B
     187: putfield      #79                 // Field responseBody:[B
     190: aload_0
     191: getfield      #79                 // Field responseBody:[B
     194: areturn

  public java.io.InputStream getResponseBodyAsStream() throws java.io.IOException;
    Code:
       0: aload_0
       1: getfield      #75                 // Field responseStream:Ljava/io/InputStream;
       4: ifnull        12
       7: aload_0
       8: getfield      #75                 // Field responseStream:Ljava/io/InputStream;
      11: areturn
      12: aload_0
      13: getfield      #79                 // Field responseBody:[B
      16: ifnull        44
      19: new           #440                // class java/io/ByteArrayInputStream
      22: dup
      23: aload_0
      24: getfield      #79                 // Field responseBody:[B
      27: invokespecial #443                // Method java/io/ByteArrayInputStream."<init>":([B)V
      30: astore_1
      31: getstatic     #254                // Field LOG:Lorg/apache/commons/logging/Log;
      34: ldc_w         #445                // String re-creating response stream from byte array
      37: invokeinterface #267,  2          // InterfaceMethod org/apache/commons/logging/Log.debug:(Ljava/lang/Object;)V
      42: aload_1
      43: areturn
      44: aconst_null
      45: areturn

  public java.lang.String getResponseBodyAsString() throws java.io.IOException;
    Code:
       0: aconst_null
       1: astore_1
       2: aload_0
       3: invokespecial #449                // Method responseAvailable:()Z
       6: ifeq          14
       9: aload_0
      10: invokevirtual #451                // Method getResponseBody:()[B
      13: astore_1
      14: aload_1
      15: ifnull        27
      18: aload_1
      19: aload_0
      20: invokevirtual #454                // Method getResponseCharSet:()Ljava/lang/String;
      23: invokestatic  #458                // Method org/elasticsearch/hadoop/thirdparty/apache/commons/httpclient/util/EncodingUtil.getString:([BLjava/lang/String;)Ljava/lang/String;
      26: areturn
      27: aconst_null
      28: areturn

  public org.elasticsearch.hadoop.thirdparty.apache.commons.httpclient.Header[] getResponseFooters();
    Code:
       0: aload_0
       1: invokevirtual #280                // Method getResponseTrailerHeaderGroup:()Lorg/elasticsearch/hadoop/thirdparty/apache/commons/httpclient/HeaderGroup;
       4: invokevirtual #328                // Method org/elasticsearch/hadoop/thirdparty/apache/commons/httpclient/HeaderGroup.getAllHeaders:()[Lorg/elasticsearch/hadoop/thirdparty/apache/commons/httpclient/Header;
       7: areturn

  public org.elasticsearch.hadoop.thirdparty.apache.commons.httpclient.Header getResponseFooter(java.lang.String);
    Code:
       0: aload_1
       1: ifnonnull     6
       4: aconst_null
       5: areturn
       6: aload_0
       7: invokevirtual #280                // Method getResponseTrailerHeaderGroup:()Lorg/elasticsearch/hadoop/thirdparty/apache/commons/httpclient/HeaderGroup;
      10: aload_1
      11: invokevirtual #323                // Method org/elasticsearch/hadoop/thirdparty/apache/commons/httpclient/HeaderGroup.getCondensedHeader:(Ljava/lang/String;)Lorg/elasticsearch/hadoop/thirdparty/apache/commons/httpclient/Header;
      14: areturn

  protected void setResponseStream(java.io.InputStream);
    Code:
       0: aload_0
       1: aload_1
       2: putfield      #75                 // Field responseStream:Ljava/io/InputStream;
       5: return

  protected java.io.InputStream getResponseStream();
    Code:
       0: aload_0
       1: getfield      #75                 // Field responseStream:Ljava/io/InputStream;
       4: areturn

  public java.lang.String getStatusText();
    Code:
       0: aload_0
       1: getfield      #65                 // Field statusLine:Lorg/elasticsearch/hadoop/thirdparty/apache/commons/httpclient/StatusLine;
       4: invokevirtual #467                // Method org/elasticsearch/hadoop/thirdparty/apache/commons/httpclient/StatusLine.getReasonPhrase:()Ljava/lang/String;
       7: areturn

  public void setStrictMode(boolean);
    Code:
       0: iload_1
       1: ifeq          14
       4: aload_0
       5: getfield      #88                 // Field params:Lorg/elasticsearch/hadoop/thirdparty/apache/commons/httpclient/params/HttpMethodParams;
       8: invokevirtual #471                // Method org/elasticsearch/hadoop/thirdparty/apache/commons/httpclient/params/HttpMethodParams.makeStrict:()V
      11: goto          21
      14: aload_0
      15: getfield      #88                 // Field params:Lorg/elasticsearch/hadoop/thirdparty/apache/commons/httpclient/params/HttpMethodParams;
      18: invokevirtual #474                // Method org/elasticsearch/hadoop/thirdparty/apache/commons/httpclient/params/HttpMethodParams.makeLenient:()V
      21: return

  public boolean isStrictMode();
    Code:
       0: iconst_0
       1: ireturn

  public void addRequestHeader(java.lang.String, java.lang.String);
    Code:
       0: aload_0
       1: new           #298                // class org/elasticsearch/hadoop/thirdparty/apache/commons/httpclient/Header
       4: dup
       5: aload_1
       6: aload_2
       7: invokespecial #300                // Method org/elasticsearch/hadoop/thirdparty/apache/commons/httpclient/Header."<init>":(Ljava/lang/String;Ljava/lang/String;)V
      10: invokevirtual #478                // Method addRequestHeader:(Lorg/elasticsearch/hadoop/thirdparty/apache/commons/httpclient/Header;)V
      13: return

  protected boolean isConnectionCloseForced();
    Code:
       0: aload_0
       1: getfield      #103                // Field connectionCloseForced:Z
       4: ireturn

  protected void setConnectionCloseForced(boolean);
    Code:
       0: getstatic     #254                // Field LOG:Lorg/apache/commons/logging/Log;
       3: invokeinterface #483,  1          // InterfaceMethod org/apache/commons/logging/Log.isDebugEnabled:()Z
       8: ifeq          39
      11: getstatic     #254                // Field LOG:Lorg/apache/commons/logging/Log;
      14: new           #141                // class java/lang/StringBuffer
      17: dup
      18: invokespecial #142                // Method java/lang/StringBuffer."<init>":()V
      21: ldc_w         #485                // String Force-close connection:
      24: invokevirtual #148                // Method java/lang/StringBuffer.append:(Ljava/lang/String;)Ljava/lang/StringBuffer;
      27: iload_1
      28: invokevirtual #488                // Method java/lang/StringBuffer.append:(Z)Ljava/lang/StringBuffer;
      31: invokevirtual #159                // Method java/lang/StringBuffer.toString:()Ljava/lang/String;
      34: invokeinterface #267,  2          // InterfaceMethod org/apache/commons/logging/Log.debug:(Ljava/lang/Object;)V
      39: aload_0
      40: iload_1
      41: putfield      #103                // Field connectionCloseForced:Z
      44: return

  protected boolean shouldCloseConnection(org.elasticsearch.hadoop.thirdparty.apache.commons.httpclient.HttpConnection);
    Code:
       0: aload_0
       1: invokevirtual #493                // Method isConnectionCloseForced:()Z
       4: ifeq          20
       7: getstatic     #254                // Field LOG:Lorg/apache/commons/logging/Log;
      10: ldc_w         #495                // String Should force-close connection.
      13: invokeinterface #267,  2          // InterfaceMethod org/apache/commons/logging/Log.debug:(Ljava/lang/Object;)V
      18: iconst_1
      19: ireturn
      20: aconst_null
      21: astore_2
      22: aload_1
      23: invokevirtual #500                // Method org/elasticsearch/hadoop/thirdparty/apache/commons/httpclient/HttpConnection.isTransparent:()Z
      26: ifne          40
      29: aload_0
      30: getfield      #67                 // Field responseHeaders:Lorg/elasticsearch/hadoop/thirdparty/apache/commons/httpclient/HeaderGroup;
      33: ldc_w         #502                // String proxy-connection
      36: invokevirtual #505                // Method org/elasticsearch/hadoop/thirdparty/apache/commons/httpclient/HeaderGroup.getFirstHeader:(Ljava/lang/String;)Lorg/elasticsearch/hadoop/thirdparty/apache/commons/httpclient/Header;
      39: astore_2
      40: aload_2
      41: ifnonnull     55
      44: aload_0
      45: getfield      #67                 // Field responseHeaders:Lorg/elasticsearch/hadoop/thirdparty/apache/commons/httpclient/HeaderGroup;
      48: ldc_w         #507                // String connection
      51: invokevirtual #505                // Method org/elasticsearch/hadoop/thirdparty/apache/commons/httpclient/HeaderGroup.getFirstHeader:(Ljava/lang/String;)Lorg/elasticsearch/hadoop/thirdparty/apache/commons/httpclient/Header;
      54: astore_2
      55: aload_2
      56: ifnonnull     70
      59: aload_0
      60: getfield      #63                 // Field requestHeaders:Lorg/elasticsearch/hadoop/thirdparty/apache/commons/httpclient/HeaderGroup;
      63: ldc_w         #507                // String connection
      66: invokevirtual #505                // Method org/elasticsearch/hadoop/thirdparty/apache/commons/httpclient/HeaderGroup.getFirstHeader:(Ljava/lang/String;)Lorg/elasticsearch/hadoop/thirdparty/apache/commons/httpclient/Header;
      69: astore_2
      70: aload_2
      71: ifnull        230
      74: aload_2
      75: invokevirtual #357                // Method org/elasticsearch/hadoop/thirdparty/apache/commons/httpclient/NameValuePair.getValue:()Ljava/lang/String;
      78: ldc_w         #508                // String close
      81: invokevirtual #512                // Method java/lang/String.equalsIgnoreCase:(Ljava/lang/String;)Z
      84: ifeq          131
      87: getstatic     #254                // Field LOG:Lorg/apache/commons/logging/Log;
      90: invokeinterface #483,  1          // InterfaceMethod org/apache/commons/logging/Log.isDebugEnabled:()Z
      95: ifeq          129
      98: getstatic     #254                // Field LOG:Lorg/apache/commons/logging/Log;
     101: new           #141                // class java/lang/StringBuffer
     104: dup
     105: invokespecial #142                // Method java/lang/StringBuffer."<init>":()V
     108: ldc_w         #514                // String Should close connection in response to directive:
     111: invokevirtual #148                // Method java/lang/StringBuffer.append:(Ljava/lang/String;)Ljava/lang/StringBuffer;
     114: aload_2
     115: invokevirtual #357                // Method org/elasticsearch/hadoop/thirdparty/apache/commons/httpclient/NameValuePair.getValue:()Ljava/lang/String;
     118: invokevirtual #148                // Method java/lang/StringBuffer.append:(Ljava/lang/String;)Ljava/lang/StringBuffer;
     121: invokevirtual #159                // Method java/lang/StringBuffer.toString:()Ljava/lang/String;
     124: invokeinterface #267,  2          // InterfaceMethod org/apache/commons/logging/Log.debug:(Ljava/lang/Object;)V
     129: iconst_1
     130: ireturn
     131: aload_2
     132: invokevirtual #357                // Method org/elasticsearch/hadoop/thirdparty/apache/commons/httpclient/NameValuePair.getValue:()Ljava/lang/String;
     135: ldc_w         #516                // String keep-alive
     138: invokevirtual #512                // Method java/lang/String.equalsIgnoreCase:(Ljava/lang/String;)Z
     141: ifeq          188
     144: getstatic     #254                // Field LOG:Lorg/apache/commons/logging/Log;
     147: invokeinterface #483,  1          // InterfaceMethod org/apache/commons/logging/Log.isDebugEnabled:()Z
     152: ifeq          186
     155: getstatic     #254                // Field LOG:Lorg/apache/commons/logging/Log;
     158: new           #141                // class java/lang/StringBuffer
     161: dup
     162: invokespecial #142                // Method java/lang/StringBuffer."<init>":()V
     165: ldc_w         #518                // String Should NOT close connection in response to directive:
     168: invokevirtual #148                // Method java/lang/StringBuffer.append:(Ljava/lang/String;)Ljava/lang/StringBuffer;
     171: aload_2
     172: invokevirtual #357                // Method org/elasticsearch/hadoop/thirdparty/apache/commons/httpclient/NameValuePair.getValue:()Ljava/lang/String;
     175: invokevirtual #148                // Method java/lang/StringBuffer.append:(Ljava/lang/String;)Ljava/lang/StringBuffer;
     178: invokevirtual #159                // Method java/lang/StringBuffer.toString:()Ljava/lang/String;
     181: invokeinterface #267,  2          // InterfaceMethod org/apache/commons/logging/Log.debug:(Ljava/lang/Object;)V
     186: iconst_0
     187: ireturn
     188: getstatic     #254                // Field LOG:Lorg/apache/commons/logging/Log;
     191: invokeinterface #483,  1          // InterfaceMethod org/apache/commons/logging/Log.isDebugEnabled:()Z
     196: ifeq          230
     199: getstatic     #254                // Field LOG:Lorg/apache/commons/logging/Log;
     202: new           #141                // class java/lang/StringBuffer
     205: dup
     206: invokespecial #142                // Method java/lang/StringBuffer."<init>":()V
     209: ldc_w         #520                // String Unknown directive:
     212: invokevirtual #148                // Method java/lang/StringBuffer.append:(Ljava/lang/String;)Ljava/lang/StringBuffer;
     215: aload_2
     216: invokevirtual #523                // Method org/elasticsearch/hadoop/thirdparty/apache/commons/httpclient/Header.toExternalForm:()Ljava/lang/String;
     219: invokevirtual #148                // Method java/lang/StringBuffer.append:(Ljava/lang/String;)Ljava/lang/StringBuffer;
     222: invokevirtual #159                // Method java/lang/StringBuffer.toString:()Ljava/lang/String;
     225: invokeinterface #267,  2          // InterfaceMethod org/apache/commons/logging/Log.debug:(Ljava/lang/Object;)V
     230: getstatic     #254                // Field LOG:Lorg/apache/commons/logging/Log;
     233: ldc_w         #525                // String Resorting to protocol version default close connection policy
     236: invokeinterface #267,  2          // InterfaceMethod org/apache/commons/logging/Log.debug:(Ljava/lang/Object;)V
     241: aload_0
     242: getfield      #105                // Field effectiveVersion:Lorg/elasticsearch/hadoop/thirdparty/apache/commons/httpclient/HttpVersion;
     245: getstatic     #232                // Field org/elasticsearch/hadoop/thirdparty/apache/commons/httpclient/HttpVersion.HTTP_1_1:Lorg/elasticsearch/hadoop/thirdparty/apache/commons/httpclient/HttpVersion;
     248: invokevirtual #528                // Method org/elasticsearch/hadoop/thirdparty/apache/commons/httpclient/HttpVersion.greaterEquals:(Lorg/elasticsearch/hadoop/thirdparty/apache/commons/httpclient/HttpVersion;)Z
     251: ifeq          302
     254: getstatic     #254                // Field LOG:Lorg/apache/commons/logging/Log;
     257: invokeinterface #483,  1          // InterfaceMethod org/apache/commons/logging/Log.isDebugEnabled:()Z
     262: ifeq          347
     265: getstatic     #254                // Field LOG:Lorg/apache/commons/logging/Log;
     268: new           #141                // class java/lang/StringBuffer
     271: dup
     272: invokespecial #142                // Method java/lang/StringBuffer."<init>":()V
     275: ldc_w         #530                // String Should NOT close connection, using
     278: invokevirtual #148                // Method java/lang/StringBuffer.append:(Ljava/lang/String;)Ljava/lang/StringBuffer;
     281: aload_0
     282: getfield      #105                // Field effectiveVersion:Lorg/elasticsearch/hadoop/thirdparty/apache/commons/httpclient/HttpVersion;
     285: invokevirtual #531                // Method org/elasticsearch/hadoop/thirdparty/apache/commons/httpclient/HttpVersion.toString:()Ljava/lang/String;
     288: invokevirtual #148                // Method java/lang/StringBuffer.append:(Ljava/lang/String;)Ljava/lang/StringBuffer;
     291: invokevirtual #159                // Method java/lang/StringBuffer.toString:()Ljava/lang/String;
     294: invokeinterface #267,  2          // InterfaceMethod org/apache/commons/logging/Log.debug:(Ljava/lang/Object;)V
     299: goto          347
     302: getstatic     #254                // Field LOG:Lorg/apache/commons/logging/Log;
     305: invokeinterface #483,  1          // InterfaceMethod org/apache/commons/logging/Log.isDebugEnabled:()Z
     310: ifeq          347
     313: getstatic     #254                // Field LOG:Lorg/apache/commons/logging/Log;
     316: new           #141                // class java/lang/StringBuffer
     319: dup
     320: invokespecial #142                // Method java/lang/StringBuffer."<init>":()V
     323: ldc_w         #533                // String Should close connection, using
     326: invokevirtual #148                // Method java/lang/StringBuffer.append:(Ljava/lang/String;)Ljava/lang/StringBuffer;
     329: aload_0
     330: getfield      #105                // Field effectiveVersion:Lorg/elasticsearch/hadoop/thirdparty/apache/commons/httpclient/HttpVersion;
     333: invokevirtual #531                // Method org/elasticsearch/hadoop/thirdparty/apache/commons/httpclient/HttpVersion.toString:()Ljava/lang/String;
     336: invokevirtual #148                // Method java/lang/StringBuffer.append:(Ljava/lang/String;)Ljava/lang/StringBuffer;
     339: invokevirtual #159                // Method java/lang/StringBuffer.toString:()Ljava/lang/String;
     342: invokeinterface #267,  2          // InterfaceMethod org/apache/commons/logging/Log.debug:(Ljava/lang/Object;)V
     347: aload_0
     348: getfield      #105                // Field effectiveVersion:Lorg/elasticsearch/hadoop/thirdparty/apache/commons/httpclient/HttpVersion;
     351: getstatic     #239                // Field org/elasticsearch/hadoop/thirdparty/apache/commons/httpclient/HttpVersion.HTTP_1_0:Lorg/elasticsearch/hadoop/thirdparty/apache/commons/httpclient/HttpVersion;
     354: invokevirtual #536                // Method org/elasticsearch/hadoop/thirdparty/apache/commons/httpclient/HttpVersion.lessEquals:(Lorg/elasticsearch/hadoop/thirdparty/apache/commons/httpclient/HttpVersion;)Z
     357: ireturn

  private void checkExecuteConditions(org.elasticsearch.hadoop.thirdparty.apache.commons.httpclient.HttpState, org.elasticsearch.hadoop.thirdparty.apache.commons.httpclient.HttpConnection) throws org.elasticsearch.hadoop.thirdparty.apache.commons.httpclient.HttpException;
    Code:
       0: aload_1
       1: ifnonnull     15
       4: new           #116                // class java/lang/IllegalArgumentException
       7: dup
       8: ldc_w         #544                // String HttpState parameter may not be null
      11: invokespecial #161                // Method java/lang/IllegalArgumentException."<init>":(Ljava/lang/String;)V
      14: athrow
      15: aload_2
      16: ifnonnull     30
      19: new           #116                // class java/lang/IllegalArgumentException
      22: dup
      23: ldc_w         #546                // String HttpConnection parameter may not be null
      26: invokespecial #161                // Method java/lang/IllegalArgumentException."<init>":(Ljava/lang/String;)V
      29: athrow
      30: aload_0
      31: getfield      #107                // Field aborted:Z
      34: ifeq          48
      37: new           #118                // class java/lang/IllegalStateException
      40: dup
      41: ldc_w         #548                // String Method has been aborted
      44: invokespecial #549                // Method java/lang/IllegalStateException."<init>":(Ljava/lang/String;)V
      47: athrow
      48: aload_0
      49: invokevirtual #552                // Method validate:()Z
      52: ifne          66
      55: new           #554                // class org/elasticsearch/hadoop/thirdparty/apache/commons/httpclient/ProtocolException
      58: dup
      59: ldc_w         #556                // String HttpMethodBase object not valid
      62: invokespecial #557                // Method org/elasticsearch/hadoop/thirdparty/apache/commons/httpclient/ProtocolException."<init>":(Ljava/lang/String;)V
      65: athrow
      66: return

  public int execute(org.elasticsearch.hadoop.thirdparty.apache.commons.httpclient.HttpState, org.elasticsearch.hadoop.thirdparty.apache.commons.httpclient.HttpConnection) throws org.elasticsearch.hadoop.thirdparty.apache.commons.httpclient.HttpException, java.io.IOException;
    Code:
       0: getstatic     #254                // Field LOG:Lorg/apache/commons/logging/Log;
       3: ldc_w         #563                // String enter HttpMethodBase.execute(HttpState, HttpConnection)
       6: invokeinterface #262,  2          // InterfaceMethod org/apache/commons/logging/Log.trace:(Ljava/lang/Object;)V
      11: aload_0
      12: aload_2
      13: putfield      #77                 // Field responseConnection:Lorg/elasticsearch/hadoop/thirdparty/apache/commons/httpclient/HttpConnection;
      16: aload_0
      17: aload_1
      18: aload_2
      19: invokespecial #565                // Method checkExecuteConditions:(Lorg/elasticsearch/hadoop/thirdparty/apache/commons/httpclient/HttpState;Lorg/elasticsearch/hadoop/thirdparty/apache/commons/httpclient/HttpConnection;)V
      22: aload_0
      23: aconst_null
      24: putfield      #65                 // Field statusLine:Lorg/elasticsearch/hadoop/thirdparty/apache/commons/httpclient/StatusLine;
      27: aload_0
      28: iconst_0
      29: putfield      #103                // Field connectionCloseForced:Z
      32: aload_2
      33: aconst_null
      34: invokevirtual #568                // Method org/elasticsearch/hadoop/thirdparty/apache/commons/httpclient/HttpConnection.setLastResponseInputStream:(Ljava/io/InputStream;)V
      37: aload_0
      38: getfield      #105                // Field effectiveVersion:Lorg/elasticsearch/hadoop/thirdparty/apache/commons/httpclient/HttpVersion;
      41: ifnonnull     55
      44: aload_0
      45: aload_0
      46: getfield      #88                 // Field params:Lorg/elasticsearch/hadoop/thirdparty/apache/commons/httpclient/params/HttpMethodParams;
      49: invokevirtual #247                // Method org/elasticsearch/hadoop/thirdparty/apache/commons/httpclient/params/HttpMethodParams.getVersion:()Lorg/elasticsearch/hadoop/thirdparty/apache/commons/httpclient/HttpVersion;
      52: putfield      #105                // Field effectiveVersion:Lorg/elasticsearch/hadoop/thirdparty/apache/commons/httpclient/HttpVersion;
      55: aload_0
      56: aload_1
      57: aload_2
      58: invokevirtual #571                // Method writeRequest:(Lorg/elasticsearch/hadoop/thirdparty/apache/commons/httpclient/HttpState;Lorg/elasticsearch/hadoop/thirdparty/apache/commons/httpclient/HttpConnection;)V
      61: aload_0
      62: iconst_1
      63: putfield      #109                // Field requestSent:Z
      66: aload_0
      67: aload_1
      68: aload_2
      69: invokevirtual #574                // Method readResponse:(Lorg/elasticsearch/hadoop/thirdparty/apache/commons/httpclient/HttpState;Lorg/elasticsearch/hadoop/thirdparty/apache/commons/httpclient/HttpConnection;)V
      72: aload_0
      73: iconst_1
      74: putfield      #97                 // Field used:Z
      77: aload_0
      78: getfield      #65                 // Field statusLine:Lorg/elasticsearch/hadoop/thirdparty/apache/commons/httpclient/StatusLine;
      81: invokevirtual #337                // Method org/elasticsearch/hadoop/thirdparty/apache/commons/httpclient/StatusLine.getStatusCode:()I
      84: ireturn

  public void abort();
    Code:
       0: aload_0
       1: getfield      #107                // Field aborted:Z
       4: ifeq          8
       7: return
       8: aload_0
       9: iconst_1
      10: putfield      #107                // Field aborted:Z
      13: aload_0
      14: getfield      #77                 // Field responseConnection:Lorg/elasticsearch/hadoop/thirdparty/apache/commons/httpclient/HttpConnection;
      17: astore_1
      18: aload_1
      19: ifnull        26
      22: aload_1
      23: invokevirtual #576                // Method org/elasticsearch/hadoop/thirdparty/apache/commons/httpclient/HttpConnection.close:()V
      26: return

  public boolean hasBeenUsed();
    Code:
       0: aload_0
       1: getfield      #97                 // Field used:Z
       4: ireturn

  public void recycle();
    Code:
       0: getstatic     #254                // Field LOG:Lorg/apache/commons/logging/Log;
       3: ldc_w         #580                // String enter HttpMethodBase.recycle()
       6: invokeinterface #262,  2          // InterfaceMethod org/apache/commons/logging/Log.trace:(Ljava/lang/Object;)V
      11: aload_0
      12: invokevirtual #583                // Method releaseConnection:()V
      15: aload_0
      16: aconst_null
      17: putfield      #71                 // Field path:Ljava/lang/String;
      20: aload_0
      21: iconst_0
      22: putfield      #81                 // Field followRedirects:Z
      25: aload_0
      26: iconst_1
      27: putfield      #83                 // Field doAuthentication:Z
      30: aload_0
      31: aconst_null
      32: putfield      #73                 // Field queryString:Ljava/lang/String;
      35: aload_0
      36: invokevirtual #271                // Method getRequestHeaderGroup:()Lorg/elasticsearch/hadoop/thirdparty/apache/commons/httpclient/HeaderGroup;
      39: invokevirtual #586                // Method org/elasticsearch/hadoop/thirdparty/apache/commons/httpclient/HeaderGroup.clear:()V
      42: aload_0
      43: invokevirtual #332                // Method getResponseHeaderGroup:()Lorg/elasticsearch/hadoop/thirdparty/apache/commons/httpclient/HeaderGroup;
      46: invokevirtual #586                // Method org/elasticsearch/hadoop/thirdparty/apache/commons/httpclient/HeaderGroup.clear:()V
      49: aload_0
      50: invokevirtual #280                // Method getResponseTrailerHeaderGroup:()Lorg/elasticsearch/hadoop/thirdparty/apache/commons/httpclient/HeaderGroup;
      53: invokevirtual #586                // Method org/elasticsearch/hadoop/thirdparty/apache/commons/httpclient/HeaderGroup.clear:()V
      56: aload_0
      57: aconst_null
      58: putfield      #65                 // Field statusLine:Lorg/elasticsearch/hadoop/thirdparty/apache/commons/httpclient/StatusLine;
      61: aload_0
      62: aconst_null
      63: putfield      #105                // Field effectiveVersion:Lorg/elasticsearch/hadoop/thirdparty/apache/commons/httpclient/HttpVersion;
      66: aload_0
      67: iconst_0
      68: putfield      #107                // Field aborted:Z
      71: aload_0
      72: iconst_0
      73: putfield      #97                 // Field used:Z
      76: aload_0
      77: new           #85                 // class org/elasticsearch/hadoop/thirdparty/apache/commons/httpclient/params/HttpMethodParams
      80: dup
      81: invokespecial #86                 // Method org/elasticsearch/hadoop/thirdparty/apache/commons/httpclient/params/HttpMethodParams."<init>":()V
      84: putfield      #88                 // Field params:Lorg/elasticsearch/hadoop/thirdparty/apache/commons/httpclient/params/HttpMethodParams;
      87: aload_0
      88: aconst_null
      89: putfield      #79                 // Field responseBody:[B
      92: aload_0
      93: iconst_0
      94: putfield      #99                 // Field recoverableExceptionCount:I
      97: aload_0
      98: iconst_0
      99: putfield      #103                // Field connectionCloseForced:Z
     102: aload_0
     103: getfield      #93                 // Field hostAuthState:Lorg/elasticsearch/hadoop/thirdparty/apache/commons/httpclient/auth/AuthState;
     106: invokevirtual #589                // Method org/elasticsearch/hadoop/thirdparty/apache/commons/httpclient/auth/AuthState.invalidate:()V
     109: aload_0
     110: getfield      #95                 // Field proxyAuthState:Lorg/elasticsearch/hadoop/thirdparty/apache/commons/httpclient/auth/AuthState;
     113: invokevirtual #589                // Method org/elasticsearch/hadoop/thirdparty/apache/commons/httpclient/auth/AuthState.invalidate:()V
     116: aload_0
     117: aconst_null
     118: putfield      #111                // Field cookiespec:Lorg/elasticsearch/hadoop/thirdparty/apache/commons/httpclient/cookie/CookieSpec;
     121: aload_0
     122: iconst_0
     123: putfield      #109                // Field requestSent:Z
     126: return

  public void releaseConnection();
    Code:
       0: aload_0
       1: getfield      #75                 // Field responseStream:Ljava/io/InputStream;
       4: ifnull        18
       7: aload_0
       8: getfield      #75                 // Field responseStream:Ljava/io/InputStream;
      11: invokevirtual #590                // Method java/io/InputStream.close:()V
      14: goto          18
      17: astore_1
      18: jsr           30
      21: goto          37
      24: astore_2
      25: jsr           30
      28: aload_2
      29: athrow
      30: astore_3
      31: aload_0
      32: invokespecial #593                // Method ensureConnectionRelease:()V
      35: ret           3
      37: return
    Exception table:
       from    to  target type
           7    14    17   Class java/io/IOException
           0    24    24   any

  public void removeRequestHeader(java.lang.String);
    Code:
       0: aload_0
       1: invokevirtual #271                // Method getRequestHeaderGroup:()Lorg/elasticsearch/hadoop/thirdparty/apache/commons/httpclient/HeaderGroup;
       4: aload_1
       5: invokevirtual #312                // Method org/elasticsearch/hadoop/thirdparty/apache/commons/httpclient/HeaderGroup.getHeaders:(Ljava/lang/String;)[Lorg/elasticsearch/hadoop/thirdparty/apache/commons/httpclient/Header;
       8: astore_2
       9: iconst_0
      10: istore_3
      11: goto          27
      14: aload_0
      15: invokevirtual #271                // Method getRequestHeaderGroup:()Lorg/elasticsearch/hadoop/thirdparty/apache/commons/httpclient/HeaderGroup;
      18: aload_2
      19: iload_3
      20: aaload
      21: invokevirtual #315                // Method org/elasticsearch/hadoop/thirdparty/apache/commons/httpclient/HeaderGroup.removeHeader:(Lorg/elasticsearch/hadoop/thirdparty/apache/commons/httpclient/Header;)V
      24: iinc          3, 1
      27: iload_3
      28: aload_2
      29: arraylength
      30: if_icmplt     14
      33: return

  public void removeRequestHeader(org.elasticsearch.hadoop.thirdparty.apache.commons.httpclient.Header);
    Code:
       0: aload_1
       1: ifnonnull     5
       4: return
       5: aload_0
       6: invokevirtual #271                // Method getRequestHeaderGroup:()Lorg/elasticsearch/hadoop/thirdparty/apache/commons/httpclient/HeaderGroup;
       9: aload_1
      10: invokevirtual #315                // Method org/elasticsearch/hadoop/thirdparty/apache/commons/httpclient/HeaderGroup.removeHeader:(Lorg/elasticsearch/hadoop/thirdparty/apache/commons/httpclient/Header;)V
      13: return

  public boolean validate();
    Code:
       0: iconst_1
       1: ireturn

  private org.elasticsearch.hadoop.thirdparty.apache.commons.httpclient.cookie.CookieSpec getCookieSpec(org.elasticsearch.hadoop.thirdparty.apache.commons.httpclient.HttpState);
    Code:
       0: aload_0
       1: getfield      #111                // Field cookiespec:Lorg/elasticsearch/hadoop/thirdparty/apache/commons/httpclient/cookie/CookieSpec;
       4: ifnonnull     64
       7: aload_1
       8: invokevirtual #603                // Method org/elasticsearch/hadoop/thirdparty/apache/commons/httpclient/HttpState.getCookiePolicy:()I
      11: istore_2
      12: iload_2
      13: iconst_m1
      14: if_icmpne     34
      17: aload_0
      18: aload_0
      19: getfield      #88                 // Field params:Lorg/elasticsearch/hadoop/thirdparty/apache/commons/httpclient/params/HttpMethodParams;
      22: invokevirtual #605                // Method org/elasticsearch/hadoop/thirdparty/apache/commons/httpclient/params/HttpMethodParams.getCookiePolicy:()Ljava/lang/String;
      25: invokestatic  #610                // Method org/elasticsearch/hadoop/thirdparty/apache/commons/httpclient/cookie/CookiePolicy.getCookieSpec:(Ljava/lang/String;)Lorg/elasticsearch/hadoop/thirdparty/apache/commons/httpclient/cookie/CookieSpec;
      28: putfield      #111                // Field cookiespec:Lorg/elasticsearch/hadoop/thirdparty/apache/commons/httpclient/cookie/CookieSpec;
      31: goto          42
      34: aload_0
      35: iload_2
      36: invokestatic  #614                // Method org/elasticsearch/hadoop/thirdparty/apache/commons/httpclient/cookie/CookiePolicy.getSpecByPolicy:(I)Lorg/elasticsearch/hadoop/thirdparty/apache/commons/httpclient/cookie/CookieSpec;
      39: putfield      #111                // Field cookiespec:Lorg/elasticsearch/hadoop/thirdparty/apache/commons/httpclient/cookie/CookieSpec;
      42: aload_0
      43: getfield      #111                // Field cookiespec:Lorg/elasticsearch/hadoop/thirdparty/apache/commons/httpclient/cookie/CookieSpec;
      46: aload_0
      47: getfield      #88                 // Field params:Lorg/elasticsearch/hadoop/thirdparty/apache/commons/httpclient/params/HttpMethodParams;
      50: ldc_w         #616                // String http.dateparser.patterns
      53: invokevirtual #620                // Method org/elasticsearch/hadoop/thirdparty/apache/commons/httpclient/params/DefaultHttpParams.getParameter:(Ljava/lang/String;)Ljava/lang/Object;
      56: checkcast     #622                // class java/util/Collection
      59: invokeinterface #628,  2          // InterfaceMethod org/elasticsearch/hadoop/thirdparty/apache/commons/httpclient/cookie/CookieSpec.setValidDateFormats:(Ljava/util/Collection;)V
      64: aload_0
      65: getfield      #111                // Field cookiespec:Lorg/elasticsearch/hadoop/thirdparty/apache/commons/httpclient/cookie/CookieSpec;
      68: areturn

  protected void addCookieRequestHeader(org.elasticsearch.hadoop.thirdparty.apache.commons.httpclient.HttpState, org.elasticsearch.hadoop.thirdparty.apache.commons.httpclient.HttpConnection) throws java.io.IOException, org.elasticsearch.hadoop.thirdparty.apache.commons.httpclient.HttpException;
    Code:
       0: getstatic     #254                // Field LOG:Lorg/apache/commons/logging/Log;
       3: ldc_w         #631                // String enter HttpMethodBase.addCookieRequestHeader(HttpState, HttpConnection)
       6: invokeinterface #262,  2          // InterfaceMethod org/apache/commons/logging/Log.trace:(Ljava/lang/Object;)V
      11: aload_0
      12: invokevirtual #271                // Method getRequestHeaderGroup:()Lorg/elasticsearch/hadoop/thirdparty/apache/commons/httpclient/HeaderGroup;
      15: ldc_w         #633                // String Cookie
      18: invokevirtual #312                // Method org/elasticsearch/hadoop/thirdparty/apache/commons/httpclient/HeaderGroup.getHeaders:(Ljava/lang/String;)[Lorg/elasticsearch/hadoop/thirdparty/apache/commons/httpclient/Header;
      21: astore_3
      22: iconst_0
      23: istore        4
      25: goto          54
      28: aload_3
      29: iload         4
      31: aaload
      32: astore        5
      34: aload         5
      36: invokevirtual #636                // Method org/elasticsearch/hadoop/thirdparty/apache/commons/httpclient/Header.isAutogenerated:()Z
      39: ifeq          51
      42: aload_0
      43: invokevirtual #271                // Method getRequestHeaderGroup:()Lorg/elasticsearch/hadoop/thirdparty/apache/commons/httpclient/HeaderGroup;
      46: aload         5
      48: invokevirtual #315                // Method org/elasticsearch/hadoop/thirdparty/apache/commons/httpclient/HeaderGroup.removeHeader:(Lorg/elasticsearch/hadoop/thirdparty/apache/commons/httpclient/Header;)V
      51: iinc          4, 1
      54: iload         4
      56: aload_3
      57: arraylength
      58: if_icmplt     28
      61: aload_0
      62: aload_1
      63: invokespecial #638                // Method getCookieSpec:(Lorg/elasticsearch/hadoop/thirdparty/apache/commons/httpclient/HttpState;)Lorg/elasticsearch/hadoop/thirdparty/apache/commons/httpclient/cookie/CookieSpec;
      66: astore        5
      68: aload_0
      69: getfield      #88                 // Field params:Lorg/elasticsearch/hadoop/thirdparty/apache/commons/httpclient/params/HttpMethodParams;
      72: invokevirtual #641                // Method org/elasticsearch/hadoop/thirdparty/apache/commons/httpclient/params/HttpMethodParams.getVirtualHost:()Ljava/lang/String;
      75: astore        6
      77: aload         6
      79: ifnonnull     88
      82: aload_2
      83: invokevirtual #644                // Method org/elasticsearch/hadoop/thirdparty/apache/commons/httpclient/HttpConnection.getHost:()Ljava/lang/String;
      86: astore        6
      88: aload         5
      90: aload         6
      92: aload_2
      93: invokevirtual #645                // Method org/elasticsearch/hadoop/thirdparty/apache/commons/httpclient/HttpConnection.getPort:()I
      96: aload_0
      97: invokevirtual #646                // Method getPath:()Ljava/lang/String;
     100: aload_2
     101: invokevirtual #649                // Method org/elasticsearch/hadoop/thirdparty/apache/commons/httpclient/HttpConnection.isSecure:()Z
     104: aload_1
     105: invokevirtual #653                // Method org/elasticsearch/hadoop/thirdparty/apache/commons/httpclient/HttpState.getCookies:()[Lorg/elasticsearch/hadoop/thirdparty/apache/commons/httpclient/Cookie;
     108: invokeinterface #657,  6          // InterfaceMethod org/elasticsearch/hadoop/thirdparty/apache/commons/httpclient/cookie/CookieSpec.match:(Ljava/lang/String;ILjava/lang/String;Z[Lorg/elasticsearch/hadoop/thirdparty/apache/commons/httpclient/Cookie;)[Lorg/elasticsearch/hadoop/thirdparty/apache/commons/httpclient/Cookie;
     113: astore        7
     115: aload         7
     117: ifnull        224
     120: aload         7
     122: arraylength
     123: ifle          224
     126: aload_0
     127: invokevirtual #393                // Method getParams:()Lorg/elasticsearch/hadoop/thirdparty/apache/commons/httpclient/params/HttpMethodParams;
     130: ldc_w         #659                // String http.protocol.single-cookie-header
     133: invokevirtual #662                // Method org/elasticsearch/hadoop/thirdparty/apache/commons/httpclient/params/DefaultHttpParams.isParameterTrue:(Ljava/lang/String;)Z
     136: ifeq          173
     139: aload         5
     141: aload         7
     143: invokeinterface #666,  2          // InterfaceMethod org/elasticsearch/hadoop/thirdparty/apache/commons/httpclient/cookie/CookieSpec.formatCookies:([Lorg/elasticsearch/hadoop/thirdparty/apache/commons/httpclient/Cookie;)Ljava/lang/String;
     148: astore        8
     150: aload_0
     151: invokevirtual #271                // Method getRequestHeaderGroup:()Lorg/elasticsearch/hadoop/thirdparty/apache/commons/httpclient/HeaderGroup;
     154: new           #298                // class org/elasticsearch/hadoop/thirdparty/apache/commons/httpclient/Header
     157: dup
     158: ldc_w         #633                // String Cookie
     161: aload         8
     163: iconst_1
     164: invokespecial #669                // Method org/elasticsearch/hadoop/thirdparty/apache/commons/httpclient/Header."<init>":(Ljava/lang/String;Ljava/lang/String;Z)V
     167: invokevirtual #274                // Method org/elasticsearch/hadoop/thirdparty/apache/commons/httpclient/HeaderGroup.addHeader:(Lorg/elasticsearch/hadoop/thirdparty/apache/commons/httpclient/Header;)V
     170: goto          224
     173: iconst_0
     174: istore        8
     176: goto          216
     179: aload         5
     181: aload         7
     183: iload         8
     185: aaload
     186: invokeinterface #673,  2          // InterfaceMethod org/elasticsearch/hadoop/thirdparty/apache/commons/httpclient/cookie/CookieSpec.formatCookie:(Lorg/elasticsearch/hadoop/thirdparty/apache/commons/httpclient/Cookie;)Ljava/lang/String;
     191: astore        9
     193: aload_0
     194: invokevirtual #271                // Method getRequestHeaderGroup:()Lorg/elasticsearch/hadoop/thirdparty/apache/commons/httpclient/HeaderGroup;
     197: new           #298                // class org/elasticsearch/hadoop/thirdparty/apache/commons/httpclient/Header
     200: dup
     201: ldc_w         #633                // String Cookie
     204: aload         9
     206: iconst_1
     207: invokespecial #669                // Method org/elasticsearch/hadoop/thirdparty/apache/commons/httpclient/Header."<init>":(Ljava/lang/String;Ljava/lang/String;Z)V
     210: invokevirtual #274                // Method org/elasticsearch/hadoop/thirdparty/apache/commons/httpclient/HeaderGroup.addHeader:(Lorg/elasticsearch/hadoop/thirdparty/apache/commons/httpclient/Header;)V
     213: iinc          8, 1
     216: iload         8
     218: aload         7
     220: arraylength
     221: if_icmplt     179
     224: return

  protected void addHostRequestHeader(org.elasticsearch.hadoop.thirdparty.apache.commons.httpclient.HttpState, org.elasticsearch.hadoop.thirdparty.apache.commons.httpclient.HttpConnection) throws java.io.IOException, org.elasticsearch.hadoop.thirdparty.apache.commons.httpclient.HttpException;
    Code:
       0: getstatic     #254                // Field LOG:Lorg/apache/commons/logging/Log;
       3: ldc_w         #683                // String enter HttpMethodBase.addHostRequestHeader(HttpState, HttpConnection)
       6: invokeinterface #262,  2          // InterfaceMethod org/apache/commons/logging/Log.trace:(Ljava/lang/Object;)V
      11: aload_0
      12: getfield      #88                 // Field params:Lorg/elasticsearch/hadoop/thirdparty/apache/commons/httpclient/params/HttpMethodParams;
      15: invokevirtual #641                // Method org/elasticsearch/hadoop/thirdparty/apache/commons/httpclient/params/HttpMethodParams.getVirtualHost:()Ljava/lang/String;
      18: astore_3
      19: aload_3
      20: ifnull        54
      23: getstatic     #254                // Field LOG:Lorg/apache/commons/logging/Log;
      26: new           #141                // class java/lang/StringBuffer
      29: dup
      30: invokespecial #142                // Method java/lang/StringBuffer."<init>":()V
      33: ldc_w         #685                // String Using virtual host name:
      36: invokevirtual #148                // Method java/lang/StringBuffer.append:(Ljava/lang/String;)Ljava/lang/StringBuffer;
      39: aload_3
      40: invokevirtual #148                // Method java/lang/StringBuffer.append:(Ljava/lang/String;)Ljava/lang/StringBuffer;
      43: invokevirtual #159                // Method java/lang/StringBuffer.toString:()Ljava/lang/String;
      46: invokeinterface #267,  2          // InterfaceMethod org/apache/commons/logging/Log.debug:(Ljava/lang/Object;)V
      51: goto          59
      54: aload_2
      55: invokevirtual #644                // Method org/elasticsearch/hadoop/thirdparty/apache/commons/httpclient/HttpConnection.getHost:()Ljava/lang/String;
      58: astore_3
      59: aload_2
      60: invokevirtual #645                // Method org/elasticsearch/hadoop/thirdparty/apache/commons/httpclient/HttpConnection.getPort:()I
      63: istore        4
      65: getstatic     #254                // Field LOG:Lorg/apache/commons/logging/Log;
      68: invokeinterface #483,  1          // InterfaceMethod org/apache/commons/logging/Log.isDebugEnabled:()Z
      73: ifeq          87
      76: getstatic     #254                // Field LOG:Lorg/apache/commons/logging/Log;
      79: ldc_w         #687                // String Adding Host request header
      82: invokeinterface #267,  2          // InterfaceMethod org/apache/commons/logging/Log.debug:(Ljava/lang/Object;)V
      87: aload_2
      88: invokevirtual #688                // Method org/elasticsearch/hadoop/thirdparty/apache/commons/httpclient/HttpConnection.getProtocol:()Lorg/elasticsearch/hadoop/thirdparty/apache/commons/httpclient/protocol/Protocol;
      91: invokevirtual #190                // Method org/elasticsearch/hadoop/thirdparty/apache/commons/httpclient/protocol/Protocol.getDefaultPort:()I
      94: iload         4
      96: if_icmpeq     124
      99: new           #141                // class java/lang/StringBuffer
     102: dup
     103: invokespecial #142                // Method java/lang/StringBuffer."<init>":()V
     106: aload_3
     107: invokevirtual #148                // Method java/lang/StringBuffer.append:(Ljava/lang/String;)Ljava/lang/StringBuffer;
     110: ldc           #192                // String :
     112: invokevirtual #148                // Method java/lang/StringBuffer.append:(Ljava/lang/String;)Ljava/lang/StringBuffer;
     115: iload         4
     117: invokevirtual #195                // Method java/lang/StringBuffer.append:(I)Ljava/lang/StringBuffer;
     120: invokevirtual #159                // Method java/lang/StringBuffer.toString:()Ljava/lang/String;
     123: astore_3
     124: aload_0
     125: ldc_w         #690                // String Host
     128: aload_3
     129: invokevirtual #692                // Method setRequestHeader:(Ljava/lang/String;Ljava/lang/String;)V
     132: return

  protected void addProxyConnectionHeader(org.elasticsearch.hadoop.thirdparty.apache.commons.httpclient.HttpState, org.elasticsearch.hadoop.thirdparty.apache.commons.httpclient.HttpConnection) throws java.io.IOException, org.elasticsearch.hadoop.thirdparty.apache.commons.httpclient.HttpException;
    Code:
       0: getstatic     #254                // Field LOG:Lorg/apache/commons/logging/Log;
       3: ldc_w         #695                // String enter HttpMethodBase.addProxyConnectionHeader(HttpState, HttpConnection)
       6: invokeinterface #262,  2          // InterfaceMethod org/apache/commons/logging/Log.trace:(Ljava/lang/Object;)V
      11: aload_2
      12: invokevirtual #500                // Method org/elasticsearch/hadoop/thirdparty/apache/commons/httpclient/HttpConnection.isTransparent:()Z
      15: ifne          38
      18: aload_0
      19: ldc_w         #697                // String Proxy-Connection
      22: invokevirtual #699                // Method getRequestHeader:(Ljava/lang/String;)Lorg/elasticsearch/hadoop/thirdparty/apache/commons/httpclient/Header;
      25: ifnonnull     38
      28: aload_0
      29: ldc_w         #697                // String Proxy-Connection
      32: ldc_w         #701                // String Keep-Alive
      35: invokevirtual #703                // Method addRequestHeader:(Ljava/lang/String;Ljava/lang/String;)V
      38: return

  protected void addRequestHeaders(org.elasticsearch.hadoop.thirdparty.apache.commons.httpclient.HttpState, org.elasticsearch.hadoop.thirdparty.apache.commons.httpclient.HttpConnection) throws java.io.IOException, org.elasticsearch.hadoop.thirdparty.apache.commons.httpclient.HttpException;
    Code:
       0: getstatic     #254                // Field LOG:Lorg/apache/commons/logging/Log;
       3: ldc_w         #706                // String enter HttpMethodBase.addRequestHeaders(HttpState, HttpConnection)
       6: invokeinterface #262,  2          // InterfaceMethod org/apache/commons/logging/Log.trace:(Ljava/lang/Object;)V
      11: aload_0
      12: aload_1
      13: aload_2
      14: invokevirtual #709                // Method addUserAgentRequestHeader:(Lorg/elasticsearch/hadoop/thirdparty/apache/commons/httpclient/HttpState;Lorg/elasticsearch/hadoop/thirdparty/apache/commons/httpclient/HttpConnection;)V
      17: aload_0
      18: aload_1
      19: aload_2
      20: invokevirtual #711                // Method addHostRequestHeader:(Lorg/elasticsearch/hadoop/thirdparty/apache/commons/httpclient/HttpState;Lorg/elasticsearch/hadoop/thirdparty/apache/commons/httpclient/HttpConnection;)V
      23: aload_0
      24: aload_1
      25: aload_2
      26: invokevirtual #713                // Method addCookieRequestHeader:(Lorg/elasticsearch/hadoop/thirdparty/apache/commons/httpclient/HttpState;Lorg/elasticsearch/hadoop/thirdparty/apache/commons/httpclient/HttpConnection;)V
      29: aload_0
      30: aload_1
      31: aload_2
      32: invokevirtual #715                // Method addProxyConnectionHeader:(Lorg/elasticsearch/hadoop/thirdparty/apache/commons/httpclient/HttpState;Lorg/elasticsearch/hadoop/thirdparty/apache/commons/httpclient/HttpConnection;)V
      35: return

  protected void addUserAgentRequestHeader(org.elasticsearch.hadoop.thirdparty.apache.commons.httpclient.HttpState, org.elasticsearch.hadoop.thirdparty.apache.commons.httpclient.HttpConnection) throws java.io.IOException, org.elasticsearch.hadoop.thirdparty.apache.commons.httpclient.HttpException;
    Code:
       0: getstatic     #254                // Field LOG:Lorg/apache/commons/logging/Log;
       3: ldc_w         #717                // String enter HttpMethodBase.addUserAgentRequestHeaders(HttpState, HttpConnection)
       6: invokeinterface #262,  2          // InterfaceMethod org/apache/commons/logging/Log.trace:(Ljava/lang/Object;)V
      11: aload_0
      12: ldc_w         #719                // String User-Agent
      15: invokevirtual #699                // Method getRequestHeader:(Ljava/lang/String;)Lorg/elasticsearch/hadoop/thirdparty/apache/commons/httpclient/Header;
      18: ifnonnull     51
      21: aload_0
      22: invokevirtual #393                // Method getParams:()Lorg/elasticsearch/hadoop/thirdparty/apache/commons/httpclient/params/HttpMethodParams;
      25: ldc_w         #721                // String http.useragent
      28: invokevirtual #620                // Method org/elasticsearch/hadoop/thirdparty/apache/commons/httpclient/params/DefaultHttpParams.getParameter:(Ljava/lang/String;)Ljava/lang/Object;
      31: checkcast     #124                // class java/lang/String
      34: astore_3
      35: aload_3
      36: ifnonnull     43
      39: ldc_w         #723                // String Jakarta Commons-HttpClient
      42: astore_3
      43: aload_0
      44: ldc_w         #719                // String User-Agent
      47: aload_3
      48: invokevirtual #692                // Method setRequestHeader:(Ljava/lang/String;Ljava/lang/String;)V
      51: return

  protected void checkNotUsed() throws java.lang.IllegalStateException;
    Code:
       0: aload_0
       1: getfield      #97                 // Field used:Z
       4: ifeq          18
       7: new           #118                // class java/lang/IllegalStateException
      10: dup
      11: ldc_w         #727                // String Already used.
      14: invokespecial #549                // Method java/lang/IllegalStateException."<init>":(Ljava/lang/String;)V
      17: athrow
      18: return

  protected void checkUsed() throws java.lang.IllegalStateException;
    Code:
       0: aload_0
       1: getfield      #97                 // Field used:Z
       4: ifne          18
       7: new           #118                // class java/lang/IllegalStateException
      10: dup
      11: ldc_w         #730                // String Not Used.
      14: invokespecial #549                // Method java/lang/IllegalStateException."<init>":(Ljava/lang/String;)V
      17: athrow
      18: return

  protected static java.lang.String generateRequestLine(org.elasticsearch.hadoop.thirdparty.apache.commons.httpclient.HttpConnection, java.lang.String, java.lang.String, java.lang.String, java.lang.String);
    Code:
       0: getstatic     #254                // Field LOG:Lorg/apache/commons/logging/Log;
       3: ldc_w         #734                // String enter HttpMethodBase.generateRequestLine(HttpConnection, String, String, String, String)
       6: invokeinterface #262,  2          // InterfaceMethod org/apache/commons/logging/Log.trace:(Ljava/lang/Object;)V
      11: new           #141                // class java/lang/StringBuffer
      14: dup
      15: invokespecial #142                // Method java/lang/StringBuffer."<init>":()V
      18: astore        5
      20: aload         5
      22: aload_1
      23: invokevirtual #148                // Method java/lang/StringBuffer.append:(Ljava/lang/String;)Ljava/lang/StringBuffer;
      26: pop
      27: aload         5
      29: ldc_w         #736                // String
      32: invokevirtual #148                // Method java/lang/StringBuffer.append:(Ljava/lang/String;)Ljava/lang/StringBuffer;
      35: pop
      36: aload_0
      37: invokevirtual #500                // Method org/elasticsearch/hadoop/thirdparty/apache/commons/httpclient/HttpConnection.isTransparent:()Z
      40: ifne          119
      43: aload_0
      44: invokevirtual #688                // Method org/elasticsearch/hadoop/thirdparty/apache/commons/httpclient/HttpConnection.getProtocol:()Lorg/elasticsearch/hadoop/thirdparty/apache/commons/httpclient/protocol/Protocol;
      47: astore        6
      49: aload         5
      51: aload         6
      53: invokevirtual #178                // Method org/elasticsearch/hadoop/thirdparty/apache/commons/httpclient/protocol/Protocol.getScheme:()Ljava/lang/String;
      56: invokevirtual #739                // Method java/lang/String.toLowerCase:()Ljava/lang/String;
      59: invokevirtual #148                // Method java/lang/StringBuffer.append:(Ljava/lang/String;)Ljava/lang/StringBuffer;
      62: pop
      63: aload         5
      65: ldc           #180                // String ://
      67: invokevirtual #148                // Method java/lang/StringBuffer.append:(Ljava/lang/String;)Ljava/lang/StringBuffer;
      70: pop
      71: aload         5
      73: aload_0
      74: invokevirtual #644                // Method org/elasticsearch/hadoop/thirdparty/apache/commons/httpclient/HttpConnection.getHost:()Ljava/lang/String;
      77: invokevirtual #148                // Method java/lang/StringBuffer.append:(Ljava/lang/String;)Ljava/lang/StringBuffer;
      80: pop
      81: aload_0
      82: invokevirtual #645                // Method org/elasticsearch/hadoop/thirdparty/apache/commons/httpclient/HttpConnection.getPort:()I
      85: iconst_m1
      86: if_icmpeq     119
      89: aload_0
      90: invokevirtual #645                // Method org/elasticsearch/hadoop/thirdparty/apache/commons/httpclient/HttpConnection.getPort:()I
      93: aload         6
      95: invokevirtual #190                // Method org/elasticsearch/hadoop/thirdparty/apache/commons/httpclient/protocol/Protocol.getDefaultPort:()I
      98: if_icmpeq     119
     101: aload         5
     103: ldc           #192                // String :
     105: invokevirtual #148                // Method java/lang/StringBuffer.append:(Ljava/lang/String;)Ljava/lang/StringBuffer;
     108: pop
     109: aload         5
     111: aload_0
     112: invokevirtual #645                // Method org/elasticsearch/hadoop/thirdparty/apache/commons/httpclient/HttpConnection.getPort:()I
     115: invokevirtual #195                // Method java/lang/StringBuffer.append:(I)Ljava/lang/StringBuffer;
     118: pop
     119: aload_2
     120: ifnonnull     134
     123: aload         5
     125: ldc           #130                // String /
     127: invokevirtual #148                // Method java/lang/StringBuffer.append:(Ljava/lang/String;)Ljava/lang/StringBuffer;
     130: pop
     131: goto          165
     134: aload_0
     135: invokevirtual #500                // Method org/elasticsearch/hadoop/thirdparty/apache/commons/httpclient/HttpConnection.isTransparent:()Z
     138: ifne          158
     141: aload_2
     142: ldc           #130                // String /
     144: invokevirtual #742                // Method java/lang/String.startsWith:(Ljava/lang/String;)Z
     147: ifne          158
     150: aload         5
     152: ldc           #130                // String /
     154: invokevirtual #148                // Method java/lang/StringBuffer.append:(Ljava/lang/String;)Ljava/lang/StringBuffer;
     157: pop
     158: aload         5
     160: aload_2
     161: invokevirtual #148                // Method java/lang/StringBuffer.append:(Ljava/lang/String;)Ljava/lang/StringBuffer;
     164: pop
     165: aload_3
     166: ifnull        195
     169: aload_3
     170: ldc_w         #744                // String ?
     173: invokevirtual #748                // Method java/lang/String.indexOf:(Ljava/lang/String;)I
     176: ifeq          188
     179: aload         5
     181: ldc_w         #744                // String ?
     184: invokevirtual #148                // Method java/lang/StringBuffer.append:(Ljava/lang/String;)Ljava/lang/StringBuffer;
     187: pop
     188: aload         5
     190: aload_3
     191: invokevirtual #148                // Method java/lang/StringBuffer.append:(Ljava/lang/String;)Ljava/lang/StringBuffer;
     194: pop
     195: aload         5
     197: ldc_w         #736                // String
     200: invokevirtual #148                // Method java/lang/StringBuffer.append:(Ljava/lang/String;)Ljava/lang/StringBuffer;
     203: pop
     204: aload         5
     206: aload         4
     208: invokevirtual #148                // Method java/lang/StringBuffer.append:(Ljava/lang/String;)Ljava/lang/StringBuffer;
     211: pop
     212: aload         5
     214: ldc_w         #750                // String \r\n
     217: invokevirtual #148                // Method java/lang/StringBuffer.append:(Ljava/lang/String;)Ljava/lang/StringBuffer;
     220: pop
     221: aload         5
     223: invokevirtual #159                // Method java/lang/StringBuffer.toString:()Ljava/lang/String;
     226: areturn

  protected void processResponseBody(org.elasticsearch.hadoop.thirdparty.apache.commons.httpclient.HttpState, org.elasticsearch.hadoop.thirdparty.apache.commons.httpclient.HttpConnection);
    Code:
       0: return

  protected void processResponseHeaders(org.elasticsearch.hadoop.thirdparty.apache.commons.httpclient.HttpState, org.elasticsearch.hadoop.thirdparty.apache.commons.httpclient.HttpConnection);
    Code:
       0: getstatic     #254                // Field LOG:Lorg/apache/commons/logging/Log;
       3: ldc_w         #763                // String enter HttpMethodBase.processResponseHeaders(HttpState, HttpConnection)
       6: invokeinterface #262,  2          // InterfaceMethod org/apache/commons/logging/Log.trace:(Ljava/lang/Object;)V
      11: aload_0
      12: invokevirtual #332                // Method getResponseHeaderGroup:()Lorg/elasticsearch/hadoop/thirdparty/apache/commons/httpclient/HeaderGroup;
      15: ldc_w         #765                // String set-cookie2
      18: invokevirtual #312                // Method org/elasticsearch/hadoop/thirdparty/apache/commons/httpclient/HeaderGroup.getHeaders:(Ljava/lang/String;)[Lorg/elasticsearch/hadoop/thirdparty/apache/commons/httpclient/Header;
      21: astore_3
      22: aload_3
      23: arraylength
      24: ifne          38
      27: aload_0
      28: invokevirtual #332                // Method getResponseHeaderGroup:()Lorg/elasticsearch/hadoop/thirdparty/apache/commons/httpclient/HeaderGroup;
      31: ldc_w         #767                // String set-cookie
      34: invokevirtual #312                // Method org/elasticsearch/hadoop/thirdparty/apache/commons/httpclient/HeaderGroup.getHeaders:(Ljava/lang/String;)[Lorg/elasticsearch/hadoop/thirdparty/apache/commons/httpclient/Header;
      37: astore_3
      38: aload_0
      39: aload_1
      40: invokespecial #638                // Method getCookieSpec:(Lorg/elasticsearch/hadoop/thirdparty/apache/commons/httpclient/HttpState;)Lorg/elasticsearch/hadoop/thirdparty/apache/commons/httpclient/cookie/CookieSpec;
      43: astore        4
      45: aload_0
      46: getfield      #88                 // Field params:Lorg/elasticsearch/hadoop/thirdparty/apache/commons/httpclient/params/HttpMethodParams;
      49: invokevirtual #641                // Method org/elasticsearch/hadoop/thirdparty/apache/commons/httpclient/params/HttpMethodParams.getVirtualHost:()Ljava/lang/String;
      52: astore        5
      54: aload         5
      56: ifnonnull     65
      59: aload_2
      60: invokevirtual #644                // Method org/elasticsearch/hadoop/thirdparty/apache/commons/httpclient/HttpConnection.getHost:()Ljava/lang/String;
      63: astore        5
      65: iconst_0
      66: istore        6
      68: goto          347
      71: aload_3
      72: iload         6
      74: aaload
      75: astore        7
      77: aconst_null
      78: astore        8
      80: aload         4
      82: aload         5
      84: aload_2
      85: invokevirtual #645                // Method org/elasticsearch/hadoop/thirdparty/apache/commons/httpclient/HttpConnection.getPort:()I
      88: aload_0
      89: invokevirtual #646                // Method getPath:()Ljava/lang/String;
      92: aload_2
      93: invokevirtual #649                // Method org/elasticsearch/hadoop/thirdparty/apache/commons/httpclient/HttpConnection.isSecure:()Z
      96: aload         7
      98: invokeinterface #771,  6          // InterfaceMethod org/elasticsearch/hadoop/thirdparty/apache/commons/httpclient/cookie/CookieSpec.parse:(Ljava/lang/String;ILjava/lang/String;ZLorg/elasticsearch/hadoop/thirdparty/apache/commons/httpclient/Header;)[Lorg/elasticsearch/hadoop/thirdparty/apache/commons/httpclient/Cookie;
     103: astore        8
     105: goto          167
     108: astore        9
     110: getstatic     #254                // Field LOG:Lorg/apache/commons/logging/Log;
     113: invokeinterface #366,  1          // InterfaceMethod org/apache/commons/logging/Log.isWarnEnabled:()Z
     118: ifeq          167
     121: getstatic     #254                // Field LOG:Lorg/apache/commons/logging/Log;
     124: new           #141                // class java/lang/StringBuffer
     127: dup
     128: invokespecial #142                // Method java/lang/StringBuffer."<init>":()V
     131: ldc_w         #773                // String Invalid cookie header: \"
     134: invokevirtual #148                // Method java/lang/StringBuffer.append:(Ljava/lang/String;)Ljava/lang/StringBuffer;
     137: aload         7
     139: invokevirtual #357                // Method org/elasticsearch/hadoop/thirdparty/apache/commons/httpclient/NameValuePair.getValue:()Ljava/lang/String;
     142: invokevirtual #148                // Method java/lang/StringBuffer.append:(Ljava/lang/String;)Ljava/lang/StringBuffer;
     145: ldc_w         #775                // String \".
     148: invokevirtual #148                // Method java/lang/StringBuffer.append:(Ljava/lang/String;)Ljava/lang/StringBuffer;
     151: aload         9
     153: invokevirtual #156                // Method java/lang/Throwable.getMessage:()Ljava/lang/String;
     156: invokevirtual #148                // Method java/lang/StringBuffer.append:(Ljava/lang/String;)Ljava/lang/StringBuffer;
     159: invokevirtual #159                // Method java/lang/StringBuffer.toString:()Ljava/lang/String;
     162: invokeinterface #354,  2          // InterfaceMethod org/apache/commons/logging/Log.warn:(Ljava/lang/Object;)V
     167: aload         8
     169: ifnull        344
     172: iconst_0
     173: istore        9
     175: goto          336
     178: aload         8
     180: iload         9
     182: aaload
     183: astore        10
     185: aload         4
     187: aload         5
     189: aload_2
     190: invokevirtual #645                // Method org/elasticsearch/hadoop/thirdparty/apache/commons/httpclient/HttpConnection.getPort:()I
     193: aload_0
     194: invokevirtual #646                // Method getPath:()Ljava/lang/String;
     197: aload_2
     198: invokevirtual #649                // Method org/elasticsearch/hadoop/thirdparty/apache/commons/httpclient/HttpConnection.isSecure:()Z
     201: aload         10
     203: invokeinterface #778,  6          // InterfaceMethod org/elasticsearch/hadoop/thirdparty/apache/commons/httpclient/cookie/CookieSpec.validate:(Ljava/lang/String;ILjava/lang/String;ZLorg/elasticsearch/hadoop/thirdparty/apache/commons/httpclient/Cookie;)V
     208: aload_1
     209: aload         10
     211: invokevirtual #782                // Method org/elasticsearch/hadoop/thirdparty/apache/commons/httpclient/HttpState.addCookie:(Lorg/elasticsearch/hadoop/thirdparty/apache/commons/httpclient/Cookie;)V
     214: getstatic     #254                // Field LOG:Lorg/apache/commons/logging/Log;
     217: invokeinterface #483,  1          // InterfaceMethod org/apache/commons/logging/Log.isDebugEnabled:()Z
     222: ifeq          267
     225: getstatic     #254                // Field LOG:Lorg/apache/commons/logging/Log;
     228: new           #141                // class java/lang/StringBuffer
     231: dup
     232: invokespecial #142                // Method java/lang/StringBuffer."<init>":()V
     235: ldc_w         #784                // String Cookie accepted: \"
     238: invokevirtual #148                // Method java/lang/StringBuffer.append:(Ljava/lang/String;)Ljava/lang/StringBuffer;
     241: aload         4
     243: aload         10
     245: invokeinterface #673,  2          // InterfaceMethod org/elasticsearch/hadoop/thirdparty/apache/commons/httpclient/cookie/CookieSpec.formatCookie:(Lorg/elasticsearch/hadoop/thirdparty/apache/commons/httpclient/Cookie;)Ljava/lang/String;
     250: invokevirtual #148                // Method java/lang/StringBuffer.append:(Ljava/lang/String;)Ljava/lang/StringBuffer;
     253: ldc_w         #786                // String \"
     256: invokevirtual #148                // Method java/lang/StringBuffer.append:(Ljava/lang/String;)Ljava/lang/StringBuffer;
     259: invokevirtual #159                // Method java/lang/StringBuffer.toString:()Ljava/lang/String;
     262: invokeinterface #267,  2          // InterfaceMethod org/apache/commons/logging/Log.debug:(Ljava/lang/Object;)V
     267: goto          333
     270: astore        11
     272: getstatic     #254                // Field LOG:Lorg/apache/commons/logging/Log;
     275: invokeinterface #366,  1          // InterfaceMethod org/apache/commons/logging/Log.isWarnEnabled:()Z
     280: ifeq          333
     283: getstatic     #254                // Field LOG:Lorg/apache/commons/logging/Log;
     286: new           #141                // class java/lang/StringBuffer
     289: dup
     290: invokespecial #142                // Method java/lang/StringBuffer."<init>":()V
     293: ldc_w         #788                // String Cookie rejected: \"
     296: invokevirtual #148                // Method java/lang/StringBuffer.append:(Ljava/lang/String;)Ljava/lang/StringBuffer;
     299: aload         4
     301: aload         10
     303: invokeinterface #673,  2          // InterfaceMethod org/elasticsearch/hadoop/thirdparty/apache/commons/httpclient/cookie/CookieSpec.formatCookie:(Lorg/elasticsearch/hadoop/thirdparty/apache/commons/httpclient/Cookie;)Ljava/lang/String;
     308: invokevirtual #148                // Method java/lang/StringBuffer.append:(Ljava/lang/String;)Ljava/lang/StringBuffer;
     311: ldc_w         #775                // String \".
     314: invokevirtual #148                // Method java/lang/StringBuffer.append:(Ljava/lang/String;)Ljava/lang/StringBuffer;
     317: aload         11
     319: invokevirtual #156                // Method java/lang/Throwable.getMessage:()Ljava/lang/String;
     322: invokevirtual #148                // Method java/lang/StringBuffer.append:(Ljava/lang/String;)Ljava/lang/StringBuffer;
     325: invokevirtual #159                // Method java/lang/StringBuffer.toString:()Ljava/lang/String;
     328: invokeinterface #354,  2          // InterfaceMethod org/apache/commons/logging/Log.warn:(Ljava/lang/Object;)V
     333: iinc          9, 1
     336: iload         9
     338: aload         8
     340: arraylength
     341: if_icmplt     178
     344: iinc          6, 1
     347: iload         6
     349: aload_3
     350: arraylength
     351: if_icmplt     71
     354: return
    Exception table:
       from    to  target type
          80   105   108   Class org/elasticsearch/hadoop/thirdparty/apache/commons/httpclient/cookie/MalformedCookieException
         185   267   270   Class org/elasticsearch/hadoop/thirdparty/apache/commons/httpclient/cookie/MalformedCookieException

  protected void processStatusLine(org.elasticsearch.hadoop.thirdparty.apache.commons.httpclient.HttpState, org.elasticsearch.hadoop.thirdparty.apache.commons.httpclient.HttpConnection);
    Code:
       0: return

  protected void readResponse(org.elasticsearch.hadoop.thirdparty.apache.commons.httpclient.HttpState, org.elasticsearch.hadoop.thirdparty.apache.commons.httpclient.HttpConnection) throws java.io.IOException, org.elasticsearch.hadoop.thirdparty.apache.commons.httpclient.HttpException;
    Code:
       0: getstatic     #254                // Field LOG:Lorg/apache/commons/logging/Log;
       3: ldc_w         #796                // String enter HttpMethodBase.readResponse(HttpState, HttpConnection)
       6: invokeinterface #262,  2          // InterfaceMethod org/apache/commons/logging/Log.trace:(Ljava/lang/Object;)V
      11: goto          109
      14: aload_0
      15: aload_1
      16: aload_2
      17: invokevirtual #799                // Method readStatusLine:(Lorg/elasticsearch/hadoop/thirdparty/apache/commons/httpclient/HttpState;Lorg/elasticsearch/hadoop/thirdparty/apache/commons/httpclient/HttpConnection;)V
      20: aload_0
      21: aload_1
      22: aload_2
      23: invokevirtual #801                // Method processStatusLine:(Lorg/elasticsearch/hadoop/thirdparty/apache/commons/httpclient/HttpState;Lorg/elasticsearch/hadoop/thirdparty/apache/commons/httpclient/HttpConnection;)V
      26: aload_0
      27: aload_1
      28: aload_2
      29: invokevirtual #804                // Method readResponseHeaders:(Lorg/elasticsearch/hadoop/thirdparty/apache/commons/httpclient/HttpState;Lorg/elasticsearch/hadoop/thirdparty/apache/commons/httpclient/HttpConnection;)V
      32: aload_0
      33: aload_1
      34: aload_2
      35: invokevirtual #806                // Method processResponseHeaders:(Lorg/elasticsearch/hadoop/thirdparty/apache/commons/httpclient/HttpState;Lorg/elasticsearch/hadoop/thirdparty/apache/commons/httpclient/HttpConnection;)V
      38: aload_0
      39: getfield      #65                 // Field statusLine:Lorg/elasticsearch/hadoop/thirdparty/apache/commons/httpclient/StatusLine;
      42: invokevirtual #337                // Method org/elasticsearch/hadoop/thirdparty/apache/commons/httpclient/StatusLine.getStatusCode:()I
      45: istore_3
      46: iload_3
      47: bipush        100
      49: if_icmplt     109
      52: iload_3
      53: sipush        200
      56: if_icmpge     109
      59: getstatic     #254                // Field LOG:Lorg/apache/commons/logging/Log;
      62: invokeinterface #809,  1          // InterfaceMethod org/apache/commons/logging/Log.isInfoEnabled:()Z
      67: ifeq          104
      70: getstatic     #254                // Field LOG:Lorg/apache/commons/logging/Log;
      73: new           #141                // class java/lang/StringBuffer
      76: dup
      77: invokespecial #142                // Method java/lang/StringBuffer."<init>":()V
      80: ldc_w         #811                // String Discarding unexpected response:
      83: invokevirtual #148                // Method java/lang/StringBuffer.append:(Ljava/lang/String;)Ljava/lang/StringBuffer;
      86: aload_0
      87: getfield      #65                 // Field statusLine:Lorg/elasticsearch/hadoop/thirdparty/apache/commons/httpclient/StatusLine;
      90: invokevirtual #812                // Method org/elasticsearch/hadoop/thirdparty/apache/commons/httpclient/StatusLine.toString:()Ljava/lang/String;
      93: invokevirtual #148                // Method java/lang/StringBuffer.append:(Ljava/lang/String;)Ljava/lang/StringBuffer;
      96: invokevirtual #159                // Method java/lang/StringBuffer.toString:()Ljava/lang/String;
      99: invokeinterface #815,  2          // InterfaceMethod org/apache/commons/logging/Log.info:(Ljava/lang/Object;)V
     104: aload_0
     105: aconst_null
     106: putfield      #65                 // Field statusLine:Lorg/elasticsearch/hadoop/thirdparty/apache/commons/httpclient/StatusLine;
     109: aload_0
     110: getfield      #65                 // Field statusLine:Lorg/elasticsearch/hadoop/thirdparty/apache/commons/httpclient/StatusLine;
     113: ifnull        14
     116: aload_0
     117: aload_1
     118: aload_2
     119: invokevirtual #818                // Method readResponseBody:(Lorg/elasticsearch/hadoop/thirdparty/apache/commons/httpclient/HttpState;Lorg/elasticsearch/hadoop/thirdparty/apache/commons/httpclient/HttpConnection;)V
     122: aload_0
     123: aload_1
     124: aload_2
     125: invokevirtual #820                // Method processResponseBody:(Lorg/elasticsearch/hadoop/thirdparty/apache/commons/httpclient/HttpState;Lorg/elasticsearch/hadoop/thirdparty/apache/commons/httpclient/HttpConnection;)V
     128: return

  protected void readResponseBody(org.elasticsearch.hadoop.thirdparty.apache.commons.httpclient.HttpState, org.elasticsearch.hadoop.thirdparty.apache.commons.httpclient.HttpConnection) throws java.io.IOException, org.elasticsearch.hadoop.thirdparty.apache.commons.httpclient.HttpException;
    Code:
       0: getstatic     #254                // Field LOG:Lorg/apache/commons/logging/Log;
       3: ldc_w         #823                // String enter HttpMethodBase.readResponseBody(HttpState, HttpConnection)
       6: invokeinterface #262,  2          // InterfaceMethod org/apache/commons/logging/Log.trace:(Ljava/lang/Object;)V
      11: aload_0
      12: aload_2
      13: invokespecial #826                // Method readResponseBody:(Lorg/elasticsearch/hadoop/thirdparty/apache/commons/httpclient/HttpConnection;)Ljava/io/InputStream;
      16: astore_3
      17: aload_3
      18: ifnonnull     28
      21: aload_0
      22: invokevirtual #829                // Method responseBodyConsumed:()V
      25: goto          38
      28: aload_2
      29: aload_3
      30: invokevirtual #568                // Method org/elasticsearch/hadoop/thirdparty/apache/commons/httpclient/HttpConnection.setLastResponseInputStream:(Ljava/io/InputStream;)V
      33: aload_0
      34: aload_3
      35: invokevirtual #428                // Method setResponseStream:(Ljava/io/InputStream;)V
      38: return

  private java.io.InputStream readResponseBody(org.elasticsearch.hadoop.thirdparty.apache.commons.httpclient.HttpConnection) throws org.elasticsearch.hadoop.thirdparty.apache.commons.httpclient.HttpException, java.io.IOException;
    Code:
       0: getstatic     #254                // Field LOG:Lorg/apache/commons/logging/Log;
       3: ldc_w         #832                // String enter HttpMethodBase.readResponseBody(HttpConnection)
       6: invokeinterface #262,  2          // InterfaceMethod org/apache/commons/logging/Log.trace:(Ljava/lang/Object;)V
      11: aload_0
      12: aconst_null
      13: putfield      #79                 // Field responseBody:[B
      16: aload_1
      17: invokevirtual #835                // Method org/elasticsearch/hadoop/thirdparty/apache/commons/httpclient/HttpConnection.getResponseInputStream:()Ljava/io/InputStream;
      20: astore_2
      21: getstatic     #841                // Field org/elasticsearch/hadoop/thirdparty/apache/commons/httpclient/Wire.CONTENT_WIRE:Lorg/elasticsearch/hadoop/thirdparty/apache/commons/httpclient/Wire;
      24: invokevirtual #844                // Method org/elasticsearch/hadoop/thirdparty/apache/commons/httpclient/Wire.enabled:()Z
      27: ifeq          42
      30: new           #846                // class org/elasticsearch/hadoop/thirdparty/apache/commons/httpclient/WireLogInputStream
      33: dup
      34: aload_2
      35: getstatic     #841                // Field org/elasticsearch/hadoop/thirdparty/apache/commons/httpclient/Wire.CONTENT_WIRE:Lorg/elasticsearch/hadoop/thirdparty/apache/commons/httpclient/Wire;
      38: invokespecial #849                // Method org/elasticsearch/hadoop/thirdparty/apache/commons/httpclient/WireLogInputStream."<init>":(Ljava/io/InputStream;Lorg/elasticsearch/hadoop/thirdparty/apache/commons/httpclient/Wire;)V
      41: astore_2
      42: aload_0
      43: getfield      #65                 // Field statusLine:Lorg/elasticsearch/hadoop/thirdparty/apache/commons/httpclient/StatusLine;
      46: invokevirtual #337                // Method org/elasticsearch/hadoop/thirdparty/apache/commons/httpclient/StatusLine.getStatusCode:()I
      49: invokestatic  #853                // Method canResponseHaveBody:(I)Z
      52: istore_3
      53: aconst_null
      54: astore        4
      56: aload_0
      57: getfield      #67                 // Field responseHeaders:Lorg/elasticsearch/hadoop/thirdparty/apache/commons/httpclient/HeaderGroup;
      60: ldc_w         #855                // String Transfer-Encoding
      63: invokevirtual #505                // Method org/elasticsearch/hadoop/thirdparty/apache/commons/httpclient/HeaderGroup.getFirstHeader:(Ljava/lang/String;)Lorg/elasticsearch/hadoop/thirdparty/apache/commons/httpclient/Header;
      66: astore        5
      68: aload         5
      70: ifnull        266
      73: aload         5
      75: invokevirtual #357                // Method org/elasticsearch/hadoop/thirdparty/apache/commons/httpclient/NameValuePair.getValue:()Ljava/lang/String;
      78: astore        6
      80: ldc_w         #857                // String chunked
      83: aload         6
      85: invokevirtual #512                // Method java/lang/String.equalsIgnoreCase:(Ljava/lang/String;)Z
      88: ifne          142
      91: ldc_w         #859                // String identity
      94: aload         6
      96: invokevirtual #512                // Method java/lang/String.equalsIgnoreCase:(Ljava/lang/String;)Z
      99: ifne          142
     102: getstatic     #254                // Field LOG:Lorg/apache/commons/logging/Log;
     105: invokeinterface #366,  1          // InterfaceMethod org/apache/commons/logging/Log.isWarnEnabled:()Z
     110: ifeq          142
     113: getstatic     #254                // Field LOG:Lorg/apache/commons/logging/Log;
     116: new           #141                // class java/lang/StringBuffer
     119: dup
     120: invokespecial #142                // Method java/lang/StringBuffer."<init>":()V
     123: ldc_w         #861                // String Unsupported transfer encoding:
     126: invokevirtual #148                // Method java/lang/StringBuffer.append:(Ljava/lang/String;)Ljava/lang/StringBuffer;
     129: aload         6
     131: invokevirtual #148                // Method java/lang/StringBuffer.append:(Ljava/lang/String;)Ljava/lang/StringBuffer;
     134: invokevirtual #159                // Method java/lang/StringBuffer.toString:()Ljava/lang/String;
     137: invokeinterface #354,  2          // InterfaceMethod org/apache/commons/logging/Log.warn:(Ljava/lang/Object;)V
     142: aload         5
     144: invokevirtual #865                // Method org/elasticsearch/hadoop/thirdparty/apache/commons/httpclient/Header.getElements:()[Lorg/elasticsearch/hadoop/thirdparty/apache/commons/httpclient/HeaderElement;
     147: astore        7
     149: aload         7
     151: arraylength
     152: istore        8
     154: iload         8
     156: ifle          244
     159: ldc_w         #857                // String chunked
     162: aload         7
     164: iload         8
     166: iconst_1
     167: isub
     168: aaload
     169: invokevirtual #308                // Method org/elasticsearch/hadoop/thirdparty/apache/commons/httpclient/NameValuePair.getName:()Ljava/lang/String;
     172: invokevirtual #512                // Method java/lang/String.equalsIgnoreCase:(Ljava/lang/String;)Z
     175: ifeq          244
     178: aload_1
     179: aload_1
     180: invokevirtual #868                // Method org/elasticsearch/hadoop/thirdparty/apache/commons/httpclient/HttpConnection.getParams:()Lorg/elasticsearch/hadoop/thirdparty/apache/commons/httpclient/params/HttpConnectionParams;
     183: invokevirtual #873                // Method org/elasticsearch/hadoop/thirdparty/apache/commons/httpclient/params/HttpConnectionParams.getSoTimeout:()I
     186: invokevirtual #876                // Method org/elasticsearch/hadoop/thirdparty/apache/commons/httpclient/HttpConnection.isResponseAvailable:(I)Z
     189: ifeq          206
     192: new           #878                // class org/elasticsearch/hadoop/thirdparty/apache/commons/httpclient/ChunkedInputStream
     195: dup
     196: aload_2
     197: aload_0
     198: invokespecial #881                // Method org/elasticsearch/hadoop/thirdparty/apache/commons/httpclient/ChunkedInputStream."<init>":(Ljava/io/InputStream;Lorg/elasticsearch/hadoop/thirdparty/apache/commons/httpclient/HttpMethod;)V
     201: astore        4
     203: goto          263
     206: aload_0
     207: invokevirtual #393                // Method getParams:()Lorg/elasticsearch/hadoop/thirdparty/apache/commons/httpclient/params/HttpMethodParams;
     210: ldc_w         #883                // String http.protocol.strict-transfer-encoding
     213: invokevirtual #662                // Method org/elasticsearch/hadoop/thirdparty/apache/commons/httpclient/params/DefaultHttpParams.isParameterTrue:(Ljava/lang/String;)Z
     216: ifeq          230
     219: new           #554                // class org/elasticsearch/hadoop/thirdparty/apache/commons/httpclient/ProtocolException
     222: dup
     223: ldc_w         #885                // String Chunk-encoded body declared but not sent
     226: invokespecial #557                // Method org/elasticsearch/hadoop/thirdparty/apache/commons/httpclient/ProtocolException."<init>":(Ljava/lang/String;)V
     229: athrow
     230: getstatic     #254                // Field LOG:Lorg/apache/commons/logging/Log;
     233: ldc_w         #887                // String Chunk-encoded body missing
     236: invokeinterface #354,  2          // InterfaceMethod org/apache/commons/logging/Log.warn:(Ljava/lang/Object;)V
     241: goto          263
     244: getstatic     #254                // Field LOG:Lorg/apache/commons/logging/Log;
     247: ldc_w         #889                // String Response content is not chunk-encoded
     250: invokeinterface #815,  2          // InterfaceMethod org/apache/commons/logging/Log.info:(Ljava/lang/Object;)V
     255: aload_0
     256: iconst_1
     257: invokevirtual #891                // Method setConnectionCloseForced:(Z)V
     260: aload_2
     261: astore        4
     263: goto          370
     266: aload_0
     267: invokevirtual #379                // Method getResponseContentLength:()J
     270: lstore        6
     272: lload         6
     274: ldc2_w        #348                // long -1l
     277: lcmp
     278: ifne          358
     281: iload_3
     282: ifeq          352
     285: aload_0
     286: getfield      #105                // Field effectiveVersion:Lorg/elasticsearch/hadoop/thirdparty/apache/commons/httpclient/HttpVersion;
     289: getstatic     #232                // Field org/elasticsearch/hadoop/thirdparty/apache/commons/httpclient/HttpVersion.HTTP_1_1:Lorg/elasticsearch/hadoop/thirdparty/apache/commons/httpclient/HttpVersion;
     292: invokevirtual #528                // Method org/elasticsearch/hadoop/thirdparty/apache/commons/httpclient/HttpVersion.greaterEquals:(Lorg/elasticsearch/hadoop/thirdparty/apache/commons/httpclient/HttpVersion;)Z
     295: ifeq          352
     298: aload_0
     299: getfield      #67                 // Field responseHeaders:Lorg/elasticsearch/hadoop/thirdparty/apache/commons/httpclient/HeaderGroup;
     302: ldc_w         #893                // String Connection
     305: invokevirtual #505                // Method org/elasticsearch/hadoop/thirdparty/apache/commons/httpclient/HeaderGroup.getFirstHeader:(Ljava/lang/String;)Lorg/elasticsearch/hadoop/thirdparty/apache/commons/httpclient/Header;
     308: astore        8
     310: aconst_null
     311: astore        9
     313: aload         8
     315: ifnull        325
     318: aload         8
     320: invokevirtual #357                // Method org/elasticsearch/hadoop/thirdparty/apache/commons/httpclient/NameValuePair.getValue:()Ljava/lang/String;
     323: astore        9
     325: ldc_w         #508                // String close
     328: aload         9
     330: invokevirtual #512                // Method java/lang/String.equalsIgnoreCase:(Ljava/lang/String;)Z
     333: ifne          352
     336: getstatic     #254                // Field LOG:Lorg/apache/commons/logging/Log;
     339: ldc_w         #895                // String Response content length is not known
     342: invokeinterface #815,  2          // InterfaceMethod org/apache/commons/logging/Log.info:(Ljava/lang/Object;)V
     347: aload_0
     348: iconst_1
     349: invokevirtual #891                // Method setConnectionCloseForced:(Z)V
     352: aload_2
     353: astore        4
     355: goto          370
     358: new           #897                // class org/elasticsearch/hadoop/thirdparty/apache/commons/httpclient/ContentLengthInputStream
     361: dup
     362: aload_2
     363: lload         6
     365: invokespecial #900                // Method org/elasticsearch/hadoop/thirdparty/apache/commons/httpclient/ContentLengthInputStream."<init>":(Ljava/io/InputStream;J)V
     368: astore        4
     370: iload_3
     371: ifne          377
     374: aconst_null
     375: astore        4
     377: aload         4
     379: ifnull        401
     382: new           #902                // class org/elasticsearch/hadoop/thirdparty/apache/commons/httpclient/AutoCloseInputStream
     385: dup
     386: aload         4
     388: new           #9                  // class org/elasticsearch/hadoop/thirdparty/apache/commons/httpclient/HttpMethodBase$1
     391: dup
     392: aload_0
     393: invokespecial #905                // Method org/elasticsearch/hadoop/thirdparty/apache/commons/httpclient/HttpMethodBase$1."<init>":(Lorg/elasticsearch/hadoop/thirdparty/apache/commons/httpclient/HttpMethodBase;)V
     396: invokespecial #908                // Method org/elasticsearch/hadoop/thirdparty/apache/commons/httpclient/AutoCloseInputStream."<init>":(Ljava/io/InputStream;Lorg/elasticsearch/hadoop/thirdparty/apache/commons/httpclient/ResponseConsumedWatcher;)V
     399: astore        4
     401: aload         4
     403: areturn

  protected void readResponseHeaders(org.elasticsearch.hadoop.thirdparty.apache.commons.httpclient.HttpState, org.elasticsearch.hadoop.thirdparty.apache.commons.httpclient.HttpConnection) throws java.io.IOException, org.elasticsearch.hadoop.thirdparty.apache.commons.httpclient.HttpException;
    Code:
       0: getstatic     #254                // Field LOG:Lorg/apache/commons/logging/Log;
       3: ldc_w         #919                // String enter HttpMethodBase.readResponseHeaders(HttpState,HttpConnection)
       6: invokeinterface #262,  2          // InterfaceMethod org/apache/commons/logging/Log.trace:(Ljava/lang/Object;)V
      11: aload_0
      12: invokevirtual #332                // Method getResponseHeaderGroup:()Lorg/elasticsearch/hadoop/thirdparty/apache/commons/httpclient/HeaderGroup;
      15: invokevirtual #586                // Method org/elasticsearch/hadoop/thirdparty/apache/commons/httpclient/HeaderGroup.clear:()V
      18: aload_2
      19: invokevirtual #835                // Method org/elasticsearch/hadoop/thirdparty/apache/commons/httpclient/HttpConnection.getResponseInputStream:()Ljava/io/InputStream;
      22: aload_0
      23: invokevirtual #393                // Method getParams:()Lorg/elasticsearch/hadoop/thirdparty/apache/commons/httpclient/params/HttpMethodParams;
      26: invokevirtual #922                // Method org/elasticsearch/hadoop/thirdparty/apache/commons/httpclient/params/HttpMethodParams.getHttpElementCharset:()Ljava/lang/String;
      29: invokestatic  #928                // Method org/elasticsearch/hadoop/thirdparty/apache/commons/httpclient/HttpParser.parseHeaders:(Ljava/io/InputStream;Ljava/lang/String;)[Lorg/elasticsearch/hadoop/thirdparty/apache/commons/httpclient/Header;
      32: astore_3
      33: getstatic     #931                // Field org/elasticsearch/hadoop/thirdparty/apache/commons/httpclient/Wire.HEADER_WIRE:Lorg/elasticsearch/hadoop/thirdparty/apache/commons/httpclient/Wire;
      36: invokevirtual #844                // Method org/elasticsearch/hadoop/thirdparty/apache/commons/httpclient/Wire.enabled:()Z
      39: ifeq          71
      42: iconst_0
      43: istore        4
      45: goto          64
      48: getstatic     #931                // Field org/elasticsearch/hadoop/thirdparty/apache/commons/httpclient/Wire.HEADER_WIRE:Lorg/elasticsearch/hadoop/thirdparty/apache/commons/httpclient/Wire;
      51: aload_3
      52: iload         4
      54: aaload
      55: invokevirtual #523                // Method org/elasticsearch/hadoop/thirdparty/apache/commons/httpclient/Header.toExternalForm:()Ljava/lang/String;
      58: invokevirtual #934                // Method org/elasticsearch/hadoop/thirdparty/apache/commons/httpclient/Wire.input:(Ljava/lang/String;)V
      61: iinc          4, 1
      64: iload         4
      66: aload_3
      67: arraylength
      68: if_icmplt     48
      71: aload_0
      72: invokevirtual #332                // Method getResponseHeaderGroup:()Lorg/elasticsearch/hadoop/thirdparty/apache/commons/httpclient/HeaderGroup;
      75: aload_3
      76: invokevirtual #938                // Method org/elasticsearch/hadoop/thirdparty/apache/commons/httpclient/HeaderGroup.setHeaders:([Lorg/elasticsearch/hadoop/thirdparty/apache/commons/httpclient/Header;)V
      79: return

  protected void readStatusLine(org.elasticsearch.hadoop.thirdparty.apache.commons.httpclient.HttpState, org.elasticsearch.hadoop.thirdparty.apache.commons.httpclient.HttpConnection) throws java.io.IOException, org.elasticsearch.hadoop.thirdparty.apache.commons.httpclient.HttpException;
    Code:
       0: getstatic     #254                // Field LOG:Lorg/apache/commons/logging/Log;
       3: ldc_w         #940                // String enter HttpMethodBase.readStatusLine(HttpState, HttpConnection)
       6: invokeinterface #262,  2          // InterfaceMethod org/apache/commons/logging/Log.trace:(Ljava/lang/Object;)V
      11: aload_0
      12: invokevirtual #393                // Method getParams:()Lorg/elasticsearch/hadoop/thirdparty/apache/commons/httpclient/params/HttpMethodParams;
      15: ldc_w         #942                // String http.protocol.status-line-garbage-limit
      18: ldc_w         #943                // int 2147483647
      21: invokevirtual #402                // Method org/elasticsearch/hadoop/thirdparty/apache/commons/httpclient/params/DefaultHttpParams.getIntParameter:(Ljava/lang/String;I)I
      24: istore_3
      25: iconst_0
      26: istore        4
      28: aload_2
      29: aload_0
      30: invokevirtual #393                // Method getParams:()Lorg/elasticsearch/hadoop/thirdparty/apache/commons/httpclient/params/HttpMethodParams;
      33: invokevirtual #922                // Method org/elasticsearch/hadoop/thirdparty/apache/commons/httpclient/params/HttpMethodParams.getHttpElementCharset:()Ljava/lang/String;
      36: invokevirtual #947                // Method org/elasticsearch/hadoop/thirdparty/apache/commons/httpclient/HttpConnection.readLine:(Ljava/lang/String;)Ljava/lang/String;
      39: astore        5
      41: aload         5
      43: ifnonnull     88
      46: iload         4
      48: ifne          88
      51: new           #949                // class org/elasticsearch/hadoop/thirdparty/apache/commons/httpclient/NoHttpResponseException
      54: dup
      55: new           #141                // class java/lang/StringBuffer
      58: dup
      59: invokespecial #142                // Method java/lang/StringBuffer."<init>":()V
      62: ldc_w         #951                // String The server
      65: invokevirtual #148                // Method java/lang/StringBuffer.append:(Ljava/lang/String;)Ljava/lang/StringBuffer;
      68: aload_2
      69: invokevirtual #644                // Method org/elasticsearch/hadoop/thirdparty/apache/commons/httpclient/HttpConnection.getHost:()Ljava/lang/String;
      72: invokevirtual #148                // Method java/lang/StringBuffer.append:(Ljava/lang/String;)Ljava/lang/StringBuffer;
      75: ldc_w         #953                // String  failed to respond
      78: invokevirtual #148                // Method java/lang/StringBuffer.append:(Ljava/lang/String;)Ljava/lang/StringBuffer;
      81: invokevirtual #159                // Method java/lang/StringBuffer.toString:()Ljava/lang/String;
      84: invokespecial #954                // Method org/elasticsearch/hadoop/thirdparty/apache/commons/httpclient/NoHttpResponseException."<init>":(Ljava/lang/String;)V
      87: athrow
      88: getstatic     #931                // Field org/elasticsearch/hadoop/thirdparty/apache/commons/httpclient/Wire.HEADER_WIRE:Lorg/elasticsearch/hadoop/thirdparty/apache/commons/httpclient/Wire;
      91: invokevirtual #844                // Method org/elasticsearch/hadoop/thirdparty/apache/commons/httpclient/Wire.enabled:()Z
      94: ifeq          124
      97: getstatic     #931                // Field org/elasticsearch/hadoop/thirdparty/apache/commons/httpclient/Wire.HEADER_WIRE:Lorg/elasticsearch/hadoop/thirdparty/apache/commons/httpclient/Wire;
     100: new           #141                // class java/lang/StringBuffer
     103: dup
     104: invokespecial #142                // Method java/lang/StringBuffer."<init>":()V
     107: aload         5
     109: invokevirtual #148                // Method java/lang/StringBuffer.append:(Ljava/lang/String;)Ljava/lang/StringBuffer;
     112: ldc_w         #750                // String \r\n
     115: invokevirtual #148                // Method java/lang/StringBuffer.append:(Ljava/lang/String;)Ljava/lang/StringBuffer;
     118: invokevirtual #159                // Method java/lang/StringBuffer.toString:()Ljava/lang/String;
     121: invokevirtual #934                // Method org/elasticsearch/hadoop/thirdparty/apache/commons/httpclient/Wire.input:(Ljava/lang/String;)V
     124: aload         5
     126: ifnull        140
     129: aload         5
     131: invokestatic  #957                // Method org/elasticsearch/hadoop/thirdparty/apache/commons/httpclient/StatusLine.startsWithHTTP:(Ljava/lang/String;)Z
     134: ifeq          140
     137: goto          194
     140: aload         5
     142: ifnull        151
     145: iload         4
     147: iload_3
     148: if_icmplt     188
     151: new           #554                // class org/elasticsearch/hadoop/thirdparty/apache/commons/httpclient/ProtocolException
     154: dup
     155: new           #141                // class java/lang/StringBuffer
     158: dup
     159: invokespecial #142                // Method java/lang/StringBuffer."<init>":()V
     162: ldc_w         #951                // String The server
     165: invokevirtual #148                // Method java/lang/StringBuffer.append:(Ljava/lang/String;)Ljava/lang/StringBuffer;
     168: aload_2
     169: invokevirtual #644                // Method org/elasticsearch/hadoop/thirdparty/apache/commons/httpclient/HttpConnection.getHost:()Ljava/lang/String;
     172: invokevirtual #148                // Method java/lang/StringBuffer.append:(Ljava/lang/String;)Ljava/lang/StringBuffer;
     175: ldc_w         #959                // String  failed to respond with a valid HTTP response
     178: invokevirtual #148                // Method java/lang/StringBuffer.append:(Ljava/lang/String;)Ljava/lang/StringBuffer;
     181: invokevirtual #159                // Method java/lang/StringBuffer.toString:()Ljava/lang/String;
     184: invokespecial #557                // Method org/elasticsearch/hadoop/thirdparty/apache/commons/httpclient/ProtocolException."<init>":(Ljava/lang/String;)V
     187: athrow
     188: iinc          4, 1
     191: goto          28
     194: aload_0
     195: new           #335                // class org/elasticsearch/hadoop/thirdparty/apache/commons/httpclient/StatusLine
     198: dup
     199: aload         5
     201: invokespecial #960                // Method org/elasticsearch/hadoop/thirdparty/apache/commons/httpclient/StatusLine."<init>":(Ljava/lang/String;)V
     204: putfield      #65                 // Field statusLine:Lorg/elasticsearch/hadoop/thirdparty/apache/commons/httpclient/StatusLine;
     207: aload_0
     208: getfield      #65                 // Field statusLine:Lorg/elasticsearch/hadoop/thirdparty/apache/commons/httpclient/StatusLine;
     211: invokevirtual #963                // Method org/elasticsearch/hadoop/thirdparty/apache/commons/httpclient/StatusLine.getHttpVersion:()Ljava/lang/String;
     214: astore        6
     216: aload_0
     217: invokevirtual #393                // Method getParams:()Lorg/elasticsearch/hadoop/thirdparty/apache/commons/httpclient/params/HttpMethodParams;
     220: ldc_w         #965                // String http.protocol.unambiguous-statusline
     223: invokevirtual #968                // Method org/elasticsearch/hadoop/thirdparty/apache/commons/httpclient/params/DefaultHttpParams.isParameterFalse:(Ljava/lang/String;)Z
     226: ifeq          298
     229: aload         6
     231: ldc_w         #970                // String HTTP
     234: invokevirtual #128                // Method java/lang/String.equals:(Ljava/lang/Object;)Z
     237: ifeq          298
     240: aload_0
     241: invokevirtual #393                // Method getParams:()Lorg/elasticsearch/hadoop/thirdparty/apache/commons/httpclient/params/HttpMethodParams;
     244: getstatic     #239                // Field org/elasticsearch/hadoop/thirdparty/apache/commons/httpclient/HttpVersion.HTTP_1_0:Lorg/elasticsearch/hadoop/thirdparty/apache/commons/httpclient/HttpVersion;
     247: invokevirtual #236                // Method org/elasticsearch/hadoop/thirdparty/apache/commons/httpclient/params/HttpMethodParams.setVersion:(Lorg/elasticsearch/hadoop/thirdparty/apache/commons/httpclient/HttpVersion;)V
     250: getstatic     #254                // Field LOG:Lorg/apache/commons/logging/Log;
     253: invokeinterface #366,  1          // InterfaceMethod org/apache/commons/logging/Log.isWarnEnabled:()Z
     258: ifeq          307
     261: getstatic     #254                // Field LOG:Lorg/apache/commons/logging/Log;
     264: new           #141                // class java/lang/StringBuffer
     267: dup
     268: invokespecial #142                // Method java/lang/StringBuffer."<init>":()V
     271: ldc_w         #972                // String Ambiguous status line (HTTP protocol version missing):
     274: invokevirtual #148                // Method java/lang/StringBuffer.append:(Ljava/lang/String;)Ljava/lang/StringBuffer;
     277: aload_0
     278: getfield      #65                 // Field statusLine:Lorg/elasticsearch/hadoop/thirdparty/apache/commons/httpclient/StatusLine;
     281: invokevirtual #812                // Method org/elasticsearch/hadoop/thirdparty/apache/commons/httpclient/StatusLine.toString:()Ljava/lang/String;
     284: invokevirtual #148                // Method java/lang/StringBuffer.append:(Ljava/lang/String;)Ljava/lang/StringBuffer;
     287: invokevirtual #159                // Method java/lang/StringBuffer.toString:()Ljava/lang/String;
     290: invokeinterface #354,  2          // InterfaceMethod org/apache/commons/logging/Log.warn:(Ljava/lang/Object;)V
     295: goto          307
     298: aload_0
     299: aload         6
     301: invokestatic  #975                // Method org/elasticsearch/hadoop/thirdparty/apache/commons/httpclient/HttpVersion.parse:(Ljava/lang/String;)Lorg/elasticsearch/hadoop/thirdparty/apache/commons/httpclient/HttpVersion;
     304: putfield      #105                // Field effectiveVersion:Lorg/elasticsearch/hadoop/thirdparty/apache/commons/httpclient/HttpVersion;
     307: return

  protected void writeRequest(org.elasticsearch.hadoop.thirdparty.apache.commons.httpclient.HttpState, org.elasticsearch.hadoop.thirdparty.apache.commons.httpclient.HttpConnection) throws java.io.IOException, org.elasticsearch.hadoop.thirdparty.apache.commons.httpclient.HttpException;
    Code:
       0: getstatic     #254                // Field LOG:Lorg/apache/commons/logging/Log;
       3: ldc_w         #982                // String enter HttpMethodBase.writeRequest(HttpState, HttpConnection)
       6: invokeinterface #262,  2          // InterfaceMethod org/apache/commons/logging/Log.trace:(Ljava/lang/Object;)V
      11: aload_0
      12: aload_1
      13: aload_2
      14: invokevirtual #985                // Method writeRequestLine:(Lorg/elasticsearch/hadoop/thirdparty/apache/commons/httpclient/HttpState;Lorg/elasticsearch/hadoop/thirdparty/apache/commons/httpclient/HttpConnection;)V
      17: aload_0
      18: aload_1
      19: aload_2
      20: invokevirtual #988                // Method writeRequestHeaders:(Lorg/elasticsearch/hadoop/thirdparty/apache/commons/httpclient/HttpState;Lorg/elasticsearch/hadoop/thirdparty/apache/commons/httpclient/HttpConnection;)V
      23: aload_2
      24: invokevirtual #991                // Method org/elasticsearch/hadoop/thirdparty/apache/commons/httpclient/HttpConnection.writeLine:()V
      27: getstatic     #931                // Field org/elasticsearch/hadoop/thirdparty/apache/commons/httpclient/Wire.HEADER_WIRE:Lorg/elasticsearch/hadoop/thirdparty/apache/commons/httpclient/Wire;
      30: invokevirtual #844                // Method org/elasticsearch/hadoop/thirdparty/apache/commons/httpclient/Wire.enabled:()Z
      33: ifeq          45
      36: getstatic     #931                // Field org/elasticsearch/hadoop/thirdparty/apache/commons/httpclient/Wire.HEADER_WIRE:Lorg/elasticsearch/hadoop/thirdparty/apache/commons/httpclient/Wire;
      39: ldc_w         #750                // String \r\n
      42: invokevirtual #994                // Method org/elasticsearch/hadoop/thirdparty/apache/commons/httpclient/Wire.output:(Ljava/lang/String;)V
      45: aload_0
      46: invokevirtual #393                // Method getParams:()Lorg/elasticsearch/hadoop/thirdparty/apache/commons/httpclient/params/HttpMethodParams;
      49: invokevirtual #247                // Method org/elasticsearch/hadoop/thirdparty/apache/commons/httpclient/params/HttpMethodParams.getVersion:()Lorg/elasticsearch/hadoop/thirdparty/apache/commons/httpclient/HttpVersion;
      52: astore_3
      53: aload_0
      54: ldc_w         #996                // String Expect
      57: invokevirtual #699                // Method getRequestHeader:(Ljava/lang/String;)Lorg/elasticsearch/hadoop/thirdparty/apache/commons/httpclient/Header;
      60: astore        4
      62: aconst_null
      63: astore        5
      65: aload         4
      67: ifnull        77
      70: aload         4
      72: invokevirtual #357                // Method org/elasticsearch/hadoop/thirdparty/apache/commons/httpclient/NameValuePair.getValue:()Ljava/lang/String;
      75: astore        5
      77: aload         5
      79: ifnull        264
      82: aload         5
      84: ldc_w         #998                // String 100-continue
      87: invokevirtual #1001               // Method java/lang/String.compareToIgnoreCase:(Ljava/lang/String;)I
      90: ifne          264
      93: aload_3
      94: getstatic     #232                // Field org/elasticsearch/hadoop/thirdparty/apache/commons/httpclient/HttpVersion.HTTP_1_1:Lorg/elasticsearch/hadoop/thirdparty/apache/commons/httpclient/HttpVersion;
      97: invokevirtual #528                // Method org/elasticsearch/hadoop/thirdparty/apache/commons/httpclient/HttpVersion.greaterEquals:(Lorg/elasticsearch/hadoop/thirdparty/apache/commons/httpclient/HttpVersion;)Z
     100: ifeq          246
     103: aload_2
     104: invokevirtual #1004               // Method org/elasticsearch/hadoop/thirdparty/apache/commons/httpclient/HttpConnection.flushRequestOutputStream:()V
     107: aload_2
     108: invokevirtual #868                // Method org/elasticsearch/hadoop/thirdparty/apache/commons/httpclient/HttpConnection.getParams:()Lorg/elasticsearch/hadoop/thirdparty/apache/commons/httpclient/params/HttpConnectionParams;
     111: invokevirtual #873                // Method org/elasticsearch/hadoop/thirdparty/apache/commons/httpclient/params/HttpConnectionParams.getSoTimeout:()I
     114: istore        6
     116: aload_2
     117: sipush        3000
     120: invokevirtual #1007               // Method org/elasticsearch/hadoop/thirdparty/apache/commons/httpclient/HttpConnection.setSocketTimeout:(I)V
     123: aload_0
     124: aload_1
     125: aload_2
     126: invokevirtual #799                // Method readStatusLine:(Lorg/elasticsearch/hadoop/thirdparty/apache/commons/httpclient/HttpState;Lorg/elasticsearch/hadoop/thirdparty/apache/commons/httpclient/HttpConnection;)V
     129: aload_0
     130: aload_1
     131: aload_2
     132: invokevirtual #801                // Method processStatusLine:(Lorg/elasticsearch/hadoop/thirdparty/apache/commons/httpclient/HttpState;Lorg/elasticsearch/hadoop/thirdparty/apache/commons/httpclient/HttpConnection;)V
     135: aload_0
     136: aload_1
     137: aload_2
     138: invokevirtual #804                // Method readResponseHeaders:(Lorg/elasticsearch/hadoop/thirdparty/apache/commons/httpclient/HttpState;Lorg/elasticsearch/hadoop/thirdparty/apache/commons/httpclient/HttpConnection;)V
     141: aload_0
     142: aload_1
     143: aload_2
     144: invokevirtual #806                // Method processResponseHeaders:(Lorg/elasticsearch/hadoop/thirdparty/apache/commons/httpclient/HttpState;Lorg/elasticsearch/hadoop/thirdparty/apache/commons/httpclient/HttpConnection;)V
     147: aload_0
     148: getfield      #65                 // Field statusLine:Lorg/elasticsearch/hadoop/thirdparty/apache/commons/httpclient/StatusLine;
     151: invokevirtual #337                // Method org/elasticsearch/hadoop/thirdparty/apache/commons/httpclient/StatusLine.getStatusCode:()I
     154: bipush        100
     156: if_icmpne     178
     159: aload_0
     160: aconst_null
     161: putfield      #65                 // Field statusLine:Lorg/elasticsearch/hadoop/thirdparty/apache/commons/httpclient/StatusLine;
     164: getstatic     #254                // Field LOG:Lorg/apache/commons/logging/Log;
     167: ldc_w         #1009               // String OK to continue received
     170: invokeinterface #267,  2          // InterfaceMethod org/apache/commons/logging/Log.debug:(Ljava/lang/Object;)V
     175: goto          182
     178: jsr           233
     181: return
     182: jsr           233
     185: goto          243
     188: astore        7
     190: aload         7
     192: invokestatic  #1015               // Method org/elasticsearch/hadoop/thirdparty/apache/commons/httpclient/util/ExceptionUtil.isSocketTimeoutException:(Ljava/io/InterruptedIOException;)Z
     195: ifne          201
     198: aload         7
     200: athrow
     201: aload_0
     202: ldc_w         #996                // String Expect
     205: invokevirtual #1017               // Method removeRequestHeader:(Ljava/lang/String;)V
     208: getstatic     #254                // Field LOG:Lorg/apache/commons/logging/Log;
     211: ldc_w         #1019               // String 100 (continue) read timeout. Resume sending the request
     214: invokeinterface #815,  2          // InterfaceMethod org/apache/commons/logging/Log.info:(Ljava/lang/Object;)V
     219: jsr           233
     222: goto          243
     225: astore        8
     227: jsr           233
     230: aload         8
     232: athrow
     233: astore        9
     235: aload_2
     236: iload         6
     238: invokevirtual #1007               // Method org/elasticsearch/hadoop/thirdparty/apache/commons/httpclient/HttpConnection.setSocketTimeout:(I)V
     241: ret           9
     243: goto          264
     246: aload_0
     247: ldc_w         #996                // String Expect
     250: invokevirtual #1017               // Method removeRequestHeader:(Ljava/lang/String;)V
     253: getstatic     #254                // Field LOG:Lorg/apache/commons/logging/Log;
     256: ldc_w         #1021               // String \'Expect: 100-continue\' handshake is only supported by HTTP/1.1 or higher
     259: invokeinterface #815,  2          // InterfaceMethod org/apache/commons/logging/Log.info:(Ljava/lang/Object;)V
     264: aload_0
     265: aload_1
     266: aload_2
     267: invokevirtual #1025               // Method writeRequestBody:(Lorg/elasticsearch/hadoop/thirdparty/apache/commons/httpclient/HttpState;Lorg/elasticsearch/hadoop/thirdparty/apache/commons/httpclient/HttpConnection;)Z
     270: pop
     271: aload_2
     272: invokevirtual #1004               // Method org/elasticsearch/hadoop/thirdparty/apache/commons/httpclient/HttpConnection.flushRequestOutputStream:()V
     275: return
    Exception table:
       from    to  target type
         116   182   188   Class java/io/InterruptedIOException
         116   225   225   any

  protected boolean writeRequestBody(org.elasticsearch.hadoop.thirdparty.apache.commons.httpclient.HttpState, org.elasticsearch.hadoop.thirdparty.apache.commons.httpclient.HttpConnection) throws java.io.IOException, org.elasticsearch.hadoop.thirdparty.apache.commons.httpclient.HttpException;
    Code:
       0: iconst_1
       1: ireturn

  protected void writeRequestHeaders(org.elasticsearch.hadoop.thirdparty.apache.commons.httpclient.HttpState, org.elasticsearch.hadoop.thirdparty.apache.commons.httpclient.HttpConnection) throws java.io.IOException, org.elasticsearch.hadoop.thirdparty.apache.commons.httpclient.HttpException;
    Code:
       0: getstatic     #254                // Field LOG:Lorg/apache/commons/logging/Log;
       3: ldc_w         #1032               // String enter HttpMethodBase.writeRequestHeaders(HttpState,HttpConnection)
       6: invokeinterface #262,  2          // InterfaceMethod org/apache/commons/logging/Log.trace:(Ljava/lang/Object;)V
      11: aload_0
      12: aload_1
      13: aload_2
      14: invokevirtual #1034               // Method addRequestHeaders:(Lorg/elasticsearch/hadoop/thirdparty/apache/commons/httpclient/HttpState;Lorg/elasticsearch/hadoop/thirdparty/apache/commons/httpclient/HttpConnection;)V
      17: aload_0
      18: invokevirtual #393                // Method getParams:()Lorg/elasticsearch/hadoop/thirdparty/apache/commons/httpclient/params/HttpMethodParams;
      21: invokevirtual #922                // Method org/elasticsearch/hadoop/thirdparty/apache/commons/httpclient/params/HttpMethodParams.getHttpElementCharset:()Ljava/lang/String;
      24: astore_3
      25: aload_0
      26: invokevirtual #1036               // Method getRequestHeaders:()[Lorg/elasticsearch/hadoop/thirdparty/apache/commons/httpclient/Header;
      29: astore        4
      31: iconst_0
      32: istore        5
      34: goto          74
      37: aload         4
      39: iload         5
      41: aaload
      42: invokevirtual #523                // Method org/elasticsearch/hadoop/thirdparty/apache/commons/httpclient/Header.toExternalForm:()Ljava/lang/String;
      45: astore        6
      47: getstatic     #931                // Field org/elasticsearch/hadoop/thirdparty/apache/commons/httpclient/Wire.HEADER_WIRE:Lorg/elasticsearch/hadoop/thirdparty/apache/commons/httpclient/Wire;
      50: invokevirtual #844                // Method org/elasticsearch/hadoop/thirdparty/apache/commons/httpclient/Wire.enabled:()Z
      53: ifeq          64
      56: getstatic     #931                // Field org/elasticsearch/hadoop/thirdparty/apache/commons/httpclient/Wire.HEADER_WIRE:Lorg/elasticsearch/hadoop/thirdparty/apache/commons/httpclient/Wire;
      59: aload         6
      61: invokevirtual #994                // Method org/elasticsearch/hadoop/thirdparty/apache/commons/httpclient/Wire.output:(Ljava/lang/String;)V
      64: aload_2
      65: aload         6
      67: aload_3
      68: invokevirtual #1039               // Method org/elasticsearch/hadoop/thirdparty/apache/commons/httpclient/HttpConnection.print:(Ljava/lang/String;Ljava/lang/String;)V
      71: iinc          5, 1
      74: iload         5
      76: aload         4
      78: arraylength
      79: if_icmplt     37
      82: return

  protected void writeRequestLine(org.elasticsearch.hadoop.thirdparty.apache.commons.httpclient.HttpState, org.elasticsearch.hadoop.thirdparty.apache.commons.httpclient.HttpConnection) throws java.io.IOException, org.elasticsearch.hadoop.thirdparty.apache.commons.httpclient.HttpException;
    Code:
       0: getstatic     #254                // Field LOG:Lorg/apache/commons/logging/Log;
       3: ldc_w         #1042               // String enter HttpMethodBase.writeRequestLine(HttpState, HttpConnection)
       6: invokeinterface #262,  2          // InterfaceMethod org/apache/commons/logging/Log.trace:(Ljava/lang/Object;)V
      11: aload_0
      12: aload_2
      13: invokespecial #1046               // Method getRequestLine:(Lorg/elasticsearch/hadoop/thirdparty/apache/commons/httpclient/HttpConnection;)Ljava/lang/String;
      16: astore_3
      17: getstatic     #931                // Field org/elasticsearch/hadoop/thirdparty/apache/commons/httpclient/Wire.HEADER_WIRE:Lorg/elasticsearch/hadoop/thirdparty/apache/commons/httpclient/Wire;
      20: invokevirtual #844                // Method org/elasticsearch/hadoop/thirdparty/apache/commons/httpclient/Wire.enabled:()Z
      23: ifeq          33
      26: getstatic     #931                // Field org/elasticsearch/hadoop/thirdparty/apache/commons/httpclient/Wire.HEADER_WIRE:Lorg/elasticsearch/hadoop/thirdparty/apache/commons/httpclient/Wire;
      29: aload_3
      30: invokevirtual #994                // Method org/elasticsearch/hadoop/thirdparty/apache/commons/httpclient/Wire.output:(Ljava/lang/String;)V
      33: aload_2
      34: aload_3
      35: aload_0
      36: invokevirtual #393                // Method getParams:()Lorg/elasticsearch/hadoop/thirdparty/apache/commons/httpclient/params/HttpMethodParams;
      39: invokevirtual #922                // Method org/elasticsearch/hadoop/thirdparty/apache/commons/httpclient/params/HttpMethodParams.getHttpElementCharset:()Ljava/lang/String;
      42: invokevirtual #1039               // Method org/elasticsearch/hadoop/thirdparty/apache/commons/httpclient/HttpConnection.print:(Ljava/lang/String;Ljava/lang/String;)V
      45: return

  private java.lang.String getRequestLine(org.elasticsearch.hadoop.thirdparty.apache.commons.httpclient.HttpConnection);
    Code:
       0: aload_1
       1: aload_0
       2: invokevirtual #1048               // Method getName:()Ljava/lang/String;
       5: aload_0
       6: invokevirtual #646                // Method getPath:()Ljava/lang/String;
       9: aload_0
      10: invokevirtual #1050               // Method getQueryString:()Ljava/lang/String;
      13: aload_0
      14: getfield      #105                // Field effectiveVersion:Lorg/elasticsearch/hadoop/thirdparty/apache/commons/httpclient/HttpVersion;
      17: invokevirtual #531                // Method org/elasticsearch/hadoop/thirdparty/apache/commons/httpclient/HttpVersion.toString:()Ljava/lang/String;
      20: invokestatic  #1052               // Method generateRequestLine:(Lorg/elasticsearch/hadoop/thirdparty/apache/commons/httpclient/HttpConnection;Ljava/lang/String;Ljava/lang/String;Ljava/lang/String;Ljava/lang/String;)Ljava/lang/String;
      23: areturn

  public org.elasticsearch.hadoop.thirdparty.apache.commons.httpclient.params.HttpMethodParams getParams();
    Code:
       0: aload_0
       1: getfield      #88                 // Field params:Lorg/elasticsearch/hadoop/thirdparty/apache/commons/httpclient/params/HttpMethodParams;
       4: areturn

  public void setParams(org.elasticsearch.hadoop.thirdparty.apache.commons.httpclient.params.HttpMethodParams);
    Code:
       0: aload_1
       1: ifnonnull     15
       4: new           #116                // class java/lang/IllegalArgumentException
       7: dup
       8: ldc_w         #1056               // String Parameters may not be null
      11: invokespecial #161                // Method java/lang/IllegalArgumentException."<init>":(Ljava/lang/String;)V
      14: athrow
      15: aload_0
      16: aload_1
      17: putfield      #88                 // Field params:Lorg/elasticsearch/hadoop/thirdparty/apache/commons/httpclient/params/HttpMethodParams;
      20: return

  public org.elasticsearch.hadoop.thirdparty.apache.commons.httpclient.HttpVersion getEffectiveVersion();
    Code:
       0: aload_0
       1: getfield      #105                // Field effectiveVersion:Lorg/elasticsearch/hadoop/thirdparty/apache/commons/httpclient/HttpVersion;
       4: areturn

  private static boolean canResponseHaveBody(int);
    Code:
       0: getstatic     #254                // Field LOG:Lorg/apache/commons/logging/Log;
       3: ldc_w         #1059               // String enter HttpMethodBase.canResponseHaveBody(int)
       6: invokeinterface #262,  2          // InterfaceMethod org/apache/commons/logging/Log.trace:(Ljava/lang/Object;)V
      11: iconst_1
      12: istore_1
      13: iload_0
      14: bipush        100
      16: if_icmplt     26
      19: iload_0
      20: sipush        199
      23: if_icmple     40
      26: iload_0
      27: sipush        204
      30: if_icmpeq     40
      33: iload_0
      34: sipush        304
      37: if_icmpne     42
      40: iconst_0
      41: istore_1
      42: iload_1
      43: ireturn

  public java.lang.String getProxyAuthenticationRealm();
    Code:
       0: aload_0
       1: getfield      #95                 // Field proxyAuthState:Lorg/elasticsearch/hadoop/thirdparty/apache/commons/httpclient/auth/AuthState;
       4: invokevirtual #1063               // Method org/elasticsearch/hadoop/thirdparty/apache/commons/httpclient/auth/AuthState.getRealm:()Ljava/lang/String;
       7: areturn

  public java.lang.String getAuthenticationRealm();
    Code:
       0: aload_0
       1: getfield      #93                 // Field hostAuthState:Lorg/elasticsearch/hadoop/thirdparty/apache/commons/httpclient/auth/AuthState;
       4: invokevirtual #1063               // Method org/elasticsearch/hadoop/thirdparty/apache/commons/httpclient/auth/AuthState.getRealm:()Ljava/lang/String;
       7: areturn

  protected java.lang.String getContentCharSet(org.elasticsearch.hadoop.thirdparty.apache.commons.httpclient.Header);
    Code:
       0: getstatic     #254                // Field LOG:Lorg/apache/commons/logging/Log;
       3: ldc_w         #1068               // String enter getContentCharSet( Header contentheader )
       6: invokeinterface #262,  2          // InterfaceMethod org/apache/commons/logging/Log.trace:(Ljava/lang/Object;)V
      11: aconst_null
      12: astore_2
      13: aload_1
      14: ifnull        50
      17: aload_1
      18: invokevirtual #865                // Method org/elasticsearch/hadoop/thirdparty/apache/commons/httpclient/Header.getElements:()[Lorg/elasticsearch/hadoop/thirdparty/apache/commons/httpclient/HeaderElement;
      21: astore_3
      22: aload_3
      23: arraylength
      24: iconst_1
      25: if_icmpne     50
      28: aload_3
      29: iconst_0
      30: aaload
      31: ldc_w         #1069               // String charset
      34: invokevirtual #1075               // Method org/elasticsearch/hadoop/thirdparty/apache/commons/httpclient/HeaderElement.getParameterByName:(Ljava/lang/String;)Lorg/elasticsearch/hadoop/thirdparty/apache/commons/httpclient/NameValuePair;
      37: astore        4
      39: aload         4
      41: ifnull        50
      44: aload         4
      46: invokevirtual #357                // Method org/elasticsearch/hadoop/thirdparty/apache/commons/httpclient/NameValuePair.getValue:()Ljava/lang/String;
      49: astore_2
      50: aload_2
      51: ifnonnull     101
      54: aload_0
      55: invokevirtual #393                // Method getParams:()Lorg/elasticsearch/hadoop/thirdparty/apache/commons/httpclient/params/HttpMethodParams;
      58: invokevirtual #1078               // Method org/elasticsearch/hadoop/thirdparty/apache/commons/httpclient/params/HttpMethodParams.getContentCharset:()Ljava/lang/String;
      61: astore_2
      62: getstatic     #254                // Field LOG:Lorg/apache/commons/logging/Log;
      65: invokeinterface #483,  1          // InterfaceMethod org/apache/commons/logging/Log.isDebugEnabled:()Z
      70: ifeq          101
      73: getstatic     #254                // Field LOG:Lorg/apache/commons/logging/Log;
      76: new           #141                // class java/lang/StringBuffer
      79: dup
      80: invokespecial #142                // Method java/lang/StringBuffer."<init>":()V
      83: ldc_w         #1080               // String Default charset used:
      86: invokevirtual #148                // Method java/lang/StringBuffer.append:(Ljava/lang/String;)Ljava/lang/StringBuffer;
      89: aload_2
      90: invokevirtual #148                // Method java/lang/StringBuffer.append:(Ljava/lang/String;)Ljava/lang/StringBuffer;
      93: invokevirtual #159                // Method java/lang/StringBuffer.toString:()Ljava/lang/String;
      96: invokeinterface #267,  2          // InterfaceMethod org/apache/commons/logging/Log.debug:(Ljava/lang/Object;)V
     101: aload_2
     102: areturn

  public java.lang.String getRequestCharSet();
    Code:
       0: aload_0
       1: aload_0
       2: ldc_w         #1087               // String Content-Type
       5: invokevirtual #699                // Method getRequestHeader:(Ljava/lang/String;)Lorg/elasticsearch/hadoop/thirdparty/apache/commons/httpclient/Header;
       8: invokevirtual #1089               // Method getContentCharSet:(Lorg/elasticsearch/hadoop/thirdparty/apache/commons/httpclient/Header;)Ljava/lang/String;
      11: areturn

  public java.lang.String getResponseCharSet();
    Code:
       0: aload_0
       1: aload_0
       2: ldc_w         #1087               // String Content-Type
       5: invokevirtual #1091               // Method getResponseHeader:(Ljava/lang/String;)Lorg/elasticsearch/hadoop/thirdparty/apache/commons/httpclient/Header;
       8: invokevirtual #1089               // Method getContentCharSet:(Lorg/elasticsearch/hadoop/thirdparty/apache/commons/httpclient/Header;)Ljava/lang/String;
      11: areturn

  public int getRecoverableExceptionCount();
    Code:
       0: aload_0
       1: getfield      #99                 // Field recoverableExceptionCount:I
       4: ireturn

  protected void responseBodyConsumed();
    Code:
       0: aload_0
       1: aconst_null
       2: putfield      #75                 // Field responseStream:Ljava/io/InputStream;
       5: aload_0
       6: getfield      #77                 // Field responseConnection:Lorg/elasticsearch/hadoop/thirdparty/apache/commons/httpclient/HttpConnection;
       9: ifnull        107
      12: aload_0
      13: getfield      #77                 // Field responseConnection:Lorg/elasticsearch/hadoop/thirdparty/apache/commons/httpclient/HttpConnection;
      16: aconst_null
      17: invokevirtual #568                // Method org/elasticsearch/hadoop/thirdparty/apache/commons/httpclient/HttpConnection.setLastResponseInputStream:(Ljava/io/InputStream;)V
      20: aload_0
      21: aload_0
      22: getfield      #77                 // Field responseConnection:Lorg/elasticsearch/hadoop/thirdparty/apache/commons/httpclient/HttpConnection;
      25: invokevirtual #1094               // Method shouldCloseConnection:(Lorg/elasticsearch/hadoop/thirdparty/apache/commons/httpclient/HttpConnection;)Z
      28: ifeq          41
      31: aload_0
      32: getfield      #77                 // Field responseConnection:Lorg/elasticsearch/hadoop/thirdparty/apache/commons/httpclient/HttpConnection;
      35: invokevirtual #576                // Method org/elasticsearch/hadoop/thirdparty/apache/commons/httpclient/HttpConnection.close:()V
      38: goto          107
      41: aload_0
      42: getfield      #77                 // Field responseConnection:Lorg/elasticsearch/hadoop/thirdparty/apache/commons/httpclient/HttpConnection;
      45: invokevirtual #1096               // Method org/elasticsearch/hadoop/thirdparty/apache/commons/httpclient/HttpConnection.isResponseAvailable:()Z
      48: ifeq          84
      51: aload_0
      52: invokevirtual #393                // Method getParams:()Lorg/elasticsearch/hadoop/thirdparty/apache/commons/httpclient/params/HttpMethodParams;
      55: ldc_w         #1098               // String http.protocol.warn-extra-input
      58: invokevirtual #662                // Method org/elasticsearch/hadoop/thirdparty/apache/commons/httpclient/params/DefaultHttpParams.isParameterTrue:(Ljava/lang/String;)Z
      61: istore_1
      62: iload_1
      63: ifeq          77
      66: getstatic     #254                // Field LOG:Lorg/apache/commons/logging/Log;
      69: ldc_w         #1100               // String Extra response data detected - closing connection
      72: invokeinterface #354,  2          // InterfaceMethod org/apache/commons/logging/Log.warn:(Ljava/lang/Object;)V
      77: aload_0
      78: getfield      #77                 // Field responseConnection:Lorg/elasticsearch/hadoop/thirdparty/apache/commons/httpclient/HttpConnection;
      81: invokevirtual #576                // Method org/elasticsearch/hadoop/thirdparty/apache/commons/httpclient/HttpConnection.close:()V
      84: goto          107
      87: astore_1
      88: getstatic     #254                // Field LOG:Lorg/apache/commons/logging/Log;
      91: aload_1
      92: invokevirtual #156                // Method java/lang/Throwable.getMessage:()Ljava/lang/String;
      95: invokeinterface #354,  2          // InterfaceMethod org/apache/commons/logging/Log.warn:(Ljava/lang/Object;)V
     100: aload_0
     101: getfield      #77                 // Field responseConnection:Lorg/elasticsearch/hadoop/thirdparty/apache/commons/httpclient/HttpConnection;
     104: invokevirtual #576                // Method org/elasticsearch/hadoop/thirdparty/apache/commons/httpclient/HttpConnection.close:()V
     107: aload_0
     108: iconst_0
     109: putfield      #103                // Field connectionCloseForced:Z
     112: aload_0
     113: invokespecial #593                // Method ensureConnectionRelease:()V
     116: return
    Exception table:
       from    to  target type
          41    84    87   Class java/io/IOException

  private void ensureConnectionRelease();
    Code:
       0: aload_0
       1: getfield      #77                 // Field responseConnection:Lorg/elasticsearch/hadoop/thirdparty/apache/commons/httpclient/HttpConnection;
       4: ifnull        19
       7: aload_0
       8: getfield      #77                 // Field responseConnection:Lorg/elasticsearch/hadoop/thirdparty/apache/commons/httpclient/HttpConnection;
      11: invokevirtual #1102               // Method org/elasticsearch/hadoop/thirdparty/apache/commons/httpclient/HttpConnection.releaseConnection:()V
      14: aload_0
      15: aconst_null
      16: putfield      #77                 // Field responseConnection:Lorg/elasticsearch/hadoop/thirdparty/apache/commons/httpclient/HttpConnection;
      19: return

  public org.elasticsearch.hadoop.thirdparty.apache.commons.httpclient.HostConfiguration getHostConfiguration();
    Code:
       0: new           #1106               // class org/elasticsearch/hadoop/thirdparty/apache/commons/httpclient/HostConfiguration
       3: dup
       4: invokespecial #1107               // Method org/elasticsearch/hadoop/thirdparty/apache/commons/httpclient/HostConfiguration."<init>":()V
       7: astore_1
       8: aload_1
       9: aload_0
      10: getfield      #101                // Field httphost:Lorg/elasticsearch/hadoop/thirdparty/apache/commons/httpclient/HttpHost;
      13: invokevirtual #1111               // Method org/elasticsearch/hadoop/thirdparty/apache/commons/httpclient/HostConfiguration.setHost:(Lorg/elasticsearch/hadoop/thirdparty/apache/commons/httpclient/HttpHost;)V
      16: aload_1
      17: areturn

  public void setHostConfiguration(org.elasticsearch.hadoop.thirdparty.apache.commons.httpclient.HostConfiguration);
    Code:
       0: aload_1
       1: ifnull        30
       4: aload_0
       5: new           #169                // class org/elasticsearch/hadoop/thirdparty/apache/commons/httpclient/HttpHost
       8: dup
       9: aload_1
      10: invokevirtual #1116               // Method org/elasticsearch/hadoop/thirdparty/apache/commons/httpclient/HostConfiguration.getHost:()Ljava/lang/String;
      13: aload_1
      14: invokevirtual #1117               // Method org/elasticsearch/hadoop/thirdparty/apache/commons/httpclient/HostConfiguration.getPort:()I
      17: aload_1
      18: invokevirtual #1118               // Method org/elasticsearch/hadoop/thirdparty/apache/commons/httpclient/HostConfiguration.getProtocol:()Lorg/elasticsearch/hadoop/thirdparty/apache/commons/httpclient/protocol/Protocol;
      21: invokespecial #1121               // Method org/elasticsearch/hadoop/thirdparty/apache/commons/httpclient/HttpHost."<init>":(Ljava/lang/String;ILorg/elasticsearch/hadoop/thirdparty/apache/commons/httpclient/protocol/Protocol;)V
      24: putfield      #101                // Field httphost:Lorg/elasticsearch/hadoop/thirdparty/apache/commons/httpclient/HttpHost;
      27: goto          35
      30: aload_0
      31: aconst_null
      32: putfield      #101                // Field httphost:Lorg/elasticsearch/hadoop/thirdparty/apache/commons/httpclient/HttpHost;
      35: return

  public org.elasticsearch.hadoop.thirdparty.apache.commons.httpclient.MethodRetryHandler getMethodRetryHandler();
    Code:
       0: aload_0
       1: getfield      #1125               // Field methodRetryHandler:Lorg/elasticsearch/hadoop/thirdparty/apache/commons/httpclient/MethodRetryHandler;
       4: areturn

  public void setMethodRetryHandler(org.elasticsearch.hadoop.thirdparty.apache.commons.httpclient.MethodRetryHandler);
    Code:
       0: aload_0
       1: aload_1
       2: putfield      #1125               // Field methodRetryHandler:Lorg/elasticsearch/hadoop/thirdparty/apache/commons/httpclient/MethodRetryHandler;
       5: return

  void fakeResponse(org.elasticsearch.hadoop.thirdparty.apache.commons.httpclient.StatusLine, org.elasticsearch.hadoop.thirdparty.apache.commons.httpclient.HeaderGroup, java.io.InputStream);
    Code:
       0: aload_0
       1: iconst_1
       2: putfield      #97                 // Field used:Z
       5: aload_0
       6: aload_1
       7: putfield      #65                 // Field statusLine:Lorg/elasticsearch/hadoop/thirdparty/apache/commons/httpclient/StatusLine;
      10: aload_0
      11: aload_2
      12: putfield      #67                 // Field responseHeaders:Lorg/elasticsearch/hadoop/thirdparty/apache/commons/httpclient/HeaderGroup;
      15: aload_0
      16: aconst_null
      17: putfield      #79                 // Field responseBody:[B
      20: aload_0
      21: aload_3
      22: putfield      #75                 // Field responseStream:Ljava/io/InputStream;
      25: return

  public org.elasticsearch.hadoop.thirdparty.apache.commons.httpclient.auth.AuthState getHostAuthState();
    Code:
       0: aload_0
       1: getfield      #93                 // Field hostAuthState:Lorg/elasticsearch/hadoop/thirdparty/apache/commons/httpclient/auth/AuthState;
       4: areturn

  public org.elasticsearch.hadoop.thirdparty.apache.commons.httpclient.auth.AuthState getProxyAuthState();
    Code:
       0: aload_0
       1: getfield      #95                 // Field proxyAuthState:Lorg/elasticsearch/hadoop/thirdparty/apache/commons/httpclient/auth/AuthState;
       4: areturn

  public boolean isAborted();
    Code:
       0: aload_0
       1: getfield      #107                // Field aborted:Z
       4: ireturn

  public boolean isRequestSent();
    Code:
       0: aload_0
       1: getfield      #109                // Field requestSent:Z
       4: ireturn

  static java.lang.Class class$(java.lang.String);
    Code:
       0: aload_0
       1: invokestatic  #1146               // Method java/lang/Class.forName:(Ljava/lang/String;)Ljava/lang/Class;
       4: areturn
       5: astore_1
       6: new           #1148               // class java/lang/NoClassDefFoundError
       9: dup
      10: aload_1
      11: invokevirtual #156                // Method java/lang/Throwable.getMessage:()Ljava/lang/String;
      14: invokespecial #1149               // Method java/lang/NoClassDefFoundError."<init>":(Ljava/lang/String;)V
      17: athrow
    Exception table:
       from    to  target type
           0     5     5   Class java/lang/ClassNotFoundException

  static {};
    Code:
       0: getstatic     #1155               // Field class$org$apache$commons$httpclient$HttpMethodBase:Ljava/lang/Class;
       3: ifnonnull     19
       6: ldc_w         #1157               // String org.elasticsearch.hadoop.thirdparty.apache.commons.httpclient.HttpMethodBase
       9: invokestatic  #1159               // Method class$:(Ljava/lang/String;)Ljava/lang/Class;
      12: dup
      13: putstatic     #1155               // Field class$org$apache$commons$httpclient$HttpMethodBase:Ljava/lang/Class;
      16: goto          22
      19: getstatic     #1155               // Field class$org$apache$commons$httpclient$HttpMethodBase:Ljava/lang/Class;
      22: invokestatic  #1165               // Method org/apache/commons/logging/LogFactory.getLog:(Ljava/lang/Class;)Lorg/apache/commons/logging/Log;
      25: putstatic     #254                // Field LOG:Lorg/apache/commons/logging/Log;
      28: return
}
