Compiled from "HttpMethodBase.java"
class org.elasticsearch.hadoop.thirdparty.apache.commons.httpclient.HttpMethodBase$1 implements org.elasticsearch.hadoop.thirdparty.apache.commons.httpclient.ResponseConsumedWatcher {
  private final org.elasticsearch.hadoop.thirdparty.apache.commons.httpclient.HttpMethodBase this$0;

  org.elasticsearch.hadoop.thirdparty.apache.commons.httpclient.HttpMethodBase$1(org.elasticsearch.hadoop.thirdparty.apache.commons.httpclient.HttpMethodBase);
    Code:
       0: aload_0
       1: invokespecial #14                 // Method java/lang/Object."<init>":()V
       4: aload_0
       5: aload_1
       6: putfield      #16                 // Field this$0:Lorg/elasticsearch/hadoop/thirdparty/apache/commons/httpclient/HttpMethodBase;
       9: return

  public void responseConsumed();
    Code:
       0: aload_0
       1: getfield      #16                 // Field this$0:Lorg/elasticsearch/hadoop/thirdparty/apache/commons/httpclient/HttpMethodBase;
       4: invokevirtual #24                 // Method org/elasticsearch/hadoop/thirdparty/apache/commons/httpclient/HttpMethodBase.responseBodyConsumed:()V
       7: return
}
