Compiled from "HttpException.java"
public class org.elasticsearch.hadoop.thirdparty.apache.commons.httpclient.HttpException extends java.io.IOException {
  private java.lang.String reason;

  private int reasonCode;

  private final java.lang.Throwable cause;

  static java.lang.Class class$java$lang$Throwable;

  public org.elasticsearch.hadoop.thirdparty.apache.commons.httpclient.HttpException();
    Code:
       0: aload_0
       1: invokespecial #17                 // Method java/io/IOException."<init>":()V
       4: aload_0
       5: sipush        200
       8: putfield      #19                 // Field reasonCode:I
      11: aload_0
      12: aconst_null
      13: putfield      #21                 // Field cause:Ljava/lang/Throwable;
      16: return

  public org.elasticsearch.hadoop.thirdparty.apache.commons.httpclient.HttpException(java.lang.String);
    Code:
       0: aload_0
       1: aload_1
       2: invokespecial #26                 // Method java/io/IOException."<init>":(Ljava/lang/String;)V
       5: aload_0
       6: sipush        200
       9: putfield      #19                 // Field reasonCode:I
      12: aload_0
      13: aconst_null
      14: putfield      #21                 // Field cause:Ljava/lang/Throwable;
      17: return

  public org.elasticsearch.hadoop.thirdparty.apache.commons.httpclient.HttpException(java.lang.String, java.lang.Throwable);
    Code:
       0: aload_0
       1: aload_1
       2: invokespecial #26                 // Method java/io/IOException."<init>":(Ljava/lang/String;)V
       5: aload_0
       6: sipush        200
       9: putfield      #19                 // Field reasonCode:I
      12: aload_0
      13: aload_2
      14: putfield      #21                 // Field cause:Ljava/lang/Throwable;
      17: iconst_1
      18: anewarray     #32                 // class java/lang/Class
      21: dup
      22: iconst_0
      23: getstatic     #34                 // Field class$java$lang$Throwable:Ljava/lang/Class;
      26: ifnonnull     41
      29: ldc           #36                 // String java.lang.Throwable
      31: invokestatic  #40                 // Method class$:(Ljava/lang/String;)Ljava/lang/Class;
      34: dup
      35: putstatic     #34                 // Field class$java$lang$Throwable:Ljava/lang/Class;
      38: goto          44
      41: getstatic     #34                 // Field class$java$lang$Throwable:Ljava/lang/Class;
      44: aastore
      45: astore_3
      46: getstatic     #34                 // Field class$java$lang$Throwable:Ljava/lang/Class;
      49: ifnonnull     64
      52: ldc           #36                 // String java.lang.Throwable
      54: invokestatic  #40                 // Method class$:(Ljava/lang/String;)Ljava/lang/Class;
      57: dup
      58: putstatic     #34                 // Field class$java$lang$Throwable:Ljava/lang/Class;
      61: goto          67
      64: getstatic     #34                 // Field class$java$lang$Throwable:Ljava/lang/Class;
      67: ldc           #42                 // String initCause
      69: aload_3
      70: invokevirtual #46                 // Method java/lang/Class.getMethod:(Ljava/lang/String;[Ljava/lang/Class;)Ljava/lang/reflect/Method;
      73: astore        4
      75: aload         4
      77: aload_0
      78: iconst_1
      79: anewarray     #48                 // class java/lang/Object
      82: dup
      83: iconst_0
      84: aload_2
      85: aastore
      86: invokevirtual #54                 // Method java/lang/reflect/Method.invoke:(Ljava/lang/Object;[Ljava/lang/Object;)Ljava/lang/Object;
      89: pop
      90: goto          94
      93: astore_3
      94: return
    Exception table:
       from    to  target type
          17    90    93   Class java/lang/Exception

  public java.lang.Throwable getCause();
    Code:
       0: aload_0
       1: getfield      #21                 // Field cause:Ljava/lang/Throwable;
       4: areturn

  public void printStackTrace();
    Code:
       0: aload_0
       1: getstatic     #68                 // Field java/lang/System.err:Ljava/io/PrintStream;
       4: invokevirtual #71                 // Method printStackTrace:(Ljava/io/PrintStream;)V
       7: return

  public void printStackTrace(java.io.PrintStream);
    Code:
       0: iconst_0
       1: anewarray     #32                 // class java/lang/Class
       4: astore_2
       5: aload_0
       6: invokevirtual #75                 // Method java/lang/Object.getClass:()Ljava/lang/Class;
       9: ldc           #77                 // String getStackTrace
      11: aload_2
      12: invokevirtual #46                 // Method java/lang/Class.getMethod:(Ljava/lang/String;[Ljava/lang/Class;)Ljava/lang/reflect/Method;
      15: pop
      16: aload_0
      17: aload_1
      18: invokespecial #80                 // Method java/lang/Throwable.printStackTrace:(Ljava/io/PrintStream;)V
      21: goto          51
      24: astore_2
      25: aload_0
      26: aload_1
      27: invokespecial #80                 // Method java/lang/Throwable.printStackTrace:(Ljava/io/PrintStream;)V
      30: aload_0
      31: getfield      #21                 // Field cause:Ljava/lang/Throwable;
      34: ifnull        51
      37: aload_1
      38: ldc           #82                 // String Caused by:
      40: invokevirtual #87                 // Method java/io/PrintStream.print:(Ljava/lang/String;)V
      43: aload_0
      44: getfield      #21                 // Field cause:Ljava/lang/Throwable;
      47: aload_1
      48: invokevirtual #80                 // Method java/lang/Throwable.printStackTrace:(Ljava/io/PrintStream;)V
      51: return
    Exception table:
       from    to  target type
           0    21    24   Class java/lang/Exception

  public void printStackTrace(java.io.PrintWriter);
    Code:
       0: iconst_0
       1: anewarray     #32                 // class java/lang/Class
       4: astore_2
       5: aload_0
       6: invokevirtual #75                 // Method java/lang/Object.getClass:()Ljava/lang/Class;
       9: ldc           #77                 // String getStackTrace
      11: aload_2
      12: invokevirtual #46                 // Method java/lang/Class.getMethod:(Ljava/lang/String;[Ljava/lang/Class;)Ljava/lang/reflect/Method;
      15: pop
      16: aload_0
      17: aload_1
      18: invokespecial #92                 // Method java/lang/Throwable.printStackTrace:(Ljava/io/PrintWriter;)V
      21: goto          51
      24: astore_2
      25: aload_0
      26: aload_1
      27: invokespecial #92                 // Method java/lang/Throwable.printStackTrace:(Ljava/io/PrintWriter;)V
      30: aload_0
      31: getfield      #21                 // Field cause:Ljava/lang/Throwable;
      34: ifnull        51
      37: aload_1
      38: ldc           #82                 // String Caused by:
      40: invokevirtual #95                 // Method java/io/PrintWriter.print:(Ljava/lang/String;)V
      43: aload_0
      44: getfield      #21                 // Field cause:Ljava/lang/Throwable;
      47: aload_1
      48: invokevirtual #92                 // Method java/lang/Throwable.printStackTrace:(Ljava/io/PrintWriter;)V
      51: return
    Exception table:
       from    to  target type
           0    21    24   Class java/lang/Exception

  public void setReason(java.lang.String);
    Code:
       0: aload_0
       1: aload_1
       2: putfield      #99                 // Field reason:Ljava/lang/String;
       5: return

  public java.lang.String getReason();
    Code:
       0: aload_0
       1: getfield      #99                 // Field reason:Ljava/lang/String;
       4: areturn

  public void setReasonCode(int);
    Code:
       0: aload_0
       1: iload_1
       2: putfield      #19                 // Field reasonCode:I
       5: return

  public int getReasonCode();
    Code:
       0: aload_0
       1: getfield      #19                 // Field reasonCode:I
       4: ireturn

  static java.lang.Class class$(java.lang.String);
    Code:
       0: aload_0
       1: invokestatic  #111                // Method java/lang/Class.forName:(Ljava/lang/String;)Ljava/lang/Class;
       4: areturn
       5: astore_1
       6: new           #113                // class java/lang/NoClassDefFoundError
       9: dup
      10: aload_1
      11: invokevirtual #116                // Method java/lang/Throwable.getMessage:()Ljava/lang/String;
      14: invokespecial #117                // Method java/lang/NoClassDefFoundError."<init>":(Ljava/lang/String;)V
      17: athrow
    Exception table:
       from    to  target type
           0     5     5   Class java/lang/ClassNotFoundException
}
