Compiled from "NoHttpResponseException.java"
public class org.elasticsearch.hadoop.thirdparty.apache.commons.httpclient.NoHttpResponseException extends java.io.IOException {
  public org.elasticsearch.hadoop.thirdparty.apache.commons.httpclient.NoHttpResponseException();
    Code:
       0: aload_0
       1: invokespecial #9                  // Method java/io/IOException."<init>":()V
       4: return

  public org.elasticsearch.hadoop.thirdparty.apache.commons.httpclient.NoHttpResponseException(java.lang.String);
    Code:
       0: aload_0
       1: aload_1
       2: invokespecial #14                 // Method java/io/IOException."<init>":(Ljava/lang/String;)V
       5: return

  public org.elasticsearch.hadoop.thirdparty.apache.commons.httpclient.NoHttpResponseException(java.lang.String, java.lang.Throwable);
    Code:
       0: aload_0
       1: aload_1
       2: invokespecial #14                 // Method java/io/IOException."<init>":(Ljava/lang/String;)V
       5: aload_0
       6: aload_2
       7: invokestatic  #23                 // Method org/elasticsearch/hadoop/thirdparty/apache/commons/httpclient/util/ExceptionUtil.initCause:(Ljava/lang/Throwable;Ljava/lang/Throwable;)V
      10: return
}
