Compiled from "UsernamePasswordCredentials.java"
public class org.elasticsearch.hadoop.thirdparty.apache.commons.httpclient.UsernamePasswordCredentials implements org.elasticsearch.hadoop.thirdparty.apache.commons.httpclient.Credentials {
  private java.lang.String userName;

  private java.lang.String password;

  public org.elasticsearch.hadoop.thirdparty.apache.commons.httpclient.UsernamePasswordCredentials();
    Code:
       0: aload_0
       1: invokespecial #14                 // Method java/lang/Object."<init>":()V
       4: return

  public org.elasticsearch.hadoop.thirdparty.apache.commons.httpclient.UsernamePasswordCredentials(java.lang.String);
    Code:
       0: aload_0
       1: invokespecial #14                 // Method java/lang/Object."<init>":()V
       4: aload_1
       5: ifnonnull     18
       8: new           #19                 // class java/lang/IllegalArgumentException
      11: dup
      12: ldc           #21                 // String Username:password string may not be null
      14: invokespecial #23                 // Method java/lang/IllegalArgumentException."<init>":(Ljava/lang/String;)V
      17: athrow
      18: aload_1
      19: bipush        58
      21: invokevirtual #29                 // Method java/lang/String.indexOf:(I)I
      24: istore_2
      25: iload_2
      26: iflt          53
      29: aload_0
      30: aload_1
      31: iconst_0
      32: iload_2
      33: invokevirtual #33                 // Method java/lang/String.substring:(II)Ljava/lang/String;
      36: putfield      #35                 // Field userName:Ljava/lang/String;
      39: aload_0
      40: aload_1
      41: iload_2
      42: iconst_1
      43: iadd
      44: invokevirtual #38                 // Method java/lang/String.substring:(I)Ljava/lang/String;
      47: putfield      #40                 // Field password:Ljava/lang/String;
      50: goto          58
      53: aload_0
      54: aload_1
      55: putfield      #35                 // Field userName:Ljava/lang/String;
      58: return

  public org.elasticsearch.hadoop.thirdparty.apache.commons.httpclient.UsernamePasswordCredentials(java.lang.String, java.lang.String);
    Code:
       0: aload_0
       1: invokespecial #14                 // Method java/lang/Object."<init>":()V
       4: aload_1
       5: ifnonnull     18
       8: new           #19                 // class java/lang/IllegalArgumentException
      11: dup
      12: ldc           #46                 // String Username may not be null
      14: invokespecial #23                 // Method java/lang/IllegalArgumentException."<init>":(Ljava/lang/String;)V
      17: athrow
      18: aload_0
      19: aload_1
      20: putfield      #35                 // Field userName:Ljava/lang/String;
      23: aload_0
      24: aload_2
      25: putfield      #40                 // Field password:Ljava/lang/String;
      28: return

  public void setUserName(java.lang.String);
    Code:
       0: aload_1
       1: ifnonnull     14
       4: new           #19                 // class java/lang/IllegalArgumentException
       7: dup
       8: ldc           #46                 // String Username may not be null
      10: invokespecial #23                 // Method java/lang/IllegalArgumentException."<init>":(Ljava/lang/String;)V
      13: athrow
      14: aload_0
      15: aload_1
      16: putfield      #35                 // Field userName:Ljava/lang/String;
      19: return

  public java.lang.String getUserName();
    Code:
       0: aload_0
       1: getfield      #35                 // Field userName:Ljava/lang/String;
       4: areturn

  public void setPassword(java.lang.String);
    Code:
       0: aload_0
       1: aload_1
       2: putfield      #40                 // Field password:Ljava/lang/String;
       5: return

  public java.lang.String getPassword();
    Code:
       0: aload_0
       1: getfield      #40                 // Field password:Ljava/lang/String;
       4: areturn

  public java.lang.String toString();
    Code:
       0: new           #54                 // class java/lang/StringBuffer
       3: dup
       4: invokespecial #55                 // Method java/lang/StringBuffer."<init>":()V
       7: astore_1
       8: aload_1
       9: aload_0
      10: getfield      #35                 // Field userName:Ljava/lang/String;
      13: invokevirtual #59                 // Method java/lang/StringBuffer.append:(Ljava/lang/String;)Ljava/lang/StringBuffer;
      16: pop
      17: aload_1
      18: ldc           #61                 // String :
      20: invokevirtual #59                 // Method java/lang/StringBuffer.append:(Ljava/lang/String;)Ljava/lang/StringBuffer;
      23: pop
      24: aload_1
      25: aload_0
      26: getfield      #40                 // Field password:Ljava/lang/String;
      29: ifnonnull     37
      32: ldc           #63                 // String null
      34: goto          41
      37: aload_0
      38: getfield      #40                 // Field password:Ljava/lang/String;
      41: invokevirtual #59                 // Method java/lang/StringBuffer.append:(Ljava/lang/String;)Ljava/lang/StringBuffer;
      44: pop
      45: aload_1
      46: invokevirtual #65                 // Method java/lang/StringBuffer.toString:()Ljava/lang/String;
      49: areturn

  public int hashCode();
    Code:
       0: bipush        17
       2: istore_1
       3: iload_1
       4: aload_0
       5: getfield      #35                 // Field userName:Ljava/lang/String;
       8: invokestatic  #74                 // Method org/elasticsearch/hadoop/thirdparty/apache/commons/httpclient/util/LangUtils.hashCode:(ILjava/lang/Object;)I
      11: istore_1
      12: iload_1
      13: aload_0
      14: getfield      #40                 // Field password:Ljava/lang/String;
      17: invokestatic  #74                 // Method org/elasticsearch/hadoop/thirdparty/apache/commons/httpclient/util/LangUtils.hashCode:(ILjava/lang/Object;)I
      20: istore_1
      21: iload_1
      22: ireturn

  public boolean equals(java.lang.Object);
    Code:
       0: aload_1
       1: ifnonnull     6
       4: iconst_0
       5: ireturn
       6: aload_0
       7: aload_1
       8: if_acmpne     13
      11: iconst_1
      12: ireturn
      13: aload_0
      14: invokevirtual #81                 // Method java/lang/Object.getClass:()Ljava/lang/Class;
      17: aload_1
      18: invokevirtual #81                 // Method java/lang/Object.getClass:()Ljava/lang/Class;
      21: invokevirtual #83                 // Method java/lang/Object.equals:(Ljava/lang/Object;)Z
      24: ifeq          62
      27: aload_1
      28: checkcast     #2                  // class org/elasticsearch/hadoop/thirdparty/apache/commons/httpclient/UsernamePasswordCredentials
      31: astore_2
      32: aload_0
      33: getfield      #35                 // Field userName:Ljava/lang/String;
      36: aload_2
      37: getfield      #35                 // Field userName:Ljava/lang/String;
      40: invokestatic  #86                 // Method org/elasticsearch/hadoop/thirdparty/apache/commons/httpclient/util/LangUtils.equals:(Ljava/lang/Object;Ljava/lang/Object;)Z
      43: ifeq          62
      46: aload_0
      47: getfield      #40                 // Field password:Ljava/lang/String;
      50: aload_2
      51: getfield      #40                 // Field password:Ljava/lang/String;
      54: invokestatic  #86                 // Method org/elasticsearch/hadoop/thirdparty/apache/commons/httpclient/util/LangUtils.equals:(Ljava/lang/Object;Ljava/lang/Object;)Z
      57: ifeq          62
      60: iconst_1
      61: ireturn
      62: iconst_0
      63: ireturn
}
