Compiled from "Wire.java"
class org.elasticsearch.hadoop.thirdparty.apache.commons.httpclient.Wire {
  public static org.elasticsearch.hadoop.thirdparty.apache.commons.httpclient.Wire HEADER_WIRE;

  public static org.elasticsearch.hadoop.thirdparty.apache.commons.httpclient.Wire CONTENT_WIRE;

  private org.apache.commons.logging.Log log;

  private org.elasticsearch.hadoop.thirdparty.apache.commons.httpclient.Wire(org.apache.commons.logging.Log);
    Code:
       0: aload_0
       1: invokespecial #15                 // Method java/lang/Object."<init>":()V
       4: aload_0
       5: aload_1
       6: putfield      #17                 // Field log:Lorg/apache/commons/logging/Log;
       9: return

  private void wire(java.lang.String, java.io.InputStream) throws java.io.IOException;
    Code:
       0: new           #24                 // class java/lang/StringBuffer
       3: dup
       4: invokespecial #25                 // Method java/lang/StringBuffer."<init>":()V
       7: astore_3
       8: goto          127
      11: iload         4
      13: bipush        13
      15: if_icmpne     28
      18: aload_3
      19: ldc           #27                 // String [\\r]
      21: invokevirtual #31                 // Method java/lang/StringBuffer.append:(Ljava/lang/String;)Ljava/lang/StringBuffer;
      24: pop
      25: goto          127
      28: iload         4
      30: bipush        10
      32: if_icmpne     78
      35: aload_3
      36: ldc           #33                 // String [\\n]\"
      38: invokevirtual #31                 // Method java/lang/StringBuffer.append:(Ljava/lang/String;)Ljava/lang/StringBuffer;
      41: pop
      42: aload_3
      43: iconst_0
      44: ldc           #35                 // String \"
      46: invokevirtual #39                 // Method java/lang/StringBuffer.insert:(ILjava/lang/String;)Ljava/lang/StringBuffer;
      49: pop
      50: aload_3
      51: iconst_0
      52: aload_1
      53: invokevirtual #39                 // Method java/lang/StringBuffer.insert:(ILjava/lang/String;)Ljava/lang/StringBuffer;
      56: pop
      57: aload_0
      58: getfield      #17                 // Field log:Lorg/apache/commons/logging/Log;
      61: aload_3
      62: invokevirtual #43                 // Method java/lang/StringBuffer.toString:()Ljava/lang/String;
      65: invokeinterface #49,  2           // InterfaceMethod org/apache/commons/logging/Log.debug:(Ljava/lang/Object;)V
      70: aload_3
      71: iconst_0
      72: invokevirtual #53                 // Method java/lang/StringBuffer.setLength:(I)V
      75: goto          127
      78: iload         4
      80: bipush        32
      82: if_icmplt     92
      85: iload         4
      87: bipush        127
      89: if_icmple     119
      92: aload_3
      93: ldc           #55                 // String [0x
      95: invokevirtual #31                 // Method java/lang/StringBuffer.append:(Ljava/lang/String;)Ljava/lang/StringBuffer;
      98: pop
      99: aload_3
     100: iload         4
     102: invokestatic  #61                 // Method java/lang/Integer.toHexString:(I)Ljava/lang/String;
     105: invokevirtual #31                 // Method java/lang/StringBuffer.append:(Ljava/lang/String;)Ljava/lang/StringBuffer;
     108: pop
     109: aload_3
     110: ldc           #63                 // String ]
     112: invokevirtual #31                 // Method java/lang/StringBuffer.append:(Ljava/lang/String;)Ljava/lang/StringBuffer;
     115: pop
     116: goto          127
     119: aload_3
     120: iload         4
     122: i2c
     123: invokevirtual #66                 // Method java/lang/StringBuffer.append:(C)Ljava/lang/StringBuffer;
     126: pop
     127: aload_2
     128: invokevirtual #72                 // Method java/io/InputStream.read:()I
     131: dup
     132: istore        4
     134: iconst_m1
     135: if_icmpne     11
     138: aload_3
     139: invokevirtual #75                 // Method java/lang/StringBuffer.length:()I
     142: ifle          180
     145: aload_3
     146: ldc           #35                 // String \"
     148: invokevirtual #31                 // Method java/lang/StringBuffer.append:(Ljava/lang/String;)Ljava/lang/StringBuffer;
     151: pop
     152: aload_3
     153: iconst_0
     154: ldc           #35                 // String \"
     156: invokevirtual #39                 // Method java/lang/StringBuffer.insert:(ILjava/lang/String;)Ljava/lang/StringBuffer;
     159: pop
     160: aload_3
     161: iconst_0
     162: aload_1
     163: invokevirtual #39                 // Method java/lang/StringBuffer.insert:(ILjava/lang/String;)Ljava/lang/StringBuffer;
     166: pop
     167: aload_0
     168: getfield      #17                 // Field log:Lorg/apache/commons/logging/Log;
     171: aload_3
     172: invokevirtual #43                 // Method java/lang/StringBuffer.toString:()Ljava/lang/String;
     175: invokeinterface #49,  2           // InterfaceMethod org/apache/commons/logging/Log.debug:(Ljava/lang/Object;)V
     180: return

  public boolean enabled();
    Code:
       0: aload_0
       1: getfield      #17                 // Field log:Lorg/apache/commons/logging/Log;
       4: invokeinterface #88,  1           // InterfaceMethod org/apache/commons/logging/Log.isDebugEnabled:()Z
       9: ireturn

  public void output(java.io.InputStream) throws java.io.IOException;
    Code:
       0: aload_1
       1: ifnonnull     14
       4: new           #92                 // class java/lang/IllegalArgumentException
       7: dup
       8: ldc           #94                 // String Output may not be null
      10: invokespecial #97                 // Method java/lang/IllegalArgumentException."<init>":(Ljava/lang/String;)V
      13: athrow
      14: aload_0
      15: ldc           #99                 // String >>
      17: aload_1
      18: invokespecial #101                // Method wire:(Ljava/lang/String;Ljava/io/InputStream;)V
      21: return

  public void input(java.io.InputStream) throws java.io.IOException;
    Code:
       0: aload_1
       1: ifnonnull     14
       4: new           #92                 // class java/lang/IllegalArgumentException
       7: dup
       8: ldc           #105                // String Input may not be null
      10: invokespecial #97                 // Method java/lang/IllegalArgumentException."<init>":(Ljava/lang/String;)V
      13: athrow
      14: aload_0
      15: ldc           #107                // String <<
      17: aload_1
      18: invokespecial #101                // Method wire:(Ljava/lang/String;Ljava/io/InputStream;)V
      21: return

  public void output(byte[], int, int) throws java.io.IOException;
    Code:
       0: aload_1
       1: ifnonnull     14
       4: new           #92                 // class java/lang/IllegalArgumentException
       7: dup
       8: ldc           #94                 // String Output may not be null
      10: invokespecial #97                 // Method java/lang/IllegalArgumentException."<init>":(Ljava/lang/String;)V
      13: athrow
      14: aload_0
      15: ldc           #99                 // String >>
      17: new           #110                // class java/io/ByteArrayInputStream
      20: dup
      21: aload_1
      22: iload_2
      23: iload_3
      24: invokespecial #112                // Method java/io/ByteArrayInputStream."<init>":([BII)V
      27: invokespecial #101                // Method wire:(Ljava/lang/String;Ljava/io/InputStream;)V
      30: return

  public void input(byte[], int, int) throws java.io.IOException;
    Code:
       0: aload_1
       1: ifnonnull     14
       4: new           #92                 // class java/lang/IllegalArgumentException
       7: dup
       8: ldc           #105                // String Input may not be null
      10: invokespecial #97                 // Method java/lang/IllegalArgumentException."<init>":(Ljava/lang/String;)V
      13: athrow
      14: aload_0
      15: ldc           #107                // String <<
      17: new           #110                // class java/io/ByteArrayInputStream
      20: dup
      21: aload_1
      22: iload_2
      23: iload_3
      24: invokespecial #112                // Method java/io/ByteArrayInputStream."<init>":([BII)V
      27: invokespecial #101                // Method wire:(Ljava/lang/String;Ljava/io/InputStream;)V
      30: return

  public void output(byte[]) throws java.io.IOException;
    Code:
       0: aload_1
       1: ifnonnull     14
       4: new           #92                 // class java/lang/IllegalArgumentException
       7: dup
       8: ldc           #94                 // String Output may not be null
      10: invokespecial #97                 // Method java/lang/IllegalArgumentException."<init>":(Ljava/lang/String;)V
      13: athrow
      14: aload_0
      15: ldc           #99                 // String >>
      17: new           #110                // class java/io/ByteArrayInputStream
      20: dup
      21: aload_1
      22: invokespecial #119                // Method java/io/ByteArrayInputStream."<init>":([B)V
      25: invokespecial #101                // Method wire:(Ljava/lang/String;Ljava/io/InputStream;)V
      28: return

  public void input(byte[]) throws java.io.IOException;
    Code:
       0: aload_1
       1: ifnonnull     14
       4: new           #92                 // class java/lang/IllegalArgumentException
       7: dup
       8: ldc           #105                // String Input may not be null
      10: invokespecial #97                 // Method java/lang/IllegalArgumentException."<init>":(Ljava/lang/String;)V
      13: athrow
      14: aload_0
      15: ldc           #107                // String <<
      17: new           #110                // class java/io/ByteArrayInputStream
      20: dup
      21: aload_1
      22: invokespecial #119                // Method java/io/ByteArrayInputStream."<init>":([B)V
      25: invokespecial #101                // Method wire:(Ljava/lang/String;Ljava/io/InputStream;)V
      28: return

  public void output(int) throws java.io.IOException;
    Code:
       0: aload_0
       1: iconst_1
       2: newarray       byte
       4: dup
       5: iconst_0
       6: iload_1
       7: i2b
       8: bastore
       9: invokevirtual #121                // Method output:([B)V
      12: return

  public void input(int) throws java.io.IOException;
    Code:
       0: aload_0
       1: iconst_1
       2: newarray       byte
       4: dup
       5: iconst_0
       6: iload_1
       7: i2b
       8: bastore
       9: invokevirtual #123                // Method input:([B)V
      12: return

  public void output(java.lang.String) throws java.io.IOException;
    Code:
       0: aload_1
       1: ifnonnull     14
       4: new           #92                 // class java/lang/IllegalArgumentException
       7: dup
       8: ldc           #94                 // String Output may not be null
      10: invokespecial #97                 // Method java/lang/IllegalArgumentException."<init>":(Ljava/lang/String;)V
      13: athrow
      14: aload_0
      15: aload_1
      16: invokevirtual #129                // Method java/lang/String.getBytes:()[B
      19: invokevirtual #121                // Method output:([B)V
      22: return

  public void input(java.lang.String) throws java.io.IOException;
    Code:
       0: aload_1
       1: ifnonnull     14
       4: new           #92                 // class java/lang/IllegalArgumentException
       7: dup
       8: ldc           #105                // String Input may not be null
      10: invokespecial #97                 // Method java/lang/IllegalArgumentException."<init>":(Ljava/lang/String;)V
      13: athrow
      14: aload_0
      15: aload_1
      16: invokevirtual #129                // Method java/lang/String.getBytes:()[B
      19: invokevirtual #123                // Method input:([B)V
      22: return

  static {};
    Code:
       0: new           #2                  // class org/elasticsearch/hadoop/thirdparty/apache/commons/httpclient/Wire
       3: dup
       4: ldc           #133                // String httpclient.wire.header
       6: invokestatic  #139                // Method org/apache/commons/logging/LogFactory.getLog:(Ljava/lang/String;)Lorg/apache/commons/logging/Log;
       9: invokespecial #141                // Method "<init>":(Lorg/apache/commons/logging/Log;)V
      12: putstatic     #143                // Field HEADER_WIRE:Lorg/elasticsearch/hadoop/thirdparty/apache/commons/httpclient/Wire;
      15: new           #2                  // class org/elasticsearch/hadoop/thirdparty/apache/commons/httpclient/Wire
      18: dup
      19: ldc           #145                // String httpclient.wire.content
      21: invokestatic  #139                // Method org/apache/commons/logging/LogFactory.getLog:(Ljava/lang/String;)Lorg/apache/commons/logging/Log;
      24: invokespecial #141                // Method "<init>":(Lorg/apache/commons/logging/Log;)V
      27: putstatic     #147                // Field CONTENT_WIRE:Lorg/elasticsearch/hadoop/thirdparty/apache/commons/httpclient/Wire;
      30: return
}
