Compiled from "Rename.java"
class org.apache.jena.sparql.engine.Rename$RenameNode implements org.apache.jena.sparql.graph.NodeTransform {
  private final org.apache.jena.graph.Node oldName;

  private final org.apache.jena.graph.Node newName;

  public org.apache.jena.sparql.engine.Rename$RenameNode(org.apache.jena.graph.Node, org.apache.jena.graph.Node);
    Code:
       0: aload_0
       1: invokespecial #1                  // Method java/lang/Object."<init>":()V
       4: aload_0
       5: aload_1
       6: putfield      #2                  // Field oldName:Lorg/apache/jena/graph/Node;
       9: aload_0
      10: aload_2
      11: putfield      #3                  // Field newName:Lorg/apache/jena/graph/Node;
      14: return

  public org.apache.jena.graph.Node apply(org.apache.jena.graph.Node);
    Code:
       0: aload_1
       1: aload_0
       2: getfield      #2                  // Field oldName:Lorg/apache/jena/graph/Node;
       5: invokevirtual #4                  // Method org/apache/jena/graph/Node.equals:(Ljava/lang/Object;)Z
       8: ifeq          16
      11: aload_0
      12: getfield      #3                  // Field newName:Lorg/apache/jena/graph/Node;
      15: areturn
      16: aload_1
      17: areturn

  public java.lang.Object apply(java.lang.Object);
    Code:
       0: aload_0
       1: aload_1
       2: checkcast     #5                  // class org/apache/jena/graph/Node
       5: invokevirtual #6                  // Method apply:(Lorg/apache/jena/graph/Node;)Lorg/apache/jena/graph/Node;
       8: areturn
}
