Compiled from "AsArraySerializerBase.java"
public abstract class org.codehaus.jackson.map.ser.std.AsArraySerializerBase<T> extends org.codehaus.jackson.map.ser.std.ContainerSerializerBase<T> implements org.codehaus.jackson.map.ResolvableSerializer {
  protected final boolean _staticTyping;

  protected final org.codehaus.jackson.type.JavaType _elementType;

  protected final org.codehaus.jackson.map.TypeSerializer _valueTypeSerializer;

  protected org.codehaus.jackson.map.JsonSerializer<java.lang.Object> _elementSerializer;

  protected final org.codehaus.jackson.map.BeanProperty _property;

  protected org.codehaus.jackson.map.ser.impl.PropertySerializerMap _dynamicSerializers;

  protected org.codehaus.jackson.map.ser.std.AsArraySerializerBase(java.lang.Class<?>, org.codehaus.jackson.type.JavaType, boolean, org.codehaus.jackson.map.TypeSerializer, org.codehaus.jackson.map.BeanProperty);
    Code:
       0: aload_0
       1: aload_1
       2: aload_2
       3: iload_3
       4: aload         4
       6: aload         5
       8: aconst_null
       9: invokespecial #1                  // Method "<init>":(Ljava/lang/Class;Lorg/codehaus/jackson/type/JavaType;ZLorg/codehaus/jackson/map/TypeSerializer;Lorg/codehaus/jackson/map/BeanProperty;Lorg/codehaus/jackson/map/JsonSerializer;)V
      12: return

  protected org.codehaus.jackson.map.ser.std.AsArraySerializerBase(java.lang.Class<?>, org.codehaus.jackson.type.JavaType, boolean, org.codehaus.jackson.map.TypeSerializer, org.codehaus.jackson.map.BeanProperty, org.codehaus.jackson.map.JsonSerializer<java.lang.Object>);
    Code:
       0: aload_0
       1: aload_1
       2: iconst_0
       3: invokespecial #2                  // Method org/codehaus/jackson/map/ser/std/ContainerSerializerBase."<init>":(Ljava/lang/Class;Z)V
       6: aload_0
       7: aload_2
       8: putfield      #3                  // Field _elementType:Lorg/codehaus/jackson/type/JavaType;
      11: aload_0
      12: iload_3
      13: ifne          27
      16: aload_2
      17: ifnull        31
      20: aload_2
      21: invokevirtual #4                  // Method org/codehaus/jackson/type/JavaType.isFinal:()Z
      24: ifeq          31
      27: iconst_1
      28: goto          32
      31: iconst_0
      32: putfield      #5                  // Field _staticTyping:Z
      35: aload_0
      36: aload         4
      38: putfield      #6                  // Field _valueTypeSerializer:Lorg/codehaus/jackson/map/TypeSerializer;
      41: aload_0
      42: aload         5
      44: putfield      #7                  // Field _property:Lorg/codehaus/jackson/map/BeanProperty;
      47: aload_0
      48: aload         6
      50: putfield      #8                  // Field _elementSerializer:Lorg/codehaus/jackson/map/JsonSerializer;
      53: aload_0
      54: invokestatic  #9                  // Method org/codehaus/jackson/map/ser/impl/PropertySerializerMap.emptyMap:()Lorg/codehaus/jackson/map/ser/impl/PropertySerializerMap;
      57: putfield      #10                 // Field _dynamicSerializers:Lorg/codehaus/jackson/map/ser/impl/PropertySerializerMap;
      60: return

  public final void serialize(T, org.codehaus.jackson.JsonGenerator, org.codehaus.jackson.map.SerializerProvider) throws java.io.IOException, org.codehaus.jackson.JsonGenerationException;
    Code:
       0: aload_2
       1: invokevirtual #11                 // Method org/codehaus/jackson/JsonGenerator.writeStartArray:()V
       4: aload_0
       5: aload_1
       6: aload_2
       7: aload_3
       8: invokevirtual #12                 // Method serializeContents:(Ljava/lang/Object;Lorg/codehaus/jackson/JsonGenerator;Lorg/codehaus/jackson/map/SerializerProvider;)V
      11: aload_2
      12: invokevirtual #13                 // Method org/codehaus/jackson/JsonGenerator.writeEndArray:()V
      15: return

  public final void serializeWithType(T, org.codehaus.jackson.JsonGenerator, org.codehaus.jackson.map.SerializerProvider, org.codehaus.jackson.map.TypeSerializer) throws java.io.IOException, org.codehaus.jackson.JsonGenerationException;
    Code:
       0: aload         4
       2: aload_1
       3: aload_2
       4: invokevirtual #14                 // Method org/codehaus/jackson/map/TypeSerializer.writeTypePrefixForArray:(Ljava/lang/Object;Lorg/codehaus/jackson/JsonGenerator;)V
       7: aload_0
       8: aload_1
       9: aload_2
      10: aload_3
      11: invokevirtual #12                 // Method serializeContents:(Ljava/lang/Object;Lorg/codehaus/jackson/JsonGenerator;Lorg/codehaus/jackson/map/SerializerProvider;)V
      14: aload         4
      16: aload_1
      17: aload_2
      18: invokevirtual #15                 // Method org/codehaus/jackson/map/TypeSerializer.writeTypeSuffixForArray:(Ljava/lang/Object;Lorg/codehaus/jackson/JsonGenerator;)V
      21: return

  protected abstract void serializeContents(T, org.codehaus.jackson.JsonGenerator, org.codehaus.jackson.map.SerializerProvider) throws java.io.IOException, org.codehaus.jackson.JsonGenerationException;

  public org.codehaus.jackson.JsonNode getSchema(org.codehaus.jackson.map.SerializerProvider, java.lang.reflect.Type) throws org.codehaus.jackson.map.JsonMappingException;
    Code:
       0: aload_0
       1: ldc           #16                 // String array
       3: iconst_1
       4: invokevirtual #17                 // Method createSchemaNode:(Ljava/lang/String;Z)Lorg/codehaus/jackson/node/ObjectNode;
       7: astore_3
       8: aconst_null
       9: astore        4
      11: aload_2
      12: ifnull        69
      15: aload_1
      16: aload_2
      17: invokevirtual #18                 // Method org/codehaus/jackson/map/SerializerProvider.constructType:(Ljava/lang/reflect/Type;)Lorg/codehaus/jackson/type/JavaType;
      20: astore        5
      22: aload         5
      24: invokevirtual #19                 // Method org/codehaus/jackson/type/JavaType.getContentType:()Lorg/codehaus/jackson/type/JavaType;
      27: astore        4
      29: aload         4
      31: ifnonnull     69
      34: aload_2
      35: instanceof    #20                 // class java/lang/reflect/ParameterizedType
      38: ifeq          69
      41: aload_2
      42: checkcast     #20                 // class java/lang/reflect/ParameterizedType
      45: invokeinterface #21,  1           // InterfaceMethod java/lang/reflect/ParameterizedType.getActualTypeArguments:()[Ljava/lang/reflect/Type;
      50: astore        6
      52: aload         6
      54: arraylength
      55: iconst_1
      56: if_icmpne     69
      59: aload_1
      60: aload         6
      62: iconst_0
      63: aaload
      64: invokevirtual #18                 // Method org/codehaus/jackson/map/SerializerProvider.constructType:(Ljava/lang/reflect/Type;)Lorg/codehaus/jackson/type/JavaType;
      67: astore        4
      69: aload         4
      71: ifnonnull     87
      74: aload_0
      75: getfield      #3                  // Field _elementType:Lorg/codehaus/jackson/type/JavaType;
      78: ifnull        87
      81: aload_0
      82: getfield      #3                  // Field _elementType:Lorg/codehaus/jackson/type/JavaType;
      85: astore        4
      87: aload         4
      89: ifnull        159
      92: aconst_null
      93: astore        5
      95: aload         4
      97: invokevirtual #22                 // Method org/codehaus/jackson/type/JavaType.getRawClass:()Ljava/lang/Class;
     100: ldc_w         #23                 // class java/lang/Object
     103: if_acmpeq     140
     106: aload_1
     107: aload         4
     109: aload_0
     110: getfield      #7                  // Field _property:Lorg/codehaus/jackson/map/BeanProperty;
     113: invokevirtual #24                 // Method org/codehaus/jackson/map/SerializerProvider.findValueSerializer:(Lorg/codehaus/jackson/type/JavaType;Lorg/codehaus/jackson/map/BeanProperty;)Lorg/codehaus/jackson/map/JsonSerializer;
     116: astore        6
     118: aload         6
     120: instanceof    #25                 // class org/codehaus/jackson/schema/SchemaAware
     123: ifeq          140
     126: aload         6
     128: checkcast     #25                 // class org/codehaus/jackson/schema/SchemaAware
     131: aload_1
     132: aconst_null
     133: invokeinterface #26,  3           // InterfaceMethod org/codehaus/jackson/schema/SchemaAware.getSchema:(Lorg/codehaus/jackson/map/SerializerProvider;Ljava/lang/reflect/Type;)Lorg/codehaus/jackson/JsonNode;
     138: astore        5
     140: aload         5
     142: ifnonnull     150
     145: invokestatic  #27                 // Method org/codehaus/jackson/schema/JsonSchema.getDefaultSchemaNode:()Lorg/codehaus/jackson/JsonNode;
     148: astore        5
     150: aload_3
     151: ldc           #28                 // String items
     153: aload         5
     155: invokevirtual #29                 // Method org/codehaus/jackson/node/ObjectNode.put:(Ljava/lang/String;Lorg/codehaus/jackson/JsonNode;)Lorg/codehaus/jackson/JsonNode;
     158: pop
     159: aload_3
     160: areturn

  public void resolve(org.codehaus.jackson.map.SerializerProvider) throws org.codehaus.jackson.map.JsonMappingException;
    Code:
       0: aload_0
       1: getfield      #5                  // Field _staticTyping:Z
       4: ifeq          37
       7: aload_0
       8: getfield      #3                  // Field _elementType:Lorg/codehaus/jackson/type/JavaType;
      11: ifnull        37
      14: aload_0
      15: getfield      #8                  // Field _elementSerializer:Lorg/codehaus/jackson/map/JsonSerializer;
      18: ifnonnull     37
      21: aload_0
      22: aload_1
      23: aload_0
      24: getfield      #3                  // Field _elementType:Lorg/codehaus/jackson/type/JavaType;
      27: aload_0
      28: getfield      #7                  // Field _property:Lorg/codehaus/jackson/map/BeanProperty;
      31: invokevirtual #24                 // Method org/codehaus/jackson/map/SerializerProvider.findValueSerializer:(Lorg/codehaus/jackson/type/JavaType;Lorg/codehaus/jackson/map/BeanProperty;)Lorg/codehaus/jackson/map/JsonSerializer;
      34: putfield      #8                  // Field _elementSerializer:Lorg/codehaus/jackson/map/JsonSerializer;
      37: return

  protected final org.codehaus.jackson.map.JsonSerializer<java.lang.Object> _findAndAddDynamic(org.codehaus.jackson.map.ser.impl.PropertySerializerMap, java.lang.Class<?>, org.codehaus.jackson.map.SerializerProvider) throws org.codehaus.jackson.map.JsonMappingException;
    Code:
       0: aload_1
       1: aload_2
       2: aload_3
       3: aload_0
       4: getfield      #7                  // Field _property:Lorg/codehaus/jackson/map/BeanProperty;
       7: invokevirtual #30                 // Method org/codehaus/jackson/map/ser/impl/PropertySerializerMap.findAndAddSerializer:(Ljava/lang/Class;Lorg/codehaus/jackson/map/SerializerProvider;Lorg/codehaus/jackson/map/BeanProperty;)Lorg/codehaus/jackson/map/ser/impl/PropertySerializerMap$SerializerAndMapResult;
      10: astore        4
      12: aload_1
      13: aload         4
      15: getfield      #31                 // Field org/codehaus/jackson/map/ser/impl/PropertySerializerMap$SerializerAndMapResult.map:Lorg/codehaus/jackson/map/ser/impl/PropertySerializerMap;
      18: if_acmpeq     30
      21: aload_0
      22: aload         4
      24: getfield      #31                 // Field org/codehaus/jackson/map/ser/impl/PropertySerializerMap$SerializerAndMapResult.map:Lorg/codehaus/jackson/map/ser/impl/PropertySerializerMap;
      27: putfield      #10                 // Field _dynamicSerializers:Lorg/codehaus/jackson/map/ser/impl/PropertySerializerMap;
      30: aload         4
      32: getfield      #32                 // Field org/codehaus/jackson/map/ser/impl/PropertySerializerMap$SerializerAndMapResult.serializer:Lorg/codehaus/jackson/map/JsonSerializer;
      35: areturn

  protected final org.codehaus.jackson.map.JsonSerializer<java.lang.Object> _findAndAddDynamic(org.codehaus.jackson.map.ser.impl.PropertySerializerMap, org.codehaus.jackson.type.JavaType, org.codehaus.jackson.map.SerializerProvider) throws org.codehaus.jackson.map.JsonMappingException;
    Code:
       0: aload_1
       1: aload_2
       2: aload_3
       3: aload_0
       4: getfield      #7                  // Field _property:Lorg/codehaus/jackson/map/BeanProperty;
       7: invokevirtual #33                 // Method org/codehaus/jackson/map/ser/impl/PropertySerializerMap.findAndAddSerializer:(Lorg/codehaus/jackson/type/JavaType;Lorg/codehaus/jackson/map/SerializerProvider;Lorg/codehaus/jackson/map/BeanProperty;)Lorg/codehaus/jackson/map/ser/impl/PropertySerializerMap$SerializerAndMapResult;
      10: astore        4
      12: aload_1
      13: aload         4
      15: getfield      #31                 // Field org/codehaus/jackson/map/ser/impl/PropertySerializerMap$SerializerAndMapResult.map:Lorg/codehaus/jackson/map/ser/impl/PropertySerializerMap;
      18: if_acmpeq     30
      21: aload_0
      22: aload         4
      24: getfield      #31                 // Field org/codehaus/jackson/map/ser/impl/PropertySerializerMap$SerializerAndMapResult.map:Lorg/codehaus/jackson/map/ser/impl/PropertySerializerMap;
      27: putfield      #10                 // Field _dynamicSerializers:Lorg/codehaus/jackson/map/ser/impl/PropertySerializerMap;
      30: aload         4
      32: getfield      #32                 // Field org/codehaus/jackson/map/ser/impl/PropertySerializerMap$SerializerAndMapResult.serializer:Lorg/codehaus/jackson/map/JsonSerializer;
      35: areturn
}
