Compiled from "CompositeByteBuf.java"
final class io.netty.buffer.CompositeByteBuf$1 implements io.netty.buffer.CompositeByteBuf$ByteWrapper<byte[]> {
  io.netty.buffer.CompositeByteBuf$1();
    Code:
       0: aload_0
       1: invokespecial #1                  // Method java/lang/Object."<init>":()V
       4: return

  public io.netty.buffer.ByteBuf wrap(byte[]);
    Code:
       0: aload_1
       1: invokestatic  #2                  // Method io/netty/buffer/Unpooled.wrappedBuffer:([B)Lio/netty/buffer/ByteBuf;
       4: areturn

  public boolean isEmpty(byte[]);
    Code:
       0: aload_1
       1: arraylength
       2: ifne          9
       5: iconst_1
       6: goto          10
       9: iconst_0
      10: ireturn

  public boolean isEmpty(java.lang.Object);
    Code:
       0: aload_0
       1: aload_1
       2: checkcast     #3                  // class "[B"
       5: invokevirtual #4                  // Method isEmpty:([B)Z
       8: ireturn

  public io.netty.buffer.ByteBuf wrap(java.lang.Object);
    Code:
       0: aload_0
       1: aload_1
       2: checkcast     #3                  // class "[B"
       5: invokevirtual #5                  // Method wrap:([B)Lio/netty/buffer/ByteBuf;
       8: areturn
}
