Compiled from "FixedCompositeByteBuf.java"
final class io.netty.buffer.FixedCompositeByteBuf$Component extends io.netty.buffer.WrappedByteBuf {
  private final int index;

  private final int offset;

  private final int endOffset;

  io.netty.buffer.FixedCompositeByteBuf$Component(int, int, io.netty.buffer.ByteBuf);
    Code:
       0: aload_0
       1: aload_3
       2: invokespecial #4                  // Method io/netty/buffer/WrappedByteBuf."<init>":(Lio/netty/buffer/ByteBuf;)V
       5: aload_0
       6: iload_1
       7: putfield      #1                  // Field index:I
      10: aload_0
      11: iload_2
      12: putfield      #3                  // Field offset:I
      15: aload_0
      16: iload_2
      17: aload_3
      18: invokevirtual #5                  // Method io/netty/buffer/ByteBuf.readableBytes:()I
      21: iadd
      22: putfield      #2                  // Field endOffset:I
      25: return

  static int access$000(io.netty.buffer.FixedCompositeByteBuf$Component);
    Code:
       0: aload_0
       1: getfield      #3                  // Field offset:I
       4: ireturn

  static int access$100(io.netty.buffer.FixedCompositeByteBuf$Component);
    Code:
       0: aload_0
       1: getfield      #2                  // Field endOffset:I
       4: ireturn

  static int access$200(io.netty.buffer.FixedCompositeByteBuf$Component);
    Code:
       0: aload_0
       1: getfield      #1                  // Field index:I
       4: ireturn
}
