Compiled from "POJOWorkflowDefinition.java"
class com.amazonaws.services.simpleworkflow.flow.pojo.POJOWorkflowDefinition$1 extends com.amazonaws.services.simpleworkflow.flow.core.TryCatchFinally {
  final com.amazonaws.services.simpleworkflow.flow.pojo.POJOWorkflowDefinition this$0;

  private final com.amazonaws.services.simpleworkflow.flow.DataConverter val$c;

  private final java.lang.String val$input;

  private final java.util.concurrent.atomic.AtomicReference val$methodResult;

  private final com.amazonaws.services.simpleworkflow.flow.core.Settable val$result;

  com.amazonaws.services.simpleworkflow.flow.pojo.POJOWorkflowDefinition$1(com.amazonaws.services.simpleworkflow.flow.pojo.POJOWorkflowDefinition, com.amazonaws.services.simpleworkflow.flow.DataConverter, java.lang.String, java.util.concurrent.atomic.AtomicReference, com.amazonaws.services.simpleworkflow.flow.core.Settable);
    Code:
       0: aload_0
       1: aload_1
       2: putfield      #18                 // Field this$0:Lcom/amazonaws/services/simpleworkflow/flow/pojo/POJOWorkflowDefinition;
       5: aload_0
       6: aload_2
       7: putfield      #20                 // Field val$c:Lcom/amazonaws/services/simpleworkflow/flow/DataConverter;
      10: aload_0
      11: aload_3
      12: putfield      #22                 // Field val$input:Ljava/lang/String;
      15: aload_0
      16: aload         4
      18: putfield      #24                 // Field val$methodResult:Ljava/util/concurrent/atomic/AtomicReference;
      21: aload_0
      22: aload         5
      24: putfield      #26                 // Field val$result:Lcom/amazonaws/services/simpleworkflow/flow/core/Settable;
      27: aload_0
      28: invokespecial #28                 // Method com/amazonaws/services/simpleworkflow/flow/core/TryCatchFinally."<init>":()V
      31: return

  protected void doTry() throws java.lang.Throwable;
    Code:
       0: aload_0
       1: getfield      #20                 // Field val$c:Lcom/amazonaws/services/simpleworkflow/flow/DataConverter;
       4: aload_0
       5: getfield      #22                 // Field val$input:Ljava/lang/String;
       8: ldc           #40                 // class "[Ljava/lang/Object;"
      10: invokevirtual #42                 // Method com/amazonaws/services/simpleworkflow/flow/DataConverter.fromData:(Ljava/lang/String;Ljava/lang/Class;)Ljava/lang/Object;
      13: checkcast     #40                 // class "[Ljava/lang/Object;"
      16: astore_1
      17: aload_0
      18: getfield      #18                 // Field this$0:Lcom/amazonaws/services/simpleworkflow/flow/pojo/POJOWorkflowDefinition;
      21: invokestatic  #48                 // Method com/amazonaws/services/simpleworkflow/flow/pojo/POJOWorkflowDefinition.access$0:(Lcom/amazonaws/services/simpleworkflow/flow/pojo/POJOWorkflowDefinition;)Lcom/amazonaws/services/simpleworkflow/flow/pojo/MethodConverterPair;
      24: invokevirtual #54                 // Method com/amazonaws/services/simpleworkflow/flow/pojo/MethodConverterPair.getMethod:()Ljava/lang/reflect/Method;
      27: astore_2
      28: aload_0
      29: getfield      #18                 // Field this$0:Lcom/amazonaws/services/simpleworkflow/flow/pojo/POJOWorkflowDefinition;
      32: aload_2
      33: aload_1
      34: invokestatic  #60                 // Method com/amazonaws/services/simpleworkflow/flow/pojo/POJOWorkflowDefinition.access$1:(Lcom/amazonaws/services/simpleworkflow/flow/pojo/POJOWorkflowDefinition;Ljava/lang/reflect/Method;[Ljava/lang/Object;)Ljava/lang/Object;
      37: astore_3
      38: aload_2
      39: invokevirtual #64                 // Method java/lang/reflect/Method.getReturnType:()Ljava/lang/Class;
      42: getstatic     #70                 // Field java/lang/Void.TYPE:Ljava/lang/Class;
      45: invokevirtual #76                 // Method java/lang/Object.equals:(Ljava/lang/Object;)Z
      48: ifne          62
      51: aload_0
      52: getfield      #24                 // Field val$methodResult:Ljava/util/concurrent/atomic/AtomicReference;
      55: aload_3
      56: checkcast     #82                 // class com/amazonaws/services/simpleworkflow/flow/core/Promise
      59: invokevirtual #84                 // Method java/util/concurrent/atomic/AtomicReference.set:(Ljava/lang/Object;)V
      62: return

  protected void doCatch(java.lang.Throwable) throws java.lang.Throwable;
    Code:
       0: aload_1
       1: instanceof    #98                 // class java/util/concurrent/CancellationException
       4: ifeq          25
       7: aload_0
       8: getfield      #18                 // Field this$0:Lcom/amazonaws/services/simpleworkflow/flow/pojo/POJOWorkflowDefinition;
      11: invokestatic  #100                // Method com/amazonaws/services/simpleworkflow/flow/pojo/POJOWorkflowDefinition.access$2:(Lcom/amazonaws/services/simpleworkflow/flow/pojo/POJOWorkflowDefinition;)Lcom/amazonaws/services/simpleworkflow/flow/DecisionContext;
      14: invokevirtual #104                // Method com/amazonaws/services/simpleworkflow/flow/DecisionContext.getWorkflowContext:()Lcom/amazonaws/services/simpleworkflow/flow/WorkflowContext;
      17: invokeinterface #110,  1          // InterfaceMethod com/amazonaws/services/simpleworkflow/flow/WorkflowContext.isCancelRequested:()Z
      22: ifne          37
      25: aload_0
      26: getfield      #18                 // Field this$0:Lcom/amazonaws/services/simpleworkflow/flow/pojo/POJOWorkflowDefinition;
      29: aload_0
      30: getfield      #20                 // Field val$c:Lcom/amazonaws/services/simpleworkflow/flow/DataConverter;
      33: aload_1
      34: invokestatic  #116                // Method com/amazonaws/services/simpleworkflow/flow/pojo/POJOWorkflowDefinition.access$3:(Lcom/amazonaws/services/simpleworkflow/flow/pojo/POJOWorkflowDefinition;Lcom/amazonaws/services/simpleworkflow/flow/DataConverter;Ljava/lang/Throwable;)V
      37: return

  protected void doFinally() throws java.lang.Throwable;
    Code:
       0: aload_0
       1: getfield      #24                 // Field val$methodResult:Ljava/util/concurrent/atomic/AtomicReference;
       4: invokevirtual #123                // Method java/util/concurrent/atomic/AtomicReference.get:()Ljava/lang/Object;
       7: checkcast     #82                 // class com/amazonaws/services/simpleworkflow/flow/core/Promise
      10: astore_1
      11: aload_1
      12: ifnull        22
      15: aload_1
      16: invokevirtual #127                // Method com/amazonaws/services/simpleworkflow/flow/core/Promise.isReady:()Z
      19: ifeq          52
      22: aload_1
      23: ifnonnull     30
      26: aconst_null
      27: goto          34
      30: aload_1
      31: invokevirtual #130                // Method com/amazonaws/services/simpleworkflow/flow/core/Promise.get:()Ljava/lang/Object;
      34: astore_2
      35: aload_0
      36: getfield      #20                 // Field val$c:Lcom/amazonaws/services/simpleworkflow/flow/DataConverter;
      39: aload_2
      40: invokevirtual #131                // Method com/amazonaws/services/simpleworkflow/flow/DataConverter.toData:(Ljava/lang/Object;)Ljava/lang/String;
      43: astore_3
      44: aload_0
      45: getfield      #26                 // Field val$result:Lcom/amazonaws/services/simpleworkflow/flow/core/Settable;
      48: aload_3
      49: invokevirtual #135                // Method com/amazonaws/services/simpleworkflow/flow/core/Settable.set:(Ljava/lang/Object;)V
      52: return
}
