Compiled from "GetLensResponse.java"
final class software.amazon.awssdk.services.wellarchitected.model.GetLensResponse$BuilderImpl extends software.amazon.awssdk.services.wellarchitected.model.WellArchitectedResponse$BuilderImpl implements software.amazon.awssdk.services.wellarchitected.model.GetLensResponse$Builder {
  private software.amazon.awssdk.services.wellarchitected.model.Lens lens;

  private software.amazon.awssdk.services.wellarchitected.model.GetLensResponse$BuilderImpl();
    Code:
       0: aload_0
       1: invokespecial #4                  // Method software/amazon/awssdk/services/wellarchitected/model/WellArchitectedResponse$BuilderImpl."<init>":()V
       4: return

  private software.amazon.awssdk.services.wellarchitected.model.GetLensResponse$BuilderImpl(software.amazon.awssdk.services.wellarchitected.model.GetLensResponse);
    Code:
       0: aload_0
       1: aload_1
       2: invokespecial #5                  // Method software/amazon/awssdk/services/wellarchitected/model/WellArchitectedResponse$BuilderImpl."<init>":(Lsoftware/amazon/awssdk/services/wellarchitected/model/WellArchitectedResponse;)V
       5: aload_0
       6: aload_1
       7: invokestatic  #6                  // Method software/amazon/awssdk/services/wellarchitected/model/GetLensResponse.access$300:(Lsoftware/amazon/awssdk/services/wellarchitected/model/GetLensResponse;)Lsoftware/amazon/awssdk/services/wellarchitected/model/Lens;
      10: invokevirtual #7                  // Method lens:(Lsoftware/amazon/awssdk/services/wellarchitected/model/Lens;)Lsoftware/amazon/awssdk/services/wellarchitected/model/GetLensResponse$Builder;
      13: pop
      14: return

  public final software.amazon.awssdk.services.wellarchitected.model.Lens$Builder getLens();
    Code:
       0: aload_0
       1: getfield      #3                  // Field lens:Lsoftware/amazon/awssdk/services/wellarchitected/model/Lens;
       4: ifnull        17
       7: aload_0
       8: getfield      #3                  // Field lens:Lsoftware/amazon/awssdk/services/wellarchitected/model/Lens;
      11: invokevirtual #8                  // Method software/amazon/awssdk/services/wellarchitected/model/Lens.toBuilder:()Lsoftware/amazon/awssdk/services/wellarchitected/model/Lens$Builder;
      14: goto          18
      17: aconst_null
      18: areturn

  public final void setLens(software.amazon.awssdk.services.wellarchitected.model.Lens$BuilderImpl);
    Code:
       0: aload_0
       1: aload_1
       2: ifnull        12
       5: aload_1
       6: invokevirtual #9                  // Method software/amazon/awssdk/services/wellarchitected/model/Lens$BuilderImpl.build:()Lsoftware/amazon/awssdk/services/wellarchitected/model/Lens;
       9: goto          13
      12: aconst_null
      13: putfield      #3                  // Field lens:Lsoftware/amazon/awssdk/services/wellarchitected/model/Lens;
      16: return

  public final software.amazon.awssdk.services.wellarchitected.model.GetLensResponse$Builder lens(software.amazon.awssdk.services.wellarchitected.model.Lens);
    Code:
       0: aload_0
       1: aload_1
       2: putfield      #3                  // Field lens:Lsoftware/amazon/awssdk/services/wellarchitected/model/Lens;
       5: aload_0
       6: areturn

  public software.amazon.awssdk.services.wellarchitected.model.GetLensResponse build();
    Code:
       0: new           #10                 // class software/amazon/awssdk/services/wellarchitected/model/GetLensResponse
       3: dup
       4: aload_0
       5: aconst_null
       6: invokespecial #11                 // Method software/amazon/awssdk/services/wellarchitected/model/GetLensResponse."<init>":(Lsoftware/amazon/awssdk/services/wellarchitected/model/GetLensResponse$BuilderImpl;Lsoftware/amazon/awssdk/services/wellarchitected/model/GetLensResponse$1;)V
       9: areturn

  public java.util.List<software.amazon.awssdk.core.SdkField<?>> sdkFields();
    Code:
       0: invokestatic  #12                 // Method software/amazon/awssdk/services/wellarchitected/model/GetLensResponse.access$500:()Ljava/util/List;
       3: areturn

  public software.amazon.awssdk.services.wellarchitected.model.WellArchitectedResponse build();
    Code:
       0: aload_0
       1: invokevirtual #13                 // Method build:()Lsoftware/amazon/awssdk/services/wellarchitected/model/GetLensResponse;
       4: areturn

  public software.amazon.awssdk.awscore.AwsResponse build();
    Code:
       0: aload_0
       1: invokevirtual #13                 // Method build:()Lsoftware/amazon/awssdk/services/wellarchitected/model/GetLensResponse;
       4: areturn

  public software.amazon.awssdk.core.SdkResponse build();
    Code:
       0: aload_0
       1: invokevirtual #13                 // Method build:()Lsoftware/amazon/awssdk/services/wellarchitected/model/GetLensResponse;
       4: areturn

  public java.lang.Object build();
    Code:
       0: aload_0
       1: invokevirtual #13                 // Method build:()Lsoftware/amazon/awssdk/services/wellarchitected/model/GetLensResponse;
       4: areturn

  static software.amazon.awssdk.services.wellarchitected.model.Lens access$000(software.amazon.awssdk.services.wellarchitected.model.GetLensResponse$BuilderImpl);
    Code:
       0: aload_0
       1: getfield      #3                  // Field lens:Lsoftware/amazon/awssdk/services/wellarchitected/model/Lens;
       4: areturn

  software.amazon.awssdk.services.wellarchitected.model.GetLensResponse$BuilderImpl(software.amazon.awssdk.services.wellarchitected.model.GetLensResponse, software.amazon.awssdk.services.wellarchitected.model.GetLensResponse$1);
    Code:
       0: aload_0
       1: aload_1
       2: invokespecial #2                  // Method "<init>":(Lsoftware/amazon/awssdk/services/wellarchitected/model/GetLensResponse;)V
       5: return

  software.amazon.awssdk.services.wellarchitected.model.GetLensResponse$BuilderImpl(software.amazon.awssdk.services.wellarchitected.model.GetLensResponse$1);
    Code:
       0: aload_0
       1: invokespecial #1                  // Method "<init>":()V
       4: return
}
