Compiled from "Environment.java"
public class org.jboss.modules.Environment {
  public org.jboss.modules.Environment();
    Code:
       0: aload_0
       1: invokespecial #1                  // Method java/lang/Object."<init>":()V
       4: return

  public static java.nio.file.FileSystem getFileSystem();
    Code:
       0: getstatic     #2                  // Field org/jboss/modules/Environment$Holder.FILE_SYSTEM:Ljava/nio/file/FileSystem;
       3: areturn

  public static org.jboss.modules.ResourceLoader getModuleResourceLoader(java.lang.String, java.lang.String, java.lang.String);
    Code:
       0: getstatic     #3                  // Field org/jboss/modules/Environment$Holder.JAR_FILE:Ljava/util/jar/JarFile;
       3: ifnull        38
       6: new           #4                  // class org/jboss/modules/JarFileResourceLoader
       9: dup
      10: aload_2
      11: getstatic     #3                  // Field org/jboss/modules/Environment$Holder.JAR_FILE:Ljava/util/jar/JarFile;
      14: getstatic     #2                  // Field org/jboss/modules/Environment$Holder.FILE_SYSTEM:Ljava/nio/file/FileSystem;
      17: aload_0
      18: iconst_1
      19: anewarray     #5                  // class java/lang/String
      22: dup
      23: iconst_0
      24: aload_1
      25: aastore
      26: invokevirtual #6                  // Method java/nio/file/FileSystem.getPath:(Ljava/lang/String;[Ljava/lang/String;)Ljava/nio/file/Path;
      29: invokeinterface #7,  1            // InterfaceMethod java/nio/file/Path.toString:()Ljava/lang/String;
      34: invokespecial #8                  // Method org/jboss/modules/JarFileResourceLoader."<init>":(Ljava/lang/String;Ljava/util/jar/JarFile;Ljava/lang/String;)V
      37: areturn
      38: aload_1
      39: new           #9                  // class java/io/File
      42: dup
      43: aload_0
      44: invokespecial #10                 // Method java/io/File."<init>":(Ljava/lang/String;)V
      47: invokestatic  #11                 // Method org/jboss/modules/ResourceLoaders.createFileResourceLoader:(Ljava/lang/String;Ljava/io/File;)Lorg/jboss/modules/ResourceLoader;
      50: areturn
}
