Compiled from "ResourceLoaderSpec.java"
public final class org.jboss.modules.ResourceLoaderSpec {
  private final org.jboss.modules.ResourceLoader resourceLoader;

  private final org.jboss.modules.filter.PathFilter pathFilter;

  org.jboss.modules.ResourceLoaderSpec(org.jboss.modules.ResourceLoader, org.jboss.modules.filter.PathFilter);
    Code:
       0: aload_0
       1: invokespecial #1                  // Method java/lang/Object."<init>":()V
       4: aload_0
       5: aload_1
       6: putfield      #2                  // Field resourceLoader:Lorg/jboss/modules/ResourceLoader;
       9: aload_0
      10: aload_2
      11: putfield      #3                  // Field pathFilter:Lorg/jboss/modules/filter/PathFilter;
      14: return

  public static org.jboss.modules.ResourceLoaderSpec createResourceLoaderSpec(org.jboss.modules.ResourceLoader, org.jboss.modules.filter.PathFilter);
    Code:
       0: new           #4                  // class org/jboss/modules/ResourceLoaderSpec
       3: dup
       4: aload_0
       5: aload_1
       6: invokespecial #5                  // Method "<init>":(Lorg/jboss/modules/ResourceLoader;Lorg/jboss/modules/filter/PathFilter;)V
       9: areturn

  public static org.jboss.modules.ResourceLoaderSpec createResourceLoaderSpec(org.jboss.modules.ResourceLoader);
    Code:
       0: new           #4                  // class org/jboss/modules/ResourceLoaderSpec
       3: dup
       4: aload_0
       5: invokestatic  #6                  // Method org/jboss/modules/filter/PathFilters.acceptAll:()Lorg/jboss/modules/filter/PathFilter;
       8: invokespecial #5                  // Method "<init>":(Lorg/jboss/modules/ResourceLoader;Lorg/jboss/modules/filter/PathFilter;)V
      11: areturn

  org.jboss.modules.ResourceLoader getResourceLoader();
    Code:
       0: aload_0
       1: getfield      #2                  // Field resourceLoader:Lorg/jboss/modules/ResourceLoader;
       4: areturn

  org.jboss.modules.filter.PathFilter getPathFilter();
    Code:
       0: aload_0
       1: getfield      #3                  // Field pathFilter:Lorg/jboss/modules/filter/PathFilter;
       4: areturn
}
