Compiled from "JettyEmbeddedServletContainerFactory.java"
class org.springframework.boot.context.embedded.jetty.JettyEmbeddedServletContainerFactory$1 extends org.eclipse.jetty.webapp.AbstractConfiguration {
  final org.springframework.boot.context.embedded.jetty.JettyEmbeddedServletContainerFactory this$0;

  org.springframework.boot.context.embedded.jetty.JettyEmbeddedServletContainerFactory$1(org.springframework.boot.context.embedded.jetty.JettyEmbeddedServletContainerFactory);
    Code:
       0: aload_0
       1: aload_1
       2: putfield      #1                  // Field this$0:Lorg/springframework/boot/context/embedded/jetty/JettyEmbeddedServletContainerFactory;
       5: aload_0
       6: invokespecial #2                  // Method org/eclipse/jetty/webapp/AbstractConfiguration."<init>":()V
       9: return

  public void configure(org.eclipse.jetty.webapp.WebAppContext) throws java.lang.Exception;
    Code:
       0: aload_1
       1: invokevirtual #3                  // Method org/eclipse/jetty/webapp/WebAppContext.getErrorHandler:()Lorg/eclipse/jetty/server/handler/ErrorHandler;
       4: astore_2
       5: aload_1
       6: new           #4                  // class org/springframework/boot/context/embedded/jetty/JettyEmbeddedErrorHandler
       9: dup
      10: aload_2
      11: invokespecial #5                  // Method org/springframework/boot/context/embedded/jetty/JettyEmbeddedErrorHandler."<init>":(Lorg/eclipse/jetty/server/handler/ErrorHandler;)V
      14: invokevirtual #6                  // Method org/eclipse/jetty/webapp/WebAppContext.setErrorHandler:(Lorg/eclipse/jetty/server/handler/ErrorHandler;)V
      17: aload_0
      18: getfield      #1                  // Field this$0:Lorg/springframework/boot/context/embedded/jetty/JettyEmbeddedServletContainerFactory;
      21: aload_2
      22: aload_0
      23: getfield      #1                  // Field this$0:Lorg/springframework/boot/context/embedded/jetty/JettyEmbeddedServletContainerFactory;
      26: invokevirtual #7                  // Method org/springframework/boot/context/embedded/jetty/JettyEmbeddedServletContainerFactory.getErrorPages:()Ljava/util/Set;
      29: invokestatic  #8                  // Method org/springframework/boot/context/embedded/jetty/JettyEmbeddedServletContainerFactory.access$1000:(Lorg/springframework/boot/context/embedded/jetty/JettyEmbeddedServletContainerFactory;Lorg/eclipse/jetty/server/handler/ErrorHandler;Ljava/util/Collection;)V
      32: return
}
