Compiled from "AnalysisTempFolderProvider.java"
public class org.sonarsource.sonarlint.core.analysis.container.analysis.AnalysisTempFolderProvider extends org.sonarsource.sonarlint.shaded.org.picocontainer.injectors.ProviderAdapter {
  private final org.sonarsource.sonarlint.core.analysis.container.analysis.AnalysisTempFolderProvider$NoTempFilesDuringAnalysis instance;

  public org.sonarsource.sonarlint.core.analysis.container.analysis.AnalysisTempFolderProvider();
    Code:
       0: aload_0
       1: invokespecial #14                 // Method org/sonarsource/sonarlint/shaded/org/picocontainer/injectors/ProviderAdapter."<init>":()V
       4: aload_0
       5: new           #7                  // class org/sonarsource/sonarlint/core/analysis/container/analysis/AnalysisTempFolderProvider$NoTempFilesDuringAnalysis
       8: dup
       9: invokespecial #15                 // Method org/sonarsource/sonarlint/core/analysis/container/analysis/AnalysisTempFolderProvider$NoTempFilesDuringAnalysis."<init>":()V
      12: putfield      #17                 // Field instance:Lorg/sonarsource/sonarlint/core/analysis/container/analysis/AnalysisTempFolderProvider$NoTempFilesDuringAnalysis;
      15: return

  public org.sonar.api.utils.TempFolder provide();
    Code:
       0: aload_0
       1: getfield      #17                 // Field instance:Lorg/sonarsource/sonarlint/core/analysis/container/analysis/AnalysisTempFolderProvider$NoTempFilesDuringAnalysis;
       4: areturn
}
