Compiled from "IssueListenerHolder.java"
public class org.sonarsource.sonarlint.core.analysis.container.analysis.IssueListenerHolder {
  private final java.util.function.Consumer<org.sonarsource.sonarlint.core.analysis.api.Issue> wrapped;

  public org.sonarsource.sonarlint.core.analysis.container.analysis.IssueListenerHolder(java.util.function.Consumer<org.sonarsource.sonarlint.core.analysis.api.Issue>);
    Code:
       0: aload_0
       1: invokespecial #14                 // Method java/lang/Object."<init>":()V
       4: aload_0
       5: aload_1
       6: putfield      #16                 // Field wrapped:Ljava/util/function/Consumer;
       9: return

  public void handle(org.sonarsource.sonarlint.core.analysis.api.Issue);
    Code:
       0: aload_0
       1: getfield      #16                 // Field wrapped:Ljava/util/function/Consumer;
       4: aload_1
       5: invokeinterface #27,  2           // InterfaceMethod java/util/function/Consumer.accept:(Ljava/lang/Object;)V
      10: return
}
