Compiled from "JReleaserModelPrinter.java"
public class org.jreleaser.cli.internal.JReleaserModelPrinter extends org.jreleaser.model.internal.JReleaserModelPrinter {
  public org.jreleaser.cli.internal.JReleaserModelPrinter(java.io.PrintWriter);
    Code:
       0: aload_0
       1: aload_1
       2: invokespecial #1                  // Method org/jreleaser/model/internal/JReleaserModelPrinter."<init>":(Ljava/io/PrintWriter;)V
       5: return

  protected java.lang.String color(java.lang.String, java.lang.String);
    Code:
       0: getstatic     #2                  // Field picocli/CommandLine$Help$Ansi.AUTO:Lpicocli/CommandLine$Help$Ansi;
       3: new           #3                  // class java/lang/StringBuilder
       6: dup
       7: invokespecial #4                  // Method java/lang/StringBuilder."<init>":()V
      10: ldc           #5                  // String @|
      12: invokevirtual #6                  // Method java/lang/StringBuilder.append:(Ljava/lang/String;)Ljava/lang/StringBuilder;
      15: aload_1
      16: invokevirtual #6                  // Method java/lang/StringBuilder.append:(Ljava/lang/String;)Ljava/lang/StringBuilder;
      19: ldc           #7                  // String
      21: invokevirtual #6                  // Method java/lang/StringBuilder.append:(Ljava/lang/String;)Ljava/lang/StringBuilder;
      24: aload_2
      25: invokevirtual #6                  // Method java/lang/StringBuilder.append:(Ljava/lang/String;)Ljava/lang/StringBuilder;
      28: ldc           #8                  // String |@
      30: invokevirtual #6                  // Method java/lang/StringBuilder.append:(Ljava/lang/String;)Ljava/lang/StringBuilder;
      33: invokevirtual #9                  // Method java/lang/StringBuilder.toString:()Ljava/lang/String;
      36: invokevirtual #10                 // Method picocli/CommandLine$Help$Ansi.string:(Ljava/lang/String;)Ljava/lang/String;
      39: areturn
}
