Compiled from "PartTree.java"
public class org.springframework.data.repository.query.parser.PartTree$OrPart implements java.lang.Iterable<org.springframework.data.repository.query.parser.Part> {
  private final java.util.List<org.springframework.data.repository.query.parser.Part> children;

  org.springframework.data.repository.query.parser.PartTree$OrPart(java.lang.String, java.lang.Class<?>, boolean);
    Code:
       0: aload_0
       1: invokespecial #1                  // Method java/lang/Object."<init>":()V
       4: aload_0
       5: new           #2                  // class java/util/ArrayList
       8: dup
       9: invokespecial #3                  // Method java/util/ArrayList."<init>":()V
      12: putfield      #4                  // Field children:Ljava/util/List;
      15: aload_1
      16: ldc           #5                  // String And
      18: invokestatic  #6                  // Method org/springframework/data/repository/query/parser/PartTree.access$100:(Ljava/lang/String;Ljava/lang/String;)[Ljava/lang/String;
      21: astore        4
      23: aload         4
      25: astore        5
      27: aload         5
      29: arraylength
      30: istore        6
      32: iconst_0
      33: istore        7
      35: iload         7
      37: iload         6
      39: if_icmpge     84
      42: aload         5
      44: iload         7
      46: aaload
      47: astore        8
      49: aload         8
      51: invokestatic  #7                  // Method org/springframework/util/StringUtils.hasText:(Ljava/lang/String;)Z
      54: ifeq          78
      57: aload_0
      58: getfield      #4                  // Field children:Ljava/util/List;
      61: new           #8                  // class org/springframework/data/repository/query/parser/Part
      64: dup
      65: aload         8
      67: aload_2
      68: iload_3
      69: invokespecial #9                  // Method org/springframework/data/repository/query/parser/Part."<init>":(Ljava/lang/String;Ljava/lang/Class;Z)V
      72: invokeinterface #10,  2           // InterfaceMethod java/util/List.add:(Ljava/lang/Object;)Z
      77: pop
      78: iinc          7, 1
      81: goto          35
      84: return

  public java.util.Iterator<org.springframework.data.repository.query.parser.Part> iterator();
    Code:
       0: aload_0
       1: getfield      #4                  // Field children:Ljava/util/List;
       4: invokeinterface #11,  1           // InterfaceMethod java/util/List.iterator:()Ljava/util/Iterator;
       9: areturn

  public java.lang.String toString();
    Code:
       0: aload_0
       1: getfield      #4                  // Field children:Ljava/util/List;
       4: ldc           #12                 // String  and
       6: invokestatic  #13                 // Method org/springframework/util/StringUtils.collectionToDelimitedString:(Ljava/util/Collection;Ljava/lang/String;)Ljava/lang/String;
       9: areturn
}
