Compiled from "ReflectiveAspectJAdvisorFactory.java"
class org.springframework.aop.aspectj.annotation.ReflectiveAspectJAdvisorFactory$SyntheticInstantiationAdvisor$1 implements org.springframework.aop.MethodBeforeAdvice {
  final org.springframework.aop.aspectj.annotation.MetadataAwareAspectInstanceFactory val$aif;

  org.springframework.aop.aspectj.annotation.ReflectiveAspectJAdvisorFactory$SyntheticInstantiationAdvisor$1(org.springframework.aop.aspectj.annotation.MetadataAwareAspectInstanceFactory);
    Code:
       0: aload_0
       1: aload_1
       2: putfield      #1                  // Field val$aif:Lorg/springframework/aop/aspectj/annotation/MetadataAwareAspectInstanceFactory;
       5: aload_0
       6: invokespecial #2                  // Method java/lang/Object."<init>":()V
       9: return

  public void before(java.lang.reflect.Method, java.lang.Object[], java.lang.Object);
    Code:
       0: aload_0
       1: getfield      #1                  // Field val$aif:Lorg/springframework/aop/aspectj/annotation/MetadataAwareAspectInstanceFactory;
       4: invokeinterface #3,  1            // InterfaceMethod org/springframework/aop/aspectj/annotation/MetadataAwareAspectInstanceFactory.getAspectInstance:()Ljava/lang/Object;
       9: pop
      10: return
}
