Compiled from "AbstractInDatabindingInterceptor.java"
public abstract class org.apache.cxf.interceptor.AbstractInDatabindingInterceptor extends org.apache.cxf.phase.AbstractPhaseInterceptor<org.apache.cxf.message.Message> {
  public static final java.lang.String NO_VALIDATE_PARTS;

  private static final java.util.ResourceBundle BUNDLE;

  public org.apache.cxf.interceptor.AbstractInDatabindingInterceptor(java.lang.String);
    Code:
       0: aload_0
       1: aload_1
       2: invokespecial #1                  // Method org/apache/cxf/phase/AbstractPhaseInterceptor."<init>":(Ljava/lang/String;)V
       5: return

  public org.apache.cxf.interceptor.AbstractInDatabindingInterceptor(java.lang.String, java.lang.String);
    Code:
       0: aload_0
       1: aload_1
       2: aload_2
       3: invokespecial #2                  // Method org/apache/cxf/phase/AbstractPhaseInterceptor."<init>":(Ljava/lang/String;Ljava/lang/String;)V
       6: return

  protected boolean supportsDataReader(org.apache.cxf.message.Message, java.lang.Class<?>);
    Code:
       0: aload_1
       1: invokeinterface #3,  1            // InterfaceMethod org/apache/cxf/message/Message.getExchange:()Lorg/apache/cxf/message/Exchange;
       6: invokestatic  #4                  // Method org/apache/cxf/service/model/ServiceModelUtil.getService:(Lorg/apache/cxf/message/Exchange;)Lorg/apache/cxf/service/Service;
       9: astore_3
      10: aload_3
      11: invokeinterface #5,  1            // InterfaceMethod org/apache/cxf/service/Service.getDataBinding:()Lorg/apache/cxf/databinding/DataBinding;
      16: invokeinterface #6,  1            // InterfaceMethod org/apache/cxf/databinding/DataBinding.getSupportedReaderFormats:()[Ljava/lang/Class;
      21: astore        4
      23: aload         4
      25: astore        5
      27: aload         5
      29: arraylength
      30: istore        6
      32: iconst_0
      33: istore        7
      35: iload         7
      37: iload         6
      39: if_icmpge     66
      42: aload         5
      44: iload         7
      46: aaload
      47: astore        8
      49: aload         8
      51: aload_2
      52: invokevirtual #7                  // Method java/lang/Object.equals:(Ljava/lang/Object;)Z
      55: ifeq          60
      58: iconst_1
      59: ireturn
      60: iinc          7, 1
      63: goto          35
      66: iconst_0
      67: ireturn

  protected <T> org.apache.cxf.databinding.DataReader<T> getDataReader(org.apache.cxf.message.Message, java.lang.Class<T>);
    Code:
       0: aload_1
       1: invokeinterface #3,  1            // InterfaceMethod org/apache/cxf/message/Message.getExchange:()Lorg/apache/cxf/message/Exchange;
       6: invokestatic  #4                  // Method org/apache/cxf/service/model/ServiceModelUtil.getService:(Lorg/apache/cxf/message/Exchange;)Lorg/apache/cxf/service/Service;
       9: astore_3
      10: aload_3
      11: invokeinterface #5,  1            // InterfaceMethod org/apache/cxf/service/Service.getDataBinding:()Lorg/apache/cxf/databinding/DataBinding;
      16: aload_2
      17: invokeinterface #8,  2            // InterfaceMethod org/apache/cxf/databinding/DataBinding.createReader:(Ljava/lang/Class;)Lorg/apache/cxf/databinding/DataReader;
      22: astore        4
      24: aload         4
      26: ifnonnull     62
      29: new           #9                  // class org/apache/cxf/interceptor/Fault
      32: dup
      33: new           #10                 // class org/apache/cxf/common/i18n/Message
      36: dup
      37: ldc           #11                 // String NO_DATAREADER
      39: getstatic     #12                 // Field BUNDLE:Ljava/util/ResourceBundle;
      42: iconst_1
      43: anewarray     #13                 // class java/lang/Object
      46: dup
      47: iconst_0
      48: aload_3
      49: invokeinterface #14,  1           // InterfaceMethod org/apache/cxf/service/Service.getName:()Ljavax/xml/namespace/QName;
      54: aastore
      55: invokespecial #15                 // Method org/apache/cxf/common/i18n/Message."<init>":(Ljava/lang/String;Ljava/util/ResourceBundle;[Ljava/lang/Object;)V
      58: invokespecial #16                 // Method org/apache/cxf/interceptor/Fault."<init>":(Lorg/apache/cxf/common/i18n/Message;)V
      61: athrow
      62: aload         4
      64: aload_1
      65: invokeinterface #17,  1           // InterfaceMethod org/apache/cxf/message/Message.getAttachments:()Ljava/util/Collection;
      70: invokeinterface #18,  2           // InterfaceMethod org/apache/cxf/databinding/DataReader.setAttachments:(Ljava/util/Collection;)V
      75: aload         4
      77: getstatic     #19                 // Field org/apache/cxf/databinding/DataReader.ENDPOINT:Ljava/lang/String;
      80: aload_1
      81: invokeinterface #3,  1            // InterfaceMethod org/apache/cxf/message/Message.getExchange:()Lorg/apache/cxf/message/Exchange;
      86: invokeinterface #20,  1           // InterfaceMethod org/apache/cxf/message/Exchange.getEndpoint:()Lorg/apache/cxf/endpoint/Endpoint;
      91: invokeinterface #21,  3           // InterfaceMethod org/apache/cxf/databinding/DataReader.setProperty:(Ljava/lang/String;Ljava/lang/Object;)V
      96: aload         4
      98: ldc_w         #22                 // class org/apache/cxf/message/Message
     101: invokevirtual #23                 // Method java/lang/Class.getName:()Ljava/lang/String;
     104: aload_1
     105: invokeinterface #21,  3           // InterfaceMethod org/apache/cxf/databinding/DataReader.setProperty:(Ljava/lang/String;Ljava/lang/Object;)V
     110: aload_0
     111: aload_3
     112: aload_1
     113: aload         4
     115: invokevirtual #24                 // Method setDataReaderValidation:(Lorg/apache/cxf/service/Service;Lorg/apache/cxf/message/Message;Lorg/apache/cxf/databinding/DataReader;)V
     118: aload         4
     120: areturn

  protected org.apache.cxf.databinding.DataReader<javax.xml.stream.XMLStreamReader> getDataReader(org.apache.cxf.message.Message);
    Code:
       0: aload_0
       1: aload_1
       2: ldc_w         #25                 // class javax/xml/stream/XMLStreamReader
       5: invokevirtual #26                 // Method getDataReader:(Lorg/apache/cxf/message/Message;Ljava/lang/Class;)Lorg/apache/cxf/databinding/DataReader;
       8: areturn

  protected org.apache.cxf.databinding.DataReader<org.w3c.dom.Node> getNodeDataReader(org.apache.cxf.message.Message);
    Code:
       0: aload_0
       1: aload_1
       2: ldc_w         #27                 // class org/w3c/dom/Node
       5: invokevirtual #26                 // Method getDataReader:(Lorg/apache/cxf/message/Message;Ljava/lang/Class;)Lorg/apache/cxf/databinding/DataReader;
       8: areturn

  protected boolean shouldValidate(org.apache.cxf.message.Message);
    Code:
       0: getstatic     #28                 // Field org/apache/cxf/annotations/SchemaValidation$SchemaValidationType.IN:Lorg/apache/cxf/annotations/SchemaValidation$SchemaValidationType;
       3: aload_1
       4: invokestatic  #29                 // Method org/apache/cxf/helpers/ServiceUtils.isSchemaValidationEnabled:(Lorg/apache/cxf/annotations/SchemaValidation$SchemaValidationType;Lorg/apache/cxf/message/Message;)Z
       7: ireturn

  protected void setDataReaderValidation(org.apache.cxf.service.Service, org.apache.cxf.message.Message, org.apache.cxf.databinding.DataReader<?>);
    Code:
       0: aload_0
       1: aload_2
       2: invokevirtual #30                 // Method shouldValidate:(Lorg/apache/cxf/message/Message;)Z
       5: ifeq          50
       8: aload_1
       9: invokeinterface #31,  1           // InterfaceMethod org/apache/cxf/service/Service.getServiceInfos:()Ljava/util/List;
      14: iconst_0
      15: invokeinterface #32,  2           // InterfaceMethod java/util/List.get:(I)Ljava/lang/Object;
      20: checkcast     #33                 // class org/apache/cxf/service/model/ServiceInfo
      23: aload_2
      24: invokeinterface #3,  1            // InterfaceMethod org/apache/cxf/message/Message.getExchange:()Lorg/apache/cxf/message/Exchange;
      29: invokeinterface #34,  1           // InterfaceMethod org/apache/cxf/message/Exchange.getBus:()Lorg/apache/cxf/Bus;
      34: invokestatic  #35                 // Method org/apache/cxf/ws/addressing/EndpointReferenceUtils.getSchema:(Lorg/apache/cxf/service/model/ServiceInfo;Lorg/apache/cxf/Bus;)Ljavax/xml/validation/Schema;
      37: astore        4
      39: aload_3
      40: aload         4
      42: invokeinterface #36,  2           // InterfaceMethod org/apache/cxf/databinding/DataReader.setSchema:(Ljavax/xml/validation/Schema;)V
      47: goto          57
      50: aload_3
      51: aconst_null
      52: invokeinterface #36,  2           // InterfaceMethod org/apache/cxf/databinding/DataReader.setSchema:(Ljavax/xml/validation/Schema;)V
      57: return

  protected void setOperationSchemaValidation(org.apache.cxf.message.Message);
    Code:
       0: aload_1
       1: invokestatic  #37                 // Method org/apache/cxf/helpers/ServiceUtils.getSchemaValidationType:(Lorg/apache/cxf/message/Message;)Lorg/apache/cxf/annotations/SchemaValidation$SchemaValidationType;
       4: astore_2
       5: aload_1
       6: ldc           #38                 // String schema-validation-enabled
       8: aload_2
       9: invokeinterface #39,  3           // InterfaceMethod org/apache/cxf/message/Message.put:(Ljava/lang/Object;Ljava/lang/Object;)Ljava/lang/Object;
      14: pop
      15: return

  protected org.apache.cxf.staxutils.DepthXMLStreamReader getXMLStreamReader(org.apache.cxf.message.Message);
    Code:
       0: aload_1
       1: ldc_w         #25                 // class javax/xml/stream/XMLStreamReader
       4: invokeinterface #40,  2           // InterfaceMethod org/apache/cxf/message/Message.getContent:(Ljava/lang/Class;)Ljava/lang/Object;
       9: checkcast     #25                 // class javax/xml/stream/XMLStreamReader
      12: astore_2
      13: aload_2
      14: ifnonnull     19
      17: aconst_null
      18: areturn
      19: aload_2
      20: instanceof    #41                 // class org/apache/cxf/staxutils/DepthXMLStreamReader
      23: ifeq          31
      26: aload_2
      27: checkcast     #41                 // class org/apache/cxf/staxutils/DepthXMLStreamReader
      30: areturn
      31: new           #41                 // class org/apache/cxf/staxutils/DepthXMLStreamReader
      34: dup
      35: aload_2
      36: invokespecial #42                 // Method org/apache/cxf/staxutils/DepthXMLStreamReader."<init>":(Ljavax/xml/stream/XMLStreamReader;)V
      39: astore_3
      40: aload_1
      41: ldc_w         #25                 // class javax/xml/stream/XMLStreamReader
      44: aload_3
      45: invokeinterface #43,  3           // InterfaceMethod org/apache/cxf/message/Message.setContent:(Ljava/lang/Class;Ljava/lang/Object;)V
      50: aload_3
      51: areturn

  protected org.apache.cxf.service.model.MessagePartInfo findMessagePart(org.apache.cxf.message.Exchange, java.util.Collection<org.apache.cxf.service.model.OperationInfo>, javax.xml.namespace.QName, boolean, int, org.apache.cxf.message.Message);
    Code:
       0: aload_1
       1: invokeinterface #20,  1           // InterfaceMethod org/apache/cxf/message/Exchange.getEndpoint:()Lorg/apache/cxf/endpoint/Endpoint;
       6: astore        7
       8: aconst_null
       9: astore        8
      11: aconst_null
      12: astore        9
      14: aconst_null
      15: astore        10
      17: aconst_null
      18: astore        11
      20: aconst_null
      21: astore        12
      23: aload_2
      24: invokeinterface #44,  1           // InterfaceMethod java/util/Collection.iterator:()Ljava/util/Iterator;
      29: astore        13
      31: aload         13
      33: invokeinterface #45,  1           // InterfaceMethod java/util/Iterator.hasNext:()Z
      38: ifeq          287
      41: aload         13
      43: invokeinterface #46,  1           // InterfaceMethod java/util/Iterator.next:()Ljava/lang/Object;
      48: checkcast     #47                 // class org/apache/cxf/service/model/OperationInfo
      51: astore        14
      53: aload         7
      55: invokeinterface #48,  1           // InterfaceMethod org/apache/cxf/endpoint/Endpoint.getEndpointInfo:()Lorg/apache/cxf/service/model/EndpointInfo;
      60: invokevirtual #49                 // Method org/apache/cxf/service/model/EndpointInfo.getBinding:()Lorg/apache/cxf/service/model/BindingInfo;
      63: aload         14
      65: invokevirtual #50                 // Method org/apache/cxf/service/model/BindingInfo.getOperation:(Lorg/apache/cxf/service/model/OperationInfo;)Lorg/apache/cxf/service/model/BindingOperationInfo;
      68: astore        12
      70: aload         12
      72: ifnonnull     78
      75: goto          31
      78: iload         4
      80: ifeq          93
      83: aload         12
      85: invokevirtual #51                 // Method org/apache/cxf/service/model/BindingOperationInfo.getOutput:()Lorg/apache/cxf/service/model/BindingMessageInfo;
      88: astore        11
      90: goto          100
      93: aload         12
      95: invokevirtual #52                 // Method org/apache/cxf/service/model/BindingOperationInfo.getInput:()Lorg/apache/cxf/service/model/BindingMessageInfo;
      98: astore        11
     100: aload         11
     102: ifnonnull     115
     105: aload         13
     107: invokeinterface #53,  1           // InterfaceMethod java/util/Iterator.remove:()V
     112: goto          31
     115: aload         11
     117: invokevirtual #54                 // Method org/apache/cxf/service/model/BindingMessageInfo.getMessageParts:()Ljava/util/List;
     120: astore        15
     122: aload         15
     124: invokeinterface #55,  1           // InterfaceMethod java/util/Collection.size:()I
     129: ifeq          144
     132: aload         15
     134: invokeinterface #55,  1           // InterfaceMethod java/util/Collection.size:()I
     139: iload         5
     141: if_icmpgt     154
     144: aload         13
     146: invokeinterface #53,  1           // InterfaceMethod java/util/Iterator.remove:()V
     151: goto          31
     154: aload         11
     156: invokevirtual #54                 // Method org/apache/cxf/service/model/BindingMessageInfo.getMessageParts:()Ljava/util/List;
     159: iload         5
     161: invokeinterface #32,  2           // InterfaceMethod java/util/List.get:(I)Ljava/lang/Object;
     166: checkcast     #56                 // class org/apache/cxf/service/model/MessagePartInfo
     169: astore        16
     171: aload_3
     172: invokevirtual #57                 // Method javax/xml/namespace/QName.getNamespaceURI:()Ljava/lang/String;
     175: ifnull        188
     178: aload_3
     179: invokevirtual #57                 // Method javax/xml/namespace/QName.getNamespaceURI:()Ljava/lang/String;
     182: invokevirtual #58                 // Method java/lang/String.length:()I
     185: ifne          211
     188: new           #59                 // class javax/xml/namespace/QName
     191: dup
     192: aload         16
     194: invokevirtual #60                 // Method org/apache/cxf/service/model/MessagePartInfo.getMessageInfo:()Lorg/apache/cxf/service/model/AbstractMessageContainer;
     197: invokevirtual #61                 // Method org/apache/cxf/service/model/AbstractMessageContainer.getName:()Ljavax/xml/namespace/QName;
     200: invokevirtual #57                 // Method javax/xml/namespace/QName.getNamespaceURI:()Ljava/lang/String;
     203: aload_3
     204: invokevirtual #62                 // Method javax/xml/namespace/QName.getLocalPart:()Ljava/lang/String;
     207: invokespecial #63                 // Method javax/xml/namespace/QName."<init>":(Ljava/lang/String;Ljava/lang/String;)V
     210: astore_3
     211: aload_3
     212: aload         16
     214: invokevirtual #64                 // Method org/apache/cxf/service/model/MessagePartInfo.getConcreteName:()Ljavax/xml/namespace/QName;
     217: invokevirtual #65                 // Method javax/xml/namespace/QName.equals:(Ljava/lang/Object;)Z
     220: ifeq          248
     223: aload_1
     224: ldc_w         #66                 // class org/apache/cxf/service/model/BindingOperationInfo
     227: aload         12
     229: invokeinterface #67,  3           // InterfaceMethod org/apache/cxf/message/Exchange.put:(Ljava/lang/Class;Ljava/lang/Object;)V
     234: aload_1
     235: aload         14
     237: invokevirtual #68                 // Method org/apache/cxf/service/model/OperationInfo.isOneWay:()Z
     240: invokeinterface #69,  2           // InterfaceMethod org/apache/cxf/message/Exchange.setOneWay:(Z)V
     245: aload         16
     247: areturn
     248: getstatic     #70                 // Field org/apache/ws/commons/schema/constants/Constants.XSD_ANYTYPE:Ljavax/xml/namespace/QName;
     251: aload         16
     253: invokevirtual #71                 // Method org/apache/cxf/service/model/MessagePartInfo.getTypeQName:()Ljavax/xml/namespace/QName;
     256: invokevirtual #65                 // Method javax/xml/namespace/QName.equals:(Ljava/lang/Object;)Z
     259: ifeq          277
     262: aload         16
     264: astore        8
     266: aload         12
     268: astore        9
     270: aload         11
     272: astore        10
     274: goto          284
     277: aload         13
     279: invokeinterface #53,  1           // InterfaceMethod java/util/Iterator.remove:()V
     284: goto          31
     287: aload         8
     289: ifnull        316
     292: aload_0
     293: aload         6
     295: aload         9
     297: iload         4
     299: aload         9
     301: invokevirtual #72                 // Method org/apache/cxf/service/model/BindingOperationInfo.getBinding:()Lorg/apache/cxf/service/model/BindingInfo;
     304: invokevirtual #73                 // Method org/apache/cxf/service/model/BindingInfo.getService:()Lorg/apache/cxf/service/model/ServiceInfo;
     307: aload         10
     309: invokevirtual #74                 // Method org/apache/cxf/service/model/BindingMessageInfo.getMessageInfo:()Lorg/apache/cxf/service/model/MessageInfo;
     312: invokevirtual #75                 // Method setMessage:(Lorg/apache/cxf/message/Message;Lorg/apache/cxf/service/model/BindingOperationInfo;ZLorg/apache/cxf/service/model/ServiceInfo;Lorg/apache/cxf/service/model/MessageInfo;)Lorg/apache/cxf/service/model/MessageInfo;
     315: pop
     316: aload         8
     318: areturn

  protected org.apache.cxf.service.model.MessageInfo setMessage(org.apache.cxf.message.Message, org.apache.cxf.service.model.BindingOperationInfo, boolean, org.apache.cxf.service.model.ServiceInfo, org.apache.cxf.service.model.MessageInfo);
    Code:
       0: aload_1
       1: ldc_w         #76                 // class org/apache/cxf/service/model/MessageInfo
       4: aload         5
       6: invokeinterface #77,  3           // InterfaceMethod org/apache/cxf/message/Message.put:(Ljava/lang/Class;Ljava/lang/Object;)V
      11: aload_1
      12: invokeinterface #3,  1            // InterfaceMethod org/apache/cxf/message/Message.getExchange:()Lorg/apache/cxf/message/Exchange;
      17: astore        6
      19: aload         6
      21: ldc_w         #66                 // class org/apache/cxf/service/model/BindingOperationInfo
      24: aload_2
      25: invokeinterface #67,  3           // InterfaceMethod org/apache/cxf/message/Exchange.put:(Ljava/lang/Class;Ljava/lang/Object;)V
      30: aload         6
      32: aload_2
      33: invokevirtual #78                 // Method org/apache/cxf/service/model/BindingOperationInfo.getOperationInfo:()Lorg/apache/cxf/service/model/OperationInfo;
      36: invokevirtual #68                 // Method org/apache/cxf/service/model/OperationInfo.isOneWay:()Z
      39: invokeinterface #69,  2           // InterfaceMethod org/apache/cxf/message/Exchange.setOneWay:(Z)V
      44: getstatic     #79                 // Field java/lang/Boolean.TRUE:Ljava/lang/Boolean;
      47: aload_2
      48: ldc           #80                 // String operation.is.synthetic
      50: invokevirtual #81                 // Method org/apache/cxf/service/model/BindingOperationInfo.getProperty:(Ljava/lang/String;)Ljava/lang/Object;
      53: invokevirtual #82                 // Method java/lang/Boolean.equals:(Ljava/lang/Object;)Z
      56: istore        7
      58: iload         7
      60: ifne          76
      63: aload_1
      64: ldc           #83                 // String javax.xml.ws.wsdl.operation
      66: aload_2
      67: invokevirtual #84                 // Method org/apache/cxf/service/model/BindingOperationInfo.getName:()Ljavax/xml/namespace/QName;
      70: invokeinterface #39,  3           // InterfaceMethod org/apache/cxf/message/Message.put:(Ljava/lang/Object;Ljava/lang/Object;)Ljava/lang/Object;
      75: pop
      76: aload_0
      77: aload_1
      78: invokevirtual #85                 // Method setOperationSchemaValidation:(Lorg/apache/cxf/message/Message;)V
      81: aload         4
      83: invokevirtual #86                 // Method org/apache/cxf/service/model/ServiceInfo.getName:()Ljavax/xml/namespace/QName;
      86: astore        8
      88: aload_1
      89: ldc           #87                 // String javax.xml.ws.wsdl.service
      91: aload         8
      93: invokeinterface #39,  3           // InterfaceMethod org/apache/cxf/message/Message.put:(Ljava/lang/Object;Ljava/lang/Object;)Ljava/lang/Object;
      98: pop
      99: aload         4
     101: invokevirtual #88                 // Method org/apache/cxf/service/model/ServiceInfo.getInterface:()Lorg/apache/cxf/service/model/InterfaceInfo;
     104: invokevirtual #89                 // Method org/apache/cxf/service/model/InterfaceInfo.getName:()Ljavax/xml/namespace/QName;
     107: astore        9
     109: aload_1
     110: ldc           #90                 // String javax.xml.ws.wsdl.interface
     112: aload         9
     114: invokeinterface #39,  3           // InterfaceMethod org/apache/cxf/message/Message.put:(Ljava/lang/Object;Ljava/lang/Object;)Ljava/lang/Object;
     119: pop
     120: aload         6
     122: invokeinterface #20,  1           // InterfaceMethod org/apache/cxf/message/Exchange.getEndpoint:()Lorg/apache/cxf/endpoint/Endpoint;
     127: invokeinterface #48,  1           // InterfaceMethod org/apache/cxf/endpoint/Endpoint.getEndpointInfo:()Lorg/apache/cxf/service/model/EndpointInfo;
     132: astore        10
     134: aload         10
     136: invokevirtual #91                 // Method org/apache/cxf/service/model/EndpointInfo.getName:()Ljavax/xml/namespace/QName;
     139: astore        11
     141: aload_1
     142: ldc           #92                 // String javax.xml.ws.wsdl.port
     144: aload         11
     146: invokeinterface #39,  3           // InterfaceMethod org/apache/cxf/message/Message.put:(Ljava/lang/Object;Ljava/lang/Object;)Ljava/lang/Object;
     151: pop
     152: aload         10
     154: ldc           #93                 // String URI
     156: ldc_w         #94                 // class java/net/URI
     159: invokevirtual #95                 // Method org/apache/cxf/service/model/EndpointInfo.getProperty:(Ljava/lang/String;Ljava/lang/Class;)Ljava/lang/Object;
     162: checkcast     #94                 // class java/net/URI
     165: astore        12
     167: aload         12
     169: ifnonnull     222
     172: aload         10
     174: invokevirtual #96                 // Method org/apache/cxf/service/model/EndpointInfo.getAddress:()Ljava/lang/String;
     177: astore        13
     179: new           #94                 // class java/net/URI
     182: dup
     183: new           #97                 // class java/lang/StringBuilder
     186: dup
     187: invokespecial #98                 // Method java/lang/StringBuilder."<init>":()V
     190: aload         13
     192: invokevirtual #99                 // Method java/lang/StringBuilder.append:(Ljava/lang/String;)Ljava/lang/StringBuilder;
     195: ldc           #100                // String ?wsdl
     197: invokevirtual #99                 // Method java/lang/StringBuilder.append:(Ljava/lang/String;)Ljava/lang/StringBuilder;
     200: invokevirtual #101                // Method java/lang/StringBuilder.toString:()Ljava/lang/String;
     203: invokespecial #102                // Method java/net/URI."<init>":(Ljava/lang/String;)V
     206: astore        12
     208: goto          213
     211: astore        14
     213: aload         10
     215: ldc           #93                 // String URI
     217: aload         12
     219: invokevirtual #104                // Method org/apache/cxf/service/model/EndpointInfo.setProperty:(Ljava/lang/String;Ljava/lang/Object;)V
     222: aload_1
     223: ldc           #105                // String javax.xml.ws.wsdl.description
     225: aload         12
     227: invokeinterface #39,  3           // InterfaceMethod org/apache/cxf/message/Message.put:(Ljava/lang/Object;Ljava/lang/Object;)Ljava/lang/Object;
     232: pop
     233: aload         5
     235: areturn
    Exception table:
       from    to  target type
         179   208   211   Class java/net/URISyntaxException

  protected org.apache.cxf.service.model.BindingOperationInfo getBindingOperationInfo(org.apache.cxf.message.Exchange, javax.xml.namespace.QName, boolean);
    Code:
       0: aload_2
       1: invokevirtual #62                 // Method javax/xml/namespace/QName.getLocalPart:()Ljava/lang/String;
       4: astore        4
       6: iload_3
       7: ifeq          36
      10: aload         4
      12: ldc           #106                // String Response
      14: invokevirtual #107                // Method java/lang/String.endsWith:(Ljava/lang/String;)Z
      17: ifeq          36
      20: aload         4
      22: iconst_0
      23: aload         4
      25: invokevirtual #58                 // Method java/lang/String.length:()I
      28: bipush        8
      30: isub
      31: invokevirtual #108                // Method java/lang/String.substring:(II)Ljava/lang/String;
      34: astore        4
      36: aload_1
      37: aload         4
      39: invokestatic  #109                // Method org/apache/cxf/service/model/ServiceModelUtil.getOperation:(Lorg/apache/cxf/message/Exchange;Ljava/lang/String;)Lorg/apache/cxf/service/model/BindingOperationInfo;
      42: astore        5
      44: aload         5
      46: ifnull        60
      49: aload_1
      50: ldc_w         #66                 // class org/apache/cxf/service/model/BindingOperationInfo
      53: aload         5
      55: invokeinterface #67,  3           // InterfaceMethod org/apache/cxf/message/Exchange.put:(Ljava/lang/Class;Ljava/lang/Object;)V
      60: aload         5
      62: areturn

  protected org.apache.cxf.service.model.MessageInfo getMessageInfo(org.apache.cxf.message.Message, org.apache.cxf.service.model.BindingOperationInfo);
    Code:
       0: aload_0
       1: aload_1
       2: aload_2
       3: aload_0
       4: aload_1
       5: invokevirtual #110                // Method isRequestor:(Lorg/apache/cxf/message/Message;)Z
       8: invokevirtual #111                // Method getMessageInfo:(Lorg/apache/cxf/message/Message;Lorg/apache/cxf/service/model/BindingOperationInfo;Z)Lorg/apache/cxf/service/model/MessageInfo;
      11: areturn

  protected org.apache.cxf.service.model.MessageInfo getMessageInfo(org.apache.cxf.message.Message, org.apache.cxf.service.model.BindingOperationInfo, boolean);
    Code:
       0: aload_2
       1: invokevirtual #78                 // Method org/apache/cxf/service/model/BindingOperationInfo.getOperationInfo:()Lorg/apache/cxf/service/model/OperationInfo;
       4: astore        5
       6: iload_3
       7: ifeq          34
      10: aload         5
      12: invokevirtual #112                // Method org/apache/cxf/service/model/OperationInfo.getOutput:()Lorg/apache/cxf/service/model/MessageInfo;
      15: astore        4
      17: aload_1
      18: ldc_w         #76                 // class org/apache/cxf/service/model/MessageInfo
      21: aload         5
      23: invokevirtual #112                // Method org/apache/cxf/service/model/OperationInfo.getOutput:()Lorg/apache/cxf/service/model/MessageInfo;
      26: invokeinterface #77,  3           // InterfaceMethod org/apache/cxf/message/Message.put:(Ljava/lang/Class;Ljava/lang/Object;)V
      31: goto          55
      34: aload         5
      36: invokevirtual #113                // Method org/apache/cxf/service/model/OperationInfo.getInput:()Lorg/apache/cxf/service/model/MessageInfo;
      39: astore        4
      41: aload_1
      42: ldc_w         #76                 // class org/apache/cxf/service/model/MessageInfo
      45: aload         5
      47: invokevirtual #113                // Method org/apache/cxf/service/model/OperationInfo.getInput:()Lorg/apache/cxf/service/model/MessageInfo;
      50: invokeinterface #77,  3           // InterfaceMethod org/apache/cxf/message/Message.put:(Ljava/lang/Class;Ljava/lang/Object;)V
      55: aload         4
      57: areturn

  static {};
    Code:
       0: new           #97                 // class java/lang/StringBuilder
       3: dup
       4: invokespecial #98                 // Method java/lang/StringBuilder."<init>":()V
       7: ldc_w         #114                // class org/apache/cxf/interceptor/AbstractInDatabindingInterceptor
      10: invokevirtual #23                 // Method java/lang/Class.getName:()Ljava/lang/String;
      13: invokevirtual #99                 // Method java/lang/StringBuilder.append:(Ljava/lang/String;)Ljava/lang/StringBuilder;
      16: ldc           #115                // String .novalidate-parts
      18: invokevirtual #99                 // Method java/lang/StringBuilder.append:(Ljava/lang/String;)Ljava/lang/StringBuilder;
      21: invokevirtual #101                // Method java/lang/StringBuilder.toString:()Ljava/lang/String;
      24: putstatic     #116                // Field NO_VALIDATE_PARTS:Ljava/lang/String;
      27: ldc_w         #114                // class org/apache/cxf/interceptor/AbstractInDatabindingInterceptor
      30: invokestatic  #117                // Method org/apache/cxf/common/i18n/BundleUtils.getBundle:(Ljava/lang/Class;)Ljava/util/ResourceBundle;
      33: putstatic     #12                 // Field BUNDLE:Ljava/util/ResourceBundle;
      36: return
}
