Compiled from "StaxOutEndingInterceptor.java"
public class org.apache.cxf.interceptor.StaxOutEndingInterceptor extends org.apache.cxf.phase.AbstractPhaseInterceptor<org.apache.cxf.message.Message> {
  private static final java.util.ResourceBundle BUNDLE;

  private java.lang.String outStreamHolder;

  private java.lang.String writerHolder;

  public org.apache.cxf.interceptor.StaxOutEndingInterceptor(java.lang.String);
    Code:
       0: aload_0
       1: aload_1
       2: aconst_null
       3: invokespecial #1                  // Method "<init>":(Ljava/lang/String;Ljava/lang/String;)V
       6: return

  public org.apache.cxf.interceptor.StaxOutEndingInterceptor(java.lang.String, java.lang.String);
    Code:
       0: aload_0
       1: ldc           #2                  // String pre-stream-ending
       3: invokespecial #3                  // Method org/apache/cxf/phase/AbstractPhaseInterceptor."<init>":(Ljava/lang/String;)V
       6: aload_0
       7: invokevirtual #4                  // Method getAfter:()Ljava/util/Set;
      10: ldc_w         #5                  // class org/apache/cxf/interceptor/AttachmentOutInterceptor$AttachmentOutEndingInterceptor
      13: invokevirtual #6                  // Method java/lang/Class.getName:()Ljava/lang/String;
      16: invokeinterface #7,  2            // InterfaceMethod java/util/Set.add:(Ljava/lang/Object;)Z
      21: pop
      22: aload_0
      23: aload_1
      24: putfield      #8                  // Field outStreamHolder:Ljava/lang/String;
      27: aload_0
      28: aload_2
      29: putfield      #9                  // Field writerHolder:Ljava/lang/String;
      32: return

  public void handleMessage(org.apache.cxf.message.Message) throws org.apache.cxf.interceptor.Fault;
    Code:
       0: aload_1
       1: ldc_w         #10                 // class javax/xml/stream/XMLStreamWriter
       4: invokeinterface #11,  2           // InterfaceMethod org/apache/cxf/message/Message.getContent:(Ljava/lang/Class;)Ljava/lang/Object;
       9: checkcast     #10                 // class javax/xml/stream/XMLStreamWriter
      12: astore_2
      13: aload_2
      14: ifnull        43
      17: aload_2
      18: invokeinterface #12,  1           // InterfaceMethod javax/xml/stream/XMLStreamWriter.writeEndDocument:()V
      23: aload_2
      24: invokeinterface #13,  1           // InterfaceMethod javax/xml/stream/XMLStreamWriter.flush:()V
      29: aload_2
      30: invokestatic  #14                 // Method org/apache/cxf/staxutils/StaxUtils.close:(Ljavax/xml/stream/XMLStreamWriter;)V
      33: goto          43
      36: astore_3
      37: aload_2
      38: invokestatic  #14                 // Method org/apache/cxf/staxutils/StaxUtils.close:(Ljavax/xml/stream/XMLStreamWriter;)V
      41: aload_3
      42: athrow
      43: aload_1
      44: aload_0
      45: getfield      #8                  // Field outStreamHolder:Ljava/lang/String;
      48: invokeinterface #15,  2           // InterfaceMethod org/apache/cxf/message/Message.get:(Ljava/lang/Object;)Ljava/lang/Object;
      53: checkcast     #16                 // class java/io/OutputStream
      56: astore_3
      57: aload_3
      58: ifnull        71
      61: aload_1
      62: ldc_w         #16                 // class java/io/OutputStream
      65: aload_3
      66: invokeinterface #17,  3           // InterfaceMethod org/apache/cxf/message/Message.setContent:(Ljava/lang/Class;Ljava/lang/Object;)V
      71: aload_0
      72: getfield      #9                  // Field writerHolder:Ljava/lang/String;
      75: ifnull        109
      78: aload_1
      79: aload_0
      80: getfield      #9                  // Field writerHolder:Ljava/lang/String;
      83: invokeinterface #15,  2           // InterfaceMethod org/apache/cxf/message/Message.get:(Ljava/lang/Object;)Ljava/lang/Object;
      88: checkcast     #18                 // class java/io/Writer
      91: astore        4
      93: aload         4
      95: ifnull        109
      98: aload_1
      99: ldc_w         #18                 // class java/io/Writer
     102: aload         4
     104: invokeinterface #17,  3           // InterfaceMethod org/apache/cxf/message/Message.setContent:(Ljava/lang/Class;Ljava/lang/Object;)V
     109: aload_1
     110: ldc_w         #10                 // class javax/xml/stream/XMLStreamWriter
     113: invokeinterface #19,  2           // InterfaceMethod org/apache/cxf/message/Message.removeContent:(Ljava/lang/Class;)V
     118: goto          147
     121: astore_2
     122: new           #21                 // class org/apache/cxf/interceptor/Fault
     125: dup
     126: new           #22                 // class org/apache/cxf/common/i18n/Message
     129: dup
     130: ldc           #23                 // String STAX_WRITE_EXC
     132: getstatic     #24                 // Field BUNDLE:Ljava/util/ResourceBundle;
     135: iconst_0
     136: anewarray     #25                 // class java/lang/Object
     139: invokespecial #26                 // Method org/apache/cxf/common/i18n/Message."<init>":(Ljava/lang/String;Ljava/util/ResourceBundle;[Ljava/lang/Object;)V
     142: aload_2
     143: invokespecial #27                 // Method org/apache/cxf/interceptor/Fault."<init>":(Lorg/apache/cxf/common/i18n/Message;Ljava/lang/Throwable;)V
     146: athrow
     147: return
    Exception table:
       from    to  target type
          17    29    36   any
          36    37    36   any
           0   118   121   Class javax/xml/stream/XMLStreamException

  static {};
    Code:
       0: ldc_w         #28                 // class org/apache/cxf/interceptor/StaxOutEndingInterceptor
       3: invokestatic  #29                 // Method org/apache/cxf/common/i18n/BundleUtils.getBundle:(Ljava/lang/Class;)Ljava/util/ResourceBundle;
       6: putstatic     #24                 // Field BUNDLE:Ljava/util/ResourceBundle;
       9: return
}
