Compiled from "SharedStoreSlavePolicyConfiguration.java"
public class org.apache.activemq.artemis.core.config.ha.SharedStoreSlavePolicyConfiguration implements org.apache.activemq.artemis.core.config.HAPolicyConfiguration {
  private boolean failoverOnServerShutdown;

  private boolean restartBackup;

  private boolean allowFailBack;

  private org.apache.activemq.artemis.core.config.ScaleDownConfiguration scaleDownConfiguration;

  public org.apache.activemq.artemis.core.config.ha.SharedStoreSlavePolicyConfiguration();
    Code:
       0: aload_0
       1: invokespecial #1                  // Method java/lang/Object."<init>":()V
       4: aload_0
       5: invokestatic  #2                  // Method org/apache/activemq/artemis/api/config/ActiveMQDefaultConfiguration.isDefaultFailoverOnServerShutdown:()Z
       8: putfield      #3                  // Field failoverOnServerShutdown:Z
      11: aload_0
      12: invokestatic  #4                  // Method org/apache/activemq/artemis/api/config/ActiveMQDefaultConfiguration.isDefaultRestartBackup:()Z
      15: putfield      #5                  // Field restartBackup:Z
      18: aload_0
      19: invokestatic  #6                  // Method org/apache/activemq/artemis/api/config/ActiveMQDefaultConfiguration.isDefaultAllowAutoFailback:()Z
      22: putfield      #7                  // Field allowFailBack:Z
      25: return

  public org.apache.activemq.artemis.core.config.HAPolicyConfiguration$TYPE getType();
    Code:
       0: getstatic     #8                  // Field org/apache/activemq/artemis/core/config/HAPolicyConfiguration$TYPE.SHARED_STORE_SLAVE:Lorg/apache/activemq/artemis/core/config/HAPolicyConfiguration$TYPE;
       3: areturn

  public boolean isRestartBackup();
    Code:
       0: aload_0
       1: getfield      #5                  // Field restartBackup:Z
       4: ireturn

  public org.apache.activemq.artemis.core.config.ha.SharedStoreSlavePolicyConfiguration setRestartBackup(boolean);
    Code:
       0: aload_0
       1: iload_1
       2: putfield      #5                  // Field restartBackup:Z
       5: aload_0
       6: areturn

  public org.apache.activemq.artemis.core.config.ScaleDownConfiguration getScaleDownConfiguration();
    Code:
       0: aload_0
       1: getfield      #9                  // Field scaleDownConfiguration:Lorg/apache/activemq/artemis/core/config/ScaleDownConfiguration;
       4: areturn

  public org.apache.activemq.artemis.core.config.ha.SharedStoreSlavePolicyConfiguration setScaleDownConfiguration(org.apache.activemq.artemis.core.config.ScaleDownConfiguration);
    Code:
       0: aload_0
       1: aload_1
       2: putfield      #9                  // Field scaleDownConfiguration:Lorg/apache/activemq/artemis/core/config/ScaleDownConfiguration;
       5: aload_0
       6: areturn

  public boolean isAllowFailBack();
    Code:
       0: aload_0
       1: getfield      #7                  // Field allowFailBack:Z
       4: ireturn

  public org.apache.activemq.artemis.core.config.ha.SharedStoreSlavePolicyConfiguration setAllowFailBack(boolean);
    Code:
       0: aload_0
       1: iload_1
       2: putfield      #7                  // Field allowFailBack:Z
       5: aload_0
       6: areturn

  public boolean isFailoverOnServerShutdown();
    Code:
       0: aload_0
       1: getfield      #3                  // Field failoverOnServerShutdown:Z
       4: ireturn

  public org.apache.activemq.artemis.core.config.ha.SharedStoreSlavePolicyConfiguration setFailoverOnServerShutdown(boolean);
    Code:
       0: aload_0
       1: iload_1
       2: putfield      #3                  // Field failoverOnServerShutdown:Z
       5: aload_0
       6: areturn

  public long getFailbackDelay();
    Code:
       0: ldc2_w        #10                 // long -1l
       3: lreturn

  public org.apache.activemq.artemis.core.config.ha.SharedStoreSlavePolicyConfiguration setFailbackDelay(long);
    Code:
       0: aload_0
       1: areturn
}
