public class org.bouncycastle.asn1.its.EncryptedData {
  private org.bouncycastle.asn1.its.EncryptedData(org.bouncycastle.asn1.ASN1Sequence);
    Code:
       0: aload_0
       1: invokespecial #16                 // Method java/lang/Object."<init>":()V
       4: return

  public static org.bouncycastle.asn1.its.EncryptedData getInstance(java.lang.Object);
    Code:
       0: aload_0
       1: instanceof    #9                  // class org/bouncycastle/asn1/its/EncryptedData
       4: ifeq          12
       7: aload_0
       8: checkcast     #9                  // class org/bouncycastle/asn1/its/EncryptedData
      11: areturn
      12: aload_0
      13: ifnull        28
      16: new           #9                  // class org/bouncycastle/asn1/its/EncryptedData
      19: dup
      20: aload_0
      21: invokestatic  #17                 // Method org/bouncycastle/asn1/ASN1Sequence.getInstance:(Ljava/lang/Object;)Lorg/bouncycastle/asn1/ASN1Sequence;
      24: invokespecial #18                 // Method "<init>":(Lorg/bouncycastle/asn1/ASN1Sequence;)V
      27: areturn
      28: aconst_null
      29: areturn
}
