Compiled from "InstrumentedReadWriteLock.java"
public class org.apache.hadoop.util.InstrumentedReadWriteLock implements java.util.concurrent.locks.ReadWriteLock {
  private final java.util.concurrent.locks.Lock readLock;

  private final java.util.concurrent.locks.Lock writeLock;

  public org.apache.hadoop.util.InstrumentedReadWriteLock(boolean, java.lang.String, org.slf4j.Logger, long, long);
    Code:
       0: aload_0
       1: invokespecial #1                  // Method java/lang/Object."<init>":()V
       4: new           #2                  // class java/util/concurrent/locks/ReentrantReadWriteLock
       7: dup
       8: iload_1
       9: invokespecial #3                  // Method java/util/concurrent/locks/ReentrantReadWriteLock."<init>":(Z)V
      12: astore        8
      14: aload_0
      15: new           #4                  // class org/apache/hadoop/util/InstrumentedReadLock
      18: dup
      19: aload_2
      20: aload_3
      21: aload         8
      23: lload         4
      25: lload         6
      27: invokespecial #5                  // Method org/apache/hadoop/util/InstrumentedReadLock."<init>":(Ljava/lang/String;Lorg/slf4j/Logger;Ljava/util/concurrent/locks/ReentrantReadWriteLock;JJ)V
      30: putfield      #6                  // Field readLock:Ljava/util/concurrent/locks/Lock;
      33: aload_0
      34: new           #7                  // class org/apache/hadoop/util/InstrumentedWriteLock
      37: dup
      38: aload_2
      39: aload_3
      40: aload         8
      42: lload         4
      44: lload         6
      46: invokespecial #8                  // Method org/apache/hadoop/util/InstrumentedWriteLock."<init>":(Ljava/lang/String;Lorg/slf4j/Logger;Ljava/util/concurrent/locks/ReentrantReadWriteLock;JJ)V
      49: putfield      #9                  // Field writeLock:Ljava/util/concurrent/locks/Lock;
      52: return

  public java.util.concurrent.locks.Lock readLock();
    Code:
       0: aload_0
       1: getfield      #6                  // Field readLock:Ljava/util/concurrent/locks/Lock;
       4: areturn

  public java.util.concurrent.locks.Lock writeLock();
    Code:
       0: aload_0
       1: getfield      #9                  // Field writeLock:Ljava/util/concurrent/locks/Lock;
       4: areturn
}
