Compiled from "LightWeightCache.java"
class org.apache.hadoop.util.LightWeightCache$2 implements java.util.Iterator<E> {
  final java.util.Iterator val$iter;

  final org.apache.hadoop.util.LightWeightCache this$0;

  org.apache.hadoop.util.LightWeightCache$2(org.apache.hadoop.util.LightWeightCache, java.util.Iterator);
    Code:
       0: aload_0
       1: aload_1
       2: putfield      #1                  // Field this$0:Lorg/apache/hadoop/util/LightWeightCache;
       5: aload_0
       6: aload_2
       7: putfield      #2                  // Field val$iter:Ljava/util/Iterator;
      10: aload_0
      11: invokespecial #3                  // Method java/lang/Object."<init>":()V
      14: return

  public boolean hasNext();
    Code:
       0: aload_0
       1: getfield      #2                  // Field val$iter:Ljava/util/Iterator;
       4: invokeinterface #4,  1            // InterfaceMethod java/util/Iterator.hasNext:()Z
       9: ireturn

  public E next();
    Code:
       0: aload_0
       1: getfield      #2                  // Field val$iter:Ljava/util/Iterator;
       4: invokeinterface #5,  1            // InterfaceMethod java/util/Iterator.next:()Ljava/lang/Object;
       9: areturn

  public void remove();
    Code:
       0: new           #6                  // class java/lang/UnsupportedOperationException
       3: dup
       4: ldc           #7                  // String Remove via iterator is not supported for LightWeightCache
       6: invokespecial #8                  // Method java/lang/UnsupportedOperationException."<init>":(Ljava/lang/String;)V
       9: athrow
}
