Compiled from "NativeLibraryChecker.java"
public class org.apache.hadoop.util.NativeLibraryChecker {
  public static final org.slf4j.Logger LOG;

  public org.apache.hadoop.util.NativeLibraryChecker();
    Code:
       0: aload_0
       1: invokespecial #1                  // Method java/lang/Object."<init>":()V
       4: return

  public static void main(java.lang.String[]);
    Code:
       0: ldc           #2                  // String NativeLibraryChecker [-a|-h]\n  -a  use -a to check all libraries are available\n      by default just check hadoop library (and\n      winutils.exe on Windows OS) is available\n      exit with error code 1 if check failed\n  -h  print this message\n
       2: astore_1
       3: aload_0
       4: arraylength
       5: iconst_1
       6: if_icmpgt     37
       9: aload_0
      10: arraylength
      11: iconst_1
      12: if_icmpne     48
      15: aload_0
      16: iconst_0
      17: aaload
      18: ldc           #3                  // String -a
      20: invokevirtual #4                  // Method java/lang/String.equals:(Ljava/lang/Object;)Z
      23: ifne          48
      26: aload_0
      27: iconst_0
      28: aaload
      29: ldc           #5                  // String -h
      31: invokevirtual #4                  // Method java/lang/String.equals:(Ljava/lang/Object;)Z
      34: ifne          48
      37: getstatic     #6                  // Field java/lang/System.err:Ljava/io/PrintStream;
      40: aload_1
      41: invokevirtual #7                  // Method java/io/PrintStream.println:(Ljava/lang/String;)V
      44: iconst_1
      45: invokestatic  #8                  // Method org/apache/hadoop/util/ExitUtil.terminate:(I)V
      48: iconst_0
      49: istore_2
      50: aload_0
      51: arraylength
      52: iconst_1
      53: if_icmpne     77
      56: aload_0
      57: iconst_0
      58: aaload
      59: ldc           #5                  // String -h
      61: invokevirtual #4                  // Method java/lang/String.equals:(Ljava/lang/Object;)Z
      64: ifeq          75
      67: getstatic     #9                  // Field java/lang/System.out:Ljava/io/PrintStream;
      70: aload_1
      71: invokevirtual #7                  // Method java/io/PrintStream.println:(Ljava/lang/String;)V
      74: return
      75: iconst_1
      76: istore_2
      77: new           #10                 // class org/apache/hadoop/conf/Configuration
      80: dup
      81: invokespecial #11                 // Method org/apache/hadoop/conf/Configuration."<init>":()V
      84: astore_3
      85: invokestatic  #12                 // Method org/apache/hadoop/util/NativeCodeLoader.isNativeCodeLoaded:()Z
      88: istore        4
      90: iconst_0
      91: istore        5
      93: iconst_0
      94: istore        6
      96: iconst_0
      97: istore        7
      99: iconst_0
     100: istore        8
     102: iconst_0
     103: istore        9
     105: iload         4
     107: istore        10
     109: aload_3
     110: invokestatic  #13                 // Method org/apache/hadoop/io/compress/bzip2/Bzip2Factory.isNativeBzip2Loaded:(Lorg/apache/hadoop/conf/Configuration;)Z
     113: istore        11
     115: iconst_0
     116: istore        12
     118: iconst_0
     119: istore        13
     121: ldc           #14                 // String
     123: astore        14
     125: ldc           #14                 // String
     127: astore        15
     129: ldc           #14                 // String
     131: astore        16
     133: ldc           #14                 // String
     135: astore        17
     137: ldc           #14                 // String
     139: astore        18
     141: ldc           #14                 // String
     143: astore        19
     145: ldc           #14                 // String
     147: astore        20
     149: ldc           #14                 // String
     151: astore        21
     153: ldc           #14                 // String
     155: astore        22
     157: aconst_null
     158: astore        23
     160: iload         4
     162: ifeq          345
     165: invokestatic  #15                 // Method org/apache/hadoop/util/NativeCodeLoader.getLibraryName:()Ljava/lang/String;
     168: astore        15
     170: aload_3
     171: invokestatic  #16                 // Method org/apache/hadoop/io/compress/zlib/ZlibFactory.isNativeZlibLoaded:(Lorg/apache/hadoop/conf/Configuration;)Z
     174: istore        5
     176: iload         5
     178: ifeq          186
     181: invokestatic  #17                 // Method org/apache/hadoop/io/compress/zlib/ZlibFactory.getLibraryName:()Ljava/lang/String;
     184: astore        16
     186: invokestatic  #18                 // Method org/apache/hadoop/util/NativeCodeLoader.buildSupportsZstd:()Z
     189: ifeq          202
     192: invokestatic  #19                 // Method org/apache/hadoop/io/compress/ZStandardCodec.isNativeCodeLoaded:()Z
     195: ifeq          202
     198: iconst_1
     199: goto          203
     202: iconst_0
     203: istore        8
     205: iload         8
     207: ifeq          221
     210: invokestatic  #18                 // Method org/apache/hadoop/util/NativeCodeLoader.buildSupportsZstd:()Z
     213: ifeq          221
     216: invokestatic  #20                 // Method org/apache/hadoop/io/compress/ZStandardCodec.getLibraryName:()Ljava/lang/String;
     219: astore        20
     221: invokestatic  #21                 // Method org/apache/hadoop/util/NativeCodeLoader.buildSupportsSnappy:()Z
     224: ifeq          237
     227: invokestatic  #22                 // Method org/apache/hadoop/io/compress/SnappyCodec.isNativeCodeLoaded:()Z
     230: ifeq          237
     233: iconst_1
     234: goto          238
     237: iconst_0
     238: istore        6
     240: iload         6
     242: ifeq          256
     245: invokestatic  #21                 // Method org/apache/hadoop/util/NativeCodeLoader.buildSupportsSnappy:()Z
     248: ifeq          256
     251: invokestatic  #23                 // Method org/apache/hadoop/io/compress/SnappyCodec.getLibraryName:()Ljava/lang/String;
     254: astore        17
     256: invokestatic  #24                 // Method org/apache/hadoop/io/erasurecode/ErasureCodeNative.getLoadingFailureReason:()Ljava/lang/String;
     259: astore        18
     261: aload         18
     263: ifnull        272
     266: iconst_0
     267: istore        7
     269: goto          280
     272: invokestatic  #25                 // Method org/apache/hadoop/io/erasurecode/ErasureCodeNative.getLibraryName:()Ljava/lang/String;
     275: astore        18
     277: iconst_1
     278: istore        7
     280: invokestatic  #26                 // Method org/apache/hadoop/io/nativeio/NativeIO$POSIX.getPmdkSupportStateMessage:()Ljava/lang/String;
     283: astore        19
     285: invokestatic  #27                 // Method org/apache/hadoop/io/nativeio/NativeIO$POSIX.isPmdkAvailable:()Z
     288: istore        9
     290: iload         9
     292: ifeq          300
     295: invokestatic  #28                 // Method org/apache/hadoop/io/nativeio/NativeIO$POSIX$Pmem.getPmdkLibPath:()Ljava/lang/String;
     298: astore        19
     300: invokestatic  #29                 // Method org/apache/hadoop/crypto/OpensslCipher.getLoadingFailureReason:()Ljava/lang/String;
     303: astore        14
     305: aload         14
     307: ifnull        316
     310: iconst_0
     311: istore        12
     313: goto          324
     316: invokestatic  #30                 // Method org/apache/hadoop/crypto/OpensslCipher.getLibraryName:()Ljava/lang/String;
     319: astore        14
     321: iconst_1
     322: istore        12
     324: iload         10
     326: ifeq          334
     329: invokestatic  #31                 // Method org/apache/hadoop/io/compress/Lz4Codec.getLibraryName:()Ljava/lang/String;
     332: astore        21
     334: iload         11
     336: ifeq          345
     339: aload_3
     340: invokestatic  #32                 // Method org/apache/hadoop/io/compress/bzip2/Bzip2Factory.getLibraryName:(Lorg/apache/hadoop/conf/Configuration;)Ljava/lang/String;
     343: astore        22
     345: getstatic     #33                 // Field org/apache/hadoop/util/Shell.WINDOWS:Z
     348: ifeq          415
     351: invokestatic  #34                 // Method org/apache/hadoop/util/Shell.getWinUtilsFile:()Ljava/io/File;
     354: invokevirtual #35                 // Method java/io/File.getCanonicalPath:()Ljava/lang/String;
     357: astore        23
     359: iconst_1
     360: istore        13
     362: goto          389
     365: astore        24
     367: getstatic     #37                 // Field LOG:Lorg/slf4j/Logger;
     370: ldc           #38                 // String No Winutils:
     372: aload         24
     374: invokeinterface #39,  3           // InterfaceMethod org/slf4j/Logger.debug:(Ljava/lang/String;Ljava/lang/Throwable;)V
     379: aload         24
     381: invokevirtual #40                 // Method java/io/IOException.getMessage:()Ljava/lang/String;
     384: astore        23
     386: iconst_0
     387: istore        13
     389: getstatic     #9                  // Field java/lang/System.out:Ljava/io/PrintStream;
     392: ldc           #41                 // String winutils: %b %s%n
     394: iconst_2
     395: anewarray     #42                 // class java/lang/Object
     398: dup
     399: iconst_0
     400: iload         13
     402: invokestatic  #43                 // Method java/lang/Boolean.valueOf:(Z)Ljava/lang/Boolean;
     405: aastore
     406: dup
     407: iconst_1
     408: aload         23
     410: aastore
     411: invokevirtual #44                 // Method java/io/PrintStream.printf:(Ljava/lang/String;[Ljava/lang/Object;)Ljava/io/PrintStream;
     414: pop
     415: getstatic     #9                  // Field java/lang/System.out:Ljava/io/PrintStream;
     418: ldc           #45                 // String Native library checking:
     420: invokevirtual #7                  // Method java/io/PrintStream.println:(Ljava/lang/String;)V
     423: getstatic     #9                  // Field java/lang/System.out:Ljava/io/PrintStream;
     426: ldc           #46                 // String hadoop:  %b %s%n
     428: iconst_2
     429: anewarray     #42                 // class java/lang/Object
     432: dup
     433: iconst_0
     434: iload         4
     436: invokestatic  #43                 // Method java/lang/Boolean.valueOf:(Z)Ljava/lang/Boolean;
     439: aastore
     440: dup
     441: iconst_1
     442: aload         15
     444: aastore
     445: invokevirtual #44                 // Method java/io/PrintStream.printf:(Ljava/lang/String;[Ljava/lang/Object;)Ljava/io/PrintStream;
     448: pop
     449: getstatic     #9                  // Field java/lang/System.out:Ljava/io/PrintStream;
     452: ldc           #47                 // String zlib:    %b %s%n
     454: iconst_2
     455: anewarray     #42                 // class java/lang/Object
     458: dup
     459: iconst_0
     460: iload         5
     462: invokestatic  #43                 // Method java/lang/Boolean.valueOf:(Z)Ljava/lang/Boolean;
     465: aastore
     466: dup
     467: iconst_1
     468: aload         16
     470: aastore
     471: invokevirtual #44                 // Method java/io/PrintStream.printf:(Ljava/lang/String;[Ljava/lang/Object;)Ljava/io/PrintStream;
     474: pop
     475: getstatic     #9                  // Field java/lang/System.out:Ljava/io/PrintStream;
     478: ldc           #48                 // String zstd  :  %b %s%n
     480: iconst_2
     481: anewarray     #42                 // class java/lang/Object
     484: dup
     485: iconst_0
     486: iload         8
     488: invokestatic  #43                 // Method java/lang/Boolean.valueOf:(Z)Ljava/lang/Boolean;
     491: aastore
     492: dup
     493: iconst_1
     494: aload         20
     496: aastore
     497: invokevirtual #44                 // Method java/io/PrintStream.printf:(Ljava/lang/String;[Ljava/lang/Object;)Ljava/io/PrintStream;
     500: pop
     501: getstatic     #9                  // Field java/lang/System.out:Ljava/io/PrintStream;
     504: ldc           #49                 // String snappy:  %b %s%n
     506: iconst_2
     507: anewarray     #42                 // class java/lang/Object
     510: dup
     511: iconst_0
     512: iload         6
     514: invokestatic  #43                 // Method java/lang/Boolean.valueOf:(Z)Ljava/lang/Boolean;
     517: aastore
     518: dup
     519: iconst_1
     520: aload         17
     522: aastore
     523: invokevirtual #44                 // Method java/io/PrintStream.printf:(Ljava/lang/String;[Ljava/lang/Object;)Ljava/io/PrintStream;
     526: pop
     527: getstatic     #9                  // Field java/lang/System.out:Ljava/io/PrintStream;
     530: ldc           #50                 // String lz4:     %b %s%n
     532: iconst_2
     533: anewarray     #42                 // class java/lang/Object
     536: dup
     537: iconst_0
     538: iload         10
     540: invokestatic  #43                 // Method java/lang/Boolean.valueOf:(Z)Ljava/lang/Boolean;
     543: aastore
     544: dup
     545: iconst_1
     546: aload         21
     548: aastore
     549: invokevirtual #44                 // Method java/io/PrintStream.printf:(Ljava/lang/String;[Ljava/lang/Object;)Ljava/io/PrintStream;
     552: pop
     553: getstatic     #9                  // Field java/lang/System.out:Ljava/io/PrintStream;
     556: ldc           #51                 // String bzip2:   %b %s%n
     558: iconst_2
     559: anewarray     #42                 // class java/lang/Object
     562: dup
     563: iconst_0
     564: iload         11
     566: invokestatic  #43                 // Method java/lang/Boolean.valueOf:(Z)Ljava/lang/Boolean;
     569: aastore
     570: dup
     571: iconst_1
     572: aload         22
     574: aastore
     575: invokevirtual #44                 // Method java/io/PrintStream.printf:(Ljava/lang/String;[Ljava/lang/Object;)Ljava/io/PrintStream;
     578: pop
     579: getstatic     #9                  // Field java/lang/System.out:Ljava/io/PrintStream;
     582: ldc           #52                 // String openssl: %b %s%n
     584: iconst_2
     585: anewarray     #42                 // class java/lang/Object
     588: dup
     589: iconst_0
     590: iload         12
     592: invokestatic  #43                 // Method java/lang/Boolean.valueOf:(Z)Ljava/lang/Boolean;
     595: aastore
     596: dup
     597: iconst_1
     598: aload         14
     600: aastore
     601: invokevirtual #44                 // Method java/io/PrintStream.printf:(Ljava/lang/String;[Ljava/lang/Object;)Ljava/io/PrintStream;
     604: pop
     605: getstatic     #9                  // Field java/lang/System.out:Ljava/io/PrintStream;
     608: ldc           #53                 // String ISA-L:   %b %s%n
     610: iconst_2
     611: anewarray     #42                 // class java/lang/Object
     614: dup
     615: iconst_0
     616: iload         7
     618: invokestatic  #43                 // Method java/lang/Boolean.valueOf:(Z)Ljava/lang/Boolean;
     621: aastore
     622: dup
     623: iconst_1
     624: aload         18
     626: aastore
     627: invokevirtual #44                 // Method java/io/PrintStream.printf:(Ljava/lang/String;[Ljava/lang/Object;)Ljava/io/PrintStream;
     630: pop
     631: getstatic     #9                  // Field java/lang/System.out:Ljava/io/PrintStream;
     634: ldc           #54                 // String PMDK:    %b %s%n
     636: iconst_2
     637: anewarray     #42                 // class java/lang/Object
     640: dup
     641: iconst_0
     642: iload         9
     644: invokestatic  #43                 // Method java/lang/Boolean.valueOf:(Z)Ljava/lang/Boolean;
     647: aastore
     648: dup
     649: iconst_1
     650: aload         19
     652: aastore
     653: invokevirtual #44                 // Method java/io/PrintStream.printf:(Ljava/lang/String;[Ljava/lang/Object;)Ljava/io/PrintStream;
     656: pop
     657: getstatic     #33                 // Field org/apache/hadoop/util/Shell.WINDOWS:Z
     660: ifeq          689
     663: getstatic     #9                  // Field java/lang/System.out:Ljava/io/PrintStream;
     666: ldc           #41                 // String winutils: %b %s%n
     668: iconst_2
     669: anewarray     #42                 // class java/lang/Object
     672: dup
     673: iconst_0
     674: iload         13
     676: invokestatic  #43                 // Method java/lang/Boolean.valueOf:(Z)Ljava/lang/Boolean;
     679: aastore
     680: dup
     681: iconst_1
     682: aload         23
     684: aastore
     685: invokevirtual #44                 // Method java/io/PrintStream.printf:(Ljava/lang/String;[Ljava/lang/Object;)Ljava/io/PrintStream;
     688: pop
     689: iload         4
     691: ifeq          739
     694: getstatic     #33                 // Field org/apache/hadoop/util/Shell.WINDOWS:Z
     697: ifeq          705
     700: iload         13
     702: ifeq          739
     705: iload_2
     706: ifeq          743
     709: iload         5
     711: ifeq          739
     714: iload         6
     716: ifeq          739
     719: iload         10
     721: ifeq          739
     724: iload         11
     726: ifeq          739
     729: iload         7
     731: ifeq          739
     734: iload         8
     736: ifne          743
     739: iconst_1
     740: invokestatic  #8                  // Method org/apache/hadoop/util/ExitUtil.terminate:(I)V
     743: return
    Exception table:
       from    to  target type
         351   362   365   Class java/io/IOException

  static {};
    Code:
       0: ldc           #55                 // class org/apache/hadoop/util/NativeLibraryChecker
       2: invokestatic  #56                 // Method org/slf4j/LoggerFactory.getLogger:(Ljava/lang/Class;)Lorg/slf4j/Logger;
       5: putstatic     #37                 // Field LOG:Lorg/slf4j/Logger;
       8: return
}
