Compiled from "SemaphoredDelegatingExecutor.java"
public class org.apache.hadoop.util.SemaphoredDelegatingExecutor extends com.google.common.util.concurrent.ForwardingExecutorService {
  private final java.util.concurrent.Semaphore queueingPermits;

  private final java.util.concurrent.ExecutorService executorDelegatee;

  private final int permitCount;

  public org.apache.hadoop.util.SemaphoredDelegatingExecutor(java.util.concurrent.ExecutorService, int, boolean);
    Code:
       0: aload_0
       1: invokespecial #2                  // Method com/google/common/util/concurrent/ForwardingExecutorService."<init>":()V
       4: aload_0
       5: iload_2
       6: putfield      #3                  // Field permitCount:I
       9: aload_0
      10: new           #4                  // class java/util/concurrent/Semaphore
      13: dup
      14: iload_2
      15: iload_3
      16: invokespecial #5                  // Method java/util/concurrent/Semaphore."<init>":(IZ)V
      19: putfield      #1                  // Field queueingPermits:Ljava/util/concurrent/Semaphore;
      22: aload_0
      23: aload_1
      24: putfield      #6                  // Field executorDelegatee:Ljava/util/concurrent/ExecutorService;
      27: return

  protected java.util.concurrent.ExecutorService delegate();
    Code:
       0: aload_0
       1: getfield      #6                  // Field executorDelegatee:Ljava/util/concurrent/ExecutorService;
       4: areturn

  public <T> java.util.List<java.util.concurrent.Future<T>> invokeAll(java.util.Collection<? extends java.util.concurrent.Callable<T>>) throws java.lang.InterruptedException;
    Code:
       0: new           #7                  // class java/lang/RuntimeException
       3: dup
       4: ldc           #8                  // String Not implemented
       6: invokespecial #9                  // Method java/lang/RuntimeException."<init>":(Ljava/lang/String;)V
       9: athrow

  public <T> java.util.List<java.util.concurrent.Future<T>> invokeAll(java.util.Collection<? extends java.util.concurrent.Callable<T>>, long, java.util.concurrent.TimeUnit) throws java.lang.InterruptedException;
    Code:
       0: new           #7                  // class java/lang/RuntimeException
       3: dup
       4: ldc           #8                  // String Not implemented
       6: invokespecial #9                  // Method java/lang/RuntimeException."<init>":(Ljava/lang/String;)V
       9: athrow

  public <T> T invokeAny(java.util.Collection<? extends java.util.concurrent.Callable<T>>) throws java.lang.InterruptedException, java.util.concurrent.ExecutionException;
    Code:
       0: new           #7                  // class java/lang/RuntimeException
       3: dup
       4: ldc           #8                  // String Not implemented
       6: invokespecial #9                  // Method java/lang/RuntimeException."<init>":(Ljava/lang/String;)V
       9: athrow

  public <T> T invokeAny(java.util.Collection<? extends java.util.concurrent.Callable<T>>, long, java.util.concurrent.TimeUnit) throws java.lang.InterruptedException, java.util.concurrent.ExecutionException, java.util.concurrent.TimeoutException;
    Code:
       0: new           #7                  // class java/lang/RuntimeException
       3: dup
       4: ldc           #8                  // String Not implemented
       6: invokespecial #9                  // Method java/lang/RuntimeException."<init>":(Ljava/lang/String;)V
       9: athrow

  public <T> java.util.concurrent.Future<T> submit(java.util.concurrent.Callable<T>);
    Code:
       0: aload_0
       1: getfield      #1                  // Field queueingPermits:Ljava/util/concurrent/Semaphore;
       4: invokevirtual #10                 // Method java/util/concurrent/Semaphore.acquire:()V
       7: goto          22
      10: astore_2
      11: invokestatic  #12                 // Method java/lang/Thread.currentThread:()Ljava/lang/Thread;
      14: invokevirtual #13                 // Method java/lang/Thread.interrupt:()V
      17: aload_2
      18: invokestatic  #14                 // Method com/google/common/util/concurrent/Futures.immediateFailedFuture:(Ljava/lang/Throwable;)Lcom/google/common/util/concurrent/ListenableFuture;
      21: areturn
      22: aload_0
      23: new           #15                 // class org/apache/hadoop/util/SemaphoredDelegatingExecutor$CallableWithPermitRelease
      26: dup
      27: aload_0
      28: aload_1
      29: invokespecial #16                 // Method org/apache/hadoop/util/SemaphoredDelegatingExecutor$CallableWithPermitRelease."<init>":(Lorg/apache/hadoop/util/SemaphoredDelegatingExecutor;Ljava/util/concurrent/Callable;)V
      32: invokespecial #17                 // Method com/google/common/util/concurrent/ForwardingExecutorService.submit:(Ljava/util/concurrent/Callable;)Ljava/util/concurrent/Future;
      35: areturn
    Exception table:
       from    to  target type
           0     7    10   Class java/lang/InterruptedException

  public <T> java.util.concurrent.Future<T> submit(java.lang.Runnable, T);
    Code:
       0: aload_0
       1: getfield      #1                  // Field queueingPermits:Ljava/util/concurrent/Semaphore;
       4: invokevirtual #10                 // Method java/util/concurrent/Semaphore.acquire:()V
       7: goto          22
      10: astore_3
      11: invokestatic  #12                 // Method java/lang/Thread.currentThread:()Ljava/lang/Thread;
      14: invokevirtual #13                 // Method java/lang/Thread.interrupt:()V
      17: aload_3
      18: invokestatic  #14                 // Method com/google/common/util/concurrent/Futures.immediateFailedFuture:(Ljava/lang/Throwable;)Lcom/google/common/util/concurrent/ListenableFuture;
      21: areturn
      22: aload_0
      23: new           #18                 // class org/apache/hadoop/util/SemaphoredDelegatingExecutor$RunnableWithPermitRelease
      26: dup
      27: aload_0
      28: aload_1
      29: invokespecial #19                 // Method org/apache/hadoop/util/SemaphoredDelegatingExecutor$RunnableWithPermitRelease."<init>":(Lorg/apache/hadoop/util/SemaphoredDelegatingExecutor;Ljava/lang/Runnable;)V
      32: aload_2
      33: invokespecial #20                 // Method com/google/common/util/concurrent/ForwardingExecutorService.submit:(Ljava/lang/Runnable;Ljava/lang/Object;)Ljava/util/concurrent/Future;
      36: areturn
    Exception table:
       from    to  target type
           0     7    10   Class java/lang/InterruptedException

  public java.util.concurrent.Future<?> submit(java.lang.Runnable);
    Code:
       0: aload_0
       1: getfield      #1                  // Field queueingPermits:Ljava/util/concurrent/Semaphore;
       4: invokevirtual #10                 // Method java/util/concurrent/Semaphore.acquire:()V
       7: goto          22
      10: astore_2
      11: invokestatic  #12                 // Method java/lang/Thread.currentThread:()Ljava/lang/Thread;
      14: invokevirtual #13                 // Method java/lang/Thread.interrupt:()V
      17: aload_2
      18: invokestatic  #14                 // Method com/google/common/util/concurrent/Futures.immediateFailedFuture:(Ljava/lang/Throwable;)Lcom/google/common/util/concurrent/ListenableFuture;
      21: areturn
      22: aload_0
      23: new           #18                 // class org/apache/hadoop/util/SemaphoredDelegatingExecutor$RunnableWithPermitRelease
      26: dup
      27: aload_0
      28: aload_1
      29: invokespecial #19                 // Method org/apache/hadoop/util/SemaphoredDelegatingExecutor$RunnableWithPermitRelease."<init>":(Lorg/apache/hadoop/util/SemaphoredDelegatingExecutor;Ljava/lang/Runnable;)V
      32: invokespecial #21                 // Method com/google/common/util/concurrent/ForwardingExecutorService.submit:(Ljava/lang/Runnable;)Ljava/util/concurrent/Future;
      35: areturn
    Exception table:
       from    to  target type
           0     7    10   Class java/lang/InterruptedException

  public void execute(java.lang.Runnable);
    Code:
       0: aload_0
       1: getfield      #1                  // Field queueingPermits:Ljava/util/concurrent/Semaphore;
       4: invokevirtual #10                 // Method java/util/concurrent/Semaphore.acquire:()V
       7: goto          17
      10: astore_2
      11: invokestatic  #12                 // Method java/lang/Thread.currentThread:()Ljava/lang/Thread;
      14: invokevirtual #13                 // Method java/lang/Thread.interrupt:()V
      17: aload_0
      18: new           #18                 // class org/apache/hadoop/util/SemaphoredDelegatingExecutor$RunnableWithPermitRelease
      21: dup
      22: aload_0
      23: aload_1
      24: invokespecial #19                 // Method org/apache/hadoop/util/SemaphoredDelegatingExecutor$RunnableWithPermitRelease."<init>":(Lorg/apache/hadoop/util/SemaphoredDelegatingExecutor;Ljava/lang/Runnable;)V
      27: invokespecial #22                 // Method com/google/common/util/concurrent/ForwardingExecutorService.execute:(Ljava/lang/Runnable;)V
      30: return
    Exception table:
       from    to  target type
           0     7    10   Class java/lang/InterruptedException

  public int getAvailablePermits();
    Code:
       0: aload_0
       1: getfield      #1                  // Field queueingPermits:Ljava/util/concurrent/Semaphore;
       4: invokevirtual #23                 // Method java/util/concurrent/Semaphore.availablePermits:()I
       7: ireturn

  public int getWaitingCount();
    Code:
       0: aload_0
       1: getfield      #1                  // Field queueingPermits:Ljava/util/concurrent/Semaphore;
       4: invokevirtual #24                 // Method java/util/concurrent/Semaphore.getQueueLength:()I
       7: ireturn

  public int getPermitCount();
    Code:
       0: aload_0
       1: getfield      #3                  // Field permitCount:I
       4: ireturn

  public java.lang.String toString();
    Code:
       0: new           #25                 // class java/lang/StringBuilder
       3: dup
       4: ldc           #26                 // String SemaphoredDelegatingExecutor{
       6: invokespecial #27                 // Method java/lang/StringBuilder."<init>":(Ljava/lang/String;)V
       9: astore_1
      10: aload_1
      11: ldc           #28                 // String permitCount=
      13: invokevirtual #29                 // Method java/lang/StringBuilder.append:(Ljava/lang/String;)Ljava/lang/StringBuilder;
      16: aload_0
      17: invokevirtual #30                 // Method getPermitCount:()I
      20: invokevirtual #31                 // Method java/lang/StringBuilder.append:(I)Ljava/lang/StringBuilder;
      23: ldc           #32                 // String , available=
      25: invokevirtual #29                 // Method java/lang/StringBuilder.append:(Ljava/lang/String;)Ljava/lang/StringBuilder;
      28: aload_0
      29: invokevirtual #33                 // Method getAvailablePermits:()I
      32: invokevirtual #31                 // Method java/lang/StringBuilder.append:(I)Ljava/lang/StringBuilder;
      35: ldc           #34                 // String , waiting=
      37: invokevirtual #29                 // Method java/lang/StringBuilder.append:(Ljava/lang/String;)Ljava/lang/StringBuilder;
      40: aload_0
      41: invokevirtual #35                 // Method getWaitingCount:()I
      44: invokevirtual #31                 // Method java/lang/StringBuilder.append:(I)Ljava/lang/StringBuilder;
      47: bipush        125
      49: invokevirtual #36                 // Method java/lang/StringBuilder.append:(C)Ljava/lang/StringBuilder;
      52: pop
      53: aload_1
      54: invokevirtual #37                 // Method java/lang/StringBuilder.toString:()Ljava/lang/String;
      57: areturn

  protected java.lang.Object delegate();
    Code:
       0: aload_0
       1: invokevirtual #38                 // Method delegate:()Ljava/util/concurrent/ExecutorService;
       4: areturn

  static java.util.concurrent.Semaphore access$000(org.apache.hadoop.util.SemaphoredDelegatingExecutor);
    Code:
       0: aload_0
       1: getfield      #1                  // Field queueingPermits:Ljava/util/concurrent/Semaphore;
       4: areturn
}
