Compiled from "Waitable.java"
public class org.apache.hadoop.util.Waitable<T> {
  private T val;

  private final java.util.concurrent.locks.Condition cond;

  public org.apache.hadoop.util.Waitable(java.util.concurrent.locks.Condition);
    Code:
       0: aload_0
       1: invokespecial #1                  // Method java/lang/Object."<init>":()V
       4: aload_0
       5: aconst_null
       6: putfield      #2                  // Field val:Ljava/lang/Object;
       9: aload_0
      10: aload_1
      11: putfield      #3                  // Field cond:Ljava/util/concurrent/locks/Condition;
      14: return

  public T await() throws java.lang.InterruptedException;
    Code:
       0: aload_0
       1: getfield      #2                  // Field val:Ljava/lang/Object;
       4: ifnonnull     19
       7: aload_0
       8: getfield      #3                  // Field cond:Ljava/util/concurrent/locks/Condition;
      11: invokeinterface #4,  1            // InterfaceMethod java/util/concurrent/locks/Condition.await:()V
      16: goto          0
      19: aload_0
      20: getfield      #2                  // Field val:Ljava/lang/Object;
      23: areturn

  public void provide(T);
    Code:
       0: aload_0
       1: aload_1
       2: putfield      #2                  // Field val:Ljava/lang/Object;
       5: aload_0
       6: getfield      #3                  // Field cond:Ljava/util/concurrent/locks/Condition;
       9: invokeinterface #5,  1            // InterfaceMethod java/util/concurrent/locks/Condition.signalAll:()V
      14: return

  public boolean hasVal();
    Code:
       0: aload_0
       1: getfield      #2                  // Field val:Ljava/lang/Object;
       4: ifnull        11
       7: iconst_1
       8: goto          12
      11: iconst_0
      12: ireturn

  public T getVal();
    Code:
       0: aload_0
       1: getfield      #2                  // Field val:Ljava/lang/Object;
       4: areturn
}
