Compiled from "Syntax.scala"
public final class scalaz.syntax.apply$ implements scalaz.syntax.ToApplyOps<scalaz.Apply> {
  public static final scalaz.syntax.apply$ MODULE$;

  public static {};
    Code:
       0: new           #2                  // class scalaz/syntax/apply$
       3: dup
       4: invokespecial #23                 // Method "<init>":()V
       7: putstatic     #25                 // Field MODULE$:Lscalaz/syntax/apply$;
      10: getstatic     #25                 // Field MODULE$:Lscalaz/syntax/apply$;
      13: pop
      14: getstatic     #25                 // Field MODULE$:Lscalaz/syntax/apply$;
      17: pop
      18: getstatic     #25                 // Field MODULE$:Lscalaz/syntax/apply$;
      21: pop
      22: getstatic     #25                 // Field MODULE$:Lscalaz/syntax/apply$;
      25: pop
      26: getstatic     #25                 // Field MODULE$:Lscalaz/syntax/apply$;
      29: pop
      30: getstatic     #25                 // Field MODULE$:Lscalaz/syntax/apply$;
      33: pop
      34: return

  public scalaz.syntax.InvariantFunctorOps ToInvariantFunctorOps(java.lang.Object, scalaz.InvariantFunctor);
    Code:
       0: aload_0
       1: aload_1
       2: aload_2
       3: invokestatic  #35                 // InterfaceMethod scalaz/syntax/ToInvariantFunctorOps0.ToInvariantFunctorOps$:(Lscalaz/syntax/ToInvariantFunctorOps0;Ljava/lang/Object;Lscalaz/InvariantFunctor;)Lscalaz/syntax/InvariantFunctorOps;
       6: areturn

  public <FA> scalaz.syntax.InvariantFunctorOps<java.lang.Object, java.lang.Object> ToInvariantFunctorOpsUnapply(FA, scalaz.Unapply<scalaz.Apply, FA>);
    Code:
       0: aload_0
       1: aload_1
       2: aload_2
       3: invokestatic  #47                 // InterfaceMethod scalaz/syntax/ToInvariantFunctorOpsU.ToInvariantFunctorOpsUnapply$:(Lscalaz/syntax/ToInvariantFunctorOpsU;Ljava/lang/Object;Lscalaz/Unapply;)Lscalaz/syntax/InvariantFunctorOps;
       6: areturn

  public scalaz.syntax.FunctorOps ToFunctorOps(java.lang.Object, scalaz.Functor);
    Code:
       0: aload_0
       1: aload_1
       2: aload_2
       3: invokestatic  #54                 // InterfaceMethod scalaz/syntax/ToFunctorOps0.ToFunctorOps$:(Lscalaz/syntax/ToFunctorOps0;Ljava/lang/Object;Lscalaz/Functor;)Lscalaz/syntax/FunctorOps;
       6: areturn

  public <F$, A, B> scalaz.syntax.ToFunctorOps0<scalaz.Apply>.LiftV<F$, A, B> ToLiftV(scala.Function1<A, B>);
    Code:
       0: aload_0
       1: aload_1
       2: invokestatic  #62                 // InterfaceMethod scalaz/syntax/ToFunctorOps0.ToLiftV$:(Lscalaz/syntax/ToFunctorOps0;Lscala/Function1;)Lscalaz/syntax/ToFunctorOps0$LiftV;
       5: areturn

  public <A> scalaz.syntax.ToFunctorOps0<scalaz.Apply>.FunctorIdV<A> ToFunctorIdV(A);
    Code:
       0: aload_0
       1: aload_1
       2: invokestatic  #70                 // InterfaceMethod scalaz/syntax/ToFunctorOps0.ToFunctorIdV$:(Lscalaz/syntax/ToFunctorOps0;Ljava/lang/Object;)Lscalaz/syntax/ToFunctorOps0$FunctorIdV;
       5: areturn

  public <FA> scalaz.syntax.FunctorOps<java.lang.Object, java.lang.Object> ToFunctorOpsUnapply(FA, scalaz.Unapply<scalaz.Apply, FA>);
    Code:
       0: aload_0
       1: aload_1
       2: aload_2
       3: invokestatic  #79                 // InterfaceMethod scalaz/syntax/ToFunctorOpsU.ToFunctorOpsUnapply$:(Lscalaz/syntax/ToFunctorOpsU;Ljava/lang/Object;Lscalaz/Unapply;)Lscalaz/syntax/FunctorOps;
       6: areturn

  public <F, A> scalaz.syntax.ApplyOps<F, A> ToApplyOps(F, scalaz.Apply<F>);
    Code:
       0: aload_0
       1: aload_1
       2: aload_2
       3: invokestatic  #88                 // InterfaceMethod scalaz/syntax/ToApplyOps0.ToApplyOps$:(Lscalaz/syntax/ToApplyOps0;Ljava/lang/Object;Lscalaz/Apply;)Lscalaz/syntax/ApplyOps;
       6: areturn

  public <F, A, B, C> F $up(scala.Function0<F>, scala.Function0<F>, scala.Function2<A, B, C>, scalaz.Apply<F>);
    Code:
       0: aload_0
       1: aload_1
       2: aload_2
       3: aload_3
       4: aload         4
       6: invokestatic  #100                // InterfaceMethod scalaz/syntax/ToApplyOps0.$up$:(Lscalaz/syntax/ToApplyOps0;Lscala/Function0;Lscala/Function0;Lscala/Function2;Lscalaz/Apply;)Ljava/lang/Object;
       9: areturn

  public <F, A, B, C, D> F $up$up(scala.Function0<F>, scala.Function0<F>, scala.Function0<F>, scala.Function3<A, B, C, D>, scalaz.Apply<F>);
    Code:
       0: aload_0
       1: aload_1
       2: aload_2
       3: aload_3
       4: aload         4
       6: aload         5
       8: invokestatic  #110                // InterfaceMethod scalaz/syntax/ToApplyOps0.$up$up$:(Lscalaz/syntax/ToApplyOps0;Lscala/Function0;Lscala/Function0;Lscala/Function0;Lscala/Function3;Lscalaz/Apply;)Ljava/lang/Object;
      11: areturn

  public <F, A, B, C, D, E> F $up$up$up(scala.Function0<F>, scala.Function0<F>, scala.Function0<F>, scala.Function0<F>, scala.Function4<A, B, C, D, E>, scalaz.Apply<F>);
    Code:
       0: aload_0
       1: aload_1
       2: aload_2
       3: aload_3
       4: aload         4
       6: aload         5
       8: aload         6
      10: invokestatic  #119                // InterfaceMethod scalaz/syntax/ToApplyOps0.$up$up$up$:(Lscalaz/syntax/ToApplyOps0;Lscala/Function0;Lscala/Function0;Lscala/Function0;Lscala/Function0;Lscala/Function4;Lscalaz/Apply;)Ljava/lang/Object;
      13: areturn

  public <F, A, B, C, D, E, I> F $up$up$up$up(scala.Function0<F>, scala.Function0<F>, scala.Function0<F>, scala.Function0<F>, scala.Function0<F>, scala.Function5<A, B, C, D, E, I>, scalaz.Apply<F>);
    Code:
       0: aload_0
       1: aload_1
       2: aload_2
       3: aload_3
       4: aload         4
       6: aload         5
       8: aload         6
      10: aload         7
      12: invokestatic  #128                // InterfaceMethod scalaz/syntax/ToApplyOps0.$up$up$up$up$:(Lscalaz/syntax/ToApplyOps0;Lscala/Function0;Lscala/Function0;Lscala/Function0;Lscala/Function0;Lscala/Function0;Lscala/Function5;Lscalaz/Apply;)Ljava/lang/Object;
      15: areturn

  public <F, A, B, C, D, E, I, J> F $up$up$up$up$up(scala.Function0<F>, scala.Function0<F>, scala.Function0<F>, scala.Function0<F>, scala.Function0<F>, scala.Function0<F>, scala.Function6<A, B, C, D, E, I, J>, scalaz.Apply<F>);
    Code:
       0: aload_0
       1: aload_1
       2: aload_2
       3: aload_3
       4: aload         4
       6: aload         5
       8: aload         6
      10: aload         7
      12: aload         8
      14: invokestatic  #137                // InterfaceMethod scalaz/syntax/ToApplyOps0.$up$up$up$up$up$:(Lscalaz/syntax/ToApplyOps0;Lscala/Function0;Lscala/Function0;Lscala/Function0;Lscala/Function0;Lscala/Function0;Lscala/Function0;Lscala/Function6;Lscalaz/Apply;)Ljava/lang/Object;
      17: areturn

  public <F, A, B, C, D, E, I, J, K> F $up$up$up$up$up$up(scala.Function0<F>, scala.Function0<F>, scala.Function0<F>, scala.Function0<F>, scala.Function0<F>, scala.Function0<F>, scala.Function0<F>, scala.Function7<A, B, C, D, E, I, J, K>, scalaz.Apply<F>);
    Code:
       0: aload_0
       1: aload_1
       2: aload_2
       3: aload_3
       4: aload         4
       6: aload         5
       8: aload         6
      10: aload         7
      12: aload         8
      14: aload         9
      16: invokestatic  #146                // InterfaceMethod scalaz/syntax/ToApplyOps0.$up$up$up$up$up$up$:(Lscalaz/syntax/ToApplyOps0;Lscala/Function0;Lscala/Function0;Lscala/Function0;Lscala/Function0;Lscala/Function0;Lscala/Function0;Lscala/Function0;Lscala/Function7;Lscalaz/Apply;)Ljava/lang/Object;
      19: areturn

  public <FA> scalaz.syntax.ApplyOps<java.lang.Object, java.lang.Object> ToApplyOpsUnapply(FA, scalaz.Unapply<scalaz.Apply, FA>);
    Code:
       0: aload_0
       1: aload_1
       2: aload_2
       3: invokestatic  #156                // InterfaceMethod scalaz/syntax/ToApplyOpsU.ToApplyOpsUnapply$:(Lscalaz/syntax/ToApplyOpsU;Ljava/lang/Object;Lscalaz/Unapply;)Lscalaz/syntax/ApplyOps;
       6: areturn

  private scalaz.syntax.apply$();
    Code:
       0: aload_0
       1: invokespecial #157                // Method java/lang/Object."<init>":()V
       4: return
}
