Compiled from "Syntax.scala"
public final class scalaz.syntax.arrow0$ implements scalaz.syntax.ToArrowOps0<scalaz.Arrow> {
  public static final scalaz.syntax.arrow0$ MODULE$;

  public static {};
    Code:
       0: new           #2                  // class scalaz/syntax/arrow0$
       3: dup
       4: invokespecial #15                 // Method "<init>":()V
       7: putstatic     #17                 // Field MODULE$:Lscalaz/syntax/arrow0$;
      10: getstatic     #17                 // Field MODULE$:Lscalaz/syntax/arrow0$;
      13: pop
      14: getstatic     #17                 // Field MODULE$:Lscalaz/syntax/arrow0$;
      17: pop
      18: return

  public <F, A, B> scalaz.syntax.ArrowOps<F, A, B> ToArrowOps(F, scalaz.Arrow<F>);
    Code:
       0: aload_0
       1: aload_1
       2: aload_2
       3: invokestatic  #26                 // InterfaceMethod scalaz/syntax/ToArrowOps0.ToArrowOps$:(Lscalaz/syntax/ToArrowOps0;Ljava/lang/Object;Lscalaz/Arrow;)Lscalaz/syntax/ArrowOps;
       6: areturn

  public <G, F, A, B> scalaz.syntax.ArrowOps<?, A, B> ToArrowVFromKleisliLike(F, scalaz.Arrow<?>);
    Code:
       0: aload_0
       1: aload_1
       2: aload_2
       3: invokestatic  #34                 // InterfaceMethod scalaz/syntax/ToArrowOps0.ToArrowVFromKleisliLike$:(Lscalaz/syntax/ToArrowOps0;Ljava/lang/Object;Lscalaz/Arrow;)Lscalaz/syntax/ArrowOps;
       6: areturn

  public <FA> scalaz.syntax.ArrowOps<java.lang.Object, java.lang.Object, java.lang.Object> ToArrowOpsUnapply(FA, scalaz.Unapply2<scalaz.Arrow, FA>);
    Code:
       0: aload_0
       1: aload_1
       2: aload_2
       3: invokestatic  #43                 // InterfaceMethod scalaz/syntax/ToArrowOpsU.ToArrowOpsUnapply$:(Lscalaz/syntax/ToArrowOpsU;Ljava/lang/Object;Lscalaz/Unapply2;)Lscalaz/syntax/ArrowOps;
       6: areturn

  private scalaz.syntax.arrow0$();
    Code:
       0: aload_0
       1: invokespecial #45                 // Method java/lang/Object."<init>":()V
       4: return
}
