Compiled from "Syntax.scala"
public final class scalaz.syntax.comonad0$ implements scalaz.syntax.ToComonadOps0<scalaz.Comonad> {
  public static final scalaz.syntax.comonad0$ MODULE$;

  public static {};
    Code:
       0: new           #2                  // class scalaz/syntax/comonad0$
       3: dup
       4: invokespecial #15                 // Method "<init>":()V
       7: putstatic     #17                 // Field MODULE$:Lscalaz/syntax/comonad0$;
      10: getstatic     #17                 // Field MODULE$:Lscalaz/syntax/comonad0$;
      13: pop
      14: getstatic     #17                 // Field MODULE$:Lscalaz/syntax/comonad0$;
      17: pop
      18: return

  public <F, A> scalaz.syntax.ComonadOps<F, A> ToComonadOps(F, scalaz.Comonad<F>);
    Code:
       0: aload_0
       1: aload_1
       2: aload_2
       3: invokestatic  #26                 // InterfaceMethod scalaz/syntax/ToComonadOps0.ToComonadOps$:(Lscalaz/syntax/ToComonadOps0;Ljava/lang/Object;Lscalaz/Comonad;)Lscalaz/syntax/ComonadOps;
       6: areturn

  public <FA> scalaz.syntax.ComonadOps<java.lang.Object, java.lang.Object> ToComonadOpsUnapply(FA, scalaz.Unapply<scalaz.Comonad, FA>);
    Code:
       0: aload_0
       1: aload_1
       2: aload_2
       3: invokestatic  #38                 // InterfaceMethod scalaz/syntax/ToComonadOpsU.ToComonadOpsUnapply$:(Lscalaz/syntax/ToComonadOpsU;Ljava/lang/Object;Lscalaz/Unapply;)Lscalaz/syntax/ComonadOps;
       6: areturn

  private scalaz.syntax.comonad0$();
    Code:
       0: aload_0
       1: invokespecial #40                 // Method java/lang/Object."<init>":()V
       4: return
}
