Compiled from "ComposeSyntax.scala"
public interface scalaz.syntax.ComposeSyntax<F> {
  public static scalaz.syntax.ComposeOps ToComposeOps$(scalaz.syntax.ComposeSyntax, java.lang.Object);
    Code:
       0: aload_0
       1: aload_1
       2: invokespecial #17                 // InterfaceMethod ToComposeOps:(Ljava/lang/Object;)Lscalaz/syntax/ComposeOps;
       5: areturn

  public default <A, B> scalaz.syntax.ComposeOps<F, A, B> ToComposeOps(F);
    Code:
       0: new           #22                 // class scalaz/syntax/ComposeOps
       3: dup
       4: aload_1
       5: aload_0
       6: invokeinterface #26,  1           // InterfaceMethod F:()Lscalaz/Compose;
      11: invokespecial #30                 // Method scalaz/syntax/ComposeOps."<init>":(Ljava/lang/Object;Lscalaz/Compose;)V
      14: areturn

  public abstract scalaz.Compose<F> F();

  public static void $init$(scalaz.syntax.ComposeSyntax);
    Code:
       0: return
}
