Compiled from "Syntax.scala"
public final class scalaz.syntax.contravariant0 {
  public static <F, A> scalaz.syntax.ContravariantOps<F, A> ToContravariantOps(F, scalaz.Contravariant<F>);
    Code:
       0: getstatic     #19                 // Field scalaz/syntax/contravariant0$.MODULE$:Lscalaz/syntax/contravariant0$;
       3: aload_0
       4: aload_1
       5: invokevirtual #21                 // Method scalaz/syntax/contravariant0$.ToContravariantOps:(Ljava/lang/Object;Lscalaz/Contravariant;)Lscalaz/syntax/ContravariantOps;
       8: areturn

  public static <FA> scalaz.syntax.ContravariantOps<java.lang.Object, java.lang.Object> ToContravariantOpsUnapply(FA, scalaz.Unapply<scalaz.Contravariant, FA>);
    Code:
       0: getstatic     #19                 // Field scalaz/syntax/contravariant0$.MODULE$:Lscalaz/syntax/contravariant0$;
       3: aload_0
       4: aload_1
       5: invokevirtual #28                 // Method scalaz/syntax/contravariant0$.ToContravariantOpsUnapply:(Ljava/lang/Object;Lscalaz/Unapply;)Lscalaz/syntax/ContravariantOps;
       8: areturn
}
