Compiled from "Syntax.scala"
public final class scalaz.syntax.monadError0$ implements scalaz.syntax.ToMonadErrorOps0<scalaz.MonadError> {
  public static final scalaz.syntax.monadError0$ MODULE$;

  public static {};
    Code:
       0: new           #2                  // class scalaz/syntax/monadError0$
       3: dup
       4: invokespecial #15                 // Method "<init>":()V
       7: putstatic     #17                 // Field MODULE$:Lscalaz/syntax/monadError0$;
      10: getstatic     #17                 // Field MODULE$:Lscalaz/syntax/monadError0$;
      13: pop
      14: return

  public <F, S, A> scalaz.syntax.MonadErrorOps<F, S, A> ToMonadErrorOps(F, scalaz.MonadError<F, S>);
    Code:
       0: aload_0
       1: aload_1
       2: aload_2
       3: invokestatic  #26                 // InterfaceMethod scalaz/syntax/ToMonadErrorOps0.ToMonadErrorOps$:(Lscalaz/syntax/ToMonadErrorOps0;Ljava/lang/Object;Lscalaz/MonadError;)Lscalaz/syntax/MonadErrorOps;
       6: areturn

  public <E> E ToMonadErrorIdOps(E);
    Code:
       0: aload_0
       1: aload_1
       2: invokestatic  #36                 // InterfaceMethod scalaz/syntax/ToMonadErrorOps0.ToMonadErrorIdOps$:(Lscalaz/syntax/ToMonadErrorOps0;Ljava/lang/Object;)Ljava/lang/Object;
       5: areturn

  private scalaz.syntax.monadError0$();
    Code:
       0: aload_0
       1: invokespecial #37                 // Method java/lang/Object."<init>":()V
       4: return
}
