Compiled from "Syntax.scala"
public final class scalaz.syntax.profunctor {
  public static <G, F, A, B> scalaz.syntax.ProfunctorOps<?, A, B> ToProfunctorVFromKleisliLike(F, scalaz.Profunctor<?>);
    Code:
       0: getstatic     #19                 // Field scalaz/syntax/profunctor$.MODULE$:Lscalaz/syntax/profunctor$;
       3: aload_0
       4: aload_1
       5: invokevirtual #21                 // Method scalaz/syntax/profunctor$.ToProfunctorVFromKleisliLike:(Ljava/lang/Object;Lscalaz/Profunctor;)Lscalaz/syntax/ProfunctorOps;
       8: areturn

  public static <F, A, B> scalaz.syntax.ProfunctorOps<F, A, B> ToProfunctorOps(F, scalaz.Profunctor<F>);
    Code:
       0: getstatic     #19                 // Field scalaz/syntax/profunctor$.MODULE$:Lscalaz/syntax/profunctor$;
       3: aload_0
       4: aload_1
       5: invokevirtual #27                 // Method scalaz/syntax/profunctor$.ToProfunctorOps:(Ljava/lang/Object;Lscalaz/Profunctor;)Lscalaz/syntax/ProfunctorOps;
       8: areturn

  public static <FA> scalaz.syntax.ProfunctorOps<java.lang.Object, java.lang.Object, java.lang.Object> ToProfunctorOpsUnapply(FA, scalaz.Unapply2<scalaz.Profunctor, FA>);
    Code:
       0: getstatic     #19                 // Field scalaz/syntax/profunctor$.MODULE$:Lscalaz/syntax/profunctor$;
       3: aload_0
       4: aload_1
       5: invokevirtual #32                 // Method scalaz/syntax/profunctor$.ToProfunctorOpsUnapply:(Ljava/lang/Object;Lscalaz/Unapply2;)Lscalaz/syntax/ProfunctorOps;
       8: areturn
}
