Compiled from "FunctorSyntax.scala"
public final class scalaz.syntax.ToFunctorOps0$$anon$2 implements scalaz.syntax.ToFunctorOps0<TC>.FunctorIdV<A> {
  private final scalaz.syntax.ToFunctorOps0 $outer;

  private final java.lang.Object v$2;

  public <F, B> F mapply(F, TC);
    Code:
       0: aload_0
       1: aload_1
       2: aload_2
       3: invokestatic  #27                 // InterfaceMethod scalaz/syntax/ToFunctorOps0$FunctorIdV.mapply$:(Lscalaz/syntax/ToFunctorOps0$FunctorIdV;Ljava/lang/Object;Lscalaz/Functor;)Ljava/lang/Object;
       6: areturn

  public A self();
    Code:
       0: aload_0
       1: getfield      #35                 // Field v$2:Ljava/lang/Object;
       4: areturn

  public scalaz.syntax.ToFunctorOps0 scalaz$syntax$ToFunctorOps0$FunctorIdV$$$outer();
    Code:
       0: aload_0
       1: getfield      #39                 // Field $outer:Lscalaz/syntax/ToFunctorOps0;
       4: areturn

  public scalaz.syntax.ToFunctorOps0$$anon$2(scalaz.syntax.ToFunctorOps0, java.lang.Object);
    Code:
       0: aload_1
       1: ifnonnull     6
       4: aconst_null
       5: athrow
       6: aload_0
       7: aload_1
       8: putfield      #39                 // Field $outer:Lscalaz/syntax/ToFunctorOps0;
      11: aload_0
      12: aload_2
      13: putfield      #35                 // Field v$2:Ljava/lang/Object;
      16: aload_0
      17: invokespecial #44                 // Method java/lang/Object."<init>":()V
      20: return
}
