Compiled from "PlusEmptySyntax.scala"
public interface scalaz.syntax.ToPlusEmptyOps0<TC extends scalaz.PlusEmpty<java.lang.Object>> extends scalaz.syntax.ToPlusEmptyOpsU<TC> {
  public static scalaz.syntax.PlusEmptyOps ToPlusEmptyOps$(scalaz.syntax.ToPlusEmptyOps0, java.lang.Object, scalaz.PlusEmpty);
    Code:
       0: aload_0
       1: aload_1
       2: aload_2
       3: invokespecial #20                 // InterfaceMethod ToPlusEmptyOps:(Ljava/lang/Object;Lscalaz/PlusEmpty;)Lscalaz/syntax/PlusEmptyOps;
       6: areturn

  public default <F, A> scalaz.syntax.PlusEmptyOps<F, A> ToPlusEmptyOps(F, TC);
    Code:
       0: new           #26                 // class scalaz/syntax/PlusEmptyOps
       3: dup
       4: aload_1
       5: aload_2
       6: invokespecial #30                 // Method scalaz/syntax/PlusEmptyOps."<init>":(Ljava/lang/Object;Lscalaz/PlusEmpty;)V
       9: areturn

  public static java.lang.Object mempty$(scalaz.syntax.ToPlusEmptyOps0, scalaz.PlusEmpty);
    Code:
       0: aload_0
       1: aload_1
       2: invokespecial #38                 // InterfaceMethod mempty:(Lscalaz/PlusEmpty;)Ljava/lang/Object;
       5: areturn

  public default <F, A> F mempty(scalaz.PlusEmpty<F>);
    Code:
       0: aload_1
       1: invokeinterface #45,  1           // InterfaceMethod scalaz/PlusEmpty.empty:()Ljava/lang/Object;
       6: areturn

  public static void $init$(scalaz.syntax.ToPlusEmptyOps0);
    Code:
       0: return
}
