Compiled from "Traverse1Syntax.scala"
public interface scalaz.syntax.Traverse1Syntax<F> extends scalaz.syntax.TraverseSyntax<F>, scalaz.syntax.Foldable1Syntax<F> {
  public static scalaz.syntax.Traverse1Ops ToTraverse1Ops$(scalaz.syntax.Traverse1Syntax, java.lang.Object);
    Code:
       0: aload_0
       1: aload_1
       2: invokespecial #21                 // InterfaceMethod ToTraverse1Ops:(Ljava/lang/Object;)Lscalaz/syntax/Traverse1Ops;
       5: areturn

  public default <A> scalaz.syntax.Traverse1Ops<F, A> ToTraverse1Ops(F);
    Code:
       0: new           #26                 // class scalaz/syntax/Traverse1Ops
       3: dup
       4: aload_1
       5: aload_0
       6: invokeinterface #30,  1           // InterfaceMethod F:()Lscalaz/Traverse1;
      11: invokespecial #34                 // Method scalaz/syntax/Traverse1Ops."<init>":(Ljava/lang/Object;Lscalaz/Traverse1;)V
      14: areturn

  public abstract scalaz.Traverse1<F> F();

  public static void $init$(scalaz.syntax.Traverse1Syntax);
    Code:
       0: return
}
