Compiled from "Syntax.scala"
public final class scalaz.syntax.unzip0$ implements scalaz.syntax.ToUnzipOps0<scalaz.Unzip> {
  public static final scalaz.syntax.unzip0$ MODULE$;

  public static {};
    Code:
       0: new           #2                  // class scalaz/syntax/unzip0$
       3: dup
       4: invokespecial #18                 // Method "<init>":()V
       7: putstatic     #20                 // Field MODULE$:Lscalaz/syntax/unzip0$;
      10: getstatic     #20                 // Field MODULE$:Lscalaz/syntax/unzip0$;
      13: pop
      14: getstatic     #20                 // Field MODULE$:Lscalaz/syntax/unzip0$;
      17: pop
      18: return

  public <F, A> scalaz.syntax.UnzipOps<F, A> ToUnzipOps(F, scalaz.Unzip<F>);
    Code:
       0: aload_0
       1: aload_1
       2: aload_2
       3: invokestatic  #29                 // InterfaceMethod scalaz/syntax/ToUnzipOps0.ToUnzipOps$:(Lscalaz/syntax/ToUnzipOps0;Ljava/lang/Object;Lscalaz/Unzip;)Lscalaz/syntax/UnzipOps;
       6: areturn

  public <F, A, B> scalaz.syntax.ToUnzipOps0<scalaz.Unzip>.UnzipPairOps<F, A, B> ToUnzipPairOps(F, scalaz.Unzip<F>);
    Code:
       0: aload_0
       1: aload_1
       2: aload_2
       3: invokestatic  #39                 // InterfaceMethod scalaz/syntax/ToUnzipOps0.ToUnzipPairOps$:(Lscalaz/syntax/ToUnzipOps0;Ljava/lang/Object;Lscalaz/Unzip;)Lscalaz/syntax/ToUnzipOps0$UnzipPairOps;
       6: areturn

  public <FA> scalaz.syntax.UnzipOps<java.lang.Object, java.lang.Object> ToUnzipOpsUnapply(FA, scalaz.Unapply<scalaz.Unzip, FA>);
    Code:
       0: aload_0
       1: aload_1
       2: aload_2
       3: invokestatic  #48                 // InterfaceMethod scalaz/syntax/ToUnzipOpsU.ToUnzipOpsUnapply$:(Lscalaz/syntax/ToUnzipOpsU;Ljava/lang/Object;Lscalaz/Unapply;)Lscalaz/syntax/UnzipOps;
       6: areturn

  private scalaz.syntax.unzip0$();
    Code:
       0: aload_0
       1: invokespecial #50                 // Method java/lang/Object."<init>":()V
       4: return
}
