Compiled from "CarbonRealmServiceComponent.java"
public class org.wso2.carbon.tomcat.ext.internal.CarbonRealmServiceComponent {
  private static org.apache.commons.logging.Log log;

  public org.wso2.carbon.tomcat.ext.internal.CarbonRealmServiceComponent();
    Code:
       0: aload_0
       1: invokespecial #1                  // Method java/lang/Object."<init>":()V
       4: return

  protected void setRealmService(org.wso2.carbon.user.core.service.RealmService);
    Code:
       0: aload_1
       1: invokestatic  #2                  // Method org/wso2/carbon/tomcat/ext/internal/CarbonRealmServiceHolder.setRealmService:(Lorg/wso2/carbon/user/core/service/RealmService;)V
       4: getstatic     #3                  // Field log:Lorg/apache/commons/logging/Log;
       7: invokeinterface #4,  1            // InterfaceMethod org/apache/commons/logging/Log.isDebugEnabled:()Z
      12: ifeq          42
      15: getstatic     #3                  // Field log:Lorg/apache/commons/logging/Log;
      18: new           #5                  // class java/lang/StringBuilder
      21: dup
      22: invokespecial #6                  // Method java/lang/StringBuilder."<init>":()V
      25: aload_1
      26: invokevirtual #7                  // Method java/lang/StringBuilder.append:(Ljava/lang/Object;)Ljava/lang/StringBuilder;
      29: ldc           #8                  // String is being set
      31: invokevirtual #9                  // Method java/lang/StringBuilder.append:(Ljava/lang/String;)Ljava/lang/StringBuilder;
      34: invokevirtual #10                 // Method java/lang/StringBuilder.toString:()Ljava/lang/String;
      37: invokeinterface #11,  2           // InterfaceMethod org/apache/commons/logging/Log.debug:(Ljava/lang/Object;)V
      42: return

  protected void unsetRealmService(org.wso2.carbon.user.core.service.RealmService);
    Code:
       0: aconst_null
       1: invokestatic  #2                  // Method org/wso2/carbon/tomcat/ext/internal/CarbonRealmServiceHolder.setRealmService:(Lorg/wso2/carbon/user/core/service/RealmService;)V
       4: getstatic     #3                  // Field log:Lorg/apache/commons/logging/Log;
       7: invokeinterface #4,  1            // InterfaceMethod org/apache/commons/logging/Log.isDebugEnabled:()Z
      12: ifeq          42
      15: getstatic     #3                  // Field log:Lorg/apache/commons/logging/Log;
      18: new           #5                  // class java/lang/StringBuilder
      21: dup
      22: invokespecial #6                  // Method java/lang/StringBuilder."<init>":()V
      25: aload_1
      26: invokevirtual #7                  // Method java/lang/StringBuilder.append:(Ljava/lang/Object;)Ljava/lang/StringBuilder;
      29: ldc           #12                 // String is being unset
      31: invokevirtual #9                  // Method java/lang/StringBuilder.append:(Ljava/lang/String;)Ljava/lang/StringBuilder;
      34: invokevirtual #10                 // Method java/lang/StringBuilder.toString:()Ljava/lang/String;
      37: invokeinterface #11,  2           // InterfaceMethod org/apache/commons/logging/Log.debug:(Ljava/lang/Object;)V
      42: return

  protected void setRegistryService(org.wso2.carbon.registry.core.service.RegistryService);
    Code:
       0: aload_1
       1: invokestatic  #13                 // Method org/wso2/carbon/tomcat/ext/internal/CarbonRealmServiceHolder.setRegistryService:(Lorg/wso2/carbon/registry/core/service/RegistryService;)V
       4: getstatic     #3                  // Field log:Lorg/apache/commons/logging/Log;
       7: invokeinterface #4,  1            // InterfaceMethod org/apache/commons/logging/Log.isDebugEnabled:()Z
      12: ifeq          42
      15: getstatic     #3                  // Field log:Lorg/apache/commons/logging/Log;
      18: new           #5                  // class java/lang/StringBuilder
      21: dup
      22: invokespecial #6                  // Method java/lang/StringBuilder."<init>":()V
      25: aload_1
      26: invokevirtual #7                  // Method java/lang/StringBuilder.append:(Ljava/lang/Object;)Ljava/lang/StringBuilder;
      29: ldc           #8                  // String is being set
      31: invokevirtual #9                  // Method java/lang/StringBuilder.append:(Ljava/lang/String;)Ljava/lang/StringBuilder;
      34: invokevirtual #10                 // Method java/lang/StringBuilder.toString:()Ljava/lang/String;
      37: invokeinterface #11,  2           // InterfaceMethod org/apache/commons/logging/Log.debug:(Ljava/lang/Object;)V
      42: return

  protected void unsetRegistryService(org.wso2.carbon.registry.core.service.RegistryService);
    Code:
       0: aconst_null
       1: invokestatic  #13                 // Method org/wso2/carbon/tomcat/ext/internal/CarbonRealmServiceHolder.setRegistryService:(Lorg/wso2/carbon/registry/core/service/RegistryService;)V
       4: getstatic     #3                  // Field log:Lorg/apache/commons/logging/Log;
       7: invokeinterface #4,  1            // InterfaceMethod org/apache/commons/logging/Log.isDebugEnabled:()Z
      12: ifeq          42
      15: getstatic     #3                  // Field log:Lorg/apache/commons/logging/Log;
      18: new           #5                  // class java/lang/StringBuilder
      21: dup
      22: invokespecial #6                  // Method java/lang/StringBuilder."<init>":()V
      25: aload_1
      26: invokevirtual #7                  // Method java/lang/StringBuilder.append:(Ljava/lang/Object;)Ljava/lang/StringBuilder;
      29: ldc           #12                 // String is being unset
      31: invokevirtual #9                  // Method java/lang/StringBuilder.append:(Ljava/lang/String;)Ljava/lang/StringBuilder;
      34: invokevirtual #10                 // Method java/lang/StringBuilder.toString:()Ljava/lang/String;
      37: invokeinterface #11,  2           // InterfaceMethod org/apache/commons/logging/Log.debug:(Ljava/lang/Object;)V
      42: return

  static {};
    Code:
       0: ldc           #14                 // class org/wso2/carbon/tomcat/ext/internal/CarbonRealmServiceComponent
       2: invokestatic  #15                 // Method org/apache/commons/logging/LogFactory.getLog:(Ljava/lang/Class;)Lorg/apache/commons/logging/Log;
       5: putstatic     #3                  // Field log:Lorg/apache/commons/logging/Log;
       8: return
}
