Compiled from "NewDirectoryOutputStreamException.java"
public class net.oneandone.sushi.fs.NewDirectoryOutputStreamException extends net.oneandone.sushi.fs.NewOutputStreamException {
  public net.oneandone.sushi.fs.NewDirectoryOutputStreamException(net.oneandone.sushi.fs.Node);
    Code:
       0: aload_0
       1: aload_1
       2: aconst_null
       3: invokespecial #1                  // Method "<init>":(Lnet/oneandone/sushi/fs/Node;Ljava/lang/Throwable;)V
       6: return

  public net.oneandone.sushi.fs.NewDirectoryOutputStreamException(net.oneandone.sushi.fs.Node, java.lang.Throwable);
    Code:
       0: aload_0
       1: aload_1
       2: ldc           #2                  // String cannot create OutputStream for directory
       4: aload_2
       5: invokespecial #3                  // Method net/oneandone/sushi/fs/NewOutputStreamException."<init>":(Lnet/oneandone/sushi/fs/Node;Ljava/lang/String;Ljava/lang/Throwable;)V
       8: return
}
