Compiled from "DeserializedMemberScope.kt"
public abstract class kotlin.reflect.jvm.internal.impl.serialization.deserialization.descriptors.DeserializedMemberScope extends kotlin.reflect.jvm.internal.impl.resolve.scopes.MemberScopeImpl {
  static final kotlin.reflect.KProperty[] $$delegatedProperties;

  private final java.util.Map<kotlin.reflect.jvm.internal.impl.name.Name, byte[]> functionProtosBytes;

  private final java.util.Map<kotlin.reflect.jvm.internal.impl.name.Name, byte[]> propertyProtosBytes;

  private final java.util.Map<kotlin.reflect.jvm.internal.impl.name.Name, byte[]> typeAliasBytes;

  private final kotlin.reflect.jvm.internal.impl.storage.MemoizedFunctionToNotNull<kotlin.reflect.jvm.internal.impl.name.Name, java.util.Collection<kotlin.reflect.jvm.internal.impl.descriptors.SimpleFunctionDescriptor>> functions;

  private final kotlin.reflect.jvm.internal.impl.storage.MemoizedFunctionToNotNull<kotlin.reflect.jvm.internal.impl.name.Name, java.util.Collection<kotlin.reflect.jvm.internal.impl.descriptors.PropertyDescriptor>> properties;

  private final kotlin.reflect.jvm.internal.impl.storage.MemoizedFunctionToNullable<kotlin.reflect.jvm.internal.impl.name.Name, kotlin.reflect.jvm.internal.impl.descriptors.TypeAliasDescriptor> typeAliasByName;

  private final kotlin.reflect.jvm.internal.impl.storage.NotNullLazyValue functionNamesLazy$delegate;

  private final kotlin.reflect.jvm.internal.impl.storage.NotNullLazyValue variableNamesLazy$delegate;

  private final kotlin.reflect.jvm.internal.impl.storage.NotNullLazyValue classNames$delegate;

  private final kotlin.reflect.jvm.internal.impl.serialization.deserialization.DeserializationContext c;

  static {};
    Code:
       0: iconst_3
       1: anewarray     #46                 // class kotlin/reflect/KProperty
       4: dup
       5: iconst_0
       6: new           #44                 // class kotlin/jvm/internal/PropertyReference1Impl
       9: dup
      10: ldc           #64                 // class kotlin/reflect/jvm/internal/impl/serialization/deserialization/descriptors/DeserializedMemberScope
      12: invokestatic  #112                // Method kotlin/jvm/internal/Reflection.getOrCreateKotlinClass:(Ljava/lang/Class;)Lkotlin/reflect/KClass;
      15: ldc           #8                  // String functionNamesLazy
      17: ldc           #11                 // String getFunctionNamesLazy()Ljava/util/Set;
      19: invokespecial #111                // Method kotlin/jvm/internal/PropertyReference1Impl."<init>":(Lkotlin/reflect/KDeclarationContainer;Ljava/lang/String;Ljava/lang/String;)V
      22: invokestatic  #113                // Method kotlin/jvm/internal/Reflection.property1:(Lkotlin/jvm/internal/PropertyReference1;)Lkotlin/reflect/KProperty1;
      25: checkcast     #46                 // class kotlin/reflect/KProperty
      28: aastore
      29: dup
      30: iconst_1
      31: new           #44                 // class kotlin/jvm/internal/PropertyReference1Impl
      34: dup
      35: ldc           #64                 // class kotlin/reflect/jvm/internal/impl/serialization/deserialization/descriptors/DeserializedMemberScope
      37: invokestatic  #112                // Method kotlin/jvm/internal/Reflection.getOrCreateKotlinClass:(Ljava/lang/Class;)Lkotlin/reflect/KClass;
      40: ldc           #20                 // String variableNamesLazy
      42: ldc           #12                 // String getVariableNamesLazy()Ljava/util/Set;
      44: invokespecial #111                // Method kotlin/jvm/internal/PropertyReference1Impl."<init>":(Lkotlin/reflect/KDeclarationContainer;Ljava/lang/String;Ljava/lang/String;)V
      47: invokestatic  #113                // Method kotlin/jvm/internal/Reflection.property1:(Lkotlin/jvm/internal/PropertyReference1;)Lkotlin/reflect/KProperty1;
      50: checkcast     #46                 // class kotlin/reflect/KProperty
      53: aastore
      54: dup
      55: iconst_2
      56: new           #44                 // class kotlin/jvm/internal/PropertyReference1Impl
      59: dup
      60: ldc           #64                 // class kotlin/reflect/jvm/internal/impl/serialization/deserialization/descriptors/DeserializedMemberScope
      62: invokestatic  #112                // Method kotlin/jvm/internal/Reflection.getOrCreateKotlinClass:(Ljava/lang/Class;)Lkotlin/reflect/KClass;
      65: ldc           #5                  // String classNames
      67: ldc           #10                 // String getClassNames$deserialization()Ljava/util/Set;
      69: invokespecial #111                // Method kotlin/jvm/internal/PropertyReference1Impl."<init>":(Lkotlin/reflect/KDeclarationContainer;Ljava/lang/String;Ljava/lang/String;)V
      72: invokestatic  #113                // Method kotlin/jvm/internal/Reflection.property1:(Lkotlin/jvm/internal/PropertyReference1;)Lkotlin/reflect/KProperty1;
      75: checkcast     #46                 // class kotlin/reflect/KProperty
      78: aastore
      79: putstatic     #84                 // Field $$delegatedProperties:[Lkotlin/reflect/KProperty;
      82: return

  private final java.util.Map<kotlin.reflect.jvm.internal.impl.name.Name, byte[]> packToByteArray(java.util.Map<kotlin.reflect.jvm.internal.impl.name.Name, ? extends java.util.Collection<? extends kotlin.reflect.jvm.internal.impl.protobuf.AbstractMessageLite>>);
    Code:
       0: aload_1
       1: astore_2
       2: aload_2
       3: astore_3
       4: new           #33                 // class java/util/LinkedHashMap
       7: dup
       8: aload_2
       9: invokeinterface #181,  1          // InterfaceMethod java/util/Map.size:()I
      14: invokestatic  #108                // Method kotlin/collections/MapsKt.mapCapacity:(I)I
      17: invokespecial #103                // Method java/util/LinkedHashMap."<init>":(I)V
      20: checkcast     #35                 // class java/util/Map
      23: astore        4
      25: aload_3
      26: invokeinterface #177,  1          // InterfaceMethod java/util/Map.entrySet:()Ljava/util/Set;
      31: checkcast     #27                 // class java/lang/Iterable
      34: astore        5
      36: aload         5
      38: invokeinterface #170,  1          // InterfaceMethod java/lang/Iterable.iterator:()Ljava/util/Iterator;
      43: astore        6
      45: aload         6
      47: invokeinterface #174,  1          // InterfaceMethod java/util/Iterator.hasNext:()Z
      52: ifeq          239
      55: aload         6
      57: invokeinterface #175,  1          // InterfaceMethod java/util/Iterator.next:()Ljava/lang/Object;
      62: astore        7
      64: aload         4
      66: aload         7
      68: checkcast     #36                 // class java/util/Map$Entry
      71: astore        8
      73: astore        9
      75: aload         8
      77: invokeinterface #182,  1          // InterfaceMethod java/util/Map$Entry.getKey:()Ljava/lang/Object;
      82: astore        10
      84: aload         9
      86: aload         10
      88: aload         7
      90: checkcast     #36                 // class java/util/Map$Entry
      93: astore        11
      95: astore        30
      97: astore        29
      99: new           #23                 // class java/io/ByteArrayOutputStream
     102: dup
     103: invokespecial #96                 // Method java/io/ByteArrayOutputStream."<init>":()V
     106: astore        12
     108: aload         11
     110: invokeinterface #183,  1          // InterfaceMethod java/util/Map$Entry.getValue:()Ljava/lang/Object;
     115: checkcast     #27                 // class java/lang/Iterable
     118: astore        13
     120: aload         13
     122: astore        14
     124: new           #29                 // class java/util/ArrayList
     127: dup
     128: aload         13
     130: bipush        10
     132: invokestatic  #104                // Method kotlin/collections/CollectionsKt.collectionSizeOrDefault:(Ljava/lang/Iterable;I)I
     135: invokespecial #100                // Method java/util/ArrayList."<init>":(I)V
     138: checkcast     #30                 // class java/util/Collection
     141: astore        15
     143: aload         14
     145: invokeinterface #170,  1          // InterfaceMethod java/lang/Iterable.iterator:()Ljava/util/Iterator;
     150: astore        16
     152: aload         16
     154: invokeinterface #174,  1          // InterfaceMethod java/util/Iterator.hasNext:()Z
     159: ifeq          210
     162: aload         16
     164: invokeinterface #175,  1          // InterfaceMethod java/util/Iterator.next:()Ljava/lang/Object;
     169: astore        17
     171: aload         15
     173: aload         17
     175: checkcast     #53                 // class kotlin/reflect/jvm/internal/impl/protobuf/AbstractMessageLite
     178: astore        18
     180: astore        19
     182: aload         18
     184: aload         12
     186: checkcast     #25                 // class java/io/OutputStream
     189: invokevirtual #118                // Method kotlin/reflect/jvm/internal/impl/protobuf/AbstractMessageLite.writeDelimitedTo:(Ljava/io/OutputStream;)V
     192: getstatic     #79                 // Field kotlin/Unit.INSTANCE:Lkotlin/Unit;
     195: astore        20
     197: aload         19
     199: aload         20
     201: invokeinterface #171,  2          // InterfaceMethod java/util/Collection.add:(Ljava/lang/Object;)Z
     206: pop
     207: goto          152
     210: aload         15
     212: checkcast     #34                 // class java/util/List
     215: pop
     216: aload         12
     218: invokevirtual #97                 // Method java/io/ByteArrayOutputStream.toByteArray:()[B
     221: nop
     222: astore        31
     224: aload         29
     226: aload         30
     228: aload         31
     230: invokeinterface #180,  3          // InterfaceMethod java/util/Map.put:(Ljava/lang/Object;Ljava/lang/Object;)Ljava/lang/Object;
     235: pop
     236: goto          45
     239: aload         4
     241: nop
     242: nop
     243: areturn

  private final java.util.Set<kotlin.reflect.jvm.internal.impl.name.Name> getFunctionNamesLazy();
    Code:
       0: aload_0
       1: getfield      #87                 // Field functionNamesLazy$delegate:Lkotlin/reflect/jvm/internal/impl/storage/NotNullLazyValue;
       4: aload_0
       5: getstatic     #84                 // Field $$delegatedProperties:[Lkotlin/reflect/KProperty;
       8: iconst_0
       9: aaload
      10: invokestatic  #165                // Method kotlin/reflect/jvm/internal/impl/storage/StorageKt.getValue:(Lkotlin/reflect/jvm/internal/impl/storage/NotNullLazyValue;Ljava/lang/Object;Lkotlin/reflect/KProperty;)Ljava/lang/Object;
      13: checkcast     #37                 // class java/util/Set
      16: areturn

  private final java.util.Set<kotlin.reflect.jvm.internal.impl.name.Name> getVariableNamesLazy();
    Code:
       0: aload_0
       1: getfield      #94                 // Field variableNamesLazy$delegate:Lkotlin/reflect/jvm/internal/impl/storage/NotNullLazyValue;
       4: aload_0
       5: getstatic     #84                 // Field $$delegatedProperties:[Lkotlin/reflect/KProperty;
       8: iconst_1
       9: aaload
      10: invokestatic  #165                // Method kotlin/reflect/jvm/internal/impl/storage/StorageKt.getValue:(Lkotlin/reflect/jvm/internal/impl/storage/NotNullLazyValue;Ljava/lang/Object;Lkotlin/reflect/KProperty;)Ljava/lang/Object;
      13: checkcast     #37                 // class java/util/Set
      16: areturn

  private final java.util.Set<kotlin.reflect.jvm.internal.impl.name.Name> getTypeAliasNames();
    Code:
       0: aload_0
       1: getfield      #93                 // Field typeAliasBytes:Ljava/util/Map;
       4: invokeinterface #179,  1          // InterfaceMethod java/util/Map.keySet:()Ljava/util/Set;
       9: areturn

  public final java.util.Set<kotlin.reflect.jvm.internal.impl.name.Name> getClassNames$deserialization();
    Code:
       0: aload_0
       1: getfield      #86                 // Field classNames$delegate:Lkotlin/reflect/jvm/internal/impl/storage/NotNullLazyValue;
       4: aload_0
       5: getstatic     #84                 // Field $$delegatedProperties:[Lkotlin/reflect/KProperty;
       8: iconst_2
       9: aaload
      10: invokestatic  #165                // Method kotlin/reflect/jvm/internal/impl/storage/StorageKt.getValue:(Lkotlin/reflect/jvm/internal/impl/storage/NotNullLazyValue;Ljava/lang/Object;Lkotlin/reflect/KProperty;)Ljava/lang/Object;
      13: checkcast     #37                 // class java/util/Set
      16: areturn

  public java.util.Set<kotlin.reflect.jvm.internal.impl.name.Name> getFunctionNames();
    Code:
       0: aload_0
       1: invokespecial #151                // Method getFunctionNamesLazy:()Ljava/util/Set;
       4: areturn

  public java.util.Set<kotlin.reflect.jvm.internal.impl.name.Name> getVariableNames();
    Code:
       0: aload_0
       1: invokespecial #154                // Method getVariableNamesLazy:()Ljava/util/Set;
       4: areturn

  private final java.util.Collection<kotlin.reflect.jvm.internal.impl.descriptors.SimpleFunctionDescriptor> computeFunctions(kotlin.reflect.jvm.internal.impl.name.Name);
    Code:
       0: aload_0
       1: astore_2
       2: aload_0
       3: getfield      #88                 // Field functionProtosBytes:Ljava/util/Map;
       6: astore_3
       7: getstatic     #80                 // Field kotlin/reflect/jvm/internal/impl/metadata/ProtoBuf$Function.PARSER:Lkotlin/reflect/jvm/internal/impl/protobuf/Parser;
      10: dup
      11: ldc           #2                  // String ProtoBuf.Function.PARSER
      13: invokestatic  #109                // Method kotlin/jvm/internal/Intrinsics.checkExpressionValueIsNotNull:(Ljava/lang/Object;Ljava/lang/String;)V
      16: astore        4
      18: nop
      19: aload_2
      20: astore        5
      22: aload_3
      23: aload_1
      24: invokeinterface #178,  2          // InterfaceMethod java/util/Map.get:(Ljava/lang/Object;)Ljava/lang/Object;
      29: checkcast     #21                 // class "[B"
      32: dup
      33: ifnull        85
      36: astore        6
      38: aload         6
      40: astore        7
      42: new           #22                 // class java/io/ByteArrayInputStream
      45: dup
      46: aload         7
      48: invokespecial #95                 // Method java/io/ByteArrayInputStream."<init>":([B)V
      51: astore        8
      53: new           #66                 // class kotlin/reflect/jvm/internal/impl/serialization/deserialization/descriptors/DeserializedMemberScope$computeDescriptors$$inlined$let$lambda$1
      56: dup
      57: aload         8
      59: aload_2
      60: aload         4
      62: invokespecial #158                // Method kotlin/reflect/jvm/internal/impl/serialization/deserialization/descriptors/DeserializedMemberScope$computeDescriptors$$inlined$let$lambda$1."<init>":(Ljava/io/ByteArrayInputStream;Lkotlin/reflect/jvm/internal/impl/serialization/deserialization/descriptors/DeserializedMemberScope;Lkotlin/reflect/jvm/internal/impl/protobuf/Parser;)V
      65: checkcast     #41                 // class kotlin/jvm/functions/Function0
      68: invokestatic  #168                // Method kotlin/sequences/SequencesKt.generateSequence:(Lkotlin/jvm/functions/Function0;)Lkotlin/sequences/Sequence;
      71: invokestatic  #169                // Method kotlin/sequences/SequencesKt.toList:(Lkotlin/sequences/Sequence;)Ljava/util/List;
      74: nop
      75: dup
      76: ifnull        85
      79: checkcast     #30                 // class java/util/Collection
      82: goto          92
      85: pop
      86: invokestatic  #105                // Method kotlin/collections/CollectionsKt.emptyList:()Ljava/util/List;
      89: checkcast     #30                 // class java/util/Collection
      92: astore        6
      94: nop
      95: aload         6
      97: checkcast     #27                 // class java/lang/Iterable
     100: astore        7
     102: new           #29                 // class java/util/ArrayList
     105: dup
     106: invokespecial #99                 // Method java/util/ArrayList."<init>":()V
     109: checkcast     #30                 // class java/util/Collection
     112: astore        8
     114: nop
     115: aload         7
     117: invokeinterface #170,  1          // InterfaceMethod java/lang/Iterable.iterator:()Ljava/util/Iterator;
     122: astore        9
     124: aload         9
     126: invokeinterface #174,  1          // InterfaceMethod java/util/Iterator.hasNext:()Z
     131: ifeq          187
     134: aload         9
     136: invokeinterface #175,  1          // InterfaceMethod java/util/Iterator.next:()Ljava/lang/Object;
     141: astore        10
     143: aload         8
     145: aload         10
     147: checkcast     #49                 // class kotlin/reflect/jvm/internal/impl/metadata/ProtoBuf$Function
     150: astore        11
     152: astore        17
     154: aload_0
     155: getfield      #85                 // Field c:Lkotlin/reflect/jvm/internal/impl/serialization/deserialization/DeserializationContext;
     158: invokevirtual #130                // Method kotlin/reflect/jvm/internal/impl/serialization/deserialization/DeserializationContext.getMemberDeserializer:()Lkotlin/reflect/jvm/internal/impl/serialization/deserialization/MemberDeserializer;
     161: aload         11
     163: dup
     164: ldc           #13                 // String it
     166: invokestatic  #109                // Method kotlin/jvm/internal/Intrinsics.checkExpressionValueIsNotNull:(Ljava/lang/Object;Ljava/lang/String;)V
     169: invokevirtual #133                // Method kotlin/reflect/jvm/internal/impl/serialization/deserialization/MemberDeserializer.loadFunction:(Lkotlin/reflect/jvm/internal/impl/metadata/ProtoBuf$Function;)Lkotlin/reflect/jvm/internal/impl/descriptors/SimpleFunctionDescriptor;
     172: astore        18
     174: aload         17
     176: aload         18
     178: invokeinterface #171,  2          // InterfaceMethod java/util/Collection.add:(Ljava/lang/Object;)Z
     183: pop
     184: goto          124
     187: aload         8
     189: checkcast     #29                 // class java/util/ArrayList
     192: astore        13
     194: aload         13
     196: checkcast     #30                 // class java/util/Collection
     199: astore        11
     201: aload_0
     202: aload_1
     203: aload         11
     205: invokevirtual #141                // Method computeNonDeclaredFunctions:(Lkotlin/reflect/jvm/internal/impl/name/Name;Ljava/util/Collection;)V
     208: aload         13
     210: invokestatic  #167                // Method kotlin/reflect/jvm/internal/impl/utils/CollectionsKt.compact:(Ljava/util/ArrayList;)Ljava/util/List;
     213: checkcast     #30                 // class java/util/Collection
     216: nop
     217: areturn

  protected void computeNonDeclaredFunctions(kotlin.reflect.jvm.internal.impl.name.Name, java.util.Collection<kotlin.reflect.jvm.internal.impl.descriptors.SimpleFunctionDescriptor>);
    Code:
       0: aload_1
       1: ldc           #16                 // String name
       3: invokestatic  #110                // Method kotlin/jvm/internal/Intrinsics.checkParameterIsNotNull:(Ljava/lang/Object;Ljava/lang/String;)V
       6: aload_2
       7: ldc           #9                  // String functions
       9: invokestatic  #110                // Method kotlin/jvm/internal/Intrinsics.checkParameterIsNotNull:(Ljava/lang/Object;Ljava/lang/String;)V
      12: return

  public java.util.Collection<kotlin.reflect.jvm.internal.impl.descriptors.SimpleFunctionDescriptor> getContributedFunctions(kotlin.reflect.jvm.internal.impl.name.Name, kotlin.reflect.jvm.internal.impl.incremental.components.LookupLocation);
    Code:
       0: aload_1
       1: ldc           #16                 // String name
       3: invokestatic  #110                // Method kotlin/jvm/internal/Intrinsics.checkParameterIsNotNull:(Ljava/lang/Object;Ljava/lang/String;)V
       6: aload_2
       7: ldc           #15                 // String location
       9: invokestatic  #110                // Method kotlin/jvm/internal/Intrinsics.checkParameterIsNotNull:(Ljava/lang/Object;Ljava/lang/String;)V
      12: aload_0
      13: invokevirtual #150                // Method getFunctionNames:()Ljava/util/Set;
      16: aload_1
      17: invokeinterface #184,  2          // InterfaceMethod java/util/Set.contains:(Ljava/lang/Object;)Z
      22: ifne          32
      25: invokestatic  #105                // Method kotlin/collections/CollectionsKt.emptyList:()Ljava/util/List;
      28: checkcast     #30                 // class java/util/Collection
      31: areturn
      32: aload_0
      33: getfield      #89                 // Field functions:Lkotlin/reflect/jvm/internal/impl/storage/MemoizedFunctionToNotNull;
      36: aload_1
      37: invokeinterface #188,  2          // InterfaceMethod kotlin/reflect/jvm/internal/impl/storage/MemoizedFunctionToNotNull.invoke:(Ljava/lang/Object;)Ljava/lang/Object;
      42: checkcast     #30                 // class java/util/Collection
      45: areturn

  private final java.util.Collection<kotlin.reflect.jvm.internal.impl.descriptors.PropertyDescriptor> computeProperties(kotlin.reflect.jvm.internal.impl.name.Name);
    Code:
       0: aload_0
       1: astore_2
       2: aload_0
       3: getfield      #91                 // Field propertyProtosBytes:Ljava/util/Map;
       6: astore_3
       7: getstatic     #81                 // Field kotlin/reflect/jvm/internal/impl/metadata/ProtoBuf$Property.PARSER:Lkotlin/reflect/jvm/internal/impl/protobuf/Parser;
      10: dup
      11: ldc           #3                  // String ProtoBuf.Property.PARSER
      13: invokestatic  #109                // Method kotlin/jvm/internal/Intrinsics.checkExpressionValueIsNotNull:(Ljava/lang/Object;Ljava/lang/String;)V
      16: astore        4
      18: nop
      19: aload_2
      20: astore        5
      22: aload_3
      23: aload_1
      24: invokeinterface #178,  2          // InterfaceMethod java/util/Map.get:(Ljava/lang/Object;)Ljava/lang/Object;
      29: checkcast     #21                 // class "[B"
      32: dup
      33: ifnull        85
      36: astore        6
      38: aload         6
      40: astore        7
      42: new           #22                 // class java/io/ByteArrayInputStream
      45: dup
      46: aload         7
      48: invokespecial #95                 // Method java/io/ByteArrayInputStream."<init>":([B)V
      51: astore        8
      53: new           #67                 // class kotlin/reflect/jvm/internal/impl/serialization/deserialization/descriptors/DeserializedMemberScope$computeDescriptors$$inlined$let$lambda$3
      56: dup
      57: aload         8
      59: aload_2
      60: aload         4
      62: invokespecial #159                // Method kotlin/reflect/jvm/internal/impl/serialization/deserialization/descriptors/DeserializedMemberScope$computeDescriptors$$inlined$let$lambda$3."<init>":(Ljava/io/ByteArrayInputStream;Lkotlin/reflect/jvm/internal/impl/serialization/deserialization/descriptors/DeserializedMemberScope;Lkotlin/reflect/jvm/internal/impl/protobuf/Parser;)V
      65: checkcast     #41                 // class kotlin/jvm/functions/Function0
      68: invokestatic  #168                // Method kotlin/sequences/SequencesKt.generateSequence:(Lkotlin/jvm/functions/Function0;)Lkotlin/sequences/Sequence;
      71: invokestatic  #169                // Method kotlin/sequences/SequencesKt.toList:(Lkotlin/sequences/Sequence;)Ljava/util/List;
      74: nop
      75: dup
      76: ifnull        85
      79: checkcast     #30                 // class java/util/Collection
      82: goto          92
      85: pop
      86: invokestatic  #105                // Method kotlin/collections/CollectionsKt.emptyList:()Ljava/util/List;
      89: checkcast     #30                 // class java/util/Collection
      92: astore        6
      94: nop
      95: aload         6
      97: checkcast     #27                 // class java/lang/Iterable
     100: astore        7
     102: new           #29                 // class java/util/ArrayList
     105: dup
     106: invokespecial #99                 // Method java/util/ArrayList."<init>":()V
     109: checkcast     #30                 // class java/util/Collection
     112: astore        8
     114: nop
     115: aload         7
     117: invokeinterface #170,  1          // InterfaceMethod java/lang/Iterable.iterator:()Ljava/util/Iterator;
     122: astore        9
     124: aload         9
     126: invokeinterface #174,  1          // InterfaceMethod java/util/Iterator.hasNext:()Z
     131: ifeq          187
     134: aload         9
     136: invokeinterface #175,  1          // InterfaceMethod java/util/Iterator.next:()Ljava/lang/Object;
     141: astore        10
     143: aload         8
     145: aload         10
     147: checkcast     #50                 // class kotlin/reflect/jvm/internal/impl/metadata/ProtoBuf$Property
     150: astore        11
     152: astore        17
     154: aload_0
     155: getfield      #85                 // Field c:Lkotlin/reflect/jvm/internal/impl/serialization/deserialization/DeserializationContext;
     158: invokevirtual #130                // Method kotlin/reflect/jvm/internal/impl/serialization/deserialization/DeserializationContext.getMemberDeserializer:()Lkotlin/reflect/jvm/internal/impl/serialization/deserialization/MemberDeserializer;
     161: aload         11
     163: dup
     164: ldc           #13                 // String it
     166: invokestatic  #109                // Method kotlin/jvm/internal/Intrinsics.checkExpressionValueIsNotNull:(Ljava/lang/Object;Ljava/lang/String;)V
     169: invokevirtual #134                // Method kotlin/reflect/jvm/internal/impl/serialization/deserialization/MemberDeserializer.loadProperty:(Lkotlin/reflect/jvm/internal/impl/metadata/ProtoBuf$Property;)Lkotlin/reflect/jvm/internal/impl/descriptors/PropertyDescriptor;
     172: astore        18
     174: aload         17
     176: aload         18
     178: invokeinterface #171,  2          // InterfaceMethod java/util/Collection.add:(Ljava/lang/Object;)Z
     183: pop
     184: goto          124
     187: aload         8
     189: checkcast     #29                 // class java/util/ArrayList
     192: astore        13
     194: aload         13
     196: checkcast     #30                 // class java/util/Collection
     199: astore        11
     201: aload_0
     202: aload_1
     203: aload         11
     205: invokevirtual #142                // Method computeNonDeclaredProperties:(Lkotlin/reflect/jvm/internal/impl/name/Name;Ljava/util/Collection;)V
     208: aload         13
     210: invokestatic  #167                // Method kotlin/reflect/jvm/internal/impl/utils/CollectionsKt.compact:(Ljava/util/ArrayList;)Ljava/util/List;
     213: checkcast     #30                 // class java/util/Collection
     216: nop
     217: areturn

  protected void computeNonDeclaredProperties(kotlin.reflect.jvm.internal.impl.name.Name, java.util.Collection<kotlin.reflect.jvm.internal.impl.descriptors.PropertyDescriptor>);
    Code:
       0: aload_1
       1: ldc           #16                 // String name
       3: invokestatic  #110                // Method kotlin/jvm/internal/Intrinsics.checkParameterIsNotNull:(Ljava/lang/Object;Ljava/lang/String;)V
       6: aload_2
       7: ldc           #6                  // String descriptors
       9: invokestatic  #110                // Method kotlin/jvm/internal/Intrinsics.checkParameterIsNotNull:(Ljava/lang/Object;Ljava/lang/String;)V
      12: return

  private final kotlin.reflect.jvm.internal.impl.descriptors.TypeAliasDescriptor createTypeAlias(kotlin.reflect.jvm.internal.impl.name.Name);
    Code:
       0: aload_0
       1: getfield      #93                 // Field typeAliasBytes:Ljava/util/Map;
       4: aload_1
       5: invokeinterface #178,  2          // InterfaceMethod java/util/Map.get:(Ljava/lang/Object;)Ljava/lang/Object;
      10: checkcast     #21                 // class "[B"
      13: dup
      14: ifnull        20
      17: goto          23
      20: pop
      21: aconst_null
      22: areturn
      23: astore_2
      24: new           #22                 // class java/io/ByteArrayInputStream
      27: dup
      28: aload_2
      29: invokespecial #95                 // Method java/io/ByteArrayInputStream."<init>":([B)V
      32: checkcast     #24                 // class java/io/InputStream
      35: aload_0
      36: getfield      #85                 // Field c:Lkotlin/reflect/jvm/internal/impl/serialization/deserialization/DeserializationContext;
      39: invokevirtual #129                // Method kotlin/reflect/jvm/internal/impl/serialization/deserialization/DeserializationContext.getComponents:()Lkotlin/reflect/jvm/internal/impl/serialization/deserialization/DeserializationComponents;
      42: invokevirtual #128                // Method kotlin/reflect/jvm/internal/impl/serialization/deserialization/DeserializationComponents.getExtensionRegistryLite:()Lkotlin/reflect/jvm/internal/impl/protobuf/ExtensionRegistryLite;
      45: invokestatic  #117                // Method kotlin/reflect/jvm/internal/impl/metadata/ProtoBuf$TypeAlias.parseDelimitedFrom:(Ljava/io/InputStream;Lkotlin/reflect/jvm/internal/impl/protobuf/ExtensionRegistryLite;)Lkotlin/reflect/jvm/internal/impl/metadata/ProtoBuf$TypeAlias;
      48: dup
      49: ifnull        55
      52: goto          58
      55: pop
      56: aconst_null
      57: areturn
      58: astore_3
      59: aload_0
      60: getfield      #85                 // Field c:Lkotlin/reflect/jvm/internal/impl/serialization/deserialization/DeserializationContext;
      63: invokevirtual #130                // Method kotlin/reflect/jvm/internal/impl/serialization/deserialization/DeserializationContext.getMemberDeserializer:()Lkotlin/reflect/jvm/internal/impl/serialization/deserialization/MemberDeserializer;
      66: aload_3
      67: invokevirtual #135                // Method kotlin/reflect/jvm/internal/impl/serialization/deserialization/MemberDeserializer.loadTypeAlias:(Lkotlin/reflect/jvm/internal/impl/metadata/ProtoBuf$TypeAlias;)Lkotlin/reflect/jvm/internal/impl/descriptors/TypeAliasDescriptor;
      70: areturn

  public java.util.Collection<kotlin.reflect.jvm.internal.impl.descriptors.PropertyDescriptor> getContributedVariables(kotlin.reflect.jvm.internal.impl.name.Name, kotlin.reflect.jvm.internal.impl.incremental.components.LookupLocation);
    Code:
       0: aload_1
       1: ldc           #16                 // String name
       3: invokestatic  #110                // Method kotlin/jvm/internal/Intrinsics.checkParameterIsNotNull:(Ljava/lang/Object;Ljava/lang/String;)V
       6: aload_2
       7: ldc           #15                 // String location
       9: invokestatic  #110                // Method kotlin/jvm/internal/Intrinsics.checkParameterIsNotNull:(Ljava/lang/Object;Ljava/lang/String;)V
      12: aload_0
      13: invokevirtual #153                // Method getVariableNames:()Ljava/util/Set;
      16: aload_1
      17: invokeinterface #184,  2          // InterfaceMethod java/util/Set.contains:(Ljava/lang/Object;)Z
      22: ifne          32
      25: invokestatic  #105                // Method kotlin/collections/CollectionsKt.emptyList:()Ljava/util/List;
      28: checkcast     #30                 // class java/util/Collection
      31: areturn
      32: aload_0
      33: getfield      #90                 // Field properties:Lkotlin/reflect/jvm/internal/impl/storage/MemoizedFunctionToNotNull;
      36: aload_1
      37: invokeinterface #188,  2          // InterfaceMethod kotlin/reflect/jvm/internal/impl/storage/MemoizedFunctionToNotNull.invoke:(Ljava/lang/Object;)Ljava/lang/Object;
      42: checkcast     #30                 // class java/util/Collection
      45: areturn

  protected final java.util.Collection<kotlin.reflect.jvm.internal.impl.descriptors.DeclarationDescriptor> computeDescriptors(kotlin.reflect.jvm.internal.impl.resolve.scopes.DescriptorKindFilter, kotlin.jvm.functions.Function1<? super kotlin.reflect.jvm.internal.impl.name.Name, java.lang.Boolean>, kotlin.reflect.jvm.internal.impl.incremental.components.LookupLocation);
    Code:
       0: aload_1
       1: ldc           #14                 // String kindFilter
       3: invokestatic  #110                // Method kotlin/jvm/internal/Intrinsics.checkParameterIsNotNull:(Ljava/lang/Object;Ljava/lang/String;)V
       6: aload_2
       7: ldc           #17                 // String nameFilter
       9: invokestatic  #110                // Method kotlin/jvm/internal/Intrinsics.checkParameterIsNotNull:(Ljava/lang/Object;Ljava/lang/String;)V
      12: aload_3
      13: ldc           #15                 // String location
      15: invokestatic  #110                // Method kotlin/jvm/internal/Intrinsics.checkParameterIsNotNull:(Ljava/lang/Object;Ljava/lang/String;)V
      18: new           #29                 // class java/util/ArrayList
      21: dup
      22: iconst_0
      23: invokespecial #100                // Method java/util/ArrayList."<init>":(I)V
      26: astore        4
      28: aload_1
      29: getstatic     #83                 // Field kotlin/reflect/jvm/internal/impl/resolve/scopes/DescriptorKindFilter.Companion:Lkotlin/reflect/jvm/internal/impl/resolve/scopes/DescriptorKindFilter$Companion;
      32: invokevirtual #122                // Method kotlin/reflect/jvm/internal/impl/resolve/scopes/DescriptorKindFilter$Companion.getSINGLETON_CLASSIFIERS_MASK:()I
      35: invokevirtual #119                // Method kotlin/reflect/jvm/internal/impl/resolve/scopes/DescriptorKindFilter.acceptsKinds:(I)Z
      38: ifeq          51
      41: aload_0
      42: aload         4
      44: checkcast     #30                 // class java/util/Collection
      47: aload_2
      48: invokevirtual #138                // Method addEnumEntryDescriptors:(Ljava/util/Collection;Lkotlin/jvm/functions/Function1;)V
      51: aload_0
      52: aload         4
      54: checkcast     #30                 // class java/util/Collection
      57: aload_1
      58: aload_2
      59: aload_3
      60: invokespecial #139                // Method addFunctionsAndProperties:(Ljava/util/Collection;Lkotlin/reflect/jvm/internal/impl/resolve/scopes/DescriptorKindFilter;Lkotlin/jvm/functions/Function1;Lkotlin/reflect/jvm/internal/impl/incremental/components/LookupLocation;)V
      63: aload_1
      64: getstatic     #83                 // Field kotlin/reflect/jvm/internal/impl/resolve/scopes/DescriptorKindFilter.Companion:Lkotlin/reflect/jvm/internal/impl/resolve/scopes/DescriptorKindFilter$Companion;
      67: invokevirtual #120                // Method kotlin/reflect/jvm/internal/impl/resolve/scopes/DescriptorKindFilter$Companion.getCLASSIFIERS_MASK:()I
      70: invokevirtual #119                // Method kotlin/reflect/jvm/internal/impl/resolve/scopes/DescriptorKindFilter.acceptsKinds:(I)Z
      73: ifeq          143
      76: aload_0
      77: invokevirtual #147                // Method getClassNames$deserialization:()Ljava/util/Set;
      80: invokeinterface #185,  1          // InterfaceMethod java/util/Set.iterator:()Ljava/util/Iterator;
      85: astore        6
      87: aload         6
      89: invokeinterface #174,  1          // InterfaceMethod java/util/Iterator.hasNext:()Z
      94: ifeq          143
      97: aload         6
      99: invokeinterface #175,  1          // InterfaceMethod java/util/Iterator.next:()Ljava/lang/Object;
     104: checkcast     #52                 // class kotlin/reflect/jvm/internal/impl/name/Name
     107: astore        5
     109: aload_2
     110: aload         5
     112: invokeinterface #186,  2          // InterfaceMethod kotlin/jvm/functions/Function1.invoke:(Ljava/lang/Object;)Ljava/lang/Object;
     117: checkcast     #26                 // class java/lang/Boolean
     120: invokevirtual #98                 // Method java/lang/Boolean.booleanValue:()Z
     123: ifeq          140
     126: aload         4
     128: checkcast     #30                 // class java/util/Collection
     131: aload_0
     132: aload         5
     134: invokespecial #146                // Method deserializeClass:(Lkotlin/reflect/jvm/internal/impl/name/Name;)Lkotlin/reflect/jvm/internal/impl/descriptors/ClassDescriptor;
     137: invokestatic  #166                // Method kotlin/reflect/jvm/internal/impl/utils/CollectionsKt.addIfNotNull:(Ljava/util/Collection;Ljava/lang/Object;)V
     140: goto          87
     143: aload_1
     144: getstatic     #83                 // Field kotlin/reflect/jvm/internal/impl/resolve/scopes/DescriptorKindFilter.Companion:Lkotlin/reflect/jvm/internal/impl/resolve/scopes/DescriptorKindFilter$Companion;
     147: invokevirtual #123                // Method kotlin/reflect/jvm/internal/impl/resolve/scopes/DescriptorKindFilter$Companion.getTYPE_ALIASES_MASK:()I
     150: invokevirtual #119                // Method kotlin/reflect/jvm/internal/impl/resolve/scopes/DescriptorKindFilter.acceptsKinds:(I)Z
     153: ifeq          228
     156: aload_0
     157: invokespecial #152                // Method getTypeAliasNames:()Ljava/util/Set;
     160: invokeinterface #185,  1          // InterfaceMethod java/util/Set.iterator:()Ljava/util/Iterator;
     165: astore        6
     167: aload         6
     169: invokeinterface #174,  1          // InterfaceMethod java/util/Iterator.hasNext:()Z
     174: ifeq          228
     177: aload         6
     179: invokeinterface #175,  1          // InterfaceMethod java/util/Iterator.next:()Ljava/lang/Object;
     184: checkcast     #52                 // class kotlin/reflect/jvm/internal/impl/name/Name
     187: astore        5
     189: aload_2
     190: aload         5
     192: invokeinterface #186,  2          // InterfaceMethod kotlin/jvm/functions/Function1.invoke:(Ljava/lang/Object;)Ljava/lang/Object;
     197: checkcast     #26                 // class java/lang/Boolean
     200: invokevirtual #98                 // Method java/lang/Boolean.booleanValue:()Z
     203: ifeq          225
     206: aload         4
     208: checkcast     #30                 // class java/util/Collection
     211: aload_0
     212: getfield      #92                 // Field typeAliasByName:Lkotlin/reflect/jvm/internal/impl/storage/MemoizedFunctionToNullable;
     215: aload         5
     217: invokeinterface #189,  2          // InterfaceMethod kotlin/reflect/jvm/internal/impl/storage/MemoizedFunctionToNullable.invoke:(Ljava/lang/Object;)Ljava/lang/Object;
     222: invokestatic  #166                // Method kotlin/reflect/jvm/internal/impl/utils/CollectionsKt.addIfNotNull:(Ljava/util/Collection;Ljava/lang/Object;)V
     225: goto          167
     228: aload         4
     230: invokestatic  #167                // Method kotlin/reflect/jvm/internal/impl/utils/CollectionsKt.compact:(Ljava/util/ArrayList;)Ljava/util/List;
     233: checkcast     #30                 // class java/util/Collection
     236: areturn

  private final void addFunctionsAndProperties(java.util.Collection<kotlin.reflect.jvm.internal.impl.descriptors.DeclarationDescriptor>, kotlin.reflect.jvm.internal.impl.resolve.scopes.DescriptorKindFilter, kotlin.jvm.functions.Function1<? super kotlin.reflect.jvm.internal.impl.name.Name, java.lang.Boolean>, kotlin.reflect.jvm.internal.impl.incremental.components.LookupLocation);
    Code:
       0: aload_2
       1: getstatic     #83                 // Field kotlin/reflect/jvm/internal/impl/resolve/scopes/DescriptorKindFilter.Companion:Lkotlin/reflect/jvm/internal/impl/resolve/scopes/DescriptorKindFilter$Companion;
       4: invokevirtual #124                // Method kotlin/reflect/jvm/internal/impl/resolve/scopes/DescriptorKindFilter$Companion.getVARIABLES_MASK:()I
       7: invokevirtual #119                // Method kotlin/reflect/jvm/internal/impl/resolve/scopes/DescriptorKindFilter.acceptsKinds:(I)Z
      10: ifeq          145
      13: aload_0
      14: astore        5
      16: aload_0
      17: invokevirtual #153                // Method getVariableNames:()Ljava/util/Set;
      20: checkcast     #30                 // class java/util/Collection
      23: astore        6
      25: nop
      26: new           #29                 // class java/util/ArrayList
      29: dup
      30: invokespecial #99                 // Method java/util/ArrayList."<init>":()V
      33: astore        7
      35: aload         6
      37: invokeinterface #173,  1          // InterfaceMethod java/util/Collection.iterator:()Ljava/util/Iterator;
      42: astore        8
      44: aload         8
      46: invokeinterface #174,  1          // InterfaceMethod java/util/Iterator.hasNext:()Z
      51: ifeq          112
      54: aload         8
      56: invokeinterface #175,  1          // InterfaceMethod java/util/Iterator.next:()Ljava/lang/Object;
      61: checkcast     #52                 // class kotlin/reflect/jvm/internal/impl/name/Name
      64: astore        9
      66: aload_3
      67: aload         9
      69: invokeinterface #186,  2          // InterfaceMethod kotlin/jvm/functions/Function1.invoke:(Ljava/lang/Object;)Ljava/lang/Object;
      74: checkcast     #26                 // class java/lang/Boolean
      77: invokevirtual #98                 // Method java/lang/Boolean.booleanValue:()Z
      80: ifeq          109
      83: aload         7
      85: aload         9
      87: astore        10
      89: astore        13
      91: aload_0
      92: aload         10
      94: aload         4
      96: invokevirtual #149                // Method getContributedVariables:(Lkotlin/reflect/jvm/internal/impl/name/Name;Lkotlin/reflect/jvm/internal/impl/incremental/components/LookupLocation;)Ljava/util/Collection;
      99: astore        14
     101: aload         13
     103: aload         14
     105: invokevirtual #101                // Method java/util/ArrayList.addAll:(Ljava/util/Collection;)Z
     108: pop
     109: goto          44
     112: aload         7
     114: checkcast     #34                 // class java/util/List
     117: getstatic     #82                 // Field kotlin/reflect/jvm/internal/impl/resolve/MemberComparator$NameAndTypeMemberComparator.INSTANCE:Lkotlin/reflect/jvm/internal/impl/resolve/MemberComparator$NameAndTypeMemberComparator;
     120: dup
     121: ldc           #1                  // String MemberComparator.NameAnd…MemberComparator.INSTANCE
     123: invokestatic  #109                // Method kotlin/jvm/internal/Intrinsics.checkExpressionValueIsNotNull:(Ljava/lang/Object;Ljava/lang/String;)V
     126: checkcast     #31                 // class java/util/Comparator
     129: invokestatic  #106                // Method kotlin/collections/CollectionsKt.sortWith:(Ljava/util/List;Ljava/util/Comparator;)V
     132: aload_1
     133: aload         7
     135: checkcast     #30                 // class java/util/Collection
     138: invokeinterface #172,  2          // InterfaceMethod java/util/Collection.addAll:(Ljava/util/Collection;)Z
     143: pop
     144: nop
     145: aload_2
     146: getstatic     #83                 // Field kotlin/reflect/jvm/internal/impl/resolve/scopes/DescriptorKindFilter.Companion:Lkotlin/reflect/jvm/internal/impl/resolve/scopes/DescriptorKindFilter$Companion;
     149: invokevirtual #121                // Method kotlin/reflect/jvm/internal/impl/resolve/scopes/DescriptorKindFilter$Companion.getFUNCTIONS_MASK:()I
     152: invokevirtual #119                // Method kotlin/reflect/jvm/internal/impl/resolve/scopes/DescriptorKindFilter.acceptsKinds:(I)Z
     155: ifeq          290
     158: aload_0
     159: astore        5
     161: aload_0
     162: invokevirtual #150                // Method getFunctionNames:()Ljava/util/Set;
     165: checkcast     #30                 // class java/util/Collection
     168: astore        6
     170: nop
     171: new           #29                 // class java/util/ArrayList
     174: dup
     175: invokespecial #99                 // Method java/util/ArrayList."<init>":()V
     178: astore        7
     180: aload         6
     182: invokeinterface #173,  1          // InterfaceMethod java/util/Collection.iterator:()Ljava/util/Iterator;
     187: astore        8
     189: aload         8
     191: invokeinterface #174,  1          // InterfaceMethod java/util/Iterator.hasNext:()Z
     196: ifeq          257
     199: aload         8
     201: invokeinterface #175,  1          // InterfaceMethod java/util/Iterator.next:()Ljava/lang/Object;
     206: checkcast     #52                 // class kotlin/reflect/jvm/internal/impl/name/Name
     209: astore        9
     211: aload_3
     212: aload         9
     214: invokeinterface #186,  2          // InterfaceMethod kotlin/jvm/functions/Function1.invoke:(Ljava/lang/Object;)Ljava/lang/Object;
     219: checkcast     #26                 // class java/lang/Boolean
     222: invokevirtual #98                 // Method java/lang/Boolean.booleanValue:()Z
     225: ifeq          254
     228: aload         7
     230: aload         9
     232: astore        10
     234: astore        13
     236: aload_0
     237: aload         10
     239: aload         4
     241: invokevirtual #148                // Method getContributedFunctions:(Lkotlin/reflect/jvm/internal/impl/name/Name;Lkotlin/reflect/jvm/internal/impl/incremental/components/LookupLocation;)Ljava/util/Collection;
     244: astore        14
     246: aload         13
     248: aload         14
     250: invokevirtual #101                // Method java/util/ArrayList.addAll:(Ljava/util/Collection;)Z
     253: pop
     254: goto          189
     257: aload         7
     259: checkcast     #34                 // class java/util/List
     262: getstatic     #82                 // Field kotlin/reflect/jvm/internal/impl/resolve/MemberComparator$NameAndTypeMemberComparator.INSTANCE:Lkotlin/reflect/jvm/internal/impl/resolve/MemberComparator$NameAndTypeMemberComparator;
     265: dup
     266: ldc           #1                  // String MemberComparator.NameAnd…MemberComparator.INSTANCE
     268: invokestatic  #109                // Method kotlin/jvm/internal/Intrinsics.checkExpressionValueIsNotNull:(Ljava/lang/Object;Ljava/lang/String;)V
     271: checkcast     #31                 // class java/util/Comparator
     274: invokestatic  #106                // Method kotlin/collections/CollectionsKt.sortWith:(Ljava/util/List;Ljava/util/Comparator;)V
     277: aload_1
     278: aload         7
     280: checkcast     #30                 // class java/util/Collection
     283: invokeinterface #172,  2          // InterfaceMethod java/util/Collection.addAll:(Ljava/util/Collection;)Z
     288: pop
     289: nop
     290: return

  public kotlin.reflect.jvm.internal.impl.descriptors.ClassifierDescriptor getContributedClassifier(kotlin.reflect.jvm.internal.impl.name.Name, kotlin.reflect.jvm.internal.impl.incremental.components.LookupLocation);
    Code:
       0: aload_1
       1: ldc           #16                 // String name
       3: invokestatic  #110                // Method kotlin/jvm/internal/Intrinsics.checkParameterIsNotNull:(Ljava/lang/Object;Ljava/lang/String;)V
       6: aload_2
       7: ldc           #15                 // String location
       9: invokestatic  #110                // Method kotlin/jvm/internal/Intrinsics.checkParameterIsNotNull:(Ljava/lang/Object;Ljava/lang/String;)V
      12: aload_0
      13: aload_1
      14: invokevirtual #155                // Method hasClass:(Lkotlin/reflect/jvm/internal/impl/name/Name;)Z
      17: ifeq          31
      20: aload_0
      21: aload_1
      22: invokespecial #146                // Method deserializeClass:(Lkotlin/reflect/jvm/internal/impl/name/Name;)Lkotlin/reflect/jvm/internal/impl/descriptors/ClassDescriptor;
      25: checkcast     #47                 // class kotlin/reflect/jvm/internal/impl/descriptors/ClassifierDescriptor
      28: goto          61
      31: aload_0
      32: invokespecial #152                // Method getTypeAliasNames:()Ljava/util/Set;
      35: aload_1
      36: invokeinterface #184,  2          // InterfaceMethod java/util/Set.contains:(Ljava/lang/Object;)Z
      41: ifeq          60
      44: aload_0
      45: getfield      #92                 // Field typeAliasByName:Lkotlin/reflect/jvm/internal/impl/storage/MemoizedFunctionToNullable;
      48: aload_1
      49: invokeinterface #189,  2          // InterfaceMethod kotlin/reflect/jvm/internal/impl/storage/MemoizedFunctionToNullable.invoke:(Ljava/lang/Object;)Ljava/lang/Object;
      54: checkcast     #47                 // class kotlin/reflect/jvm/internal/impl/descriptors/ClassifierDescriptor
      57: goto          61
      60: aconst_null
      61: areturn

  private final kotlin.reflect.jvm.internal.impl.descriptors.ClassDescriptor deserializeClass(kotlin.reflect.jvm.internal.impl.name.Name);
    Code:
       0: aload_0
       1: getfield      #85                 // Field c:Lkotlin/reflect/jvm/internal/impl/serialization/deserialization/DeserializationContext;
       4: invokevirtual #129                // Method kotlin/reflect/jvm/internal/impl/serialization/deserialization/DeserializationContext.getComponents:()Lkotlin/reflect/jvm/internal/impl/serialization/deserialization/DeserializationComponents;
       7: aload_0
       8: aload_1
       9: invokevirtual #144                // Method createClassId:(Lkotlin/reflect/jvm/internal/impl/name/Name;)Lkotlin/reflect/jvm/internal/impl/name/ClassId;
      12: invokevirtual #126                // Method kotlin/reflect/jvm/internal/impl/serialization/deserialization/DeserializationComponents.deserializeClass:(Lkotlin/reflect/jvm/internal/impl/name/ClassId;)Lkotlin/reflect/jvm/internal/impl/descriptors/ClassDescriptor;
      15: areturn

  protected boolean hasClass(kotlin.reflect.jvm.internal.impl.name.Name);
    Code:
       0: aload_1
       1: ldc           #16                 // String name
       3: invokestatic  #110                // Method kotlin/jvm/internal/Intrinsics.checkParameterIsNotNull:(Ljava/lang/Object;Ljava/lang/String;)V
       6: aload_0
       7: invokevirtual #147                // Method getClassNames$deserialization:()Ljava/util/Set;
      10: aload_1
      11: invokeinterface #184,  2          // InterfaceMethod java/util/Set.contains:(Ljava/lang/Object;)Z
      16: ireturn

  protected abstract kotlin.reflect.jvm.internal.impl.name.ClassId createClassId(kotlin.reflect.jvm.internal.impl.name.Name);

  protected abstract java.util.Set<kotlin.reflect.jvm.internal.impl.name.Name> getNonDeclaredFunctionNames();

  protected abstract java.util.Set<kotlin.reflect.jvm.internal.impl.name.Name> getNonDeclaredVariableNames();

  protected abstract void addEnumEntryDescriptors(java.util.Collection<kotlin.reflect.jvm.internal.impl.descriptors.DeclarationDescriptor>, kotlin.jvm.functions.Function1<? super kotlin.reflect.jvm.internal.impl.name.Name, java.lang.Boolean>);

  protected final kotlin.reflect.jvm.internal.impl.serialization.deserialization.DeserializationContext getC();
    Code:
       0: aload_0
       1: getfield      #85                 // Field c:Lkotlin/reflect/jvm/internal/impl/serialization/deserialization/DeserializationContext;
       4: areturn

  protected kotlin.reflect.jvm.internal.impl.serialization.deserialization.descriptors.DeserializedMemberScope(kotlin.reflect.jvm.internal.impl.serialization.deserialization.DeserializationContext, java.util.Collection<kotlin.reflect.jvm.internal.impl.metadata.ProtoBuf$Function>, java.util.Collection<kotlin.reflect.jvm.internal.impl.metadata.ProtoBuf$Property>, java.util.Collection<kotlin.reflect.jvm.internal.impl.metadata.ProtoBuf$TypeAlias>, kotlin.jvm.functions.Function0<? extends java.util.Collection<kotlin.reflect.jvm.internal.impl.name.Name>>);
    Code:
       0: aload_1
       1: ldc           #4                  // String c
       3: invokestatic  #110                // Method kotlin/jvm/internal/Intrinsics.checkParameterIsNotNull:(Ljava/lang/Object;Ljava/lang/String;)V
       6: aload_2
       7: ldc           #7                  // String functionList
       9: invokestatic  #110                // Method kotlin/jvm/internal/Intrinsics.checkParameterIsNotNull:(Ljava/lang/Object;Ljava/lang/String;)V
      12: aload_3
      13: ldc           #18                 // String propertyList
      15: invokestatic  #110                // Method kotlin/jvm/internal/Intrinsics.checkParameterIsNotNull:(Ljava/lang/Object;Ljava/lang/String;)V
      18: aload         4
      20: ldc           #19                 // String typeAliasList
      22: invokestatic  #110                // Method kotlin/jvm/internal/Intrinsics.checkParameterIsNotNull:(Ljava/lang/Object;Ljava/lang/String;)V
      25: aload         5
      27: ldc           #5                  // String classNames
      29: invokestatic  #110                // Method kotlin/jvm/internal/Intrinsics.checkParameterIsNotNull:(Ljava/lang/Object;Ljava/lang/String;)V
      32: aload_0
      33: invokespecial #125                // Method kotlin/reflect/jvm/internal/impl/resolve/scopes/MemberScopeImpl."<init>":()V
      36: aload_0
      37: aload_1
      38: putfield      #85                 // Field c:Lkotlin/reflect/jvm/internal/impl/serialization/deserialization/DeserializationContext;
      41: aload_0
      42: aload_0
      43: aload_0
      44: aload_2
      45: astore        7
      47: astore        6
      49: astore        27
      51: astore        26
      53: aload         7
      55: checkcast     #27                 // class java/lang/Iterable
      58: astore        8
      60: aload         8
      62: astore        9
      64: new           #33                 // class java/util/LinkedHashMap
      67: dup
      68: invokespecial #102                // Method java/util/LinkedHashMap."<init>":()V
      71: checkcast     #35                 // class java/util/Map
      74: astore        10
      76: aload         9
      78: invokeinterface #170,  1          // InterfaceMethod java/lang/Iterable.iterator:()Ljava/util/Iterator;
      83: astore        11
      85: aload         11
      87: invokeinterface #174,  1          // InterfaceMethod java/util/Iterator.hasNext:()Z
      92: ifeq          212
      95: aload         11
      97: invokeinterface #175,  1          // InterfaceMethod java/util/Iterator.next:()Ljava/lang/Object;
     102: astore        12
     104: aload         12
     106: checkcast     #54                 // class kotlin/reflect/jvm/internal/impl/protobuf/MessageLite
     109: astore        13
     111: aload         6
     113: invokestatic  #137                // Method access$getC$p:(Lkotlin/reflect/jvm/internal/impl/serialization/deserialization/descriptors/DeserializedMemberScope;)Lkotlin/reflect/jvm/internal/impl/serialization/deserialization/DeserializationContext;
     116: invokevirtual #131                // Method kotlin/reflect/jvm/internal/impl/serialization/deserialization/DeserializationContext.getNameResolver:()Lkotlin/reflect/jvm/internal/impl/metadata/deserialization/NameResolver;
     119: aload         13
     121: checkcast     #49                 // class kotlin/reflect/jvm/internal/impl/metadata/ProtoBuf$Function
     124: astore        14
     126: astore        28
     128: aload         14
     130: invokevirtual #114                // Method kotlin/reflect/jvm/internal/impl/metadata/ProtoBuf$Function.getName:()I
     133: istore        29
     135: aload         28
     137: iload         29
     139: invokestatic  #136                // Method kotlin/reflect/jvm/internal/impl/serialization/deserialization/NameResolverUtilKt.getName:(Lkotlin/reflect/jvm/internal/impl/metadata/deserialization/NameResolver;I)Lkotlin/reflect/jvm/internal/impl/name/Name;
     142: astore        16
     144: aload         10
     146: astore        17
     148: aload         17
     150: aload         16
     152: invokeinterface #178,  2          // InterfaceMethod java/util/Map.get:(Ljava/lang/Object;)Ljava/lang/Object;
     157: astore        18
     159: aload         18
     161: ifnonnull     191
     164: nop
     165: new           #29                 // class java/util/ArrayList
     168: dup
     169: invokespecial #99                 // Method java/util/ArrayList."<init>":()V
     172: astore        19
     174: aload         17
     176: aload         16
     178: aload         19
     180: invokeinterface #180,  3          // InterfaceMethod java/util/Map.put:(Ljava/lang/Object;Ljava/lang/Object;)Ljava/lang/Object;
     185: pop
     186: aload         19
     188: goto          193
     191: aload         18
     193: nop
     194: checkcast     #34                 // class java/util/List
     197: astore        20
     199: aload         20
     201: aload         12
     203: invokeinterface #176,  2          // InterfaceMethod java/util/List.add:(Ljava/lang/Object;)Z
     208: pop
     209: goto          85
     212: aload         10
     214: nop
     215: nop
     216: astore        28
     218: aload         26
     220: aload         27
     222: aload         28
     224: invokespecial #156                // Method packToByteArray:(Ljava/util/Map;)Ljava/util/Map;
     227: putfield      #88                 // Field functionProtosBytes:Ljava/util/Map;
     230: aload_0
     231: aload_0
     232: aload_0
     233: aload_3
     234: astore        7
     236: astore        6
     238: astore        27
     240: astore        26
     242: aload         7
     244: checkcast     #27                 // class java/lang/Iterable
     247: astore        8
     249: aload         8
     251: astore        9
     253: new           #33                 // class java/util/LinkedHashMap
     256: dup
     257: invokespecial #102                // Method java/util/LinkedHashMap."<init>":()V
     260: checkcast     #35                 // class java/util/Map
     263: astore        10
     265: aload         9
     267: invokeinterface #170,  1          // InterfaceMethod java/lang/Iterable.iterator:()Ljava/util/Iterator;
     272: astore        11
     274: aload         11
     276: invokeinterface #174,  1          // InterfaceMethod java/util/Iterator.hasNext:()Z
     281: ifeq          401
     284: aload         11
     286: invokeinterface #175,  1          // InterfaceMethod java/util/Iterator.next:()Ljava/lang/Object;
     291: astore        12
     293: aload         12
     295: checkcast     #54                 // class kotlin/reflect/jvm/internal/impl/protobuf/MessageLite
     298: astore        13
     300: aload         6
     302: invokestatic  #137                // Method access$getC$p:(Lkotlin/reflect/jvm/internal/impl/serialization/deserialization/descriptors/DeserializedMemberScope;)Lkotlin/reflect/jvm/internal/impl/serialization/deserialization/DeserializationContext;
     305: invokevirtual #131                // Method kotlin/reflect/jvm/internal/impl/serialization/deserialization/DeserializationContext.getNameResolver:()Lkotlin/reflect/jvm/internal/impl/metadata/deserialization/NameResolver;
     308: aload         13
     310: checkcast     #50                 // class kotlin/reflect/jvm/internal/impl/metadata/ProtoBuf$Property
     313: astore        14
     315: astore        28
     317: aload         14
     319: invokevirtual #115                // Method kotlin/reflect/jvm/internal/impl/metadata/ProtoBuf$Property.getName:()I
     322: istore        29
     324: aload         28
     326: iload         29
     328: invokestatic  #136                // Method kotlin/reflect/jvm/internal/impl/serialization/deserialization/NameResolverUtilKt.getName:(Lkotlin/reflect/jvm/internal/impl/metadata/deserialization/NameResolver;I)Lkotlin/reflect/jvm/internal/impl/name/Name;
     331: astore        16
     333: aload         10
     335: astore        17
     337: aload         17
     339: aload         16
     341: invokeinterface #178,  2          // InterfaceMethod java/util/Map.get:(Ljava/lang/Object;)Ljava/lang/Object;
     346: astore        18
     348: aload         18
     350: ifnonnull     380
     353: nop
     354: new           #29                 // class java/util/ArrayList
     357: dup
     358: invokespecial #99                 // Method java/util/ArrayList."<init>":()V
     361: astore        19
     363: aload         17
     365: aload         16
     367: aload         19
     369: invokeinterface #180,  3          // InterfaceMethod java/util/Map.put:(Ljava/lang/Object;Ljava/lang/Object;)Ljava/lang/Object;
     374: pop
     375: aload         19
     377: goto          382
     380: aload         18
     382: nop
     383: checkcast     #34                 // class java/util/List
     386: astore        20
     388: aload         20
     390: aload         12
     392: invokeinterface #176,  2          // InterfaceMethod java/util/List.add:(Ljava/lang/Object;)Z
     397: pop
     398: goto          274
     401: aload         10
     403: nop
     404: nop
     405: astore        28
     407: aload         26
     409: aload         27
     411: aload         28
     413: invokespecial #156                // Method packToByteArray:(Ljava/util/Map;)Ljava/util/Map;
     416: putfield      #91                 // Field propertyProtosBytes:Ljava/util/Map;
     419: aload_0
     420: aload_0
     421: getfield      #85                 // Field c:Lkotlin/reflect/jvm/internal/impl/serialization/deserialization/DeserializationContext;
     424: invokevirtual #129                // Method kotlin/reflect/jvm/internal/impl/serialization/deserialization/DeserializationContext.getComponents:()Lkotlin/reflect/jvm/internal/impl/serialization/deserialization/DeserializationComponents;
     427: invokevirtual #127                // Method kotlin/reflect/jvm/internal/impl/serialization/deserialization/DeserializationComponents.getConfiguration:()Lkotlin/reflect/jvm/internal/impl/serialization/deserialization/DeserializationConfiguration;
     430: invokeinterface #187,  1          // InterfaceMethod kotlin/reflect/jvm/internal/impl/serialization/deserialization/DeserializationConfiguration.getTypeAliasesAllowed:()Z
     435: ifeq          627
     438: aload_0
     439: aload_0
     440: aload         4
     442: astore        7
     444: astore        6
     446: astore        27
     448: astore        26
     450: aload         7
     452: checkcast     #27                 // class java/lang/Iterable
     455: astore        8
     457: aload         8
     459: astore        9
     461: new           #33                 // class java/util/LinkedHashMap
     464: dup
     465: invokespecial #102                // Method java/util/LinkedHashMap."<init>":()V
     468: checkcast     #35                 // class java/util/Map
     471: astore        10
     473: aload         9
     475: invokeinterface #170,  1          // InterfaceMethod java/lang/Iterable.iterator:()Ljava/util/Iterator;
     480: astore        11
     482: aload         11
     484: invokeinterface #174,  1          // InterfaceMethod java/util/Iterator.hasNext:()Z
     489: ifeq          609
     492: aload         11
     494: invokeinterface #175,  1          // InterfaceMethod java/util/Iterator.next:()Ljava/lang/Object;
     499: astore        12
     501: aload         12
     503: checkcast     #54                 // class kotlin/reflect/jvm/internal/impl/protobuf/MessageLite
     506: astore        13
     508: aload         6
     510: invokestatic  #137                // Method access$getC$p:(Lkotlin/reflect/jvm/internal/impl/serialization/deserialization/descriptors/DeserializedMemberScope;)Lkotlin/reflect/jvm/internal/impl/serialization/deserialization/DeserializationContext;
     513: invokevirtual #131                // Method kotlin/reflect/jvm/internal/impl/serialization/deserialization/DeserializationContext.getNameResolver:()Lkotlin/reflect/jvm/internal/impl/metadata/deserialization/NameResolver;
     516: aload         13
     518: checkcast     #51                 // class kotlin/reflect/jvm/internal/impl/metadata/ProtoBuf$TypeAlias
     521: astore        14
     523: astore        28
     525: aload         14
     527: invokevirtual #116                // Method kotlin/reflect/jvm/internal/impl/metadata/ProtoBuf$TypeAlias.getName:()I
     530: istore        29
     532: aload         28
     534: iload         29
     536: invokestatic  #136                // Method kotlin/reflect/jvm/internal/impl/serialization/deserialization/NameResolverUtilKt.getName:(Lkotlin/reflect/jvm/internal/impl/metadata/deserialization/NameResolver;I)Lkotlin/reflect/jvm/internal/impl/name/Name;
     539: astore        16
     541: aload         10
     543: astore        17
     545: aload         17
     547: aload         16
     549: invokeinterface #178,  2          // InterfaceMethod java/util/Map.get:(Ljava/lang/Object;)Ljava/lang/Object;
     554: astore        18
     556: aload         18
     558: ifnonnull     588
     561: nop
     562: new           #29                 // class java/util/ArrayList
     565: dup
     566: invokespecial #99                 // Method java/util/ArrayList."<init>":()V
     569: astore        19
     571: aload         17
     573: aload         16
     575: aload         19
     577: invokeinterface #180,  3          // InterfaceMethod java/util/Map.put:(Ljava/lang/Object;Ljava/lang/Object;)Ljava/lang/Object;
     582: pop
     583: aload         19
     585: goto          590
     588: aload         18
     590: nop
     591: checkcast     #34                 // class java/util/List
     594: astore        20
     596: aload         20
     598: aload         12
     600: invokeinterface #176,  2          // InterfaceMethod java/util/List.add:(Ljava/lang/Object;)Z
     605: pop
     606: goto          482
     609: aload         10
     611: nop
     612: nop
     613: astore        28
     615: aload         26
     617: aload         27
     619: aload         28
     621: invokespecial #156                // Method packToByteArray:(Ljava/util/Map;)Ljava/util/Map;
     624: goto          630
     627: invokestatic  #107                // Method kotlin/collections/MapsKt.emptyMap:()Ljava/util/Map;
     630: putfield      #93                 // Field typeAliasBytes:Ljava/util/Map;
     633: aload_0
     634: aload_0
     635: getfield      #85                 // Field c:Lkotlin/reflect/jvm/internal/impl/serialization/deserialization/DeserializationContext;
     638: invokevirtual #132                // Method kotlin/reflect/jvm/internal/impl/serialization/deserialization/DeserializationContext.getStorageManager:()Lkotlin/reflect/jvm/internal/impl/storage/StorageManager;
     641: new           #69                 // class kotlin/reflect/jvm/internal/impl/serialization/deserialization/descriptors/DeserializedMemberScope$functions$1
     644: dup
     645: aload_0
     646: invokespecial #161                // Method kotlin/reflect/jvm/internal/impl/serialization/deserialization/descriptors/DeserializedMemberScope$functions$1."<init>":(Lkotlin/reflect/jvm/internal/impl/serialization/deserialization/descriptors/DeserializedMemberScope;)V
     649: checkcast     #42                 // class kotlin/jvm/functions/Function1
     652: invokeinterface #191,  2          // InterfaceMethod kotlin/reflect/jvm/internal/impl/storage/StorageManager.createMemoizedFunction:(Lkotlin/jvm/functions/Function1;)Lkotlin/reflect/jvm/internal/impl/storage/MemoizedFunctionToNotNull;
     657: putfield      #89                 // Field functions:Lkotlin/reflect/jvm/internal/impl/storage/MemoizedFunctionToNotNull;
     660: aload_0
     661: aload_0
     662: getfield      #85                 // Field c:Lkotlin/reflect/jvm/internal/impl/serialization/deserialization/DeserializationContext;
     665: invokevirtual #132                // Method kotlin/reflect/jvm/internal/impl/serialization/deserialization/DeserializationContext.getStorageManager:()Lkotlin/reflect/jvm/internal/impl/storage/StorageManager;
     668: new           #70                 // class kotlin/reflect/jvm/internal/impl/serialization/deserialization/descriptors/DeserializedMemberScope$properties$1
     671: dup
     672: aload_0
     673: invokespecial #162                // Method kotlin/reflect/jvm/internal/impl/serialization/deserialization/descriptors/DeserializedMemberScope$properties$1."<init>":(Lkotlin/reflect/jvm/internal/impl/serialization/deserialization/descriptors/DeserializedMemberScope;)V
     676: checkcast     #42                 // class kotlin/jvm/functions/Function1
     679: invokeinterface #191,  2          // InterfaceMethod kotlin/reflect/jvm/internal/impl/storage/StorageManager.createMemoizedFunction:(Lkotlin/jvm/functions/Function1;)Lkotlin/reflect/jvm/internal/impl/storage/MemoizedFunctionToNotNull;
     684: putfield      #90                 // Field properties:Lkotlin/reflect/jvm/internal/impl/storage/MemoizedFunctionToNotNull;
     687: aload_0
     688: aload_0
     689: getfield      #85                 // Field c:Lkotlin/reflect/jvm/internal/impl/serialization/deserialization/DeserializationContext;
     692: invokevirtual #132                // Method kotlin/reflect/jvm/internal/impl/serialization/deserialization/DeserializationContext.getStorageManager:()Lkotlin/reflect/jvm/internal/impl/storage/StorageManager;
     695: new           #71                 // class kotlin/reflect/jvm/internal/impl/serialization/deserialization/descriptors/DeserializedMemberScope$typeAliasByName$1
     698: dup
     699: aload_0
     700: invokespecial #163                // Method kotlin/reflect/jvm/internal/impl/serialization/deserialization/descriptors/DeserializedMemberScope$typeAliasByName$1."<init>":(Lkotlin/reflect/jvm/internal/impl/serialization/deserialization/descriptors/DeserializedMemberScope;)V
     703: checkcast     #42                 // class kotlin/jvm/functions/Function1
     706: invokeinterface #192,  2          // InterfaceMethod kotlin/reflect/jvm/internal/impl/storage/StorageManager.createMemoizedFunctionWithNullableValues:(Lkotlin/jvm/functions/Function1;)Lkotlin/reflect/jvm/internal/impl/storage/MemoizedFunctionToNullable;
     711: putfield      #92                 // Field typeAliasByName:Lkotlin/reflect/jvm/internal/impl/storage/MemoizedFunctionToNullable;
     714: aload_0
     715: aload_0
     716: getfield      #85                 // Field c:Lkotlin/reflect/jvm/internal/impl/serialization/deserialization/DeserializationContext;
     719: invokevirtual #132                // Method kotlin/reflect/jvm/internal/impl/serialization/deserialization/DeserializationContext.getStorageManager:()Lkotlin/reflect/jvm/internal/impl/storage/StorageManager;
     722: new           #68                 // class kotlin/reflect/jvm/internal/impl/serialization/deserialization/descriptors/DeserializedMemberScope$functionNamesLazy$2
     725: dup
     726: aload_0
     727: invokespecial #160                // Method kotlin/reflect/jvm/internal/impl/serialization/deserialization/descriptors/DeserializedMemberScope$functionNamesLazy$2."<init>":(Lkotlin/reflect/jvm/internal/impl/serialization/deserialization/descriptors/DeserializedMemberScope;)V
     730: checkcast     #41                 // class kotlin/jvm/functions/Function0
     733: invokeinterface #190,  2          // InterfaceMethod kotlin/reflect/jvm/internal/impl/storage/StorageManager.createLazyValue:(Lkotlin/jvm/functions/Function0;)Lkotlin/reflect/jvm/internal/impl/storage/NotNullLazyValue;
     738: putfield      #87                 // Field functionNamesLazy$delegate:Lkotlin/reflect/jvm/internal/impl/storage/NotNullLazyValue;
     741: aload_0
     742: aload_0
     743: getfield      #85                 // Field c:Lkotlin/reflect/jvm/internal/impl/serialization/deserialization/DeserializationContext;
     746: invokevirtual #132                // Method kotlin/reflect/jvm/internal/impl/serialization/deserialization/DeserializationContext.getStorageManager:()Lkotlin/reflect/jvm/internal/impl/storage/StorageManager;
     749: new           #72                 // class kotlin/reflect/jvm/internal/impl/serialization/deserialization/descriptors/DeserializedMemberScope$variableNamesLazy$2
     752: dup
     753: aload_0
     754: invokespecial #164                // Method kotlin/reflect/jvm/internal/impl/serialization/deserialization/descriptors/DeserializedMemberScope$variableNamesLazy$2."<init>":(Lkotlin/reflect/jvm/internal/impl/serialization/deserialization/descriptors/DeserializedMemberScope;)V
     757: checkcast     #41                 // class kotlin/jvm/functions/Function0
     760: invokeinterface #190,  2          // InterfaceMethod kotlin/reflect/jvm/internal/impl/storage/StorageManager.createLazyValue:(Lkotlin/jvm/functions/Function0;)Lkotlin/reflect/jvm/internal/impl/storage/NotNullLazyValue;
     765: putfield      #94                 // Field variableNamesLazy$delegate:Lkotlin/reflect/jvm/internal/impl/storage/NotNullLazyValue;
     768: aload_0
     769: aload_0
     770: getfield      #85                 // Field c:Lkotlin/reflect/jvm/internal/impl/serialization/deserialization/DeserializationContext;
     773: invokevirtual #132                // Method kotlin/reflect/jvm/internal/impl/serialization/deserialization/DeserializationContext.getStorageManager:()Lkotlin/reflect/jvm/internal/impl/storage/StorageManager;
     776: new           #65                 // class kotlin/reflect/jvm/internal/impl/serialization/deserialization/descriptors/DeserializedMemberScope$classNames$2
     779: dup
     780: aload         5
     782: invokespecial #157                // Method kotlin/reflect/jvm/internal/impl/serialization/deserialization/descriptors/DeserializedMemberScope$classNames$2."<init>":(Lkotlin/jvm/functions/Function0;)V
     785: checkcast     #41                 // class kotlin/jvm/functions/Function0
     788: invokeinterface #190,  2          // InterfaceMethod kotlin/reflect/jvm/internal/impl/storage/StorageManager.createLazyValue:(Lkotlin/jvm/functions/Function0;)Lkotlin/reflect/jvm/internal/impl/storage/NotNullLazyValue;
     793: putfield      #86                 // Field classNames$delegate:Lkotlin/reflect/jvm/internal/impl/storage/NotNullLazyValue;
     796: return

  public static final kotlin.reflect.jvm.internal.impl.serialization.deserialization.DeserializationContext access$getC$p(kotlin.reflect.jvm.internal.impl.serialization.deserialization.descriptors.DeserializedMemberScope);
    Code:
       0: aload_0
       1: getfield      #85                 // Field c:Lkotlin/reflect/jvm/internal/impl/serialization/deserialization/DeserializationContext;
       4: areturn

  public static final java.util.Collection access$computeFunctions(kotlin.reflect.jvm.internal.impl.serialization.deserialization.descriptors.DeserializedMemberScope, kotlin.reflect.jvm.internal.impl.name.Name);
    Code:
       0: aload_0
       1: aload_1
       2: invokespecial #140                // Method computeFunctions:(Lkotlin/reflect/jvm/internal/impl/name/Name;)Ljava/util/Collection;
       5: areturn

  public static final java.util.Collection access$computeProperties(kotlin.reflect.jvm.internal.impl.serialization.deserialization.descriptors.DeserializedMemberScope, kotlin.reflect.jvm.internal.impl.name.Name);
    Code:
       0: aload_0
       1: aload_1
       2: invokespecial #143                // Method computeProperties:(Lkotlin/reflect/jvm/internal/impl/name/Name;)Ljava/util/Collection;
       5: areturn

  public static final kotlin.reflect.jvm.internal.impl.descriptors.TypeAliasDescriptor access$createTypeAlias(kotlin.reflect.jvm.internal.impl.serialization.deserialization.descriptors.DeserializedMemberScope, kotlin.reflect.jvm.internal.impl.name.Name);
    Code:
       0: aload_0
       1: aload_1
       2: invokespecial #145                // Method createTypeAlias:(Lkotlin/reflect/jvm/internal/impl/name/Name;)Lkotlin/reflect/jvm/internal/impl/descriptors/TypeAliasDescriptor;
       5: areturn

  public static final java.util.Map access$getFunctionProtosBytes$p(kotlin.reflect.jvm.internal.impl.serialization.deserialization.descriptors.DeserializedMemberScope);
    Code:
       0: aload_0
       1: getfield      #88                 // Field functionProtosBytes:Ljava/util/Map;
       4: areturn

  public static final java.util.Map access$getPropertyProtosBytes$p(kotlin.reflect.jvm.internal.impl.serialization.deserialization.descriptors.DeserializedMemberScope);
    Code:
       0: aload_0
       1: getfield      #91                 // Field propertyProtosBytes:Ljava/util/Map;
       4: areturn
}
