Compiled from "TabbedPaneFactory.groovy"
public class groovy.swing.factory.TabbedPaneFactory extends groovy.swing.factory.BeanFactory {
  public static final java.lang.String DELEGATE_PROPERTY_TITLE;

  public static final java.lang.String DEFAULT_DELEGATE_PROPERTY_TITLE;

  public static final java.lang.String DELEGATE_PROPERTY_TAB_ICON;

  public static final java.lang.String DEFAULT_DELEGATE_PROPERTY_TAB_ICON;

  public static final java.lang.String DELEGATE_PROPERTY_TAB_DISABLED_ICON;

  public static final java.lang.String DEFAULT_DELEGATE_PROPERTY_TAB_DISABLED_ICON;

  public static final java.lang.String DELEGATE_PROPERTY_TAB_TOOL_TIP;

  public static final java.lang.String DEFAULT_DELEGATE_PROPERTY_TAB_TOOL_TIP;

  public static final java.lang.String DELEGATE_PROPERTY_TAB_FOREGROUND;

  public static final java.lang.String DEFAULT_DELEGATE_PROPERTY_TAB_FOREGROUND;

  public static final java.lang.String DELEGATE_PROPERTY_TAB_BACKGROUND;

  public static final java.lang.String DEFAULT_DELEGATE_PROPERTY_TAB_BACKGROUND;

  public static final java.lang.String DELEGATE_PROPERTY_TAB_ENABLED;

  public static final java.lang.String DEFAULT_DELEGATE_PROPERTY_TAB_ENABLED;

  public static final java.lang.String DELEGATE_PROPERTY_TAB_MNEMONIC;

  public static final java.lang.String DEFAULT_DELEGATE_PROPERTY_TAB_MNEMONIC;

  public static final java.lang.String DELEGATE_PROPERTY_TAB_DISPLAYED_MNEMONIC_INDEX;

  public static final java.lang.String DEFAULT_DELEGATE_PROPERTY_TAB_DISPLAYED_MNEMONIC_INDEX;

  public static final java.lang.String CONTEXT_DATA_KEY;

  private static org.codehaus.groovy.reflection.ClassInfo $staticClassInfo;

  public static transient boolean __$stMC;

  private transient groovy.lang.MetaClass metaClass;

  private static org.codehaus.groovy.reflection.ClassInfo $staticClassInfo$;

  private static java.lang.ref.SoftReference $callSiteArray;

  public groovy.swing.factory.TabbedPaneFactory(java.lang.Class);
    Code:
       0: invokestatic  #81                 // Method $getCallSiteArray:()[Lorg/codehaus/groovy/runtime/callsite/CallSite;
       3: astore_2
       4: aload_0
       5: aload_1
       6: iconst_0
       7: invokespecial #84                 // Method groovy/swing/factory/BeanFactory."<init>":(Ljava/lang/Class;Z)V
      10: aload_0
      11: invokevirtual #88                 // Method $getStaticMetaClass:()Lgroovy/lang/MetaClass;
      14: astore_3
      15: aload_3
      16: aload_0
      17: swap
      18: putfield      #90                 // Field metaClass:Lgroovy/lang/MetaClass;
      21: aload_3
      22: pop
      23: return

  public java.lang.Object newInstance(groovy.util.FactoryBuilderSupport, java.lang.Object, java.lang.Object, java.util.Map) throws java.lang.InstantiationException, java.lang.IllegalAccessException;
    Code:
       0: aload_1
       1: new           #102                // class groovy/lang/Reference
       4: dup_x1
       5: swap
       6: invokespecial #105                // Method groovy/lang/Reference."<init>":(Ljava/lang/Object;)V
       9: astore        5
      11: invokestatic  #81                 // Method $getCallSiteArray:()[Lorg/codehaus/groovy/runtime/callsite/CallSite;
      14: astore        6
      16: ldc           #4                  // class groovy/swing/factory/BeanFactory
      18: aload_0
      19: ldc           #106                // String newInstance
      21: checkcast     #108                // class java/lang/String
      24: iconst_4
      25: anewarray     #110                // class java/lang/Object
      28: dup
      29: iconst_0
      30: aload         5
      32: invokevirtual #114                // Method groovy/lang/Reference.get:()Ljava/lang/Object;
      35: checkcast     #116                // class groovy/util/FactoryBuilderSupport
      38: aastore
      39: dup
      40: iconst_1
      41: aload_2
      42: aastore
      43: dup
      44: iconst_2
      45: aload_3
      46: aastore
      47: dup
      48: iconst_3
      49: aload         4
      51: aastore
      52: invokestatic  #122                // Method org/codehaus/groovy/runtime/ScriptBytecodeAdapter.invokeMethodOnSuperN:(Ljava/lang/Class;Lgroovy/lang/GroovyObject;Ljava/lang/String;[Ljava/lang/Object;)Ljava/lang/Object;
      55: new           #102                // class groovy/lang/Reference
      58: dup_x1
      59: swap
      60: invokespecial #105                // Method groovy/lang/Reference."<init>":(Ljava/lang/Object;)V
      63: astore        7
      65: aload         7
      67: pop
      68: new           #7                  // class groovy/swing/factory/TabbedPaneFactory$_newInstance_closure1
      71: dup
      72: aload_0
      73: aload_0
      74: aload         5
      76: aload         7
      78: invokespecial #125                // Method groovy/swing/factory/TabbedPaneFactory$_newInstance_closure1."<init>":(Ljava/lang/Object;Ljava/lang/Object;Lgroovy/lang/Reference;Lgroovy/lang/Reference;)V
      81: astore        8
      83: aload         8
      85: aconst_null
      86: aload         6
      88: ldc           #126                // int 0
      90: aaload
      91: aload         5
      93: invokevirtual #114                // Method groovy/lang/Reference.get:()Ljava/lang/Object;
      96: checkcast     #116                // class groovy/util/FactoryBuilderSupport
      99: invokeinterface #132,  2          // InterfaceMethod org/codehaus/groovy/runtime/callsite/CallSite.callGroovyObjectGetProperty:(Ljava/lang/Object;)Ljava/lang/Object;
     104: ldc           #134                // String tabbedPaneFactoryClosure
     106: checkcast     #108                // class java/lang/String
     109: invokestatic  #138                // Method org/codehaus/groovy/runtime/ScriptBytecodeAdapter.setProperty:(Ljava/lang/Object;Ljava/lang/Class;Ljava/lang/Object;Ljava/lang/String;)V
     112: aload         8
     114: pop
     115: aload         6
     117: ldc           #139                // int 1
     119: aaload
     120: aload         5
     122: invokevirtual #114                // Method groovy/lang/Reference.get:()Ljava/lang/Object;
     125: checkcast     #116                // class groovy/util/FactoryBuilderSupport
     128: aload         6
     130: ldc           #140                // int 2
     132: aaload
     133: aload         6
     135: ldc           #141                // int 3
     137: aaload
     138: aload         5
     140: invokevirtual #114                // Method groovy/lang/Reference.get:()Ljava/lang/Object;
     143: checkcast     #116                // class groovy/util/FactoryBuilderSupport
     146: invokeinterface #132,  2          // InterfaceMethod org/codehaus/groovy/runtime/callsite/CallSite.callGroovyObjectGetProperty:(Ljava/lang/Object;)Ljava/lang/Object;
     151: invokeinterface #144,  2          // InterfaceMethod org/codehaus/groovy/runtime/callsite/CallSite.callGetProperty:(Ljava/lang/Object;)Ljava/lang/Object;
     156: invokeinterface #148,  3          // InterfaceMethod org/codehaus/groovy/runtime/callsite/CallSite.call:(Ljava/lang/Object;Ljava/lang/Object;)Ljava/lang/Object;
     161: pop
     162: aload         6
     164: ldc           #149                // int 4
     166: aaload
     167: aload         4
     169: ldc           #151                // String selectedIndex
     171: invokeinterface #148,  3          // InterfaceMethod org/codehaus/groovy/runtime/callsite/CallSite.call:(Ljava/lang/Object;Ljava/lang/Object;)Ljava/lang/Object;
     176: astore        9
     178: aload         9
     180: aconst_null
     181: aload         6
     183: ldc           #152                // int 5
     185: aaload
     186: aload         5
     188: invokevirtual #114                // Method groovy/lang/Reference.get:()Ljava/lang/Object;
     191: checkcast     #116                // class groovy/util/FactoryBuilderSupport
     194: invokeinterface #132,  2          // InterfaceMethod org/codehaus/groovy/runtime/callsite/CallSite.callGroovyObjectGetProperty:(Ljava/lang/Object;)Ljava/lang/Object;
     199: ldc           #151                // String selectedIndex
     201: checkcast     #108                // class java/lang/String
     204: invokestatic  #138                // Method org/codehaus/groovy/runtime/ScriptBytecodeAdapter.setProperty:(Ljava/lang/Object;Ljava/lang/Class;Ljava/lang/Object;Ljava/lang/String;)V
     207: aload         9
     209: pop
     210: aload         6
     212: ldc           #153                // int 6
     214: aaload
     215: aload         4
     217: ldc           #155                // String selectedComponent
     219: invokeinterface #148,  3          // InterfaceMethod org/codehaus/groovy/runtime/callsite/CallSite.call:(Ljava/lang/Object;Ljava/lang/Object;)Ljava/lang/Object;
     224: astore        10
     226: aload         10
     228: aconst_null
     229: aload         6
     231: ldc           #156                // int 7
     233: aaload
     234: aload         5
     236: invokevirtual #114                // Method groovy/lang/Reference.get:()Ljava/lang/Object;
     239: checkcast     #116                // class groovy/util/FactoryBuilderSupport
     242: invokeinterface #132,  2          // InterfaceMethod org/codehaus/groovy/runtime/callsite/CallSite.callGroovyObjectGetProperty:(Ljava/lang/Object;)Ljava/lang/Object;
     247: ldc           #155                // String selectedComponent
     249: checkcast     #108                // class java/lang/String
     252: invokestatic  #138                // Method org/codehaus/groovy/runtime/ScriptBytecodeAdapter.setProperty:(Ljava/lang/Object;Ljava/lang/Class;Ljava/lang/Object;Ljava/lang/String;)V
     255: aload         10
     257: pop
     258: aload         6
     260: ldc           #157                // int 8
     262: aaload
     263: aload         4
     265: ldc           #159                // String titleProperty
     267: invokeinterface #148,  3          // InterfaceMethod org/codehaus/groovy/runtime/callsite/CallSite.call:(Ljava/lang/Object;Ljava/lang/Object;)Ljava/lang/Object;
     272: dup
     273: astore        11
     275: invokestatic  #165                // Method org/codehaus/groovy/runtime/typehandling/DefaultTypeTransformation.booleanUnbox:(Ljava/lang/Object;)Z
     278: ifeq          286
     281: aload         11
     283: goto          289
     286: getstatic     #167                // Field DEFAULT_DELEGATE_PROPERTY_TITLE:Ljava/lang/String;
     289: astore        12
     291: aload         6
     293: ldc           #168                // int 9
     295: aaload
     296: aload         6
     298: ldc           #169                // int 10
     300: aaload
     301: aload         5
     303: invokevirtual #114                // Method groovy/lang/Reference.get:()Ljava/lang/Object;
     306: checkcast     #116                // class groovy/util/FactoryBuilderSupport
     309: invokeinterface #132,  2          // InterfaceMethod org/codehaus/groovy/runtime/callsite/CallSite.callGroovyObjectGetProperty:(Ljava/lang/Object;)Ljava/lang/Object;
     314: getstatic     #171                // Field DELEGATE_PROPERTY_TITLE:Ljava/lang/String;
     317: aload         12
     319: invokeinterface #174,  4          // InterfaceMethod org/codehaus/groovy/runtime/callsite/CallSite.call:(Ljava/lang/Object;Ljava/lang/Object;Ljava/lang/Object;)Ljava/lang/Object;
     324: pop
     325: aload         12
     327: pop
     328: aload         6
     330: ldc           #175                // int 11
     332: aaload
     333: aload         4
     335: ldc           #177                // String tabIconProperty
     337: invokeinterface #148,  3          // InterfaceMethod org/codehaus/groovy/runtime/callsite/CallSite.call:(Ljava/lang/Object;Ljava/lang/Object;)Ljava/lang/Object;
     342: dup
     343: astore        13
     345: invokestatic  #165                // Method org/codehaus/groovy/runtime/typehandling/DefaultTypeTransformation.booleanUnbox:(Ljava/lang/Object;)Z
     348: ifeq          356
     351: aload         13
     353: goto          359
     356: getstatic     #179                // Field DEFAULT_DELEGATE_PROPERTY_TAB_ICON:Ljava/lang/String;
     359: astore        14
     361: aload         6
     363: ldc           #180                // int 12
     365: aaload
     366: aload         6
     368: ldc           #181                // int 13
     370: aaload
     371: aload         5
     373: invokevirtual #114                // Method groovy/lang/Reference.get:()Ljava/lang/Object;
     376: checkcast     #116                // class groovy/util/FactoryBuilderSupport
     379: invokeinterface #132,  2          // InterfaceMethod org/codehaus/groovy/runtime/callsite/CallSite.callGroovyObjectGetProperty:(Ljava/lang/Object;)Ljava/lang/Object;
     384: getstatic     #183                // Field DELEGATE_PROPERTY_TAB_ICON:Ljava/lang/String;
     387: aload         14
     389: invokeinterface #174,  4          // InterfaceMethod org/codehaus/groovy/runtime/callsite/CallSite.call:(Ljava/lang/Object;Ljava/lang/Object;Ljava/lang/Object;)Ljava/lang/Object;
     394: pop
     395: aload         14
     397: pop
     398: aload         6
     400: ldc           #184                // int 14
     402: aaload
     403: aload         4
     405: ldc           #186                // String tabDisabledIconProperty
     407: invokeinterface #148,  3          // InterfaceMethod org/codehaus/groovy/runtime/callsite/CallSite.call:(Ljava/lang/Object;Ljava/lang/Object;)Ljava/lang/Object;
     412: dup
     413: astore        15
     415: invokestatic  #165                // Method org/codehaus/groovy/runtime/typehandling/DefaultTypeTransformation.booleanUnbox:(Ljava/lang/Object;)Z
     418: ifeq          426
     421: aload         15
     423: goto          429
     426: getstatic     #188                // Field DEFAULT_DELEGATE_PROPERTY_TAB_DISABLED_ICON:Ljava/lang/String;
     429: astore        16
     431: aload         6
     433: ldc           #189                // int 15
     435: aaload
     436: aload         6
     438: ldc           #190                // int 16
     440: aaload
     441: aload         5
     443: invokevirtual #114                // Method groovy/lang/Reference.get:()Ljava/lang/Object;
     446: checkcast     #116                // class groovy/util/FactoryBuilderSupport
     449: invokeinterface #132,  2          // InterfaceMethod org/codehaus/groovy/runtime/callsite/CallSite.callGroovyObjectGetProperty:(Ljava/lang/Object;)Ljava/lang/Object;
     454: getstatic     #192                // Field DELEGATE_PROPERTY_TAB_DISABLED_ICON:Ljava/lang/String;
     457: aload         16
     459: invokeinterface #174,  4          // InterfaceMethod org/codehaus/groovy/runtime/callsite/CallSite.call:(Ljava/lang/Object;Ljava/lang/Object;Ljava/lang/Object;)Ljava/lang/Object;
     464: pop
     465: aload         16
     467: pop
     468: aload         6
     470: ldc           #193                // int 17
     472: aaload
     473: aload         4
     475: ldc           #195                // String tabToolTipProperty
     477: invokeinterface #148,  3          // InterfaceMethod org/codehaus/groovy/runtime/callsite/CallSite.call:(Ljava/lang/Object;Ljava/lang/Object;)Ljava/lang/Object;
     482: dup
     483: astore        17
     485: invokestatic  #165                // Method org/codehaus/groovy/runtime/typehandling/DefaultTypeTransformation.booleanUnbox:(Ljava/lang/Object;)Z
     488: ifeq          496
     491: aload         17
     493: goto          499
     496: getstatic     #197                // Field DEFAULT_DELEGATE_PROPERTY_TAB_TOOL_TIP:Ljava/lang/String;
     499: astore        18
     501: aload         6
     503: ldc           #198                // int 18
     505: aaload
     506: aload         6
     508: ldc           #199                // int 19
     510: aaload
     511: aload         5
     513: invokevirtual #114                // Method groovy/lang/Reference.get:()Ljava/lang/Object;
     516: checkcast     #116                // class groovy/util/FactoryBuilderSupport
     519: invokeinterface #132,  2          // InterfaceMethod org/codehaus/groovy/runtime/callsite/CallSite.callGroovyObjectGetProperty:(Ljava/lang/Object;)Ljava/lang/Object;
     524: getstatic     #201                // Field DELEGATE_PROPERTY_TAB_TOOL_TIP:Ljava/lang/String;
     527: aload         18
     529: invokeinterface #174,  4          // InterfaceMethod org/codehaus/groovy/runtime/callsite/CallSite.call:(Ljava/lang/Object;Ljava/lang/Object;Ljava/lang/Object;)Ljava/lang/Object;
     534: pop
     535: aload         18
     537: pop
     538: aload         6
     540: ldc           #202                // int 20
     542: aaload
     543: aload         4
     545: ldc           #204                // String tabBackgroundProperty
     547: invokeinterface #148,  3          // InterfaceMethod org/codehaus/groovy/runtime/callsite/CallSite.call:(Ljava/lang/Object;Ljava/lang/Object;)Ljava/lang/Object;
     552: dup
     553: astore        19
     555: invokestatic  #165                // Method org/codehaus/groovy/runtime/typehandling/DefaultTypeTransformation.booleanUnbox:(Ljava/lang/Object;)Z
     558: ifeq          566
     561: aload         19
     563: goto          569
     566: getstatic     #206                // Field DEFAULT_DELEGATE_PROPERTY_TAB_BACKGROUND:Ljava/lang/String;
     569: astore        20
     571: aload         6
     573: ldc           #207                // int 21
     575: aaload
     576: aload         6
     578: ldc           #208                // int 22
     580: aaload
     581: aload         5
     583: invokevirtual #114                // Method groovy/lang/Reference.get:()Ljava/lang/Object;
     586: checkcast     #116                // class groovy/util/FactoryBuilderSupport
     589: invokeinterface #132,  2          // InterfaceMethod org/codehaus/groovy/runtime/callsite/CallSite.callGroovyObjectGetProperty:(Ljava/lang/Object;)Ljava/lang/Object;
     594: getstatic     #210                // Field DELEGATE_PROPERTY_TAB_BACKGROUND:Ljava/lang/String;
     597: aload         20
     599: invokeinterface #174,  4          // InterfaceMethod org/codehaus/groovy/runtime/callsite/CallSite.call:(Ljava/lang/Object;Ljava/lang/Object;Ljava/lang/Object;)Ljava/lang/Object;
     604: pop
     605: aload         20
     607: pop
     608: aload         6
     610: ldc           #211                // int 23
     612: aaload
     613: aload         4
     615: ldc           #213                // String tabForegroundProperty
     617: invokeinterface #148,  3          // InterfaceMethod org/codehaus/groovy/runtime/callsite/CallSite.call:(Ljava/lang/Object;Ljava/lang/Object;)Ljava/lang/Object;
     622: dup
     623: astore        21
     625: invokestatic  #165                // Method org/codehaus/groovy/runtime/typehandling/DefaultTypeTransformation.booleanUnbox:(Ljava/lang/Object;)Z
     628: ifeq          636
     631: aload         21
     633: goto          639
     636: getstatic     #215                // Field DEFAULT_DELEGATE_PROPERTY_TAB_FOREGROUND:Ljava/lang/String;
     639: astore        22
     641: aload         6
     643: ldc           #216                // int 24
     645: aaload
     646: aload         6
     648: ldc           #217                // int 25
     650: aaload
     651: aload         5
     653: invokevirtual #114                // Method groovy/lang/Reference.get:()Ljava/lang/Object;
     656: checkcast     #116                // class groovy/util/FactoryBuilderSupport
     659: invokeinterface #132,  2          // InterfaceMethod org/codehaus/groovy/runtime/callsite/CallSite.callGroovyObjectGetProperty:(Ljava/lang/Object;)Ljava/lang/Object;
     664: getstatic     #219                // Field DELEGATE_PROPERTY_TAB_FOREGROUND:Ljava/lang/String;
     667: aload         22
     669: invokeinterface #174,  4          // InterfaceMethod org/codehaus/groovy/runtime/callsite/CallSite.call:(Ljava/lang/Object;Ljava/lang/Object;Ljava/lang/Object;)Ljava/lang/Object;
     674: pop
     675: aload         22
     677: pop
     678: aload         6
     680: ldc           #220                // int 26
     682: aaload
     683: aload         4
     685: ldc           #222                // String tabEnabledProperty
     687: invokeinterface #148,  3          // InterfaceMethod org/codehaus/groovy/runtime/callsite/CallSite.call:(Ljava/lang/Object;Ljava/lang/Object;)Ljava/lang/Object;
     692: dup
     693: astore        23
     695: invokestatic  #165                // Method org/codehaus/groovy/runtime/typehandling/DefaultTypeTransformation.booleanUnbox:(Ljava/lang/Object;)Z
     698: ifeq          706
     701: aload         23
     703: goto          709
     706: getstatic     #224                // Field DEFAULT_DELEGATE_PROPERTY_TAB_ENABLED:Ljava/lang/String;
     709: astore        24
     711: aload         6
     713: ldc           #225                // int 27
     715: aaload
     716: aload         6
     718: ldc           #226                // int 28
     720: aaload
     721: aload         5
     723: invokevirtual #114                // Method groovy/lang/Reference.get:()Ljava/lang/Object;
     726: checkcast     #116                // class groovy/util/FactoryBuilderSupport
     729: invokeinterface #132,  2          // InterfaceMethod org/codehaus/groovy/runtime/callsite/CallSite.callGroovyObjectGetProperty:(Ljava/lang/Object;)Ljava/lang/Object;
     734: getstatic     #228                // Field DELEGATE_PROPERTY_TAB_ENABLED:Ljava/lang/String;
     737: aload         24
     739: invokeinterface #174,  4          // InterfaceMethod org/codehaus/groovy/runtime/callsite/CallSite.call:(Ljava/lang/Object;Ljava/lang/Object;Ljava/lang/Object;)Ljava/lang/Object;
     744: pop
     745: aload         24
     747: pop
     748: aload         6
     750: ldc           #229                // int 29
     752: aaload
     753: aload         4
     755: ldc           #231                // String tabMnemonicProperty
     757: invokeinterface #148,  3          // InterfaceMethod org/codehaus/groovy/runtime/callsite/CallSite.call:(Ljava/lang/Object;Ljava/lang/Object;)Ljava/lang/Object;
     762: dup
     763: astore        25
     765: invokestatic  #165                // Method org/codehaus/groovy/runtime/typehandling/DefaultTypeTransformation.booleanUnbox:(Ljava/lang/Object;)Z
     768: ifeq          776
     771: aload         25
     773: goto          779
     776: getstatic     #233                // Field DEFAULT_DELEGATE_PROPERTY_TAB_MNEMONIC:Ljava/lang/String;
     779: astore        26
     781: aload         6
     783: ldc           #234                // int 30
     785: aaload
     786: aload         6
     788: ldc           #235                // int 31
     790: aaload
     791: aload         5
     793: invokevirtual #114                // Method groovy/lang/Reference.get:()Ljava/lang/Object;
     796: checkcast     #116                // class groovy/util/FactoryBuilderSupport
     799: invokeinterface #132,  2          // InterfaceMethod org/codehaus/groovy/runtime/callsite/CallSite.callGroovyObjectGetProperty:(Ljava/lang/Object;)Ljava/lang/Object;
     804: getstatic     #237                // Field DELEGATE_PROPERTY_TAB_MNEMONIC:Ljava/lang/String;
     807: aload         26
     809: invokeinterface #174,  4          // InterfaceMethod org/codehaus/groovy/runtime/callsite/CallSite.call:(Ljava/lang/Object;Ljava/lang/Object;Ljava/lang/Object;)Ljava/lang/Object;
     814: pop
     815: aload         26
     817: pop
     818: aload         6
     820: ldc           #238                // int 32
     822: aaload
     823: aload         4
     825: ldc           #240                // String tabDisplayedMnemonicIndexProperty
     827: invokeinterface #148,  3          // InterfaceMethod org/codehaus/groovy/runtime/callsite/CallSite.call:(Ljava/lang/Object;Ljava/lang/Object;)Ljava/lang/Object;
     832: dup
     833: astore        27
     835: invokestatic  #165                // Method org/codehaus/groovy/runtime/typehandling/DefaultTypeTransformation.booleanUnbox:(Ljava/lang/Object;)Z
     838: ifeq          846
     841: aload         27
     843: goto          849
     846: getstatic     #242                // Field DEFAULT_DELEGATE_PROPERTY_TAB_DISPLAYED_MNEMONIC_INDEX:Ljava/lang/String;
     849: astore        28
     851: aload         6
     853: ldc           #243                // int 33
     855: aaload
     856: aload         6
     858: ldc           #244                // int 34
     860: aaload
     861: aload         5
     863: invokevirtual #114                // Method groovy/lang/Reference.get:()Ljava/lang/Object;
     866: checkcast     #116                // class groovy/util/FactoryBuilderSupport
     869: invokeinterface #132,  2          // InterfaceMethod org/codehaus/groovy/runtime/callsite/CallSite.callGroovyObjectGetProperty:(Ljava/lang/Object;)Ljava/lang/Object;
     874: getstatic     #246                // Field DELEGATE_PROPERTY_TAB_DISPLAYED_MNEMONIC_INDEX:Ljava/lang/String;
     877: aload         28
     879: invokeinterface #174,  4          // InterfaceMethod org/codehaus/groovy/runtime/callsite/CallSite.call:(Ljava/lang/Object;Ljava/lang/Object;Ljava/lang/Object;)Ljava/lang/Object;
     884: pop
     885: aload         28
     887: pop
     888: aload         7
     890: invokevirtual #114                // Method groovy/lang/Reference.get:()Ljava/lang/Object;
     893: areturn
     894: aconst_null
     895: areturn

  public static void inspectChild(groovy.util.FactoryBuilderSupport, java.lang.Object, java.util.Map);
    Code:
       0: invokestatic  #81                 // Method $getCallSiteArray:()[Lorg/codehaus/groovy/runtime/callsite/CallSite;
       3: astore_3
       4: aload_1
       5: instanceof    #259                // class java/awt/Component
       8: ifne          15
      11: iconst_1
      12: goto          16
      15: iconst_0
      16: ifne          26
      19: aload_1
      20: instanceof    #261                // class java/awt/Window
      23: ifeq          30
      26: iconst_1
      27: goto          31
      30: iconst_0
      31: ifeq          35
      34: return
      35: aload_3
      36: ldc_w         #262                // int 35
      39: aaload
      40: aload_2
      41: aload_3
      42: ldc_w         #263                // int 36
      45: aaload
      46: aload_3
      47: ldc_w         #264                // int 37
      50: aaload
      51: aload_0
      52: invokeinterface #267,  2          // InterfaceMethod org/codehaus/groovy/runtime/callsite/CallSite.callGroovyObjectGetPropertySafe:(Ljava/lang/Object;)Ljava/lang/Object;
      57: getstatic     #171                // Field DELEGATE_PROPERTY_TITLE:Ljava/lang/String;
      60: invokeinterface #270,  3          // InterfaceMethod org/codehaus/groovy/runtime/callsite/CallSite.callSafe:(Ljava/lang/Object;Ljava/lang/Object;)Ljava/lang/Object;
      65: dup
      66: astore        4
      68: invokestatic  #165                // Method org/codehaus/groovy/runtime/typehandling/DefaultTypeTransformation.booleanUnbox:(Ljava/lang/Object;)Z
      71: ifeq          79
      74: aload         4
      76: goto          82
      79: getstatic     #167                // Field DEFAULT_DELEGATE_PROPERTY_TITLE:Ljava/lang/String;
      82: invokeinterface #148,  3          // InterfaceMethod org/codehaus/groovy/runtime/callsite/CallSite.call:(Ljava/lang/Object;Ljava/lang/Object;)Ljava/lang/Object;
      87: astore        5
      89: aload         5
      91: pop
      92: aload_3
      93: ldc_w         #271                // int 38
      96: aaload
      97: aload_2
      98: aload_3
      99: ldc_w         #272                // int 39
     102: aaload
     103: aload_3
     104: ldc_w         #273                // int 40
     107: aaload
     108: aload_0
     109: invokeinterface #267,  2          // InterfaceMethod org/codehaus/groovy/runtime/callsite/CallSite.callGroovyObjectGetPropertySafe:(Ljava/lang/Object;)Ljava/lang/Object;
     114: getstatic     #183                // Field DELEGATE_PROPERTY_TAB_ICON:Ljava/lang/String;
     117: invokeinterface #270,  3          // InterfaceMethod org/codehaus/groovy/runtime/callsite/CallSite.callSafe:(Ljava/lang/Object;Ljava/lang/Object;)Ljava/lang/Object;
     122: dup
     123: astore        6
     125: invokestatic  #165                // Method org/codehaus/groovy/runtime/typehandling/DefaultTypeTransformation.booleanUnbox:(Ljava/lang/Object;)Z
     128: ifeq          136
     131: aload         6
     133: goto          139
     136: getstatic     #179                // Field DEFAULT_DELEGATE_PROPERTY_TAB_ICON:Ljava/lang/String;
     139: invokeinterface #148,  3          // InterfaceMethod org/codehaus/groovy/runtime/callsite/CallSite.call:(Ljava/lang/Object;Ljava/lang/Object;)Ljava/lang/Object;
     144: astore        7
     146: aload         7
     148: pop
     149: aload_3
     150: ldc_w         #274                // int 41
     153: aaload
     154: aload_2
     155: aload_3
     156: ldc_w         #275                // int 42
     159: aaload
     160: aload_3
     161: ldc_w         #276                // int 43
     164: aaload
     165: aload_0
     166: invokeinterface #267,  2          // InterfaceMethod org/codehaus/groovy/runtime/callsite/CallSite.callGroovyObjectGetPropertySafe:(Ljava/lang/Object;)Ljava/lang/Object;
     171: getstatic     #192                // Field DELEGATE_PROPERTY_TAB_DISABLED_ICON:Ljava/lang/String;
     174: invokeinterface #270,  3          // InterfaceMethod org/codehaus/groovy/runtime/callsite/CallSite.callSafe:(Ljava/lang/Object;Ljava/lang/Object;)Ljava/lang/Object;
     179: dup
     180: astore        8
     182: invokestatic  #165                // Method org/codehaus/groovy/runtime/typehandling/DefaultTypeTransformation.booleanUnbox:(Ljava/lang/Object;)Z
     185: ifeq          193
     188: aload         8
     190: goto          196
     193: getstatic     #188                // Field DEFAULT_DELEGATE_PROPERTY_TAB_DISABLED_ICON:Ljava/lang/String;
     196: invokeinterface #148,  3          // InterfaceMethod org/codehaus/groovy/runtime/callsite/CallSite.call:(Ljava/lang/Object;Ljava/lang/Object;)Ljava/lang/Object;
     201: astore        9
     203: aload         9
     205: pop
     206: aload_3
     207: ldc_w         #277                // int 44
     210: aaload
     211: aload_2
     212: aload_3
     213: ldc_w         #278                // int 45
     216: aaload
     217: aload_3
     218: ldc_w         #279                // int 46
     221: aaload
     222: aload_0
     223: invokeinterface #267,  2          // InterfaceMethod org/codehaus/groovy/runtime/callsite/CallSite.callGroovyObjectGetPropertySafe:(Ljava/lang/Object;)Ljava/lang/Object;
     228: getstatic     #201                // Field DELEGATE_PROPERTY_TAB_TOOL_TIP:Ljava/lang/String;
     231: invokeinterface #270,  3          // InterfaceMethod org/codehaus/groovy/runtime/callsite/CallSite.callSafe:(Ljava/lang/Object;Ljava/lang/Object;)Ljava/lang/Object;
     236: dup
     237: astore        10
     239: invokestatic  #165                // Method org/codehaus/groovy/runtime/typehandling/DefaultTypeTransformation.booleanUnbox:(Ljava/lang/Object;)Z
     242: ifeq          250
     245: aload         10
     247: goto          253
     250: getstatic     #197                // Field DEFAULT_DELEGATE_PROPERTY_TAB_TOOL_TIP:Ljava/lang/String;
     253: invokeinterface #148,  3          // InterfaceMethod org/codehaus/groovy/runtime/callsite/CallSite.call:(Ljava/lang/Object;Ljava/lang/Object;)Ljava/lang/Object;
     258: astore        11
     260: aload         11
     262: pop
     263: aload_3
     264: ldc_w         #280                // int 47
     267: aaload
     268: aload_2
     269: aload_3
     270: ldc_w         #281                // int 48
     273: aaload
     274: aload_3
     275: ldc_w         #282                // int 49
     278: aaload
     279: aload_0
     280: invokeinterface #267,  2          // InterfaceMethod org/codehaus/groovy/runtime/callsite/CallSite.callGroovyObjectGetPropertySafe:(Ljava/lang/Object;)Ljava/lang/Object;
     285: getstatic     #210                // Field DELEGATE_PROPERTY_TAB_BACKGROUND:Ljava/lang/String;
     288: invokeinterface #270,  3          // InterfaceMethod org/codehaus/groovy/runtime/callsite/CallSite.callSafe:(Ljava/lang/Object;Ljava/lang/Object;)Ljava/lang/Object;
     293: dup
     294: astore        12
     296: invokestatic  #165                // Method org/codehaus/groovy/runtime/typehandling/DefaultTypeTransformation.booleanUnbox:(Ljava/lang/Object;)Z
     299: ifeq          307
     302: aload         12
     304: goto          310
     307: getstatic     #206                // Field DEFAULT_DELEGATE_PROPERTY_TAB_BACKGROUND:Ljava/lang/String;
     310: invokeinterface #148,  3          // InterfaceMethod org/codehaus/groovy/runtime/callsite/CallSite.call:(Ljava/lang/Object;Ljava/lang/Object;)Ljava/lang/Object;
     315: astore        13
     317: aload         13
     319: pop
     320: aload_3
     321: ldc_w         #283                // int 50
     324: aaload
     325: aload_2
     326: aload_3
     327: ldc_w         #284                // int 51
     330: aaload
     331: aload_3
     332: ldc_w         #285                // int 52
     335: aaload
     336: aload_0
     337: invokeinterface #267,  2          // InterfaceMethod org/codehaus/groovy/runtime/callsite/CallSite.callGroovyObjectGetPropertySafe:(Ljava/lang/Object;)Ljava/lang/Object;
     342: getstatic     #219                // Field DELEGATE_PROPERTY_TAB_FOREGROUND:Ljava/lang/String;
     345: invokeinterface #270,  3          // InterfaceMethod org/codehaus/groovy/runtime/callsite/CallSite.callSafe:(Ljava/lang/Object;Ljava/lang/Object;)Ljava/lang/Object;
     350: dup
     351: astore        14
     353: invokestatic  #165                // Method org/codehaus/groovy/runtime/typehandling/DefaultTypeTransformation.booleanUnbox:(Ljava/lang/Object;)Z
     356: ifeq          364
     359: aload         14
     361: goto          367
     364: getstatic     #215                // Field DEFAULT_DELEGATE_PROPERTY_TAB_FOREGROUND:Ljava/lang/String;
     367: invokeinterface #148,  3          // InterfaceMethod org/codehaus/groovy/runtime/callsite/CallSite.call:(Ljava/lang/Object;Ljava/lang/Object;)Ljava/lang/Object;
     372: astore        15
     374: aload         15
     376: pop
     377: aload_3
     378: ldc_w         #286                // int 53
     381: aaload
     382: aload_2
     383: aload_3
     384: ldc_w         #287                // int 54
     387: aaload
     388: aload_3
     389: ldc_w         #288                // int 55
     392: aaload
     393: aload_0
     394: invokeinterface #267,  2          // InterfaceMethod org/codehaus/groovy/runtime/callsite/CallSite.callGroovyObjectGetPropertySafe:(Ljava/lang/Object;)Ljava/lang/Object;
     399: getstatic     #228                // Field DELEGATE_PROPERTY_TAB_ENABLED:Ljava/lang/String;
     402: invokeinterface #270,  3          // InterfaceMethod org/codehaus/groovy/runtime/callsite/CallSite.callSafe:(Ljava/lang/Object;Ljava/lang/Object;)Ljava/lang/Object;
     407: dup
     408: astore        16
     410: invokestatic  #165                // Method org/codehaus/groovy/runtime/typehandling/DefaultTypeTransformation.booleanUnbox:(Ljava/lang/Object;)Z
     413: ifeq          421
     416: aload         16
     418: goto          424
     421: getstatic     #224                // Field DEFAULT_DELEGATE_PROPERTY_TAB_ENABLED:Ljava/lang/String;
     424: invokeinterface #148,  3          // InterfaceMethod org/codehaus/groovy/runtime/callsite/CallSite.call:(Ljava/lang/Object;Ljava/lang/Object;)Ljava/lang/Object;
     429: astore        17
     431: aload         17
     433: pop
     434: aload_3
     435: ldc_w         #289                // int 56
     438: aaload
     439: aload_2
     440: aload_3
     441: ldc_w         #290                // int 57
     444: aaload
     445: aload_3
     446: ldc_w         #291                // int 58
     449: aaload
     450: aload_0
     451: invokeinterface #267,  2          // InterfaceMethod org/codehaus/groovy/runtime/callsite/CallSite.callGroovyObjectGetPropertySafe:(Ljava/lang/Object;)Ljava/lang/Object;
     456: getstatic     #237                // Field DELEGATE_PROPERTY_TAB_MNEMONIC:Ljava/lang/String;
     459: invokeinterface #270,  3          // InterfaceMethod org/codehaus/groovy/runtime/callsite/CallSite.callSafe:(Ljava/lang/Object;Ljava/lang/Object;)Ljava/lang/Object;
     464: dup
     465: astore        18
     467: invokestatic  #165                // Method org/codehaus/groovy/runtime/typehandling/DefaultTypeTransformation.booleanUnbox:(Ljava/lang/Object;)Z
     470: ifeq          478
     473: aload         18
     475: goto          481
     478: getstatic     #233                // Field DEFAULT_DELEGATE_PROPERTY_TAB_MNEMONIC:Ljava/lang/String;
     481: invokeinterface #148,  3          // InterfaceMethod org/codehaus/groovy/runtime/callsite/CallSite.call:(Ljava/lang/Object;Ljava/lang/Object;)Ljava/lang/Object;
     486: astore        19
     488: aload         19
     490: pop
     491: aload_3
     492: ldc_w         #292                // int 59
     495: aaload
     496: aload_2
     497: aload_3
     498: ldc_w         #293                // int 60
     501: aaload
     502: aload_3
     503: ldc_w         #294                // int 61
     506: aaload
     507: aload_0
     508: invokeinterface #267,  2          // InterfaceMethod org/codehaus/groovy/runtime/callsite/CallSite.callGroovyObjectGetPropertySafe:(Ljava/lang/Object;)Ljava/lang/Object;
     513: getstatic     #246                // Field DELEGATE_PROPERTY_TAB_DISPLAYED_MNEMONIC_INDEX:Ljava/lang/String;
     516: invokeinterface #270,  3          // InterfaceMethod org/codehaus/groovy/runtime/callsite/CallSite.callSafe:(Ljava/lang/Object;Ljava/lang/Object;)Ljava/lang/Object;
     521: dup
     522: astore        20
     524: invokestatic  #165                // Method org/codehaus/groovy/runtime/typehandling/DefaultTypeTransformation.booleanUnbox:(Ljava/lang/Object;)Z
     527: ifeq          535
     530: aload         20
     532: goto          538
     535: getstatic     #242                // Field DEFAULT_DELEGATE_PROPERTY_TAB_DISPLAYED_MNEMONIC_INDEX:Ljava/lang/String;
     538: invokeinterface #148,  3          // InterfaceMethod org/codehaus/groovy/runtime/callsite/CallSite.call:(Ljava/lang/Object;Ljava/lang/Object;)Ljava/lang/Object;
     543: astore        21
     545: aload         21
     547: pop
     548: aload_3
     549: ldc_w         #295                // int 62
     552: aaload
     553: aload_3
     554: ldc_w         #296                // int 63
     557: aaload
     558: aload_0
     559: invokeinterface #132,  2          // InterfaceMethod org/codehaus/groovy/runtime/callsite/CallSite.callGroovyObjectGetProperty:(Ljava/lang/Object;)Ljava/lang/Object;
     564: getstatic     #298                // Field CONTEXT_DATA_KEY:Ljava/lang/String;
     567: invokeinterface #148,  3          // InterfaceMethod org/codehaus/groovy/runtime/callsite/CallSite.call:(Ljava/lang/Object;Ljava/lang/Object;)Ljava/lang/Object;
     572: dup
     573: astore        22
     575: invokestatic  #165                // Method org/codehaus/groovy/runtime/typehandling/DefaultTypeTransformation.booleanUnbox:(Ljava/lang/Object;)Z
     578: ifeq          586
     581: aload         22
     583: goto          593
     586: iconst_0
     587: anewarray     #110                // class java/lang/Object
     590: invokestatic  #302                // Method org/codehaus/groovy/runtime/ScriptBytecodeAdapter.createMap:([Ljava/lang/Object;)Ljava/util/Map;
     593: astore        23
     595: aload         23
     597: pop
     598: aload_3
     599: ldc_w         #303                // int 64
     602: aaload
     603: aload         23
     605: invokeinterface #305,  2          // InterfaceMethod org/codehaus/groovy/runtime/callsite/CallSite.call:(Ljava/lang/Object;)Ljava/lang/Object;
     610: invokestatic  #165                // Method org/codehaus/groovy/runtime/typehandling/DefaultTypeTransformation.booleanUnbox:(Ljava/lang/Object;)Z
     613: ifeq          643
     616: aload_3
     617: ldc_w         #306                // int 65
     620: aaload
     621: aload_3
     622: ldc_w         #307                // int 66
     625: aaload
     626: aload_0
     627: invokeinterface #132,  2          // InterfaceMethod org/codehaus/groovy/runtime/callsite/CallSite.callGroovyObjectGetProperty:(Ljava/lang/Object;)Ljava/lang/Object;
     632: getstatic     #298                // Field CONTEXT_DATA_KEY:Ljava/lang/String;
     635: aload         23
     637: invokeinterface #174,  4          // InterfaceMethod org/codehaus/groovy/runtime/callsite/CallSite.call:(Ljava/lang/Object;Ljava/lang/Object;Ljava/lang/Object;)Ljava/lang/Object;
     642: pop
     643: aload_3
     644: ldc_w         #308                // int 67
     647: aaload
     648: aload         23
     650: aload_1
     651: bipush        9
     653: anewarray     #110                // class java/lang/Object
     656: dup
     657: iconst_0
     658: aload         5
     660: aastore
     661: dup
     662: iconst_1
     663: aload         7
     665: aastore
     666: dup
     667: iconst_2
     668: aload         9
     670: aastore
     671: dup
     672: iconst_3
     673: aload         11
     675: aastore
     676: dup
     677: iconst_4
     678: aload         13
     680: aastore
     681: dup
     682: iconst_5
     683: aload         15
     685: aastore
     686: dup
     687: bipush        6
     689: aload         17
     691: aastore
     692: dup
     693: bipush        7
     695: aload         19
     697: aastore
     698: dup
     699: bipush        8
     701: aload         21
     703: aastore
     704: invokestatic  #312                // Method org/codehaus/groovy/runtime/ScriptBytecodeAdapter.createList:([Ljava/lang/Object;)Ljava/util/List;
     707: invokeinterface #174,  4          // InterfaceMethod org/codehaus/groovy/runtime/callsite/CallSite.call:(Ljava/lang/Object;Ljava/lang/Object;Ljava/lang/Object;)Ljava/lang/Object;
     712: pop
     713: return

  public void setChild(groovy.util.FactoryBuilderSupport, java.lang.Object, java.lang.Object);
    Code:
       0: invokestatic  #81                 // Method $getCallSiteArray:()[Lorg/codehaus/groovy/runtime/callsite/CallSite;
       3: astore        4
       5: aload_3
       6: instanceof    #259                // class java/awt/Component
       9: ifne          16
      12: iconst_1
      13: goto          17
      16: iconst_0
      17: ifne          27
      20: aload_3
      21: instanceof    #261                // class java/awt/Window
      24: ifeq          31
      27: iconst_1
      28: goto          32
      31: iconst_0
      32: ifeq          36
      35: return
      36: aload         4
      38: ldc_w         #327                // int 68
      41: aaload
      42: aload         4
      44: ldc_w         #328                // int 69
      47: aaload
      48: aload         4
      50: ldc_w         #329                // int 70
      53: aaload
      54: aload_1
      55: invokeinterface #132,  2          // InterfaceMethod org/codehaus/groovy/runtime/callsite/CallSite.callGroovyObjectGetProperty:(Ljava/lang/Object;)Ljava/lang/Object;
      60: getstatic     #298                // Field CONTEXT_DATA_KEY:Ljava/lang/String;
      63: invokeinterface #148,  3          // InterfaceMethod org/codehaus/groovy/runtime/callsite/CallSite.call:(Ljava/lang/Object;Ljava/lang/Object;)Ljava/lang/Object;
      68: aload_3
      69: invokeinterface #270,  3          // InterfaceMethod org/codehaus/groovy/runtime/callsite/CallSite.callSafe:(Ljava/lang/Object;Ljava/lang/Object;)Ljava/lang/Object;
      74: dup
      75: astore        5
      77: invokestatic  #165                // Method org/codehaus/groovy/runtime/typehandling/DefaultTypeTransformation.booleanUnbox:(Ljava/lang/Object;)Z
      80: ifeq          88
      83: aload         5
      85: goto          135
      88: bipush        9
      90: anewarray     #110                // class java/lang/Object
      93: dup
      94: iconst_0
      95: aconst_null
      96: aastore
      97: dup
      98: iconst_1
      99: aconst_null
     100: aastore
     101: dup
     102: iconst_2
     103: aconst_null
     104: aastore
     105: dup
     106: iconst_3
     107: aconst_null
     108: aastore
     109: dup
     110: iconst_4
     111: aconst_null
     112: aastore
     113: dup
     114: iconst_5
     115: aconst_null
     116: aastore
     117: dup
     118: bipush        6
     120: aconst_null
     121: aastore
     122: dup
     123: bipush        7
     125: aconst_null
     126: aastore
     127: dup
     128: bipush        8
     130: aconst_null
     131: aastore
     132: invokestatic  #312                // Method org/codehaus/groovy/runtime/ScriptBytecodeAdapter.createList:([Ljava/lang/Object;)Ljava/util/List;
     135: astore        6
     137: aload         6
     139: pop
     140: aload         4
     142: ldc_w         #330                // int 71
     145: aaload
     146: aload         6
     148: iconst_0
     149: invokestatic  #336                // Method java/lang/Integer.valueOf:(I)Ljava/lang/Integer;
     152: invokeinterface #148,  3          // InterfaceMethod org/codehaus/groovy/runtime/callsite/CallSite.call:(Ljava/lang/Object;Ljava/lang/Object;)Ljava/lang/Object;
     157: aconst_null
     158: invokestatic  #340                // Method org/codehaus/groovy/runtime/ScriptBytecodeAdapter.compareEqual:(Ljava/lang/Object;Ljava/lang/Object;)Z
     161: ifeq          201
     164: aload         4
     166: ldc_w         #341                // int 72
     169: aaload
     170: aload_3
     171: invokeinterface #144,  2          // InterfaceMethod org/codehaus/groovy/runtime/callsite/CallSite.callGetProperty:(Ljava/lang/Object;)Ljava/lang/Object;
     176: astore        7
     178: aload         4
     180: ldc_w         #342                // int 73
     183: aaload
     184: aload         6
     186: iconst_0
     187: invokestatic  #336                // Method java/lang/Integer.valueOf:(I)Ljava/lang/Integer;
     190: aload         7
     192: invokeinterface #174,  4          // InterfaceMethod org/codehaus/groovy/runtime/callsite/CallSite.call:(Ljava/lang/Object;Ljava/lang/Object;Ljava/lang/Object;)Ljava/lang/Object;
     197: pop
     198: aload         7
     200: pop
     201: aload         4
     203: ldc_w         #343                // int 74
     206: aaload
     207: aload_2
     208: aload         4
     210: ldc_w         #344                // int 75
     213: aaload
     214: aload         6
     216: iconst_0
     217: invokestatic  #336                // Method java/lang/Integer.valueOf:(I)Ljava/lang/Integer;
     220: invokeinterface #148,  3          // InterfaceMethod org/codehaus/groovy/runtime/callsite/CallSite.call:(Ljava/lang/Object;Ljava/lang/Object;)Ljava/lang/Object;
     225: aload         4
     227: ldc_w         #345                // int 76
     230: aaload
     231: aload         6
     233: iconst_1
     234: invokestatic  #336                // Method java/lang/Integer.valueOf:(I)Ljava/lang/Integer;
     237: invokeinterface #148,  3          // InterfaceMethod org/codehaus/groovy/runtime/callsite/CallSite.call:(Ljava/lang/Object;Ljava/lang/Object;)Ljava/lang/Object;
     242: aload_3
     243: aload         4
     245: ldc_w         #346                // int 77
     248: aaload
     249: aload         6
     251: iconst_3
     252: invokestatic  #336                // Method java/lang/Integer.valueOf:(I)Ljava/lang/Integer;
     255: invokeinterface #148,  3          // InterfaceMethod org/codehaus/groovy/runtime/callsite/CallSite.call:(Ljava/lang/Object;Ljava/lang/Object;)Ljava/lang/Object;
     260: invokeinterface #349,  6          // InterfaceMethod org/codehaus/groovy/runtime/callsite/CallSite.call:(Ljava/lang/Object;Ljava/lang/Object;Ljava/lang/Object;Ljava/lang/Object;Ljava/lang/Object;)Ljava/lang/Object;
     265: pop
     266: aload         4
     268: ldc_w         #350                // int 78
     271: aaload
     272: aload_2
     273: aload_3
     274: invokeinterface #148,  3          // InterfaceMethod org/codehaus/groovy/runtime/callsite/CallSite.call:(Ljava/lang/Object;Ljava/lang/Object;)Ljava/lang/Object;
     279: invokestatic  #354                // Method org/codehaus/groovy/runtime/typehandling/DefaultTypeTransformation.intUnbox:(Ljava/lang/Object;)I
     282: istore        8
     284: iload         8
     286: pop
     287: aload         4
     289: ldc_w         #355                // int 79
     292: aaload
     293: aload         6
     295: iconst_2
     296: invokestatic  #336                // Method java/lang/Integer.valueOf:(I)Ljava/lang/Integer;
     299: invokeinterface #148,  3          // InterfaceMethod org/codehaus/groovy/runtime/callsite/CallSite.call:(Ljava/lang/Object;Ljava/lang/Object;)Ljava/lang/Object;
     304: invokestatic  #165                // Method org/codehaus/groovy/runtime/typehandling/DefaultTypeTransformation.booleanUnbox:(Ljava/lang/Object;)Z
     307: ifeq          345
     310: aload         4
     312: ldc_w         #356                // int 80
     315: aaload
     316: aload_2
     317: iload         8
     319: invokestatic  #336                // Method java/lang/Integer.valueOf:(I)Ljava/lang/Integer;
     322: aload         4
     324: ldc_w         #357                // int 81
     327: aaload
     328: aload         6
     330: iconst_2
     331: invokestatic  #336                // Method java/lang/Integer.valueOf:(I)Ljava/lang/Integer;
     334: invokeinterface #148,  3          // InterfaceMethod org/codehaus/groovy/runtime/callsite/CallSite.call:(Ljava/lang/Object;Ljava/lang/Object;)Ljava/lang/Object;
     339: invokeinterface #174,  4          // InterfaceMethod org/codehaus/groovy/runtime/callsite/CallSite.call:(Ljava/lang/Object;Ljava/lang/Object;Ljava/lang/Object;)Ljava/lang/Object;
     344: pop
     345: aload         4
     347: ldc_w         #358                // int 82
     350: aaload
     351: aload         6
     353: iconst_4
     354: invokestatic  #336                // Method java/lang/Integer.valueOf:(I)Ljava/lang/Integer;
     357: invokeinterface #148,  3          // InterfaceMethod org/codehaus/groovy/runtime/callsite/CallSite.call:(Ljava/lang/Object;Ljava/lang/Object;)Ljava/lang/Object;
     362: invokestatic  #165                // Method org/codehaus/groovy/runtime/typehandling/DefaultTypeTransformation.booleanUnbox:(Ljava/lang/Object;)Z
     365: ifeq          403
     368: aload         4
     370: ldc_w         #359                // int 83
     373: aaload
     374: aload_2
     375: iload         8
     377: invokestatic  #336                // Method java/lang/Integer.valueOf:(I)Ljava/lang/Integer;
     380: aload         4
     382: ldc_w         #360                // int 84
     385: aaload
     386: aload         6
     388: iconst_4
     389: invokestatic  #336                // Method java/lang/Integer.valueOf:(I)Ljava/lang/Integer;
     392: invokeinterface #148,  3          // InterfaceMethod org/codehaus/groovy/runtime/callsite/CallSite.call:(Ljava/lang/Object;Ljava/lang/Object;)Ljava/lang/Object;
     397: invokeinterface #174,  4          // InterfaceMethod org/codehaus/groovy/runtime/callsite/CallSite.call:(Ljava/lang/Object;Ljava/lang/Object;Ljava/lang/Object;)Ljava/lang/Object;
     402: pop
     403: aload         4
     405: ldc_w         #361                // int 85
     408: aaload
     409: aload         6
     411: iconst_5
     412: invokestatic  #336                // Method java/lang/Integer.valueOf:(I)Ljava/lang/Integer;
     415: invokeinterface #148,  3          // InterfaceMethod org/codehaus/groovy/runtime/callsite/CallSite.call:(Ljava/lang/Object;Ljava/lang/Object;)Ljava/lang/Object;
     420: invokestatic  #165                // Method org/codehaus/groovy/runtime/typehandling/DefaultTypeTransformation.booleanUnbox:(Ljava/lang/Object;)Z
     423: ifeq          461
     426: aload         4
     428: ldc_w         #362                // int 86
     431: aaload
     432: aload_2
     433: iload         8
     435: invokestatic  #336                // Method java/lang/Integer.valueOf:(I)Ljava/lang/Integer;
     438: aload         4
     440: ldc_w         #363                // int 87
     443: aaload
     444: aload         6
     446: iconst_5
     447: invokestatic  #336                // Method java/lang/Integer.valueOf:(I)Ljava/lang/Integer;
     450: invokeinterface #148,  3          // InterfaceMethod org/codehaus/groovy/runtime/callsite/CallSite.call:(Ljava/lang/Object;Ljava/lang/Object;)Ljava/lang/Object;
     455: invokeinterface #174,  4          // InterfaceMethod org/codehaus/groovy/runtime/callsite/CallSite.call:(Ljava/lang/Object;Ljava/lang/Object;Ljava/lang/Object;)Ljava/lang/Object;
     460: pop
     461: aload         4
     463: ldc_w         #364                // int 88
     466: aaload
     467: aload         6
     469: bipush        6
     471: invokestatic  #336                // Method java/lang/Integer.valueOf:(I)Ljava/lang/Integer;
     474: invokeinterface #148,  3          // InterfaceMethod org/codehaus/groovy/runtime/callsite/CallSite.call:(Ljava/lang/Object;Ljava/lang/Object;)Ljava/lang/Object;
     479: aconst_null
     480: invokestatic  #367                // Method org/codehaus/groovy/runtime/ScriptBytecodeAdapter.compareNotEqual:(Ljava/lang/Object;Ljava/lang/Object;)Z
     483: ifeq          522
     486: aload         4
     488: ldc_w         #368                // int 89
     491: aaload
     492: aload_2
     493: iload         8
     495: invokestatic  #336                // Method java/lang/Integer.valueOf:(I)Ljava/lang/Integer;
     498: aload         4
     500: ldc_w         #369                // int 90
     503: aaload
     504: aload         6
     506: bipush        6
     508: invokestatic  #336                // Method java/lang/Integer.valueOf:(I)Ljava/lang/Integer;
     511: invokeinterface #148,  3          // InterfaceMethod org/codehaus/groovy/runtime/callsite/CallSite.call:(Ljava/lang/Object;Ljava/lang/Object;)Ljava/lang/Object;
     516: invokeinterface #174,  4          // InterfaceMethod org/codehaus/groovy/runtime/callsite/CallSite.call:(Ljava/lang/Object;Ljava/lang/Object;Ljava/lang/Object;)Ljava/lang/Object;
     521: pop
     522: aload         4
     524: ldc_w         #370                // int 91
     527: aaload
     528: aload         6
     530: bipush        7
     532: invokestatic  #336                // Method java/lang/Integer.valueOf:(I)Ljava/lang/Integer;
     535: invokeinterface #148,  3          // InterfaceMethod org/codehaus/groovy/runtime/callsite/CallSite.call:(Ljava/lang/Object;Ljava/lang/Object;)Ljava/lang/Object;
     540: invokestatic  #165                // Method org/codehaus/groovy/runtime/typehandling/DefaultTypeTransformation.booleanUnbox:(Ljava/lang/Object;)Z
     543: ifeq          687
     546: aload         4
     548: ldc_w         #371                // int 92
     551: aaload
     552: aload         6
     554: bipush        7
     556: invokestatic  #336                // Method java/lang/Integer.valueOf:(I)Ljava/lang/Integer;
     559: invokeinterface #148,  3          // InterfaceMethod org/codehaus/groovy/runtime/callsite/CallSite.call:(Ljava/lang/Object;Ljava/lang/Object;)Ljava/lang/Object;
     564: astore        9
     566: aload         9
     568: pop
     569: aload         9
     571: instanceof    #108                // class java/lang/String
     574: ifne          585
     577: aload         9
     579: instanceof    #373                // class groovy/lang/GString
     582: ifeq          589
     585: iconst_1
     586: goto          590
     589: iconst_0
     590: ifeq          649
     593: aload         4
     595: ldc_w         #374                // int 93
     598: aaload
     599: aload_2
     600: iload         8
     602: invokestatic  #336                // Method java/lang/Integer.valueOf:(I)Ljava/lang/Integer;
     605: aload         4
     607: ldc_w         #375                // int 94
     610: aaload
     611: aload         9
     613: iconst_0
     614: invokestatic  #336                // Method java/lang/Integer.valueOf:(I)Ljava/lang/Integer;
     617: invokeinterface #148,  3          // InterfaceMethod org/codehaus/groovy/runtime/callsite/CallSite.call:(Ljava/lang/Object;Ljava/lang/Object;)Ljava/lang/Object;
     622: getstatic     #378                // Field java/lang/Integer.TYPE:Ljava/lang/Class;
     625: invokestatic  #382                // Method org/codehaus/groovy/runtime/ScriptBytecodeAdapter.asType:(Ljava/lang/Object;Ljava/lang/Class;)Ljava/lang/Object;
     628: invokestatic  #354                // Method org/codehaus/groovy/runtime/typehandling/DefaultTypeTransformation.intUnbox:(Ljava/lang/Object;)I
     631: invokestatic  #336                // Method java/lang/Integer.valueOf:(I)Ljava/lang/Integer;
     634: getstatic     #378                // Field java/lang/Integer.TYPE:Ljava/lang/Class;
     637: invokestatic  #386                // Method org/codehaus/groovy/runtime/ScriptBytecodeAdapter.createPojoWrapper:(Ljava/lang/Object;Ljava/lang/Class;)Lorg/codehaus/groovy/runtime/wrappers/Wrapper;
     640: invokeinterface #174,  4          // InterfaceMethod org/codehaus/groovy/runtime/callsite/CallSite.call:(Ljava/lang/Object;Ljava/lang/Object;Ljava/lang/Object;)Ljava/lang/Object;
     645: pop
     646: goto          687
     649: aload         4
     651: ldc_w         #387                // int 95
     654: aaload
     655: aload_2
     656: iload         8
     658: invokestatic  #336                // Method java/lang/Integer.valueOf:(I)Ljava/lang/Integer;
     661: aload         9
     663: getstatic     #378                // Field java/lang/Integer.TYPE:Ljava/lang/Class;
     666: invokestatic  #382                // Method org/codehaus/groovy/runtime/ScriptBytecodeAdapter.asType:(Ljava/lang/Object;Ljava/lang/Class;)Ljava/lang/Object;
     669: invokestatic  #354                // Method org/codehaus/groovy/runtime/typehandling/DefaultTypeTransformation.intUnbox:(Ljava/lang/Object;)I
     672: invokestatic  #336                // Method java/lang/Integer.valueOf:(I)Ljava/lang/Integer;
     675: getstatic     #378                // Field java/lang/Integer.TYPE:Ljava/lang/Class;
     678: invokestatic  #386                // Method org/codehaus/groovy/runtime/ScriptBytecodeAdapter.createPojoWrapper:(Ljava/lang/Object;Ljava/lang/Class;)Lorg/codehaus/groovy/runtime/wrappers/Wrapper;
     681: invokeinterface #174,  4          // InterfaceMethod org/codehaus/groovy/runtime/callsite/CallSite.call:(Ljava/lang/Object;Ljava/lang/Object;Ljava/lang/Object;)Ljava/lang/Object;
     686: pop
     687: aload         4
     689: ldc_w         #388                // int 96
     692: aaload
     693: aload         6
     695: bipush        8
     697: invokestatic  #336                // Method java/lang/Integer.valueOf:(I)Ljava/lang/Integer;
     700: invokeinterface #148,  3          // InterfaceMethod org/codehaus/groovy/runtime/callsite/CallSite.call:(Ljava/lang/Object;Ljava/lang/Object;)Ljava/lang/Object;
     705: invokestatic  #165                // Method org/codehaus/groovy/runtime/typehandling/DefaultTypeTransformation.booleanUnbox:(Ljava/lang/Object;)Z
     708: ifeq          747
     711: aload         4
     713: ldc_w         #389                // int 97
     716: aaload
     717: aload_2
     718: iload         8
     720: invokestatic  #336                // Method java/lang/Integer.valueOf:(I)Ljava/lang/Integer;
     723: aload         4
     725: ldc_w         #390                // int 98
     728: aaload
     729: aload         6
     731: bipush        8
     733: invokestatic  #336                // Method java/lang/Integer.valueOf:(I)Ljava/lang/Integer;
     736: invokeinterface #148,  3          // InterfaceMethod org/codehaus/groovy/runtime/callsite/CallSite.call:(Ljava/lang/Object;Ljava/lang/Object;)Ljava/lang/Object;
     741: invokeinterface #174,  4          // InterfaceMethod org/codehaus/groovy/runtime/callsite/CallSite.call:(Ljava/lang/Object;Ljava/lang/Object;Ljava/lang/Object;)Ljava/lang/Object;
     746: pop
     747: goto          770
     750: astore        10
     752: aload         4
     754: ldc_w         #391                // int 99
     757: aaload
     758: aload_2
     759: aload_3
     760: invokeinterface #148,  3          // InterfaceMethod org/codehaus/groovy/runtime/callsite/CallSite.call:(Ljava/lang/Object;Ljava/lang/Object;)Ljava/lang/Object;
     765: pop
     766: nop
     767: goto          770
     770: nop
     771: goto          779
     774: astore        11
     776: aload         11
     778: athrow
     779: return
    Exception table:
       from    to  target type
          36   750   750   Class groovy/lang/MissingPropertyException
          36   750   774   any
         750   767   774   any

  public void onNodeCompleted(groovy.util.FactoryBuilderSupport, java.lang.Object, java.lang.Object);
    Code:
       0: invokestatic  #81                 // Method $getCallSiteArray:()[Lorg/codehaus/groovy/runtime/callsite/CallSite;
       3: astore        4
       5: ldc           #4                  // class groovy/swing/factory/BeanFactory
       7: aload_0
       8: ldc_w         #399                // String onNodeCompleted
      11: checkcast     #108                // class java/lang/String
      14: iconst_3
      15: anewarray     #110                // class java/lang/Object
      18: dup
      19: iconst_0
      20: aload_1
      21: aastore
      22: dup
      23: iconst_1
      24: aload_2
      25: aastore
      26: dup
      27: iconst_2
      28: aload_3
      29: aastore
      30: invokestatic  #122                // Method org/codehaus/groovy/runtime/ScriptBytecodeAdapter.invokeMethodOnSuperN:(Ljava/lang/Class;Lgroovy/lang/GroovyObject;Ljava/lang/String;[Ljava/lang/Object;)Ljava/lang/Object;
      33: pop
      34: aload         4
      36: ldc_w         #400                // int 100
      39: aaload
      40: aload_1
      41: aload         4
      43: ldc_w         #401                // int 101
      46: aaload
      47: aload         4
      49: ldc_w         #402                // int 102
      52: aaload
      53: aload_1
      54: invokeinterface #132,  2          // InterfaceMethod org/codehaus/groovy/runtime/callsite/CallSite.callGroovyObjectGetProperty:(Ljava/lang/Object;)Ljava/lang/Object;
      59: invokeinterface #144,  2          // InterfaceMethod org/codehaus/groovy/runtime/callsite/CallSite.callGetProperty:(Ljava/lang/Object;)Ljava/lang/Object;
      64: invokeinterface #148,  3          // InterfaceMethod org/codehaus/groovy/runtime/callsite/CallSite.call:(Ljava/lang/Object;Ljava/lang/Object;)Ljava/lang/Object;
      69: pop
      70: aload         4
      72: ldc_w         #403                // int 103
      75: aaload
      76: aload         4
      78: ldc_w         #404                // int 104
      81: aaload
      82: aload_1
      83: invokeinterface #132,  2          // InterfaceMethod org/codehaus/groovy/runtime/callsite/CallSite.callGroovyObjectGetProperty:(Ljava/lang/Object;)Ljava/lang/Object;
      88: invokeinterface #144,  2          // InterfaceMethod org/codehaus/groovy/runtime/callsite/CallSite.callGetProperty:(Ljava/lang/Object;)Ljava/lang/Object;
      93: aconst_null
      94: invokestatic  #367                // Method org/codehaus/groovy/runtime/ScriptBytecodeAdapter.compareNotEqual:(Ljava/lang/Object;Ljava/lang/Object;)Z
      97: ifeq          140
     100: aload         4
     102: ldc_w         #405                // int 105
     105: aaload
     106: aload         4
     108: ldc_w         #406                // int 106
     111: aaload
     112: aload_1
     113: invokeinterface #132,  2          // InterfaceMethod org/codehaus/groovy/runtime/callsite/CallSite.callGroovyObjectGetProperty:(Ljava/lang/Object;)Ljava/lang/Object;
     118: invokeinterface #144,  2          // InterfaceMethod org/codehaus/groovy/runtime/callsite/CallSite.callGetProperty:(Ljava/lang/Object;)Ljava/lang/Object;
     123: astore        5
     125: aload         5
     127: aconst_null
     128: aload_3
     129: ldc           #155                // String selectedComponent
     131: checkcast     #108                // class java/lang/String
     134: invokestatic  #138                // Method org/codehaus/groovy/runtime/ScriptBytecodeAdapter.setProperty:(Ljava/lang/Object;Ljava/lang/Class;Ljava/lang/Object;Ljava/lang/String;)V
     137: aload         5
     139: pop
     140: aload         4
     142: ldc_w         #407                // int 107
     145: aaload
     146: aload         4
     148: ldc_w         #408                // int 108
     151: aaload
     152: aload_1
     153: invokeinterface #132,  2          // InterfaceMethod org/codehaus/groovy/runtime/callsite/CallSite.callGroovyObjectGetProperty:(Ljava/lang/Object;)Ljava/lang/Object;
     158: invokeinterface #144,  2          // InterfaceMethod org/codehaus/groovy/runtime/callsite/CallSite.callGetProperty:(Ljava/lang/Object;)Ljava/lang/Object;
     163: aconst_null
     164: invokestatic  #367                // Method org/codehaus/groovy/runtime/ScriptBytecodeAdapter.compareNotEqual:(Ljava/lang/Object;Ljava/lang/Object;)Z
     167: ifeq          210
     170: aload         4
     172: ldc_w         #409                // int 109
     175: aaload
     176: aload         4
     178: ldc_w         #410                // int 110
     181: aaload
     182: aload_1
     183: invokeinterface #132,  2          // InterfaceMethod org/codehaus/groovy/runtime/callsite/CallSite.callGroovyObjectGetProperty:(Ljava/lang/Object;)Ljava/lang/Object;
     188: invokeinterface #144,  2          // InterfaceMethod org/codehaus/groovy/runtime/callsite/CallSite.callGetProperty:(Ljava/lang/Object;)Ljava/lang/Object;
     193: astore        6
     195: aload         6
     197: aconst_null
     198: aload_3
     199: ldc           #151                // String selectedIndex
     201: checkcast     #108                // class java/lang/String
     204: invokestatic  #138                // Method org/codehaus/groovy/runtime/ScriptBytecodeAdapter.setProperty:(Ljava/lang/Object;Ljava/lang/Class;Ljava/lang/Object;Ljava/lang/String;)V
     207: aload         6
     209: pop
     210: return

  protected groovy.lang.MetaClass $getStaticMetaClass();
    Code:
       0: aload_0
       1: invokevirtual #414                // Method java/lang/Object.getClass:()Ljava/lang/Class;
       4: ldc           #2                  // class groovy/swing/factory/TabbedPaneFactory
       6: if_acmpeq     14
       9: aload_0
      10: invokestatic  #418                // Method org/codehaus/groovy/runtime/ScriptBytecodeAdapter.initMetaClass:(Ljava/lang/Object;)Lgroovy/lang/MetaClass;
      13: areturn
      14: getstatic     #420                // Field $staticClassInfo:Lorg/codehaus/groovy/reflection/ClassInfo;
      17: astore_1
      18: aload_1
      19: ifnonnull     34
      22: aload_0
      23: invokevirtual #414                // Method java/lang/Object.getClass:()Ljava/lang/Class;
      26: invokestatic  #426                // Method org/codehaus/groovy/reflection/ClassInfo.getClassInfo:(Ljava/lang/Class;)Lorg/codehaus/groovy/reflection/ClassInfo;
      29: dup
      30: astore_1
      31: putstatic     #420                // Field $staticClassInfo:Lorg/codehaus/groovy/reflection/ClassInfo;
      34: aload_1
      35: invokevirtual #429                // Method org/codehaus/groovy/reflection/ClassInfo.getMetaClass:()Lgroovy/lang/MetaClass;
      38: areturn

  public java.lang.Object super$3$newInstance(groovy.util.FactoryBuilderSupport, java.lang.Object, java.lang.Object, java.util.Map);
    Code:
       0: aload_0
       1: aload_1
       2: aload_2
       3: aload_3
       4: aload         4
       6: invokespecial #432                // Method groovy/swing/factory/BeanFactory.newInstance:(Lgroovy/util/FactoryBuilderSupport;Ljava/lang/Object;Ljava/lang/Object;Ljava/util/Map;)Ljava/lang/Object;
       9: areturn

  public void super$2$onNodeCompleted(groovy.util.FactoryBuilderSupport, java.lang.Object, java.lang.Object);
    Code:
       0: aload_0
       1: aload_1
       2: aload_2
       3: aload_3
       4: invokespecial #437                // Method groovy/util/AbstractFactory.onNodeCompleted:(Lgroovy/util/FactoryBuilderSupport;Ljava/lang/Object;Ljava/lang/Object;)V
       7: return

  public void super$2$setChild(groovy.util.FactoryBuilderSupport, java.lang.Object, java.lang.Object);
    Code:
       0: aload_0
       1: aload_1
       2: aload_2
       3: aload_3
       4: invokespecial #440                // Method groovy/util/AbstractFactory.setChild:(Lgroovy/util/FactoryBuilderSupport;Ljava/lang/Object;Ljava/lang/Object;)V
       7: return

  public groovy.lang.MetaClass super$3$$getStaticMetaClass();
    Code:
       0: aload_0
       1: invokespecial #442                // Method groovy/swing/factory/BeanFactory.$getStaticMetaClass:()Lgroovy/lang/MetaClass;
       4: areturn

  private static void $createCallSiteArray_1(java.lang.String[]);
    Code:
       0: aload_0
       1: ldc           #126                // int 0
       3: ldc_w         #446                // String context
       6: aastore
       7: aload_0
       8: ldc           #139                // int 1
      10: ldc_w         #448                // String addAttributeDelegate
      13: aastore
      14: aload_0
      15: ldc           #140                // int 2
      17: ldc           #134                // String tabbedPaneFactoryClosure
      19: aastore
      20: aload_0
      21: ldc           #141                // int 3
      23: ldc_w         #446                // String context
      26: aastore
      27: aload_0
      28: ldc           #149                // int 4
      30: ldc_w         #450                // String remove
      33: aastore
      34: aload_0
      35: ldc           #152                // int 5
      37: ldc_w         #446                // String context
      40: aastore
      41: aload_0
      42: ldc           #153                // int 6
      44: ldc_w         #450                // String remove
      47: aastore
      48: aload_0
      49: ldc           #156                // int 7
      51: ldc_w         #446                // String context
      54: aastore
      55: aload_0
      56: ldc           #157                // int 8
      58: ldc_w         #450                // String remove
      61: aastore
      62: aload_0
      63: ldc           #168                // int 9
      65: ldc_w         #452                // String putAt
      68: aastore
      69: aload_0
      70: ldc           #169                // int 10
      72: ldc_w         #446                // String context
      75: aastore
      76: aload_0
      77: ldc           #175                // int 11
      79: ldc_w         #450                // String remove
      82: aastore
      83: aload_0
      84: ldc           #180                // int 12
      86: ldc_w         #452                // String putAt
      89: aastore
      90: aload_0
      91: ldc           #181                // int 13
      93: ldc_w         #446                // String context
      96: aastore
      97: aload_0
      98: ldc           #184                // int 14
     100: ldc_w         #450                // String remove
     103: aastore
     104: aload_0
     105: ldc           #189                // int 15
     107: ldc_w         #452                // String putAt
     110: aastore
     111: aload_0
     112: ldc           #190                // int 16
     114: ldc_w         #446                // String context
     117: aastore
     118: aload_0
     119: ldc           #193                // int 17
     121: ldc_w         #450                // String remove
     124: aastore
     125: aload_0
     126: ldc           #198                // int 18
     128: ldc_w         #452                // String putAt
     131: aastore
     132: aload_0
     133: ldc           #199                // int 19
     135: ldc_w         #446                // String context
     138: aastore
     139: aload_0
     140: ldc           #202                // int 20
     142: ldc_w         #450                // String remove
     145: aastore
     146: aload_0
     147: ldc           #207                // int 21
     149: ldc_w         #452                // String putAt
     152: aastore
     153: aload_0
     154: ldc           #208                // int 22
     156: ldc_w         #446                // String context
     159: aastore
     160: aload_0
     161: ldc           #211                // int 23
     163: ldc_w         #450                // String remove
     166: aastore
     167: aload_0
     168: ldc           #216                // int 24
     170: ldc_w         #452                // String putAt
     173: aastore
     174: aload_0
     175: ldc           #217                // int 25
     177: ldc_w         #446                // String context
     180: aastore
     181: aload_0
     182: ldc           #220                // int 26
     184: ldc_w         #450                // String remove
     187: aastore
     188: aload_0
     189: ldc           #225                // int 27
     191: ldc_w         #452                // String putAt
     194: aastore
     195: aload_0
     196: ldc           #226                // int 28
     198: ldc_w         #446                // String context
     201: aastore
     202: aload_0
     203: ldc           #229                // int 29
     205: ldc_w         #450                // String remove
     208: aastore
     209: aload_0
     210: ldc           #234                // int 30
     212: ldc_w         #452                // String putAt
     215: aastore
     216: aload_0
     217: ldc           #235                // int 31
     219: ldc_w         #446                // String context
     222: aastore
     223: aload_0
     224: ldc           #238                // int 32
     226: ldc_w         #450                // String remove
     229: aastore
     230: aload_0
     231: ldc           #243                // int 33
     233: ldc_w         #452                // String putAt
     236: aastore
     237: aload_0
     238: ldc           #244                // int 34
     240: ldc_w         #446                // String context
     243: aastore
     244: aload_0
     245: ldc_w         #262                // int 35
     248: ldc_w         #450                // String remove
     251: aastore
     252: aload_0
     253: ldc_w         #263                // int 36
     256: ldc_w         #454                // String getAt
     259: aastore
     260: aload_0
     261: ldc_w         #264                // int 37
     264: ldc_w         #456                // String parentContext
     267: aastore
     268: aload_0
     269: ldc_w         #271                // int 38
     272: ldc_w         #450                // String remove
     275: aastore
     276: aload_0
     277: ldc_w         #272                // int 39
     280: ldc_w         #454                // String getAt
     283: aastore
     284: aload_0
     285: ldc_w         #273                // int 40
     288: ldc_w         #456                // String parentContext
     291: aastore
     292: aload_0
     293: ldc_w         #274                // int 41
     296: ldc_w         #450                // String remove
     299: aastore
     300: aload_0
     301: ldc_w         #275                // int 42
     304: ldc_w         #454                // String getAt
     307: aastore
     308: aload_0
     309: ldc_w         #276                // int 43
     312: ldc_w         #456                // String parentContext
     315: aastore
     316: aload_0
     317: ldc_w         #277                // int 44
     320: ldc_w         #450                // String remove
     323: aastore
     324: aload_0
     325: ldc_w         #278                // int 45
     328: ldc_w         #454                // String getAt
     331: aastore
     332: aload_0
     333: ldc_w         #279                // int 46
     336: ldc_w         #456                // String parentContext
     339: aastore
     340: aload_0
     341: ldc_w         #280                // int 47
     344: ldc_w         #450                // String remove
     347: aastore
     348: aload_0
     349: ldc_w         #281                // int 48
     352: ldc_w         #454                // String getAt
     355: aastore
     356: aload_0
     357: ldc_w         #282                // int 49
     360: ldc_w         #456                // String parentContext
     363: aastore
     364: aload_0
     365: ldc_w         #283                // int 50
     368: ldc_w         #450                // String remove
     371: aastore
     372: aload_0
     373: ldc_w         #284                // int 51
     376: ldc_w         #454                // String getAt
     379: aastore
     380: aload_0
     381: ldc_w         #285                // int 52
     384: ldc_w         #456                // String parentContext
     387: aastore
     388: aload_0
     389: ldc_w         #286                // int 53
     392: ldc_w         #450                // String remove
     395: aastore
     396: aload_0
     397: ldc_w         #287                // int 54
     400: ldc_w         #454                // String getAt
     403: aastore
     404: aload_0
     405: ldc_w         #288                // int 55
     408: ldc_w         #456                // String parentContext
     411: aastore
     412: aload_0
     413: ldc_w         #289                // int 56
     416: ldc_w         #450                // String remove
     419: aastore
     420: aload_0
     421: ldc_w         #290                // int 57
     424: ldc_w         #454                // String getAt
     427: aastore
     428: aload_0
     429: ldc_w         #291                // int 58
     432: ldc_w         #456                // String parentContext
     435: aastore
     436: aload_0
     437: ldc_w         #292                // int 59
     440: ldc_w         #450                // String remove
     443: aastore
     444: aload_0
     445: ldc_w         #293                // int 60
     448: ldc_w         #454                // String getAt
     451: aastore
     452: aload_0
     453: ldc_w         #294                // int 61
     456: ldc_w         #456                // String parentContext
     459: aastore
     460: aload_0
     461: ldc_w         #295                // int 62
     464: ldc_w         #457                // String get
     467: aastore
     468: aload_0
     469: ldc_w         #296                // int 63
     472: ldc_w         #446                // String context
     475: aastore
     476: aload_0
     477: ldc_w         #303                // int 64
     480: ldc_w         #459                // String isEmpty
     483: aastore
     484: aload_0
     485: ldc_w         #306                // int 65
     488: ldc_w         #461                // String put
     491: aastore
     492: aload_0
     493: ldc_w         #307                // int 66
     496: ldc_w         #446                // String context
     499: aastore
     500: aload_0
     501: ldc_w         #308                // int 67
     504: ldc_w         #461                // String put
     507: aastore
     508: aload_0
     509: ldc_w         #327                // int 68
     512: ldc_w         #457                // String get
     515: aastore
     516: aload_0
     517: ldc_w         #328                // int 69
     520: ldc_w         #454                // String getAt
     523: aastore
     524: aload_0
     525: ldc_w         #329                // int 70
     528: ldc_w         #446                // String context
     531: aastore
     532: aload_0
     533: ldc_w         #330                // int 71
     536: ldc_w         #454                // String getAt
     539: aastore
     540: aload_0
     541: ldc_w         #341                // int 72
     544: ldc_w         #462                // String name
     547: aastore
     548: aload_0
     549: ldc_w         #342                // int 73
     552: ldc_w         #452                // String putAt
     555: aastore
     556: aload_0
     557: ldc_w         #343                // int 74
     560: ldc_w         #464                // String addTab
     563: aastore
     564: aload_0
     565: ldc_w         #344                // int 75
     568: ldc_w         #454                // String getAt
     571: aastore
     572: aload_0
     573: ldc_w         #345                // int 76
     576: ldc_w         #454                // String getAt
     579: aastore
     580: aload_0
     581: ldc_w         #346                // int 77
     584: ldc_w         #454                // String getAt
     587: aastore
     588: aload_0
     589: ldc_w         #350                // int 78
     592: ldc_w         #466                // String indexOfComponent
     595: aastore
     596: aload_0
     597: ldc_w         #355                // int 79
     600: ldc_w         #454                // String getAt
     603: aastore
     604: aload_0
     605: ldc_w         #356                // int 80
     608: ldc_w         #468                // String setDisabledIconAt
     611: aastore
     612: aload_0
     613: ldc_w         #357                // int 81
     616: ldc_w         #454                // String getAt
     619: aastore
     620: aload_0
     621: ldc_w         #358                // int 82
     624: ldc_w         #454                // String getAt
     627: aastore
     628: aload_0
     629: ldc_w         #359                // int 83
     632: ldc_w         #470                // String setBackgroundAt
     635: aastore
     636: aload_0
     637: ldc_w         #360                // int 84
     640: ldc_w         #454                // String getAt
     643: aastore
     644: aload_0
     645: ldc_w         #361                // int 85
     648: ldc_w         #454                // String getAt
     651: aastore
     652: aload_0
     653: ldc_w         #362                // int 86
     656: ldc_w         #472                // String setForegroundAt
     659: aastore
     660: aload_0
     661: ldc_w         #363                // int 87
     664: ldc_w         #454                // String getAt
     667: aastore
     668: aload_0
     669: ldc_w         #364                // int 88
     672: ldc_w         #454                // String getAt
     675: aastore
     676: aload_0
     677: ldc_w         #368                // int 89
     680: ldc_w         #474                // String setEnabledAt
     683: aastore
     684: aload_0
     685: ldc_w         #369                // int 90
     688: ldc_w         #454                // String getAt
     691: aastore
     692: aload_0
     693: ldc_w         #370                // int 91
     696: ldc_w         #454                // String getAt
     699: aastore
     700: aload_0
     701: ldc_w         #371                // int 92
     704: ldc_w         #454                // String getAt
     707: aastore
     708: aload_0
     709: ldc_w         #374                // int 93
     712: ldc_w         #476                // String setMnemonicAt
     715: aastore
     716: aload_0
     717: ldc_w         #375                // int 94
     720: ldc_w         #478                // String charAt
     723: aastore
     724: aload_0
     725: ldc_w         #387                // int 95
     728: ldc_w         #476                // String setMnemonicAt
     731: aastore
     732: aload_0
     733: ldc_w         #388                // int 96
     736: ldc_w         #454                // String getAt
     739: aastore
     740: aload_0
     741: ldc_w         #389                // int 97
     744: ldc_w         #480                // String setDisplayedMnemonicIndexAt
     747: aastore
     748: aload_0
     749: ldc_w         #390                // int 98
     752: ldc_w         #454                // String getAt
     755: aastore
     756: aload_0
     757: ldc_w         #391                // int 99
     760: ldc_w         #482                // String add
     763: aastore
     764: aload_0
     765: ldc_w         #400                // int 100
     768: ldc_w         #484                // String removeAttributeDelegate
     771: aastore
     772: aload_0
     773: ldc_w         #401                // int 101
     776: ldc           #134                // String tabbedPaneFactoryClosure
     778: aastore
     779: aload_0
     780: ldc_w         #402                // int 102
     783: ldc_w         #446                // String context
     786: aastore
     787: aload_0
     788: ldc_w         #403                // int 103
     791: ldc           #155                // String selectedComponent
     793: aastore
     794: aload_0
     795: ldc_w         #404                // int 104
     798: ldc_w         #446                // String context
     801: aastore
     802: aload_0
     803: ldc_w         #405                // int 105
     806: ldc           #155                // String selectedComponent
     808: aastore
     809: aload_0
     810: ldc_w         #406                // int 106
     813: ldc_w         #446                // String context
     816: aastore
     817: aload_0
     818: ldc_w         #407                // int 107
     821: ldc           #151                // String selectedIndex
     823: aastore
     824: aload_0
     825: ldc_w         #408                // int 108
     828: ldc_w         #446                // String context
     831: aastore
     832: aload_0
     833: ldc_w         #409                // int 109
     836: ldc           #151                // String selectedIndex
     838: aastore
     839: aload_0
     840: ldc_w         #410                // int 110
     843: ldc_w         #446                // String context
     846: aastore
     847: return

  private static org.codehaus.groovy.runtime.callsite.CallSiteArray $createCallSiteArray();
    Code:
       0: ldc_w         #487                // int 111
       3: anewarray     #108                // class java/lang/String
       6: astore_0
       7: aload_0
       8: invokestatic  #489                // Method $createCallSiteArray_1:([Ljava/lang/String;)V
      11: new           #491                // class org/codehaus/groovy/runtime/callsite/CallSiteArray
      14: dup
      15: ldc           #2                  // class groovy/swing/factory/TabbedPaneFactory
      17: aload_0
      18: invokespecial #494                // Method org/codehaus/groovy/runtime/callsite/CallSiteArray."<init>":(Ljava/lang/Class;[Ljava/lang/String;)V
      21: areturn

  private static org.codehaus.groovy.runtime.callsite.CallSite[] $getCallSiteArray();
    Code:
       0: getstatic     #496                // Field $callSiteArray:Ljava/lang/ref/SoftReference;
       3: ifnull        20
       6: getstatic     #496                // Field $callSiteArray:Ljava/lang/ref/SoftReference;
       9: invokevirtual #499                // Method java/lang/ref/SoftReference.get:()Ljava/lang/Object;
      12: checkcast     #491                // class org/codehaus/groovy/runtime/callsite/CallSiteArray
      15: dup
      16: astore_0
      17: ifnonnull     35
      20: invokestatic  #501                // Method $createCallSiteArray:()Lorg/codehaus/groovy/runtime/callsite/CallSiteArray;
      23: astore_0
      24: new           #498                // class java/lang/ref/SoftReference
      27: dup
      28: aload_0
      29: invokespecial #502                // Method java/lang/ref/SoftReference."<init>":(Ljava/lang/Object;)V
      32: putstatic     #496                // Field $callSiteArray:Ljava/lang/ref/SoftReference;
      35: aload_0
      36: getfield      #506                // Field org/codehaus/groovy/runtime/callsite/CallSiteArray.array:[Lorg/codehaus/groovy/runtime/callsite/CallSite;
      39: areturn
}
