Compiled from "AnnotationInstance.java"
public final class org.jboss.jandex.AnnotationInstance {
  private static final org.jboss.jandex.AnnotationValue[] ANNOTATION_VALUES_TYPE;

  static final org.jboss.jandex.AnnotationInstance$InstanceNameComparator NAME_COMPARATOR;

  static final org.jboss.jandex.AnnotationInstance[] EMPTY_ARRAY;

  private final org.jboss.jandex.DotName name;

  private org.jboss.jandex.AnnotationTarget target;

  private final org.jboss.jandex.AnnotationValue[] values;

  org.jboss.jandex.AnnotationInstance(org.jboss.jandex.AnnotationInstance, org.jboss.jandex.AnnotationTarget);
    Code:
       0: aload_0
       1: invokespecial #1                  // Method java/lang/Object."<init>":()V
       4: aload_0
       5: aload_1
       6: getfield      #2                  // Field name:Lorg/jboss/jandex/DotName;
       9: putfield      #2                  // Field name:Lorg/jboss/jandex/DotName;
      12: aload_0
      13: aload_1
      14: getfield      #3                  // Field values:[Lorg/jboss/jandex/AnnotationValue;
      17: putfield      #3                  // Field values:[Lorg/jboss/jandex/AnnotationValue;
      20: aload_0
      21: aload_2
      22: putfield      #4                  // Field target:Lorg/jboss/jandex/AnnotationTarget;
      25: return

  org.jboss.jandex.AnnotationInstance(org.jboss.jandex.DotName, org.jboss.jandex.AnnotationTarget, org.jboss.jandex.AnnotationValue[]);
    Code:
       0: aload_0
       1: invokespecial #1                  // Method java/lang/Object."<init>":()V
       4: aload_0
       5: aload_1
       6: putfield      #2                  // Field name:Lorg/jboss/jandex/DotName;
       9: aload_0
      10: aload_2
      11: putfield      #4                  // Field target:Lorg/jboss/jandex/AnnotationTarget;
      14: aload_0
      15: aload_3
      16: ifnull        28
      19: aload_3
      20: arraylength
      21: ifle          28
      24: aload_3
      25: goto          31
      28: getstatic     #5                  // Field org/jboss/jandex/AnnotationValue.EMPTY_VALUE_ARRAY:[Lorg/jboss/jandex/AnnotationValue;
      31: putfield      #3                  // Field values:[Lorg/jboss/jandex/AnnotationValue;
      34: return

  public static final org.jboss.jandex.AnnotationInstance create(org.jboss.jandex.DotName, org.jboss.jandex.AnnotationTarget, org.jboss.jandex.AnnotationValue[]);
    Code:
       0: aload_0
       1: ifnonnull     14
       4: new           #6                  // class java/lang/IllegalArgumentException
       7: dup
       8: ldc           #7                  // String Name can\'t be null
      10: invokespecial #8                  // Method java/lang/IllegalArgumentException."<init>":(Ljava/lang/String;)V
      13: athrow
      14: aload_2
      15: ifnonnull     28
      18: new           #6                  // class java/lang/IllegalArgumentException
      21: dup
      22: ldc           #9                  // String Values can\'t be null
      24: invokespecial #8                  // Method java/lang/IllegalArgumentException."<init>":(Ljava/lang/String;)V
      27: athrow
      28: aload_2
      29: invokevirtual #10                 // Method "[Lorg/jboss/jandex/AnnotationValue;".clone:()Ljava/lang/Object;
      32: checkcast     #11                 // class "[Lorg/jboss/jandex/AnnotationValue;"
      35: astore_2
      36: aload_2
      37: new           #12                 // class org/jboss/jandex/AnnotationInstance$1
      40: dup
      41: invokespecial #13                 // Method org/jboss/jandex/AnnotationInstance$1."<init>":()V
      44: invokestatic  #14                 // Method java/util/Arrays.sort:([Ljava/lang/Object;Ljava/util/Comparator;)V
      47: new           #15                 // class org/jboss/jandex/AnnotationInstance
      50: dup
      51: aload_0
      52: aload_1
      53: aload_2
      54: invokespecial #16                 // Method "<init>":(Lorg/jboss/jandex/DotName;Lorg/jboss/jandex/AnnotationTarget;[Lorg/jboss/jandex/AnnotationValue;)V
      57: areturn

  public static final org.jboss.jandex.AnnotationInstance create(org.jboss.jandex.DotName, org.jboss.jandex.AnnotationTarget, java.util.List<org.jboss.jandex.AnnotationValue>);
    Code:
       0: aload_0
       1: ifnonnull     14
       4: new           #6                  // class java/lang/IllegalArgumentException
       7: dup
       8: ldc           #7                  // String Name can\'t be null
      10: invokespecial #8                  // Method java/lang/IllegalArgumentException."<init>":(Ljava/lang/String;)V
      13: athrow
      14: aload_2
      15: ifnonnull     28
      18: new           #6                  // class java/lang/IllegalArgumentException
      21: dup
      22: ldc           #9                  // String Values can\'t be null
      24: invokespecial #8                  // Method java/lang/IllegalArgumentException."<init>":(Ljava/lang/String;)V
      27: athrow
      28: aload_0
      29: aload_1
      30: aload_2
      31: getstatic     #17                 // Field ANNOTATION_VALUES_TYPE:[Lorg/jboss/jandex/AnnotationValue;
      34: invokeinterface #18,  2           // InterfaceMethod java/util/List.toArray:([Ljava/lang/Object;)[Ljava/lang/Object;
      39: checkcast     #11                 // class "[Lorg/jboss/jandex/AnnotationValue;"
      42: invokestatic  #19                 // Method create:(Lorg/jboss/jandex/DotName;Lorg/jboss/jandex/AnnotationTarget;[Lorg/jboss/jandex/AnnotationValue;)Lorg/jboss/jandex/AnnotationInstance;
      45: areturn

  public org.jboss.jandex.DotName name();
    Code:
       0: aload_0
       1: getfield      #2                  // Field name:Lorg/jboss/jandex/DotName;
       4: areturn

  public org.jboss.jandex.AnnotationTarget target();
    Code:
       0: aload_0
       1: getfield      #4                  // Field target:Lorg/jboss/jandex/AnnotationTarget;
       4: areturn

  public org.jboss.jandex.AnnotationValue value(java.lang.String);
    Code:
       0: aload_0
       1: getfield      #3                  // Field values:[Lorg/jboss/jandex/AnnotationValue;
       4: aload_1
       5: new           #20                 // class org/jboss/jandex/AnnotationInstance$2
       8: dup
       9: aload_0
      10: aload_1
      11: invokespecial #21                 // Method org/jboss/jandex/AnnotationInstance$2."<init>":(Lorg/jboss/jandex/AnnotationInstance;Ljava/lang/String;)V
      14: invokestatic  #22                 // Method java/util/Arrays.binarySearch:([Ljava/lang/Object;Ljava/lang/Object;Ljava/util/Comparator;)I
      17: istore_2
      18: iload_2
      19: iflt          31
      22: aload_0
      23: getfield      #3                  // Field values:[Lorg/jboss/jandex/AnnotationValue;
      26: iload_2
      27: aaload
      28: goto          32
      31: aconst_null
      32: areturn

  public org.jboss.jandex.AnnotationValue value();
    Code:
       0: aload_0
       1: ldc           #23                 // String value
       3: invokevirtual #24                 // Method value:(Ljava/lang/String;)Lorg/jboss/jandex/AnnotationValue;
       6: areturn

  public java.util.List<org.jboss.jandex.AnnotationValue> values();
    Code:
       0: aload_0
       1: getfield      #3                  // Field values:[Lorg/jboss/jandex/AnnotationValue;
       4: invokestatic  #25                 // Method java/util/Arrays.asList:([Ljava/lang/Object;)Ljava/util/List;
       7: invokestatic  #26                 // Method java/util/Collections.unmodifiableList:(Ljava/util/List;)Ljava/util/List;
      10: areturn

  org.jboss.jandex.AnnotationValue[] valueArray();
    Code:
       0: aload_0
       1: getfield      #3                  // Field values:[Lorg/jboss/jandex/AnnotationValue;
       4: areturn

  public java.lang.String toString(boolean);
    Code:
       0: new           #27                 // class java/lang/StringBuilder
       3: dup
       4: ldc           #28                 // String @
       6: invokespecial #29                 // Method java/lang/StringBuilder."<init>":(Ljava/lang/String;)V
       9: iload_1
      10: ifeq          23
      13: aload_0
      14: getfield      #2                  // Field name:Lorg/jboss/jandex/DotName;
      17: invokevirtual #30                 // Method org/jboss/jandex/DotName.local:()Ljava/lang/String;
      20: goto          27
      23: aload_0
      24: getfield      #2                  // Field name:Lorg/jboss/jandex/DotName;
      27: invokevirtual #31                 // Method java/lang/StringBuilder.append:(Ljava/lang/Object;)Ljava/lang/StringBuilder;
      30: astore_2
      31: aload_0
      32: getfield      #3                  // Field values:[Lorg/jboss/jandex/AnnotationValue;
      35: arraylength
      36: ifle          99
      39: aload_2
      40: ldc           #32                 // String (
      42: invokevirtual #33                 // Method java/lang/StringBuilder.append:(Ljava/lang/String;)Ljava/lang/StringBuilder;
      45: pop
      46: iconst_0
      47: istore_3
      48: iload_3
      49: aload_0
      50: getfield      #3                  // Field values:[Lorg/jboss/jandex/AnnotationValue;
      53: arraylength
      54: if_icmpge     92
      57: aload_2
      58: aload_0
      59: getfield      #3                  // Field values:[Lorg/jboss/jandex/AnnotationValue;
      62: iload_3
      63: aaload
      64: invokevirtual #31                 // Method java/lang/StringBuilder.append:(Ljava/lang/Object;)Ljava/lang/StringBuilder;
      67: pop
      68: iload_3
      69: aload_0
      70: getfield      #3                  // Field values:[Lorg/jboss/jandex/AnnotationValue;
      73: arraylength
      74: iconst_1
      75: isub
      76: if_icmpge     86
      79: aload_2
      80: ldc           #34                 // String ,
      82: invokevirtual #33                 // Method java/lang/StringBuilder.append:(Ljava/lang/String;)Ljava/lang/StringBuilder;
      85: pop
      86: iinc          3, 1
      89: goto          48
      92: aload_2
      93: bipush        41
      95: invokevirtual #35                 // Method java/lang/StringBuilder.append:(C)Ljava/lang/StringBuilder;
      98: pop
      99: aload_2
     100: invokevirtual #36                 // Method java/lang/StringBuilder.toString:()Ljava/lang/String;
     103: areturn

  public java.lang.String toString();
    Code:
       0: aload_0
       1: iconst_1
       2: invokevirtual #37                 // Method toString:(Z)Ljava/lang/String;
       5: areturn

  void setTarget(org.jboss.jandex.AnnotationTarget);
    Code:
       0: aload_0
       1: getfield      #4                  // Field target:Lorg/jboss/jandex/AnnotationTarget;
       4: ifnull        17
       7: new           #38                 // class java/lang/IllegalStateException
      10: dup
      11: ldc           #39                 // String Attempt to modify target post-initialization
      13: invokespecial #40                 // Method java/lang/IllegalStateException."<init>":(Ljava/lang/String;)V
      16: athrow
      17: aload_0
      18: aload_1
      19: putfield      #4                  // Field target:Lorg/jboss/jandex/AnnotationTarget;
      22: return

  public boolean equals(java.lang.Object);
    Code:
       0: aload_0
       1: aload_1
       2: if_acmpne     7
       5: iconst_1
       6: ireturn
       7: aload_1
       8: ifnull        22
      11: aload_0
      12: invokevirtual #41                 // Method java/lang/Object.getClass:()Ljava/lang/Class;
      15: aload_1
      16: invokevirtual #41                 // Method java/lang/Object.getClass:()Ljava/lang/Class;
      19: if_acmpeq     24
      22: iconst_0
      23: ireturn
      24: aload_1
      25: checkcast     #15                 // class org/jboss/jandex/AnnotationInstance
      28: astore_2
      29: aload_0
      30: getfield      #4                  // Field target:Lorg/jboss/jandex/AnnotationTarget;
      33: aload_2
      34: getfield      #4                  // Field target:Lorg/jboss/jandex/AnnotationTarget;
      37: if_acmpne     72
      40: aload_0
      41: getfield      #2                  // Field name:Lorg/jboss/jandex/DotName;
      44: aload_2
      45: getfield      #2                  // Field name:Lorg/jboss/jandex/DotName;
      48: invokevirtual #42                 // Method org/jboss/jandex/DotName.equals:(Ljava/lang/Object;)Z
      51: ifeq          72
      54: aload_0
      55: getfield      #3                  // Field values:[Lorg/jboss/jandex/AnnotationValue;
      58: aload_2
      59: getfield      #3                  // Field values:[Lorg/jboss/jandex/AnnotationValue;
      62: invokestatic  #43                 // Method java/util/Arrays.equals:([Ljava/lang/Object;[Ljava/lang/Object;)Z
      65: ifeq          72
      68: iconst_1
      69: goto          73
      72: iconst_0
      73: ireturn

  public int hashCode();
    Code:
       0: aload_0
       1: getfield      #2                  // Field name:Lorg/jboss/jandex/DotName;
       4: invokevirtual #44                 // Method org/jboss/jandex/DotName.hashCode:()I
       7: istore_1
       8: bipush        31
      10: iload_1
      11: imul
      12: aload_0
      13: getfield      #3                  // Field values:[Lorg/jboss/jandex/AnnotationValue;
      16: invokestatic  #45                 // Method java/util/Arrays.hashCode:([Ljava/lang/Object;)I
      19: iadd
      20: istore_1
      21: aload_0
      22: getfield      #4                  // Field target:Lorg/jboss/jandex/AnnotationTarget;
      25: ifnull        41
      28: bipush        31
      30: iload_1
      31: imul
      32: aload_0
      33: getfield      #4                  // Field target:Lorg/jboss/jandex/AnnotationTarget;
      36: invokevirtual #46                 // Method java/lang/Object.hashCode:()I
      39: iadd
      40: istore_1
      41: iload_1
      42: ireturn

  static {};
    Code:
       0: iconst_0
       1: anewarray     #47                 // class org/jboss/jandex/AnnotationValue
       4: putstatic     #17                 // Field ANNOTATION_VALUES_TYPE:[Lorg/jboss/jandex/AnnotationValue;
       7: new           #48                 // class org/jboss/jandex/AnnotationInstance$InstanceNameComparator
      10: dup
      11: invokespecial #49                 // Method org/jboss/jandex/AnnotationInstance$InstanceNameComparator."<init>":()V
      14: putstatic     #50                 // Field NAME_COMPARATOR:Lorg/jboss/jandex/AnnotationInstance$InstanceNameComparator;
      17: iconst_0
      18: anewarray     #15                 // class org/jboss/jandex/AnnotationInstance
      21: putstatic     #51                 // Field EMPTY_ARRAY:[Lorg/jboss/jandex/AnnotationInstance;
      24: return
}
