Compiled from "Indexer.java"
class org.jboss.jandex.Indexer$PathElement {
  private static org.jboss.jandex.Indexer$PathElement$Kind[] KINDS;

  private org.jboss.jandex.Indexer$PathElement$Kind kind;

  private int pos;

  private org.jboss.jandex.Indexer$PathElement(org.jboss.jandex.Indexer$PathElement$Kind, int);
    Code:
       0: aload_0
       1: invokespecial #5                  // Method java/lang/Object."<init>":()V
       4: aload_0
       5: aload_1
       6: putfield      #4                  // Field kind:Lorg/jboss/jandex/Indexer$PathElement$Kind;
       9: aload_0
      10: iload_2
      11: putfield      #3                  // Field pos:I
      14: return

  static org.jboss.jandex.Indexer$PathElement$Kind access$900(org.jboss.jandex.Indexer$PathElement);
    Code:
       0: aload_0
       1: getfield      #4                  // Field kind:Lorg/jboss/jandex/Indexer$PathElement$Kind;
       4: areturn

  static int access$1000(org.jboss.jandex.Indexer$PathElement);
    Code:
       0: aload_0
       1: getfield      #3                  // Field pos:I
       4: ireturn

  static org.jboss.jandex.Indexer$PathElement$Kind[] access$1400();
    Code:
       0: getstatic     #2                  // Field KINDS:[Lorg/jboss/jandex/Indexer$PathElement$Kind;
       3: areturn

  org.jboss.jandex.Indexer$PathElement(org.jboss.jandex.Indexer$PathElement$Kind, int, org.jboss.jandex.Indexer$1);
    Code:
       0: aload_0
       1: aload_1
       2: iload_2
       3: invokespecial #1                  // Method "<init>":(Lorg/jboss/jandex/Indexer$PathElement$Kind;I)V
       6: return

  static {};
    Code:
       0: invokestatic  #6                  // Method org/jboss/jandex/Indexer$PathElement$Kind.values:()[Lorg/jboss/jandex/Indexer$PathElement$Kind;
       3: putstatic     #2                  // Field KINDS:[Lorg/jboss/jandex/Indexer$PathElement$Kind;
       6: return
}
