Compiled from "AbstractStoreConfigurationBuilder.java"
public abstract class org.infinispan.configuration.cache.AbstractStoreConfigurationBuilder<T extends org.infinispan.configuration.cache.StoreConfiguration, S extends org.infinispan.configuration.cache.AbstractStoreConfigurationBuilder<T, S>> extends org.infinispan.configuration.cache.AbstractPersistenceConfigurationChildBuilder implements org.infinispan.configuration.cache.StoreConfigurationBuilder<T, S> {
  private static final org.infinispan.util.logging.Log log;

  protected final org.infinispan.commons.configuration.attributes.AttributeSet attributes;

  protected final org.infinispan.configuration.cache.AsyncStoreConfigurationBuilder<S> async;

  protected final org.infinispan.configuration.cache.SingletonStoreConfigurationBuilder<S> singletonStore;

  protected boolean preload;

  protected boolean shared;

  protected boolean ignoreModifications;

  protected java.util.Properties properties;

  protected boolean purgeOnStartup;

  protected boolean fetchPersistentState;

  public org.infinispan.configuration.cache.AbstractStoreConfigurationBuilder(org.infinispan.configuration.cache.PersistenceConfigurationBuilder);
    Code:
       0: aload_0
       1: aload_1
       2: invokespecial #1                  // Method org/infinispan/configuration/cache/AbstractPersistenceConfigurationChildBuilder."<init>":(Lorg/infinispan/configuration/cache/PersistenceConfigurationBuilder;)V
       5: aload_0
       6: invokestatic  #2                  // Method org/infinispan/configuration/cache/AbstractStoreConfiguration.attributeDefinitionSet:()Lorg/infinispan/commons/configuration/attributes/AttributeSet;
       9: putfield      #3                  // Field attributes:Lorg/infinispan/commons/configuration/attributes/AttributeSet;
      12: aload_0
      13: new           #4                  // class org/infinispan/configuration/cache/AsyncStoreConfigurationBuilder
      16: dup
      17: aload_0
      18: invokespecial #5                  // Method org/infinispan/configuration/cache/AsyncStoreConfigurationBuilder."<init>":(Lorg/infinispan/configuration/cache/AbstractStoreConfigurationBuilder;)V
      21: putfield      #6                  // Field async:Lorg/infinispan/configuration/cache/AsyncStoreConfigurationBuilder;
      24: aload_0
      25: new           #7                  // class org/infinispan/configuration/cache/SingletonStoreConfigurationBuilder
      28: dup
      29: aload_0
      30: invokespecial #8                  // Method org/infinispan/configuration/cache/SingletonStoreConfigurationBuilder."<init>":(Lorg/infinispan/configuration/cache/AbstractStoreConfigurationBuilder;)V
      33: putfield      #9                  // Field singletonStore:Lorg/infinispan/configuration/cache/SingletonStoreConfigurationBuilder;
      36: aload_0
      37: invokespecial #10                 // Method initCompatibilitySettings:()V
      40: return

  public org.infinispan.configuration.cache.AbstractStoreConfigurationBuilder(org.infinispan.configuration.cache.PersistenceConfigurationBuilder, org.infinispan.commons.configuration.attributes.AttributeSet);
    Code:
       0: aload_0
       1: aload_1
       2: invokespecial #1                  // Method org/infinispan/configuration/cache/AbstractPersistenceConfigurationChildBuilder."<init>":(Lorg/infinispan/configuration/cache/PersistenceConfigurationBuilder;)V
       5: aload_0
       6: aload_2
       7: putfield      #3                  // Field attributes:Lorg/infinispan/commons/configuration/attributes/AttributeSet;
      10: aload_0
      11: new           #4                  // class org/infinispan/configuration/cache/AsyncStoreConfigurationBuilder
      14: dup
      15: aload_0
      16: invokespecial #5                  // Method org/infinispan/configuration/cache/AsyncStoreConfigurationBuilder."<init>":(Lorg/infinispan/configuration/cache/AbstractStoreConfigurationBuilder;)V
      19: putfield      #6                  // Field async:Lorg/infinispan/configuration/cache/AsyncStoreConfigurationBuilder;
      22: aload_0
      23: new           #7                  // class org/infinispan/configuration/cache/SingletonStoreConfigurationBuilder
      26: dup
      27: aload_0
      28: invokespecial #8                  // Method org/infinispan/configuration/cache/SingletonStoreConfigurationBuilder."<init>":(Lorg/infinispan/configuration/cache/AbstractStoreConfigurationBuilder;)V
      31: putfield      #9                  // Field singletonStore:Lorg/infinispan/configuration/cache/SingletonStoreConfigurationBuilder;
      34: aload_0
      35: invokespecial #10                 // Method initCompatibilitySettings:()V
      38: return

  private void initCompatibilitySettings();
    Code:
       0: aload_0
       1: aload_0
       2: getfield      #3                  // Field attributes:Lorg/infinispan/commons/configuration/attributes/AttributeSet;
       5: getstatic     #11                 // Field org/infinispan/configuration/cache/AbstractStoreConfiguration.FETCH_PERSISTENT_STATE:Lorg/infinispan/commons/configuration/attributes/AttributeDefinition;
       8: invokevirtual #12                 // Method org/infinispan/commons/configuration/attributes/AttributeSet.attribute:(Lorg/infinispan/commons/configuration/attributes/AttributeDefinition;)Lorg/infinispan/commons/configuration/attributes/Attribute;
      11: invokevirtual #13                 // Method org/infinispan/commons/configuration/attributes/Attribute.get:()Ljava/lang/Object;
      14: checkcast     #14                 // class java/lang/Boolean
      17: invokevirtual #15                 // Method java/lang/Boolean.booleanValue:()Z
      20: putfield      #16                 // Field fetchPersistentState:Z
      23: aload_0
      24: aload_0
      25: getfield      #3                  // Field attributes:Lorg/infinispan/commons/configuration/attributes/AttributeSet;
      28: getstatic     #17                 // Field org/infinispan/configuration/cache/AbstractStoreConfiguration.PRELOAD:Lorg/infinispan/commons/configuration/attributes/AttributeDefinition;
      31: invokevirtual #12                 // Method org/infinispan/commons/configuration/attributes/AttributeSet.attribute:(Lorg/infinispan/commons/configuration/attributes/AttributeDefinition;)Lorg/infinispan/commons/configuration/attributes/Attribute;
      34: invokevirtual #13                 // Method org/infinispan/commons/configuration/attributes/Attribute.get:()Ljava/lang/Object;
      37: checkcast     #14                 // class java/lang/Boolean
      40: invokevirtual #15                 // Method java/lang/Boolean.booleanValue:()Z
      43: putfield      #18                 // Field preload:Z
      46: aload_0
      47: aload_0
      48: getfield      #3                  // Field attributes:Lorg/infinispan/commons/configuration/attributes/AttributeSet;
      51: getstatic     #19                 // Field org/infinispan/configuration/cache/AbstractStoreConfiguration.PURGE_ON_STARTUP:Lorg/infinispan/commons/configuration/attributes/AttributeDefinition;
      54: invokevirtual #12                 // Method org/infinispan/commons/configuration/attributes/AttributeSet.attribute:(Lorg/infinispan/commons/configuration/attributes/AttributeDefinition;)Lorg/infinispan/commons/configuration/attributes/Attribute;
      57: invokevirtual #13                 // Method org/infinispan/commons/configuration/attributes/Attribute.get:()Ljava/lang/Object;
      60: checkcast     #14                 // class java/lang/Boolean
      63: invokevirtual #15                 // Method java/lang/Boolean.booleanValue:()Z
      66: putfield      #20                 // Field purgeOnStartup:Z
      69: aload_0
      70: aload_0
      71: getfield      #3                  // Field attributes:Lorg/infinispan/commons/configuration/attributes/AttributeSet;
      74: getstatic     #21                 // Field org/infinispan/configuration/cache/AbstractStoreConfiguration.SHARED:Lorg/infinispan/commons/configuration/attributes/AttributeDefinition;
      77: invokevirtual #12                 // Method org/infinispan/commons/configuration/attributes/AttributeSet.attribute:(Lorg/infinispan/commons/configuration/attributes/AttributeDefinition;)Lorg/infinispan/commons/configuration/attributes/Attribute;
      80: invokevirtual #13                 // Method org/infinispan/commons/configuration/attributes/Attribute.get:()Ljava/lang/Object;
      83: checkcast     #14                 // class java/lang/Boolean
      86: invokevirtual #15                 // Method java/lang/Boolean.booleanValue:()Z
      89: putfield      #22                 // Field shared:Z
      92: aload_0
      93: aload_0
      94: getfield      #3                  // Field attributes:Lorg/infinispan/commons/configuration/attributes/AttributeSet;
      97: getstatic     #23                 // Field org/infinispan/configuration/cache/AbstractStoreConfiguration.IGNORE_MODIFICATIONS:Lorg/infinispan/commons/configuration/attributes/AttributeDefinition;
     100: invokevirtual #12                 // Method org/infinispan/commons/configuration/attributes/AttributeSet.attribute:(Lorg/infinispan/commons/configuration/attributes/AttributeDefinition;)Lorg/infinispan/commons/configuration/attributes/Attribute;
     103: invokevirtual #13                 // Method org/infinispan/commons/configuration/attributes/Attribute.get:()Ljava/lang/Object;
     106: checkcast     #14                 // class java/lang/Boolean
     109: invokevirtual #15                 // Method java/lang/Boolean.booleanValue:()Z
     112: putfield      #24                 // Field ignoreModifications:Z
     115: aload_0
     116: aload_0
     117: getfield      #3                  // Field attributes:Lorg/infinispan/commons/configuration/attributes/AttributeSet;
     120: getstatic     #25                 // Field org/infinispan/configuration/cache/AbstractStoreConfiguration.PROPERTIES:Lorg/infinispan/commons/configuration/attributes/AttributeDefinition;
     123: invokevirtual #12                 // Method org/infinispan/commons/configuration/attributes/AttributeSet.attribute:(Lorg/infinispan/commons/configuration/attributes/AttributeDefinition;)Lorg/infinispan/commons/configuration/attributes/Attribute;
     126: invokevirtual #13                 // Method org/infinispan/commons/configuration/attributes/Attribute.get:()Ljava/lang/Object;
     129: checkcast     #26                 // class java/util/Properties
     132: putfield      #27                 // Field properties:Ljava/util/Properties;
     135: return

  public org.infinispan.configuration.cache.AsyncStoreConfigurationBuilder<S> async();
    Code:
       0: aload_0
       1: getfield      #6                  // Field async:Lorg/infinispan/configuration/cache/AsyncStoreConfigurationBuilder;
       4: areturn

  public org.infinispan.configuration.cache.SingletonStoreConfigurationBuilder<S> singleton();
    Code:
       0: aload_0
       1: getfield      #9                  // Field singletonStore:Lorg/infinispan/configuration/cache/SingletonStoreConfigurationBuilder;
       4: areturn

  public S fetchPersistentState(boolean);
    Code:
       0: aload_0
       1: getfield      #3                  // Field attributes:Lorg/infinispan/commons/configuration/attributes/AttributeSet;
       4: getstatic     #11                 // Field org/infinispan/configuration/cache/AbstractStoreConfiguration.FETCH_PERSISTENT_STATE:Lorg/infinispan/commons/configuration/attributes/AttributeDefinition;
       7: invokevirtual #12                 // Method org/infinispan/commons/configuration/attributes/AttributeSet.attribute:(Lorg/infinispan/commons/configuration/attributes/AttributeDefinition;)Lorg/infinispan/commons/configuration/attributes/Attribute;
      10: iload_1
      11: invokestatic  #28                 // Method java/lang/Boolean.valueOf:(Z)Ljava/lang/Boolean;
      14: invokevirtual #29                 // Method org/infinispan/commons/configuration/attributes/Attribute.set:(Ljava/lang/Object;)V
      17: aload_0
      18: iload_1
      19: putfield      #16                 // Field fetchPersistentState:Z
      22: aload_0
      23: invokevirtual #30                 // Method self:()Lorg/infinispan/commons/configuration/Self;
      26: checkcast     #31                 // class org/infinispan/configuration/cache/AbstractStoreConfigurationBuilder
      29: areturn

  public S ignoreModifications(boolean);
    Code:
       0: aload_0
       1: getfield      #3                  // Field attributes:Lorg/infinispan/commons/configuration/attributes/AttributeSet;
       4: getstatic     #23                 // Field org/infinispan/configuration/cache/AbstractStoreConfiguration.IGNORE_MODIFICATIONS:Lorg/infinispan/commons/configuration/attributes/AttributeDefinition;
       7: invokevirtual #12                 // Method org/infinispan/commons/configuration/attributes/AttributeSet.attribute:(Lorg/infinispan/commons/configuration/attributes/AttributeDefinition;)Lorg/infinispan/commons/configuration/attributes/Attribute;
      10: iload_1
      11: invokestatic  #28                 // Method java/lang/Boolean.valueOf:(Z)Ljava/lang/Boolean;
      14: invokevirtual #29                 // Method org/infinispan/commons/configuration/attributes/Attribute.set:(Ljava/lang/Object;)V
      17: aload_0
      18: iload_1
      19: putfield      #24                 // Field ignoreModifications:Z
      22: aload_0
      23: invokevirtual #30                 // Method self:()Lorg/infinispan/commons/configuration/Self;
      26: checkcast     #31                 // class org/infinispan/configuration/cache/AbstractStoreConfigurationBuilder
      29: areturn

  public S purgeOnStartup(boolean);
    Code:
       0: aload_0
       1: getfield      #3                  // Field attributes:Lorg/infinispan/commons/configuration/attributes/AttributeSet;
       4: getstatic     #19                 // Field org/infinispan/configuration/cache/AbstractStoreConfiguration.PURGE_ON_STARTUP:Lorg/infinispan/commons/configuration/attributes/AttributeDefinition;
       7: invokevirtual #12                 // Method org/infinispan/commons/configuration/attributes/AttributeSet.attribute:(Lorg/infinispan/commons/configuration/attributes/AttributeDefinition;)Lorg/infinispan/commons/configuration/attributes/Attribute;
      10: iload_1
      11: invokestatic  #28                 // Method java/lang/Boolean.valueOf:(Z)Ljava/lang/Boolean;
      14: invokevirtual #29                 // Method org/infinispan/commons/configuration/attributes/Attribute.set:(Ljava/lang/Object;)V
      17: aload_0
      18: iload_1
      19: putfield      #20                 // Field purgeOnStartup:Z
      22: aload_0
      23: invokevirtual #30                 // Method self:()Lorg/infinispan/commons/configuration/Self;
      26: checkcast     #31                 // class org/infinispan/configuration/cache/AbstractStoreConfigurationBuilder
      29: areturn

  public S properties(java.util.Properties);
    Code:
       0: aload_0
       1: getfield      #3                  // Field attributes:Lorg/infinispan/commons/configuration/attributes/AttributeSet;
       4: getstatic     #25                 // Field org/infinispan/configuration/cache/AbstractStoreConfiguration.PROPERTIES:Lorg/infinispan/commons/configuration/attributes/AttributeDefinition;
       7: invokevirtual #12                 // Method org/infinispan/commons/configuration/attributes/AttributeSet.attribute:(Lorg/infinispan/commons/configuration/attributes/AttributeDefinition;)Lorg/infinispan/commons/configuration/attributes/Attribute;
      10: new           #32                 // class org/infinispan/commons/util/TypedProperties
      13: dup
      14: aload_1
      15: invokespecial #33                 // Method org/infinispan/commons/util/TypedProperties."<init>":(Ljava/util/Properties;)V
      18: invokevirtual #29                 // Method org/infinispan/commons/configuration/attributes/Attribute.set:(Ljava/lang/Object;)V
      21: aload_0
      22: aload_1
      23: putfield      #27                 // Field properties:Ljava/util/Properties;
      26: aload_0
      27: invokevirtual #30                 // Method self:()Lorg/infinispan/commons/configuration/Self;
      30: checkcast     #31                 // class org/infinispan/configuration/cache/AbstractStoreConfigurationBuilder
      33: areturn

  public S addProperty(java.lang.String, java.lang.String);
    Code:
       0: aload_0
       1: getfield      #3                  // Field attributes:Lorg/infinispan/commons/configuration/attributes/AttributeSet;
       4: getstatic     #25                 // Field org/infinispan/configuration/cache/AbstractStoreConfiguration.PROPERTIES:Lorg/infinispan/commons/configuration/attributes/AttributeDefinition;
       7: invokevirtual #12                 // Method org/infinispan/commons/configuration/attributes/AttributeSet.attribute:(Lorg/infinispan/commons/configuration/attributes/AttributeDefinition;)Lorg/infinispan/commons/configuration/attributes/Attribute;
      10: invokevirtual #13                 // Method org/infinispan/commons/configuration/attributes/Attribute.get:()Ljava/lang/Object;
      13: checkcast     #32                 // class org/infinispan/commons/util/TypedProperties
      16: astore_3
      17: aload_3
      18: aload_1
      19: aload_2
      20: invokevirtual #34                 // Method org/infinispan/commons/util/TypedProperties.put:(Ljava/lang/Object;Ljava/lang/Object;)Ljava/lang/Object;
      23: pop
      24: aload_0
      25: getfield      #3                  // Field attributes:Lorg/infinispan/commons/configuration/attributes/AttributeSet;
      28: getstatic     #25                 // Field org/infinispan/configuration/cache/AbstractStoreConfiguration.PROPERTIES:Lorg/infinispan/commons/configuration/attributes/AttributeDefinition;
      31: invokevirtual #12                 // Method org/infinispan/commons/configuration/attributes/AttributeSet.attribute:(Lorg/infinispan/commons/configuration/attributes/AttributeDefinition;)Lorg/infinispan/commons/configuration/attributes/Attribute;
      34: aload_3
      35: invokevirtual #29                 // Method org/infinispan/commons/configuration/attributes/Attribute.set:(Ljava/lang/Object;)V
      38: aload_0
      39: getfield      #3                  // Field attributes:Lorg/infinispan/commons/configuration/attributes/AttributeSet;
      42: aload_3
      43: iconst_0
      44: iconst_0
      45: invokestatic  #35                 // Method org/infinispan/configuration/parsing/XmlConfigHelper.setAttributes:(Lorg/infinispan/commons/configuration/attributes/AttributeSet;Ljava/util/Map;ZZ)Ljava/util/Map;
      48: pop
      49: aload_0
      50: aload_3
      51: putfield      #27                 // Field properties:Ljava/util/Properties;
      54: aload_0
      55: invokevirtual #30                 // Method self:()Lorg/infinispan/commons/configuration/Self;
      58: checkcast     #31                 // class org/infinispan/configuration/cache/AbstractStoreConfigurationBuilder
      61: areturn

  public S withProperties(java.util.Properties);
    Code:
       0: aload_0
       1: getfield      #3                  // Field attributes:Lorg/infinispan/commons/configuration/attributes/AttributeSet;
       4: aload_1
       5: iconst_0
       6: iconst_0
       7: invokestatic  #35                 // Method org/infinispan/configuration/parsing/XmlConfigHelper.setAttributes:(Lorg/infinispan/commons/configuration/attributes/AttributeSet;Ljava/util/Map;ZZ)Ljava/util/Map;
      10: invokestatic  #36                 // Method org/infinispan/configuration/parsing/XmlConfigHelper.showUnrecognizedAttributes:(Ljava/util/Map;)V
      13: aload_0
      14: getfield      #3                  // Field attributes:Lorg/infinispan/commons/configuration/attributes/AttributeSet;
      17: getstatic     #25                 // Field org/infinispan/configuration/cache/AbstractStoreConfiguration.PROPERTIES:Lorg/infinispan/commons/configuration/attributes/AttributeDefinition;
      20: invokevirtual #12                 // Method org/infinispan/commons/configuration/attributes/AttributeSet.attribute:(Lorg/infinispan/commons/configuration/attributes/AttributeDefinition;)Lorg/infinispan/commons/configuration/attributes/Attribute;
      23: new           #32                 // class org/infinispan/commons/util/TypedProperties
      26: dup
      27: aload_1
      28: invokespecial #33                 // Method org/infinispan/commons/util/TypedProperties."<init>":(Ljava/util/Properties;)V
      31: invokevirtual #29                 // Method org/infinispan/commons/configuration/attributes/Attribute.set:(Ljava/lang/Object;)V
      34: aload_0
      35: aload_1
      36: putfield      #27                 // Field properties:Ljava/util/Properties;
      39: aload_0
      40: invokevirtual #30                 // Method self:()Lorg/infinispan/commons/configuration/Self;
      43: checkcast     #31                 // class org/infinispan/configuration/cache/AbstractStoreConfigurationBuilder
      46: areturn

  public S preload(boolean);
    Code:
       0: aload_0
       1: getfield      #3                  // Field attributes:Lorg/infinispan/commons/configuration/attributes/AttributeSet;
       4: getstatic     #17                 // Field org/infinispan/configuration/cache/AbstractStoreConfiguration.PRELOAD:Lorg/infinispan/commons/configuration/attributes/AttributeDefinition;
       7: invokevirtual #12                 // Method org/infinispan/commons/configuration/attributes/AttributeSet.attribute:(Lorg/infinispan/commons/configuration/attributes/AttributeDefinition;)Lorg/infinispan/commons/configuration/attributes/Attribute;
      10: iload_1
      11: invokestatic  #28                 // Method java/lang/Boolean.valueOf:(Z)Ljava/lang/Boolean;
      14: invokevirtual #29                 // Method org/infinispan/commons/configuration/attributes/Attribute.set:(Ljava/lang/Object;)V
      17: aload_0
      18: iload_1
      19: putfield      #18                 // Field preload:Z
      22: aload_0
      23: invokevirtual #30                 // Method self:()Lorg/infinispan/commons/configuration/Self;
      26: checkcast     #31                 // class org/infinispan/configuration/cache/AbstractStoreConfigurationBuilder
      29: areturn

  public S shared(boolean);
    Code:
       0: aload_0
       1: getfield      #3                  // Field attributes:Lorg/infinispan/commons/configuration/attributes/AttributeSet;
       4: getstatic     #21                 // Field org/infinispan/configuration/cache/AbstractStoreConfiguration.SHARED:Lorg/infinispan/commons/configuration/attributes/AttributeDefinition;
       7: invokevirtual #12                 // Method org/infinispan/commons/configuration/attributes/AttributeSet.attribute:(Lorg/infinispan/commons/configuration/attributes/AttributeDefinition;)Lorg/infinispan/commons/configuration/attributes/Attribute;
      10: iload_1
      11: invokestatic  #28                 // Method java/lang/Boolean.valueOf:(Z)Ljava/lang/Boolean;
      14: invokevirtual #29                 // Method org/infinispan/commons/configuration/attributes/Attribute.set:(Ljava/lang/Object;)V
      17: aload_0
      18: iload_1
      19: putfield      #22                 // Field shared:Z
      22: aload_0
      23: invokevirtual #30                 // Method self:()Lorg/infinispan/commons/configuration/Self;
      26: checkcast     #31                 // class org/infinispan/configuration/cache/AbstractStoreConfigurationBuilder
      29: areturn

  public void validate();
    Code:
       0: aload_0
       1: getfield      #6                  // Field async:Lorg/infinispan/configuration/cache/AsyncStoreConfigurationBuilder;
       4: invokevirtual #37                 // Method org/infinispan/configuration/cache/AsyncStoreConfigurationBuilder.validate:()V
       7: aload_0
       8: getfield      #9                  // Field singletonStore:Lorg/infinispan/configuration/cache/SingletonStoreConfigurationBuilder;
      11: invokevirtual #38                 // Method org/infinispan/configuration/cache/SingletonStoreConfigurationBuilder.validate:()V
      14: aload_0
      15: getfield      #3                  // Field attributes:Lorg/infinispan/commons/configuration/attributes/AttributeSet;
      18: getstatic     #21                 // Field org/infinispan/configuration/cache/AbstractStoreConfiguration.SHARED:Lorg/infinispan/commons/configuration/attributes/AttributeDefinition;
      21: invokevirtual #12                 // Method org/infinispan/commons/configuration/attributes/AttributeSet.attribute:(Lorg/infinispan/commons/configuration/attributes/AttributeDefinition;)Lorg/infinispan/commons/configuration/attributes/Attribute;
      24: invokevirtual #13                 // Method org/infinispan/commons/configuration/attributes/Attribute.get:()Ljava/lang/Object;
      27: checkcast     #14                 // class java/lang/Boolean
      30: invokevirtual #15                 // Method java/lang/Boolean.booleanValue:()Z
      33: istore_1
      34: aload_0
      35: getfield      #3                  // Field attributes:Lorg/infinispan/commons/configuration/attributes/AttributeSet;
      38: getstatic     #11                 // Field org/infinispan/configuration/cache/AbstractStoreConfiguration.FETCH_PERSISTENT_STATE:Lorg/infinispan/commons/configuration/attributes/AttributeDefinition;
      41: invokevirtual #12                 // Method org/infinispan/commons/configuration/attributes/AttributeSet.attribute:(Lorg/infinispan/commons/configuration/attributes/AttributeDefinition;)Lorg/infinispan/commons/configuration/attributes/Attribute;
      44: invokevirtual #13                 // Method org/infinispan/commons/configuration/attributes/Attribute.get:()Ljava/lang/Object;
      47: checkcast     #14                 // class java/lang/Boolean
      50: invokevirtual #15                 // Method java/lang/Boolean.booleanValue:()Z
      53: istore_2
      54: aload_0
      55: getfield      #3                  // Field attributes:Lorg/infinispan/commons/configuration/attributes/AttributeSet;
      58: getstatic     #19                 // Field org/infinispan/configuration/cache/AbstractStoreConfiguration.PURGE_ON_STARTUP:Lorg/infinispan/commons/configuration/attributes/AttributeDefinition;
      61: invokevirtual #12                 // Method org/infinispan/commons/configuration/attributes/AttributeSet.attribute:(Lorg/infinispan/commons/configuration/attributes/AttributeDefinition;)Lorg/infinispan/commons/configuration/attributes/Attribute;
      64: invokevirtual #13                 // Method org/infinispan/commons/configuration/attributes/Attribute.get:()Ljava/lang/Object;
      67: checkcast     #14                 // class java/lang/Boolean
      70: invokevirtual #15                 // Method java/lang/Boolean.booleanValue:()Z
      73: istore_3
      74: aload_0
      75: getfield      #3                  // Field attributes:Lorg/infinispan/commons/configuration/attributes/AttributeSet;
      78: getstatic     #17                 // Field org/infinispan/configuration/cache/AbstractStoreConfiguration.PRELOAD:Lorg/infinispan/commons/configuration/attributes/AttributeDefinition;
      81: invokevirtual #12                 // Method org/infinispan/commons/configuration/attributes/AttributeSet.attribute:(Lorg/infinispan/commons/configuration/attributes/AttributeDefinition;)Lorg/infinispan/commons/configuration/attributes/Attribute;
      84: invokevirtual #13                 // Method org/infinispan/commons/configuration/attributes/Attribute.get:()Ljava/lang/Object;
      87: checkcast     #14                 // class java/lang/Boolean
      90: invokevirtual #15                 // Method java/lang/Boolean.booleanValue:()Z
      93: istore        4
      95: aload_0
      96: invokevirtual #39                 // Method getBuilder:()Lorg/infinispan/configuration/cache/ConfigurationBuilder;
      99: astore        5
     101: iload_1
     102: ifne          135
     105: iload_2
     106: ifne          135
     109: iload_3
     110: ifne          135
     113: aload         5
     115: invokevirtual #40                 // Method org/infinispan/configuration/cache/ConfigurationBuilder.clustering:()Lorg/infinispan/configuration/cache/ClusteringConfigurationBuilder;
     118: invokevirtual #41                 // Method org/infinispan/configuration/cache/ClusteringConfigurationBuilder.cacheMode:()Lorg/infinispan/configuration/cache/CacheMode;
     121: invokevirtual #42                 // Method org/infinispan/configuration/cache/CacheMode.isClustered:()Z
     124: ifeq          135
     127: getstatic     #43                 // Field log:Lorg/infinispan/util/logging/Log;
     130: invokeinterface #44,  1           // InterfaceMethod org/infinispan/util/logging/Log.staleEntriesWithoutFetchPersistentStateOrPurgeOnStartup:()V
     135: iload_1
     136: ifeq          174
     139: iload         4
     141: ifne          174
     144: aload         5
     146: invokevirtual #45                 // Method org/infinispan/configuration/cache/ConfigurationBuilder.indexing:()Lorg/infinispan/configuration/cache/IndexingConfigurationBuilder;
     149: invokevirtual #46                 // Method org/infinispan/configuration/cache/IndexingConfigurationBuilder.enabled:()Z
     152: ifeq          174
     155: aload         5
     157: invokevirtual #45                 // Method org/infinispan/configuration/cache/ConfigurationBuilder.indexing:()Lorg/infinispan/configuration/cache/IndexingConfigurationBuilder;
     160: invokevirtual #47                 // Method org/infinispan/configuration/cache/IndexingConfigurationBuilder.indexLocalOnly:()Z
     163: ifeq          174
     166: getstatic     #43                 // Field log:Lorg/infinispan/util/logging/Log;
     169: invokeinterface #48,  1           // InterfaceMethod org/infinispan/util/logging/Log.localIndexingWithSharedCacheLoaderRequiresPreload:()V
     174: return

  public void validate(org.infinispan.configuration.global.GlobalConfiguration);
    Code:
       0: return

  public org.infinispan.commons.configuration.Builder<?> read(T);
    Code:
       0: aload_1
       1: invokevirtual #49                 // Method java/lang/Object.getClass:()Ljava/lang/Class;
       4: ldc           #50                 // String attributes
       6: invokestatic  #51                 // Method org/infinispan/commons/util/ReflectionUtil.findMethod:(Ljava/lang/Class;Ljava/lang/String;)Ljava/lang/reflect/Method;
       9: astore_2
      10: aload_0
      11: getfield      #3                  // Field attributes:Lorg/infinispan/commons/configuration/attributes/AttributeSet;
      14: aload_2
      15: aload_1
      16: aconst_null
      17: invokevirtual #52                 // Method java/lang/reflect/Method.invoke:(Ljava/lang/Object;[Ljava/lang/Object;)Ljava/lang/Object;
      20: checkcast     #53                 // class org/infinispan/commons/configuration/attributes/AttributeSet
      23: invokevirtual #54                 // Method org/infinispan/commons/configuration/attributes/AttributeSet.read:(Lorg/infinispan/commons/configuration/attributes/AttributeSet;)V
      26: goto          39
      29: astore_3
      30: new           #56                 // class org/infinispan/commons/CacheConfigurationException
      33: dup
      34: aload_3
      35: invokespecial #57                 // Method org/infinispan/commons/CacheConfigurationException."<init>":(Ljava/lang/Exception;)V
      38: athrow
      39: aload_0
      40: invokespecial #10                 // Method initCompatibilitySettings:()V
      43: aload_0
      44: getfield      #6                  // Field async:Lorg/infinispan/configuration/cache/AsyncStoreConfigurationBuilder;
      47: aload_1
      48: invokeinterface #58,  1           // InterfaceMethod org/infinispan/configuration/cache/StoreConfiguration.async:()Lorg/infinispan/configuration/cache/AsyncStoreConfiguration;
      53: invokevirtual #59                 // Method org/infinispan/configuration/cache/AsyncStoreConfigurationBuilder.read:(Lorg/infinispan/configuration/cache/AsyncStoreConfiguration;)Lorg/infinispan/configuration/cache/AsyncStoreConfigurationBuilder;
      56: pop
      57: aload_0
      58: getfield      #9                  // Field singletonStore:Lorg/infinispan/configuration/cache/SingletonStoreConfigurationBuilder;
      61: aload_1
      62: invokeinterface #60,  1           // InterfaceMethod org/infinispan/configuration/cache/StoreConfiguration.singletonStore:()Lorg/infinispan/configuration/cache/SingletonStoreConfiguration;
      67: invokevirtual #61                 // Method org/infinispan/configuration/cache/SingletonStoreConfigurationBuilder.read:(Lorg/infinispan/configuration/cache/SingletonStoreConfiguration;)Lorg/infinispan/configuration/cache/SingletonStoreConfigurationBuilder;
      70: pop
      71: aload_0
      72: areturn
    Exception table:
       from    to  target type
          10    26    29   Class java/lang/Exception

  public java.lang.String toString();
    Code:
       0: new           #62                 // class java/lang/StringBuilder
       3: dup
       4: invokespecial #63                 // Method java/lang/StringBuilder."<init>":()V
       7: ldc           #64                 // String AbstractStoreConfigurationBuilder [attributes=
       9: invokevirtual #65                 // Method java/lang/StringBuilder.append:(Ljava/lang/String;)Ljava/lang/StringBuilder;
      12: aload_0
      13: getfield      #3                  // Field attributes:Lorg/infinispan/commons/configuration/attributes/AttributeSet;
      16: invokevirtual #66                 // Method java/lang/StringBuilder.append:(Ljava/lang/Object;)Ljava/lang/StringBuilder;
      19: ldc           #67                 // String , async=
      21: invokevirtual #65                 // Method java/lang/StringBuilder.append:(Ljava/lang/String;)Ljava/lang/StringBuilder;
      24: aload_0
      25: getfield      #6                  // Field async:Lorg/infinispan/configuration/cache/AsyncStoreConfigurationBuilder;
      28: invokevirtual #66                 // Method java/lang/StringBuilder.append:(Ljava/lang/Object;)Ljava/lang/StringBuilder;
      31: ldc           #68                 // String , singletonStore=
      33: invokevirtual #65                 // Method java/lang/StringBuilder.append:(Ljava/lang/String;)Ljava/lang/StringBuilder;
      36: aload_0
      37: getfield      #9                  // Field singletonStore:Lorg/infinispan/configuration/cache/SingletonStoreConfigurationBuilder;
      40: invokevirtual #66                 // Method java/lang/StringBuilder.append:(Ljava/lang/Object;)Ljava/lang/StringBuilder;
      43: ldc           #69                 // String ]
      45: invokevirtual #65                 // Method java/lang/StringBuilder.append:(Ljava/lang/String;)Ljava/lang/StringBuilder;
      48: invokevirtual #70                 // Method java/lang/StringBuilder.toString:()Ljava/lang/String;
      51: areturn

  public org.infinispan.commons.configuration.Builder read(java.lang.Object);
    Code:
       0: aload_0
       1: aload_1
       2: checkcast     #71                 // class org/infinispan/configuration/cache/StoreConfiguration
       5: invokevirtual #72                 // Method read:(Lorg/infinispan/configuration/cache/StoreConfiguration;)Lorg/infinispan/commons/configuration/Builder;
       8: areturn

  public java.lang.Object withProperties(java.util.Properties);
    Code:
       0: aload_0
       1: aload_1
       2: invokevirtual #73                 // Method withProperties:(Ljava/util/Properties;)Lorg/infinispan/configuration/cache/AbstractStoreConfigurationBuilder;
       5: areturn

  public java.lang.Object addProperty(java.lang.String, java.lang.String);
    Code:
       0: aload_0
       1: aload_1
       2: aload_2
       3: invokevirtual #74                 // Method addProperty:(Ljava/lang/String;Ljava/lang/String;)Lorg/infinispan/configuration/cache/AbstractStoreConfigurationBuilder;
       6: areturn

  public java.lang.Object shared(boolean);
    Code:
       0: aload_0
       1: iload_1
       2: invokevirtual #75                 // Method shared:(Z)Lorg/infinispan/configuration/cache/AbstractStoreConfigurationBuilder;
       5: areturn

  public java.lang.Object preload(boolean);
    Code:
       0: aload_0
       1: iload_1
       2: invokevirtual #76                 // Method preload:(Z)Lorg/infinispan/configuration/cache/AbstractStoreConfigurationBuilder;
       5: areturn

  public java.lang.Object purgeOnStartup(boolean);
    Code:
       0: aload_0
       1: iload_1
       2: invokevirtual #77                 // Method purgeOnStartup:(Z)Lorg/infinispan/configuration/cache/AbstractStoreConfigurationBuilder;
       5: areturn

  public java.lang.Object ignoreModifications(boolean);
    Code:
       0: aload_0
       1: iload_1
       2: invokevirtual #78                 // Method ignoreModifications:(Z)Lorg/infinispan/configuration/cache/AbstractStoreConfigurationBuilder;
       5: areturn

  public java.lang.Object fetchPersistentState(boolean);
    Code:
       0: aload_0
       1: iload_1
       2: invokevirtual #79                 // Method fetchPersistentState:(Z)Lorg/infinispan/configuration/cache/AbstractStoreConfigurationBuilder;
       5: areturn

  static {};
    Code:
       0: ldc           #31                 // class org/infinispan/configuration/cache/AbstractStoreConfigurationBuilder
       2: invokestatic  #80                 // Method org/infinispan/util/logging/LogFactory.getLog:(Ljava/lang/Class;)Lorg/infinispan/util/logging/Log;
       5: putstatic     #43                 // Field log:Lorg/infinispan/util/logging/Log;
       8: return
}
