Compiled from "InterceptorConfiguration.java"
public final class org.infinispan.configuration.cache.InterceptorConfiguration$Position extends java.lang.Enum<org.infinispan.configuration.cache.InterceptorConfiguration$Position> {
  public static final org.infinispan.configuration.cache.InterceptorConfiguration$Position FIRST;

  public static final org.infinispan.configuration.cache.InterceptorConfiguration$Position LAST;

  public static final org.infinispan.configuration.cache.InterceptorConfiguration$Position OTHER_THAN_FIRST_OR_LAST;

  private static final org.infinispan.configuration.cache.InterceptorConfiguration$Position[] $VALUES;

  public static org.infinispan.configuration.cache.InterceptorConfiguration$Position[] values();
    Code:
       0: getstatic     #1                  // Field $VALUES:[Lorg/infinispan/configuration/cache/InterceptorConfiguration$Position;
       3: invokevirtual #2                  // Method "[Lorg/infinispan/configuration/cache/InterceptorConfiguration$Position;".clone:()Ljava/lang/Object;
       6: checkcast     #3                  // class "[Lorg/infinispan/configuration/cache/InterceptorConfiguration$Position;"
       9: areturn

  public static org.infinispan.configuration.cache.InterceptorConfiguration$Position valueOf(java.lang.String);
    Code:
       0: ldc           #4                  // class org/infinispan/configuration/cache/InterceptorConfiguration$Position
       2: aload_0
       3: invokestatic  #5                  // Method java/lang/Enum.valueOf:(Ljava/lang/Class;Ljava/lang/String;)Ljava/lang/Enum;
       6: checkcast     #4                  // class org/infinispan/configuration/cache/InterceptorConfiguration$Position
       9: areturn

  private org.infinispan.configuration.cache.InterceptorConfiguration$Position();
    Code:
       0: aload_0
       1: aload_1
       2: iload_2
       3: invokespecial #6                  // Method java/lang/Enum."<init>":(Ljava/lang/String;I)V
       6: return

  static {};
    Code:
       0: new           #4                  // class org/infinispan/configuration/cache/InterceptorConfiguration$Position
       3: dup
       4: ldc           #7                  // String FIRST
       6: iconst_0
       7: invokespecial #8                  // Method "<init>":(Ljava/lang/String;I)V
      10: putstatic     #9                  // Field FIRST:Lorg/infinispan/configuration/cache/InterceptorConfiguration$Position;
      13: new           #4                  // class org/infinispan/configuration/cache/InterceptorConfiguration$Position
      16: dup
      17: ldc           #10                 // String LAST
      19: iconst_1
      20: invokespecial #8                  // Method "<init>":(Ljava/lang/String;I)V
      23: putstatic     #11                 // Field LAST:Lorg/infinispan/configuration/cache/InterceptorConfiguration$Position;
      26: new           #4                  // class org/infinispan/configuration/cache/InterceptorConfiguration$Position
      29: dup
      30: ldc           #12                 // String OTHER_THAN_FIRST_OR_LAST
      32: iconst_2
      33: invokespecial #8                  // Method "<init>":(Ljava/lang/String;I)V
      36: putstatic     #13                 // Field OTHER_THAN_FIRST_OR_LAST:Lorg/infinispan/configuration/cache/InterceptorConfiguration$Position;
      39: iconst_3
      40: anewarray     #4                  // class org/infinispan/configuration/cache/InterceptorConfiguration$Position
      43: dup
      44: iconst_0
      45: getstatic     #9                  // Field FIRST:Lorg/infinispan/configuration/cache/InterceptorConfiguration$Position;
      48: aastore
      49: dup
      50: iconst_1
      51: getstatic     #11                 // Field LAST:Lorg/infinispan/configuration/cache/InterceptorConfiguration$Position;
      54: aastore
      55: dup
      56: iconst_2
      57: getstatic     #13                 // Field OTHER_THAN_FIRST_OR_LAST:Lorg/infinispan/configuration/cache/InterceptorConfiguration$Position;
      60: aastore
      61: putstatic     #1                  // Field $VALUES:[Lorg/infinispan/configuration/cache/InterceptorConfiguration$Position;
      64: return
}
