Compiled from "InterceptorConfiguration.java"
public class org.infinispan.configuration.cache.InterceptorConfiguration extends org.infinispan.commons.configuration.AbstractTypedPropertiesConfiguration {
  public static final org.infinispan.commons.configuration.attributes.AttributeDefinition<org.infinispan.configuration.cache.InterceptorConfiguration$Position> POSITION;

  public static final org.infinispan.commons.configuration.attributes.AttributeDefinition<java.lang.Class> AFTER;

  public static final org.infinispan.commons.configuration.attributes.AttributeDefinition<java.lang.Class> BEFORE;

  public static final org.infinispan.commons.configuration.attributes.AttributeDefinition<org.infinispan.interceptors.base.CommandInterceptor> INTERCEPTOR;

  public static final org.infinispan.commons.configuration.attributes.AttributeDefinition<java.lang.Class> INTERCEPTOR_CLASS;

  public static final org.infinispan.commons.configuration.attributes.AttributeDefinition<java.lang.Integer> INDEX;

  private final org.infinispan.commons.configuration.attributes.Attribute<org.infinispan.configuration.cache.InterceptorConfiguration$Position> position;

  private final org.infinispan.commons.configuration.attributes.Attribute<java.lang.Class> after;

  private final org.infinispan.commons.configuration.attributes.Attribute<java.lang.Class> before;

  private final org.infinispan.commons.configuration.attributes.Attribute<org.infinispan.interceptors.base.CommandInterceptor> interceptor;

  private final org.infinispan.commons.configuration.attributes.Attribute<java.lang.Class> interceptorClass;

  private final org.infinispan.commons.configuration.attributes.Attribute<java.lang.Integer> index;

  public static org.infinispan.commons.configuration.attributes.AttributeSet attributeDefinitionSet();
    Code:
       0: new           #1                  // class org/infinispan/commons/configuration/attributes/AttributeSet
       3: dup
       4: ldc           #2                  // class org/infinispan/configuration/cache/InterceptorConfiguration
       6: invokestatic  #3                  // Method org/infinispan/commons/configuration/AbstractTypedPropertiesConfiguration.attributeSet:()Lorg/infinispan/commons/configuration/attributes/AttributeSet;
       9: bipush        6
      11: anewarray     #4                  // class org/infinispan/commons/configuration/attributes/AttributeDefinition
      14: dup
      15: iconst_0
      16: getstatic     #5                  // Field POSITION:Lorg/infinispan/commons/configuration/attributes/AttributeDefinition;
      19: aastore
      20: dup
      21: iconst_1
      22: getstatic     #6                  // Field AFTER:Lorg/infinispan/commons/configuration/attributes/AttributeDefinition;
      25: aastore
      26: dup
      27: iconst_2
      28: getstatic     #7                  // Field BEFORE:Lorg/infinispan/commons/configuration/attributes/AttributeDefinition;
      31: aastore
      32: dup
      33: iconst_3
      34: getstatic     #8                  // Field INTERCEPTOR:Lorg/infinispan/commons/configuration/attributes/AttributeDefinition;
      37: aastore
      38: dup
      39: iconst_4
      40: getstatic     #9                  // Field INTERCEPTOR_CLASS:Lorg/infinispan/commons/configuration/attributes/AttributeDefinition;
      43: aastore
      44: dup
      45: iconst_5
      46: getstatic     #10                 // Field INDEX:Lorg/infinispan/commons/configuration/attributes/AttributeDefinition;
      49: aastore
      50: invokespecial #11                 // Method org/infinispan/commons/configuration/attributes/AttributeSet."<init>":(Ljava/lang/Class;Lorg/infinispan/commons/configuration/attributes/AttributeSet;[Lorg/infinispan/commons/configuration/attributes/AttributeDefinition;)V
      53: areturn

  org.infinispan.configuration.cache.InterceptorConfiguration(org.infinispan.commons.configuration.attributes.AttributeSet);
    Code:
       0: aload_0
       1: aload_1
       2: invokespecial #12                 // Method org/infinispan/commons/configuration/AbstractTypedPropertiesConfiguration."<init>":(Lorg/infinispan/commons/configuration/attributes/AttributeSet;)V
       5: aload_0
       6: aload_1
       7: getstatic     #5                  // Field POSITION:Lorg/infinispan/commons/configuration/attributes/AttributeDefinition;
      10: invokevirtual #13                 // Method org/infinispan/commons/configuration/attributes/AttributeSet.attribute:(Lorg/infinispan/commons/configuration/attributes/AttributeDefinition;)Lorg/infinispan/commons/configuration/attributes/Attribute;
      13: putfield      #14                 // Field position:Lorg/infinispan/commons/configuration/attributes/Attribute;
      16: aload_0
      17: aload_1
      18: getstatic     #6                  // Field AFTER:Lorg/infinispan/commons/configuration/attributes/AttributeDefinition;
      21: invokevirtual #13                 // Method org/infinispan/commons/configuration/attributes/AttributeSet.attribute:(Lorg/infinispan/commons/configuration/attributes/AttributeDefinition;)Lorg/infinispan/commons/configuration/attributes/Attribute;
      24: putfield      #15                 // Field after:Lorg/infinispan/commons/configuration/attributes/Attribute;
      27: aload_0
      28: aload_1
      29: getstatic     #7                  // Field BEFORE:Lorg/infinispan/commons/configuration/attributes/AttributeDefinition;
      32: invokevirtual #13                 // Method org/infinispan/commons/configuration/attributes/AttributeSet.attribute:(Lorg/infinispan/commons/configuration/attributes/AttributeDefinition;)Lorg/infinispan/commons/configuration/attributes/Attribute;
      35: putfield      #16                 // Field before:Lorg/infinispan/commons/configuration/attributes/Attribute;
      38: aload_0
      39: aload_1
      40: getstatic     #8                  // Field INTERCEPTOR:Lorg/infinispan/commons/configuration/attributes/AttributeDefinition;
      43: invokevirtual #13                 // Method org/infinispan/commons/configuration/attributes/AttributeSet.attribute:(Lorg/infinispan/commons/configuration/attributes/AttributeDefinition;)Lorg/infinispan/commons/configuration/attributes/Attribute;
      46: putfield      #17                 // Field interceptor:Lorg/infinispan/commons/configuration/attributes/Attribute;
      49: aload_0
      50: aload_1
      51: getstatic     #9                  // Field INTERCEPTOR_CLASS:Lorg/infinispan/commons/configuration/attributes/AttributeDefinition;
      54: invokevirtual #13                 // Method org/infinispan/commons/configuration/attributes/AttributeSet.attribute:(Lorg/infinispan/commons/configuration/attributes/AttributeDefinition;)Lorg/infinispan/commons/configuration/attributes/Attribute;
      57: putfield      #18                 // Field interceptorClass:Lorg/infinispan/commons/configuration/attributes/Attribute;
      60: aload_0
      61: aload_1
      62: getstatic     #10                 // Field INDEX:Lorg/infinispan/commons/configuration/attributes/AttributeDefinition;
      65: invokevirtual #13                 // Method org/infinispan/commons/configuration/attributes/AttributeSet.attribute:(Lorg/infinispan/commons/configuration/attributes/AttributeDefinition;)Lorg/infinispan/commons/configuration/attributes/Attribute;
      68: putfield      #19                 // Field index:Lorg/infinispan/commons/configuration/attributes/Attribute;
      71: return

  public java.lang.Class<? extends org.infinispan.interceptors.base.CommandInterceptor> after();
    Code:
       0: aload_0
       1: getfield      #15                 // Field after:Lorg/infinispan/commons/configuration/attributes/Attribute;
       4: invokevirtual #20                 // Method org/infinispan/commons/configuration/attributes/Attribute.get:()Ljava/lang/Object;
       7: checkcast     #21                 // class java/lang/Class
      10: areturn

  public java.lang.Class<? extends org.infinispan.interceptors.base.CommandInterceptor> before();
    Code:
       0: aload_0
       1: getfield      #16                 // Field before:Lorg/infinispan/commons/configuration/attributes/Attribute;
       4: invokevirtual #20                 // Method org/infinispan/commons/configuration/attributes/Attribute.get:()Ljava/lang/Object;
       7: checkcast     #21                 // class java/lang/Class
      10: areturn

  public org.infinispan.interceptors.base.CommandInterceptor interceptor();
    Code:
       0: aload_0
       1: getfield      #17                 // Field interceptor:Lorg/infinispan/commons/configuration/attributes/Attribute;
       4: invokevirtual #22                 // Method org/infinispan/commons/configuration/attributes/Attribute.isNull:()Z
       7: ifeq          27
      10: aload_0
      11: getfield      #18                 // Field interceptorClass:Lorg/infinispan/commons/configuration/attributes/Attribute;
      14: invokevirtual #20                 // Method org/infinispan/commons/configuration/attributes/Attribute.get:()Ljava/lang/Object;
      17: checkcast     #21                 // class java/lang/Class
      20: invokestatic  #23                 // Method org/infinispan/commons/util/Util.getInstance:(Ljava/lang/Class;)Ljava/lang/Object;
      23: checkcast     #24                 // class org/infinispan/interceptors/base/CommandInterceptor
      26: areturn
      27: aload_0
      28: getfield      #17                 // Field interceptor:Lorg/infinispan/commons/configuration/attributes/Attribute;
      31: invokevirtual #20                 // Method org/infinispan/commons/configuration/attributes/Attribute.get:()Ljava/lang/Object;
      34: checkcast     #24                 // class org/infinispan/interceptors/base/CommandInterceptor
      37: areturn

  public java.lang.Class<? extends org.infinispan.interceptors.base.CommandInterceptor> interceptorClass();
    Code:
       0: aload_0
       1: getfield      #18                 // Field interceptorClass:Lorg/infinispan/commons/configuration/attributes/Attribute;
       4: invokevirtual #20                 // Method org/infinispan/commons/configuration/attributes/Attribute.get:()Ljava/lang/Object;
       7: checkcast     #21                 // class java/lang/Class
      10: areturn

  public int index();
    Code:
       0: aload_0
       1: getfield      #19                 // Field index:Lorg/infinispan/commons/configuration/attributes/Attribute;
       4: invokevirtual #20                 // Method org/infinispan/commons/configuration/attributes/Attribute.get:()Ljava/lang/Object;
       7: checkcast     #25                 // class java/lang/Integer
      10: invokevirtual #26                 // Method java/lang/Integer.intValue:()I
      13: ireturn

  public org.infinispan.configuration.cache.InterceptorConfiguration$Position position();
    Code:
       0: aload_0
       1: getfield      #14                 // Field position:Lorg/infinispan/commons/configuration/attributes/Attribute;
       4: invokevirtual #20                 // Method org/infinispan/commons/configuration/attributes/Attribute.get:()Ljava/lang/Object;
       7: checkcast     #27                 // class org/infinispan/configuration/cache/InterceptorConfiguration$Position
      10: areturn

  public boolean first();
    Code:
       0: aload_0
       1: invokevirtual #28                 // Method position:()Lorg/infinispan/configuration/cache/InterceptorConfiguration$Position;
       4: getstatic     #29                 // Field org/infinispan/configuration/cache/InterceptorConfiguration$Position.FIRST:Lorg/infinispan/configuration/cache/InterceptorConfiguration$Position;
       7: if_acmpne     14
      10: iconst_1
      11: goto          15
      14: iconst_0
      15: ireturn

  public boolean last();
    Code:
       0: aload_0
       1: invokevirtual #28                 // Method position:()Lorg/infinispan/configuration/cache/InterceptorConfiguration$Position;
       4: getstatic     #30                 // Field org/infinispan/configuration/cache/InterceptorConfiguration$Position.LAST:Lorg/infinispan/configuration/cache/InterceptorConfiguration$Position;
       7: if_acmpne     14
      10: iconst_1
      11: goto          15
      14: iconst_0
      15: ireturn

  public org.infinispan.commons.configuration.attributes.AttributeSet attributes();
    Code:
       0: aload_0
       1: getfield      #31                 // Field attributes:Lorg/infinispan/commons/configuration/attributes/AttributeSet;
       4: areturn

  public java.lang.String toString();
    Code:
       0: new           #32                 // class java/lang/StringBuilder
       3: dup
       4: invokespecial #33                 // Method java/lang/StringBuilder."<init>":()V
       7: ldc           #34                 // String InterceptorConfiguration [attributes=
       9: invokevirtual #35                 // Method java/lang/StringBuilder.append:(Ljava/lang/String;)Ljava/lang/StringBuilder;
      12: aload_0
      13: getfield      #31                 // Field attributes:Lorg/infinispan/commons/configuration/attributes/AttributeSet;
      16: invokevirtual #36                 // Method java/lang/StringBuilder.append:(Ljava/lang/Object;)Ljava/lang/StringBuilder;
      19: ldc           #37                 // String ]
      21: invokevirtual #35                 // Method java/lang/StringBuilder.append:(Ljava/lang/String;)Ljava/lang/StringBuilder;
      24: invokevirtual #38                 // Method java/lang/StringBuilder.toString:()Ljava/lang/String;
      27: areturn

  static {};
    Code:
       0: ldc           #39                 // String position
       2: getstatic     #40                 // Field org/infinispan/configuration/cache/InterceptorConfiguration$Position.OTHER_THAN_FIRST_OR_LAST:Lorg/infinispan/configuration/cache/InterceptorConfiguration$Position;
       5: invokestatic  #41                 // Method org/infinispan/commons/configuration/attributes/AttributeDefinition.builder:(Ljava/lang/String;Ljava/lang/Object;)Lorg/infinispan/commons/configuration/attributes/AttributeDefinition$Builder;
       8: invokevirtual #42                 // Method org/infinispan/commons/configuration/attributes/AttributeDefinition$Builder.immutable:()Lorg/infinispan/commons/configuration/attributes/AttributeDefinition$Builder;
      11: invokevirtual #43                 // Method org/infinispan/commons/configuration/attributes/AttributeDefinition$Builder.build:()Lorg/infinispan/commons/configuration/attributes/AttributeDefinition;
      14: putstatic     #5                  // Field POSITION:Lorg/infinispan/commons/configuration/attributes/AttributeDefinition;
      17: ldc           #44                 // String after
      19: aconst_null
      20: ldc           #21                 // class java/lang/Class
      22: invokestatic  #45                 // Method org/infinispan/commons/configuration/attributes/AttributeDefinition.builder:(Ljava/lang/String;Ljava/lang/Object;Ljava/lang/Class;)Lorg/infinispan/commons/configuration/attributes/AttributeDefinition$Builder;
      25: invokevirtual #42                 // Method org/infinispan/commons/configuration/attributes/AttributeDefinition$Builder.immutable:()Lorg/infinispan/commons/configuration/attributes/AttributeDefinition$Builder;
      28: invokevirtual #43                 // Method org/infinispan/commons/configuration/attributes/AttributeDefinition$Builder.build:()Lorg/infinispan/commons/configuration/attributes/AttributeDefinition;
      31: putstatic     #6                  // Field AFTER:Lorg/infinispan/commons/configuration/attributes/AttributeDefinition;
      34: ldc           #46                 // String before
      36: aconst_null
      37: ldc           #21                 // class java/lang/Class
      39: invokestatic  #45                 // Method org/infinispan/commons/configuration/attributes/AttributeDefinition.builder:(Ljava/lang/String;Ljava/lang/Object;Ljava/lang/Class;)Lorg/infinispan/commons/configuration/attributes/AttributeDefinition$Builder;
      42: invokevirtual #42                 // Method org/infinispan/commons/configuration/attributes/AttributeDefinition$Builder.immutable:()Lorg/infinispan/commons/configuration/attributes/AttributeDefinition$Builder;
      45: invokevirtual #43                 // Method org/infinispan/commons/configuration/attributes/AttributeDefinition$Builder.build:()Lorg/infinispan/commons/configuration/attributes/AttributeDefinition;
      48: putstatic     #7                  // Field BEFORE:Lorg/infinispan/commons/configuration/attributes/AttributeDefinition;
      51: ldc           #47                 // String interceptor
      53: aconst_null
      54: ldc           #24                 // class org/infinispan/interceptors/base/CommandInterceptor
      56: invokestatic  #45                 // Method org/infinispan/commons/configuration/attributes/AttributeDefinition.builder:(Ljava/lang/String;Ljava/lang/Object;Ljava/lang/Class;)Lorg/infinispan/commons/configuration/attributes/AttributeDefinition$Builder;
      59: getstatic     #48                 // Field org/infinispan/commons/configuration/attributes/IdentityAttributeCopier.INSTANCE:Lorg/infinispan/commons/configuration/attributes/AttributeCopier;
      62: invokevirtual #49                 // Method org/infinispan/commons/configuration/attributes/AttributeDefinition$Builder.copier:(Lorg/infinispan/commons/configuration/attributes/AttributeCopier;)Lorg/infinispan/commons/configuration/attributes/AttributeDefinition$Builder;
      65: invokevirtual #42                 // Method org/infinispan/commons/configuration/attributes/AttributeDefinition$Builder.immutable:()Lorg/infinispan/commons/configuration/attributes/AttributeDefinition$Builder;
      68: invokevirtual #43                 // Method org/infinispan/commons/configuration/attributes/AttributeDefinition$Builder.build:()Lorg/infinispan/commons/configuration/attributes/AttributeDefinition;
      71: putstatic     #8                  // Field INTERCEPTOR:Lorg/infinispan/commons/configuration/attributes/AttributeDefinition;
      74: ldc           #50                 // String interceptorClass
      76: aconst_null
      77: ldc           #21                 // class java/lang/Class
      79: invokestatic  #45                 // Method org/infinispan/commons/configuration/attributes/AttributeDefinition.builder:(Ljava/lang/String;Ljava/lang/Object;Ljava/lang/Class;)Lorg/infinispan/commons/configuration/attributes/AttributeDefinition$Builder;
      82: invokevirtual #42                 // Method org/infinispan/commons/configuration/attributes/AttributeDefinition$Builder.immutable:()Lorg/infinispan/commons/configuration/attributes/AttributeDefinition$Builder;
      85: invokevirtual #43                 // Method org/infinispan/commons/configuration/attributes/AttributeDefinition$Builder.build:()Lorg/infinispan/commons/configuration/attributes/AttributeDefinition;
      88: putstatic     #9                  // Field INTERCEPTOR_CLASS:Lorg/infinispan/commons/configuration/attributes/AttributeDefinition;
      91: ldc           #51                 // String index
      93: iconst_m1
      94: invokestatic  #52                 // Method java/lang/Integer.valueOf:(I)Ljava/lang/Integer;
      97: invokestatic  #41                 // Method org/infinispan/commons/configuration/attributes/AttributeDefinition.builder:(Ljava/lang/String;Ljava/lang/Object;)Lorg/infinispan/commons/configuration/attributes/AttributeDefinition$Builder;
     100: invokevirtual #42                 // Method org/infinispan/commons/configuration/attributes/AttributeDefinition$Builder.immutable:()Lorg/infinispan/commons/configuration/attributes/AttributeDefinition$Builder;
     103: invokevirtual #43                 // Method org/infinispan/commons/configuration/attributes/AttributeDefinition$Builder.build:()Lorg/infinispan/commons/configuration/attributes/AttributeDefinition;
     106: putstatic     #10                 // Field INDEX:Lorg/infinispan/commons/configuration/attributes/AttributeDefinition;
     109: return
}
