Compiled from "VersioningScheme.java"
public final class org.infinispan.configuration.cache.VersioningScheme extends java.lang.Enum<org.infinispan.configuration.cache.VersioningScheme> {
  public static final org.infinispan.configuration.cache.VersioningScheme SIMPLE;

  public static final org.infinispan.configuration.cache.VersioningScheme NONE;

  private static final org.infinispan.configuration.cache.VersioningScheme[] $VALUES;

  public static org.infinispan.configuration.cache.VersioningScheme[] values();
    Code:
       0: getstatic     #1                  // Field $VALUES:[Lorg/infinispan/configuration/cache/VersioningScheme;
       3: invokevirtual #2                  // Method "[Lorg/infinispan/configuration/cache/VersioningScheme;".clone:()Ljava/lang/Object;
       6: checkcast     #3                  // class "[Lorg/infinispan/configuration/cache/VersioningScheme;"
       9: areturn

  public static org.infinispan.configuration.cache.VersioningScheme valueOf(java.lang.String);
    Code:
       0: ldc           #4                  // class org/infinispan/configuration/cache/VersioningScheme
       2: aload_0
       3: invokestatic  #5                  // Method java/lang/Enum.valueOf:(Ljava/lang/Class;Ljava/lang/String;)Ljava/lang/Enum;
       6: checkcast     #4                  // class org/infinispan/configuration/cache/VersioningScheme
       9: areturn

  private org.infinispan.configuration.cache.VersioningScheme();
    Code:
       0: aload_0
       1: aload_1
       2: iload_2
       3: invokespecial #6                  // Method java/lang/Enum."<init>":(Ljava/lang/String;I)V
       6: return

  static {};
    Code:
       0: new           #4                  // class org/infinispan/configuration/cache/VersioningScheme
       3: dup
       4: ldc           #7                  // String SIMPLE
       6: iconst_0
       7: invokespecial #8                  // Method "<init>":(Ljava/lang/String;I)V
      10: putstatic     #9                  // Field SIMPLE:Lorg/infinispan/configuration/cache/VersioningScheme;
      13: new           #4                  // class org/infinispan/configuration/cache/VersioningScheme
      16: dup
      17: ldc           #10                 // String NONE
      19: iconst_1
      20: invokespecial #8                  // Method "<init>":(Ljava/lang/String;I)V
      23: putstatic     #11                 // Field NONE:Lorg/infinispan/configuration/cache/VersioningScheme;
      26: iconst_2
      27: anewarray     #4                  // class org/infinispan/configuration/cache/VersioningScheme
      30: dup
      31: iconst_0
      32: getstatic     #9                  // Field SIMPLE:Lorg/infinispan/configuration/cache/VersioningScheme;
      35: aastore
      36: dup
      37: iconst_1
      38: getstatic     #11                 // Field NONE:Lorg/infinispan/configuration/cache/VersioningScheme;
      41: aastore
      42: putstatic     #1                  // Field $VALUES:[Lorg/infinispan/configuration/cache/VersioningScheme;
      45: return
}
