Compiled from "AjpProtocol.java"
public class org.apache.coyote.ajp.AjpProtocol extends org.apache.coyote.ajp.AjpNioProtocol {
  private static final org.apache.juli.logging.Log log;

  private static final org.apache.tomcat.util.res.StringManager sm;

  public org.apache.coyote.ajp.AjpProtocol();
    Code:
       0: aload_0
       1: invokespecial #1                  // Method org/apache/coyote/ajp/AjpNioProtocol."<init>":()V
       4: getstatic     #2                  // Field log:Lorg/apache/juli/logging/Log;
       7: getstatic     #3                  // Field sm:Lorg/apache/tomcat/util/res/StringManager;
      10: ldc           #4                  // String ajpprotocol.noBio
      12: invokevirtual #5                  // Method org/apache/tomcat/util/res/StringManager.getString:(Ljava/lang/String;)Ljava/lang/String;
      15: invokeinterface #6,  2            // InterfaceMethod org/apache/juli/logging/Log.warn:(Ljava/lang/Object;)V
      20: return

  static {};
    Code:
       0: ldc_w         #7                  // class org/apache/coyote/ajp/AjpProtocol
       3: invokestatic  #8                  // Method org/apache/juli/logging/LogFactory.getLog:(Ljava/lang/Class;)Lorg/apache/juli/logging/Log;
       6: putstatic     #2                  // Field log:Lorg/apache/juli/logging/Log;
       9: ldc_w         #7                  // class org/apache/coyote/ajp/AjpProtocol
      12: invokestatic  #9                  // Method org/apache/tomcat/util/res/StringManager.getManager:(Ljava/lang/Class;)Lorg/apache/tomcat/util/res/StringManager;
      15: putstatic     #3                  // Field sm:Lorg/apache/tomcat/util/res/StringManager;
      18: return
}
