Compiled from "Catalina.java"
public class org.apache.catalina.startup.Catalina {
  protected static final org.apache.tomcat.util.res.StringManager sm;

  public static final java.lang.String SERVER_XML;

  protected boolean await;

  protected java.lang.String configFile;

  protected java.lang.ClassLoader parentClassLoader;

  protected org.apache.catalina.Server server;

  protected boolean useShutdownHook;

  protected java.lang.Thread shutdownHook;

  protected boolean useNaming;

  protected boolean loaded;

  protected boolean generateCode;

  protected java.io.File generatedCodeLocation;

  protected java.lang.String generatedCodeLocationParameter;

  protected java.lang.String generatedCodePackage;

  protected boolean useGeneratedCode;

  private static final org.apache.juli.logging.Log log;

  public org.apache.catalina.startup.Catalina();
    Code:
       0: aload_0
       1: invokespecial #2                  // Method java/lang/Object."<init>":()V
       4: aload_0
       5: iconst_0
       6: putfield      #3                  // Field await:Z
       9: aload_0
      10: ldc           #5                  // String conf/server.xml
      12: putfield      #6                  // Field configFile:Ljava/lang/String;
      15: aload_0
      16: ldc           #4                  // class org/apache/catalina/startup/Catalina
      18: invokevirtual #7                  // Method java/lang/Class.getClassLoader:()Ljava/lang/ClassLoader;
      21: putfield      #8                  // Field parentClassLoader:Ljava/lang/ClassLoader;
      24: aload_0
      25: aconst_null
      26: putfield      #9                  // Field server:Lorg/apache/catalina/Server;
      29: aload_0
      30: iconst_1
      31: putfield      #10                 // Field useShutdownHook:Z
      34: aload_0
      35: aconst_null
      36: putfield      #11                 // Field shutdownHook:Ljava/lang/Thread;
      39: aload_0
      40: iconst_1
      41: putfield      #12                 // Field useNaming:Z
      44: aload_0
      45: iconst_0
      46: putfield      #13                 // Field loaded:Z
      49: aload_0
      50: iconst_0
      51: putfield      #14                 // Field generateCode:Z
      54: aload_0
      55: aconst_null
      56: putfield      #15                 // Field generatedCodeLocation:Ljava/io/File;
      59: aload_0
      60: aconst_null
      61: putfield      #16                 // Field generatedCodeLocationParameter:Ljava/lang/String;
      64: aload_0
      65: ldc           #17                 // String catalinaembedded
      67: putfield      #18                 // Field generatedCodePackage:Ljava/lang/String;
      70: aload_0
      71: iconst_0
      72: putfield      #19                 // Field useGeneratedCode:Z
      75: aload_0
      76: invokevirtual #20                 // Method setSecurityProtection:()V
      79: invokestatic  #21                 // Method org/apache/tomcat/util/ExceptionUtils.preload:()V
      82: return

  public void setConfigFile(java.lang.String);
    Code:
       0: aload_0
       1: aload_1
       2: putfield      #6                  // Field configFile:Ljava/lang/String;
       5: return

  public java.lang.String getConfigFile();
    Code:
       0: aload_0
       1: getfield      #6                  // Field configFile:Ljava/lang/String;
       4: areturn

  public void setUseShutdownHook(boolean);
    Code:
       0: aload_0
       1: iload_1
       2: putfield      #10                 // Field useShutdownHook:Z
       5: return

  public boolean getUseShutdownHook();
    Code:
       0: aload_0
       1: getfield      #10                 // Field useShutdownHook:Z
       4: ireturn

  public boolean getGenerateCode();
    Code:
       0: aload_0
       1: getfield      #14                 // Field generateCode:Z
       4: ireturn

  public void setGenerateCode(boolean);
    Code:
       0: aload_0
       1: iload_1
       2: putfield      #14                 // Field generateCode:Z
       5: return

  public boolean getUseGeneratedCode();
    Code:
       0: aload_0
       1: getfield      #19                 // Field useGeneratedCode:Z
       4: ireturn

  public void setUseGeneratedCode(boolean);
    Code:
       0: aload_0
       1: iload_1
       2: putfield      #19                 // Field useGeneratedCode:Z
       5: return

  public java.io.File getGeneratedCodeLocation();
    Code:
       0: aload_0
       1: getfield      #15                 // Field generatedCodeLocation:Ljava/io/File;
       4: areturn

  public void setGeneratedCodeLocation(java.io.File);
    Code:
       0: aload_0
       1: aload_1
       2: putfield      #15                 // Field generatedCodeLocation:Ljava/io/File;
       5: return

  public java.lang.String getGeneratedCodePackage();
    Code:
       0: aload_0
       1: getfield      #18                 // Field generatedCodePackage:Ljava/lang/String;
       4: areturn

  public void setGeneratedCodePackage(java.lang.String);
    Code:
       0: aload_0
       1: aload_1
       2: putfield      #18                 // Field generatedCodePackage:Ljava/lang/String;
       5: return

  public void setParentClassLoader(java.lang.ClassLoader);
    Code:
       0: aload_0
       1: aload_1
       2: putfield      #8                  // Field parentClassLoader:Ljava/lang/ClassLoader;
       5: return

  public java.lang.ClassLoader getParentClassLoader();
    Code:
       0: aload_0
       1: getfield      #8                  // Field parentClassLoader:Ljava/lang/ClassLoader;
       4: ifnull        12
       7: aload_0
       8: getfield      #8                  // Field parentClassLoader:Ljava/lang/ClassLoader;
      11: areturn
      12: invokestatic  #22                 // Method java/lang/ClassLoader.getSystemClassLoader:()Ljava/lang/ClassLoader;
      15: areturn

  public void setServer(org.apache.catalina.Server);
    Code:
       0: aload_0
       1: aload_1
       2: putfield      #9                  // Field server:Lorg/apache/catalina/Server;
       5: return

  public org.apache.catalina.Server getServer();
    Code:
       0: aload_0
       1: getfield      #9                  // Field server:Lorg/apache/catalina/Server;
       4: areturn

  public boolean isUseNaming();
    Code:
       0: aload_0
       1: getfield      #12                 // Field useNaming:Z
       4: ireturn

  public void setUseNaming(boolean);
    Code:
       0: aload_0
       1: iload_1
       2: putfield      #12                 // Field useNaming:Z
       5: return

  public void setAwait(boolean);
    Code:
       0: aload_0
       1: iload_1
       2: putfield      #3                  // Field await:Z
       5: return

  public boolean isAwait();
    Code:
       0: aload_0
       1: getfield      #3                  // Field await:Z
       4: ireturn

  protected boolean arguments(java.lang.String[]);
    Code:
       0: iconst_0
       1: istore_2
       2: iconst_0
       3: istore_3
       4: aload_1
       5: arraylength
       6: iconst_1
       7: if_icmpge     16
      10: aload_0
      11: invokevirtual #23                 // Method usage:()V
      14: iconst_0
      15: ireturn
      16: aload_1
      17: astore        4
      19: aload         4
      21: arraylength
      22: istore        5
      24: iconst_0
      25: istore        6
      27: iload         6
      29: iload         5
      31: if_icmpge     219
      34: aload         4
      36: iload         6
      38: aaload
      39: astore        7
      41: iload_2
      42: ifeq          56
      45: aload_0
      46: aload         7
      48: putfield      #6                  // Field configFile:Ljava/lang/String;
      51: iconst_0
      52: istore_2
      53: goto          213
      56: aload         7
      58: ldc           #24                 // String -config
      60: invokevirtual #25                 // Method java/lang/String.equals:(Ljava/lang/Object;)Z
      63: ifeq          71
      66: iconst_1
      67: istore_2
      68: goto          213
      71: aload         7
      73: ldc           #26                 // String -generateCode
      75: invokevirtual #25                 // Method java/lang/String.equals:(Ljava/lang/Object;)Z
      78: ifeq          91
      81: aload_0
      82: iconst_1
      83: invokevirtual #27                 // Method setGenerateCode:(Z)V
      86: iconst_1
      87: istore_3
      88: goto          213
      91: aload         7
      93: ldc           #28                 // String -useGeneratedCode
      95: invokevirtual #25                 // Method java/lang/String.equals:(Ljava/lang/Object;)Z
      98: ifeq          111
     101: aload_0
     102: iconst_1
     103: invokevirtual #29                 // Method setUseGeneratedCode:(Z)V
     106: iconst_0
     107: istore_3
     108: goto          213
     111: aload         7
     113: ldc           #30                 // String -nonaming
     115: invokevirtual #25                 // Method java/lang/String.equals:(Ljava/lang/Object;)Z
     118: ifeq          131
     121: aload_0
     122: iconst_0
     123: invokevirtual #31                 // Method setUseNaming:(Z)V
     126: iconst_0
     127: istore_3
     128: goto          213
     131: aload         7
     133: ldc           #32                 // String -help
     135: invokevirtual #25                 // Method java/lang/String.equals:(Ljava/lang/Object;)Z
     138: ifeq          147
     141: aload_0
     142: invokevirtual #23                 // Method usage:()V
     145: iconst_0
     146: ireturn
     147: aload         7
     149: ldc           #33                 // String start
     151: invokevirtual #25                 // Method java/lang/String.equals:(Ljava/lang/Object;)Z
     154: ifeq          162
     157: iconst_0
     158: istore_3
     159: goto          213
     162: aload         7
     164: ldc           #34                 // String configtest
     166: invokevirtual #25                 // Method java/lang/String.equals:(Ljava/lang/Object;)Z
     169: ifeq          177
     172: iconst_0
     173: istore_3
     174: goto          213
     177: aload         7
     179: ldc           #35                 // String stop
     181: invokevirtual #25                 // Method java/lang/String.equals:(Ljava/lang/Object;)Z
     184: ifeq          192
     187: iconst_0
     188: istore_3
     189: goto          213
     192: iload_3
     193: ifeq          207
     196: aload_0
     197: aload         7
     199: putfield      #16                 // Field generatedCodeLocationParameter:Ljava/lang/String;
     202: iconst_0
     203: istore_3
     204: goto          213
     207: aload_0
     208: invokevirtual #23                 // Method usage:()V
     211: iconst_0
     212: ireturn
     213: iinc          6, 1
     216: goto          27
     219: iconst_1
     220: ireturn

  protected java.io.File configFile();
    Code:
       0: new           #36                 // class java/io/File
       3: dup
       4: aload_0
       5: getfield      #6                  // Field configFile:Ljava/lang/String;
       8: invokespecial #37                 // Method java/io/File."<init>":(Ljava/lang/String;)V
      11: astore_1
      12: aload_1
      13: invokevirtual #38                 // Method java/io/File.isAbsolute:()Z
      16: ifne          34
      19: new           #36                 // class java/io/File
      22: dup
      23: invokestatic  #39                 // Method org/apache/catalina/startup/Bootstrap.getCatalinaBase:()Ljava/lang/String;
      26: aload_0
      27: getfield      #6                  // Field configFile:Ljava/lang/String;
      30: invokespecial #40                 // Method java/io/File."<init>":(Ljava/lang/String;Ljava/lang/String;)V
      33: astore_1
      34: aload_1
      35: areturn

  protected org.apache.tomcat.util.digester.Digester createStartDigester();
    Code:
       0: new           #41                 // class org/apache/tomcat/util/digester/Digester
       3: dup
       4: invokespecial #42                 // Method org/apache/tomcat/util/digester/Digester."<init>":()V
       7: astore_1
       8: aload_1
       9: iconst_0
      10: invokevirtual #43                 // Method org/apache/tomcat/util/digester/Digester.setValidating:(Z)V
      13: aload_1
      14: iconst_1
      15: invokevirtual #44                 // Method org/apache/tomcat/util/digester/Digester.setRulesValidation:(Z)V
      18: new           #45                 // class java/util/HashMap
      21: dup
      22: invokespecial #46                 // Method java/util/HashMap."<init>":()V
      25: astore_2
      26: new           #47                 // class java/util/ArrayList
      29: dup
      30: invokespecial #48                 // Method java/util/ArrayList."<init>":()V
      33: astore_3
      34: aload_3
      35: ldc           #49                 // String className
      37: invokeinterface #50,  2           // InterfaceMethod java/util/List.add:(Ljava/lang/Object;)Z
      42: pop
      43: aload_2
      44: ldc           #51                 // class java/lang/Object
      46: aload_3
      47: invokeinterface #52,  3           // InterfaceMethod java/util/Map.put:(Ljava/lang/Object;Ljava/lang/Object;)Ljava/lang/Object;
      52: pop
      53: new           #47                 // class java/util/ArrayList
      56: dup
      57: invokespecial #48                 // Method java/util/ArrayList."<init>":()V
      60: astore        4
      62: aload         4
      64: ldc           #53                 // String source
      66: invokeinterface #50,  2           // InterfaceMethod java/util/List.add:(Ljava/lang/Object;)Z
      71: pop
      72: aload_2
      73: ldc           #54                 // class org/apache/catalina/core/StandardContext
      75: aload         4
      77: invokeinterface #52,  3           // InterfaceMethod java/util/Map.put:(Ljava/lang/Object;Ljava/lang/Object;)Ljava/lang/Object;
      82: pop
      83: new           #47                 // class java/util/ArrayList
      86: dup
      87: invokespecial #48                 // Method java/util/ArrayList."<init>":()V
      90: astore        5
      92: aload         5
      94: ldc           #55                 // String portOffset
      96: invokeinterface #50,  2           // InterfaceMethod java/util/List.add:(Ljava/lang/Object;)Z
     101: pop
     102: aload_2
     103: ldc           #56                 // class org/apache/catalina/connector/Connector
     105: aload         5
     107: invokeinterface #52,  3           // InterfaceMethod java/util/Map.put:(Ljava/lang/Object;Ljava/lang/Object;)Ljava/lang/Object;
     112: pop
     113: aload_1
     114: aload_2
     115: invokevirtual #57                 // Method org/apache/tomcat/util/digester/Digester.setFakeAttributes:(Ljava/util/Map;)V
     118: aload_1
     119: iconst_1
     120: invokevirtual #58                 // Method org/apache/tomcat/util/digester/Digester.setUseContextClassLoader:(Z)V
     123: aload_1
     124: ldc           #59                 // String Server
     126: ldc           #60                 // String org.apache.catalina.core.StandardServer
     128: ldc           #49                 // String className
     130: invokevirtual #61                 // Method org/apache/tomcat/util/digester/Digester.addObjectCreate:(Ljava/lang/String;Ljava/lang/String;Ljava/lang/String;)V
     133: aload_1
     134: ldc           #59                 // String Server
     136: invokevirtual #62                 // Method org/apache/tomcat/util/digester/Digester.addSetProperties:(Ljava/lang/String;)V
     139: aload_1
     140: ldc           #59                 // String Server
     142: ldc           #63                 // String setServer
     144: ldc           #64                 // String org.apache.catalina.Server
     146: invokevirtual #65                 // Method org/apache/tomcat/util/digester/Digester.addSetNext:(Ljava/lang/String;Ljava/lang/String;Ljava/lang/String;)V
     149: aload_1
     150: ldc           #66                 // String Server/GlobalNamingResources
     152: ldc           #67                 // String org.apache.catalina.deploy.NamingResourcesImpl
     154: invokevirtual #68                 // Method org/apache/tomcat/util/digester/Digester.addObjectCreate:(Ljava/lang/String;Ljava/lang/String;)V
     157: aload_1
     158: ldc           #66                 // String Server/GlobalNamingResources
     160: invokevirtual #62                 // Method org/apache/tomcat/util/digester/Digester.addSetProperties:(Ljava/lang/String;)V
     163: aload_1
     164: ldc           #66                 // String Server/GlobalNamingResources
     166: ldc           #69                 // String setGlobalNamingResources
     168: ldc           #67                 // String org.apache.catalina.deploy.NamingResourcesImpl
     170: invokevirtual #65                 // Method org/apache/tomcat/util/digester/Digester.addSetNext:(Ljava/lang/String;Ljava/lang/String;Ljava/lang/String;)V
     173: aload_1
     174: ldc           #70                 // String Server/Listener
     176: new           #71                 // class org/apache/catalina/startup/ListenerCreateRule
     179: dup
     180: aconst_null
     181: ldc           #49                 // String className
     183: invokespecial #72                 // Method org/apache/catalina/startup/ListenerCreateRule."<init>":(Ljava/lang/String;Ljava/lang/String;)V
     186: invokevirtual #73                 // Method org/apache/tomcat/util/digester/Digester.addRule:(Ljava/lang/String;Lorg/apache/tomcat/util/digester/Rule;)V
     189: aload_1
     190: ldc           #70                 // String Server/Listener
     192: invokevirtual #62                 // Method org/apache/tomcat/util/digester/Digester.addSetProperties:(Ljava/lang/String;)V
     195: aload_1
     196: ldc           #70                 // String Server/Listener
     198: ldc           #74                 // String addLifecycleListener
     200: ldc           #75                 // String org.apache.catalina.LifecycleListener
     202: invokevirtual #65                 // Method org/apache/tomcat/util/digester/Digester.addSetNext:(Ljava/lang/String;Ljava/lang/String;Ljava/lang/String;)V
     205: aload_1
     206: ldc           #76                 // String Server/Service
     208: ldc           #77                 // String org.apache.catalina.core.StandardService
     210: ldc           #49                 // String className
     212: invokevirtual #61                 // Method org/apache/tomcat/util/digester/Digester.addObjectCreate:(Ljava/lang/String;Ljava/lang/String;Ljava/lang/String;)V
     215: aload_1
     216: ldc           #76                 // String Server/Service
     218: invokevirtual #62                 // Method org/apache/tomcat/util/digester/Digester.addSetProperties:(Ljava/lang/String;)V
     221: aload_1
     222: ldc           #76                 // String Server/Service
     224: ldc           #78                 // String addService
     226: ldc           #79                 // String org.apache.catalina.Service
     228: invokevirtual #65                 // Method org/apache/tomcat/util/digester/Digester.addSetNext:(Ljava/lang/String;Ljava/lang/String;Ljava/lang/String;)V
     231: aload_1
     232: ldc           #80                 // String Server/Service/Listener
     234: aconst_null
     235: ldc           #49                 // String className
     237: invokevirtual #61                 // Method org/apache/tomcat/util/digester/Digester.addObjectCreate:(Ljava/lang/String;Ljava/lang/String;Ljava/lang/String;)V
     240: aload_1
     241: ldc           #80                 // String Server/Service/Listener
     243: invokevirtual #62                 // Method org/apache/tomcat/util/digester/Digester.addSetProperties:(Ljava/lang/String;)V
     246: aload_1
     247: ldc           #80                 // String Server/Service/Listener
     249: ldc           #74                 // String addLifecycleListener
     251: ldc           #75                 // String org.apache.catalina.LifecycleListener
     253: invokevirtual #65                 // Method org/apache/tomcat/util/digester/Digester.addSetNext:(Ljava/lang/String;Ljava/lang/String;Ljava/lang/String;)V
     256: aload_1
     257: ldc           #81                 // String Server/Service/Executor
     259: ldc           #82                 // String org.apache.catalina.core.StandardThreadExecutor
     261: ldc           #49                 // String className
     263: invokevirtual #61                 // Method org/apache/tomcat/util/digester/Digester.addObjectCreate:(Ljava/lang/String;Ljava/lang/String;Ljava/lang/String;)V
     266: aload_1
     267: ldc           #81                 // String Server/Service/Executor
     269: invokevirtual #62                 // Method org/apache/tomcat/util/digester/Digester.addSetProperties:(Ljava/lang/String;)V
     272: aload_1
     273: ldc           #81                 // String Server/Service/Executor
     275: ldc           #83                 // String addExecutor
     277: ldc           #84                 // String org.apache.catalina.Executor
     279: invokevirtual #65                 // Method org/apache/tomcat/util/digester/Digester.addSetNext:(Ljava/lang/String;Ljava/lang/String;Ljava/lang/String;)V
     282: aload_1
     283: ldc           #85                 // String Server/Service/Connector
     285: new           #86                 // class org/apache/catalina/startup/ConnectorCreateRule
     288: dup
     289: invokespecial #87                 // Method org/apache/catalina/startup/ConnectorCreateRule."<init>":()V
     292: invokevirtual #73                 // Method org/apache/tomcat/util/digester/Digester.addRule:(Ljava/lang/String;Lorg/apache/tomcat/util/digester/Rule;)V
     295: aload_1
     296: ldc           #85                 // String Server/Service/Connector
     298: iconst_3
     299: anewarray     #88                 // class java/lang/String
     302: dup
     303: iconst_0
     304: ldc           #89                 // String executor
     306: aastore
     307: dup
     308: iconst_1
     309: ldc           #90                 // String sslImplementationName
     311: aastore
     312: dup
     313: iconst_2
     314: ldc           #91                 // String protocol
     316: aastore
     317: invokevirtual #92                 // Method org/apache/tomcat/util/digester/Digester.addSetProperties:(Ljava/lang/String;[Ljava/lang/String;)V
     320: aload_1
     321: ldc           #85                 // String Server/Service/Connector
     323: ldc           #93                 // String addConnector
     325: ldc           #94                 // String org.apache.catalina.connector.Connector
     327: invokevirtual #65                 // Method org/apache/tomcat/util/digester/Digester.addSetNext:(Ljava/lang/String;Ljava/lang/String;Ljava/lang/String;)V
     330: aload_1
     331: ldc           #85                 // String Server/Service/Connector
     333: new           #95                 // class org/apache/catalina/startup/AddPortOffsetRule
     336: dup
     337: invokespecial #96                 // Method org/apache/catalina/startup/AddPortOffsetRule."<init>":()V
     340: invokevirtual #73                 // Method org/apache/tomcat/util/digester/Digester.addRule:(Ljava/lang/String;Lorg/apache/tomcat/util/digester/Rule;)V
     343: aload_1
     344: ldc           #97                 // String Server/Service/Connector/SSLHostConfig
     346: ldc           #98                 // String org.apache.tomcat.util.net.SSLHostConfig
     348: invokevirtual #68                 // Method org/apache/tomcat/util/digester/Digester.addObjectCreate:(Ljava/lang/String;Ljava/lang/String;)V
     351: aload_1
     352: ldc           #97                 // String Server/Service/Connector/SSLHostConfig
     354: invokevirtual #62                 // Method org/apache/tomcat/util/digester/Digester.addSetProperties:(Ljava/lang/String;)V
     357: aload_1
     358: ldc           #97                 // String Server/Service/Connector/SSLHostConfig
     360: ldc           #99                 // String addSslHostConfig
     362: ldc           #98                 // String org.apache.tomcat.util.net.SSLHostConfig
     364: invokevirtual #65                 // Method org/apache/tomcat/util/digester/Digester.addSetNext:(Ljava/lang/String;Ljava/lang/String;Ljava/lang/String;)V
     367: aload_1
     368: ldc           #100                // String Server/Service/Connector/SSLHostConfig/Certificate
     370: new           #101                // class org/apache/catalina/startup/CertificateCreateRule
     373: dup
     374: invokespecial #102                // Method org/apache/catalina/startup/CertificateCreateRule."<init>":()V
     377: invokevirtual #73                 // Method org/apache/tomcat/util/digester/Digester.addRule:(Ljava/lang/String;Lorg/apache/tomcat/util/digester/Rule;)V
     380: aload_1
     381: ldc           #100                // String Server/Service/Connector/SSLHostConfig/Certificate
     383: iconst_1
     384: anewarray     #88                 // class java/lang/String
     387: dup
     388: iconst_0
     389: ldc           #103                // String type
     391: aastore
     392: invokevirtual #92                 // Method org/apache/tomcat/util/digester/Digester.addSetProperties:(Ljava/lang/String;[Ljava/lang/String;)V
     395: aload_1
     396: ldc           #100                // String Server/Service/Connector/SSLHostConfig/Certificate
     398: ldc           #104                // String addCertificate
     400: ldc           #105                // String org.apache.tomcat.util.net.SSLHostConfigCertificate
     402: invokevirtual #65                 // Method org/apache/tomcat/util/digester/Digester.addSetNext:(Ljava/lang/String;Ljava/lang/String;Ljava/lang/String;)V
     405: aload_1
     406: ldc           #106                // String Server/Service/Connector/SSLHostConfig/OpenSSLConf
     408: ldc           #107                // String org.apache.tomcat.util.net.openssl.OpenSSLConf
     410: invokevirtual #68                 // Method org/apache/tomcat/util/digester/Digester.addObjectCreate:(Ljava/lang/String;Ljava/lang/String;)V
     413: aload_1
     414: ldc           #106                // String Server/Service/Connector/SSLHostConfig/OpenSSLConf
     416: invokevirtual #62                 // Method org/apache/tomcat/util/digester/Digester.addSetProperties:(Ljava/lang/String;)V
     419: aload_1
     420: ldc           #106                // String Server/Service/Connector/SSLHostConfig/OpenSSLConf
     422: ldc           #108                // String setOpenSslConf
     424: ldc           #107                // String org.apache.tomcat.util.net.openssl.OpenSSLConf
     426: invokevirtual #65                 // Method org/apache/tomcat/util/digester/Digester.addSetNext:(Ljava/lang/String;Ljava/lang/String;Ljava/lang/String;)V
     429: aload_1
     430: ldc           #109                // String Server/Service/Connector/SSLHostConfig/OpenSSLConf/OpenSSLConfCmd
     432: ldc           #110                // String org.apache.tomcat.util.net.openssl.OpenSSLConfCmd
     434: invokevirtual #68                 // Method org/apache/tomcat/util/digester/Digester.addObjectCreate:(Ljava/lang/String;Ljava/lang/String;)V
     437: aload_1
     438: ldc           #109                // String Server/Service/Connector/SSLHostConfig/OpenSSLConf/OpenSSLConfCmd
     440: invokevirtual #62                 // Method org/apache/tomcat/util/digester/Digester.addSetProperties:(Ljava/lang/String;)V
     443: aload_1
     444: ldc           #109                // String Server/Service/Connector/SSLHostConfig/OpenSSLConf/OpenSSLConfCmd
     446: ldc           #111                // String addCmd
     448: ldc           #110                // String org.apache.tomcat.util.net.openssl.OpenSSLConfCmd
     450: invokevirtual #65                 // Method org/apache/tomcat/util/digester/Digester.addSetNext:(Ljava/lang/String;Ljava/lang/String;Ljava/lang/String;)V
     453: aload_1
     454: ldc           #112                // String Server/Service/Connector/Listener
     456: aconst_null
     457: ldc           #49                 // String className
     459: invokevirtual #61                 // Method org/apache/tomcat/util/digester/Digester.addObjectCreate:(Ljava/lang/String;Ljava/lang/String;Ljava/lang/String;)V
     462: aload_1
     463: ldc           #112                // String Server/Service/Connector/Listener
     465: invokevirtual #62                 // Method org/apache/tomcat/util/digester/Digester.addSetProperties:(Ljava/lang/String;)V
     468: aload_1
     469: ldc           #112                // String Server/Service/Connector/Listener
     471: ldc           #74                 // String addLifecycleListener
     473: ldc           #75                 // String org.apache.catalina.LifecycleListener
     475: invokevirtual #65                 // Method org/apache/tomcat/util/digester/Digester.addSetNext:(Ljava/lang/String;Ljava/lang/String;Ljava/lang/String;)V
     478: aload_1
     479: ldc           #113                // String Server/Service/Connector/UpgradeProtocol
     481: aconst_null
     482: ldc           #49                 // String className
     484: invokevirtual #61                 // Method org/apache/tomcat/util/digester/Digester.addObjectCreate:(Ljava/lang/String;Ljava/lang/String;Ljava/lang/String;)V
     487: aload_1
     488: ldc           #113                // String Server/Service/Connector/UpgradeProtocol
     490: invokevirtual #62                 // Method org/apache/tomcat/util/digester/Digester.addSetProperties:(Ljava/lang/String;)V
     493: aload_1
     494: ldc           #113                // String Server/Service/Connector/UpgradeProtocol
     496: ldc           #114                // String addUpgradeProtocol
     498: ldc           #115                // String org.apache.coyote.UpgradeProtocol
     500: invokevirtual #65                 // Method org/apache/tomcat/util/digester/Digester.addSetNext:(Ljava/lang/String;Ljava/lang/String;Ljava/lang/String;)V
     503: aload_1
     504: new           #116                // class org/apache/catalina/startup/NamingRuleSet
     507: dup
     508: ldc           #117                // String Server/GlobalNamingResources/
     510: invokespecial #118                // Method org/apache/catalina/startup/NamingRuleSet."<init>":(Ljava/lang/String;)V
     513: invokevirtual #119                // Method org/apache/tomcat/util/digester/Digester.addRuleSet:(Lorg/apache/tomcat/util/digester/RuleSet;)V
     516: aload_1
     517: new           #120                // class org/apache/catalina/startup/EngineRuleSet
     520: dup
     521: ldc           #121                // String Server/Service/
     523: invokespecial #122                // Method org/apache/catalina/startup/EngineRuleSet."<init>":(Ljava/lang/String;)V
     526: invokevirtual #119                // Method org/apache/tomcat/util/digester/Digester.addRuleSet:(Lorg/apache/tomcat/util/digester/RuleSet;)V
     529: aload_1
     530: new           #123                // class org/apache/catalina/startup/HostRuleSet
     533: dup
     534: ldc           #124                // String Server/Service/Engine/
     536: invokespecial #125                // Method org/apache/catalina/startup/HostRuleSet."<init>":(Ljava/lang/String;)V
     539: invokevirtual #119                // Method org/apache/tomcat/util/digester/Digester.addRuleSet:(Lorg/apache/tomcat/util/digester/RuleSet;)V
     542: aload_1
     543: new           #126                // class org/apache/catalina/startup/ContextRuleSet
     546: dup
     547: ldc           #127                // String Server/Service/Engine/Host/
     549: invokespecial #128                // Method org/apache/catalina/startup/ContextRuleSet."<init>":(Ljava/lang/String;)V
     552: invokevirtual #119                // Method org/apache/tomcat/util/digester/Digester.addRuleSet:(Lorg/apache/tomcat/util/digester/RuleSet;)V
     555: aload_0
     556: aload_1
     557: ldc           #129                // String Server/Service/Engine/Host/Cluster/
     559: invokespecial #130                // Method addClusterRuleSet:(Lorg/apache/tomcat/util/digester/Digester;Ljava/lang/String;)V
     562: aload_1
     563: new           #116                // class org/apache/catalina/startup/NamingRuleSet
     566: dup
     567: ldc           #131                // String Server/Service/Engine/Host/Context/
     569: invokespecial #118                // Method org/apache/catalina/startup/NamingRuleSet."<init>":(Ljava/lang/String;)V
     572: invokevirtual #119                // Method org/apache/tomcat/util/digester/Digester.addRuleSet:(Lorg/apache/tomcat/util/digester/RuleSet;)V
     575: aload_1
     576: ldc           #132                // String Server/Service/Engine
     578: new           #133                // class org/apache/catalina/startup/Catalina$SetParentClassLoaderRule
     581: dup
     582: aload_0
     583: aload_0
     584: getfield      #8                  // Field parentClassLoader:Ljava/lang/ClassLoader;
     587: invokespecial #134                // Method org/apache/catalina/startup/Catalina$SetParentClassLoaderRule."<init>":(Lorg/apache/catalina/startup/Catalina;Ljava/lang/ClassLoader;)V
     590: invokevirtual #73                 // Method org/apache/tomcat/util/digester/Digester.addRule:(Ljava/lang/String;Lorg/apache/tomcat/util/digester/Rule;)V
     593: aload_0
     594: aload_1
     595: ldc           #135                // String Server/Service/Engine/Cluster/
     597: invokespecial #130                // Method addClusterRuleSet:(Lorg/apache/tomcat/util/digester/Digester;Ljava/lang/String;)V
     600: aload_1
     601: areturn

  private void addClusterRuleSet(org.apache.tomcat.util.digester.Digester, java.lang.String);
    Code:
       0: aconst_null
       1: astore_3
       2: aconst_null
       3: astore        4
       5: ldc           #136                // String org.apache.catalina.ha.ClusterRuleSet
       7: invokestatic  #137                // Method java/lang/Class.forName:(Ljava/lang/String;)Ljava/lang/Class;
      10: astore_3
      11: aload_3
      12: iconst_1
      13: anewarray     #138                // class java/lang/Class
      16: dup
      17: iconst_0
      18: ldc           #88                 // class java/lang/String
      20: aastore
      21: invokevirtual #139                // Method java/lang/Class.getConstructor:([Ljava/lang/Class;)Ljava/lang/reflect/Constructor;
      24: astore        4
      26: aload         4
      28: iconst_1
      29: anewarray     #51                 // class java/lang/Object
      32: dup
      33: iconst_0
      34: aload_2
      35: aastore
      36: invokevirtual #140                // Method java/lang/reflect/Constructor.newInstance:([Ljava/lang/Object;)Ljava/lang/Object;
      39: checkcast     #141                // class org/apache/tomcat/util/digester/RuleSet
      42: astore        5
      44: aload_1
      45: aload         5
      47: invokevirtual #119                // Method org/apache/tomcat/util/digester/Digester.addRuleSet:(Lorg/apache/tomcat/util/digester/RuleSet;)V
      50: goto          196
      53: astore        5
      55: getstatic     #1                  // Field log:Lorg/apache/juli/logging/Log;
      58: invokeinterface #143,  1          // InterfaceMethod org/apache/juli/logging/Log.isDebugEnabled:()Z
      63: ifeq          128
      66: getstatic     #1                  // Field log:Lorg/apache/juli/logging/Log;
      69: getstatic     #144                // Field sm:Lorg/apache/tomcat/util/res/StringManager;
      72: ldc           #145                // String catalina.noCluster
      74: iconst_1
      75: anewarray     #51                 // class java/lang/Object
      78: dup
      79: iconst_0
      80: new           #146                // class java/lang/StringBuilder
      83: dup
      84: invokespecial #147                // Method java/lang/StringBuilder."<init>":()V
      87: aload         5
      89: invokevirtual #148                // Method java/lang/Object.getClass:()Ljava/lang/Class;
      92: invokevirtual #149                // Method java/lang/Class.getName:()Ljava/lang/String;
      95: invokevirtual #150                // Method java/lang/StringBuilder.append:(Ljava/lang/String;)Ljava/lang/StringBuilder;
      98: ldc           #151                // String :
     100: invokevirtual #150                // Method java/lang/StringBuilder.append:(Ljava/lang/String;)Ljava/lang/StringBuilder;
     103: aload         5
     105: invokevirtual #152                // Method java/lang/Exception.getMessage:()Ljava/lang/String;
     108: invokevirtual #150                // Method java/lang/StringBuilder.append:(Ljava/lang/String;)Ljava/lang/StringBuilder;
     111: invokevirtual #153                // Method java/lang/StringBuilder.toString:()Ljava/lang/String;
     114: aastore
     115: invokevirtual #154                // Method org/apache/tomcat/util/res/StringManager.getString:(Ljava/lang/String;[Ljava/lang/Object;)Ljava/lang/String;
     118: aload         5
     120: invokeinterface #155,  3          // InterfaceMethod org/apache/juli/logging/Log.debug:(Ljava/lang/Object;Ljava/lang/Throwable;)V
     125: goto          196
     128: getstatic     #1                  // Field log:Lorg/apache/juli/logging/Log;
     131: invokeinterface #156,  1          // InterfaceMethod org/apache/juli/logging/Log.isInfoEnabled:()Z
     136: ifeq          196
     139: getstatic     #1                  // Field log:Lorg/apache/juli/logging/Log;
     142: getstatic     #144                // Field sm:Lorg/apache/tomcat/util/res/StringManager;
     145: ldc           #145                // String catalina.noCluster
     147: iconst_1
     148: anewarray     #51                 // class java/lang/Object
     151: dup
     152: iconst_0
     153: new           #146                // class java/lang/StringBuilder
     156: dup
     157: invokespecial #147                // Method java/lang/StringBuilder."<init>":()V
     160: aload         5
     162: invokevirtual #148                // Method java/lang/Object.getClass:()Ljava/lang/Class;
     165: invokevirtual #149                // Method java/lang/Class.getName:()Ljava/lang/String;
     168: invokevirtual #150                // Method java/lang/StringBuilder.append:(Ljava/lang/String;)Ljava/lang/StringBuilder;
     171: ldc           #151                // String :
     173: invokevirtual #150                // Method java/lang/StringBuilder.append:(Ljava/lang/String;)Ljava/lang/StringBuilder;
     176: aload         5
     178: invokevirtual #152                // Method java/lang/Exception.getMessage:()Ljava/lang/String;
     181: invokevirtual #150                // Method java/lang/StringBuilder.append:(Ljava/lang/String;)Ljava/lang/StringBuilder;
     184: invokevirtual #153                // Method java/lang/StringBuilder.toString:()Ljava/lang/String;
     187: aastore
     188: invokevirtual #154                // Method org/apache/tomcat/util/res/StringManager.getString:(Ljava/lang/String;[Ljava/lang/Object;)Ljava/lang/String;
     191: invokeinterface #157,  2          // InterfaceMethod org/apache/juli/logging/Log.info:(Ljava/lang/Object;)V
     196: return
    Exception table:
       from    to  target type
           5    50    53   Class java/lang/Exception

  protected org.apache.tomcat.util.digester.Digester createStopDigester();
    Code:
       0: new           #41                 // class org/apache/tomcat/util/digester/Digester
       3: dup
       4: invokespecial #42                 // Method org/apache/tomcat/util/digester/Digester."<init>":()V
       7: astore_1
       8: aload_1
       9: iconst_1
      10: invokevirtual #58                 // Method org/apache/tomcat/util/digester/Digester.setUseContextClassLoader:(Z)V
      13: aload_1
      14: ldc           #59                 // String Server
      16: ldc           #60                 // String org.apache.catalina.core.StandardServer
      18: ldc           #49                 // String className
      20: invokevirtual #61                 // Method org/apache/tomcat/util/digester/Digester.addObjectCreate:(Ljava/lang/String;Ljava/lang/String;Ljava/lang/String;)V
      23: aload_1
      24: ldc           #59                 // String Server
      26: invokevirtual #62                 // Method org/apache/tomcat/util/digester/Digester.addSetProperties:(Ljava/lang/String;)V
      29: aload_1
      30: ldc           #59                 // String Server
      32: ldc           #63                 // String setServer
      34: ldc           #64                 // String org.apache.catalina.Server
      36: invokevirtual #65                 // Method org/apache/tomcat/util/digester/Digester.addSetNext:(Ljava/lang/String;Ljava/lang/String;Ljava/lang/String;)V
      39: aload_1
      40: areturn

  protected void parseServerXml(boolean);
    Code:
       0: new           #158                // class org/apache/catalina/startup/CatalinaBaseConfigurationSource
       3: dup
       4: invokestatic  #159                // Method org/apache/catalina/startup/Bootstrap.getCatalinaBaseFile:()Ljava/io/File;
       7: aload_0
       8: invokevirtual #160                // Method getConfigFile:()Ljava/lang/String;
      11: invokespecial #161                // Method org/apache/catalina/startup/CatalinaBaseConfigurationSource."<init>":(Ljava/io/File;Ljava/lang/String;)V
      14: invokestatic  #162                // Method org/apache/tomcat/util/file/ConfigFileLoader.setSource:(Lorg/apache/tomcat/util/file/ConfigurationSource;)V
      17: aload_0
      18: invokevirtual #163                // Method configFile:()Ljava/io/File;
      21: astore_2
      22: aload_0
      23: getfield      #19                 // Field useGeneratedCode:Z
      26: ifeq          154
      29: invokestatic  #164                // Method org/apache/tomcat/util/digester/Digester.isGeneratedCodeLoaderSet:()Z
      32: ifne          154
      35: new           #146                // class java/lang/StringBuilder
      38: dup
      39: invokespecial #147                // Method java/lang/StringBuilder."<init>":()V
      42: aload_0
      43: getfield      #18                 // Field generatedCodePackage:Ljava/lang/String;
      46: invokevirtual #150                // Method java/lang/StringBuilder.append:(Ljava/lang/String;)Ljava/lang/StringBuilder;
      49: ldc           #165                // String .DigesterGeneratedCodeLoader
      51: invokevirtual #150                // Method java/lang/StringBuilder.append:(Ljava/lang/String;)Ljava/lang/StringBuilder;
      54: invokevirtual #153                // Method java/lang/StringBuilder.toString:()Ljava/lang/String;
      57: astore_3
      58: ldc           #4                  // class org/apache/catalina/startup/Catalina
      60: invokevirtual #7                  // Method java/lang/Class.getClassLoader:()Ljava/lang/ClassLoader;
      63: aload_3
      64: invokevirtual #166                // Method java/lang/ClassLoader.loadClass:(Ljava/lang/String;)Ljava/lang/Class;
      67: invokevirtual #167                // Method java/lang/Class.newInstance:()Ljava/lang/Object;
      70: checkcast     #168                // class org/apache/tomcat/util/digester/Digester$GeneratedCodeLoader
      73: astore        4
      75: aload         4
      77: invokestatic  #169                // Method org/apache/tomcat/util/digester/Digester.setGeneratedCodeLoader:(Lorg/apache/tomcat/util/digester/Digester$GeneratedCodeLoader;)V
      80: goto          154
      83: astore        4
      85: getstatic     #1                  // Field log:Lorg/apache/juli/logging/Log;
      88: invokeinterface #143,  1          // InterfaceMethod org/apache/juli/logging/Log.isDebugEnabled:()Z
      93: ifeq          125
      96: getstatic     #1                  // Field log:Lorg/apache/juli/logging/Log;
      99: getstatic     #144                // Field sm:Lorg/apache/tomcat/util/res/StringManager;
     102: ldc           #170                // String catalina.noLoader
     104: iconst_1
     105: anewarray     #51                 // class java/lang/Object
     108: dup
     109: iconst_0
     110: aload_3
     111: aastore
     112: invokevirtual #154                // Method org/apache/tomcat/util/res/StringManager.getString:(Ljava/lang/String;[Ljava/lang/Object;)Ljava/lang/String;
     115: aload         4
     117: invokeinterface #171,  3          // InterfaceMethod org/apache/juli/logging/Log.info:(Ljava/lang/Object;Ljava/lang/Throwable;)V
     122: goto          149
     125: getstatic     #1                  // Field log:Lorg/apache/juli/logging/Log;
     128: getstatic     #144                // Field sm:Lorg/apache/tomcat/util/res/StringManager;
     131: ldc           #170                // String catalina.noLoader
     133: iconst_1
     134: anewarray     #51                 // class java/lang/Object
     137: dup
     138: iconst_0
     139: aload_3
     140: aastore
     141: invokevirtual #154                // Method org/apache/tomcat/util/res/StringManager.getString:(Ljava/lang/String;[Ljava/lang/Object;)Ljava/lang/String;
     144: invokeinterface #157,  2          // InterfaceMethod org/apache/juli/logging/Log.info:(Ljava/lang/Object;)V
     149: aload_0
     150: iconst_0
     151: putfield      #19                 // Field useGeneratedCode:Z
     154: aconst_null
     155: astore_3
     156: aconst_null
     157: astore        4
     159: aload_0
     160: getfield      #14                 // Field generateCode:Z
     163: ifne          173
     166: aload_0
     167: getfield      #19                 // Field useGeneratedCode:Z
     170: ifeq          226
     173: iload_1
     174: ifeq          202
     177: new           #146                // class java/lang/StringBuilder
     180: dup
     181: invokespecial #147                // Method java/lang/StringBuilder."<init>":()V
     184: aload_0
     185: getfield      #18                 // Field generatedCodePackage:Ljava/lang/String;
     188: invokevirtual #150                // Method java/lang/StringBuilder.append:(Ljava/lang/String;)Ljava/lang/StringBuilder;
     191: ldc           #172                // String .ServerXml
     193: invokevirtual #150                // Method java/lang/StringBuilder.append:(Ljava/lang/String;)Ljava/lang/StringBuilder;
     196: invokevirtual #153                // Method java/lang/StringBuilder.toString:()Ljava/lang/String;
     199: goto          224
     202: new           #146                // class java/lang/StringBuilder
     205: dup
     206: invokespecial #147                // Method java/lang/StringBuilder."<init>":()V
     209: aload_0
     210: getfield      #18                 // Field generatedCodePackage:Ljava/lang/String;
     213: invokevirtual #150                // Method java/lang/StringBuilder.append:(Ljava/lang/String;)Ljava/lang/StringBuilder;
     216: ldc           #173                // String .ServerXmlStop
     218: invokevirtual #150                // Method java/lang/StringBuilder.append:(Ljava/lang/String;)Ljava/lang/StringBuilder;
     221: invokevirtual #153                // Method java/lang/StringBuilder.toString:()Ljava/lang/String;
     224: astore        4
     226: aload_0
     227: getfield      #14                 // Field generateCode:Z
     230: ifeq          367
     233: aload_0
     234: getfield      #16                 // Field generatedCodeLocationParameter:Ljava/lang/String;
     237: ifnull        286
     240: aload_0
     241: new           #36                 // class java/io/File
     244: dup
     245: aload_0
     246: getfield      #16                 // Field generatedCodeLocationParameter:Ljava/lang/String;
     249: invokespecial #37                 // Method java/io/File."<init>":(Ljava/lang/String;)V
     252: putfield      #15                 // Field generatedCodeLocation:Ljava/io/File;
     255: aload_0
     256: getfield      #15                 // Field generatedCodeLocation:Ljava/io/File;
     259: invokevirtual #38                 // Method java/io/File.isAbsolute:()Z
     262: ifne          302
     265: aload_0
     266: new           #36                 // class java/io/File
     269: dup
     270: invokestatic  #174                // Method org/apache/catalina/startup/Bootstrap.getCatalinaHomeFile:()Ljava/io/File;
     273: aload_0
     274: getfield      #16                 // Field generatedCodeLocationParameter:Ljava/lang/String;
     277: invokespecial #175                // Method java/io/File."<init>":(Ljava/io/File;Ljava/lang/String;)V
     280: putfield      #15                 // Field generatedCodeLocation:Ljava/io/File;
     283: goto          302
     286: aload_0
     287: new           #36                 // class java/io/File
     290: dup
     291: invokestatic  #174                // Method org/apache/catalina/startup/Bootstrap.getCatalinaHomeFile:()Ljava/io/File;
     294: ldc           #176                // String work
     296: invokespecial #175                // Method java/io/File."<init>":(Ljava/io/File;Ljava/lang/String;)V
     299: putfield      #15                 // Field generatedCodeLocation:Ljava/io/File;
     302: new           #36                 // class java/io/File
     305: dup
     306: aload_0
     307: getfield      #15                 // Field generatedCodeLocation:Ljava/io/File;
     310: aload_0
     311: getfield      #18                 // Field generatedCodePackage:Ljava/lang/String;
     314: invokespecial #175                // Method java/io/File."<init>":(Ljava/io/File;Ljava/lang/String;)V
     317: astore_3
     318: aload_3
     319: invokevirtual #177                // Method java/io/File.isDirectory:()Z
     322: ifne          367
     325: aload_3
     326: invokevirtual #178                // Method java/io/File.mkdirs:()Z
     329: ifne          367
     332: getstatic     #1                  // Field log:Lorg/apache/juli/logging/Log;
     335: getstatic     #144                // Field sm:Lorg/apache/tomcat/util/res/StringManager;
     338: ldc           #179                // String catalina.generatedCodeLocationError
     340: iconst_1
     341: anewarray     #51                 // class java/lang/Object
     344: dup
     345: iconst_0
     346: aload_0
     347: getfield      #15                 // Field generatedCodeLocation:Ljava/io/File;
     350: invokevirtual #180                // Method java/io/File.getAbsolutePath:()Ljava/lang/String;
     353: aastore
     354: invokevirtual #154                // Method org/apache/tomcat/util/res/StringManager.getString:(Ljava/lang/String;[Ljava/lang/Object;)Ljava/lang/String;
     357: invokeinterface #181,  2          // InterfaceMethod org/apache/juli/logging/Log.warn:(Ljava/lang/Object;)V
     362: aload_0
     363: iconst_0
     364: putfield      #14                 // Field generateCode:Z
     367: aconst_null
     368: astore        5
     370: aload_0
     371: getfield      #19                 // Field useGeneratedCode:Z
     374: ifeq          387
     377: aload         4
     379: invokestatic  #182                // Method org/apache/tomcat/util/digester/Digester.loadGeneratedClass:(Ljava/lang/String;)Ljava/lang/Object;
     382: checkcast     #183                // class org/apache/catalina/startup/Catalina$ServerXml
     385: astore        5
     387: aload         5
     389: ifnull        403
     392: aload         5
     394: aload_0
     395: invokeinterface #184,  2          // InterfaceMethod org/apache/catalina/startup/Catalina$ServerXml.load:(Lorg/apache/catalina/startup/Catalina;)V
     400: goto          805
     403: invokestatic  #185                // Method org/apache/tomcat/util/file/ConfigFileLoader.getSource:()Lorg/apache/tomcat/util/file/ConfigurationSource;
     406: invokeinterface #186,  1          // InterfaceMethod org/apache/tomcat/util/file/ConfigurationSource.getServerXml:()Lorg/apache/tomcat/util/file/ConfigurationSource$Resource;
     411: astore        6
     413: aconst_null
     414: astore        7
     416: iload_1
     417: ifeq          427
     420: aload_0
     421: invokevirtual #187                // Method createStartDigester:()Lorg/apache/tomcat/util/digester/Digester;
     424: goto          431
     427: aload_0
     428: invokevirtual #188                // Method createStopDigester:()Lorg/apache/tomcat/util/digester/Digester;
     431: astore        8
     433: aload         6
     435: invokevirtual #189                // Method org/apache/tomcat/util/file/ConfigurationSource$Resource.getInputStream:()Ljava/io/InputStream;
     438: astore        9
     440: new           #190                // class org/xml/sax/InputSource
     443: dup
     444: aload         6
     446: invokevirtual #191                // Method org/apache/tomcat/util/file/ConfigurationSource$Resource.getURI:()Ljava/net/URI;
     449: invokevirtual #192                // Method java/net/URI.toURL:()Ljava/net/URL;
     452: invokevirtual #193                // Method java/net/URL.toString:()Ljava/lang/String;
     455: invokespecial #194                // Method org/xml/sax/InputSource."<init>":(Ljava/lang/String;)V
     458: astore        10
     460: aload         10
     462: aload         9
     464: invokevirtual #195                // Method org/xml/sax/InputSource.setByteStream:(Ljava/io/InputStream;)V
     467: aload         8
     469: aload_0
     470: invokevirtual #196                // Method org/apache/tomcat/util/digester/Digester.push:(Ljava/lang/Object;)V
     473: aload_0
     474: getfield      #14                 // Field generateCode:Z
     477: ifeq          492
     480: aload         8
     482: invokevirtual #197                // Method org/apache/tomcat/util/digester/Digester.startGeneratingCode:()V
     485: aload_0
     486: aload         8
     488: iload_1
     489: invokevirtual #198                // Method generateClassHeader:(Lorg/apache/tomcat/util/digester/Digester;Z)V
     492: aload         8
     494: aload         10
     496: invokevirtual #199                // Method org/apache/tomcat/util/digester/Digester.parse:(Lorg/xml/sax/InputSource;)Ljava/lang/Object;
     499: pop
     500: aload_0
     501: getfield      #14                 // Field generateCode:Z
     504: ifeq          654
     507: aload_0
     508: aload         8
     510: invokevirtual #200                // Method generateClassFooter:(Lorg/apache/tomcat/util/digester/Digester;)V
     513: new           #201                // class java/io/FileWriter
     516: dup
     517: new           #36                 // class java/io/File
     520: dup
     521: aload_3
     522: iload_1
     523: ifeq          531
     526: ldc           #202                // String ServerXml.java
     528: goto          533
     531: ldc           #203                // String ServerXmlStop.java
     533: invokespecial #175                // Method java/io/File."<init>":(Ljava/io/File;Ljava/lang/String;)V
     536: invokespecial #204                // Method java/io/FileWriter."<init>":(Ljava/io/File;)V
     539: astore        11
     541: aconst_null
     542: astore        12
     544: aload         11
     546: aload         8
     548: invokevirtual #205                // Method org/apache/tomcat/util/digester/Digester.getGeneratedCode:()Ljava/lang/StringBuilder;
     551: invokevirtual #153                // Method java/lang/StringBuilder.toString:()Ljava/lang/String;
     554: invokevirtual #206                // Method java/io/FileWriter.write:(Ljava/lang/String;)V
     557: aload         11
     559: ifnull        644
     562: aload         12
     564: ifnull        587
     567: aload         11
     569: invokevirtual #207                // Method java/io/FileWriter.close:()V
     572: goto          644
     575: astore        13
     577: aload         12
     579: aload         13
     581: invokevirtual #209                // Method java/lang/Throwable.addSuppressed:(Ljava/lang/Throwable;)V
     584: goto          644
     587: aload         11
     589: invokevirtual #207                // Method java/io/FileWriter.close:()V
     592: goto          644
     595: astore        13
     597: aload         13
     599: astore        12
     601: aload         13
     603: athrow
     604: astore        14
     606: aload         11
     608: ifnull        641
     611: aload         12
     613: ifnull        636
     616: aload         11
     618: invokevirtual #207                // Method java/io/FileWriter.close:()V
     621: goto          641
     624: astore        15
     626: aload         12
     628: aload         15
     630: invokevirtual #209                // Method java/lang/Throwable.addSuppressed:(Ljava/lang/Throwable;)V
     633: goto          641
     636: aload         11
     638: invokevirtual #207                // Method java/io/FileWriter.close:()V
     641: aload         14
     643: athrow
     644: aload         8
     646: invokevirtual #210                // Method org/apache/tomcat/util/digester/Digester.endGeneratingCode:()V
     649: aload         4
     651: invokestatic  #211                // Method org/apache/tomcat/util/digester/Digester.addGeneratedClass:(Ljava/lang/String;)V
     654: aload         6
     656: ifnull        741
     659: aload         7
     661: ifnull        684
     664: aload         6
     666: invokevirtual #212                // Method org/apache/tomcat/util/file/ConfigurationSource$Resource.close:()V
     669: goto          741
     672: astore        8
     674: aload         7
     676: aload         8
     678: invokevirtual #209                // Method java/lang/Throwable.addSuppressed:(Ljava/lang/Throwable;)V
     681: goto          741
     684: aload         6
     686: invokevirtual #212                // Method org/apache/tomcat/util/file/ConfigurationSource$Resource.close:()V
     689: goto          741
     692: astore        8
     694: aload         8
     696: astore        7
     698: aload         8
     700: athrow
     701: astore        16
     703: aload         6
     705: ifnull        738
     708: aload         7
     710: ifnull        733
     713: aload         6
     715: invokevirtual #212                // Method org/apache/tomcat/util/file/ConfigurationSource$Resource.close:()V
     718: goto          738
     721: astore        17
     723: aload         7
     725: aload         17
     727: invokevirtual #209                // Method java/lang/Throwable.addSuppressed:(Ljava/lang/Throwable;)V
     730: goto          738
     733: aload         6
     735: invokevirtual #212                // Method org/apache/tomcat/util/file/ConfigurationSource$Resource.close:()V
     738: aload         16
     740: athrow
     741: goto          805
     744: astore        6
     746: getstatic     #1                  // Field log:Lorg/apache/juli/logging/Log;
     749: getstatic     #144                // Field sm:Lorg/apache/tomcat/util/res/StringManager;
     752: ldc           #213                // String catalina.configFail
     754: iconst_1
     755: anewarray     #51                 // class java/lang/Object
     758: dup
     759: iconst_0
     760: aload_2
     761: invokevirtual #180                // Method java/io/File.getAbsolutePath:()Ljava/lang/String;
     764: aastore
     765: invokevirtual #154                // Method org/apache/tomcat/util/res/StringManager.getString:(Ljava/lang/String;[Ljava/lang/Object;)Ljava/lang/String;
     768: aload         6
     770: invokeinterface #214,  3          // InterfaceMethod org/apache/juli/logging/Log.warn:(Ljava/lang/Object;Ljava/lang/Throwable;)V
     775: aload_2
     776: invokevirtual #215                // Method java/io/File.exists:()Z
     779: ifeq          805
     782: aload_2
     783: invokevirtual #216                // Method java/io/File.canRead:()Z
     786: ifne          805
     789: getstatic     #1                  // Field log:Lorg/apache/juli/logging/Log;
     792: getstatic     #144                // Field sm:Lorg/apache/tomcat/util/res/StringManager;
     795: ldc           #217                // String catalina.incorrectPermissions
     797: invokevirtual #218                // Method org/apache/tomcat/util/res/StringManager.getString:(Ljava/lang/String;)Ljava/lang/String;
     800: invokeinterface #181,  2          // InterfaceMethod org/apache/juli/logging/Log.warn:(Ljava/lang/Object;)V
     805: return
    Exception table:
       from    to  target type
          58    80    83   Class java/lang/Exception
         567   572   575   Class java/lang/Throwable
         544   557   595   Class java/lang/Throwable
         544   557   604   any
         616   621   624   Class java/lang/Throwable
         595   606   604   any
         664   669   672   Class java/lang/Throwable
         416   654   692   Class java/lang/Throwable
         416   654   701   any
         713   718   721   Class java/lang/Throwable
         692   703   701   any
         403   741   744   Class java/lang/Exception

  public void stopServer();
    Code:
       0: aload_0
       1: aconst_null
       2: invokevirtual #219                // Method stopServer:([Ljava/lang/String;)V
       5: return

  public void stopServer(java.lang.String[]);
    Code:
       0: aload_1
       1: ifnull        10
       4: aload_0
       5: aload_1
       6: invokevirtual #220                // Method arguments:([Ljava/lang/String;)Z
       9: pop
      10: aload_0
      11: invokevirtual #221                // Method getServer:()Lorg/apache/catalina/Server;
      14: astore_2
      15: aload_2
      16: ifnonnull     54
      19: aload_0
      20: iconst_0
      21: invokevirtual #222                // Method parseServerXml:(Z)V
      24: aload_0
      25: invokevirtual #221                // Method getServer:()Lorg/apache/catalina/Server;
      28: ifnonnull     88
      31: getstatic     #1                  // Field log:Lorg/apache/juli/logging/Log;
      34: getstatic     #144                // Field sm:Lorg/apache/tomcat/util/res/StringManager;
      37: ldc           #223                // String catalina.stopError
      39: invokevirtual #218                // Method org/apache/tomcat/util/res/StringManager.getString:(Ljava/lang/String;)Ljava/lang/String;
      42: invokeinterface #224,  2          // InterfaceMethod org/apache/juli/logging/Log.error:(Ljava/lang/Object;)V
      47: iconst_1
      48: invokestatic  #225                // Method java/lang/System.exit:(I)V
      51: goto          88
      54: aload_2
      55: invokeinterface #226,  1          // InterfaceMethod org/apache/catalina/Server.stop:()V
      60: aload_2
      61: invokeinterface #227,  1          // InterfaceMethod org/apache/catalina/Server.destroy:()V
      66: goto          87
      69: astore_3
      70: getstatic     #1                  // Field log:Lorg/apache/juli/logging/Log;
      73: getstatic     #144                // Field sm:Lorg/apache/tomcat/util/res/StringManager;
      76: ldc           #223                // String catalina.stopError
      78: invokevirtual #218                // Method org/apache/tomcat/util/res/StringManager.getString:(Ljava/lang/String;)Ljava/lang/String;
      81: aload_3
      82: invokeinterface #229,  3          // InterfaceMethod org/apache/juli/logging/Log.error:(Ljava/lang/Object;Ljava/lang/Throwable;)V
      87: return
      88: aload_0
      89: invokevirtual #221                // Method getServer:()Lorg/apache/catalina/Server;
      92: astore_2
      93: aload_2
      94: invokeinterface #230,  1          // InterfaceMethod org/apache/catalina/Server.getPortWithOffset:()I
      99: ifle          464
     102: new           #231                // class java/net/Socket
     105: dup
     106: aload_2
     107: invokeinterface #232,  1          // InterfaceMethod org/apache/catalina/Server.getAddress:()Ljava/lang/String;
     112: aload_2
     113: invokeinterface #230,  1          // InterfaceMethod org/apache/catalina/Server.getPortWithOffset:()I
     118: invokespecial #233                // Method java/net/Socket."<init>":(Ljava/lang/String;I)V
     121: astore_3
     122: aconst_null
     123: astore        4
     125: aload_3
     126: invokevirtual #234                // Method java/net/Socket.getOutputStream:()Ljava/io/OutputStream;
     129: astore        5
     131: aconst_null
     132: astore        6
     134: aload_2
     135: invokeinterface #235,  1          // InterfaceMethod org/apache/catalina/Server.getShutdown:()Ljava/lang/String;
     140: astore        7
     142: iconst_0
     143: istore        8
     145: iload         8
     147: aload         7
     149: invokevirtual #236                // Method java/lang/String.length:()I
     152: if_icmpge     173
     155: aload         5
     157: aload         7
     159: iload         8
     161: invokevirtual #237                // Method java/lang/String.charAt:(I)C
     164: invokevirtual #238                // Method java/io/OutputStream.write:(I)V
     167: iinc          8, 1
     170: goto          145
     173: aload         5
     175: invokevirtual #239                // Method java/io/OutputStream.flush:()V
     178: aload         5
     180: ifnull        265
     183: aload         6
     185: ifnull        208
     188: aload         5
     190: invokevirtual #240                // Method java/io/OutputStream.close:()V
     193: goto          265
     196: astore        7
     198: aload         6
     200: aload         7
     202: invokevirtual #209                // Method java/lang/Throwable.addSuppressed:(Ljava/lang/Throwable;)V
     205: goto          265
     208: aload         5
     210: invokevirtual #240                // Method java/io/OutputStream.close:()V
     213: goto          265
     216: astore        7
     218: aload         7
     220: astore        6
     222: aload         7
     224: athrow
     225: astore        9
     227: aload         5
     229: ifnull        262
     232: aload         6
     234: ifnull        257
     237: aload         5
     239: invokevirtual #240                // Method java/io/OutputStream.close:()V
     242: goto          262
     245: astore        10
     247: aload         6
     249: aload         10
     251: invokevirtual #209                // Method java/lang/Throwable.addSuppressed:(Ljava/lang/Throwable;)V
     254: goto          262
     257: aload         5
     259: invokevirtual #240                // Method java/io/OutputStream.close:()V
     262: aload         9
     264: athrow
     265: aload_3
     266: ifnull        346
     269: aload         4
     271: ifnull        293
     274: aload_3
     275: invokevirtual #241                // Method java/net/Socket.close:()V
     278: goto          346
     281: astore        5
     283: aload         4
     285: aload         5
     287: invokevirtual #209                // Method java/lang/Throwable.addSuppressed:(Ljava/lang/Throwable;)V
     290: goto          346
     293: aload_3
     294: invokevirtual #241                // Method java/net/Socket.close:()V
     297: goto          346
     300: astore        5
     302: aload         5
     304: astore        4
     306: aload         5
     308: athrow
     309: astore        11
     311: aload_3
     312: ifnull        343
     315: aload         4
     317: ifnull        339
     320: aload_3
     321: invokevirtual #241                // Method java/net/Socket.close:()V
     324: goto          343
     327: astore        12
     329: aload         4
     331: aload         12
     333: invokevirtual #209                // Method java/lang/Throwable.addSuppressed:(Ljava/lang/Throwable;)V
     336: goto          343
     339: aload_3
     340: invokevirtual #241                // Method java/net/Socket.close:()V
     343: aload         11
     345: athrow
     346: goto          484
     349: astore_3
     350: getstatic     #1                  // Field log:Lorg/apache/juli/logging/Log;
     353: getstatic     #144                // Field sm:Lorg/apache/tomcat/util/res/StringManager;
     356: ldc           #243                // String catalina.stopServer.connectException
     358: iconst_4
     359: anewarray     #51                 // class java/lang/Object
     362: dup
     363: iconst_0
     364: aload_2
     365: invokeinterface #232,  1          // InterfaceMethod org/apache/catalina/Server.getAddress:()Ljava/lang/String;
     370: aastore
     371: dup
     372: iconst_1
     373: aload_2
     374: invokeinterface #230,  1          // InterfaceMethod org/apache/catalina/Server.getPortWithOffset:()I
     379: invokestatic  #244                // Method java/lang/String.valueOf:(I)Ljava/lang/String;
     382: aastore
     383: dup
     384: iconst_2
     385: aload_2
     386: invokeinterface #245,  1          // InterfaceMethod org/apache/catalina/Server.getPort:()I
     391: invokestatic  #244                // Method java/lang/String.valueOf:(I)Ljava/lang/String;
     394: aastore
     395: dup
     396: iconst_3
     397: aload_2
     398: invokeinterface #246,  1          // InterfaceMethod org/apache/catalina/Server.getPortOffset:()I
     403: invokestatic  #244                // Method java/lang/String.valueOf:(I)Ljava/lang/String;
     406: aastore
     407: invokevirtual #154                // Method org/apache/tomcat/util/res/StringManager.getString:(Ljava/lang/String;[Ljava/lang/Object;)Ljava/lang/String;
     410: invokeinterface #224,  2          // InterfaceMethod org/apache/juli/logging/Log.error:(Ljava/lang/Object;)V
     415: getstatic     #1                  // Field log:Lorg/apache/juli/logging/Log;
     418: getstatic     #144                // Field sm:Lorg/apache/tomcat/util/res/StringManager;
     421: ldc           #223                // String catalina.stopError
     423: invokevirtual #218                // Method org/apache/tomcat/util/res/StringManager.getString:(Ljava/lang/String;)Ljava/lang/String;
     426: aload_3
     427: invokeinterface #229,  3          // InterfaceMethod org/apache/juli/logging/Log.error:(Ljava/lang/Object;Ljava/lang/Throwable;)V
     432: iconst_1
     433: invokestatic  #225                // Method java/lang/System.exit:(I)V
     436: goto          484
     439: astore_3
     440: getstatic     #1                  // Field log:Lorg/apache/juli/logging/Log;
     443: getstatic     #144                // Field sm:Lorg/apache/tomcat/util/res/StringManager;
     446: ldc           #223                // String catalina.stopError
     448: invokevirtual #218                // Method org/apache/tomcat/util/res/StringManager.getString:(Ljava/lang/String;)Ljava/lang/String;
     451: aload_3
     452: invokeinterface #229,  3          // InterfaceMethod org/apache/juli/logging/Log.error:(Ljava/lang/Object;Ljava/lang/Throwable;)V
     457: iconst_1
     458: invokestatic  #225                // Method java/lang/System.exit:(I)V
     461: goto          484
     464: getstatic     #1                  // Field log:Lorg/apache/juli/logging/Log;
     467: getstatic     #144                // Field sm:Lorg/apache/tomcat/util/res/StringManager;
     470: ldc           #248                // String catalina.stopServer
     472: invokevirtual #218                // Method org/apache/tomcat/util/res/StringManager.getString:(Ljava/lang/String;)Ljava/lang/String;
     475: invokeinterface #224,  2          // InterfaceMethod org/apache/juli/logging/Log.error:(Ljava/lang/Object;)V
     480: iconst_1
     481: invokestatic  #225                // Method java/lang/System.exit:(I)V
     484: return
    Exception table:
       from    to  target type
          54    66    69   Class org/apache/catalina/LifecycleException
         188   193   196   Class java/lang/Throwable
         134   178   216   Class java/lang/Throwable
         134   178   225   any
         237   242   245   Class java/lang/Throwable
         216   227   225   any
         274   278   281   Class java/lang/Throwable
         125   265   300   Class java/lang/Throwable
         125   265   309   any
         320   324   327   Class java/lang/Throwable
         300   311   309   any
         102   346   349   Class java/net/ConnectException
         102   346   439   Class java/io/IOException

  public void load();
    Code:
       0: aload_0
       1: getfield      #13                 // Field loaded:Z
       4: ifeq          8
       7: return
       8: aload_0
       9: iconst_1
      10: putfield      #13                 // Field loaded:Z
      13: invokestatic  #249                // Method java/lang/System.nanoTime:()J
      16: lstore_1
      17: aload_0
      18: invokevirtual #250                // Method initDirs:()V
      21: aload_0
      22: invokevirtual #251                // Method initNaming:()V
      25: aload_0
      26: iconst_1
      27: invokevirtual #222                // Method parseServerXml:(Z)V
      30: aload_0
      31: invokevirtual #221                // Method getServer:()Lorg/apache/catalina/Server;
      34: astore_3
      35: aload_3
      36: ifnonnull     40
      39: return
      40: aload_0
      41: invokevirtual #221                // Method getServer:()Lorg/apache/catalina/Server;
      44: aload_0
      45: invokeinterface #252,  2          // InterfaceMethod org/apache/catalina/Server.setCatalina:(Lorg/apache/catalina/startup/Catalina;)V
      50: aload_0
      51: invokevirtual #221                // Method getServer:()Lorg/apache/catalina/Server;
      54: invokestatic  #174                // Method org/apache/catalina/startup/Bootstrap.getCatalinaHomeFile:()Ljava/io/File;
      57: invokeinterface #253,  2          // InterfaceMethod org/apache/catalina/Server.setCatalinaHome:(Ljava/io/File;)V
      62: aload_0
      63: invokevirtual #221                // Method getServer:()Lorg/apache/catalina/Server;
      66: invokestatic  #159                // Method org/apache/catalina/startup/Bootstrap.getCatalinaBaseFile:()Ljava/io/File;
      69: invokeinterface #254,  2          // InterfaceMethod org/apache/catalina/Server.setCatalinaBase:(Ljava/io/File;)V
      74: aload_0
      75: invokevirtual #255                // Method initStreams:()V
      78: aload_0
      79: invokevirtual #221                // Method getServer:()Lorg/apache/catalina/Server;
      82: invokeinterface #256,  1          // InterfaceMethod org/apache/catalina/Server.init:()V
      87: goto          130
      90: astore        4
      92: ldc_w         #257                // String org.apache.catalina.startup.EXIT_ON_INIT_FAILURE
      95: invokestatic  #258                // Method java/lang/Boolean.getBoolean:(Ljava/lang/String;)Z
      98: ifeq          111
     101: new           #259                // class java/lang/Error
     104: dup
     105: aload         4
     107: invokespecial #260                // Method java/lang/Error."<init>":(Ljava/lang/Throwable;)V
     110: athrow
     111: getstatic     #1                  // Field log:Lorg/apache/juli/logging/Log;
     114: getstatic     #144                // Field sm:Lorg/apache/tomcat/util/res/StringManager;
     117: ldc_w         #261                // String catalina.initError
     120: invokevirtual #218                // Method org/apache/tomcat/util/res/StringManager.getString:(Ljava/lang/String;)Ljava/lang/String;
     123: aload         4
     125: invokeinterface #229,  3          // InterfaceMethod org/apache/juli/logging/Log.error:(Ljava/lang/Object;Ljava/lang/Throwable;)V
     130: getstatic     #1                  // Field log:Lorg/apache/juli/logging/Log;
     133: invokeinterface #156,  1          // InterfaceMethod org/apache/juli/logging/Log.isInfoEnabled:()Z
     138: ifeq          179
     141: getstatic     #1                  // Field log:Lorg/apache/juli/logging/Log;
     144: getstatic     #144                // Field sm:Lorg/apache/tomcat/util/res/StringManager;
     147: ldc_w         #262                // String catalina.init
     150: iconst_1
     151: anewarray     #51                 // class java/lang/Object
     154: dup
     155: iconst_0
     156: getstatic     #263                // Field java/util/concurrent/TimeUnit.NANOSECONDS:Ljava/util/concurrent/TimeUnit;
     159: invokestatic  #249                // Method java/lang/System.nanoTime:()J
     162: lload_1
     163: lsub
     164: invokevirtual #264                // Method java/util/concurrent/TimeUnit.toMillis:(J)J
     167: invokestatic  #265                // Method java/lang/Long.toString:(J)Ljava/lang/String;
     170: aastore
     171: invokevirtual #154                // Method org/apache/tomcat/util/res/StringManager.getString:(Ljava/lang/String;[Ljava/lang/Object;)Ljava/lang/String;
     174: invokeinterface #157,  2          // InterfaceMethod org/apache/juli/logging/Log.info:(Ljava/lang/Object;)V
     179: return
    Exception table:
       from    to  target type
          78    87    90   Class org/apache/catalina/LifecycleException

  public void load(java.lang.String[]);
    Code:
       0: aload_0
       1: aload_1
       2: invokevirtual #220                // Method arguments:([Ljava/lang/String;)Z
       5: ifeq          12
       8: aload_0
       9: invokevirtual #266                // Method load:()V
      12: goto          23
      15: astore_2
      16: aload_2
      17: getstatic     #267                // Field java/lang/System.out:Ljava/io/PrintStream;
      20: invokevirtual #268                // Method java/lang/Exception.printStackTrace:(Ljava/io/PrintStream;)V
      23: return
    Exception table:
       from    to  target type
           0    12    15   Class java/lang/Exception

  public void start();
    Code:
       0: aload_0
       1: invokevirtual #221                // Method getServer:()Lorg/apache/catalina/Server;
       4: ifnonnull     11
       7: aload_0
       8: invokevirtual #266                // Method load:()V
      11: aload_0
      12: invokevirtual #221                // Method getServer:()Lorg/apache/catalina/Server;
      15: ifnonnull     36
      18: getstatic     #1                  // Field log:Lorg/apache/juli/logging/Log;
      21: getstatic     #144                // Field sm:Lorg/apache/tomcat/util/res/StringManager;
      24: ldc_w         #269                // String catalina.noServer
      27: invokevirtual #218                // Method org/apache/tomcat/util/res/StringManager.getString:(Ljava/lang/String;)Ljava/lang/String;
      30: invokeinterface #270,  2          // InterfaceMethod org/apache/juli/logging/Log.fatal:(Ljava/lang/Object;)V
      35: return
      36: invokestatic  #249                // Method java/lang/System.nanoTime:()J
      39: lstore_1
      40: aload_0
      41: invokevirtual #221                // Method getServer:()Lorg/apache/catalina/Server;
      44: invokeinterface #271,  1          // InterfaceMethod org/apache/catalina/Server.start:()V
      49: goto          99
      52: astore_3
      53: getstatic     #1                  // Field log:Lorg/apache/juli/logging/Log;
      56: getstatic     #144                // Field sm:Lorg/apache/tomcat/util/res/StringManager;
      59: ldc_w         #272                // String catalina.serverStartFail
      62: invokevirtual #218                // Method org/apache/tomcat/util/res/StringManager.getString:(Ljava/lang/String;)Ljava/lang/String;
      65: aload_3
      66: invokeinterface #273,  3          // InterfaceMethod org/apache/juli/logging/Log.fatal:(Ljava/lang/Object;Ljava/lang/Throwable;)V
      71: aload_0
      72: invokevirtual #221                // Method getServer:()Lorg/apache/catalina/Server;
      75: invokeinterface #227,  1          // InterfaceMethod org/apache/catalina/Server.destroy:()V
      80: goto          98
      83: astore        4
      85: getstatic     #1                  // Field log:Lorg/apache/juli/logging/Log;
      88: ldc_w         #274                // String destroy() failed for failed Server
      91: aload         4
      93: invokeinterface #155,  3          // InterfaceMethod org/apache/juli/logging/Log.debug:(Ljava/lang/Object;Ljava/lang/Throwable;)V
      98: return
      99: getstatic     #1                  // Field log:Lorg/apache/juli/logging/Log;
     102: invokeinterface #156,  1          // InterfaceMethod org/apache/juli/logging/Log.isInfoEnabled:()Z
     107: ifeq          148
     110: getstatic     #1                  // Field log:Lorg/apache/juli/logging/Log;
     113: getstatic     #144                // Field sm:Lorg/apache/tomcat/util/res/StringManager;
     116: ldc_w         #275                // String catalina.startup
     119: iconst_1
     120: anewarray     #51                 // class java/lang/Object
     123: dup
     124: iconst_0
     125: getstatic     #263                // Field java/util/concurrent/TimeUnit.NANOSECONDS:Ljava/util/concurrent/TimeUnit;
     128: invokestatic  #249                // Method java/lang/System.nanoTime:()J
     131: lload_1
     132: lsub
     133: invokevirtual #264                // Method java/util/concurrent/TimeUnit.toMillis:(J)J
     136: invokestatic  #265                // Method java/lang/Long.toString:(J)Ljava/lang/String;
     139: aastore
     140: invokevirtual #154                // Method org/apache/tomcat/util/res/StringManager.getString:(Ljava/lang/String;[Ljava/lang/Object;)Ljava/lang/String;
     143: invokeinterface #157,  2          // InterfaceMethod org/apache/juli/logging/Log.info:(Ljava/lang/Object;)V
     148: aload_0
     149: getfield      #14                 // Field generateCode:Z
     152: ifeq          159
     155: aload_0
     156: invokevirtual #276                // Method generateLoader:()V
     159: aload_0
     160: getfield      #10                 // Field useShutdownHook:Z
     163: ifeq          214
     166: aload_0
     167: getfield      #11                 // Field shutdownHook:Ljava/lang/Thread;
     170: ifnonnull     185
     173: aload_0
     174: new           #277                // class org/apache/catalina/startup/Catalina$CatalinaShutdownHook
     177: dup
     178: aload_0
     179: invokespecial #278                // Method org/apache/catalina/startup/Catalina$CatalinaShutdownHook."<init>":(Lorg/apache/catalina/startup/Catalina;)V
     182: putfield      #11                 // Field shutdownHook:Ljava/lang/Thread;
     185: invokestatic  #279                // Method java/lang/Runtime.getRuntime:()Ljava/lang/Runtime;
     188: aload_0
     189: getfield      #11                 // Field shutdownHook:Ljava/lang/Thread;
     192: invokevirtual #280                // Method java/lang/Runtime.addShutdownHook:(Ljava/lang/Thread;)V
     195: invokestatic  #281                // Method java/util/logging/LogManager.getLogManager:()Ljava/util/logging/LogManager;
     198: astore_3
     199: aload_3
     200: instanceof    #282                // class org/apache/juli/ClassLoaderLogManager
     203: ifeq          214
     206: aload_3
     207: checkcast     #282                // class org/apache/juli/ClassLoaderLogManager
     210: iconst_0
     211: invokevirtual #283                // Method org/apache/juli/ClassLoaderLogManager.setUseShutdownHook:(Z)V
     214: aload_0
     215: getfield      #3                  // Field await:Z
     218: ifeq          229
     221: aload_0
     222: invokevirtual #284                // Method await:()V
     225: aload_0
     226: invokevirtual #285                // Method stop:()V
     229: return
    Exception table:
       from    to  target type
          40    49    52   Class org/apache/catalina/LifecycleException
          71    80    83   Class org/apache/catalina/LifecycleException

  public void stop();
    Code:
       0: aload_0
       1: getfield      #10                 // Field useShutdownHook:Z
       4: ifeq          37
       7: invokestatic  #279                // Method java/lang/Runtime.getRuntime:()Ljava/lang/Runtime;
      10: aload_0
      11: getfield      #11                 // Field shutdownHook:Ljava/lang/Thread;
      14: invokevirtual #286                // Method java/lang/Runtime.removeShutdownHook:(Ljava/lang/Thread;)Z
      17: pop
      18: invokestatic  #281                // Method java/util/logging/LogManager.getLogManager:()Ljava/util/logging/LogManager;
      21: astore_1
      22: aload_1
      23: instanceof    #282                // class org/apache/juli/ClassLoaderLogManager
      26: ifeq          37
      29: aload_1
      30: checkcast     #282                // class org/apache/juli/ClassLoaderLogManager
      33: iconst_1
      34: invokevirtual #283                // Method org/apache/juli/ClassLoaderLogManager.setUseShutdownHook:(Z)V
      37: goto          45
      40: astore_1
      41: aload_1
      42: invokestatic  #287                // Method org/apache/tomcat/util/ExceptionUtils.handleThrowable:(Ljava/lang/Throwable;)V
      45: aload_0
      46: invokevirtual #221                // Method getServer:()Lorg/apache/catalina/Server;
      49: astore_1
      50: aload_1
      51: invokeinterface #288,  1          // InterfaceMethod org/apache/catalina/Server.getState:()Lorg/apache/catalina/LifecycleState;
      56: astore_2
      57: getstatic     #289                // Field org/apache/catalina/LifecycleState.STOPPING_PREP:Lorg/apache/catalina/LifecycleState;
      60: aload_2
      61: invokevirtual #290                // Method org/apache/catalina/LifecycleState.compareTo:(Ljava/lang/Enum;)I
      64: ifgt          80
      67: getstatic     #291                // Field org/apache/catalina/LifecycleState.DESTROYED:Lorg/apache/catalina/LifecycleState;
      70: aload_2
      71: invokevirtual #290                // Method org/apache/catalina/LifecycleState.compareTo:(Ljava/lang/Enum;)I
      74: iflt          80
      77: goto          92
      80: aload_1
      81: invokeinterface #226,  1          // InterfaceMethod org/apache/catalina/Server.stop:()V
      86: aload_1
      87: invokeinterface #227,  1          // InterfaceMethod org/apache/catalina/Server.destroy:()V
      92: goto          113
      95: astore_1
      96: getstatic     #1                  // Field log:Lorg/apache/juli/logging/Log;
      99: getstatic     #144                // Field sm:Lorg/apache/tomcat/util/res/StringManager;
     102: ldc           #223                // String catalina.stopError
     104: invokevirtual #218                // Method org/apache/tomcat/util/res/StringManager.getString:(Ljava/lang/String;)Ljava/lang/String;
     107: aload_1
     108: invokeinterface #229,  3          // InterfaceMethod org/apache/juli/logging/Log.error:(Ljava/lang/Object;Ljava/lang/Throwable;)V
     113: return
    Exception table:
       from    to  target type
           0    37    40   Class java/lang/Throwable
          45    92    95   Class org/apache/catalina/LifecycleException

  public void await();
    Code:
       0: aload_0
       1: invokevirtual #221                // Method getServer:()Lorg/apache/catalina/Server;
       4: invokeinterface #292,  1          // InterfaceMethod org/apache/catalina/Server.await:()V
       9: return

  protected void usage();
    Code:
       0: getstatic     #267                // Field java/lang/System.out:Ljava/io/PrintStream;
       3: getstatic     #144                // Field sm:Lorg/apache/tomcat/util/res/StringManager;
       6: ldc_w         #293                // String catalina.usage
       9: invokevirtual #218                // Method org/apache/tomcat/util/res/StringManager.getString:(Ljava/lang/String;)Ljava/lang/String;
      12: invokevirtual #294                // Method java/io/PrintStream.println:(Ljava/lang/String;)V
      15: return

  protected void initDirs();
    Code:
       0: return

  protected void initStreams();
    Code:
       0: new           #295                // class org/apache/tomcat/util/log/SystemLogHandler
       3: dup
       4: getstatic     #267                // Field java/lang/System.out:Ljava/io/PrintStream;
       7: invokespecial #296                // Method org/apache/tomcat/util/log/SystemLogHandler."<init>":(Ljava/io/PrintStream;)V
      10: invokestatic  #297                // Method java/lang/System.setOut:(Ljava/io/PrintStream;)V
      13: new           #295                // class org/apache/tomcat/util/log/SystemLogHandler
      16: dup
      17: getstatic     #298                // Field java/lang/System.err:Ljava/io/PrintStream;
      20: invokespecial #296                // Method org/apache/tomcat/util/log/SystemLogHandler."<init>":(Ljava/io/PrintStream;)V
      23: invokestatic  #299                // Method java/lang/System.setErr:(Ljava/io/PrintStream;)V
      26: return

  protected void initNaming();
    Code:
       0: aload_0
       1: getfield      #12                 // Field useNaming:Z
       4: ifne          37
       7: getstatic     #1                  // Field log:Lorg/apache/juli/logging/Log;
      10: getstatic     #144                // Field sm:Lorg/apache/tomcat/util/res/StringManager;
      13: ldc_w         #300                // String catalina.noNatming
      16: invokevirtual #218                // Method org/apache/tomcat/util/res/StringManager.getString:(Ljava/lang/String;)Ljava/lang/String;
      19: invokeinterface #157,  2          // InterfaceMethod org/apache/juli/logging/Log.info:(Ljava/lang/Object;)V
      24: ldc_w         #301                // String catalina.useNaming
      27: ldc_w         #302                // String false
      30: invokestatic  #303                // Method java/lang/System.setProperty:(Ljava/lang/String;Ljava/lang/String;)Ljava/lang/String;
      33: pop
      34: goto          186
      37: ldc_w         #301                // String catalina.useNaming
      40: ldc_w         #304                // String true
      43: invokestatic  #303                // Method java/lang/System.setProperty:(Ljava/lang/String;Ljava/lang/String;)Ljava/lang/String;
      46: pop
      47: ldc_w         #305                // String org.apache.naming
      50: astore_1
      51: ldc_w         #307                // String java.naming.factory.url.pkgs
      54: invokestatic  #308                // Method java/lang/System.getProperty:(Ljava/lang/String;)Ljava/lang/String;
      57: astore_2
      58: aload_2
      59: ifnull        87
      62: new           #146                // class java/lang/StringBuilder
      65: dup
      66: invokespecial #147                // Method java/lang/StringBuilder."<init>":()V
      69: aload_1
      70: invokevirtual #150                // Method java/lang/StringBuilder.append:(Ljava/lang/String;)Ljava/lang/StringBuilder;
      73: ldc_w         #309                // String :
      76: invokevirtual #150                // Method java/lang/StringBuilder.append:(Ljava/lang/String;)Ljava/lang/StringBuilder;
      79: aload_2
      80: invokevirtual #150                // Method java/lang/StringBuilder.append:(Ljava/lang/String;)Ljava/lang/StringBuilder;
      83: invokevirtual #153                // Method java/lang/StringBuilder.toString:()Ljava/lang/String;
      86: astore_1
      87: ldc_w         #307                // String java.naming.factory.url.pkgs
      90: aload_1
      91: invokestatic  #303                // Method java/lang/System.setProperty:(Ljava/lang/String;Ljava/lang/String;)Ljava/lang/String;
      94: pop
      95: getstatic     #1                  // Field log:Lorg/apache/juli/logging/Log;
      98: invokeinterface #143,  1          // InterfaceMethod org/apache/juli/logging/Log.isDebugEnabled:()Z
     103: ifeq          134
     106: getstatic     #1                  // Field log:Lorg/apache/juli/logging/Log;
     109: new           #146                // class java/lang/StringBuilder
     112: dup
     113: invokespecial #147                // Method java/lang/StringBuilder."<init>":()V
     116: ldc_w         #310                // String Setting naming prefix=
     119: invokevirtual #150                // Method java/lang/StringBuilder.append:(Ljava/lang/String;)Ljava/lang/StringBuilder;
     122: aload_1
     123: invokevirtual #150                // Method java/lang/StringBuilder.append:(Ljava/lang/String;)Ljava/lang/StringBuilder;
     126: invokevirtual #153                // Method java/lang/StringBuilder.toString:()Ljava/lang/String;
     129: invokeinterface #311,  2          // InterfaceMethod org/apache/juli/logging/Log.debug:(Ljava/lang/Object;)V
     134: ldc_w         #312                // String java.naming.factory.initial
     137: invokestatic  #308                // Method java/lang/System.getProperty:(Ljava/lang/String;)Ljava/lang/String;
     140: astore_1
     141: aload_1
     142: ifnonnull     158
     145: ldc_w         #312                // String java.naming.factory.initial
     148: ldc_w         #313                // String org.apache.naming.java.javaURLContextFactory
     151: invokestatic  #303                // Method java/lang/System.setProperty:(Ljava/lang/String;Ljava/lang/String;)Ljava/lang/String;
     154: pop
     155: goto          186
     158: getstatic     #1                  // Field log:Lorg/apache/juli/logging/Log;
     161: new           #146                // class java/lang/StringBuilder
     164: dup
     165: invokespecial #147                // Method java/lang/StringBuilder."<init>":()V
     168: ldc_w         #314                // String INITIAL_CONTEXT_FACTORY already set
     171: invokevirtual #150                // Method java/lang/StringBuilder.append:(Ljava/lang/String;)Ljava/lang/StringBuilder;
     174: aload_1
     175: invokevirtual #150                // Method java/lang/StringBuilder.append:(Ljava/lang/String;)Ljava/lang/StringBuilder;
     178: invokevirtual #153                // Method java/lang/StringBuilder.toString:()Ljava/lang/String;
     181: invokeinterface #311,  2          // InterfaceMethod org/apache/juli/logging/Log.debug:(Ljava/lang/Object;)V
     186: return

  protected void setSecurityProtection();
    Code:
       0: invokestatic  #315                // Method org/apache/catalina/security/SecurityConfig.newInstance:()Lorg/apache/catalina/security/SecurityConfig;
       3: astore_1
       4: aload_1
       5: invokevirtual #316                // Method org/apache/catalina/security/SecurityConfig.setPackageDefinition:()V
       8: aload_1
       9: invokevirtual #317                // Method org/apache/catalina/security/SecurityConfig.setPackageAccess:()V
      12: return

  protected void generateLoader();
    Code:
       0: ldc_w         #318                // String DigesterGeneratedCodeLoader
       3: astore_1
       4: new           #146                // class java/lang/StringBuilder
       7: dup
       8: invokespecial #147                // Method java/lang/StringBuilder."<init>":()V
      11: astore_2
      12: aload_2
      13: ldc_w         #319                // String package
      16: invokevirtual #150                // Method java/lang/StringBuilder.append:(Ljava/lang/String;)Ljava/lang/StringBuilder;
      19: aload_0
      20: getfield      #18                 // Field generatedCodePackage:Ljava/lang/String;
      23: invokevirtual #150                // Method java/lang/StringBuilder.append:(Ljava/lang/String;)Ljava/lang/StringBuilder;
      26: ldc_w         #320                // String ;
      29: invokevirtual #150                // Method java/lang/StringBuilder.append:(Ljava/lang/String;)Ljava/lang/StringBuilder;
      32: invokestatic  #321                // Method java/lang/System.lineSeparator:()Ljava/lang/String;
      35: invokevirtual #150                // Method java/lang/StringBuilder.append:(Ljava/lang/String;)Ljava/lang/StringBuilder;
      38: pop
      39: aload_2
      40: ldc_w         #322                // String public class
      43: invokevirtual #150                // Method java/lang/StringBuilder.append:(Ljava/lang/String;)Ljava/lang/StringBuilder;
      46: aload_1
      47: invokevirtual #150                // Method java/lang/StringBuilder.append:(Ljava/lang/String;)Ljava/lang/StringBuilder;
      50: pop
      51: aload_2
      52: ldc_w         #323                // String  implements org.apache.tomcat.util.digester.Digester.GeneratedCodeLoader {
      55: invokevirtual #150                // Method java/lang/StringBuilder.append:(Ljava/lang/String;)Ljava/lang/StringBuilder;
      58: invokestatic  #321                // Method java/lang/System.lineSeparator:()Ljava/lang/String;
      61: invokevirtual #150                // Method java/lang/StringBuilder.append:(Ljava/lang/String;)Ljava/lang/StringBuilder;
      64: pop
      65: aload_2
      66: ldc_w         #324                // String public Object loadGeneratedCode(String className) {
      69: invokevirtual #150                // Method java/lang/StringBuilder.append:(Ljava/lang/String;)Ljava/lang/StringBuilder;
      72: invokestatic  #321                // Method java/lang/System.lineSeparator:()Ljava/lang/String;
      75: invokevirtual #150                // Method java/lang/StringBuilder.append:(Ljava/lang/String;)Ljava/lang/StringBuilder;
      78: pop
      79: aload_2
      80: ldc_w         #325                // String switch (className) {
      83: invokevirtual #150                // Method java/lang/StringBuilder.append:(Ljava/lang/String;)Ljava/lang/StringBuilder;
      86: invokestatic  #321                // Method java/lang/System.lineSeparator:()Ljava/lang/String;
      89: invokevirtual #150                // Method java/lang/StringBuilder.append:(Ljava/lang/String;)Ljava/lang/StringBuilder;
      92: pop
      93: invokestatic  #326                // Method org/apache/tomcat/util/digester/Digester.getGeneratedClasses:()[Ljava/lang/String;
      96: astore_3
      97: aload_3
      98: arraylength
      99: istore        4
     101: iconst_0
     102: istore        5
     104: iload         5
     106: iload         4
     108: if_icmpge     161
     111: aload_3
     112: iload         5
     114: aaload
     115: astore        6
     117: aload_2
     118: ldc_w         #327                // String case \"
     121: invokevirtual #150                // Method java/lang/StringBuilder.append:(Ljava/lang/String;)Ljava/lang/StringBuilder;
     124: aload         6
     126: invokevirtual #150                // Method java/lang/StringBuilder.append:(Ljava/lang/String;)Ljava/lang/StringBuilder;
     129: ldc_w         #328                // String \" : return new
     132: invokevirtual #150                // Method java/lang/StringBuilder.append:(Ljava/lang/String;)Ljava/lang/StringBuilder;
     135: aload         6
     137: invokevirtual #150                // Method java/lang/StringBuilder.append:(Ljava/lang/String;)Ljava/lang/StringBuilder;
     140: pop
     141: aload_2
     142: ldc_w         #329                // String ();
     145: invokevirtual #150                // Method java/lang/StringBuilder.append:(Ljava/lang/String;)Ljava/lang/StringBuilder;
     148: invokestatic  #321                // Method java/lang/System.lineSeparator:()Ljava/lang/String;
     151: invokevirtual #150                // Method java/lang/StringBuilder.append:(Ljava/lang/String;)Ljava/lang/StringBuilder;
     154: pop
     155: iinc          5, 1
     158: goto          104
     161: aload_2
     162: ldc_w         #330                // String default: return null; }
     165: invokevirtual #150                // Method java/lang/StringBuilder.append:(Ljava/lang/String;)Ljava/lang/StringBuilder;
     168: invokestatic  #321                // Method java/lang/System.lineSeparator:()Ljava/lang/String;
     171: invokevirtual #150                // Method java/lang/StringBuilder.append:(Ljava/lang/String;)Ljava/lang/StringBuilder;
     174: pop
     175: aload_2
     176: ldc_w         #331                // String }}
     179: invokevirtual #150                // Method java/lang/StringBuilder.append:(Ljava/lang/String;)Ljava/lang/StringBuilder;
     182: invokestatic  #321                // Method java/lang/System.lineSeparator:()Ljava/lang/String;
     185: invokevirtual #150                // Method java/lang/StringBuilder.append:(Ljava/lang/String;)Ljava/lang/StringBuilder;
     188: pop
     189: new           #36                 // class java/io/File
     192: dup
     193: aload_0
     194: getfield      #15                 // Field generatedCodeLocation:Ljava/io/File;
     197: aload_0
     198: getfield      #18                 // Field generatedCodePackage:Ljava/lang/String;
     201: invokespecial #175                // Method java/io/File."<init>":(Ljava/io/File;Ljava/lang/String;)V
     204: astore_3
     205: new           #201                // class java/io/FileWriter
     208: dup
     209: new           #36                 // class java/io/File
     212: dup
     213: aload_3
     214: new           #146                // class java/lang/StringBuilder
     217: dup
     218: invokespecial #147                // Method java/lang/StringBuilder."<init>":()V
     221: aload_1
     222: invokevirtual #150                // Method java/lang/StringBuilder.append:(Ljava/lang/String;)Ljava/lang/StringBuilder;
     225: ldc_w         #332                // String .java
     228: invokevirtual #150                // Method java/lang/StringBuilder.append:(Ljava/lang/String;)Ljava/lang/StringBuilder;
     231: invokevirtual #153                // Method java/lang/StringBuilder.toString:()Ljava/lang/String;
     234: invokespecial #175                // Method java/io/File."<init>":(Ljava/io/File;Ljava/lang/String;)V
     237: invokespecial #204                // Method java/io/FileWriter."<init>":(Ljava/io/File;)V
     240: astore        4
     242: aconst_null
     243: astore        5
     245: aload         4
     247: aload_2
     248: invokevirtual #153                // Method java/lang/StringBuilder.toString:()Ljava/lang/String;
     251: invokevirtual #206                // Method java/io/FileWriter.write:(Ljava/lang/String;)V
     254: aload         4
     256: ifnull        341
     259: aload         5
     261: ifnull        284
     264: aload         4
     266: invokevirtual #207                // Method java/io/FileWriter.close:()V
     269: goto          341
     272: astore        6
     274: aload         5
     276: aload         6
     278: invokevirtual #209                // Method java/lang/Throwable.addSuppressed:(Ljava/lang/Throwable;)V
     281: goto          341
     284: aload         4
     286: invokevirtual #207                // Method java/io/FileWriter.close:()V
     289: goto          341
     292: astore        6
     294: aload         6
     296: astore        5
     298: aload         6
     300: athrow
     301: astore        7
     303: aload         4
     305: ifnull        338
     308: aload         5
     310: ifnull        333
     313: aload         4
     315: invokevirtual #207                // Method java/io/FileWriter.close:()V
     318: goto          338
     321: astore        8
     323: aload         5
     325: aload         8
     327: invokevirtual #209                // Method java/lang/Throwable.addSuppressed:(Ljava/lang/Throwable;)V
     330: goto          338
     333: aload         4
     335: invokevirtual #207                // Method java/io/FileWriter.close:()V
     338: aload         7
     340: athrow
     341: goto          359
     344: astore        4
     346: getstatic     #1                  // Field log:Lorg/apache/juli/logging/Log;
     349: ldc_w         #333                // String Error writing code loader
     352: aload         4
     354: invokeinterface #155,  3          // InterfaceMethod org/apache/juli/logging/Log.debug:(Ljava/lang/Object;Ljava/lang/Throwable;)V
     359: return
    Exception table:
       from    to  target type
         264   269   272   Class java/lang/Throwable
         245   254   292   Class java/lang/Throwable
         245   254   301   any
         313   318   321   Class java/lang/Throwable
         292   303   301   any
         205   341   344   Class java/io/IOException

  protected void generateClassHeader(org.apache.tomcat.util.digester.Digester, boolean);
    Code:
       0: aload_1
       1: invokevirtual #205                // Method org/apache/tomcat/util/digester/Digester.getGeneratedCode:()Ljava/lang/StringBuilder;
       4: astore_3
       5: aload_3
       6: ldc_w         #319                // String package
       9: invokevirtual #150                // Method java/lang/StringBuilder.append:(Ljava/lang/String;)Ljava/lang/StringBuilder;
      12: aload_0
      13: getfield      #18                 // Field generatedCodePackage:Ljava/lang/String;
      16: invokevirtual #150                // Method java/lang/StringBuilder.append:(Ljava/lang/String;)Ljava/lang/StringBuilder;
      19: ldc_w         #320                // String ;
      22: invokevirtual #150                // Method java/lang/StringBuilder.append:(Ljava/lang/String;)Ljava/lang/StringBuilder;
      25: invokestatic  #321                // Method java/lang/System.lineSeparator:()Ljava/lang/String;
      28: invokevirtual #150                // Method java/lang/StringBuilder.append:(Ljava/lang/String;)Ljava/lang/StringBuilder;
      31: pop
      32: aload_3
      33: ldc_w         #334                // String public class ServerXml
      36: invokevirtual #150                // Method java/lang/StringBuilder.append:(Ljava/lang/String;)Ljava/lang/StringBuilder;
      39: pop
      40: iload_2
      41: ifne          52
      44: aload_3
      45: ldc_w         #335                // String Stop
      48: invokevirtual #150                // Method java/lang/StringBuilder.append:(Ljava/lang/String;)Ljava/lang/StringBuilder;
      51: pop
      52: aload_3
      53: ldc_w         #336                // String  implements
      56: invokevirtual #150                // Method java/lang/StringBuilder.append:(Ljava/lang/String;)Ljava/lang/StringBuilder;
      59: pop
      60: aload_3
      61: ldc           #183                // class org/apache/catalina/startup/Catalina$ServerXml
      63: invokevirtual #149                // Method java/lang/Class.getName:()Ljava/lang/String;
      66: bipush        36
      68: bipush        46
      70: invokevirtual #337                // Method java/lang/String.replace:(CC)Ljava/lang/String;
      73: invokevirtual #150                // Method java/lang/StringBuilder.append:(Ljava/lang/String;)Ljava/lang/StringBuilder;
      76: ldc_w         #338                // String  {
      79: invokevirtual #150                // Method java/lang/StringBuilder.append:(Ljava/lang/String;)Ljava/lang/StringBuilder;
      82: invokestatic  #321                // Method java/lang/System.lineSeparator:()Ljava/lang/String;
      85: invokevirtual #150                // Method java/lang/StringBuilder.append:(Ljava/lang/String;)Ljava/lang/StringBuilder;
      88: pop
      89: aload_3
      90: ldc_w         #339                // String public void load(
      93: invokevirtual #150                // Method java/lang/StringBuilder.append:(Ljava/lang/String;)Ljava/lang/StringBuilder;
      96: ldc           #4                  // class org/apache/catalina/startup/Catalina
      98: invokevirtual #149                // Method java/lang/Class.getName:()Ljava/lang/String;
     101: invokevirtual #150                // Method java/lang/StringBuilder.append:(Ljava/lang/String;)Ljava/lang/StringBuilder;
     104: pop
     105: aload_3
     106: bipush        32
     108: invokevirtual #340                // Method java/lang/StringBuilder.append:(C)Ljava/lang/StringBuilder;
     111: aload_1
     112: aload_0
     113: invokevirtual #341                // Method org/apache/tomcat/util/digester/Digester.toVariableName:(Ljava/lang/Object;)Ljava/lang/String;
     116: invokevirtual #150                // Method java/lang/StringBuilder.append:(Ljava/lang/String;)Ljava/lang/StringBuilder;
     119: ldc_w         #342                // String ) {
     122: invokevirtual #150                // Method java/lang/StringBuilder.append:(Ljava/lang/String;)Ljava/lang/StringBuilder;
     125: invokestatic  #321                // Method java/lang/System.lineSeparator:()Ljava/lang/String;
     128: invokevirtual #150                // Method java/lang/StringBuilder.append:(Ljava/lang/String;)Ljava/lang/StringBuilder;
     131: pop
     132: return

  protected void generateClassFooter(org.apache.tomcat.util.digester.Digester);
    Code:
       0: aload_1
       1: invokevirtual #205                // Method org/apache/tomcat/util/digester/Digester.getGeneratedCode:()Ljava/lang/StringBuilder;
       4: astore_2
       5: aload_2
       6: bipush        125
       8: invokevirtual #340                // Method java/lang/StringBuilder.append:(C)Ljava/lang/StringBuilder;
      11: invokestatic  #321                // Method java/lang/System.lineSeparator:()Ljava/lang/String;
      14: invokevirtual #150                // Method java/lang/StringBuilder.append:(Ljava/lang/String;)Ljava/lang/StringBuilder;
      17: pop
      18: aload_2
      19: bipush        125
      21: invokevirtual #340                // Method java/lang/StringBuilder.append:(C)Ljava/lang/StringBuilder;
      24: invokestatic  #321                // Method java/lang/System.lineSeparator:()Ljava/lang/String;
      27: invokevirtual #150                // Method java/lang/StringBuilder.append:(Ljava/lang/String;)Ljava/lang/StringBuilder;
      30: pop
      31: return

  static org.apache.juli.logging.Log access$000();
    Code:
       0: getstatic     #1                  // Field log:Lorg/apache/juli/logging/Log;
       3: areturn

  static {};
    Code:
       0: ldc_w         #344                // String org.apache.catalina.startup
       3: invokestatic  #345                // Method org/apache/tomcat/util/res/StringManager.getManager:(Ljava/lang/String;)Lorg/apache/tomcat/util/res/StringManager;
       6: putstatic     #144                // Field sm:Lorg/apache/tomcat/util/res/StringManager;
       9: ldc           #4                  // class org/apache/catalina/startup/Catalina
      11: invokestatic  #346                // Method org/apache/juli/logging/LogFactory.getLog:(Ljava/lang/Class;)Lorg/apache/juli/logging/Log;
      14: putstatic     #1                  // Field log:Lorg/apache/juli/logging/Log;
      17: return
}
