Compiled from "AbstractTypeDescriptor.java"
public abstract class org.hibernate.type.descriptor.java.AbstractTypeDescriptor<T> implements org.hibernate.type.descriptor.java.BasicJavaDescriptor<T>, java.io.Serializable {
  private final java.lang.Class<T> type;

  private final org.hibernate.type.descriptor.java.MutabilityPlan<T> mutabilityPlan;

  private final java.util.Comparator<T> comparator;

  protected org.hibernate.type.descriptor.java.AbstractTypeDescriptor(java.lang.Class<T>);
    Code:
       0: aload_0
       1: aload_1
       2: getstatic     #1                  // Field org/hibernate/type/descriptor/java/ImmutableMutabilityPlan.INSTANCE:Lorg/hibernate/type/descriptor/java/ImmutableMutabilityPlan;
       5: invokespecial #2                  // Method "<init>":(Ljava/lang/Class;Lorg/hibernate/type/descriptor/java/MutabilityPlan;)V
       8: return

  protected org.hibernate.type.descriptor.java.AbstractTypeDescriptor(java.lang.Class<T>, org.hibernate.type.descriptor.java.MutabilityPlan<T>);
    Code:
       0: aload_0
       1: invokespecial #3                  // Method java/lang/Object."<init>":()V
       4: aload_0
       5: aload_1
       6: putfield      #4                  // Field type:Ljava/lang/Class;
       9: aload_0
      10: aload_2
      11: putfield      #5                  // Field mutabilityPlan:Lorg/hibernate/type/descriptor/java/MutabilityPlan;
      14: aload_0
      15: ldc           #6                  // class java/lang/Comparable
      17: aload_1
      18: invokevirtual #7                  // Method java/lang/Class.isAssignableFrom:(Ljava/lang/Class;)Z
      21: ifeq          30
      24: getstatic     #8                  // Field org/hibernate/internal/util/compare/ComparableComparator.INSTANCE:Ljava/util/Comparator;
      27: goto          31
      30: aconst_null
      31: putfield      #9                  // Field comparator:Ljava/util/Comparator;
      34: return

  public org.hibernate.type.descriptor.java.MutabilityPlan<T> getMutabilityPlan();
    Code:
       0: aload_0
       1: getfield      #5                  // Field mutabilityPlan:Lorg/hibernate/type/descriptor/java/MutabilityPlan;
       4: areturn

  public java.lang.Class<T> getJavaType();
    Code:
       0: aload_0
       1: getfield      #4                  // Field type:Ljava/lang/Class;
       4: areturn

  public java.lang.Class<T> getJavaTypeClass();
    Code:
       0: aload_0
       1: invokevirtual #10                 // Method getJavaType:()Ljava/lang/Class;
       4: areturn

  public int extractHashCode(T);
    Code:
       0: aload_1
       1: invokevirtual #11                 // Method java/lang/Object.hashCode:()I
       4: ireturn

  public boolean areEqual(T, T);
    Code:
       0: aload_1
       1: aload_2
       2: invokestatic  #12                 // Method java/util/Objects.equals:(Ljava/lang/Object;Ljava/lang/Object;)Z
       5: ireturn

  public java.util.Comparator<T> getComparator();
    Code:
       0: aload_0
       1: getfield      #9                  // Field comparator:Ljava/util/Comparator;
       4: areturn

  public java.lang.String extractLoggableRepresentation(T);
    Code:
       0: aload_1
       1: ifnonnull     9
       4: ldc           #13                 // String null
       6: goto          13
       9: aload_1
      10: invokevirtual #14                 // Method java/lang/Object.toString:()Ljava/lang/String;
      13: areturn

  protected org.hibernate.HibernateException unknownUnwrap(java.lang.Class);
    Code:
       0: new           #15                 // class org/hibernate/HibernateException
       3: dup
       4: new           #16                 // class java/lang/StringBuilder
       7: dup
       8: invokespecial #17                 // Method java/lang/StringBuilder."<init>":()V
      11: ldc           #18                 // String Unknown unwrap conversion requested:
      13: invokevirtual #19                 // Method java/lang/StringBuilder.append:(Ljava/lang/String;)Ljava/lang/StringBuilder;
      16: aload_0
      17: getfield      #4                  // Field type:Ljava/lang/Class;
      20: invokevirtual #20                 // Method java/lang/Class.getName:()Ljava/lang/String;
      23: invokevirtual #19                 // Method java/lang/StringBuilder.append:(Ljava/lang/String;)Ljava/lang/StringBuilder;
      26: ldc           #21                 // String  to
      28: invokevirtual #19                 // Method java/lang/StringBuilder.append:(Ljava/lang/String;)Ljava/lang/StringBuilder;
      31: aload_1
      32: invokevirtual #20                 // Method java/lang/Class.getName:()Ljava/lang/String;
      35: invokevirtual #19                 // Method java/lang/StringBuilder.append:(Ljava/lang/String;)Ljava/lang/StringBuilder;
      38: invokevirtual #22                 // Method java/lang/StringBuilder.toString:()Ljava/lang/String;
      41: invokespecial #23                 // Method org/hibernate/HibernateException."<init>":(Ljava/lang/String;)V
      44: athrow

  protected org.hibernate.HibernateException unknownWrap(java.lang.Class);
    Code:
       0: new           #15                 // class org/hibernate/HibernateException
       3: dup
       4: new           #16                 // class java/lang/StringBuilder
       7: dup
       8: invokespecial #17                 // Method java/lang/StringBuilder."<init>":()V
      11: ldc           #24                 // String Unknown wrap conversion requested:
      13: invokevirtual #19                 // Method java/lang/StringBuilder.append:(Ljava/lang/String;)Ljava/lang/StringBuilder;
      16: aload_1
      17: invokevirtual #20                 // Method java/lang/Class.getName:()Ljava/lang/String;
      20: invokevirtual #19                 // Method java/lang/StringBuilder.append:(Ljava/lang/String;)Ljava/lang/StringBuilder;
      23: ldc           #21                 // String  to
      25: invokevirtual #19                 // Method java/lang/StringBuilder.append:(Ljava/lang/String;)Ljava/lang/StringBuilder;
      28: aload_0
      29: getfield      #4                  // Field type:Ljava/lang/Class;
      32: invokevirtual #20                 // Method java/lang/Class.getName:()Ljava/lang/String;
      35: invokevirtual #19                 // Method java/lang/StringBuilder.append:(Ljava/lang/String;)Ljava/lang/StringBuilder;
      38: invokevirtual #22                 // Method java/lang/StringBuilder.toString:()Ljava/lang/String;
      41: invokespecial #23                 // Method org/hibernate/HibernateException."<init>":(Ljava/lang/String;)V
      44: athrow
}
