Compiled from "TemplateServlet.java"
class groovy.servlet.TemplateServlet$TemplateCacheEntry {
  java.util.Date date;

  long hit;

  long lastModified;

  long length;

  groovy.text.Template template;

  public groovy.servlet.TemplateServlet$TemplateCacheEntry(java.io.File, groovy.text.Template, boolean);
    Code:
       0: aload_0
       1: invokespecial #21                 // Method java/lang/Object."<init>":()V
       4: aload_2
       5: ifnonnull     18
       8: new           #23                 // class java/lang/NullPointerException
      11: dup
      12: ldc           #24                 // String template
      14: invokespecial #27                 // Method java/lang/NullPointerException."<init>":(Ljava/lang/String;)V
      17: athrow
      18: iload_3
      19: ifeq          39
      22: aload_0
      23: new           #33                 // class java/util/Date
      26: dup
      27: invokestatic  #39                 // Method java/lang/System.currentTimeMillis:()J
      30: invokespecial #42                 // Method java/util/Date."<init>":(J)V
      33: putfield      #44                 // Field date:Ljava/util/Date;
      36: goto          44
      39: aload_0
      40: aconst_null
      41: putfield      #44                 // Field date:Ljava/util/Date;
      44: aload_0
      45: lconst_0
      46: putfield      #46                 // Field hit:J
      49: aload_1
      50: ifnull        69
      53: aload_0
      54: aload_1
      55: invokevirtual #48                 // Method java/io/File.lastModified:()J
      58: putfield      #50                 // Field lastModified:J
      61: aload_0
      62: aload_1
      63: invokevirtual #52                 // Method java/io/File.length:()J
      66: putfield      #54                 // Field length:J
      69: aload_0
      70: aload_2
      71: putfield      #56                 // Field template:Lgroovy/text/Template;
      74: return

  public boolean validate(java.io.File);
    Code:
       0: aload_1
       1: ifnull        32
       4: aload_1
       5: invokevirtual #48                 // Method java/io/File.lastModified:()J
       8: aload_0
       9: getfield      #50                 // Field lastModified:J
      12: lcmp
      13: ifeq          18
      16: iconst_0
      17: ireturn
      18: aload_1
      19: invokevirtual #52                 // Method java/io/File.length:()J
      22: aload_0
      23: getfield      #54                 // Field length:J
      26: lcmp
      27: ifeq          32
      30: iconst_0
      31: ireturn
      32: aload_0
      33: dup
      34: getfield      #46                 // Field hit:J
      37: lconst_1
      38: ladd
      39: putfield      #46                 // Field hit:J
      42: iconst_1
      43: ireturn

  public java.lang.String toString();
    Code:
       0: aload_0
       1: getfield      #44                 // Field date:Ljava/util/Date;
       4: ifnonnull     30
       7: new           #68                 // class java/lang/StringBuilder
      10: dup
      11: invokespecial #69                 // Method java/lang/StringBuilder."<init>":()V
      14: ldc           #71                 // String Hit #
      16: invokevirtual #75                 // Method java/lang/StringBuilder.append:(Ljava/lang/String;)Ljava/lang/StringBuilder;
      19: aload_0
      20: getfield      #46                 // Field hit:J
      23: invokevirtual #78                 // Method java/lang/StringBuilder.append:(J)Ljava/lang/StringBuilder;
      26: invokevirtual #80                 // Method java/lang/StringBuilder.toString:()Ljava/lang/String;
      29: areturn
      30: new           #68                 // class java/lang/StringBuilder
      33: dup
      34: invokespecial #69                 // Method java/lang/StringBuilder."<init>":()V
      37: ldc           #71                 // String Hit #
      39: invokevirtual #75                 // Method java/lang/StringBuilder.append:(Ljava/lang/String;)Ljava/lang/StringBuilder;
      42: aload_0
      43: getfield      #46                 // Field hit:J
      46: invokevirtual #78                 // Method java/lang/StringBuilder.append:(J)Ljava/lang/StringBuilder;
      49: ldc           #82                 // String  since
      51: invokevirtual #75                 // Method java/lang/StringBuilder.append:(Ljava/lang/String;)Ljava/lang/StringBuilder;
      54: aload_0
      55: getfield      #44                 // Field date:Ljava/util/Date;
      58: invokevirtual #85                 // Method java/lang/StringBuilder.append:(Ljava/lang/Object;)Ljava/lang/StringBuilder;
      61: invokevirtual #80                 // Method java/lang/StringBuilder.toString:()Ljava/lang/String;
      64: areturn
}
