Compiled from "signatureEnhancement.kt"
final class kotlin.reflect.jvm.internal.impl.load.java.typeEnhancement.SignatureEnhancement$ValueParameterEnhancementResult extends kotlin.reflect.jvm.internal.impl.load.java.typeEnhancement.SignatureEnhancement$PartEnhancementResult {
  private final boolean hasDefaultValue;

  public final boolean getHasDefaultValue();
    Code:
       0: aload_0
       1: getfield      #6                  // Field hasDefaultValue:Z
       4: ireturn

  public kotlin.reflect.jvm.internal.impl.load.java.typeEnhancement.SignatureEnhancement$ValueParameterEnhancementResult(kotlin.reflect.jvm.internal.impl.types.KotlinType, boolean, boolean, boolean);
    Code:
       0: aload_1
       1: ldc           #1                  // String type
       3: invokestatic  #7                  // Method kotlin/jvm/internal/Intrinsics.checkParameterIsNotNull:(Ljava/lang/Object;Ljava/lang/String;)V
       6: aload_0
       7: aload_1
       8: iload_3
       9: iload         4
      11: invokespecial #8                  // Method kotlin/reflect/jvm/internal/impl/load/java/typeEnhancement/SignatureEnhancement$PartEnhancementResult."<init>":(Lkotlin/reflect/jvm/internal/impl/types/KotlinType;ZZ)V
      14: aload_0
      15: iload_2
      16: putfield      #6                  // Field hasDefaultValue:Z
      19: return
}
