Compiled from "SequenceFileInputFilter.java"
public class org.apache.hadoop.mapreduce.lib.input.SequenceFileInputFilter$PercentFilter extends org.apache.hadoop.mapreduce.lib.input.SequenceFileInputFilter$FilterBase {
  private int frequency;

  private int count;

  public static void setFrequency(org.apache.hadoop.conf.Configuration, int);
    Code:
       0: iload_1
       1: ifgt          31
       4: new           #2                  // class java/lang/IllegalArgumentException
       7: dup
       8: new           #3                  // class java/lang/StringBuilder
      11: dup
      12: invokespecial #4                  // Method java/lang/StringBuilder."<init>":()V
      15: ldc           #5                  // String Negative mapreduce.input.sequencefileinputfilter.frequency:
      17: invokevirtual #6                  // Method java/lang/StringBuilder.append:(Ljava/lang/String;)Ljava/lang/StringBuilder;
      20: iload_1
      21: invokevirtual #7                  // Method java/lang/StringBuilder.append:(I)Ljava/lang/StringBuilder;
      24: invokevirtual #8                  // Method java/lang/StringBuilder.toString:()Ljava/lang/String;
      27: invokespecial #9                  // Method java/lang/IllegalArgumentException."<init>":(Ljava/lang/String;)V
      30: athrow
      31: aload_0
      32: ldc           #10                 // String mapreduce.input.sequencefileinputfilter.frequency
      34: iload_1
      35: invokevirtual #11                 // Method org/apache/hadoop/conf/Configuration.setInt:(Ljava/lang/String;I)V
      38: return

  public org.apache.hadoop.mapreduce.lib.input.SequenceFileInputFilter$PercentFilter();
    Code:
       0: aload_0
       1: invokespecial #12                 // Method org/apache/hadoop/mapreduce/lib/input/SequenceFileInputFilter$FilterBase."<init>":()V
       4: return

  public void setConf(org.apache.hadoop.conf.Configuration);
    Code:
       0: aload_0
       1: aload_1
       2: ldc           #10                 // String mapreduce.input.sequencefileinputfilter.frequency
       4: bipush        10
       6: invokevirtual #13                 // Method org/apache/hadoop/conf/Configuration.getInt:(Ljava/lang/String;I)I
       9: putfield      #14                 // Field frequency:I
      12: aload_0
      13: getfield      #14                 // Field frequency:I
      16: ifgt          49
      19: new           #15                 // class java/lang/RuntimeException
      22: dup
      23: new           #3                  // class java/lang/StringBuilder
      26: dup
      27: invokespecial #4                  // Method java/lang/StringBuilder."<init>":()V
      30: ldc           #5                  // String Negative mapreduce.input.sequencefileinputfilter.frequency:
      32: invokevirtual #6                  // Method java/lang/StringBuilder.append:(Ljava/lang/String;)Ljava/lang/StringBuilder;
      35: aload_0
      36: getfield      #14                 // Field frequency:I
      39: invokevirtual #7                  // Method java/lang/StringBuilder.append:(I)Ljava/lang/StringBuilder;
      42: invokevirtual #8                  // Method java/lang/StringBuilder.toString:()Ljava/lang/String;
      45: invokespecial #16                 // Method java/lang/RuntimeException."<init>":(Ljava/lang/String;)V
      48: athrow
      49: aload_0
      50: aload_1
      51: putfield      #17                 // Field conf:Lorg/apache/hadoop/conf/Configuration;
      54: return

  public boolean accept(java.lang.Object);
    Code:
       0: iconst_0
       1: istore_2
       2: aload_0
       3: getfield      #18                 // Field count:I
       6: ifne          11
       9: iconst_1
      10: istore_2
      11: aload_0
      12: dup
      13: getfield      #18                 // Field count:I
      16: iconst_1
      17: iadd
      18: dup_x1
      19: putfield      #18                 // Field count:I
      22: aload_0
      23: getfield      #14                 // Field frequency:I
      26: if_icmpne     34
      29: aload_0
      30: iconst_0
      31: putfield      #18                 // Field count:I
      34: iload_2
      35: ireturn
}
