Compiled from "CallCredentialsApplyingTransportFactory.java"
class io.grpc.internal.CallCredentialsApplyingTransportFactory$CallCredentialsApplyingTransport extends io.grpc.internal.ForwardingConnectionClientTransport {
  private final io.grpc.internal.ConnectionClientTransport delegate;

  private final java.lang.String authority;

  private final java.util.concurrent.atomic.AtomicInteger pendingApplier;

  private volatile io.grpc.Status shutdownStatus;

  private io.grpc.Status savedShutdownStatus;

  private io.grpc.Status savedShutdownNowStatus;

  private final io.grpc.internal.MetadataApplierImpl$MetadataApplierListener applierListener;

  final io.grpc.internal.CallCredentialsApplyingTransportFactory this$0;

  io.grpc.internal.CallCredentialsApplyingTransportFactory$CallCredentialsApplyingTransport(io.grpc.internal.CallCredentialsApplyingTransportFactory, io.grpc.internal.ConnectionClientTransport, java.lang.String);
    Code:
       0: aload_0
       1: aload_1
       2: putfield      #5                  // Field this$0:Lio/grpc/internal/CallCredentialsApplyingTransportFactory;
       5: aload_0
       6: invokespecial #6                  // Method io/grpc/internal/ForwardingConnectionClientTransport."<init>":()V
       9: aload_0
      10: new           #7                  // class java/util/concurrent/atomic/AtomicInteger
      13: dup
      14: ldc           #9                  // int -2147483647
      16: invokespecial #10                 // Method java/util/concurrent/atomic/AtomicInteger."<init>":(I)V
      19: putfield      #4                  // Field pendingApplier:Ljava/util/concurrent/atomic/AtomicInteger;
      22: aload_0
      23: new           #11                 // class io/grpc/internal/CallCredentialsApplyingTransportFactory$CallCredentialsApplyingTransport$1
      26: dup
      27: aload_0
      28: invokespecial #12                 // Method io/grpc/internal/CallCredentialsApplyingTransportFactory$CallCredentialsApplyingTransport$1."<init>":(Lio/grpc/internal/CallCredentialsApplyingTransportFactory$CallCredentialsApplyingTransport;)V
      31: putfield      #13                 // Field applierListener:Lio/grpc/internal/MetadataApplierImpl$MetadataApplierListener;
      34: aload_0
      35: aload_2
      36: ldc           #14                 // String delegate
      38: invokestatic  #15                 // Method com/google/common/base/Preconditions.checkNotNull:(Ljava/lang/Object;Ljava/lang/Object;)Ljava/lang/Object;
      41: checkcast     #16                 // class io/grpc/internal/ConnectionClientTransport
      44: putfield      #2                  // Field delegate:Lio/grpc/internal/ConnectionClientTransport;
      47: aload_0
      48: aload_3
      49: ldc           #17                 // String authority
      51: invokestatic  #15                 // Method com/google/common/base/Preconditions.checkNotNull:(Ljava/lang/Object;Ljava/lang/Object;)Ljava/lang/Object;
      54: checkcast     #18                 // class java/lang/String
      57: putfield      #1                  // Field authority:Ljava/lang/String;
      60: return

  protected io.grpc.internal.ConnectionClientTransport delegate();
    Code:
       0: aload_0
       1: getfield      #2                  // Field delegate:Lio/grpc/internal/ConnectionClientTransport;
       4: areturn

  public io.grpc.internal.ClientStream newStream(io.grpc.MethodDescriptor<?, ?>, io.grpc.Metadata, io.grpc.CallOptions, io.grpc.ClientStreamTracer[]);
    Code:
       0: aload_3
       1: invokevirtual #19                 // Method io/grpc/CallOptions.getCredentials:()Lio/grpc/CallCredentials;
       4: astore        5
       6: aload         5
       8: ifnonnull     23
      11: aload_0
      12: getfield      #5                  // Field this$0:Lio/grpc/internal/CallCredentialsApplyingTransportFactory;
      15: invokestatic  #20                 // Method io/grpc/internal/CallCredentialsApplyingTransportFactory.access$200:(Lio/grpc/internal/CallCredentialsApplyingTransportFactory;)Lio/grpc/CallCredentials;
      18: astore        5
      20: goto          51
      23: aload_0
      24: getfield      #5                  // Field this$0:Lio/grpc/internal/CallCredentialsApplyingTransportFactory;
      27: invokestatic  #20                 // Method io/grpc/internal/CallCredentialsApplyingTransportFactory.access$200:(Lio/grpc/internal/CallCredentialsApplyingTransportFactory;)Lio/grpc/CallCredentials;
      30: ifnull        51
      33: new           #21                 // class io/grpc/CompositeCallCredentials
      36: dup
      37: aload_0
      38: getfield      #5                  // Field this$0:Lio/grpc/internal/CallCredentialsApplyingTransportFactory;
      41: invokestatic  #20                 // Method io/grpc/internal/CallCredentialsApplyingTransportFactory.access$200:(Lio/grpc/internal/CallCredentialsApplyingTransportFactory;)Lio/grpc/CallCredentials;
      44: aload         5
      46: invokespecial #22                 // Method io/grpc/CompositeCallCredentials."<init>":(Lio/grpc/CallCredentials;Lio/grpc/CallCredentials;)V
      49: astore        5
      51: aload         5
      53: ifnull        178
      56: new           #23                 // class io/grpc/internal/MetadataApplierImpl
      59: dup
      60: aload_0
      61: getfield      #2                  // Field delegate:Lio/grpc/internal/ConnectionClientTransport;
      64: aload_1
      65: aload_2
      66: aload_3
      67: aload_0
      68: getfield      #13                 // Field applierListener:Lio/grpc/internal/MetadataApplierImpl$MetadataApplierListener;
      71: aload         4
      73: invokespecial #24                 // Method io/grpc/internal/MetadataApplierImpl."<init>":(Lio/grpc/internal/ClientTransport;Lio/grpc/MethodDescriptor;Lio/grpc/Metadata;Lio/grpc/CallOptions;Lio/grpc/internal/MetadataApplierImpl$MetadataApplierListener;[Lio/grpc/ClientStreamTracer;)V
      76: astore        6
      78: aload_0
      79: getfield      #4                  // Field pendingApplier:Ljava/util/concurrent/atomic/AtomicInteger;
      82: invokevirtual #25                 // Method java/util/concurrent/atomic/AtomicInteger.incrementAndGet:()I
      85: ifle          111
      88: aload_0
      89: getfield      #13                 // Field applierListener:Lio/grpc/internal/MetadataApplierImpl$MetadataApplierListener;
      92: invokeinterface #26,  1           // InterfaceMethod io/grpc/internal/MetadataApplierImpl$MetadataApplierListener.onComplete:()V
      97: new           #27                 // class io/grpc/internal/FailingClientStream
     100: dup
     101: aload_0
     102: getfield      #28                 // Field shutdownStatus:Lio/grpc/Status;
     105: aload         4
     107: invokespecial #29                 // Method io/grpc/internal/FailingClientStream."<init>":(Lio/grpc/Status;[Lio/grpc/ClientStreamTracer;)V
     110: areturn
     111: new           #30                 // class io/grpc/internal/CallCredentialsApplyingTransportFactory$CallCredentialsApplyingTransport$2
     114: dup
     115: aload_0
     116: aload_1
     117: aload_3
     118: invokespecial #31                 // Method io/grpc/internal/CallCredentialsApplyingTransportFactory$CallCredentialsApplyingTransport$2."<init>":(Lio/grpc/internal/CallCredentialsApplyingTransportFactory$CallCredentialsApplyingTransport;Lio/grpc/MethodDescriptor;Lio/grpc/CallOptions;)V
     121: astore        7
     123: aload         5
     125: aload         7
     127: aload_3
     128: invokevirtual #32                 // Method io/grpc/CallOptions.getExecutor:()Ljava/util/concurrent/Executor;
     131: aload_0
     132: getfield      #5                  // Field this$0:Lio/grpc/internal/CallCredentialsApplyingTransportFactory;
     135: invokestatic  #33                 // Method io/grpc/internal/CallCredentialsApplyingTransportFactory.access$500:(Lio/grpc/internal/CallCredentialsApplyingTransportFactory;)Ljava/util/concurrent/Executor;
     138: invokestatic  #34                 // Method com/google/common/base/MoreObjects.firstNonNull:(Ljava/lang/Object;Ljava/lang/Object;)Ljava/lang/Object;
     141: checkcast     #35                 // class java/util/concurrent/Executor
     144: aload         6
     146: invokevirtual #36                 // Method io/grpc/CallCredentials.applyRequestMetadata:(Lio/grpc/CallCredentials$RequestInfo;Ljava/util/concurrent/Executor;Lio/grpc/CallCredentials$MetadataApplier;)V
     149: goto          172
     152: astore        8
     154: aload         6
     156: getstatic     #38                 // Field io/grpc/Status.UNAUTHENTICATED:Lio/grpc/Status;
     159: ldc           #39                 // String Credentials should use fail() instead of throwing exceptions
     161: invokevirtual #40                 // Method io/grpc/Status.withDescription:(Ljava/lang/String;)Lio/grpc/Status;
     164: aload         8
     166: invokevirtual #41                 // Method io/grpc/Status.withCause:(Ljava/lang/Throwable;)Lio/grpc/Status;
     169: invokevirtual #42                 // Method io/grpc/internal/MetadataApplierImpl.fail:(Lio/grpc/Status;)V
     172: aload         6
     174: invokevirtual #43                 // Method io/grpc/internal/MetadataApplierImpl.returnStream:()Lio/grpc/internal/ClientStream;
     177: areturn
     178: aload_0
     179: getfield      #4                  // Field pendingApplier:Ljava/util/concurrent/atomic/AtomicInteger;
     182: invokevirtual #44                 // Method java/util/concurrent/atomic/AtomicInteger.get:()I
     185: iflt          202
     188: new           #27                 // class io/grpc/internal/FailingClientStream
     191: dup
     192: aload_0
     193: getfield      #28                 // Field shutdownStatus:Lio/grpc/Status;
     196: aload         4
     198: invokespecial #29                 // Method io/grpc/internal/FailingClientStream."<init>":(Lio/grpc/Status;[Lio/grpc/ClientStreamTracer;)V
     201: areturn
     202: aload_0
     203: getfield      #2                  // Field delegate:Lio/grpc/internal/ConnectionClientTransport;
     206: aload_1
     207: aload_2
     208: aload_3
     209: aload         4
     211: invokeinterface #45,  5           // InterfaceMethod io/grpc/internal/ConnectionClientTransport.newStream:(Lio/grpc/MethodDescriptor;Lio/grpc/Metadata;Lio/grpc/CallOptions;[Lio/grpc/ClientStreamTracer;)Lio/grpc/internal/ClientStream;
     216: areturn
    Exception table:
       from    to  target type
         123   149   152   Class java/lang/Throwable

  public void shutdown(io.grpc.Status);
    Code:
       0: aload_1
       1: ldc           #46                 // String status
       3: invokestatic  #15                 // Method com/google/common/base/Preconditions.checkNotNull:(Ljava/lang/Object;Ljava/lang/Object;)Ljava/lang/Object;
       6: pop
       7: aload_0
       8: dup
       9: astore_2
      10: monitorenter
      11: aload_0
      12: getfield      #4                  // Field pendingApplier:Ljava/util/concurrent/atomic/AtomicInteger;
      15: invokevirtual #44                 // Method java/util/concurrent/atomic/AtomicInteger.get:()I
      18: ifge          39
      21: aload_0
      22: aload_1
      23: putfield      #28                 // Field shutdownStatus:Lio/grpc/Status;
      26: aload_0
      27: getfield      #4                  // Field pendingApplier:Ljava/util/concurrent/atomic/AtomicInteger;
      30: ldc           #47                 // int 2147483647
      32: invokevirtual #48                 // Method java/util/concurrent/atomic/AtomicInteger.addAndGet:(I)I
      35: pop
      36: goto          42
      39: aload_2
      40: monitorexit
      41: return
      42: aload_0
      43: getfield      #4                  // Field pendingApplier:Ljava/util/concurrent/atomic/AtomicInteger;
      46: invokevirtual #44                 // Method java/util/concurrent/atomic/AtomicInteger.get:()I
      49: ifeq          60
      52: aload_0
      53: aload_1
      54: putfield      #49                 // Field savedShutdownStatus:Lio/grpc/Status;
      57: aload_2
      58: monitorexit
      59: return
      60: aload_2
      61: monitorexit
      62: goto          70
      65: astore_3
      66: aload_2
      67: monitorexit
      68: aload_3
      69: athrow
      70: aload_0
      71: aload_1
      72: invokespecial #50                 // Method io/grpc/internal/ForwardingConnectionClientTransport.shutdown:(Lio/grpc/Status;)V
      75: return
    Exception table:
       from    to  target type
          11    41    65   any
          42    59    65   any
          60    62    65   any
          65    68    65   any

  public void shutdownNow(io.grpc.Status);
    Code:
       0: aload_1
       1: ldc           #46                 // String status
       3: invokestatic  #15                 // Method com/google/common/base/Preconditions.checkNotNull:(Ljava/lang/Object;Ljava/lang/Object;)Ljava/lang/Object;
       6: pop
       7: aload_0
       8: dup
       9: astore_2
      10: monitorenter
      11: aload_0
      12: getfield      #4                  // Field pendingApplier:Ljava/util/concurrent/atomic/AtomicInteger;
      15: invokevirtual #44                 // Method java/util/concurrent/atomic/AtomicInteger.get:()I
      18: ifge          39
      21: aload_0
      22: aload_1
      23: putfield      #28                 // Field shutdownStatus:Lio/grpc/Status;
      26: aload_0
      27: getfield      #4                  // Field pendingApplier:Ljava/util/concurrent/atomic/AtomicInteger;
      30: ldc           #47                 // int 2147483647
      32: invokevirtual #48                 // Method java/util/concurrent/atomic/AtomicInteger.addAndGet:(I)I
      35: pop
      36: goto          49
      39: aload_0
      40: getfield      #51                 // Field savedShutdownNowStatus:Lio/grpc/Status;
      43: ifnull        49
      46: aload_2
      47: monitorexit
      48: return
      49: aload_0
      50: getfield      #4                  // Field pendingApplier:Ljava/util/concurrent/atomic/AtomicInteger;
      53: invokevirtual #44                 // Method java/util/concurrent/atomic/AtomicInteger.get:()I
      56: ifeq          67
      59: aload_0
      60: aload_1
      61: putfield      #51                 // Field savedShutdownNowStatus:Lio/grpc/Status;
      64: aload_2
      65: monitorexit
      66: return
      67: aload_2
      68: monitorexit
      69: goto          77
      72: astore_3
      73: aload_2
      74: monitorexit
      75: aload_3
      76: athrow
      77: aload_0
      78: aload_1
      79: invokespecial #52                 // Method io/grpc/internal/ForwardingConnectionClientTransport.shutdownNow:(Lio/grpc/Status;)V
      82: return
    Exception table:
       from    to  target type
          11    48    72   any
          49    66    72   any
          67    69    72   any
          72    75    72   any

  private void maybeShutdown();
    Code:
       0: aload_0
       1: dup
       2: astore_3
       3: monitorenter
       4: aload_0
       5: getfield      #4                  // Field pendingApplier:Ljava/util/concurrent/atomic/AtomicInteger;
       8: invokevirtual #44                 // Method java/util/concurrent/atomic/AtomicInteger.get:()I
      11: ifeq          17
      14: aload_3
      15: monitorexit
      16: return
      17: aload_0
      18: getfield      #49                 // Field savedShutdownStatus:Lio/grpc/Status;
      21: astore_1
      22: aload_0
      23: getfield      #51                 // Field savedShutdownNowStatus:Lio/grpc/Status;
      26: astore_2
      27: aload_0
      28: aconst_null
      29: putfield      #49                 // Field savedShutdownStatus:Lio/grpc/Status;
      32: aload_0
      33: aconst_null
      34: putfield      #51                 // Field savedShutdownNowStatus:Lio/grpc/Status;
      37: aload_3
      38: monitorexit
      39: goto          49
      42: astore        4
      44: aload_3
      45: monitorexit
      46: aload         4
      48: athrow
      49: aload_1
      50: ifnull        58
      53: aload_0
      54: aload_1
      55: invokespecial #50                 // Method io/grpc/internal/ForwardingConnectionClientTransport.shutdown:(Lio/grpc/Status;)V
      58: aload_2
      59: ifnull        67
      62: aload_0
      63: aload_2
      64: invokespecial #52                 // Method io/grpc/internal/ForwardingConnectionClientTransport.shutdownNow:(Lio/grpc/Status;)V
      67: return
    Exception table:
       from    to  target type
           4    16    42   any
          17    39    42   any
          42    46    42   any

  static java.util.concurrent.atomic.AtomicInteger access$000(io.grpc.internal.CallCredentialsApplyingTransportFactory$CallCredentialsApplyingTransport);
    Code:
       0: aload_0
       1: getfield      #4                  // Field pendingApplier:Ljava/util/concurrent/atomic/AtomicInteger;
       4: areturn

  static void access$100(io.grpc.internal.CallCredentialsApplyingTransportFactory$CallCredentialsApplyingTransport);
    Code:
       0: aload_0
       1: invokespecial #3                  // Method maybeShutdown:()V
       4: return

  static io.grpc.internal.ConnectionClientTransport access$300(io.grpc.internal.CallCredentialsApplyingTransportFactory$CallCredentialsApplyingTransport);
    Code:
       0: aload_0
       1: getfield      #2                  // Field delegate:Lio/grpc/internal/ConnectionClientTransport;
       4: areturn

  static java.lang.String access$400(io.grpc.internal.CallCredentialsApplyingTransportFactory$CallCredentialsApplyingTransport);
    Code:
       0: aload_0
       1: getfield      #1                  // Field authority:Ljava/lang/String;
       4: areturn
}
