Compiled from "ManagedChannelImpl.java"
class io.grpc.internal.ManagedChannelImpl$4 extends io.grpc.internal.ForwardingNameResolver {
  final java.lang.String val$overrideAuthority;

  io.grpc.internal.ManagedChannelImpl$4(io.grpc.NameResolver, java.lang.String);
    Code:
       0: aload_0
       1: aload_2
       2: putfield      #1                  // Field val$overrideAuthority:Ljava/lang/String;
       5: aload_0
       6: aload_1
       7: invokespecial #2                  // Method io/grpc/internal/ForwardingNameResolver."<init>":(Lio/grpc/NameResolver;)V
      10: return

  public java.lang.String getServiceAuthority();
    Code:
       0: aload_0
       1: getfield      #1                  // Field val$overrideAuthority:Ljava/lang/String;
       4: areturn
}
