Compiled from "ManagedChannelImpl.java"
class io.grpc.internal.ManagedChannelImpl$RealChannel$4 implements java.lang.Runnable {
  final io.grpc.internal.ManagedChannelImpl$RealChannel$PendingCall val$pendingCall;

  final io.grpc.internal.ManagedChannelImpl$RealChannel this$1;

  io.grpc.internal.ManagedChannelImpl$RealChannel$4(io.grpc.internal.ManagedChannelImpl$RealChannel, io.grpc.internal.ManagedChannelImpl$RealChannel$PendingCall);
    Code:
       0: aload_0
       1: aload_1
       2: putfield      #1                  // Field this$1:Lio/grpc/internal/ManagedChannelImpl$RealChannel;
       5: aload_0
       6: aload_2
       7: putfield      #2                  // Field val$pendingCall:Lio/grpc/internal/ManagedChannelImpl$RealChannel$PendingCall;
      10: aload_0
      11: invokespecial #3                  // Method java/lang/Object."<init>":()V
      14: return

  public void run();
    Code:
       0: aload_0
       1: getfield      #1                  // Field this$1:Lio/grpc/internal/ManagedChannelImpl$RealChannel;
       4: invokestatic  #4                  // Method io/grpc/internal/ManagedChannelImpl$RealChannel.access$3000:(Lio/grpc/internal/ManagedChannelImpl$RealChannel;)Ljava/util/concurrent/atomic/AtomicReference;
       7: invokevirtual #5                  // Method java/util/concurrent/atomic/AtomicReference.get:()Ljava/lang/Object;
      10: invokestatic  #6                  // Method io/grpc/internal/ManagedChannelImpl.access$3500:()Lio/grpc/InternalConfigSelector;
      13: if_acmpne     94
      16: aload_0
      17: getfield      #1                  // Field this$1:Lio/grpc/internal/ManagedChannelImpl$RealChannel;
      20: getfield      #7                  // Field io/grpc/internal/ManagedChannelImpl$RealChannel.this$0:Lio/grpc/internal/ManagedChannelImpl;
      23: invokestatic  #8                  // Method io/grpc/internal/ManagedChannelImpl.access$4200:(Lio/grpc/internal/ManagedChannelImpl;)Ljava/util/Collection;
      26: ifnonnull     71
      29: aload_0
      30: getfield      #1                  // Field this$1:Lio/grpc/internal/ManagedChannelImpl$RealChannel;
      33: getfield      #7                  // Field io/grpc/internal/ManagedChannelImpl$RealChannel.this$0:Lio/grpc/internal/ManagedChannelImpl;
      36: new           #9                  // class java/util/LinkedHashSet
      39: dup
      40: invokespecial #10                 // Method java/util/LinkedHashSet."<init>":()V
      43: invokestatic  #11                 // Method io/grpc/internal/ManagedChannelImpl.access$4202:(Lio/grpc/internal/ManagedChannelImpl;Ljava/util/Collection;)Ljava/util/Collection;
      46: pop
      47: aload_0
      48: getfield      #1                  // Field this$1:Lio/grpc/internal/ManagedChannelImpl$RealChannel;
      51: getfield      #7                  // Field io/grpc/internal/ManagedChannelImpl$RealChannel.this$0:Lio/grpc/internal/ManagedChannelImpl;
      54: getfield      #12                 // Field io/grpc/internal/ManagedChannelImpl.inUseStateAggregator:Lio/grpc/internal/InUseStateAggregator;
      57: aload_0
      58: getfield      #1                  // Field this$1:Lio/grpc/internal/ManagedChannelImpl$RealChannel;
      61: getfield      #7                  // Field io/grpc/internal/ManagedChannelImpl$RealChannel.this$0:Lio/grpc/internal/ManagedChannelImpl;
      64: invokestatic  #13                 // Method io/grpc/internal/ManagedChannelImpl.access$4300:(Lio/grpc/internal/ManagedChannelImpl;)Ljava/lang/Object;
      67: iconst_1
      68: invokevirtual #14                 // Method io/grpc/internal/InUseStateAggregator.updateObjectInUse:(Ljava/lang/Object;Z)V
      71: aload_0
      72: getfield      #1                  // Field this$1:Lio/grpc/internal/ManagedChannelImpl$RealChannel;
      75: getfield      #7                  // Field io/grpc/internal/ManagedChannelImpl$RealChannel.this$0:Lio/grpc/internal/ManagedChannelImpl;
      78: invokestatic  #8                  // Method io/grpc/internal/ManagedChannelImpl.access$4200:(Lio/grpc/internal/ManagedChannelImpl;)Ljava/util/Collection;
      81: aload_0
      82: getfield      #2                  // Field val$pendingCall:Lio/grpc/internal/ManagedChannelImpl$RealChannel$PendingCall;
      85: invokeinterface #15,  2           // InterfaceMethod java/util/Collection.add:(Ljava/lang/Object;)Z
      90: pop
      91: goto          101
      94: aload_0
      95: getfield      #2                  // Field val$pendingCall:Lio/grpc/internal/ManagedChannelImpl$RealChannel$PendingCall;
      98: invokevirtual #16                 // Method io/grpc/internal/ManagedChannelImpl$RealChannel$PendingCall.reprocess:()V
     101: return
}
