Compiled from "ManagedChannelImpl.java"
final class io.grpc.internal.ManagedChannelImpl$1PanicSubchannelPicker extends io.grpc.LoadBalancer$SubchannelPicker {
  private final io.grpc.LoadBalancer$PickResult panicPickResult;

  final java.lang.Throwable val$t;

  final io.grpc.internal.ManagedChannelImpl this$0;

  io.grpc.internal.ManagedChannelImpl$1PanicSubchannelPicker();
    Code:
       0: aload_0
       1: aload_1
       2: putfield      #1                  // Field this$0:Lio/grpc/internal/ManagedChannelImpl;
       5: aload_0
       6: aload_2
       7: putfield      #2                  // Field val$t:Ljava/lang/Throwable;
      10: aload_0
      11: invokespecial #3                  // Method io/grpc/LoadBalancer$SubchannelPicker."<init>":()V
      14: aload_0
      15: getstatic     #4                  // Field io/grpc/Status.INTERNAL:Lio/grpc/Status;
      18: ldc           #5                  // String Panic! This is a bug!
      20: invokevirtual #6                  // Method io/grpc/Status.withDescription:(Ljava/lang/String;)Lio/grpc/Status;
      23: aload_0
      24: getfield      #2                  // Field val$t:Ljava/lang/Throwable;
      27: invokevirtual #7                  // Method io/grpc/Status.withCause:(Ljava/lang/Throwable;)Lio/grpc/Status;
      30: invokestatic  #8                  // Method io/grpc/LoadBalancer$PickResult.withDrop:(Lio/grpc/Status;)Lio/grpc/LoadBalancer$PickResult;
      33: putfield      #9                  // Field panicPickResult:Lio/grpc/LoadBalancer$PickResult;
      36: return

  public io.grpc.LoadBalancer$PickResult pickSubchannel(io.grpc.LoadBalancer$PickSubchannelArgs);
    Code:
       0: aload_0
       1: getfield      #9                  // Field panicPickResult:Lio/grpc/LoadBalancer$PickResult;
       4: areturn

  public java.lang.String toString();
    Code:
       0: ldc           #10                 // class io/grpc/internal/ManagedChannelImpl$1PanicSubchannelPicker
       2: invokestatic  #11                 // Method com/google/common/base/MoreObjects.toStringHelper:(Ljava/lang/Class;)Lcom/google/common/base/MoreObjects$ToStringHelper;
       5: ldc           #12                 // String panicPickResult
       7: aload_0
       8: getfield      #9                  // Field panicPickResult:Lio/grpc/LoadBalancer$PickResult;
      11: invokevirtual #13                 // Method com/google/common/base/MoreObjects$ToStringHelper.add:(Ljava/lang/String;Ljava/lang/Object;)Lcom/google/common/base/MoreObjects$ToStringHelper;
      14: invokevirtual #14                 // Method com/google/common/base/MoreObjects$ToStringHelper.toString:()Ljava/lang/String;
      17: areturn
}
