Compiled from "ManagedChannelImpl.java"
class io.grpc.internal.ManagedChannelImpl$3 implements java.util.concurrent.Executor {
  final io.grpc.internal.ManagedChannelImpl this$0;

  io.grpc.internal.ManagedChannelImpl$3(io.grpc.internal.ManagedChannelImpl);
    Code:
       0: aload_0
       1: aload_1
       2: putfield      #1                  // Field this$0:Lio/grpc/internal/ManagedChannelImpl;
       5: aload_0
       6: invokespecial #2                  // Method java/lang/Object."<init>":()V
       9: return

  public void execute(java.lang.Runnable);
    Code:
       0: aload_0
       1: getfield      #1                  // Field this$0:Lio/grpc/internal/ManagedChannelImpl;
       4: invokestatic  #3                  // Method io/grpc/internal/ManagedChannelImpl.access$2700:(Lio/grpc/internal/ManagedChannelImpl;)Lio/grpc/internal/ManagedChannelImpl$ExecutorHolder;
       7: invokevirtual #4                  // Method io/grpc/internal/ManagedChannelImpl$ExecutorHolder.getExecutor:()Ljava/util/concurrent/Executor;
      10: aload_1
      11: invokeinterface #5,  2            // InterfaceMethod java/util/concurrent/Executor.execute:(Ljava/lang/Runnable;)V
      16: return
}
