Compiled from "MessageFramer.java"
final class io.grpc.internal.MessageFramer$BufferChainOutputStream extends java.io.OutputStream {
  private final java.util.List<io.grpc.internal.WritableBuffer> bufferList;

  private io.grpc.internal.WritableBuffer current;

  final io.grpc.internal.MessageFramer this$0;

  private io.grpc.internal.MessageFramer$BufferChainOutputStream(io.grpc.internal.MessageFramer);
    Code:
       0: aload_0
       1: aload_1
       2: putfield      #4                  // Field this$0:Lio/grpc/internal/MessageFramer;
       5: aload_0
       6: invokespecial #5                  // Method java/io/OutputStream."<init>":()V
       9: aload_0
      10: new           #6                  // class java/util/ArrayList
      13: dup
      14: invokespecial #7                  // Method java/util/ArrayList."<init>":()V
      17: putfield      #1                  // Field bufferList:Ljava/util/List;
      20: return

  public void write(int) throws java.io.IOException;
    Code:
       0: aload_0
       1: getfield      #8                  // Field current:Lio/grpc/internal/WritableBuffer;
       4: ifnull        31
       7: aload_0
       8: getfield      #8                  // Field current:Lio/grpc/internal/WritableBuffer;
      11: invokeinterface #9,  1            // InterfaceMethod io/grpc/internal/WritableBuffer.writableBytes:()I
      16: ifle          31
      19: aload_0
      20: getfield      #8                  // Field current:Lio/grpc/internal/WritableBuffer;
      23: iload_1
      24: i2b
      25: invokeinterface #10,  2           // InterfaceMethod io/grpc/internal/WritableBuffer.write:(B)V
      30: return
      31: iconst_1
      32: newarray       byte
      34: dup
      35: iconst_0
      36: iload_1
      37: i2b
      38: bastore
      39: astore_2
      40: aload_0
      41: aload_2
      42: iconst_0
      43: iconst_1
      44: invokevirtual #11                 // Method write:([BII)V
      47: return

  public void write(byte[], int, int);
    Code:
       0: aload_0
       1: getfield      #8                  // Field current:Lio/grpc/internal/WritableBuffer;
       4: ifnonnull     38
       7: aload_0
       8: aload_0
       9: getfield      #4                  // Field this$0:Lio/grpc/internal/MessageFramer;
      12: invokestatic  #12                 // Method io/grpc/internal/MessageFramer.access$500:(Lio/grpc/internal/MessageFramer;)Lio/grpc/internal/WritableBufferAllocator;
      15: iload_3
      16: invokeinterface #13,  2           // InterfaceMethod io/grpc/internal/WritableBufferAllocator.allocate:(I)Lio/grpc/internal/WritableBuffer;
      21: putfield      #8                  // Field current:Lio/grpc/internal/WritableBuffer;
      24: aload_0
      25: getfield      #1                  // Field bufferList:Ljava/util/List;
      28: aload_0
      29: getfield      #8                  // Field current:Lio/grpc/internal/WritableBuffer;
      32: invokeinterface #14,  2           // InterfaceMethod java/util/List.add:(Ljava/lang/Object;)Z
      37: pop
      38: iload_3
      39: ifle          140
      42: iload_3
      43: aload_0
      44: getfield      #8                  // Field current:Lio/grpc/internal/WritableBuffer;
      47: invokeinterface #9,  1            // InterfaceMethod io/grpc/internal/WritableBuffer.writableBytes:()I
      52: invokestatic  #15                 // Method java/lang/Math.min:(II)I
      55: istore        4
      57: iload         4
      59: ifne          114
      62: iload_3
      63: aload_0
      64: getfield      #8                  // Field current:Lio/grpc/internal/WritableBuffer;
      67: invokeinterface #16,  1           // InterfaceMethod io/grpc/internal/WritableBuffer.readableBytes:()I
      72: iconst_2
      73: imul
      74: invokestatic  #17                 // Method java/lang/Math.max:(II)I
      77: istore        5
      79: aload_0
      80: aload_0
      81: getfield      #4                  // Field this$0:Lio/grpc/internal/MessageFramer;
      84: invokestatic  #12                 // Method io/grpc/internal/MessageFramer.access$500:(Lio/grpc/internal/MessageFramer;)Lio/grpc/internal/WritableBufferAllocator;
      87: iload         5
      89: invokeinterface #13,  2           // InterfaceMethod io/grpc/internal/WritableBufferAllocator.allocate:(I)Lio/grpc/internal/WritableBuffer;
      94: putfield      #8                  // Field current:Lio/grpc/internal/WritableBuffer;
      97: aload_0
      98: getfield      #1                  // Field bufferList:Ljava/util/List;
     101: aload_0
     102: getfield      #8                  // Field current:Lio/grpc/internal/WritableBuffer;
     105: invokeinterface #14,  2           // InterfaceMethod java/util/List.add:(Ljava/lang/Object;)Z
     110: pop
     111: goto          137
     114: aload_0
     115: getfield      #8                  // Field current:Lio/grpc/internal/WritableBuffer;
     118: aload_1
     119: iload_2
     120: iload         4
     122: invokeinterface #18,  4           // InterfaceMethod io/grpc/internal/WritableBuffer.write:([BII)V
     127: iload_2
     128: iload         4
     130: iadd
     131: istore_2
     132: iload_3
     133: iload         4
     135: isub
     136: istore_3
     137: goto          38
     140: return

  private int readableBytes();
    Code:
       0: iconst_0
       1: istore_1
       2: aload_0
       3: getfield      #1                  // Field bufferList:Ljava/util/List;
       6: invokeinterface #19,  1           // InterfaceMethod java/util/List.iterator:()Ljava/util/Iterator;
      11: astore_2
      12: aload_2
      13: invokeinterface #20,  1           // InterfaceMethod java/util/Iterator.hasNext:()Z
      18: ifeq          43
      21: aload_2
      22: invokeinterface #21,  1           // InterfaceMethod java/util/Iterator.next:()Ljava/lang/Object;
      27: checkcast     #22                 // class io/grpc/internal/WritableBuffer
      30: astore_3
      31: iload_1
      32: aload_3
      33: invokeinterface #16,  1           // InterfaceMethod io/grpc/internal/WritableBuffer.readableBytes:()I
      38: iadd
      39: istore_1
      40: goto          12
      43: iload_1
      44: ireturn

  io.grpc.internal.MessageFramer$BufferChainOutputStream(io.grpc.internal.MessageFramer, io.grpc.internal.MessageFramer$1);
    Code:
       0: aload_0
       1: aload_1
       2: invokespecial #3                  // Method "<init>":(Lio/grpc/internal/MessageFramer;)V
       5: return

  static int access$200(io.grpc.internal.MessageFramer$BufferChainOutputStream);
    Code:
       0: aload_0
       1: invokespecial #2                  // Method readableBytes:()I
       4: ireturn

  static java.util.List access$300(io.grpc.internal.MessageFramer$BufferChainOutputStream);
    Code:
       0: aload_0
       1: getfield      #1                  // Field bufferList:Ljava/util/List;
       4: areturn
}
