Compiled from "MigratingThreadDeframer.java"
class io.grpc.internal.MigratingThreadDeframer$DeframeMessageProducer implements io.grpc.internal.StreamListener$MessageProducer,java.io.Closeable {
  final io.grpc.internal.MigratingThreadDeframer this$0;

  io.grpc.internal.MigratingThreadDeframer$DeframeMessageProducer(io.grpc.internal.MigratingThreadDeframer);
    Code:
       0: aload_0
       1: aload_1
       2: putfield      #1                  // Field this$0:Lio/grpc/internal/MigratingThreadDeframer;
       5: aload_0
       6: invokespecial #2                  // Method java/lang/Object."<init>":()V
       9: return

  public java.io.InputStream next();
    Code:
       0: aload_0
       1: getfield      #1                  // Field this$0:Lio/grpc/internal/MigratingThreadDeframer;
       4: invokestatic  #3                  // Method io/grpc/internal/MigratingThreadDeframer.access$500:(Lio/grpc/internal/MigratingThreadDeframer;)Lio/grpc/internal/ApplicationThreadDeframerListener;
       7: invokevirtual #4                  // Method io/grpc/internal/ApplicationThreadDeframerListener.messageReadQueuePoll:()Ljava/io/InputStream;
      10: astore_1
      11: aload_1
      12: ifnull        17
      15: aload_1
      16: areturn
      17: aload_0
      18: getfield      #1                  // Field this$0:Lio/grpc/internal/MigratingThreadDeframer;
      21: invokestatic  #5                  // Method io/grpc/internal/MigratingThreadDeframer.access$600:(Lio/grpc/internal/MigratingThreadDeframer;)Ljava/lang/Object;
      24: dup
      25: astore_3
      26: monitorenter
      27: aload_0
      28: getfield      #1                  // Field this$0:Lio/grpc/internal/MigratingThreadDeframer;
      31: invokestatic  #6                  // Method io/grpc/internal/MigratingThreadDeframer.access$900:(Lio/grpc/internal/MigratingThreadDeframer;)Ljava/util/Queue;
      34: invokeinterface #7,  1            // InterfaceMethod java/util/Queue.poll:()Ljava/lang/Object;
      39: checkcast     #8                  // class io/grpc/internal/MigratingThreadDeframer$Op
      42: astore_2
      43: aload_2
      44: ifnonnull     104
      47: aload_0
      48: getfield      #1                  // Field this$0:Lio/grpc/internal/MigratingThreadDeframer;
      51: invokestatic  #9                  // Method io/grpc/internal/MigratingThreadDeframer.access$400:(Lio/grpc/internal/MigratingThreadDeframer;)Lio/grpc/internal/MessageDeframer;
      54: invokevirtual #10                 // Method io/grpc/internal/MessageDeframer.hasPendingDeliveries:()Z
      57: ifeq          91
      60: ldc           #11                 // String MigratingThreadDeframer.deframerOnTransportThread
      62: invokestatic  #12                 // Method io/perfmark/PerfMark.event:(Ljava/lang/String;)V
      65: aload_0
      66: getfield      #1                  // Field this$0:Lio/grpc/internal/MigratingThreadDeframer;
      69: invokestatic  #13                 // Method io/grpc/internal/MigratingThreadDeframer.access$700:(Lio/grpc/internal/MigratingThreadDeframer;)Lio/grpc/internal/MigratingThreadDeframer$MigratingDeframerListener;
      72: aload_0
      73: getfield      #1                  // Field this$0:Lio/grpc/internal/MigratingThreadDeframer;
      76: invokestatic  #14                 // Method io/grpc/internal/MigratingThreadDeframer.access$100:(Lio/grpc/internal/MigratingThreadDeframer;)Lio/grpc/internal/MessageDeframer$Listener;
      79: invokevirtual #15                 // Method io/grpc/internal/MigratingThreadDeframer$MigratingDeframerListener.setDelegate:(Lio/grpc/internal/MessageDeframer$Listener;)V
      82: aload_0
      83: getfield      #1                  // Field this$0:Lio/grpc/internal/MigratingThreadDeframer;
      86: iconst_1
      87: invokestatic  #16                 // Method io/grpc/internal/MigratingThreadDeframer.access$802:(Lio/grpc/internal/MigratingThreadDeframer;Z)Z
      90: pop
      91: aload_0
      92: getfield      #1                  // Field this$0:Lio/grpc/internal/MigratingThreadDeframer;
      95: iconst_0
      96: invokestatic  #17                 // Method io/grpc/internal/MigratingThreadDeframer.access$1002:(Lio/grpc/internal/MigratingThreadDeframer;Z)Z
      99: pop
     100: aconst_null
     101: aload_3
     102: monitorexit
     103: areturn
     104: aload_3
     105: monitorexit
     106: goto          116
     109: astore        4
     111: aload_3
     112: monitorexit
     113: aload         4
     115: athrow
     116: aload_2
     117: iconst_0
     118: invokeinterface #18,  2           // InterfaceMethod io/grpc/internal/MigratingThreadDeframer$Op.run:(Z)V
     123: goto          0
    Exception table:
       from    to  target type
          27   103   109   any
         104   106   109   any
         109   113   109   any

  public void close();
    Code:
       0: aload_0
       1: getfield      #1                  // Field this$0:Lio/grpc/internal/MigratingThreadDeframer;
       4: invokestatic  #5                  // Method io/grpc/internal/MigratingThreadDeframer.access$600:(Lio/grpc/internal/MigratingThreadDeframer;)Ljava/lang/Object;
       7: dup
       8: astore_2
       9: monitorenter
      10: aload_0
      11: getfield      #1                  // Field this$0:Lio/grpc/internal/MigratingThreadDeframer;
      14: invokestatic  #6                  // Method io/grpc/internal/MigratingThreadDeframer.access$900:(Lio/grpc/internal/MigratingThreadDeframer;)Ljava/util/Queue;
      17: invokeinterface #7,  1            // InterfaceMethod java/util/Queue.poll:()Ljava/lang/Object;
      22: checkcast     #8                  // class io/grpc/internal/MigratingThreadDeframer$Op
      25: astore_1
      26: aload_1
      27: ifnull        37
      30: aload_1
      31: instanceof    #19                 // class java/io/Closeable
      34: ifeq          10
      37: aload_1
      38: ifnonnull     53
      41: aload_0
      42: getfield      #1                  // Field this$0:Lio/grpc/internal/MigratingThreadDeframer;
      45: iconst_0
      46: invokestatic  #17                 // Method io/grpc/internal/MigratingThreadDeframer.access$1002:(Lio/grpc/internal/MigratingThreadDeframer;Z)Z
      49: pop
      50: aload_2
      51: monitorexit
      52: return
      53: aload_2
      54: monitorexit
      55: goto          63
      58: astore_3
      59: aload_2
      60: monitorexit
      61: aload_3
      62: athrow
      63: aload_1
      64: checkcast     #19                 // class java/io/Closeable
      67: invokestatic  #20                 // Method io/grpc/internal/GrpcUtil.closeQuietly:(Ljava/io/Closeable;)V
      70: goto          0
    Exception table:
       from    to  target type
          10    52    58   any
          53    55    58   any
          58    61    58   any
}
