Compiled from "ServerCallImpl.java"
final class io.grpc.internal.ServerCallImpl$ServerStreamListenerImpl<ReqT> implements io.grpc.internal.ServerStreamListener {
  private final io.grpc.internal.ServerCallImpl<ReqT, ?> call;

  private final io.grpc.ServerCall$Listener<ReqT> listener;

  private final io.grpc.Context$CancellableContext context;

  public io.grpc.internal.ServerCallImpl$ServerStreamListenerImpl(io.grpc.internal.ServerCallImpl<ReqT, ?>, io.grpc.ServerCall$Listener<ReqT>, io.grpc.Context$CancellableContext);
    Code:
       0: aload_0
       1: invokespecial #2                  // Method java/lang/Object."<init>":()V
       4: aload_0
       5: aload_1
       6: ldc           #3                  // String call
       8: invokestatic  #4                  // Method com/google/common/base/Preconditions.checkNotNull:(Ljava/lang/Object;Ljava/lang/Object;)Ljava/lang/Object;
      11: checkcast     #5                  // class io/grpc/internal/ServerCallImpl
      14: putfield      #1                  // Field call:Lio/grpc/internal/ServerCallImpl;
      17: aload_0
      18: aload_2
      19: ldc           #6                  // String listener must not be null
      21: invokestatic  #4                  // Method com/google/common/base/Preconditions.checkNotNull:(Ljava/lang/Object;Ljava/lang/Object;)Ljava/lang/Object;
      24: checkcast     #7                  // class io/grpc/ServerCall$Listener
      27: putfield      #8                  // Field listener:Lio/grpc/ServerCall$Listener;
      30: aload_0
      31: aload_3
      32: ldc           #9                  // String context
      34: invokestatic  #4                  // Method com/google/common/base/Preconditions.checkNotNull:(Ljava/lang/Object;Ljava/lang/Object;)Ljava/lang/Object;
      37: checkcast     #10                 // class io/grpc/Context$CancellableContext
      40: putfield      #11                 // Field context:Lio/grpc/Context$CancellableContext;
      43: aload_0
      44: getfield      #11                 // Field context:Lio/grpc/Context$CancellableContext;
      47: new           #12                 // class io/grpc/internal/ServerCallImpl$ServerStreamListenerImpl$1
      50: dup
      51: aload_0
      52: invokespecial #13                 // Method io/grpc/internal/ServerCallImpl$ServerStreamListenerImpl$1."<init>":(Lio/grpc/internal/ServerCallImpl$ServerStreamListenerImpl;)V
      55: invokestatic  #14                 // Method com/google/common/util/concurrent/MoreExecutors.directExecutor:()Ljava/util/concurrent/Executor;
      58: invokevirtual #15                 // Method io/grpc/Context$CancellableContext.addListener:(Lio/grpc/Context$CancellationListener;Ljava/util/concurrent/Executor;)V
      61: return

  public void messagesAvailable(io.grpc.internal.StreamListener$MessageProducer);
    Code:
       0: ldc           #16                 // String ServerStreamListener.messagesAvailable
       2: aload_0
       3: getfield      #1                  // Field call:Lio/grpc/internal/ServerCallImpl;
       6: invokestatic  #17                 // Method io/grpc/internal/ServerCallImpl.access$200:(Lio/grpc/internal/ServerCallImpl;)Lio/perfmark/Tag;
       9: invokestatic  #18                 // Method io/perfmark/PerfMark.startTask:(Ljava/lang/String;Lio/perfmark/Tag;)V
      12: aload_0
      13: aload_1
      14: invokespecial #19                 // Method messagesAvailableInternal:(Lio/grpc/internal/StreamListener$MessageProducer;)V
      17: ldc           #16                 // String ServerStreamListener.messagesAvailable
      19: aload_0
      20: getfield      #1                  // Field call:Lio/grpc/internal/ServerCallImpl;
      23: invokestatic  #17                 // Method io/grpc/internal/ServerCallImpl.access$200:(Lio/grpc/internal/ServerCallImpl;)Lio/perfmark/Tag;
      26: invokestatic  #20                 // Method io/perfmark/PerfMark.stopTask:(Ljava/lang/String;Lio/perfmark/Tag;)V
      29: goto          47
      32: astore_2
      33: ldc           #16                 // String ServerStreamListener.messagesAvailable
      35: aload_0
      36: getfield      #1                  // Field call:Lio/grpc/internal/ServerCallImpl;
      39: invokestatic  #17                 // Method io/grpc/internal/ServerCallImpl.access$200:(Lio/grpc/internal/ServerCallImpl;)Lio/perfmark/Tag;
      42: invokestatic  #20                 // Method io/perfmark/PerfMark.stopTask:(Ljava/lang/String;Lio/perfmark/Tag;)V
      45: aload_2
      46: athrow
      47: return
    Exception table:
       from    to  target type
          12    17    32   any

  private void messagesAvailableInternal(io.grpc.internal.StreamListener$MessageProducer);
    Code:
       0: aload_0
       1: getfield      #1                  // Field call:Lio/grpc/internal/ServerCallImpl;
       4: invokestatic  #21                 // Method io/grpc/internal/ServerCallImpl.access$100:(Lio/grpc/internal/ServerCallImpl;)Z
       7: ifeq          15
      10: aload_1
      11: invokestatic  #22                 // Method io/grpc/internal/GrpcUtil.closeQuietly:(Lio/grpc/internal/StreamListener$MessageProducer;)V
      14: return
      15: aload_1
      16: invokeinterface #23,  1           // InterfaceMethod io/grpc/internal/StreamListener$MessageProducer.next:()Ljava/io/InputStream;
      21: dup
      22: astore_2
      23: ifnull        61
      26: aload_0
      27: getfield      #8                  // Field listener:Lio/grpc/ServerCall$Listener;
      30: aload_0
      31: getfield      #1                  // Field call:Lio/grpc/internal/ServerCallImpl;
      34: invokestatic  #24                 // Method io/grpc/internal/ServerCallImpl.access$300:(Lio/grpc/internal/ServerCallImpl;)Lio/grpc/MethodDescriptor;
      37: aload_2
      38: invokevirtual #25                 // Method io/grpc/MethodDescriptor.parseRequest:(Ljava/io/InputStream;)Ljava/lang/Object;
      41: invokevirtual #26                 // Method io/grpc/ServerCall$Listener.onMessage:(Ljava/lang/Object;)V
      44: goto          54
      47: astore_3
      48: aload_2
      49: invokestatic  #28                 // Method io/grpc/internal/GrpcUtil.closeQuietly:(Ljava/io/Closeable;)V
      52: aload_3
      53: athrow
      54: aload_2
      55: invokevirtual #29                 // Method java/io/InputStream.close:()V
      58: goto          15
      61: goto          82
      64: astore_3
      65: aload_1
      66: invokestatic  #22                 // Method io/grpc/internal/GrpcUtil.closeQuietly:(Lio/grpc/internal/StreamListener$MessageProducer;)V
      69: aload_3
      70: invokestatic  #30                 // Method com/google/common/base/Throwables.throwIfUnchecked:(Ljava/lang/Throwable;)V
      73: new           #31                 // class java/lang/RuntimeException
      76: dup
      77: aload_3
      78: invokespecial #32                 // Method java/lang/RuntimeException."<init>":(Ljava/lang/Throwable;)V
      81: athrow
      82: return
    Exception table:
       from    to  target type
          26    44    47   Class java/lang/Throwable
          15    61    64   Class java/lang/Throwable

  public void halfClosed();
    Code:
       0: ldc           #33                 // String ServerStreamListener.halfClosed
       2: aload_0
       3: getfield      #1                  // Field call:Lio/grpc/internal/ServerCallImpl;
       6: invokestatic  #17                 // Method io/grpc/internal/ServerCallImpl.access$200:(Lio/grpc/internal/ServerCallImpl;)Lio/perfmark/Tag;
       9: invokestatic  #18                 // Method io/perfmark/PerfMark.startTask:(Ljava/lang/String;Lio/perfmark/Tag;)V
      12: aload_0
      13: getfield      #1                  // Field call:Lio/grpc/internal/ServerCallImpl;
      16: invokestatic  #21                 // Method io/grpc/internal/ServerCallImpl.access$100:(Lio/grpc/internal/ServerCallImpl;)Z
      19: ifeq          35
      22: ldc           #33                 // String ServerStreamListener.halfClosed
      24: aload_0
      25: getfield      #1                  // Field call:Lio/grpc/internal/ServerCallImpl;
      28: invokestatic  #17                 // Method io/grpc/internal/ServerCallImpl.access$200:(Lio/grpc/internal/ServerCallImpl;)Lio/perfmark/Tag;
      31: invokestatic  #20                 // Method io/perfmark/PerfMark.stopTask:(Ljava/lang/String;Lio/perfmark/Tag;)V
      34: return
      35: aload_0
      36: getfield      #8                  // Field listener:Lio/grpc/ServerCall$Listener;
      39: invokevirtual #34                 // Method io/grpc/ServerCall$Listener.onHalfClose:()V
      42: ldc           #33                 // String ServerStreamListener.halfClosed
      44: aload_0
      45: getfield      #1                  // Field call:Lio/grpc/internal/ServerCallImpl;
      48: invokestatic  #17                 // Method io/grpc/internal/ServerCallImpl.access$200:(Lio/grpc/internal/ServerCallImpl;)Lio/perfmark/Tag;
      51: invokestatic  #20                 // Method io/perfmark/PerfMark.stopTask:(Ljava/lang/String;Lio/perfmark/Tag;)V
      54: goto          72
      57: astore_1
      58: ldc           #33                 // String ServerStreamListener.halfClosed
      60: aload_0
      61: getfield      #1                  // Field call:Lio/grpc/internal/ServerCallImpl;
      64: invokestatic  #17                 // Method io/grpc/internal/ServerCallImpl.access$200:(Lio/grpc/internal/ServerCallImpl;)Lio/perfmark/Tag;
      67: invokestatic  #20                 // Method io/perfmark/PerfMark.stopTask:(Ljava/lang/String;Lio/perfmark/Tag;)V
      70: aload_1
      71: athrow
      72: return
    Exception table:
       from    to  target type
          12    22    57   any
          35    42    57   any

  public void closed(io.grpc.Status);
    Code:
       0: ldc           #35                 // String ServerStreamListener.closed
       2: aload_0
       3: getfield      #1                  // Field call:Lio/grpc/internal/ServerCallImpl;
       6: invokestatic  #17                 // Method io/grpc/internal/ServerCallImpl.access$200:(Lio/grpc/internal/ServerCallImpl;)Lio/perfmark/Tag;
       9: invokestatic  #18                 // Method io/perfmark/PerfMark.startTask:(Ljava/lang/String;Lio/perfmark/Tag;)V
      12: aload_0
      13: aload_1
      14: invokespecial #36                 // Method closedInternal:(Lio/grpc/Status;)V
      17: ldc           #35                 // String ServerStreamListener.closed
      19: aload_0
      20: getfield      #1                  // Field call:Lio/grpc/internal/ServerCallImpl;
      23: invokestatic  #17                 // Method io/grpc/internal/ServerCallImpl.access$200:(Lio/grpc/internal/ServerCallImpl;)Lio/perfmark/Tag;
      26: invokestatic  #20                 // Method io/perfmark/PerfMark.stopTask:(Ljava/lang/String;Lio/perfmark/Tag;)V
      29: goto          47
      32: astore_2
      33: ldc           #35                 // String ServerStreamListener.closed
      35: aload_0
      36: getfield      #1                  // Field call:Lio/grpc/internal/ServerCallImpl;
      39: invokestatic  #17                 // Method io/grpc/internal/ServerCallImpl.access$200:(Lio/grpc/internal/ServerCallImpl;)Lio/perfmark/Tag;
      42: invokestatic  #20                 // Method io/perfmark/PerfMark.stopTask:(Ljava/lang/String;Lio/perfmark/Tag;)V
      45: aload_2
      46: athrow
      47: return
    Exception table:
       from    to  target type
          12    17    32   any

  private void closedInternal(io.grpc.Status);
    Code:
       0: aload_1
       1: invokevirtual #37                 // Method io/grpc/Status.isOk:()Z
       4: ifeq          17
       7: aload_0
       8: getfield      #8                  // Field listener:Lio/grpc/ServerCall$Listener;
      11: invokevirtual #38                 // Method io/grpc/ServerCall$Listener.onComplete:()V
      14: goto          33
      17: aload_0
      18: getfield      #1                  // Field call:Lio/grpc/internal/ServerCallImpl;
      21: iconst_1
      22: invokestatic  #39                 // Method io/grpc/internal/ServerCallImpl.access$102:(Lio/grpc/internal/ServerCallImpl;Z)Z
      25: pop
      26: aload_0
      27: getfield      #8                  // Field listener:Lio/grpc/ServerCall$Listener;
      30: invokevirtual #40                 // Method io/grpc/ServerCall$Listener.onCancel:()V
      33: aload_0
      34: getfield      #11                 // Field context:Lio/grpc/Context$CancellableContext;
      37: aconst_null
      38: invokevirtual #41                 // Method io/grpc/Context$CancellableContext.cancel:(Ljava/lang/Throwable;)Z
      41: pop
      42: goto          57
      45: astore_2
      46: aload_0
      47: getfield      #11                 // Field context:Lio/grpc/Context$CancellableContext;
      50: aconst_null
      51: invokevirtual #41                 // Method io/grpc/Context$CancellableContext.cancel:(Ljava/lang/Throwable;)Z
      54: pop
      55: aload_2
      56: athrow
      57: return
    Exception table:
       from    to  target type
           0    33    45   any

  public void onReady();
    Code:
       0: ldc           #42                 // String ServerStreamListener.onReady
       2: aload_0
       3: getfield      #1                  // Field call:Lio/grpc/internal/ServerCallImpl;
       6: invokestatic  #17                 // Method io/grpc/internal/ServerCallImpl.access$200:(Lio/grpc/internal/ServerCallImpl;)Lio/perfmark/Tag;
       9: invokestatic  #18                 // Method io/perfmark/PerfMark.startTask:(Ljava/lang/String;Lio/perfmark/Tag;)V
      12: aload_0
      13: getfield      #1                  // Field call:Lio/grpc/internal/ServerCallImpl;
      16: invokestatic  #21                 // Method io/grpc/internal/ServerCallImpl.access$100:(Lio/grpc/internal/ServerCallImpl;)Z
      19: ifeq          35
      22: ldc           #43                 // String ServerCall.closed
      24: aload_0
      25: getfield      #1                  // Field call:Lio/grpc/internal/ServerCallImpl;
      28: invokestatic  #17                 // Method io/grpc/internal/ServerCallImpl.access$200:(Lio/grpc/internal/ServerCallImpl;)Lio/perfmark/Tag;
      31: invokestatic  #20                 // Method io/perfmark/PerfMark.stopTask:(Ljava/lang/String;Lio/perfmark/Tag;)V
      34: return
      35: aload_0
      36: getfield      #8                  // Field listener:Lio/grpc/ServerCall$Listener;
      39: invokevirtual #44                 // Method io/grpc/ServerCall$Listener.onReady:()V
      42: ldc           #43                 // String ServerCall.closed
      44: aload_0
      45: getfield      #1                  // Field call:Lio/grpc/internal/ServerCallImpl;
      48: invokestatic  #17                 // Method io/grpc/internal/ServerCallImpl.access$200:(Lio/grpc/internal/ServerCallImpl;)Lio/perfmark/Tag;
      51: invokestatic  #20                 // Method io/perfmark/PerfMark.stopTask:(Ljava/lang/String;Lio/perfmark/Tag;)V
      54: goto          72
      57: astore_1
      58: ldc           #43                 // String ServerCall.closed
      60: aload_0
      61: getfield      #1                  // Field call:Lio/grpc/internal/ServerCallImpl;
      64: invokestatic  #17                 // Method io/grpc/internal/ServerCallImpl.access$200:(Lio/grpc/internal/ServerCallImpl;)Lio/perfmark/Tag;
      67: invokestatic  #20                 // Method io/perfmark/PerfMark.stopTask:(Ljava/lang/String;Lio/perfmark/Tag;)V
      70: aload_1
      71: athrow
      72: return
    Exception table:
       from    to  target type
          12    22    57   any
          35    42    57   any

  static io.grpc.internal.ServerCallImpl access$000(io.grpc.internal.ServerCallImpl$ServerStreamListenerImpl);
    Code:
       0: aload_0
       1: getfield      #1                  // Field call:Lio/grpc/internal/ServerCallImpl;
       4: areturn
}
