Compiled from "ServerImpl.java"
final class io.grpc.internal.ServerImpl$ServerTransportListenerImpl$1MethodLookup extends io.grpc.internal.ContextRunnable {
  final io.grpc.Context$CancellableContext val$context;

  final io.perfmark.Tag val$tag;

  final io.perfmark.Link val$link;

  final java.lang.String val$methodName;

  final io.grpc.internal.ServerStream val$stream;

  final io.grpc.internal.ServerImpl$JumpToApplicationThreadServerStreamListener val$jumpListener;

  final com.google.common.util.concurrent.SettableFuture val$future;

  final io.grpc.internal.StatsTraceContext val$statsTraceCtx;

  final io.grpc.Metadata val$headers;

  final java.util.concurrent.Executor val$wrappedExecutor;

  final io.grpc.internal.ServerImpl$ServerTransportListenerImpl this$1;

  io.grpc.internal.ServerImpl$ServerTransportListenerImpl$1MethodLookup();
    Code:
       0: aload_0
       1: aload_1
       2: putfield      #1                  // Field this$1:Lio/grpc/internal/ServerImpl$ServerTransportListenerImpl;
       5: aload_0
       6: aload_2
       7: putfield      #2                  // Field val$context:Lio/grpc/Context$CancellableContext;
      10: aload_0
      11: aload_3
      12: putfield      #3                  // Field val$tag:Lio/perfmark/Tag;
      15: aload_0
      16: aload         4
      18: putfield      #4                  // Field val$link:Lio/perfmark/Link;
      21: aload_0
      22: aload         5
      24: putfield      #5                  // Field val$methodName:Ljava/lang/String;
      27: aload_0
      28: aload         6
      30: putfield      #6                  // Field val$stream:Lio/grpc/internal/ServerStream;
      33: aload_0
      34: aload         7
      36: putfield      #7                  // Field val$jumpListener:Lio/grpc/internal/ServerImpl$JumpToApplicationThreadServerStreamListener;
      39: aload_0
      40: aload         8
      42: putfield      #8                  // Field val$future:Lcom/google/common/util/concurrent/SettableFuture;
      45: aload_0
      46: aload         9
      48: putfield      #9                  // Field val$statsTraceCtx:Lio/grpc/internal/StatsTraceContext;
      51: aload_0
      52: aload         10
      54: putfield      #10                 // Field val$headers:Lio/grpc/Metadata;
      57: aload_0
      58: aload         11
      60: putfield      #11                 // Field val$wrappedExecutor:Ljava/util/concurrent/Executor;
      63: aload_0
      64: aload_2
      65: invokespecial #12                 // Method io/grpc/internal/ContextRunnable."<init>":(Lio/grpc/Context;)V
      68: return

  public void runInContext();
    Code:
       0: ldc           #13                 // String ServerTransportListener$MethodLookup.startCall
       2: aload_0
       3: getfield      #3                  // Field val$tag:Lio/perfmark/Tag;
       6: invokestatic  #14                 // Method io/perfmark/PerfMark.startTask:(Ljava/lang/String;Lio/perfmark/Tag;)V
       9: aload_0
      10: getfield      #4                  // Field val$link:Lio/perfmark/Link;
      13: invokestatic  #15                 // Method io/perfmark/PerfMark.linkIn:(Lio/perfmark/Link;)V
      16: aload_0
      17: invokespecial #16                 // Method runInternal:()V
      20: ldc           #13                 // String ServerTransportListener$MethodLookup.startCall
      22: aload_0
      23: getfield      #3                  // Field val$tag:Lio/perfmark/Tag;
      26: invokestatic  #17                 // Method io/perfmark/PerfMark.stopTask:(Ljava/lang/String;Lio/perfmark/Tag;)V
      29: goto          44
      32: astore_1
      33: ldc           #13                 // String ServerTransportListener$MethodLookup.startCall
      35: aload_0
      36: getfield      #3                  // Field val$tag:Lio/perfmark/Tag;
      39: invokestatic  #17                 // Method io/perfmark/PerfMark.stopTask:(Ljava/lang/String;Lio/perfmark/Tag;)V
      42: aload_1
      43: athrow
      44: return
    Exception table:
       from    to  target type
          16    20    32   any

  private void runInternal();
    Code:
       0: aload_0
       1: getfield      #1                  // Field this$1:Lio/grpc/internal/ServerImpl$ServerTransportListenerImpl;
       4: getfield      #18                 // Field io/grpc/internal/ServerImpl$ServerTransportListenerImpl.this$0:Lio/grpc/internal/ServerImpl;
       7: invokestatic  #19                 // Method io/grpc/internal/ServerImpl.access$1700:(Lio/grpc/internal/ServerImpl;)Lio/grpc/HandlerRegistry;
      10: aload_0
      11: getfield      #5                  // Field val$methodName:Ljava/lang/String;
      14: invokevirtual #20                 // Method io/grpc/HandlerRegistry.lookupMethod:(Ljava/lang/String;)Lio/grpc/ServerMethodDefinition;
      17: astore_3
      18: aload_3
      19: ifnonnull     49
      22: aload_0
      23: getfield      #1                  // Field this$1:Lio/grpc/internal/ServerImpl$ServerTransportListenerImpl;
      26: getfield      #18                 // Field io/grpc/internal/ServerImpl$ServerTransportListenerImpl.this$0:Lio/grpc/internal/ServerImpl;
      29: invokestatic  #21                 // Method io/grpc/internal/ServerImpl.access$1800:(Lio/grpc/internal/ServerImpl;)Lio/grpc/HandlerRegistry;
      32: aload_0
      33: getfield      #5                  // Field val$methodName:Ljava/lang/String;
      36: aload_0
      37: getfield      #6                  // Field val$stream:Lio/grpc/internal/ServerStream;
      40: invokeinterface #22,  1           // InterfaceMethod io/grpc/internal/ServerStream.getAuthority:()Ljava/lang/String;
      45: invokevirtual #23                 // Method io/grpc/HandlerRegistry.lookupMethod:(Ljava/lang/String;Ljava/lang/String;)Lio/grpc/ServerMethodDefinition;
      48: astore_3
      49: aload_3
      50: ifnonnull     130
      53: getstatic     #24                 // Field io/grpc/Status.UNIMPLEMENTED:Lio/grpc/Status;
      56: new           #25                 // class java/lang/StringBuilder
      59: dup
      60: invokespecial #26                 // Method java/lang/StringBuilder."<init>":()V
      63: ldc           #27                 // String Method not found:
      65: invokevirtual #28                 // Method java/lang/StringBuilder.append:(Ljava/lang/String;)Ljava/lang/StringBuilder;
      68: aload_0
      69: getfield      #5                  // Field val$methodName:Ljava/lang/String;
      72: invokevirtual #28                 // Method java/lang/StringBuilder.append:(Ljava/lang/String;)Ljava/lang/StringBuilder;
      75: invokevirtual #29                 // Method java/lang/StringBuilder.toString:()Ljava/lang/String;
      78: invokevirtual #30                 // Method io/grpc/Status.withDescription:(Ljava/lang/String;)Lio/grpc/Status;
      81: astore        4
      83: aload_0
      84: getfield      #7                  // Field val$jumpListener:Lio/grpc/internal/ServerImpl$JumpToApplicationThreadServerStreamListener;
      87: invokestatic  #31                 // Method io/grpc/internal/ServerImpl.access$1600:()Lio/grpc/internal/ServerStreamListener;
      90: invokevirtual #32                 // Method io/grpc/internal/ServerImpl$JumpToApplicationThreadServerStreamListener.setListener:(Lio/grpc/internal/ServerStreamListener;)V
      93: aload_0
      94: getfield      #6                  // Field val$stream:Lio/grpc/internal/ServerStream;
      97: aload         4
      99: new           #33                 // class io/grpc/Metadata
     102: dup
     103: invokespecial #34                 // Method io/grpc/Metadata."<init>":()V
     106: invokeinterface #35,  3           // InterfaceMethod io/grpc/internal/ServerStream.close:(Lio/grpc/Status;Lio/grpc/Metadata;)V
     111: aload_0
     112: getfield      #2                  // Field val$context:Lio/grpc/Context$CancellableContext;
     115: aconst_null
     116: invokevirtual #36                 // Method io/grpc/Context$CancellableContext.cancel:(Ljava/lang/Throwable;)Z
     119: pop
     120: aload_0
     121: getfield      #8                  // Field val$future:Lcom/google/common/util/concurrent/SettableFuture;
     124: iconst_0
     125: invokevirtual #37                 // Method com/google/common/util/concurrent/SettableFuture.cancel:(Z)Z
     128: pop
     129: return
     130: aload_0
     131: getfield      #1                  // Field this$1:Lio/grpc/internal/ServerImpl$ServerTransportListenerImpl;
     134: aload_0
     135: getfield      #6                  // Field val$stream:Lio/grpc/internal/ServerStream;
     138: aload_3
     139: aload_0
     140: getfield      #9                  // Field val$statsTraceCtx:Lio/grpc/internal/StatsTraceContext;
     143: invokestatic  #38                 // Method io/grpc/internal/ServerImpl$ServerTransportListenerImpl.access$1900:(Lio/grpc/internal/ServerImpl$ServerTransportListenerImpl;Lio/grpc/internal/ServerStream;Lio/grpc/ServerMethodDefinition;Lio/grpc/internal/StatsTraceContext;)Lio/grpc/ServerMethodDefinition;
     146: astore_1
     147: aload_0
     148: aload_1
     149: aload_0
     150: getfield      #6                  // Field val$stream:Lio/grpc/internal/ServerStream;
     153: aload_0
     154: getfield      #10                 // Field val$headers:Lio/grpc/Metadata;
     157: aload_0
     158: getfield      #2                  // Field val$context:Lio/grpc/Context$CancellableContext;
     161: aload_0
     162: getfield      #3                  // Field val$tag:Lio/perfmark/Tag;
     165: invokespecial #39                 // Method maySwitchExecutor:(Lio/grpc/ServerMethodDefinition;Lio/grpc/internal/ServerStream;Lio/grpc/Metadata;Lio/grpc/Context$CancellableContext;Lio/perfmark/Tag;)Lio/grpc/internal/ServerImpl$ServerTransportListenerImpl$ServerCallParameters;
     168: astore_2
     169: aload_0
     170: getfield      #8                  // Field val$future:Lcom/google/common/util/concurrent/SettableFuture;
     173: aload_2
     174: invokevirtual #40                 // Method com/google/common/util/concurrent/SettableFuture.set:(Ljava/lang/Object;)Z
     177: pop
     178: goto          232
     181: astore_3
     182: aload_0
     183: getfield      #7                  // Field val$jumpListener:Lio/grpc/internal/ServerImpl$JumpToApplicationThreadServerStreamListener;
     186: invokestatic  #31                 // Method io/grpc/internal/ServerImpl.access$1600:()Lio/grpc/internal/ServerStreamListener;
     189: invokevirtual #32                 // Method io/grpc/internal/ServerImpl$JumpToApplicationThreadServerStreamListener.setListener:(Lio/grpc/internal/ServerStreamListener;)V
     192: aload_0
     193: getfield      #6                  // Field val$stream:Lio/grpc/internal/ServerStream;
     196: aload_3
     197: invokestatic  #42                 // Method io/grpc/Status.fromThrowable:(Ljava/lang/Throwable;)Lio/grpc/Status;
     200: new           #33                 // class io/grpc/Metadata
     203: dup
     204: invokespecial #34                 // Method io/grpc/Metadata."<init>":()V
     207: invokeinterface #35,  3           // InterfaceMethod io/grpc/internal/ServerStream.close:(Lio/grpc/Status;Lio/grpc/Metadata;)V
     212: aload_0
     213: getfield      #2                  // Field val$context:Lio/grpc/Context$CancellableContext;
     216: aconst_null
     217: invokevirtual #36                 // Method io/grpc/Context$CancellableContext.cancel:(Ljava/lang/Throwable;)Z
     220: pop
     221: aload_0
     222: getfield      #8                  // Field val$future:Lcom/google/common/util/concurrent/SettableFuture;
     225: iconst_0
     226: invokevirtual #37                 // Method com/google/common/util/concurrent/SettableFuture.cancel:(Z)Z
     229: pop
     230: aload_3
     231: athrow
     232: return
    Exception table:
       from    to  target type
           0   129   181   Class java/lang/Throwable
         130   178   181   Class java/lang/Throwable

  private <ReqT, RespT> io.grpc.internal.ServerImpl$ServerTransportListenerImpl$ServerCallParameters<ReqT, RespT> maySwitchExecutor(io.grpc.ServerMethodDefinition<ReqT, RespT>, io.grpc.internal.ServerStream, io.grpc.Metadata, io.grpc.Context$CancellableContext, io.perfmark.Tag);
    Code:
       0: new           #43                 // class io/grpc/internal/ServerCallImpl
       3: dup
       4: aload_2
       5: aload_1
       6: invokevirtual #44                 // Method io/grpc/ServerMethodDefinition.getMethodDescriptor:()Lio/grpc/MethodDescriptor;
       9: aload_3
      10: aload         4
      12: aload_0
      13: getfield      #1                  // Field this$1:Lio/grpc/internal/ServerImpl$ServerTransportListenerImpl;
      16: getfield      #18                 // Field io/grpc/internal/ServerImpl$ServerTransportListenerImpl.this$0:Lio/grpc/internal/ServerImpl;
      19: invokestatic  #45                 // Method io/grpc/internal/ServerImpl.access$1500:(Lio/grpc/internal/ServerImpl;)Lio/grpc/DecompressorRegistry;
      22: aload_0
      23: getfield      #1                  // Field this$1:Lio/grpc/internal/ServerImpl$ServerTransportListenerImpl;
      26: getfield      #18                 // Field io/grpc/internal/ServerImpl$ServerTransportListenerImpl.this$0:Lio/grpc/internal/ServerImpl;
      29: invokestatic  #46                 // Method io/grpc/internal/ServerImpl.access$2000:(Lio/grpc/internal/ServerImpl;)Lio/grpc/CompressorRegistry;
      32: aload_0
      33: getfield      #1                  // Field this$1:Lio/grpc/internal/ServerImpl$ServerTransportListenerImpl;
      36: getfield      #18                 // Field io/grpc/internal/ServerImpl$ServerTransportListenerImpl.this$0:Lio/grpc/internal/ServerImpl;
      39: invokestatic  #47                 // Method io/grpc/internal/ServerImpl.access$2100:(Lio/grpc/internal/ServerImpl;)Lio/grpc/internal/CallTracer;
      42: aload         5
      44: invokespecial #48                 // Method io/grpc/internal/ServerCallImpl."<init>":(Lio/grpc/internal/ServerStream;Lio/grpc/MethodDescriptor;Lio/grpc/Metadata;Lio/grpc/Context$CancellableContext;Lio/grpc/DecompressorRegistry;Lio/grpc/CompressorRegistry;Lio/grpc/internal/CallTracer;Lio/perfmark/Tag;)V
      47: astore        6
      49: aload_0
      50: getfield      #1                  // Field this$1:Lio/grpc/internal/ServerImpl$ServerTransportListenerImpl;
      53: getfield      #18                 // Field io/grpc/internal/ServerImpl$ServerTransportListenerImpl.this$0:Lio/grpc/internal/ServerImpl;
      56: invokestatic  #49                 // Method io/grpc/internal/ServerImpl.access$1300:(Lio/grpc/internal/ServerImpl;)Lio/grpc/ServerCallExecutorSupplier;
      59: ifnull        99
      62: aload_0
      63: getfield      #1                  // Field this$1:Lio/grpc/internal/ServerImpl$ServerTransportListenerImpl;
      66: getfield      #18                 // Field io/grpc/internal/ServerImpl$ServerTransportListenerImpl.this$0:Lio/grpc/internal/ServerImpl;
      69: invokestatic  #49                 // Method io/grpc/internal/ServerImpl.access$1300:(Lio/grpc/internal/ServerImpl;)Lio/grpc/ServerCallExecutorSupplier;
      72: aload         6
      74: aload_3
      75: invokeinterface #50,  3           // InterfaceMethod io/grpc/ServerCallExecutorSupplier.getExecutor:(Lio/grpc/ServerCall;Lio/grpc/Metadata;)Ljava/util/concurrent/Executor;
      80: astore        7
      82: aload         7
      84: ifnull        99
      87: aload_0
      88: getfield      #11                 // Field val$wrappedExecutor:Ljava/util/concurrent/Executor;
      91: checkcast     #51                 // class io/grpc/internal/SerializingExecutor
      94: aload         7
      96: invokevirtual #52                 // Method io/grpc/internal/SerializingExecutor.setExecutor:(Ljava/util/concurrent/Executor;)V
      99: new           #53                 // class io/grpc/internal/ServerImpl$ServerTransportListenerImpl$ServerCallParameters
     102: dup
     103: aload_0
     104: getfield      #1                  // Field this$1:Lio/grpc/internal/ServerImpl$ServerTransportListenerImpl;
     107: aload         6
     109: aload_1
     110: invokevirtual #54                 // Method io/grpc/ServerMethodDefinition.getServerCallHandler:()Lio/grpc/ServerCallHandler;
     113: invokespecial #55                 // Method io/grpc/internal/ServerImpl$ServerTransportListenerImpl$ServerCallParameters."<init>":(Lio/grpc/internal/ServerImpl$ServerTransportListenerImpl;Lio/grpc/internal/ServerCallImpl;Lio/grpc/ServerCallHandler;)V
     116: areturn
}
