Compiled from "BulkAccessor.java"
public abstract class org.hibernate.bytecode.internal.javassist.BulkAccessor implements java.io.Serializable {
  protected java.lang.Class target;

  protected java.lang.String[] getters;

  protected java.lang.String[] setters;

  protected java.lang.Class[] types;

  protected org.hibernate.bytecode.internal.javassist.BulkAccessor();
    Code:
       0: aload_0
       1: invokespecial #1                  // Method java/lang/Object."<init>":()V
       4: return

  public abstract void getPropertyValues(java.lang.Object, java.lang.Object[]);

  public abstract void setPropertyValues(java.lang.Object, java.lang.Object[]);

  public java.lang.Object[] getPropertyValues(java.lang.Object);
    Code:
       0: aload_0
       1: getfield      #2                  // Field getters:[Ljava/lang/String;
       4: arraylength
       5: anewarray     #3                  // class java/lang/Object
       8: astore_2
       9: aload_0
      10: aload_1
      11: aload_2
      12: invokevirtual #4                  // Method getPropertyValues:(Ljava/lang/Object;[Ljava/lang/Object;)V
      15: aload_2
      16: areturn

  public java.lang.Class[] getPropertyTypes();
    Code:
       0: aload_0
       1: getfield      #5                  // Field types:[Ljava/lang/Class;
       4: invokevirtual #6                  // Method "[Ljava/lang/Class;".clone:()Ljava/lang/Object;
       7: checkcast     #7                  // class "[Ljava/lang/Class;"
      10: areturn

  public java.lang.String[] getGetters();
    Code:
       0: aload_0
       1: getfield      #2                  // Field getters:[Ljava/lang/String;
       4: invokevirtual #8                  // Method "[Ljava/lang/String;".clone:()Ljava/lang/Object;
       7: checkcast     #9                  // class "[Ljava/lang/String;"
      10: areturn

  public java.lang.String[] getSetters();
    Code:
       0: aload_0
       1: getfield      #10                 // Field setters:[Ljava/lang/String;
       4: invokevirtual #11                 // Method "[Ljava/lang/String;".clone:()Ljava/lang/Object;
       7: checkcast     #9                  // class "[Ljava/lang/String;"
      10: areturn

  public static org.hibernate.bytecode.internal.javassist.BulkAccessor create(java.lang.Class, java.lang.String[], java.lang.String[], java.lang.Class[]);
    Code:
       0: new           #12                 // class org/hibernate/bytecode/internal/javassist/BulkAccessorFactory
       3: dup
       4: aload_0
       5: aload_1
       6: aload_2
       7: aload_3
       8: invokespecial #13                 // Method org/hibernate/bytecode/internal/javassist/BulkAccessorFactory."<init>":(Ljava/lang/Class;[Ljava/lang/String;[Ljava/lang/String;[Ljava/lang/Class;)V
      11: invokevirtual #14                 // Method org/hibernate/bytecode/internal/javassist/BulkAccessorFactory.create:()Lorg/hibernate/bytecode/internal/javassist/BulkAccessor;
      14: areturn
}
