Compiled from "JavaAnnotationMapper.kt"
final class kotlin.reflect.jvm.internal.impl.load.java.components.JavaTargetAnnotationDescriptor$allValueArguments$2 extends kotlin.jvm.internal.Lambda implements kotlin.jvm.functions.Function0<java.util.Map<kotlin.reflect.jvm.internal.impl.name.Name, ? extends kotlin.reflect.jvm.internal.impl.resolve.constants.ConstantValue<? extends java.lang.Object>>> {
  final kotlin.reflect.jvm.internal.impl.load.java.components.JavaTargetAnnotationDescriptor this$0;

  kotlin.reflect.jvm.internal.impl.load.java.components.JavaTargetAnnotationDescriptor$allValueArguments$2(kotlin.reflect.jvm.internal.impl.load.java.components.JavaTargetAnnotationDescriptor);
    Code:
       0: aload_0
       1: aload_1
       2: putfield      #17                 // Field this$0:Lkotlin/reflect/jvm/internal/impl/load/java/components/JavaTargetAnnotationDescriptor;
       5: aload_0
       6: iconst_0
       7: invokespecial #22                 // Method kotlin/jvm/internal/Lambda."<init>":(I)V
      10: return

  public final java.util.Map<kotlin.reflect.jvm.internal.impl.name.Name, kotlin.reflect.jvm.internal.impl.resolve.constants.ConstantValue<java.lang.Object>> invoke();
    Code:
       0: aload_0
       1: getfield      #17                 // Field this$0:Lkotlin/reflect/jvm/internal/impl/load/java/components/JavaTargetAnnotationDescriptor;
       4: invokevirtual #25                 // Method kotlin/reflect/jvm/internal/impl/load/java/components/JavaTargetAnnotationDescriptor.getFirstArgument:()Lkotlin/reflect/jvm/internal/impl/load/java/structure/JavaAnnotationArgument;
       7: astore_2
       8: aload_2
       9: instanceof    #12                 // class kotlin/reflect/jvm/internal/impl/load/java/structure/JavaArrayAnnotationArgument
      12: ifeq          39
      15: getstatic     #16                 // Field kotlin/reflect/jvm/internal/impl/load/java/components/JavaAnnotationTargetMapper.INSTANCE:Lkotlin/reflect/jvm/internal/impl/load/java/components/JavaAnnotationTargetMapper;
      18: aload_0
      19: getfield      #17                 // Field this$0:Lkotlin/reflect/jvm/internal/impl/load/java/components/JavaTargetAnnotationDescriptor;
      22: invokevirtual #25                 // Method kotlin/reflect/jvm/internal/impl/load/java/components/JavaTargetAnnotationDescriptor.getFirstArgument:()Lkotlin/reflect/jvm/internal/impl/load/java/structure/JavaAnnotationArgument;
      25: checkcast     #12                 // class kotlin/reflect/jvm/internal/impl/load/java/structure/JavaArrayAnnotationArgument
      28: invokeinterface #27,  1           // InterfaceMethod kotlin/reflect/jvm/internal/impl/load/java/structure/JavaArrayAnnotationArgument.getElements:()Ljava/util/List;
      33: invokevirtual #24                 // Method kotlin/reflect/jvm/internal/impl/load/java/components/JavaAnnotationTargetMapper.mapJavaTargetArguments$descriptors_jvm:(Ljava/util/List;)Lkotlin/reflect/jvm/internal/impl/resolve/constants/ConstantValue;
      36: goto          66
      39: aload_2
      40: instanceof    #13                 // class kotlin/reflect/jvm/internal/impl/load/java/structure/JavaEnumValueAnnotationArgument
      43: ifeq          65
      46: getstatic     #16                 // Field kotlin/reflect/jvm/internal/impl/load/java/components/JavaAnnotationTargetMapper.INSTANCE:Lkotlin/reflect/jvm/internal/impl/load/java/components/JavaAnnotationTargetMapper;
      49: aload_0
      50: getfield      #17                 // Field this$0:Lkotlin/reflect/jvm/internal/impl/load/java/components/JavaTargetAnnotationDescriptor;
      53: invokevirtual #25                 // Method kotlin/reflect/jvm/internal/impl/load/java/components/JavaTargetAnnotationDescriptor.getFirstArgument:()Lkotlin/reflect/jvm/internal/impl/load/java/structure/JavaAnnotationArgument;
      56: invokestatic  #19                 // Method kotlin/collections/CollectionsKt.listOf:(Ljava/lang/Object;)Ljava/util/List;
      59: invokevirtual #24                 // Method kotlin/reflect/jvm/internal/impl/load/java/components/JavaAnnotationTargetMapper.mapJavaTargetArguments$descriptors_jvm:(Ljava/util/List;)Lkotlin/reflect/jvm/internal/impl/resolve/constants/ConstantValue;
      62: goto          66
      65: aconst_null
      66: astore_1
      67: aload_1
      68: dup
      69: ifnull        92
      72: astore_3
      73: iconst_0
      74: istore        4
      76: getstatic     #15                 // Field kotlin/reflect/jvm/internal/impl/load/java/components/JavaAnnotationMapper.INSTANCE:Lkotlin/reflect/jvm/internal/impl/load/java/components/JavaAnnotationMapper;
      79: invokevirtual #23                 // Method kotlin/reflect/jvm/internal/impl/load/java/components/JavaAnnotationMapper.getTARGET_ANNOTATION_ALLOWED_TARGETS$descriptors_jvm:()Lkotlin/reflect/jvm/internal/impl/name/Name;
      82: aload_3
      83: invokestatic  #18                 // Method kotlin/TuplesKt.to:(Ljava/lang/Object;Ljava/lang/Object;)Lkotlin/Pair;
      86: invokestatic  #21                 // Method kotlin/collections/MapsKt.mapOf:(Lkotlin/Pair;)Ljava/util/Map;
      89: goto          94
      92: pop
      93: aconst_null
      94: dup
      95: ifnonnull     102
      98: pop
      99: invokestatic  #20                 // Method kotlin/collections/MapsKt.emptyMap:()Ljava/util/Map;
     102: areturn

  public java.lang.Object invoke();
    Code:
       0: aload_0
       1: invokevirtual #26                 // Method invoke:()Ljava/util/Map;
       4: areturn
}
