Compiled from "StringToCharacterConverter.java"
final class org.springframework.core.convert.support.StringToCharacterConverter implements org.springframework.core.convert.converter.Converter<java.lang.String, java.lang.Character> {
  org.springframework.core.convert.support.StringToCharacterConverter();
    Code:
       0: aload_0
       1: invokespecial #1                  // Method java/lang/Object."<init>":()V
       4: return

  public java.lang.Character convert(java.lang.String);
    Code:
       0: aload_1
       1: invokevirtual #2                  // Method java/lang/String.isEmpty:()Z
       4: ifeq          9
       7: aconst_null
       8: areturn
       9: aload_1
      10: invokevirtual #3                  // Method java/lang/String.length:()I
      13: iconst_1
      14: if_icmple     56
      17: new           #4                  // class java/lang/IllegalArgumentException
      20: dup
      21: new           #5                  // class java/lang/StringBuilder
      24: dup
      25: invokespecial #6                  // Method java/lang/StringBuilder."<init>":()V
      28: ldc           #7                  // String Can only convert a [String] with length of 1 to a [Character]; string value \'
      30: invokevirtual #8                  // Method java/lang/StringBuilder.append:(Ljava/lang/String;)Ljava/lang/StringBuilder;
      33: aload_1
      34: invokevirtual #8                  // Method java/lang/StringBuilder.append:(Ljava/lang/String;)Ljava/lang/StringBuilder;
      37: ldc           #9                  // String \'  has length of
      39: invokevirtual #8                  // Method java/lang/StringBuilder.append:(Ljava/lang/String;)Ljava/lang/StringBuilder;
      42: aload_1
      43: invokevirtual #3                  // Method java/lang/String.length:()I
      46: invokevirtual #10                 // Method java/lang/StringBuilder.append:(I)Ljava/lang/StringBuilder;
      49: invokevirtual #11                 // Method java/lang/StringBuilder.toString:()Ljava/lang/String;
      52: invokespecial #12                 // Method java/lang/IllegalArgumentException."<init>":(Ljava/lang/String;)V
      55: athrow
      56: aload_1
      57: iconst_0
      58: invokevirtual #13                 // Method java/lang/String.charAt:(I)C
      61: invokestatic  #14                 // Method java/lang/Character.valueOf:(C)Ljava/lang/Character;
      64: areturn

  public java.lang.Object convert(java.lang.Object);
    Code:
       0: aload_0
       1: aload_1
       2: checkcast     #15                 // class java/lang/String
       5: invokevirtual #16                 // Method convert:(Ljava/lang/String;)Ljava/lang/Character;
       8: areturn
}
