Compiled from "RAM.scala"
public final class facade.amazonaws.services.ram.ResourceShareFeatureSet$ extends scala.scalajs.js.Object {
  public static facade.amazonaws.services.ram.ResourceShareFeatureSet$ MODULE$;

  private final facade.amazonaws.services.ram.ResourceShareFeatureSet CREATED_FROM_POLICY;

  private final facade.amazonaws.services.ram.ResourceShareFeatureSet PROMOTING_TO_STANDARD;

  private final facade.amazonaws.services.ram.ResourceShareFeatureSet STANDARD;

  private final scala.scalajs.js.Array<facade.amazonaws.services.ram.ResourceShareFeatureSet> values;

  public static {};
    Code:
       0: new           #2                  // class facade/amazonaws/services/ram/ResourceShareFeatureSet$
       3: invokespecial #19                 // Method "<init>":()V
       6: return

  public facade.amazonaws.services.ram.ResourceShareFeatureSet CREATED_FROM_POLICY();
    Code:
       0: aload_0
       1: getfield      #22                 // Field CREATED_FROM_POLICY:Lfacade/amazonaws/services/ram/ResourceShareFeatureSet;
       4: areturn

  public facade.amazonaws.services.ram.ResourceShareFeatureSet PROMOTING_TO_STANDARD();
    Code:
       0: aload_0
       1: getfield      #25                 // Field PROMOTING_TO_STANDARD:Lfacade/amazonaws/services/ram/ResourceShareFeatureSet;
       4: areturn

  public facade.amazonaws.services.ram.ResourceShareFeatureSet STANDARD();
    Code:
       0: aload_0
       1: getfield      #27                 // Field STANDARD:Lfacade/amazonaws/services/ram/ResourceShareFeatureSet;
       4: areturn

  public scala.scalajs.js.Array<facade.amazonaws.services.ram.ResourceShareFeatureSet> values();
    Code:
       0: aload_0
       1: getfield      #31                 // Field values:Lscala/scalajs/js/Array;
       4: areturn

  private facade.amazonaws.services.ram.ResourceShareFeatureSet$();
    Code:
       0: aload_0
       1: invokespecial #32                 // Method scala/scalajs/js/Object."<init>":()V
       4: aload_0
       5: putstatic     #34                 // Field MODULE$:Lfacade/amazonaws/services/ram/ResourceShareFeatureSet$;
       8: aload_0
       9: ldc           #35                 // String CREATED_FROM_POLICY
      11: checkcast     #37                 // class facade/amazonaws/services/ram/ResourceShareFeatureSet
      14: putfield      #22                 // Field CREATED_FROM_POLICY:Lfacade/amazonaws/services/ram/ResourceShareFeatureSet;
      17: aload_0
      18: ldc           #38                 // String PROMOTING_TO_STANDARD
      20: checkcast     #37                 // class facade/amazonaws/services/ram/ResourceShareFeatureSet
      23: putfield      #25                 // Field PROMOTING_TO_STANDARD:Lfacade/amazonaws/services/ram/ResourceShareFeatureSet;
      26: aload_0
      27: ldc           #39                 // String STANDARD
      29: checkcast     #37                 // class facade/amazonaws/services/ram/ResourceShareFeatureSet
      32: putfield      #27                 // Field STANDARD:Lfacade/amazonaws/services/ram/ResourceShareFeatureSet;
      35: aload_0
      36: getstatic     #44                 // Field scala/scalajs/js/Object$.MODULE$:Lscala/scalajs/js/Object$;
      39: getstatic     #49                 // Field scala/scalajs/js/Array$.MODULE$:Lscala/scalajs/js/Array$;
      42: getstatic     #54                 // Field scala/Predef$.MODULE$:Lscala/Predef$;
      45: iconst_3
      46: anewarray     #37                 // class facade/amazonaws/services/ram/ResourceShareFeatureSet
      49: dup
      50: iconst_0
      51: aload_0
      52: invokevirtual #56                 // Method CREATED_FROM_POLICY:()Lfacade/amazonaws/services/ram/ResourceShareFeatureSet;
      55: aastore
      56: dup
      57: iconst_1
      58: aload_0
      59: invokevirtual #58                 // Method PROMOTING_TO_STANDARD:()Lfacade/amazonaws/services/ram/ResourceShareFeatureSet;
      62: aastore
      63: dup
      64: iconst_2
      65: aload_0
      66: invokevirtual #60                 // Method STANDARD:()Lfacade/amazonaws/services/ram/ResourceShareFeatureSet;
      69: aastore
      70: checkcast     #62                 // class "[Ljava/lang/Object;"
      73: invokevirtual #66                 // Method scala/Predef$.wrapRefArray:([Ljava/lang/Object;)Lscala/collection/mutable/WrappedArray;
      76: invokevirtual #70                 // Method scala/scalajs/js/Array$.apply:(Lscala/collection/Seq;)Lscala/scalajs/js/Array;
      79: invokevirtual #74                 // Method scala/scalajs/js/Object$.freeze:(Lscala/scalajs/js/Object;)Lscala/scalajs/js/Object;
      82: checkcast     #76                 // class scala/scalajs/js/Array
      85: putfield      #31                 // Field values:Lscala/scalajs/js/Array;
      88: return
}
