Compiled from "RAM.scala"
public interface facade.amazonaws.services.ram.ResourceShareAssociationStatus extends scala.scalajs.js.Any {
  public static scala.scalajs.js.Array<facade.amazonaws.services.ram.ResourceShareAssociationStatus> values();
    Code:
       0: getstatic     #19                 // Field facade/amazonaws/services/ram/ResourceShareAssociationStatus$.MODULE$:Lfacade/amazonaws/services/ram/ResourceShareAssociationStatus$;
       3: invokevirtual #21                 // Method facade/amazonaws/services/ram/ResourceShareAssociationStatus$.values:()Lscala/scalajs/js/Array;
       6: areturn

  public static facade.amazonaws.services.ram.ResourceShareAssociationStatus DISASSOCIATED();
    Code:
       0: getstatic     #19                 // Field facade/amazonaws/services/ram/ResourceShareAssociationStatus$.MODULE$:Lfacade/amazonaws/services/ram/ResourceShareAssociationStatus$;
       3: invokevirtual #25                 // Method facade/amazonaws/services/ram/ResourceShareAssociationStatus$.DISASSOCIATED:()Lfacade/amazonaws/services/ram/ResourceShareAssociationStatus;
       6: areturn

  public static facade.amazonaws.services.ram.ResourceShareAssociationStatus DISASSOCIATING();
    Code:
       0: getstatic     #19                 // Field facade/amazonaws/services/ram/ResourceShareAssociationStatus$.MODULE$:Lfacade/amazonaws/services/ram/ResourceShareAssociationStatus$;
       3: invokevirtual #28                 // Method facade/amazonaws/services/ram/ResourceShareAssociationStatus$.DISASSOCIATING:()Lfacade/amazonaws/services/ram/ResourceShareAssociationStatus;
       6: areturn

  public static facade.amazonaws.services.ram.ResourceShareAssociationStatus FAILED();
    Code:
       0: getstatic     #19                 // Field facade/amazonaws/services/ram/ResourceShareAssociationStatus$.MODULE$:Lfacade/amazonaws/services/ram/ResourceShareAssociationStatus$;
       3: invokevirtual #31                 // Method facade/amazonaws/services/ram/ResourceShareAssociationStatus$.FAILED:()Lfacade/amazonaws/services/ram/ResourceShareAssociationStatus;
       6: areturn

  public static facade.amazonaws.services.ram.ResourceShareAssociationStatus ASSOCIATED();
    Code:
       0: getstatic     #19                 // Field facade/amazonaws/services/ram/ResourceShareAssociationStatus$.MODULE$:Lfacade/amazonaws/services/ram/ResourceShareAssociationStatus$;
       3: invokevirtual #34                 // Method facade/amazonaws/services/ram/ResourceShareAssociationStatus$.ASSOCIATED:()Lfacade/amazonaws/services/ram/ResourceShareAssociationStatus;
       6: areturn

  public static facade.amazonaws.services.ram.ResourceShareAssociationStatus ASSOCIATING();
    Code:
       0: getstatic     #19                 // Field facade/amazonaws/services/ram/ResourceShareAssociationStatus$.MODULE$:Lfacade/amazonaws/services/ram/ResourceShareAssociationStatus$;
       3: invokevirtual #37                 // Method facade/amazonaws/services/ram/ResourceShareAssociationStatus$.ASSOCIATING:()Lfacade/amazonaws/services/ram/ResourceShareAssociationStatus;
       6: areturn

  public static boolean propertyIsEnumerable(java.lang.String);
    Code:
       0: getstatic     #19                 // Field facade/amazonaws/services/ram/ResourceShareAssociationStatus$.MODULE$:Lfacade/amazonaws/services/ram/ResourceShareAssociationStatus$;
       3: aload_0
       4: invokevirtual #42                 // Method facade/amazonaws/services/ram/ResourceShareAssociationStatus$.propertyIsEnumerable:(Ljava/lang/String;)Z
       7: ireturn

  public static boolean isPrototypeOf(scala.scalajs.js.Object);
    Code:
       0: getstatic     #19                 // Field facade/amazonaws/services/ram/ResourceShareAssociationStatus$.MODULE$:Lfacade/amazonaws/services/ram/ResourceShareAssociationStatus$;
       3: aload_0
       4: invokevirtual #46                 // Method facade/amazonaws/services/ram/ResourceShareAssociationStatus$.isPrototypeOf:(Lscala/scalajs/js/Object;)Z
       7: ireturn

  public static boolean hasOwnProperty(java.lang.String);
    Code:
       0: getstatic     #19                 // Field facade/amazonaws/services/ram/ResourceShareAssociationStatus$.MODULE$:Lfacade/amazonaws/services/ram/ResourceShareAssociationStatus$;
       3: aload_0
       4: invokevirtual #49                 // Method facade/amazonaws/services/ram/ResourceShareAssociationStatus$.hasOwnProperty:(Ljava/lang/String;)Z
       7: ireturn

  public static java.lang.Object valueOf();
    Code:
       0: getstatic     #19                 // Field facade/amazonaws/services/ram/ResourceShareAssociationStatus$.MODULE$:Lfacade/amazonaws/services/ram/ResourceShareAssociationStatus$;
       3: invokevirtual #53                 // Method facade/amazonaws/services/ram/ResourceShareAssociationStatus$.valueOf:()Ljava/lang/Object;
       6: areturn

  public static java.lang.String toLocaleString();
    Code:
       0: getstatic     #19                 // Field facade/amazonaws/services/ram/ResourceShareAssociationStatus$.MODULE$:Lfacade/amazonaws/services/ram/ResourceShareAssociationStatus$;
       3: invokevirtual #57                 // Method facade/amazonaws/services/ram/ResourceShareAssociationStatus$.toLocaleString:()Ljava/lang/String;
       6: areturn
}
