Compiled from "ResolveEndpoint.kt"
final class aws.sdk.kotlin.services.route53recoverycluster.endpoints.internal.ResolveEndpoint$modifyBeforeRetryLoop$2 extends kotlin.jvm.internal.Lambda implements kotlin.jvm.functions.Function0<java.lang.Object> {
  final aws.smithy.kotlin.runtime.client.endpoints.Endpoint $endpoint;

  aws.sdk.kotlin.services.route53recoverycluster.endpoints.internal.ResolveEndpoint$modifyBeforeRetryLoop$2(aws.smithy.kotlin.runtime.client.endpoints.Endpoint);
    Code:
       0: aload_0
       1: aload_1
       2: putfield      #13                 // Field $endpoint:Laws/smithy/kotlin/runtime/client/endpoints/Endpoint;
       5: aload_0
       6: iconst_0
       7: invokespecial #16                 // Method kotlin/jvm/internal/Lambda."<init>":(I)V
      10: return

  public final java.lang.Object invoke();
    Code:
       0: new           #23                 // class java/lang/StringBuilder
       3: dup
       4: invokespecial #26                 // Method java/lang/StringBuilder."<init>":()V
       7: ldc           #28                 // String resolved endpoint:
       9: invokevirtual #32                 // Method java/lang/StringBuilder.append:(Ljava/lang/String;)Ljava/lang/StringBuilder;
      12: aload_0
      13: getfield      #13                 // Field $endpoint:Laws/smithy/kotlin/runtime/client/endpoints/Endpoint;
      16: invokevirtual #35                 // Method java/lang/StringBuilder.append:(Ljava/lang/Object;)Ljava/lang/StringBuilder;
      19: invokevirtual #39                 // Method java/lang/StringBuilder.toString:()Ljava/lang/String;
      22: areturn
}
