Compiled from "AuthGrpc.java"
public final class io.etcd.jetcd.api.AuthGrpc {
  public static final java.lang.String SERVICE_NAME;

  private static volatile io.grpc.MethodDescriptor<io.etcd.jetcd.api.AuthEnableRequest, io.etcd.jetcd.api.AuthEnableResponse> getAuthEnableMethod;

  private static volatile io.grpc.MethodDescriptor<io.etcd.jetcd.api.AuthDisableRequest, io.etcd.jetcd.api.AuthDisableResponse> getAuthDisableMethod;

  private static volatile io.grpc.MethodDescriptor<io.etcd.jetcd.api.AuthenticateRequest, io.etcd.jetcd.api.AuthenticateResponse> getAuthenticateMethod;

  private static volatile io.grpc.MethodDescriptor<io.etcd.jetcd.api.AuthUserAddRequest, io.etcd.jetcd.api.AuthUserAddResponse> getUserAddMethod;

  private static volatile io.grpc.MethodDescriptor<io.etcd.jetcd.api.AuthUserGetRequest, io.etcd.jetcd.api.AuthUserGetResponse> getUserGetMethod;

  private static volatile io.grpc.MethodDescriptor<io.etcd.jetcd.api.AuthUserListRequest, io.etcd.jetcd.api.AuthUserListResponse> getUserListMethod;

  private static volatile io.grpc.MethodDescriptor<io.etcd.jetcd.api.AuthUserDeleteRequest, io.etcd.jetcd.api.AuthUserDeleteResponse> getUserDeleteMethod;

  private static volatile io.grpc.MethodDescriptor<io.etcd.jetcd.api.AuthUserChangePasswordRequest, io.etcd.jetcd.api.AuthUserChangePasswordResponse> getUserChangePasswordMethod;

  private static volatile io.grpc.MethodDescriptor<io.etcd.jetcd.api.AuthUserGrantRoleRequest, io.etcd.jetcd.api.AuthUserGrantRoleResponse> getUserGrantRoleMethod;

  private static volatile io.grpc.MethodDescriptor<io.etcd.jetcd.api.AuthUserRevokeRoleRequest, io.etcd.jetcd.api.AuthUserRevokeRoleResponse> getUserRevokeRoleMethod;

  private static volatile io.grpc.MethodDescriptor<io.etcd.jetcd.api.AuthRoleAddRequest, io.etcd.jetcd.api.AuthRoleAddResponse> getRoleAddMethod;

  private static volatile io.grpc.MethodDescriptor<io.etcd.jetcd.api.AuthRoleGetRequest, io.etcd.jetcd.api.AuthRoleGetResponse> getRoleGetMethod;

  private static volatile io.grpc.MethodDescriptor<io.etcd.jetcd.api.AuthRoleListRequest, io.etcd.jetcd.api.AuthRoleListResponse> getRoleListMethod;

  private static volatile io.grpc.MethodDescriptor<io.etcd.jetcd.api.AuthRoleDeleteRequest, io.etcd.jetcd.api.AuthRoleDeleteResponse> getRoleDeleteMethod;

  private static volatile io.grpc.MethodDescriptor<io.etcd.jetcd.api.AuthRoleGrantPermissionRequest, io.etcd.jetcd.api.AuthRoleGrantPermissionResponse> getRoleGrantPermissionMethod;

  private static volatile io.grpc.MethodDescriptor<io.etcd.jetcd.api.AuthRoleRevokePermissionRequest, io.etcd.jetcd.api.AuthRoleRevokePermissionResponse> getRoleRevokePermissionMethod;

  private static final int METHODID_AUTH_ENABLE;

  private static final int METHODID_AUTH_DISABLE;

  private static final int METHODID_AUTHENTICATE;

  private static final int METHODID_USER_ADD;

  private static final int METHODID_USER_GET;

  private static final int METHODID_USER_LIST;

  private static final int METHODID_USER_DELETE;

  private static final int METHODID_USER_CHANGE_PASSWORD;

  private static final int METHODID_USER_GRANT_ROLE;

  private static final int METHODID_USER_REVOKE_ROLE;

  private static final int METHODID_ROLE_ADD;

  private static final int METHODID_ROLE_GET;

  private static final int METHODID_ROLE_LIST;

  private static final int METHODID_ROLE_DELETE;

  private static final int METHODID_ROLE_GRANT_PERMISSION;

  private static final int METHODID_ROLE_REVOKE_PERMISSION;

  private static volatile io.grpc.ServiceDescriptor serviceDescriptor;

  private io.etcd.jetcd.api.AuthGrpc();
    Code:
       0: aload_0
       1: invokespecial #1                  // Method java/lang/Object."<init>":()V
       4: return

  public static io.grpc.MethodDescriptor<io.etcd.jetcd.api.AuthEnableRequest, io.etcd.jetcd.api.AuthEnableResponse> getAuthEnableMethod();
    Code:
       0: getstatic     #2                  // Field getAuthEnableMethod:Lio/grpc/MethodDescriptor;
       3: dup
       4: astore_0
       5: ifnonnull     92
       8: ldc           #3                  // class io/etcd/jetcd/api/AuthGrpc
      10: dup
      11: astore_1
      12: monitorenter
      13: getstatic     #2                  // Field getAuthEnableMethod:Lio/grpc/MethodDescriptor;
      16: dup
      17: astore_0
      18: ifnonnull     82
      21: invokestatic  #4                  // Method io/grpc/MethodDescriptor.newBuilder:()Lio/grpc/MethodDescriptor$Builder;
      24: getstatic     #5                  // Field io/grpc/MethodDescriptor$MethodType.UNARY:Lio/grpc/MethodDescriptor$MethodType;
      27: invokevirtual #6                  // Method io/grpc/MethodDescriptor$Builder.setType:(Lio/grpc/MethodDescriptor$MethodType;)Lio/grpc/MethodDescriptor$Builder;
      30: ldc           #7                  // String etcdserverpb.Auth
      32: ldc           #8                  // String AuthEnable
      34: invokestatic  #9                  // Method io/grpc/MethodDescriptor.generateFullMethodName:(Ljava/lang/String;Ljava/lang/String;)Ljava/lang/String;
      37: invokevirtual #10                 // Method io/grpc/MethodDescriptor$Builder.setFullMethodName:(Ljava/lang/String;)Lio/grpc/MethodDescriptor$Builder;
      40: iconst_1
      41: invokevirtual #11                 // Method io/grpc/MethodDescriptor$Builder.setSampledToLocalTracing:(Z)Lio/grpc/MethodDescriptor$Builder;
      44: invokestatic  #12                 // Method io/etcd/jetcd/api/AuthEnableRequest.getDefaultInstance:()Lio/etcd/jetcd/api/AuthEnableRequest;
      47: invokestatic  #13                 // Method io/grpc/protobuf/ProtoUtils.marshaller:(Lcom/google/protobuf/Message;)Lio/grpc/MethodDescriptor$Marshaller;
      50: invokevirtual #14                 // Method io/grpc/MethodDescriptor$Builder.setRequestMarshaller:(Lio/grpc/MethodDescriptor$Marshaller;)Lio/grpc/MethodDescriptor$Builder;
      53: invokestatic  #15                 // Method io/etcd/jetcd/api/AuthEnableResponse.getDefaultInstance:()Lio/etcd/jetcd/api/AuthEnableResponse;
      56: invokestatic  #13                 // Method io/grpc/protobuf/ProtoUtils.marshaller:(Lcom/google/protobuf/Message;)Lio/grpc/MethodDescriptor$Marshaller;
      59: invokevirtual #16                 // Method io/grpc/MethodDescriptor$Builder.setResponseMarshaller:(Lio/grpc/MethodDescriptor$Marshaller;)Lio/grpc/MethodDescriptor$Builder;
      62: new           #17                 // class io/etcd/jetcd/api/AuthGrpc$AuthMethodDescriptorSupplier
      65: dup
      66: ldc           #8                  // String AuthEnable
      68: invokespecial #18                 // Method io/etcd/jetcd/api/AuthGrpc$AuthMethodDescriptorSupplier."<init>":(Ljava/lang/String;)V
      71: invokevirtual #19                 // Method io/grpc/MethodDescriptor$Builder.setSchemaDescriptor:(Ljava/lang/Object;)Lio/grpc/MethodDescriptor$Builder;
      74: invokevirtual #20                 // Method io/grpc/MethodDescriptor$Builder.build:()Lio/grpc/MethodDescriptor;
      77: dup
      78: astore_0
      79: putstatic     #2                  // Field getAuthEnableMethod:Lio/grpc/MethodDescriptor;
      82: aload_1
      83: monitorexit
      84: goto          92
      87: astore_2
      88: aload_1
      89: monitorexit
      90: aload_2
      91: athrow
      92: aload_0
      93: areturn
    Exception table:
       from    to  target type
          13    84    87   any
          87    90    87   any

  public static io.grpc.MethodDescriptor<io.etcd.jetcd.api.AuthDisableRequest, io.etcd.jetcd.api.AuthDisableResponse> getAuthDisableMethod();
    Code:
       0: getstatic     #21                 // Field getAuthDisableMethod:Lio/grpc/MethodDescriptor;
       3: dup
       4: astore_0
       5: ifnonnull     92
       8: ldc           #3                  // class io/etcd/jetcd/api/AuthGrpc
      10: dup
      11: astore_1
      12: monitorenter
      13: getstatic     #21                 // Field getAuthDisableMethod:Lio/grpc/MethodDescriptor;
      16: dup
      17: astore_0
      18: ifnonnull     82
      21: invokestatic  #4                  // Method io/grpc/MethodDescriptor.newBuilder:()Lio/grpc/MethodDescriptor$Builder;
      24: getstatic     #5                  // Field io/grpc/MethodDescriptor$MethodType.UNARY:Lio/grpc/MethodDescriptor$MethodType;
      27: invokevirtual #6                  // Method io/grpc/MethodDescriptor$Builder.setType:(Lio/grpc/MethodDescriptor$MethodType;)Lio/grpc/MethodDescriptor$Builder;
      30: ldc           #7                  // String etcdserverpb.Auth
      32: ldc           #22                 // String AuthDisable
      34: invokestatic  #9                  // Method io/grpc/MethodDescriptor.generateFullMethodName:(Ljava/lang/String;Ljava/lang/String;)Ljava/lang/String;
      37: invokevirtual #10                 // Method io/grpc/MethodDescriptor$Builder.setFullMethodName:(Ljava/lang/String;)Lio/grpc/MethodDescriptor$Builder;
      40: iconst_1
      41: invokevirtual #11                 // Method io/grpc/MethodDescriptor$Builder.setSampledToLocalTracing:(Z)Lio/grpc/MethodDescriptor$Builder;
      44: invokestatic  #23                 // Method io/etcd/jetcd/api/AuthDisableRequest.getDefaultInstance:()Lio/etcd/jetcd/api/AuthDisableRequest;
      47: invokestatic  #13                 // Method io/grpc/protobuf/ProtoUtils.marshaller:(Lcom/google/protobuf/Message;)Lio/grpc/MethodDescriptor$Marshaller;
      50: invokevirtual #14                 // Method io/grpc/MethodDescriptor$Builder.setRequestMarshaller:(Lio/grpc/MethodDescriptor$Marshaller;)Lio/grpc/MethodDescriptor$Builder;
      53: invokestatic  #24                 // Method io/etcd/jetcd/api/AuthDisableResponse.getDefaultInstance:()Lio/etcd/jetcd/api/AuthDisableResponse;
      56: invokestatic  #13                 // Method io/grpc/protobuf/ProtoUtils.marshaller:(Lcom/google/protobuf/Message;)Lio/grpc/MethodDescriptor$Marshaller;
      59: invokevirtual #16                 // Method io/grpc/MethodDescriptor$Builder.setResponseMarshaller:(Lio/grpc/MethodDescriptor$Marshaller;)Lio/grpc/MethodDescriptor$Builder;
      62: new           #17                 // class io/etcd/jetcd/api/AuthGrpc$AuthMethodDescriptorSupplier
      65: dup
      66: ldc           #22                 // String AuthDisable
      68: invokespecial #18                 // Method io/etcd/jetcd/api/AuthGrpc$AuthMethodDescriptorSupplier."<init>":(Ljava/lang/String;)V
      71: invokevirtual #19                 // Method io/grpc/MethodDescriptor$Builder.setSchemaDescriptor:(Ljava/lang/Object;)Lio/grpc/MethodDescriptor$Builder;
      74: invokevirtual #20                 // Method io/grpc/MethodDescriptor$Builder.build:()Lio/grpc/MethodDescriptor;
      77: dup
      78: astore_0
      79: putstatic     #21                 // Field getAuthDisableMethod:Lio/grpc/MethodDescriptor;
      82: aload_1
      83: monitorexit
      84: goto          92
      87: astore_2
      88: aload_1
      89: monitorexit
      90: aload_2
      91: athrow
      92: aload_0
      93: areturn
    Exception table:
       from    to  target type
          13    84    87   any
          87    90    87   any

  public static io.grpc.MethodDescriptor<io.etcd.jetcd.api.AuthenticateRequest, io.etcd.jetcd.api.AuthenticateResponse> getAuthenticateMethod();
    Code:
       0: getstatic     #25                 // Field getAuthenticateMethod:Lio/grpc/MethodDescriptor;
       3: dup
       4: astore_0
       5: ifnonnull     92
       8: ldc           #3                  // class io/etcd/jetcd/api/AuthGrpc
      10: dup
      11: astore_1
      12: monitorenter
      13: getstatic     #25                 // Field getAuthenticateMethod:Lio/grpc/MethodDescriptor;
      16: dup
      17: astore_0
      18: ifnonnull     82
      21: invokestatic  #4                  // Method io/grpc/MethodDescriptor.newBuilder:()Lio/grpc/MethodDescriptor$Builder;
      24: getstatic     #5                  // Field io/grpc/MethodDescriptor$MethodType.UNARY:Lio/grpc/MethodDescriptor$MethodType;
      27: invokevirtual #6                  // Method io/grpc/MethodDescriptor$Builder.setType:(Lio/grpc/MethodDescriptor$MethodType;)Lio/grpc/MethodDescriptor$Builder;
      30: ldc           #7                  // String etcdserverpb.Auth
      32: ldc           #26                 // String Authenticate
      34: invokestatic  #9                  // Method io/grpc/MethodDescriptor.generateFullMethodName:(Ljava/lang/String;Ljava/lang/String;)Ljava/lang/String;
      37: invokevirtual #10                 // Method io/grpc/MethodDescriptor$Builder.setFullMethodName:(Ljava/lang/String;)Lio/grpc/MethodDescriptor$Builder;
      40: iconst_1
      41: invokevirtual #11                 // Method io/grpc/MethodDescriptor$Builder.setSampledToLocalTracing:(Z)Lio/grpc/MethodDescriptor$Builder;
      44: invokestatic  #27                 // Method io/etcd/jetcd/api/AuthenticateRequest.getDefaultInstance:()Lio/etcd/jetcd/api/AuthenticateRequest;
      47: invokestatic  #13                 // Method io/grpc/protobuf/ProtoUtils.marshaller:(Lcom/google/protobuf/Message;)Lio/grpc/MethodDescriptor$Marshaller;
      50: invokevirtual #14                 // Method io/grpc/MethodDescriptor$Builder.setRequestMarshaller:(Lio/grpc/MethodDescriptor$Marshaller;)Lio/grpc/MethodDescriptor$Builder;
      53: invokestatic  #28                 // Method io/etcd/jetcd/api/AuthenticateResponse.getDefaultInstance:()Lio/etcd/jetcd/api/AuthenticateResponse;
      56: invokestatic  #13                 // Method io/grpc/protobuf/ProtoUtils.marshaller:(Lcom/google/protobuf/Message;)Lio/grpc/MethodDescriptor$Marshaller;
      59: invokevirtual #16                 // Method io/grpc/MethodDescriptor$Builder.setResponseMarshaller:(Lio/grpc/MethodDescriptor$Marshaller;)Lio/grpc/MethodDescriptor$Builder;
      62: new           #17                 // class io/etcd/jetcd/api/AuthGrpc$AuthMethodDescriptorSupplier
      65: dup
      66: ldc           #26                 // String Authenticate
      68: invokespecial #18                 // Method io/etcd/jetcd/api/AuthGrpc$AuthMethodDescriptorSupplier."<init>":(Ljava/lang/String;)V
      71: invokevirtual #19                 // Method io/grpc/MethodDescriptor$Builder.setSchemaDescriptor:(Ljava/lang/Object;)Lio/grpc/MethodDescriptor$Builder;
      74: invokevirtual #20                 // Method io/grpc/MethodDescriptor$Builder.build:()Lio/grpc/MethodDescriptor;
      77: dup
      78: astore_0
      79: putstatic     #25                 // Field getAuthenticateMethod:Lio/grpc/MethodDescriptor;
      82: aload_1
      83: monitorexit
      84: goto          92
      87: astore_2
      88: aload_1
      89: monitorexit
      90: aload_2
      91: athrow
      92: aload_0
      93: areturn
    Exception table:
       from    to  target type
          13    84    87   any
          87    90    87   any

  public static io.grpc.MethodDescriptor<io.etcd.jetcd.api.AuthUserAddRequest, io.etcd.jetcd.api.AuthUserAddResponse> getUserAddMethod();
    Code:
       0: getstatic     #29                 // Field getUserAddMethod:Lio/grpc/MethodDescriptor;
       3: dup
       4: astore_0
       5: ifnonnull     92
       8: ldc           #3                  // class io/etcd/jetcd/api/AuthGrpc
      10: dup
      11: astore_1
      12: monitorenter
      13: getstatic     #29                 // Field getUserAddMethod:Lio/grpc/MethodDescriptor;
      16: dup
      17: astore_0
      18: ifnonnull     82
      21: invokestatic  #4                  // Method io/grpc/MethodDescriptor.newBuilder:()Lio/grpc/MethodDescriptor$Builder;
      24: getstatic     #5                  // Field io/grpc/MethodDescriptor$MethodType.UNARY:Lio/grpc/MethodDescriptor$MethodType;
      27: invokevirtual #6                  // Method io/grpc/MethodDescriptor$Builder.setType:(Lio/grpc/MethodDescriptor$MethodType;)Lio/grpc/MethodDescriptor$Builder;
      30: ldc           #7                  // String etcdserverpb.Auth
      32: ldc           #30                 // String UserAdd
      34: invokestatic  #9                  // Method io/grpc/MethodDescriptor.generateFullMethodName:(Ljava/lang/String;Ljava/lang/String;)Ljava/lang/String;
      37: invokevirtual #10                 // Method io/grpc/MethodDescriptor$Builder.setFullMethodName:(Ljava/lang/String;)Lio/grpc/MethodDescriptor$Builder;
      40: iconst_1
      41: invokevirtual #11                 // Method io/grpc/MethodDescriptor$Builder.setSampledToLocalTracing:(Z)Lio/grpc/MethodDescriptor$Builder;
      44: invokestatic  #31                 // Method io/etcd/jetcd/api/AuthUserAddRequest.getDefaultInstance:()Lio/etcd/jetcd/api/AuthUserAddRequest;
      47: invokestatic  #13                 // Method io/grpc/protobuf/ProtoUtils.marshaller:(Lcom/google/protobuf/Message;)Lio/grpc/MethodDescriptor$Marshaller;
      50: invokevirtual #14                 // Method io/grpc/MethodDescriptor$Builder.setRequestMarshaller:(Lio/grpc/MethodDescriptor$Marshaller;)Lio/grpc/MethodDescriptor$Builder;
      53: invokestatic  #32                 // Method io/etcd/jetcd/api/AuthUserAddResponse.getDefaultInstance:()Lio/etcd/jetcd/api/AuthUserAddResponse;
      56: invokestatic  #13                 // Method io/grpc/protobuf/ProtoUtils.marshaller:(Lcom/google/protobuf/Message;)Lio/grpc/MethodDescriptor$Marshaller;
      59: invokevirtual #16                 // Method io/grpc/MethodDescriptor$Builder.setResponseMarshaller:(Lio/grpc/MethodDescriptor$Marshaller;)Lio/grpc/MethodDescriptor$Builder;
      62: new           #17                 // class io/etcd/jetcd/api/AuthGrpc$AuthMethodDescriptorSupplier
      65: dup
      66: ldc           #30                 // String UserAdd
      68: invokespecial #18                 // Method io/etcd/jetcd/api/AuthGrpc$AuthMethodDescriptorSupplier."<init>":(Ljava/lang/String;)V
      71: invokevirtual #19                 // Method io/grpc/MethodDescriptor$Builder.setSchemaDescriptor:(Ljava/lang/Object;)Lio/grpc/MethodDescriptor$Builder;
      74: invokevirtual #20                 // Method io/grpc/MethodDescriptor$Builder.build:()Lio/grpc/MethodDescriptor;
      77: dup
      78: astore_0
      79: putstatic     #29                 // Field getUserAddMethod:Lio/grpc/MethodDescriptor;
      82: aload_1
      83: monitorexit
      84: goto          92
      87: astore_2
      88: aload_1
      89: monitorexit
      90: aload_2
      91: athrow
      92: aload_0
      93: areturn
    Exception table:
       from    to  target type
          13    84    87   any
          87    90    87   any

  public static io.grpc.MethodDescriptor<io.etcd.jetcd.api.AuthUserGetRequest, io.etcd.jetcd.api.AuthUserGetResponse> getUserGetMethod();
    Code:
       0: getstatic     #33                 // Field getUserGetMethod:Lio/grpc/MethodDescriptor;
       3: dup
       4: astore_0
       5: ifnonnull     92
       8: ldc           #3                  // class io/etcd/jetcd/api/AuthGrpc
      10: dup
      11: astore_1
      12: monitorenter
      13: getstatic     #33                 // Field getUserGetMethod:Lio/grpc/MethodDescriptor;
      16: dup
      17: astore_0
      18: ifnonnull     82
      21: invokestatic  #4                  // Method io/grpc/MethodDescriptor.newBuilder:()Lio/grpc/MethodDescriptor$Builder;
      24: getstatic     #5                  // Field io/grpc/MethodDescriptor$MethodType.UNARY:Lio/grpc/MethodDescriptor$MethodType;
      27: invokevirtual #6                  // Method io/grpc/MethodDescriptor$Builder.setType:(Lio/grpc/MethodDescriptor$MethodType;)Lio/grpc/MethodDescriptor$Builder;
      30: ldc           #7                  // String etcdserverpb.Auth
      32: ldc           #34                 // String UserGet
      34: invokestatic  #9                  // Method io/grpc/MethodDescriptor.generateFullMethodName:(Ljava/lang/String;Ljava/lang/String;)Ljava/lang/String;
      37: invokevirtual #10                 // Method io/grpc/MethodDescriptor$Builder.setFullMethodName:(Ljava/lang/String;)Lio/grpc/MethodDescriptor$Builder;
      40: iconst_1
      41: invokevirtual #11                 // Method io/grpc/MethodDescriptor$Builder.setSampledToLocalTracing:(Z)Lio/grpc/MethodDescriptor$Builder;
      44: invokestatic  #35                 // Method io/etcd/jetcd/api/AuthUserGetRequest.getDefaultInstance:()Lio/etcd/jetcd/api/AuthUserGetRequest;
      47: invokestatic  #13                 // Method io/grpc/protobuf/ProtoUtils.marshaller:(Lcom/google/protobuf/Message;)Lio/grpc/MethodDescriptor$Marshaller;
      50: invokevirtual #14                 // Method io/grpc/MethodDescriptor$Builder.setRequestMarshaller:(Lio/grpc/MethodDescriptor$Marshaller;)Lio/grpc/MethodDescriptor$Builder;
      53: invokestatic  #36                 // Method io/etcd/jetcd/api/AuthUserGetResponse.getDefaultInstance:()Lio/etcd/jetcd/api/AuthUserGetResponse;
      56: invokestatic  #13                 // Method io/grpc/protobuf/ProtoUtils.marshaller:(Lcom/google/protobuf/Message;)Lio/grpc/MethodDescriptor$Marshaller;
      59: invokevirtual #16                 // Method io/grpc/MethodDescriptor$Builder.setResponseMarshaller:(Lio/grpc/MethodDescriptor$Marshaller;)Lio/grpc/MethodDescriptor$Builder;
      62: new           #17                 // class io/etcd/jetcd/api/AuthGrpc$AuthMethodDescriptorSupplier
      65: dup
      66: ldc           #34                 // String UserGet
      68: invokespecial #18                 // Method io/etcd/jetcd/api/AuthGrpc$AuthMethodDescriptorSupplier."<init>":(Ljava/lang/String;)V
      71: invokevirtual #19                 // Method io/grpc/MethodDescriptor$Builder.setSchemaDescriptor:(Ljava/lang/Object;)Lio/grpc/MethodDescriptor$Builder;
      74: invokevirtual #20                 // Method io/grpc/MethodDescriptor$Builder.build:()Lio/grpc/MethodDescriptor;
      77: dup
      78: astore_0
      79: putstatic     #33                 // Field getUserGetMethod:Lio/grpc/MethodDescriptor;
      82: aload_1
      83: monitorexit
      84: goto          92
      87: astore_2
      88: aload_1
      89: monitorexit
      90: aload_2
      91: athrow
      92: aload_0
      93: areturn
    Exception table:
       from    to  target type
          13    84    87   any
          87    90    87   any

  public static io.grpc.MethodDescriptor<io.etcd.jetcd.api.AuthUserListRequest, io.etcd.jetcd.api.AuthUserListResponse> getUserListMethod();
    Code:
       0: getstatic     #37                 // Field getUserListMethod:Lio/grpc/MethodDescriptor;
       3: dup
       4: astore_0
       5: ifnonnull     92
       8: ldc           #3                  // class io/etcd/jetcd/api/AuthGrpc
      10: dup
      11: astore_1
      12: monitorenter
      13: getstatic     #37                 // Field getUserListMethod:Lio/grpc/MethodDescriptor;
      16: dup
      17: astore_0
      18: ifnonnull     82
      21: invokestatic  #4                  // Method io/grpc/MethodDescriptor.newBuilder:()Lio/grpc/MethodDescriptor$Builder;
      24: getstatic     #5                  // Field io/grpc/MethodDescriptor$MethodType.UNARY:Lio/grpc/MethodDescriptor$MethodType;
      27: invokevirtual #6                  // Method io/grpc/MethodDescriptor$Builder.setType:(Lio/grpc/MethodDescriptor$MethodType;)Lio/grpc/MethodDescriptor$Builder;
      30: ldc           #7                  // String etcdserverpb.Auth
      32: ldc           #38                 // String UserList
      34: invokestatic  #9                  // Method io/grpc/MethodDescriptor.generateFullMethodName:(Ljava/lang/String;Ljava/lang/String;)Ljava/lang/String;
      37: invokevirtual #10                 // Method io/grpc/MethodDescriptor$Builder.setFullMethodName:(Ljava/lang/String;)Lio/grpc/MethodDescriptor$Builder;
      40: iconst_1
      41: invokevirtual #11                 // Method io/grpc/MethodDescriptor$Builder.setSampledToLocalTracing:(Z)Lio/grpc/MethodDescriptor$Builder;
      44: invokestatic  #39                 // Method io/etcd/jetcd/api/AuthUserListRequest.getDefaultInstance:()Lio/etcd/jetcd/api/AuthUserListRequest;
      47: invokestatic  #13                 // Method io/grpc/protobuf/ProtoUtils.marshaller:(Lcom/google/protobuf/Message;)Lio/grpc/MethodDescriptor$Marshaller;
      50: invokevirtual #14                 // Method io/grpc/MethodDescriptor$Builder.setRequestMarshaller:(Lio/grpc/MethodDescriptor$Marshaller;)Lio/grpc/MethodDescriptor$Builder;
      53: invokestatic  #40                 // Method io/etcd/jetcd/api/AuthUserListResponse.getDefaultInstance:()Lio/etcd/jetcd/api/AuthUserListResponse;
      56: invokestatic  #13                 // Method io/grpc/protobuf/ProtoUtils.marshaller:(Lcom/google/protobuf/Message;)Lio/grpc/MethodDescriptor$Marshaller;
      59: invokevirtual #16                 // Method io/grpc/MethodDescriptor$Builder.setResponseMarshaller:(Lio/grpc/MethodDescriptor$Marshaller;)Lio/grpc/MethodDescriptor$Builder;
      62: new           #17                 // class io/etcd/jetcd/api/AuthGrpc$AuthMethodDescriptorSupplier
      65: dup
      66: ldc           #38                 // String UserList
      68: invokespecial #18                 // Method io/etcd/jetcd/api/AuthGrpc$AuthMethodDescriptorSupplier."<init>":(Ljava/lang/String;)V
      71: invokevirtual #19                 // Method io/grpc/MethodDescriptor$Builder.setSchemaDescriptor:(Ljava/lang/Object;)Lio/grpc/MethodDescriptor$Builder;
      74: invokevirtual #20                 // Method io/grpc/MethodDescriptor$Builder.build:()Lio/grpc/MethodDescriptor;
      77: dup
      78: astore_0
      79: putstatic     #37                 // Field getUserListMethod:Lio/grpc/MethodDescriptor;
      82: aload_1
      83: monitorexit
      84: goto          92
      87: astore_2
      88: aload_1
      89: monitorexit
      90: aload_2
      91: athrow
      92: aload_0
      93: areturn
    Exception table:
       from    to  target type
          13    84    87   any
          87    90    87   any

  public static io.grpc.MethodDescriptor<io.etcd.jetcd.api.AuthUserDeleteRequest, io.etcd.jetcd.api.AuthUserDeleteResponse> getUserDeleteMethod();
    Code:
       0: getstatic     #41                 // Field getUserDeleteMethod:Lio/grpc/MethodDescriptor;
       3: dup
       4: astore_0
       5: ifnonnull     92
       8: ldc           #3                  // class io/etcd/jetcd/api/AuthGrpc
      10: dup
      11: astore_1
      12: monitorenter
      13: getstatic     #41                 // Field getUserDeleteMethod:Lio/grpc/MethodDescriptor;
      16: dup
      17: astore_0
      18: ifnonnull     82
      21: invokestatic  #4                  // Method io/grpc/MethodDescriptor.newBuilder:()Lio/grpc/MethodDescriptor$Builder;
      24: getstatic     #5                  // Field io/grpc/MethodDescriptor$MethodType.UNARY:Lio/grpc/MethodDescriptor$MethodType;
      27: invokevirtual #6                  // Method io/grpc/MethodDescriptor$Builder.setType:(Lio/grpc/MethodDescriptor$MethodType;)Lio/grpc/MethodDescriptor$Builder;
      30: ldc           #7                  // String etcdserverpb.Auth
      32: ldc           #42                 // String UserDelete
      34: invokestatic  #9                  // Method io/grpc/MethodDescriptor.generateFullMethodName:(Ljava/lang/String;Ljava/lang/String;)Ljava/lang/String;
      37: invokevirtual #10                 // Method io/grpc/MethodDescriptor$Builder.setFullMethodName:(Ljava/lang/String;)Lio/grpc/MethodDescriptor$Builder;
      40: iconst_1
      41: invokevirtual #11                 // Method io/grpc/MethodDescriptor$Builder.setSampledToLocalTracing:(Z)Lio/grpc/MethodDescriptor$Builder;
      44: invokestatic  #43                 // Method io/etcd/jetcd/api/AuthUserDeleteRequest.getDefaultInstance:()Lio/etcd/jetcd/api/AuthUserDeleteRequest;
      47: invokestatic  #13                 // Method io/grpc/protobuf/ProtoUtils.marshaller:(Lcom/google/protobuf/Message;)Lio/grpc/MethodDescriptor$Marshaller;
      50: invokevirtual #14                 // Method io/grpc/MethodDescriptor$Builder.setRequestMarshaller:(Lio/grpc/MethodDescriptor$Marshaller;)Lio/grpc/MethodDescriptor$Builder;
      53: invokestatic  #44                 // Method io/etcd/jetcd/api/AuthUserDeleteResponse.getDefaultInstance:()Lio/etcd/jetcd/api/AuthUserDeleteResponse;
      56: invokestatic  #13                 // Method io/grpc/protobuf/ProtoUtils.marshaller:(Lcom/google/protobuf/Message;)Lio/grpc/MethodDescriptor$Marshaller;
      59: invokevirtual #16                 // Method io/grpc/MethodDescriptor$Builder.setResponseMarshaller:(Lio/grpc/MethodDescriptor$Marshaller;)Lio/grpc/MethodDescriptor$Builder;
      62: new           #17                 // class io/etcd/jetcd/api/AuthGrpc$AuthMethodDescriptorSupplier
      65: dup
      66: ldc           #42                 // String UserDelete
      68: invokespecial #18                 // Method io/etcd/jetcd/api/AuthGrpc$AuthMethodDescriptorSupplier."<init>":(Ljava/lang/String;)V
      71: invokevirtual #19                 // Method io/grpc/MethodDescriptor$Builder.setSchemaDescriptor:(Ljava/lang/Object;)Lio/grpc/MethodDescriptor$Builder;
      74: invokevirtual #20                 // Method io/grpc/MethodDescriptor$Builder.build:()Lio/grpc/MethodDescriptor;
      77: dup
      78: astore_0
      79: putstatic     #41                 // Field getUserDeleteMethod:Lio/grpc/MethodDescriptor;
      82: aload_1
      83: monitorexit
      84: goto          92
      87: astore_2
      88: aload_1
      89: monitorexit
      90: aload_2
      91: athrow
      92: aload_0
      93: areturn
    Exception table:
       from    to  target type
          13    84    87   any
          87    90    87   any

  public static io.grpc.MethodDescriptor<io.etcd.jetcd.api.AuthUserChangePasswordRequest, io.etcd.jetcd.api.AuthUserChangePasswordResponse> getUserChangePasswordMethod();
    Code:
       0: getstatic     #45                 // Field getUserChangePasswordMethod:Lio/grpc/MethodDescriptor;
       3: dup
       4: astore_0
       5: ifnonnull     92
       8: ldc           #3                  // class io/etcd/jetcd/api/AuthGrpc
      10: dup
      11: astore_1
      12: monitorenter
      13: getstatic     #45                 // Field getUserChangePasswordMethod:Lio/grpc/MethodDescriptor;
      16: dup
      17: astore_0
      18: ifnonnull     82
      21: invokestatic  #4                  // Method io/grpc/MethodDescriptor.newBuilder:()Lio/grpc/MethodDescriptor$Builder;
      24: getstatic     #5                  // Field io/grpc/MethodDescriptor$MethodType.UNARY:Lio/grpc/MethodDescriptor$MethodType;
      27: invokevirtual #6                  // Method io/grpc/MethodDescriptor$Builder.setType:(Lio/grpc/MethodDescriptor$MethodType;)Lio/grpc/MethodDescriptor$Builder;
      30: ldc           #7                  // String etcdserverpb.Auth
      32: ldc           #46                 // String UserChangePassword
      34: invokestatic  #9                  // Method io/grpc/MethodDescriptor.generateFullMethodName:(Ljava/lang/String;Ljava/lang/String;)Ljava/lang/String;
      37: invokevirtual #10                 // Method io/grpc/MethodDescriptor$Builder.setFullMethodName:(Ljava/lang/String;)Lio/grpc/MethodDescriptor$Builder;
      40: iconst_1
      41: invokevirtual #11                 // Method io/grpc/MethodDescriptor$Builder.setSampledToLocalTracing:(Z)Lio/grpc/MethodDescriptor$Builder;
      44: invokestatic  #47                 // Method io/etcd/jetcd/api/AuthUserChangePasswordRequest.getDefaultInstance:()Lio/etcd/jetcd/api/AuthUserChangePasswordRequest;
      47: invokestatic  #13                 // Method io/grpc/protobuf/ProtoUtils.marshaller:(Lcom/google/protobuf/Message;)Lio/grpc/MethodDescriptor$Marshaller;
      50: invokevirtual #14                 // Method io/grpc/MethodDescriptor$Builder.setRequestMarshaller:(Lio/grpc/MethodDescriptor$Marshaller;)Lio/grpc/MethodDescriptor$Builder;
      53: invokestatic  #48                 // Method io/etcd/jetcd/api/AuthUserChangePasswordResponse.getDefaultInstance:()Lio/etcd/jetcd/api/AuthUserChangePasswordResponse;
      56: invokestatic  #13                 // Method io/grpc/protobuf/ProtoUtils.marshaller:(Lcom/google/protobuf/Message;)Lio/grpc/MethodDescriptor$Marshaller;
      59: invokevirtual #16                 // Method io/grpc/MethodDescriptor$Builder.setResponseMarshaller:(Lio/grpc/MethodDescriptor$Marshaller;)Lio/grpc/MethodDescriptor$Builder;
      62: new           #17                 // class io/etcd/jetcd/api/AuthGrpc$AuthMethodDescriptorSupplier
      65: dup
      66: ldc           #46                 // String UserChangePassword
      68: invokespecial #18                 // Method io/etcd/jetcd/api/AuthGrpc$AuthMethodDescriptorSupplier."<init>":(Ljava/lang/String;)V
      71: invokevirtual #19                 // Method io/grpc/MethodDescriptor$Builder.setSchemaDescriptor:(Ljava/lang/Object;)Lio/grpc/MethodDescriptor$Builder;
      74: invokevirtual #20                 // Method io/grpc/MethodDescriptor$Builder.build:()Lio/grpc/MethodDescriptor;
      77: dup
      78: astore_0
      79: putstatic     #45                 // Field getUserChangePasswordMethod:Lio/grpc/MethodDescriptor;
      82: aload_1
      83: monitorexit
      84: goto          92
      87: astore_2
      88: aload_1
      89: monitorexit
      90: aload_2
      91: athrow
      92: aload_0
      93: areturn
    Exception table:
       from    to  target type
          13    84    87   any
          87    90    87   any

  public static io.grpc.MethodDescriptor<io.etcd.jetcd.api.AuthUserGrantRoleRequest, io.etcd.jetcd.api.AuthUserGrantRoleResponse> getUserGrantRoleMethod();
    Code:
       0: getstatic     #49                 // Field getUserGrantRoleMethod:Lio/grpc/MethodDescriptor;
       3: dup
       4: astore_0
       5: ifnonnull     92
       8: ldc           #3                  // class io/etcd/jetcd/api/AuthGrpc
      10: dup
      11: astore_1
      12: monitorenter
      13: getstatic     #49                 // Field getUserGrantRoleMethod:Lio/grpc/MethodDescriptor;
      16: dup
      17: astore_0
      18: ifnonnull     82
      21: invokestatic  #4                  // Method io/grpc/MethodDescriptor.newBuilder:()Lio/grpc/MethodDescriptor$Builder;
      24: getstatic     #5                  // Field io/grpc/MethodDescriptor$MethodType.UNARY:Lio/grpc/MethodDescriptor$MethodType;
      27: invokevirtual #6                  // Method io/grpc/MethodDescriptor$Builder.setType:(Lio/grpc/MethodDescriptor$MethodType;)Lio/grpc/MethodDescriptor$Builder;
      30: ldc           #7                  // String etcdserverpb.Auth
      32: ldc           #50                 // String UserGrantRole
      34: invokestatic  #9                  // Method io/grpc/MethodDescriptor.generateFullMethodName:(Ljava/lang/String;Ljava/lang/String;)Ljava/lang/String;
      37: invokevirtual #10                 // Method io/grpc/MethodDescriptor$Builder.setFullMethodName:(Ljava/lang/String;)Lio/grpc/MethodDescriptor$Builder;
      40: iconst_1
      41: invokevirtual #11                 // Method io/grpc/MethodDescriptor$Builder.setSampledToLocalTracing:(Z)Lio/grpc/MethodDescriptor$Builder;
      44: invokestatic  #51                 // Method io/etcd/jetcd/api/AuthUserGrantRoleRequest.getDefaultInstance:()Lio/etcd/jetcd/api/AuthUserGrantRoleRequest;
      47: invokestatic  #13                 // Method io/grpc/protobuf/ProtoUtils.marshaller:(Lcom/google/protobuf/Message;)Lio/grpc/MethodDescriptor$Marshaller;
      50: invokevirtual #14                 // Method io/grpc/MethodDescriptor$Builder.setRequestMarshaller:(Lio/grpc/MethodDescriptor$Marshaller;)Lio/grpc/MethodDescriptor$Builder;
      53: invokestatic  #52                 // Method io/etcd/jetcd/api/AuthUserGrantRoleResponse.getDefaultInstance:()Lio/etcd/jetcd/api/AuthUserGrantRoleResponse;
      56: invokestatic  #13                 // Method io/grpc/protobuf/ProtoUtils.marshaller:(Lcom/google/protobuf/Message;)Lio/grpc/MethodDescriptor$Marshaller;
      59: invokevirtual #16                 // Method io/grpc/MethodDescriptor$Builder.setResponseMarshaller:(Lio/grpc/MethodDescriptor$Marshaller;)Lio/grpc/MethodDescriptor$Builder;
      62: new           #17                 // class io/etcd/jetcd/api/AuthGrpc$AuthMethodDescriptorSupplier
      65: dup
      66: ldc           #50                 // String UserGrantRole
      68: invokespecial #18                 // Method io/etcd/jetcd/api/AuthGrpc$AuthMethodDescriptorSupplier."<init>":(Ljava/lang/String;)V
      71: invokevirtual #19                 // Method io/grpc/MethodDescriptor$Builder.setSchemaDescriptor:(Ljava/lang/Object;)Lio/grpc/MethodDescriptor$Builder;
      74: invokevirtual #20                 // Method io/grpc/MethodDescriptor$Builder.build:()Lio/grpc/MethodDescriptor;
      77: dup
      78: astore_0
      79: putstatic     #49                 // Field getUserGrantRoleMethod:Lio/grpc/MethodDescriptor;
      82: aload_1
      83: monitorexit
      84: goto          92
      87: astore_2
      88: aload_1
      89: monitorexit
      90: aload_2
      91: athrow
      92: aload_0
      93: areturn
    Exception table:
       from    to  target type
          13    84    87   any
          87    90    87   any

  public static io.grpc.MethodDescriptor<io.etcd.jetcd.api.AuthUserRevokeRoleRequest, io.etcd.jetcd.api.AuthUserRevokeRoleResponse> getUserRevokeRoleMethod();
    Code:
       0: getstatic     #53                 // Field getUserRevokeRoleMethod:Lio/grpc/MethodDescriptor;
       3: dup
       4: astore_0
       5: ifnonnull     92
       8: ldc           #3                  // class io/etcd/jetcd/api/AuthGrpc
      10: dup
      11: astore_1
      12: monitorenter
      13: getstatic     #53                 // Field getUserRevokeRoleMethod:Lio/grpc/MethodDescriptor;
      16: dup
      17: astore_0
      18: ifnonnull     82
      21: invokestatic  #4                  // Method io/grpc/MethodDescriptor.newBuilder:()Lio/grpc/MethodDescriptor$Builder;
      24: getstatic     #5                  // Field io/grpc/MethodDescriptor$MethodType.UNARY:Lio/grpc/MethodDescriptor$MethodType;
      27: invokevirtual #6                  // Method io/grpc/MethodDescriptor$Builder.setType:(Lio/grpc/MethodDescriptor$MethodType;)Lio/grpc/MethodDescriptor$Builder;
      30: ldc           #7                  // String etcdserverpb.Auth
      32: ldc           #54                 // String UserRevokeRole
      34: invokestatic  #9                  // Method io/grpc/MethodDescriptor.generateFullMethodName:(Ljava/lang/String;Ljava/lang/String;)Ljava/lang/String;
      37: invokevirtual #10                 // Method io/grpc/MethodDescriptor$Builder.setFullMethodName:(Ljava/lang/String;)Lio/grpc/MethodDescriptor$Builder;
      40: iconst_1
      41: invokevirtual #11                 // Method io/grpc/MethodDescriptor$Builder.setSampledToLocalTracing:(Z)Lio/grpc/MethodDescriptor$Builder;
      44: invokestatic  #55                 // Method io/etcd/jetcd/api/AuthUserRevokeRoleRequest.getDefaultInstance:()Lio/etcd/jetcd/api/AuthUserRevokeRoleRequest;
      47: invokestatic  #13                 // Method io/grpc/protobuf/ProtoUtils.marshaller:(Lcom/google/protobuf/Message;)Lio/grpc/MethodDescriptor$Marshaller;
      50: invokevirtual #14                 // Method io/grpc/MethodDescriptor$Builder.setRequestMarshaller:(Lio/grpc/MethodDescriptor$Marshaller;)Lio/grpc/MethodDescriptor$Builder;
      53: invokestatic  #56                 // Method io/etcd/jetcd/api/AuthUserRevokeRoleResponse.getDefaultInstance:()Lio/etcd/jetcd/api/AuthUserRevokeRoleResponse;
      56: invokestatic  #13                 // Method io/grpc/protobuf/ProtoUtils.marshaller:(Lcom/google/protobuf/Message;)Lio/grpc/MethodDescriptor$Marshaller;
      59: invokevirtual #16                 // Method io/grpc/MethodDescriptor$Builder.setResponseMarshaller:(Lio/grpc/MethodDescriptor$Marshaller;)Lio/grpc/MethodDescriptor$Builder;
      62: new           #17                 // class io/etcd/jetcd/api/AuthGrpc$AuthMethodDescriptorSupplier
      65: dup
      66: ldc           #54                 // String UserRevokeRole
      68: invokespecial #18                 // Method io/etcd/jetcd/api/AuthGrpc$AuthMethodDescriptorSupplier."<init>":(Ljava/lang/String;)V
      71: invokevirtual #19                 // Method io/grpc/MethodDescriptor$Builder.setSchemaDescriptor:(Ljava/lang/Object;)Lio/grpc/MethodDescriptor$Builder;
      74: invokevirtual #20                 // Method io/grpc/MethodDescriptor$Builder.build:()Lio/grpc/MethodDescriptor;
      77: dup
      78: astore_0
      79: putstatic     #53                 // Field getUserRevokeRoleMethod:Lio/grpc/MethodDescriptor;
      82: aload_1
      83: monitorexit
      84: goto          92
      87: astore_2
      88: aload_1
      89: monitorexit
      90: aload_2
      91: athrow
      92: aload_0
      93: areturn
    Exception table:
       from    to  target type
          13    84    87   any
          87    90    87   any

  public static io.grpc.MethodDescriptor<io.etcd.jetcd.api.AuthRoleAddRequest, io.etcd.jetcd.api.AuthRoleAddResponse> getRoleAddMethod();
    Code:
       0: getstatic     #57                 // Field getRoleAddMethod:Lio/grpc/MethodDescriptor;
       3: dup
       4: astore_0
       5: ifnonnull     92
       8: ldc           #3                  // class io/etcd/jetcd/api/AuthGrpc
      10: dup
      11: astore_1
      12: monitorenter
      13: getstatic     #57                 // Field getRoleAddMethod:Lio/grpc/MethodDescriptor;
      16: dup
      17: astore_0
      18: ifnonnull     82
      21: invokestatic  #4                  // Method io/grpc/MethodDescriptor.newBuilder:()Lio/grpc/MethodDescriptor$Builder;
      24: getstatic     #5                  // Field io/grpc/MethodDescriptor$MethodType.UNARY:Lio/grpc/MethodDescriptor$MethodType;
      27: invokevirtual #6                  // Method io/grpc/MethodDescriptor$Builder.setType:(Lio/grpc/MethodDescriptor$MethodType;)Lio/grpc/MethodDescriptor$Builder;
      30: ldc           #7                  // String etcdserverpb.Auth
      32: ldc           #58                 // String RoleAdd
      34: invokestatic  #9                  // Method io/grpc/MethodDescriptor.generateFullMethodName:(Ljava/lang/String;Ljava/lang/String;)Ljava/lang/String;
      37: invokevirtual #10                 // Method io/grpc/MethodDescriptor$Builder.setFullMethodName:(Ljava/lang/String;)Lio/grpc/MethodDescriptor$Builder;
      40: iconst_1
      41: invokevirtual #11                 // Method io/grpc/MethodDescriptor$Builder.setSampledToLocalTracing:(Z)Lio/grpc/MethodDescriptor$Builder;
      44: invokestatic  #59                 // Method io/etcd/jetcd/api/AuthRoleAddRequest.getDefaultInstance:()Lio/etcd/jetcd/api/AuthRoleAddRequest;
      47: invokestatic  #13                 // Method io/grpc/protobuf/ProtoUtils.marshaller:(Lcom/google/protobuf/Message;)Lio/grpc/MethodDescriptor$Marshaller;
      50: invokevirtual #14                 // Method io/grpc/MethodDescriptor$Builder.setRequestMarshaller:(Lio/grpc/MethodDescriptor$Marshaller;)Lio/grpc/MethodDescriptor$Builder;
      53: invokestatic  #60                 // Method io/etcd/jetcd/api/AuthRoleAddResponse.getDefaultInstance:()Lio/etcd/jetcd/api/AuthRoleAddResponse;
      56: invokestatic  #13                 // Method io/grpc/protobuf/ProtoUtils.marshaller:(Lcom/google/protobuf/Message;)Lio/grpc/MethodDescriptor$Marshaller;
      59: invokevirtual #16                 // Method io/grpc/MethodDescriptor$Builder.setResponseMarshaller:(Lio/grpc/MethodDescriptor$Marshaller;)Lio/grpc/MethodDescriptor$Builder;
      62: new           #17                 // class io/etcd/jetcd/api/AuthGrpc$AuthMethodDescriptorSupplier
      65: dup
      66: ldc           #58                 // String RoleAdd
      68: invokespecial #18                 // Method io/etcd/jetcd/api/AuthGrpc$AuthMethodDescriptorSupplier."<init>":(Ljava/lang/String;)V
      71: invokevirtual #19                 // Method io/grpc/MethodDescriptor$Builder.setSchemaDescriptor:(Ljava/lang/Object;)Lio/grpc/MethodDescriptor$Builder;
      74: invokevirtual #20                 // Method io/grpc/MethodDescriptor$Builder.build:()Lio/grpc/MethodDescriptor;
      77: dup
      78: astore_0
      79: putstatic     #57                 // Field getRoleAddMethod:Lio/grpc/MethodDescriptor;
      82: aload_1
      83: monitorexit
      84: goto          92
      87: astore_2
      88: aload_1
      89: monitorexit
      90: aload_2
      91: athrow
      92: aload_0
      93: areturn
    Exception table:
       from    to  target type
          13    84    87   any
          87    90    87   any

  public static io.grpc.MethodDescriptor<io.etcd.jetcd.api.AuthRoleGetRequest, io.etcd.jetcd.api.AuthRoleGetResponse> getRoleGetMethod();
    Code:
       0: getstatic     #61                 // Field getRoleGetMethod:Lio/grpc/MethodDescriptor;
       3: dup
       4: astore_0
       5: ifnonnull     92
       8: ldc           #3                  // class io/etcd/jetcd/api/AuthGrpc
      10: dup
      11: astore_1
      12: monitorenter
      13: getstatic     #61                 // Field getRoleGetMethod:Lio/grpc/MethodDescriptor;
      16: dup
      17: astore_0
      18: ifnonnull     82
      21: invokestatic  #4                  // Method io/grpc/MethodDescriptor.newBuilder:()Lio/grpc/MethodDescriptor$Builder;
      24: getstatic     #5                  // Field io/grpc/MethodDescriptor$MethodType.UNARY:Lio/grpc/MethodDescriptor$MethodType;
      27: invokevirtual #6                  // Method io/grpc/MethodDescriptor$Builder.setType:(Lio/grpc/MethodDescriptor$MethodType;)Lio/grpc/MethodDescriptor$Builder;
      30: ldc           #7                  // String etcdserverpb.Auth
      32: ldc           #62                 // String RoleGet
      34: invokestatic  #9                  // Method io/grpc/MethodDescriptor.generateFullMethodName:(Ljava/lang/String;Ljava/lang/String;)Ljava/lang/String;
      37: invokevirtual #10                 // Method io/grpc/MethodDescriptor$Builder.setFullMethodName:(Ljava/lang/String;)Lio/grpc/MethodDescriptor$Builder;
      40: iconst_1
      41: invokevirtual #11                 // Method io/grpc/MethodDescriptor$Builder.setSampledToLocalTracing:(Z)Lio/grpc/MethodDescriptor$Builder;
      44: invokestatic  #63                 // Method io/etcd/jetcd/api/AuthRoleGetRequest.getDefaultInstance:()Lio/etcd/jetcd/api/AuthRoleGetRequest;
      47: invokestatic  #13                 // Method io/grpc/protobuf/ProtoUtils.marshaller:(Lcom/google/protobuf/Message;)Lio/grpc/MethodDescriptor$Marshaller;
      50: invokevirtual #14                 // Method io/grpc/MethodDescriptor$Builder.setRequestMarshaller:(Lio/grpc/MethodDescriptor$Marshaller;)Lio/grpc/MethodDescriptor$Builder;
      53: invokestatic  #64                 // Method io/etcd/jetcd/api/AuthRoleGetResponse.getDefaultInstance:()Lio/etcd/jetcd/api/AuthRoleGetResponse;
      56: invokestatic  #13                 // Method io/grpc/protobuf/ProtoUtils.marshaller:(Lcom/google/protobuf/Message;)Lio/grpc/MethodDescriptor$Marshaller;
      59: invokevirtual #16                 // Method io/grpc/MethodDescriptor$Builder.setResponseMarshaller:(Lio/grpc/MethodDescriptor$Marshaller;)Lio/grpc/MethodDescriptor$Builder;
      62: new           #17                 // class io/etcd/jetcd/api/AuthGrpc$AuthMethodDescriptorSupplier
      65: dup
      66: ldc           #62                 // String RoleGet
      68: invokespecial #18                 // Method io/etcd/jetcd/api/AuthGrpc$AuthMethodDescriptorSupplier."<init>":(Ljava/lang/String;)V
      71: invokevirtual #19                 // Method io/grpc/MethodDescriptor$Builder.setSchemaDescriptor:(Ljava/lang/Object;)Lio/grpc/MethodDescriptor$Builder;
      74: invokevirtual #20                 // Method io/grpc/MethodDescriptor$Builder.build:()Lio/grpc/MethodDescriptor;
      77: dup
      78: astore_0
      79: putstatic     #61                 // Field getRoleGetMethod:Lio/grpc/MethodDescriptor;
      82: aload_1
      83: monitorexit
      84: goto          92
      87: astore_2
      88: aload_1
      89: monitorexit
      90: aload_2
      91: athrow
      92: aload_0
      93: areturn
    Exception table:
       from    to  target type
          13    84    87   any
          87    90    87   any

  public static io.grpc.MethodDescriptor<io.etcd.jetcd.api.AuthRoleListRequest, io.etcd.jetcd.api.AuthRoleListResponse> getRoleListMethod();
    Code:
       0: getstatic     #65                 // Field getRoleListMethod:Lio/grpc/MethodDescriptor;
       3: dup
       4: astore_0
       5: ifnonnull     92
       8: ldc           #3                  // class io/etcd/jetcd/api/AuthGrpc
      10: dup
      11: astore_1
      12: monitorenter
      13: getstatic     #65                 // Field getRoleListMethod:Lio/grpc/MethodDescriptor;
      16: dup
      17: astore_0
      18: ifnonnull     82
      21: invokestatic  #4                  // Method io/grpc/MethodDescriptor.newBuilder:()Lio/grpc/MethodDescriptor$Builder;
      24: getstatic     #5                  // Field io/grpc/MethodDescriptor$MethodType.UNARY:Lio/grpc/MethodDescriptor$MethodType;
      27: invokevirtual #6                  // Method io/grpc/MethodDescriptor$Builder.setType:(Lio/grpc/MethodDescriptor$MethodType;)Lio/grpc/MethodDescriptor$Builder;
      30: ldc           #7                  // String etcdserverpb.Auth
      32: ldc           #66                 // String RoleList
      34: invokestatic  #9                  // Method io/grpc/MethodDescriptor.generateFullMethodName:(Ljava/lang/String;Ljava/lang/String;)Ljava/lang/String;
      37: invokevirtual #10                 // Method io/grpc/MethodDescriptor$Builder.setFullMethodName:(Ljava/lang/String;)Lio/grpc/MethodDescriptor$Builder;
      40: iconst_1
      41: invokevirtual #11                 // Method io/grpc/MethodDescriptor$Builder.setSampledToLocalTracing:(Z)Lio/grpc/MethodDescriptor$Builder;
      44: invokestatic  #67                 // Method io/etcd/jetcd/api/AuthRoleListRequest.getDefaultInstance:()Lio/etcd/jetcd/api/AuthRoleListRequest;
      47: invokestatic  #13                 // Method io/grpc/protobuf/ProtoUtils.marshaller:(Lcom/google/protobuf/Message;)Lio/grpc/MethodDescriptor$Marshaller;
      50: invokevirtual #14                 // Method io/grpc/MethodDescriptor$Builder.setRequestMarshaller:(Lio/grpc/MethodDescriptor$Marshaller;)Lio/grpc/MethodDescriptor$Builder;
      53: invokestatic  #68                 // Method io/etcd/jetcd/api/AuthRoleListResponse.getDefaultInstance:()Lio/etcd/jetcd/api/AuthRoleListResponse;
      56: invokestatic  #13                 // Method io/grpc/protobuf/ProtoUtils.marshaller:(Lcom/google/protobuf/Message;)Lio/grpc/MethodDescriptor$Marshaller;
      59: invokevirtual #16                 // Method io/grpc/MethodDescriptor$Builder.setResponseMarshaller:(Lio/grpc/MethodDescriptor$Marshaller;)Lio/grpc/MethodDescriptor$Builder;
      62: new           #17                 // class io/etcd/jetcd/api/AuthGrpc$AuthMethodDescriptorSupplier
      65: dup
      66: ldc           #66                 // String RoleList
      68: invokespecial #18                 // Method io/etcd/jetcd/api/AuthGrpc$AuthMethodDescriptorSupplier."<init>":(Ljava/lang/String;)V
      71: invokevirtual #19                 // Method io/grpc/MethodDescriptor$Builder.setSchemaDescriptor:(Ljava/lang/Object;)Lio/grpc/MethodDescriptor$Builder;
      74: invokevirtual #20                 // Method io/grpc/MethodDescriptor$Builder.build:()Lio/grpc/MethodDescriptor;
      77: dup
      78: astore_0
      79: putstatic     #65                 // Field getRoleListMethod:Lio/grpc/MethodDescriptor;
      82: aload_1
      83: monitorexit
      84: goto          92
      87: astore_2
      88: aload_1
      89: monitorexit
      90: aload_2
      91: athrow
      92: aload_0
      93: areturn
    Exception table:
       from    to  target type
          13    84    87   any
          87    90    87   any

  public static io.grpc.MethodDescriptor<io.etcd.jetcd.api.AuthRoleDeleteRequest, io.etcd.jetcd.api.AuthRoleDeleteResponse> getRoleDeleteMethod();
    Code:
       0: getstatic     #69                 // Field getRoleDeleteMethod:Lio/grpc/MethodDescriptor;
       3: dup
       4: astore_0
       5: ifnonnull     92
       8: ldc           #3                  // class io/etcd/jetcd/api/AuthGrpc
      10: dup
      11: astore_1
      12: monitorenter
      13: getstatic     #69                 // Field getRoleDeleteMethod:Lio/grpc/MethodDescriptor;
      16: dup
      17: astore_0
      18: ifnonnull     82
      21: invokestatic  #4                  // Method io/grpc/MethodDescriptor.newBuilder:()Lio/grpc/MethodDescriptor$Builder;
      24: getstatic     #5                  // Field io/grpc/MethodDescriptor$MethodType.UNARY:Lio/grpc/MethodDescriptor$MethodType;
      27: invokevirtual #6                  // Method io/grpc/MethodDescriptor$Builder.setType:(Lio/grpc/MethodDescriptor$MethodType;)Lio/grpc/MethodDescriptor$Builder;
      30: ldc           #7                  // String etcdserverpb.Auth
      32: ldc           #70                 // String RoleDelete
      34: invokestatic  #9                  // Method io/grpc/MethodDescriptor.generateFullMethodName:(Ljava/lang/String;Ljava/lang/String;)Ljava/lang/String;
      37: invokevirtual #10                 // Method io/grpc/MethodDescriptor$Builder.setFullMethodName:(Ljava/lang/String;)Lio/grpc/MethodDescriptor$Builder;
      40: iconst_1
      41: invokevirtual #11                 // Method io/grpc/MethodDescriptor$Builder.setSampledToLocalTracing:(Z)Lio/grpc/MethodDescriptor$Builder;
      44: invokestatic  #71                 // Method io/etcd/jetcd/api/AuthRoleDeleteRequest.getDefaultInstance:()Lio/etcd/jetcd/api/AuthRoleDeleteRequest;
      47: invokestatic  #13                 // Method io/grpc/protobuf/ProtoUtils.marshaller:(Lcom/google/protobuf/Message;)Lio/grpc/MethodDescriptor$Marshaller;
      50: invokevirtual #14                 // Method io/grpc/MethodDescriptor$Builder.setRequestMarshaller:(Lio/grpc/MethodDescriptor$Marshaller;)Lio/grpc/MethodDescriptor$Builder;
      53: invokestatic  #72                 // Method io/etcd/jetcd/api/AuthRoleDeleteResponse.getDefaultInstance:()Lio/etcd/jetcd/api/AuthRoleDeleteResponse;
      56: invokestatic  #13                 // Method io/grpc/protobuf/ProtoUtils.marshaller:(Lcom/google/protobuf/Message;)Lio/grpc/MethodDescriptor$Marshaller;
      59: invokevirtual #16                 // Method io/grpc/MethodDescriptor$Builder.setResponseMarshaller:(Lio/grpc/MethodDescriptor$Marshaller;)Lio/grpc/MethodDescriptor$Builder;
      62: new           #17                 // class io/etcd/jetcd/api/AuthGrpc$AuthMethodDescriptorSupplier
      65: dup
      66: ldc           #70                 // String RoleDelete
      68: invokespecial #18                 // Method io/etcd/jetcd/api/AuthGrpc$AuthMethodDescriptorSupplier."<init>":(Ljava/lang/String;)V
      71: invokevirtual #19                 // Method io/grpc/MethodDescriptor$Builder.setSchemaDescriptor:(Ljava/lang/Object;)Lio/grpc/MethodDescriptor$Builder;
      74: invokevirtual #20                 // Method io/grpc/MethodDescriptor$Builder.build:()Lio/grpc/MethodDescriptor;
      77: dup
      78: astore_0
      79: putstatic     #69                 // Field getRoleDeleteMethod:Lio/grpc/MethodDescriptor;
      82: aload_1
      83: monitorexit
      84: goto          92
      87: astore_2
      88: aload_1
      89: monitorexit
      90: aload_2
      91: athrow
      92: aload_0
      93: areturn
    Exception table:
       from    to  target type
          13    84    87   any
          87    90    87   any

  public static io.grpc.MethodDescriptor<io.etcd.jetcd.api.AuthRoleGrantPermissionRequest, io.etcd.jetcd.api.AuthRoleGrantPermissionResponse> getRoleGrantPermissionMethod();
    Code:
       0: getstatic     #73                 // Field getRoleGrantPermissionMethod:Lio/grpc/MethodDescriptor;
       3: dup
       4: astore_0
       5: ifnonnull     92
       8: ldc           #3                  // class io/etcd/jetcd/api/AuthGrpc
      10: dup
      11: astore_1
      12: monitorenter
      13: getstatic     #73                 // Field getRoleGrantPermissionMethod:Lio/grpc/MethodDescriptor;
      16: dup
      17: astore_0
      18: ifnonnull     82
      21: invokestatic  #4                  // Method io/grpc/MethodDescriptor.newBuilder:()Lio/grpc/MethodDescriptor$Builder;
      24: getstatic     #5                  // Field io/grpc/MethodDescriptor$MethodType.UNARY:Lio/grpc/MethodDescriptor$MethodType;
      27: invokevirtual #6                  // Method io/grpc/MethodDescriptor$Builder.setType:(Lio/grpc/MethodDescriptor$MethodType;)Lio/grpc/MethodDescriptor$Builder;
      30: ldc           #7                  // String etcdserverpb.Auth
      32: ldc           #74                 // String RoleGrantPermission
      34: invokestatic  #9                  // Method io/grpc/MethodDescriptor.generateFullMethodName:(Ljava/lang/String;Ljava/lang/String;)Ljava/lang/String;
      37: invokevirtual #10                 // Method io/grpc/MethodDescriptor$Builder.setFullMethodName:(Ljava/lang/String;)Lio/grpc/MethodDescriptor$Builder;
      40: iconst_1
      41: invokevirtual #11                 // Method io/grpc/MethodDescriptor$Builder.setSampledToLocalTracing:(Z)Lio/grpc/MethodDescriptor$Builder;
      44: invokestatic  #75                 // Method io/etcd/jetcd/api/AuthRoleGrantPermissionRequest.getDefaultInstance:()Lio/etcd/jetcd/api/AuthRoleGrantPermissionRequest;
      47: invokestatic  #13                 // Method io/grpc/protobuf/ProtoUtils.marshaller:(Lcom/google/protobuf/Message;)Lio/grpc/MethodDescriptor$Marshaller;
      50: invokevirtual #14                 // Method io/grpc/MethodDescriptor$Builder.setRequestMarshaller:(Lio/grpc/MethodDescriptor$Marshaller;)Lio/grpc/MethodDescriptor$Builder;
      53: invokestatic  #76                 // Method io/etcd/jetcd/api/AuthRoleGrantPermissionResponse.getDefaultInstance:()Lio/etcd/jetcd/api/AuthRoleGrantPermissionResponse;
      56: invokestatic  #13                 // Method io/grpc/protobuf/ProtoUtils.marshaller:(Lcom/google/protobuf/Message;)Lio/grpc/MethodDescriptor$Marshaller;
      59: invokevirtual #16                 // Method io/grpc/MethodDescriptor$Builder.setResponseMarshaller:(Lio/grpc/MethodDescriptor$Marshaller;)Lio/grpc/MethodDescriptor$Builder;
      62: new           #17                 // class io/etcd/jetcd/api/AuthGrpc$AuthMethodDescriptorSupplier
      65: dup
      66: ldc           #74                 // String RoleGrantPermission
      68: invokespecial #18                 // Method io/etcd/jetcd/api/AuthGrpc$AuthMethodDescriptorSupplier."<init>":(Ljava/lang/String;)V
      71: invokevirtual #19                 // Method io/grpc/MethodDescriptor$Builder.setSchemaDescriptor:(Ljava/lang/Object;)Lio/grpc/MethodDescriptor$Builder;
      74: invokevirtual #20                 // Method io/grpc/MethodDescriptor$Builder.build:()Lio/grpc/MethodDescriptor;
      77: dup
      78: astore_0
      79: putstatic     #73                 // Field getRoleGrantPermissionMethod:Lio/grpc/MethodDescriptor;
      82: aload_1
      83: monitorexit
      84: goto          92
      87: astore_2
      88: aload_1
      89: monitorexit
      90: aload_2
      91: athrow
      92: aload_0
      93: areturn
    Exception table:
       from    to  target type
          13    84    87   any
          87    90    87   any

  public static io.grpc.MethodDescriptor<io.etcd.jetcd.api.AuthRoleRevokePermissionRequest, io.etcd.jetcd.api.AuthRoleRevokePermissionResponse> getRoleRevokePermissionMethod();
    Code:
       0: getstatic     #77                 // Field getRoleRevokePermissionMethod:Lio/grpc/MethodDescriptor;
       3: dup
       4: astore_0
       5: ifnonnull     92
       8: ldc           #3                  // class io/etcd/jetcd/api/AuthGrpc
      10: dup
      11: astore_1
      12: monitorenter
      13: getstatic     #77                 // Field getRoleRevokePermissionMethod:Lio/grpc/MethodDescriptor;
      16: dup
      17: astore_0
      18: ifnonnull     82
      21: invokestatic  #4                  // Method io/grpc/MethodDescriptor.newBuilder:()Lio/grpc/MethodDescriptor$Builder;
      24: getstatic     #5                  // Field io/grpc/MethodDescriptor$MethodType.UNARY:Lio/grpc/MethodDescriptor$MethodType;
      27: invokevirtual #6                  // Method io/grpc/MethodDescriptor$Builder.setType:(Lio/grpc/MethodDescriptor$MethodType;)Lio/grpc/MethodDescriptor$Builder;
      30: ldc           #7                  // String etcdserverpb.Auth
      32: ldc           #78                 // String RoleRevokePermission
      34: invokestatic  #9                  // Method io/grpc/MethodDescriptor.generateFullMethodName:(Ljava/lang/String;Ljava/lang/String;)Ljava/lang/String;
      37: invokevirtual #10                 // Method io/grpc/MethodDescriptor$Builder.setFullMethodName:(Ljava/lang/String;)Lio/grpc/MethodDescriptor$Builder;
      40: iconst_1
      41: invokevirtual #11                 // Method io/grpc/MethodDescriptor$Builder.setSampledToLocalTracing:(Z)Lio/grpc/MethodDescriptor$Builder;
      44: invokestatic  #79                 // Method io/etcd/jetcd/api/AuthRoleRevokePermissionRequest.getDefaultInstance:()Lio/etcd/jetcd/api/AuthRoleRevokePermissionRequest;
      47: invokestatic  #13                 // Method io/grpc/protobuf/ProtoUtils.marshaller:(Lcom/google/protobuf/Message;)Lio/grpc/MethodDescriptor$Marshaller;
      50: invokevirtual #14                 // Method io/grpc/MethodDescriptor$Builder.setRequestMarshaller:(Lio/grpc/MethodDescriptor$Marshaller;)Lio/grpc/MethodDescriptor$Builder;
      53: invokestatic  #80                 // Method io/etcd/jetcd/api/AuthRoleRevokePermissionResponse.getDefaultInstance:()Lio/etcd/jetcd/api/AuthRoleRevokePermissionResponse;
      56: invokestatic  #13                 // Method io/grpc/protobuf/ProtoUtils.marshaller:(Lcom/google/protobuf/Message;)Lio/grpc/MethodDescriptor$Marshaller;
      59: invokevirtual #16                 // Method io/grpc/MethodDescriptor$Builder.setResponseMarshaller:(Lio/grpc/MethodDescriptor$Marshaller;)Lio/grpc/MethodDescriptor$Builder;
      62: new           #17                 // class io/etcd/jetcd/api/AuthGrpc$AuthMethodDescriptorSupplier
      65: dup
      66: ldc           #78                 // String RoleRevokePermission
      68: invokespecial #18                 // Method io/etcd/jetcd/api/AuthGrpc$AuthMethodDescriptorSupplier."<init>":(Ljava/lang/String;)V
      71: invokevirtual #19                 // Method io/grpc/MethodDescriptor$Builder.setSchemaDescriptor:(Ljava/lang/Object;)Lio/grpc/MethodDescriptor$Builder;
      74: invokevirtual #20                 // Method io/grpc/MethodDescriptor$Builder.build:()Lio/grpc/MethodDescriptor;
      77: dup
      78: astore_0
      79: putstatic     #77                 // Field getRoleRevokePermissionMethod:Lio/grpc/MethodDescriptor;
      82: aload_1
      83: monitorexit
      84: goto          92
      87: astore_2
      88: aload_1
      89: monitorexit
      90: aload_2
      91: athrow
      92: aload_0
      93: areturn
    Exception table:
       from    to  target type
          13    84    87   any
          87    90    87   any

  public static io.etcd.jetcd.api.AuthGrpc$AuthStub newStub(io.grpc.Channel);
    Code:
       0: new           #81                 // class io/etcd/jetcd/api/AuthGrpc$1
       3: dup
       4: invokespecial #82                 // Method io/etcd/jetcd/api/AuthGrpc$1."<init>":()V
       7: astore_1
       8: aload_1
       9: aload_0
      10: invokestatic  #83                 // Method io/etcd/jetcd/api/AuthGrpc$AuthStub.newStub:(Lio/grpc/stub/AbstractStub$StubFactory;Lio/grpc/Channel;)Lio/grpc/stub/AbstractStub;
      13: checkcast     #84                 // class io/etcd/jetcd/api/AuthGrpc$AuthStub
      16: areturn

  public static io.etcd.jetcd.api.AuthGrpc$AuthBlockingStub newBlockingStub(io.grpc.Channel);
    Code:
       0: new           #85                 // class io/etcd/jetcd/api/AuthGrpc$2
       3: dup
       4: invokespecial #86                 // Method io/etcd/jetcd/api/AuthGrpc$2."<init>":()V
       7: astore_1
       8: aload_1
       9: aload_0
      10: invokestatic  #87                 // Method io/etcd/jetcd/api/AuthGrpc$AuthBlockingStub.newStub:(Lio/grpc/stub/AbstractStub$StubFactory;Lio/grpc/Channel;)Lio/grpc/stub/AbstractStub;
      13: checkcast     #88                 // class io/etcd/jetcd/api/AuthGrpc$AuthBlockingStub
      16: areturn

  public static io.etcd.jetcd.api.AuthGrpc$AuthFutureStub newFutureStub(io.grpc.Channel);
    Code:
       0: new           #89                 // class io/etcd/jetcd/api/AuthGrpc$3
       3: dup
       4: invokespecial #90                 // Method io/etcd/jetcd/api/AuthGrpc$3."<init>":()V
       7: astore_1
       8: aload_1
       9: aload_0
      10: invokestatic  #91                 // Method io/etcd/jetcd/api/AuthGrpc$AuthFutureStub.newStub:(Lio/grpc/stub/AbstractStub$StubFactory;Lio/grpc/Channel;)Lio/grpc/stub/AbstractStub;
      13: checkcast     #92                 // class io/etcd/jetcd/api/AuthGrpc$AuthFutureStub
      16: areturn

  public static io.grpc.ServiceDescriptor getServiceDescriptor();
    Code:
       0: getstatic     #93                 // Field serviceDescriptor:Lio/grpc/ServiceDescriptor;
       3: astore_0
       4: aload_0
       5: ifnonnull     150
       8: ldc           #3                  // class io/etcd/jetcd/api/AuthGrpc
      10: dup
      11: astore_1
      12: monitorenter
      13: getstatic     #93                 // Field serviceDescriptor:Lio/grpc/ServiceDescriptor;
      16: astore_0
      17: aload_0
      18: ifnonnull     140
      21: ldc           #7                  // String etcdserverpb.Auth
      23: invokestatic  #94                 // Method io/grpc/ServiceDescriptor.newBuilder:(Ljava/lang/String;)Lio/grpc/ServiceDescriptor$Builder;
      26: new           #95                 // class io/etcd/jetcd/api/AuthGrpc$AuthFileDescriptorSupplier
      29: dup
      30: invokespecial #96                 // Method io/etcd/jetcd/api/AuthGrpc$AuthFileDescriptorSupplier."<init>":()V
      33: invokevirtual #97                 // Method io/grpc/ServiceDescriptor$Builder.setSchemaDescriptor:(Ljava/lang/Object;)Lio/grpc/ServiceDescriptor$Builder;
      36: invokestatic  #98                 // Method getAuthEnableMethod:()Lio/grpc/MethodDescriptor;
      39: invokevirtual #99                 // Method io/grpc/ServiceDescriptor$Builder.addMethod:(Lio/grpc/MethodDescriptor;)Lio/grpc/ServiceDescriptor$Builder;
      42: invokestatic  #100                // Method getAuthDisableMethod:()Lio/grpc/MethodDescriptor;
      45: invokevirtual #99                 // Method io/grpc/ServiceDescriptor$Builder.addMethod:(Lio/grpc/MethodDescriptor;)Lio/grpc/ServiceDescriptor$Builder;
      48: invokestatic  #101                // Method getAuthenticateMethod:()Lio/grpc/MethodDescriptor;
      51: invokevirtual #99                 // Method io/grpc/ServiceDescriptor$Builder.addMethod:(Lio/grpc/MethodDescriptor;)Lio/grpc/ServiceDescriptor$Builder;
      54: invokestatic  #102                // Method getUserAddMethod:()Lio/grpc/MethodDescriptor;
      57: invokevirtual #99                 // Method io/grpc/ServiceDescriptor$Builder.addMethod:(Lio/grpc/MethodDescriptor;)Lio/grpc/ServiceDescriptor$Builder;
      60: invokestatic  #103                // Method getUserGetMethod:()Lio/grpc/MethodDescriptor;
      63: invokevirtual #99                 // Method io/grpc/ServiceDescriptor$Builder.addMethod:(Lio/grpc/MethodDescriptor;)Lio/grpc/ServiceDescriptor$Builder;
      66: invokestatic  #104                // Method getUserListMethod:()Lio/grpc/MethodDescriptor;
      69: invokevirtual #99                 // Method io/grpc/ServiceDescriptor$Builder.addMethod:(Lio/grpc/MethodDescriptor;)Lio/grpc/ServiceDescriptor$Builder;
      72: invokestatic  #105                // Method getUserDeleteMethod:()Lio/grpc/MethodDescriptor;
      75: invokevirtual #99                 // Method io/grpc/ServiceDescriptor$Builder.addMethod:(Lio/grpc/MethodDescriptor;)Lio/grpc/ServiceDescriptor$Builder;
      78: invokestatic  #106                // Method getUserChangePasswordMethod:()Lio/grpc/MethodDescriptor;
      81: invokevirtual #99                 // Method io/grpc/ServiceDescriptor$Builder.addMethod:(Lio/grpc/MethodDescriptor;)Lio/grpc/ServiceDescriptor$Builder;
      84: invokestatic  #107                // Method getUserGrantRoleMethod:()Lio/grpc/MethodDescriptor;
      87: invokevirtual #99                 // Method io/grpc/ServiceDescriptor$Builder.addMethod:(Lio/grpc/MethodDescriptor;)Lio/grpc/ServiceDescriptor$Builder;
      90: invokestatic  #108                // Method getUserRevokeRoleMethod:()Lio/grpc/MethodDescriptor;
      93: invokevirtual #99                 // Method io/grpc/ServiceDescriptor$Builder.addMethod:(Lio/grpc/MethodDescriptor;)Lio/grpc/ServiceDescriptor$Builder;
      96: invokestatic  #109                // Method getRoleAddMethod:()Lio/grpc/MethodDescriptor;
      99: invokevirtual #99                 // Method io/grpc/ServiceDescriptor$Builder.addMethod:(Lio/grpc/MethodDescriptor;)Lio/grpc/ServiceDescriptor$Builder;
     102: invokestatic  #110                // Method getRoleGetMethod:()Lio/grpc/MethodDescriptor;
     105: invokevirtual #99                 // Method io/grpc/ServiceDescriptor$Builder.addMethod:(Lio/grpc/MethodDescriptor;)Lio/grpc/ServiceDescriptor$Builder;
     108: invokestatic  #111                // Method getRoleListMethod:()Lio/grpc/MethodDescriptor;
     111: invokevirtual #99                 // Method io/grpc/ServiceDescriptor$Builder.addMethod:(Lio/grpc/MethodDescriptor;)Lio/grpc/ServiceDescriptor$Builder;
     114: invokestatic  #112                // Method getRoleDeleteMethod:()Lio/grpc/MethodDescriptor;
     117: invokevirtual #99                 // Method io/grpc/ServiceDescriptor$Builder.addMethod:(Lio/grpc/MethodDescriptor;)Lio/grpc/ServiceDescriptor$Builder;
     120: invokestatic  #113                // Method getRoleGrantPermissionMethod:()Lio/grpc/MethodDescriptor;
     123: invokevirtual #99                 // Method io/grpc/ServiceDescriptor$Builder.addMethod:(Lio/grpc/MethodDescriptor;)Lio/grpc/ServiceDescriptor$Builder;
     126: invokestatic  #114                // Method getRoleRevokePermissionMethod:()Lio/grpc/MethodDescriptor;
     129: invokevirtual #99                 // Method io/grpc/ServiceDescriptor$Builder.addMethod:(Lio/grpc/MethodDescriptor;)Lio/grpc/ServiceDescriptor$Builder;
     132: invokevirtual #115                // Method io/grpc/ServiceDescriptor$Builder.build:()Lio/grpc/ServiceDescriptor;
     135: dup
     136: astore_0
     137: putstatic     #93                 // Field serviceDescriptor:Lio/grpc/ServiceDescriptor;
     140: aload_1
     141: monitorexit
     142: goto          150
     145: astore_2
     146: aload_1
     147: monitorexit
     148: aload_2
     149: athrow
     150: aload_0
     151: areturn
    Exception table:
       from    to  target type
          13   142   145   any
         145   148   145   any
}
