Compiled from "KVGrpc.java"
public final class io.etcd.jetcd.api.KVGrpc$KVBlockingStub extends io.grpc.stub.AbstractBlockingStub<io.etcd.jetcd.api.KVGrpc$KVBlockingStub> {
  private io.etcd.jetcd.api.KVGrpc$KVBlockingStub(io.grpc.Channel, io.grpc.CallOptions);
    Code:
       0: aload_0
       1: aload_1
       2: aload_2
       3: invokespecial #2                  // Method io/grpc/stub/AbstractBlockingStub."<init>":(Lio/grpc/Channel;Lio/grpc/CallOptions;)V
       6: return

  protected io.etcd.jetcd.api.KVGrpc$KVBlockingStub build(io.grpc.Channel, io.grpc.CallOptions);
    Code:
       0: new           #3                  // class io/etcd/jetcd/api/KVGrpc$KVBlockingStub
       3: dup
       4: aload_1
       5: aload_2
       6: invokespecial #1                  // Method "<init>":(Lio/grpc/Channel;Lio/grpc/CallOptions;)V
       9: areturn

  public io.etcd.jetcd.api.RangeResponse range(io.etcd.jetcd.api.RangeRequest);
    Code:
       0: aload_0
       1: invokevirtual #4                  // Method getChannel:()Lio/grpc/Channel;
       4: invokestatic  #5                  // Method io/etcd/jetcd/api/KVGrpc.getRangeMethod:()Lio/grpc/MethodDescriptor;
       7: aload_0
       8: invokevirtual #6                  // Method getCallOptions:()Lio/grpc/CallOptions;
      11: aload_1
      12: invokestatic  #7                  // Method io/grpc/stub/ClientCalls.blockingUnaryCall:(Lio/grpc/Channel;Lio/grpc/MethodDescriptor;Lio/grpc/CallOptions;Ljava/lang/Object;)Ljava/lang/Object;
      15: checkcast     #8                  // class io/etcd/jetcd/api/RangeResponse
      18: areturn

  public io.etcd.jetcd.api.PutResponse put(io.etcd.jetcd.api.PutRequest);
    Code:
       0: aload_0
       1: invokevirtual #4                  // Method getChannel:()Lio/grpc/Channel;
       4: invokestatic  #9                  // Method io/etcd/jetcd/api/KVGrpc.getPutMethod:()Lio/grpc/MethodDescriptor;
       7: aload_0
       8: invokevirtual #6                  // Method getCallOptions:()Lio/grpc/CallOptions;
      11: aload_1
      12: invokestatic  #7                  // Method io/grpc/stub/ClientCalls.blockingUnaryCall:(Lio/grpc/Channel;Lio/grpc/MethodDescriptor;Lio/grpc/CallOptions;Ljava/lang/Object;)Ljava/lang/Object;
      15: checkcast     #10                 // class io/etcd/jetcd/api/PutResponse
      18: areturn

  public io.etcd.jetcd.api.DeleteRangeResponse deleteRange(io.etcd.jetcd.api.DeleteRangeRequest);
    Code:
       0: aload_0
       1: invokevirtual #4                  // Method getChannel:()Lio/grpc/Channel;
       4: invokestatic  #11                 // Method io/etcd/jetcd/api/KVGrpc.getDeleteRangeMethod:()Lio/grpc/MethodDescriptor;
       7: aload_0
       8: invokevirtual #6                  // Method getCallOptions:()Lio/grpc/CallOptions;
      11: aload_1
      12: invokestatic  #7                  // Method io/grpc/stub/ClientCalls.blockingUnaryCall:(Lio/grpc/Channel;Lio/grpc/MethodDescriptor;Lio/grpc/CallOptions;Ljava/lang/Object;)Ljava/lang/Object;
      15: checkcast     #12                 // class io/etcd/jetcd/api/DeleteRangeResponse
      18: areturn

  public io.etcd.jetcd.api.TxnResponse txn(io.etcd.jetcd.api.TxnRequest);
    Code:
       0: aload_0
       1: invokevirtual #4                  // Method getChannel:()Lio/grpc/Channel;
       4: invokestatic  #13                 // Method io/etcd/jetcd/api/KVGrpc.getTxnMethod:()Lio/grpc/MethodDescriptor;
       7: aload_0
       8: invokevirtual #6                  // Method getCallOptions:()Lio/grpc/CallOptions;
      11: aload_1
      12: invokestatic  #7                  // Method io/grpc/stub/ClientCalls.blockingUnaryCall:(Lio/grpc/Channel;Lio/grpc/MethodDescriptor;Lio/grpc/CallOptions;Ljava/lang/Object;)Ljava/lang/Object;
      15: checkcast     #14                 // class io/etcd/jetcd/api/TxnResponse
      18: areturn

  public io.etcd.jetcd.api.CompactionResponse compact(io.etcd.jetcd.api.CompactionRequest);
    Code:
       0: aload_0
       1: invokevirtual #4                  // Method getChannel:()Lio/grpc/Channel;
       4: invokestatic  #15                 // Method io/etcd/jetcd/api/KVGrpc.getCompactMethod:()Lio/grpc/MethodDescriptor;
       7: aload_0
       8: invokevirtual #6                  // Method getCallOptions:()Lio/grpc/CallOptions;
      11: aload_1
      12: invokestatic  #7                  // Method io/grpc/stub/ClientCalls.blockingUnaryCall:(Lio/grpc/Channel;Lio/grpc/MethodDescriptor;Lio/grpc/CallOptions;Ljava/lang/Object;)Ljava/lang/Object;
      15: checkcast     #16                 // class io/etcd/jetcd/api/CompactionResponse
      18: areturn

  protected io.grpc.stub.AbstractStub build(io.grpc.Channel, io.grpc.CallOptions);
    Code:
       0: aload_0
       1: aload_1
       2: aload_2
       3: invokevirtual #17                 // Method build:(Lio/grpc/Channel;Lio/grpc/CallOptions;)Lio/etcd/jetcd/api/KVGrpc$KVBlockingStub;
       6: areturn

  io.etcd.jetcd.api.KVGrpc$KVBlockingStub(io.grpc.Channel, io.grpc.CallOptions, io.etcd.jetcd.api.KVGrpc$1);
    Code:
       0: aload_0
       1: aload_1
       2: aload_2
       3: invokespecial #1                  // Method "<init>":(Lio/grpc/Channel;Lio/grpc/CallOptions;)V
       6: return
}
