Compiled from "RangeRequest.java"
final class io.etcd.jetcd.api.RangeRequest$SortOrder$1 implements com.google.protobuf.Internal$EnumLiteMap<io.etcd.jetcd.api.RangeRequest$SortOrder> {
  io.etcd.jetcd.api.RangeRequest$SortOrder$1();
    Code:
       0: aload_0
       1: invokespecial #1                  // Method java/lang/Object."<init>":()V
       4: return

  public io.etcd.jetcd.api.RangeRequest$SortOrder findValueByNumber(int);
    Code:
       0: iload_1
       1: invokestatic  #2                  // Method io/etcd/jetcd/api/RangeRequest$SortOrder.forNumber:(I)Lio/etcd/jetcd/api/RangeRequest$SortOrder;
       4: areturn

  public com.google.protobuf.Internal$EnumLite findValueByNumber(int);
    Code:
       0: aload_0
       1: iload_1
       2: invokevirtual #3                  // Method findValueByNumber:(I)Lio/etcd/jetcd/api/RangeRequest$SortOrder;
       5: areturn
}
