Compiled from "BeanPropertyName.java"
abstract class org.springframework.boot.context.properties.bind.BeanPropertyName {
  private org.springframework.boot.context.properties.bind.BeanPropertyName();
    Code:
       0: aload_0
       1: invokespecial #1                  // Method java/lang/Object."<init>":()V
       4: return

  public static java.lang.String toDashedForm(java.lang.String);
    Code:
       0: aload_0
       1: iconst_0
       2: invokestatic  #2                  // Method toDashedForm:(Ljava/lang/String;I)Ljava/lang/String;
       5: areturn

  public static java.lang.String toDashedForm(java.lang.String, int);
    Code:
       0: new           #3                  // class java/lang/StringBuilder
       3: dup
       4: invokespecial #4                  // Method java/lang/StringBuilder."<init>":()V
       7: astore_2
       8: aload_0
       9: ldc           #5                  // String _
      11: ldc           #6                  // String -
      13: invokevirtual #7                  // Method java/lang/String.replace:(Ljava/lang/CharSequence;Ljava/lang/CharSequence;)Ljava/lang/String;
      16: invokevirtual #8                  // Method java/lang/String.toCharArray:()[C
      19: astore_3
      20: iload_1
      21: istore        4
      23: iload         4
      25: aload_3
      26: arraylength
      27: if_icmpge     89
      30: aload_3
      31: iload         4
      33: caload
      34: istore        5
      36: iload         5
      38: invokestatic  #9                  // Method java/lang/Character.isUpperCase:(C)Z
      41: ifeq          73
      44: aload_2
      45: invokevirtual #10                 // Method java/lang/StringBuilder.length:()I
      48: ifle          73
      51: aload_2
      52: aload_2
      53: invokevirtual #10                 // Method java/lang/StringBuilder.length:()I
      56: iconst_1
      57: isub
      58: invokevirtual #11                 // Method java/lang/StringBuilder.charAt:(I)C
      61: bipush        45
      63: if_icmpeq     73
      66: aload_2
      67: ldc           #6                  // String -
      69: invokevirtual #12                 // Method java/lang/StringBuilder.append:(Ljava/lang/String;)Ljava/lang/StringBuilder;
      72: pop
      73: aload_2
      74: iload         5
      76: invokestatic  #13                 // Method java/lang/Character.toLowerCase:(C)C
      79: invokevirtual #14                 // Method java/lang/StringBuilder.append:(C)Ljava/lang/StringBuilder;
      82: pop
      83: iinc          4, 1
      86: goto          23
      89: aload_2
      90: invokevirtual #15                 // Method java/lang/StringBuilder.toString:()Ljava/lang/String;
      93: areturn
}
