Compiled from "ATNDeserializationOptions.java"
public class org.antlr.v4.runtime.atn.ATNDeserializationOptions {
  private static final org.antlr.v4.runtime.atn.ATNDeserializationOptions defaultOptions;

  private boolean readOnly;

  private boolean verifyATN;

  private boolean generateRuleBypassTransitions;

  public org.antlr.v4.runtime.atn.ATNDeserializationOptions();
    Code:
       0: aload_0
       1: invokespecial #1                  // Method java/lang/Object."<init>":()V
       4: aload_0
       5: iconst_1
       6: putfield      #2                  // Field verifyATN:Z
       9: aload_0
      10: iconst_0
      11: putfield      #3                  // Field generateRuleBypassTransitions:Z
      14: return

  public org.antlr.v4.runtime.atn.ATNDeserializationOptions(org.antlr.v4.runtime.atn.ATNDeserializationOptions);
    Code:
       0: aload_0
       1: invokespecial #1                  // Method java/lang/Object."<init>":()V
       4: aload_0
       5: aload_1
       6: getfield      #2                  // Field verifyATN:Z
       9: putfield      #2                  // Field verifyATN:Z
      12: aload_0
      13: aload_1
      14: getfield      #3                  // Field generateRuleBypassTransitions:Z
      17: putfield      #3                  // Field generateRuleBypassTransitions:Z
      20: return

  public static org.antlr.v4.runtime.atn.ATNDeserializationOptions getDefaultOptions();
    Code:
       0: getstatic     #4                  // Field defaultOptions:Lorg/antlr/v4/runtime/atn/ATNDeserializationOptions;
       3: areturn

  public final boolean isReadOnly();
    Code:
       0: aload_0
       1: getfield      #5                  // Field readOnly:Z
       4: ireturn

  public final void makeReadOnly();
    Code:
       0: aload_0
       1: iconst_1
       2: putfield      #5                  // Field readOnly:Z
       5: return

  public final boolean isVerifyATN();
    Code:
       0: aload_0
       1: getfield      #2                  // Field verifyATN:Z
       4: ireturn

  public final void setVerifyATN(boolean);
    Code:
       0: aload_0
       1: invokevirtual #6                  // Method throwIfReadOnly:()V
       4: aload_0
       5: iload_1
       6: putfield      #2                  // Field verifyATN:Z
       9: return

  public final boolean isGenerateRuleBypassTransitions();
    Code:
       0: aload_0
       1: getfield      #3                  // Field generateRuleBypassTransitions:Z
       4: ireturn

  public final void setGenerateRuleBypassTransitions(boolean);
    Code:
       0: aload_0
       1: invokevirtual #6                  // Method throwIfReadOnly:()V
       4: aload_0
       5: iload_1
       6: putfield      #3                  // Field generateRuleBypassTransitions:Z
       9: return

  protected void throwIfReadOnly();
    Code:
       0: aload_0
       1: invokevirtual #7                  // Method isReadOnly:()Z
       4: ifeq          17
       7: new           #8                  // class java/lang/IllegalStateException
      10: dup
      11: ldc           #9                  // String The object is read only.
      13: invokespecial #10                 // Method java/lang/IllegalStateException."<init>":(Ljava/lang/String;)V
      16: athrow
      17: return

  static {};
    Code:
       0: new           #11                 // class org/antlr/v4/runtime/atn/ATNDeserializationOptions
       3: dup
       4: invokespecial #12                 // Method "<init>":()V
       7: putstatic     #4                  // Field defaultOptions:Lorg/antlr/v4/runtime/atn/ATNDeserializationOptions;
      10: getstatic     #4                  // Field defaultOptions:Lorg/antlr/v4/runtime/atn/ATNDeserializationOptions;
      13: invokevirtual #13                 // Method makeReadOnly:()V
      16: return
}
