Compiled from "RDF_Quad.java"
class org.apache.jena.riot.thrift.wire.RDF_Quad$RDF_QuadStandardScheme extends org.apache.thrift.scheme.StandardScheme<org.apache.jena.riot.thrift.wire.RDF_Quad> {
  private org.apache.jena.riot.thrift.wire.RDF_Quad$RDF_QuadStandardScheme();
    Code:
       0: aload_0
       1: invokespecial #2                  // Method org/apache/thrift/scheme/StandardScheme."<init>":()V
       4: return

  public void read(org.apache.thrift.protocol.TProtocol, org.apache.jena.riot.thrift.wire.RDF_Quad) throws org.apache.thrift.TException;
    Code:
       0: aload_1
       1: invokevirtual #3                  // Method org/apache/thrift/protocol/TProtocol.readStructBegin:()Lorg/apache/thrift/protocol/TStruct;
       4: pop
       5: aload_1
       6: invokevirtual #4                  // Method org/apache/thrift/protocol/TProtocol.readFieldBegin:()Lorg/apache/thrift/protocol/TField;
       9: astore_3
      10: aload_3
      11: getfield      #5                  // Field org/apache/thrift/protocol/TField.type:B
      14: ifne          20
      17: goto          259
      20: aload_3
      21: getfield      #6                  // Field org/apache/thrift/protocol/TField.id:S
      24: tableswitch   { // 1 to 4
                     1: 56
                     2: 103
                     3: 150
                     4: 197
               default: 244
          }
      56: aload_3
      57: getfield      #5                  // Field org/apache/thrift/protocol/TField.type:B
      60: bipush        12
      62: if_icmpne     92
      65: aload_2
      66: new           #8                  // class org/apache/jena/riot/thrift/wire/RDF_Term
      69: dup
      70: invokespecial #9                  // Method org/apache/jena/riot/thrift/wire/RDF_Term."<init>":()V
      73: putfield      #10                 // Field org/apache/jena/riot/thrift/wire/RDF_Quad.S:Lorg/apache/jena/riot/thrift/wire/RDF_Term;
      76: aload_2
      77: getfield      #10                 // Field org/apache/jena/riot/thrift/wire/RDF_Quad.S:Lorg/apache/jena/riot/thrift/wire/RDF_Term;
      80: aload_1
      81: invokevirtual #11                 // Method org/apache/jena/riot/thrift/wire/RDF_Term.read:(Lorg/apache/thrift/protocol/TProtocol;)V
      84: aload_2
      85: iconst_1
      86: invokevirtual #12                 // Method org/apache/jena/riot/thrift/wire/RDF_Quad.setSIsSet:(Z)V
      89: goto          252
      92: aload_1
      93: aload_3
      94: getfield      #5                  // Field org/apache/thrift/protocol/TField.type:B
      97: invokestatic  #13                 // Method org/apache/thrift/protocol/TProtocolUtil.skip:(Lorg/apache/thrift/protocol/TProtocol;B)V
     100: goto          252
     103: aload_3
     104: getfield      #5                  // Field org/apache/thrift/protocol/TField.type:B
     107: bipush        12
     109: if_icmpne     139
     112: aload_2
     113: new           #8                  // class org/apache/jena/riot/thrift/wire/RDF_Term
     116: dup
     117: invokespecial #9                  // Method org/apache/jena/riot/thrift/wire/RDF_Term."<init>":()V
     120: putfield      #14                 // Field org/apache/jena/riot/thrift/wire/RDF_Quad.P:Lorg/apache/jena/riot/thrift/wire/RDF_Term;
     123: aload_2
     124: getfield      #14                 // Field org/apache/jena/riot/thrift/wire/RDF_Quad.P:Lorg/apache/jena/riot/thrift/wire/RDF_Term;
     127: aload_1
     128: invokevirtual #11                 // Method org/apache/jena/riot/thrift/wire/RDF_Term.read:(Lorg/apache/thrift/protocol/TProtocol;)V
     131: aload_2
     132: iconst_1
     133: invokevirtual #15                 // Method org/apache/jena/riot/thrift/wire/RDF_Quad.setPIsSet:(Z)V
     136: goto          252
     139: aload_1
     140: aload_3
     141: getfield      #5                  // Field org/apache/thrift/protocol/TField.type:B
     144: invokestatic  #13                 // Method org/apache/thrift/protocol/TProtocolUtil.skip:(Lorg/apache/thrift/protocol/TProtocol;B)V
     147: goto          252
     150: aload_3
     151: getfield      #5                  // Field org/apache/thrift/protocol/TField.type:B
     154: bipush        12
     156: if_icmpne     186
     159: aload_2
     160: new           #8                  // class org/apache/jena/riot/thrift/wire/RDF_Term
     163: dup
     164: invokespecial #9                  // Method org/apache/jena/riot/thrift/wire/RDF_Term."<init>":()V
     167: putfield      #16                 // Field org/apache/jena/riot/thrift/wire/RDF_Quad.O:Lorg/apache/jena/riot/thrift/wire/RDF_Term;
     170: aload_2
     171: getfield      #16                 // Field org/apache/jena/riot/thrift/wire/RDF_Quad.O:Lorg/apache/jena/riot/thrift/wire/RDF_Term;
     174: aload_1
     175: invokevirtual #11                 // Method org/apache/jena/riot/thrift/wire/RDF_Term.read:(Lorg/apache/thrift/protocol/TProtocol;)V
     178: aload_2
     179: iconst_1
     180: invokevirtual #17                 // Method org/apache/jena/riot/thrift/wire/RDF_Quad.setOIsSet:(Z)V
     183: goto          252
     186: aload_1
     187: aload_3
     188: getfield      #5                  // Field org/apache/thrift/protocol/TField.type:B
     191: invokestatic  #13                 // Method org/apache/thrift/protocol/TProtocolUtil.skip:(Lorg/apache/thrift/protocol/TProtocol;B)V
     194: goto          252
     197: aload_3
     198: getfield      #5                  // Field org/apache/thrift/protocol/TField.type:B
     201: bipush        12
     203: if_icmpne     233
     206: aload_2
     207: new           #8                  // class org/apache/jena/riot/thrift/wire/RDF_Term
     210: dup
     211: invokespecial #9                  // Method org/apache/jena/riot/thrift/wire/RDF_Term."<init>":()V
     214: putfield      #18                 // Field org/apache/jena/riot/thrift/wire/RDF_Quad.G:Lorg/apache/jena/riot/thrift/wire/RDF_Term;
     217: aload_2
     218: getfield      #18                 // Field org/apache/jena/riot/thrift/wire/RDF_Quad.G:Lorg/apache/jena/riot/thrift/wire/RDF_Term;
     221: aload_1
     222: invokevirtual #11                 // Method org/apache/jena/riot/thrift/wire/RDF_Term.read:(Lorg/apache/thrift/protocol/TProtocol;)V
     225: aload_2
     226: iconst_1
     227: invokevirtual #19                 // Method org/apache/jena/riot/thrift/wire/RDF_Quad.setGIsSet:(Z)V
     230: goto          252
     233: aload_1
     234: aload_3
     235: getfield      #5                  // Field org/apache/thrift/protocol/TField.type:B
     238: invokestatic  #13                 // Method org/apache/thrift/protocol/TProtocolUtil.skip:(Lorg/apache/thrift/protocol/TProtocol;B)V
     241: goto          252
     244: aload_1
     245: aload_3
     246: getfield      #5                  // Field org/apache/thrift/protocol/TField.type:B
     249: invokestatic  #13                 // Method org/apache/thrift/protocol/TProtocolUtil.skip:(Lorg/apache/thrift/protocol/TProtocol;B)V
     252: aload_1
     253: invokevirtual #20                 // Method org/apache/thrift/protocol/TProtocol.readFieldEnd:()V
     256: goto          5
     259: aload_1
     260: invokevirtual #21                 // Method org/apache/thrift/protocol/TProtocol.readStructEnd:()V
     263: aload_2
     264: invokevirtual #22                 // Method org/apache/jena/riot/thrift/wire/RDF_Quad.validate:()V
     267: return

  public void write(org.apache.thrift.protocol.TProtocol, org.apache.jena.riot.thrift.wire.RDF_Quad) throws org.apache.thrift.TException;
    Code:
       0: aload_2
       1: invokevirtual #22                 // Method org/apache/jena/riot/thrift/wire/RDF_Quad.validate:()V
       4: aload_1
       5: invokestatic  #23                 // Method org/apache/jena/riot/thrift/wire/RDF_Quad.access$300:()Lorg/apache/thrift/protocol/TStruct;
       8: invokevirtual #24                 // Method org/apache/thrift/protocol/TProtocol.writeStructBegin:(Lorg/apache/thrift/protocol/TStruct;)V
      11: aload_2
      12: getfield      #10                 // Field org/apache/jena/riot/thrift/wire/RDF_Quad.S:Lorg/apache/jena/riot/thrift/wire/RDF_Term;
      15: ifnull        37
      18: aload_1
      19: invokestatic  #25                 // Method org/apache/jena/riot/thrift/wire/RDF_Quad.access$400:()Lorg/apache/thrift/protocol/TField;
      22: invokevirtual #26                 // Method org/apache/thrift/protocol/TProtocol.writeFieldBegin:(Lorg/apache/thrift/protocol/TField;)V
      25: aload_2
      26: getfield      #10                 // Field org/apache/jena/riot/thrift/wire/RDF_Quad.S:Lorg/apache/jena/riot/thrift/wire/RDF_Term;
      29: aload_1
      30: invokevirtual #27                 // Method org/apache/jena/riot/thrift/wire/RDF_Term.write:(Lorg/apache/thrift/protocol/TProtocol;)V
      33: aload_1
      34: invokevirtual #28                 // Method org/apache/thrift/protocol/TProtocol.writeFieldEnd:()V
      37: aload_2
      38: getfield      #14                 // Field org/apache/jena/riot/thrift/wire/RDF_Quad.P:Lorg/apache/jena/riot/thrift/wire/RDF_Term;
      41: ifnull        63
      44: aload_1
      45: invokestatic  #29                 // Method org/apache/jena/riot/thrift/wire/RDF_Quad.access$500:()Lorg/apache/thrift/protocol/TField;
      48: invokevirtual #26                 // Method org/apache/thrift/protocol/TProtocol.writeFieldBegin:(Lorg/apache/thrift/protocol/TField;)V
      51: aload_2
      52: getfield      #14                 // Field org/apache/jena/riot/thrift/wire/RDF_Quad.P:Lorg/apache/jena/riot/thrift/wire/RDF_Term;
      55: aload_1
      56: invokevirtual #27                 // Method org/apache/jena/riot/thrift/wire/RDF_Term.write:(Lorg/apache/thrift/protocol/TProtocol;)V
      59: aload_1
      60: invokevirtual #28                 // Method org/apache/thrift/protocol/TProtocol.writeFieldEnd:()V
      63: aload_2
      64: getfield      #16                 // Field org/apache/jena/riot/thrift/wire/RDF_Quad.O:Lorg/apache/jena/riot/thrift/wire/RDF_Term;
      67: ifnull        89
      70: aload_1
      71: invokestatic  #30                 // Method org/apache/jena/riot/thrift/wire/RDF_Quad.access$600:()Lorg/apache/thrift/protocol/TField;
      74: invokevirtual #26                 // Method org/apache/thrift/protocol/TProtocol.writeFieldBegin:(Lorg/apache/thrift/protocol/TField;)V
      77: aload_2
      78: getfield      #16                 // Field org/apache/jena/riot/thrift/wire/RDF_Quad.O:Lorg/apache/jena/riot/thrift/wire/RDF_Term;
      81: aload_1
      82: invokevirtual #27                 // Method org/apache/jena/riot/thrift/wire/RDF_Term.write:(Lorg/apache/thrift/protocol/TProtocol;)V
      85: aload_1
      86: invokevirtual #28                 // Method org/apache/thrift/protocol/TProtocol.writeFieldEnd:()V
      89: aload_2
      90: getfield      #18                 // Field org/apache/jena/riot/thrift/wire/RDF_Quad.G:Lorg/apache/jena/riot/thrift/wire/RDF_Term;
      93: ifnull        122
      96: aload_2
      97: invokevirtual #31                 // Method org/apache/jena/riot/thrift/wire/RDF_Quad.isSetG:()Z
     100: ifeq          122
     103: aload_1
     104: invokestatic  #32                 // Method org/apache/jena/riot/thrift/wire/RDF_Quad.access$700:()Lorg/apache/thrift/protocol/TField;
     107: invokevirtual #26                 // Method org/apache/thrift/protocol/TProtocol.writeFieldBegin:(Lorg/apache/thrift/protocol/TField;)V
     110: aload_2
     111: getfield      #18                 // Field org/apache/jena/riot/thrift/wire/RDF_Quad.G:Lorg/apache/jena/riot/thrift/wire/RDF_Term;
     114: aload_1
     115: invokevirtual #27                 // Method org/apache/jena/riot/thrift/wire/RDF_Term.write:(Lorg/apache/thrift/protocol/TProtocol;)V
     118: aload_1
     119: invokevirtual #28                 // Method org/apache/thrift/protocol/TProtocol.writeFieldEnd:()V
     122: aload_1
     123: invokevirtual #33                 // Method org/apache/thrift/protocol/TProtocol.writeFieldStop:()V
     126: aload_1
     127: invokevirtual #34                 // Method org/apache/thrift/protocol/TProtocol.writeStructEnd:()V
     130: return

  public void write(org.apache.thrift.protocol.TProtocol, org.apache.thrift.TBase) throws org.apache.thrift.TException;
    Code:
       0: aload_0
       1: aload_1
       2: aload_2
       3: checkcast     #35                 // class org/apache/jena/riot/thrift/wire/RDF_Quad
       6: invokevirtual #36                 // Method write:(Lorg/apache/thrift/protocol/TProtocol;Lorg/apache/jena/riot/thrift/wire/RDF_Quad;)V
       9: return

  public void read(org.apache.thrift.protocol.TProtocol, org.apache.thrift.TBase) throws org.apache.thrift.TException;
    Code:
       0: aload_0
       1: aload_1
       2: aload_2
       3: checkcast     #35                 // class org/apache/jena/riot/thrift/wire/RDF_Quad
       6: invokevirtual #37                 // Method read:(Lorg/apache/thrift/protocol/TProtocol;Lorg/apache/jena/riot/thrift/wire/RDF_Quad;)V
       9: return

  org.apache.jena.riot.thrift.wire.RDF_Quad$RDF_QuadStandardScheme(org.apache.jena.riot.thrift.wire.RDF_Quad$1);
    Code:
       0: aload_0
       1: invokespecial #1                  // Method "<init>":()V
       4: return
}
