Compiled from "ErrorPageErrorHandler.java"
public class org.eclipse.jetty.servlet.ErrorPageErrorHandler extends org.eclipse.jetty.server.handler.ErrorHandler implements org.eclipse.jetty.server.handler.ErrorHandler$ErrorPageMapper {
  public static final java.lang.String GLOBAL_ERROR_PAGE;

  private static final org.eclipse.jetty.util.log.Logger LOG;

  protected javax.servlet.ServletContext _servletContext;

  private final java.util.Map<java.lang.String, java.lang.String> _errorPages;

  private final java.util.List<org.eclipse.jetty.servlet.ErrorPageErrorHandler$ErrorCodeRange> _errorPageList;

  public org.eclipse.jetty.servlet.ErrorPageErrorHandler();
    Code:
       0: aload_0
       1: invokespecial #1                  // Method org/eclipse/jetty/server/handler/ErrorHandler."<init>":()V
       4: aload_0
       5: new           #2                  // class java/util/HashMap
       8: dup
       9: invokespecial #3                  // Method java/util/HashMap."<init>":()V
      12: putfield      #4                  // Field _errorPages:Ljava/util/Map;
      15: aload_0
      16: new           #5                  // class java/util/ArrayList
      19: dup
      20: invokespecial #6                  // Method java/util/ArrayList."<init>":()V
      23: putfield      #7                  // Field _errorPageList:Ljava/util/List;
      26: return

  public java.lang.String getErrorPage(javax.servlet.http.HttpServletRequest);
    Code:
       0: aconst_null
       1: astore_2
       2: aconst_null
       3: astore_3
       4: aconst_null
       5: astore        4
       7: aload_1
       8: ldc           #9                  // String javax.servlet.error.exception
      10: invokeinterface #10,  2           // InterfaceMethod javax/servlet/http/HttpServletRequest.getAttribute:(Ljava/lang/String;)Ljava/lang/Object;
      15: checkcast     #11                 // class java/lang/Throwable
      18: astore        5
      20: aload_2
      21: ifnonnull     131
      24: aload         5
      26: ifnull        131
      29: getstatic     #12                 // Field org/eclipse/jetty/servlet/ErrorPageErrorHandler$PageLookupTechnique.THROWABLE:Lorg/eclipse/jetty/servlet/ErrorPageErrorHandler$PageLookupTechnique;
      32: astore_3
      33: aload         5
      35: invokevirtual #13                 // Method java/lang/Object.getClass:()Ljava/lang/Class;
      38: astore        6
      40: aload_0
      41: getfield      #4                  // Field _errorPages:Ljava/util/Map;
      44: aload         6
      46: invokevirtual #14                 // Method java/lang/Class.getName:()Ljava/lang/String;
      49: invokeinterface #15,  2           // InterfaceMethod java/util/Map.get:(Ljava/lang/Object;)Ljava/lang/Object;
      54: checkcast     #16                 // class java/lang/String
      57: astore_2
      58: aload_2
      59: ifnonnull     98
      62: aload         6
      64: invokevirtual #17                 // Method java/lang/Class.getSuperclass:()Ljava/lang/Class;
      67: astore        6
      69: aload         6
      71: ifnonnull     77
      74: goto          98
      77: aload_0
      78: getfield      #4                  // Field _errorPages:Ljava/util/Map;
      81: aload         6
      83: invokevirtual #14                 // Method java/lang/Class.getName:()Ljava/lang/String;
      86: invokeinterface #15,  2           // InterfaceMethod java/util/Map.get:(Ljava/lang/Object;)Ljava/lang/Object;
      91: checkcast     #16                 // class java/lang/String
      94: astore_2
      95: goto          58
      98: aload_2
      99: ifnull        106
     102: aload         6
     104: astore        4
     106: aload         5
     108: instanceof    #18                 // class javax/servlet/ServletException
     111: ifeq          125
     114: aload         5
     116: checkcast     #18                 // class javax/servlet/ServletException
     119: invokevirtual #19                 // Method javax/servlet/ServletException.getRootCause:()Ljava/lang/Throwable;
     122: goto          126
     125: aconst_null
     126: astore        5
     128: goto          20
     131: aconst_null
     132: astore        6
     134: aload_2
     135: ifnonnull     243
     138: getstatic     #20                 // Field org/eclipse/jetty/servlet/ErrorPageErrorHandler$PageLookupTechnique.STATUS_CODE:Lorg/eclipse/jetty/servlet/ErrorPageErrorHandler$PageLookupTechnique;
     141: astore_3
     142: aload_1
     143: ldc           #21                 // String javax.servlet.error.status_code
     145: invokeinterface #10,  2           // InterfaceMethod javax/servlet/http/HttpServletRequest.getAttribute:(Ljava/lang/String;)Ljava/lang/Object;
     150: checkcast     #22                 // class java/lang/Integer
     153: astore        6
     155: aload         6
     157: ifnull        243
     160: aload_0
     161: getfield      #4                  // Field _errorPages:Ljava/util/Map;
     164: aload         6
     166: invokevirtual #23                 // Method java/lang/Integer.intValue:()I
     169: invokestatic  #24                 // Method java/lang/Integer.toString:(I)Ljava/lang/String;
     172: invokeinterface #15,  2           // InterfaceMethod java/util/Map.get:(Ljava/lang/Object;)Ljava/lang/Object;
     177: checkcast     #16                 // class java/lang/String
     180: astore_2
     181: aload_2
     182: ifnonnull     243
     185: aload_0
     186: getfield      #7                  // Field _errorPageList:Ljava/util/List;
     189: invokeinterface #25,  1           // InterfaceMethod java/util/List.iterator:()Ljava/util/Iterator;
     194: astore        7
     196: aload         7
     198: invokeinterface #26,  1           // InterfaceMethod java/util/Iterator.hasNext:()Z
     203: ifeq          243
     206: aload         7
     208: invokeinterface #27,  1           // InterfaceMethod java/util/Iterator.next:()Ljava/lang/Object;
     213: checkcast     #28                 // class org/eclipse/jetty/servlet/ErrorPageErrorHandler$ErrorCodeRange
     216: astore        8
     218: aload         8
     220: aload         6
     222: invokevirtual #23                 // Method java/lang/Integer.intValue:()I
     225: invokevirtual #29                 // Method org/eclipse/jetty/servlet/ErrorPageErrorHandler$ErrorCodeRange.isInRange:(I)Z
     228: ifeq          240
     231: aload         8
     233: invokevirtual #30                 // Method org/eclipse/jetty/servlet/ErrorPageErrorHandler$ErrorCodeRange.getUri:()Ljava/lang/String;
     236: astore_2
     237: goto          243
     240: goto          196
     243: aload_2
     244: ifnonnull     266
     247: getstatic     #31                 // Field org/eclipse/jetty/servlet/ErrorPageErrorHandler$PageLookupTechnique.GLOBAL:Lorg/eclipse/jetty/servlet/ErrorPageErrorHandler$PageLookupTechnique;
     250: astore_3
     251: aload_0
     252: getfield      #4                  // Field _errorPages:Ljava/util/Map;
     255: ldc           #33                 // String org.eclipse.jetty.server.error_page.global
     257: invokeinterface #15,  2           // InterfaceMethod java/util/Map.get:(Ljava/lang/Object;)Ljava/lang/Object;
     262: checkcast     #16                 // class java/lang/String
     265: astore_2
     266: getstatic     #34                 // Field LOG:Lorg/eclipse/jetty/util/log/Logger;
     269: invokeinterface #35,  1           // InterfaceMethod org/eclipse/jetty/util/log/Logger.isDebugEnabled:()Z
     274: ifeq          517
     277: new           #36                 // class java/lang/StringBuilder
     280: dup
     281: invokespecial #37                 // Method java/lang/StringBuilder."<init>":()V
     284: astore        7
     286: aload         7
     288: ldc           #38                 // String getErrorPage(
     290: invokevirtual #39                 // Method java/lang/StringBuilder.append:(Ljava/lang/String;)Ljava/lang/StringBuilder;
     293: pop
     294: aload         7
     296: aload_1
     297: invokeinterface #40,  1           // InterfaceMethod javax/servlet/http/HttpServletRequest.getMethod:()Ljava/lang/String;
     302: invokevirtual #39                 // Method java/lang/StringBuilder.append:(Ljava/lang/String;)Ljava/lang/StringBuilder;
     305: bipush        32
     307: invokevirtual #41                 // Method java/lang/StringBuilder.append:(C)Ljava/lang/StringBuilder;
     310: pop
     311: aload         7
     313: aload_1
     314: invokeinterface #42,  1           // InterfaceMethod javax/servlet/http/HttpServletRequest.getRequestURI:()Ljava/lang/String;
     319: invokevirtual #39                 // Method java/lang/StringBuilder.append:(Ljava/lang/String;)Ljava/lang/StringBuilder;
     322: pop
     323: aload         7
     325: ldc           #43                 // String ) => error_page=
     327: invokevirtual #39                 // Method java/lang/StringBuilder.append:(Ljava/lang/String;)Ljava/lang/StringBuilder;
     330: aload_2
     331: invokevirtual #39                 // Method java/lang/StringBuilder.append:(Ljava/lang/String;)Ljava/lang/StringBuilder;
     334: pop
     335: getstatic     #44                 // Field org/eclipse/jetty/servlet/ErrorPageErrorHandler$1.$SwitchMap$org$eclipse$jetty$servlet$ErrorPageErrorHandler$PageLookupTechnique:[I
     338: aload_3
     339: invokevirtual #45                 // Method org/eclipse/jetty/servlet/ErrorPageErrorHandler$PageLookupTechnique.ordinal:()I
     342: iaload
     343: tableswitch   { // 1 to 3
                     1: 368
                     2: 448
                     3: 492
               default: 517
          }
     368: aload         7
     370: ldc           #46                 // String  (using matched Throwable
     372: invokevirtual #39                 // Method java/lang/StringBuilder.append:(Ljava/lang/String;)Ljava/lang/StringBuilder;
     375: pop
     376: aload         7
     378: aload         4
     380: invokevirtual #14                 // Method java/lang/Class.getName:()Ljava/lang/String;
     383: invokevirtual #39                 // Method java/lang/StringBuilder.append:(Ljava/lang/String;)Ljava/lang/StringBuilder;
     386: pop
     387: aload         7
     389: ldc           #47                 // String  / actually thrown as
     391: invokevirtual #39                 // Method java/lang/StringBuilder.append:(Ljava/lang/String;)Ljava/lang/StringBuilder;
     394: pop
     395: aload_1
     396: ldc           #9                  // String javax.servlet.error.exception
     398: invokeinterface #10,  2           // InterfaceMethod javax/servlet/http/HttpServletRequest.getAttribute:(Ljava/lang/String;)Ljava/lang/Object;
     403: checkcast     #11                 // class java/lang/Throwable
     406: astore        8
     408: aload         7
     410: aload         8
     412: invokevirtual #13                 // Method java/lang/Object.getClass:()Ljava/lang/Class;
     415: invokevirtual #14                 // Method java/lang/Class.getName:()Ljava/lang/String;
     418: invokevirtual #39                 // Method java/lang/StringBuilder.append:(Ljava/lang/String;)Ljava/lang/StringBuilder;
     421: pop
     422: aload         7
     424: bipush        41
     426: invokevirtual #41                 // Method java/lang/StringBuilder.append:(C)Ljava/lang/StringBuilder;
     429: pop
     430: getstatic     #34                 // Field LOG:Lorg/eclipse/jetty/util/log/Logger;
     433: aload         7
     435: invokevirtual #48                 // Method java/lang/StringBuilder.toString:()Ljava/lang/String;
     438: aload         5
     440: invokeinterface #49,  3           // InterfaceMethod org/eclipse/jetty/util/log/Logger.debug:(Ljava/lang/String;Ljava/lang/Throwable;)V
     445: goto          517
     448: aload         7
     450: ldc           #50                 // String  (from status code
     452: invokevirtual #39                 // Method java/lang/StringBuilder.append:(Ljava/lang/String;)Ljava/lang/StringBuilder;
     455: pop
     456: aload         7
     458: aload         6
     460: invokevirtual #51                 // Method java/lang/StringBuilder.append:(Ljava/lang/Object;)Ljava/lang/StringBuilder;
     463: pop
     464: aload         7
     466: bipush        41
     468: invokevirtual #41                 // Method java/lang/StringBuilder.append:(C)Ljava/lang/StringBuilder;
     471: pop
     472: getstatic     #34                 // Field LOG:Lorg/eclipse/jetty/util/log/Logger;
     475: aload         7
     477: invokevirtual #48                 // Method java/lang/StringBuilder.toString:()Ljava/lang/String;
     480: iconst_0
     481: anewarray     #52                 // class java/lang/Object
     484: invokeinterface #53,  3           // InterfaceMethod org/eclipse/jetty/util/log/Logger.debug:(Ljava/lang/String;[Ljava/lang/Object;)V
     489: goto          517
     492: aload         7
     494: ldc           #54                 // String  (from global default)
     496: invokevirtual #39                 // Method java/lang/StringBuilder.append:(Ljava/lang/String;)Ljava/lang/StringBuilder;
     499: pop
     500: getstatic     #34                 // Field LOG:Lorg/eclipse/jetty/util/log/Logger;
     503: aload         7
     505: invokevirtual #48                 // Method java/lang/StringBuilder.toString:()Ljava/lang/String;
     508: iconst_0
     509: anewarray     #52                 // class java/lang/Object
     512: invokeinterface #53,  3           // InterfaceMethod org/eclipse/jetty/util/log/Logger.debug:(Ljava/lang/String;[Ljava/lang/Object;)V
     517: aload_2
     518: areturn

  public java.util.Map<java.lang.String, java.lang.String> getErrorPages();
    Code:
       0: aload_0
       1: getfield      #4                  // Field _errorPages:Ljava/util/Map;
       4: areturn

  public void setErrorPages(java.util.Map<java.lang.String, java.lang.String>);
    Code:
       0: aload_0
       1: getfield      #4                  // Field _errorPages:Ljava/util/Map;
       4: invokeinterface #55,  1           // InterfaceMethod java/util/Map.clear:()V
       9: aload_1
      10: ifnull        23
      13: aload_0
      14: getfield      #4                  // Field _errorPages:Ljava/util/Map;
      17: aload_1
      18: invokeinterface #56,  2           // InterfaceMethod java/util/Map.putAll:(Ljava/util/Map;)V
      23: return

  public void addErrorPage(java.lang.Class<? extends java.lang.Throwable>, java.lang.String);
    Code:
       0: aload_0
       1: getfield      #4                  // Field _errorPages:Ljava/util/Map;
       4: aload_1
       5: invokevirtual #14                 // Method java/lang/Class.getName:()Ljava/lang/String;
       8: aload_2
       9: invokeinterface #57,  3           // InterfaceMethod java/util/Map.put:(Ljava/lang/Object;Ljava/lang/Object;)Ljava/lang/Object;
      14: pop
      15: return

  public void addErrorPage(java.lang.String, java.lang.String);
    Code:
       0: aload_0
       1: getfield      #4                  // Field _errorPages:Ljava/util/Map;
       4: aload_1
       5: aload_2
       6: invokeinterface #57,  3           // InterfaceMethod java/util/Map.put:(Ljava/lang/Object;Ljava/lang/Object;)Ljava/lang/Object;
      11: pop
      12: return

  public void addErrorPage(int, java.lang.String);
    Code:
       0: aload_0
       1: getfield      #4                  // Field _errorPages:Ljava/util/Map;
       4: iload_1
       5: invokestatic  #24                 // Method java/lang/Integer.toString:(I)Ljava/lang/String;
       8: aload_2
       9: invokeinterface #57,  3           // InterfaceMethod java/util/Map.put:(Ljava/lang/Object;Ljava/lang/Object;)Ljava/lang/Object;
      14: pop
      15: return

  public void addErrorPage(int, int, java.lang.String);
    Code:
       0: aload_0
       1: getfield      #7                  // Field _errorPageList:Ljava/util/List;
       4: new           #28                 // class org/eclipse/jetty/servlet/ErrorPageErrorHandler$ErrorCodeRange
       7: dup
       8: iload_1
       9: iload_2
      10: aload_3
      11: invokespecial #58                 // Method org/eclipse/jetty/servlet/ErrorPageErrorHandler$ErrorCodeRange."<init>":(IILjava/lang/String;)V
      14: invokeinterface #59,  2           // InterfaceMethod java/util/List.add:(Ljava/lang/Object;)Z
      19: pop
      20: return

  protected void doStart() throws java.lang.Exception;
    Code:
       0: aload_0
       1: invokespecial #60                 // Method org/eclipse/jetty/server/handler/ErrorHandler.doStart:()V
       4: aload_0
       5: invokestatic  #61                 // Method org/eclipse/jetty/server/handler/ContextHandler.getCurrentContext:()Lorg/eclipse/jetty/server/handler/ContextHandler$Context;
       8: putfield      #62                 // Field _servletContext:Ljavax/servlet/ServletContext;
      11: return

  static {};
    Code:
       0: ldc           #32                 // class org/eclipse/jetty/servlet/ErrorPageErrorHandler
       2: invokestatic  #63                 // Method org/eclipse/jetty/util/log/Log.getLogger:(Ljava/lang/Class;)Lorg/eclipse/jetty/util/log/Logger;
       5: putstatic     #34                 // Field LOG:Lorg/eclipse/jetty/util/log/Logger;
       8: return
}
