Compiled from "ServletHandler.java"
class org.eclipse.jetty.servlet.ServletHandler$ChainEnd implements javax.servlet.FilterChain {
  private final org.eclipse.jetty.servlet.ServletHolder _servletHolder;

  org.eclipse.jetty.servlet.ServletHandler$ChainEnd(org.eclipse.jetty.servlet.ServletHolder);
    Code:
       0: aload_0
       1: invokespecial #1                  // Method java/lang/Object."<init>":()V
       4: aload_1
       5: invokestatic  #2                  // Method java/util/Objects.requireNonNull:(Ljava/lang/Object;)Ljava/lang/Object;
       8: pop
       9: aload_0
      10: aload_1
      11: putfield      #3                  // Field _servletHolder:Lorg/eclipse/jetty/servlet/ServletHolder;
      14: return

  public org.eclipse.jetty.servlet.ServletHolder getServletHolder();
    Code:
       0: aload_0
       1: getfield      #3                  // Field _servletHolder:Lorg/eclipse/jetty/servlet/ServletHolder;
       4: areturn

  public void doFilter(javax.servlet.ServletRequest, javax.servlet.ServletResponse) throws java.io.IOException, javax.servlet.ServletException;
    Code:
       0: aload_1
       1: invokestatic  #4                  // Method org/eclipse/jetty/server/Request.getBaseRequest:(Ljavax/servlet/ServletRequest;)Lorg/eclipse/jetty/server/Request;
       4: astore_3
       5: aload_3
       6: invokestatic  #2                  // Method java/util/Objects.requireNonNull:(Ljava/lang/Object;)Ljava/lang/Object;
       9: pop
      10: aload_0
      11: getfield      #3                  // Field _servletHolder:Lorg/eclipse/jetty/servlet/ServletHolder;
      14: aload_3
      15: aload_1
      16: aload_2
      17: invokevirtual #5                  // Method org/eclipse/jetty/servlet/ServletHolder.handle:(Lorg/eclipse/jetty/server/Request;Ljavax/servlet/ServletRequest;Ljavax/servlet/ServletResponse;)V
      20: return

  public java.lang.String toString();
    Code:
       0: ldc           #6                  // String ChainEnd@%x(%s)
       2: iconst_2
       3: anewarray     #7                  // class java/lang/Object
       6: dup
       7: iconst_0
       8: aload_0
       9: invokevirtual #8                  // Method java/lang/Object.hashCode:()I
      12: invokestatic  #9                  // Method java/lang/Integer.valueOf:(I)Ljava/lang/Integer;
      15: aastore
      16: dup
      17: iconst_1
      18: aload_0
      19: getfield      #3                  // Field _servletHolder:Lorg/eclipse/jetty/servlet/ServletHolder;
      22: aastore
      23: invokestatic  #10                 // Method java/lang/String.format:(Ljava/lang/String;[Ljava/lang/Object;)Ljava/lang/String;
      26: areturn
}
