Compiled from "ServletContextHandler.java"
public class org.eclipse.jetty.servlet.ServletContextHandler$JspPropertyGroup implements javax.servlet.descriptor.JspPropertyGroupDescriptor {
  private final java.util.List<java.lang.String> _urlPatterns;

  private java.lang.String _elIgnored;

  private java.lang.String _pageEncoding;

  private java.lang.String _scriptingInvalid;

  private java.lang.String _isXml;

  private final java.util.List<java.lang.String> _includePreludes;

  private final java.util.List<java.lang.String> _includeCodas;

  private java.lang.String _deferredSyntaxAllowedAsLiteral;

  private java.lang.String _trimDirectiveWhitespaces;

  private java.lang.String _defaultContentType;

  private java.lang.String _buffer;

  private java.lang.String _errorOnUndeclaredNamespace;

  public org.eclipse.jetty.servlet.ServletContextHandler$JspPropertyGroup();
    Code:
       0: aload_0
       1: invokespecial #1                  // Method java/lang/Object."<init>":()V
       4: aload_0
       5: new           #2                  // class java/util/ArrayList
       8: dup
       9: invokespecial #3                  // Method java/util/ArrayList."<init>":()V
      12: putfield      #4                  // Field _urlPatterns:Ljava/util/List;
      15: aload_0
      16: new           #2                  // class java/util/ArrayList
      19: dup
      20: invokespecial #3                  // Method java/util/ArrayList."<init>":()V
      23: putfield      #5                  // Field _includePreludes:Ljava/util/List;
      26: aload_0
      27: new           #2                  // class java/util/ArrayList
      30: dup
      31: invokespecial #3                  // Method java/util/ArrayList."<init>":()V
      34: putfield      #6                  // Field _includeCodas:Ljava/util/List;
      37: return

  public java.util.Collection<java.lang.String> getUrlPatterns();
    Code:
       0: new           #2                  // class java/util/ArrayList
       3: dup
       4: aload_0
       5: getfield      #4                  // Field _urlPatterns:Ljava/util/List;
       8: invokespecial #7                  // Method java/util/ArrayList."<init>":(Ljava/util/Collection;)V
      11: areturn

  public void addUrlPattern(java.lang.String);
    Code:
       0: aload_0
       1: getfield      #4                  // Field _urlPatterns:Ljava/util/List;
       4: aload_1
       5: invokeinterface #8,  2            // InterfaceMethod java/util/List.contains:(Ljava/lang/Object;)Z
      10: ifne          24
      13: aload_0
      14: getfield      #4                  // Field _urlPatterns:Ljava/util/List;
      17: aload_1
      18: invokeinterface #9,  2            // InterfaceMethod java/util/List.add:(Ljava/lang/Object;)Z
      23: pop
      24: return

  public java.lang.String getElIgnored();
    Code:
       0: aload_0
       1: getfield      #10                 // Field _elIgnored:Ljava/lang/String;
       4: areturn

  public void setElIgnored(java.lang.String);
    Code:
       0: aload_0
       1: aload_1
       2: putfield      #10                 // Field _elIgnored:Ljava/lang/String;
       5: return

  public java.lang.String getPageEncoding();
    Code:
       0: aload_0
       1: getfield      #11                 // Field _pageEncoding:Ljava/lang/String;
       4: areturn

  public void setPageEncoding(java.lang.String);
    Code:
       0: aload_0
       1: aload_1
       2: putfield      #11                 // Field _pageEncoding:Ljava/lang/String;
       5: return

  public void setScriptingInvalid(java.lang.String);
    Code:
       0: aload_0
       1: aload_1
       2: putfield      #12                 // Field _scriptingInvalid:Ljava/lang/String;
       5: return

  public void setIsXml(java.lang.String);
    Code:
       0: aload_0
       1: aload_1
       2: putfield      #13                 // Field _isXml:Ljava/lang/String;
       5: return

  public void setDeferredSyntaxAllowedAsLiteral(java.lang.String);
    Code:
       0: aload_0
       1: aload_1
       2: putfield      #14                 // Field _deferredSyntaxAllowedAsLiteral:Ljava/lang/String;
       5: return

  public void setTrimDirectiveWhitespaces(java.lang.String);
    Code:
       0: aload_0
       1: aload_1
       2: putfield      #15                 // Field _trimDirectiveWhitespaces:Ljava/lang/String;
       5: return

  public void setDefaultContentType(java.lang.String);
    Code:
       0: aload_0
       1: aload_1
       2: putfield      #16                 // Field _defaultContentType:Ljava/lang/String;
       5: return

  public void setBuffer(java.lang.String);
    Code:
       0: aload_0
       1: aload_1
       2: putfield      #17                 // Field _buffer:Ljava/lang/String;
       5: return

  public void setErrorOnUndeclaredNamespace(java.lang.String);
    Code:
       0: aload_0
       1: aload_1
       2: putfield      #18                 // Field _errorOnUndeclaredNamespace:Ljava/lang/String;
       5: return

  public java.lang.String getScriptingInvalid();
    Code:
       0: aload_0
       1: getfield      #12                 // Field _scriptingInvalid:Ljava/lang/String;
       4: areturn

  public java.lang.String getIsXml();
    Code:
       0: aload_0
       1: getfield      #13                 // Field _isXml:Ljava/lang/String;
       4: areturn

  public java.util.Collection<java.lang.String> getIncludePreludes();
    Code:
       0: new           #2                  // class java/util/ArrayList
       3: dup
       4: aload_0
       5: getfield      #5                  // Field _includePreludes:Ljava/util/List;
       8: invokespecial #7                  // Method java/util/ArrayList."<init>":(Ljava/util/Collection;)V
      11: areturn

  public void addIncludePrelude(java.lang.String);
    Code:
       0: aload_0
       1: getfield      #5                  // Field _includePreludes:Ljava/util/List;
       4: aload_1
       5: invokeinterface #8,  2            // InterfaceMethod java/util/List.contains:(Ljava/lang/Object;)Z
      10: ifne          24
      13: aload_0
      14: getfield      #5                  // Field _includePreludes:Ljava/util/List;
      17: aload_1
      18: invokeinterface #9,  2            // InterfaceMethod java/util/List.add:(Ljava/lang/Object;)Z
      23: pop
      24: return

  public java.util.Collection<java.lang.String> getIncludeCodas();
    Code:
       0: new           #2                  // class java/util/ArrayList
       3: dup
       4: aload_0
       5: getfield      #6                  // Field _includeCodas:Ljava/util/List;
       8: invokespecial #7                  // Method java/util/ArrayList."<init>":(Ljava/util/Collection;)V
      11: areturn

  public void addIncludeCoda(java.lang.String);
    Code:
       0: aload_0
       1: getfield      #6                  // Field _includeCodas:Ljava/util/List;
       4: aload_1
       5: invokeinterface #8,  2            // InterfaceMethod java/util/List.contains:(Ljava/lang/Object;)Z
      10: ifne          24
      13: aload_0
      14: getfield      #6                  // Field _includeCodas:Ljava/util/List;
      17: aload_1
      18: invokeinterface #9,  2            // InterfaceMethod java/util/List.add:(Ljava/lang/Object;)Z
      23: pop
      24: return

  public java.lang.String getDeferredSyntaxAllowedAsLiteral();
    Code:
       0: aload_0
       1: getfield      #14                 // Field _deferredSyntaxAllowedAsLiteral:Ljava/lang/String;
       4: areturn

  public java.lang.String getTrimDirectiveWhitespaces();
    Code:
       0: aload_0
       1: getfield      #15                 // Field _trimDirectiveWhitespaces:Ljava/lang/String;
       4: areturn

  public java.lang.String getDefaultContentType();
    Code:
       0: aload_0
       1: getfield      #16                 // Field _defaultContentType:Ljava/lang/String;
       4: areturn

  public java.lang.String getBuffer();
    Code:
       0: aload_0
       1: getfield      #17                 // Field _buffer:Ljava/lang/String;
       4: areturn

  public java.lang.String getErrorOnUndeclaredNamespace();
    Code:
       0: aload_0
       1: getfield      #18                 // Field _errorOnUndeclaredNamespace:Ljava/lang/String;
       4: areturn

  public java.lang.String toString();
    Code:
       0: new           #19                 // class java/lang/StringBuilder
       3: dup
       4: invokespecial #20                 // Method java/lang/StringBuilder."<init>":()V
       7: astore_1
       8: aload_1
       9: ldc           #21                 // String JspPropertyGroupDescriptor:
      11: invokevirtual #22                 // Method java/lang/StringBuilder.append:(Ljava/lang/String;)Ljava/lang/StringBuilder;
      14: pop
      15: aload_1
      16: ldc           #23                 // String  el-ignored=
      18: invokevirtual #22                 // Method java/lang/StringBuilder.append:(Ljava/lang/String;)Ljava/lang/StringBuilder;
      21: aload_0
      22: getfield      #10                 // Field _elIgnored:Ljava/lang/String;
      25: invokevirtual #22                 // Method java/lang/StringBuilder.append:(Ljava/lang/String;)Ljava/lang/StringBuilder;
      28: pop
      29: aload_1
      30: ldc           #24                 // String  is-xml=
      32: invokevirtual #22                 // Method java/lang/StringBuilder.append:(Ljava/lang/String;)Ljava/lang/StringBuilder;
      35: aload_0
      36: getfield      #13                 // Field _isXml:Ljava/lang/String;
      39: invokevirtual #22                 // Method java/lang/StringBuilder.append:(Ljava/lang/String;)Ljava/lang/StringBuilder;
      42: pop
      43: aload_1
      44: ldc           #25                 // String  page-encoding=
      46: invokevirtual #22                 // Method java/lang/StringBuilder.append:(Ljava/lang/String;)Ljava/lang/StringBuilder;
      49: aload_0
      50: getfield      #11                 // Field _pageEncoding:Ljava/lang/String;
      53: invokevirtual #22                 // Method java/lang/StringBuilder.append:(Ljava/lang/String;)Ljava/lang/StringBuilder;
      56: pop
      57: aload_1
      58: ldc           #26                 // String  scripting-invalid=
      60: invokevirtual #22                 // Method java/lang/StringBuilder.append:(Ljava/lang/String;)Ljava/lang/StringBuilder;
      63: aload_0
      64: getfield      #12                 // Field _scriptingInvalid:Ljava/lang/String;
      67: invokevirtual #22                 // Method java/lang/StringBuilder.append:(Ljava/lang/String;)Ljava/lang/StringBuilder;
      70: pop
      71: aload_1
      72: ldc           #27                 // String  deferred-syntax-allowed-as-literal=
      74: invokevirtual #22                 // Method java/lang/StringBuilder.append:(Ljava/lang/String;)Ljava/lang/StringBuilder;
      77: aload_0
      78: getfield      #14                 // Field _deferredSyntaxAllowedAsLiteral:Ljava/lang/String;
      81: invokevirtual #22                 // Method java/lang/StringBuilder.append:(Ljava/lang/String;)Ljava/lang/StringBuilder;
      84: pop
      85: aload_1
      86: ldc           #28                 // String  trim-directive-whitespaces
      88: invokevirtual #22                 // Method java/lang/StringBuilder.append:(Ljava/lang/String;)Ljava/lang/StringBuilder;
      91: aload_0
      92: getfield      #15                 // Field _trimDirectiveWhitespaces:Ljava/lang/String;
      95: invokevirtual #22                 // Method java/lang/StringBuilder.append:(Ljava/lang/String;)Ljava/lang/StringBuilder;
      98: pop
      99: aload_1
     100: ldc           #29                 // String  default-content-type=
     102: invokevirtual #22                 // Method java/lang/StringBuilder.append:(Ljava/lang/String;)Ljava/lang/StringBuilder;
     105: aload_0
     106: getfield      #16                 // Field _defaultContentType:Ljava/lang/String;
     109: invokevirtual #22                 // Method java/lang/StringBuilder.append:(Ljava/lang/String;)Ljava/lang/StringBuilder;
     112: pop
     113: aload_1
     114: ldc           #30                 // String  buffer=
     116: invokevirtual #22                 // Method java/lang/StringBuilder.append:(Ljava/lang/String;)Ljava/lang/StringBuilder;
     119: aload_0
     120: getfield      #17                 // Field _buffer:Ljava/lang/String;
     123: invokevirtual #22                 // Method java/lang/StringBuilder.append:(Ljava/lang/String;)Ljava/lang/StringBuilder;
     126: pop
     127: aload_1
     128: ldc           #31                 // String  error-on-undeclared-namespace=
     130: invokevirtual #22                 // Method java/lang/StringBuilder.append:(Ljava/lang/String;)Ljava/lang/StringBuilder;
     133: aload_0
     134: getfield      #18                 // Field _errorOnUndeclaredNamespace:Ljava/lang/String;
     137: invokevirtual #22                 // Method java/lang/StringBuilder.append:(Ljava/lang/String;)Ljava/lang/StringBuilder;
     140: pop
     141: aload_0
     142: getfield      #5                  // Field _includePreludes:Ljava/util/List;
     145: invokeinterface #32,  1           // InterfaceMethod java/util/List.iterator:()Ljava/util/Iterator;
     150: astore_2
     151: aload_2
     152: invokeinterface #33,  1           // InterfaceMethod java/util/Iterator.hasNext:()Z
     157: ifeq          184
     160: aload_2
     161: invokeinterface #34,  1           // InterfaceMethod java/util/Iterator.next:()Ljava/lang/Object;
     166: checkcast     #35                 // class java/lang/String
     169: astore_3
     170: aload_1
     171: ldc           #36                 // String  include-prelude=
     173: invokevirtual #22                 // Method java/lang/StringBuilder.append:(Ljava/lang/String;)Ljava/lang/StringBuilder;
     176: aload_3
     177: invokevirtual #22                 // Method java/lang/StringBuilder.append:(Ljava/lang/String;)Ljava/lang/StringBuilder;
     180: pop
     181: goto          151
     184: aload_0
     185: getfield      #6                  // Field _includeCodas:Ljava/util/List;
     188: invokeinterface #32,  1           // InterfaceMethod java/util/List.iterator:()Ljava/util/Iterator;
     193: astore_2
     194: aload_2
     195: invokeinterface #33,  1           // InterfaceMethod java/util/Iterator.hasNext:()Z
     200: ifeq          227
     203: aload_2
     204: invokeinterface #34,  1           // InterfaceMethod java/util/Iterator.next:()Ljava/lang/Object;
     209: checkcast     #35                 // class java/lang/String
     212: astore_3
     213: aload_1
     214: ldc           #37                 // String  include-coda=
     216: invokevirtual #22                 // Method java/lang/StringBuilder.append:(Ljava/lang/String;)Ljava/lang/StringBuilder;
     219: aload_3
     220: invokevirtual #22                 // Method java/lang/StringBuilder.append:(Ljava/lang/String;)Ljava/lang/StringBuilder;
     223: pop
     224: goto          194
     227: aload_1
     228: invokevirtual #38                 // Method java/lang/StringBuilder.toString:()Ljava/lang/String;
     231: areturn
}
