Compiled from "ServletHolder.java"
class org.eclipse.jetty.servlet.ServletHolder$NotAsync extends org.eclipse.jetty.servlet.ServletHolder$Wrapper {
  public org.eclipse.jetty.servlet.ServletHolder$NotAsync(javax.servlet.Servlet);
    Code:
       0: aload_0
       1: aload_1
       2: invokespecial #1                  // Method org/eclipse/jetty/servlet/ServletHolder$Wrapper."<init>":(Ljavax/servlet/Servlet;)V
       5: return

  public void service(javax.servlet.ServletRequest, javax.servlet.ServletResponse) throws javax.servlet.ServletException, java.io.IOException;
    Code:
       0: aload_1
       1: invokeinterface #2,  1            // InterfaceMethod javax/servlet/ServletRequest.isAsyncSupported:()Z
       6: ifeq          57
       9: aload_1
      10: invokestatic  #3                  // Method org/eclipse/jetty/server/Request.getBaseRequest:(Ljavax/servlet/ServletRequest;)Lorg/eclipse/jetty/server/Request;
      13: astore_3
      14: aload_3
      15: iconst_0
      16: aload_0
      17: invokevirtual #4                  // Method toString:()Ljava/lang/String;
      20: invokevirtual #5                  // Method org/eclipse/jetty/server/Request.setAsyncSupported:(ZLjava/lang/Object;)V
      23: aload_0
      24: invokevirtual #6                  // Method getWrapped:()Ljavax/servlet/Servlet;
      27: aload_1
      28: aload_2
      29: invokeinterface #7,  3            // InterfaceMethod javax/servlet/Servlet.service:(Ljavax/servlet/ServletRequest;Ljavax/servlet/ServletResponse;)V
      34: aload_3
      35: iconst_1
      36: aconst_null
      37: invokevirtual #5                  // Method org/eclipse/jetty/server/Request.setAsyncSupported:(ZLjava/lang/Object;)V
      40: goto          54
      43: astore        4
      45: aload_3
      46: iconst_1
      47: aconst_null
      48: invokevirtual #5                  // Method org/eclipse/jetty/server/Request.setAsyncSupported:(ZLjava/lang/Object;)V
      51: aload         4
      53: athrow
      54: goto          68
      57: aload_0
      58: invokevirtual #6                  // Method getWrapped:()Ljavax/servlet/Servlet;
      61: aload_1
      62: aload_2
      63: invokeinterface #7,  3            // InterfaceMethod javax/servlet/Servlet.service:(Ljavax/servlet/ServletRequest;Ljavax/servlet/ServletResponse;)V
      68: return
    Exception table:
       from    to  target type
          14    34    43   any
          43    45    43   any
}
