Compiled from "CoordinatorManager.java"
public class org.joyqueue.client.internal.consumer.coordinator.CoordinatorManager extends org.joyqueue.toolkit.service.Service {
  protected static final org.slf4j.Logger logger;

  private org.joyqueue.client.internal.cluster.ClusterClientManager clusterClientManager;

  public org.joyqueue.client.internal.consumer.coordinator.CoordinatorManager(org.joyqueue.client.internal.cluster.ClusterClientManager);
    Code:
       0: aload_0
       1: invokespecial #1                  // Method org/joyqueue/toolkit/service/Service."<init>":()V
       4: aload_0
       5: aload_1
       6: putfield      #2                  // Field clusterClientManager:Lorg/joyqueue/client/internal/cluster/ClusterClientManager;
       9: return

  public org.joyqueue.network.command.FetchAssignedPartitionResponse fetchAssignedPartition(org.joyqueue.network.domain.BrokerNode, java.lang.String, java.lang.String, boolean, long);
    Code:
       0: aconst_null
       1: astore        7
       3: aload_0
       4: getfield      #2                  // Field clusterClientManager:Lorg/joyqueue/client/internal/cluster/ClusterClientManager;
       7: aload_1
       8: invokevirtual #3                  // Method org/joyqueue/client/internal/cluster/ClusterClientManager.createClient:(Lorg/joyqueue/network/domain/BrokerNode;)Lorg/joyqueue/client/internal/cluster/ClusterClient;
      11: astore        7
      13: aload         7
      15: iconst_1
      16: anewarray     #4                  // class org/joyqueue/network/command/FetchAssignedPartitionData
      19: dup
      20: iconst_0
      21: new           #4                  // class org/joyqueue/network/command/FetchAssignedPartitionData
      24: dup
      25: aload_2
      26: lload         5
      28: l2i
      29: iload         4
      31: invokespecial #5                  // Method org/joyqueue/network/command/FetchAssignedPartitionData."<init>":(Ljava/lang/String;IZ)V
      34: aastore
      35: invokestatic  #6                  // Method com/google/common/collect/Lists.newArrayList:([Ljava/lang/Object;)Ljava/util/ArrayList;
      38: aload_3
      39: invokevirtual #7                  // Method org/joyqueue/client/internal/cluster/ClusterClient.fetchAssignedPartition:(Ljava/util/List;Ljava/lang/String;)Lorg/joyqueue/network/command/FetchAssignedPartitionResponse;
      42: astore        8
      44: aload         7
      46: ifnull        54
      49: aload         7
      51: invokevirtual #8                  // Method org/joyqueue/client/internal/cluster/ClusterClient.close:()V
      54: aload         8
      56: areturn
      57: astore        9
      59: aload         7
      61: ifnull        69
      64: aload         7
      66: invokevirtual #8                  // Method org/joyqueue/client/internal/cluster/ClusterClient.close:()V
      69: aload         9
      71: athrow
    Exception table:
       from    to  target type
           3    44    57   any
          57    59    57   any

  public org.joyqueue.network.domain.BrokerNode findCoordinator(java.lang.String, java.lang.String);
    Code:
       0: aload_0
       1: iconst_1
       2: anewarray     #9                  // class java/lang/String
       5: dup
       6: iconst_0
       7: aload_1
       8: aastore
       9: invokestatic  #6                  // Method com/google/common/collect/Lists.newArrayList:([Ljava/lang/Object;)Ljava/util/ArrayList;
      12: aload_2
      13: invokevirtual #10                 // Method findCoordinators:(Ljava/util/List;Ljava/lang/String;)Ljava/util/Map;
      16: astore_3
      17: aload_3
      18: invokestatic  #11                 // Method org/apache/commons/collections/MapUtils.isEmpty:(Ljava/util/Map;)Z
      21: ifeq          26
      24: aconst_null
      25: areturn
      26: aload_3
      27: aload_1
      28: invokeinterface #12,  2           // InterfaceMethod java/util/Map.get:(Ljava/lang/Object;)Ljava/lang/Object;
      33: checkcast     #13                 // class org/joyqueue/network/domain/BrokerNode
      36: areturn

  public java.util.Map<java.lang.String, org.joyqueue.network.domain.BrokerNode> findCoordinators(java.util.List<java.lang.String>, java.lang.String);
    Code:
       0: aload_0
       1: getfield      #2                  // Field clusterClientManager:Lorg/joyqueue/client/internal/cluster/ClusterClientManager;
       4: invokevirtual #14                 // Method org/joyqueue/client/internal/cluster/ClusterClientManager.getOrCreateClient:()Lorg/joyqueue/client/internal/cluster/ClusterClient;
       7: aload_1
       8: aload_2
       9: invokevirtual #15                 // Method org/joyqueue/client/internal/cluster/ClusterClient.findCoordinators:(Ljava/util/List;Ljava/lang/String;)Lorg/joyqueue/network/command/FindCoordinatorResponse;
      12: astore_3
      13: aload_3
      14: invokevirtual #16                 // Method org/joyqueue/network/command/FindCoordinatorResponse.getCoordinators:()Ljava/util/Map;
      17: astore        4
      19: invokestatic  #17                 // Method com/google/common/collect/Maps.newHashMap:()Ljava/util/HashMap;
      22: astore        5
      24: aload         4
      26: invokeinterface #18,  1           // InterfaceMethod java/util/Map.entrySet:()Ljava/util/Set;
      31: invokeinterface #19,  1           // InterfaceMethod java/util/Set.iterator:()Ljava/util/Iterator;
      36: astore        6
      38: aload         6
      40: invokeinterface #20,  1           // InterfaceMethod java/util/Iterator.hasNext:()Z
      45: ifeq          140
      48: aload         6
      50: invokeinterface #21,  1           // InterfaceMethod java/util/Iterator.next:()Ljava/lang/Object;
      55: checkcast     #22                 // class java/util/Map$Entry
      58: astore        7
      60: aload         7
      62: invokeinterface #23,  1           // InterfaceMethod java/util/Map$Entry.getKey:()Ljava/lang/Object;
      67: checkcast     #9                  // class java/lang/String
      70: astore        8
      72: aload         7
      74: invokeinterface #24,  1           // InterfaceMethod java/util/Map$Entry.getValue:()Ljava/lang/Object;
      79: checkcast     #25                 // class org/joyqueue/network/command/FindCoordinatorAckData
      82: astore        9
      84: aload         9
      86: invokevirtual #26                 // Method org/joyqueue/network/command/FindCoordinatorAckData.getCode:()Lorg/joyqueue/exception/JoyQueueCode;
      89: getstatic     #27                 // Field org/joyqueue/exception/JoyQueueCode.SUCCESS:Lorg/joyqueue/exception/JoyQueueCode;
      92: invokevirtual #28                 // Method org/joyqueue/exception/JoyQueueCode.equals:(Ljava/lang/Object;)Z
      95: ifne          122
      98: getstatic     #29                 // Field logger:Lorg/slf4j/Logger;
     101: ldc           #30                 // String find coordinator error, topic: {}, error: {}
     103: aload         8
     105: aload         9
     107: invokevirtual #26                 // Method org/joyqueue/network/command/FindCoordinatorAckData.getCode:()Lorg/joyqueue/exception/JoyQueueCode;
     110: iconst_0
     111: anewarray     #31                 // class java/lang/Object
     114: invokevirtual #32                 // Method org/joyqueue/exception/JoyQueueCode.getMessage:([Ljava/lang/Object;)Ljava/lang/String;
     117: invokeinterface #33,  4           // InterfaceMethod org/slf4j/Logger.error:(Ljava/lang/String;Ljava/lang/Object;Ljava/lang/Object;)V
     122: aload         5
     124: aload         8
     126: aload         9
     128: invokevirtual #34                 // Method org/joyqueue/network/command/FindCoordinatorAckData.getNode:()Lorg/joyqueue/network/domain/BrokerNode;
     131: invokeinterface #35,  3           // InterfaceMethod java/util/Map.put:(Ljava/lang/Object;Ljava/lang/Object;)Ljava/lang/Object;
     136: pop
     137: goto          38
     140: aload         5
     142: areturn

  static {};
    Code:
       0: ldc           #36                 // class org/joyqueue/client/internal/consumer/coordinator/CoordinatorManager
       2: invokestatic  #37                 // Method org/slf4j/LoggerFactory.getLogger:(Ljava/lang/Class;)Lorg/slf4j/Logger;
       5: putstatic     #29                 // Field logger:Lorg/slf4j/Logger;
       8: return
}
