Compiled from "IsEventFrom.java"
public class org.hamcrest.object.IsEventFrom extends org.hamcrest.TypeSafeDiagnosingMatcher<java.util.EventObject> {
  private final java.lang.Class<?> eventClass;

  private final java.lang.Object source;

  public org.hamcrest.object.IsEventFrom(java.lang.Class<?>, java.lang.Object);
    Code:
       0: aload_0
       1: invokespecial #1                  // Method org/hamcrest/TypeSafeDiagnosingMatcher."<init>":()V
       4: aload_0
       5: aload_1
       6: putfield      #2                  // Field eventClass:Ljava/lang/Class;
       9: aload_0
      10: aload_2
      11: putfield      #3                  // Field source:Ljava/lang/Object;
      14: return

  public boolean matchesSafely(java.util.EventObject, org.hamcrest.Description);
    Code:
       0: aload_0
       1: getfield      #2                  // Field eventClass:Ljava/lang/Class;
       4: aload_1
       5: invokevirtual #4                  // Method java/lang/Class.isInstance:(Ljava/lang/Object;)Z
       8: ifne          45
      11: aload_2
      12: new           #5                  // class java/lang/StringBuilder
      15: dup
      16: invokespecial #6                  // Method java/lang/StringBuilder."<init>":()V
      19: ldc           #7                  // String item type was
      21: invokevirtual #8                  // Method java/lang/StringBuilder.append:(Ljava/lang/String;)Ljava/lang/StringBuilder;
      24: aload_1
      25: invokevirtual #9                  // Method java/lang/Object.getClass:()Ljava/lang/Class;
      28: invokevirtual #10                 // Method java/lang/Class.getName:()Ljava/lang/String;
      31: invokevirtual #8                  // Method java/lang/StringBuilder.append:(Ljava/lang/String;)Ljava/lang/StringBuilder;
      34: invokevirtual #11                 // Method java/lang/StringBuilder.toString:()Ljava/lang/String;
      37: invokeinterface #12,  2           // InterfaceMethod org/hamcrest/Description.appendText:(Ljava/lang/String;)Lorg/hamcrest/Description;
      42: pop
      43: iconst_0
      44: ireturn
      45: aload_0
      46: aload_1
      47: invokespecial #13                 // Method eventHasSameSource:(Ljava/util/EventObject;)Z
      50: ifne          73
      53: aload_2
      54: ldc           #14                 // String source was
      56: invokeinterface #12,  2           // InterfaceMethod org/hamcrest/Description.appendText:(Ljava/lang/String;)Lorg/hamcrest/Description;
      61: aload_1
      62: invokevirtual #15                 // Method java/util/EventObject.getSource:()Ljava/lang/Object;
      65: invokeinterface #16,  2           // InterfaceMethod org/hamcrest/Description.appendValue:(Ljava/lang/Object;)Lorg/hamcrest/Description;
      70: pop
      71: iconst_0
      72: ireturn
      73: iconst_1
      74: ireturn

  private boolean eventHasSameSource(java.util.EventObject);
    Code:
       0: aload_1
       1: invokevirtual #15                 // Method java/util/EventObject.getSource:()Ljava/lang/Object;
       4: aload_0
       5: getfield      #3                  // Field source:Ljava/lang/Object;
       8: if_acmpne     15
      11: iconst_1
      12: goto          16
      15: iconst_0
      16: ireturn

  public void describeTo(org.hamcrest.Description);
    Code:
       0: aload_1
       1: ldc           #17                 // String an event of type
       3: invokeinterface #12,  2           // InterfaceMethod org/hamcrest/Description.appendText:(Ljava/lang/String;)Lorg/hamcrest/Description;
       8: aload_0
       9: getfield      #2                  // Field eventClass:Ljava/lang/Class;
      12: invokevirtual #10                 // Method java/lang/Class.getName:()Ljava/lang/String;
      15: invokeinterface #12,  2           // InterfaceMethod org/hamcrest/Description.appendText:(Ljava/lang/String;)Lorg/hamcrest/Description;
      20: ldc           #18                 // String  from
      22: invokeinterface #12,  2           // InterfaceMethod org/hamcrest/Description.appendText:(Ljava/lang/String;)Lorg/hamcrest/Description;
      27: aload_0
      28: getfield      #3                  // Field source:Ljava/lang/Object;
      31: invokeinterface #16,  2           // InterfaceMethod org/hamcrest/Description.appendValue:(Ljava/lang/Object;)Lorg/hamcrest/Description;
      36: pop
      37: return

  public static org.hamcrest.Matcher<java.util.EventObject> eventFrom(java.lang.Class<? extends java.util.EventObject>, java.lang.Object);
    Code:
       0: new           #19                 // class org/hamcrest/object/IsEventFrom
       3: dup
       4: aload_0
       5: aload_1
       6: invokespecial #20                 // Method "<init>":(Ljava/lang/Class;Ljava/lang/Object;)V
       9: areturn

  public static org.hamcrest.Matcher<java.util.EventObject> eventFrom(java.lang.Object);
    Code:
       0: ldc_w         #21                 // class java/util/EventObject
       3: aload_0
       4: invokestatic  #22                 // Method eventFrom:(Ljava/lang/Class;Ljava/lang/Object;)Lorg/hamcrest/Matcher;
       7: areturn

  public boolean matchesSafely(java.lang.Object, org.hamcrest.Description);
    Code:
       0: aload_0
       1: aload_1
       2: checkcast     #21                 // class java/util/EventObject
       5: aload_2
       6: invokevirtual #23                 // Method matchesSafely:(Ljava/util/EventObject;Lorg/hamcrest/Description;)Z
       9: ireturn
}
