Compiled from "Arrays.java"
public final class org.thymeleaf.expression.Arrays {
  public java.lang.Object[] toArray(java.lang.Object);
    Code:
       0: aload_1
       1: invokestatic  #1                  // Method org/thymeleaf/util/ArrayUtils.toArray:(Ljava/lang/Object;)[Ljava/lang/Object;
       4: areturn

  public java.lang.Object[] toStringArray(java.lang.Object);
    Code:
       0: aload_1
       1: invokestatic  #2                  // Method org/thymeleaf/util/ArrayUtils.toStringArray:(Ljava/lang/Object;)[Ljava/lang/Object;
       4: areturn

  public java.lang.Object[] toIntegerArray(java.lang.Object);
    Code:
       0: aload_1
       1: invokestatic  #3                  // Method org/thymeleaf/util/ArrayUtils.toIntegerArray:(Ljava/lang/Object;)[Ljava/lang/Object;
       4: areturn

  public java.lang.Object[] toLongArray(java.lang.Object);
    Code:
       0: aload_1
       1: invokestatic  #4                  // Method org/thymeleaf/util/ArrayUtils.toLongArray:(Ljava/lang/Object;)[Ljava/lang/Object;
       4: areturn

  public java.lang.Object[] toDoubleArray(java.lang.Object);
    Code:
       0: aload_1
       1: invokestatic  #5                  // Method org/thymeleaf/util/ArrayUtils.toDoubleArray:(Ljava/lang/Object;)[Ljava/lang/Object;
       4: areturn

  public java.lang.Object[] toFloatArray(java.lang.Object);
    Code:
       0: aload_1
       1: invokestatic  #6                  // Method org/thymeleaf/util/ArrayUtils.toFloatArray:(Ljava/lang/Object;)[Ljava/lang/Object;
       4: areturn

  public java.lang.Object[] toBooleanArray(java.lang.Object);
    Code:
       0: aload_1
       1: invokestatic  #7                  // Method org/thymeleaf/util/ArrayUtils.toBooleanArray:(Ljava/lang/Object;)[Ljava/lang/Object;
       4: areturn

  public int length(java.lang.Object[]);
    Code:
       0: aload_1
       1: invokestatic  #8                  // Method org/thymeleaf/util/ArrayUtils.length:([Ljava/lang/Object;)I
       4: ireturn

  public boolean isEmpty(java.lang.Object[]);
    Code:
       0: aload_1
       1: invokestatic  #9                  // Method org/thymeleaf/util/ArrayUtils.isEmpty:([Ljava/lang/Object;)Z
       4: ireturn

  public boolean contains(java.lang.Object[], java.lang.Object);
    Code:
       0: aload_1
       1: aload_2
       2: invokestatic  #10                 // Method org/thymeleaf/util/ArrayUtils.contains:([Ljava/lang/Object;Ljava/lang/Object;)Z
       5: ireturn

  public boolean containsAll(java.lang.Object[], java.lang.Object[]);
    Code:
       0: aload_1
       1: aload_2
       2: invokestatic  #11                 // Method org/thymeleaf/util/ArrayUtils.containsAll:([Ljava/lang/Object;[Ljava/lang/Object;)Z
       5: ireturn

  public boolean containsAll(java.lang.Object[], java.util.Collection<?>);
    Code:
       0: aload_1
       1: aload_2
       2: invokestatic  #12                 // Method org/thymeleaf/util/ArrayUtils.containsAll:([Ljava/lang/Object;Ljava/util/Collection;)Z
       5: ireturn

  public org.thymeleaf.expression.Arrays();
    Code:
       0: aload_0
       1: invokespecial #13                 // Method java/lang/Object."<init>":()V
       4: return
}
