Compiled from "JsonParser.java"
public final class org.codehaus.jackson.JsonParser$NumberType extends java.lang.Enum<org.codehaus.jackson.JsonParser$NumberType> {
  public static final org.codehaus.jackson.JsonParser$NumberType INT;

  public static final org.codehaus.jackson.JsonParser$NumberType LONG;

  public static final org.codehaus.jackson.JsonParser$NumberType BIG_INTEGER;

  public static final org.codehaus.jackson.JsonParser$NumberType FLOAT;

  public static final org.codehaus.jackson.JsonParser$NumberType DOUBLE;

  public static final org.codehaus.jackson.JsonParser$NumberType BIG_DECIMAL;

  private static final org.codehaus.jackson.JsonParser$NumberType[] $VALUES;

  public static org.codehaus.jackson.JsonParser$NumberType[] values();
    Code:
       0: getstatic     #1                  // Field $VALUES:[Lorg/codehaus/jackson/JsonParser$NumberType;
       3: invokevirtual #2                  // Method "[Lorg/codehaus/jackson/JsonParser$NumberType;".clone:()Ljava/lang/Object;
       6: checkcast     #3                  // class "[Lorg/codehaus/jackson/JsonParser$NumberType;"
       9: areturn

  public static org.codehaus.jackson.JsonParser$NumberType valueOf(java.lang.String);
    Code:
       0: ldc_w         #4                  // class org/codehaus/jackson/JsonParser$NumberType
       3: aload_0
       4: invokestatic  #5                  // Method java/lang/Enum.valueOf:(Ljava/lang/Class;Ljava/lang/String;)Ljava/lang/Enum;
       7: checkcast     #4                  // class org/codehaus/jackson/JsonParser$NumberType
      10: areturn

  private org.codehaus.jackson.JsonParser$NumberType();
    Code:
       0: aload_0
       1: aload_1
       2: iload_2
       3: invokespecial #6                  // Method java/lang/Enum."<init>":(Ljava/lang/String;I)V
       6: return

  static {};
    Code:
       0: new           #4                  // class org/codehaus/jackson/JsonParser$NumberType
       3: dup
       4: ldc           #7                  // String INT
       6: iconst_0
       7: invokespecial #8                  // Method "<init>":(Ljava/lang/String;I)V
      10: putstatic     #9                  // Field INT:Lorg/codehaus/jackson/JsonParser$NumberType;
      13: new           #4                  // class org/codehaus/jackson/JsonParser$NumberType
      16: dup
      17: ldc           #10                 // String LONG
      19: iconst_1
      20: invokespecial #8                  // Method "<init>":(Ljava/lang/String;I)V
      23: putstatic     #11                 // Field LONG:Lorg/codehaus/jackson/JsonParser$NumberType;
      26: new           #4                  // class org/codehaus/jackson/JsonParser$NumberType
      29: dup
      30: ldc           #12                 // String BIG_INTEGER
      32: iconst_2
      33: invokespecial #8                  // Method "<init>":(Ljava/lang/String;I)V
      36: putstatic     #13                 // Field BIG_INTEGER:Lorg/codehaus/jackson/JsonParser$NumberType;
      39: new           #4                  // class org/codehaus/jackson/JsonParser$NumberType
      42: dup
      43: ldc           #14                 // String FLOAT
      45: iconst_3
      46: invokespecial #8                  // Method "<init>":(Ljava/lang/String;I)V
      49: putstatic     #15                 // Field FLOAT:Lorg/codehaus/jackson/JsonParser$NumberType;
      52: new           #4                  // class org/codehaus/jackson/JsonParser$NumberType
      55: dup
      56: ldc           #16                 // String DOUBLE
      58: iconst_4
      59: invokespecial #8                  // Method "<init>":(Ljava/lang/String;I)V
      62: putstatic     #17                 // Field DOUBLE:Lorg/codehaus/jackson/JsonParser$NumberType;
      65: new           #4                  // class org/codehaus/jackson/JsonParser$NumberType
      68: dup
      69: ldc           #18                 // String BIG_DECIMAL
      71: iconst_5
      72: invokespecial #8                  // Method "<init>":(Ljava/lang/String;I)V
      75: putstatic     #19                 // Field BIG_DECIMAL:Lorg/codehaus/jackson/JsonParser$NumberType;
      78: bipush        6
      80: anewarray     #4                  // class org/codehaus/jackson/JsonParser$NumberType
      83: dup
      84: iconst_0
      85: getstatic     #9                  // Field INT:Lorg/codehaus/jackson/JsonParser$NumberType;
      88: aastore
      89: dup
      90: iconst_1
      91: getstatic     #11                 // Field LONG:Lorg/codehaus/jackson/JsonParser$NumberType;
      94: aastore
      95: dup
      96: iconst_2
      97: getstatic     #13                 // Field BIG_INTEGER:Lorg/codehaus/jackson/JsonParser$NumberType;
     100: aastore
     101: dup
     102: iconst_3
     103: getstatic     #15                 // Field FLOAT:Lorg/codehaus/jackson/JsonParser$NumberType;
     106: aastore
     107: dup
     108: iconst_4
     109: getstatic     #17                 // Field DOUBLE:Lorg/codehaus/jackson/JsonParser$NumberType;
     112: aastore
     113: dup
     114: iconst_5
     115: getstatic     #19                 // Field BIG_DECIMAL:Lorg/codehaus/jackson/JsonParser$NumberType;
     118: aastore
     119: putstatic     #1                  // Field $VALUES:[Lorg/codehaus/jackson/JsonParser$NumberType;
     122: return
}
