Compiled from "ComparableValue.java"
class net.sf.ehcache.search.expression.ComparableValue$LuceneCaseAgnosticStringComparator implements java.util.Comparator<java.lang.String>, java.io.Serializable {
  private net.sf.ehcache.search.expression.ComparableValue$LuceneCaseAgnosticStringComparator();
    Code:
       0: aload_0
       1: invokespecial #2                  // Method java/lang/Object."<init>":()V
       4: return

  public int compare(java.lang.String, java.lang.String);
    Code:
       0: aload_1
       1: invokevirtual #3                  // Method java/lang/String.length:()I
       4: istore_3
       5: aload_2
       6: invokevirtual #3                  // Method java/lang/String.length:()I
       9: istore        4
      11: iconst_0
      12: istore        5
      14: iload         5
      16: iload_3
      17: if_icmpge     83
      20: iload         5
      22: iload         4
      24: if_icmpge     83
      27: aload_1
      28: iload         5
      30: invokevirtual #4                  // Method java/lang/String.charAt:(I)C
      33: istore        6
      35: aload_2
      36: iload         5
      38: invokevirtual #4                  // Method java/lang/String.charAt:(I)C
      41: istore        7
      43: iload         6
      45: iload         7
      47: if_icmpeq     77
      50: iload         6
      52: invokestatic  #5                  // Method java/lang/Character.toLowerCase:(C)C
      55: istore        6
      57: iload         7
      59: invokestatic  #5                  // Method java/lang/Character.toLowerCase:(C)C
      62: istore        7
      64: iload         6
      66: iload         7
      68: if_icmpeq     77
      71: iload         6
      73: iload         7
      75: isub
      76: ireturn
      77: iinc          5, 1
      80: goto          14
      83: iload_3
      84: iload         4
      86: isub
      87: ireturn

  public int compare(java.lang.Object, java.lang.Object);
    Code:
       0: aload_0
       1: aload_1
       2: checkcast     #6                  // class java/lang/String
       5: aload_2
       6: checkcast     #6                  // class java/lang/String
       9: invokevirtual #7                  // Method compare:(Ljava/lang/String;Ljava/lang/String;)I
      12: ireturn

  net.sf.ehcache.search.expression.ComparableValue$LuceneCaseAgnosticStringComparator(net.sf.ehcache.search.expression.ComparableValue$1);
    Code:
       0: aload_0
       1: invokespecial #1                  // Method "<init>":()V
       4: return
}
