Compiled from "NotEqualTo.java"
public class net.sf.ehcache.search.expression.NotEqualTo extends net.sf.ehcache.search.expression.EqualTo {
  public net.sf.ehcache.search.expression.NotEqualTo(java.lang.String, java.lang.Object);
    Code:
       0: aload_0
       1: aload_1
       2: aload_2
       3: invokespecial #1                  // Method net/sf/ehcache/search/expression/EqualTo."<init>":(Ljava/lang/String;Ljava/lang/Object;)V
       6: return

  public boolean execute(net.sf.ehcache.Element, java.util.Map<java.lang.String, net.sf.ehcache.search.attribute.AttributeExtractor>);
    Code:
       0: aload_0
       1: aload_1
       2: aload_2
       3: invokespecial #2                  // Method net/sf/ehcache/search/expression/EqualTo.execute:(Lnet/sf/ehcache/Element;Ljava/util/Map;)Z
       6: ifne          13
       9: iconst_1
      10: goto          14
      13: iconst_0
      14: ireturn
}
