Compiled from "SmartValidator.java"
public interface org.springframework.validation.SmartValidator extends org.springframework.validation.Validator {
  public abstract void validate(java.lang.Object, org.springframework.validation.Errors, java.lang.Object...);

  public default void validateValue(java.lang.Class<?>, java.lang.String, java.lang.Object, org.springframework.validation.Errors, java.lang.Object...);
    Code:
       0: new           #1                  // class java/lang/IllegalArgumentException
       3: dup
       4: new           #2                  // class java/lang/StringBuilder
       7: dup
       8: invokespecial #3                  // Method java/lang/StringBuilder."<init>":()V
      11: ldc           #4                  // String Cannot validate individual value for
      13: invokevirtual #5                  // Method java/lang/StringBuilder.append:(Ljava/lang/String;)Ljava/lang/StringBuilder;
      16: aload_1
      17: invokevirtual #6                  // Method java/lang/StringBuilder.append:(Ljava/lang/Object;)Ljava/lang/StringBuilder;
      20: invokevirtual #7                  // Method java/lang/StringBuilder.toString:()Ljava/lang/String;
      23: invokespecial #8                  // Method java/lang/IllegalArgumentException."<init>":(Ljava/lang/String;)V
      26: athrow
}
