Compiled from "DefaultMethodCall.java"
public class net.bytebuddy.implementation.DefaultMethodCall implements net.bytebuddy.implementation.Implementation {
  private final java.util.List<net.bytebuddy.description.type.TypeDescription> prioritizedInterfaces;

  protected net.bytebuddy.implementation.DefaultMethodCall(java.util.List<net.bytebuddy.description.type.TypeDescription>);
    Code:
       0: aload_0
       1: invokespecial #36                 // Method java/lang/Object."<init>":()V
       4: aload_0
       5: aload_1
       6: putfield      #38                 // Field prioritizedInterfaces:Ljava/util/List;
       9: return

  public static net.bytebuddy.implementation.Implementation prioritize(java.lang.Class<?>...);
    Code:
       0: new           #21                 // class net/bytebuddy/description/type/TypeList$ForLoadedTypes
       3: dup
       4: aload_0
       5: invokespecial #46                 // Method net/bytebuddy/description/type/TypeList$ForLoadedTypes."<init>":([Ljava/lang/Class;)V
       8: invokestatic  #49                 // Method prioritize:(Ljava/util/Collection;)Lnet/bytebuddy/implementation/Implementation;
      11: areturn

  public static net.bytebuddy.implementation.Implementation prioritize(java.lang.Iterable<? extends java.lang.Class<?>>);
    Code:
       0: new           #56                 // class java/util/ArrayList
       3: dup
       4: invokespecial #57                 // Method java/util/ArrayList."<init>":()V
       7: astore_1
       8: aload_0
       9: invokeinterface #63,  1           // InterfaceMethod java/lang/Iterable.iterator:()Ljava/util/Iterator;
      14: astore_2
      15: aload_2
      16: invokeinterface #69,  1           // InterfaceMethod java/util/Iterator.hasNext:()Z
      21: ifeq          45
      24: aload_2
      25: invokeinterface #73,  1           // InterfaceMethod java/util/Iterator.next:()Ljava/lang/Object;
      30: checkcast     #75                 // class java/lang/Class
      33: astore_3
      34: aload_1
      35: aload_3
      36: invokeinterface #81,  2           // InterfaceMethod java/util/List.add:(Ljava/lang/Object;)Z
      41: pop
      42: goto          15
      45: new           #21                 // class net/bytebuddy/description/type/TypeList$ForLoadedTypes
      48: dup
      49: aload_1
      50: invokespecial #83                 // Method net/bytebuddy/description/type/TypeList$ForLoadedTypes."<init>":(Ljava/util/List;)V
      53: invokestatic  #49                 // Method prioritize:(Ljava/util/Collection;)Lnet/bytebuddy/implementation/Implementation;
      56: areturn

  public static net.bytebuddy.implementation.Implementation prioritize(net.bytebuddy.description.type.TypeDescription...);
    Code:
       0: aload_0
       1: invokestatic  #96                 // Method java/util/Arrays.asList:([Ljava/lang/Object;)Ljava/util/List;
       4: invokestatic  #49                 // Method prioritize:(Ljava/util/Collection;)Lnet/bytebuddy/implementation/Implementation;
       7: areturn

  public static net.bytebuddy.implementation.Implementation prioritize(java.util.Collection<? extends net.bytebuddy.description.type.TypeDescription>);
    Code:
       0: new           #2                  // class net/bytebuddy/implementation/DefaultMethodCall
       3: dup
       4: new           #56                 // class java/util/ArrayList
       7: dup
       8: aload_0
       9: invokespecial #101                // Method java/util/ArrayList."<init>":(Ljava/util/Collection;)V
      12: invokespecial #102                // Method "<init>":(Ljava/util/List;)V
      15: areturn

  public static net.bytebuddy.implementation.Implementation unambiguousOnly();
    Code:
       0: new           #2                  // class net/bytebuddy/implementation/DefaultMethodCall
       3: dup
       4: invokestatic  #112                // Method java/util/Collections.emptyList:()Ljava/util/List;
       7: invokespecial #102                // Method "<init>":(Ljava/util/List;)V
      10: areturn

  public net.bytebuddy.dynamic.scaffold.InstrumentedType prepare(net.bytebuddy.dynamic.scaffold.InstrumentedType);
    Code:
       0: aload_1
       1: areturn

  public net.bytebuddy.implementation.bytecode.ByteCodeAppender appender(net.bytebuddy.implementation.Implementation$Target);
    Code:
       0: new           #10                 // class net/bytebuddy/implementation/DefaultMethodCall$Appender
       3: dup
       4: aload_1
       5: aload_0
       6: aload_1
       7: invokeinterface #122,  1          // InterfaceMethod net/bytebuddy/implementation/Implementation$Target.getInstrumentedType:()Lnet/bytebuddy/description/type/TypeDescription;
      12: invokespecial #126                // Method filterRelevant:(Lnet/bytebuddy/description/type/TypeDescription;)Ljava/util/List;
      15: invokespecial #129                // Method net/bytebuddy/implementation/DefaultMethodCall$Appender."<init>":(Lnet/bytebuddy/implementation/Implementation$Target;Ljava/util/List;)V
      18: areturn

  private java.util.List<net.bytebuddy.description.type.TypeDescription> filterRelevant(net.bytebuddy.description.type.TypeDescription);
    Code:
       0: new           #56                 // class java/util/ArrayList
       3: dup
       4: aload_0
       5: getfield      #38                 // Field prioritizedInterfaces:Ljava/util/List;
       8: invokeinterface #136,  1          // InterfaceMethod java/util/List.size:()I
      13: invokespecial #139                // Method java/util/ArrayList."<init>":(I)V
      16: astore_2
      17: new           #141                // class java/util/HashSet
      20: dup
      21: aload_1
      22: invokeinterface #147,  1          // InterfaceMethod net/bytebuddy/description/type/TypeDescription.getInterfaces:()Lnet/bytebuddy/description/type/TypeList$Generic;
      27: invokeinterface #151,  1          // InterfaceMethod net/bytebuddy/description/type/TypeList$Generic.asErasures:()Lnet/bytebuddy/description/type/TypeList;
      32: invokespecial #152                // Method java/util/HashSet."<init>":(Ljava/util/Collection;)V
      35: astore_3
      36: aload_0
      37: getfield      #38                 // Field prioritizedInterfaces:Ljava/util/List;
      40: invokeinterface #153,  1          // InterfaceMethod java/util/List.iterator:()Ljava/util/Iterator;
      45: astore        4
      47: aload         4
      49: invokeinterface #69,  1           // InterfaceMethod java/util/Iterator.hasNext:()Z
      54: ifeq          92
      57: aload         4
      59: invokeinterface #73,  1           // InterfaceMethod java/util/Iterator.next:()Ljava/lang/Object;
      64: checkcast     #143                // class net/bytebuddy/description/type/TypeDescription
      67: astore        5
      69: aload_3
      70: aload         5
      72: invokeinterface #158,  2          // InterfaceMethod java/util/Set.remove:(Ljava/lang/Object;)Z
      77: ifeq          89
      80: aload_2
      81: aload         5
      83: invokeinterface #81,  2           // InterfaceMethod java/util/List.add:(Ljava/lang/Object;)Z
      88: pop
      89: goto          47
      92: aload_2
      93: areturn

  public boolean equals(java.lang.Object);
    Code:
       0: aload_0
       1: aload_1
       2: if_acmpne     7
       5: iconst_1
       6: ireturn
       7: aload_1
       8: ifnonnull     13
      11: iconst_0
      12: ireturn
      13: aload_0
      14: invokevirtual #169                // Method java/lang/Object.getClass:()Ljava/lang/Class;
      17: aload_1
      18: invokevirtual #169                // Method java/lang/Object.getClass:()Ljava/lang/Class;
      21: if_acmpeq     26
      24: iconst_0
      25: ireturn
      26: aload_0
      27: getfield      #38                 // Field prioritizedInterfaces:Ljava/util/List;
      30: aload_1
      31: checkcast     #2                  // class net/bytebuddy/implementation/DefaultMethodCall
      34: getfield      #38                 // Field prioritizedInterfaces:Ljava/util/List;
      37: invokevirtual #171                // Method java/lang/Object.equals:(Ljava/lang/Object;)Z
      40: ifne          45
      43: iconst_0
      44: ireturn
      45: iconst_1
      46: ireturn

  public int hashCode();
    Code:
       0: bipush        17
       2: bipush        31
       4: imul
       5: aload_0
       6: getfield      #38                 // Field prioritizedInterfaces:Ljava/util/List;
       9: invokevirtual #174                // Method java/lang/Object.hashCode:()I
      12: iadd
      13: ireturn
}
