Compiled from "MethodDelegation.java"
public abstract class net.bytebuddy.implementation.MethodDelegation$ImplementationDelegate$ForField implements net.bytebuddy.implementation.MethodDelegation$ImplementationDelegate {
  protected final java.lang.String fieldName;

  protected final net.bytebuddy.dynamic.scaffold.MethodGraph$Compiler methodGraphCompiler;

  protected final java.util.List<? extends net.bytebuddy.implementation.bind.annotation.TargetMethodAnnotationDrivenBinder$ParameterBinder<?>> parameterBinders;

  protected final net.bytebuddy.matcher.ElementMatcher<? super net.bytebuddy.description.method.MethodDescription> matcher;

  protected net.bytebuddy.implementation.MethodDelegation$ImplementationDelegate$ForField(java.lang.String, net.bytebuddy.dynamic.scaffold.MethodGraph$Compiler, java.util.List<? extends net.bytebuddy.implementation.bind.annotation.TargetMethodAnnotationDrivenBinder$ParameterBinder<?>>, net.bytebuddy.matcher.ElementMatcher<? super net.bytebuddy.description.method.MethodDescription>);
    Code:
       0: aload_0
       1: invokespecial #70                 // Method java/lang/Object."<init>":()V
       4: aload_0
       5: aload_1
       6: putfield      #72                 // Field fieldName:Ljava/lang/String;
       9: aload_0
      10: aload_2
      11: putfield      #74                 // Field methodGraphCompiler:Lnet/bytebuddy/dynamic/scaffold/MethodGraph$Compiler;
      14: aload_0
      15: aload_3
      16: putfield      #76                 // Field parameterBinders:Ljava/util/List;
      19: aload_0
      20: aload         4
      22: putfield      #78                 // Field matcher:Lnet/bytebuddy/matcher/ElementMatcher;
      25: return

  public net.bytebuddy.implementation.MethodDelegation$ImplementationDelegate$Compiled compile(net.bytebuddy.description.type.TypeDescription);
    Code:
       0: aload_0
       1: aload_1
       2: invokevirtual #86                 // Method resolve:(Lnet/bytebuddy/description/type/TypeDescription;)Lnet/bytebuddy/description/field/FieldDescription;
       5: astore_2
       6: aload_2
       7: invokeinterface #92,  1           // InterfaceMethod net/bytebuddy/description/field/FieldDescription.getType:()Lnet/bytebuddy/description/type/TypeDescription$Generic;
      12: invokeinterface #96,  1           // InterfaceMethod net/bytebuddy/description/type/TypeDescription$Generic.asErasure:()Lnet/bytebuddy/description/type/TypeDescription;
      17: aload_1
      18: invokeinterface #100,  2          // InterfaceMethod net/bytebuddy/description/type/TypeDescription.isVisibleTo:(Lnet/bytebuddy/description/type/TypeDescription;)Z
      23: ifne          57
      26: new           #102                // class java/lang/IllegalStateException
      29: dup
      30: new           #104                // class java/lang/StringBuilder
      33: dup
      34: invokespecial #105                // Method java/lang/StringBuilder."<init>":()V
      37: aload_2
      38: invokevirtual #109                // Method java/lang/StringBuilder.append:(Ljava/lang/Object;)Ljava/lang/StringBuilder;
      41: ldc           #111                // String  is not visible to
      43: invokevirtual #114                // Method java/lang/StringBuilder.append:(Ljava/lang/String;)Ljava/lang/StringBuilder;
      46: aload_1
      47: invokevirtual #109                // Method java/lang/StringBuilder.append:(Ljava/lang/Object;)Ljava/lang/StringBuilder;
      50: invokevirtual #118                // Method java/lang/StringBuilder.toString:()Ljava/lang/String;
      53: invokespecial #121                // Method java/lang/IllegalStateException."<init>":(Ljava/lang/String;)V
      56: athrow
      57: aload_0
      58: getfield      #74                 // Field methodGraphCompiler:Lnet/bytebuddy/dynamic/scaffold/MethodGraph$Compiler;
      61: aload_2
      62: invokeinterface #92,  1           // InterfaceMethod net/bytebuddy/description/field/FieldDescription.getType:()Lnet/bytebuddy/description/type/TypeDescription$Generic;
      67: aload_1
      68: invokeinterface #124,  3          // InterfaceMethod net/bytebuddy/dynamic/scaffold/MethodGraph$Compiler.compile:(Lnet/bytebuddy/description/type/TypeDefinition;Lnet/bytebuddy/description/type/TypeDescription;)Lnet/bytebuddy/dynamic/scaffold/MethodGraph$Linked;
      73: invokeinterface #128,  1          // InterfaceMethod net/bytebuddy/dynamic/scaffold/MethodGraph$Linked.listNodes:()Lnet/bytebuddy/dynamic/scaffold/MethodGraph$NodeList;
      78: invokevirtual #132                // Method net/bytebuddy/dynamic/scaffold/MethodGraph$NodeList.asMethodList:()Lnet/bytebuddy/description/method/MethodList;
      81: aload_0
      82: getfield      #78                 // Field matcher:Lnet/bytebuddy/matcher/ElementMatcher;
      85: invokeinterface #138,  2          // InterfaceMethod net/bytebuddy/description/method/MethodList.filter:(Lnet/bytebuddy/matcher/ElementMatcher;)Lnet/bytebuddy/matcher/FilterableList;
      90: checkcast     #134                // class net/bytebuddy/description/method/MethodList
      93: astore_3
      94: new           #140                // class java/util/ArrayList
      97: dup
      98: aload_3
      99: invokeinterface #144,  1          // InterfaceMethod net/bytebuddy/description/method/MethodList.size:()I
     104: invokespecial #147                // Method java/util/ArrayList."<init>":(I)V
     107: astore        4
     109: aload_0
     110: getfield      #76                 // Field parameterBinders:Ljava/util/List;
     113: invokestatic  #151                // Method net/bytebuddy/implementation/bind/annotation/TargetMethodAnnotationDrivenBinder.of:(Ljava/util/List;)Lnet/bytebuddy/implementation/bind/MethodDelegationBinder;
     116: astore        5
     118: aload_3
     119: invokeinterface #155,  1          // InterfaceMethod net/bytebuddy/description/method/MethodList.iterator:()Ljava/util/Iterator;
     124: astore        6
     126: aload         6
     128: invokeinterface #161,  1          // InterfaceMethod java/util/Iterator.hasNext:()Z
     133: ifeq          168
     136: aload         6
     138: invokeinterface #165,  1          // InterfaceMethod java/util/Iterator.next:()Ljava/lang/Object;
     143: checkcast     #167                // class net/bytebuddy/description/method/MethodDescription
     146: astore        7
     148: aload         4
     150: aload         5
     152: aload         7
     154: invokeinterface #170,  2          // InterfaceMethod net/bytebuddy/implementation/bind/MethodDelegationBinder.compile:(Lnet/bytebuddy/description/method/MethodDescription;)Lnet/bytebuddy/implementation/bind/MethodDelegationBinder$Record;
     159: invokeinterface #176,  2          // InterfaceMethod java/util/List.add:(Ljava/lang/Object;)Z
     164: pop
     165: goto          126
     168: new           #42                 // class net/bytebuddy/implementation/MethodDelegation$ImplementationDelegate$Compiled$ForField
     171: dup
     172: aload_2
     173: aload         4
     175: invokespecial #179                // Method net/bytebuddy/implementation/MethodDelegation$ImplementationDelegate$Compiled$ForField."<init>":(Lnet/bytebuddy/description/field/FieldDescription;Ljava/util/List;)V
     178: areturn

  protected abstract net.bytebuddy.description.field.FieldDescription resolve(net.bytebuddy.description.type.TypeDescription);

  public boolean equals(java.lang.Object);
    Code:
       0: aload_0
       1: aload_1
       2: if_acmpne     7
       5: iconst_1
       6: ireturn
       7: aload_1
       8: ifnonnull     13
      11: iconst_0
      12: ireturn
      13: aload_0
      14: invokevirtual #197                // Method java/lang/Object.getClass:()Ljava/lang/Class;
      17: aload_1
      18: invokevirtual #197                // Method java/lang/Object.getClass:()Ljava/lang/Class;
      21: if_acmpeq     26
      24: iconst_0
      25: ireturn
      26: aload_0
      27: getfield      #72                 // Field fieldName:Ljava/lang/String;
      30: aload_1
      31: checkcast     #2                  // class net/bytebuddy/implementation/MethodDelegation$ImplementationDelegate$ForField
      34: getfield      #72                 // Field fieldName:Ljava/lang/String;
      37: invokevirtual #201                // Method java/lang/String.equals:(Ljava/lang/Object;)Z
      40: ifne          45
      43: iconst_0
      44: ireturn
      45: aload_0
      46: getfield      #74                 // Field methodGraphCompiler:Lnet/bytebuddy/dynamic/scaffold/MethodGraph$Compiler;
      49: aload_1
      50: checkcast     #2                  // class net/bytebuddy/implementation/MethodDelegation$ImplementationDelegate$ForField
      53: getfield      #74                 // Field methodGraphCompiler:Lnet/bytebuddy/dynamic/scaffold/MethodGraph$Compiler;
      56: invokevirtual #202                // Method java/lang/Object.equals:(Ljava/lang/Object;)Z
      59: ifne          64
      62: iconst_0
      63: ireturn
      64: aload_0
      65: getfield      #76                 // Field parameterBinders:Ljava/util/List;
      68: aload_1
      69: checkcast     #2                  // class net/bytebuddy/implementation/MethodDelegation$ImplementationDelegate$ForField
      72: getfield      #76                 // Field parameterBinders:Ljava/util/List;
      75: invokevirtual #202                // Method java/lang/Object.equals:(Ljava/lang/Object;)Z
      78: ifne          83
      81: iconst_0
      82: ireturn
      83: aload_0
      84: getfield      #78                 // Field matcher:Lnet/bytebuddy/matcher/ElementMatcher;
      87: aload_1
      88: checkcast     #2                  // class net/bytebuddy/implementation/MethodDelegation$ImplementationDelegate$ForField
      91: getfield      #78                 // Field matcher:Lnet/bytebuddy/matcher/ElementMatcher;
      94: invokevirtual #202                // Method java/lang/Object.equals:(Ljava/lang/Object;)Z
      97: ifne          102
     100: iconst_0
     101: ireturn
     102: iconst_1
     103: ireturn

  public int hashCode();
    Code:
       0: bipush        17
       2: bipush        31
       4: imul
       5: aload_0
       6: getfield      #72                 // Field fieldName:Ljava/lang/String;
       9: invokevirtual #205                // Method java/lang/String.hashCode:()I
      12: iadd
      13: bipush        31
      15: imul
      16: aload_0
      17: getfield      #74                 // Field methodGraphCompiler:Lnet/bytebuddy/dynamic/scaffold/MethodGraph$Compiler;
      20: invokevirtual #206                // Method java/lang/Object.hashCode:()I
      23: iadd
      24: bipush        31
      26: imul
      27: aload_0
      28: getfield      #76                 // Field parameterBinders:Ljava/util/List;
      31: invokevirtual #206                // Method java/lang/Object.hashCode:()I
      34: iadd
      35: bipush        31
      37: imul
      38: aload_0
      39: getfield      #78                 // Field matcher:Lnet/bytebuddy/matcher/ElementMatcher;
      42: invokevirtual #206                // Method java/lang/Object.hashCode:()I
      45: iadd
      46: ireturn
}
