Compiled from "Linqy.java"
class org.xmlunit.util.Linqy$FilteringIterator<T> implements java.util.Iterator<T> {
  private final java.util.Iterator<T> i;

  private final org.xmlunit.util.Predicate<? super T> filter;

  private T lookAhead;

  private org.xmlunit.util.Linqy$FilteringIterator(java.util.Iterator<T>, org.xmlunit.util.Predicate<? super T>);
    Code:
       0: aload_0
       1: invokespecial #2                  // Method java/lang/Object."<init>":()V
       4: aload_0
       5: aconst_null
       6: putfield      #3                  // Field lookAhead:Ljava/lang/Object;
       9: aload_0
      10: aload_1
      11: putfield      #4                  // Field i:Ljava/util/Iterator;
      14: aload_0
      15: aload_2
      16: putfield      #5                  // Field filter:Lorg/xmlunit/util/Predicate;
      19: aload_0
      20: invokevirtual #6                  // Method hasNext:()Z
      23: pop
      24: return

  public void remove();
    Code:
       0: aload_0
       1: getfield      #4                  // Field i:Ljava/util/Iterator;
       4: invokeinterface #7,  1            // InterfaceMethod java/util/Iterator.remove:()V
       9: return

  public T next();
    Code:
       0: aload_0
       1: getfield      #3                  // Field lookAhead:Ljava/lang/Object;
       4: ifnonnull     15
       7: new           #8                  // class java/util/NoSuchElementException
      10: dup
      11: invokespecial #9                  // Method java/util/NoSuchElementException."<init>":()V
      14: athrow
      15: aload_0
      16: getfield      #3                  // Field lookAhead:Ljava/lang/Object;
      19: astore_1
      20: aload_0
      21: aconst_null
      22: putfield      #3                  // Field lookAhead:Ljava/lang/Object;
      25: aload_1
      26: areturn

  public boolean hasNext();
    Code:
       0: aload_0
       1: getfield      #3                  // Field lookAhead:Ljava/lang/Object;
       4: ifnonnull     50
       7: aload_0
       8: getfield      #4                  // Field i:Ljava/util/Iterator;
      11: invokeinterface #10,  1           // InterfaceMethod java/util/Iterator.hasNext:()Z
      16: ifeq          50
      19: aload_0
      20: getfield      #4                  // Field i:Ljava/util/Iterator;
      23: invokeinterface #11,  1           // InterfaceMethod java/util/Iterator.next:()Ljava/lang/Object;
      28: astore_1
      29: aload_0
      30: getfield      #5                  // Field filter:Lorg/xmlunit/util/Predicate;
      33: aload_1
      34: invokeinterface #12,  2           // InterfaceMethod org/xmlunit/util/Predicate.test:(Ljava/lang/Object;)Z
      39: ifeq          47
      42: aload_0
      43: aload_1
      44: putfield      #3                  // Field lookAhead:Ljava/lang/Object;
      47: goto          0
      50: aload_0
      51: getfield      #3                  // Field lookAhead:Ljava/lang/Object;
      54: ifnull        61
      57: iconst_1
      58: goto          62
      61: iconst_0
      62: ireturn

  org.xmlunit.util.Linqy$FilteringIterator(java.util.Iterator, org.xmlunit.util.Predicate, org.xmlunit.util.Linqy$1);
    Code:
       0: aload_0
       1: aload_1
       2: aload_2
       3: invokespecial #1                  // Method "<init>":(Ljava/util/Iterator;Lorg/xmlunit/util/Predicate;)V
       6: return
}
