Compiled from "SelectionEnabler.java"
public final class org.eclipse.ui.SelectionEnabler {
  public static final int ANY_NUMBER;

  private static final int HASH_CODE_NOT_COMPUTED;

  private static final int HASH_FACTOR;

  private static final int HASH_INITIAL;

  private static java.lang.Class<?> iTextSelectionClass;

  private static final java.lang.String JFACE_TEXT_PLUG_IN;

  public static final int MULTIPLE;

  public static final int NONE;

  public static final int NONE_OR_ONE;

  public static final int ONE_OR_MORE;

  private static final java.lang.String TEXT_SELECTION_CLASS;

  private static boolean textSelectionPossible;

  public static final int UNKNOWN;

  private java.util.List<org.eclipse.ui.SelectionEnabler$SelectionClass> classes;

  private org.eclipse.ui.internal.ActionExpression enablementExpression;

  private transient int hashCode;

  private int mode;

  static {};
    Code:
       0: ldc           #4                  // class org/eclipse/ui/SelectionEnabler
       2: invokevirtual #291                // Method java/lang/Class.getName:()Ljava/lang/String;
       5: invokevirtual #299                // Method java/lang/String.hashCode:()I
       8: putstatic     #279                // Field HASH_INITIAL:I
      11: aconst_null
      12: putstatic     #283                // Field iTextSelectionClass:Ljava/lang/Class;
      15: iconst_1
      16: putstatic     #282                // Field textSelectionPossible:Z
      19: return

  private static java.lang.Class<?> getTextSelectionClass();
    Code:
       0: getstatic     #283                // Field iTextSelectionClass:Ljava/lang/Class;
       3: ifnull        10
       6: getstatic     #283                // Field iTextSelectionClass:Ljava/lang/Class;
       9: areturn
      10: getstatic     #282                // Field textSelectionPossible:Z
      13: ifne          18
      16: aconst_null
      17: areturn
      18: ldc           #2                  // String org.eclipse.jface.text
      20: invokestatic  #306                // Method org/eclipse/core/runtime/Platform.getBundle:(Ljava/lang/String;)Lorg/osgi/framework/Bundle;
      23: astore_0
      24: aload_0
      25: ifnull        38
      28: aload_0
      29: invokeinterface #332,  1          // InterfaceMethod org/osgi/framework/Bundle.getState:()I
      34: iconst_1
      35: if_icmpne     44
      38: iconst_0
      39: putstatic     #282                // Field textSelectionPossible:Z
      42: aconst_null
      43: areturn
      44: aload_0
      45: invokeinterface #332,  1          // InterfaceMethod org/osgi/framework/Bundle.getState:()I
      50: iconst_2
      51: if_icmpne     60
      54: iconst_1
      55: putstatic     #282                // Field textSelectionPossible:Z
      58: aconst_null
      59: areturn
      60: aload_0
      61: ldc           #3                  // String org.eclipse.jface.text.ITextSelection
      63: invokeinterface #333,  2          // InterfaceMethod org/osgi/framework/Bundle.loadClass:(Ljava/lang/String;)Ljava/lang/Class;
      68: astore_1
      69: aload_1
      70: putstatic     #283                // Field iTextSelectionClass:Ljava/lang/Class;
      73: getstatic     #283                // Field iTextSelectionClass:Ljava/lang/Class;
      76: areturn
      77: pop
      78: iconst_0
      79: putstatic     #282                // Field textSelectionPossible:Z
      82: aconst_null
      83: areturn
    Exception table:
       from    to  target type
          60    76    77   Class java/lang/ClassNotFoundException

  public static boolean verifyNameMatch(java.lang.String, java.lang.String);
    Code:
       0: aload_1
       1: aload_0
       2: invokestatic  #317                // Method org/eclipse/ui/actions/SimpleWildcardTester.testWildcardIgnoreCase:(Ljava/lang/String;Ljava/lang/String;)Z
       5: ireturn

  public org.eclipse.ui.SelectionEnabler(org.eclipse.core.runtime.IConfigurationElement);
    Code:
       0: aload_0
       1: invokespecial #297                // Method java/lang/Object."<init>":()V
       4: aload_0
       5: new           #170                // class java/util/ArrayList
       8: dup
       9: invokespecial #302                // Method java/util/ArrayList."<init>":()V
      12: putfield      #284                // Field classes:Ljava/util/List;
      15: aload_0
      16: iconst_m1
      17: putfield      #280                // Field hashCode:I
      20: aload_0
      21: iconst_0
      22: putfield      #281                // Field mode:I
      25: aload_1
      26: ifnonnull     37
      29: new           #161                // class java/lang/IllegalArgumentException
      32: dup
      33: invokespecial #293                // Method java/lang/IllegalArgumentException."<init>":()V
      36: athrow
      37: aload_0
      38: aload_1
      39: invokevirtual #310                // Method parseClasses:(Lorg/eclipse/core/runtime/IConfigurationElement;)V
      42: return

  public boolean equals(java.lang.Object);
    Code:
       0: aload_1
       1: instanceof    #4                  // class org/eclipse/ui/SelectionEnabler
       4: ifeq          55
       7: aload_1
       8: checkcast     #4                  // class org/eclipse/ui/SelectionEnabler
      11: astore_2
      12: aload_0
      13: getfield      #284                // Field classes:Ljava/util/List;
      16: aload_2
      17: getfield      #284                // Field classes:Ljava/util/List;
      20: invokestatic  #304                // Method java/util/Objects.equals:(Ljava/lang/Object;Ljava/lang/Object;)Z
      23: ifeq          53
      26: aload_0
      27: getfield      #285                // Field enablementExpression:Lorg/eclipse/ui/internal/ActionExpression;
      30: aload_2
      31: getfield      #285                // Field enablementExpression:Lorg/eclipse/ui/internal/ActionExpression;
      34: invokestatic  #304                // Method java/util/Objects.equals:(Ljava/lang/Object;Ljava/lang/Object;)Z
      37: ifeq          53
      40: aload_0
      41: getfield      #281                // Field mode:I
      44: aload_2
      45: getfield      #281                // Field mode:I
      48: if_icmpne     53
      51: iconst_1
      52: ireturn
      53: iconst_0
      54: ireturn
      55: iconst_0
      56: ireturn

  public int hashCode();
    Code:
       0: aload_0
       1: getfield      #280                // Field hashCode:I
       4: iconst_m1
       5: if_icmpne     82
       8: aload_0
       9: getstatic     #279                // Field HASH_INITIAL:I
      12: bipush        89
      14: imul
      15: aload_0
      16: getfield      #284                // Field classes:Ljava/util/List;
      19: invokestatic  #303                // Method java/util/Objects.hashCode:(Ljava/lang/Object;)I
      22: iadd
      23: putfield      #280                // Field hashCode:I
      26: aload_0
      27: aload_0
      28: getfield      #280                // Field hashCode:I
      31: bipush        89
      33: imul
      34: aload_0
      35: getfield      #285                // Field enablementExpression:Lorg/eclipse/ui/internal/ActionExpression;
      38: invokestatic  #303                // Method java/util/Objects.hashCode:(Ljava/lang/Object;)I
      41: iadd
      42: putfield      #280                // Field hashCode:I
      45: aload_0
      46: aload_0
      47: getfield      #280                // Field hashCode:I
      50: bipush        89
      52: imul
      53: aload_0
      54: getfield      #281                // Field mode:I
      57: invokestatic  #295                // Method java/lang/Integer.hashCode:(I)I
      60: iadd
      61: putfield      #280                // Field hashCode:I
      64: aload_0
      65: getfield      #280                // Field hashCode:I
      68: iconst_m1
      69: if_icmpne     82
      72: aload_0
      73: dup
      74: getfield      #280                // Field hashCode:I
      77: iconst_1
      78: iadd
      79: putfield      #280                // Field hashCode:I
      82: aload_0
      83: getfield      #280                // Field hashCode:I
      86: ireturn

  private boolean isEnabledFor(org.eclipse.jface.viewers.ISelection);
    Code:
       0: aload_1
       1: astore_2
       2: aload_1
       3: invokeinterface #328,  1          // InterfaceMethod org/eclipse/jface/viewers/ISelection.isEmpty:()Z
       8: ifeq          15
      11: iconst_0
      12: goto          16
      15: iconst_1
      16: istore_3
      17: aload_0
      18: iload_3
      19: invokevirtual #307                // Method verifySelectionCount:(I)Z
      22: ifne          27
      25: iconst_0
      26: ireturn
      27: aload_0
      28: getfield      #285                // Field enablementExpression:Lorg/eclipse/ui/internal/ActionExpression;
      31: ifnull        43
      34: aload_0
      35: getfield      #285                // Field enablementExpression:Lorg/eclipse/ui/internal/ActionExpression;
      38: aload_2
      39: invokevirtual #318                // Method org/eclipse/ui/internal/ActionExpression.isEnabledFor:(Ljava/lang/Object;)Z
      42: ireturn
      43: aload_0
      44: getfield      #284                // Field classes:Ljava/util/List;
      47: invokeinterface #323,  1          // InterfaceMethod java/util/List.isEmpty:()Z
      52: ifeq          57
      55: iconst_1
      56: ireturn
      57: aload_2
      58: instanceof    #175                // class org/eclipse/core/runtime/IAdaptable
      61: ifeq          81
      64: aload_2
      65: checkcast     #175                // class org/eclipse/core/runtime/IAdaptable
      68: astore        4
      70: aload_0
      71: aload         4
      73: invokevirtual #309                // Method verifyElement:(Lorg/eclipse/core/runtime/IAdaptable;)Z
      76: ifne          83
      79: iconst_0
      80: ireturn
      81: iconst_0
      82: ireturn
      83: iconst_1
      84: ireturn

  private boolean isEnabledFor(org.eclipse.jface.viewers.ISelection, int);
    Code:
       0: aload_0
       1: iload_2
       2: invokevirtual #307                // Method verifySelectionCount:(I)Z
       5: ifne          10
       8: iconst_0
       9: ireturn
      10: aload_0
      11: getfield      #285                // Field enablementExpression:Lorg/eclipse/ui/internal/ActionExpression;
      14: ifnull        26
      17: aload_0
      18: getfield      #285                // Field enablementExpression:Lorg/eclipse/ui/internal/ActionExpression;
      21: aload_1
      22: invokevirtual #318                // Method org/eclipse/ui/internal/ActionExpression.isEnabledFor:(Ljava/lang/Object;)Z
      25: ireturn
      26: aload_0
      27: getfield      #284                // Field classes:Ljava/util/List;
      30: invokeinterface #323,  1          // InterfaceMethod java/util/List.isEmpty:()Z
      35: ifeq          40
      38: iconst_1
      39: ireturn
      40: aload_0
      41: getfield      #284                // Field classes:Ljava/util/List;
      44: invokeinterface #325,  1          // InterfaceMethod java/util/List.iterator:()Ljava/util/Iterator;
      49: astore        4
      51: goto          79
      54: aload         4
      56: invokeinterface #322,  1          // InterfaceMethod java/util/Iterator.next:()Ljava/lang/Object;
      61: checkcast     #181                // class org/eclipse/ui/SelectionEnabler$SelectionClass
      64: astore_3
      65: aload_0
      66: aload_1
      67: aload_3
      68: getfield      #286                // Field org/eclipse/ui/SelectionEnabler$SelectionClass.className:Ljava/lang/String;
      71: invokevirtual #314                // Method verifyClass:(Ljava/lang/Object;Ljava/lang/String;)Z
      74: ifeq          79
      77: iconst_1
      78: ireturn
      79: aload         4
      81: invokeinterface #321,  1          // InterfaceMethod java/util/Iterator.hasNext:()Z
      86: ifne          54
      89: iconst_0
      90: ireturn

  private boolean isEnabledFor(org.eclipse.jface.viewers.IStructuredSelection);
    Code:
       0: aload_1
       1: invokeinterface #329,  1          // InterfaceMethod org/eclipse/jface/viewers/IStructuredSelection.size:()I
       6: istore_2
       7: aload_0
       8: iload_2
       9: invokevirtual #307                // Method verifySelectionCount:(I)Z
      12: ifne          17
      15: iconst_0
      16: ireturn
      17: aload_0
      18: getfield      #285                // Field enablementExpression:Lorg/eclipse/ui/internal/ActionExpression;
      21: ifnull        33
      24: aload_0
      25: getfield      #285                // Field enablementExpression:Lorg/eclipse/ui/internal/ActionExpression;
      28: aload_1
      29: invokevirtual #320                // Method org/eclipse/ui/internal/ActionExpression.isEnabledFor:(Lorg/eclipse/jface/viewers/IStructuredSelection;)Z
      32: ireturn
      33: aload_0
      34: getfield      #284                // Field classes:Ljava/util/List;
      37: invokeinterface #323,  1          // InterfaceMethod java/util/List.isEmpty:()Z
      42: ifeq          47
      45: iconst_1
      46: ireturn
      47: aload_1
      48: invokeinterface #330,  1          // InterfaceMethod org/eclipse/jface/viewers/IStructuredSelection.iterator:()Ljava/util/Iterator;
      53: astore        4
      55: goto          92
      58: aload         4
      60: invokeinterface #322,  1          // InterfaceMethod java/util/Iterator.next:()Ljava/lang/Object;
      65: astore_3
      66: aload_3
      67: instanceof    #175                // class org/eclipse/core/runtime/IAdaptable
      70: ifeq          90
      73: aload_3
      74: checkcast     #175                // class org/eclipse/core/runtime/IAdaptable
      77: astore        5
      79: aload_0
      80: aload         5
      82: invokevirtual #309                // Method verifyElement:(Lorg/eclipse/core/runtime/IAdaptable;)Z
      85: ifne          92
      88: iconst_0
      89: ireturn
      90: iconst_0
      91: ireturn
      92: aload         4
      94: invokeinterface #321,  1          // InterfaceMethod java/util/Iterator.hasNext:()Z
      99: ifne          58
     102: iconst_1
     103: ireturn

  public boolean isEnabledForSelection(org.eclipse.jface.viewers.ISelection);
    Code:
       0: aload_0
       1: getfield      #281                // Field mode:I
       4: ifne          9
       7: iconst_0
       8: ireturn
       9: aload_1
      10: ifnonnull     17
      13: getstatic     #278                // Field org/eclipse/jface/viewers/StructuredSelection.EMPTY:Lorg/eclipse/jface/viewers/StructuredSelection;
      16: astore_1
      17: aload_1
      18: instanceof    #179                // class org/eclipse/jface/viewers/IStructuredSelection
      21: ifeq          33
      24: aload_0
      25: aload_1
      26: checkcast     #179                // class org/eclipse/jface/viewers/IStructuredSelection
      29: invokevirtual #313                // Method isEnabledFor:(Lorg/eclipse/jface/viewers/IStructuredSelection;)Z
      32: ireturn
      33: invokestatic  #308                // Method getTextSelectionClass:()Ljava/lang/Class;
      36: astore_2
      37: aload_2
      38: ifnull        96
      41: aload_2
      42: aload_1
      43: invokevirtual #290                // Method java/lang/Class.isInstance:(Ljava/lang/Object;)Z
      46: ifeq          96
      49: aload_2
      50: ldc           #1                  // String getLength
      52: iconst_0
      53: anewarray     #158                // class java/lang/Class
      56: invokevirtual #292                // Method java/lang/Class.getDeclaredMethod:(Ljava/lang/String;[Ljava/lang/Class;)Ljava/lang/reflect/Method;
      59: astore_3
      60: aload_3
      61: aload_1
      62: iconst_0
      63: anewarray     #165                // class java/lang/Object
      66: invokevirtual #301                // Method java/lang/reflect/Method.invoke:(Ljava/lang/Object;[Ljava/lang/Object;)Ljava/lang/Object;
      69: astore        4
      71: aload         4
      73: instanceof    #162                // class java/lang/Integer
      76: ifeq          93
      79: aload_0
      80: aload_1
      81: aload         4
      83: checkcast     #162                // class java/lang/Integer
      86: invokevirtual #294                // Method java/lang/Integer.intValue:()I
      89: invokevirtual #312                // Method isEnabledFor:(Lorg/eclipse/jface/viewers/ISelection;I)Z
      92: ireturn
      93: iconst_1
      94: ireturn
      95: pop
      96: aload_0
      97: aload_1
      98: invokevirtual #311                // Method isEnabledFor:(Lorg/eclipse/jface/viewers/ISelection;)Z
     101: ireturn
    Exception table:
       from    to  target type
          49    92    95   Class java/lang/NoSuchMethodException
          49    92    95   Class java/lang/IllegalAccessException
          49    92    95   Class java/lang/reflect/InvocationTargetException

  private void parseClasses(org.eclipse.core.runtime.IConfigurationElement);
    Code:
       0: aload_1
       1: ldc_w         #152                // String enablesFor
       4: invokeinterface #326,  2          // InterfaceMethod org/eclipse/core/runtime/IConfigurationElement.getAttribute:(Ljava/lang/String;)Ljava/lang/String;
       9: astore_2
      10: aload_2
      11: ifnonnull     18
      14: ldc_w         #146                // String *
      17: astore_2
      18: aload_2
      19: dup
      20: astore_3
      21: invokevirtual #299                // Method java/lang/String.hashCode:()I
      24: lookupswitch  { // 6
                    33: 84
                    42: 97
                    43: 110
                    63: 123
                  1593: 136
             653829648: 149
               default: 206
          }
      84: aload_3
      85: ldc_w         #145                // String !
      88: invokevirtual #300                // Method java/lang/String.equals:(Ljava/lang/Object;)Z
      91: ifne          180
      94: goto          206
      97: aload_3
      98: ldc_w         #146                // String *
     101: invokevirtual #300                // Method java/lang/String.equals:(Ljava/lang/Object;)Z
     104: ifne          162
     107: goto          206
     110: aload_3
     111: ldc_w         #147                // String +
     114: invokevirtual #300                // Method java/lang/String.equals:(Ljava/lang/Object;)Z
     117: ifne          189
     120: goto          206
     123: aload_3
     124: ldc_w         #149                // String ?
     127: invokevirtual #300                // Method java/lang/String.equals:(Ljava/lang/Object;)Z
     130: ifne          171
     133: goto          206
     136: aload_3
     137: ldc_w         #148                // String 2+
     140: invokevirtual #300                // Method java/lang/String.equals:(Ljava/lang/Object;)Z
     143: ifne          197
     146: goto          206
     149: aload_3
     150: ldc_w         #153                // String multiple
     153: invokevirtual #300                // Method java/lang/String.equals:(Ljava/lang/Object;)Z
     156: ifne          197
     159: goto          206
     162: aload_0
     163: bipush        -2
     165: putfield      #281                // Field mode:I
     168: goto          223
     171: aload_0
     172: bipush        -3
     174: putfield      #281                // Field mode:I
     177: goto          223
     180: aload_0
     181: bipush        -4
     183: putfield      #281                // Field mode:I
     186: goto          223
     189: aload_0
     190: iconst_m1
     191: putfield      #281                // Field mode:I
     194: goto          223
     197: aload_0
     198: bipush        -5
     200: putfield      #281                // Field mode:I
     203: goto          223
     206: aload_0
     207: aload_2
     208: invokestatic  #296                // Method java/lang/Integer.parseInt:(Ljava/lang/String;)I
     211: putfield      #281                // Field mode:I
     214: goto          223
     217: pop
     218: aload_0
     219: iconst_0
     220: putfield      #281                // Field mode:I
     223: aload_1
     224: ldc_w         #151                // String enablement
     227: invokeinterface #327,  2          // InterfaceMethod org/eclipse/core/runtime/IConfigurationElement.getChildren:(Ljava/lang/String;)[Lorg/eclipse/core/runtime/IConfigurationElement;
     232: astore        4
     234: aload         4
     236: arraylength
     237: ifle          256
     240: aload_0
     241: new           #183                // class org/eclipse/ui/internal/ActionExpression
     244: dup
     245: aload         4
     247: iconst_0
     248: aaload
     249: invokespecial #319                // Method org/eclipse/ui/internal/ActionExpression."<init>":(Lorg/eclipse/core/runtime/IConfigurationElement;)V
     252: putfield      #285                // Field enablementExpression:Lorg/eclipse/ui/internal/ActionExpression;
     255: return
     256: aload_1
     257: ldc_w         #155                // String selection
     260: invokeinterface #327,  2          // InterfaceMethod org/eclipse/core/runtime/IConfigurationElement.getChildren:(Ljava/lang/String;)[Lorg/eclipse/core/runtime/IConfigurationElement;
     265: astore        4
     267: aload         4
     269: arraylength
     270: ifle          374
     273: aload_0
     274: new           #170                // class java/util/ArrayList
     277: dup
     278: invokespecial #302                // Method java/util/ArrayList."<init>":()V
     281: putfield      #284                // Field classes:Ljava/util/List;
     284: aload         4
     286: dup
     287: astore        8
     289: arraylength
     290: istore        7
     292: iconst_0
     293: istore        6
     295: goto          367
     298: aload         8
     300: iload         6
     302: aaload
     303: astore        5
     305: aload         5
     307: ldc_w         #150                // String class
     310: invokeinterface #326,  2          // InterfaceMethod org/eclipse/core/runtime/IConfigurationElement.getAttribute:(Ljava/lang/String;)Ljava/lang/String;
     315: astore        9
     317: aload         5
     319: ldc_w         #154                // String name
     322: invokeinterface #326,  2          // InterfaceMethod org/eclipse/core/runtime/IConfigurationElement.getAttribute:(Ljava/lang/String;)Ljava/lang/String;
     327: astore        10
     329: new           #181                // class org/eclipse/ui/SelectionEnabler$SelectionClass
     332: dup
     333: invokespecial #316                // Method org/eclipse/ui/SelectionEnabler$SelectionClass."<init>":()V
     336: astore        11
     338: aload         11
     340: aload         9
     342: putfield      #286                // Field org/eclipse/ui/SelectionEnabler$SelectionClass.className:Ljava/lang/String;
     345: aload         11
     347: aload         10
     349: putfield      #287                // Field org/eclipse/ui/SelectionEnabler$SelectionClass.nameFilter:Ljava/lang/String;
     352: aload_0
     353: getfield      #284                // Field classes:Ljava/util/List;
     356: aload         11
     358: invokeinterface #324,  2          // InterfaceMethod java/util/List.add:(Ljava/lang/Object;)Z
     363: pop
     364: iinc          6, 1
     367: iload         6
     369: iload         7
     371: if_icmplt     298
     374: return
    Exception table:
       from    to  target type
         206   214   217   Class java/lang/NumberFormatException

  private boolean verifyClass(java.lang.Object, java.lang.String);
    Code:
       0: aload_1
       1: invokevirtual #298                // Method java/lang/Object.getClass:()Ljava/lang/Class;
       4: astore_3
       5: aload_3
       6: astore        4
       8: iconst_0
       9: istore        5
      11: goto          103
      14: aload         4
      16: invokevirtual #291                // Method java/lang/Class.getName:()Ljava/lang/String;
      19: aload_2
      20: invokevirtual #300                // Method java/lang/String.equals:(Ljava/lang/Object;)Z
      23: ifeq          32
      26: iconst_1
      27: istore        5
      29: goto          108
      32: aload         4
      34: invokevirtual #289                // Method java/lang/Class.getInterfaces:()[Ljava/lang/Class;
      37: astore        6
      39: aload         6
      41: dup
      42: astore        10
      44: arraylength
      45: istore        9
      47: iconst_0
      48: istore        8
      50: goto          81
      53: aload         10
      55: iload         8
      57: aaload
      58: astore        7
      60: aload         7
      62: invokevirtual #291                // Method java/lang/Class.getName:()Ljava/lang/String;
      65: aload_2
      66: invokevirtual #300                // Method java/lang/String.equals:(Ljava/lang/Object;)Z
      69: ifeq          78
      72: iconst_1
      73: istore        5
      75: goto          88
      78: iinc          8, 1
      81: iload         8
      83: iload         9
      85: if_icmplt     53
      88: iload         5
      90: ifeq          96
      93: goto          108
      96: aload         4
      98: invokevirtual #288                // Method java/lang/Class.getSuperclass:()Ljava/lang/Class;
     101: astore        4
     103: aload         4
     105: ifnonnull     14
     108: iload         5
     110: ireturn

  private boolean verifyElement(org.eclipse.core.runtime.IAdaptable);
    Code:
       0: aload_0
       1: getfield      #284                // Field classes:Ljava/util/List;
       4: invokeinterface #323,  1          // InterfaceMethod java/util/List.isEmpty:()Z
       9: ifeq          14
      12: iconst_1
      13: ireturn
      14: aload_0
      15: getfield      #284                // Field classes:Ljava/util/List;
      18: invokeinterface #325,  1          // InterfaceMethod java/util/List.iterator:()Ljava/util/Iterator;
      23: astore_3
      24: goto          98
      27: aload_3
      28: invokeinterface #322,  1          // InterfaceMethod java/util/Iterator.next:()Ljava/lang/Object;
      33: checkcast     #181                // class org/eclipse/ui/SelectionEnabler$SelectionClass
      36: astore_2
      37: aload_0
      38: aload_1
      39: aload_2
      40: getfield      #286                // Field org/eclipse/ui/SelectionEnabler$SelectionClass.className:Ljava/lang/String;
      43: invokevirtual #314                // Method verifyClass:(Ljava/lang/Object;Ljava/lang/String;)Z
      46: ifne          52
      49: goto          98
      52: aload_2
      53: getfield      #287                // Field org/eclipse/ui/SelectionEnabler$SelectionClass.nameFilter:Ljava/lang/String;
      56: ifnonnull     61
      59: iconst_1
      60: ireturn
      61: aload_1
      62: ldc_w         #184                // class org/eclipse/ui/model/IWorkbenchAdapter
      65: invokestatic  #305                // Method org/eclipse/core/runtime/Adapters.adapt:(Ljava/lang/Object;Ljava/lang/Class;)Ljava/lang/Object;
      68: checkcast     #184                // class org/eclipse/ui/model/IWorkbenchAdapter
      71: astore        4
      73: aload         4
      75: ifnull        98
      78: aload         4
      80: aload_1
      81: invokeinterface #331,  2          // InterfaceMethod org/eclipse/ui/model/IWorkbenchAdapter.getLabel:(Ljava/lang/Object;)Ljava/lang/String;
      86: aload_2
      87: getfield      #287                // Field org/eclipse/ui/SelectionEnabler$SelectionClass.nameFilter:Ljava/lang/String;
      90: invokestatic  #315                // Method verifyNameMatch:(Ljava/lang/String;Ljava/lang/String;)Z
      93: ifeq          98
      96: iconst_1
      97: ireturn
      98: aload_3
      99: invokeinterface #321,  1          // InterfaceMethod java/util/Iterator.hasNext:()Z
     104: ifne          27
     107: iconst_0
     108: ireturn

  private boolean verifySelectionCount(int);
    Code:
       0: iload_1
       1: ifle          15
       4: aload_0
       5: getfield      #281                // Field mode:I
       8: bipush        -4
      10: if_icmpne     15
      13: iconst_0
      14: ireturn
      15: iload_1
      16: ifne          29
      19: aload_0
      20: getfield      #281                // Field mode:I
      23: iconst_m1
      24: if_icmpne     29
      27: iconst_0
      28: ireturn
      29: iload_1
      30: iconst_1
      31: if_icmple     45
      34: aload_0
      35: getfield      #281                // Field mode:I
      38: bipush        -3
      40: if_icmpne     45
      43: iconst_0
      44: ireturn
      45: iload_1
      46: iconst_2
      47: if_icmpge     61
      50: aload_0
      51: getfield      #281                // Field mode:I
      54: bipush        -5
      56: if_icmpne     61
      59: iconst_0
      60: ireturn
      61: aload_0
      62: getfield      #281                // Field mode:I
      65: ifle          78
      68: iload_1
      69: aload_0
      70: getfield      #281                // Field mode:I
      73: if_icmpeq     78
      76: iconst_0
      77: ireturn
      78: iconst_1
      79: ireturn
}
