Compiled from "WorkbenchEncoding.java"
class org.eclipse.ui.WorkbenchEncoding$EncodingsRegistryReader extends org.eclipse.ui.internal.registry.RegistryReader {
  private java.util.List<java.lang.String> encodings;

  public org.eclipse.ui.WorkbenchEncoding$EncodingsRegistryReader(java.util.List<java.lang.String>);
    Code:
       0: aload_0
       1: invokespecial #40                 // Method org/eclipse/ui/internal/registry/RegistryReader."<init>":()V
       4: aload_0
       5: aload_1
       6: putfield      #39                 // Field encodings:Ljava/util/List;
       9: return

  protected boolean readElement(org.eclipse.core.runtime.IConfigurationElement);
    Code:
       0: aload_1
       1: ldc           #1                  // String name
       3: invokeinterface #42,  2           // InterfaceMethod org/eclipse/core/runtime/IConfigurationElement.getAttribute:(Ljava/lang/String;)Ljava/lang/String;
       8: astore_2
       9: aload_2
      10: ifnull        24
      13: aload_0
      14: getfield      #39                 // Field encodings:Ljava/util/List;
      17: aload_2
      18: invokeinterface #41,  2           // InterfaceMethod java/util/List.add:(Ljava/lang/Object;)Z
      23: pop
      24: iconst_1
      25: ireturn
}
