Compiled from "DateTimeFormatterBuilder.java"
public class org.joda.time.format.DateTimeFormatterBuilder {
  private java.util.ArrayList<java.lang.Object> iElementPairs;

  private java.lang.Object iFormatter;

  public org.joda.time.format.DateTimeFormatterBuilder();
    Code:
       0: aload_0
       1: invokespecial #1                  // Method java/lang/Object."<init>":()V
       4: aload_0
       5: new           #2                  // class java/util/ArrayList
       8: dup
       9: invokespecial #3                  // Method java/util/ArrayList."<init>":()V
      12: putfield      #4                  // Field iElementPairs:Ljava/util/ArrayList;
      15: return

  public org.joda.time.format.DateTimeFormatter toFormatter();
    Code:
       0: aload_0
       1: invokespecial #5                  // Method getFormatter:()Ljava/lang/Object;
       4: astore_1
       5: aconst_null
       6: astore_2
       7: aload_0
       8: aload_1
       9: invokespecial #6                  // Method isPrinter:(Ljava/lang/Object;)Z
      12: ifeq          20
      15: aload_1
      16: checkcast     #7                  // class org/joda/time/format/InternalPrinter
      19: astore_2
      20: aconst_null
      21: astore_3
      22: aload_0
      23: aload_1
      24: invokespecial #8                  // Method isParser:(Ljava/lang/Object;)Z
      27: ifeq          35
      30: aload_1
      31: checkcast     #9                  // class org/joda/time/format/InternalParser
      34: astore_3
      35: aload_2
      36: ifnonnull     43
      39: aload_3
      40: ifnull        53
      43: new           #10                 // class org/joda/time/format/DateTimeFormatter
      46: dup
      47: aload_2
      48: aload_3
      49: invokespecial #11                 // Method org/joda/time/format/DateTimeFormatter."<init>":(Lorg/joda/time/format/InternalPrinter;Lorg/joda/time/format/InternalParser;)V
      52: areturn
      53: new           #12                 // class java/lang/UnsupportedOperationException
      56: dup
      57: ldc           #13                 // String Both printing and parsing not supported
      59: invokespecial #14                 // Method java/lang/UnsupportedOperationException."<init>":(Ljava/lang/String;)V
      62: athrow

  public org.joda.time.format.DateTimePrinter toPrinter();
    Code:
       0: aload_0
       1: invokespecial #5                  // Method getFormatter:()Ljava/lang/Object;
       4: astore_1
       5: aload_0
       6: aload_1
       7: invokespecial #6                  // Method isPrinter:(Ljava/lang/Object;)Z
      10: ifeq          23
      13: aload_1
      14: checkcast     #7                  // class org/joda/time/format/InternalPrinter
      17: astore_2
      18: aload_2
      19: invokestatic  #15                 // Method org/joda/time/format/InternalPrinterDateTimePrinter.of:(Lorg/joda/time/format/InternalPrinter;)Lorg/joda/time/format/DateTimePrinter;
      22: areturn
      23: new           #12                 // class java/lang/UnsupportedOperationException
      26: dup
      27: ldc           #16                 // String Printing is not supported
      29: invokespecial #14                 // Method java/lang/UnsupportedOperationException."<init>":(Ljava/lang/String;)V
      32: athrow

  public org.joda.time.format.DateTimeParser toParser();
    Code:
       0: aload_0
       1: invokespecial #5                  // Method getFormatter:()Ljava/lang/Object;
       4: astore_1
       5: aload_0
       6: aload_1
       7: invokespecial #8                  // Method isParser:(Ljava/lang/Object;)Z
      10: ifeq          23
      13: aload_1
      14: checkcast     #9                  // class org/joda/time/format/InternalParser
      17: astore_2
      18: aload_2
      19: invokestatic  #17                 // Method org/joda/time/format/InternalParserDateTimeParser.of:(Lorg/joda/time/format/InternalParser;)Lorg/joda/time/format/DateTimeParser;
      22: areturn
      23: new           #12                 // class java/lang/UnsupportedOperationException
      26: dup
      27: ldc           #18                 // String Parsing is not supported
      29: invokespecial #14                 // Method java/lang/UnsupportedOperationException."<init>":(Ljava/lang/String;)V
      32: athrow

  public boolean canBuildFormatter();
    Code:
       0: aload_0
       1: aload_0
       2: invokespecial #5                  // Method getFormatter:()Ljava/lang/Object;
       5: invokespecial #19                 // Method isFormatter:(Ljava/lang/Object;)Z
       8: ireturn

  public boolean canBuildPrinter();
    Code:
       0: aload_0
       1: aload_0
       2: invokespecial #5                  // Method getFormatter:()Ljava/lang/Object;
       5: invokespecial #6                  // Method isPrinter:(Ljava/lang/Object;)Z
       8: ireturn

  public boolean canBuildParser();
    Code:
       0: aload_0
       1: aload_0
       2: invokespecial #5                  // Method getFormatter:()Ljava/lang/Object;
       5: invokespecial #8                  // Method isParser:(Ljava/lang/Object;)Z
       8: ireturn

  public void clear();
    Code:
       0: aload_0
       1: aconst_null
       2: putfield      #20                 // Field iFormatter:Ljava/lang/Object;
       5: aload_0
       6: getfield      #4                  // Field iElementPairs:Ljava/util/ArrayList;
       9: invokevirtual #21                 // Method java/util/ArrayList.clear:()V
      12: return

  public org.joda.time.format.DateTimeFormatterBuilder append(org.joda.time.format.DateTimeFormatter);
    Code:
       0: aload_1
       1: ifnonnull     14
       4: new           #22                 // class java/lang/IllegalArgumentException
       7: dup
       8: ldc           #23                 // String No formatter supplied
      10: invokespecial #24                 // Method java/lang/IllegalArgumentException."<init>":(Ljava/lang/String;)V
      13: athrow
      14: aload_0
      15: aload_1
      16: invokevirtual #25                 // Method org/joda/time/format/DateTimeFormatter.getPrinter0:()Lorg/joda/time/format/InternalPrinter;
      19: aload_1
      20: invokevirtual #26                 // Method org/joda/time/format/DateTimeFormatter.getParser0:()Lorg/joda/time/format/InternalParser;
      23: invokespecial #27                 // Method append0:(Lorg/joda/time/format/InternalPrinter;Lorg/joda/time/format/InternalParser;)Lorg/joda/time/format/DateTimeFormatterBuilder;
      26: areturn

  public org.joda.time.format.DateTimeFormatterBuilder append(org.joda.time.format.DateTimePrinter);
    Code:
       0: aload_0
       1: aload_1
       2: invokespecial #28                 // Method checkPrinter:(Lorg/joda/time/format/DateTimePrinter;)V
       5: aload_0
       6: aload_1
       7: invokestatic  #29                 // Method org/joda/time/format/DateTimePrinterInternalPrinter.of:(Lorg/joda/time/format/DateTimePrinter;)Lorg/joda/time/format/InternalPrinter;
      10: aconst_null
      11: invokespecial #27                 // Method append0:(Lorg/joda/time/format/InternalPrinter;Lorg/joda/time/format/InternalParser;)Lorg/joda/time/format/DateTimeFormatterBuilder;
      14: areturn

  public org.joda.time.format.DateTimeFormatterBuilder append(org.joda.time.format.DateTimeParser);
    Code:
       0: aload_0
       1: aload_1
       2: invokespecial #30                 // Method checkParser:(Lorg/joda/time/format/DateTimeParser;)V
       5: aload_0
       6: aconst_null
       7: aload_1
       8: invokestatic  #31                 // Method org/joda/time/format/DateTimeParserInternalParser.of:(Lorg/joda/time/format/DateTimeParser;)Lorg/joda/time/format/InternalParser;
      11: invokespecial #27                 // Method append0:(Lorg/joda/time/format/InternalPrinter;Lorg/joda/time/format/InternalParser;)Lorg/joda/time/format/DateTimeFormatterBuilder;
      14: areturn

  public org.joda.time.format.DateTimeFormatterBuilder append(org.joda.time.format.DateTimePrinter, org.joda.time.format.DateTimeParser);
    Code:
       0: aload_0
       1: aload_1
       2: invokespecial #28                 // Method checkPrinter:(Lorg/joda/time/format/DateTimePrinter;)V
       5: aload_0
       6: aload_2
       7: invokespecial #30                 // Method checkParser:(Lorg/joda/time/format/DateTimeParser;)V
      10: aload_0
      11: aload_1
      12: invokestatic  #29                 // Method org/joda/time/format/DateTimePrinterInternalPrinter.of:(Lorg/joda/time/format/DateTimePrinter;)Lorg/joda/time/format/InternalPrinter;
      15: aload_2
      16: invokestatic  #31                 // Method org/joda/time/format/DateTimeParserInternalParser.of:(Lorg/joda/time/format/DateTimeParser;)Lorg/joda/time/format/InternalParser;
      19: invokespecial #27                 // Method append0:(Lorg/joda/time/format/InternalPrinter;Lorg/joda/time/format/InternalParser;)Lorg/joda/time/format/DateTimeFormatterBuilder;
      22: areturn

  public org.joda.time.format.DateTimeFormatterBuilder append(org.joda.time.format.DateTimePrinter, org.joda.time.format.DateTimeParser[]);
    Code:
       0: aload_1
       1: ifnull        9
       4: aload_0
       5: aload_1
       6: invokespecial #28                 // Method checkPrinter:(Lorg/joda/time/format/DateTimePrinter;)V
       9: aload_2
      10: ifnonnull     23
      13: new           #22                 // class java/lang/IllegalArgumentException
      16: dup
      17: ldc           #32                 // String No parsers supplied
      19: invokespecial #24                 // Method java/lang/IllegalArgumentException."<init>":(Ljava/lang/String;)V
      22: athrow
      23: aload_2
      24: arraylength
      25: istore_3
      26: iload_3
      27: iconst_1
      28: if_icmpne     62
      31: aload_2
      32: iconst_0
      33: aaload
      34: ifnonnull     47
      37: new           #22                 // class java/lang/IllegalArgumentException
      40: dup
      41: ldc           #33                 // String No parser supplied
      43: invokespecial #24                 // Method java/lang/IllegalArgumentException."<init>":(Ljava/lang/String;)V
      46: athrow
      47: aload_0
      48: aload_1
      49: invokestatic  #29                 // Method org/joda/time/format/DateTimePrinterInternalPrinter.of:(Lorg/joda/time/format/DateTimePrinter;)Lorg/joda/time/format/InternalPrinter;
      52: aload_2
      53: iconst_0
      54: aaload
      55: invokestatic  #31                 // Method org/joda/time/format/DateTimeParserInternalParser.of:(Lorg/joda/time/format/DateTimeParser;)Lorg/joda/time/format/InternalParser;
      58: invokespecial #27                 // Method append0:(Lorg/joda/time/format/InternalPrinter;Lorg/joda/time/format/InternalParser;)Lorg/joda/time/format/DateTimeFormatterBuilder;
      61: areturn
      62: iload_3
      63: anewarray     #9                  // class org/joda/time/format/InternalParser
      66: astore        4
      68: iconst_0
      69: istore        5
      71: iload         5
      73: iload_3
      74: iconst_1
      75: isub
      76: if_icmpge     111
      79: aload         4
      81: iload         5
      83: aload_2
      84: iload         5
      86: aaload
      87: invokestatic  #31                 // Method org/joda/time/format/DateTimeParserInternalParser.of:(Lorg/joda/time/format/DateTimeParser;)Lorg/joda/time/format/InternalParser;
      90: dup_x2
      91: aastore
      92: ifnonnull     105
      95: new           #22                 // class java/lang/IllegalArgumentException
      98: dup
      99: ldc           #34                 // String Incomplete parser array
     101: invokespecial #24                 // Method java/lang/IllegalArgumentException."<init>":(Ljava/lang/String;)V
     104: athrow
     105: iinc          5, 1
     108: goto          71
     111: aload         4
     113: iload         5
     115: aload_2
     116: iload         5
     118: aaload
     119: invokestatic  #31                 // Method org/joda/time/format/DateTimeParserInternalParser.of:(Lorg/joda/time/format/DateTimeParser;)Lorg/joda/time/format/InternalParser;
     122: aastore
     123: aload_0
     124: aload_1
     125: invokestatic  #29                 // Method org/joda/time/format/DateTimePrinterInternalPrinter.of:(Lorg/joda/time/format/DateTimePrinter;)Lorg/joda/time/format/InternalPrinter;
     128: new           #35                 // class org/joda/time/format/DateTimeFormatterBuilder$MatchingParser
     131: dup
     132: aload         4
     134: invokespecial #36                 // Method org/joda/time/format/DateTimeFormatterBuilder$MatchingParser."<init>":([Lorg/joda/time/format/InternalParser;)V
     137: invokespecial #27                 // Method append0:(Lorg/joda/time/format/InternalPrinter;Lorg/joda/time/format/InternalParser;)Lorg/joda/time/format/DateTimeFormatterBuilder;
     140: areturn

  public org.joda.time.format.DateTimeFormatterBuilder appendOptional(org.joda.time.format.DateTimeParser);
    Code:
       0: aload_0
       1: aload_1
       2: invokespecial #30                 // Method checkParser:(Lorg/joda/time/format/DateTimeParser;)V
       5: iconst_2
       6: anewarray     #9                  // class org/joda/time/format/InternalParser
       9: dup
      10: iconst_0
      11: aload_1
      12: invokestatic  #31                 // Method org/joda/time/format/DateTimeParserInternalParser.of:(Lorg/joda/time/format/DateTimeParser;)Lorg/joda/time/format/InternalParser;
      15: aastore
      16: dup
      17: iconst_1
      18: aconst_null
      19: aastore
      20: astore_2
      21: aload_0
      22: aconst_null
      23: new           #35                 // class org/joda/time/format/DateTimeFormatterBuilder$MatchingParser
      26: dup
      27: aload_2
      28: invokespecial #36                 // Method org/joda/time/format/DateTimeFormatterBuilder$MatchingParser."<init>":([Lorg/joda/time/format/InternalParser;)V
      31: invokespecial #27                 // Method append0:(Lorg/joda/time/format/InternalPrinter;Lorg/joda/time/format/InternalParser;)Lorg/joda/time/format/DateTimeFormatterBuilder;
      34: areturn

  private void checkParser(org.joda.time.format.DateTimeParser);
    Code:
       0: aload_1
       1: ifnonnull     14
       4: new           #22                 // class java/lang/IllegalArgumentException
       7: dup
       8: ldc           #33                 // String No parser supplied
      10: invokespecial #24                 // Method java/lang/IllegalArgumentException."<init>":(Ljava/lang/String;)V
      13: athrow
      14: return

  private void checkPrinter(org.joda.time.format.DateTimePrinter);
    Code:
       0: aload_1
       1: ifnonnull     14
       4: new           #22                 // class java/lang/IllegalArgumentException
       7: dup
       8: ldc           #37                 // String No printer supplied
      10: invokespecial #24                 // Method java/lang/IllegalArgumentException."<init>":(Ljava/lang/String;)V
      13: athrow
      14: return

  private org.joda.time.format.DateTimeFormatterBuilder append0(java.lang.Object);
    Code:
       0: aload_0
       1: aconst_null
       2: putfield      #20                 // Field iFormatter:Ljava/lang/Object;
       5: aload_0
       6: getfield      #4                  // Field iElementPairs:Ljava/util/ArrayList;
       9: aload_1
      10: invokevirtual #38                 // Method java/util/ArrayList.add:(Ljava/lang/Object;)Z
      13: pop
      14: aload_0
      15: getfield      #4                  // Field iElementPairs:Ljava/util/ArrayList;
      18: aload_1
      19: invokevirtual #38                 // Method java/util/ArrayList.add:(Ljava/lang/Object;)Z
      22: pop
      23: aload_0
      24: areturn

  private org.joda.time.format.DateTimeFormatterBuilder append0(org.joda.time.format.InternalPrinter, org.joda.time.format.InternalParser);
    Code:
       0: aload_0
       1: aconst_null
       2: putfield      #20                 // Field iFormatter:Ljava/lang/Object;
       5: aload_0
       6: getfield      #4                  // Field iElementPairs:Ljava/util/ArrayList;
       9: aload_1
      10: invokevirtual #38                 // Method java/util/ArrayList.add:(Ljava/lang/Object;)Z
      13: pop
      14: aload_0
      15: getfield      #4                  // Field iElementPairs:Ljava/util/ArrayList;
      18: aload_2
      19: invokevirtual #38                 // Method java/util/ArrayList.add:(Ljava/lang/Object;)Z
      22: pop
      23: aload_0
      24: areturn

  public org.joda.time.format.DateTimeFormatterBuilder appendLiteral(char);
    Code:
       0: aload_0
       1: new           #39                 // class org/joda/time/format/DateTimeFormatterBuilder$CharacterLiteral
       4: dup
       5: iload_1
       6: invokespecial #40                 // Method org/joda/time/format/DateTimeFormatterBuilder$CharacterLiteral."<init>":(C)V
       9: invokespecial #41                 // Method append0:(Ljava/lang/Object;)Lorg/joda/time/format/DateTimeFormatterBuilder;
      12: areturn

  public org.joda.time.format.DateTimeFormatterBuilder appendLiteral(java.lang.String);
    Code:
       0: aload_1
       1: ifnonnull     14
       4: new           #22                 // class java/lang/IllegalArgumentException
       7: dup
       8: ldc           #42                 // String Literal must not be null
      10: invokespecial #24                 // Method java/lang/IllegalArgumentException."<init>":(Ljava/lang/String;)V
      13: athrow
      14: aload_1
      15: invokevirtual #43                 // Method java/lang/String.length:()I
      18: lookupswitch  { // 2
                     0: 44
                     1: 46
               default: 63
          }
      44: aload_0
      45: areturn
      46: aload_0
      47: new           #39                 // class org/joda/time/format/DateTimeFormatterBuilder$CharacterLiteral
      50: dup
      51: aload_1
      52: iconst_0
      53: invokevirtual #44                 // Method java/lang/String.charAt:(I)C
      56: invokespecial #40                 // Method org/joda/time/format/DateTimeFormatterBuilder$CharacterLiteral."<init>":(C)V
      59: invokespecial #41                 // Method append0:(Ljava/lang/Object;)Lorg/joda/time/format/DateTimeFormatterBuilder;
      62: areturn
      63: aload_0
      64: new           #45                 // class org/joda/time/format/DateTimeFormatterBuilder$StringLiteral
      67: dup
      68: aload_1
      69: invokespecial #46                 // Method org/joda/time/format/DateTimeFormatterBuilder$StringLiteral."<init>":(Ljava/lang/String;)V
      72: invokespecial #41                 // Method append0:(Ljava/lang/Object;)Lorg/joda/time/format/DateTimeFormatterBuilder;
      75: areturn

  public org.joda.time.format.DateTimeFormatterBuilder appendDecimal(org.joda.time.DateTimeFieldType, int, int);
    Code:
       0: aload_1
       1: ifnonnull     14
       4: new           #22                 // class java/lang/IllegalArgumentException
       7: dup
       8: ldc           #47                 // String Field type must not be null
      10: invokespecial #24                 // Method java/lang/IllegalArgumentException."<init>":(Ljava/lang/String;)V
      13: athrow
      14: iload_3
      15: iload_2
      16: if_icmpge     21
      19: iload_2
      20: istore_3
      21: iload_2
      22: iflt          29
      25: iload_3
      26: ifgt          37
      29: new           #22                 // class java/lang/IllegalArgumentException
      32: dup
      33: invokespecial #48                 // Method java/lang/IllegalArgumentException."<init>":()V
      36: athrow
      37: iload_2
      38: iconst_1
      39: if_icmpgt     57
      42: aload_0
      43: new           #49                 // class org/joda/time/format/DateTimeFormatterBuilder$UnpaddedNumber
      46: dup
      47: aload_1
      48: iload_3
      49: iconst_0
      50: invokespecial #50                 // Method org/joda/time/format/DateTimeFormatterBuilder$UnpaddedNumber."<init>":(Lorg/joda/time/DateTimeFieldType;IZ)V
      53: invokespecial #41                 // Method append0:(Ljava/lang/Object;)Lorg/joda/time/format/DateTimeFormatterBuilder;
      56: areturn
      57: aload_0
      58: new           #51                 // class org/joda/time/format/DateTimeFormatterBuilder$PaddedNumber
      61: dup
      62: aload_1
      63: iload_3
      64: iconst_0
      65: iload_2
      66: invokespecial #52                 // Method org/joda/time/format/DateTimeFormatterBuilder$PaddedNumber."<init>":(Lorg/joda/time/DateTimeFieldType;IZI)V
      69: invokespecial #41                 // Method append0:(Ljava/lang/Object;)Lorg/joda/time/format/DateTimeFormatterBuilder;
      72: areturn

  public org.joda.time.format.DateTimeFormatterBuilder appendFixedDecimal(org.joda.time.DateTimeFieldType, int);
    Code:
       0: aload_1
       1: ifnonnull     14
       4: new           #22                 // class java/lang/IllegalArgumentException
       7: dup
       8: ldc           #47                 // String Field type must not be null
      10: invokespecial #24                 // Method java/lang/IllegalArgumentException."<init>":(Ljava/lang/String;)V
      13: athrow
      14: iload_2
      15: ifgt          45
      18: new           #22                 // class java/lang/IllegalArgumentException
      21: dup
      22: new           #53                 // class java/lang/StringBuilder
      25: dup
      26: invokespecial #54                 // Method java/lang/StringBuilder."<init>":()V
      29: ldc           #55                 // String Illegal number of digits:
      31: invokevirtual #56                 // Method java/lang/StringBuilder.append:(Ljava/lang/String;)Ljava/lang/StringBuilder;
      34: iload_2
      35: invokevirtual #57                 // Method java/lang/StringBuilder.append:(I)Ljava/lang/StringBuilder;
      38: invokevirtual #58                 // Method java/lang/StringBuilder.toString:()Ljava/lang/String;
      41: invokespecial #24                 // Method java/lang/IllegalArgumentException."<init>":(Ljava/lang/String;)V
      44: athrow
      45: aload_0
      46: new           #59                 // class org/joda/time/format/DateTimeFormatterBuilder$FixedNumber
      49: dup
      50: aload_1
      51: iload_2
      52: iconst_0
      53: invokespecial #60                 // Method org/joda/time/format/DateTimeFormatterBuilder$FixedNumber."<init>":(Lorg/joda/time/DateTimeFieldType;IZ)V
      56: invokespecial #41                 // Method append0:(Ljava/lang/Object;)Lorg/joda/time/format/DateTimeFormatterBuilder;
      59: areturn

  public org.joda.time.format.DateTimeFormatterBuilder appendSignedDecimal(org.joda.time.DateTimeFieldType, int, int);
    Code:
       0: aload_1
       1: ifnonnull     14
       4: new           #22                 // class java/lang/IllegalArgumentException
       7: dup
       8: ldc           #47                 // String Field type must not be null
      10: invokespecial #24                 // Method java/lang/IllegalArgumentException."<init>":(Ljava/lang/String;)V
      13: athrow
      14: iload_3
      15: iload_2
      16: if_icmpge     21
      19: iload_2
      20: istore_3
      21: iload_2
      22: iflt          29
      25: iload_3
      26: ifgt          37
      29: new           #22                 // class java/lang/IllegalArgumentException
      32: dup
      33: invokespecial #48                 // Method java/lang/IllegalArgumentException."<init>":()V
      36: athrow
      37: iload_2
      38: iconst_1
      39: if_icmpgt     57
      42: aload_0
      43: new           #49                 // class org/joda/time/format/DateTimeFormatterBuilder$UnpaddedNumber
      46: dup
      47: aload_1
      48: iload_3
      49: iconst_1
      50: invokespecial #50                 // Method org/joda/time/format/DateTimeFormatterBuilder$UnpaddedNumber."<init>":(Lorg/joda/time/DateTimeFieldType;IZ)V
      53: invokespecial #41                 // Method append0:(Ljava/lang/Object;)Lorg/joda/time/format/DateTimeFormatterBuilder;
      56: areturn
      57: aload_0
      58: new           #51                 // class org/joda/time/format/DateTimeFormatterBuilder$PaddedNumber
      61: dup
      62: aload_1
      63: iload_3
      64: iconst_1
      65: iload_2
      66: invokespecial #52                 // Method org/joda/time/format/DateTimeFormatterBuilder$PaddedNumber."<init>":(Lorg/joda/time/DateTimeFieldType;IZI)V
      69: invokespecial #41                 // Method append0:(Ljava/lang/Object;)Lorg/joda/time/format/DateTimeFormatterBuilder;
      72: areturn

  public org.joda.time.format.DateTimeFormatterBuilder appendFixedSignedDecimal(org.joda.time.DateTimeFieldType, int);
    Code:
       0: aload_1
       1: ifnonnull     14
       4: new           #22                 // class java/lang/IllegalArgumentException
       7: dup
       8: ldc           #47                 // String Field type must not be null
      10: invokespecial #24                 // Method java/lang/IllegalArgumentException."<init>":(Ljava/lang/String;)V
      13: athrow
      14: iload_2
      15: ifgt          45
      18: new           #22                 // class java/lang/IllegalArgumentException
      21: dup
      22: new           #53                 // class java/lang/StringBuilder
      25: dup
      26: invokespecial #54                 // Method java/lang/StringBuilder."<init>":()V
      29: ldc           #55                 // String Illegal number of digits:
      31: invokevirtual #56                 // Method java/lang/StringBuilder.append:(Ljava/lang/String;)Ljava/lang/StringBuilder;
      34: iload_2
      35: invokevirtual #57                 // Method java/lang/StringBuilder.append:(I)Ljava/lang/StringBuilder;
      38: invokevirtual #58                 // Method java/lang/StringBuilder.toString:()Ljava/lang/String;
      41: invokespecial #24                 // Method java/lang/IllegalArgumentException."<init>":(Ljava/lang/String;)V
      44: athrow
      45: aload_0
      46: new           #59                 // class org/joda/time/format/DateTimeFormatterBuilder$FixedNumber
      49: dup
      50: aload_1
      51: iload_2
      52: iconst_1
      53: invokespecial #60                 // Method org/joda/time/format/DateTimeFormatterBuilder$FixedNumber."<init>":(Lorg/joda/time/DateTimeFieldType;IZ)V
      56: invokespecial #41                 // Method append0:(Ljava/lang/Object;)Lorg/joda/time/format/DateTimeFormatterBuilder;
      59: areturn

  public org.joda.time.format.DateTimeFormatterBuilder appendText(org.joda.time.DateTimeFieldType);
    Code:
       0: aload_1
       1: ifnonnull     14
       4: new           #22                 // class java/lang/IllegalArgumentException
       7: dup
       8: ldc           #47                 // String Field type must not be null
      10: invokespecial #24                 // Method java/lang/IllegalArgumentException."<init>":(Ljava/lang/String;)V
      13: athrow
      14: aload_0
      15: new           #61                 // class org/joda/time/format/DateTimeFormatterBuilder$TextField
      18: dup
      19: aload_1
      20: iconst_0
      21: invokespecial #62                 // Method org/joda/time/format/DateTimeFormatterBuilder$TextField."<init>":(Lorg/joda/time/DateTimeFieldType;Z)V
      24: invokespecial #41                 // Method append0:(Ljava/lang/Object;)Lorg/joda/time/format/DateTimeFormatterBuilder;
      27: areturn

  public org.joda.time.format.DateTimeFormatterBuilder appendShortText(org.joda.time.DateTimeFieldType);
    Code:
       0: aload_1
       1: ifnonnull     14
       4: new           #22                 // class java/lang/IllegalArgumentException
       7: dup
       8: ldc           #47                 // String Field type must not be null
      10: invokespecial #24                 // Method java/lang/IllegalArgumentException."<init>":(Ljava/lang/String;)V
      13: athrow
      14: aload_0
      15: new           #61                 // class org/joda/time/format/DateTimeFormatterBuilder$TextField
      18: dup
      19: aload_1
      20: iconst_1
      21: invokespecial #62                 // Method org/joda/time/format/DateTimeFormatterBuilder$TextField."<init>":(Lorg/joda/time/DateTimeFieldType;Z)V
      24: invokespecial #41                 // Method append0:(Ljava/lang/Object;)Lorg/joda/time/format/DateTimeFormatterBuilder;
      27: areturn

  public org.joda.time.format.DateTimeFormatterBuilder appendFraction(org.joda.time.DateTimeFieldType, int, int);
    Code:
       0: aload_1
       1: ifnonnull     14
       4: new           #22                 // class java/lang/IllegalArgumentException
       7: dup
       8: ldc           #47                 // String Field type must not be null
      10: invokespecial #24                 // Method java/lang/IllegalArgumentException."<init>":(Ljava/lang/String;)V
      13: athrow
      14: iload_3
      15: iload_2
      16: if_icmpge     21
      19: iload_2
      20: istore_3
      21: iload_2
      22: iflt          29
      25: iload_3
      26: ifgt          37
      29: new           #22                 // class java/lang/IllegalArgumentException
      32: dup
      33: invokespecial #48                 // Method java/lang/IllegalArgumentException."<init>":()V
      36: athrow
      37: aload_0
      38: new           #63                 // class org/joda/time/format/DateTimeFormatterBuilder$Fraction
      41: dup
      42: aload_1
      43: iload_2
      44: iload_3
      45: invokespecial #64                 // Method org/joda/time/format/DateTimeFormatterBuilder$Fraction."<init>":(Lorg/joda/time/DateTimeFieldType;II)V
      48: invokespecial #41                 // Method append0:(Ljava/lang/Object;)Lorg/joda/time/format/DateTimeFormatterBuilder;
      51: areturn

  public org.joda.time.format.DateTimeFormatterBuilder appendFractionOfSecond(int, int);
    Code:
       0: aload_0
       1: invokestatic  #65                 // Method org/joda/time/DateTimeFieldType.secondOfDay:()Lorg/joda/time/DateTimeFieldType;
       4: iload_1
       5: iload_2
       6: invokevirtual #66                 // Method appendFraction:(Lorg/joda/time/DateTimeFieldType;II)Lorg/joda/time/format/DateTimeFormatterBuilder;
       9: areturn

  public org.joda.time.format.DateTimeFormatterBuilder appendFractionOfMinute(int, int);
    Code:
       0: aload_0
       1: invokestatic  #67                 // Method org/joda/time/DateTimeFieldType.minuteOfDay:()Lorg/joda/time/DateTimeFieldType;
       4: iload_1
       5: iload_2
       6: invokevirtual #66                 // Method appendFraction:(Lorg/joda/time/DateTimeFieldType;II)Lorg/joda/time/format/DateTimeFormatterBuilder;
       9: areturn

  public org.joda.time.format.DateTimeFormatterBuilder appendFractionOfHour(int, int);
    Code:
       0: aload_0
       1: invokestatic  #68                 // Method org/joda/time/DateTimeFieldType.hourOfDay:()Lorg/joda/time/DateTimeFieldType;
       4: iload_1
       5: iload_2
       6: invokevirtual #66                 // Method appendFraction:(Lorg/joda/time/DateTimeFieldType;II)Lorg/joda/time/format/DateTimeFormatterBuilder;
       9: areturn

  public org.joda.time.format.DateTimeFormatterBuilder appendFractionOfDay(int, int);
    Code:
       0: aload_0
       1: invokestatic  #69                 // Method org/joda/time/DateTimeFieldType.dayOfYear:()Lorg/joda/time/DateTimeFieldType;
       4: iload_1
       5: iload_2
       6: invokevirtual #66                 // Method appendFraction:(Lorg/joda/time/DateTimeFieldType;II)Lorg/joda/time/format/DateTimeFormatterBuilder;
       9: areturn

  public org.joda.time.format.DateTimeFormatterBuilder appendMillisOfSecond(int);
    Code:
       0: aload_0
       1: invokestatic  #70                 // Method org/joda/time/DateTimeFieldType.millisOfSecond:()Lorg/joda/time/DateTimeFieldType;
       4: iload_1
       5: iconst_3
       6: invokevirtual #71                 // Method appendDecimal:(Lorg/joda/time/DateTimeFieldType;II)Lorg/joda/time/format/DateTimeFormatterBuilder;
       9: areturn

  public org.joda.time.format.DateTimeFormatterBuilder appendMillisOfDay(int);
    Code:
       0: aload_0
       1: invokestatic  #72                 // Method org/joda/time/DateTimeFieldType.millisOfDay:()Lorg/joda/time/DateTimeFieldType;
       4: iload_1
       5: bipush        8
       7: invokevirtual #71                 // Method appendDecimal:(Lorg/joda/time/DateTimeFieldType;II)Lorg/joda/time/format/DateTimeFormatterBuilder;
      10: areturn

  public org.joda.time.format.DateTimeFormatterBuilder appendSecondOfMinute(int);
    Code:
       0: aload_0
       1: invokestatic  #73                 // Method org/joda/time/DateTimeFieldType.secondOfMinute:()Lorg/joda/time/DateTimeFieldType;
       4: iload_1
       5: iconst_2
       6: invokevirtual #71                 // Method appendDecimal:(Lorg/joda/time/DateTimeFieldType;II)Lorg/joda/time/format/DateTimeFormatterBuilder;
       9: areturn

  public org.joda.time.format.DateTimeFormatterBuilder appendSecondOfDay(int);
    Code:
       0: aload_0
       1: invokestatic  #65                 // Method org/joda/time/DateTimeFieldType.secondOfDay:()Lorg/joda/time/DateTimeFieldType;
       4: iload_1
       5: iconst_5
       6: invokevirtual #71                 // Method appendDecimal:(Lorg/joda/time/DateTimeFieldType;II)Lorg/joda/time/format/DateTimeFormatterBuilder;
       9: areturn

  public org.joda.time.format.DateTimeFormatterBuilder appendMinuteOfHour(int);
    Code:
       0: aload_0
       1: invokestatic  #74                 // Method org/joda/time/DateTimeFieldType.minuteOfHour:()Lorg/joda/time/DateTimeFieldType;
       4: iload_1
       5: iconst_2
       6: invokevirtual #71                 // Method appendDecimal:(Lorg/joda/time/DateTimeFieldType;II)Lorg/joda/time/format/DateTimeFormatterBuilder;
       9: areturn

  public org.joda.time.format.DateTimeFormatterBuilder appendMinuteOfDay(int);
    Code:
       0: aload_0
       1: invokestatic  #67                 // Method org/joda/time/DateTimeFieldType.minuteOfDay:()Lorg/joda/time/DateTimeFieldType;
       4: iload_1
       5: iconst_4
       6: invokevirtual #71                 // Method appendDecimal:(Lorg/joda/time/DateTimeFieldType;II)Lorg/joda/time/format/DateTimeFormatterBuilder;
       9: areturn

  public org.joda.time.format.DateTimeFormatterBuilder appendHourOfDay(int);
    Code:
       0: aload_0
       1: invokestatic  #68                 // Method org/joda/time/DateTimeFieldType.hourOfDay:()Lorg/joda/time/DateTimeFieldType;
       4: iload_1
       5: iconst_2
       6: invokevirtual #71                 // Method appendDecimal:(Lorg/joda/time/DateTimeFieldType;II)Lorg/joda/time/format/DateTimeFormatterBuilder;
       9: areturn

  public org.joda.time.format.DateTimeFormatterBuilder appendClockhourOfDay(int);
    Code:
       0: aload_0
       1: invokestatic  #75                 // Method org/joda/time/DateTimeFieldType.clockhourOfDay:()Lorg/joda/time/DateTimeFieldType;
       4: iload_1
       5: iconst_2
       6: invokevirtual #71                 // Method appendDecimal:(Lorg/joda/time/DateTimeFieldType;II)Lorg/joda/time/format/DateTimeFormatterBuilder;
       9: areturn

  public org.joda.time.format.DateTimeFormatterBuilder appendHourOfHalfday(int);
    Code:
       0: aload_0
       1: invokestatic  #76                 // Method org/joda/time/DateTimeFieldType.hourOfHalfday:()Lorg/joda/time/DateTimeFieldType;
       4: iload_1
       5: iconst_2
       6: invokevirtual #71                 // Method appendDecimal:(Lorg/joda/time/DateTimeFieldType;II)Lorg/joda/time/format/DateTimeFormatterBuilder;
       9: areturn

  public org.joda.time.format.DateTimeFormatterBuilder appendClockhourOfHalfday(int);
    Code:
       0: aload_0
       1: invokestatic  #77                 // Method org/joda/time/DateTimeFieldType.clockhourOfHalfday:()Lorg/joda/time/DateTimeFieldType;
       4: iload_1
       5: iconst_2
       6: invokevirtual #71                 // Method appendDecimal:(Lorg/joda/time/DateTimeFieldType;II)Lorg/joda/time/format/DateTimeFormatterBuilder;
       9: areturn

  public org.joda.time.format.DateTimeFormatterBuilder appendDayOfWeek(int);
    Code:
       0: aload_0
       1: invokestatic  #78                 // Method org/joda/time/DateTimeFieldType.dayOfWeek:()Lorg/joda/time/DateTimeFieldType;
       4: iload_1
       5: iconst_1
       6: invokevirtual #71                 // Method appendDecimal:(Lorg/joda/time/DateTimeFieldType;II)Lorg/joda/time/format/DateTimeFormatterBuilder;
       9: areturn

  public org.joda.time.format.DateTimeFormatterBuilder appendDayOfMonth(int);
    Code:
       0: aload_0
       1: invokestatic  #79                 // Method org/joda/time/DateTimeFieldType.dayOfMonth:()Lorg/joda/time/DateTimeFieldType;
       4: iload_1
       5: iconst_2
       6: invokevirtual #71                 // Method appendDecimal:(Lorg/joda/time/DateTimeFieldType;II)Lorg/joda/time/format/DateTimeFormatterBuilder;
       9: areturn

  public org.joda.time.format.DateTimeFormatterBuilder appendDayOfYear(int);
    Code:
       0: aload_0
       1: invokestatic  #69                 // Method org/joda/time/DateTimeFieldType.dayOfYear:()Lorg/joda/time/DateTimeFieldType;
       4: iload_1
       5: iconst_3
       6: invokevirtual #71                 // Method appendDecimal:(Lorg/joda/time/DateTimeFieldType;II)Lorg/joda/time/format/DateTimeFormatterBuilder;
       9: areturn

  public org.joda.time.format.DateTimeFormatterBuilder appendWeekOfWeekyear(int);
    Code:
       0: aload_0
       1: invokestatic  #80                 // Method org/joda/time/DateTimeFieldType.weekOfWeekyear:()Lorg/joda/time/DateTimeFieldType;
       4: iload_1
       5: iconst_2
       6: invokevirtual #71                 // Method appendDecimal:(Lorg/joda/time/DateTimeFieldType;II)Lorg/joda/time/format/DateTimeFormatterBuilder;
       9: areturn

  public org.joda.time.format.DateTimeFormatterBuilder appendWeekyear(int, int);
    Code:
       0: aload_0
       1: invokestatic  #81                 // Method org/joda/time/DateTimeFieldType.weekyear:()Lorg/joda/time/DateTimeFieldType;
       4: iload_1
       5: iload_2
       6: invokevirtual #82                 // Method appendSignedDecimal:(Lorg/joda/time/DateTimeFieldType;II)Lorg/joda/time/format/DateTimeFormatterBuilder;
       9: areturn

  public org.joda.time.format.DateTimeFormatterBuilder appendMonthOfYear(int);
    Code:
       0: aload_0
       1: invokestatic  #83                 // Method org/joda/time/DateTimeFieldType.monthOfYear:()Lorg/joda/time/DateTimeFieldType;
       4: iload_1
       5: iconst_2
       6: invokevirtual #71                 // Method appendDecimal:(Lorg/joda/time/DateTimeFieldType;II)Lorg/joda/time/format/DateTimeFormatterBuilder;
       9: areturn

  public org.joda.time.format.DateTimeFormatterBuilder appendYear(int, int);
    Code:
       0: aload_0
       1: invokestatic  #84                 // Method org/joda/time/DateTimeFieldType.year:()Lorg/joda/time/DateTimeFieldType;
       4: iload_1
       5: iload_2
       6: invokevirtual #82                 // Method appendSignedDecimal:(Lorg/joda/time/DateTimeFieldType;II)Lorg/joda/time/format/DateTimeFormatterBuilder;
       9: areturn

  public org.joda.time.format.DateTimeFormatterBuilder appendTwoDigitYear(int);
    Code:
       0: aload_0
       1: iload_1
       2: iconst_0
       3: invokevirtual #85                 // Method appendTwoDigitYear:(IZ)Lorg/joda/time/format/DateTimeFormatterBuilder;
       6: areturn

  public org.joda.time.format.DateTimeFormatterBuilder appendTwoDigitYear(int, boolean);
    Code:
       0: aload_0
       1: new           #86                 // class org/joda/time/format/DateTimeFormatterBuilder$TwoDigitYear
       4: dup
       5: invokestatic  #84                 // Method org/joda/time/DateTimeFieldType.year:()Lorg/joda/time/DateTimeFieldType;
       8: iload_1
       9: iload_2
      10: invokespecial #87                 // Method org/joda/time/format/DateTimeFormatterBuilder$TwoDigitYear."<init>":(Lorg/joda/time/DateTimeFieldType;IZ)V
      13: invokespecial #41                 // Method append0:(Ljava/lang/Object;)Lorg/joda/time/format/DateTimeFormatterBuilder;
      16: areturn

  public org.joda.time.format.DateTimeFormatterBuilder appendTwoDigitWeekyear(int);
    Code:
       0: aload_0
       1: iload_1
       2: iconst_0
       3: invokevirtual #88                 // Method appendTwoDigitWeekyear:(IZ)Lorg/joda/time/format/DateTimeFormatterBuilder;
       6: areturn

  public org.joda.time.format.DateTimeFormatterBuilder appendTwoDigitWeekyear(int, boolean);
    Code:
       0: aload_0
       1: new           #86                 // class org/joda/time/format/DateTimeFormatterBuilder$TwoDigitYear
       4: dup
       5: invokestatic  #81                 // Method org/joda/time/DateTimeFieldType.weekyear:()Lorg/joda/time/DateTimeFieldType;
       8: iload_1
       9: iload_2
      10: invokespecial #87                 // Method org/joda/time/format/DateTimeFormatterBuilder$TwoDigitYear."<init>":(Lorg/joda/time/DateTimeFieldType;IZ)V
      13: invokespecial #41                 // Method append0:(Ljava/lang/Object;)Lorg/joda/time/format/DateTimeFormatterBuilder;
      16: areturn

  public org.joda.time.format.DateTimeFormatterBuilder appendYearOfEra(int, int);
    Code:
       0: aload_0
       1: invokestatic  #89                 // Method org/joda/time/DateTimeFieldType.yearOfEra:()Lorg/joda/time/DateTimeFieldType;
       4: iload_1
       5: iload_2
       6: invokevirtual #71                 // Method appendDecimal:(Lorg/joda/time/DateTimeFieldType;II)Lorg/joda/time/format/DateTimeFormatterBuilder;
       9: areturn

  public org.joda.time.format.DateTimeFormatterBuilder appendYearOfCentury(int, int);
    Code:
       0: aload_0
       1: invokestatic  #90                 // Method org/joda/time/DateTimeFieldType.yearOfCentury:()Lorg/joda/time/DateTimeFieldType;
       4: iload_1
       5: iload_2
       6: invokevirtual #71                 // Method appendDecimal:(Lorg/joda/time/DateTimeFieldType;II)Lorg/joda/time/format/DateTimeFormatterBuilder;
       9: areturn

  public org.joda.time.format.DateTimeFormatterBuilder appendCenturyOfEra(int, int);
    Code:
       0: aload_0
       1: invokestatic  #91                 // Method org/joda/time/DateTimeFieldType.centuryOfEra:()Lorg/joda/time/DateTimeFieldType;
       4: iload_1
       5: iload_2
       6: invokevirtual #82                 // Method appendSignedDecimal:(Lorg/joda/time/DateTimeFieldType;II)Lorg/joda/time/format/DateTimeFormatterBuilder;
       9: areturn

  public org.joda.time.format.DateTimeFormatterBuilder appendHalfdayOfDayText();
    Code:
       0: aload_0
       1: invokestatic  #92                 // Method org/joda/time/DateTimeFieldType.halfdayOfDay:()Lorg/joda/time/DateTimeFieldType;
       4: invokevirtual #93                 // Method appendText:(Lorg/joda/time/DateTimeFieldType;)Lorg/joda/time/format/DateTimeFormatterBuilder;
       7: areturn

  public org.joda.time.format.DateTimeFormatterBuilder appendDayOfWeekText();
    Code:
       0: aload_0
       1: invokestatic  #78                 // Method org/joda/time/DateTimeFieldType.dayOfWeek:()Lorg/joda/time/DateTimeFieldType;
       4: invokevirtual #93                 // Method appendText:(Lorg/joda/time/DateTimeFieldType;)Lorg/joda/time/format/DateTimeFormatterBuilder;
       7: areturn

  public org.joda.time.format.DateTimeFormatterBuilder appendDayOfWeekShortText();
    Code:
       0: aload_0
       1: invokestatic  #78                 // Method org/joda/time/DateTimeFieldType.dayOfWeek:()Lorg/joda/time/DateTimeFieldType;
       4: invokevirtual #94                 // Method appendShortText:(Lorg/joda/time/DateTimeFieldType;)Lorg/joda/time/format/DateTimeFormatterBuilder;
       7: areturn

  public org.joda.time.format.DateTimeFormatterBuilder appendMonthOfYearText();
    Code:
       0: aload_0
       1: invokestatic  #83                 // Method org/joda/time/DateTimeFieldType.monthOfYear:()Lorg/joda/time/DateTimeFieldType;
       4: invokevirtual #93                 // Method appendText:(Lorg/joda/time/DateTimeFieldType;)Lorg/joda/time/format/DateTimeFormatterBuilder;
       7: areturn

  public org.joda.time.format.DateTimeFormatterBuilder appendMonthOfYearShortText();
    Code:
       0: aload_0
       1: invokestatic  #83                 // Method org/joda/time/DateTimeFieldType.monthOfYear:()Lorg/joda/time/DateTimeFieldType;
       4: invokevirtual #94                 // Method appendShortText:(Lorg/joda/time/DateTimeFieldType;)Lorg/joda/time/format/DateTimeFormatterBuilder;
       7: areturn

  public org.joda.time.format.DateTimeFormatterBuilder appendEraText();
    Code:
       0: aload_0
       1: invokestatic  #95                 // Method org/joda/time/DateTimeFieldType.era:()Lorg/joda/time/DateTimeFieldType;
       4: invokevirtual #93                 // Method appendText:(Lorg/joda/time/DateTimeFieldType;)Lorg/joda/time/format/DateTimeFormatterBuilder;
       7: areturn

  public org.joda.time.format.DateTimeFormatterBuilder appendTimeZoneName();
    Code:
       0: aload_0
       1: new           #96                 // class org/joda/time/format/DateTimeFormatterBuilder$TimeZoneName
       4: dup
       5: iconst_0
       6: aconst_null
       7: invokespecial #97                 // Method org/joda/time/format/DateTimeFormatterBuilder$TimeZoneName."<init>":(ILjava/util/Map;)V
      10: aconst_null
      11: invokespecial #27                 // Method append0:(Lorg/joda/time/format/InternalPrinter;Lorg/joda/time/format/InternalParser;)Lorg/joda/time/format/DateTimeFormatterBuilder;
      14: areturn

  public org.joda.time.format.DateTimeFormatterBuilder appendTimeZoneName(java.util.Map<java.lang.String, org.joda.time.DateTimeZone>);
    Code:
       0: new           #96                 // class org/joda/time/format/DateTimeFormatterBuilder$TimeZoneName
       3: dup
       4: iconst_0
       5: aload_1
       6: invokespecial #97                 // Method org/joda/time/format/DateTimeFormatterBuilder$TimeZoneName."<init>":(ILjava/util/Map;)V
       9: astore_2
      10: aload_0
      11: aload_2
      12: aload_2
      13: invokespecial #27                 // Method append0:(Lorg/joda/time/format/InternalPrinter;Lorg/joda/time/format/InternalParser;)Lorg/joda/time/format/DateTimeFormatterBuilder;
      16: areturn

  public org.joda.time.format.DateTimeFormatterBuilder appendTimeZoneShortName();
    Code:
       0: aload_0
       1: new           #96                 // class org/joda/time/format/DateTimeFormatterBuilder$TimeZoneName
       4: dup
       5: iconst_1
       6: aconst_null
       7: invokespecial #97                 // Method org/joda/time/format/DateTimeFormatterBuilder$TimeZoneName."<init>":(ILjava/util/Map;)V
      10: aconst_null
      11: invokespecial #27                 // Method append0:(Lorg/joda/time/format/InternalPrinter;Lorg/joda/time/format/InternalParser;)Lorg/joda/time/format/DateTimeFormatterBuilder;
      14: areturn

  public org.joda.time.format.DateTimeFormatterBuilder appendTimeZoneShortName(java.util.Map<java.lang.String, org.joda.time.DateTimeZone>);
    Code:
       0: new           #96                 // class org/joda/time/format/DateTimeFormatterBuilder$TimeZoneName
       3: dup
       4: iconst_1
       5: aload_1
       6: invokespecial #97                 // Method org/joda/time/format/DateTimeFormatterBuilder$TimeZoneName."<init>":(ILjava/util/Map;)V
       9: astore_2
      10: aload_0
      11: aload_2
      12: aload_2
      13: invokespecial #27                 // Method append0:(Lorg/joda/time/format/InternalPrinter;Lorg/joda/time/format/InternalParser;)Lorg/joda/time/format/DateTimeFormatterBuilder;
      16: areturn

  public org.joda.time.format.DateTimeFormatterBuilder appendTimeZoneId();
    Code:
       0: aload_0
       1: getstatic     #98                 // Field org/joda/time/format/DateTimeFormatterBuilder$TimeZoneId.INSTANCE:Lorg/joda/time/format/DateTimeFormatterBuilder$TimeZoneId;
       4: getstatic     #98                 // Field org/joda/time/format/DateTimeFormatterBuilder$TimeZoneId.INSTANCE:Lorg/joda/time/format/DateTimeFormatterBuilder$TimeZoneId;
       7: invokespecial #27                 // Method append0:(Lorg/joda/time/format/InternalPrinter;Lorg/joda/time/format/InternalParser;)Lorg/joda/time/format/DateTimeFormatterBuilder;
      10: areturn

  public org.joda.time.format.DateTimeFormatterBuilder appendTimeZoneOffset(java.lang.String, boolean, int, int);
    Code:
       0: aload_0
       1: new           #99                 // class org/joda/time/format/DateTimeFormatterBuilder$TimeZoneOffset
       4: dup
       5: aload_1
       6: aload_1
       7: iload_2
       8: iload_3
       9: iload         4
      11: invokespecial #100                // Method org/joda/time/format/DateTimeFormatterBuilder$TimeZoneOffset."<init>":(Ljava/lang/String;Ljava/lang/String;ZII)V
      14: invokespecial #41                 // Method append0:(Ljava/lang/Object;)Lorg/joda/time/format/DateTimeFormatterBuilder;
      17: areturn

  public org.joda.time.format.DateTimeFormatterBuilder appendTimeZoneOffset(java.lang.String, java.lang.String, boolean, int, int);
    Code:
       0: aload_0
       1: new           #99                 // class org/joda/time/format/DateTimeFormatterBuilder$TimeZoneOffset
       4: dup
       5: aload_1
       6: aload_2
       7: iload_3
       8: iload         4
      10: iload         5
      12: invokespecial #100                // Method org/joda/time/format/DateTimeFormatterBuilder$TimeZoneOffset."<init>":(Ljava/lang/String;Ljava/lang/String;ZII)V
      15: invokespecial #41                 // Method append0:(Ljava/lang/Object;)Lorg/joda/time/format/DateTimeFormatterBuilder;
      18: areturn

  public org.joda.time.format.DateTimeFormatterBuilder appendPattern(java.lang.String);
    Code:
       0: aload_0
       1: aload_1
       2: invokestatic  #101                // Method org/joda/time/format/DateTimeFormat.appendPatternTo:(Lorg/joda/time/format/DateTimeFormatterBuilder;Ljava/lang/String;)V
       5: aload_0
       6: areturn

  private java.lang.Object getFormatter();
    Code:
       0: aload_0
       1: getfield      #20                 // Field iFormatter:Ljava/lang/Object;
       4: astore_1
       5: aload_1
       6: ifnonnull     79
       9: aload_0
      10: getfield      #4                  // Field iElementPairs:Ljava/util/ArrayList;
      13: invokevirtual #102                // Method java/util/ArrayList.size:()I
      16: iconst_2
      17: if_icmpne     58
      20: aload_0
      21: getfield      #4                  // Field iElementPairs:Ljava/util/ArrayList;
      24: iconst_0
      25: invokevirtual #103                // Method java/util/ArrayList.get:(I)Ljava/lang/Object;
      28: astore_2
      29: aload_0
      30: getfield      #4                  // Field iElementPairs:Ljava/util/ArrayList;
      33: iconst_1
      34: invokevirtual #103                // Method java/util/ArrayList.get:(I)Ljava/lang/Object;
      37: astore_3
      38: aload_2
      39: ifnull        56
      42: aload_2
      43: aload_3
      44: if_acmpeq     51
      47: aload_3
      48: ifnonnull     58
      51: aload_2
      52: astore_1
      53: goto          58
      56: aload_3
      57: astore_1
      58: aload_1
      59: ifnonnull     74
      62: new           #104                // class org/joda/time/format/DateTimeFormatterBuilder$Composite
      65: dup
      66: aload_0
      67: getfield      #4                  // Field iElementPairs:Ljava/util/ArrayList;
      70: invokespecial #105                // Method org/joda/time/format/DateTimeFormatterBuilder$Composite."<init>":(Ljava/util/List;)V
      73: astore_1
      74: aload_0
      75: aload_1
      76: putfield      #20                 // Field iFormatter:Ljava/lang/Object;
      79: aload_1
      80: areturn

  private boolean isPrinter(java.lang.Object);
    Code:
       0: aload_1
       1: instanceof    #7                  // class org/joda/time/format/InternalPrinter
       4: ifeq          24
       7: aload_1
       8: instanceof    #104                // class org/joda/time/format/DateTimeFormatterBuilder$Composite
      11: ifeq          22
      14: aload_1
      15: checkcast     #104                // class org/joda/time/format/DateTimeFormatterBuilder$Composite
      18: invokevirtual #106                // Method org/joda/time/format/DateTimeFormatterBuilder$Composite.isPrinter:()Z
      21: ireturn
      22: iconst_1
      23: ireturn
      24: iconst_0
      25: ireturn

  private boolean isParser(java.lang.Object);
    Code:
       0: aload_1
       1: instanceof    #9                  // class org/joda/time/format/InternalParser
       4: ifeq          24
       7: aload_1
       8: instanceof    #104                // class org/joda/time/format/DateTimeFormatterBuilder$Composite
      11: ifeq          22
      14: aload_1
      15: checkcast     #104                // class org/joda/time/format/DateTimeFormatterBuilder$Composite
      18: invokevirtual #107                // Method org/joda/time/format/DateTimeFormatterBuilder$Composite.isParser:()Z
      21: ireturn
      22: iconst_1
      23: ireturn
      24: iconst_0
      25: ireturn

  private boolean isFormatter(java.lang.Object);
    Code:
       0: aload_0
       1: aload_1
       2: invokespecial #6                  // Method isPrinter:(Ljava/lang/Object;)Z
       5: ifne          16
       8: aload_0
       9: aload_1
      10: invokespecial #8                  // Method isParser:(Ljava/lang/Object;)Z
      13: ifeq          20
      16: iconst_1
      17: goto          21
      20: iconst_0
      21: ireturn

  static void appendUnknownString(java.lang.Appendable, int) throws java.io.IOException;
    Code:
       0: iload_1
       1: istore_2
       2: iinc          2, -1
       5: iload_2
       6: iflt          21
       9: aload_0
      10: ldc           #108                // int 65533
      12: invokeinterface #109,  2          // InterfaceMethod java/lang/Appendable.append:(C)Ljava/lang/Appendable;
      17: pop
      18: goto          2
      21: return

  static boolean csStartsWith(java.lang.CharSequence, int, java.lang.String);
    Code:
       0: aload_2
       1: invokevirtual #43                 // Method java/lang/String.length:()I
       4: istore_3
       5: aload_0
       6: invokeinterface #110,  1          // InterfaceMethod java/lang/CharSequence.length:()I
      11: iload_1
      12: isub
      13: iload_3
      14: if_icmpge     19
      17: iconst_0
      18: ireturn
      19: iconst_0
      20: istore        4
      22: iload         4
      24: iload_3
      25: if_icmpge     55
      28: aload_0
      29: iload_1
      30: iload         4
      32: iadd
      33: invokeinterface #111,  2          // InterfaceMethod java/lang/CharSequence.charAt:(I)C
      38: aload_2
      39: iload         4
      41: invokevirtual #44                 // Method java/lang/String.charAt:(I)C
      44: if_icmpeq     49
      47: iconst_0
      48: ireturn
      49: iinc          4, 1
      52: goto          22
      55: iconst_1
      56: ireturn

  static boolean csStartsWithIgnoreCase(java.lang.CharSequence, int, java.lang.String);
    Code:
       0: aload_2
       1: invokevirtual #43                 // Method java/lang/String.length:()I
       4: istore_3
       5: aload_0
       6: invokeinterface #110,  1          // InterfaceMethod java/lang/CharSequence.length:()I
      11: iload_1
      12: isub
      13: iload_3
      14: if_icmpge     19
      17: iconst_0
      18: ireturn
      19: iconst_0
      20: istore        4
      22: iload         4
      24: iload_3
      25: if_icmpge     97
      28: aload_0
      29: iload_1
      30: iload         4
      32: iadd
      33: invokeinterface #111,  2          // InterfaceMethod java/lang/CharSequence.charAt:(I)C
      38: istore        5
      40: aload_2
      41: iload         4
      43: invokevirtual #44                 // Method java/lang/String.charAt:(I)C
      46: istore        6
      48: iload         5
      50: iload         6
      52: if_icmpeq     91
      55: iload         5
      57: invokestatic  #112                // Method java/lang/Character.toUpperCase:(C)C
      60: istore        7
      62: iload         6
      64: invokestatic  #112                // Method java/lang/Character.toUpperCase:(C)C
      67: istore        8
      69: iload         7
      71: iload         8
      73: if_icmpeq     91
      76: iload         7
      78: invokestatic  #113                // Method java/lang/Character.toLowerCase:(C)C
      81: iload         8
      83: invokestatic  #113                // Method java/lang/Character.toLowerCase:(C)C
      86: if_icmpeq     91
      89: iconst_0
      90: ireturn
      91: iinc          4, 1
      94: goto          22
      97: iconst_1
      98: ireturn
}
