Compiled from "Main.java"
final class org.jboss.as.process.Main$2 implements java.lang.Runnable {
  final org.jboss.as.process.ProcessController val$processController;

  org.jboss.as.process.Main$2(org.jboss.as.process.ProcessController);
    Code:
       0: aload_0
       1: aload_1
       2: putfield      #1                  // Field val$processController:Lorg/jboss/as/process/ProcessController;
       5: aload_0
       6: invokespecial #2                  // Method java/lang/Object."<init>":()V
       9: return

  public void run();
    Code:
       0: aload_0
       1: getfield      #1                  // Field val$processController:Lorg/jboss/as/process/ProcessController;
       4: invokevirtual #3                  // Method org/jboss/as/process/ProcessController.shutdown:()V
       7: return
}
