Compiled from "OptionValidator.java"
final class org.apache.commons.cli.OptionValidator {
  org.apache.commons.cli.OptionValidator();
    Code:
       0: aload_0
       1: invokespecial #1                  // Method java/lang/Object."<init>":()V
       4: return

  static void validateOption(java.lang.String) throws java.lang.IllegalArgumentException;
    Code:
       0: aload_0
       1: ifnonnull     5
       4: return
       5: aload_0
       6: invokevirtual #2                  // Method java/lang/String.length:()I
       9: iconst_1
      10: if_icmpne     61
      13: aload_0
      14: iconst_0
      15: invokevirtual #3                  // Method java/lang/String.charAt:(I)C
      18: istore_1
      19: iload_1
      20: invokestatic  #4                  // Method isValidOpt:(C)Z
      23: ifne          58
      26: new           #5                  // class java/lang/IllegalArgumentException
      29: dup
      30: new           #6                  // class java/lang/StringBuilder
      33: dup
      34: invokespecial #7                  // Method java/lang/StringBuilder."<init>":()V
      37: ldc           #8                  // String Illegal option name \'
      39: invokevirtual #9                  // Method java/lang/StringBuilder.append:(Ljava/lang/String;)Ljava/lang/StringBuilder;
      42: iload_1
      43: invokevirtual #10                 // Method java/lang/StringBuilder.append:(C)Ljava/lang/StringBuilder;
      46: ldc           #11                 // String \'
      48: invokevirtual #9                  // Method java/lang/StringBuilder.append:(Ljava/lang/String;)Ljava/lang/StringBuilder;
      51: invokevirtual #12                 // Method java/lang/StringBuilder.toString:()Ljava/lang/String;
      54: invokespecial #13                 // Method java/lang/IllegalArgumentException."<init>":(Ljava/lang/String;)V
      57: athrow
      58: goto          137
      61: aload_0
      62: invokevirtual #14                 // Method java/lang/String.toCharArray:()[C
      65: astore_1
      66: aload_1
      67: arraylength
      68: istore_2
      69: iconst_0
      70: istore_3
      71: iload_3
      72: iload_2
      73: if_icmpge     137
      76: aload_1
      77: iload_3
      78: caload
      79: istore        4
      81: iload         4
      83: invokestatic  #15                 // Method isValidChar:(C)Z
      86: ifne          131
      89: new           #5                  // class java/lang/IllegalArgumentException
      92: dup
      93: new           #6                  // class java/lang/StringBuilder
      96: dup
      97: invokespecial #7                  // Method java/lang/StringBuilder."<init>":()V
     100: ldc           #16                 // String The option \'
     102: invokevirtual #9                  // Method java/lang/StringBuilder.append:(Ljava/lang/String;)Ljava/lang/StringBuilder;
     105: aload_0
     106: invokevirtual #9                  // Method java/lang/StringBuilder.append:(Ljava/lang/String;)Ljava/lang/StringBuilder;
     109: ldc           #17                 // String \' contains an illegal character : \'
     111: invokevirtual #9                  // Method java/lang/StringBuilder.append:(Ljava/lang/String;)Ljava/lang/StringBuilder;
     114: iload         4
     116: invokevirtual #10                 // Method java/lang/StringBuilder.append:(C)Ljava/lang/StringBuilder;
     119: ldc           #11                 // String \'
     121: invokevirtual #9                  // Method java/lang/StringBuilder.append:(Ljava/lang/String;)Ljava/lang/StringBuilder;
     124: invokevirtual #12                 // Method java/lang/StringBuilder.toString:()Ljava/lang/String;
     127: invokespecial #13                 // Method java/lang/IllegalArgumentException."<init>":(Ljava/lang/String;)V
     130: athrow
     131: iinc          3, 1
     134: goto          71
     137: return

  private static boolean isValidOpt(char);
    Code:
       0: iload_0
       1: invokestatic  #15                 // Method isValidChar:(C)Z
       4: ifne          19
       7: iload_0
       8: bipush        63
      10: if_icmpeq     19
      13: iload_0
      14: bipush        64
      16: if_icmpne     23
      19: iconst_1
      20: goto          24
      23: iconst_0
      24: ireturn

  private static boolean isValidChar(char);
    Code:
       0: iload_0
       1: invokestatic  #18                 // Method java/lang/Character.isJavaIdentifierPart:(C)Z
       4: ireturn
}
