Compiled from "SPARQLParserRegistry.java"
public class org.apache.jena.sparql.lang.SPARQLParserRegistry {
  java.util.Map<org.apache.jena.query.Syntax, org.apache.jena.sparql.lang.SPARQLParserFactory> factories;

  static org.apache.jena.sparql.lang.SPARQLParserRegistry registry;

  public static synchronized org.apache.jena.sparql.lang.SPARQLParserRegistry get();
    Code:
       0: getstatic     #1                  // Field registry:Lorg/apache/jena/sparql/lang/SPARQLParserRegistry;
       3: ifnonnull     9
       6: invokestatic  #2                  // Method init:()V
       9: getstatic     #1                  // Field registry:Lorg/apache/jena/sparql/lang/SPARQLParserRegistry;
      12: areturn

  private org.apache.jena.sparql.lang.SPARQLParserRegistry();
    Code:
       0: aload_0
       1: invokespecial #3                  // Method java/lang/Object."<init>":()V
       4: aload_0
       5: new           #4                  // class java/util/HashMap
       8: dup
       9: invokespecial #5                  // Method java/util/HashMap."<init>":()V
      12: putfield      #6                  // Field factories:Ljava/util/Map;
      15: return

  private static synchronized void init();
    Code:
       0: new           #7                  // class org/apache/jena/sparql/lang/SPARQLParserRegistry
       3: dup
       4: invokespecial #8                  // Method "<init>":()V
       7: astore_0
       8: aload_0
       9: getstatic     #9                  // Field org/apache/jena/query/Syntax.syntaxSPARQL_10:Lorg/apache/jena/query/Syntax;
      12: new           #10                 // class org/apache/jena/sparql/lang/SPARQLParserRegistry$1
      15: dup
      16: invokespecial #11                 // Method org/apache/jena/sparql/lang/SPARQLParserRegistry$1."<init>":()V
      19: invokevirtual #12                 // Method add:(Lorg/apache/jena/query/Syntax;Lorg/apache/jena/sparql/lang/SPARQLParserFactory;)V
      22: aload_0
      23: getstatic     #13                 // Field org/apache/jena/query/Syntax.syntaxSPARQL_11:Lorg/apache/jena/query/Syntax;
      26: new           #14                 // class org/apache/jena/sparql/lang/SPARQLParserRegistry$2
      29: dup
      30: invokespecial #15                 // Method org/apache/jena/sparql/lang/SPARQLParserRegistry$2."<init>":()V
      33: invokevirtual #12                 // Method add:(Lorg/apache/jena/query/Syntax;Lorg/apache/jena/sparql/lang/SPARQLParserFactory;)V
      36: aload_0
      37: getstatic     #16                 // Field org/apache/jena/query/Syntax.syntaxARQ:Lorg/apache/jena/query/Syntax;
      40: new           #17                 // class org/apache/jena/sparql/lang/SPARQLParserRegistry$3
      43: dup
      44: invokespecial #18                 // Method org/apache/jena/sparql/lang/SPARQLParserRegistry$3."<init>":()V
      47: invokevirtual #12                 // Method add:(Lorg/apache/jena/query/Syntax;Lorg/apache/jena/sparql/lang/SPARQLParserFactory;)V
      50: aload_0
      51: putstatic     #1                  // Field registry:Lorg/apache/jena/sparql/lang/SPARQLParserRegistry;
      54: return

  public static org.apache.jena.sparql.lang.SPARQLParserFactory findFactory(org.apache.jena.query.Syntax);
    Code:
       0: invokestatic  #19                 // Method get:()Lorg/apache/jena/sparql/lang/SPARQLParserRegistry;
       3: aload_0
       4: invokevirtual #20                 // Method getFactory:(Lorg/apache/jena/query/Syntax;)Lorg/apache/jena/sparql/lang/SPARQLParserFactory;
       7: areturn

  public static org.apache.jena.sparql.lang.SPARQLParser parser(org.apache.jena.query.Syntax);
    Code:
       0: invokestatic  #19                 // Method get:()Lorg/apache/jena/sparql/lang/SPARQLParserRegistry;
       3: aload_0
       4: invokevirtual #21                 // Method createParser:(Lorg/apache/jena/query/Syntax;)Lorg/apache/jena/sparql/lang/SPARQLParser;
       7: areturn

  public org.apache.jena.sparql.lang.SPARQLParserFactory getFactory(org.apache.jena.query.Syntax);
    Code:
       0: aload_0
       1: getfield      #6                  // Field factories:Ljava/util/Map;
       4: aload_1
       5: invokeinterface #22,  2           // InterfaceMethod java/util/Map.get:(Ljava/lang/Object;)Ljava/lang/Object;
      10: checkcast     #23                 // class org/apache/jena/sparql/lang/SPARQLParserFactory
      13: areturn

  public org.apache.jena.sparql.lang.SPARQLParser createParser(org.apache.jena.query.Syntax);
    Code:
       0: aload_0
       1: aload_1
       2: invokevirtual #20                 // Method getFactory:(Lorg/apache/jena/query/Syntax;)Lorg/apache/jena/sparql/lang/SPARQLParserFactory;
       5: astore_2
       6: aload_2
       7: ifnull        20
      10: aload_2
      11: aload_1
      12: invokeinterface #24,  2           // InterfaceMethod org/apache/jena/sparql/lang/SPARQLParserFactory.create:(Lorg/apache/jena/query/Syntax;)Lorg/apache/jena/sparql/lang/SPARQLParser;
      17: goto          21
      20: aconst_null
      21: areturn

  public static void addFactory(org.apache.jena.query.Syntax, org.apache.jena.sparql.lang.SPARQLParserFactory);
    Code:
       0: invokestatic  #19                 // Method get:()Lorg/apache/jena/sparql/lang/SPARQLParserRegistry;
       3: aload_0
       4: aload_1
       5: invokevirtual #12                 // Method add:(Lorg/apache/jena/query/Syntax;Lorg/apache/jena/sparql/lang/SPARQLParserFactory;)V
       8: return

  public void add(org.apache.jena.query.Syntax, org.apache.jena.sparql.lang.SPARQLParserFactory);
    Code:
       0: aload_2
       1: aload_1
       2: invokeinterface #25,  2           // InterfaceMethod org/apache/jena/sparql/lang/SPARQLParserFactory.accept:(Lorg/apache/jena/query/Syntax;)Z
       7: ifne          20
      10: new           #26                 // class java/lang/IllegalArgumentException
      13: dup
      14: ldc           #27                 // String The given parser factory does not accept the specified syntax.
      16: invokespecial #28                 // Method java/lang/IllegalArgumentException."<init>":(Ljava/lang/String;)V
      19: athrow
      20: aload_0
      21: getfield      #6                  // Field factories:Ljava/util/Map;
      24: aload_1
      25: aload_2
      26: invokeinterface #29,  3           // InterfaceMethod java/util/Map.put:(Ljava/lang/Object;Ljava/lang/Object;)Ljava/lang/Object;
      31: pop
      32: return

  public static void removeFactory(org.apache.jena.query.Syntax);
    Code:
       0: invokestatic  #19                 // Method get:()Lorg/apache/jena/sparql/lang/SPARQLParserRegistry;
       3: aload_0
       4: invokevirtual #30                 // Method remove:(Lorg/apache/jena/query/Syntax;)V
       7: return

  public void remove(org.apache.jena.query.Syntax);
    Code:
       0: aload_0
       1: getfield      #6                  // Field factories:Ljava/util/Map;
       4: aload_1
       5: invokeinterface #31,  2           // InterfaceMethod java/util/Map.remove:(Ljava/lang/Object;)Ljava/lang/Object;
      10: pop
      11: return

  public static boolean containsParserFactory(org.apache.jena.query.Syntax);
    Code:
       0: invokestatic  #19                 // Method get:()Lorg/apache/jena/sparql/lang/SPARQLParserRegistry;
       3: aload_0
       4: invokevirtual #32                 // Method containsFactory:(Lorg/apache/jena/query/Syntax;)Z
       7: ireturn

  public boolean containsFactory(org.apache.jena.query.Syntax);
    Code:
       0: aload_0
       1: getfield      #6                  // Field factories:Ljava/util/Map;
       4: aload_1
       5: invokeinterface #33,  2           // InterfaceMethod java/util/Map.containsKey:(Ljava/lang/Object;)Z
      10: ireturn

  static {};
    Code:
       0: aconst_null
       1: putstatic     #1                  // Field registry:Lorg/apache/jena/sparql/lang/SPARQLParserRegistry;
       4: return
}
