Compiled from "DataMap.java"
final class com.google.api.client.util.DataMap extends java.util.AbstractMap<java.lang.String, java.lang.Object> {
  final java.lang.Object object;

  final com.google.api.client.util.ClassInfo classInfo;

  com.google.api.client.util.DataMap(java.lang.Object, boolean);
    Code:
       0: aload_0
       1: invokespecial #24                 // Method java/util/AbstractMap."<init>":()V
       4: aload_0
       5: aload_1
       6: putfield      #26                 // Field object:Ljava/lang/Object;
       9: aload_0
      10: aload_1
      11: invokevirtual #32                 // Method java/lang/Object.getClass:()Ljava/lang/Class;
      14: iload_2
      15: invokestatic  #38                 // Method com/google/api/client/util/ClassInfo.of:(Ljava/lang/Class;Z)Lcom/google/api/client/util/ClassInfo;
      18: putfield      #40                 // Field classInfo:Lcom/google/api/client/util/ClassInfo;
      21: aload_0
      22: getfield      #40                 // Field classInfo:Lcom/google/api/client/util/ClassInfo;
      25: invokevirtual #44                 // Method com/google/api/client/util/ClassInfo.isEnum:()Z
      28: ifne          35
      31: iconst_1
      32: goto          36
      35: iconst_0
      36: invokestatic  #50                 // Method com/google/api/client/util/Preconditions.checkArgument:(Z)V
      39: return

  public com.google.api.client.util.DataMap$EntrySet entrySet();
    Code:
       0: new           #14                 // class com/google/api/client/util/DataMap$EntrySet
       3: dup
       4: aload_0
       5: invokespecial #59                 // Method com/google/api/client/util/DataMap$EntrySet."<init>":(Lcom/google/api/client/util/DataMap;)V
       8: areturn

  public boolean containsKey(java.lang.Object);
    Code:
       0: aload_0
       1: aload_1
       2: invokevirtual #65                 // Method get:(Ljava/lang/Object;)Ljava/lang/Object;
       5: ifnull        12
       8: iconst_1
       9: goto          13
      12: iconst_0
      13: ireturn

  public java.lang.Object get(java.lang.Object);
    Code:
       0: aload_1
       1: instanceof    #68                 // class java/lang/String
       4: ifne          9
       7: aconst_null
       8: areturn
       9: aload_0
      10: getfield      #40                 // Field classInfo:Lcom/google/api/client/util/ClassInfo;
      13: aload_1
      14: checkcast     #68                 // class java/lang/String
      17: invokevirtual #72                 // Method com/google/api/client/util/ClassInfo.getFieldInfo:(Ljava/lang/String;)Lcom/google/api/client/util/FieldInfo;
      20: astore_2
      21: aload_2
      22: ifnonnull     27
      25: aconst_null
      26: areturn
      27: aload_2
      28: aload_0
      29: getfield      #26                 // Field object:Ljava/lang/Object;
      32: invokevirtual #77                 // Method com/google/api/client/util/FieldInfo.getValue:(Ljava/lang/Object;)Ljava/lang/Object;
      35: areturn

  public java.lang.Object put(java.lang.String, java.lang.Object);
    Code:
       0: aload_0
       1: getfield      #40                 // Field classInfo:Lcom/google/api/client/util/ClassInfo;
       4: aload_1
       5: invokevirtual #72                 // Method com/google/api/client/util/ClassInfo.getFieldInfo:(Ljava/lang/String;)Lcom/google/api/client/util/FieldInfo;
       8: astore_3
       9: aload_3
      10: ldc           #83                 // String no field of key
      12: aload_1
      13: invokestatic  #87                 // Method java/lang/String.valueOf:(Ljava/lang/Object;)Ljava/lang/String;
      16: dup
      17: invokevirtual #91                 // Method java/lang/String.length:()I
      20: ifeq          29
      23: invokevirtual #95                 // Method java/lang/String.concat:(Ljava/lang/String;)Ljava/lang/String;
      26: goto          38
      29: pop
      30: new           #68                 // class java/lang/String
      33: dup_x1
      34: swap
      35: invokespecial #98                 // Method java/lang/String."<init>":(Ljava/lang/String;)V
      38: invokestatic  #102                // Method com/google/api/client/util/Preconditions.checkNotNull:(Ljava/lang/Object;Ljava/lang/Object;)Ljava/lang/Object;
      41: pop
      42: aload_3
      43: aload_0
      44: getfield      #26                 // Field object:Ljava/lang/Object;
      47: invokevirtual #77                 // Method com/google/api/client/util/FieldInfo.getValue:(Ljava/lang/Object;)Ljava/lang/Object;
      50: astore        4
      52: aload_3
      53: aload_0
      54: getfield      #26                 // Field object:Ljava/lang/Object;
      57: aload_2
      58: invokestatic  #104                // Method com/google/api/client/util/Preconditions.checkNotNull:(Ljava/lang/Object;)Ljava/lang/Object;
      61: invokevirtual #108                // Method com/google/api/client/util/FieldInfo.setValue:(Ljava/lang/Object;Ljava/lang/Object;)V
      64: aload         4
      66: areturn

  public java.util.Set entrySet();
    Code:
       0: aload_0
       1: invokevirtual #114                // Method entrySet:()Lcom/google/api/client/util/DataMap$EntrySet;
       4: areturn

  public java.lang.Object put(java.lang.Object, java.lang.Object);
    Code:
       0: aload_0
       1: aload_1
       2: checkcast     #68                 // class java/lang/String
       5: aload_2
       6: invokevirtual #116                // Method put:(Ljava/lang/String;Ljava/lang/Object;)Ljava/lang/Object;
       9: areturn
}
