Compiled from "ContentListDescribeResponseResource.java"
public class org.sonatype.nexus.rest.model.ContentListDescribeResponseResource implements java.io.Serializable {
  private java.lang.String responseType;

  private java.lang.String responseActualClass;

  private java.lang.String responsePath;

  private java.lang.String responseUid;

  private java.lang.String originatingRepositoryId;

  private java.lang.String originatingRepositoryName;

  private java.lang.String originatingRepositoryMainFacet;

  private java.util.List<java.lang.String> processedRepositoriesList;

  private java.util.List<java.lang.String> appliedMappings;

  private java.util.List<java.lang.String> properties;

  private java.util.List<java.lang.String> attributes;

  private java.util.List<java.lang.String> sources;

  private java.util.List<org.sonatype.nexus.rest.model.NotFoundReasoning> notFoundReasoning;

  public org.sonatype.nexus.rest.model.ContentListDescribeResponseResource();
    Code:
       0: aload_0
       1: invokespecial #1                  // Method java/lang/Object."<init>":()V
       4: return

  public void addAppliedMapping(java.lang.String);
    Code:
       0: aload_0
       1: invokevirtual #2                  // Method getAppliedMappings:()Ljava/util/List;
       4: aload_1
       5: invokeinterface #3,  2            // InterfaceMethod java/util/List.add:(Ljava/lang/Object;)Z
      10: pop
      11: return

  public void addAttribute(java.lang.String);
    Code:
       0: aload_0
       1: invokevirtual #4                  // Method getAttributes:()Ljava/util/List;
       4: aload_1
       5: invokeinterface #3,  2            // InterfaceMethod java/util/List.add:(Ljava/lang/Object;)Z
      10: pop
      11: return

  public void addNotFoundReasoning(org.sonatype.nexus.rest.model.NotFoundReasoning);
    Code:
       0: aload_0
       1: invokevirtual #5                  // Method getNotFoundReasoning:()Ljava/util/List;
       4: aload_1
       5: invokeinterface #3,  2            // InterfaceMethod java/util/List.add:(Ljava/lang/Object;)Z
      10: pop
      11: return

  public void addProcessedRepositoriesList(java.lang.String);
    Code:
       0: aload_0
       1: invokevirtual #6                  // Method getProcessedRepositoriesList:()Ljava/util/List;
       4: aload_1
       5: invokeinterface #3,  2            // InterfaceMethod java/util/List.add:(Ljava/lang/Object;)Z
      10: pop
      11: return

  public void addProperty(java.lang.String);
    Code:
       0: aload_0
       1: invokevirtual #7                  // Method getProperties:()Ljava/util/List;
       4: aload_1
       5: invokeinterface #3,  2            // InterfaceMethod java/util/List.add:(Ljava/lang/Object;)Z
      10: pop
      11: return

  public void addSource(java.lang.String);
    Code:
       0: aload_0
       1: invokevirtual #8                  // Method getSources:()Ljava/util/List;
       4: aload_1
       5: invokeinterface #3,  2            // InterfaceMethod java/util/List.add:(Ljava/lang/Object;)Z
      10: pop
      11: return

  public java.util.List<java.lang.String> getAppliedMappings();
    Code:
       0: aload_0
       1: getfield      #9                  // Field appliedMappings:Ljava/util/List;
       4: ifnonnull     18
       7: aload_0
       8: new           #10                 // class java/util/ArrayList
      11: dup
      12: invokespecial #11                 // Method java/util/ArrayList."<init>":()V
      15: putfield      #9                  // Field appliedMappings:Ljava/util/List;
      18: aload_0
      19: getfield      #9                  // Field appliedMappings:Ljava/util/List;
      22: areturn

  public java.util.List<java.lang.String> getAttributes();
    Code:
       0: aload_0
       1: getfield      #12                 // Field attributes:Ljava/util/List;
       4: ifnonnull     18
       7: aload_0
       8: new           #10                 // class java/util/ArrayList
      11: dup
      12: invokespecial #11                 // Method java/util/ArrayList."<init>":()V
      15: putfield      #12                 // Field attributes:Ljava/util/List;
      18: aload_0
      19: getfield      #12                 // Field attributes:Ljava/util/List;
      22: areturn

  public java.util.List<org.sonatype.nexus.rest.model.NotFoundReasoning> getNotFoundReasoning();
    Code:
       0: aload_0
       1: getfield      #13                 // Field notFoundReasoning:Ljava/util/List;
       4: ifnonnull     18
       7: aload_0
       8: new           #10                 // class java/util/ArrayList
      11: dup
      12: invokespecial #11                 // Method java/util/ArrayList."<init>":()V
      15: putfield      #13                 // Field notFoundReasoning:Ljava/util/List;
      18: aload_0
      19: getfield      #13                 // Field notFoundReasoning:Ljava/util/List;
      22: areturn

  public java.lang.String getOriginatingRepositoryId();
    Code:
       0: aload_0
       1: getfield      #14                 // Field originatingRepositoryId:Ljava/lang/String;
       4: areturn

  public java.lang.String getOriginatingRepositoryMainFacet();
    Code:
       0: aload_0
       1: getfield      #15                 // Field originatingRepositoryMainFacet:Ljava/lang/String;
       4: areturn

  public java.lang.String getOriginatingRepositoryName();
    Code:
       0: aload_0
       1: getfield      #16                 // Field originatingRepositoryName:Ljava/lang/String;
       4: areturn

  public java.util.List<java.lang.String> getProcessedRepositoriesList();
    Code:
       0: aload_0
       1: getfield      #17                 // Field processedRepositoriesList:Ljava/util/List;
       4: ifnonnull     18
       7: aload_0
       8: new           #10                 // class java/util/ArrayList
      11: dup
      12: invokespecial #11                 // Method java/util/ArrayList."<init>":()V
      15: putfield      #17                 // Field processedRepositoriesList:Ljava/util/List;
      18: aload_0
      19: getfield      #17                 // Field processedRepositoriesList:Ljava/util/List;
      22: areturn

  public java.util.List<java.lang.String> getProperties();
    Code:
       0: aload_0
       1: getfield      #18                 // Field properties:Ljava/util/List;
       4: ifnonnull     18
       7: aload_0
       8: new           #10                 // class java/util/ArrayList
      11: dup
      12: invokespecial #11                 // Method java/util/ArrayList."<init>":()V
      15: putfield      #18                 // Field properties:Ljava/util/List;
      18: aload_0
      19: getfield      #18                 // Field properties:Ljava/util/List;
      22: areturn

  public java.lang.String getResponseActualClass();
    Code:
       0: aload_0
       1: getfield      #19                 // Field responseActualClass:Ljava/lang/String;
       4: areturn

  public java.lang.String getResponsePath();
    Code:
       0: aload_0
       1: getfield      #20                 // Field responsePath:Ljava/lang/String;
       4: areturn

  public java.lang.String getResponseType();
    Code:
       0: aload_0
       1: getfield      #21                 // Field responseType:Ljava/lang/String;
       4: areturn

  public java.lang.String getResponseUid();
    Code:
       0: aload_0
       1: getfield      #22                 // Field responseUid:Ljava/lang/String;
       4: areturn

  public java.util.List<java.lang.String> getSources();
    Code:
       0: aload_0
       1: getfield      #23                 // Field sources:Ljava/util/List;
       4: ifnonnull     18
       7: aload_0
       8: new           #10                 // class java/util/ArrayList
      11: dup
      12: invokespecial #11                 // Method java/util/ArrayList."<init>":()V
      15: putfield      #23                 // Field sources:Ljava/util/List;
      18: aload_0
      19: getfield      #23                 // Field sources:Ljava/util/List;
      22: areturn

  public void removeAppliedMapping(java.lang.String);
    Code:
       0: aload_0
       1: invokevirtual #2                  // Method getAppliedMappings:()Ljava/util/List;
       4: aload_1
       5: invokeinterface #24,  2           // InterfaceMethod java/util/List.remove:(Ljava/lang/Object;)Z
      10: pop
      11: return

  public void removeAttribute(java.lang.String);
    Code:
       0: aload_0
       1: invokevirtual #4                  // Method getAttributes:()Ljava/util/List;
       4: aload_1
       5: invokeinterface #24,  2           // InterfaceMethod java/util/List.remove:(Ljava/lang/Object;)Z
      10: pop
      11: return

  public void removeNotFoundReasoning(org.sonatype.nexus.rest.model.NotFoundReasoning);
    Code:
       0: aload_0
       1: invokevirtual #5                  // Method getNotFoundReasoning:()Ljava/util/List;
       4: aload_1
       5: invokeinterface #24,  2           // InterfaceMethod java/util/List.remove:(Ljava/lang/Object;)Z
      10: pop
      11: return

  public void removeProcessedRepositoriesList(java.lang.String);
    Code:
       0: aload_0
       1: invokevirtual #6                  // Method getProcessedRepositoriesList:()Ljava/util/List;
       4: aload_1
       5: invokeinterface #24,  2           // InterfaceMethod java/util/List.remove:(Ljava/lang/Object;)Z
      10: pop
      11: return

  public void removeProperty(java.lang.String);
    Code:
       0: aload_0
       1: invokevirtual #7                  // Method getProperties:()Ljava/util/List;
       4: aload_1
       5: invokeinterface #24,  2           // InterfaceMethod java/util/List.remove:(Ljava/lang/Object;)Z
      10: pop
      11: return

  public void removeSource(java.lang.String);
    Code:
       0: aload_0
       1: invokevirtual #8                  // Method getSources:()Ljava/util/List;
       4: aload_1
       5: invokeinterface #24,  2           // InterfaceMethod java/util/List.remove:(Ljava/lang/Object;)Z
      10: pop
      11: return

  public void setAppliedMappings(java.util.List<java.lang.String>);
    Code:
       0: aload_0
       1: aload_1
       2: putfield      #9                  // Field appliedMappings:Ljava/util/List;
       5: return

  public void setAttributes(java.util.List<java.lang.String>);
    Code:
       0: aload_0
       1: aload_1
       2: putfield      #12                 // Field attributes:Ljava/util/List;
       5: return

  public void setNotFoundReasoning(java.util.List<org.sonatype.nexus.rest.model.NotFoundReasoning>);
    Code:
       0: aload_0
       1: aload_1
       2: putfield      #13                 // Field notFoundReasoning:Ljava/util/List;
       5: return

  public void setOriginatingRepositoryId(java.lang.String);
    Code:
       0: aload_0
       1: aload_1
       2: putfield      #14                 // Field originatingRepositoryId:Ljava/lang/String;
       5: return

  public void setOriginatingRepositoryMainFacet(java.lang.String);
    Code:
       0: aload_0
       1: aload_1
       2: putfield      #15                 // Field originatingRepositoryMainFacet:Ljava/lang/String;
       5: return

  public void setOriginatingRepositoryName(java.lang.String);
    Code:
       0: aload_0
       1: aload_1
       2: putfield      #16                 // Field originatingRepositoryName:Ljava/lang/String;
       5: return

  public void setProcessedRepositoriesList(java.util.List<java.lang.String>);
    Code:
       0: aload_0
       1: aload_1
       2: putfield      #17                 // Field processedRepositoriesList:Ljava/util/List;
       5: return

  public void setProperties(java.util.List<java.lang.String>);
    Code:
       0: aload_0
       1: aload_1
       2: putfield      #18                 // Field properties:Ljava/util/List;
       5: return

  public void setResponseActualClass(java.lang.String);
    Code:
       0: aload_0
       1: aload_1
       2: putfield      #19                 // Field responseActualClass:Ljava/lang/String;
       5: return

  public void setResponsePath(java.lang.String);
    Code:
       0: aload_0
       1: aload_1
       2: putfield      #20                 // Field responsePath:Ljava/lang/String;
       5: return

  public void setResponseType(java.lang.String);
    Code:
       0: aload_0
       1: aload_1
       2: putfield      #21                 // Field responseType:Ljava/lang/String;
       5: return

  public void setResponseUid(java.lang.String);
    Code:
       0: aload_0
       1: aload_1
       2: putfield      #22                 // Field responseUid:Ljava/lang/String;
       5: return

  public void setSources(java.util.List<java.lang.String>);
    Code:
       0: aload_0
       1: aload_1
       2: putfield      #23                 // Field sources:Ljava/util/List;
       5: return
}
