Compiled from "RestApiSettings.java"
public class org.sonatype.nexus.rest.model.RestApiSettings implements java.io.Serializable {
  private boolean forceBaseUrl;

  private java.lang.String baseUrl;

  private int uiTimeout;

  public org.sonatype.nexus.rest.model.RestApiSettings();
    Code:
       0: aload_0
       1: invokespecial #1                  // Method java/lang/Object."<init>":()V
       4: aload_0
       5: iconst_0
       6: putfield      #2                  // Field forceBaseUrl:Z
       9: aload_0
      10: iconst_0
      11: putfield      #3                  // Field uiTimeout:I
      14: return

  public java.lang.String getBaseUrl();
    Code:
       0: aload_0
       1: getfield      #4                  // Field baseUrl:Ljava/lang/String;
       4: areturn

  public int getUiTimeout();
    Code:
       0: aload_0
       1: getfield      #3                  // Field uiTimeout:I
       4: ireturn

  public boolean isForceBaseUrl();
    Code:
       0: aload_0
       1: getfield      #2                  // Field forceBaseUrl:Z
       4: ireturn

  public void setBaseUrl(java.lang.String);
    Code:
       0: aload_0
       1: aload_1
       2: putfield      #4                  // Field baseUrl:Ljava/lang/String;
       5: return

  public void setForceBaseUrl(boolean);
    Code:
       0: aload_0
       1: iload_1
       2: putfield      #2                  // Field forceBaseUrl:Z
       5: return

  public void setUiTimeout(int);
    Code:
       0: aload_0
       1: iload_1
       2: putfield      #3                  // Field uiTimeout:I
       5: return
}
