Compiled from "RoutingConfigMessage.java"
public class org.sonatype.nexus.rest.model.RoutingConfigMessage implements java.io.Serializable {
  private boolean discoveryEnabled;

  private int discoveryIntervalHours;

  public org.sonatype.nexus.rest.model.RoutingConfigMessage();
    Code:
       0: aload_0
       1: invokespecial #1                  // Method java/lang/Object."<init>":()V
       4: aload_0
       5: iconst_0
       6: putfield      #2                  // Field discoveryEnabled:Z
       9: aload_0
      10: iconst_0
      11: putfield      #3                  // Field discoveryIntervalHours:I
      14: return

  public int getDiscoveryIntervalHours();
    Code:
       0: aload_0
       1: getfield      #3                  // Field discoveryIntervalHours:I
       4: ireturn

  public boolean isDiscoveryEnabled();
    Code:
       0: aload_0
       1: getfield      #2                  // Field discoveryEnabled:Z
       4: ireturn

  public void setDiscoveryEnabled(boolean);
    Code:
       0: aload_0
       1: iload_1
       2: putfield      #2                  // Field discoveryEnabled:Z
       5: return

  public void setDiscoveryIntervalHours(int);
    Code:
       0: aload_0
       1: iload_1
       2: putfield      #3                  // Field discoveryIntervalHours:I
       5: return
}
