Compiled from "StatusResource.java"
public class org.sonatype.nexus.rest.model.StatusResource implements java.io.Serializable {
  private java.lang.String appName;

  private java.lang.String formattedAppName;

  private java.lang.String version;

  private java.lang.String apiVersion;

  private java.lang.String editionLong;

  private java.lang.String editionShort;

  private java.lang.String attributionsURL;

  private java.lang.String purchaseURL;

  private java.lang.String userLicenseURL;

  private java.lang.String state;

  private java.lang.String operationMode;

  private java.util.Date initializedAt;

  private java.util.Date startedAt;

  private java.util.Date lastConfigChange;

  private boolean firstStart;

  private boolean instanceUpgraded;

  private boolean configurationUpgraded;

  private org.sonatype.nexus.rest.model.StatusConfigurationValidationResponse configurationValidationResponse;

  private java.lang.String errorCause;

  private org.sonatype.nexus.rest.model.NexusAuthenticationClientPermissions clientPermissions;

  private java.lang.String baseUrl;

  private boolean licenseInstalled;

  private boolean licenseExpired;

  private boolean trialLicense;

  public org.sonatype.nexus.rest.model.StatusResource();
    Code:
       0: aload_0
       1: invokespecial #1                  // Method java/lang/Object."<init>":()V
       4: aload_0
       5: iconst_0
       6: putfield      #2                  // Field firstStart:Z
       9: aload_0
      10: iconst_0
      11: putfield      #3                  // Field instanceUpgraded:Z
      14: aload_0
      15: iconst_0
      16: putfield      #4                  // Field configurationUpgraded:Z
      19: aload_0
      20: iconst_0
      21: putfield      #5                  // Field licenseInstalled:Z
      24: aload_0
      25: iconst_0
      26: putfield      #6                  // Field licenseExpired:Z
      29: aload_0
      30: iconst_0
      31: putfield      #7                  // Field trialLicense:Z
      34: return

  public java.lang.String getApiVersion();
    Code:
       0: aload_0
       1: getfield      #8                  // Field apiVersion:Ljava/lang/String;
       4: areturn

  public java.lang.String getAppName();
    Code:
       0: aload_0
       1: getfield      #9                  // Field appName:Ljava/lang/String;
       4: areturn

  public java.lang.String getAttributionsURL();
    Code:
       0: aload_0
       1: getfield      #10                 // Field attributionsURL:Ljava/lang/String;
       4: areturn

  public java.lang.String getBaseUrl();
    Code:
       0: aload_0
       1: getfield      #11                 // Field baseUrl:Ljava/lang/String;
       4: areturn

  public org.sonatype.nexus.rest.model.NexusAuthenticationClientPermissions getClientPermissions();
    Code:
       0: aload_0
       1: getfield      #12                 // Field clientPermissions:Lorg/sonatype/nexus/rest/model/NexusAuthenticationClientPermissions;
       4: areturn

  public org.sonatype.nexus.rest.model.StatusConfigurationValidationResponse getConfigurationValidationResponse();
    Code:
       0: aload_0
       1: getfield      #13                 // Field configurationValidationResponse:Lorg/sonatype/nexus/rest/model/StatusConfigurationValidationResponse;
       4: areturn

  public java.lang.String getEditionLong();
    Code:
       0: aload_0
       1: getfield      #14                 // Field editionLong:Ljava/lang/String;
       4: areturn

  public java.lang.String getEditionShort();
    Code:
       0: aload_0
       1: getfield      #15                 // Field editionShort:Ljava/lang/String;
       4: areturn

  public java.lang.String getErrorCause();
    Code:
       0: aload_0
       1: getfield      #16                 // Field errorCause:Ljava/lang/String;
       4: areturn

  public java.lang.String getFormattedAppName();
    Code:
       0: aload_0
       1: getfield      #17                 // Field formattedAppName:Ljava/lang/String;
       4: areturn

  public java.util.Date getInitializedAt();
    Code:
       0: aload_0
       1: getfield      #18                 // Field initializedAt:Ljava/util/Date;
       4: areturn

  public java.util.Date getLastConfigChange();
    Code:
       0: aload_0
       1: getfield      #19                 // Field lastConfigChange:Ljava/util/Date;
       4: areturn

  public java.lang.String getOperationMode();
    Code:
       0: aload_0
       1: getfield      #20                 // Field operationMode:Ljava/lang/String;
       4: areturn

  public java.lang.String getPurchaseURL();
    Code:
       0: aload_0
       1: getfield      #21                 // Field purchaseURL:Ljava/lang/String;
       4: areturn

  public java.util.Date getStartedAt();
    Code:
       0: aload_0
       1: getfield      #22                 // Field startedAt:Ljava/util/Date;
       4: areturn

  public java.lang.String getState();
    Code:
       0: aload_0
       1: getfield      #23                 // Field state:Ljava/lang/String;
       4: areturn

  public java.lang.String getUserLicenseURL();
    Code:
       0: aload_0
       1: getfield      #24                 // Field userLicenseURL:Ljava/lang/String;
       4: areturn

  public java.lang.String getVersion();
    Code:
       0: aload_0
       1: getfield      #25                 // Field version:Ljava/lang/String;
       4: areturn

  public boolean isConfigurationUpgraded();
    Code:
       0: aload_0
       1: getfield      #4                  // Field configurationUpgraded:Z
       4: ireturn

  public boolean isFirstStart();
    Code:
       0: aload_0
       1: getfield      #2                  // Field firstStart:Z
       4: ireturn

  public boolean isInstanceUpgraded();
    Code:
       0: aload_0
       1: getfield      #3                  // Field instanceUpgraded:Z
       4: ireturn

  public boolean isLicenseExpired();
    Code:
       0: aload_0
       1: getfield      #6                  // Field licenseExpired:Z
       4: ireturn

  public boolean isLicenseInstalled();
    Code:
       0: aload_0
       1: getfield      #5                  // Field licenseInstalled:Z
       4: ireturn

  public boolean isTrialLicense();
    Code:
       0: aload_0
       1: getfield      #7                  // Field trialLicense:Z
       4: ireturn

  public void setApiVersion(java.lang.String);
    Code:
       0: aload_0
       1: aload_1
       2: putfield      #8                  // Field apiVersion:Ljava/lang/String;
       5: return

  public void setAppName(java.lang.String);
    Code:
       0: aload_0
       1: aload_1
       2: putfield      #9                  // Field appName:Ljava/lang/String;
       5: return

  public void setAttributionsURL(java.lang.String);
    Code:
       0: aload_0
       1: aload_1
       2: putfield      #10                 // Field attributionsURL:Ljava/lang/String;
       5: return

  public void setBaseUrl(java.lang.String);
    Code:
       0: aload_0
       1: aload_1
       2: putfield      #11                 // Field baseUrl:Ljava/lang/String;
       5: return

  public void setClientPermissions(org.sonatype.nexus.rest.model.NexusAuthenticationClientPermissions);
    Code:
       0: aload_0
       1: aload_1
       2: putfield      #12                 // Field clientPermissions:Lorg/sonatype/nexus/rest/model/NexusAuthenticationClientPermissions;
       5: return

  public void setConfigurationUpgraded(boolean);
    Code:
       0: aload_0
       1: iload_1
       2: putfield      #4                  // Field configurationUpgraded:Z
       5: return

  public void setConfigurationValidationResponse(org.sonatype.nexus.rest.model.StatusConfigurationValidationResponse);
    Code:
       0: aload_0
       1: aload_1
       2: putfield      #13                 // Field configurationValidationResponse:Lorg/sonatype/nexus/rest/model/StatusConfigurationValidationResponse;
       5: return

  public void setEditionLong(java.lang.String);
    Code:
       0: aload_0
       1: aload_1
       2: putfield      #14                 // Field editionLong:Ljava/lang/String;
       5: return

  public void setEditionShort(java.lang.String);
    Code:
       0: aload_0
       1: aload_1
       2: putfield      #15                 // Field editionShort:Ljava/lang/String;
       5: return

  public void setErrorCause(java.lang.String);
    Code:
       0: aload_0
       1: aload_1
       2: putfield      #16                 // Field errorCause:Ljava/lang/String;
       5: return

  public void setFirstStart(boolean);
    Code:
       0: aload_0
       1: iload_1
       2: putfield      #2                  // Field firstStart:Z
       5: return

  public void setFormattedAppName(java.lang.String);
    Code:
       0: aload_0
       1: aload_1
       2: putfield      #17                 // Field formattedAppName:Ljava/lang/String;
       5: return

  public void setInitializedAt(java.util.Date);
    Code:
       0: aload_0
       1: aload_1
       2: putfield      #18                 // Field initializedAt:Ljava/util/Date;
       5: return

  public void setInstanceUpgraded(boolean);
    Code:
       0: aload_0
       1: iload_1
       2: putfield      #3                  // Field instanceUpgraded:Z
       5: return

  public void setLastConfigChange(java.util.Date);
    Code:
       0: aload_0
       1: aload_1
       2: putfield      #19                 // Field lastConfigChange:Ljava/util/Date;
       5: return

  public void setLicenseExpired(boolean);
    Code:
       0: aload_0
       1: iload_1
       2: putfield      #6                  // Field licenseExpired:Z
       5: return

  public void setLicenseInstalled(boolean);
    Code:
       0: aload_0
       1: iload_1
       2: putfield      #5                  // Field licenseInstalled:Z
       5: return

  public void setOperationMode(java.lang.String);
    Code:
       0: aload_0
       1: aload_1
       2: putfield      #20                 // Field operationMode:Ljava/lang/String;
       5: return

  public void setPurchaseURL(java.lang.String);
    Code:
       0: aload_0
       1: aload_1
       2: putfield      #21                 // Field purchaseURL:Ljava/lang/String;
       5: return

  public void setStartedAt(java.util.Date);
    Code:
       0: aload_0
       1: aload_1
       2: putfield      #22                 // Field startedAt:Ljava/util/Date;
       5: return

  public void setState(java.lang.String);
    Code:
       0: aload_0
       1: aload_1
       2: putfield      #23                 // Field state:Ljava/lang/String;
       5: return

  public void setTrialLicense(boolean);
    Code:
       0: aload_0
       1: iload_1
       2: putfield      #7                  // Field trialLicense:Z
       5: return

  public void setUserLicenseURL(java.lang.String);
    Code:
       0: aload_0
       1: aload_1
       2: putfield      #24                 // Field userLicenseURL:Ljava/lang/String;
       5: return

  public void setVersion(java.lang.String);
    Code:
       0: aload_0
       1: aload_1
       2: putfield      #25                 // Field version:Ljava/lang/String;
       5: return
}
