Compiled from "FilteredEntryMultimap.java"
final class org.apache.jena.ext.com.google.common.collect.FilteredEntryMultimap$ValuePredicate implements org.apache.jena.ext.com.google.common.base.Predicate<V> {
  private final K key;

  final org.apache.jena.ext.com.google.common.collect.FilteredEntryMultimap this$0;

  org.apache.jena.ext.com.google.common.collect.FilteredEntryMultimap$ValuePredicate(K);
    Code:
       0: aload_0
       1: aload_1
       2: putfield      #20                 // Field this$0:Lorg/apache/jena/ext/com/google/common/collect/FilteredEntryMultimap;
       5: aload_0
       6: invokespecial #23                 // Method java/lang/Object."<init>":()V
       9: aload_0
      10: aload_2
      11: putfield      #25                 // Field key:Ljava/lang/Object;
      14: return

  public boolean apply(V);
    Code:
       0: aload_0
       1: getfield      #20                 // Field this$0:Lorg/apache/jena/ext/com/google/common/collect/FilteredEntryMultimap;
       4: aload_0
       5: getfield      #25                 // Field key:Ljava/lang/Object;
       8: aload_1
       9: invokestatic  #35                 // Method org/apache/jena/ext/com/google/common/collect/FilteredEntryMultimap.access$000:(Lorg/apache/jena/ext/com/google/common/collect/FilteredEntryMultimap;Ljava/lang/Object;Ljava/lang/Object;)Z
      12: ireturn
}
