Compiled from "ImmutableEnumSet.java"
class org.apache.jena.ext.com.google.common.collect.ImmutableEnumSet$EnumSerializedForm<E extends java.lang.Enum<E>> implements java.io.Serializable {
  final java.util.EnumSet<E> delegate;

  private static final long serialVersionUID;

  org.apache.jena.ext.com.google.common.collect.ImmutableEnumSet$EnumSerializedForm(java.util.EnumSet<E>);
    Code:
       0: aload_0
       1: invokespecial #25                 // Method java/lang/Object."<init>":()V
       4: aload_0
       5: aload_1
       6: putfield      #27                 // Field delegate:Ljava/util/EnumSet;
       9: return

  java.lang.Object readResolve();
    Code:
       0: new           #10                 // class org/apache/jena/ext/com/google/common/collect/ImmutableEnumSet
       3: dup
       4: aload_0
       5: getfield      #27                 // Field delegate:Ljava/util/EnumSet;
       8: invokevirtual #38                 // Method java/util/EnumSet.clone:()Ljava/util/EnumSet;
      11: aconst_null
      12: invokespecial #41                 // Method org/apache/jena/ext/com/google/common/collect/ImmutableEnumSet."<init>":(Ljava/util/EnumSet;Lorg/apache/jena/ext/com/google/common/collect/ImmutableEnumSet$1;)V
      15: areturn
}
