Compiled from "ImmutableMap.java"
class org.apache.jena.ext.com.google.common.collect.ImmutableMap$MapViewOfValuesAsSingletonSets$1 extends org.apache.jena.ext.com.google.common.collect.UnmodifiableIterator<java.util.Map$Entry<K, org.apache.jena.ext.com.google.common.collect.ImmutableSet<V>>> {
  final java.util.Iterator val$backingIterator;

  final org.apache.jena.ext.com.google.common.collect.ImmutableMap$MapViewOfValuesAsSingletonSets this$1;

  org.apache.jena.ext.com.google.common.collect.ImmutableMap$MapViewOfValuesAsSingletonSets$1(org.apache.jena.ext.com.google.common.collect.ImmutableMap$MapViewOfValuesAsSingletonSets, java.util.Iterator);
    Code:
       0: aload_0
       1: aload_1
       2: putfield      #29                 // Field this$1:Lorg/apache/jena/ext/com/google/common/collect/ImmutableMap$MapViewOfValuesAsSingletonSets;
       5: aload_0
       6: aload_2
       7: putfield      #31                 // Field val$backingIterator:Ljava/util/Iterator;
      10: aload_0
      11: invokespecial #34                 // Method org/apache/jena/ext/com/google/common/collect/UnmodifiableIterator."<init>":()V
      14: return

  public boolean hasNext();
    Code:
       0: aload_0
       1: getfield      #31                 // Field val$backingIterator:Ljava/util/Iterator;
       4: invokeinterface #42,  1           // InterfaceMethod java/util/Iterator.hasNext:()Z
       9: ireturn

  public java.util.Map$Entry<K, org.apache.jena.ext.com.google.common.collect.ImmutableSet<V>> next();
    Code:
       0: aload_0
       1: getfield      #31                 // Field val$backingIterator:Ljava/util/Iterator;
       4: invokeinterface #47,  1           // InterfaceMethod java/util/Iterator.next:()Ljava/lang/Object;
       9: checkcast     #18                 // class java/util/Map$Entry
      12: astore_1
      13: new           #16                 // class org/apache/jena/ext/com/google/common/collect/ImmutableMap$MapViewOfValuesAsSingletonSets$1$1
      16: dup
      17: aload_0
      18: aload_1
      19: invokespecial #50                 // Method org/apache/jena/ext/com/google/common/collect/ImmutableMap$MapViewOfValuesAsSingletonSets$1$1."<init>":(Lorg/apache/jena/ext/com/google/common/collect/ImmutableMap$MapViewOfValuesAsSingletonSets$1;Ljava/util/Map$Entry;)V
      22: areturn

  public java.lang.Object next();
    Code:
       0: aload_0
       1: invokevirtual #55                 // Method next:()Ljava/util/Map$Entry;
       4: areturn
}
