Compiled from "ImmutableMap.java"
abstract class org.apache.jena.ext.com.google.common.collect.ImmutableMap$IteratorBasedImmutableMap<K, V> extends org.apache.jena.ext.com.google.common.collect.ImmutableMap<K, V> {
  org.apache.jena.ext.com.google.common.collect.ImmutableMap$IteratorBasedImmutableMap();
    Code:
       0: aload_0
       1: invokespecial #19                 // Method org/apache/jena/ext/com/google/common/collect/ImmutableMap."<init>":()V
       4: return

  abstract org.apache.jena.ext.com.google.common.collect.UnmodifiableIterator<java.util.Map$Entry<K, V>> entryIterator();

  java.util.Spliterator<java.util.Map$Entry<K, V>> entrySpliterator();
    Code:
       0: aload_0
       1: invokevirtual #28                 // Method entryIterator:()Lorg/apache/jena/ext/com/google/common/collect/UnmodifiableIterator;
       4: aload_0
       5: invokevirtual #32                 // Method size:()I
       8: i2l
       9: sipush        1297
      12: invokestatic  #38                 // Method java/util/Spliterators.spliterator:(Ljava/util/Iterator;JI)Ljava/util/Spliterator;
      15: areturn

  org.apache.jena.ext.com.google.common.collect.ImmutableSet<java.util.Map$Entry<K, V>> createEntrySet();
    Code:
       0: new           #9                  // class org/apache/jena/ext/com/google/common/collect/ImmutableMap$IteratorBasedImmutableMap$1EntrySetImpl
       3: dup
       4: aload_0
       5: invokespecial #43                 // Method org/apache/jena/ext/com/google/common/collect/ImmutableMap$IteratorBasedImmutableMap$1EntrySetImpl."<init>":(Lorg/apache/jena/ext/com/google/common/collect/ImmutableMap$IteratorBasedImmutableMap;)V
       8: areturn

  public java.util.Set entrySet();
    Code:
       0: aload_0
       1: invokespecial #47                 // Method org/apache/jena/ext/com/google/common/collect/ImmutableMap.entrySet:()Lorg/apache/jena/ext/com/google/common/collect/ImmutableSet;
       4: areturn

  public java.util.Collection values();
    Code:
       0: aload_0
       1: invokespecial #52                 // Method org/apache/jena/ext/com/google/common/collect/ImmutableMap.values:()Lorg/apache/jena/ext/com/google/common/collect/ImmutableCollection;
       4: areturn

  public java.util.Set keySet();
    Code:
       0: aload_0
       1: invokespecial #55                 // Method org/apache/jena/ext/com/google/common/collect/ImmutableMap.keySet:()Lorg/apache/jena/ext/com/google/common/collect/ImmutableSet;
       4: areturn
}
