Compiled from "MapMakerInternalMap.java"
final class org.apache.jena.ext.com.google.common.collect.MapMakerInternalMap$StrongKeyStrongValueEntry<K, V> extends org.apache.jena.ext.com.google.common.collect.MapMakerInternalMap$AbstractStrongKeyEntry<K, V, org.apache.jena.ext.com.google.common.collect.MapMakerInternalMap$StrongKeyStrongValueEntry<K, V>> implements org.apache.jena.ext.com.google.common.collect.MapMakerInternalMap$StrongValueEntry<K, V, org.apache.jena.ext.com.google.common.collect.MapMakerInternalMap$StrongKeyStrongValueEntry<K, V>> {
  private volatile V value;

  org.apache.jena.ext.com.google.common.collect.MapMakerInternalMap$StrongKeyStrongValueEntry(K, int, org.apache.jena.ext.com.google.common.collect.MapMakerInternalMap$StrongKeyStrongValueEntry<K, V>);
    Code:
       0: aload_0
       1: aload_1
       2: iload_2
       3: aload_3
       4: invokespecial #28                 // Method org/apache/jena/ext/com/google/common/collect/MapMakerInternalMap$AbstractStrongKeyEntry."<init>":(Ljava/lang/Object;ILorg/apache/jena/ext/com/google/common/collect/MapMakerInternalMap$InternalEntry;)V
       7: aload_0
       8: aconst_null
       9: putfield      #30                 // Field value:Ljava/lang/Object;
      12: return

  public V getValue();
    Code:
       0: aload_0
       1: getfield      #30                 // Field value:Ljava/lang/Object;
       4: areturn

  void setValue(V);
    Code:
       0: aload_0
       1: aload_1
       2: putfield      #30                 // Field value:Ljava/lang/Object;
       5: return

  org.apache.jena.ext.com.google.common.collect.MapMakerInternalMap$StrongKeyStrongValueEntry<K, V> copy(org.apache.jena.ext.com.google.common.collect.MapMakerInternalMap$StrongKeyStrongValueEntry<K, V>);
    Code:
       0: new           #2                  // class org/apache/jena/ext/com/google/common/collect/MapMakerInternalMap$StrongKeyStrongValueEntry
       3: dup
       4: aload_0
       5: getfield      #46                 // Field key:Ljava/lang/Object;
       8: aload_0
       9: getfield      #48                 // Field hash:I
      12: aload_1
      13: invokespecial #50                 // Method "<init>":(Ljava/lang/Object;ILorg/apache/jena/ext/com/google/common/collect/MapMakerInternalMap$StrongKeyStrongValueEntry;)V
      16: astore_2
      17: aload_2
      18: aload_0
      19: getfield      #30                 // Field value:Ljava/lang/Object;
      22: putfield      #30                 // Field value:Ljava/lang/Object;
      25: aload_2
      26: areturn
}
