Compiled from "SortedSetMultimap.java"
public interface org.apache.jena.ext.com.google.common.collect.SortedSetMultimap<K, V> extends org.apache.jena.ext.com.google.common.collect.SetMultimap<K, V> {
  public abstract java.util.SortedSet<V> get(K);

  public abstract java.util.SortedSet<V> removeAll(java.lang.Object);

  public abstract java.util.SortedSet<V> replaceValues(K, java.lang.Iterable<? extends V>);

  public abstract java.util.Map<K, java.util.Collection<V>> asMap();

  public abstract java.util.Comparator<? super V> valueComparator();

  public default java.util.Set replaceValues(java.lang.Object, java.lang.Iterable);
    Code:
       0: aload_0
       1: aload_1
       2: aload_2
       3: invokeinterface #23,  3           // InterfaceMethod replaceValues:(Ljava/lang/Object;Ljava/lang/Iterable;)Ljava/util/SortedSet;
       8: areturn

  public default java.util.Set removeAll(java.lang.Object);
    Code:
       0: aload_0
       1: aload_1
       2: invokeinterface #29,  2           // InterfaceMethod removeAll:(Ljava/lang/Object;)Ljava/util/SortedSet;
       7: areturn

  public default java.util.Set get(java.lang.Object);
    Code:
       0: aload_0
       1: aload_1
       2: invokeinterface #31,  2           // InterfaceMethod get:(Ljava/lang/Object;)Ljava/util/SortedSet;
       7: areturn

  public default java.util.Collection get(java.lang.Object);
    Code:
       0: aload_0
       1: aload_1
       2: invokeinterface #31,  2           // InterfaceMethod get:(Ljava/lang/Object;)Ljava/util/SortedSet;
       7: areturn

  public default java.util.Collection removeAll(java.lang.Object);
    Code:
       0: aload_0
       1: aload_1
       2: invokeinterface #29,  2           // InterfaceMethod removeAll:(Ljava/lang/Object;)Ljava/util/SortedSet;
       7: areturn

  public default java.util.Collection replaceValues(java.lang.Object, java.lang.Iterable);
    Code:
       0: aload_0
       1: aload_1
       2: aload_2
       3: invokeinterface #23,  3           // InterfaceMethod replaceValues:(Ljava/lang/Object;Ljava/lang/Iterable;)Ljava/util/SortedSet;
       8: areturn
}
