Compiled from "TreeRangeMap.java"
class org.apache.jena.ext.com.google.common.collect.TreeRangeMap$SubRangeMap$1 extends org.apache.jena.ext.com.google.common.collect.TreeRangeMap<K, V>.SubRangeMap.SubRangeMapAsMap {
  final org.apache.jena.ext.com.google.common.collect.TreeRangeMap$SubRangeMap this$1;

  org.apache.jena.ext.com.google.common.collect.TreeRangeMap$SubRangeMap$1(org.apache.jena.ext.com.google.common.collect.TreeRangeMap$SubRangeMap);
    Code:
       0: aload_0
       1: aload_1
       2: putfield      #31                 // Field this$1:Lorg/apache/jena/ext/com/google/common/collect/TreeRangeMap$SubRangeMap;
       5: aload_0
       6: aload_1
       7: invokespecial #33                 // Method org/apache/jena/ext/com/google/common/collect/TreeRangeMap$SubRangeMap$SubRangeMapAsMap."<init>":(Lorg/apache/jena/ext/com/google/common/collect/TreeRangeMap$SubRangeMap;)V
      10: return

  java.util.Iterator<java.util.Map$Entry<org.apache.jena.ext.com.google.common.collect.Range<K>, V>> entryIterator();
    Code:
       0: aload_0
       1: getfield      #31                 // Field this$1:Lorg/apache/jena/ext/com/google/common/collect/TreeRangeMap$SubRangeMap;
       4: invokestatic  #41                 // Method org/apache/jena/ext/com/google/common/collect/TreeRangeMap$SubRangeMap.access$200:(Lorg/apache/jena/ext/com/google/common/collect/TreeRangeMap$SubRangeMap;)Lorg/apache/jena/ext/com/google/common/collect/Range;
       7: invokevirtual #47                 // Method org/apache/jena/ext/com/google/common/collect/Range.isEmpty:()Z
      10: ifeq          17
      13: invokestatic  #53                 // Method org/apache/jena/ext/com/google/common/collect/Iterators.emptyIterator:()Lorg/apache/jena/ext/com/google/common/collect/UnmodifiableIterator;
      16: areturn
      17: aload_0
      18: getfield      #31                 // Field this$1:Lorg/apache/jena/ext/com/google/common/collect/TreeRangeMap$SubRangeMap;
      21: getfield      #57                 // Field org/apache/jena/ext/com/google/common/collect/TreeRangeMap$SubRangeMap.this$0:Lorg/apache/jena/ext/com/google/common/collect/TreeRangeMap;
      24: invokestatic  #61                 // Method org/apache/jena/ext/com/google/common/collect/TreeRangeMap.access$000:(Lorg/apache/jena/ext/com/google/common/collect/TreeRangeMap;)Ljava/util/NavigableMap;
      27: aload_0
      28: getfield      #31                 // Field this$1:Lorg/apache/jena/ext/com/google/common/collect/TreeRangeMap$SubRangeMap;
      31: invokestatic  #41                 // Method org/apache/jena/ext/com/google/common/collect/TreeRangeMap$SubRangeMap.access$200:(Lorg/apache/jena/ext/com/google/common/collect/TreeRangeMap$SubRangeMap;)Lorg/apache/jena/ext/com/google/common/collect/Range;
      34: getfield      #65                 // Field org/apache/jena/ext/com/google/common/collect/Range.upperBound:Lorg/apache/jena/ext/com/google/common/collect/Cut;
      37: iconst_0
      38: invokeinterface #71,  3           // InterfaceMethod java/util/NavigableMap.headMap:(Ljava/lang/Object;Z)Ljava/util/NavigableMap;
      43: invokeinterface #75,  1           // InterfaceMethod java/util/NavigableMap.descendingMap:()Ljava/util/NavigableMap;
      48: invokeinterface #79,  1           // InterfaceMethod java/util/NavigableMap.values:()Ljava/util/Collection;
      53: invokeinterface #84,  1           // InterfaceMethod java/util/Collection.iterator:()Ljava/util/Iterator;
      58: astore_1
      59: new           #16                 // class org/apache/jena/ext/com/google/common/collect/TreeRangeMap$SubRangeMap$1$1
      62: dup
      63: aload_0
      64: aload_1
      65: invokespecial #87                 // Method org/apache/jena/ext/com/google/common/collect/TreeRangeMap$SubRangeMap$1$1."<init>":(Lorg/apache/jena/ext/com/google/common/collect/TreeRangeMap$SubRangeMap$1;Ljava/util/Iterator;)V
      68: areturn
}
