Compiled from "PropertyState.java"
public class org.jboss.as.cli.parsing.operation.PropertyState extends org.jboss.as.cli.parsing.ExpressionBaseState {
  public static final org.jboss.as.cli.parsing.operation.PropertyState INSTANCE;

  public static final java.lang.String ID;

  org.jboss.as.cli.parsing.operation.PropertyState();
    Code:
       0: aload_0
       1: getstatic     #1                  // Field org/jboss/as/cli/parsing/operation/PropertyValueState.INSTANCE:Lorg/jboss/as/cli/parsing/operation/PropertyValueState;
       4: invokespecial #2                  // Method "<init>":(Lorg/jboss/as/cli/parsing/operation/PropertyValueState;)V
       7: return

  org.jboss.as.cli.parsing.operation.PropertyState(org.jboss.as.cli.parsing.operation.PropertyValueState);
    Code:
       0: aload_0
       1: bipush        44
       3: aload_1
       4: iconst_1
       5: newarray       char
       7: dup
       8: iconst_0
       9: bipush        41
      11: castore
      12: invokespecial #3                  // Method "<init>":(CLorg/jboss/as/cli/parsing/operation/PropertyValueState;[C)V
      15: return

  org.jboss.as.cli.parsing.operation.PropertyState(char, char...);
    Code:
       0: aload_0
       1: iload_1
       2: new           #4                  // class org/jboss/as/cli/parsing/operation/PropertyValueState
       5: dup
       6: iload_1
       7: aload_2
       8: invokespecial #5                  // Method org/jboss/as/cli/parsing/operation/PropertyValueState."<init>":(C[C)V
      11: aload_2
      12: invokespecial #3                  // Method "<init>":(CLorg/jboss/as/cli/parsing/operation/PropertyValueState;[C)V
      15: return

  org.jboss.as.cli.parsing.operation.PropertyState(char, org.jboss.as.cli.parsing.operation.PropertyValueState, char...);
    Code:
       0: aload_0
       1: ldc           #7                  // String PROP
       3: invokespecial #8                  // Method org/jboss/as/cli/parsing/ExpressionBaseState."<init>":(Ljava/lang/String;)V
       6: aload_0
       7: iconst_1
       8: invokevirtual #9                  // Method setIgnoreWhitespaces:(Z)V
      11: aload_0
      12: new           #10                 // class org/jboss/as/cli/parsing/operation/PropertyState$1
      15: dup
      16: aload_0
      17: invokespecial #11                 // Method org/jboss/as/cli/parsing/operation/PropertyState$1."<init>":(Lorg/jboss/as/cli/parsing/operation/PropertyState;)V
      20: invokevirtual #12                 // Method setEnterHandler:(Lorg/jboss/as/cli/parsing/CharacterHandler;)V
      23: iconst_0
      24: istore        4
      26: iload         4
      28: aload_3
      29: arraylength
      30: if_icmpge     50
      33: aload_0
      34: aload_3
      35: iload         4
      37: caload
      38: getstatic     #13                 // Field org/jboss/as/cli/parsing/GlobalCharacterHandlers.LEAVE_STATE_HANDLER:Lorg/jboss/as/cli/parsing/CharacterHandler;
      41: invokevirtual #14                 // Method putHandler:(CLorg/jboss/as/cli/parsing/CharacterHandler;)V
      44: iinc          4, 1
      47: goto          26
      50: aload_0
      51: bipush        61
      53: new           #15                 // class org/jboss/as/cli/parsing/operation/PropertyState$NameValueSeparatorState
      56: dup
      57: aload_2
      58: invokespecial #16                 // Method org/jboss/as/cli/parsing/operation/PropertyState$NameValueSeparatorState."<init>":(Lorg/jboss/as/cli/parsing/operation/PropertyValueState;)V
      61: invokevirtual #17                 // Method enterState:(CLorg/jboss/as/cli/parsing/ParsingState;)V
      64: aload_0
      65: getstatic     #18                 // Field org/jboss/as/cli/parsing/WordCharacterHandler.IGNORE_LB_ESCAPE_OFF:Lorg/jboss/as/cli/parsing/WordCharacterHandler;
      68: invokevirtual #19                 // Method setDefaultHandler:(Lorg/jboss/as/cli/parsing/CharacterHandler;)V
      71: aload_0
      72: getstatic     #13                 // Field org/jboss/as/cli/parsing/GlobalCharacterHandlers.LEAVE_STATE_HANDLER:Lorg/jboss/as/cli/parsing/CharacterHandler;
      75: invokevirtual #20                 // Method setReturnHandler:(Lorg/jboss/as/cli/parsing/CharacterHandler;)V
      78: return

  static {};
    Code:
       0: new           #6                  // class org/jboss/as/cli/parsing/operation/PropertyState
       3: dup
       4: invokespecial #21                 // Method "<init>":()V
       7: putstatic     #22                 // Field INSTANCE:Lorg/jboss/as/cli/parsing/operation/PropertyState;
      10: return
}
