Compiled from "ActionNamespaceMarshaller.java"
public class org.opensaml.samlext.saml2mdquery.impl.ActionNamespaceMarshaller extends org.opensaml.common.impl.AbstractSAMLObjectMarshaller {
  public org.opensaml.samlext.saml2mdquery.impl.ActionNamespaceMarshaller();
    Code:
       0: aload_0
       1: invokespecial #1                  // Method org/opensaml/common/impl/AbstractSAMLObjectMarshaller."<init>":()V
       4: return

  protected void marshallElementContent(org.opensaml.xml.XMLObject, org.w3c.dom.Element) throws org.opensaml.xml.io.MarshallingException;
    Code:
       0: aload_1
       1: checkcast     #2                  // class org/opensaml/samlext/saml2mdquery/ActionNamespace
       4: astore_3
       5: aload_3
       6: invokeinterface #3,  1            // InterfaceMethod org/opensaml/samlext/saml2mdquery/ActionNamespace.getValue:()Ljava/lang/String;
      11: invokestatic  #4                  // Method org/opensaml/xml/util/DatatypeHelper.isEmpty:(Ljava/lang/String;)Z
      14: ifne          27
      17: aload_2
      18: aload_3
      19: invokeinterface #3,  1            // InterfaceMethod org/opensaml/samlext/saml2mdquery/ActionNamespace.getValue:()Ljava/lang/String;
      24: invokestatic  #5                  // Method org/opensaml/xml/util/XMLHelper.appendTextContent:(Lorg/w3c/dom/Element;Ljava/lang/String;)V
      27: return
}
