Compiled from "XTSBASubordinateRecoveryModule.java"
public class org.jboss.jbossts.xts.recovery.participant.ba.XTSBASubordinateRecoveryModule implements org.jboss.jbossts.xts.recovery.participant.ba.XTSBARecoveryModule {
  public org.jboss.jbossts.xts.recovery.participant.ba.XTSBASubordinateRecoveryModule();
    Code:
       0: aload_0
       1: invokespecial #1                  // Method java/lang/Object."<init>":()V
       4: return

  public com.arjuna.wst.BusinessAgreementWithParticipantCompletionParticipant deserializeParticipantCompletionParticipant(java.lang.String, java.io.ObjectInputStream) throws java.lang.Exception;
    Code:
       0: aload_1
       1: getstatic     #2                  // Field com/arjuna/mwlabs/wscf/model/sagas/arjunacore/subordinate/SubordinateBACoordinator.PARTICIPANT_PREFIX:Ljava/lang/String;
       4: invokevirtual #3                  // Method java/lang/String.startsWith:(Ljava/lang/String;)Z
       7: ifeq          37
      10: new           #4                  // class java/lang/Exception
      13: dup
      14: new           #5                  // class java/lang/StringBuilder
      17: dup
      18: invokespecial #6                  // Method java/lang/StringBuilder."<init>":()V
      21: ldc           #7                  // String XTSBASubordinateRecoveryModule : invalid request to deserialize() subordinate WS-BA coordinator participant completion participant
      23: invokevirtual #8                  // Method java/lang/StringBuilder.append:(Ljava/lang/String;)Ljava/lang/StringBuilder;
      26: aload_1
      27: invokevirtual #8                  // Method java/lang/StringBuilder.append:(Ljava/lang/String;)Ljava/lang/StringBuilder;
      30: invokevirtual #9                  // Method java/lang/StringBuilder.toString:()Ljava/lang/String;
      33: invokespecial #10                 // Method java/lang/Exception."<init>":(Ljava/lang/String;)V
      36: athrow
      37: aconst_null
      38: areturn

  public com.arjuna.wst.BusinessAgreementWithParticipantCompletionParticipant recreateParticipantCompletionParticipant(java.lang.String, byte[]) throws java.lang.Exception;
    Code:
       0: aload_1
       1: getstatic     #2                  // Field com/arjuna/mwlabs/wscf/model/sagas/arjunacore/subordinate/SubordinateBACoordinator.PARTICIPANT_PREFIX:Ljava/lang/String;
       4: invokevirtual #3                  // Method java/lang/String.startsWith:(Ljava/lang/String;)Z
       7: ifeq          37
      10: new           #4                  // class java/lang/Exception
      13: dup
      14: new           #5                  // class java/lang/StringBuilder
      17: dup
      18: invokespecial #6                  // Method java/lang/StringBuilder."<init>":()V
      21: ldc           #7                  // String XTSBASubordinateRecoveryModule : invalid request to deserialize() subordinate WS-BA coordinator participant completion participant
      23: invokevirtual #8                  // Method java/lang/StringBuilder.append:(Ljava/lang/String;)Ljava/lang/StringBuilder;
      26: aload_1
      27: invokevirtual #8                  // Method java/lang/StringBuilder.append:(Ljava/lang/String;)Ljava/lang/StringBuilder;
      30: invokevirtual #9                  // Method java/lang/StringBuilder.toString:()Ljava/lang/String;
      33: invokespecial #10                 // Method java/lang/Exception."<init>":(Ljava/lang/String;)V
      36: athrow
      37: aconst_null
      38: areturn

  public com.arjuna.wst.BusinessAgreementWithCoordinatorCompletionParticipant deserializeCoordinatorCompletionParticipant(java.lang.String, java.io.ObjectInputStream) throws java.lang.Exception;
    Code:
       0: aload_1
       1: getstatic     #2                  // Field com/arjuna/mwlabs/wscf/model/sagas/arjunacore/subordinate/SubordinateBACoordinator.PARTICIPANT_PREFIX:Ljava/lang/String;
       4: invokevirtual #3                  // Method java/lang/String.startsWith:(Ljava/lang/String;)Z
       7: ifeq          37
      10: new           #4                  // class java/lang/Exception
      13: dup
      14: new           #5                  // class java/lang/StringBuilder
      17: dup
      18: invokespecial #6                  // Method java/lang/StringBuilder."<init>":()V
      21: ldc           #11                 // String XTSBASubordinateRecoveryModule : invalid request to deserialize() subordinate WS-BA coordinator coordinator completion participant
      23: invokevirtual #8                  // Method java/lang/StringBuilder.append:(Ljava/lang/String;)Ljava/lang/StringBuilder;
      26: aload_1
      27: invokevirtual #8                  // Method java/lang/StringBuilder.append:(Ljava/lang/String;)Ljava/lang/StringBuilder;
      30: invokevirtual #9                  // Method java/lang/StringBuilder.toString:()Ljava/lang/String;
      33: invokespecial #10                 // Method java/lang/Exception."<init>":(Ljava/lang/String;)V
      36: athrow
      37: aconst_null
      38: areturn

  public com.arjuna.wst.BusinessAgreementWithCoordinatorCompletionParticipant recreateCoordinatorCompletionParticipant(java.lang.String, byte[]) throws java.lang.Exception;
    Code:
       0: aload_1
       1: getstatic     #2                  // Field com/arjuna/mwlabs/wscf/model/sagas/arjunacore/subordinate/SubordinateBACoordinator.PARTICIPANT_PREFIX:Ljava/lang/String;
       4: invokevirtual #3                  // Method java/lang/String.startsWith:(Ljava/lang/String;)Z
       7: ifeq          104
      10: aload_1
      11: ldc           #12                 // String _CCP
      13: invokevirtual #13                 // Method java/lang/String.endsWith:(Ljava/lang/String;)Z
      16: ifne          46
      19: new           #4                  // class java/lang/Exception
      22: dup
      23: new           #5                  // class java/lang/StringBuilder
      26: dup
      27: invokespecial #6                  // Method java/lang/StringBuilder."<init>":()V
      30: ldc           #14                 // String XTSBASubordinateRecoveryModule : invalid name for subordinate WS-BA coordinator coordinator completion participant participant
      32: invokevirtual #8                  // Method java/lang/StringBuilder.append:(Ljava/lang/String;)Ljava/lang/StringBuilder;
      35: aload_1
      36: invokevirtual #8                  // Method java/lang/StringBuilder.append:(Ljava/lang/String;)Ljava/lang/StringBuilder;
      39: invokevirtual #9                  // Method java/lang/StringBuilder.toString:()Ljava/lang/String;
      42: invokespecial #10                 // Method java/lang/Exception."<init>":(Ljava/lang/String;)V
      45: athrow
      46: new           #15                 // class com/arjuna/ats/arjuna/state/InputObjectState
      49: dup
      50: invokespecial #16                 // Method com/arjuna/ats/arjuna/state/InputObjectState."<init>":()V
      53: astore_3
      54: aload_3
      55: aload_2
      56: invokevirtual #17                 // Method com/arjuna/ats/arjuna/state/InputObjectState.setBuffer:([B)V
      59: aload_3
      60: invokevirtual #18                 // Method com/arjuna/ats/arjuna/state/InputObjectState.unpackString:()Ljava/lang/String;
      63: astore        4
      65: aload_0
      66: invokevirtual #19                 // Method java/lang/Object.getClass:()Ljava/lang/Class;
      69: invokevirtual #20                 // Method java/lang/Class.getClassLoader:()Ljava/lang/ClassLoader;
      72: aload         4
      74: invokevirtual #21                 // Method java/lang/ClassLoader.loadClass:(Ljava/lang/String;)Ljava/lang/Class;
      77: astore        5
      79: aload         5
      81: invokevirtual #22                 // Method java/lang/Class.newInstance:()Ljava/lang/Object;
      84: checkcast     #23                 // class com/arjuna/wst/BusinessAgreementWithCoordinatorCompletionParticipant
      87: astore        6
      89: aload         6
      91: checkcast     #24                 // class com/arjuna/wst/PersistableParticipant
      94: aload_3
      95: invokeinterface #25,  2           // InterfaceMethod com/arjuna/wst/PersistableParticipant.restoreState:(Lcom/arjuna/ats/arjuna/state/InputObjectState;)Z
     100: pop
     101: aload         6
     103: areturn
     104: aconst_null
     105: areturn

  public void endScan();
    Code:
       0: return
}
