Compiled from "ForwardingNamingScheme.java"
public abstract class org.jboss.weld.context.beanstore.ForwardingNamingScheme implements org.jboss.weld.context.beanstore.NamingScheme {
  public org.jboss.weld.context.beanstore.ForwardingNamingScheme();
    Code:
       0: aload_0
       1: invokespecial #1                  // Method java/lang/Object."<init>":()V
       4: return

  protected abstract org.jboss.weld.context.beanstore.NamingScheme delegate();

  public boolean accept(java.lang.String);
    Code:
       0: aload_0
       1: invokevirtual #2                  // Method delegate:()Lorg/jboss/weld/context/beanstore/NamingScheme;
       4: aload_1
       5: invokeinterface #3,  2            // InterfaceMethod org/jboss/weld/context/beanstore/NamingScheme.accept:(Ljava/lang/String;)Z
      10: ireturn

  public org.jboss.weld.serialization.spi.BeanIdentifier deprefix(java.lang.String);
    Code:
       0: aload_0
       1: invokevirtual #2                  // Method delegate:()Lorg/jboss/weld/context/beanstore/NamingScheme;
       4: aload_1
       5: invokeinterface #4,  2            // InterfaceMethod org/jboss/weld/context/beanstore/NamingScheme.deprefix:(Ljava/lang/String;)Lorg/jboss/weld/serialization/spi/BeanIdentifier;
      10: areturn

  public java.lang.String prefix(org.jboss.weld.serialization.spi.BeanIdentifier);
    Code:
       0: aload_0
       1: invokevirtual #2                  // Method delegate:()Lorg/jboss/weld/context/beanstore/NamingScheme;
       4: aload_1
       5: invokeinterface #5,  2            // InterfaceMethod org/jboss/weld/context/beanstore/NamingScheme.prefix:(Lorg/jboss/weld/serialization/spi/BeanIdentifier;)Ljava/lang/String;
      10: areturn

  public java.util.Collection<java.lang.String> filterIds(java.util.Iterator<java.lang.String>);
    Code:
       0: aload_0
       1: invokevirtual #2                  // Method delegate:()Lorg/jboss/weld/context/beanstore/NamingScheme;
       4: aload_1
       5: invokeinterface #6,  2            // InterfaceMethod org/jboss/weld/context/beanstore/NamingScheme.filterIds:(Ljava/util/Iterator;)Ljava/util/Collection;
      10: areturn

  public java.util.Collection<org.jboss.weld.serialization.spi.BeanIdentifier> deprefix(java.util.Collection<java.lang.String>);
    Code:
       0: aload_0
       1: invokevirtual #2                  // Method delegate:()Lorg/jboss/weld/context/beanstore/NamingScheme;
       4: aload_1
       5: invokeinterface #7,  2            // InterfaceMethod org/jboss/weld/context/beanstore/NamingScheme.deprefix:(Ljava/util/Collection;)Ljava/util/Collection;
      10: areturn

  public java.util.Collection<java.lang.String> prefix(java.util.Collection<org.jboss.weld.serialization.spi.BeanIdentifier>);
    Code:
       0: aload_0
       1: invokevirtual #2                  // Method delegate:()Lorg/jboss/weld/context/beanstore/NamingScheme;
       4: aload_1
       5: invokeinterface #8,  2            // InterfaceMethod org/jboss/weld/context/beanstore/NamingScheme.prefix:(Ljava/util/Collection;)Ljava/util/Collection;
      10: areturn

  public boolean equals(java.lang.Object);
    Code:
       0: aload_0
       1: invokevirtual #2                  // Method delegate:()Lorg/jboss/weld/context/beanstore/NamingScheme;
       4: aload_1
       5: invokevirtual #9                  // Method java/lang/Object.equals:(Ljava/lang/Object;)Z
       8: ireturn

  public int hashCode();
    Code:
       0: aload_0
       1: invokevirtual #2                  // Method delegate:()Lorg/jboss/weld/context/beanstore/NamingScheme;
       4: invokevirtual #10                 // Method java/lang/Object.hashCode:()I
       7: ireturn

  public java.lang.String toString();
    Code:
       0: aload_0
       1: invokevirtual #2                  // Method delegate:()Lorg/jboss/weld/context/beanstore/NamingScheme;
       4: invokevirtual #11                 // Method java/lang/Object.toString:()Ljava/lang/String;
       7: areturn
}
