Compiled from "Promises.java"
class com.amazonaws.services.simpleworkflow.flow.core.Promises$2 extends com.amazonaws.services.simpleworkflow.flow.core.Task {
  private final java.util.Map val$map;

  private final com.amazonaws.services.simpleworkflow.flow.core.Settable val$result;

  com.amazonaws.services.simpleworkflow.flow.core.Promises$2(com.amazonaws.services.simpleworkflow.flow.core.Promise..., java.util.Map, com.amazonaws.services.simpleworkflow.flow.core.Settable);
    Code:
       0: aload_0
       1: aload_2
       2: putfield      #12                 // Field val$map:Ljava/util/Map;
       5: aload_0
       6: aload_3
       7: putfield      #14                 // Field val$result:Lcom/amazonaws/services/simpleworkflow/flow/core/Settable;
      10: aload_0
      11: aload_1
      12: invokespecial #16                 // Method com/amazonaws/services/simpleworkflow/flow/core/Task."<init>":([Lcom/amazonaws/services/simpleworkflow/flow/core/Promise;)V
      15: return

  protected void doExecute() throws java.lang.Throwable;
    Code:
       0: new           #31                 // class java/util/HashMap
       3: dup
       4: aload_0
       5: getfield      #12                 // Field val$map:Ljava/util/Map;
       8: invokeinterface #33,  1           // InterfaceMethod java/util/Map.size:()I
      13: invokespecial #39                 // Method java/util/HashMap."<init>":(I)V
      16: astore_1
      17: aload_0
      18: getfield      #12                 // Field val$map:Ljava/util/Map;
      21: invokeinterface #42,  1           // InterfaceMethod java/util/Map.entrySet:()Ljava/util/Set;
      26: invokeinterface #46,  1           // InterfaceMethod java/util/Set.iterator:()Ljava/util/Iterator;
      31: astore_3
      32: goto          70
      35: aload_3
      36: invokeinterface #52,  1           // InterfaceMethod java/util/Iterator.next:()Ljava/lang/Object;
      41: checkcast     #58                 // class java/util/Map$Entry
      44: astore_2
      45: aload_1
      46: aload_2
      47: invokeinterface #60,  1           // InterfaceMethod java/util/Map$Entry.getKey:()Ljava/lang/Object;
      52: aload_2
      53: invokeinterface #63,  1           // InterfaceMethod java/util/Map$Entry.getValue:()Ljava/lang/Object;
      58: checkcast     #66                 // class com/amazonaws/services/simpleworkflow/flow/core/Promise
      61: invokevirtual #68                 // Method com/amazonaws/services/simpleworkflow/flow/core/Promise.get:()Ljava/lang/Object;
      64: invokeinterface #71,  3           // InterfaceMethod java/util/Map.put:(Ljava/lang/Object;Ljava/lang/Object;)Ljava/lang/Object;
      69: pop
      70: aload_3
      71: invokeinterface #75,  1           // InterfaceMethod java/util/Iterator.hasNext:()Z
      76: ifne          35
      79: aload_0
      80: getfield      #14                 // Field val$result:Lcom/amazonaws/services/simpleworkflow/flow/core/Settable;
      83: aload_1
      84: invokevirtual #79                 // Method com/amazonaws/services/simpleworkflow/flow/core/Settable.set:(Ljava/lang/Object;)V
      87: return
}
