Compiled from "Log_$logger.java"
public class org.hibernate.ogm.util.impl.Log_$logger extends org.jboss.logging.DelegatingBasicLogger implements java.io.Serializable,org.hibernate.ogm.util.impl.Log,org.jboss.logging.BasicLogger {
  private static final long serialVersionUID;

  private static final java.lang.String projectCode;

  private static final java.lang.String FQCN;

  private static final java.lang.String useGridDialect;

  private static final java.lang.String unexpectedDatastoreProvider;

  private static final java.lang.String persistenceXmlNotFoundInClassPath;

  private static final java.lang.String noDatastoreConfigured;

  private static final java.lang.String querySyntaxException;

  private static final java.lang.String jtaCommitFailed;

  private static final java.lang.String useDatastoreProvider;

  private static final java.lang.String unableToInitializeInfinispan;

  private static final java.lang.String unableToSetTimeout;

  private static final java.lang.String jtaRollbackFailed;

  private static final java.lang.String usingDefaultTransactionFactory;

  private static final java.lang.String dialectClassCannotBeFound;

  private static final java.lang.String gridDialectPropertyOfUnknownType;

  private static final java.lang.String notADatastoreManager;

  private static final java.lang.String jtaCouldNotDetermineStatus;

  private static final java.lang.String jtaTransactionBeginFailed;

  private static final java.lang.String unknownDatastoreManagerType;

  private static final java.lang.String version;

  private static final java.lang.String doesNotImplementGridDialect;

  private static final java.lang.String unableToMarkTransactionForRollback;

  private static final java.lang.String gridDialectHasNoProperConstrutor;

  private static final java.lang.String unableToInstantiateDatastoreManager;

  private static final java.lang.String datastoreClassCannotBeFound;

  private static final java.lang.String cannotInstantiateGridDialect;

  public org.hibernate.ogm.util.impl.Log_$logger(org.jboss.logging.Logger);
    Code:
       0: aload_0
       1: aload_1
       2: invokespecial #1                  // Method org/jboss/logging/DelegatingBasicLogger."<init>":(Lorg/jboss/logging/Logger;)V
       5: return

  public final void useGridDialect(java.lang.String);
    Code:
       0: aload_0
       1: getfield      #2                  // Field org/jboss/logging/DelegatingBasicLogger.log:Lorg/jboss/logging/Logger;
       4: getstatic     #3                  // Field FQCN:Ljava/lang/String;
       7: getstatic     #4                  // Field org/jboss/logging/Logger$Level.INFO:Lorg/jboss/logging/Logger$Level;
      10: aconst_null
      11: new           #5                  // class java/lang/StringBuilder
      14: dup
      15: invokespecial #6                  // Method java/lang/StringBuilder."<init>":()V
      18: ldc           #7                  // String OGM000017:
      20: invokevirtual #8                  // Method java/lang/StringBuilder.append:(Ljava/lang/String;)Ljava/lang/StringBuilder;
      23: aload_0
      24: invokevirtual #9                  // Method useGridDialect$str:()Ljava/lang/String;
      27: invokevirtual #8                  // Method java/lang/StringBuilder.append:(Ljava/lang/String;)Ljava/lang/StringBuilder;
      30: invokevirtual #10                 // Method java/lang/StringBuilder.toString:()Ljava/lang/String;
      33: aload_1
      34: invokevirtual #11                 // Method org/jboss/logging/Logger.logf:(Ljava/lang/String;Lorg/jboss/logging/Logger$Level;Ljava/lang/Throwable;Ljava/lang/String;Ljava/lang/Object;)V
      37: return

  protected java.lang.String useGridDialect$str();
    Code:
       0: ldc           #12                 // String Grid Dialect: %1$s
       2: areturn

  public final org.hibernate.HibernateException unexpectedDatastoreProvider(java.lang.Class, java.lang.Class);
    Code:
       0: new           #13                 // class org/hibernate/HibernateException
       3: dup
       4: new           #5                  // class java/lang/StringBuilder
       7: dup
       8: invokespecial #6                  // Method java/lang/StringBuilder."<init>":()V
      11: ldc           #14                 // String OGM000015:
      13: invokevirtual #8                  // Method java/lang/StringBuilder.append:(Ljava/lang/String;)Ljava/lang/StringBuilder;
      16: aload_0
      17: invokevirtual #15                 // Method unexpectedDatastoreProvider$str:()Ljava/lang/String;
      20: invokevirtual #8                  // Method java/lang/StringBuilder.append:(Ljava/lang/String;)Ljava/lang/StringBuilder;
      23: invokevirtual #10                 // Method java/lang/StringBuilder.toString:()Ljava/lang/String;
      26: iconst_2
      27: anewarray     #16                 // class java/lang/Object
      30: dup
      31: iconst_0
      32: aload_1
      33: aastore
      34: dup
      35: iconst_1
      36: aload_2
      37: aastore
      38: invokestatic  #17                 // Method java/lang/String.format:(Ljava/lang/String;[Ljava/lang/Object;)Ljava/lang/String;
      41: invokespecial #18                 // Method org/hibernate/HibernateException."<init>":(Ljava/lang/String;)V
      44: astore_3
      45: aload_3
      46: invokevirtual #19                 // Method org/hibernate/HibernateException.getStackTrace:()[Ljava/lang/StackTraceElement;
      49: astore        4
      51: aload_3
      52: aload         4
      54: iconst_1
      55: aload         4
      57: arraylength
      58: invokestatic  #20                 // Method java/util/Arrays.copyOfRange:([Ljava/lang/Object;II)[Ljava/lang/Object;
      61: checkcast     #21                 // class "[Ljava/lang/StackTraceElement;"
      64: invokevirtual #22                 // Method org/hibernate/HibernateException.setStackTrace:([Ljava/lang/StackTraceElement;)V
      67: aload_3
      68: areturn

  protected java.lang.String unexpectedDatastoreProvider$str();
    Code:
       0: ldc           #23                 // String Expected DatastoreProvider %2$s but found %1$s
       2: areturn

  public final void persistenceXmlNotFoundInClassPath(java.lang.String);
    Code:
       0: aload_0
       1: getfield      #2                  // Field org/jboss/logging/DelegatingBasicLogger.log:Lorg/jboss/logging/Logger;
       4: getstatic     #3                  // Field FQCN:Ljava/lang/String;
       7: getstatic     #24                 // Field org/jboss/logging/Logger$Level.WARN:Lorg/jboss/logging/Logger$Level;
      10: aconst_null
      11: new           #5                  // class java/lang/StringBuilder
      14: dup
      15: invokespecial #6                  // Method java/lang/StringBuilder."<init>":()V
      18: ldc           #25                 // String OGM000002:
      20: invokevirtual #8                  // Method java/lang/StringBuilder.append:(Ljava/lang/String;)Ljava/lang/StringBuilder;
      23: aload_0
      24: invokevirtual #26                 // Method persistenceXmlNotFoundInClassPath$str:()Ljava/lang/String;
      27: invokevirtual #8                  // Method java/lang/StringBuilder.append:(Ljava/lang/String;)Ljava/lang/StringBuilder;
      30: invokevirtual #10                 // Method java/lang/StringBuilder.toString:()Ljava/lang/String;
      33: aload_1
      34: invokevirtual #11                 // Method org/jboss/logging/Logger.logf:(Ljava/lang/String;Lorg/jboss/logging/Logger$Level;Ljava/lang/Throwable;Ljava/lang/String;Ljava/lang/Object;)V
      37: return

  protected java.lang.String persistenceXmlNotFoundInClassPath$str();
    Code:
       0: ldc           #27                 // String Could not find any META-INF/persistence.xml file in the classpath. Unable to build Persistence Unit %1$s
       2: areturn

  public final org.hibernate.HibernateException noDatastoreConfigured();
    Code:
       0: new           #13                 // class org/hibernate/HibernateException
       3: dup
       4: new           #5                  // class java/lang/StringBuilder
       7: dup
       8: invokespecial #6                  // Method java/lang/StringBuilder."<init>":()V
      11: ldc           #28                 // String OGM000009:
      13: invokevirtual #8                  // Method java/lang/StringBuilder.append:(Ljava/lang/String;)Ljava/lang/StringBuilder;
      16: aload_0
      17: invokevirtual #29                 // Method noDatastoreConfigured$str:()Ljava/lang/String;
      20: invokevirtual #8                  // Method java/lang/StringBuilder.append:(Ljava/lang/String;)Ljava/lang/StringBuilder;
      23: invokevirtual #10                 // Method java/lang/StringBuilder.toString:()Ljava/lang/String;
      26: iconst_0
      27: anewarray     #16                 // class java/lang/Object
      30: invokestatic  #17                 // Method java/lang/String.format:(Ljava/lang/String;[Ljava/lang/Object;)Ljava/lang/String;
      33: invokespecial #18                 // Method org/hibernate/HibernateException."<init>":(Ljava/lang/String;)V
      36: astore_1
      37: aload_1
      38: invokevirtual #19                 // Method org/hibernate/HibernateException.getStackTrace:()[Ljava/lang/StackTraceElement;
      41: astore_2
      42: aload_1
      43: aload_2
      44: iconst_1
      45: aload_2
      46: arraylength
      47: invokestatic  #20                 // Method java/util/Arrays.copyOfRange:([Ljava/lang/Object;II)[Ljava/lang/Object;
      50: checkcast     #21                 // class "[Ljava/lang/StackTraceElement;"
      53: invokevirtual #22                 // Method org/hibernate/HibernateException.setStackTrace:([Ljava/lang/StackTraceElement;)V
      56: aload_1
      57: areturn

  protected java.lang.String noDatastoreConfigured$str();
    Code:
       0: ldc           #30                 // String hibernate.ogm.datastore.provider has not been defined and no DatastoreManager could be guessed
       2: areturn

  public final org.hibernate.HibernateException querySyntaxException(org.hibernate.hql.internal.ast.QuerySyntaxException, java.lang.String);
    Code:
       0: new           #13                 // class org/hibernate/HibernateException
       3: dup
       4: new           #5                  // class java/lang/StringBuilder
       7: dup
       8: invokespecial #6                  // Method java/lang/StringBuilder."<init>":()V
      11: ldc           #31                 // String OGM000024:
      13: invokevirtual #8                  // Method java/lang/StringBuilder.append:(Ljava/lang/String;)Ljava/lang/StringBuilder;
      16: aload_0
      17: invokevirtual #32                 // Method querySyntaxException$str:()Ljava/lang/String;
      20: invokevirtual #8                  // Method java/lang/StringBuilder.append:(Ljava/lang/String;)Ljava/lang/StringBuilder;
      23: invokevirtual #10                 // Method java/lang/StringBuilder.toString:()Ljava/lang/String;
      26: iconst_1
      27: anewarray     #16                 // class java/lang/Object
      30: dup
      31: iconst_0
      32: aload_2
      33: aastore
      34: invokestatic  #17                 // Method java/lang/String.format:(Ljava/lang/String;[Ljava/lang/Object;)Ljava/lang/String;
      37: aload_1
      38: invokespecial #33                 // Method org/hibernate/HibernateException."<init>":(Ljava/lang/String;Ljava/lang/Throwable;)V
      41: astore_3
      42: aload_3
      43: invokevirtual #19                 // Method org/hibernate/HibernateException.getStackTrace:()[Ljava/lang/StackTraceElement;
      46: astore        4
      48: aload_3
      49: aload         4
      51: iconst_1
      52: aload         4
      54: arraylength
      55: invokestatic  #20                 // Method java/util/Arrays.copyOfRange:([Ljava/lang/Object;II)[Ljava/lang/Object;
      58: checkcast     #21                 // class "[Ljava/lang/StackTraceElement;"
      61: invokevirtual #22                 // Method org/hibernate/HibernateException.setStackTrace:([Ljava/lang/StackTraceElement;)V
      64: aload_3
      65: areturn

  protected java.lang.String querySyntaxException$str();
    Code:
       0: ldc           #34                 // String Syntax error in query: [%1$s]
       2: areturn

  public final org.hibernate.TransactionException jtaCommitFailed(java.lang.Exception);
    Code:
       0: new           #35                 // class org/hibernate/TransactionException
       3: dup
       4: new           #5                  // class java/lang/StringBuilder
       7: dup
       8: invokespecial #6                  // Method java/lang/StringBuilder."<init>":()V
      11: ldc           #36                 // String OGM000019:
      13: invokevirtual #8                  // Method java/lang/StringBuilder.append:(Ljava/lang/String;)Ljava/lang/StringBuilder;
      16: aload_0
      17: invokevirtual #37                 // Method jtaCommitFailed$str:()Ljava/lang/String;
      20: invokevirtual #8                  // Method java/lang/StringBuilder.append:(Ljava/lang/String;)Ljava/lang/StringBuilder;
      23: invokevirtual #10                 // Method java/lang/StringBuilder.toString:()Ljava/lang/String;
      26: iconst_0
      27: anewarray     #16                 // class java/lang/Object
      30: invokestatic  #17                 // Method java/lang/String.format:(Ljava/lang/String;[Ljava/lang/Object;)Ljava/lang/String;
      33: aload_1
      34: invokespecial #38                 // Method org/hibernate/TransactionException."<init>":(Ljava/lang/String;Ljava/lang/Throwable;)V
      37: astore_2
      38: aload_2
      39: invokevirtual #39                 // Method org/hibernate/TransactionException.getStackTrace:()[Ljava/lang/StackTraceElement;
      42: astore_3
      43: aload_2
      44: aload_3
      45: iconst_1
      46: aload_3
      47: arraylength
      48: invokestatic  #20                 // Method java/util/Arrays.copyOfRange:([Ljava/lang/Object;II)[Ljava/lang/Object;
      51: checkcast     #21                 // class "[Ljava/lang/StackTraceElement;"
      54: invokevirtual #40                 // Method org/hibernate/TransactionException.setStackTrace:([Ljava/lang/StackTraceElement;)V
      57: aload_2
      58: areturn

  protected java.lang.String jtaCommitFailed$str();
    Code:
       0: ldc           #41                 // String JTA transaction commit failed
       2: areturn

  public final void useDatastoreProvider(java.lang.String);
    Code:
       0: aload_0
       1: getfield      #2                  // Field org/jboss/logging/DelegatingBasicLogger.log:Lorg/jboss/logging/Logger;
       4: getstatic     #3                  // Field FQCN:Ljava/lang/String;
       7: getstatic     #4                  // Field org/jboss/logging/Logger$Level.INFO:Lorg/jboss/logging/Logger$Level;
      10: aconst_null
      11: new           #5                  // class java/lang/StringBuilder
      14: dup
      15: invokespecial #6                  // Method java/lang/StringBuilder."<init>":()V
      18: ldc           #42                 // String OGM000016:
      20: invokevirtual #8                  // Method java/lang/StringBuilder.append:(Ljava/lang/String;)Ljava/lang/StringBuilder;
      23: aload_0
      24: invokevirtual #43                 // Method useDatastoreProvider$str:()Ljava/lang/String;
      27: invokevirtual #8                  // Method java/lang/StringBuilder.append:(Ljava/lang/String;)Ljava/lang/StringBuilder;
      30: invokevirtual #10                 // Method java/lang/StringBuilder.toString:()Ljava/lang/String;
      33: aload_1
      34: invokevirtual #11                 // Method org/jboss/logging/Logger.logf:(Ljava/lang/String;Lorg/jboss/logging/Logger$Level;Ljava/lang/Throwable;Ljava/lang/String;Ljava/lang/Object;)V
      37: return

  protected java.lang.String useDatastoreProvider$str();
    Code:
       0: ldc           #44                 // String NoSQL Datastore provider: %1$s
       2: areturn

  public final org.hibernate.HibernateException unableToInitializeInfinispan(java.lang.RuntimeException);
    Code:
       0: new           #13                 // class org/hibernate/HibernateException
       3: dup
       4: new           #5                  // class java/lang/StringBuilder
       7: dup
       8: invokespecial #6                  // Method java/lang/StringBuilder."<init>":()V
      11: ldc           #45                 // String OGM000004:
      13: invokevirtual #8                  // Method java/lang/StringBuilder.append:(Ljava/lang/String;)Ljava/lang/StringBuilder;
      16: aload_0
      17: invokevirtual #46                 // Method unableToInitializeInfinispan$str:()Ljava/lang/String;
      20: invokevirtual #8                  // Method java/lang/StringBuilder.append:(Ljava/lang/String;)Ljava/lang/StringBuilder;
      23: invokevirtual #10                 // Method java/lang/StringBuilder.toString:()Ljava/lang/String;
      26: iconst_0
      27: anewarray     #16                 // class java/lang/Object
      30: invokestatic  #17                 // Method java/lang/String.format:(Ljava/lang/String;[Ljava/lang/Object;)Ljava/lang/String;
      33: aload_1
      34: invokespecial #33                 // Method org/hibernate/HibernateException."<init>":(Ljava/lang/String;Ljava/lang/Throwable;)V
      37: astore_2
      38: aload_2
      39: invokevirtual #19                 // Method org/hibernate/HibernateException.getStackTrace:()[Ljava/lang/StackTraceElement;
      42: astore_3
      43: aload_2
      44: aload_3
      45: iconst_1
      46: aload_3
      47: arraylength
      48: invokestatic  #20                 // Method java/util/Arrays.copyOfRange:([Ljava/lang/Object;II)[Ljava/lang/Object;
      51: checkcast     #21                 // class "[Ljava/lang/StackTraceElement;"
      54: invokevirtual #22                 // Method org/hibernate/HibernateException.setStackTrace:([Ljava/lang/StackTraceElement;)V
      57: aload_2
      58: areturn

  protected java.lang.String unableToInitializeInfinispan$str();
    Code:
       0: ldc           #47                 // String Unable to find or initialize Infinispan CacheManager
       2: areturn

  public final org.hibernate.TransactionException unableToSetTimeout(javax.transaction.SystemException, int);
    Code:
       0: new           #35                 // class org/hibernate/TransactionException
       3: dup
       4: new           #5                  // class java/lang/StringBuilder
       7: dup
       8: invokespecial #6                  // Method java/lang/StringBuilder."<init>":()V
      11: ldc           #48                 // String OGM000023:
      13: invokevirtual #8                  // Method java/lang/StringBuilder.append:(Ljava/lang/String;)Ljava/lang/StringBuilder;
      16: aload_0
      17: invokevirtual #49                 // Method unableToSetTimeout$str:()Ljava/lang/String;
      20: invokevirtual #8                  // Method java/lang/StringBuilder.append:(Ljava/lang/String;)Ljava/lang/StringBuilder;
      23: invokevirtual #10                 // Method java/lang/StringBuilder.toString:()Ljava/lang/String;
      26: iconst_1
      27: anewarray     #16                 // class java/lang/Object
      30: dup
      31: iconst_0
      32: iload_2
      33: invokestatic  #50                 // Method java/lang/Integer.valueOf:(I)Ljava/lang/Integer;
      36: aastore
      37: invokestatic  #17                 // Method java/lang/String.format:(Ljava/lang/String;[Ljava/lang/Object;)Ljava/lang/String;
      40: aload_1
      41: invokespecial #38                 // Method org/hibernate/TransactionException."<init>":(Ljava/lang/String;Ljava/lang/Throwable;)V
      44: astore_3
      45: aload_3
      46: invokevirtual #39                 // Method org/hibernate/TransactionException.getStackTrace:()[Ljava/lang/StackTraceElement;
      49: astore        4
      51: aload_3
      52: aload         4
      54: iconst_1
      55: aload         4
      57: arraylength
      58: invokestatic  #20                 // Method java/util/Arrays.copyOfRange:([Ljava/lang/Object;II)[Ljava/lang/Object;
      61: checkcast     #21                 // class "[Ljava/lang/StackTraceElement;"
      64: invokevirtual #40                 // Method org/hibernate/TransactionException.setStackTrace:([Ljava/lang/StackTraceElement;)V
      67: aload_3
      68: areturn

  protected java.lang.String unableToSetTimeout$str();
    Code:
       0: ldc           #51                 // String Unable to set transaction timeout to \'%1$s\'
       2: areturn

  public final org.hibernate.TransactionException jtaRollbackFailed(java.lang.Exception);
    Code:
       0: new           #35                 // class org/hibernate/TransactionException
       3: dup
       4: new           #5                  // class java/lang/StringBuilder
       7: dup
       8: invokespecial #6                  // Method java/lang/StringBuilder."<init>":()V
      11: ldc           #52                 // String OGM000020:
      13: invokevirtual #8                  // Method java/lang/StringBuilder.append:(Ljava/lang/String;)Ljava/lang/StringBuilder;
      16: aload_0
      17: invokevirtual #53                 // Method jtaRollbackFailed$str:()Ljava/lang/String;
      20: invokevirtual #8                  // Method java/lang/StringBuilder.append:(Ljava/lang/String;)Ljava/lang/StringBuilder;
      23: invokevirtual #10                 // Method java/lang/StringBuilder.toString:()Ljava/lang/String;
      26: iconst_0
      27: anewarray     #16                 // class java/lang/Object
      30: invokestatic  #17                 // Method java/lang/String.format:(Ljava/lang/String;[Ljava/lang/Object;)Ljava/lang/String;
      33: aload_1
      34: invokespecial #38                 // Method org/hibernate/TransactionException."<init>":(Ljava/lang/String;Ljava/lang/Throwable;)V
      37: astore_2
      38: aload_2
      39: invokevirtual #39                 // Method org/hibernate/TransactionException.getStackTrace:()[Ljava/lang/StackTraceElement;
      42: astore_3
      43: aload_2
      44: aload_3
      45: iconst_1
      46: aload_3
      47: arraylength
      48: invokestatic  #20                 // Method java/util/Arrays.copyOfRange:([Ljava/lang/Object;II)[Ljava/lang/Object;
      51: checkcast     #21                 // class "[Ljava/lang/StackTraceElement;"
      54: invokevirtual #40                 // Method org/hibernate/TransactionException.setStackTrace:([Ljava/lang/StackTraceElement;)V
      57: aload_2
      58: areturn

  protected java.lang.String jtaRollbackFailed$str();
    Code:
       0: ldc           #54                 // String JTA transaction rollback failed
       2: areturn

  public final void usingDefaultTransactionFactory();
    Code:
       0: aload_0
       1: getfield      #2                  // Field org/jboss/logging/DelegatingBasicLogger.log:Lorg/jboss/logging/Logger;
       4: getstatic     #3                  // Field FQCN:Ljava/lang/String;
       7: getstatic     #4                  // Field org/jboss/logging/Logger$Level.INFO:Lorg/jboss/logging/Logger$Level;
      10: aconst_null
      11: new           #5                  // class java/lang/StringBuilder
      14: dup
      15: invokespecial #6                  // Method java/lang/StringBuilder."<init>":()V
      18: ldc           #55                 // String OGM000003:
      20: invokevirtual #8                  // Method java/lang/StringBuilder.append:(Ljava/lang/String;)Ljava/lang/StringBuilder;
      23: aload_0
      24: invokevirtual #56                 // Method usingDefaultTransactionFactory$str:()Ljava/lang/String;
      27: invokevirtual #8                  // Method java/lang/StringBuilder.append:(Ljava/lang/String;)Ljava/lang/StringBuilder;
      30: invokevirtual #10                 // Method java/lang/StringBuilder.toString:()Ljava/lang/String;
      33: iconst_0
      34: anewarray     #16                 // class java/lang/Object
      37: invokevirtual #57                 // Method org/jboss/logging/Logger.logf:(Ljava/lang/String;Lorg/jboss/logging/Logger$Level;Ljava/lang/Throwable;Ljava/lang/String;[Ljava/lang/Object;)V
      40: return

  protected java.lang.String usingDefaultTransactionFactory$str();
    Code:
       0: ldc           #58                 // String Use default transaction factory (use a TransactionManager exclusively to pilot the transaction)
       2: areturn

  public final org.hibernate.HibernateException dialectClassCannotBeFound(java.lang.String);
    Code:
       0: new           #13                 // class org/hibernate/HibernateException
       3: dup
       4: new           #5                  // class java/lang/StringBuilder
       7: dup
       8: invokespecial #6                  // Method java/lang/StringBuilder."<init>":()V
      11: ldc           #59                 // String OGM000010:
      13: invokevirtual #8                  // Method java/lang/StringBuilder.append:(Ljava/lang/String;)Ljava/lang/StringBuilder;
      16: aload_0
      17: invokevirtual #60                 // Method dialectClassCannotBeFound$str:()Ljava/lang/String;
      20: invokevirtual #8                  // Method java/lang/StringBuilder.append:(Ljava/lang/String;)Ljava/lang/StringBuilder;
      23: invokevirtual #10                 // Method java/lang/StringBuilder.toString:()Ljava/lang/String;
      26: iconst_1
      27: anewarray     #16                 // class java/lang/Object
      30: dup
      31: iconst_0
      32: aload_1
      33: aastore
      34: invokestatic  #17                 // Method java/lang/String.format:(Ljava/lang/String;[Ljava/lang/Object;)Ljava/lang/String;
      37: invokespecial #18                 // Method org/hibernate/HibernateException."<init>":(Ljava/lang/String;)V
      40: astore_2
      41: aload_2
      42: invokevirtual #19                 // Method org/hibernate/HibernateException.getStackTrace:()[Ljava/lang/StackTraceElement;
      45: astore_3
      46: aload_2
      47: aload_3
      48: iconst_1
      49: aload_3
      50: arraylength
      51: invokestatic  #20                 // Method java/util/Arrays.copyOfRange:([Ljava/lang/Object;II)[Ljava/lang/Object;
      54: checkcast     #21                 // class "[Ljava/lang/StackTraceElement;"
      57: invokevirtual #22                 // Method org/hibernate/HibernateException.setStackTrace:([Ljava/lang/StackTraceElement;)V
      60: aload_2
      61: areturn

  protected java.lang.String dialectClassCannotBeFound$str();
    Code:
       0: ldc           #61                 // String GridDialect class [%1$s] cannot be found in classpath
       2: areturn

  public final org.hibernate.HibernateException gridDialectPropertyOfUnknownType(java.lang.Class);
    Code:
       0: new           #13                 // class org/hibernate/HibernateException
       3: dup
       4: new           #5                  // class java/lang/StringBuilder
       7: dup
       8: invokespecial #6                  // Method java/lang/StringBuilder."<init>":()V
      11: ldc           #62                 // String OGM000012:
      13: invokevirtual #8                  // Method java/lang/StringBuilder.append:(Ljava/lang/String;)Ljava/lang/StringBuilder;
      16: aload_0
      17: invokevirtual #63                 // Method gridDialectPropertyOfUnknownType$str:()Ljava/lang/String;
      20: invokevirtual #8                  // Method java/lang/StringBuilder.append:(Ljava/lang/String;)Ljava/lang/StringBuilder;
      23: invokevirtual #10                 // Method java/lang/StringBuilder.toString:()Ljava/lang/String;
      26: iconst_1
      27: anewarray     #16                 // class java/lang/Object
      30: dup
      31: iconst_0
      32: aload_1
      33: aastore
      34: invokestatic  #17                 // Method java/lang/String.format:(Ljava/lang/String;[Ljava/lang/Object;)Ljava/lang/String;
      37: invokespecial #18                 // Method org/hibernate/HibernateException."<init>":(Ljava/lang/String;)V
      40: astore_2
      41: aload_2
      42: invokevirtual #19                 // Method org/hibernate/HibernateException.getStackTrace:()[Ljava/lang/StackTraceElement;
      45: astore_3
      46: aload_2
      47: aload_3
      48: iconst_1
      49: aload_3
      50: arraylength
      51: invokestatic  #20                 // Method java/util/Arrays.copyOfRange:([Ljava/lang/Object;II)[Ljava/lang/Object;
      54: checkcast     #21                 // class "[Ljava/lang/StackTraceElement;"
      57: invokevirtual #22                 // Method org/hibernate/HibernateException.setStackTrace:([Ljava/lang/StackTraceElement;)V
      60: aload_2
      61: areturn

  protected java.lang.String gridDialectPropertyOfUnknownType$str();
    Code:
       0: ldc           #64                 // String GridDialect property is of unknown type %1$s
       2: areturn

  public final org.hibernate.HibernateException notADatastoreManager(java.lang.String);
    Code:
       0: new           #13                 // class org/hibernate/HibernateException
       3: dup
       4: new           #5                  // class java/lang/StringBuilder
       7: dup
       8: invokespecial #6                  // Method java/lang/StringBuilder."<init>":()V
      11: ldc           #65                 // String OGM000005:
      13: invokevirtual #8                  // Method java/lang/StringBuilder.append:(Ljava/lang/String;)Ljava/lang/StringBuilder;
      16: aload_0
      17: invokevirtual #66                 // Method notADatastoreManager$str:()Ljava/lang/String;
      20: invokevirtual #8                  // Method java/lang/StringBuilder.append:(Ljava/lang/String;)Ljava/lang/StringBuilder;
      23: invokevirtual #10                 // Method java/lang/StringBuilder.toString:()Ljava/lang/String;
      26: iconst_1
      27: anewarray     #16                 // class java/lang/Object
      30: dup
      31: iconst_0
      32: aload_1
      33: aastore
      34: invokestatic  #17                 // Method java/lang/String.format:(Ljava/lang/String;[Ljava/lang/Object;)Ljava/lang/String;
      37: invokespecial #18                 // Method org/hibernate/HibernateException."<init>":(Ljava/lang/String;)V
      40: astore_2
      41: aload_2
      42: invokevirtual #19                 // Method org/hibernate/HibernateException.getStackTrace:()[Ljava/lang/StackTraceElement;
      45: astore_3
      46: aload_2
      47: aload_3
      48: iconst_1
      49: aload_3
      50: arraylength
      51: invokestatic  #20                 // Method java/util/Arrays.copyOfRange:([Ljava/lang/Object;II)[Ljava/lang/Object;
      54: checkcast     #21                 // class "[Ljava/lang/StackTraceElement;"
      57: invokevirtual #22                 // Method org/hibernate/HibernateException.setStackTrace:([Ljava/lang/StackTraceElement;)V
      60: aload_2
      61: areturn

  protected java.lang.String notADatastoreManager$str();
    Code:
       0: ldc           #67                 // String %1$s is not a subclass of DatastoreManager. Update hibernate.ogm.datastore.provider
       2: areturn

  public final org.hibernate.TransactionException jtaCouldNotDetermineStatus(javax.transaction.SystemException);
    Code:
       0: new           #35                 // class org/hibernate/TransactionException
       3: dup
       4: new           #5                  // class java/lang/StringBuilder
       7: dup
       8: invokespecial #6                  // Method java/lang/StringBuilder."<init>":()V
      11: ldc           #68                 // String OGM000022:
      13: invokevirtual #8                  // Method java/lang/StringBuilder.append:(Ljava/lang/String;)Ljava/lang/StringBuilder;
      16: aload_0
      17: invokevirtual #69                 // Method jtaCouldNotDetermineStatus$str:()Ljava/lang/String;
      20: invokevirtual #8                  // Method java/lang/StringBuilder.append:(Ljava/lang/String;)Ljava/lang/StringBuilder;
      23: invokevirtual #10                 // Method java/lang/StringBuilder.toString:()Ljava/lang/String;
      26: iconst_0
      27: anewarray     #16                 // class java/lang/Object
      30: invokestatic  #17                 // Method java/lang/String.format:(Ljava/lang/String;[Ljava/lang/Object;)Ljava/lang/String;
      33: aload_1
      34: invokespecial #38                 // Method org/hibernate/TransactionException."<init>":(Ljava/lang/String;Ljava/lang/Throwable;)V
      37: astore_2
      38: aload_2
      39: invokevirtual #39                 // Method org/hibernate/TransactionException.getStackTrace:()[Ljava/lang/StackTraceElement;
      42: astore_3
      43: aload_2
      44: aload_3
      45: iconst_1
      46: aload_3
      47: arraylength
      48: invokestatic  #20                 // Method java/util/Arrays.copyOfRange:([Ljava/lang/Object;II)[Ljava/lang/Object;
      51: checkcast     #21                 // class "[Ljava/lang/StackTraceElement;"
      54: invokevirtual #40                 // Method org/hibernate/TransactionException.setStackTrace:([Ljava/lang/StackTraceElement;)V
      57: aload_2
      58: areturn

  protected java.lang.String jtaCouldNotDetermineStatus$str();
    Code:
       0: ldc           #70                 // String Could not determine transaction status
       2: areturn

  public final org.hibernate.TransactionException jtaTransactionBeginFailed(java.lang.Exception);
    Code:
       0: new           #35                 // class org/hibernate/TransactionException
       3: dup
       4: new           #5                  // class java/lang/StringBuilder
       7: dup
       8: invokespecial #6                  // Method java/lang/StringBuilder."<init>":()V
      11: ldc           #71                 // String OGM000018:
      13: invokevirtual #8                  // Method java/lang/StringBuilder.append:(Ljava/lang/String;)Ljava/lang/StringBuilder;
      16: aload_0
      17: invokevirtual #72                 // Method jtaTransactionBeginFailed$str:()Ljava/lang/String;
      20: invokevirtual #8                  // Method java/lang/StringBuilder.append:(Ljava/lang/String;)Ljava/lang/StringBuilder;
      23: invokevirtual #10                 // Method java/lang/StringBuilder.toString:()Ljava/lang/String;
      26: iconst_0
      27: anewarray     #16                 // class java/lang/Object
      30: invokestatic  #17                 // Method java/lang/String.format:(Ljava/lang/String;[Ljava/lang/Object;)Ljava/lang/String;
      33: aload_1
      34: invokespecial #38                 // Method org/hibernate/TransactionException."<init>":(Ljava/lang/String;Ljava/lang/Throwable;)V
      37: astore_2
      38: aload_2
      39: invokevirtual #39                 // Method org/hibernate/TransactionException.getStackTrace:()[Ljava/lang/StackTraceElement;
      42: astore_3
      43: aload_2
      44: aload_3
      45: iconst_1
      46: aload_3
      47: arraylength
      48: invokestatic  #20                 // Method java/util/Arrays.copyOfRange:([Ljava/lang/Object;II)[Ljava/lang/Object;
      51: checkcast     #21                 // class "[Ljava/lang/StackTraceElement;"
      54: invokevirtual #40                 // Method org/hibernate/TransactionException.setStackTrace:([Ljava/lang/StackTraceElement;)V
      57: aload_2
      58: areturn

  protected java.lang.String jtaTransactionBeginFailed$str();
    Code:
       0: ldc           #73                 // String JTA transaction begin failed
       2: areturn

  public final org.hibernate.HibernateException unknownDatastoreManagerType(java.lang.String);
    Code:
       0: new           #13                 // class org/hibernate/HibernateException
       3: dup
       4: new           #5                  // class java/lang/StringBuilder
       7: dup
       8: invokespecial #6                  // Method java/lang/StringBuilder."<init>":()V
      11: ldc           #74                 // String OGM000007:
      13: invokevirtual #8                  // Method java/lang/StringBuilder.append:(Ljava/lang/String;)Ljava/lang/StringBuilder;
      16: aload_0
      17: invokevirtual #75                 // Method unknownDatastoreManagerType$str:()Ljava/lang/String;
      20: invokevirtual #8                  // Method java/lang/StringBuilder.append:(Ljava/lang/String;)Ljava/lang/StringBuilder;
      23: invokevirtual #10                 // Method java/lang/StringBuilder.toString:()Ljava/lang/String;
      26: iconst_1
      27: anewarray     #16                 // class java/lang/Object
      30: dup
      31: iconst_0
      32: aload_1
      33: aastore
      34: invokestatic  #17                 // Method java/lang/String.format:(Ljava/lang/String;[Ljava/lang/Object;)Ljava/lang/String;
      37: invokespecial #18                 // Method org/hibernate/HibernateException."<init>":(Ljava/lang/String;)V
      40: astore_2
      41: aload_2
      42: invokevirtual #19                 // Method org/hibernate/HibernateException.getStackTrace:()[Ljava/lang/StackTraceElement;
      45: astore_3
      46: aload_2
      47: aload_3
      48: iconst_1
      49: aload_3
      50: arraylength
      51: invokestatic  #20                 // Method java/util/Arrays.copyOfRange:([Ljava/lang/Object;II)[Ljava/lang/Object;
      54: checkcast     #21                 // class "[Ljava/lang/StackTraceElement;"
      57: invokevirtual #22                 // Method org/hibernate/HibernateException.setStackTrace:([Ljava/lang/StackTraceElement;)V
      60: aload_2
      61: areturn

  protected java.lang.String unknownDatastoreManagerType$str();
    Code:
       0: ldc           #76                 // String DatastoreManager property is of unknown type %1$s
       2: areturn

  public final void version(java.lang.String);
    Code:
       0: aload_0
       1: getfield      #2                  // Field org/jboss/logging/DelegatingBasicLogger.log:Lorg/jboss/logging/Logger;
       4: getstatic     #3                  // Field FQCN:Ljava/lang/String;
       7: getstatic     #4                  // Field org/jboss/logging/Logger$Level.INFO:Lorg/jboss/logging/Logger$Level;
      10: aconst_null
      11: new           #5                  // class java/lang/StringBuilder
      14: dup
      15: invokespecial #6                  // Method java/lang/StringBuilder."<init>":()V
      18: ldc           #77                 // String OGM000001:
      20: invokevirtual #8                  // Method java/lang/StringBuilder.append:(Ljava/lang/String;)Ljava/lang/StringBuilder;
      23: aload_0
      24: invokevirtual #78                 // Method version$str:()Ljava/lang/String;
      27: invokevirtual #8                  // Method java/lang/StringBuilder.append:(Ljava/lang/String;)Ljava/lang/StringBuilder;
      30: invokevirtual #10                 // Method java/lang/StringBuilder.toString:()Ljava/lang/String;
      33: aload_1
      34: invokevirtual #11                 // Method org/jboss/logging/Logger.logf:(Ljava/lang/String;Lorg/jboss/logging/Logger$Level;Ljava/lang/Throwable;Ljava/lang/String;Ljava/lang/Object;)V
      37: return

  protected java.lang.String version$str();
    Code:
       0: ldc           #79                 // String Hibernate OGM %1$s
       2: areturn

  public final org.hibernate.HibernateException doesNotImplementGridDialect(java.lang.String);
    Code:
       0: new           #13                 // class org/hibernate/HibernateException
       3: dup
       4: new           #5                  // class java/lang/StringBuilder
       7: dup
       8: invokespecial #6                  // Method java/lang/StringBuilder."<init>":()V
      11: ldc           #80                 // String OGM000013:
      13: invokevirtual #8                  // Method java/lang/StringBuilder.append:(Ljava/lang/String;)Ljava/lang/StringBuilder;
      16: aload_0
      17: invokevirtual #81                 // Method doesNotImplementGridDialect$str:()Ljava/lang/String;
      20: invokevirtual #8                  // Method java/lang/StringBuilder.append:(Ljava/lang/String;)Ljava/lang/StringBuilder;
      23: invokevirtual #10                 // Method java/lang/StringBuilder.toString:()Ljava/lang/String;
      26: iconst_1
      27: anewarray     #16                 // class java/lang/Object
      30: dup
      31: iconst_0
      32: aload_1
      33: aastore
      34: invokestatic  #17                 // Method java/lang/String.format:(Ljava/lang/String;[Ljava/lang/Object;)Ljava/lang/String;
      37: invokespecial #18                 // Method org/hibernate/HibernateException."<init>":(Ljava/lang/String;)V
      40: astore_2
      41: aload_2
      42: invokevirtual #19                 // Method org/hibernate/HibernateException.getStackTrace:()[Ljava/lang/StackTraceElement;
      45: astore_3
      46: aload_2
      47: aload_3
      48: iconst_1
      49: aload_3
      50: arraylength
      51: invokestatic  #20                 // Method java/util/Arrays.copyOfRange:([Ljava/lang/Object;II)[Ljava/lang/Object;
      54: checkcast     #21                 // class "[Ljava/lang/StackTraceElement;"
      57: invokevirtual #22                 // Method org/hibernate/HibernateException.setStackTrace:([Ljava/lang/StackTraceElement;)V
      60: aload_2
      61: areturn

  protected java.lang.String doesNotImplementGridDialect$str();
    Code:
       0: ldc           #82                 // String %1$s property does not implement GridDialect interface
       2: areturn

  public final org.hibernate.TransactionException unableToMarkTransactionForRollback(java.lang.Exception);
    Code:
       0: new           #35                 // class org/hibernate/TransactionException
       3: dup
       4: new           #5                  // class java/lang/StringBuilder
       7: dup
       8: invokespecial #6                  // Method java/lang/StringBuilder."<init>":()V
      11: ldc           #83                 // String OGM000021:
      13: invokevirtual #8                  // Method java/lang/StringBuilder.append:(Ljava/lang/String;)Ljava/lang/StringBuilder;
      16: aload_0
      17: invokevirtual #84                 // Method unableToMarkTransactionForRollback$str:()Ljava/lang/String;
      20: invokevirtual #8                  // Method java/lang/StringBuilder.append:(Ljava/lang/String;)Ljava/lang/StringBuilder;
      23: invokevirtual #10                 // Method java/lang/StringBuilder.toString:()Ljava/lang/String;
      26: iconst_0
      27: anewarray     #16                 // class java/lang/Object
      30: invokestatic  #17                 // Method java/lang/String.format:(Ljava/lang/String;[Ljava/lang/Object;)Ljava/lang/String;
      33: aload_1
      34: invokespecial #38                 // Method org/hibernate/TransactionException."<init>":(Ljava/lang/String;Ljava/lang/Throwable;)V
      37: astore_2
      38: aload_2
      39: invokevirtual #39                 // Method org/hibernate/TransactionException.getStackTrace:()[Ljava/lang/StackTraceElement;
      42: astore_3
      43: aload_2
      44: aload_3
      45: iconst_1
      46: aload_3
      47: arraylength
      48: invokestatic  #20                 // Method java/util/Arrays.copyOfRange:([Ljava/lang/Object;II)[Ljava/lang/Object;
      51: checkcast     #21                 // class "[Ljava/lang/StackTraceElement;"
      54: invokevirtual #40                 // Method org/hibernate/TransactionException.setStackTrace:([Ljava/lang/StackTraceElement;)V
      57: aload_2
      58: areturn

  protected java.lang.String unableToMarkTransactionForRollback$str();
    Code:
       0: ldc           #85                 // String Unable to mark JTA transaction for rollback
       2: areturn

  public final org.hibernate.HibernateException gridDialectHasNoProperConstrutor(java.lang.Class);
    Code:
       0: new           #13                 // class org/hibernate/HibernateException
       3: dup
       4: new           #5                  // class java/lang/StringBuilder
       7: dup
       8: invokespecial #6                  // Method java/lang/StringBuilder."<init>":()V
      11: ldc           #86                 // String OGM000014:
      13: invokevirtual #8                  // Method java/lang/StringBuilder.append:(Ljava/lang/String;)Ljava/lang/StringBuilder;
      16: aload_0
      17: invokevirtual #87                 // Method gridDialectHasNoProperConstrutor$str:()Ljava/lang/String;
      20: invokevirtual #8                  // Method java/lang/StringBuilder.append:(Ljava/lang/String;)Ljava/lang/StringBuilder;
      23: invokevirtual #10                 // Method java/lang/StringBuilder.toString:()Ljava/lang/String;
      26: iconst_1
      27: anewarray     #16                 // class java/lang/Object
      30: dup
      31: iconst_0
      32: aload_1
      33: aastore
      34: invokestatic  #17                 // Method java/lang/String.format:(Ljava/lang/String;[Ljava/lang/Object;)Ljava/lang/String;
      37: invokespecial #18                 // Method org/hibernate/HibernateException."<init>":(Ljava/lang/String;)V
      40: astore_2
      41: aload_2
      42: invokevirtual #19                 // Method org/hibernate/HibernateException.getStackTrace:()[Ljava/lang/StackTraceElement;
      45: astore_3
      46: aload_2
      47: aload_3
      48: iconst_1
      49: aload_3
      50: arraylength
      51: invokestatic  #20                 // Method java/util/Arrays.copyOfRange:([Ljava/lang/Object;II)[Ljava/lang/Object;
      54: checkcast     #21                 // class "[Ljava/lang/StackTraceElement;"
      57: invokevirtual #22                 // Method org/hibernate/HibernateException.setStackTrace:([Ljava/lang/StackTraceElement;)V
      60: aload_2
      61: areturn

  protected java.lang.String gridDialectHasNoProperConstrutor$str();
    Code:
       0: ldc           #88                 // String %1$s has no constructor accepting DatasourceProvider
       2: areturn

  public final org.hibernate.HibernateException unableToInstantiateDatastoreManager(java.lang.String, java.lang.Exception);
    Code:
       0: new           #13                 // class org/hibernate/HibernateException
       3: dup
       4: new           #5                  // class java/lang/StringBuilder
       7: dup
       8: invokespecial #6                  // Method java/lang/StringBuilder."<init>":()V
      11: ldc           #89                 // String OGM000006:
      13: invokevirtual #8                  // Method java/lang/StringBuilder.append:(Ljava/lang/String;)Ljava/lang/StringBuilder;
      16: aload_0
      17: invokevirtual #90                 // Method unableToInstantiateDatastoreManager$str:()Ljava/lang/String;
      20: invokevirtual #8                  // Method java/lang/StringBuilder.append:(Ljava/lang/String;)Ljava/lang/StringBuilder;
      23: invokevirtual #10                 // Method java/lang/StringBuilder.toString:()Ljava/lang/String;
      26: iconst_1
      27: anewarray     #16                 // class java/lang/Object
      30: dup
      31: iconst_0
      32: aload_1
      33: aastore
      34: invokestatic  #17                 // Method java/lang/String.format:(Ljava/lang/String;[Ljava/lang/Object;)Ljava/lang/String;
      37: aload_2
      38: invokespecial #33                 // Method org/hibernate/HibernateException."<init>":(Ljava/lang/String;Ljava/lang/Throwable;)V
      41: astore_3
      42: aload_3
      43: invokevirtual #19                 // Method org/hibernate/HibernateException.getStackTrace:()[Ljava/lang/StackTraceElement;
      46: astore        4
      48: aload_3
      49: aload         4
      51: iconst_1
      52: aload         4
      54: arraylength
      55: invokestatic  #20                 // Method java/util/Arrays.copyOfRange:([Ljava/lang/Object;II)[Ljava/lang/Object;
      58: checkcast     #21                 // class "[Ljava/lang/StackTraceElement;"
      61: invokevirtual #22                 // Method org/hibernate/HibernateException.setStackTrace:([Ljava/lang/StackTraceElement;)V
      64: aload_3
      65: areturn

  protected java.lang.String unableToInstantiateDatastoreManager$str();
    Code:
       0: ldc           #91                 // String Cannot instantiate DatastoreManager %1$s
       2: areturn

  public final org.hibernate.HibernateException datastoreClassCannotBeFound(java.lang.String, java.lang.String);
    Code:
       0: new           #13                 // class org/hibernate/HibernateException
       3: dup
       4: new           #5                  // class java/lang/StringBuilder
       7: dup
       8: invokespecial #6                  // Method java/lang/StringBuilder."<init>":()V
      11: ldc           #92                 // String OGM000008:
      13: invokevirtual #8                  // Method java/lang/StringBuilder.append:(Ljava/lang/String;)Ljava/lang/StringBuilder;
      16: aload_0
      17: invokevirtual #93                 // Method datastoreClassCannotBeFound$str:()Ljava/lang/String;
      20: invokevirtual #8                  // Method java/lang/StringBuilder.append:(Ljava/lang/String;)Ljava/lang/StringBuilder;
      23: invokevirtual #10                 // Method java/lang/StringBuilder.toString:()Ljava/lang/String;
      26: iconst_2
      27: anewarray     #16                 // class java/lang/Object
      30: dup
      31: iconst_0
      32: aload_1
      33: aastore
      34: dup
      35: iconst_1
      36: aload_2
      37: aastore
      38: invokestatic  #17                 // Method java/lang/String.format:(Ljava/lang/String;[Ljava/lang/Object;)Ljava/lang/String;
      41: invokespecial #18                 // Method org/hibernate/HibernateException."<init>":(Ljava/lang/String;)V
      44: astore_3
      45: aload_3
      46: invokevirtual #19                 // Method org/hibernate/HibernateException.getStackTrace:()[Ljava/lang/StackTraceElement;
      49: astore        4
      51: aload_3
      52: aload         4
      54: iconst_1
      55: aload         4
      57: arraylength
      58: invokestatic  #20                 // Method java/util/Arrays.copyOfRange:([Ljava/lang/Object;II)[Ljava/lang/Object;
      61: checkcast     #21                 // class "[Ljava/lang/StackTraceElement;"
      64: invokevirtual #22                 // Method org/hibernate/HibernateException.setStackTrace:([Ljava/lang/StackTraceElement;)V
      67: aload_3
      68: areturn

  protected java.lang.String datastoreClassCannotBeFound$str();
    Code:
       0: ldc           #94                 // String DatastoreManager class [%1$s] cannot be found in classpath try with: %2$s
       2: areturn

  public final org.hibernate.HibernateException cannotInstantiateGridDialect(java.lang.Class, java.lang.Exception);
    Code:
       0: new           #13                 // class org/hibernate/HibernateException
       3: dup
       4: new           #5                  // class java/lang/StringBuilder
       7: dup
       8: invokespecial #6                  // Method java/lang/StringBuilder."<init>":()V
      11: ldc           #95                 // String OGM000011:
      13: invokevirtual #8                  // Method java/lang/StringBuilder.append:(Ljava/lang/String;)Ljava/lang/StringBuilder;
      16: aload_0
      17: invokevirtual #96                 // Method cannotInstantiateGridDialect$str:()Ljava/lang/String;
      20: invokevirtual #8                  // Method java/lang/StringBuilder.append:(Ljava/lang/String;)Ljava/lang/StringBuilder;
      23: invokevirtual #10                 // Method java/lang/StringBuilder.toString:()Ljava/lang/String;
      26: iconst_1
      27: anewarray     #16                 // class java/lang/Object
      30: dup
      31: iconst_0
      32: aload_1
      33: aastore
      34: invokestatic  #17                 // Method java/lang/String.format:(Ljava/lang/String;[Ljava/lang/Object;)Ljava/lang/String;
      37: aload_2
      38: invokespecial #33                 // Method org/hibernate/HibernateException."<init>":(Ljava/lang/String;Ljava/lang/Throwable;)V
      41: astore_3
      42: aload_3
      43: invokevirtual #19                 // Method org/hibernate/HibernateException.getStackTrace:()[Ljava/lang/StackTraceElement;
      46: astore        4
      48: aload_3
      49: aload         4
      51: iconst_1
      52: aload         4
      54: arraylength
      55: invokestatic  #20                 // Method java/util/Arrays.copyOfRange:([Ljava/lang/Object;II)[Ljava/lang/Object;
      58: checkcast     #21                 // class "[Ljava/lang/StackTraceElement;"
      61: invokevirtual #22                 // Method org/hibernate/HibernateException.setStackTrace:([Ljava/lang/StackTraceElement;)V
      64: aload_3
      65: areturn

  protected java.lang.String cannotInstantiateGridDialect$str();
    Code:
       0: ldc           #97                 // String Cannot instantiate GridDialect class [%1$s]
       2: areturn

  static {};
    Code:
       0: ldc_w         #98                 // class org/hibernate/ogm/util/impl/Log_$logger
       3: invokevirtual #99                 // Method java/lang/Class.getName:()Ljava/lang/String;
       6: putstatic     #3                  // Field FQCN:Ljava/lang/String;
       9: return
}
