Compiled from "AuthUserGetResponse.java"
public class io.etcd.jetcd.auth.AuthUserGetResponse extends io.etcd.jetcd.AbstractResponse<io.etcd.jetcd.api.AuthUserGetResponse> {
  public io.etcd.jetcd.auth.AuthUserGetResponse(io.etcd.jetcd.api.AuthUserGetResponse);
    Code:
       0: aload_0
       1: aload_1
       2: aload_1
       3: invokevirtual #1                  // Method io/etcd/jetcd/api/AuthUserGetResponse.getHeader:()Lio/etcd/jetcd/api/ResponseHeader;
       6: invokespecial #2                  // Method io/etcd/jetcd/AbstractResponse."<init>":(Ljava/lang/Object;Lio/etcd/jetcd/api/ResponseHeader;)V
       9: return

  public java.util.List<java.lang.String> getRoles();
    Code:
       0: aload_0
       1: invokevirtual #3                  // Method getResponse:()Ljava/lang/Object;
       4: checkcast     #4                  // class io/etcd/jetcd/api/AuthUserGetResponse
       7: invokevirtual #5                  // Method io/etcd/jetcd/api/AuthUserGetResponse.getRolesList:()Lcom/google/protobuf/ProtocolStringList;
      10: areturn
}
