Compiled from "AuthInterceptor.java"
class io.etcd.jetcd.auth.AuthInterceptor$1 extends io.grpc.ForwardingClientCall$SimpleForwardingClientCall<ReqT, RespT> {
  final io.grpc.Channel val$next;

  final io.etcd.jetcd.auth.AuthInterceptor this$0;

  io.etcd.jetcd.auth.AuthInterceptor$1(io.etcd.jetcd.auth.AuthInterceptor, io.grpc.ClientCall, io.grpc.Channel);
    Code:
       0: aload_0
       1: aload_1
       2: putfield      #1                  // Field this$0:Lio/etcd/jetcd/auth/AuthInterceptor;
       5: aload_0
       6: aload_3
       7: putfield      #2                  // Field val$next:Lio/grpc/Channel;
      10: aload_0
      11: aload_2
      12: invokespecial #3                  // Method io/grpc/ForwardingClientCall$SimpleForwardingClientCall."<init>":(Lio/grpc/ClientCall;)V
      15: return

  public void start(io.grpc.ClientCall$Listener<RespT>, io.grpc.Metadata);
    Code:
       0: aload_0
       1: getfield      #1                  // Field this$0:Lio/etcd/jetcd/auth/AuthInterceptor;
       4: aload_0
       5: getfield      #2                  // Field val$next:Lio/grpc/Channel;
       8: invokestatic  #4                  // Method io/etcd/jetcd/auth/AuthInterceptor.access$000:(Lio/etcd/jetcd/auth/AuthInterceptor;Lio/grpc/Channel;)Ljava/lang/String;
      11: astore_3
      12: aload_3
      13: ifnull        24
      16: aload_2
      17: invokestatic  #5                  // Method io/etcd/jetcd/auth/AuthInterceptor.access$100:()Lio/grpc/Metadata$Key;
      20: aload_3
      21: invokevirtual #6                  // Method io/grpc/Metadata.put:(Lio/grpc/Metadata$Key;Ljava/lang/Object;)V
      24: aload_0
      25: new           #7                  // class io/etcd/jetcd/auth/AuthInterceptor$1$1
      28: dup
      29: aload_0
      30: aload_1
      31: invokespecial #8                  // Method io/etcd/jetcd/auth/AuthInterceptor$1$1."<init>":(Lio/etcd/jetcd/auth/AuthInterceptor$1;Lio/grpc/ClientCall$Listener;)V
      34: aload_2
      35: invokespecial #9                  // Method io/grpc/ForwardingClientCall$SimpleForwardingClientCall.start:(Lio/grpc/ClientCall$Listener;Lio/grpc/Metadata;)V
      38: return
}
