Compiled from "WstxException.java"
public class com.ctc.wstx.exc.WstxException extends javax.xml.stream.XMLStreamException {
  private static final long serialVersionUID;

  protected final java.lang.String mMsg;

  public com.ctc.wstx.exc.WstxException(java.lang.String);
    Code:
       0: aload_0
       1: aload_1
       2: invokespecial #1                  // Method javax/xml/stream/XMLStreamException."<init>":(Ljava/lang/String;)V
       5: aload_0
       6: aload_1
       7: putfield      #2                  // Field mMsg:Ljava/lang/String;
      10: return

  public com.ctc.wstx.exc.WstxException(java.lang.Throwable);
    Code:
       0: aload_0
       1: aload_1
       2: invokevirtual #3                  // Method java/lang/Throwable.getMessage:()Ljava/lang/String;
       5: aload_1
       6: invokespecial #4                  // Method javax/xml/stream/XMLStreamException."<init>":(Ljava/lang/String;Ljava/lang/Throwable;)V
       9: aload_0
      10: aload_1
      11: invokevirtual #3                  // Method java/lang/Throwable.getMessage:()Ljava/lang/String;
      14: putfield      #2                  // Field mMsg:Ljava/lang/String;
      17: aload_0
      18: aload_1
      19: invokestatic  #5                  // Method com/ctc/wstx/util/ExceptionUtil.setInitCause:(Ljava/lang/Throwable;Ljava/lang/Throwable;)V
      22: return

  public com.ctc.wstx.exc.WstxException(java.lang.String, javax.xml.stream.Location);
    Code:
       0: aload_0
       1: aload_1
       2: aload_2
       3: invokespecial #6                  // Method javax/xml/stream/XMLStreamException."<init>":(Ljava/lang/String;Ljavax/xml/stream/Location;)V
       6: aload_0
       7: aload_1
       8: putfield      #2                  // Field mMsg:Ljava/lang/String;
      11: return

  public com.ctc.wstx.exc.WstxException(java.lang.String, javax.xml.stream.Location, java.lang.Throwable);
    Code:
       0: aload_0
       1: aload_1
       2: aload_2
       3: aload_3
       4: invokespecial #7                  // Method javax/xml/stream/XMLStreamException."<init>":(Ljava/lang/String;Ljavax/xml/stream/Location;Ljava/lang/Throwable;)V
       7: aload_0
       8: aload_1
       9: putfield      #2                  // Field mMsg:Ljava/lang/String;
      12: aload_0
      13: aload_3
      14: invokestatic  #5                  // Method com/ctc/wstx/util/ExceptionUtil.setInitCause:(Ljava/lang/Throwable;Ljava/lang/Throwable;)V
      17: return

  public java.lang.String getMessage();
    Code:
       0: aload_0
       1: invokevirtual #8                  // Method getLocationDesc:()Ljava/lang/String;
       4: astore_1
       5: aload_1
       6: ifnonnull     14
       9: aload_0
      10: invokespecial #9                  // Method javax/xml/stream/XMLStreamException.getMessage:()Ljava/lang/String;
      13: areturn
      14: new           #10                 // class java/lang/StringBuffer
      17: dup
      18: aload_0
      19: getfield      #2                  // Field mMsg:Ljava/lang/String;
      22: invokevirtual #11                 // Method java/lang/String.length:()I
      25: aload_1
      26: invokevirtual #11                 // Method java/lang/String.length:()I
      29: iadd
      30: bipush        20
      32: iadd
      33: invokespecial #12                 // Method java/lang/StringBuffer."<init>":(I)V
      36: astore_2
      37: aload_2
      38: aload_0
      39: getfield      #2                  // Field mMsg:Ljava/lang/String;
      42: invokevirtual #13                 // Method java/lang/StringBuffer.append:(Ljava/lang/String;)Ljava/lang/StringBuffer;
      45: pop
      46: aload_2
      47: invokestatic  #14                 // Method com/ctc/wstx/util/StringUtil.appendLF:(Ljava/lang/StringBuffer;)V
      50: aload_2
      51: ldc           #15                 // String  at
      53: invokevirtual #13                 // Method java/lang/StringBuffer.append:(Ljava/lang/String;)Ljava/lang/StringBuffer;
      56: pop
      57: aload_2
      58: aload_1
      59: invokevirtual #13                 // Method java/lang/StringBuffer.append:(Ljava/lang/String;)Ljava/lang/StringBuffer;
      62: pop
      63: aload_2
      64: invokevirtual #16                 // Method java/lang/StringBuffer.toString:()Ljava/lang/String;
      67: areturn

  public java.lang.String toString();
    Code:
       0: new           #10                 // class java/lang/StringBuffer
       3: dup
       4: invokespecial #17                 // Method java/lang/StringBuffer."<init>":()V
       7: aload_0
       8: invokevirtual #18                 // Method java/lang/Object.getClass:()Ljava/lang/Class;
      11: invokevirtual #19                 // Method java/lang/Class.getName:()Ljava/lang/String;
      14: invokevirtual #13                 // Method java/lang/StringBuffer.append:(Ljava/lang/String;)Ljava/lang/StringBuffer;
      17: ldc           #20                 // String :
      19: invokevirtual #13                 // Method java/lang/StringBuffer.append:(Ljava/lang/String;)Ljava/lang/StringBuffer;
      22: aload_0
      23: invokevirtual #21                 // Method getMessage:()Ljava/lang/String;
      26: invokevirtual #13                 // Method java/lang/StringBuffer.append:(Ljava/lang/String;)Ljava/lang/StringBuffer;
      29: invokevirtual #16                 // Method java/lang/StringBuffer.toString:()Ljava/lang/String;
      32: areturn

  protected java.lang.String getLocationDesc();
    Code:
       0: aload_0
       1: invokevirtual #22                 // Method getLocation:()Ljavax/xml/stream/Location;
       4: astore_1
       5: aload_1
       6: ifnonnull     13
       9: aconst_null
      10: goto          17
      13: aload_1
      14: invokevirtual #23                 // Method java/lang/Object.toString:()Ljava/lang/String;
      17: areturn
}
