Compiled from "BootstrapImpl.java"
class org.jboss.as.server.BootstrapImpl$ShutdownHook extends java.lang.Thread {
  private boolean down;

  private org.jboss.as.controller.ControlledProcessState processState;

  private org.jboss.msc.service.ServiceContainer container;

  private org.jboss.as.server.BootstrapImpl$ShutdownHook();
    Code:
       0: aload_0
       1: invokespecial #6                  // Method java/lang/Thread."<init>":()V
       4: return

  private org.jboss.msc.service.ServiceContainer register();
    Code:
       0: invokestatic  #7                  // Method java/lang/Runtime.getRuntime:()Ljava/lang/Runtime;
       3: aload_0
       4: invokevirtual #8                  // Method java/lang/Runtime.addShutdownHook:(Ljava/lang/Thread;)V
       7: aload_0
       8: dup
       9: astore_1
      10: monitorenter
      11: aload_0
      12: getfield      #3                  // Field down:Z
      15: ifne          44
      18: aload_0
      19: ldc           #9                  // String jboss-as
      21: invokestatic  #10                 // Method org/jboss/as/server/BootstrapImpl.access$600:()I
      24: ldc2_w        #11                 // long 30l
      27: getstatic     #13                 // Field java/util/concurrent/TimeUnit.SECONDS:Ljava/util/concurrent/TimeUnit;
      30: iconst_0
      31: invokestatic  #14                 // Method org/jboss/msc/service/ServiceContainer$Factory.create:(Ljava/lang/String;IJLjava/util/concurrent/TimeUnit;Z)Lorg/jboss/msc/service/ServiceContainer;
      34: putfield      #15                 // Field container:Lorg/jboss/msc/service/ServiceContainer;
      37: aload_0
      38: getfield      #15                 // Field container:Lorg/jboss/msc/service/ServiceContainer;
      41: aload_1
      42: monitorexit
      43: areturn
      44: new           #16                 // class java/lang/IllegalStateException
      47: dup
      48: invokespecial #17                 // Method java/lang/IllegalStateException."<init>":()V
      51: athrow
      52: astore_2
      53: aload_1
      54: monitorexit
      55: aload_2
      56: athrow
    Exception table:
       from    to  target type
          11    43    52   any
          44    55    52   any

  private synchronized void setControlledProcessState(org.jboss.as.controller.ControlledProcessState);
    Code:
       0: aload_0
       1: aload_1
       2: putfield      #18                 // Field processState:Lorg/jboss/as/controller/ControlledProcessState;
       5: return

  public void run();
    Code:
       0: aload_0
       1: iconst_0
       2: invokespecial #2                  // Method shutdown:(Z)V
       5: return

  private void shutdown(boolean);
    Code:
       0: aload_0
       1: dup
       2: astore        4
       4: monitorenter
       5: aload_0
       6: iconst_1
       7: putfield      #3                  // Field down:Z
      10: aload_0
      11: getfield      #15                 // Field container:Lorg/jboss/msc/service/ServiceContainer;
      14: astore_2
      15: aload_0
      16: getfield      #18                 // Field processState:Lorg/jboss/as/controller/ControlledProcessState;
      19: astore_3
      20: aload         4
      22: monitorexit
      23: goto          34
      26: astore        5
      28: aload         4
      30: monitorexit
      31: aload         5
      33: athrow
      34: aload_3
      35: ifnull        42
      38: aload_3
      39: invokevirtual #19                 // Method org/jboss/as/controller/ControlledProcessState.setStopping:()V
      42: aload_2
      43: ifnull        190
      46: aload_2
      47: invokeinterface #20,  1           // InterfaceMethod org/jboss/msc/service/ServiceContainer.isShutdownComplete:()Z
      52: ifne          190
      55: iload_1
      56: ifne          67
      59: getstatic     #21                 // Field org/jboss/as/server/logging/ServerLogger.ROOT_LOGGER:Lorg/jboss/as/server/logging/ServerLogger;
      62: invokeinterface #22,  1           // InterfaceMethod org/jboss/as/server/logging/ServerLogger.shutdownHookInvoked:()V
      67: new           #23                 // class java/util/concurrent/CountDownLatch
      70: dup
      71: iconst_1
      72: invokespecial #24                 // Method java/util/concurrent/CountDownLatch."<init>":(I)V
      75: astore        4
      77: aload_2
      78: new           #25                 // class org/jboss/as/server/BootstrapImpl$ShutdownHook$1
      81: dup
      82: aload_0
      83: aload         4
      85: invokespecial #26                 // Method org/jboss/as/server/BootstrapImpl$ShutdownHook$1."<init>":(Lorg/jboss/as/server/BootstrapImpl$ShutdownHook;Ljava/util/concurrent/CountDownLatch;)V
      88: invokeinterface #27,  2           // InterfaceMethod org/jboss/msc/service/ServiceContainer.addTerminateListener:(Lorg/jboss/msc/service/ServiceContainer$TerminateListener;)V
      93: aload_2
      94: invokeinterface #28,  1           // InterfaceMethod org/jboss/msc/service/ServiceContainer.shutdown:()V
      99: aload         4
     101: invokevirtual #29                 // Method java/util/concurrent/CountDownLatch.await:()V
     104: goto          112
     107: astore        5
     109: goto          99
     112: goto          190
     115: astore        6
     117: aload_2
     118: ifnull        187
     121: aload_2
     122: invokeinterface #20,  1           // InterfaceMethod org/jboss/msc/service/ServiceContainer.isShutdownComplete:()Z
     127: ifne          187
     130: iload_1
     131: ifne          142
     134: getstatic     #21                 // Field org/jboss/as/server/logging/ServerLogger.ROOT_LOGGER:Lorg/jboss/as/server/logging/ServerLogger;
     137: invokeinterface #22,  1           // InterfaceMethod org/jboss/as/server/logging/ServerLogger.shutdownHookInvoked:()V
     142: new           #23                 // class java/util/concurrent/CountDownLatch
     145: dup
     146: iconst_1
     147: invokespecial #24                 // Method java/util/concurrent/CountDownLatch."<init>":(I)V
     150: astore        7
     152: aload_2
     153: new           #25                 // class org/jboss/as/server/BootstrapImpl$ShutdownHook$1
     156: dup
     157: aload_0
     158: aload         7
     160: invokespecial #26                 // Method org/jboss/as/server/BootstrapImpl$ShutdownHook$1."<init>":(Lorg/jboss/as/server/BootstrapImpl$ShutdownHook;Ljava/util/concurrent/CountDownLatch;)V
     163: invokeinterface #27,  2           // InterfaceMethod org/jboss/msc/service/ServiceContainer.addTerminateListener:(Lorg/jboss/msc/service/ServiceContainer$TerminateListener;)V
     168: aload_2
     169: invokeinterface #28,  1           // InterfaceMethod org/jboss/msc/service/ServiceContainer.shutdown:()V
     174: aload         7
     176: invokevirtual #29                 // Method java/util/concurrent/CountDownLatch.await:()V
     179: goto          187
     182: astore        8
     184: goto          174
     187: aload         6
     189: athrow
     190: return
    Exception table:
       from    to  target type
           5    23    26   any
          26    31    26   any
          99   104   107   Class java/lang/InterruptedException
          34    42   115   any
         174   179   182   Class java/lang/InterruptedException
         115   117   115   any

  org.jboss.as.server.BootstrapImpl$ShutdownHook(org.jboss.as.server.BootstrapImpl$1);
    Code:
       0: aload_0
       1: invokespecial #5                  // Method "<init>":()V
       4: return

  static org.jboss.msc.service.ServiceContainer access$100(org.jboss.as.server.BootstrapImpl$ShutdownHook);
    Code:
       0: aload_0
       1: invokespecial #4                  // Method register:()Lorg/jboss/msc/service/ServiceContainer;
       4: areturn

  static boolean access$200(org.jboss.as.server.BootstrapImpl$ShutdownHook);
    Code:
       0: aload_0
       1: getfield      #3                  // Field down:Z
       4: ireturn

  static void access$300(org.jboss.as.server.BootstrapImpl$ShutdownHook, boolean);
    Code:
       0: aload_0
       1: iload_1
       2: invokespecial #2                  // Method shutdown:(Z)V
       5: return

  static void access$400(org.jboss.as.server.BootstrapImpl$ShutdownHook, org.jboss.as.controller.ControlledProcessState);
    Code:
       0: aload_0
       1: aload_1
       2: invokespecial #1                  // Method setControlledProcessState:(Lorg/jboss/as/controller/ControlledProcessState;)V
       5: return
}
