Compiled from "ServerEnvironmentResourceDescription.java"
public class org.jboss.as.server.ServerEnvironmentResourceDescription extends org.jboss.as.controller.SimpleResourceDefinition {
  public static final org.jboss.as.controller.PathElement RESOURCE_PATH;

  public static final org.jboss.as.controller.AttributeDefinition BASE_DIR;

  public static final org.jboss.as.controller.AttributeDefinition CONFIG_DIR;

  public static final org.jboss.as.controller.AttributeDefinition CONFIG_FILE;

  public static final org.jboss.as.controller.AttributeDefinition CONTENT_DIR;

  public static final org.jboss.as.controller.AttributeDefinition DATA_DIR;

  public static final org.jboss.as.controller.AttributeDefinition DEPLOY_DIR;

  public static final org.jboss.as.controller.AttributeDefinition EXT_DIRS;

  public static final org.jboss.as.controller.AttributeDefinition HOME_DIR;

  public static final org.jboss.as.controller.AttributeDefinition HOST_NAME;

  public static final org.jboss.as.controller.AttributeDefinition INITIAL_RUNNING_MODE;

  public static final org.jboss.as.controller.AttributeDefinition LAUNCH_TYPE;

  public static final org.jboss.as.controller.AttributeDefinition LOG_DIR;

  public static final org.jboss.as.controller.AttributeDefinition MODULES_DIR;

  public static final org.jboss.as.controller.AttributeDefinition NODE_NAME;

  public static final org.jboss.as.controller.AttributeDefinition QUALIFIED_HOST_NAME;

  public static final org.jboss.as.controller.AttributeDefinition SERVER_NAME;

  public static final org.jboss.as.controller.AttributeDefinition TEMP_DIR;

  public static final org.jboss.as.controller.AttributeDefinition[] SERVER_ENV_ATTRIBUTES;

  private final org.jboss.as.server.ServerEnvironmentResourceDescription$ServerEnvironmentReadHandler osh;

  private org.jboss.as.server.ServerEnvironmentResourceDescription(org.jboss.as.server.ServerEnvironment);
    Code:
       0: aload_0
       1: getstatic     #2                  // Field RESOURCE_PATH:Lorg/jboss/as/controller/PathElement;
       4: iconst_1
       5: anewarray     #3                  // class java/lang/String
       8: dup
       9: iconst_0
      10: ldc           #4                  // String server.env
      12: aastore
      13: invokestatic  #5                  // Method org/jboss/as/server/controller/descriptions/ServerDescriptions.getResourceDescriptionResolver:([Ljava/lang/String;)Lorg/jboss/as/controller/descriptions/ResourceDescriptionResolver;
      16: invokespecial #6                  // Method org/jboss/as/controller/SimpleResourceDefinition."<init>":(Lorg/jboss/as/controller/PathElement;Lorg/jboss/as/controller/descriptions/ResourceDescriptionResolver;)V
      19: aload_0
      20: new           #7                  // class org/jboss/as/server/ServerEnvironmentResourceDescription$ServerEnvironmentReadHandler
      23: dup
      24: aload_1
      25: invokespecial #8                  // Method org/jboss/as/server/ServerEnvironmentResourceDescription$ServerEnvironmentReadHandler."<init>":(Lorg/jboss/as/server/ServerEnvironment;)V
      28: putfield      #9                  // Field osh:Lorg/jboss/as/server/ServerEnvironmentResourceDescription$ServerEnvironmentReadHandler;
      31: return

  public static org.jboss.as.server.ServerEnvironmentResourceDescription of(org.jboss.as.server.ServerEnvironment);
    Code:
       0: new           #10                 // class org/jboss/as/server/ServerEnvironmentResourceDescription
       3: dup
       4: aload_0
       5: invokespecial #11                 // Method "<init>":(Lorg/jboss/as/server/ServerEnvironment;)V
       8: areturn

  public void registerAttributes(org.jboss.as.controller.registry.ManagementResourceRegistration);
    Code:
       0: getstatic     #12                 // Field SERVER_ENV_ATTRIBUTES:[Lorg/jboss/as/controller/AttributeDefinition;
       3: astore_2
       4: aload_2
       5: arraylength
       6: istore_3
       7: iconst_0
       8: istore        4
      10: iload         4
      12: iload_3
      13: if_icmpge     40
      16: aload_2
      17: iload         4
      19: aaload
      20: astore        5
      22: aload_1
      23: aload         5
      25: aload_0
      26: getfield      #9                  // Field osh:Lorg/jboss/as/server/ServerEnvironmentResourceDescription$ServerEnvironmentReadHandler;
      29: invokeinterface #13,  3           // InterfaceMethod org/jboss/as/controller/registry/ManagementResourceRegistration.registerReadOnlyAttribute:(Lorg/jboss/as/controller/AttributeDefinition;Lorg/jboss/as/controller/OperationStepHandler;)V
      34: iinc          4, 1
      37: goto          10
      40: return

  static {};
    Code:
       0: ldc           #15                 // String core-service
       2: ldc           #16                 // String server-environment
       4: invokestatic  #17                 // Method org/jboss/as/controller/PathElement.pathElement:(Ljava/lang/String;Ljava/lang/String;)Lorg/jboss/as/controller/PathElement;
       7: putstatic     #2                  // Field RESOURCE_PATH:Lorg/jboss/as/controller/PathElement;
      10: ldc           #18                 // String base-dir
      12: getstatic     #19                 // Field org/jboss/dmr/ModelType.STRING:Lorg/jboss/dmr/ModelType;
      15: invokestatic  #20                 // Method org/jboss/as/controller/SimpleAttributeDefinitionBuilder.create:(Ljava/lang/String;Lorg/jboss/dmr/ModelType;)Lorg/jboss/as/controller/SimpleAttributeDefinitionBuilder;
      18: iconst_1
      19: anewarray     #21                 // class org/jboss/as/controller/registry/AttributeAccess$Flag
      22: dup
      23: iconst_0
      24: getstatic     #22                 // Field org/jboss/as/controller/registry/AttributeAccess$Flag.STORAGE_RUNTIME:Lorg/jboss/as/controller/registry/AttributeAccess$Flag;
      27: aastore
      28: invokevirtual #23                 // Method org/jboss/as/controller/SimpleAttributeDefinitionBuilder.setFlags:([Lorg/jboss/as/controller/registry/AttributeAccess$Flag;)Lorg/jboss/as/controller/AbstractAttributeDefinitionBuilder;
      31: checkcast     #24                 // class org/jboss/as/controller/SimpleAttributeDefinitionBuilder
      34: invokevirtual #25                 // Method org/jboss/as/controller/SimpleAttributeDefinitionBuilder.build:()Lorg/jboss/as/controller/SimpleAttributeDefinition;
      37: putstatic     #26                 // Field BASE_DIR:Lorg/jboss/as/controller/AttributeDefinition;
      40: ldc           #27                 // String config-dir
      42: getstatic     #19                 // Field org/jboss/dmr/ModelType.STRING:Lorg/jboss/dmr/ModelType;
      45: invokestatic  #20                 // Method org/jboss/as/controller/SimpleAttributeDefinitionBuilder.create:(Ljava/lang/String;Lorg/jboss/dmr/ModelType;)Lorg/jboss/as/controller/SimpleAttributeDefinitionBuilder;
      48: iconst_1
      49: anewarray     #21                 // class org/jboss/as/controller/registry/AttributeAccess$Flag
      52: dup
      53: iconst_0
      54: getstatic     #22                 // Field org/jboss/as/controller/registry/AttributeAccess$Flag.STORAGE_RUNTIME:Lorg/jboss/as/controller/registry/AttributeAccess$Flag;
      57: aastore
      58: invokevirtual #23                 // Method org/jboss/as/controller/SimpleAttributeDefinitionBuilder.setFlags:([Lorg/jboss/as/controller/registry/AttributeAccess$Flag;)Lorg/jboss/as/controller/AbstractAttributeDefinitionBuilder;
      61: checkcast     #24                 // class org/jboss/as/controller/SimpleAttributeDefinitionBuilder
      64: invokevirtual #25                 // Method org/jboss/as/controller/SimpleAttributeDefinitionBuilder.build:()Lorg/jboss/as/controller/SimpleAttributeDefinition;
      67: putstatic     #28                 // Field CONFIG_DIR:Lorg/jboss/as/controller/AttributeDefinition;
      70: ldc           #29                 // String config-file
      72: getstatic     #19                 // Field org/jboss/dmr/ModelType.STRING:Lorg/jboss/dmr/ModelType;
      75: invokestatic  #20                 // Method org/jboss/as/controller/SimpleAttributeDefinitionBuilder.create:(Ljava/lang/String;Lorg/jboss/dmr/ModelType;)Lorg/jboss/as/controller/SimpleAttributeDefinitionBuilder;
      78: iconst_1
      79: anewarray     #21                 // class org/jboss/as/controller/registry/AttributeAccess$Flag
      82: dup
      83: iconst_0
      84: getstatic     #22                 // Field org/jboss/as/controller/registry/AttributeAccess$Flag.STORAGE_RUNTIME:Lorg/jboss/as/controller/registry/AttributeAccess$Flag;
      87: aastore
      88: invokevirtual #23                 // Method org/jboss/as/controller/SimpleAttributeDefinitionBuilder.setFlags:([Lorg/jboss/as/controller/registry/AttributeAccess$Flag;)Lorg/jboss/as/controller/AbstractAttributeDefinitionBuilder;
      91: checkcast     #24                 // class org/jboss/as/controller/SimpleAttributeDefinitionBuilder
      94: invokevirtual #25                 // Method org/jboss/as/controller/SimpleAttributeDefinitionBuilder.build:()Lorg/jboss/as/controller/SimpleAttributeDefinition;
      97: putstatic     #30                 // Field CONFIG_FILE:Lorg/jboss/as/controller/AttributeDefinition;
     100: ldc           #31                 // String content-dir
     102: getstatic     #19                 // Field org/jboss/dmr/ModelType.STRING:Lorg/jboss/dmr/ModelType;
     105: invokestatic  #20                 // Method org/jboss/as/controller/SimpleAttributeDefinitionBuilder.create:(Ljava/lang/String;Lorg/jboss/dmr/ModelType;)Lorg/jboss/as/controller/SimpleAttributeDefinitionBuilder;
     108: iconst_1
     109: anewarray     #21                 // class org/jboss/as/controller/registry/AttributeAccess$Flag
     112: dup
     113: iconst_0
     114: getstatic     #22                 // Field org/jboss/as/controller/registry/AttributeAccess$Flag.STORAGE_RUNTIME:Lorg/jboss/as/controller/registry/AttributeAccess$Flag;
     117: aastore
     118: invokevirtual #23                 // Method org/jboss/as/controller/SimpleAttributeDefinitionBuilder.setFlags:([Lorg/jboss/as/controller/registry/AttributeAccess$Flag;)Lorg/jboss/as/controller/AbstractAttributeDefinitionBuilder;
     121: checkcast     #24                 // class org/jboss/as/controller/SimpleAttributeDefinitionBuilder
     124: invokevirtual #25                 // Method org/jboss/as/controller/SimpleAttributeDefinitionBuilder.build:()Lorg/jboss/as/controller/SimpleAttributeDefinition;
     127: putstatic     #32                 // Field CONTENT_DIR:Lorg/jboss/as/controller/AttributeDefinition;
     130: ldc           #33                 // String data-dir
     132: getstatic     #19                 // Field org/jboss/dmr/ModelType.STRING:Lorg/jboss/dmr/ModelType;
     135: invokestatic  #20                 // Method org/jboss/as/controller/SimpleAttributeDefinitionBuilder.create:(Ljava/lang/String;Lorg/jboss/dmr/ModelType;)Lorg/jboss/as/controller/SimpleAttributeDefinitionBuilder;
     138: iconst_1
     139: anewarray     #21                 // class org/jboss/as/controller/registry/AttributeAccess$Flag
     142: dup
     143: iconst_0
     144: getstatic     #22                 // Field org/jboss/as/controller/registry/AttributeAccess$Flag.STORAGE_RUNTIME:Lorg/jboss/as/controller/registry/AttributeAccess$Flag;
     147: aastore
     148: invokevirtual #23                 // Method org/jboss/as/controller/SimpleAttributeDefinitionBuilder.setFlags:([Lorg/jboss/as/controller/registry/AttributeAccess$Flag;)Lorg/jboss/as/controller/AbstractAttributeDefinitionBuilder;
     151: checkcast     #24                 // class org/jboss/as/controller/SimpleAttributeDefinitionBuilder
     154: invokevirtual #25                 // Method org/jboss/as/controller/SimpleAttributeDefinitionBuilder.build:()Lorg/jboss/as/controller/SimpleAttributeDefinition;
     157: putstatic     #34                 // Field DATA_DIR:Lorg/jboss/as/controller/AttributeDefinition;
     160: ldc           #35                 // String deploy-dir
     162: getstatic     #19                 // Field org/jboss/dmr/ModelType.STRING:Lorg/jboss/dmr/ModelType;
     165: invokestatic  #20                 // Method org/jboss/as/controller/SimpleAttributeDefinitionBuilder.create:(Ljava/lang/String;Lorg/jboss/dmr/ModelType;)Lorg/jboss/as/controller/SimpleAttributeDefinitionBuilder;
     168: iconst_1
     169: anewarray     #21                 // class org/jboss/as/controller/registry/AttributeAccess$Flag
     172: dup
     173: iconst_0
     174: getstatic     #22                 // Field org/jboss/as/controller/registry/AttributeAccess$Flag.STORAGE_RUNTIME:Lorg/jboss/as/controller/registry/AttributeAccess$Flag;
     177: aastore
     178: invokevirtual #23                 // Method org/jboss/as/controller/SimpleAttributeDefinitionBuilder.setFlags:([Lorg/jboss/as/controller/registry/AttributeAccess$Flag;)Lorg/jboss/as/controller/AbstractAttributeDefinitionBuilder;
     181: checkcast     #24                 // class org/jboss/as/controller/SimpleAttributeDefinitionBuilder
     184: invokevirtual #25                 // Method org/jboss/as/controller/SimpleAttributeDefinitionBuilder.build:()Lorg/jboss/as/controller/SimpleAttributeDefinition;
     187: putstatic     #36                 // Field DEPLOY_DIR:Lorg/jboss/as/controller/AttributeDefinition;
     190: ldc           #37                 // String ext-dirs
     192: getstatic     #19                 // Field org/jboss/dmr/ModelType.STRING:Lorg/jboss/dmr/ModelType;
     195: invokestatic  #20                 // Method org/jboss/as/controller/SimpleAttributeDefinitionBuilder.create:(Ljava/lang/String;Lorg/jboss/dmr/ModelType;)Lorg/jboss/as/controller/SimpleAttributeDefinitionBuilder;
     198: iconst_1
     199: anewarray     #21                 // class org/jboss/as/controller/registry/AttributeAccess$Flag
     202: dup
     203: iconst_0
     204: getstatic     #22                 // Field org/jboss/as/controller/registry/AttributeAccess$Flag.STORAGE_RUNTIME:Lorg/jboss/as/controller/registry/AttributeAccess$Flag;
     207: aastore
     208: invokevirtual #23                 // Method org/jboss/as/controller/SimpleAttributeDefinitionBuilder.setFlags:([Lorg/jboss/as/controller/registry/AttributeAccess$Flag;)Lorg/jboss/as/controller/AbstractAttributeDefinitionBuilder;
     211: checkcast     #24                 // class org/jboss/as/controller/SimpleAttributeDefinitionBuilder
     214: invokevirtual #25                 // Method org/jboss/as/controller/SimpleAttributeDefinitionBuilder.build:()Lorg/jboss/as/controller/SimpleAttributeDefinition;
     217: putstatic     #38                 // Field EXT_DIRS:Lorg/jboss/as/controller/AttributeDefinition;
     220: ldc           #39                 // String home-dir
     222: getstatic     #19                 // Field org/jboss/dmr/ModelType.STRING:Lorg/jboss/dmr/ModelType;
     225: invokestatic  #20                 // Method org/jboss/as/controller/SimpleAttributeDefinitionBuilder.create:(Ljava/lang/String;Lorg/jboss/dmr/ModelType;)Lorg/jboss/as/controller/SimpleAttributeDefinitionBuilder;
     228: iconst_1
     229: anewarray     #21                 // class org/jboss/as/controller/registry/AttributeAccess$Flag
     232: dup
     233: iconst_0
     234: getstatic     #22                 // Field org/jboss/as/controller/registry/AttributeAccess$Flag.STORAGE_RUNTIME:Lorg/jboss/as/controller/registry/AttributeAccess$Flag;
     237: aastore
     238: invokevirtual #23                 // Method org/jboss/as/controller/SimpleAttributeDefinitionBuilder.setFlags:([Lorg/jboss/as/controller/registry/AttributeAccess$Flag;)Lorg/jboss/as/controller/AbstractAttributeDefinitionBuilder;
     241: checkcast     #24                 // class org/jboss/as/controller/SimpleAttributeDefinitionBuilder
     244: invokevirtual #25                 // Method org/jboss/as/controller/SimpleAttributeDefinitionBuilder.build:()Lorg/jboss/as/controller/SimpleAttributeDefinition;
     247: putstatic     #40                 // Field HOME_DIR:Lorg/jboss/as/controller/AttributeDefinition;
     250: ldc           #41                 // String host-name
     252: getstatic     #19                 // Field org/jboss/dmr/ModelType.STRING:Lorg/jboss/dmr/ModelType;
     255: invokestatic  #20                 // Method org/jboss/as/controller/SimpleAttributeDefinitionBuilder.create:(Ljava/lang/String;Lorg/jboss/dmr/ModelType;)Lorg/jboss/as/controller/SimpleAttributeDefinitionBuilder;
     258: iconst_1
     259: anewarray     #21                 // class org/jboss/as/controller/registry/AttributeAccess$Flag
     262: dup
     263: iconst_0
     264: getstatic     #22                 // Field org/jboss/as/controller/registry/AttributeAccess$Flag.STORAGE_RUNTIME:Lorg/jboss/as/controller/registry/AttributeAccess$Flag;
     267: aastore
     268: invokevirtual #23                 // Method org/jboss/as/controller/SimpleAttributeDefinitionBuilder.setFlags:([Lorg/jboss/as/controller/registry/AttributeAccess$Flag;)Lorg/jboss/as/controller/AbstractAttributeDefinitionBuilder;
     271: checkcast     #24                 // class org/jboss/as/controller/SimpleAttributeDefinitionBuilder
     274: invokevirtual #25                 // Method org/jboss/as/controller/SimpleAttributeDefinitionBuilder.build:()Lorg/jboss/as/controller/SimpleAttributeDefinition;
     277: putstatic     #42                 // Field HOST_NAME:Lorg/jboss/as/controller/AttributeDefinition;
     280: ldc           #43                 // String initial-running-mode
     282: getstatic     #19                 // Field org/jboss/dmr/ModelType.STRING:Lorg/jboss/dmr/ModelType;
     285: invokestatic  #20                 // Method org/jboss/as/controller/SimpleAttributeDefinitionBuilder.create:(Ljava/lang/String;Lorg/jboss/dmr/ModelType;)Lorg/jboss/as/controller/SimpleAttributeDefinitionBuilder;
     288: new           #44                 // class org/jboss/as/controller/operations/validation/EnumValidator
     291: dup
     292: ldc           #45                 // class org/jboss/as/controller/RunningMode
     294: iconst_0
     295: iconst_0
     296: invokespecial #46                 // Method org/jboss/as/controller/operations/validation/EnumValidator."<init>":(Ljava/lang/Class;ZZ)V
     299: invokevirtual #47                 // Method org/jboss/as/controller/SimpleAttributeDefinitionBuilder.setValidator:(Lorg/jboss/as/controller/operations/validation/ParameterValidator;)Lorg/jboss/as/controller/AbstractAttributeDefinitionBuilder;
     302: checkcast     #24                 // class org/jboss/as/controller/SimpleAttributeDefinitionBuilder
     305: iconst_1
     306: anewarray     #21                 // class org/jboss/as/controller/registry/AttributeAccess$Flag
     309: dup
     310: iconst_0
     311: getstatic     #22                 // Field org/jboss/as/controller/registry/AttributeAccess$Flag.STORAGE_RUNTIME:Lorg/jboss/as/controller/registry/AttributeAccess$Flag;
     314: aastore
     315: invokevirtual #23                 // Method org/jboss/as/controller/SimpleAttributeDefinitionBuilder.setFlags:([Lorg/jboss/as/controller/registry/AttributeAccess$Flag;)Lorg/jboss/as/controller/AbstractAttributeDefinitionBuilder;
     318: checkcast     #24                 // class org/jboss/as/controller/SimpleAttributeDefinitionBuilder
     321: invokevirtual #25                 // Method org/jboss/as/controller/SimpleAttributeDefinitionBuilder.build:()Lorg/jboss/as/controller/SimpleAttributeDefinition;
     324: putstatic     #48                 // Field INITIAL_RUNNING_MODE:Lorg/jboss/as/controller/AttributeDefinition;
     327: ldc           #49                 // String launch-type
     329: getstatic     #19                 // Field org/jboss/dmr/ModelType.STRING:Lorg/jboss/dmr/ModelType;
     332: invokestatic  #20                 // Method org/jboss/as/controller/SimpleAttributeDefinitionBuilder.create:(Ljava/lang/String;Lorg/jboss/dmr/ModelType;)Lorg/jboss/as/controller/SimpleAttributeDefinitionBuilder;
     335: iconst_1
     336: anewarray     #21                 // class org/jboss/as/controller/registry/AttributeAccess$Flag
     339: dup
     340: iconst_0
     341: getstatic     #22                 // Field org/jboss/as/controller/registry/AttributeAccess$Flag.STORAGE_RUNTIME:Lorg/jboss/as/controller/registry/AttributeAccess$Flag;
     344: aastore
     345: invokevirtual #23                 // Method org/jboss/as/controller/SimpleAttributeDefinitionBuilder.setFlags:([Lorg/jboss/as/controller/registry/AttributeAccess$Flag;)Lorg/jboss/as/controller/AbstractAttributeDefinitionBuilder;
     348: checkcast     #24                 // class org/jboss/as/controller/SimpleAttributeDefinitionBuilder
     351: invokevirtual #25                 // Method org/jboss/as/controller/SimpleAttributeDefinitionBuilder.build:()Lorg/jboss/as/controller/SimpleAttributeDefinition;
     354: putstatic     #50                 // Field LAUNCH_TYPE:Lorg/jboss/as/controller/AttributeDefinition;
     357: ldc           #51                 // String log-dir
     359: getstatic     #19                 // Field org/jboss/dmr/ModelType.STRING:Lorg/jboss/dmr/ModelType;
     362: invokestatic  #20                 // Method org/jboss/as/controller/SimpleAttributeDefinitionBuilder.create:(Ljava/lang/String;Lorg/jboss/dmr/ModelType;)Lorg/jboss/as/controller/SimpleAttributeDefinitionBuilder;
     365: iconst_1
     366: anewarray     #21                 // class org/jboss/as/controller/registry/AttributeAccess$Flag
     369: dup
     370: iconst_0
     371: getstatic     #22                 // Field org/jboss/as/controller/registry/AttributeAccess$Flag.STORAGE_RUNTIME:Lorg/jboss/as/controller/registry/AttributeAccess$Flag;
     374: aastore
     375: invokevirtual #23                 // Method org/jboss/as/controller/SimpleAttributeDefinitionBuilder.setFlags:([Lorg/jboss/as/controller/registry/AttributeAccess$Flag;)Lorg/jboss/as/controller/AbstractAttributeDefinitionBuilder;
     378: checkcast     #24                 // class org/jboss/as/controller/SimpleAttributeDefinitionBuilder
     381: invokevirtual #25                 // Method org/jboss/as/controller/SimpleAttributeDefinitionBuilder.build:()Lorg/jboss/as/controller/SimpleAttributeDefinition;
     384: putstatic     #52                 // Field LOG_DIR:Lorg/jboss/as/controller/AttributeDefinition;
     387: ldc           #53                 // String modules-dir
     389: getstatic     #19                 // Field org/jboss/dmr/ModelType.STRING:Lorg/jboss/dmr/ModelType;
     392: invokestatic  #20                 // Method org/jboss/as/controller/SimpleAttributeDefinitionBuilder.create:(Ljava/lang/String;Lorg/jboss/dmr/ModelType;)Lorg/jboss/as/controller/SimpleAttributeDefinitionBuilder;
     395: iconst_1
     396: anewarray     #21                 // class org/jboss/as/controller/registry/AttributeAccess$Flag
     399: dup
     400: iconst_0
     401: getstatic     #22                 // Field org/jboss/as/controller/registry/AttributeAccess$Flag.STORAGE_RUNTIME:Lorg/jboss/as/controller/registry/AttributeAccess$Flag;
     404: aastore
     405: invokevirtual #23                 // Method org/jboss/as/controller/SimpleAttributeDefinitionBuilder.setFlags:([Lorg/jboss/as/controller/registry/AttributeAccess$Flag;)Lorg/jboss/as/controller/AbstractAttributeDefinitionBuilder;
     408: checkcast     #24                 // class org/jboss/as/controller/SimpleAttributeDefinitionBuilder
     411: iconst_2
     412: iconst_1
     413: invokestatic  #54                 // Method org/jboss/as/controller/ModelVersion.create:(II)Lorg/jboss/as/controller/ModelVersion;
     416: invokevirtual #55                 // Method org/jboss/as/controller/SimpleAttributeDefinitionBuilder.setDeprecated:(Lorg/jboss/as/controller/ModelVersion;)Lorg/jboss/as/controller/AbstractAttributeDefinitionBuilder;
     419: checkcast     #24                 // class org/jboss/as/controller/SimpleAttributeDefinitionBuilder
     422: invokevirtual #25                 // Method org/jboss/as/controller/SimpleAttributeDefinitionBuilder.build:()Lorg/jboss/as/controller/SimpleAttributeDefinition;
     425: putstatic     #56                 // Field MODULES_DIR:Lorg/jboss/as/controller/AttributeDefinition;
     428: ldc           #57                 // String node-name
     430: getstatic     #19                 // Field org/jboss/dmr/ModelType.STRING:Lorg/jboss/dmr/ModelType;
     433: invokestatic  #20                 // Method org/jboss/as/controller/SimpleAttributeDefinitionBuilder.create:(Ljava/lang/String;Lorg/jboss/dmr/ModelType;)Lorg/jboss/as/controller/SimpleAttributeDefinitionBuilder;
     436: iconst_1
     437: anewarray     #21                 // class org/jboss/as/controller/registry/AttributeAccess$Flag
     440: dup
     441: iconst_0
     442: getstatic     #22                 // Field org/jboss/as/controller/registry/AttributeAccess$Flag.STORAGE_RUNTIME:Lorg/jboss/as/controller/registry/AttributeAccess$Flag;
     445: aastore
     446: invokevirtual #23                 // Method org/jboss/as/controller/SimpleAttributeDefinitionBuilder.setFlags:([Lorg/jboss/as/controller/registry/AttributeAccess$Flag;)Lorg/jboss/as/controller/AbstractAttributeDefinitionBuilder;
     449: checkcast     #24                 // class org/jboss/as/controller/SimpleAttributeDefinitionBuilder
     452: invokevirtual #25                 // Method org/jboss/as/controller/SimpleAttributeDefinitionBuilder.build:()Lorg/jboss/as/controller/SimpleAttributeDefinition;
     455: putstatic     #58                 // Field NODE_NAME:Lorg/jboss/as/controller/AttributeDefinition;
     458: ldc           #59                 // String qualified-host-name
     460: getstatic     #19                 // Field org/jboss/dmr/ModelType.STRING:Lorg/jboss/dmr/ModelType;
     463: invokestatic  #20                 // Method org/jboss/as/controller/SimpleAttributeDefinitionBuilder.create:(Ljava/lang/String;Lorg/jboss/dmr/ModelType;)Lorg/jboss/as/controller/SimpleAttributeDefinitionBuilder;
     466: iconst_1
     467: anewarray     #21                 // class org/jboss/as/controller/registry/AttributeAccess$Flag
     470: dup
     471: iconst_0
     472: getstatic     #22                 // Field org/jboss/as/controller/registry/AttributeAccess$Flag.STORAGE_RUNTIME:Lorg/jboss/as/controller/registry/AttributeAccess$Flag;
     475: aastore
     476: invokevirtual #23                 // Method org/jboss/as/controller/SimpleAttributeDefinitionBuilder.setFlags:([Lorg/jboss/as/controller/registry/AttributeAccess$Flag;)Lorg/jboss/as/controller/AbstractAttributeDefinitionBuilder;
     479: checkcast     #24                 // class org/jboss/as/controller/SimpleAttributeDefinitionBuilder
     482: invokevirtual #25                 // Method org/jboss/as/controller/SimpleAttributeDefinitionBuilder.build:()Lorg/jboss/as/controller/SimpleAttributeDefinition;
     485: putstatic     #60                 // Field QUALIFIED_HOST_NAME:Lorg/jboss/as/controller/AttributeDefinition;
     488: ldc           #61                 // String server-name
     490: getstatic     #19                 // Field org/jboss/dmr/ModelType.STRING:Lorg/jboss/dmr/ModelType;
     493: invokestatic  #20                 // Method org/jboss/as/controller/SimpleAttributeDefinitionBuilder.create:(Ljava/lang/String;Lorg/jboss/dmr/ModelType;)Lorg/jboss/as/controller/SimpleAttributeDefinitionBuilder;
     496: iconst_1
     497: anewarray     #21                 // class org/jboss/as/controller/registry/AttributeAccess$Flag
     500: dup
     501: iconst_0
     502: getstatic     #22                 // Field org/jboss/as/controller/registry/AttributeAccess$Flag.STORAGE_RUNTIME:Lorg/jboss/as/controller/registry/AttributeAccess$Flag;
     505: aastore
     506: invokevirtual #23                 // Method org/jboss/as/controller/SimpleAttributeDefinitionBuilder.setFlags:([Lorg/jboss/as/controller/registry/AttributeAccess$Flag;)Lorg/jboss/as/controller/AbstractAttributeDefinitionBuilder;
     509: checkcast     #24                 // class org/jboss/as/controller/SimpleAttributeDefinitionBuilder
     512: invokevirtual #25                 // Method org/jboss/as/controller/SimpleAttributeDefinitionBuilder.build:()Lorg/jboss/as/controller/SimpleAttributeDefinition;
     515: putstatic     #62                 // Field SERVER_NAME:Lorg/jboss/as/controller/AttributeDefinition;
     518: ldc           #63                 // String temp-dir
     520: getstatic     #19                 // Field org/jboss/dmr/ModelType.STRING:Lorg/jboss/dmr/ModelType;
     523: invokestatic  #20                 // Method org/jboss/as/controller/SimpleAttributeDefinitionBuilder.create:(Ljava/lang/String;Lorg/jboss/dmr/ModelType;)Lorg/jboss/as/controller/SimpleAttributeDefinitionBuilder;
     526: iconst_1
     527: anewarray     #21                 // class org/jboss/as/controller/registry/AttributeAccess$Flag
     530: dup
     531: iconst_0
     532: getstatic     #22                 // Field org/jboss/as/controller/registry/AttributeAccess$Flag.STORAGE_RUNTIME:Lorg/jboss/as/controller/registry/AttributeAccess$Flag;
     535: aastore
     536: invokevirtual #23                 // Method org/jboss/as/controller/SimpleAttributeDefinitionBuilder.setFlags:([Lorg/jboss/as/controller/registry/AttributeAccess$Flag;)Lorg/jboss/as/controller/AbstractAttributeDefinitionBuilder;
     539: checkcast     #24                 // class org/jboss/as/controller/SimpleAttributeDefinitionBuilder
     542: invokevirtual #25                 // Method org/jboss/as/controller/SimpleAttributeDefinitionBuilder.build:()Lorg/jboss/as/controller/SimpleAttributeDefinition;
     545: putstatic     #64                 // Field TEMP_DIR:Lorg/jboss/as/controller/AttributeDefinition;
     548: bipush        17
     550: anewarray     #65                 // class org/jboss/as/controller/AttributeDefinition
     553: dup
     554: iconst_0
     555: getstatic     #26                 // Field BASE_DIR:Lorg/jboss/as/controller/AttributeDefinition;
     558: aastore
     559: dup
     560: iconst_1
     561: getstatic     #28                 // Field CONFIG_DIR:Lorg/jboss/as/controller/AttributeDefinition;
     564: aastore
     565: dup
     566: iconst_2
     567: getstatic     #30                 // Field CONFIG_FILE:Lorg/jboss/as/controller/AttributeDefinition;
     570: aastore
     571: dup
     572: iconst_3
     573: getstatic     #32                 // Field CONTENT_DIR:Lorg/jboss/as/controller/AttributeDefinition;
     576: aastore
     577: dup
     578: iconst_4
     579: getstatic     #34                 // Field DATA_DIR:Lorg/jboss/as/controller/AttributeDefinition;
     582: aastore
     583: dup
     584: iconst_5
     585: getstatic     #36                 // Field DEPLOY_DIR:Lorg/jboss/as/controller/AttributeDefinition;
     588: aastore
     589: dup
     590: bipush        6
     592: getstatic     #38                 // Field EXT_DIRS:Lorg/jboss/as/controller/AttributeDefinition;
     595: aastore
     596: dup
     597: bipush        7
     599: getstatic     #40                 // Field HOME_DIR:Lorg/jboss/as/controller/AttributeDefinition;
     602: aastore
     603: dup
     604: bipush        8
     606: getstatic     #42                 // Field HOST_NAME:Lorg/jboss/as/controller/AttributeDefinition;
     609: aastore
     610: dup
     611: bipush        9
     613: getstatic     #48                 // Field INITIAL_RUNNING_MODE:Lorg/jboss/as/controller/AttributeDefinition;
     616: aastore
     617: dup
     618: bipush        10
     620: getstatic     #50                 // Field LAUNCH_TYPE:Lorg/jboss/as/controller/AttributeDefinition;
     623: aastore
     624: dup
     625: bipush        11
     627: getstatic     #52                 // Field LOG_DIR:Lorg/jboss/as/controller/AttributeDefinition;
     630: aastore
     631: dup
     632: bipush        12
     634: getstatic     #56                 // Field MODULES_DIR:Lorg/jboss/as/controller/AttributeDefinition;
     637: aastore
     638: dup
     639: bipush        13
     641: getstatic     #58                 // Field NODE_NAME:Lorg/jboss/as/controller/AttributeDefinition;
     644: aastore
     645: dup
     646: bipush        14
     648: getstatic     #60                 // Field QUALIFIED_HOST_NAME:Lorg/jboss/as/controller/AttributeDefinition;
     651: aastore
     652: dup
     653: bipush        15
     655: getstatic     #62                 // Field SERVER_NAME:Lorg/jboss/as/controller/AttributeDefinition;
     658: aastore
     659: dup
     660: bipush        16
     662: getstatic     #64                 // Field TEMP_DIR:Lorg/jboss/as/controller/AttributeDefinition;
     665: aastore
     666: putstatic     #12                 // Field SERVER_ENV_ATTRIBUTES:[Lorg/jboss/as/controller/AttributeDefinition;
     669: return
}
