Compiled from "FunctionSignature.java"
public class info.archinnov.achilles.internals.parser.context.FunctionSignature$FunctionParamSignature {
  public final java.lang.String name;

  public final com.squareup.javapoet.TypeName sourceTypeName;

  public final com.squareup.javapoet.TypeName targetCQLTypeName;

  public final java.lang.String targetCQLDataType;

  public static info.archinnov.achilles.internals.parser.context.FunctionSignature$FunctionParamSignature VOID();
    Code:
       0: new           #1                  // class info/archinnov/achilles/internals/parser/context/FunctionSignature$FunctionParamSignature
       3: dup
       4: ldc           #2                  // String returnType
       6: getstatic     #3                  // Field com/squareup/javapoet/TypeName.VOID:Lcom/squareup/javapoet/TypeName;
       9: getstatic     #3                  // Field com/squareup/javapoet/TypeName.VOID:Lcom/squareup/javapoet/TypeName;
      12: ldc           #4                  // String
      14: invokespecial #5                  // Method "<init>":(Ljava/lang/String;Lcom/squareup/javapoet/TypeName;Lcom/squareup/javapoet/TypeName;Ljava/lang/String;)V
      17: areturn

  public info.archinnov.achilles.internals.parser.context.FunctionSignature$FunctionParamSignature(java.lang.String, com.squareup.javapoet.TypeName, com.squareup.javapoet.TypeName, java.lang.String);
    Code:
       0: aload_0
       1: invokespecial #6                  // Method java/lang/Object."<init>":()V
       4: aload_0
       5: aload_1
       6: putfield      #7                  // Field name:Ljava/lang/String;
       9: aload_0
      10: aload_2
      11: putfield      #8                  // Field sourceTypeName:Lcom/squareup/javapoet/TypeName;
      14: aload_0
      15: aload_3
      16: putfield      #9                  // Field targetCQLTypeName:Lcom/squareup/javapoet/TypeName;
      19: aload_0
      20: aload         4
      22: putfield      #10                 // Field targetCQLDataType:Ljava/lang/String;
      25: return

  public com.squareup.javapoet.TypeName typeForFunctionParam();
    Code:
       0: aload_0
       1: getfield      #8                  // Field sourceTypeName:Lcom/squareup/javapoet/TypeName;
       4: invokestatic  #11                 // Method info/archinnov/achilles/internals/parser/TypeUtils.determineTypeForFunctionParam:(Lcom/squareup/javapoet/TypeName;)Lcom/squareup/javapoet/TypeName;
       7: areturn

  public static info.archinnov.achilles.internals.parser.context.FunctionSignature$FunctionParamSignature tupleType(java.lang.String, com.squareup.javapoet.ClassName, info.archinnov.achilles.internals.parser.context.FunctionSignature$FunctionParamSignature...);
    Code:
       0: aload_2
       1: invokestatic  #12                 // Method java/util/Arrays.stream:([Ljava/lang/Object;)Ljava/util/stream/Stream;
       4: invokedynamic #13,  0             // InvokeDynamic #0:apply:()Ljava/util/function/Function;
       9: invokeinterface #14,  2           // InterfaceMethod java/util/stream/Stream.map:(Ljava/util/function/Function;)Ljava/util/stream/Stream;
      14: invokestatic  #15                 // Method java/util/stream/Collectors.toList:()Ljava/util/stream/Collector;
      17: invokeinterface #16,  2           // InterfaceMethod java/util/stream/Stream.collect:(Ljava/util/stream/Collector;)Ljava/lang/Object;
      22: checkcast     #17                 // class java/util/List
      25: astore_3
      26: new           #18                 // class java/util/StringJoiner
      29: dup
      30: ldc           #19                 // String ,
      32: ldc           #20                 // String frozen<tuple<
      34: ldc           #21                 // String >>
      36: invokespecial #22                 // Method java/util/StringJoiner."<init>":(Ljava/lang/CharSequence;Ljava/lang/CharSequence;Ljava/lang/CharSequence;)V
      39: astore        4
      41: aload_2
      42: invokestatic  #12                 // Method java/util/Arrays.stream:([Ljava/lang/Object;)Ljava/util/stream/Stream;
      45: aload         4
      47: invokedynamic #23,  0             // InvokeDynamic #1:accept:(Ljava/util/StringJoiner;)Ljava/util/function/Consumer;
      52: invokeinterface #24,  2           // InterfaceMethod java/util/stream/Stream.forEach:(Ljava/util/function/Consumer;)V
      57: new           #1                  // class info/archinnov/achilles/internals/parser/context/FunctionSignature$FunctionParamSignature
      60: dup
      61: aload_0
      62: aload_1
      63: aload_3
      64: aload_3
      65: invokeinterface #25,  1           // InterfaceMethod java/util/List.size:()I
      70: anewarray     #26                 // class com/squareup/javapoet/TypeName
      73: invokeinterface #27,  2           // InterfaceMethod java/util/List.toArray:([Ljava/lang/Object;)[Ljava/lang/Object;
      78: checkcast     #28                 // class "[Lcom/squareup/javapoet/TypeName;"
      81: invokestatic  #29                 // Method info/archinnov/achilles/internals/parser/TypeUtils.genericType:(Lcom/squareup/javapoet/ClassName;[Lcom/squareup/javapoet/TypeName;)Lcom/squareup/javapoet/ParameterizedTypeName;
      84: getstatic     #30                 // Field info/archinnov/achilles/internals/parser/TypeUtils.JAVA_DRIVER_TUPLE_VALUE_TYPE:Lcom/squareup/javapoet/ClassName;
      87: aload         4
      89: invokevirtual #31                 // Method java/util/StringJoiner.toString:()Ljava/lang/String;
      92: invokespecial #5                  // Method "<init>":(Ljava/lang/String;Lcom/squareup/javapoet/TypeName;Lcom/squareup/javapoet/TypeName;Ljava/lang/String;)V
      95: areturn

  public static info.archinnov.achilles.internals.parser.context.FunctionSignature$FunctionParamSignature listType(java.lang.String, info.archinnov.achilles.internals.parser.context.FunctionSignature$FunctionParamSignature, boolean);
    Code:
       0: iload_2
       1: ifeq          74
       4: new           #1                  // class info/archinnov/achilles/internals/parser/context/FunctionSignature$FunctionParamSignature
       7: dup
       8: aload_0
       9: getstatic     #32                 // Field info/archinnov/achilles/internals/parser/TypeUtils.LIST:Lcom/squareup/javapoet/ClassName;
      12: iconst_1
      13: anewarray     #26                 // class com/squareup/javapoet/TypeName
      16: dup
      17: iconst_0
      18: aload_1
      19: getfield      #8                  // Field sourceTypeName:Lcom/squareup/javapoet/TypeName;
      22: aastore
      23: invokestatic  #29                 // Method info/archinnov/achilles/internals/parser/TypeUtils.genericType:(Lcom/squareup/javapoet/ClassName;[Lcom/squareup/javapoet/TypeName;)Lcom/squareup/javapoet/ParameterizedTypeName;
      26: getstatic     #32                 // Field info/archinnov/achilles/internals/parser/TypeUtils.LIST:Lcom/squareup/javapoet/ClassName;
      29: iconst_1
      30: anewarray     #26                 // class com/squareup/javapoet/TypeName
      33: dup
      34: iconst_0
      35: aload_1
      36: getfield      #9                  // Field targetCQLTypeName:Lcom/squareup/javapoet/TypeName;
      39: aastore
      40: invokestatic  #29                 // Method info/archinnov/achilles/internals/parser/TypeUtils.genericType:(Lcom/squareup/javapoet/ClassName;[Lcom/squareup/javapoet/TypeName;)Lcom/squareup/javapoet/ParameterizedTypeName;
      43: new           #33                 // class java/lang/StringBuilder
      46: dup
      47: invokespecial #34                 // Method java/lang/StringBuilder."<init>":()V
      50: ldc           #35                 // String frozen<list<
      52: invokevirtual #36                 // Method java/lang/StringBuilder.append:(Ljava/lang/String;)Ljava/lang/StringBuilder;
      55: aload_1
      56: getfield      #10                 // Field targetCQLDataType:Ljava/lang/String;
      59: invokevirtual #36                 // Method java/lang/StringBuilder.append:(Ljava/lang/String;)Ljava/lang/StringBuilder;
      62: ldc           #21                 // String >>
      64: invokevirtual #36                 // Method java/lang/StringBuilder.append:(Ljava/lang/String;)Ljava/lang/StringBuilder;
      67: invokevirtual #37                 // Method java/lang/StringBuilder.toString:()Ljava/lang/String;
      70: invokespecial #5                  // Method "<init>":(Ljava/lang/String;Lcom/squareup/javapoet/TypeName;Lcom/squareup/javapoet/TypeName;Ljava/lang/String;)V
      73: areturn
      74: new           #1                  // class info/archinnov/achilles/internals/parser/context/FunctionSignature$FunctionParamSignature
      77: dup
      78: aload_0
      79: getstatic     #32                 // Field info/archinnov/achilles/internals/parser/TypeUtils.LIST:Lcom/squareup/javapoet/ClassName;
      82: iconst_1
      83: anewarray     #26                 // class com/squareup/javapoet/TypeName
      86: dup
      87: iconst_0
      88: aload_1
      89: getfield      #8                  // Field sourceTypeName:Lcom/squareup/javapoet/TypeName;
      92: aastore
      93: invokestatic  #29                 // Method info/archinnov/achilles/internals/parser/TypeUtils.genericType:(Lcom/squareup/javapoet/ClassName;[Lcom/squareup/javapoet/TypeName;)Lcom/squareup/javapoet/ParameterizedTypeName;
      96: getstatic     #32                 // Field info/archinnov/achilles/internals/parser/TypeUtils.LIST:Lcom/squareup/javapoet/ClassName;
      99: iconst_1
     100: anewarray     #26                 // class com/squareup/javapoet/TypeName
     103: dup
     104: iconst_0
     105: aload_1
     106: getfield      #9                  // Field targetCQLTypeName:Lcom/squareup/javapoet/TypeName;
     109: aastore
     110: invokestatic  #29                 // Method info/archinnov/achilles/internals/parser/TypeUtils.genericType:(Lcom/squareup/javapoet/ClassName;[Lcom/squareup/javapoet/TypeName;)Lcom/squareup/javapoet/ParameterizedTypeName;
     113: new           #33                 // class java/lang/StringBuilder
     116: dup
     117: invokespecial #34                 // Method java/lang/StringBuilder."<init>":()V
     120: ldc           #38                 // String list<
     122: invokevirtual #36                 // Method java/lang/StringBuilder.append:(Ljava/lang/String;)Ljava/lang/StringBuilder;
     125: aload_1
     126: getfield      #10                 // Field targetCQLDataType:Ljava/lang/String;
     129: invokevirtual #36                 // Method java/lang/StringBuilder.append:(Ljava/lang/String;)Ljava/lang/StringBuilder;
     132: ldc           #39                 // String >
     134: invokevirtual #36                 // Method java/lang/StringBuilder.append:(Ljava/lang/String;)Ljava/lang/StringBuilder;
     137: invokevirtual #37                 // Method java/lang/StringBuilder.toString:()Ljava/lang/String;
     140: invokespecial #5                  // Method "<init>":(Ljava/lang/String;Lcom/squareup/javapoet/TypeName;Lcom/squareup/javapoet/TypeName;Ljava/lang/String;)V
     143: areturn

  public static info.archinnov.achilles.internals.parser.context.FunctionSignature$FunctionParamSignature setType(java.lang.String, info.archinnov.achilles.internals.parser.context.FunctionSignature$FunctionParamSignature, boolean);
    Code:
       0: iload_2
       1: ifeq          74
       4: new           #1                  // class info/archinnov/achilles/internals/parser/context/FunctionSignature$FunctionParamSignature
       7: dup
       8: aload_0
       9: getstatic     #40                 // Field info/archinnov/achilles/internals/parser/TypeUtils.SET:Lcom/squareup/javapoet/ClassName;
      12: iconst_1
      13: anewarray     #26                 // class com/squareup/javapoet/TypeName
      16: dup
      17: iconst_0
      18: aload_1
      19: getfield      #8                  // Field sourceTypeName:Lcom/squareup/javapoet/TypeName;
      22: aastore
      23: invokestatic  #29                 // Method info/archinnov/achilles/internals/parser/TypeUtils.genericType:(Lcom/squareup/javapoet/ClassName;[Lcom/squareup/javapoet/TypeName;)Lcom/squareup/javapoet/ParameterizedTypeName;
      26: getstatic     #40                 // Field info/archinnov/achilles/internals/parser/TypeUtils.SET:Lcom/squareup/javapoet/ClassName;
      29: iconst_1
      30: anewarray     #26                 // class com/squareup/javapoet/TypeName
      33: dup
      34: iconst_0
      35: aload_1
      36: getfield      #9                  // Field targetCQLTypeName:Lcom/squareup/javapoet/TypeName;
      39: aastore
      40: invokestatic  #29                 // Method info/archinnov/achilles/internals/parser/TypeUtils.genericType:(Lcom/squareup/javapoet/ClassName;[Lcom/squareup/javapoet/TypeName;)Lcom/squareup/javapoet/ParameterizedTypeName;
      43: new           #33                 // class java/lang/StringBuilder
      46: dup
      47: invokespecial #34                 // Method java/lang/StringBuilder."<init>":()V
      50: ldc           #41                 // String frozen<set<
      52: invokevirtual #36                 // Method java/lang/StringBuilder.append:(Ljava/lang/String;)Ljava/lang/StringBuilder;
      55: aload_1
      56: getfield      #10                 // Field targetCQLDataType:Ljava/lang/String;
      59: invokevirtual #36                 // Method java/lang/StringBuilder.append:(Ljava/lang/String;)Ljava/lang/StringBuilder;
      62: ldc           #21                 // String >>
      64: invokevirtual #36                 // Method java/lang/StringBuilder.append:(Ljava/lang/String;)Ljava/lang/StringBuilder;
      67: invokevirtual #37                 // Method java/lang/StringBuilder.toString:()Ljava/lang/String;
      70: invokespecial #5                  // Method "<init>":(Ljava/lang/String;Lcom/squareup/javapoet/TypeName;Lcom/squareup/javapoet/TypeName;Ljava/lang/String;)V
      73: areturn
      74: new           #1                  // class info/archinnov/achilles/internals/parser/context/FunctionSignature$FunctionParamSignature
      77: dup
      78: aload_0
      79: getstatic     #40                 // Field info/archinnov/achilles/internals/parser/TypeUtils.SET:Lcom/squareup/javapoet/ClassName;
      82: iconst_1
      83: anewarray     #26                 // class com/squareup/javapoet/TypeName
      86: dup
      87: iconst_0
      88: aload_1
      89: getfield      #8                  // Field sourceTypeName:Lcom/squareup/javapoet/TypeName;
      92: aastore
      93: invokestatic  #29                 // Method info/archinnov/achilles/internals/parser/TypeUtils.genericType:(Lcom/squareup/javapoet/ClassName;[Lcom/squareup/javapoet/TypeName;)Lcom/squareup/javapoet/ParameterizedTypeName;
      96: getstatic     #40                 // Field info/archinnov/achilles/internals/parser/TypeUtils.SET:Lcom/squareup/javapoet/ClassName;
      99: iconst_1
     100: anewarray     #26                 // class com/squareup/javapoet/TypeName
     103: dup
     104: iconst_0
     105: aload_1
     106: getfield      #9                  // Field targetCQLTypeName:Lcom/squareup/javapoet/TypeName;
     109: aastore
     110: invokestatic  #29                 // Method info/archinnov/achilles/internals/parser/TypeUtils.genericType:(Lcom/squareup/javapoet/ClassName;[Lcom/squareup/javapoet/TypeName;)Lcom/squareup/javapoet/ParameterizedTypeName;
     113: new           #33                 // class java/lang/StringBuilder
     116: dup
     117: invokespecial #34                 // Method java/lang/StringBuilder."<init>":()V
     120: ldc           #42                 // String set<
     122: invokevirtual #36                 // Method java/lang/StringBuilder.append:(Ljava/lang/String;)Ljava/lang/StringBuilder;
     125: aload_1
     126: getfield      #10                 // Field targetCQLDataType:Ljava/lang/String;
     129: invokevirtual #36                 // Method java/lang/StringBuilder.append:(Ljava/lang/String;)Ljava/lang/StringBuilder;
     132: ldc           #39                 // String >
     134: invokevirtual #36                 // Method java/lang/StringBuilder.append:(Ljava/lang/String;)Ljava/lang/StringBuilder;
     137: invokevirtual #37                 // Method java/lang/StringBuilder.toString:()Ljava/lang/String;
     140: invokespecial #5                  // Method "<init>":(Ljava/lang/String;Lcom/squareup/javapoet/TypeName;Lcom/squareup/javapoet/TypeName;Ljava/lang/String;)V
     143: areturn

  public static info.archinnov.achilles.internals.parser.context.FunctionSignature$FunctionParamSignature mapType(java.lang.String, info.archinnov.achilles.internals.parser.context.FunctionSignature$FunctionParamSignature, info.archinnov.achilles.internals.parser.context.FunctionSignature$FunctionParamSignature, boolean);
    Code:
       0: iload_3
       1: ifeq          100
       4: new           #1                  // class info/archinnov/achilles/internals/parser/context/FunctionSignature$FunctionParamSignature
       7: dup
       8: aload_0
       9: getstatic     #43                 // Field info/archinnov/achilles/internals/parser/TypeUtils.MAP:Lcom/squareup/javapoet/ClassName;
      12: iconst_2
      13: anewarray     #26                 // class com/squareup/javapoet/TypeName
      16: dup
      17: iconst_0
      18: aload_1
      19: getfield      #8                  // Field sourceTypeName:Lcom/squareup/javapoet/TypeName;
      22: aastore
      23: dup
      24: iconst_1
      25: aload_2
      26: getfield      #8                  // Field sourceTypeName:Lcom/squareup/javapoet/TypeName;
      29: aastore
      30: invokestatic  #29                 // Method info/archinnov/achilles/internals/parser/TypeUtils.genericType:(Lcom/squareup/javapoet/ClassName;[Lcom/squareup/javapoet/TypeName;)Lcom/squareup/javapoet/ParameterizedTypeName;
      33: getstatic     #43                 // Field info/archinnov/achilles/internals/parser/TypeUtils.MAP:Lcom/squareup/javapoet/ClassName;
      36: iconst_2
      37: anewarray     #26                 // class com/squareup/javapoet/TypeName
      40: dup
      41: iconst_0
      42: aload_1
      43: getfield      #9                  // Field targetCQLTypeName:Lcom/squareup/javapoet/TypeName;
      46: aastore
      47: dup
      48: iconst_1
      49: aload_2
      50: getfield      #9                  // Field targetCQLTypeName:Lcom/squareup/javapoet/TypeName;
      53: aastore
      54: invokestatic  #29                 // Method info/archinnov/achilles/internals/parser/TypeUtils.genericType:(Lcom/squareup/javapoet/ClassName;[Lcom/squareup/javapoet/TypeName;)Lcom/squareup/javapoet/ParameterizedTypeName;
      57: new           #33                 // class java/lang/StringBuilder
      60: dup
      61: invokespecial #34                 // Method java/lang/StringBuilder."<init>":()V
      64: ldc           #44                 // String frozen<map<
      66: invokevirtual #36                 // Method java/lang/StringBuilder.append:(Ljava/lang/String;)Ljava/lang/StringBuilder;
      69: aload_1
      70: getfield      #10                 // Field targetCQLDataType:Ljava/lang/String;
      73: invokevirtual #36                 // Method java/lang/StringBuilder.append:(Ljava/lang/String;)Ljava/lang/StringBuilder;
      76: ldc           #19                 // String ,
      78: invokevirtual #36                 // Method java/lang/StringBuilder.append:(Ljava/lang/String;)Ljava/lang/StringBuilder;
      81: aload_2
      82: getfield      #10                 // Field targetCQLDataType:Ljava/lang/String;
      85: invokevirtual #36                 // Method java/lang/StringBuilder.append:(Ljava/lang/String;)Ljava/lang/StringBuilder;
      88: ldc           #21                 // String >>
      90: invokevirtual #36                 // Method java/lang/StringBuilder.append:(Ljava/lang/String;)Ljava/lang/StringBuilder;
      93: invokevirtual #37                 // Method java/lang/StringBuilder.toString:()Ljava/lang/String;
      96: invokespecial #5                  // Method "<init>":(Ljava/lang/String;Lcom/squareup/javapoet/TypeName;Lcom/squareup/javapoet/TypeName;Ljava/lang/String;)V
      99: areturn
     100: new           #1                  // class info/archinnov/achilles/internals/parser/context/FunctionSignature$FunctionParamSignature
     103: dup
     104: aload_0
     105: getstatic     #43                 // Field info/archinnov/achilles/internals/parser/TypeUtils.MAP:Lcom/squareup/javapoet/ClassName;
     108: iconst_2
     109: anewarray     #26                 // class com/squareup/javapoet/TypeName
     112: dup
     113: iconst_0
     114: aload_1
     115: getfield      #8                  // Field sourceTypeName:Lcom/squareup/javapoet/TypeName;
     118: aastore
     119: dup
     120: iconst_1
     121: aload_2
     122: getfield      #8                  // Field sourceTypeName:Lcom/squareup/javapoet/TypeName;
     125: aastore
     126: invokestatic  #29                 // Method info/archinnov/achilles/internals/parser/TypeUtils.genericType:(Lcom/squareup/javapoet/ClassName;[Lcom/squareup/javapoet/TypeName;)Lcom/squareup/javapoet/ParameterizedTypeName;
     129: getstatic     #43                 // Field info/archinnov/achilles/internals/parser/TypeUtils.MAP:Lcom/squareup/javapoet/ClassName;
     132: iconst_2
     133: anewarray     #26                 // class com/squareup/javapoet/TypeName
     136: dup
     137: iconst_0
     138: aload_1
     139: getfield      #9                  // Field targetCQLTypeName:Lcom/squareup/javapoet/TypeName;
     142: aastore
     143: dup
     144: iconst_1
     145: aload_2
     146: getfield      #9                  // Field targetCQLTypeName:Lcom/squareup/javapoet/TypeName;
     149: aastore
     150: invokestatic  #29                 // Method info/archinnov/achilles/internals/parser/TypeUtils.genericType:(Lcom/squareup/javapoet/ClassName;[Lcom/squareup/javapoet/TypeName;)Lcom/squareup/javapoet/ParameterizedTypeName;
     153: new           #33                 // class java/lang/StringBuilder
     156: dup
     157: invokespecial #34                 // Method java/lang/StringBuilder."<init>":()V
     160: ldc           #45                 // String map<
     162: invokevirtual #36                 // Method java/lang/StringBuilder.append:(Ljava/lang/String;)Ljava/lang/StringBuilder;
     165: aload_1
     166: getfield      #10                 // Field targetCQLDataType:Ljava/lang/String;
     169: invokevirtual #36                 // Method java/lang/StringBuilder.append:(Ljava/lang/String;)Ljava/lang/StringBuilder;
     172: ldc           #19                 // String ,
     174: invokevirtual #36                 // Method java/lang/StringBuilder.append:(Ljava/lang/String;)Ljava/lang/StringBuilder;
     177: aload_2
     178: getfield      #10                 // Field targetCQLDataType:Ljava/lang/String;
     181: invokevirtual #36                 // Method java/lang/StringBuilder.append:(Ljava/lang/String;)Ljava/lang/StringBuilder;
     184: ldc           #39                 // String >
     186: invokevirtual #36                 // Method java/lang/StringBuilder.append:(Ljava/lang/String;)Ljava/lang/StringBuilder;
     189: invokevirtual #37                 // Method java/lang/StringBuilder.toString:()Ljava/lang/String;
     192: invokespecial #5                  // Method "<init>":(Ljava/lang/String;Lcom/squareup/javapoet/TypeName;Lcom/squareup/javapoet/TypeName;Ljava/lang/String;)V
     195: areturn

  public static info.archinnov.achilles.internals.parser.context.FunctionSignature$FunctionParamSignature optionalType(java.lang.String, info.archinnov.achilles.internals.parser.context.FunctionSignature$FunctionParamSignature);
    Code:
       0: new           #1                  // class info/archinnov/achilles/internals/parser/context/FunctionSignature$FunctionParamSignature
       3: dup
       4: aload_0
       5: getstatic     #46                 // Field info/archinnov/achilles/internals/parser/TypeUtils.OPTIONAL:Lcom/squareup/javapoet/ClassName;
       8: iconst_1
       9: anewarray     #26                 // class com/squareup/javapoet/TypeName
      12: dup
      13: iconst_0
      14: aload_1
      15: getfield      #8                  // Field sourceTypeName:Lcom/squareup/javapoet/TypeName;
      18: aastore
      19: invokestatic  #29                 // Method info/archinnov/achilles/internals/parser/TypeUtils.genericType:(Lcom/squareup/javapoet/ClassName;[Lcom/squareup/javapoet/TypeName;)Lcom/squareup/javapoet/ParameterizedTypeName;
      22: aload_1
      23: getfield      #9                  // Field targetCQLTypeName:Lcom/squareup/javapoet/TypeName;
      26: aload_1
      27: getfield      #10                 // Field targetCQLDataType:Ljava/lang/String;
      30: invokespecial #5                  // Method "<init>":(Ljava/lang/String;Lcom/squareup/javapoet/TypeName;Lcom/squareup/javapoet/TypeName;Ljava/lang/String;)V
      33: areturn

  public java.lang.String toString();
    Code:
       0: new           #33                 // class java/lang/StringBuilder
       3: dup
       4: ldc           #47                 // String UDFParamSignature{
       6: invokespecial #48                 // Method java/lang/StringBuilder."<init>":(Ljava/lang/String;)V
       9: astore_1
      10: aload_1
      11: ldc           #49                 // String name=\'
      13: invokevirtual #36                 // Method java/lang/StringBuilder.append:(Ljava/lang/String;)Ljava/lang/StringBuilder;
      16: aload_0
      17: getfield      #7                  // Field name:Ljava/lang/String;
      20: invokevirtual #36                 // Method java/lang/StringBuilder.append:(Ljava/lang/String;)Ljava/lang/StringBuilder;
      23: bipush        39
      25: invokevirtual #50                 // Method java/lang/StringBuilder.append:(C)Ljava/lang/StringBuilder;
      28: pop
      29: aload_1
      30: ldc           #51                 // String , sourceTypeName=
      32: invokevirtual #36                 // Method java/lang/StringBuilder.append:(Ljava/lang/String;)Ljava/lang/StringBuilder;
      35: aload_0
      36: getfield      #8                  // Field sourceTypeName:Lcom/squareup/javapoet/TypeName;
      39: invokevirtual #52                 // Method java/lang/StringBuilder.append:(Ljava/lang/Object;)Ljava/lang/StringBuilder;
      42: pop
      43: aload_1
      44: ldc           #53                 // String , targetCQLTypeName=
      46: invokevirtual #36                 // Method java/lang/StringBuilder.append:(Ljava/lang/String;)Ljava/lang/StringBuilder;
      49: aload_0
      50: getfield      #9                  // Field targetCQLTypeName:Lcom/squareup/javapoet/TypeName;
      53: invokevirtual #52                 // Method java/lang/StringBuilder.append:(Ljava/lang/Object;)Ljava/lang/StringBuilder;
      56: pop
      57: aload_1
      58: ldc           #54                 // String , targetCQLDataType=\'
      60: invokevirtual #36                 // Method java/lang/StringBuilder.append:(Ljava/lang/String;)Ljava/lang/StringBuilder;
      63: aload_0
      64: getfield      #10                 // Field targetCQLDataType:Ljava/lang/String;
      67: invokevirtual #36                 // Method java/lang/StringBuilder.append:(Ljava/lang/String;)Ljava/lang/StringBuilder;
      70: bipush        39
      72: invokevirtual #50                 // Method java/lang/StringBuilder.append:(C)Ljava/lang/StringBuilder;
      75: pop
      76: aload_1
      77: bipush        125
      79: invokevirtual #50                 // Method java/lang/StringBuilder.append:(C)Ljava/lang/StringBuilder;
      82: pop
      83: aload_1
      84: invokevirtual #37                 // Method java/lang/StringBuilder.toString:()Ljava/lang/String;
      87: areturn

  public boolean equals(java.lang.Object);
    Code:
       0: aload_0
       1: aload_1
       2: if_acmpne     7
       5: iconst_1
       6: ireturn
       7: aload_1
       8: ifnull        22
      11: aload_0
      12: invokevirtual #55                 // Method java/lang/Object.getClass:()Ljava/lang/Class;
      15: aload_1
      16: invokevirtual #55                 // Method java/lang/Object.getClass:()Ljava/lang/Class;
      19: if_acmpeq     24
      22: iconst_0
      23: ireturn
      24: aload_1
      25: checkcast     #1                  // class info/archinnov/achilles/internals/parser/context/FunctionSignature$FunctionParamSignature
      28: astore_2
      29: aload_0
      30: getfield      #7                  // Field name:Ljava/lang/String;
      33: aload_2
      34: getfield      #7                  // Field name:Ljava/lang/String;
      37: invokestatic  #56                 // Method java/util/Objects.equals:(Ljava/lang/Object;Ljava/lang/Object;)Z
      40: ifeq          89
      43: aload_0
      44: getfield      #8                  // Field sourceTypeName:Lcom/squareup/javapoet/TypeName;
      47: aload_2
      48: getfield      #8                  // Field sourceTypeName:Lcom/squareup/javapoet/TypeName;
      51: invokestatic  #56                 // Method java/util/Objects.equals:(Ljava/lang/Object;Ljava/lang/Object;)Z
      54: ifeq          89
      57: aload_0
      58: getfield      #9                  // Field targetCQLTypeName:Lcom/squareup/javapoet/TypeName;
      61: aload_2
      62: getfield      #9                  // Field targetCQLTypeName:Lcom/squareup/javapoet/TypeName;
      65: invokestatic  #56                 // Method java/util/Objects.equals:(Ljava/lang/Object;Ljava/lang/Object;)Z
      68: ifeq          89
      71: aload_0
      72: getfield      #10                 // Field targetCQLDataType:Ljava/lang/String;
      75: aload_2
      76: getfield      #10                 // Field targetCQLDataType:Ljava/lang/String;
      79: invokestatic  #56                 // Method java/util/Objects.equals:(Ljava/lang/Object;Ljava/lang/Object;)Z
      82: ifeq          89
      85: iconst_1
      86: goto          90
      89: iconst_0
      90: ireturn

  public int hashCode();
    Code:
       0: iconst_4
       1: anewarray     #57                 // class java/lang/Object
       4: dup
       5: iconst_0
       6: aload_0
       7: getfield      #7                  // Field name:Ljava/lang/String;
      10: aastore
      11: dup
      12: iconst_1
      13: aload_0
      14: getfield      #8                  // Field sourceTypeName:Lcom/squareup/javapoet/TypeName;
      17: aastore
      18: dup
      19: iconst_2
      20: aload_0
      21: getfield      #9                  // Field targetCQLTypeName:Lcom/squareup/javapoet/TypeName;
      24: aastore
      25: dup
      26: iconst_3
      27: aload_0
      28: getfield      #10                 // Field targetCQLDataType:Ljava/lang/String;
      31: aastore
      32: invokestatic  #58                 // Method java/util/Objects.hash:([Ljava/lang/Object;)I
      35: ireturn

  private static void lambda$tupleType$388(java.util.StringJoiner, info.archinnov.achilles.internals.parser.context.FunctionSignature$FunctionParamSignature);
    Code:
       0: aload_0
       1: aload_1
       2: getfield      #10                 // Field targetCQLDataType:Ljava/lang/String;
       5: invokevirtual #59                 // Method java/util/StringJoiner.add:(Ljava/lang/CharSequence;)Ljava/util/StringJoiner;
       8: pop
       9: return

  private static com.squareup.javapoet.TypeName lambda$tupleType$387(info.archinnov.achilles.internals.parser.context.FunctionSignature$FunctionParamSignature);
    Code:
       0: aload_0
       1: getfield      #8                  // Field sourceTypeName:Lcom/squareup/javapoet/TypeName;
       4: areturn
}
