Compiled from "Options.java"
public final class org.apache.bookkeeper.api.kv.options.Options {
  private static final org.apache.bookkeeper.api.kv.options.DeleteOption DEFAULT_DELETE_OPTION;

  private static final org.apache.bookkeeper.api.kv.options.DeleteOption DELETE_AND_GET_OPTION;

  private static final org.apache.bookkeeper.api.kv.options.RangeOption GET_OPTION;

  private static final org.apache.bookkeeper.api.kv.options.PutOption BLIND_PUT_OPTION;

  private static final org.apache.bookkeeper.api.kv.options.PutOption PUT_AND_GET_OPTION;

  private static final org.apache.bookkeeper.api.kv.options.IncrementOption BLIND_INCREMENT_OPTION;

  private static final org.apache.bookkeeper.api.kv.options.IncrementOption INCREMENT_AND_GET_OPTION;

  public static <K> org.apache.bookkeeper.api.kv.options.PutOption<K> blindPut();
    Code:
       0: getstatic     #1                  // Field BLIND_PUT_OPTION:Lorg/apache/bookkeeper/api/kv/options/PutOption;
       3: areturn

  public static <K> org.apache.bookkeeper.api.kv.options.IncrementOption<K> blindIncrement();
    Code:
       0: getstatic     #2                  // Field BLIND_INCREMENT_OPTION:Lorg/apache/bookkeeper/api/kv/options/IncrementOption;
       3: areturn

  public static <K> org.apache.bookkeeper.api.kv.options.IncrementOption<K> incrementAndGet();
    Code:
       0: getstatic     #3                  // Field INCREMENT_AND_GET_OPTION:Lorg/apache/bookkeeper/api/kv/options/IncrementOption;
       3: areturn

  public static <K> org.apache.bookkeeper.api.kv.options.PutOption<K> putAndGet();
    Code:
       0: getstatic     #4                  // Field PUT_AND_GET_OPTION:Lorg/apache/bookkeeper/api/kv/options/PutOption;
       3: areturn

  public static <K> org.apache.bookkeeper.api.kv.options.RangeOption<K> get();
    Code:
       0: getstatic     #5                  // Field GET_OPTION:Lorg/apache/bookkeeper/api/kv/options/RangeOption;
       3: areturn

  public static <K> org.apache.bookkeeper.api.kv.options.DeleteOption<K> delete();
    Code:
       0: getstatic     #6                  // Field DEFAULT_DELETE_OPTION:Lorg/apache/bookkeeper/api/kv/options/DeleteOption;
       3: areturn

  public static <K> org.apache.bookkeeper.api.kv.options.DeleteOption<K> deleteAndGet();
    Code:
       0: getstatic     #7                  // Field DELETE_AND_GET_OPTION:Lorg/apache/bookkeeper/api/kv/options/DeleteOption;
       3: areturn

  private org.apache.bookkeeper.api.kv.options.Options();
    Code:
       0: aload_0
       1: invokespecial #8                  // Method java/lang/Object."<init>":()V
       4: return

  static {};
    Code:
       0: new           #9                  // class org/apache/bookkeeper/api/kv/options/Options$1
       3: dup
       4: invokespecial #10                 // Method org/apache/bookkeeper/api/kv/options/Options$1."<init>":()V
       7: putstatic     #6                  // Field DEFAULT_DELETE_OPTION:Lorg/apache/bookkeeper/api/kv/options/DeleteOption;
      10: new           #11                 // class org/apache/bookkeeper/api/kv/options/Options$2
      13: dup
      14: invokespecial #12                 // Method org/apache/bookkeeper/api/kv/options/Options$2."<init>":()V
      17: putstatic     #7                  // Field DELETE_AND_GET_OPTION:Lorg/apache/bookkeeper/api/kv/options/DeleteOption;
      20: new           #13                 // class org/apache/bookkeeper/api/kv/options/Options$3
      23: dup
      24: invokespecial #14                 // Method org/apache/bookkeeper/api/kv/options/Options$3."<init>":()V
      27: putstatic     #5                  // Field GET_OPTION:Lorg/apache/bookkeeper/api/kv/options/RangeOption;
      30: new           #15                 // class org/apache/bookkeeper/api/kv/options/Options$4
      33: dup
      34: invokespecial #16                 // Method org/apache/bookkeeper/api/kv/options/Options$4."<init>":()V
      37: putstatic     #1                  // Field BLIND_PUT_OPTION:Lorg/apache/bookkeeper/api/kv/options/PutOption;
      40: new           #17                 // class org/apache/bookkeeper/api/kv/options/Options$5
      43: dup
      44: invokespecial #18                 // Method org/apache/bookkeeper/api/kv/options/Options$5."<init>":()V
      47: putstatic     #4                  // Field PUT_AND_GET_OPTION:Lorg/apache/bookkeeper/api/kv/options/PutOption;
      50: new           #19                 // class org/apache/bookkeeper/api/kv/options/Options$6
      53: dup
      54: invokespecial #20                 // Method org/apache/bookkeeper/api/kv/options/Options$6."<init>":()V
      57: putstatic     #2                  // Field BLIND_INCREMENT_OPTION:Lorg/apache/bookkeeper/api/kv/options/IncrementOption;
      60: new           #21                 // class org/apache/bookkeeper/api/kv/options/Options$7
      63: dup
      64: invokespecial #22                 // Method org/apache/bookkeeper/api/kv/options/Options$7."<init>":()V
      67: putstatic     #3                  // Field INCREMENT_AND_GET_OPTION:Lorg/apache/bookkeeper/api/kv/options/IncrementOption;
      70: return
}
