public class org.bouncycastle.pqc.crypto.ntru.NTRUSigningKeyPairGenerator$FGBasis extends org.bouncycastle.pqc.crypto.ntru.NTRUSigningPrivateKeyParameters$Basis {
  public org.bouncycastle.pqc.math.ntru.polynomial.IntegerPolynomial F;

  public org.bouncycastle.pqc.math.ntru.polynomial.IntegerPolynomial G;

  final org.bouncycastle.pqc.crypto.ntru.NTRUSigningKeyPairGenerator this$0;

  org.bouncycastle.pqc.crypto.ntru.NTRUSigningKeyPairGenerator$FGBasis(org.bouncycastle.pqc.crypto.ntru.NTRUSigningKeyPairGenerator, org.bouncycastle.pqc.math.ntru.polynomial.Polynomial, org.bouncycastle.pqc.math.ntru.polynomial.Polynomial, org.bouncycastle.pqc.math.ntru.polynomial.IntegerPolynomial, org.bouncycastle.pqc.math.ntru.polynomial.IntegerPolynomial, org.bouncycastle.pqc.math.ntru.polynomial.IntegerPolynomial, org.bouncycastle.pqc.crypto.ntru.NTRUSigningKeyGenerationParameters);
    Code:
       0: aload_0
       1: aload_1
       2: putfield      #42                 // Field this$0:Lorg/bouncycastle/pqc/crypto/ntru/NTRUSigningKeyPairGenerator;
       5: aload_0
       6: aload_2
       7: aload_3
       8: aload         4
      10: aload         7
      12: invokespecial #45                 // Method org/bouncycastle/pqc/crypto/ntru/NTRUSigningPrivateKeyParameters$Basis."<init>":(Lorg/bouncycastle/pqc/math/ntru/polynomial/Polynomial;Lorg/bouncycastle/pqc/math/ntru/polynomial/Polynomial;Lorg/bouncycastle/pqc/math/ntru/polynomial/IntegerPolynomial;Lorg/bouncycastle/pqc/crypto/ntru/NTRUSigningKeyGenerationParameters;)V
      15: aload_0
      16: aload         5
      18: putfield      #43                 // Field F:Lorg/bouncycastle/pqc/math/ntru/polynomial/IntegerPolynomial;
      21: aload_0
      22: aload         6
      24: putfield      #44                 // Field G:Lorg/bouncycastle/pqc/math/ntru/polynomial/IntegerPolynomial;
      27: return

  boolean isNormOk();
    Code:
       0: aload_0
       1: getfield      #41                 // Field params:Lorg/bouncycastle/pqc/crypto/ntru/NTRUSigningKeyGenerationParameters;
       4: getfield      #39                 // Field org/bouncycastle/pqc/crypto/ntru/NTRUSigningKeyGenerationParameters.keyNormBoundSq:D
       7: dstore_1
       8: aload_0
       9: getfield      #41                 // Field params:Lorg/bouncycastle/pqc/crypto/ntru/NTRUSigningKeyGenerationParameters;
      12: getfield      #40                 // Field org/bouncycastle/pqc/crypto/ntru/NTRUSigningKeyGenerationParameters.q:I
      15: istore_3
      16: aload_0
      17: getfield      #43                 // Field F:Lorg/bouncycastle/pqc/math/ntru/polynomial/IntegerPolynomial;
      20: iload_3
      21: invokevirtual #46                 // Method org/bouncycastle/pqc/math/ntru/polynomial/IntegerPolynomial.centeredNormSq:(I)J
      24: l2d
      25: dload_1
      26: dcmpg
      27: ifge          48
      30: aload_0
      31: getfield      #44                 // Field G:Lorg/bouncycastle/pqc/math/ntru/polynomial/IntegerPolynomial;
      34: iload_3
      35: invokevirtual #46                 // Method org/bouncycastle/pqc/math/ntru/polynomial/IntegerPolynomial.centeredNormSq:(I)J
      38: l2d
      39: dload_1
      40: dcmpg
      41: ifge          48
      44: iconst_1
      45: goto          49
      48: iconst_0
      49: ireturn
}
