public class org.bouncycastle.pqc.crypto.ntru.NTRUEncryptionKeyParameters extends org.bouncycastle.crypto.params.AsymmetricKeyParameter {
  protected final org.bouncycastle.pqc.crypto.ntru.NTRUEncryptionParameters params;

  public org.bouncycastle.pqc.crypto.ntru.NTRUEncryptionKeyParameters(boolean, org.bouncycastle.pqc.crypto.ntru.NTRUEncryptionParameters);
    Code:
       0: aload_0
       1: iload_1
       2: invokespecial #15                 // Method org/bouncycastle/crypto/params/AsymmetricKeyParameter."<init>":(Z)V
       5: aload_0
       6: aload_2
       7: putfield      #14                 // Field params:Lorg/bouncycastle/pqc/crypto/ntru/NTRUEncryptionParameters;
      10: return

  public org.bouncycastle.pqc.crypto.ntru.NTRUEncryptionParameters getParameters();
    Code:
       0: aload_0
       1: getfield      #14                 // Field params:Lorg/bouncycastle/pqc/crypto/ntru/NTRUEncryptionParameters;
       4: areturn
}
