Compiled from "PlatformMBeanResourceRegistrar.java"
public class org.jboss.as.platform.mbean.PlatformMBeanResourceRegistrar {
  public static void registerPlatformMBeanResources(org.jboss.as.controller.registry.ManagementResourceRegistration);
    Code:
       0: aload_0
       1: getstatic     #1                  // Field org/jboss/as/platform/mbean/PlatformMBeanResourceDefinition.INSTANCE:Lorg/jboss/as/platform/mbean/PlatformMBeanResourceDefinition;
       4: invokeinterface #2,  2            // InterfaceMethod org/jboss/as/controller/registry/ManagementResourceRegistration.registerSubModel:(Lorg/jboss/as/controller/ResourceDefinition;)Lorg/jboss/as/controller/registry/ManagementResourceRegistration;
       9: pop
      10: return

  private org.jboss.as.platform.mbean.PlatformMBeanResourceRegistrar();
    Code:
       0: aload_0
       1: invokespecial #3                  // Method java/lang/Object."<init>":()V
       4: return
}
