Compiled from "Level.java"
public final class ch.qos.logback.classic.Level implements java.io.Serializable {
  private static final long serialVersionUID;

  public static final int OFF_INT;

  public static final int ERROR_INT;

  public static final int WARN_INT;

  public static final int INFO_INT;

  public static final int DEBUG_INT;

  public static final int TRACE_INT;

  public static final int ALL_INT;

  public static final java.lang.Integer OFF_INTEGER;

  public static final java.lang.Integer ERROR_INTEGER;

  public static final java.lang.Integer WARN_INTEGER;

  public static final java.lang.Integer INFO_INTEGER;

  public static final java.lang.Integer DEBUG_INTEGER;

  public static final java.lang.Integer TRACE_INTEGER;

  public static final java.lang.Integer ALL_INTEGER;

  public static final ch.qos.logback.classic.Level OFF;

  public static final ch.qos.logback.classic.Level ERROR;

  public static final ch.qos.logback.classic.Level WARN;

  public static final ch.qos.logback.classic.Level INFO;

  public static final ch.qos.logback.classic.Level DEBUG;

  public static final ch.qos.logback.classic.Level TRACE;

  public static final ch.qos.logback.classic.Level ALL;

  public final int levelInt;

  public final java.lang.String levelStr;

  private ch.qos.logback.classic.Level(int, java.lang.String);
    Code:
       0: aload_0
       1: invokespecial #1                  // Method java/lang/Object."<init>":()V
       4: aload_0
       5: iload_1
       6: putfield      #2                  // Field levelInt:I
       9: aload_0
      10: aload_2
      11: putfield      #3                  // Field levelStr:Ljava/lang/String;
      14: return

  public java.lang.String toString();
    Code:
       0: aload_0
       1: getfield      #3                  // Field levelStr:Ljava/lang/String;
       4: areturn

  public int toInt();
    Code:
       0: aload_0
       1: getfield      #2                  // Field levelInt:I
       4: ireturn

  public java.lang.Integer toInteger();
    Code:
       0: aload_0
       1: getfield      #2                  // Field levelInt:I
       4: lookupswitch  { // 7
           -2147483648: 72
                  5000: 76
                 10000: 80
                 20000: 84
                 30000: 88
                 40000: 92
            2147483647: 96
               default: 100
          }
      72: getstatic     #4                  // Field ALL_INTEGER:Ljava/lang/Integer;
      75: areturn
      76: getstatic     #5                  // Field TRACE_INTEGER:Ljava/lang/Integer;
      79: areturn
      80: getstatic     #6                  // Field DEBUG_INTEGER:Ljava/lang/Integer;
      83: areturn
      84: getstatic     #7                  // Field INFO_INTEGER:Ljava/lang/Integer;
      87: areturn
      88: getstatic     #8                  // Field WARN_INTEGER:Ljava/lang/Integer;
      91: areturn
      92: getstatic     #9                  // Field ERROR_INTEGER:Ljava/lang/Integer;
      95: areturn
      96: getstatic     #10                 // Field OFF_INTEGER:Ljava/lang/Integer;
      99: areturn
     100: new           #11                 // class java/lang/IllegalStateException
     103: dup
     104: new           #12                 // class java/lang/StringBuilder
     107: dup
     108: invokespecial #13                 // Method java/lang/StringBuilder."<init>":()V
     111: ldc           #14                 // String Level
     113: invokevirtual #15                 // Method java/lang/StringBuilder.append:(Ljava/lang/String;)Ljava/lang/StringBuilder;
     116: aload_0
     117: getfield      #3                  // Field levelStr:Ljava/lang/String;
     120: invokevirtual #15                 // Method java/lang/StringBuilder.append:(Ljava/lang/String;)Ljava/lang/StringBuilder;
     123: ldc           #16                 // String ,
     125: invokevirtual #15                 // Method java/lang/StringBuilder.append:(Ljava/lang/String;)Ljava/lang/StringBuilder;
     128: aload_0
     129: getfield      #2                  // Field levelInt:I
     132: invokevirtual #17                 // Method java/lang/StringBuilder.append:(I)Ljava/lang/StringBuilder;
     135: ldc           #18                 // String  is unknown.
     137: invokevirtual #15                 // Method java/lang/StringBuilder.append:(Ljava/lang/String;)Ljava/lang/StringBuilder;
     140: invokevirtual #19                 // Method java/lang/StringBuilder.toString:()Ljava/lang/String;
     143: invokespecial #20                 // Method java/lang/IllegalStateException."<init>":(Ljava/lang/String;)V
     146: athrow

  public boolean isGreaterOrEqual(ch.qos.logback.classic.Level);
    Code:
       0: aload_0
       1: getfield      #2                  // Field levelInt:I
       4: aload_1
       5: getfield      #2                  // Field levelInt:I
       8: if_icmplt     15
      11: iconst_1
      12: goto          16
      15: iconst_0
      16: ireturn

  public static ch.qos.logback.classic.Level toLevel(java.lang.String);
    Code:
       0: aload_0
       1: getstatic     #21                 // Field DEBUG:Lch/qos/logback/classic/Level;
       4: invokestatic  #22                 // Method toLevel:(Ljava/lang/String;Lch/qos/logback/classic/Level;)Lch/qos/logback/classic/Level;
       7: areturn

  public static ch.qos.logback.classic.Level valueOf(java.lang.String);
    Code:
       0: aload_0
       1: getstatic     #21                 // Field DEBUG:Lch/qos/logback/classic/Level;
       4: invokestatic  #22                 // Method toLevel:(Ljava/lang/String;Lch/qos/logback/classic/Level;)Lch/qos/logback/classic/Level;
       7: areturn

  public static ch.qos.logback.classic.Level toLevel(int);
    Code:
       0: iload_0
       1: getstatic     #21                 // Field DEBUG:Lch/qos/logback/classic/Level;
       4: invokestatic  #23                 // Method toLevel:(ILch/qos/logback/classic/Level;)Lch/qos/logback/classic/Level;
       7: areturn

  public static ch.qos.logback.classic.Level toLevel(int, ch.qos.logback.classic.Level);
    Code:
       0: iload_0
       1: lookupswitch  { // 7
           -2147483648: 68
                  5000: 72
                 10000: 76
                 20000: 80
                 30000: 84
                 40000: 88
            2147483647: 92
               default: 96
          }
      68: getstatic     #24                 // Field ALL:Lch/qos/logback/classic/Level;
      71: areturn
      72: getstatic     #25                 // Field TRACE:Lch/qos/logback/classic/Level;
      75: areturn
      76: getstatic     #21                 // Field DEBUG:Lch/qos/logback/classic/Level;
      79: areturn
      80: getstatic     #26                 // Field INFO:Lch/qos/logback/classic/Level;
      83: areturn
      84: getstatic     #27                 // Field WARN:Lch/qos/logback/classic/Level;
      87: areturn
      88: getstatic     #28                 // Field ERROR:Lch/qos/logback/classic/Level;
      91: areturn
      92: getstatic     #29                 // Field OFF:Lch/qos/logback/classic/Level;
      95: areturn
      96: aload_1
      97: areturn

  public static ch.qos.logback.classic.Level toLevel(java.lang.String, ch.qos.logback.classic.Level);
    Code:
       0: aload_0
       1: ifnonnull     6
       4: aload_1
       5: areturn
       6: aload_0
       7: ldc           #30                 // String ALL
       9: invokevirtual #31                 // Method java/lang/String.equalsIgnoreCase:(Ljava/lang/String;)Z
      12: ifeq          19
      15: getstatic     #24                 // Field ALL:Lch/qos/logback/classic/Level;
      18: areturn
      19: aload_0
      20: ldc           #32                 // String TRACE
      22: invokevirtual #31                 // Method java/lang/String.equalsIgnoreCase:(Ljava/lang/String;)Z
      25: ifeq          32
      28: getstatic     #25                 // Field TRACE:Lch/qos/logback/classic/Level;
      31: areturn
      32: aload_0
      33: ldc           #33                 // String DEBUG
      35: invokevirtual #31                 // Method java/lang/String.equalsIgnoreCase:(Ljava/lang/String;)Z
      38: ifeq          45
      41: getstatic     #21                 // Field DEBUG:Lch/qos/logback/classic/Level;
      44: areturn
      45: aload_0
      46: ldc           #34                 // String INFO
      48: invokevirtual #31                 // Method java/lang/String.equalsIgnoreCase:(Ljava/lang/String;)Z
      51: ifeq          58
      54: getstatic     #26                 // Field INFO:Lch/qos/logback/classic/Level;
      57: areturn
      58: aload_0
      59: ldc           #35                 // String WARN
      61: invokevirtual #31                 // Method java/lang/String.equalsIgnoreCase:(Ljava/lang/String;)Z
      64: ifeq          71
      67: getstatic     #27                 // Field WARN:Lch/qos/logback/classic/Level;
      70: areturn
      71: aload_0
      72: ldc           #36                 // String ERROR
      74: invokevirtual #31                 // Method java/lang/String.equalsIgnoreCase:(Ljava/lang/String;)Z
      77: ifeq          84
      80: getstatic     #28                 // Field ERROR:Lch/qos/logback/classic/Level;
      83: areturn
      84: aload_0
      85: ldc           #37                 // String OFF
      87: invokevirtual #31                 // Method java/lang/String.equalsIgnoreCase:(Ljava/lang/String;)Z
      90: ifeq          97
      93: getstatic     #29                 // Field OFF:Lch/qos/logback/classic/Level;
      96: areturn
      97: aload_1
      98: areturn

  private java.lang.Object readResolve();
    Code:
       0: aload_0
       1: getfield      #2                  // Field levelInt:I
       4: invokestatic  #38                 // Method toLevel:(I)Lch/qos/logback/classic/Level;
       7: areturn

  public static ch.qos.logback.classic.Level fromLocationAwareLoggerInteger(int);
    Code:
       0: iload_0
       1: lookupswitch  { // 5
                     0: 52
                    10: 59
                    20: 66
                    30: 73
                    40: 80
               default: 87
          }
      52: getstatic     #25                 // Field TRACE:Lch/qos/logback/classic/Level;
      55: astore_1
      56: goto          114
      59: getstatic     #21                 // Field DEBUG:Lch/qos/logback/classic/Level;
      62: astore_1
      63: goto          114
      66: getstatic     #26                 // Field INFO:Lch/qos/logback/classic/Level;
      69: astore_1
      70: goto          114
      73: getstatic     #27                 // Field WARN:Lch/qos/logback/classic/Level;
      76: astore_1
      77: goto          114
      80: getstatic     #28                 // Field ERROR:Lch/qos/logback/classic/Level;
      83: astore_1
      84: goto          114
      87: new           #39                 // class java/lang/IllegalArgumentException
      90: dup
      91: new           #12                 // class java/lang/StringBuilder
      94: dup
      95: invokespecial #13                 // Method java/lang/StringBuilder."<init>":()V
      98: iload_0
      99: invokevirtual #17                 // Method java/lang/StringBuilder.append:(I)Ljava/lang/StringBuilder;
     102: ldc           #40                 // String  not a valid level value
     104: invokevirtual #15                 // Method java/lang/StringBuilder.append:(Ljava/lang/String;)Ljava/lang/StringBuilder;
     107: invokevirtual #19                 // Method java/lang/StringBuilder.toString:()Ljava/lang/String;
     110: invokespecial #41                 // Method java/lang/IllegalArgumentException."<init>":(Ljava/lang/String;)V
     113: athrow
     114: aload_1
     115: areturn

  public static int toLocationAwareLoggerInteger(ch.qos.logback.classic.Level);
    Code:
       0: aload_0
       1: ifnonnull     14
       4: new           #39                 // class java/lang/IllegalArgumentException
       7: dup
       8: ldc           #42                 // String null level parameter is not admitted
      10: invokespecial #41                 // Method java/lang/IllegalArgumentException."<init>":(Ljava/lang/String;)V
      13: athrow
      14: aload_0
      15: invokevirtual #43                 // Method toInt:()I
      18: lookupswitch  { // 5
                  5000: 68
                 10000: 70
                 20000: 73
                 30000: 76
                 40000: 79
               default: 82
          }
      68: iconst_0
      69: ireturn
      70: bipush        10
      72: ireturn
      73: bipush        20
      75: ireturn
      76: bipush        30
      78: ireturn
      79: bipush        40
      81: ireturn
      82: new           #39                 // class java/lang/IllegalArgumentException
      85: dup
      86: new           #12                 // class java/lang/StringBuilder
      89: dup
      90: invokespecial #13                 // Method java/lang/StringBuilder."<init>":()V
      93: aload_0
      94: invokevirtual #44                 // Method java/lang/StringBuilder.append:(Ljava/lang/Object;)Ljava/lang/StringBuilder;
      97: ldc           #40                 // String  not a valid level value
      99: invokevirtual #15                 // Method java/lang/StringBuilder.append:(Ljava/lang/String;)Ljava/lang/StringBuilder;
     102: invokevirtual #19                 // Method java/lang/StringBuilder.toString:()Ljava/lang/String;
     105: invokespecial #41                 // Method java/lang/IllegalArgumentException."<init>":(Ljava/lang/String;)V
     108: athrow

  static {};
    Code:
       0: ldc           #45                 // int 2147483647
       2: invokestatic  #46                 // Method java/lang/Integer.valueOf:(I)Ljava/lang/Integer;
       5: putstatic     #10                 // Field OFF_INTEGER:Ljava/lang/Integer;
       8: ldc           #47                 // int 40000
      10: invokestatic  #46                 // Method java/lang/Integer.valueOf:(I)Ljava/lang/Integer;
      13: putstatic     #9                  // Field ERROR_INTEGER:Ljava/lang/Integer;
      16: sipush        30000
      19: invokestatic  #46                 // Method java/lang/Integer.valueOf:(I)Ljava/lang/Integer;
      22: putstatic     #8                  // Field WARN_INTEGER:Ljava/lang/Integer;
      25: sipush        20000
      28: invokestatic  #46                 // Method java/lang/Integer.valueOf:(I)Ljava/lang/Integer;
      31: putstatic     #7                  // Field INFO_INTEGER:Ljava/lang/Integer;
      34: sipush        10000
      37: invokestatic  #46                 // Method java/lang/Integer.valueOf:(I)Ljava/lang/Integer;
      40: putstatic     #6                  // Field DEBUG_INTEGER:Ljava/lang/Integer;
      43: sipush        5000
      46: invokestatic  #46                 // Method java/lang/Integer.valueOf:(I)Ljava/lang/Integer;
      49: putstatic     #5                  // Field TRACE_INTEGER:Ljava/lang/Integer;
      52: ldc           #48                 // int -2147483648
      54: invokestatic  #46                 // Method java/lang/Integer.valueOf:(I)Ljava/lang/Integer;
      57: putstatic     #4                  // Field ALL_INTEGER:Ljava/lang/Integer;
      60: new           #49                 // class ch/qos/logback/classic/Level
      63: dup
      64: ldc           #45                 // int 2147483647
      66: ldc           #37                 // String OFF
      68: invokespecial #50                 // Method "<init>":(ILjava/lang/String;)V
      71: putstatic     #29                 // Field OFF:Lch/qos/logback/classic/Level;
      74: new           #49                 // class ch/qos/logback/classic/Level
      77: dup
      78: ldc           #47                 // int 40000
      80: ldc           #36                 // String ERROR
      82: invokespecial #50                 // Method "<init>":(ILjava/lang/String;)V
      85: putstatic     #28                 // Field ERROR:Lch/qos/logback/classic/Level;
      88: new           #49                 // class ch/qos/logback/classic/Level
      91: dup
      92: sipush        30000
      95: ldc           #35                 // String WARN
      97: invokespecial #50                 // Method "<init>":(ILjava/lang/String;)V
     100: putstatic     #27                 // Field WARN:Lch/qos/logback/classic/Level;
     103: new           #49                 // class ch/qos/logback/classic/Level
     106: dup
     107: sipush        20000
     110: ldc           #34                 // String INFO
     112: invokespecial #50                 // Method "<init>":(ILjava/lang/String;)V
     115: putstatic     #26                 // Field INFO:Lch/qos/logback/classic/Level;
     118: new           #49                 // class ch/qos/logback/classic/Level
     121: dup
     122: sipush        10000
     125: ldc           #33                 // String DEBUG
     127: invokespecial #50                 // Method "<init>":(ILjava/lang/String;)V
     130: putstatic     #21                 // Field DEBUG:Lch/qos/logback/classic/Level;
     133: new           #49                 // class ch/qos/logback/classic/Level
     136: dup
     137: sipush        5000
     140: ldc           #32                 // String TRACE
     142: invokespecial #50                 // Method "<init>":(ILjava/lang/String;)V
     145: putstatic     #25                 // Field TRACE:Lch/qos/logback/classic/Level;
     148: new           #49                 // class ch/qos/logback/classic/Level
     151: dup
     152: ldc           #48                 // int -2147483648
     154: ldc           #30                 // String ALL
     156: invokespecial #50                 // Method "<init>":(ILjava/lang/String;)V
     159: putstatic     #24                 // Field ALL:Lch/qos/logback/classic/Level;
     162: return
}
