Compiled from "L1WriteSynchronizer.java"
class org.infinispan.interceptors.distribution.L1WriteSynchronizer$L1WriteSync extends java.util.concurrent.locks.AbstractQueuedSynchronizer {
  private static final int READY;

  private static final int RUNNING;

  private static final int SKIP;

  private static final int COMPLETED;

  private java.lang.Object result;

  private java.lang.Throwable exception;

  private org.infinispan.interceptors.distribution.L1WriteSynchronizer$L1WriteSync();
    Code:
       0: aload_0
       1: invokespecial #2                  // Method java/util/concurrent/locks/AbstractQueuedSynchronizer."<init>":()V
       4: return

  protected int tryAcquireShared(int);
    Code:
       0: aload_0
       1: invokevirtual #3                  // Method getState:()I
       4: iconst_4
       5: if_icmpne     12
       8: iconst_1
       9: goto          13
      12: iconst_m1
      13: ireturn

  protected boolean tryReleaseShared(int);
    Code:
       0: iconst_1
       1: ireturn

  boolean attemptUpdateToRunning();
    Code:
       0: aload_0
       1: invokevirtual #3                  // Method getState:()I
       4: iconst_1
       5: if_icmpne     10
       8: iconst_1
       9: ireturn
      10: aload_0
      11: iconst_0
      12: iconst_1
      13: invokevirtual #5                  // Method compareAndSetState:(II)Z
      16: ireturn

  boolean attemptToSkipFullRun();
    Code:
       0: aload_0
       1: invokevirtual #3                  // Method getState:()I
       4: iconst_2
       5: if_icmpne     10
       8: iconst_1
       9: ireturn
      10: aload_0
      11: iconst_0
      12: iconst_2
      13: invokevirtual #5                  // Method compareAndSetState:(II)Z
      16: ireturn

  java.lang.Object innerGet() throws java.lang.InterruptedException, java.util.concurrent.ExecutionException;
    Code:
       0: aload_0
       1: iconst_0
       2: invokevirtual #6                  // Method acquireSharedInterruptibly:(I)V
       5: aload_0
       6: getfield      #7                  // Field exception:Ljava/lang/Throwable;
       9: ifnull        24
      12: new           #8                  // class java/util/concurrent/ExecutionException
      15: dup
      16: aload_0
      17: getfield      #7                  // Field exception:Ljava/lang/Throwable;
      20: invokespecial #9                  // Method java/util/concurrent/ExecutionException."<init>":(Ljava/lang/Throwable;)V
      23: athrow
      24: aload_0
      25: getfield      #10                 // Field result:Ljava/lang/Object;
      28: areturn

  java.lang.Object innerGet(long, java.util.concurrent.TimeUnit) throws java.lang.InterruptedException, java.util.concurrent.TimeoutException, java.util.concurrent.ExecutionException;
    Code:
       0: aload_0
       1: iconst_0
       2: aload_3
       3: lload_1
       4: invokevirtual #11                 // Method java/util/concurrent/TimeUnit.toNanos:(J)J
       7: invokevirtual #12                 // Method tryAcquireSharedNanos:(IJ)Z
      10: ifne          21
      13: new           #13                 // class java/util/concurrent/TimeoutException
      16: dup
      17: invokespecial #14                 // Method java/util/concurrent/TimeoutException."<init>":()V
      20: athrow
      21: aload_0
      22: getfield      #7                  // Field exception:Ljava/lang/Throwable;
      25: ifnull        40
      28: new           #8                  // class java/util/concurrent/ExecutionException
      31: dup
      32: aload_0
      33: getfield      #7                  // Field exception:Ljava/lang/Throwable;
      36: invokespecial #9                  // Method java/util/concurrent/ExecutionException."<init>":(Ljava/lang/Throwable;)V
      39: athrow
      40: aload_0
      41: getfield      #10                 // Field result:Ljava/lang/Object;
      44: areturn

  void innerSet(java.lang.Object);
    Code:
       0: aload_0
       1: invokevirtual #3                  // Method getState:()I
       4: istore_2
       5: iload_2
       6: iconst_4
       7: if_icmpne     11
      10: return
      11: aload_0
      12: iload_2
      13: iconst_4
      14: invokevirtual #5                  // Method compareAndSetState:(II)Z
      17: ifeq          32
      20: aload_0
      21: aload_1
      22: putfield      #10                 // Field result:Ljava/lang/Object;
      25: aload_0
      26: iconst_0
      27: invokevirtual #15                 // Method releaseShared:(I)Z
      30: pop
      31: return
      32: goto          0

  void innerException(java.lang.Throwable);
    Code:
       0: aload_0
       1: invokevirtual #3                  // Method getState:()I
       4: istore_2
       5: iload_2
       6: iconst_4
       7: if_icmpne     11
      10: return
      11: aload_0
      12: iload_2
      13: iconst_4
      14: invokevirtual #5                  // Method compareAndSetState:(II)Z
      17: ifeq          32
      20: aload_0
      21: aload_1
      22: putfield      #7                  // Field exception:Ljava/lang/Throwable;
      25: aload_0
      26: iconst_0
      27: invokevirtual #15                 // Method releaseShared:(I)Z
      30: pop
      31: return
      32: goto          0

  org.infinispan.interceptors.distribution.L1WriteSynchronizer$L1WriteSync(org.infinispan.interceptors.distribution.L1WriteSynchronizer$1);
    Code:
       0: aload_0
       1: invokespecial #1                  // Method "<init>":()V
       4: return
}
