Compiled from "Json.java"
public final class cool.scx.core.vo.Json implements cool.scx.core.vo.BaseVo {
  private final cool.scx.core.vo.JsonBodyWrapper<java.util.Map<java.lang.String, java.lang.Object>> jsonBodyWrapper;

  private cool.scx.core.vo.Json(java.lang.String);
    Code:
       0: aload_0
       1: invokespecial #1                  // Method java/lang/Object."<init>":()V
       4: aload_0
       5: new           #7                  // class cool/scx/core/vo/JsonBodyWrapper
       8: dup
       9: aload_1
      10: new           #9                  // class java/util/HashMap
      13: dup
      14: invokespecial #11                 // Method java/util/HashMap."<init>":()V
      17: invokespecial #12                 // Method cool/scx/core/vo/JsonBodyWrapper."<init>":(Ljava/lang/String;Ljava/lang/Object;)V
      20: putfield      #15                 // Field jsonBodyWrapper:Lcool/scx/core/vo/JsonBodyWrapper;
      23: return

  public static cool.scx.core.vo.Json ok();
    Code:
       0: new           #16                 // class cool/scx/core/vo/Json
       3: dup
       4: ldc           #21                 // String ok
       6: invokespecial #23                 // Method "<init>":(Ljava/lang/String;)V
       9: areturn

  public static cool.scx.core.vo.Json fail();
    Code:
       0: new           #16                 // class cool/scx/core/vo/Json
       3: dup
       4: ldc           #26                 // String fail
       6: invokespecial #23                 // Method "<init>":(Ljava/lang/String;)V
       9: areturn

  public static cool.scx.core.vo.Json fail(java.lang.String);
    Code:
       0: new           #16                 // class cool/scx/core/vo/Json
       3: dup
       4: aload_0
       5: invokespecial #23                 // Method "<init>":(Ljava/lang/String;)V
       8: areturn

  public cool.scx.core.vo.Json put(java.lang.String, java.lang.Object);
    Code:
       0: aload_0
       1: getfield      #15                 // Field jsonBodyWrapper:Lcool/scx/core/vo/JsonBodyWrapper;
       4: getfield      #28                 // Field cool/scx/core/vo/JsonBodyWrapper.data:Ljava/lang/Object;
       7: checkcast     #32                 // class java/util/Map
      10: aload_1
      11: aload_2
      12: invokeinterface #34,  3           // InterfaceMethod java/util/Map.put:(Ljava/lang/Object;Ljava/lang/Object;)Ljava/lang/Object;
      17: pop
      18: aload_0
      19: areturn

  public void handle(io.vertx.ext.web.RoutingContext);
    Code:
       0: aload_1
       1: invokeinterface #38,  1           // InterfaceMethod io/vertx/ext/web/RoutingContext.request:()Lio/vertx/core/http/HttpServerRequest;
       6: invokeinterface #44,  1           // InterfaceMethod io/vertx/core/http/HttpServerRequest.response:()Lio/vertx/core/http/HttpServerResponse;
      11: invokestatic  #50                 // InterfaceMethod cool/scx/core/vo/BaseVo.fillJsonContentType:(Lio/vertx/core/http/HttpServerResponse;)Lio/vertx/core/http/HttpServerResponse;
      14: aload_0
      15: ldc           #56                 // String
      17: invokevirtual #58                 // Method toJson:(Ljava/lang/String;)Ljava/lang/String;
      20: invokeinterface #62,  2           // InterfaceMethod io/vertx/core/http/HttpServerResponse.end:(Ljava/lang/String;)Lio/vertx/core/Future;
      25: pop
      26: return

  public java.lang.String toJson() throws com.fasterxml.jackson.core.JsonProcessingException;
    Code:
       0: aload_0
       1: getfield      #15                 // Field jsonBodyWrapper:Lcool/scx/core/vo/JsonBodyWrapper;
       4: invokestatic  #68                 // InterfaceMethod cool/scx/core/vo/BaseVo.toJson:(Ljava/lang/Object;)Ljava/lang/String;
       7: areturn

  public java.lang.String toJson(java.lang.String);
    Code:
       0: aload_0
       1: getfield      #15                 // Field jsonBodyWrapper:Lcool/scx/core/vo/JsonBodyWrapper;
       4: aload_1
       5: invokestatic  #71                 // InterfaceMethod cool/scx/core/vo/BaseVo.toJson:(Ljava/lang/Object;Ljava/lang/String;)Ljava/lang/String;
       8: areturn

  public void handle(java.lang.Object) throws java.lang.Exception;
    Code:
       0: aload_0
       1: aload_1
       2: checkcast     #39                 // class io/vertx/ext/web/RoutingContext
       5: invokevirtual #74                 // Method handle:(Lio/vertx/ext/web/RoutingContext;)V
       8: return
}
