Compiled from "Redirections.java"
public final class cool.scx.core.vo.Redirections implements cool.scx.core.vo.BaseVo {
  private final java.lang.String location;

  private final int statusCode;

  private cool.scx.core.vo.Redirections(java.lang.String, int);
    Code:
       0: aload_0
       1: invokespecial #1                  // Method java/lang/Object."<init>":()V
       4: aload_0
       5: aload_1
       6: putfield      #7                  // Field location:Ljava/lang/String;
       9: aload_0
      10: iload_2
      11: putfield      #13                 // Field statusCode:I
      14: return

  public static cool.scx.core.vo.Redirections ofPermanent(java.lang.String);
    Code:
       0: new           #8                  // class cool/scx/core/vo/Redirections
       3: dup
       4: aload_0
       5: sipush        301
       8: invokespecial #17                 // Method "<init>":(Ljava/lang/String;I)V
      11: areturn

  public static cool.scx.core.vo.Redirections ofTemporary(java.lang.String);
    Code:
       0: new           #8                  // class cool/scx/core/vo/Redirections
       3: dup
       4: aload_0
       5: sipush        302
       8: invokespecial #17                 // Method "<init>":(Ljava/lang/String;I)V
      11: areturn

  public void handle(io.vertx.ext.web.RoutingContext);
    Code:
       0: aload_1
       1: invokeinterface #20,  1           // InterfaceMethod io/vertx/ext/web/RoutingContext.request:()Lio/vertx/core/http/HttpServerRequest;
       6: invokeinterface #26,  1           // InterfaceMethod io/vertx/core/http/HttpServerRequest.response:()Lio/vertx/core/http/HttpServerResponse;
      11: getstatic     #32                 // Field io/netty/handler/codec/http/HttpHeaderNames.LOCATION:Lio/netty/util/AsciiString;
      14: aload_0
      15: getfield      #7                  // Field location:Ljava/lang/String;
      18: invokeinterface #38,  3           // InterfaceMethod io/vertx/core/http/HttpServerResponse.putHeader:(Ljava/lang/CharSequence;Ljava/lang/CharSequence;)Lio/vertx/core/http/HttpServerResponse;
      23: aload_0
      24: getfield      #13                 // Field statusCode:I
      27: invokeinterface #44,  2           // InterfaceMethod io/vertx/core/http/HttpServerResponse.setStatusCode:(I)Lio/vertx/core/http/HttpServerResponse;
      32: invokeinterface #48,  1           // InterfaceMethod io/vertx/core/http/HttpServerResponse.end:()Lio/vertx/core/Future;
      37: pop
      38: return

  public void handle(java.lang.Object) throws java.lang.Exception;
    Code:
       0: aload_0
       1: aload_1
       2: checkcast     #21                 // class io/vertx/ext/web/RoutingContext
       5: invokevirtual #52                 // Method handle:(Lio/vertx/ext/web/RoutingContext;)V
       8: return
}
