Compiled from "ServiceURI.java"
public class org.apache.pulsar.common.net.ServiceURI {
  private static final java.lang.String BINARY_SERVICE;

  private static final java.lang.String HTTP_SERVICE;

  private static final java.lang.String HTTPS_SERVICE;

  private static final java.lang.String SSL_SERVICE;

  private static final int BINARY_PORT;

  private static final int BINARY_TLS_PORT;

  private static final int HTTP_PORT;

  private static final int HTTPS_PORT;

  private final java.lang.String serviceName;

  private final java.lang.String[] serviceInfos;

  private final java.lang.String serviceUser;

  private final java.lang.String[] serviceHosts;

  private final java.lang.String servicePath;

  private final java.net.URI uri;

  public static org.apache.pulsar.common.net.ServiceURI create(java.lang.String);
    Code:
       0: aload_0
       1: ldc           #1                  // String service uri string is null
       3: invokestatic  #2                  // Method com/google/common/base/Preconditions.checkNotNull:(Ljava/lang/Object;Ljava/lang/Object;)Ljava/lang/Object;
       6: pop
       7: aload_0
       8: ldc           #3                  // String [
      10: invokevirtual #4                  // Method java/lang/String.contains:(Ljava/lang/CharSequence;)Z
      13: ifeq          276
      16: aload_0
      17: ldc           #5                  // String ]
      19: invokevirtual #4                  // Method java/lang/String.contains:(Ljava/lang/CharSequence;)Z
      22: ifeq          276
      25: ldc           #6                  // String ,;
      27: invokestatic  #7                  // Method com/google/common/base/CharMatcher.anyOf:(Ljava/lang/CharSequence;)Lcom/google/common/base/CharMatcher;
      30: invokestatic  #8                  // Method com/google/common/base/Splitter.on:(Lcom/google/common/base/CharMatcher;)Lcom/google/common/base/Splitter;
      33: astore_1
      34: aload_1
      35: aload_0
      36: invokevirtual #9                  // Method com/google/common/base/Splitter.splitToList:(Ljava/lang/CharSequence;)Ljava/util/List;
      39: astore_2
      40: aload_2
      41: invokeinterface #10,  1           // InterfaceMethod java/util/List.size:()I
      46: iconst_1
      47: if_icmple     276
      50: aload_2
      51: iconst_0
      52: invokeinterface #11,  2           // InterfaceMethod java/util/List.get:(I)Ljava/lang/Object;
      57: checkcast     #12                 // class java/lang/String
      60: astore_3
      61: aload_2
      62: aload_2
      63: invokeinterface #10,  1           // InterfaceMethod java/util/List.size:()I
      68: iconst_1
      69: isub
      70: invokeinterface #11,  2           // InterfaceMethod java/util/List.get:(I)Ljava/lang/Object;
      75: checkcast     #12                 // class java/lang/String
      78: astore        4
      80: aload         4
      82: ldc           #13                 // String /
      84: invokevirtual #4                  // Method java/lang/String.contains:(Ljava/lang/CharSequence;)Z
      87: istore        5
      89: iload         5
      91: ifeq          109
      94: aload         4
      96: aload         4
      98: ldc           #13                 // String /
     100: invokevirtual #14                 // Method java/lang/String.indexOf:(Ljava/lang/String;)I
     103: invokevirtual #15                 // Method java/lang/String.substring:(I)Ljava/lang/String;
     106: goto          111
     109: ldc           #16                 // String
     111: astore        6
     113: new           #17                 // class java/lang/StringBuilder
     116: dup
     117: invokespecial #18                 // Method java/lang/StringBuilder."<init>":()V
     120: aload_3
     121: invokevirtual #19                 // Method java/lang/StringBuilder.append:(Ljava/lang/String;)Ljava/lang/StringBuilder;
     124: aload         6
     126: invokevirtual #19                 // Method java/lang/StringBuilder.append:(Ljava/lang/String;)Ljava/lang/StringBuilder;
     129: invokevirtual #20                 // Method java/lang/StringBuilder.toString:()Ljava/lang/String;
     132: astore_3
     133: aload_3
     134: invokestatic  #21                 // Method java/net/URI.create:(Ljava/lang/String;)Ljava/net/URI;
     137: astore        7
     139: aload         7
     141: invokestatic  #22                 // Method create:(Ljava/net/URI;)Lorg/apache/pulsar/common/net/ServiceURI;
     144: astore        8
     146: new           #23                 // class java/util/ArrayList
     149: dup
     150: invokespecial #24                 // Method java/util/ArrayList."<init>":()V
     153: astore        9
     155: aload         9
     157: aload         8
     159: invokevirtual #25                 // Method getServiceHosts:()[Ljava/lang/String;
     162: iconst_0
     163: aaload
     164: invokeinterface #26,  2           // InterfaceMethod java/util/List.add:(Ljava/lang/Object;)Z
     169: pop
     170: aload         9
     172: aload_2
     173: iconst_1
     174: aload_2
     175: invokeinterface #10,  1           // InterfaceMethod java/util/List.size:()I
     180: invokeinterface #27,  3           // InterfaceMethod java/util/List.subList:(II)Ljava/util/List;
     185: invokeinterface #28,  2           // InterfaceMethod java/util/List.addAll:(Ljava/util/Collection;)Z
     190: pop
     191: aload         9
     193: invokeinterface #29,  1           // InterfaceMethod java/util/List.stream:()Ljava/util/stream/Stream;
     198: aload         8
     200: invokedynamic #30,  0             // InvokeDynamic #0:apply:(Lorg/apache/pulsar/common/net/ServiceURI;)Ljava/util/function/Function;
     205: invokeinterface #31,  2           // InterfaceMethod java/util/stream/Stream.map:(Ljava/util/function/Function;)Ljava/util/stream/Stream;
     210: invokestatic  #32                 // Method java/util/stream/Collectors.toList:()Ljava/util/stream/Collector;
     213: invokeinterface #33,  2           // InterfaceMethod java/util/stream/Stream.collect:(Ljava/util/stream/Collector;)Ljava/lang/Object;
     218: checkcast     #34                 // class java/util/List
     221: astore        9
     223: new           #35                 // class org/apache/pulsar/common/net/ServiceURI
     226: dup
     227: aload         8
     229: invokevirtual #36                 // Method getServiceName:()Ljava/lang/String;
     232: aload         8
     234: invokevirtual #37                 // Method getServiceInfos:()[Ljava/lang/String;
     237: aload         8
     239: invokevirtual #38                 // Method getServiceUser:()Ljava/lang/String;
     242: aload         9
     244: aload         9
     246: invokeinterface #10,  1           // InterfaceMethod java/util/List.size:()I
     251: anewarray     #12                 // class java/lang/String
     254: invokeinterface #39,  2           // InterfaceMethod java/util/List.toArray:([Ljava/lang/Object;)[Ljava/lang/Object;
     259: checkcast     #40                 // class "[Ljava/lang/String;"
     262: aload         8
     264: invokevirtual #41                 // Method getServicePath:()Ljava/lang/String;
     267: aload         8
     269: invokevirtual #42                 // Method getUri:()Ljava/net/URI;
     272: invokespecial #43                 // Method "<init>":(Ljava/lang/String;[Ljava/lang/String;Ljava/lang/String;[Ljava/lang/String;Ljava/lang/String;Ljava/net/URI;)V
     275: areturn
     276: aload_0
     277: invokestatic  #21                 // Method java/net/URI.create:(Ljava/lang/String;)Ljava/net/URI;
     280: astore_1
     281: aload_1
     282: invokestatic  #22                 // Method create:(Ljava/net/URI;)Lorg/apache/pulsar/common/net/ServiceURI;
     285: areturn

  public static org.apache.pulsar.common.net.ServiceURI create(java.net.URI);
    Code:
       0: aload_0
       1: ldc           #44                 // String service uri instance is null
       3: invokestatic  #2                  // Method com/google/common/base/Preconditions.checkNotNull:(Ljava/lang/Object;Ljava/lang/Object;)Ljava/lang/Object;
       6: pop
       7: aload_0
       8: invokevirtual #45                 // Method java/net/URI.getScheme:()Ljava/lang/String;
      11: astore_3
      12: aconst_null
      13: aload_3
      14: if_acmpeq     61
      17: aload_3
      18: invokevirtual #46                 // Method java/lang/String.toLowerCase:()Ljava/lang/String;
      21: astore_3
      22: ldc           #47                 // String +
      24: astore        4
      26: aload_3
      27: ldc           #47                 // String +
      29: invokestatic  #48                 // Method org/apache/commons/lang/StringUtils.split:(Ljava/lang/String;Ljava/lang/String;)[Ljava/lang/String;
      32: astore        5
      34: aload         5
      36: iconst_0
      37: aaload
      38: astore_1
      39: aload         5
      41: arraylength
      42: iconst_1
      43: isub
      44: anewarray     #12                 // class java/lang/String
      47: astore_2
      48: aload         5
      50: iconst_1
      51: aload_2
      52: iconst_0
      53: aload_2
      54: arraylength
      55: invokestatic  #49                 // Method java/lang/System.arraycopy:(Ljava/lang/Object;ILjava/lang/Object;II)V
      58: goto          68
      61: aconst_null
      62: astore_1
      63: iconst_0
      64: anewarray     #12                 // class java/lang/String
      67: astore_2
      68: aload_0
      69: invokevirtual #50                 // Method java/net/URI.getAuthority:()Ljava/lang/String;
      72: astore        4
      74: aload         4
      76: invokestatic  #51                 // Method com/google/common/base/Strings.isNullOrEmpty:(Ljava/lang/String;)Z
      79: ifne          86
      82: iconst_1
      83: goto          87
      86: iconst_0
      87: new           #17                 // class java/lang/StringBuilder
      90: dup
      91: invokespecial #18                 // Method java/lang/StringBuilder."<init>":()V
      94: ldc           #52                 // String authority component is missing in service uri :
      96: invokevirtual #19                 // Method java/lang/StringBuilder.append:(Ljava/lang/String;)Ljava/lang/StringBuilder;
      99: aload_0
     100: invokevirtual #53                 // Method java/lang/StringBuilder.append:(Ljava/lang/Object;)Ljava/lang/StringBuilder;
     103: invokevirtual #20                 // Method java/lang/StringBuilder.toString:()Ljava/lang/String;
     106: invokestatic  #54                 // Method com/google/common/base/Preconditions.checkArgument:(ZLjava/lang/Object;)V
     109: aload         4
     111: bipush        64
     113: invokevirtual #55                 // Method java/lang/String.indexOf:(I)I
     116: istore        7
     118: ldc           #6                  // String ,;
     120: invokestatic  #7                  // Method com/google/common/base/CharMatcher.anyOf:(Ljava/lang/CharSequence;)Lcom/google/common/base/CharMatcher;
     123: invokestatic  #8                  // Method com/google/common/base/Splitter.on:(Lcom/google/common/base/CharMatcher;)Lcom/google/common/base/Splitter;
     126: astore        8
     128: iload         7
     130: ifle          162
     133: aload         4
     135: iconst_0
     136: iload         7
     138: invokevirtual #56                 // Method java/lang/String.substring:(II)Ljava/lang/String;
     141: astore        5
     143: aload         8
     145: aload         4
     147: iload         7
     149: iconst_1
     150: iadd
     151: invokevirtual #15                 // Method java/lang/String.substring:(I)Ljava/lang/String;
     154: invokevirtual #9                  // Method com/google/common/base/Splitter.splitToList:(Ljava/lang/CharSequence;)Ljava/util/List;
     157: astore        6
     159: goto          174
     162: aconst_null
     163: astore        5
     165: aload         8
     167: aload         4
     169: invokevirtual #9                  // Method com/google/common/base/Splitter.splitToList:(Ljava/lang/CharSequence;)Ljava/util/List;
     172: astore        6
     174: aload         6
     176: invokeinterface #29,  1           // InterfaceMethod java/util/List.stream:()Ljava/util/stream/Stream;
     181: aload_1
     182: aload_2
     183: invokedynamic #57,  0             // InvokeDynamic #1:apply:(Ljava/lang/String;[Ljava/lang/String;)Ljava/util/function/Function;
     188: invokeinterface #31,  2           // InterfaceMethod java/util/stream/Stream.map:(Ljava/util/function/Function;)Ljava/util/stream/Stream;
     193: invokestatic  #32                 // Method java/util/stream/Collectors.toList:()Ljava/util/stream/Collector;
     196: invokeinterface #33,  2           // InterfaceMethod java/util/stream/Stream.collect:(Ljava/util/stream/Collector;)Ljava/lang/Object;
     201: checkcast     #34                 // class java/util/List
     204: astore        6
     206: aload_0
     207: invokevirtual #58                 // Method java/net/URI.getPath:()Ljava/lang/String;
     210: astore        9
     212: aconst_null
     213: aload         9
     215: if_acmpeq     222
     218: iconst_1
     219: goto          223
     222: iconst_0
     223: new           #17                 // class java/lang/StringBuilder
     226: dup
     227: invokespecial #18                 // Method java/lang/StringBuilder."<init>":()V
     230: ldc           #59                 // String service path component is missing in service uri :
     232: invokevirtual #19                 // Method java/lang/StringBuilder.append:(Ljava/lang/String;)Ljava/lang/StringBuilder;
     235: aload_0
     236: invokevirtual #53                 // Method java/lang/StringBuilder.append:(Ljava/lang/Object;)Ljava/lang/StringBuilder;
     239: invokevirtual #20                 // Method java/lang/StringBuilder.toString:()Ljava/lang/String;
     242: invokestatic  #54                 // Method com/google/common/base/Preconditions.checkArgument:(ZLjava/lang/Object;)V
     245: new           #35                 // class org/apache/pulsar/common/net/ServiceURI
     248: dup
     249: aload_1
     250: aload_2
     251: aload         5
     253: aload         6
     255: aload         6
     257: invokeinterface #10,  1           // InterfaceMethod java/util/List.size:()I
     262: anewarray     #12                 // class java/lang/String
     265: invokeinterface #39,  2           // InterfaceMethod java/util/List.toArray:([Ljava/lang/Object;)[Ljava/lang/Object;
     270: checkcast     #40                 // class "[Ljava/lang/String;"
     273: aload         9
     275: aload_0
     276: invokespecial #43                 // Method "<init>":(Ljava/lang/String;[Ljava/lang/String;Ljava/lang/String;[Ljava/lang/String;Ljava/lang/String;Ljava/net/URI;)V
     279: areturn

  private static java.lang.String validateHostName(java.lang.String, java.lang.String[], java.lang.String);
    Code:
       0: aconst_null
       1: astore_3
       2: new           #17                 // class java/lang/StringBuilder
       5: dup
       6: invokespecial #18                 // Method java/lang/StringBuilder."<init>":()V
       9: ldc           #60                 // String dummyscheme://
      11: invokevirtual #19                 // Method java/lang/StringBuilder.append:(Ljava/lang/String;)Ljava/lang/StringBuilder;
      14: aload_2
      15: invokevirtual #19                 // Method java/lang/StringBuilder.append:(Ljava/lang/String;)Ljava/lang/StringBuilder;
      18: invokevirtual #20                 // Method java/lang/StringBuilder.toString:()Ljava/lang/String;
      21: invokestatic  #21                 // Method java/net/URI.create:(Ljava/lang/String;)Ljava/net/URI;
      24: astore_3
      25: goto          57
      28: astore        4
      30: new           #61                 // class java/lang/IllegalArgumentException
      33: dup
      34: new           #17                 // class java/lang/StringBuilder
      37: dup
      38: invokespecial #18                 // Method java/lang/StringBuilder."<init>":()V
      41: ldc           #62                 // String Invalid hostname :
      43: invokevirtual #19                 // Method java/lang/StringBuilder.append:(Ljava/lang/String;)Ljava/lang/StringBuilder;
      46: aload_2
      47: invokevirtual #19                 // Method java/lang/StringBuilder.append:(Ljava/lang/String;)Ljava/lang/StringBuilder;
      50: invokevirtual #20                 // Method java/lang/StringBuilder.toString:()Ljava/lang/String;
      53: invokespecial #63                 // Method java/lang/IllegalArgumentException."<init>":(Ljava/lang/String;)V
      56: athrow
      57: aload_3
      58: invokevirtual #64                 // Method java/net/URI.getHost:()Ljava/lang/String;
      61: astore        4
      63: aload         4
      65: ifnonnull     95
      68: new           #61                 // class java/lang/IllegalArgumentException
      71: dup
      72: new           #17                 // class java/lang/StringBuilder
      75: dup
      76: invokespecial #18                 // Method java/lang/StringBuilder."<init>":()V
      79: ldc           #62                 // String Invalid hostname :
      81: invokevirtual #19                 // Method java/lang/StringBuilder.append:(Ljava/lang/String;)Ljava/lang/StringBuilder;
      84: aload_2
      85: invokevirtual #19                 // Method java/lang/StringBuilder.append:(Ljava/lang/String;)Ljava/lang/StringBuilder;
      88: invokevirtual #20                 // Method java/lang/StringBuilder.toString:()Ljava/lang/String;
      91: invokespecial #63                 // Method java/lang/IllegalArgumentException."<init>":(Ljava/lang/String;)V
      94: athrow
      95: aload_3
      96: invokevirtual #65                 // Method java/net/URI.getPort:()I
      99: istore        5
     101: iload         5
     103: iconst_m1
     104: if_icmpne     114
     107: aload_0
     108: aload_1
     109: invokestatic  #66                 // Method getServicePort:(Ljava/lang/String;[Ljava/lang/String;)I
     112: istore        5
     114: new           #17                 // class java/lang/StringBuilder
     117: dup
     118: invokespecial #18                 // Method java/lang/StringBuilder."<init>":()V
     121: aload         4
     123: invokevirtual #19                 // Method java/lang/StringBuilder.append:(Ljava/lang/String;)Ljava/lang/StringBuilder;
     126: ldc           #67                 // String :
     128: invokevirtual #19                 // Method java/lang/StringBuilder.append:(Ljava/lang/String;)Ljava/lang/StringBuilder;
     131: iload         5
     133: invokevirtual #68                 // Method java/lang/StringBuilder.append:(I)Ljava/lang/StringBuilder;
     136: invokevirtual #20                 // Method java/lang/StringBuilder.toString:()Ljava/lang/String;
     139: areturn
    Exception table:
       from    to  target type
           2    25    28   Class java/lang/IllegalArgumentException

  public java.lang.String[] getServiceInfos();
    Code:
       0: aload_0
       1: getfield      #69                 // Field serviceInfos:[Ljava/lang/String;
       4: areturn

  public java.lang.String[] getServiceHosts();
    Code:
       0: aload_0
       1: getfield      #70                 // Field serviceHosts:[Ljava/lang/String;
       4: areturn

  public java.lang.String getServiceScheme();
    Code:
       0: aconst_null
       1: aload_0
       2: getfield      #71                 // Field serviceName:Ljava/lang/String;
       5: if_acmpne     10
       8: aconst_null
       9: areturn
      10: aload_0
      11: getfield      #69                 // Field serviceInfos:[Ljava/lang/String;
      14: arraylength
      15: ifne          23
      18: aload_0
      19: getfield      #71                 // Field serviceName:Ljava/lang/String;
      22: areturn
      23: new           #17                 // class java/lang/StringBuilder
      26: dup
      27: invokespecial #18                 // Method java/lang/StringBuilder."<init>":()V
      30: aload_0
      31: getfield      #71                 // Field serviceName:Ljava/lang/String;
      34: invokevirtual #19                 // Method java/lang/StringBuilder.append:(Ljava/lang/String;)Ljava/lang/StringBuilder;
      37: ldc           #47                 // String +
      39: invokevirtual #19                 // Method java/lang/StringBuilder.append:(Ljava/lang/String;)Ljava/lang/StringBuilder;
      42: aload_0
      43: getfield      #69                 // Field serviceInfos:[Ljava/lang/String;
      46: bipush        43
      48: invokestatic  #72                 // Method org/apache/commons/lang/StringUtils.join:([Ljava/lang/Object;C)Ljava/lang/String;
      51: invokevirtual #19                 // Method java/lang/StringBuilder.append:(Ljava/lang/String;)Ljava/lang/StringBuilder;
      54: invokevirtual #20                 // Method java/lang/StringBuilder.toString:()Ljava/lang/String;
      57: areturn

  private static int getServicePort(java.lang.String, java.lang.String[]);
    Code:
       0: aload_0
       1: invokevirtual #46                 // Method java/lang/String.toLowerCase:()Ljava/lang/String;
       4: astore_3
       5: iconst_m1
       6: istore        4
       8: aload_3
       9: invokevirtual #73                 // Method java/lang/String.hashCode:()I
      12: lookupswitch  { // 3
            -977119363: 48
               3213448: 63
              99617003: 78
               default: 90
          }
      48: aload_3
      49: ldc           #74                 // String pulsar
      51: invokevirtual #75                 // Method java/lang/String.equals:(Ljava/lang/Object;)Z
      54: ifeq          90
      57: iconst_0
      58: istore        4
      60: goto          90
      63: aload_3
      64: ldc           #76                 // String http
      66: invokevirtual #75                 // Method java/lang/String.equals:(Ljava/lang/Object;)Z
      69: ifeq          90
      72: iconst_1
      73: istore        4
      75: goto          90
      78: aload_3
      79: ldc           #77                 // String https
      81: invokevirtual #75                 // Method java/lang/String.equals:(Ljava/lang/Object;)Z
      84: ifeq          90
      87: iconst_2
      88: istore        4
      90: iload         4
      92: tableswitch   { // 0 to 2
                     0: 120
                     1: 198
                     2: 204
               default: 211
          }
     120: aload_1
     121: arraylength
     122: ifne          132
     125: sipush        6650
     128: istore_2
     129: goto          238
     132: aload_1
     133: arraylength
     134: iconst_1
     135: if_icmpne     159
     138: aload_1
     139: iconst_0
     140: aaload
     141: invokevirtual #46                 // Method java/lang/String.toLowerCase:()Ljava/lang/String;
     144: ldc           #78                 // String ssl
     146: invokevirtual #75                 // Method java/lang/String.equals:(Ljava/lang/Object;)Z
     149: ifeq          159
     152: sipush        6651
     155: istore_2
     156: goto          238
     159: new           #61                 // class java/lang/IllegalArgumentException
     162: dup
     163: new           #17                 // class java/lang/StringBuilder
     166: dup
     167: invokespecial #18                 // Method java/lang/StringBuilder."<init>":()V
     170: ldc           #79                 // String Invalid pulsar service :
     172: invokevirtual #19                 // Method java/lang/StringBuilder.append:(Ljava/lang/String;)Ljava/lang/StringBuilder;
     175: aload_0
     176: invokevirtual #19                 // Method java/lang/StringBuilder.append:(Ljava/lang/String;)Ljava/lang/StringBuilder;
     179: ldc           #47                 // String +
     181: invokevirtual #19                 // Method java/lang/StringBuilder.append:(Ljava/lang/String;)Ljava/lang/StringBuilder;
     184: aload_1
     185: invokestatic  #80                 // Method java/util/Arrays.toString:([Ljava/lang/Object;)Ljava/lang/String;
     188: invokevirtual #19                 // Method java/lang/StringBuilder.append:(Ljava/lang/String;)Ljava/lang/StringBuilder;
     191: invokevirtual #20                 // Method java/lang/StringBuilder.toString:()Ljava/lang/String;
     194: invokespecial #63                 // Method java/lang/IllegalArgumentException."<init>":(Ljava/lang/String;)V
     197: athrow
     198: bipush        80
     200: istore_2
     201: goto          238
     204: sipush        443
     207: istore_2
     208: goto          238
     211: new           #61                 // class java/lang/IllegalArgumentException
     214: dup
     215: new           #17                 // class java/lang/StringBuilder
     218: dup
     219: invokespecial #18                 // Method java/lang/StringBuilder."<init>":()V
     222: ldc           #79                 // String Invalid pulsar service :
     224: invokevirtual #19                 // Method java/lang/StringBuilder.append:(Ljava/lang/String;)Ljava/lang/StringBuilder;
     227: aload_0
     228: invokevirtual #19                 // Method java/lang/StringBuilder.append:(Ljava/lang/String;)Ljava/lang/StringBuilder;
     231: invokevirtual #20                 // Method java/lang/StringBuilder.toString:()Ljava/lang/String;
     234: invokespecial #63                 // Method java/lang/IllegalArgumentException."<init>":(Ljava/lang/String;)V
     237: athrow
     238: iload_2
     239: ireturn

  public java.lang.String selectOne();
    Code:
       0: new           #17                 // class java/lang/StringBuilder
       3: dup
       4: invokespecial #18                 // Method java/lang/StringBuilder."<init>":()V
       7: astore_1
       8: aload_0
       9: getfield      #71                 // Field serviceName:Ljava/lang/String;
      12: ifnull        64
      15: aload_1
      16: aload_0
      17: getfield      #71                 // Field serviceName:Ljava/lang/String;
      20: invokevirtual #19                 // Method java/lang/StringBuilder.append:(Ljava/lang/String;)Ljava/lang/StringBuilder;
      23: pop
      24: iconst_0
      25: istore_2
      26: iload_2
      27: aload_0
      28: getfield      #69                 // Field serviceInfos:[Ljava/lang/String;
      31: arraylength
      32: if_icmpge     57
      35: aload_1
      36: bipush        43
      38: invokevirtual #81                 // Method java/lang/StringBuilder.append:(C)Ljava/lang/StringBuilder;
      41: aload_0
      42: getfield      #69                 // Field serviceInfos:[Ljava/lang/String;
      45: iload_2
      46: aaload
      47: invokevirtual #19                 // Method java/lang/StringBuilder.append:(Ljava/lang/String;)Ljava/lang/StringBuilder;
      50: pop
      51: iinc          2, 1
      54: goto          26
      57: aload_1
      58: ldc           #82                 // String ://
      60: invokevirtual #19                 // Method java/lang/StringBuilder.append:(Ljava/lang/String;)Ljava/lang/StringBuilder;
      63: pop
      64: aload_0
      65: getfield      #83                 // Field serviceUser:Ljava/lang/String;
      68: ifnull        85
      71: aload_1
      72: aload_0
      73: getfield      #83                 // Field serviceUser:Ljava/lang/String;
      76: invokevirtual #19                 // Method java/lang/StringBuilder.append:(Ljava/lang/String;)Ljava/lang/StringBuilder;
      79: bipush        64
      81: invokevirtual #81                 // Method java/lang/StringBuilder.append:(C)Ljava/lang/StringBuilder;
      84: pop
      85: invokestatic  #84                 // Method java/util/concurrent/ThreadLocalRandom.current:()Ljava/util/concurrent/ThreadLocalRandom;
      88: aload_0
      89: getfield      #70                 // Field serviceHosts:[Ljava/lang/String;
      92: arraylength
      93: invokevirtual #85                 // Method java/util/concurrent/ThreadLocalRandom.nextInt:(I)I
      96: istore_2
      97: aload_1
      98: aload_0
      99: getfield      #70                 // Field serviceHosts:[Ljava/lang/String;
     102: iload_2
     103: aaload
     104: invokevirtual #19                 // Method java/lang/StringBuilder.append:(Ljava/lang/String;)Ljava/lang/StringBuilder;
     107: pop
     108: aload_1
     109: aload_0
     110: getfield      #86                 // Field servicePath:Ljava/lang/String;
     113: invokevirtual #19                 // Method java/lang/StringBuilder.append:(Ljava/lang/String;)Ljava/lang/StringBuilder;
     116: invokevirtual #20                 // Method java/lang/StringBuilder.toString:()Ljava/lang/String;
     119: areturn

  private org.apache.pulsar.common.net.ServiceURI(java.lang.String, java.lang.String[], java.lang.String, java.lang.String[], java.lang.String, java.net.URI);
    Code:
       0: aload_0
       1: invokespecial #87                 // Method java/lang/Object."<init>":()V
       4: aload_0
       5: aload_1
       6: putfield      #71                 // Field serviceName:Ljava/lang/String;
       9: aload_0
      10: aload_2
      11: putfield      #69                 // Field serviceInfos:[Ljava/lang/String;
      14: aload_0
      15: aload_3
      16: putfield      #83                 // Field serviceUser:Ljava/lang/String;
      19: aload_0
      20: aload         4
      22: putfield      #70                 // Field serviceHosts:[Ljava/lang/String;
      25: aload_0
      26: aload         5
      28: putfield      #86                 // Field servicePath:Ljava/lang/String;
      31: aload_0
      32: aload         6
      34: putfield      #88                 // Field uri:Ljava/net/URI;
      37: return

  public java.lang.String getServiceName();
    Code:
       0: aload_0
       1: getfield      #71                 // Field serviceName:Ljava/lang/String;
       4: areturn

  public java.lang.String getServiceUser();
    Code:
       0: aload_0
       1: getfield      #83                 // Field serviceUser:Ljava/lang/String;
       4: areturn

  public java.lang.String getServicePath();
    Code:
       0: aload_0
       1: getfield      #86                 // Field servicePath:Ljava/lang/String;
       4: areturn

  public java.net.URI getUri();
    Code:
       0: aload_0
       1: getfield      #88                 // Field uri:Ljava/net/URI;
       4: areturn

  public boolean equals(java.lang.Object);
    Code:
       0: aload_1
       1: aload_0
       2: if_acmpne     7
       5: iconst_1
       6: ireturn
       7: aload_1
       8: instanceof    #35                 // class org/apache/pulsar/common/net/ServiceURI
      11: ifne          16
      14: iconst_0
      15: ireturn
      16: aload_1
      17: checkcast     #35                 // class org/apache/pulsar/common/net/ServiceURI
      20: astore_2
      21: aload_2
      22: aload_0
      23: invokevirtual #89                 // Method canEqual:(Ljava/lang/Object;)Z
      26: ifne          31
      29: iconst_0
      30: ireturn
      31: aload_0
      32: invokevirtual #36                 // Method getServiceName:()Ljava/lang/String;
      35: astore_3
      36: aload_2
      37: invokevirtual #36                 // Method getServiceName:()Ljava/lang/String;
      40: astore        4
      42: aload_3
      43: ifnonnull     54
      46: aload         4
      48: ifnull        65
      51: goto          63
      54: aload_3
      55: aload         4
      57: invokevirtual #90                 // Method java/lang/Object.equals:(Ljava/lang/Object;)Z
      60: ifne          65
      63: iconst_0
      64: ireturn
      65: aload_0
      66: invokevirtual #37                 // Method getServiceInfos:()[Ljava/lang/String;
      69: aload_2
      70: invokevirtual #37                 // Method getServiceInfos:()[Ljava/lang/String;
      73: invokestatic  #91                 // Method java/util/Arrays.deepEquals:([Ljava/lang/Object;[Ljava/lang/Object;)Z
      76: ifne          81
      79: iconst_0
      80: ireturn
      81: aload_0
      82: invokevirtual #38                 // Method getServiceUser:()Ljava/lang/String;
      85: astore        5
      87: aload_2
      88: invokevirtual #38                 // Method getServiceUser:()Ljava/lang/String;
      91: astore        6
      93: aload         5
      95: ifnonnull     106
      98: aload         6
     100: ifnull        118
     103: goto          116
     106: aload         5
     108: aload         6
     110: invokevirtual #90                 // Method java/lang/Object.equals:(Ljava/lang/Object;)Z
     113: ifne          118
     116: iconst_0
     117: ireturn
     118: aload_0
     119: invokevirtual #25                 // Method getServiceHosts:()[Ljava/lang/String;
     122: aload_2
     123: invokevirtual #25                 // Method getServiceHosts:()[Ljava/lang/String;
     126: invokestatic  #91                 // Method java/util/Arrays.deepEquals:([Ljava/lang/Object;[Ljava/lang/Object;)Z
     129: ifne          134
     132: iconst_0
     133: ireturn
     134: aload_0
     135: invokevirtual #41                 // Method getServicePath:()Ljava/lang/String;
     138: astore        7
     140: aload_2
     141: invokevirtual #41                 // Method getServicePath:()Ljava/lang/String;
     144: astore        8
     146: aload         7
     148: ifnonnull     159
     151: aload         8
     153: ifnull        171
     156: goto          169
     159: aload         7
     161: aload         8
     163: invokevirtual #90                 // Method java/lang/Object.equals:(Ljava/lang/Object;)Z
     166: ifne          171
     169: iconst_0
     170: ireturn
     171: aload_0
     172: invokevirtual #42                 // Method getUri:()Ljava/net/URI;
     175: astore        9
     177: aload_2
     178: invokevirtual #42                 // Method getUri:()Ljava/net/URI;
     181: astore        10
     183: aload         9
     185: ifnonnull     196
     188: aload         10
     190: ifnull        208
     193: goto          206
     196: aload         9
     198: aload         10
     200: invokevirtual #90                 // Method java/lang/Object.equals:(Ljava/lang/Object;)Z
     203: ifne          208
     206: iconst_0
     207: ireturn
     208: iconst_1
     209: ireturn

  protected boolean canEqual(java.lang.Object);
    Code:
       0: aload_1
       1: instanceof    #35                 // class org/apache/pulsar/common/net/ServiceURI
       4: ireturn

  public int hashCode();
    Code:
       0: bipush        59
       2: istore_1
       3: iconst_1
       4: istore_2
       5: aload_0
       6: invokevirtual #36                 // Method getServiceName:()Ljava/lang/String;
       9: astore_3
      10: iload_2
      11: bipush        59
      13: imul
      14: aload_3
      15: ifnonnull     23
      18: bipush        43
      20: goto          27
      23: aload_3
      24: invokevirtual #92                 // Method java/lang/Object.hashCode:()I
      27: iadd
      28: istore_2
      29: iload_2
      30: bipush        59
      32: imul
      33: aload_0
      34: invokevirtual #37                 // Method getServiceInfos:()[Ljava/lang/String;
      37: invokestatic  #93                 // Method java/util/Arrays.deepHashCode:([Ljava/lang/Object;)I
      40: iadd
      41: istore_2
      42: aload_0
      43: invokevirtual #38                 // Method getServiceUser:()Ljava/lang/String;
      46: astore        4
      48: iload_2
      49: bipush        59
      51: imul
      52: aload         4
      54: ifnonnull     62
      57: bipush        43
      59: goto          67
      62: aload         4
      64: invokevirtual #92                 // Method java/lang/Object.hashCode:()I
      67: iadd
      68: istore_2
      69: iload_2
      70: bipush        59
      72: imul
      73: aload_0
      74: invokevirtual #25                 // Method getServiceHosts:()[Ljava/lang/String;
      77: invokestatic  #93                 // Method java/util/Arrays.deepHashCode:([Ljava/lang/Object;)I
      80: iadd
      81: istore_2
      82: aload_0
      83: invokevirtual #41                 // Method getServicePath:()Ljava/lang/String;
      86: astore        5
      88: iload_2
      89: bipush        59
      91: imul
      92: aload         5
      94: ifnonnull     102
      97: bipush        43
      99: goto          107
     102: aload         5
     104: invokevirtual #92                 // Method java/lang/Object.hashCode:()I
     107: iadd
     108: istore_2
     109: aload_0
     110: invokevirtual #42                 // Method getUri:()Ljava/net/URI;
     113: astore        6
     115: iload_2
     116: bipush        59
     118: imul
     119: aload         6
     121: ifnonnull     129
     124: bipush        43
     126: goto          134
     129: aload         6
     131: invokevirtual #92                 // Method java/lang/Object.hashCode:()I
     134: iadd
     135: istore_2
     136: iload_2
     137: ireturn

  private static java.lang.String lambda$create$1(java.lang.String, java.lang.String[], java.lang.String);
    Code:
       0: aload_0
       1: aload_1
       2: aload_2
       3: invokestatic  #94                 // Method validateHostName:(Ljava/lang/String;[Ljava/lang/String;Ljava/lang/String;)Ljava/lang/String;
       6: areturn

  private static java.lang.String lambda$create$0(org.apache.pulsar.common.net.ServiceURI, java.lang.String);
    Code:
       0: aload_0
       1: invokevirtual #36                 // Method getServiceName:()Ljava/lang/String;
       4: aload_0
       5: invokevirtual #37                 // Method getServiceInfos:()[Ljava/lang/String;
       8: aload_1
       9: invokestatic  #94                 // Method validateHostName:(Ljava/lang/String;[Ljava/lang/String;Ljava/lang/String;)Ljava/lang/String;
      12: areturn
}
