Compiled from "ElementDefinitions.java"
public final class org.thymeleaf.engine.ElementDefinitions {
  public static final java.util.Set<java.lang.String> ALL_STANDARD_HTML_ELEMENT_NAMES;

  private static final org.thymeleaf.engine.ElementDefinitions$HTMLElementDefinitionSpec HTML;

  private static final org.thymeleaf.engine.ElementDefinitions$HTMLElementDefinitionSpec HEAD;

  private static final org.thymeleaf.engine.ElementDefinitions$HTMLElementDefinitionSpec TITLE;

  private static final org.thymeleaf.engine.ElementDefinitions$HTMLElementDefinitionSpec BASE;

  private static final org.thymeleaf.engine.ElementDefinitions$HTMLElementDefinitionSpec LINK;

  private static final org.thymeleaf.engine.ElementDefinitions$HTMLElementDefinitionSpec META;

  private static final org.thymeleaf.engine.ElementDefinitions$HTMLElementDefinitionSpec STYLE;

  private static final org.thymeleaf.engine.ElementDefinitions$HTMLElementDefinitionSpec SCRIPT;

  private static final org.thymeleaf.engine.ElementDefinitions$HTMLElementDefinitionSpec NOSCRIPT;

  private static final org.thymeleaf.engine.ElementDefinitions$HTMLElementDefinitionSpec BODY;

  private static final org.thymeleaf.engine.ElementDefinitions$HTMLElementDefinitionSpec ARTICLE;

  private static final org.thymeleaf.engine.ElementDefinitions$HTMLElementDefinitionSpec SECTION;

  private static final org.thymeleaf.engine.ElementDefinitions$HTMLElementDefinitionSpec NAV;

  private static final org.thymeleaf.engine.ElementDefinitions$HTMLElementDefinitionSpec ASIDE;

  private static final org.thymeleaf.engine.ElementDefinitions$HTMLElementDefinitionSpec H1;

  private static final org.thymeleaf.engine.ElementDefinitions$HTMLElementDefinitionSpec H2;

  private static final org.thymeleaf.engine.ElementDefinitions$HTMLElementDefinitionSpec H3;

  private static final org.thymeleaf.engine.ElementDefinitions$HTMLElementDefinitionSpec H4;

  private static final org.thymeleaf.engine.ElementDefinitions$HTMLElementDefinitionSpec H5;

  private static final org.thymeleaf.engine.ElementDefinitions$HTMLElementDefinitionSpec H6;

  private static final org.thymeleaf.engine.ElementDefinitions$HTMLElementDefinitionSpec HGROUP;

  private static final org.thymeleaf.engine.ElementDefinitions$HTMLElementDefinitionSpec HEADER;

  private static final org.thymeleaf.engine.ElementDefinitions$HTMLElementDefinitionSpec FOOTER;

  private static final org.thymeleaf.engine.ElementDefinitions$HTMLElementDefinitionSpec ADDRESS;

  private static final org.thymeleaf.engine.ElementDefinitions$HTMLElementDefinitionSpec MAIN;

  private static final org.thymeleaf.engine.ElementDefinitions$HTMLElementDefinitionSpec P;

  private static final org.thymeleaf.engine.ElementDefinitions$HTMLElementDefinitionSpec HR;

  private static final org.thymeleaf.engine.ElementDefinitions$HTMLElementDefinitionSpec PRE;

  private static final org.thymeleaf.engine.ElementDefinitions$HTMLElementDefinitionSpec BLOCKQUOTE;

  private static final org.thymeleaf.engine.ElementDefinitions$HTMLElementDefinitionSpec OL;

  private static final org.thymeleaf.engine.ElementDefinitions$HTMLElementDefinitionSpec UL;

  private static final org.thymeleaf.engine.ElementDefinitions$HTMLElementDefinitionSpec LI;

  private static final org.thymeleaf.engine.ElementDefinitions$HTMLElementDefinitionSpec DL;

  private static final org.thymeleaf.engine.ElementDefinitions$HTMLElementDefinitionSpec DT;

  private static final org.thymeleaf.engine.ElementDefinitions$HTMLElementDefinitionSpec DD;

  private static final org.thymeleaf.engine.ElementDefinitions$HTMLElementDefinitionSpec FIGURE;

  private static final org.thymeleaf.engine.ElementDefinitions$HTMLElementDefinitionSpec FIGCAPTION;

  private static final org.thymeleaf.engine.ElementDefinitions$HTMLElementDefinitionSpec DIV;

  private static final org.thymeleaf.engine.ElementDefinitions$HTMLElementDefinitionSpec A;

  private static final org.thymeleaf.engine.ElementDefinitions$HTMLElementDefinitionSpec EM;

  private static final org.thymeleaf.engine.ElementDefinitions$HTMLElementDefinitionSpec STRONG;

  private static final org.thymeleaf.engine.ElementDefinitions$HTMLElementDefinitionSpec SMALL;

  private static final org.thymeleaf.engine.ElementDefinitions$HTMLElementDefinitionSpec S;

  private static final org.thymeleaf.engine.ElementDefinitions$HTMLElementDefinitionSpec CITE;

  private static final org.thymeleaf.engine.ElementDefinitions$HTMLElementDefinitionSpec G;

  private static final org.thymeleaf.engine.ElementDefinitions$HTMLElementDefinitionSpec DFN;

  private static final org.thymeleaf.engine.ElementDefinitions$HTMLElementDefinitionSpec ABBR;

  private static final org.thymeleaf.engine.ElementDefinitions$HTMLElementDefinitionSpec TIME;

  private static final org.thymeleaf.engine.ElementDefinitions$HTMLElementDefinitionSpec CODE;

  private static final org.thymeleaf.engine.ElementDefinitions$HTMLElementDefinitionSpec VAR;

  private static final org.thymeleaf.engine.ElementDefinitions$HTMLElementDefinitionSpec SAMP;

  private static final org.thymeleaf.engine.ElementDefinitions$HTMLElementDefinitionSpec KBD;

  private static final org.thymeleaf.engine.ElementDefinitions$HTMLElementDefinitionSpec SUB;

  private static final org.thymeleaf.engine.ElementDefinitions$HTMLElementDefinitionSpec SUP;

  private static final org.thymeleaf.engine.ElementDefinitions$HTMLElementDefinitionSpec I;

  private static final org.thymeleaf.engine.ElementDefinitions$HTMLElementDefinitionSpec B;

  private static final org.thymeleaf.engine.ElementDefinitions$HTMLElementDefinitionSpec U;

  private static final org.thymeleaf.engine.ElementDefinitions$HTMLElementDefinitionSpec MARK;

  private static final org.thymeleaf.engine.ElementDefinitions$HTMLElementDefinitionSpec RUBY;

  private static final org.thymeleaf.engine.ElementDefinitions$HTMLElementDefinitionSpec RB;

  private static final org.thymeleaf.engine.ElementDefinitions$HTMLElementDefinitionSpec RT;

  private static final org.thymeleaf.engine.ElementDefinitions$HTMLElementDefinitionSpec RTC;

  private static final org.thymeleaf.engine.ElementDefinitions$HTMLElementDefinitionSpec RP;

  private static final org.thymeleaf.engine.ElementDefinitions$HTMLElementDefinitionSpec BDI;

  private static final org.thymeleaf.engine.ElementDefinitions$HTMLElementDefinitionSpec BDO;

  private static final org.thymeleaf.engine.ElementDefinitions$HTMLElementDefinitionSpec SPAN;

  private static final org.thymeleaf.engine.ElementDefinitions$HTMLElementDefinitionSpec BR;

  private static final org.thymeleaf.engine.ElementDefinitions$HTMLElementDefinitionSpec WBR;

  private static final org.thymeleaf.engine.ElementDefinitions$HTMLElementDefinitionSpec INS;

  private static final org.thymeleaf.engine.ElementDefinitions$HTMLElementDefinitionSpec DEL;

  private static final org.thymeleaf.engine.ElementDefinitions$HTMLElementDefinitionSpec IMG;

  private static final org.thymeleaf.engine.ElementDefinitions$HTMLElementDefinitionSpec IFRAME;

  private static final org.thymeleaf.engine.ElementDefinitions$HTMLElementDefinitionSpec EMBED;

  private static final org.thymeleaf.engine.ElementDefinitions$HTMLElementDefinitionSpec OBJECT;

  private static final org.thymeleaf.engine.ElementDefinitions$HTMLElementDefinitionSpec PARAM;

  private static final org.thymeleaf.engine.ElementDefinitions$HTMLElementDefinitionSpec VIDEO;

  private static final org.thymeleaf.engine.ElementDefinitions$HTMLElementDefinitionSpec AUDIO;

  private static final org.thymeleaf.engine.ElementDefinitions$HTMLElementDefinitionSpec SOURCE;

  private static final org.thymeleaf.engine.ElementDefinitions$HTMLElementDefinitionSpec TRACK;

  private static final org.thymeleaf.engine.ElementDefinitions$HTMLElementDefinitionSpec CANVAS;

  private static final org.thymeleaf.engine.ElementDefinitions$HTMLElementDefinitionSpec MAP;

  private static final org.thymeleaf.engine.ElementDefinitions$HTMLElementDefinitionSpec AREA;

  private static final org.thymeleaf.engine.ElementDefinitions$HTMLElementDefinitionSpec TABLE;

  private static final org.thymeleaf.engine.ElementDefinitions$HTMLElementDefinitionSpec CAPTION;

  private static final org.thymeleaf.engine.ElementDefinitions$HTMLElementDefinitionSpec COLGROUP;

  private static final org.thymeleaf.engine.ElementDefinitions$HTMLElementDefinitionSpec COL;

  private static final org.thymeleaf.engine.ElementDefinitions$HTMLElementDefinitionSpec TBODY;

  private static final org.thymeleaf.engine.ElementDefinitions$HTMLElementDefinitionSpec THEAD;

  private static final org.thymeleaf.engine.ElementDefinitions$HTMLElementDefinitionSpec TFOOT;

  private static final org.thymeleaf.engine.ElementDefinitions$HTMLElementDefinitionSpec TR;

  private static final org.thymeleaf.engine.ElementDefinitions$HTMLElementDefinitionSpec TD;

  private static final org.thymeleaf.engine.ElementDefinitions$HTMLElementDefinitionSpec TH;

  private static final org.thymeleaf.engine.ElementDefinitions$HTMLElementDefinitionSpec FORM;

  private static final org.thymeleaf.engine.ElementDefinitions$HTMLElementDefinitionSpec FIELDSET;

  private static final org.thymeleaf.engine.ElementDefinitions$HTMLElementDefinitionSpec LEGEND;

  private static final org.thymeleaf.engine.ElementDefinitions$HTMLElementDefinitionSpec LABEL;

  private static final org.thymeleaf.engine.ElementDefinitions$HTMLElementDefinitionSpec INPUT;

  private static final org.thymeleaf.engine.ElementDefinitions$HTMLElementDefinitionSpec BUTTON;

  private static final org.thymeleaf.engine.ElementDefinitions$HTMLElementDefinitionSpec SELECT;

  private static final org.thymeleaf.engine.ElementDefinitions$HTMLElementDefinitionSpec DATALIST;

  private static final org.thymeleaf.engine.ElementDefinitions$HTMLElementDefinitionSpec OPTGROUP;

  private static final org.thymeleaf.engine.ElementDefinitions$HTMLElementDefinitionSpec OPTION;

  private static final org.thymeleaf.engine.ElementDefinitions$HTMLElementDefinitionSpec TEXTAREA;

  private static final org.thymeleaf.engine.ElementDefinitions$HTMLElementDefinitionSpec KEYGEN;

  private static final org.thymeleaf.engine.ElementDefinitions$HTMLElementDefinitionSpec OUTPUT;

  private static final org.thymeleaf.engine.ElementDefinitions$HTMLElementDefinitionSpec PROGRESS;

  private static final org.thymeleaf.engine.ElementDefinitions$HTMLElementDefinitionSpec METER;

  private static final org.thymeleaf.engine.ElementDefinitions$HTMLElementDefinitionSpec DETAILS;

  private static final org.thymeleaf.engine.ElementDefinitions$HTMLElementDefinitionSpec SUMMARY;

  private static final org.thymeleaf.engine.ElementDefinitions$HTMLElementDefinitionSpec COMMAND;

  private static final org.thymeleaf.engine.ElementDefinitions$HTMLElementDefinitionSpec MENU;

  private static final org.thymeleaf.engine.ElementDefinitions$HTMLElementDefinitionSpec MENUITEM;

  private static final org.thymeleaf.engine.ElementDefinitions$HTMLElementDefinitionSpec DIALOG;

  private static final org.thymeleaf.engine.ElementDefinitions$HTMLElementDefinitionSpec TEMPLATE;

  private static final org.thymeleaf.engine.ElementDefinitions$HTMLElementDefinitionSpec ELEMENT;

  private static final org.thymeleaf.engine.ElementDefinitions$HTMLElementDefinitionSpec DECORATOR;

  private static final org.thymeleaf.engine.ElementDefinitions$HTMLElementDefinitionSpec CONTENT;

  private static final org.thymeleaf.engine.ElementDefinitions$HTMLElementDefinitionSpec SHADOW;

  private final org.thymeleaf.engine.ElementDefinitions$ElementDefinitionRepository htmlElementRepository;

  private final org.thymeleaf.engine.ElementDefinitions$ElementDefinitionRepository xmlElementRepository;

  private final org.thymeleaf.engine.ElementDefinitions$ElementDefinitionRepository textElementRepository;

  private final org.thymeleaf.engine.ElementDefinitions$ElementDefinitionRepository javascriptElementRepository;

  private final org.thymeleaf.engine.ElementDefinitions$ElementDefinitionRepository cssElementRepository;

  public org.thymeleaf.engine.ElementDefinitions(java.util.Map<org.thymeleaf.templatemode.TemplateMode, java.util.Set<org.thymeleaf.processor.element.IElementProcessor>>);
    Code:
       0: aload_0
       1: invokespecial #4                  // Method java/lang/Object."<init>":()V
       4: new           #5                  // class java/util/ArrayList
       7: dup
       8: getstatic     #6                  // Field org/thymeleaf/engine/ElementDefinitions$HTMLElementDefinitionSpec.ALL_SPECS:Ljava/util/List;
      11: invokeinterface #7,  1            // InterfaceMethod java/util/List.size:()I
      16: iconst_1
      17: iadd
      18: invokespecial #8                  // Method java/util/ArrayList."<init>":(I)V
      21: astore_2
      22: getstatic     #6                  // Field org/thymeleaf/engine/ElementDefinitions$HTMLElementDefinitionSpec.ALL_SPECS:Ljava/util/List;
      25: invokeinterface #9,  1            // InterfaceMethod java/util/List.iterator:()Ljava/util/Iterator;
      30: astore_3
      31: aload_3
      32: invokeinterface #10,  1           // InterfaceMethod java/util/Iterator.hasNext:()Z
      37: ifeq          86
      40: aload_3
      41: invokeinterface #11,  1           // InterfaceMethod java/util/Iterator.next:()Ljava/lang/Object;
      46: checkcast     #12                 // class org/thymeleaf/engine/ElementDefinitions$HTMLElementDefinitionSpec
      49: astore        4
      51: aload_2
      52: aload         4
      54: getfield      #13                 // Field org/thymeleaf/engine/ElementDefinitions$HTMLElementDefinitionSpec.name:Lorg/thymeleaf/engine/HTMLElementName;
      57: aload         4
      59: getfield      #14                 // Field org/thymeleaf/engine/ElementDefinitions$HTMLElementDefinitionSpec.type:Lorg/thymeleaf/engine/HTMLElementType;
      62: aload_1
      63: getstatic     #15                 // Field org/thymeleaf/templatemode/TemplateMode.HTML:Lorg/thymeleaf/templatemode/TemplateMode;
      66: invokeinterface #16,  2           // InterfaceMethod java/util/Map.get:(Ljava/lang/Object;)Ljava/lang/Object;
      71: checkcast     #17                 // class java/util/Set
      74: invokestatic  #3                  // Method buildHTMLElementDefinition:(Lorg/thymeleaf/engine/HTMLElementName;Lorg/thymeleaf/engine/HTMLElementType;Ljava/util/Set;)Lorg/thymeleaf/engine/HTMLElementDefinition;
      77: invokeinterface #18,  2           // InterfaceMethod java/util/List.add:(Ljava/lang/Object;)Z
      82: pop
      83: goto          31
      86: aload_0
      87: new           #19                 // class org/thymeleaf/engine/ElementDefinitions$ElementDefinitionRepository
      90: dup
      91: getstatic     #15                 // Field org/thymeleaf/templatemode/TemplateMode.HTML:Lorg/thymeleaf/templatemode/TemplateMode;
      94: aload_1
      95: invokespecial #20                 // Method org/thymeleaf/engine/ElementDefinitions$ElementDefinitionRepository."<init>":(Lorg/thymeleaf/templatemode/TemplateMode;Ljava/util/Map;)V
      98: putfield      #21                 // Field htmlElementRepository:Lorg/thymeleaf/engine/ElementDefinitions$ElementDefinitionRepository;
     101: aload_0
     102: new           #19                 // class org/thymeleaf/engine/ElementDefinitions$ElementDefinitionRepository
     105: dup
     106: getstatic     #22                 // Field org/thymeleaf/templatemode/TemplateMode.XML:Lorg/thymeleaf/templatemode/TemplateMode;
     109: aload_1
     110: invokespecial #20                 // Method org/thymeleaf/engine/ElementDefinitions$ElementDefinitionRepository."<init>":(Lorg/thymeleaf/templatemode/TemplateMode;Ljava/util/Map;)V
     113: putfield      #23                 // Field xmlElementRepository:Lorg/thymeleaf/engine/ElementDefinitions$ElementDefinitionRepository;
     116: aload_0
     117: new           #19                 // class org/thymeleaf/engine/ElementDefinitions$ElementDefinitionRepository
     120: dup
     121: getstatic     #24                 // Field org/thymeleaf/templatemode/TemplateMode.TEXT:Lorg/thymeleaf/templatemode/TemplateMode;
     124: aload_1
     125: invokespecial #20                 // Method org/thymeleaf/engine/ElementDefinitions$ElementDefinitionRepository."<init>":(Lorg/thymeleaf/templatemode/TemplateMode;Ljava/util/Map;)V
     128: putfield      #25                 // Field textElementRepository:Lorg/thymeleaf/engine/ElementDefinitions$ElementDefinitionRepository;
     131: aload_0
     132: new           #19                 // class org/thymeleaf/engine/ElementDefinitions$ElementDefinitionRepository
     135: dup
     136: getstatic     #26                 // Field org/thymeleaf/templatemode/TemplateMode.JAVASCRIPT:Lorg/thymeleaf/templatemode/TemplateMode;
     139: aload_1
     140: invokespecial #20                 // Method org/thymeleaf/engine/ElementDefinitions$ElementDefinitionRepository."<init>":(Lorg/thymeleaf/templatemode/TemplateMode;Ljava/util/Map;)V
     143: putfield      #27                 // Field javascriptElementRepository:Lorg/thymeleaf/engine/ElementDefinitions$ElementDefinitionRepository;
     146: aload_0
     147: new           #19                 // class org/thymeleaf/engine/ElementDefinitions$ElementDefinitionRepository
     150: dup
     151: getstatic     #28                 // Field org/thymeleaf/templatemode/TemplateMode.CSS:Lorg/thymeleaf/templatemode/TemplateMode;
     154: aload_1
     155: invokespecial #20                 // Method org/thymeleaf/engine/ElementDefinitions$ElementDefinitionRepository."<init>":(Lorg/thymeleaf/templatemode/TemplateMode;Ljava/util/Map;)V
     158: putfield      #29                 // Field cssElementRepository:Lorg/thymeleaf/engine/ElementDefinitions$ElementDefinitionRepository;
     161: aload_2
     162: invokeinterface #9,  1            // InterfaceMethod java/util/List.iterator:()Ljava/util/Iterator;
     167: astore_3
     168: aload_3
     169: invokeinterface #10,  1           // InterfaceMethod java/util/Iterator.hasNext:()Z
     174: ifeq          201
     177: aload_3
     178: invokeinterface #11,  1           // InterfaceMethod java/util/Iterator.next:()Ljava/lang/Object;
     183: checkcast     #30                 // class org/thymeleaf/engine/HTMLElementDefinition
     186: astore        4
     188: aload_0
     189: getfield      #21                 // Field htmlElementRepository:Lorg/thymeleaf/engine/ElementDefinitions$ElementDefinitionRepository;
     192: aload         4
     194: invokestatic  #31                 // Method org/thymeleaf/engine/ElementDefinitions$ElementDefinitionRepository.access$000:(Lorg/thymeleaf/engine/ElementDefinitions$ElementDefinitionRepository;Lorg/thymeleaf/engine/ElementDefinition;)Lorg/thymeleaf/engine/ElementDefinition;
     197: pop
     198: goto          168
     201: return

  private static org.thymeleaf.engine.HTMLElementDefinition buildHTMLElementDefinition(org.thymeleaf.engine.HTMLElementName, org.thymeleaf.engine.HTMLElementType, java.util.Set<org.thymeleaf.processor.element.IElementProcessor>);
    Code:
       0: new           #32                 // class java/util/LinkedHashSet
       3: dup
       4: iconst_2
       5: invokespecial #33                 // Method java/util/LinkedHashSet."<init>":(I)V
       8: astore_3
       9: aload_2
      10: ifnull        197
      13: aload_2
      14: invokeinterface #34,  1           // InterfaceMethod java/util/Set.iterator:()Ljava/util/Iterator;
      19: astore        4
      21: aload         4
      23: invokeinterface #10,  1           // InterfaceMethod java/util/Iterator.hasNext:()Z
      28: ifeq          197
      31: aload         4
      33: invokeinterface #11,  1           // InterfaceMethod java/util/Iterator.next:()Ljava/lang/Object;
      38: checkcast     #35                 // class org/thymeleaf/processor/element/IElementProcessor
      41: astore        5
      43: aload         5
      45: invokeinterface #36,  1           // InterfaceMethod org/thymeleaf/processor/element/IElementProcessor.getTemplateMode:()Lorg/thymeleaf/templatemode/TemplateMode;
      50: astore        6
      52: aload         6
      54: getstatic     #15                 // Field org/thymeleaf/templatemode/TemplateMode.HTML:Lorg/thymeleaf/templatemode/TemplateMode;
      57: if_acmpeq     63
      60: goto          21
      63: aload         5
      65: invokeinterface #37,  1           // InterfaceMethod org/thymeleaf/processor/element/IElementProcessor.getMatchingElementName:()Lorg/thymeleaf/processor/element/MatchingElementName;
      70: astore        7
      72: aload         5
      74: invokeinterface #38,  1           // InterfaceMethod org/thymeleaf/processor/element/IElementProcessor.getMatchingAttributeName:()Lorg/thymeleaf/processor/element/MatchingAttributeName;
      79: astore        8
      81: aload         7
      83: ifnull        97
      86: aload         7
      88: invokevirtual #39                 // Method org/thymeleaf/processor/element/MatchingElementName.getTemplateMode:()Lorg/thymeleaf/templatemode/TemplateMode;
      91: getstatic     #15                 // Field org/thymeleaf/templatemode/TemplateMode.HTML:Lorg/thymeleaf/templatemode/TemplateMode;
      94: if_acmpne     113
      97: aload         8
      99: ifnull        152
     102: aload         8
     104: invokevirtual #40                 // Method org/thymeleaf/processor/element/MatchingAttributeName.getTemplateMode:()Lorg/thymeleaf/templatemode/TemplateMode;
     107: getstatic     #15                 // Field org/thymeleaf/templatemode/TemplateMode.HTML:Lorg/thymeleaf/templatemode/TemplateMode;
     110: if_acmpeq     152
     113: new           #41                 // class org/thymeleaf/exceptions/ConfigurationException
     116: dup
     117: new           #42                 // class java/lang/StringBuilder
     120: dup
     121: invokespecial #43                 // Method java/lang/StringBuilder."<init>":()V
     124: ldc           #44                 // String HTML processors must return HTML element names and HTML attribute names (processor:
     126: invokevirtual #45                 // Method java/lang/StringBuilder.append:(Ljava/lang/String;)Ljava/lang/StringBuilder;
     129: aload         5
     131: invokevirtual #46                 // Method java/lang/Object.getClass:()Ljava/lang/Class;
     134: invokevirtual #47                 // Method java/lang/Class.getName:()Ljava/lang/String;
     137: invokevirtual #45                 // Method java/lang/StringBuilder.append:(Ljava/lang/String;)Ljava/lang/StringBuilder;
     140: ldc           #48                 // String )
     142: invokevirtual #45                 // Method java/lang/StringBuilder.append:(Ljava/lang/String;)Ljava/lang/StringBuilder;
     145: invokevirtual #49                 // Method java/lang/StringBuilder.toString:()Ljava/lang/String;
     148: invokespecial #50                 // Method org/thymeleaf/exceptions/ConfigurationException."<init>":(Ljava/lang/String;)V
     151: athrow
     152: aload         8
     154: ifnull        168
     157: aload         8
     159: invokevirtual #51                 // Method org/thymeleaf/processor/element/MatchingAttributeName.isMatchingAllAttributes:()Z
     162: ifne          168
     165: goto          21
     168: aload         7
     170: ifnull        185
     173: aload         7
     175: aload_0
     176: invokevirtual #52                 // Method org/thymeleaf/processor/element/MatchingElementName.matches:(Lorg/thymeleaf/engine/ElementName;)Z
     179: ifne          185
     182: goto          21
     185: aload_3
     186: aload         5
     188: invokeinterface #53,  2           // InterfaceMethod java/util/Set.add:(Ljava/lang/Object;)Z
     193: pop
     194: goto          21
     197: new           #30                 // class org/thymeleaf/engine/HTMLElementDefinition
     200: dup
     201: aload_0
     202: aload_1
     203: aload_3
     204: invokespecial #54                 // Method org/thymeleaf/engine/HTMLElementDefinition."<init>":(Lorg/thymeleaf/engine/HTMLElementName;Lorg/thymeleaf/engine/HTMLElementType;Ljava/util/Set;)V
     207: areturn

  private static org.thymeleaf.engine.XMLElementDefinition buildXMLElementDefinition(org.thymeleaf.engine.XMLElementName, java.util.Set<org.thymeleaf.processor.element.IElementProcessor>);
    Code:
       0: new           #32                 // class java/util/LinkedHashSet
       3: dup
       4: iconst_2
       5: invokespecial #33                 // Method java/util/LinkedHashSet."<init>":(I)V
       8: astore_2
       9: aload_1
      10: ifnull        194
      13: aload_1
      14: invokeinterface #34,  1           // InterfaceMethod java/util/Set.iterator:()Ljava/util/Iterator;
      19: astore_3
      20: aload_3
      21: invokeinterface #10,  1           // InterfaceMethod java/util/Iterator.hasNext:()Z
      26: ifeq          194
      29: aload_3
      30: invokeinterface #11,  1           // InterfaceMethod java/util/Iterator.next:()Ljava/lang/Object;
      35: checkcast     #35                 // class org/thymeleaf/processor/element/IElementProcessor
      38: astore        4
      40: aload         4
      42: invokeinterface #36,  1           // InterfaceMethod org/thymeleaf/processor/element/IElementProcessor.getTemplateMode:()Lorg/thymeleaf/templatemode/TemplateMode;
      47: astore        5
      49: aload         5
      51: getstatic     #22                 // Field org/thymeleaf/templatemode/TemplateMode.XML:Lorg/thymeleaf/templatemode/TemplateMode;
      54: if_acmpeq     60
      57: goto          20
      60: aload         4
      62: invokeinterface #37,  1           // InterfaceMethod org/thymeleaf/processor/element/IElementProcessor.getMatchingElementName:()Lorg/thymeleaf/processor/element/MatchingElementName;
      67: astore        6
      69: aload         4
      71: invokeinterface #38,  1           // InterfaceMethod org/thymeleaf/processor/element/IElementProcessor.getMatchingAttributeName:()Lorg/thymeleaf/processor/element/MatchingAttributeName;
      76: astore        7
      78: aload         6
      80: ifnull        94
      83: aload         6
      85: invokevirtual #39                 // Method org/thymeleaf/processor/element/MatchingElementName.getTemplateMode:()Lorg/thymeleaf/templatemode/TemplateMode;
      88: getstatic     #22                 // Field org/thymeleaf/templatemode/TemplateMode.XML:Lorg/thymeleaf/templatemode/TemplateMode;
      91: if_acmpne     110
      94: aload         7
      96: ifnull        149
      99: aload         7
     101: invokevirtual #40                 // Method org/thymeleaf/processor/element/MatchingAttributeName.getTemplateMode:()Lorg/thymeleaf/templatemode/TemplateMode;
     104: getstatic     #22                 // Field org/thymeleaf/templatemode/TemplateMode.XML:Lorg/thymeleaf/templatemode/TemplateMode;
     107: if_acmpeq     149
     110: new           #41                 // class org/thymeleaf/exceptions/ConfigurationException
     113: dup
     114: new           #42                 // class java/lang/StringBuilder
     117: dup
     118: invokespecial #43                 // Method java/lang/StringBuilder."<init>":()V
     121: ldc           #55                 // String XML processors must return XML element names and XML attribute names (processor:
     123: invokevirtual #45                 // Method java/lang/StringBuilder.append:(Ljava/lang/String;)Ljava/lang/StringBuilder;
     126: aload         4
     128: invokevirtual #46                 // Method java/lang/Object.getClass:()Ljava/lang/Class;
     131: invokevirtual #47                 // Method java/lang/Class.getName:()Ljava/lang/String;
     134: invokevirtual #45                 // Method java/lang/StringBuilder.append:(Ljava/lang/String;)Ljava/lang/StringBuilder;
     137: ldc           #48                 // String )
     139: invokevirtual #45                 // Method java/lang/StringBuilder.append:(Ljava/lang/String;)Ljava/lang/StringBuilder;
     142: invokevirtual #49                 // Method java/lang/StringBuilder.toString:()Ljava/lang/String;
     145: invokespecial #50                 // Method org/thymeleaf/exceptions/ConfigurationException."<init>":(Ljava/lang/String;)V
     148: athrow
     149: aload         7
     151: ifnull        165
     154: aload         7
     156: invokevirtual #51                 // Method org/thymeleaf/processor/element/MatchingAttributeName.isMatchingAllAttributes:()Z
     159: ifne          165
     162: goto          20
     165: aload         6
     167: ifnull        182
     170: aload         6
     172: aload_0
     173: invokevirtual #52                 // Method org/thymeleaf/processor/element/MatchingElementName.matches:(Lorg/thymeleaf/engine/ElementName;)Z
     176: ifne          182
     179: goto          20
     182: aload_2
     183: aload         4
     185: invokeinterface #53,  2           // InterfaceMethod java/util/Set.add:(Ljava/lang/Object;)Z
     190: pop
     191: goto          20
     194: new           #56                 // class org/thymeleaf/engine/XMLElementDefinition
     197: dup
     198: aload_0
     199: aload_2
     200: invokespecial #57                 // Method org/thymeleaf/engine/XMLElementDefinition."<init>":(Lorg/thymeleaf/engine/XMLElementName;Ljava/util/Set;)V
     203: areturn

  private static org.thymeleaf.engine.TextElementDefinition buildTextElementDefinition(org.thymeleaf.templatemode.TemplateMode, org.thymeleaf.engine.TextElementName, java.util.Set<org.thymeleaf.processor.element.IElementProcessor>);
    Code:
       0: new           #32                 // class java/util/LinkedHashSet
       3: dup
       4: iconst_2
       5: invokespecial #33                 // Method java/util/LinkedHashSet."<init>":(I)V
       8: astore_3
       9: aload_2
      10: ifnull        209
      13: aload_2
      14: invokeinterface #34,  1           // InterfaceMethod java/util/Set.iterator:()Ljava/util/Iterator;
      19: astore        4
      21: aload         4
      23: invokeinterface #10,  1           // InterfaceMethod java/util/Iterator.hasNext:()Z
      28: ifeq          209
      31: aload         4
      33: invokeinterface #11,  1           // InterfaceMethod java/util/Iterator.next:()Ljava/lang/Object;
      38: checkcast     #35                 // class org/thymeleaf/processor/element/IElementProcessor
      41: astore        5
      43: aload         5
      45: invokeinterface #36,  1           // InterfaceMethod org/thymeleaf/processor/element/IElementProcessor.getTemplateMode:()Lorg/thymeleaf/templatemode/TemplateMode;
      50: aload_0
      51: if_acmpeq     57
      54: goto          21
      57: aload         5
      59: invokeinterface #37,  1           // InterfaceMethod org/thymeleaf/processor/element/IElementProcessor.getMatchingElementName:()Lorg/thymeleaf/processor/element/MatchingElementName;
      64: astore        6
      66: aload         5
      68: invokeinterface #38,  1           // InterfaceMethod org/thymeleaf/processor/element/IElementProcessor.getMatchingAttributeName:()Lorg/thymeleaf/processor/element/MatchingAttributeName;
      73: astore        7
      75: aload         6
      77: ifnull        89
      80: aload         6
      82: invokevirtual #39                 // Method org/thymeleaf/processor/element/MatchingElementName.getTemplateMode:()Lorg/thymeleaf/templatemode/TemplateMode;
      85: aload_0
      86: if_acmpne     103
      89: aload         7
      91: ifnull        164
      94: aload         7
      96: invokevirtual #40                 // Method org/thymeleaf/processor/element/MatchingAttributeName.getTemplateMode:()Lorg/thymeleaf/templatemode/TemplateMode;
      99: aload_0
     100: if_acmpeq     164
     103: new           #41                 // class org/thymeleaf/exceptions/ConfigurationException
     106: dup
     107: new           #42                 // class java/lang/StringBuilder
     110: dup
     111: invokespecial #43                 // Method java/lang/StringBuilder."<init>":()V
     114: aload_0
     115: invokevirtual #58                 // Method java/lang/StringBuilder.append:(Ljava/lang/Object;)Ljava/lang/StringBuilder;
     118: ldc           #59                 // String  processors must return
     120: invokevirtual #45                 // Method java/lang/StringBuilder.append:(Ljava/lang/String;)Ljava/lang/StringBuilder;
     123: aload_0
     124: invokevirtual #58                 // Method java/lang/StringBuilder.append:(Ljava/lang/Object;)Ljava/lang/StringBuilder;
     127: ldc           #60                 // String element names and
     129: invokevirtual #45                 // Method java/lang/StringBuilder.append:(Ljava/lang/String;)Ljava/lang/StringBuilder;
     132: aload_0
     133: invokevirtual #58                 // Method java/lang/StringBuilder.append:(Ljava/lang/Object;)Ljava/lang/StringBuilder;
     136: ldc           #61                 // String  attribute names (processor:
     138: invokevirtual #45                 // Method java/lang/StringBuilder.append:(Ljava/lang/String;)Ljava/lang/StringBuilder;
     141: aload         5
     143: invokevirtual #46                 // Method java/lang/Object.getClass:()Ljava/lang/Class;
     146: invokevirtual #47                 // Method java/lang/Class.getName:()Ljava/lang/String;
     149: invokevirtual #45                 // Method java/lang/StringBuilder.append:(Ljava/lang/String;)Ljava/lang/StringBuilder;
     152: ldc           #48                 // String )
     154: invokevirtual #45                 // Method java/lang/StringBuilder.append:(Ljava/lang/String;)Ljava/lang/StringBuilder;
     157: invokevirtual #49                 // Method java/lang/StringBuilder.toString:()Ljava/lang/String;
     160: invokespecial #50                 // Method org/thymeleaf/exceptions/ConfigurationException."<init>":(Ljava/lang/String;)V
     163: athrow
     164: aload         7
     166: ifnull        180
     169: aload         7
     171: invokevirtual #51                 // Method org/thymeleaf/processor/element/MatchingAttributeName.isMatchingAllAttributes:()Z
     174: ifne          180
     177: goto          21
     180: aload         6
     182: ifnull        197
     185: aload         6
     187: aload_1
     188: invokevirtual #52                 // Method org/thymeleaf/processor/element/MatchingElementName.matches:(Lorg/thymeleaf/engine/ElementName;)Z
     191: ifne          197
     194: goto          21
     197: aload_3
     198: aload         5
     200: invokeinterface #53,  2           // InterfaceMethod java/util/Set.add:(Ljava/lang/Object;)Z
     205: pop
     206: goto          21
     209: new           #62                 // class org/thymeleaf/engine/TextElementDefinition
     212: dup
     213: aload_1
     214: aload_3
     215: invokespecial #63                 // Method org/thymeleaf/engine/TextElementDefinition."<init>":(Lorg/thymeleaf/engine/TextElementName;Ljava/util/Set;)V
     218: areturn

  public org.thymeleaf.engine.ElementDefinition forName(org.thymeleaf.templatemode.TemplateMode, java.lang.String);
    Code:
       0: aload_1
       1: ifnonnull     14
       4: new           #64                 // class java/lang/IllegalArgumentException
       7: dup
       8: ldc           #65                 // String Template Mode cannot be null
      10: invokespecial #66                 // Method java/lang/IllegalArgumentException."<init>":(Ljava/lang/String;)V
      13: athrow
      14: getstatic     #67                 // Field org/thymeleaf/engine/ElementDefinitions$1.$SwitchMap$org$thymeleaf$templatemode$TemplateMode:[I
      17: aload_1
      18: invokevirtual #68                 // Method org/thymeleaf/templatemode/TemplateMode.ordinal:()I
      21: iaload
      22: tableswitch   { // 1 to 6
                     1: 60
                     2: 66
                     3: 72
                     4: 78
                     5: 84
                     6: 90
               default: 122
          }
      60: aload_0
      61: aload_2
      62: invokevirtual #69                 // Method forHTMLName:(Ljava/lang/String;)Lorg/thymeleaf/engine/HTMLElementDefinition;
      65: areturn
      66: aload_0
      67: aload_2
      68: invokevirtual #70                 // Method forXMLName:(Ljava/lang/String;)Lorg/thymeleaf/engine/XMLElementDefinition;
      71: areturn
      72: aload_0
      73: aload_2
      74: invokevirtual #71                 // Method forTextName:(Ljava/lang/String;)Lorg/thymeleaf/engine/TextElementDefinition;
      77: areturn
      78: aload_0
      79: aload_2
      80: invokevirtual #72                 // Method forJavaScriptName:(Ljava/lang/String;)Lorg/thymeleaf/engine/TextElementDefinition;
      83: areturn
      84: aload_0
      85: aload_2
      86: invokevirtual #73                 // Method forCSSName:(Ljava/lang/String;)Lorg/thymeleaf/engine/TextElementDefinition;
      89: areturn
      90: new           #64                 // class java/lang/IllegalArgumentException
      93: dup
      94: new           #42                 // class java/lang/StringBuilder
      97: dup
      98: invokespecial #43                 // Method java/lang/StringBuilder."<init>":()V
     101: ldc           #74                 // String Element Definitions cannot be obtained for
     103: invokevirtual #45                 // Method java/lang/StringBuilder.append:(Ljava/lang/String;)Ljava/lang/StringBuilder;
     106: aload_1
     107: invokevirtual #58                 // Method java/lang/StringBuilder.append:(Ljava/lang/Object;)Ljava/lang/StringBuilder;
     110: ldc           #75                 // String  template mode
     112: invokevirtual #45                 // Method java/lang/StringBuilder.append:(Ljava/lang/String;)Ljava/lang/StringBuilder;
     115: invokevirtual #49                 // Method java/lang/StringBuilder.toString:()Ljava/lang/String;
     118: invokespecial #66                 // Method java/lang/IllegalArgumentException."<init>":(Ljava/lang/String;)V
     121: athrow
     122: new           #64                 // class java/lang/IllegalArgumentException
     125: dup
     126: new           #42                 // class java/lang/StringBuilder
     129: dup
     130: invokespecial #43                 // Method java/lang/StringBuilder."<init>":()V
     133: ldc           #76                 // String Unknown template mode
     135: invokevirtual #45                 // Method java/lang/StringBuilder.append:(Ljava/lang/String;)Ljava/lang/StringBuilder;
     138: aload_1
     139: invokevirtual #58                 // Method java/lang/StringBuilder.append:(Ljava/lang/Object;)Ljava/lang/StringBuilder;
     142: invokevirtual #49                 // Method java/lang/StringBuilder.toString:()Ljava/lang/String;
     145: invokespecial #66                 // Method java/lang/IllegalArgumentException."<init>":(Ljava/lang/String;)V
     148: athrow

  public org.thymeleaf.engine.ElementDefinition forName(org.thymeleaf.templatemode.TemplateMode, java.lang.String, java.lang.String);
    Code:
       0: aload_1
       1: ifnonnull     14
       4: new           #64                 // class java/lang/IllegalArgumentException
       7: dup
       8: ldc           #65                 // String Template Mode cannot be null
      10: invokespecial #66                 // Method java/lang/IllegalArgumentException."<init>":(Ljava/lang/String;)V
      13: athrow
      14: getstatic     #67                 // Field org/thymeleaf/engine/ElementDefinitions$1.$SwitchMap$org$thymeleaf$templatemode$TemplateMode:[I
      17: aload_1
      18: invokevirtual #68                 // Method org/thymeleaf/templatemode/TemplateMode.ordinal:()I
      21: iaload
      22: tableswitch   { // 1 to 6
                     1: 60
                     2: 67
                     3: 74
                     4: 81
                     5: 88
                     6: 95
               default: 127
          }
      60: aload_0
      61: aload_2
      62: aload_3
      63: invokevirtual #77                 // Method forHTMLName:(Ljava/lang/String;Ljava/lang/String;)Lorg/thymeleaf/engine/HTMLElementDefinition;
      66: areturn
      67: aload_0
      68: aload_2
      69: aload_3
      70: invokevirtual #78                 // Method forXMLName:(Ljava/lang/String;Ljava/lang/String;)Lorg/thymeleaf/engine/XMLElementDefinition;
      73: areturn
      74: aload_0
      75: aload_2
      76: aload_3
      77: invokevirtual #79                 // Method forTextName:(Ljava/lang/String;Ljava/lang/String;)Lorg/thymeleaf/engine/TextElementDefinition;
      80: areturn
      81: aload_0
      82: aload_2
      83: aload_3
      84: invokevirtual #80                 // Method forJavaScriptName:(Ljava/lang/String;Ljava/lang/String;)Lorg/thymeleaf/engine/TextElementDefinition;
      87: areturn
      88: aload_0
      89: aload_2
      90: aload_3
      91: invokevirtual #81                 // Method forCSSName:(Ljava/lang/String;Ljava/lang/String;)Lorg/thymeleaf/engine/TextElementDefinition;
      94: areturn
      95: new           #64                 // class java/lang/IllegalArgumentException
      98: dup
      99: new           #42                 // class java/lang/StringBuilder
     102: dup
     103: invokespecial #43                 // Method java/lang/StringBuilder."<init>":()V
     106: ldc           #74                 // String Element Definitions cannot be obtained for
     108: invokevirtual #45                 // Method java/lang/StringBuilder.append:(Ljava/lang/String;)Ljava/lang/StringBuilder;
     111: aload_1
     112: invokevirtual #58                 // Method java/lang/StringBuilder.append:(Ljava/lang/Object;)Ljava/lang/StringBuilder;
     115: ldc           #75                 // String  template mode
     117: invokevirtual #45                 // Method java/lang/StringBuilder.append:(Ljava/lang/String;)Ljava/lang/StringBuilder;
     120: invokevirtual #49                 // Method java/lang/StringBuilder.toString:()Ljava/lang/String;
     123: invokespecial #66                 // Method java/lang/IllegalArgumentException."<init>":(Ljava/lang/String;)V
     126: athrow
     127: new           #64                 // class java/lang/IllegalArgumentException
     130: dup
     131: new           #42                 // class java/lang/StringBuilder
     134: dup
     135: invokespecial #43                 // Method java/lang/StringBuilder."<init>":()V
     138: ldc           #76                 // String Unknown template mode
     140: invokevirtual #45                 // Method java/lang/StringBuilder.append:(Ljava/lang/String;)Ljava/lang/StringBuilder;
     143: aload_1
     144: invokevirtual #58                 // Method java/lang/StringBuilder.append:(Ljava/lang/Object;)Ljava/lang/StringBuilder;
     147: invokevirtual #49                 // Method java/lang/StringBuilder.toString:()Ljava/lang/String;
     150: invokespecial #66                 // Method java/lang/IllegalArgumentException."<init>":(Ljava/lang/String;)V
     153: athrow

  public org.thymeleaf.engine.ElementDefinition forName(org.thymeleaf.templatemode.TemplateMode, char[], int, int);
    Code:
       0: aload_1
       1: ifnonnull     14
       4: new           #64                 // class java/lang/IllegalArgumentException
       7: dup
       8: ldc           #65                 // String Template Mode cannot be null
      10: invokespecial #66                 // Method java/lang/IllegalArgumentException."<init>":(Ljava/lang/String;)V
      13: athrow
      14: getstatic     #67                 // Field org/thymeleaf/engine/ElementDefinitions$1.$SwitchMap$org$thymeleaf$templatemode$TemplateMode:[I
      17: aload_1
      18: invokevirtual #68                 // Method org/thymeleaf/templatemode/TemplateMode.ordinal:()I
      21: iaload
      22: tableswitch   { // 1 to 6
                     1: 60
                     2: 69
                     3: 78
                     4: 87
                     5: 96
                     6: 105
               default: 137
          }
      60: aload_0
      61: aload_2
      62: iload_3
      63: iload         4
      65: invokevirtual #82                 // Method forHTMLName:([CII)Lorg/thymeleaf/engine/HTMLElementDefinition;
      68: areturn
      69: aload_0
      70: aload_2
      71: iload_3
      72: iload         4
      74: invokevirtual #83                 // Method forXMLName:([CII)Lorg/thymeleaf/engine/XMLElementDefinition;
      77: areturn
      78: aload_0
      79: aload_2
      80: iload_3
      81: iload         4
      83: invokevirtual #84                 // Method forTextName:([CII)Lorg/thymeleaf/engine/TextElementDefinition;
      86: areturn
      87: aload_0
      88: aload_2
      89: iload_3
      90: iload         4
      92: invokevirtual #85                 // Method forJavaScriptName:([CII)Lorg/thymeleaf/engine/TextElementDefinition;
      95: areturn
      96: aload_0
      97: aload_2
      98: iload_3
      99: iload         4
     101: invokevirtual #86                 // Method forCSSName:([CII)Lorg/thymeleaf/engine/TextElementDefinition;
     104: areturn
     105: new           #64                 // class java/lang/IllegalArgumentException
     108: dup
     109: new           #42                 // class java/lang/StringBuilder
     112: dup
     113: invokespecial #43                 // Method java/lang/StringBuilder."<init>":()V
     116: ldc           #74                 // String Element Definitions cannot be obtained for
     118: invokevirtual #45                 // Method java/lang/StringBuilder.append:(Ljava/lang/String;)Ljava/lang/StringBuilder;
     121: aload_1
     122: invokevirtual #58                 // Method java/lang/StringBuilder.append:(Ljava/lang/Object;)Ljava/lang/StringBuilder;
     125: ldc           #75                 // String  template mode
     127: invokevirtual #45                 // Method java/lang/StringBuilder.append:(Ljava/lang/String;)Ljava/lang/StringBuilder;
     130: invokevirtual #49                 // Method java/lang/StringBuilder.toString:()Ljava/lang/String;
     133: invokespecial #66                 // Method java/lang/IllegalArgumentException."<init>":(Ljava/lang/String;)V
     136: athrow
     137: new           #64                 // class java/lang/IllegalArgumentException
     140: dup
     141: new           #42                 // class java/lang/StringBuilder
     144: dup
     145: invokespecial #43                 // Method java/lang/StringBuilder."<init>":()V
     148: ldc           #76                 // String Unknown template mode
     150: invokevirtual #45                 // Method java/lang/StringBuilder.append:(Ljava/lang/String;)Ljava/lang/StringBuilder;
     153: aload_1
     154: invokevirtual #58                 // Method java/lang/StringBuilder.append:(Ljava/lang/Object;)Ljava/lang/StringBuilder;
     157: invokevirtual #49                 // Method java/lang/StringBuilder.toString:()Ljava/lang/String;
     160: invokespecial #66                 // Method java/lang/IllegalArgumentException."<init>":(Ljava/lang/String;)V
     163: athrow

  public org.thymeleaf.engine.HTMLElementDefinition forHTMLName(java.lang.String);
    Code:
       0: aload_1
       1: ifnull        11
       4: aload_1
       5: invokevirtual #87                 // Method java/lang/String.length:()I
       8: ifne          21
      11: new           #64                 // class java/lang/IllegalArgumentException
      14: dup
      15: ldc           #88                 // String Name cannot be null or empty
      17: invokespecial #66                 // Method java/lang/IllegalArgumentException."<init>":(Ljava/lang/String;)V
      20: athrow
      21: aload_0
      22: getfield      #21                 // Field htmlElementRepository:Lorg/thymeleaf/engine/ElementDefinitions$ElementDefinitionRepository;
      25: aload_1
      26: invokevirtual #89                 // Method org/thymeleaf/engine/ElementDefinitions$ElementDefinitionRepository.getElement:(Ljava/lang/String;)Lorg/thymeleaf/engine/ElementDefinition;
      29: checkcast     #30                 // class org/thymeleaf/engine/HTMLElementDefinition
      32: areturn

  public org.thymeleaf.engine.HTMLElementDefinition forHTMLName(java.lang.String, java.lang.String);
    Code:
       0: aload_2
       1: ifnull        11
       4: aload_2
       5: invokevirtual #87                 // Method java/lang/String.length:()I
       8: ifne          21
      11: new           #64                 // class java/lang/IllegalArgumentException
      14: dup
      15: ldc           #88                 // String Name cannot be null or empty
      17: invokespecial #66                 // Method java/lang/IllegalArgumentException."<init>":(Ljava/lang/String;)V
      20: athrow
      21: aload_0
      22: getfield      #21                 // Field htmlElementRepository:Lorg/thymeleaf/engine/ElementDefinitions$ElementDefinitionRepository;
      25: aload_1
      26: aload_2
      27: invokevirtual #90                 // Method org/thymeleaf/engine/ElementDefinitions$ElementDefinitionRepository.getElement:(Ljava/lang/String;Ljava/lang/String;)Lorg/thymeleaf/engine/ElementDefinition;
      30: checkcast     #30                 // class org/thymeleaf/engine/HTMLElementDefinition
      33: areturn

  public org.thymeleaf.engine.HTMLElementDefinition forHTMLName(char[], int, int);
    Code:
       0: aload_1
       1: ifnull        8
       4: iload_3
       5: ifne          18
       8: new           #64                 // class java/lang/IllegalArgumentException
      11: dup
      12: ldc           #88                 // String Name cannot be null or empty
      14: invokespecial #66                 // Method java/lang/IllegalArgumentException."<init>":(Ljava/lang/String;)V
      17: athrow
      18: iload_2
      19: iflt          26
      22: iload_3
      23: ifge          36
      26: new           #64                 // class java/lang/IllegalArgumentException
      29: dup
      30: ldc           #91                 // String Both name offset and length must be equal to or greater than zero
      32: invokespecial #66                 // Method java/lang/IllegalArgumentException."<init>":(Ljava/lang/String;)V
      35: athrow
      36: aload_0
      37: getfield      #21                 // Field htmlElementRepository:Lorg/thymeleaf/engine/ElementDefinitions$ElementDefinitionRepository;
      40: aload_1
      41: iload_2
      42: iload_3
      43: invokevirtual #92                 // Method org/thymeleaf/engine/ElementDefinitions$ElementDefinitionRepository.getElement:([CII)Lorg/thymeleaf/engine/ElementDefinition;
      46: checkcast     #30                 // class org/thymeleaf/engine/HTMLElementDefinition
      49: areturn

  public org.thymeleaf.engine.XMLElementDefinition forXMLName(java.lang.String);
    Code:
       0: aload_1
       1: ifnull        11
       4: aload_1
       5: invokevirtual #87                 // Method java/lang/String.length:()I
       8: ifne          21
      11: new           #64                 // class java/lang/IllegalArgumentException
      14: dup
      15: ldc           #88                 // String Name cannot be null or empty
      17: invokespecial #66                 // Method java/lang/IllegalArgumentException."<init>":(Ljava/lang/String;)V
      20: athrow
      21: aload_0
      22: getfield      #23                 // Field xmlElementRepository:Lorg/thymeleaf/engine/ElementDefinitions$ElementDefinitionRepository;
      25: aload_1
      26: invokevirtual #89                 // Method org/thymeleaf/engine/ElementDefinitions$ElementDefinitionRepository.getElement:(Ljava/lang/String;)Lorg/thymeleaf/engine/ElementDefinition;
      29: checkcast     #56                 // class org/thymeleaf/engine/XMLElementDefinition
      32: areturn

  public org.thymeleaf.engine.XMLElementDefinition forXMLName(java.lang.String, java.lang.String);
    Code:
       0: aload_2
       1: ifnull        11
       4: aload_2
       5: invokevirtual #87                 // Method java/lang/String.length:()I
       8: ifne          21
      11: new           #64                 // class java/lang/IllegalArgumentException
      14: dup
      15: ldc           #88                 // String Name cannot be null or empty
      17: invokespecial #66                 // Method java/lang/IllegalArgumentException."<init>":(Ljava/lang/String;)V
      20: athrow
      21: aload_0
      22: getfield      #23                 // Field xmlElementRepository:Lorg/thymeleaf/engine/ElementDefinitions$ElementDefinitionRepository;
      25: aload_1
      26: aload_2
      27: invokevirtual #90                 // Method org/thymeleaf/engine/ElementDefinitions$ElementDefinitionRepository.getElement:(Ljava/lang/String;Ljava/lang/String;)Lorg/thymeleaf/engine/ElementDefinition;
      30: checkcast     #56                 // class org/thymeleaf/engine/XMLElementDefinition
      33: areturn

  public org.thymeleaf.engine.XMLElementDefinition forXMLName(char[], int, int);
    Code:
       0: aload_1
       1: ifnull        8
       4: iload_3
       5: ifne          18
       8: new           #64                 // class java/lang/IllegalArgumentException
      11: dup
      12: ldc           #88                 // String Name cannot be null or empty
      14: invokespecial #66                 // Method java/lang/IllegalArgumentException."<init>":(Ljava/lang/String;)V
      17: athrow
      18: iload_2
      19: iflt          26
      22: iload_3
      23: ifge          36
      26: new           #64                 // class java/lang/IllegalArgumentException
      29: dup
      30: ldc           #91                 // String Both name offset and length must be equal to or greater than zero
      32: invokespecial #66                 // Method java/lang/IllegalArgumentException."<init>":(Ljava/lang/String;)V
      35: athrow
      36: aload_0
      37: getfield      #23                 // Field xmlElementRepository:Lorg/thymeleaf/engine/ElementDefinitions$ElementDefinitionRepository;
      40: aload_1
      41: iload_2
      42: iload_3
      43: invokevirtual #92                 // Method org/thymeleaf/engine/ElementDefinitions$ElementDefinitionRepository.getElement:([CII)Lorg/thymeleaf/engine/ElementDefinition;
      46: checkcast     #56                 // class org/thymeleaf/engine/XMLElementDefinition
      49: areturn

  public org.thymeleaf.engine.TextElementDefinition forTextName(java.lang.String);
    Code:
       0: aload_1
       1: ifnonnull     14
       4: new           #64                 // class java/lang/IllegalArgumentException
       7: dup
       8: ldc           #93                 // String Name cannot be null
      10: invokespecial #66                 // Method java/lang/IllegalArgumentException."<init>":(Ljava/lang/String;)V
      13: athrow
      14: aload_0
      15: getfield      #25                 // Field textElementRepository:Lorg/thymeleaf/engine/ElementDefinitions$ElementDefinitionRepository;
      18: aload_1
      19: invokevirtual #89                 // Method org/thymeleaf/engine/ElementDefinitions$ElementDefinitionRepository.getElement:(Ljava/lang/String;)Lorg/thymeleaf/engine/ElementDefinition;
      22: checkcast     #62                 // class org/thymeleaf/engine/TextElementDefinition
      25: areturn

  public org.thymeleaf.engine.TextElementDefinition forTextName(java.lang.String, java.lang.String);
    Code:
       0: aload_2
       1: ifnonnull     14
       4: new           #64                 // class java/lang/IllegalArgumentException
       7: dup
       8: ldc           #93                 // String Name cannot be null
      10: invokespecial #66                 // Method java/lang/IllegalArgumentException."<init>":(Ljava/lang/String;)V
      13: athrow
      14: aload_0
      15: getfield      #25                 // Field textElementRepository:Lorg/thymeleaf/engine/ElementDefinitions$ElementDefinitionRepository;
      18: aload_1
      19: aload_2
      20: invokevirtual #90                 // Method org/thymeleaf/engine/ElementDefinitions$ElementDefinitionRepository.getElement:(Ljava/lang/String;Ljava/lang/String;)Lorg/thymeleaf/engine/ElementDefinition;
      23: checkcast     #62                 // class org/thymeleaf/engine/TextElementDefinition
      26: areturn

  public org.thymeleaf.engine.TextElementDefinition forTextName(char[], int, int);
    Code:
       0: aload_1
       1: ifnonnull     14
       4: new           #64                 // class java/lang/IllegalArgumentException
       7: dup
       8: ldc           #93                 // String Name cannot be null
      10: invokespecial #66                 // Method java/lang/IllegalArgumentException."<init>":(Ljava/lang/String;)V
      13: athrow
      14: iload_2
      15: iflt          22
      18: iload_3
      19: ifge          32
      22: new           #64                 // class java/lang/IllegalArgumentException
      25: dup
      26: ldc           #91                 // String Both name offset and length must be equal to or greater than zero
      28: invokespecial #66                 // Method java/lang/IllegalArgumentException."<init>":(Ljava/lang/String;)V
      31: athrow
      32: aload_0
      33: getfield      #25                 // Field textElementRepository:Lorg/thymeleaf/engine/ElementDefinitions$ElementDefinitionRepository;
      36: aload_1
      37: iload_2
      38: iload_3
      39: invokevirtual #92                 // Method org/thymeleaf/engine/ElementDefinitions$ElementDefinitionRepository.getElement:([CII)Lorg/thymeleaf/engine/ElementDefinition;
      42: checkcast     #62                 // class org/thymeleaf/engine/TextElementDefinition
      45: areturn

  public org.thymeleaf.engine.TextElementDefinition forJavaScriptName(java.lang.String);
    Code:
       0: aload_1
       1: ifnonnull     14
       4: new           #64                 // class java/lang/IllegalArgumentException
       7: dup
       8: ldc           #88                 // String Name cannot be null or empty
      10: invokespecial #66                 // Method java/lang/IllegalArgumentException."<init>":(Ljava/lang/String;)V
      13: athrow
      14: aload_0
      15: getfield      #27                 // Field javascriptElementRepository:Lorg/thymeleaf/engine/ElementDefinitions$ElementDefinitionRepository;
      18: aload_1
      19: invokevirtual #89                 // Method org/thymeleaf/engine/ElementDefinitions$ElementDefinitionRepository.getElement:(Ljava/lang/String;)Lorg/thymeleaf/engine/ElementDefinition;
      22: checkcast     #62                 // class org/thymeleaf/engine/TextElementDefinition
      25: areturn

  public org.thymeleaf.engine.TextElementDefinition forJavaScriptName(java.lang.String, java.lang.String);
    Code:
       0: aload_2
       1: ifnonnull     14
       4: new           #64                 // class java/lang/IllegalArgumentException
       7: dup
       8: ldc           #88                 // String Name cannot be null or empty
      10: invokespecial #66                 // Method java/lang/IllegalArgumentException."<init>":(Ljava/lang/String;)V
      13: athrow
      14: aload_0
      15: getfield      #27                 // Field javascriptElementRepository:Lorg/thymeleaf/engine/ElementDefinitions$ElementDefinitionRepository;
      18: aload_1
      19: aload_2
      20: invokevirtual #90                 // Method org/thymeleaf/engine/ElementDefinitions$ElementDefinitionRepository.getElement:(Ljava/lang/String;Ljava/lang/String;)Lorg/thymeleaf/engine/ElementDefinition;
      23: checkcast     #62                 // class org/thymeleaf/engine/TextElementDefinition
      26: areturn

  public org.thymeleaf.engine.TextElementDefinition forJavaScriptName(char[], int, int);
    Code:
       0: aload_1
       1: ifnonnull     14
       4: new           #64                 // class java/lang/IllegalArgumentException
       7: dup
       8: ldc           #88                 // String Name cannot be null or empty
      10: invokespecial #66                 // Method java/lang/IllegalArgumentException."<init>":(Ljava/lang/String;)V
      13: athrow
      14: iload_2
      15: iflt          22
      18: iload_3
      19: ifge          32
      22: new           #64                 // class java/lang/IllegalArgumentException
      25: dup
      26: ldc           #91                 // String Both name offset and length must be equal to or greater than zero
      28: invokespecial #66                 // Method java/lang/IllegalArgumentException."<init>":(Ljava/lang/String;)V
      31: athrow
      32: aload_0
      33: getfield      #27                 // Field javascriptElementRepository:Lorg/thymeleaf/engine/ElementDefinitions$ElementDefinitionRepository;
      36: aload_1
      37: iload_2
      38: iload_3
      39: invokevirtual #92                 // Method org/thymeleaf/engine/ElementDefinitions$ElementDefinitionRepository.getElement:([CII)Lorg/thymeleaf/engine/ElementDefinition;
      42: checkcast     #62                 // class org/thymeleaf/engine/TextElementDefinition
      45: areturn

  public org.thymeleaf.engine.TextElementDefinition forCSSName(java.lang.String);
    Code:
       0: aload_1
       1: ifnonnull     14
       4: new           #64                 // class java/lang/IllegalArgumentException
       7: dup
       8: ldc           #88                 // String Name cannot be null or empty
      10: invokespecial #66                 // Method java/lang/IllegalArgumentException."<init>":(Ljava/lang/String;)V
      13: athrow
      14: aload_0
      15: getfield      #29                 // Field cssElementRepository:Lorg/thymeleaf/engine/ElementDefinitions$ElementDefinitionRepository;
      18: aload_1
      19: invokevirtual #89                 // Method org/thymeleaf/engine/ElementDefinitions$ElementDefinitionRepository.getElement:(Ljava/lang/String;)Lorg/thymeleaf/engine/ElementDefinition;
      22: checkcast     #62                 // class org/thymeleaf/engine/TextElementDefinition
      25: areturn

  public org.thymeleaf.engine.TextElementDefinition forCSSName(java.lang.String, java.lang.String);
    Code:
       0: aload_2
       1: ifnonnull     14
       4: new           #64                 // class java/lang/IllegalArgumentException
       7: dup
       8: ldc           #88                 // String Name cannot be null or empty
      10: invokespecial #66                 // Method java/lang/IllegalArgumentException."<init>":(Ljava/lang/String;)V
      13: athrow
      14: aload_0
      15: getfield      #29                 // Field cssElementRepository:Lorg/thymeleaf/engine/ElementDefinitions$ElementDefinitionRepository;
      18: aload_1
      19: aload_2
      20: invokevirtual #90                 // Method org/thymeleaf/engine/ElementDefinitions$ElementDefinitionRepository.getElement:(Ljava/lang/String;Ljava/lang/String;)Lorg/thymeleaf/engine/ElementDefinition;
      23: checkcast     #62                 // class org/thymeleaf/engine/TextElementDefinition
      26: areturn

  public org.thymeleaf.engine.TextElementDefinition forCSSName(char[], int, int);
    Code:
       0: aload_1
       1: ifnonnull     14
       4: new           #64                 // class java/lang/IllegalArgumentException
       7: dup
       8: ldc           #88                 // String Name cannot be null or empty
      10: invokespecial #66                 // Method java/lang/IllegalArgumentException."<init>":(Ljava/lang/String;)V
      13: athrow
      14: iload_2
      15: iflt          22
      18: iload_3
      19: ifge          32
      22: new           #64                 // class java/lang/IllegalArgumentException
      25: dup
      26: ldc           #91                 // String Both name offset and length must be equal to or greater than zero
      28: invokespecial #66                 // Method java/lang/IllegalArgumentException."<init>":(Ljava/lang/String;)V
      31: athrow
      32: aload_0
      33: getfield      #29                 // Field cssElementRepository:Lorg/thymeleaf/engine/ElementDefinitions$ElementDefinitionRepository;
      36: aload_1
      37: iload_2
      38: iload_3
      39: invokevirtual #92                 // Method org/thymeleaf/engine/ElementDefinitions$ElementDefinitionRepository.getElement:([CII)Lorg/thymeleaf/engine/ElementDefinition;
      42: checkcast     #62                 // class org/thymeleaf/engine/TextElementDefinition
      45: areturn

  static org.thymeleaf.engine.HTMLElementDefinition access$100(org.thymeleaf.engine.HTMLElementName, org.thymeleaf.engine.HTMLElementType, java.util.Set);
    Code:
       0: aload_0
       1: aload_1
       2: aload_2
       3: invokestatic  #3                  // Method buildHTMLElementDefinition:(Lorg/thymeleaf/engine/HTMLElementName;Lorg/thymeleaf/engine/HTMLElementType;Ljava/util/Set;)Lorg/thymeleaf/engine/HTMLElementDefinition;
       6: areturn

  static org.thymeleaf.engine.XMLElementDefinition access$200(org.thymeleaf.engine.XMLElementName, java.util.Set);
    Code:
       0: aload_0
       1: aload_1
       2: invokestatic  #2                  // Method buildXMLElementDefinition:(Lorg/thymeleaf/engine/XMLElementName;Ljava/util/Set;)Lorg/thymeleaf/engine/XMLElementDefinition;
       5: areturn

  static org.thymeleaf.engine.TextElementDefinition access$300(org.thymeleaf.templatemode.TemplateMode, org.thymeleaf.engine.TextElementName, java.util.Set);
    Code:
       0: aload_0
       1: aload_1
       2: aload_2
       3: invokestatic  #1                  // Method buildTextElementDefinition:(Lorg/thymeleaf/templatemode/TemplateMode;Lorg/thymeleaf/engine/TextElementName;Ljava/util/Set;)Lorg/thymeleaf/engine/TextElementDefinition;
       6: areturn

  static {};
    Code:
       0: new           #12                 // class org/thymeleaf/engine/ElementDefinitions$HTMLElementDefinitionSpec
       3: dup
       4: ldc           #94                 // String html
       6: invokestatic  #95                 // Method org/thymeleaf/engine/ElementNames.forHTMLName:(Ljava/lang/String;)Lorg/thymeleaf/engine/HTMLElementName;
       9: getstatic     #96                 // Field org/thymeleaf/engine/HTMLElementType.NORMAL:Lorg/thymeleaf/engine/HTMLElementType;
      12: invokespecial #97                 // Method org/thymeleaf/engine/ElementDefinitions$HTMLElementDefinitionSpec."<init>":(Lorg/thymeleaf/engine/HTMLElementName;Lorg/thymeleaf/engine/HTMLElementType;)V
      15: putstatic     #98                 // Field HTML:Lorg/thymeleaf/engine/ElementDefinitions$HTMLElementDefinitionSpec;
      18: new           #12                 // class org/thymeleaf/engine/ElementDefinitions$HTMLElementDefinitionSpec
      21: dup
      22: ldc           #99                 // String head
      24: invokestatic  #95                 // Method org/thymeleaf/engine/ElementNames.forHTMLName:(Ljava/lang/String;)Lorg/thymeleaf/engine/HTMLElementName;
      27: getstatic     #96                 // Field org/thymeleaf/engine/HTMLElementType.NORMAL:Lorg/thymeleaf/engine/HTMLElementType;
      30: invokespecial #97                 // Method org/thymeleaf/engine/ElementDefinitions$HTMLElementDefinitionSpec."<init>":(Lorg/thymeleaf/engine/HTMLElementName;Lorg/thymeleaf/engine/HTMLElementType;)V
      33: putstatic     #100                // Field HEAD:Lorg/thymeleaf/engine/ElementDefinitions$HTMLElementDefinitionSpec;
      36: new           #12                 // class org/thymeleaf/engine/ElementDefinitions$HTMLElementDefinitionSpec
      39: dup
      40: ldc           #101                // String title
      42: invokestatic  #95                 // Method org/thymeleaf/engine/ElementNames.forHTMLName:(Ljava/lang/String;)Lorg/thymeleaf/engine/HTMLElementName;
      45: getstatic     #102                // Field org/thymeleaf/engine/HTMLElementType.ESCAPABLE_RAW_TEXT:Lorg/thymeleaf/engine/HTMLElementType;
      48: invokespecial #97                 // Method org/thymeleaf/engine/ElementDefinitions$HTMLElementDefinitionSpec."<init>":(Lorg/thymeleaf/engine/HTMLElementName;Lorg/thymeleaf/engine/HTMLElementType;)V
      51: putstatic     #103                // Field TITLE:Lorg/thymeleaf/engine/ElementDefinitions$HTMLElementDefinitionSpec;
      54: new           #12                 // class org/thymeleaf/engine/ElementDefinitions$HTMLElementDefinitionSpec
      57: dup
      58: ldc           #104                // String base
      60: invokestatic  #95                 // Method org/thymeleaf/engine/ElementNames.forHTMLName:(Ljava/lang/String;)Lorg/thymeleaf/engine/HTMLElementName;
      63: getstatic     #105                // Field org/thymeleaf/engine/HTMLElementType.VOID:Lorg/thymeleaf/engine/HTMLElementType;
      66: invokespecial #97                 // Method org/thymeleaf/engine/ElementDefinitions$HTMLElementDefinitionSpec."<init>":(Lorg/thymeleaf/engine/HTMLElementName;Lorg/thymeleaf/engine/HTMLElementType;)V
      69: putstatic     #106                // Field BASE:Lorg/thymeleaf/engine/ElementDefinitions$HTMLElementDefinitionSpec;
      72: new           #12                 // class org/thymeleaf/engine/ElementDefinitions$HTMLElementDefinitionSpec
      75: dup
      76: ldc           #107                // String link
      78: invokestatic  #95                 // Method org/thymeleaf/engine/ElementNames.forHTMLName:(Ljava/lang/String;)Lorg/thymeleaf/engine/HTMLElementName;
      81: getstatic     #105                // Field org/thymeleaf/engine/HTMLElementType.VOID:Lorg/thymeleaf/engine/HTMLElementType;
      84: invokespecial #97                 // Method org/thymeleaf/engine/ElementDefinitions$HTMLElementDefinitionSpec."<init>":(Lorg/thymeleaf/engine/HTMLElementName;Lorg/thymeleaf/engine/HTMLElementType;)V
      87: putstatic     #108                // Field LINK:Lorg/thymeleaf/engine/ElementDefinitions$HTMLElementDefinitionSpec;
      90: new           #12                 // class org/thymeleaf/engine/ElementDefinitions$HTMLElementDefinitionSpec
      93: dup
      94: ldc           #109                // String meta
      96: invokestatic  #95                 // Method org/thymeleaf/engine/ElementNames.forHTMLName:(Ljava/lang/String;)Lorg/thymeleaf/engine/HTMLElementName;
      99: getstatic     #105                // Field org/thymeleaf/engine/HTMLElementType.VOID:Lorg/thymeleaf/engine/HTMLElementType;
     102: invokespecial #97                 // Method org/thymeleaf/engine/ElementDefinitions$HTMLElementDefinitionSpec."<init>":(Lorg/thymeleaf/engine/HTMLElementName;Lorg/thymeleaf/engine/HTMLElementType;)V
     105: putstatic     #110                // Field META:Lorg/thymeleaf/engine/ElementDefinitions$HTMLElementDefinitionSpec;
     108: new           #12                 // class org/thymeleaf/engine/ElementDefinitions$HTMLElementDefinitionSpec
     111: dup
     112: ldc           #111                // String style
     114: invokestatic  #95                 // Method org/thymeleaf/engine/ElementNames.forHTMLName:(Ljava/lang/String;)Lorg/thymeleaf/engine/HTMLElementName;
     117: getstatic     #112                // Field org/thymeleaf/engine/HTMLElementType.RAW_TEXT:Lorg/thymeleaf/engine/HTMLElementType;
     120: invokespecial #97                 // Method org/thymeleaf/engine/ElementDefinitions$HTMLElementDefinitionSpec."<init>":(Lorg/thymeleaf/engine/HTMLElementName;Lorg/thymeleaf/engine/HTMLElementType;)V
     123: putstatic     #113                // Field STYLE:Lorg/thymeleaf/engine/ElementDefinitions$HTMLElementDefinitionSpec;
     126: new           #12                 // class org/thymeleaf/engine/ElementDefinitions$HTMLElementDefinitionSpec
     129: dup
     130: ldc           #114                // String script
     132: invokestatic  #95                 // Method org/thymeleaf/engine/ElementNames.forHTMLName:(Ljava/lang/String;)Lorg/thymeleaf/engine/HTMLElementName;
     135: getstatic     #112                // Field org/thymeleaf/engine/HTMLElementType.RAW_TEXT:Lorg/thymeleaf/engine/HTMLElementType;
     138: invokespecial #97                 // Method org/thymeleaf/engine/ElementDefinitions$HTMLElementDefinitionSpec."<init>":(Lorg/thymeleaf/engine/HTMLElementName;Lorg/thymeleaf/engine/HTMLElementType;)V
     141: putstatic     #115                // Field SCRIPT:Lorg/thymeleaf/engine/ElementDefinitions$HTMLElementDefinitionSpec;
     144: new           #12                 // class org/thymeleaf/engine/ElementDefinitions$HTMLElementDefinitionSpec
     147: dup
     148: ldc           #116                // String noscript
     150: invokestatic  #95                 // Method org/thymeleaf/engine/ElementNames.forHTMLName:(Ljava/lang/String;)Lorg/thymeleaf/engine/HTMLElementName;
     153: getstatic     #96                 // Field org/thymeleaf/engine/HTMLElementType.NORMAL:Lorg/thymeleaf/engine/HTMLElementType;
     156: invokespecial #97                 // Method org/thymeleaf/engine/ElementDefinitions$HTMLElementDefinitionSpec."<init>":(Lorg/thymeleaf/engine/HTMLElementName;Lorg/thymeleaf/engine/HTMLElementType;)V
     159: putstatic     #117                // Field NOSCRIPT:Lorg/thymeleaf/engine/ElementDefinitions$HTMLElementDefinitionSpec;
     162: new           #12                 // class org/thymeleaf/engine/ElementDefinitions$HTMLElementDefinitionSpec
     165: dup
     166: ldc           #118                // String body
     168: invokestatic  #95                 // Method org/thymeleaf/engine/ElementNames.forHTMLName:(Ljava/lang/String;)Lorg/thymeleaf/engine/HTMLElementName;
     171: getstatic     #96                 // Field org/thymeleaf/engine/HTMLElementType.NORMAL:Lorg/thymeleaf/engine/HTMLElementType;
     174: invokespecial #97                 // Method org/thymeleaf/engine/ElementDefinitions$HTMLElementDefinitionSpec."<init>":(Lorg/thymeleaf/engine/HTMLElementName;Lorg/thymeleaf/engine/HTMLElementType;)V
     177: putstatic     #119                // Field BODY:Lorg/thymeleaf/engine/ElementDefinitions$HTMLElementDefinitionSpec;
     180: new           #12                 // class org/thymeleaf/engine/ElementDefinitions$HTMLElementDefinitionSpec
     183: dup
     184: ldc           #120                // String article
     186: invokestatic  #95                 // Method org/thymeleaf/engine/ElementNames.forHTMLName:(Ljava/lang/String;)Lorg/thymeleaf/engine/HTMLElementName;
     189: getstatic     #96                 // Field org/thymeleaf/engine/HTMLElementType.NORMAL:Lorg/thymeleaf/engine/HTMLElementType;
     192: invokespecial #97                 // Method org/thymeleaf/engine/ElementDefinitions$HTMLElementDefinitionSpec."<init>":(Lorg/thymeleaf/engine/HTMLElementName;Lorg/thymeleaf/engine/HTMLElementType;)V
     195: putstatic     #121                // Field ARTICLE:Lorg/thymeleaf/engine/ElementDefinitions$HTMLElementDefinitionSpec;
     198: new           #12                 // class org/thymeleaf/engine/ElementDefinitions$HTMLElementDefinitionSpec
     201: dup
     202: ldc           #122                // String section
     204: invokestatic  #95                 // Method org/thymeleaf/engine/ElementNames.forHTMLName:(Ljava/lang/String;)Lorg/thymeleaf/engine/HTMLElementName;
     207: getstatic     #96                 // Field org/thymeleaf/engine/HTMLElementType.NORMAL:Lorg/thymeleaf/engine/HTMLElementType;
     210: invokespecial #97                 // Method org/thymeleaf/engine/ElementDefinitions$HTMLElementDefinitionSpec."<init>":(Lorg/thymeleaf/engine/HTMLElementName;Lorg/thymeleaf/engine/HTMLElementType;)V
     213: putstatic     #123                // Field SECTION:Lorg/thymeleaf/engine/ElementDefinitions$HTMLElementDefinitionSpec;
     216: new           #12                 // class org/thymeleaf/engine/ElementDefinitions$HTMLElementDefinitionSpec
     219: dup
     220: ldc           #124                // String nav
     222: invokestatic  #95                 // Method org/thymeleaf/engine/ElementNames.forHTMLName:(Ljava/lang/String;)Lorg/thymeleaf/engine/HTMLElementName;
     225: getstatic     #96                 // Field org/thymeleaf/engine/HTMLElementType.NORMAL:Lorg/thymeleaf/engine/HTMLElementType;
     228: invokespecial #97                 // Method org/thymeleaf/engine/ElementDefinitions$HTMLElementDefinitionSpec."<init>":(Lorg/thymeleaf/engine/HTMLElementName;Lorg/thymeleaf/engine/HTMLElementType;)V
     231: putstatic     #125                // Field NAV:Lorg/thymeleaf/engine/ElementDefinitions$HTMLElementDefinitionSpec;
     234: new           #12                 // class org/thymeleaf/engine/ElementDefinitions$HTMLElementDefinitionSpec
     237: dup
     238: ldc           #126                // String aside
     240: invokestatic  #95                 // Method org/thymeleaf/engine/ElementNames.forHTMLName:(Ljava/lang/String;)Lorg/thymeleaf/engine/HTMLElementName;
     243: getstatic     #96                 // Field org/thymeleaf/engine/HTMLElementType.NORMAL:Lorg/thymeleaf/engine/HTMLElementType;
     246: invokespecial #97                 // Method org/thymeleaf/engine/ElementDefinitions$HTMLElementDefinitionSpec."<init>":(Lorg/thymeleaf/engine/HTMLElementName;Lorg/thymeleaf/engine/HTMLElementType;)V
     249: putstatic     #127                // Field ASIDE:Lorg/thymeleaf/engine/ElementDefinitions$HTMLElementDefinitionSpec;
     252: new           #12                 // class org/thymeleaf/engine/ElementDefinitions$HTMLElementDefinitionSpec
     255: dup
     256: ldc           #128                // String h1
     258: invokestatic  #95                 // Method org/thymeleaf/engine/ElementNames.forHTMLName:(Ljava/lang/String;)Lorg/thymeleaf/engine/HTMLElementName;
     261: getstatic     #96                 // Field org/thymeleaf/engine/HTMLElementType.NORMAL:Lorg/thymeleaf/engine/HTMLElementType;
     264: invokespecial #97                 // Method org/thymeleaf/engine/ElementDefinitions$HTMLElementDefinitionSpec."<init>":(Lorg/thymeleaf/engine/HTMLElementName;Lorg/thymeleaf/engine/HTMLElementType;)V
     267: putstatic     #129                // Field H1:Lorg/thymeleaf/engine/ElementDefinitions$HTMLElementDefinitionSpec;
     270: new           #12                 // class org/thymeleaf/engine/ElementDefinitions$HTMLElementDefinitionSpec
     273: dup
     274: ldc           #130                // String h2
     276: invokestatic  #95                 // Method org/thymeleaf/engine/ElementNames.forHTMLName:(Ljava/lang/String;)Lorg/thymeleaf/engine/HTMLElementName;
     279: getstatic     #96                 // Field org/thymeleaf/engine/HTMLElementType.NORMAL:Lorg/thymeleaf/engine/HTMLElementType;
     282: invokespecial #97                 // Method org/thymeleaf/engine/ElementDefinitions$HTMLElementDefinitionSpec."<init>":(Lorg/thymeleaf/engine/HTMLElementName;Lorg/thymeleaf/engine/HTMLElementType;)V
     285: putstatic     #131                // Field H2:Lorg/thymeleaf/engine/ElementDefinitions$HTMLElementDefinitionSpec;
     288: new           #12                 // class org/thymeleaf/engine/ElementDefinitions$HTMLElementDefinitionSpec
     291: dup
     292: ldc           #132                // String h3
     294: invokestatic  #95                 // Method org/thymeleaf/engine/ElementNames.forHTMLName:(Ljava/lang/String;)Lorg/thymeleaf/engine/HTMLElementName;
     297: getstatic     #96                 // Field org/thymeleaf/engine/HTMLElementType.NORMAL:Lorg/thymeleaf/engine/HTMLElementType;
     300: invokespecial #97                 // Method org/thymeleaf/engine/ElementDefinitions$HTMLElementDefinitionSpec."<init>":(Lorg/thymeleaf/engine/HTMLElementName;Lorg/thymeleaf/engine/HTMLElementType;)V
     303: putstatic     #133                // Field H3:Lorg/thymeleaf/engine/ElementDefinitions$HTMLElementDefinitionSpec;
     306: new           #12                 // class org/thymeleaf/engine/ElementDefinitions$HTMLElementDefinitionSpec
     309: dup
     310: ldc           #134                // String h4
     312: invokestatic  #95                 // Method org/thymeleaf/engine/ElementNames.forHTMLName:(Ljava/lang/String;)Lorg/thymeleaf/engine/HTMLElementName;
     315: getstatic     #96                 // Field org/thymeleaf/engine/HTMLElementType.NORMAL:Lorg/thymeleaf/engine/HTMLElementType;
     318: invokespecial #97                 // Method org/thymeleaf/engine/ElementDefinitions$HTMLElementDefinitionSpec."<init>":(Lorg/thymeleaf/engine/HTMLElementName;Lorg/thymeleaf/engine/HTMLElementType;)V
     321: putstatic     #135                // Field H4:Lorg/thymeleaf/engine/ElementDefinitions$HTMLElementDefinitionSpec;
     324: new           #12                 // class org/thymeleaf/engine/ElementDefinitions$HTMLElementDefinitionSpec
     327: dup
     328: ldc           #136                // String h5
     330: invokestatic  #95                 // Method org/thymeleaf/engine/ElementNames.forHTMLName:(Ljava/lang/String;)Lorg/thymeleaf/engine/HTMLElementName;
     333: getstatic     #96                 // Field org/thymeleaf/engine/HTMLElementType.NORMAL:Lorg/thymeleaf/engine/HTMLElementType;
     336: invokespecial #97                 // Method org/thymeleaf/engine/ElementDefinitions$HTMLElementDefinitionSpec."<init>":(Lorg/thymeleaf/engine/HTMLElementName;Lorg/thymeleaf/engine/HTMLElementType;)V
     339: putstatic     #137                // Field H5:Lorg/thymeleaf/engine/ElementDefinitions$HTMLElementDefinitionSpec;
     342: new           #12                 // class org/thymeleaf/engine/ElementDefinitions$HTMLElementDefinitionSpec
     345: dup
     346: ldc           #138                // String h6
     348: invokestatic  #95                 // Method org/thymeleaf/engine/ElementNames.forHTMLName:(Ljava/lang/String;)Lorg/thymeleaf/engine/HTMLElementName;
     351: getstatic     #96                 // Field org/thymeleaf/engine/HTMLElementType.NORMAL:Lorg/thymeleaf/engine/HTMLElementType;
     354: invokespecial #97                 // Method org/thymeleaf/engine/ElementDefinitions$HTMLElementDefinitionSpec."<init>":(Lorg/thymeleaf/engine/HTMLElementName;Lorg/thymeleaf/engine/HTMLElementType;)V
     357: putstatic     #139                // Field H6:Lorg/thymeleaf/engine/ElementDefinitions$HTMLElementDefinitionSpec;
     360: new           #12                 // class org/thymeleaf/engine/ElementDefinitions$HTMLElementDefinitionSpec
     363: dup
     364: ldc           #140                // String hgroup
     366: invokestatic  #95                 // Method org/thymeleaf/engine/ElementNames.forHTMLName:(Ljava/lang/String;)Lorg/thymeleaf/engine/HTMLElementName;
     369: getstatic     #96                 // Field org/thymeleaf/engine/HTMLElementType.NORMAL:Lorg/thymeleaf/engine/HTMLElementType;
     372: invokespecial #97                 // Method org/thymeleaf/engine/ElementDefinitions$HTMLElementDefinitionSpec."<init>":(Lorg/thymeleaf/engine/HTMLElementName;Lorg/thymeleaf/engine/HTMLElementType;)V
     375: putstatic     #141                // Field HGROUP:Lorg/thymeleaf/engine/ElementDefinitions$HTMLElementDefinitionSpec;
     378: new           #12                 // class org/thymeleaf/engine/ElementDefinitions$HTMLElementDefinitionSpec
     381: dup
     382: ldc           #142                // String header
     384: invokestatic  #95                 // Method org/thymeleaf/engine/ElementNames.forHTMLName:(Ljava/lang/String;)Lorg/thymeleaf/engine/HTMLElementName;
     387: getstatic     #96                 // Field org/thymeleaf/engine/HTMLElementType.NORMAL:Lorg/thymeleaf/engine/HTMLElementType;
     390: invokespecial #97                 // Method org/thymeleaf/engine/ElementDefinitions$HTMLElementDefinitionSpec."<init>":(Lorg/thymeleaf/engine/HTMLElementName;Lorg/thymeleaf/engine/HTMLElementType;)V
     393: putstatic     #143                // Field HEADER:Lorg/thymeleaf/engine/ElementDefinitions$HTMLElementDefinitionSpec;
     396: new           #12                 // class org/thymeleaf/engine/ElementDefinitions$HTMLElementDefinitionSpec
     399: dup
     400: ldc           #144                // String footer
     402: invokestatic  #95                 // Method org/thymeleaf/engine/ElementNames.forHTMLName:(Ljava/lang/String;)Lorg/thymeleaf/engine/HTMLElementName;
     405: getstatic     #96                 // Field org/thymeleaf/engine/HTMLElementType.NORMAL:Lorg/thymeleaf/engine/HTMLElementType;
     408: invokespecial #97                 // Method org/thymeleaf/engine/ElementDefinitions$HTMLElementDefinitionSpec."<init>":(Lorg/thymeleaf/engine/HTMLElementName;Lorg/thymeleaf/engine/HTMLElementType;)V
     411: putstatic     #145                // Field FOOTER:Lorg/thymeleaf/engine/ElementDefinitions$HTMLElementDefinitionSpec;
     414: new           #12                 // class org/thymeleaf/engine/ElementDefinitions$HTMLElementDefinitionSpec
     417: dup
     418: ldc           #146                // String address
     420: invokestatic  #95                 // Method org/thymeleaf/engine/ElementNames.forHTMLName:(Ljava/lang/String;)Lorg/thymeleaf/engine/HTMLElementName;
     423: getstatic     #96                 // Field org/thymeleaf/engine/HTMLElementType.NORMAL:Lorg/thymeleaf/engine/HTMLElementType;
     426: invokespecial #97                 // Method org/thymeleaf/engine/ElementDefinitions$HTMLElementDefinitionSpec."<init>":(Lorg/thymeleaf/engine/HTMLElementName;Lorg/thymeleaf/engine/HTMLElementType;)V
     429: putstatic     #147                // Field ADDRESS:Lorg/thymeleaf/engine/ElementDefinitions$HTMLElementDefinitionSpec;
     432: new           #12                 // class org/thymeleaf/engine/ElementDefinitions$HTMLElementDefinitionSpec
     435: dup
     436: ldc           #148                // String main
     438: invokestatic  #95                 // Method org/thymeleaf/engine/ElementNames.forHTMLName:(Ljava/lang/String;)Lorg/thymeleaf/engine/HTMLElementName;
     441: getstatic     #96                 // Field org/thymeleaf/engine/HTMLElementType.NORMAL:Lorg/thymeleaf/engine/HTMLElementType;
     444: invokespecial #97                 // Method org/thymeleaf/engine/ElementDefinitions$HTMLElementDefinitionSpec."<init>":(Lorg/thymeleaf/engine/HTMLElementName;Lorg/thymeleaf/engine/HTMLElementType;)V
     447: putstatic     #149                // Field MAIN:Lorg/thymeleaf/engine/ElementDefinitions$HTMLElementDefinitionSpec;
     450: new           #12                 // class org/thymeleaf/engine/ElementDefinitions$HTMLElementDefinitionSpec
     453: dup
     454: ldc           #150                // String p
     456: invokestatic  #95                 // Method org/thymeleaf/engine/ElementNames.forHTMLName:(Ljava/lang/String;)Lorg/thymeleaf/engine/HTMLElementName;
     459: getstatic     #96                 // Field org/thymeleaf/engine/HTMLElementType.NORMAL:Lorg/thymeleaf/engine/HTMLElementType;
     462: invokespecial #97                 // Method org/thymeleaf/engine/ElementDefinitions$HTMLElementDefinitionSpec."<init>":(Lorg/thymeleaf/engine/HTMLElementName;Lorg/thymeleaf/engine/HTMLElementType;)V
     465: putstatic     #151                // Field P:Lorg/thymeleaf/engine/ElementDefinitions$HTMLElementDefinitionSpec;
     468: new           #12                 // class org/thymeleaf/engine/ElementDefinitions$HTMLElementDefinitionSpec
     471: dup
     472: ldc           #152                // String hr
     474: invokestatic  #95                 // Method org/thymeleaf/engine/ElementNames.forHTMLName:(Ljava/lang/String;)Lorg/thymeleaf/engine/HTMLElementName;
     477: getstatic     #105                // Field org/thymeleaf/engine/HTMLElementType.VOID:Lorg/thymeleaf/engine/HTMLElementType;
     480: invokespecial #97                 // Method org/thymeleaf/engine/ElementDefinitions$HTMLElementDefinitionSpec."<init>":(Lorg/thymeleaf/engine/HTMLElementName;Lorg/thymeleaf/engine/HTMLElementType;)V
     483: putstatic     #153                // Field HR:Lorg/thymeleaf/engine/ElementDefinitions$HTMLElementDefinitionSpec;
     486: new           #12                 // class org/thymeleaf/engine/ElementDefinitions$HTMLElementDefinitionSpec
     489: dup
     490: ldc           #154                // String pre
     492: invokestatic  #95                 // Method org/thymeleaf/engine/ElementNames.forHTMLName:(Ljava/lang/String;)Lorg/thymeleaf/engine/HTMLElementName;
     495: getstatic     #96                 // Field org/thymeleaf/engine/HTMLElementType.NORMAL:Lorg/thymeleaf/engine/HTMLElementType;
     498: invokespecial #97                 // Method org/thymeleaf/engine/ElementDefinitions$HTMLElementDefinitionSpec."<init>":(Lorg/thymeleaf/engine/HTMLElementName;Lorg/thymeleaf/engine/HTMLElementType;)V
     501: putstatic     #155                // Field PRE:Lorg/thymeleaf/engine/ElementDefinitions$HTMLElementDefinitionSpec;
     504: new           #12                 // class org/thymeleaf/engine/ElementDefinitions$HTMLElementDefinitionSpec
     507: dup
     508: ldc           #156                // String blockquote
     510: invokestatic  #95                 // Method org/thymeleaf/engine/ElementNames.forHTMLName:(Ljava/lang/String;)Lorg/thymeleaf/engine/HTMLElementName;
     513: getstatic     #96                 // Field org/thymeleaf/engine/HTMLElementType.NORMAL:Lorg/thymeleaf/engine/HTMLElementType;
     516: invokespecial #97                 // Method org/thymeleaf/engine/ElementDefinitions$HTMLElementDefinitionSpec."<init>":(Lorg/thymeleaf/engine/HTMLElementName;Lorg/thymeleaf/engine/HTMLElementType;)V
     519: putstatic     #157                // Field BLOCKQUOTE:Lorg/thymeleaf/engine/ElementDefinitions$HTMLElementDefinitionSpec;
     522: new           #12                 // class org/thymeleaf/engine/ElementDefinitions$HTMLElementDefinitionSpec
     525: dup
     526: ldc           #158                // String ol
     528: invokestatic  #95                 // Method org/thymeleaf/engine/ElementNames.forHTMLName:(Ljava/lang/String;)Lorg/thymeleaf/engine/HTMLElementName;
     531: getstatic     #96                 // Field org/thymeleaf/engine/HTMLElementType.NORMAL:Lorg/thymeleaf/engine/HTMLElementType;
     534: invokespecial #97                 // Method org/thymeleaf/engine/ElementDefinitions$HTMLElementDefinitionSpec."<init>":(Lorg/thymeleaf/engine/HTMLElementName;Lorg/thymeleaf/engine/HTMLElementType;)V
     537: putstatic     #159                // Field OL:Lorg/thymeleaf/engine/ElementDefinitions$HTMLElementDefinitionSpec;
     540: new           #12                 // class org/thymeleaf/engine/ElementDefinitions$HTMLElementDefinitionSpec
     543: dup
     544: ldc           #160                // String ul
     546: invokestatic  #95                 // Method org/thymeleaf/engine/ElementNames.forHTMLName:(Ljava/lang/String;)Lorg/thymeleaf/engine/HTMLElementName;
     549: getstatic     #96                 // Field org/thymeleaf/engine/HTMLElementType.NORMAL:Lorg/thymeleaf/engine/HTMLElementType;
     552: invokespecial #97                 // Method org/thymeleaf/engine/ElementDefinitions$HTMLElementDefinitionSpec."<init>":(Lorg/thymeleaf/engine/HTMLElementName;Lorg/thymeleaf/engine/HTMLElementType;)V
     555: putstatic     #161                // Field UL:Lorg/thymeleaf/engine/ElementDefinitions$HTMLElementDefinitionSpec;
     558: new           #12                 // class org/thymeleaf/engine/ElementDefinitions$HTMLElementDefinitionSpec
     561: dup
     562: ldc           #162                // String li
     564: invokestatic  #95                 // Method org/thymeleaf/engine/ElementNames.forHTMLName:(Ljava/lang/String;)Lorg/thymeleaf/engine/HTMLElementName;
     567: getstatic     #96                 // Field org/thymeleaf/engine/HTMLElementType.NORMAL:Lorg/thymeleaf/engine/HTMLElementType;
     570: invokespecial #97                 // Method org/thymeleaf/engine/ElementDefinitions$HTMLElementDefinitionSpec."<init>":(Lorg/thymeleaf/engine/HTMLElementName;Lorg/thymeleaf/engine/HTMLElementType;)V
     573: putstatic     #163                // Field LI:Lorg/thymeleaf/engine/ElementDefinitions$HTMLElementDefinitionSpec;
     576: new           #12                 // class org/thymeleaf/engine/ElementDefinitions$HTMLElementDefinitionSpec
     579: dup
     580: ldc           #164                // String dl
     582: invokestatic  #95                 // Method org/thymeleaf/engine/ElementNames.forHTMLName:(Ljava/lang/String;)Lorg/thymeleaf/engine/HTMLElementName;
     585: getstatic     #96                 // Field org/thymeleaf/engine/HTMLElementType.NORMAL:Lorg/thymeleaf/engine/HTMLElementType;
     588: invokespecial #97                 // Method org/thymeleaf/engine/ElementDefinitions$HTMLElementDefinitionSpec."<init>":(Lorg/thymeleaf/engine/HTMLElementName;Lorg/thymeleaf/engine/HTMLElementType;)V
     591: putstatic     #165                // Field DL:Lorg/thymeleaf/engine/ElementDefinitions$HTMLElementDefinitionSpec;
     594: new           #12                 // class org/thymeleaf/engine/ElementDefinitions$HTMLElementDefinitionSpec
     597: dup
     598: ldc           #166                // String dt
     600: invokestatic  #95                 // Method org/thymeleaf/engine/ElementNames.forHTMLName:(Ljava/lang/String;)Lorg/thymeleaf/engine/HTMLElementName;
     603: getstatic     #96                 // Field org/thymeleaf/engine/HTMLElementType.NORMAL:Lorg/thymeleaf/engine/HTMLElementType;
     606: invokespecial #97                 // Method org/thymeleaf/engine/ElementDefinitions$HTMLElementDefinitionSpec."<init>":(Lorg/thymeleaf/engine/HTMLElementName;Lorg/thymeleaf/engine/HTMLElementType;)V
     609: putstatic     #167                // Field DT:Lorg/thymeleaf/engine/ElementDefinitions$HTMLElementDefinitionSpec;
     612: new           #12                 // class org/thymeleaf/engine/ElementDefinitions$HTMLElementDefinitionSpec
     615: dup
     616: ldc           #168                // String dd
     618: invokestatic  #95                 // Method org/thymeleaf/engine/ElementNames.forHTMLName:(Ljava/lang/String;)Lorg/thymeleaf/engine/HTMLElementName;
     621: getstatic     #96                 // Field org/thymeleaf/engine/HTMLElementType.NORMAL:Lorg/thymeleaf/engine/HTMLElementType;
     624: invokespecial #97                 // Method org/thymeleaf/engine/ElementDefinitions$HTMLElementDefinitionSpec."<init>":(Lorg/thymeleaf/engine/HTMLElementName;Lorg/thymeleaf/engine/HTMLElementType;)V
     627: putstatic     #169                // Field DD:Lorg/thymeleaf/engine/ElementDefinitions$HTMLElementDefinitionSpec;
     630: new           #12                 // class org/thymeleaf/engine/ElementDefinitions$HTMLElementDefinitionSpec
     633: dup
     634: ldc           #170                // String figure
     636: invokestatic  #95                 // Method org/thymeleaf/engine/ElementNames.forHTMLName:(Ljava/lang/String;)Lorg/thymeleaf/engine/HTMLElementName;
     639: getstatic     #96                 // Field org/thymeleaf/engine/HTMLElementType.NORMAL:Lorg/thymeleaf/engine/HTMLElementType;
     642: invokespecial #97                 // Method org/thymeleaf/engine/ElementDefinitions$HTMLElementDefinitionSpec."<init>":(Lorg/thymeleaf/engine/HTMLElementName;Lorg/thymeleaf/engine/HTMLElementType;)V
     645: putstatic     #171                // Field FIGURE:Lorg/thymeleaf/engine/ElementDefinitions$HTMLElementDefinitionSpec;
     648: new           #12                 // class org/thymeleaf/engine/ElementDefinitions$HTMLElementDefinitionSpec
     651: dup
     652: ldc           #172                // String figcaption
     654: invokestatic  #95                 // Method org/thymeleaf/engine/ElementNames.forHTMLName:(Ljava/lang/String;)Lorg/thymeleaf/engine/HTMLElementName;
     657: getstatic     #96                 // Field org/thymeleaf/engine/HTMLElementType.NORMAL:Lorg/thymeleaf/engine/HTMLElementType;
     660: invokespecial #97                 // Method org/thymeleaf/engine/ElementDefinitions$HTMLElementDefinitionSpec."<init>":(Lorg/thymeleaf/engine/HTMLElementName;Lorg/thymeleaf/engine/HTMLElementType;)V
     663: putstatic     #173                // Field FIGCAPTION:Lorg/thymeleaf/engine/ElementDefinitions$HTMLElementDefinitionSpec;
     666: new           #12                 // class org/thymeleaf/engine/ElementDefinitions$HTMLElementDefinitionSpec
     669: dup
     670: ldc           #174                // String div
     672: invokestatic  #95                 // Method org/thymeleaf/engine/ElementNames.forHTMLName:(Ljava/lang/String;)Lorg/thymeleaf/engine/HTMLElementName;
     675: getstatic     #96                 // Field org/thymeleaf/engine/HTMLElementType.NORMAL:Lorg/thymeleaf/engine/HTMLElementType;
     678: invokespecial #97                 // Method org/thymeleaf/engine/ElementDefinitions$HTMLElementDefinitionSpec."<init>":(Lorg/thymeleaf/engine/HTMLElementName;Lorg/thymeleaf/engine/HTMLElementType;)V
     681: putstatic     #175                // Field DIV:Lorg/thymeleaf/engine/ElementDefinitions$HTMLElementDefinitionSpec;
     684: new           #12                 // class org/thymeleaf/engine/ElementDefinitions$HTMLElementDefinitionSpec
     687: dup
     688: ldc           #176                // String a
     690: invokestatic  #95                 // Method org/thymeleaf/engine/ElementNames.forHTMLName:(Ljava/lang/String;)Lorg/thymeleaf/engine/HTMLElementName;
     693: getstatic     #96                 // Field org/thymeleaf/engine/HTMLElementType.NORMAL:Lorg/thymeleaf/engine/HTMLElementType;
     696: invokespecial #97                 // Method org/thymeleaf/engine/ElementDefinitions$HTMLElementDefinitionSpec."<init>":(Lorg/thymeleaf/engine/HTMLElementName;Lorg/thymeleaf/engine/HTMLElementType;)V
     699: putstatic     #177                // Field A:Lorg/thymeleaf/engine/ElementDefinitions$HTMLElementDefinitionSpec;
     702: new           #12                 // class org/thymeleaf/engine/ElementDefinitions$HTMLElementDefinitionSpec
     705: dup
     706: ldc           #178                // String em
     708: invokestatic  #95                 // Method org/thymeleaf/engine/ElementNames.forHTMLName:(Ljava/lang/String;)Lorg/thymeleaf/engine/HTMLElementName;
     711: getstatic     #96                 // Field org/thymeleaf/engine/HTMLElementType.NORMAL:Lorg/thymeleaf/engine/HTMLElementType;
     714: invokespecial #97                 // Method org/thymeleaf/engine/ElementDefinitions$HTMLElementDefinitionSpec."<init>":(Lorg/thymeleaf/engine/HTMLElementName;Lorg/thymeleaf/engine/HTMLElementType;)V
     717: putstatic     #179                // Field EM:Lorg/thymeleaf/engine/ElementDefinitions$HTMLElementDefinitionSpec;
     720: new           #12                 // class org/thymeleaf/engine/ElementDefinitions$HTMLElementDefinitionSpec
     723: dup
     724: ldc           #180                // String strong
     726: invokestatic  #95                 // Method org/thymeleaf/engine/ElementNames.forHTMLName:(Ljava/lang/String;)Lorg/thymeleaf/engine/HTMLElementName;
     729: getstatic     #96                 // Field org/thymeleaf/engine/HTMLElementType.NORMAL:Lorg/thymeleaf/engine/HTMLElementType;
     732: invokespecial #97                 // Method org/thymeleaf/engine/ElementDefinitions$HTMLElementDefinitionSpec."<init>":(Lorg/thymeleaf/engine/HTMLElementName;Lorg/thymeleaf/engine/HTMLElementType;)V
     735: putstatic     #181                // Field STRONG:Lorg/thymeleaf/engine/ElementDefinitions$HTMLElementDefinitionSpec;
     738: new           #12                 // class org/thymeleaf/engine/ElementDefinitions$HTMLElementDefinitionSpec
     741: dup
     742: ldc           #182                // String small
     744: invokestatic  #95                 // Method org/thymeleaf/engine/ElementNames.forHTMLName:(Ljava/lang/String;)Lorg/thymeleaf/engine/HTMLElementName;
     747: getstatic     #96                 // Field org/thymeleaf/engine/HTMLElementType.NORMAL:Lorg/thymeleaf/engine/HTMLElementType;
     750: invokespecial #97                 // Method org/thymeleaf/engine/ElementDefinitions$HTMLElementDefinitionSpec."<init>":(Lorg/thymeleaf/engine/HTMLElementName;Lorg/thymeleaf/engine/HTMLElementType;)V
     753: putstatic     #183                // Field SMALL:Lorg/thymeleaf/engine/ElementDefinitions$HTMLElementDefinitionSpec;
     756: new           #12                 // class org/thymeleaf/engine/ElementDefinitions$HTMLElementDefinitionSpec
     759: dup
     760: ldc           #184                // String s
     762: invokestatic  #95                 // Method org/thymeleaf/engine/ElementNames.forHTMLName:(Ljava/lang/String;)Lorg/thymeleaf/engine/HTMLElementName;
     765: getstatic     #96                 // Field org/thymeleaf/engine/HTMLElementType.NORMAL:Lorg/thymeleaf/engine/HTMLElementType;
     768: invokespecial #97                 // Method org/thymeleaf/engine/ElementDefinitions$HTMLElementDefinitionSpec."<init>":(Lorg/thymeleaf/engine/HTMLElementName;Lorg/thymeleaf/engine/HTMLElementType;)V
     771: putstatic     #185                // Field S:Lorg/thymeleaf/engine/ElementDefinitions$HTMLElementDefinitionSpec;
     774: new           #12                 // class org/thymeleaf/engine/ElementDefinitions$HTMLElementDefinitionSpec
     777: dup
     778: ldc           #186                // String cite
     780: invokestatic  #95                 // Method org/thymeleaf/engine/ElementNames.forHTMLName:(Ljava/lang/String;)Lorg/thymeleaf/engine/HTMLElementName;
     783: getstatic     #96                 // Field org/thymeleaf/engine/HTMLElementType.NORMAL:Lorg/thymeleaf/engine/HTMLElementType;
     786: invokespecial #97                 // Method org/thymeleaf/engine/ElementDefinitions$HTMLElementDefinitionSpec."<init>":(Lorg/thymeleaf/engine/HTMLElementName;Lorg/thymeleaf/engine/HTMLElementType;)V
     789: putstatic     #187                // Field CITE:Lorg/thymeleaf/engine/ElementDefinitions$HTMLElementDefinitionSpec;
     792: new           #12                 // class org/thymeleaf/engine/ElementDefinitions$HTMLElementDefinitionSpec
     795: dup
     796: ldc           #188                // String g
     798: invokestatic  #95                 // Method org/thymeleaf/engine/ElementNames.forHTMLName:(Ljava/lang/String;)Lorg/thymeleaf/engine/HTMLElementName;
     801: getstatic     #96                 // Field org/thymeleaf/engine/HTMLElementType.NORMAL:Lorg/thymeleaf/engine/HTMLElementType;
     804: invokespecial #97                 // Method org/thymeleaf/engine/ElementDefinitions$HTMLElementDefinitionSpec."<init>":(Lorg/thymeleaf/engine/HTMLElementName;Lorg/thymeleaf/engine/HTMLElementType;)V
     807: putstatic     #189                // Field G:Lorg/thymeleaf/engine/ElementDefinitions$HTMLElementDefinitionSpec;
     810: new           #12                 // class org/thymeleaf/engine/ElementDefinitions$HTMLElementDefinitionSpec
     813: dup
     814: ldc           #190                // String dfn
     816: invokestatic  #95                 // Method org/thymeleaf/engine/ElementNames.forHTMLName:(Ljava/lang/String;)Lorg/thymeleaf/engine/HTMLElementName;
     819: getstatic     #96                 // Field org/thymeleaf/engine/HTMLElementType.NORMAL:Lorg/thymeleaf/engine/HTMLElementType;
     822: invokespecial #97                 // Method org/thymeleaf/engine/ElementDefinitions$HTMLElementDefinitionSpec."<init>":(Lorg/thymeleaf/engine/HTMLElementName;Lorg/thymeleaf/engine/HTMLElementType;)V
     825: putstatic     #191                // Field DFN:Lorg/thymeleaf/engine/ElementDefinitions$HTMLElementDefinitionSpec;
     828: new           #12                 // class org/thymeleaf/engine/ElementDefinitions$HTMLElementDefinitionSpec
     831: dup
     832: ldc           #192                // String abbr
     834: invokestatic  #95                 // Method org/thymeleaf/engine/ElementNames.forHTMLName:(Ljava/lang/String;)Lorg/thymeleaf/engine/HTMLElementName;
     837: getstatic     #96                 // Field org/thymeleaf/engine/HTMLElementType.NORMAL:Lorg/thymeleaf/engine/HTMLElementType;
     840: invokespecial #97                 // Method org/thymeleaf/engine/ElementDefinitions$HTMLElementDefinitionSpec."<init>":(Lorg/thymeleaf/engine/HTMLElementName;Lorg/thymeleaf/engine/HTMLElementType;)V
     843: putstatic     #193                // Field ABBR:Lorg/thymeleaf/engine/ElementDefinitions$HTMLElementDefinitionSpec;
     846: new           #12                 // class org/thymeleaf/engine/ElementDefinitions$HTMLElementDefinitionSpec
     849: dup
     850: ldc           #194                // String time
     852: invokestatic  #95                 // Method org/thymeleaf/engine/ElementNames.forHTMLName:(Ljava/lang/String;)Lorg/thymeleaf/engine/HTMLElementName;
     855: getstatic     #96                 // Field org/thymeleaf/engine/HTMLElementType.NORMAL:Lorg/thymeleaf/engine/HTMLElementType;
     858: invokespecial #97                 // Method org/thymeleaf/engine/ElementDefinitions$HTMLElementDefinitionSpec."<init>":(Lorg/thymeleaf/engine/HTMLElementName;Lorg/thymeleaf/engine/HTMLElementType;)V
     861: putstatic     #195                // Field TIME:Lorg/thymeleaf/engine/ElementDefinitions$HTMLElementDefinitionSpec;
     864: new           #12                 // class org/thymeleaf/engine/ElementDefinitions$HTMLElementDefinitionSpec
     867: dup
     868: ldc           #196                // String code
     870: invokestatic  #95                 // Method org/thymeleaf/engine/ElementNames.forHTMLName:(Ljava/lang/String;)Lorg/thymeleaf/engine/HTMLElementName;
     873: getstatic     #96                 // Field org/thymeleaf/engine/HTMLElementType.NORMAL:Lorg/thymeleaf/engine/HTMLElementType;
     876: invokespecial #97                 // Method org/thymeleaf/engine/ElementDefinitions$HTMLElementDefinitionSpec."<init>":(Lorg/thymeleaf/engine/HTMLElementName;Lorg/thymeleaf/engine/HTMLElementType;)V
     879: putstatic     #197                // Field CODE:Lorg/thymeleaf/engine/ElementDefinitions$HTMLElementDefinitionSpec;
     882: new           #12                 // class org/thymeleaf/engine/ElementDefinitions$HTMLElementDefinitionSpec
     885: dup
     886: ldc           #198                // String var
     888: invokestatic  #95                 // Method org/thymeleaf/engine/ElementNames.forHTMLName:(Ljava/lang/String;)Lorg/thymeleaf/engine/HTMLElementName;
     891: getstatic     #96                 // Field org/thymeleaf/engine/HTMLElementType.NORMAL:Lorg/thymeleaf/engine/HTMLElementType;
     894: invokespecial #97                 // Method org/thymeleaf/engine/ElementDefinitions$HTMLElementDefinitionSpec."<init>":(Lorg/thymeleaf/engine/HTMLElementName;Lorg/thymeleaf/engine/HTMLElementType;)V
     897: putstatic     #199                // Field VAR:Lorg/thymeleaf/engine/ElementDefinitions$HTMLElementDefinitionSpec;
     900: new           #12                 // class org/thymeleaf/engine/ElementDefinitions$HTMLElementDefinitionSpec
     903: dup
     904: ldc           #200                // String samp
     906: invokestatic  #95                 // Method org/thymeleaf/engine/ElementNames.forHTMLName:(Ljava/lang/String;)Lorg/thymeleaf/engine/HTMLElementName;
     909: getstatic     #96                 // Field org/thymeleaf/engine/HTMLElementType.NORMAL:Lorg/thymeleaf/engine/HTMLElementType;
     912: invokespecial #97                 // Method org/thymeleaf/engine/ElementDefinitions$HTMLElementDefinitionSpec."<init>":(Lorg/thymeleaf/engine/HTMLElementName;Lorg/thymeleaf/engine/HTMLElementType;)V
     915: putstatic     #201                // Field SAMP:Lorg/thymeleaf/engine/ElementDefinitions$HTMLElementDefinitionSpec;
     918: new           #12                 // class org/thymeleaf/engine/ElementDefinitions$HTMLElementDefinitionSpec
     921: dup
     922: ldc           #202                // String kbd
     924: invokestatic  #95                 // Method org/thymeleaf/engine/ElementNames.forHTMLName:(Ljava/lang/String;)Lorg/thymeleaf/engine/HTMLElementName;
     927: getstatic     #96                 // Field org/thymeleaf/engine/HTMLElementType.NORMAL:Lorg/thymeleaf/engine/HTMLElementType;
     930: invokespecial #97                 // Method org/thymeleaf/engine/ElementDefinitions$HTMLElementDefinitionSpec."<init>":(Lorg/thymeleaf/engine/HTMLElementName;Lorg/thymeleaf/engine/HTMLElementType;)V
     933: putstatic     #203                // Field KBD:Lorg/thymeleaf/engine/ElementDefinitions$HTMLElementDefinitionSpec;
     936: new           #12                 // class org/thymeleaf/engine/ElementDefinitions$HTMLElementDefinitionSpec
     939: dup
     940: ldc           #204                // String sub
     942: invokestatic  #95                 // Method org/thymeleaf/engine/ElementNames.forHTMLName:(Ljava/lang/String;)Lorg/thymeleaf/engine/HTMLElementName;
     945: getstatic     #96                 // Field org/thymeleaf/engine/HTMLElementType.NORMAL:Lorg/thymeleaf/engine/HTMLElementType;
     948: invokespecial #97                 // Method org/thymeleaf/engine/ElementDefinitions$HTMLElementDefinitionSpec."<init>":(Lorg/thymeleaf/engine/HTMLElementName;Lorg/thymeleaf/engine/HTMLElementType;)V
     951: putstatic     #205                // Field SUB:Lorg/thymeleaf/engine/ElementDefinitions$HTMLElementDefinitionSpec;
     954: new           #12                 // class org/thymeleaf/engine/ElementDefinitions$HTMLElementDefinitionSpec
     957: dup
     958: ldc           #206                // String sup
     960: invokestatic  #95                 // Method org/thymeleaf/engine/ElementNames.forHTMLName:(Ljava/lang/String;)Lorg/thymeleaf/engine/HTMLElementName;
     963: getstatic     #96                 // Field org/thymeleaf/engine/HTMLElementType.NORMAL:Lorg/thymeleaf/engine/HTMLElementType;
     966: invokespecial #97                 // Method org/thymeleaf/engine/ElementDefinitions$HTMLElementDefinitionSpec."<init>":(Lorg/thymeleaf/engine/HTMLElementName;Lorg/thymeleaf/engine/HTMLElementType;)V
     969: putstatic     #207                // Field SUP:Lorg/thymeleaf/engine/ElementDefinitions$HTMLElementDefinitionSpec;
     972: new           #12                 // class org/thymeleaf/engine/ElementDefinitions$HTMLElementDefinitionSpec
     975: dup
     976: ldc           #208                // String i
     978: invokestatic  #95                 // Method org/thymeleaf/engine/ElementNames.forHTMLName:(Ljava/lang/String;)Lorg/thymeleaf/engine/HTMLElementName;
     981: getstatic     #96                 // Field org/thymeleaf/engine/HTMLElementType.NORMAL:Lorg/thymeleaf/engine/HTMLElementType;
     984: invokespecial #97                 // Method org/thymeleaf/engine/ElementDefinitions$HTMLElementDefinitionSpec."<init>":(Lorg/thymeleaf/engine/HTMLElementName;Lorg/thymeleaf/engine/HTMLElementType;)V
     987: putstatic     #209                // Field I:Lorg/thymeleaf/engine/ElementDefinitions$HTMLElementDefinitionSpec;
     990: new           #12                 // class org/thymeleaf/engine/ElementDefinitions$HTMLElementDefinitionSpec
     993: dup
     994: ldc           #210                // String b
     996: invokestatic  #95                 // Method org/thymeleaf/engine/ElementNames.forHTMLName:(Ljava/lang/String;)Lorg/thymeleaf/engine/HTMLElementName;
     999: getstatic     #96                 // Field org/thymeleaf/engine/HTMLElementType.NORMAL:Lorg/thymeleaf/engine/HTMLElementType;
    1002: invokespecial #97                 // Method org/thymeleaf/engine/ElementDefinitions$HTMLElementDefinitionSpec."<init>":(Lorg/thymeleaf/engine/HTMLElementName;Lorg/thymeleaf/engine/HTMLElementType;)V
    1005: putstatic     #211                // Field B:Lorg/thymeleaf/engine/ElementDefinitions$HTMLElementDefinitionSpec;
    1008: new           #12                 // class org/thymeleaf/engine/ElementDefinitions$HTMLElementDefinitionSpec
    1011: dup
    1012: ldc           #212                // String u
    1014: invokestatic  #95                 // Method org/thymeleaf/engine/ElementNames.forHTMLName:(Ljava/lang/String;)Lorg/thymeleaf/engine/HTMLElementName;
    1017: getstatic     #96                 // Field org/thymeleaf/engine/HTMLElementType.NORMAL:Lorg/thymeleaf/engine/HTMLElementType;
    1020: invokespecial #97                 // Method org/thymeleaf/engine/ElementDefinitions$HTMLElementDefinitionSpec."<init>":(Lorg/thymeleaf/engine/HTMLElementName;Lorg/thymeleaf/engine/HTMLElementType;)V
    1023: putstatic     #213                // Field U:Lorg/thymeleaf/engine/ElementDefinitions$HTMLElementDefinitionSpec;
    1026: new           #12                 // class org/thymeleaf/engine/ElementDefinitions$HTMLElementDefinitionSpec
    1029: dup
    1030: ldc           #214                // String mark
    1032: invokestatic  #95                 // Method org/thymeleaf/engine/ElementNames.forHTMLName:(Ljava/lang/String;)Lorg/thymeleaf/engine/HTMLElementName;
    1035: getstatic     #96                 // Field org/thymeleaf/engine/HTMLElementType.NORMAL:Lorg/thymeleaf/engine/HTMLElementType;
    1038: invokespecial #97                 // Method org/thymeleaf/engine/ElementDefinitions$HTMLElementDefinitionSpec."<init>":(Lorg/thymeleaf/engine/HTMLElementName;Lorg/thymeleaf/engine/HTMLElementType;)V
    1041: putstatic     #215                // Field MARK:Lorg/thymeleaf/engine/ElementDefinitions$HTMLElementDefinitionSpec;
    1044: new           #12                 // class org/thymeleaf/engine/ElementDefinitions$HTMLElementDefinitionSpec
    1047: dup
    1048: ldc           #216                // String ruby
    1050: invokestatic  #95                 // Method org/thymeleaf/engine/ElementNames.forHTMLName:(Ljava/lang/String;)Lorg/thymeleaf/engine/HTMLElementName;
    1053: getstatic     #96                 // Field org/thymeleaf/engine/HTMLElementType.NORMAL:Lorg/thymeleaf/engine/HTMLElementType;
    1056: invokespecial #97                 // Method org/thymeleaf/engine/ElementDefinitions$HTMLElementDefinitionSpec."<init>":(Lorg/thymeleaf/engine/HTMLElementName;Lorg/thymeleaf/engine/HTMLElementType;)V
    1059: putstatic     #217                // Field RUBY:Lorg/thymeleaf/engine/ElementDefinitions$HTMLElementDefinitionSpec;
    1062: new           #12                 // class org/thymeleaf/engine/ElementDefinitions$HTMLElementDefinitionSpec
    1065: dup
    1066: ldc           #218                // String rb
    1068: invokestatic  #95                 // Method org/thymeleaf/engine/ElementNames.forHTMLName:(Ljava/lang/String;)Lorg/thymeleaf/engine/HTMLElementName;
    1071: getstatic     #96                 // Field org/thymeleaf/engine/HTMLElementType.NORMAL:Lorg/thymeleaf/engine/HTMLElementType;
    1074: invokespecial #97                 // Method org/thymeleaf/engine/ElementDefinitions$HTMLElementDefinitionSpec."<init>":(Lorg/thymeleaf/engine/HTMLElementName;Lorg/thymeleaf/engine/HTMLElementType;)V
    1077: putstatic     #219                // Field RB:Lorg/thymeleaf/engine/ElementDefinitions$HTMLElementDefinitionSpec;
    1080: new           #12                 // class org/thymeleaf/engine/ElementDefinitions$HTMLElementDefinitionSpec
    1083: dup
    1084: ldc           #220                // String rt
    1086: invokestatic  #95                 // Method org/thymeleaf/engine/ElementNames.forHTMLName:(Ljava/lang/String;)Lorg/thymeleaf/engine/HTMLElementName;
    1089: getstatic     #96                 // Field org/thymeleaf/engine/HTMLElementType.NORMAL:Lorg/thymeleaf/engine/HTMLElementType;
    1092: invokespecial #97                 // Method org/thymeleaf/engine/ElementDefinitions$HTMLElementDefinitionSpec."<init>":(Lorg/thymeleaf/engine/HTMLElementName;Lorg/thymeleaf/engine/HTMLElementType;)V
    1095: putstatic     #221                // Field RT:Lorg/thymeleaf/engine/ElementDefinitions$HTMLElementDefinitionSpec;
    1098: new           #12                 // class org/thymeleaf/engine/ElementDefinitions$HTMLElementDefinitionSpec
    1101: dup
    1102: ldc           #222                // String rtc
    1104: invokestatic  #95                 // Method org/thymeleaf/engine/ElementNames.forHTMLName:(Ljava/lang/String;)Lorg/thymeleaf/engine/HTMLElementName;
    1107: getstatic     #96                 // Field org/thymeleaf/engine/HTMLElementType.NORMAL:Lorg/thymeleaf/engine/HTMLElementType;
    1110: invokespecial #97                 // Method org/thymeleaf/engine/ElementDefinitions$HTMLElementDefinitionSpec."<init>":(Lorg/thymeleaf/engine/HTMLElementName;Lorg/thymeleaf/engine/HTMLElementType;)V
    1113: putstatic     #223                // Field RTC:Lorg/thymeleaf/engine/ElementDefinitions$HTMLElementDefinitionSpec;
    1116: new           #12                 // class org/thymeleaf/engine/ElementDefinitions$HTMLElementDefinitionSpec
    1119: dup
    1120: ldc           #224                // String rp
    1122: invokestatic  #95                 // Method org/thymeleaf/engine/ElementNames.forHTMLName:(Ljava/lang/String;)Lorg/thymeleaf/engine/HTMLElementName;
    1125: getstatic     #96                 // Field org/thymeleaf/engine/HTMLElementType.NORMAL:Lorg/thymeleaf/engine/HTMLElementType;
    1128: invokespecial #97                 // Method org/thymeleaf/engine/ElementDefinitions$HTMLElementDefinitionSpec."<init>":(Lorg/thymeleaf/engine/HTMLElementName;Lorg/thymeleaf/engine/HTMLElementType;)V
    1131: putstatic     #225                // Field RP:Lorg/thymeleaf/engine/ElementDefinitions$HTMLElementDefinitionSpec;
    1134: new           #12                 // class org/thymeleaf/engine/ElementDefinitions$HTMLElementDefinitionSpec
    1137: dup
    1138: ldc           #226                // String bdi
    1140: invokestatic  #95                 // Method org/thymeleaf/engine/ElementNames.forHTMLName:(Ljava/lang/String;)Lorg/thymeleaf/engine/HTMLElementName;
    1143: getstatic     #96                 // Field org/thymeleaf/engine/HTMLElementType.NORMAL:Lorg/thymeleaf/engine/HTMLElementType;
    1146: invokespecial #97                 // Method org/thymeleaf/engine/ElementDefinitions$HTMLElementDefinitionSpec."<init>":(Lorg/thymeleaf/engine/HTMLElementName;Lorg/thymeleaf/engine/HTMLElementType;)V
    1149: putstatic     #227                // Field BDI:Lorg/thymeleaf/engine/ElementDefinitions$HTMLElementDefinitionSpec;
    1152: new           #12                 // class org/thymeleaf/engine/ElementDefinitions$HTMLElementDefinitionSpec
    1155: dup
    1156: ldc           #228                // String bdo
    1158: invokestatic  #95                 // Method org/thymeleaf/engine/ElementNames.forHTMLName:(Ljava/lang/String;)Lorg/thymeleaf/engine/HTMLElementName;
    1161: getstatic     #96                 // Field org/thymeleaf/engine/HTMLElementType.NORMAL:Lorg/thymeleaf/engine/HTMLElementType;
    1164: invokespecial #97                 // Method org/thymeleaf/engine/ElementDefinitions$HTMLElementDefinitionSpec."<init>":(Lorg/thymeleaf/engine/HTMLElementName;Lorg/thymeleaf/engine/HTMLElementType;)V
    1167: putstatic     #229                // Field BDO:Lorg/thymeleaf/engine/ElementDefinitions$HTMLElementDefinitionSpec;
    1170: new           #12                 // class org/thymeleaf/engine/ElementDefinitions$HTMLElementDefinitionSpec
    1173: dup
    1174: ldc           #230                // String span
    1176: invokestatic  #95                 // Method org/thymeleaf/engine/ElementNames.forHTMLName:(Ljava/lang/String;)Lorg/thymeleaf/engine/HTMLElementName;
    1179: getstatic     #96                 // Field org/thymeleaf/engine/HTMLElementType.NORMAL:Lorg/thymeleaf/engine/HTMLElementType;
    1182: invokespecial #97                 // Method org/thymeleaf/engine/ElementDefinitions$HTMLElementDefinitionSpec."<init>":(Lorg/thymeleaf/engine/HTMLElementName;Lorg/thymeleaf/engine/HTMLElementType;)V
    1185: putstatic     #231                // Field SPAN:Lorg/thymeleaf/engine/ElementDefinitions$HTMLElementDefinitionSpec;
    1188: new           #12                 // class org/thymeleaf/engine/ElementDefinitions$HTMLElementDefinitionSpec
    1191: dup
    1192: ldc           #232                // String br
    1194: invokestatic  #95                 // Method org/thymeleaf/engine/ElementNames.forHTMLName:(Ljava/lang/String;)Lorg/thymeleaf/engine/HTMLElementName;
    1197: getstatic     #105                // Field org/thymeleaf/engine/HTMLElementType.VOID:Lorg/thymeleaf/engine/HTMLElementType;
    1200: invokespecial #97                 // Method org/thymeleaf/engine/ElementDefinitions$HTMLElementDefinitionSpec."<init>":(Lorg/thymeleaf/engine/HTMLElementName;Lorg/thymeleaf/engine/HTMLElementType;)V
    1203: putstatic     #233                // Field BR:Lorg/thymeleaf/engine/ElementDefinitions$HTMLElementDefinitionSpec;
    1206: new           #12                 // class org/thymeleaf/engine/ElementDefinitions$HTMLElementDefinitionSpec
    1209: dup
    1210: ldc           #234                // String wbr
    1212: invokestatic  #95                 // Method org/thymeleaf/engine/ElementNames.forHTMLName:(Ljava/lang/String;)Lorg/thymeleaf/engine/HTMLElementName;
    1215: getstatic     #105                // Field org/thymeleaf/engine/HTMLElementType.VOID:Lorg/thymeleaf/engine/HTMLElementType;
    1218: invokespecial #97                 // Method org/thymeleaf/engine/ElementDefinitions$HTMLElementDefinitionSpec."<init>":(Lorg/thymeleaf/engine/HTMLElementName;Lorg/thymeleaf/engine/HTMLElementType;)V
    1221: putstatic     #235                // Field WBR:Lorg/thymeleaf/engine/ElementDefinitions$HTMLElementDefinitionSpec;
    1224: new           #12                 // class org/thymeleaf/engine/ElementDefinitions$HTMLElementDefinitionSpec
    1227: dup
    1228: ldc           #236                // String ins
    1230: invokestatic  #95                 // Method org/thymeleaf/engine/ElementNames.forHTMLName:(Ljava/lang/String;)Lorg/thymeleaf/engine/HTMLElementName;
    1233: getstatic     #96                 // Field org/thymeleaf/engine/HTMLElementType.NORMAL:Lorg/thymeleaf/engine/HTMLElementType;
    1236: invokespecial #97                 // Method org/thymeleaf/engine/ElementDefinitions$HTMLElementDefinitionSpec."<init>":(Lorg/thymeleaf/engine/HTMLElementName;Lorg/thymeleaf/engine/HTMLElementType;)V
    1239: putstatic     #237                // Field INS:Lorg/thymeleaf/engine/ElementDefinitions$HTMLElementDefinitionSpec;
    1242: new           #12                 // class org/thymeleaf/engine/ElementDefinitions$HTMLElementDefinitionSpec
    1245: dup
    1246: ldc           #238                // String del
    1248: invokestatic  #95                 // Method org/thymeleaf/engine/ElementNames.forHTMLName:(Ljava/lang/String;)Lorg/thymeleaf/engine/HTMLElementName;
    1251: getstatic     #96                 // Field org/thymeleaf/engine/HTMLElementType.NORMAL:Lorg/thymeleaf/engine/HTMLElementType;
    1254: invokespecial #97                 // Method org/thymeleaf/engine/ElementDefinitions$HTMLElementDefinitionSpec."<init>":(Lorg/thymeleaf/engine/HTMLElementName;Lorg/thymeleaf/engine/HTMLElementType;)V
    1257: putstatic     #239                // Field DEL:Lorg/thymeleaf/engine/ElementDefinitions$HTMLElementDefinitionSpec;
    1260: new           #12                 // class org/thymeleaf/engine/ElementDefinitions$HTMLElementDefinitionSpec
    1263: dup
    1264: ldc           #240                // String img
    1266: invokestatic  #95                 // Method org/thymeleaf/engine/ElementNames.forHTMLName:(Ljava/lang/String;)Lorg/thymeleaf/engine/HTMLElementName;
    1269: getstatic     #105                // Field org/thymeleaf/engine/HTMLElementType.VOID:Lorg/thymeleaf/engine/HTMLElementType;
    1272: invokespecial #97                 // Method org/thymeleaf/engine/ElementDefinitions$HTMLElementDefinitionSpec."<init>":(Lorg/thymeleaf/engine/HTMLElementName;Lorg/thymeleaf/engine/HTMLElementType;)V
    1275: putstatic     #241                // Field IMG:Lorg/thymeleaf/engine/ElementDefinitions$HTMLElementDefinitionSpec;
    1278: new           #12                 // class org/thymeleaf/engine/ElementDefinitions$HTMLElementDefinitionSpec
    1281: dup
    1282: ldc           #242                // String iframe
    1284: invokestatic  #95                 // Method org/thymeleaf/engine/ElementNames.forHTMLName:(Ljava/lang/String;)Lorg/thymeleaf/engine/HTMLElementName;
    1287: getstatic     #96                 // Field org/thymeleaf/engine/HTMLElementType.NORMAL:Lorg/thymeleaf/engine/HTMLElementType;
    1290: invokespecial #97                 // Method org/thymeleaf/engine/ElementDefinitions$HTMLElementDefinitionSpec."<init>":(Lorg/thymeleaf/engine/HTMLElementName;Lorg/thymeleaf/engine/HTMLElementType;)V
    1293: putstatic     #243                // Field IFRAME:Lorg/thymeleaf/engine/ElementDefinitions$HTMLElementDefinitionSpec;
    1296: new           #12                 // class org/thymeleaf/engine/ElementDefinitions$HTMLElementDefinitionSpec
    1299: dup
    1300: ldc           #244                // String embed
    1302: invokestatic  #95                 // Method org/thymeleaf/engine/ElementNames.forHTMLName:(Ljava/lang/String;)Lorg/thymeleaf/engine/HTMLElementName;
    1305: getstatic     #105                // Field org/thymeleaf/engine/HTMLElementType.VOID:Lorg/thymeleaf/engine/HTMLElementType;
    1308: invokespecial #97                 // Method org/thymeleaf/engine/ElementDefinitions$HTMLElementDefinitionSpec."<init>":(Lorg/thymeleaf/engine/HTMLElementName;Lorg/thymeleaf/engine/HTMLElementType;)V
    1311: putstatic     #245                // Field EMBED:Lorg/thymeleaf/engine/ElementDefinitions$HTMLElementDefinitionSpec;
    1314: new           #12                 // class org/thymeleaf/engine/ElementDefinitions$HTMLElementDefinitionSpec
    1317: dup
    1318: ldc           #246                // String object
    1320: invokestatic  #95                 // Method org/thymeleaf/engine/ElementNames.forHTMLName:(Ljava/lang/String;)Lorg/thymeleaf/engine/HTMLElementName;
    1323: getstatic     #96                 // Field org/thymeleaf/engine/HTMLElementType.NORMAL:Lorg/thymeleaf/engine/HTMLElementType;
    1326: invokespecial #97                 // Method org/thymeleaf/engine/ElementDefinitions$HTMLElementDefinitionSpec."<init>":(Lorg/thymeleaf/engine/HTMLElementName;Lorg/thymeleaf/engine/HTMLElementType;)V
    1329: putstatic     #247                // Field OBJECT:Lorg/thymeleaf/engine/ElementDefinitions$HTMLElementDefinitionSpec;
    1332: new           #12                 // class org/thymeleaf/engine/ElementDefinitions$HTMLElementDefinitionSpec
    1335: dup
    1336: ldc           #248                // String param
    1338: invokestatic  #95                 // Method org/thymeleaf/engine/ElementNames.forHTMLName:(Ljava/lang/String;)Lorg/thymeleaf/engine/HTMLElementName;
    1341: getstatic     #105                // Field org/thymeleaf/engine/HTMLElementType.VOID:Lorg/thymeleaf/engine/HTMLElementType;
    1344: invokespecial #97                 // Method org/thymeleaf/engine/ElementDefinitions$HTMLElementDefinitionSpec."<init>":(Lorg/thymeleaf/engine/HTMLElementName;Lorg/thymeleaf/engine/HTMLElementType;)V
    1347: putstatic     #249                // Field PARAM:Lorg/thymeleaf/engine/ElementDefinitions$HTMLElementDefinitionSpec;
    1350: new           #12                 // class org/thymeleaf/engine/ElementDefinitions$HTMLElementDefinitionSpec
    1353: dup
    1354: ldc           #250                // String video
    1356: invokestatic  #95                 // Method org/thymeleaf/engine/ElementNames.forHTMLName:(Ljava/lang/String;)Lorg/thymeleaf/engine/HTMLElementName;
    1359: getstatic     #96                 // Field org/thymeleaf/engine/HTMLElementType.NORMAL:Lorg/thymeleaf/engine/HTMLElementType;
    1362: invokespecial #97                 // Method org/thymeleaf/engine/ElementDefinitions$HTMLElementDefinitionSpec."<init>":(Lorg/thymeleaf/engine/HTMLElementName;Lorg/thymeleaf/engine/HTMLElementType;)V
    1365: putstatic     #251                // Field VIDEO:Lorg/thymeleaf/engine/ElementDefinitions$HTMLElementDefinitionSpec;
    1368: new           #12                 // class org/thymeleaf/engine/ElementDefinitions$HTMLElementDefinitionSpec
    1371: dup
    1372: ldc           #252                // String audio
    1374: invokestatic  #95                 // Method org/thymeleaf/engine/ElementNames.forHTMLName:(Ljava/lang/String;)Lorg/thymeleaf/engine/HTMLElementName;
    1377: getstatic     #96                 // Field org/thymeleaf/engine/HTMLElementType.NORMAL:Lorg/thymeleaf/engine/HTMLElementType;
    1380: invokespecial #97                 // Method org/thymeleaf/engine/ElementDefinitions$HTMLElementDefinitionSpec."<init>":(Lorg/thymeleaf/engine/HTMLElementName;Lorg/thymeleaf/engine/HTMLElementType;)V
    1383: putstatic     #253                // Field AUDIO:Lorg/thymeleaf/engine/ElementDefinitions$HTMLElementDefinitionSpec;
    1386: new           #12                 // class org/thymeleaf/engine/ElementDefinitions$HTMLElementDefinitionSpec
    1389: dup
    1390: ldc           #254                // String source
    1392: invokestatic  #95                 // Method org/thymeleaf/engine/ElementNames.forHTMLName:(Ljava/lang/String;)Lorg/thymeleaf/engine/HTMLElementName;
    1395: getstatic     #105                // Field org/thymeleaf/engine/HTMLElementType.VOID:Lorg/thymeleaf/engine/HTMLElementType;
    1398: invokespecial #97                 // Method org/thymeleaf/engine/ElementDefinitions$HTMLElementDefinitionSpec."<init>":(Lorg/thymeleaf/engine/HTMLElementName;Lorg/thymeleaf/engine/HTMLElementType;)V
    1401: putstatic     #255                // Field SOURCE:Lorg/thymeleaf/engine/ElementDefinitions$HTMLElementDefinitionSpec;
    1404: new           #12                 // class org/thymeleaf/engine/ElementDefinitions$HTMLElementDefinitionSpec
    1407: dup
    1408: ldc_w         #256                // String track
    1411: invokestatic  #95                 // Method org/thymeleaf/engine/ElementNames.forHTMLName:(Ljava/lang/String;)Lorg/thymeleaf/engine/HTMLElementName;
    1414: getstatic     #105                // Field org/thymeleaf/engine/HTMLElementType.VOID:Lorg/thymeleaf/engine/HTMLElementType;
    1417: invokespecial #97                 // Method org/thymeleaf/engine/ElementDefinitions$HTMLElementDefinitionSpec."<init>":(Lorg/thymeleaf/engine/HTMLElementName;Lorg/thymeleaf/engine/HTMLElementType;)V
    1420: putstatic     #257                // Field TRACK:Lorg/thymeleaf/engine/ElementDefinitions$HTMLElementDefinitionSpec;
    1423: new           #12                 // class org/thymeleaf/engine/ElementDefinitions$HTMLElementDefinitionSpec
    1426: dup
    1427: ldc_w         #258                // String canvas
    1430: invokestatic  #95                 // Method org/thymeleaf/engine/ElementNames.forHTMLName:(Ljava/lang/String;)Lorg/thymeleaf/engine/HTMLElementName;
    1433: getstatic     #96                 // Field org/thymeleaf/engine/HTMLElementType.NORMAL:Lorg/thymeleaf/engine/HTMLElementType;
    1436: invokespecial #97                 // Method org/thymeleaf/engine/ElementDefinitions$HTMLElementDefinitionSpec."<init>":(Lorg/thymeleaf/engine/HTMLElementName;Lorg/thymeleaf/engine/HTMLElementType;)V
    1439: putstatic     #259                // Field CANVAS:Lorg/thymeleaf/engine/ElementDefinitions$HTMLElementDefinitionSpec;
    1442: new           #12                 // class org/thymeleaf/engine/ElementDefinitions$HTMLElementDefinitionSpec
    1445: dup
    1446: ldc_w         #260                // String map
    1449: invokestatic  #95                 // Method org/thymeleaf/engine/ElementNames.forHTMLName:(Ljava/lang/String;)Lorg/thymeleaf/engine/HTMLElementName;
    1452: getstatic     #96                 // Field org/thymeleaf/engine/HTMLElementType.NORMAL:Lorg/thymeleaf/engine/HTMLElementType;
    1455: invokespecial #97                 // Method org/thymeleaf/engine/ElementDefinitions$HTMLElementDefinitionSpec."<init>":(Lorg/thymeleaf/engine/HTMLElementName;Lorg/thymeleaf/engine/HTMLElementType;)V
    1458: putstatic     #261                // Field MAP:Lorg/thymeleaf/engine/ElementDefinitions$HTMLElementDefinitionSpec;
    1461: new           #12                 // class org/thymeleaf/engine/ElementDefinitions$HTMLElementDefinitionSpec
    1464: dup
    1465: ldc_w         #262                // String area
    1468: invokestatic  #95                 // Method org/thymeleaf/engine/ElementNames.forHTMLName:(Ljava/lang/String;)Lorg/thymeleaf/engine/HTMLElementName;
    1471: getstatic     #105                // Field org/thymeleaf/engine/HTMLElementType.VOID:Lorg/thymeleaf/engine/HTMLElementType;
    1474: invokespecial #97                 // Method org/thymeleaf/engine/ElementDefinitions$HTMLElementDefinitionSpec."<init>":(Lorg/thymeleaf/engine/HTMLElementName;Lorg/thymeleaf/engine/HTMLElementType;)V
    1477: putstatic     #263                // Field AREA:Lorg/thymeleaf/engine/ElementDefinitions$HTMLElementDefinitionSpec;
    1480: new           #12                 // class org/thymeleaf/engine/ElementDefinitions$HTMLElementDefinitionSpec
    1483: dup
    1484: ldc_w         #264                // String table
    1487: invokestatic  #95                 // Method org/thymeleaf/engine/ElementNames.forHTMLName:(Ljava/lang/String;)Lorg/thymeleaf/engine/HTMLElementName;
    1490: getstatic     #96                 // Field org/thymeleaf/engine/HTMLElementType.NORMAL:Lorg/thymeleaf/engine/HTMLElementType;
    1493: invokespecial #97                 // Method org/thymeleaf/engine/ElementDefinitions$HTMLElementDefinitionSpec."<init>":(Lorg/thymeleaf/engine/HTMLElementName;Lorg/thymeleaf/engine/HTMLElementType;)V
    1496: putstatic     #265                // Field TABLE:Lorg/thymeleaf/engine/ElementDefinitions$HTMLElementDefinitionSpec;
    1499: new           #12                 // class org/thymeleaf/engine/ElementDefinitions$HTMLElementDefinitionSpec
    1502: dup
    1503: ldc_w         #266                // String caption
    1506: invokestatic  #95                 // Method org/thymeleaf/engine/ElementNames.forHTMLName:(Ljava/lang/String;)Lorg/thymeleaf/engine/HTMLElementName;
    1509: getstatic     #96                 // Field org/thymeleaf/engine/HTMLElementType.NORMAL:Lorg/thymeleaf/engine/HTMLElementType;
    1512: invokespecial #97                 // Method org/thymeleaf/engine/ElementDefinitions$HTMLElementDefinitionSpec."<init>":(Lorg/thymeleaf/engine/HTMLElementName;Lorg/thymeleaf/engine/HTMLElementType;)V
    1515: putstatic     #267                // Field CAPTION:Lorg/thymeleaf/engine/ElementDefinitions$HTMLElementDefinitionSpec;
    1518: new           #12                 // class org/thymeleaf/engine/ElementDefinitions$HTMLElementDefinitionSpec
    1521: dup
    1522: ldc_w         #268                // String colgroup
    1525: invokestatic  #95                 // Method org/thymeleaf/engine/ElementNames.forHTMLName:(Ljava/lang/String;)Lorg/thymeleaf/engine/HTMLElementName;
    1528: getstatic     #96                 // Field org/thymeleaf/engine/HTMLElementType.NORMAL:Lorg/thymeleaf/engine/HTMLElementType;
    1531: invokespecial #97                 // Method org/thymeleaf/engine/ElementDefinitions$HTMLElementDefinitionSpec."<init>":(Lorg/thymeleaf/engine/HTMLElementName;Lorg/thymeleaf/engine/HTMLElementType;)V
    1534: putstatic     #269                // Field COLGROUP:Lorg/thymeleaf/engine/ElementDefinitions$HTMLElementDefinitionSpec;
    1537: new           #12                 // class org/thymeleaf/engine/ElementDefinitions$HTMLElementDefinitionSpec
    1540: dup
    1541: ldc_w         #270                // String col
    1544: invokestatic  #95                 // Method org/thymeleaf/engine/ElementNames.forHTMLName:(Ljava/lang/String;)Lorg/thymeleaf/engine/HTMLElementName;
    1547: getstatic     #105                // Field org/thymeleaf/engine/HTMLElementType.VOID:Lorg/thymeleaf/engine/HTMLElementType;
    1550: invokespecial #97                 // Method org/thymeleaf/engine/ElementDefinitions$HTMLElementDefinitionSpec."<init>":(Lorg/thymeleaf/engine/HTMLElementName;Lorg/thymeleaf/engine/HTMLElementType;)V
    1553: putstatic     #271                // Field COL:Lorg/thymeleaf/engine/ElementDefinitions$HTMLElementDefinitionSpec;
    1556: new           #12                 // class org/thymeleaf/engine/ElementDefinitions$HTMLElementDefinitionSpec
    1559: dup
    1560: ldc_w         #272                // String tbody
    1563: invokestatic  #95                 // Method org/thymeleaf/engine/ElementNames.forHTMLName:(Ljava/lang/String;)Lorg/thymeleaf/engine/HTMLElementName;
    1566: getstatic     #96                 // Field org/thymeleaf/engine/HTMLElementType.NORMAL:Lorg/thymeleaf/engine/HTMLElementType;
    1569: invokespecial #97                 // Method org/thymeleaf/engine/ElementDefinitions$HTMLElementDefinitionSpec."<init>":(Lorg/thymeleaf/engine/HTMLElementName;Lorg/thymeleaf/engine/HTMLElementType;)V
    1572: putstatic     #273                // Field TBODY:Lorg/thymeleaf/engine/ElementDefinitions$HTMLElementDefinitionSpec;
    1575: new           #12                 // class org/thymeleaf/engine/ElementDefinitions$HTMLElementDefinitionSpec
    1578: dup
    1579: ldc_w         #274                // String thead
    1582: invokestatic  #95                 // Method org/thymeleaf/engine/ElementNames.forHTMLName:(Ljava/lang/String;)Lorg/thymeleaf/engine/HTMLElementName;
    1585: getstatic     #96                 // Field org/thymeleaf/engine/HTMLElementType.NORMAL:Lorg/thymeleaf/engine/HTMLElementType;
    1588: invokespecial #97                 // Method org/thymeleaf/engine/ElementDefinitions$HTMLElementDefinitionSpec."<init>":(Lorg/thymeleaf/engine/HTMLElementName;Lorg/thymeleaf/engine/HTMLElementType;)V
    1591: putstatic     #275                // Field THEAD:Lorg/thymeleaf/engine/ElementDefinitions$HTMLElementDefinitionSpec;
    1594: new           #12                 // class org/thymeleaf/engine/ElementDefinitions$HTMLElementDefinitionSpec
    1597: dup
    1598: ldc_w         #276                // String tfoot
    1601: invokestatic  #95                 // Method org/thymeleaf/engine/ElementNames.forHTMLName:(Ljava/lang/String;)Lorg/thymeleaf/engine/HTMLElementName;
    1604: getstatic     #96                 // Field org/thymeleaf/engine/HTMLElementType.NORMAL:Lorg/thymeleaf/engine/HTMLElementType;
    1607: invokespecial #97                 // Method org/thymeleaf/engine/ElementDefinitions$HTMLElementDefinitionSpec."<init>":(Lorg/thymeleaf/engine/HTMLElementName;Lorg/thymeleaf/engine/HTMLElementType;)V
    1610: putstatic     #277                // Field TFOOT:Lorg/thymeleaf/engine/ElementDefinitions$HTMLElementDefinitionSpec;
    1613: new           #12                 // class org/thymeleaf/engine/ElementDefinitions$HTMLElementDefinitionSpec
    1616: dup
    1617: ldc_w         #278                // String tr
    1620: invokestatic  #95                 // Method org/thymeleaf/engine/ElementNames.forHTMLName:(Ljava/lang/String;)Lorg/thymeleaf/engine/HTMLElementName;
    1623: getstatic     #96                 // Field org/thymeleaf/engine/HTMLElementType.NORMAL:Lorg/thymeleaf/engine/HTMLElementType;
    1626: invokespecial #97                 // Method org/thymeleaf/engine/ElementDefinitions$HTMLElementDefinitionSpec."<init>":(Lorg/thymeleaf/engine/HTMLElementName;Lorg/thymeleaf/engine/HTMLElementType;)V
    1629: putstatic     #279                // Field TR:Lorg/thymeleaf/engine/ElementDefinitions$HTMLElementDefinitionSpec;
    1632: new           #12                 // class org/thymeleaf/engine/ElementDefinitions$HTMLElementDefinitionSpec
    1635: dup
    1636: ldc_w         #280                // String td
    1639: invokestatic  #95                 // Method org/thymeleaf/engine/ElementNames.forHTMLName:(Ljava/lang/String;)Lorg/thymeleaf/engine/HTMLElementName;
    1642: getstatic     #96                 // Field org/thymeleaf/engine/HTMLElementType.NORMAL:Lorg/thymeleaf/engine/HTMLElementType;
    1645: invokespecial #97                 // Method org/thymeleaf/engine/ElementDefinitions$HTMLElementDefinitionSpec."<init>":(Lorg/thymeleaf/engine/HTMLElementName;Lorg/thymeleaf/engine/HTMLElementType;)V
    1648: putstatic     #281                // Field TD:Lorg/thymeleaf/engine/ElementDefinitions$HTMLElementDefinitionSpec;
    1651: new           #12                 // class org/thymeleaf/engine/ElementDefinitions$HTMLElementDefinitionSpec
    1654: dup
    1655: ldc_w         #282                // String th
    1658: invokestatic  #95                 // Method org/thymeleaf/engine/ElementNames.forHTMLName:(Ljava/lang/String;)Lorg/thymeleaf/engine/HTMLElementName;
    1661: getstatic     #96                 // Field org/thymeleaf/engine/HTMLElementType.NORMAL:Lorg/thymeleaf/engine/HTMLElementType;
    1664: invokespecial #97                 // Method org/thymeleaf/engine/ElementDefinitions$HTMLElementDefinitionSpec."<init>":(Lorg/thymeleaf/engine/HTMLElementName;Lorg/thymeleaf/engine/HTMLElementType;)V
    1667: putstatic     #283                // Field TH:Lorg/thymeleaf/engine/ElementDefinitions$HTMLElementDefinitionSpec;
    1670: new           #12                 // class org/thymeleaf/engine/ElementDefinitions$HTMLElementDefinitionSpec
    1673: dup
    1674: ldc_w         #284                // String form
    1677: invokestatic  #95                 // Method org/thymeleaf/engine/ElementNames.forHTMLName:(Ljava/lang/String;)Lorg/thymeleaf/engine/HTMLElementName;
    1680: getstatic     #96                 // Field org/thymeleaf/engine/HTMLElementType.NORMAL:Lorg/thymeleaf/engine/HTMLElementType;
    1683: invokespecial #97                 // Method org/thymeleaf/engine/ElementDefinitions$HTMLElementDefinitionSpec."<init>":(Lorg/thymeleaf/engine/HTMLElementName;Lorg/thymeleaf/engine/HTMLElementType;)V
    1686: putstatic     #285                // Field FORM:Lorg/thymeleaf/engine/ElementDefinitions$HTMLElementDefinitionSpec;
    1689: new           #12                 // class org/thymeleaf/engine/ElementDefinitions$HTMLElementDefinitionSpec
    1692: dup
    1693: ldc_w         #286                // String fieldset
    1696: invokestatic  #95                 // Method org/thymeleaf/engine/ElementNames.forHTMLName:(Ljava/lang/String;)Lorg/thymeleaf/engine/HTMLElementName;
    1699: getstatic     #96                 // Field org/thymeleaf/engine/HTMLElementType.NORMAL:Lorg/thymeleaf/engine/HTMLElementType;
    1702: invokespecial #97                 // Method org/thymeleaf/engine/ElementDefinitions$HTMLElementDefinitionSpec."<init>":(Lorg/thymeleaf/engine/HTMLElementName;Lorg/thymeleaf/engine/HTMLElementType;)V
    1705: putstatic     #287                // Field FIELDSET:Lorg/thymeleaf/engine/ElementDefinitions$HTMLElementDefinitionSpec;
    1708: new           #12                 // class org/thymeleaf/engine/ElementDefinitions$HTMLElementDefinitionSpec
    1711: dup
    1712: ldc_w         #288                // String legend
    1715: invokestatic  #95                 // Method org/thymeleaf/engine/ElementNames.forHTMLName:(Ljava/lang/String;)Lorg/thymeleaf/engine/HTMLElementName;
    1718: getstatic     #96                 // Field org/thymeleaf/engine/HTMLElementType.NORMAL:Lorg/thymeleaf/engine/HTMLElementType;
    1721: invokespecial #97                 // Method org/thymeleaf/engine/ElementDefinitions$HTMLElementDefinitionSpec."<init>":(Lorg/thymeleaf/engine/HTMLElementName;Lorg/thymeleaf/engine/HTMLElementType;)V
    1724: putstatic     #289                // Field LEGEND:Lorg/thymeleaf/engine/ElementDefinitions$HTMLElementDefinitionSpec;
    1727: new           #12                 // class org/thymeleaf/engine/ElementDefinitions$HTMLElementDefinitionSpec
    1730: dup
    1731: ldc_w         #290                // String label
    1734: invokestatic  #95                 // Method org/thymeleaf/engine/ElementNames.forHTMLName:(Ljava/lang/String;)Lorg/thymeleaf/engine/HTMLElementName;
    1737: getstatic     #96                 // Field org/thymeleaf/engine/HTMLElementType.NORMAL:Lorg/thymeleaf/engine/HTMLElementType;
    1740: invokespecial #97                 // Method org/thymeleaf/engine/ElementDefinitions$HTMLElementDefinitionSpec."<init>":(Lorg/thymeleaf/engine/HTMLElementName;Lorg/thymeleaf/engine/HTMLElementType;)V
    1743: putstatic     #291                // Field LABEL:Lorg/thymeleaf/engine/ElementDefinitions$HTMLElementDefinitionSpec;
    1746: new           #12                 // class org/thymeleaf/engine/ElementDefinitions$HTMLElementDefinitionSpec
    1749: dup
    1750: ldc_w         #292                // String input
    1753: invokestatic  #95                 // Method org/thymeleaf/engine/ElementNames.forHTMLName:(Ljava/lang/String;)Lorg/thymeleaf/engine/HTMLElementName;
    1756: getstatic     #105                // Field org/thymeleaf/engine/HTMLElementType.VOID:Lorg/thymeleaf/engine/HTMLElementType;
    1759: invokespecial #97                 // Method org/thymeleaf/engine/ElementDefinitions$HTMLElementDefinitionSpec."<init>":(Lorg/thymeleaf/engine/HTMLElementName;Lorg/thymeleaf/engine/HTMLElementType;)V
    1762: putstatic     #293                // Field INPUT:Lorg/thymeleaf/engine/ElementDefinitions$HTMLElementDefinitionSpec;
    1765: new           #12                 // class org/thymeleaf/engine/ElementDefinitions$HTMLElementDefinitionSpec
    1768: dup
    1769: ldc_w         #294                // String button
    1772: invokestatic  #95                 // Method org/thymeleaf/engine/ElementNames.forHTMLName:(Ljava/lang/String;)Lorg/thymeleaf/engine/HTMLElementName;
    1775: getstatic     #96                 // Field org/thymeleaf/engine/HTMLElementType.NORMAL:Lorg/thymeleaf/engine/HTMLElementType;
    1778: invokespecial #97                 // Method org/thymeleaf/engine/ElementDefinitions$HTMLElementDefinitionSpec."<init>":(Lorg/thymeleaf/engine/HTMLElementName;Lorg/thymeleaf/engine/HTMLElementType;)V
    1781: putstatic     #295                // Field BUTTON:Lorg/thymeleaf/engine/ElementDefinitions$HTMLElementDefinitionSpec;
    1784: new           #12                 // class org/thymeleaf/engine/ElementDefinitions$HTMLElementDefinitionSpec
    1787: dup
    1788: ldc_w         #296                // String select
    1791: invokestatic  #95                 // Method org/thymeleaf/engine/ElementNames.forHTMLName:(Ljava/lang/String;)Lorg/thymeleaf/engine/HTMLElementName;
    1794: getstatic     #96                 // Field org/thymeleaf/engine/HTMLElementType.NORMAL:Lorg/thymeleaf/engine/HTMLElementType;
    1797: invokespecial #97                 // Method org/thymeleaf/engine/ElementDefinitions$HTMLElementDefinitionSpec."<init>":(Lorg/thymeleaf/engine/HTMLElementName;Lorg/thymeleaf/engine/HTMLElementType;)V
    1800: putstatic     #297                // Field SELECT:Lorg/thymeleaf/engine/ElementDefinitions$HTMLElementDefinitionSpec;
    1803: new           #12                 // class org/thymeleaf/engine/ElementDefinitions$HTMLElementDefinitionSpec
    1806: dup
    1807: ldc_w         #298                // String datalist
    1810: invokestatic  #95                 // Method org/thymeleaf/engine/ElementNames.forHTMLName:(Ljava/lang/String;)Lorg/thymeleaf/engine/HTMLElementName;
    1813: getstatic     #96                 // Field org/thymeleaf/engine/HTMLElementType.NORMAL:Lorg/thymeleaf/engine/HTMLElementType;
    1816: invokespecial #97                 // Method org/thymeleaf/engine/ElementDefinitions$HTMLElementDefinitionSpec."<init>":(Lorg/thymeleaf/engine/HTMLElementName;Lorg/thymeleaf/engine/HTMLElementType;)V
    1819: putstatic     #299                // Field DATALIST:Lorg/thymeleaf/engine/ElementDefinitions$HTMLElementDefinitionSpec;
    1822: new           #12                 // class org/thymeleaf/engine/ElementDefinitions$HTMLElementDefinitionSpec
    1825: dup
    1826: ldc_w         #300                // String optgroup
    1829: invokestatic  #95                 // Method org/thymeleaf/engine/ElementNames.forHTMLName:(Ljava/lang/String;)Lorg/thymeleaf/engine/HTMLElementName;
    1832: getstatic     #96                 // Field org/thymeleaf/engine/HTMLElementType.NORMAL:Lorg/thymeleaf/engine/HTMLElementType;
    1835: invokespecial #97                 // Method org/thymeleaf/engine/ElementDefinitions$HTMLElementDefinitionSpec."<init>":(Lorg/thymeleaf/engine/HTMLElementName;Lorg/thymeleaf/engine/HTMLElementType;)V
    1838: putstatic     #301                // Field OPTGROUP:Lorg/thymeleaf/engine/ElementDefinitions$HTMLElementDefinitionSpec;
    1841: new           #12                 // class org/thymeleaf/engine/ElementDefinitions$HTMLElementDefinitionSpec
    1844: dup
    1845: ldc_w         #302                // String option
    1848: invokestatic  #95                 // Method org/thymeleaf/engine/ElementNames.forHTMLName:(Ljava/lang/String;)Lorg/thymeleaf/engine/HTMLElementName;
    1851: getstatic     #96                 // Field org/thymeleaf/engine/HTMLElementType.NORMAL:Lorg/thymeleaf/engine/HTMLElementType;
    1854: invokespecial #97                 // Method org/thymeleaf/engine/ElementDefinitions$HTMLElementDefinitionSpec."<init>":(Lorg/thymeleaf/engine/HTMLElementName;Lorg/thymeleaf/engine/HTMLElementType;)V
    1857: putstatic     #303                // Field OPTION:Lorg/thymeleaf/engine/ElementDefinitions$HTMLElementDefinitionSpec;
    1860: new           #12                 // class org/thymeleaf/engine/ElementDefinitions$HTMLElementDefinitionSpec
    1863: dup
    1864: ldc_w         #304                // String textarea
    1867: invokestatic  #95                 // Method org/thymeleaf/engine/ElementNames.forHTMLName:(Ljava/lang/String;)Lorg/thymeleaf/engine/HTMLElementName;
    1870: getstatic     #102                // Field org/thymeleaf/engine/HTMLElementType.ESCAPABLE_RAW_TEXT:Lorg/thymeleaf/engine/HTMLElementType;
    1873: invokespecial #97                 // Method org/thymeleaf/engine/ElementDefinitions$HTMLElementDefinitionSpec."<init>":(Lorg/thymeleaf/engine/HTMLElementName;Lorg/thymeleaf/engine/HTMLElementType;)V
    1876: putstatic     #305                // Field TEXTAREA:Lorg/thymeleaf/engine/ElementDefinitions$HTMLElementDefinitionSpec;
    1879: new           #12                 // class org/thymeleaf/engine/ElementDefinitions$HTMLElementDefinitionSpec
    1882: dup
    1883: ldc_w         #306                // String keygen
    1886: invokestatic  #95                 // Method org/thymeleaf/engine/ElementNames.forHTMLName:(Ljava/lang/String;)Lorg/thymeleaf/engine/HTMLElementName;
    1889: getstatic     #105                // Field org/thymeleaf/engine/HTMLElementType.VOID:Lorg/thymeleaf/engine/HTMLElementType;
    1892: invokespecial #97                 // Method org/thymeleaf/engine/ElementDefinitions$HTMLElementDefinitionSpec."<init>":(Lorg/thymeleaf/engine/HTMLElementName;Lorg/thymeleaf/engine/HTMLElementType;)V
    1895: putstatic     #307                // Field KEYGEN:Lorg/thymeleaf/engine/ElementDefinitions$HTMLElementDefinitionSpec;
    1898: new           #12                 // class org/thymeleaf/engine/ElementDefinitions$HTMLElementDefinitionSpec
    1901: dup
    1902: ldc_w         #308                // String output
    1905: invokestatic  #95                 // Method org/thymeleaf/engine/ElementNames.forHTMLName:(Ljava/lang/String;)Lorg/thymeleaf/engine/HTMLElementName;
    1908: getstatic     #96                 // Field org/thymeleaf/engine/HTMLElementType.NORMAL:Lorg/thymeleaf/engine/HTMLElementType;
    1911: invokespecial #97                 // Method org/thymeleaf/engine/ElementDefinitions$HTMLElementDefinitionSpec."<init>":(Lorg/thymeleaf/engine/HTMLElementName;Lorg/thymeleaf/engine/HTMLElementType;)V
    1914: putstatic     #309                // Field OUTPUT:Lorg/thymeleaf/engine/ElementDefinitions$HTMLElementDefinitionSpec;
    1917: new           #12                 // class org/thymeleaf/engine/ElementDefinitions$HTMLElementDefinitionSpec
    1920: dup
    1921: ldc_w         #310                // String progress
    1924: invokestatic  #95                 // Method org/thymeleaf/engine/ElementNames.forHTMLName:(Ljava/lang/String;)Lorg/thymeleaf/engine/HTMLElementName;
    1927: getstatic     #96                 // Field org/thymeleaf/engine/HTMLElementType.NORMAL:Lorg/thymeleaf/engine/HTMLElementType;
    1930: invokespecial #97                 // Method org/thymeleaf/engine/ElementDefinitions$HTMLElementDefinitionSpec."<init>":(Lorg/thymeleaf/engine/HTMLElementName;Lorg/thymeleaf/engine/HTMLElementType;)V
    1933: putstatic     #311                // Field PROGRESS:Lorg/thymeleaf/engine/ElementDefinitions$HTMLElementDefinitionSpec;
    1936: new           #12                 // class org/thymeleaf/engine/ElementDefinitions$HTMLElementDefinitionSpec
    1939: dup
    1940: ldc_w         #312                // String meter
    1943: invokestatic  #95                 // Method org/thymeleaf/engine/ElementNames.forHTMLName:(Ljava/lang/String;)Lorg/thymeleaf/engine/HTMLElementName;
    1946: getstatic     #96                 // Field org/thymeleaf/engine/HTMLElementType.NORMAL:Lorg/thymeleaf/engine/HTMLElementType;
    1949: invokespecial #97                 // Method org/thymeleaf/engine/ElementDefinitions$HTMLElementDefinitionSpec."<init>":(Lorg/thymeleaf/engine/HTMLElementName;Lorg/thymeleaf/engine/HTMLElementType;)V
    1952: putstatic     #313                // Field METER:Lorg/thymeleaf/engine/ElementDefinitions$HTMLElementDefinitionSpec;
    1955: new           #12                 // class org/thymeleaf/engine/ElementDefinitions$HTMLElementDefinitionSpec
    1958: dup
    1959: ldc_w         #314                // String details
    1962: invokestatic  #95                 // Method org/thymeleaf/engine/ElementNames.forHTMLName:(Ljava/lang/String;)Lorg/thymeleaf/engine/HTMLElementName;
    1965: getstatic     #96                 // Field org/thymeleaf/engine/HTMLElementType.NORMAL:Lorg/thymeleaf/engine/HTMLElementType;
    1968: invokespecial #97                 // Method org/thymeleaf/engine/ElementDefinitions$HTMLElementDefinitionSpec."<init>":(Lorg/thymeleaf/engine/HTMLElementName;Lorg/thymeleaf/engine/HTMLElementType;)V
    1971: putstatic     #315                // Field DETAILS:Lorg/thymeleaf/engine/ElementDefinitions$HTMLElementDefinitionSpec;
    1974: new           #12                 // class org/thymeleaf/engine/ElementDefinitions$HTMLElementDefinitionSpec
    1977: dup
    1978: ldc_w         #316                // String summary
    1981: invokestatic  #95                 // Method org/thymeleaf/engine/ElementNames.forHTMLName:(Ljava/lang/String;)Lorg/thymeleaf/engine/HTMLElementName;
    1984: getstatic     #96                 // Field org/thymeleaf/engine/HTMLElementType.NORMAL:Lorg/thymeleaf/engine/HTMLElementType;
    1987: invokespecial #97                 // Method org/thymeleaf/engine/ElementDefinitions$HTMLElementDefinitionSpec."<init>":(Lorg/thymeleaf/engine/HTMLElementName;Lorg/thymeleaf/engine/HTMLElementType;)V
    1990: putstatic     #317                // Field SUMMARY:Lorg/thymeleaf/engine/ElementDefinitions$HTMLElementDefinitionSpec;
    1993: new           #12                 // class org/thymeleaf/engine/ElementDefinitions$HTMLElementDefinitionSpec
    1996: dup
    1997: ldc_w         #318                // String command
    2000: invokestatic  #95                 // Method org/thymeleaf/engine/ElementNames.forHTMLName:(Ljava/lang/String;)Lorg/thymeleaf/engine/HTMLElementName;
    2003: getstatic     #96                 // Field org/thymeleaf/engine/HTMLElementType.NORMAL:Lorg/thymeleaf/engine/HTMLElementType;
    2006: invokespecial #97                 // Method org/thymeleaf/engine/ElementDefinitions$HTMLElementDefinitionSpec."<init>":(Lorg/thymeleaf/engine/HTMLElementName;Lorg/thymeleaf/engine/HTMLElementType;)V
    2009: putstatic     #319                // Field COMMAND:Lorg/thymeleaf/engine/ElementDefinitions$HTMLElementDefinitionSpec;
    2012: new           #12                 // class org/thymeleaf/engine/ElementDefinitions$HTMLElementDefinitionSpec
    2015: dup
    2016: ldc_w         #320                // String menu
    2019: invokestatic  #95                 // Method org/thymeleaf/engine/ElementNames.forHTMLName:(Ljava/lang/String;)Lorg/thymeleaf/engine/HTMLElementName;
    2022: getstatic     #96                 // Field org/thymeleaf/engine/HTMLElementType.NORMAL:Lorg/thymeleaf/engine/HTMLElementType;
    2025: invokespecial #97                 // Method org/thymeleaf/engine/ElementDefinitions$HTMLElementDefinitionSpec."<init>":(Lorg/thymeleaf/engine/HTMLElementName;Lorg/thymeleaf/engine/HTMLElementType;)V
    2028: putstatic     #321                // Field MENU:Lorg/thymeleaf/engine/ElementDefinitions$HTMLElementDefinitionSpec;
    2031: new           #12                 // class org/thymeleaf/engine/ElementDefinitions$HTMLElementDefinitionSpec
    2034: dup
    2035: ldc_w         #322                // String menuitem
    2038: invokestatic  #95                 // Method org/thymeleaf/engine/ElementNames.forHTMLName:(Ljava/lang/String;)Lorg/thymeleaf/engine/HTMLElementName;
    2041: getstatic     #105                // Field org/thymeleaf/engine/HTMLElementType.VOID:Lorg/thymeleaf/engine/HTMLElementType;
    2044: invokespecial #97                 // Method org/thymeleaf/engine/ElementDefinitions$HTMLElementDefinitionSpec."<init>":(Lorg/thymeleaf/engine/HTMLElementName;Lorg/thymeleaf/engine/HTMLElementType;)V
    2047: putstatic     #323                // Field MENUITEM:Lorg/thymeleaf/engine/ElementDefinitions$HTMLElementDefinitionSpec;
    2050: new           #12                 // class org/thymeleaf/engine/ElementDefinitions$HTMLElementDefinitionSpec
    2053: dup
    2054: ldc_w         #324                // String dialog
    2057: invokestatic  #95                 // Method org/thymeleaf/engine/ElementNames.forHTMLName:(Ljava/lang/String;)Lorg/thymeleaf/engine/HTMLElementName;
    2060: getstatic     #96                 // Field org/thymeleaf/engine/HTMLElementType.NORMAL:Lorg/thymeleaf/engine/HTMLElementType;
    2063: invokespecial #97                 // Method org/thymeleaf/engine/ElementDefinitions$HTMLElementDefinitionSpec."<init>":(Lorg/thymeleaf/engine/HTMLElementName;Lorg/thymeleaf/engine/HTMLElementType;)V
    2066: putstatic     #325                // Field DIALOG:Lorg/thymeleaf/engine/ElementDefinitions$HTMLElementDefinitionSpec;
    2069: new           #12                 // class org/thymeleaf/engine/ElementDefinitions$HTMLElementDefinitionSpec
    2072: dup
    2073: ldc_w         #326                // String template
    2076: invokestatic  #95                 // Method org/thymeleaf/engine/ElementNames.forHTMLName:(Ljava/lang/String;)Lorg/thymeleaf/engine/HTMLElementName;
    2079: getstatic     #112                // Field org/thymeleaf/engine/HTMLElementType.RAW_TEXT:Lorg/thymeleaf/engine/HTMLElementType;
    2082: invokespecial #97                 // Method org/thymeleaf/engine/ElementDefinitions$HTMLElementDefinitionSpec."<init>":(Lorg/thymeleaf/engine/HTMLElementName;Lorg/thymeleaf/engine/HTMLElementType;)V
    2085: putstatic     #327                // Field TEMPLATE:Lorg/thymeleaf/engine/ElementDefinitions$HTMLElementDefinitionSpec;
    2088: new           #12                 // class org/thymeleaf/engine/ElementDefinitions$HTMLElementDefinitionSpec
    2091: dup
    2092: ldc_w         #328                // String element
    2095: invokestatic  #95                 // Method org/thymeleaf/engine/ElementNames.forHTMLName:(Ljava/lang/String;)Lorg/thymeleaf/engine/HTMLElementName;
    2098: getstatic     #96                 // Field org/thymeleaf/engine/HTMLElementType.NORMAL:Lorg/thymeleaf/engine/HTMLElementType;
    2101: invokespecial #97                 // Method org/thymeleaf/engine/ElementDefinitions$HTMLElementDefinitionSpec."<init>":(Lorg/thymeleaf/engine/HTMLElementName;Lorg/thymeleaf/engine/HTMLElementType;)V
    2104: putstatic     #329                // Field ELEMENT:Lorg/thymeleaf/engine/ElementDefinitions$HTMLElementDefinitionSpec;
    2107: new           #12                 // class org/thymeleaf/engine/ElementDefinitions$HTMLElementDefinitionSpec
    2110: dup
    2111: ldc_w         #330                // String decorator
    2114: invokestatic  #95                 // Method org/thymeleaf/engine/ElementNames.forHTMLName:(Ljava/lang/String;)Lorg/thymeleaf/engine/HTMLElementName;
    2117: getstatic     #96                 // Field org/thymeleaf/engine/HTMLElementType.NORMAL:Lorg/thymeleaf/engine/HTMLElementType;
    2120: invokespecial #97                 // Method org/thymeleaf/engine/ElementDefinitions$HTMLElementDefinitionSpec."<init>":(Lorg/thymeleaf/engine/HTMLElementName;Lorg/thymeleaf/engine/HTMLElementType;)V
    2123: putstatic     #331                // Field DECORATOR:Lorg/thymeleaf/engine/ElementDefinitions$HTMLElementDefinitionSpec;
    2126: new           #12                 // class org/thymeleaf/engine/ElementDefinitions$HTMLElementDefinitionSpec
    2129: dup
    2130: ldc_w         #332                // String content
    2133: invokestatic  #95                 // Method org/thymeleaf/engine/ElementNames.forHTMLName:(Ljava/lang/String;)Lorg/thymeleaf/engine/HTMLElementName;
    2136: getstatic     #96                 // Field org/thymeleaf/engine/HTMLElementType.NORMAL:Lorg/thymeleaf/engine/HTMLElementType;
    2139: invokespecial #97                 // Method org/thymeleaf/engine/ElementDefinitions$HTMLElementDefinitionSpec."<init>":(Lorg/thymeleaf/engine/HTMLElementName;Lorg/thymeleaf/engine/HTMLElementType;)V
    2142: putstatic     #333                // Field CONTENT:Lorg/thymeleaf/engine/ElementDefinitions$HTMLElementDefinitionSpec;
    2145: new           #12                 // class org/thymeleaf/engine/ElementDefinitions$HTMLElementDefinitionSpec
    2148: dup
    2149: ldc_w         #334                // String shadow
    2152: invokestatic  #95                 // Method org/thymeleaf/engine/ElementNames.forHTMLName:(Ljava/lang/String;)Lorg/thymeleaf/engine/HTMLElementName;
    2155: getstatic     #96                 // Field org/thymeleaf/engine/HTMLElementType.NORMAL:Lorg/thymeleaf/engine/HTMLElementType;
    2158: invokespecial #97                 // Method org/thymeleaf/engine/ElementDefinitions$HTMLElementDefinitionSpec."<init>":(Lorg/thymeleaf/engine/HTMLElementName;Lorg/thymeleaf/engine/HTMLElementType;)V
    2161: putstatic     #335                // Field SHADOW:Lorg/thymeleaf/engine/ElementDefinitions$HTMLElementDefinitionSpec;
    2164: new           #5                  // class java/util/ArrayList
    2167: dup
    2168: getstatic     #6                  // Field org/thymeleaf/engine/ElementDefinitions$HTMLElementDefinitionSpec.ALL_SPECS:Ljava/util/List;
    2171: invokeinterface #7,  1            // InterfaceMethod java/util/List.size:()I
    2176: iconst_1
    2177: iadd
    2178: invokespecial #8                  // Method java/util/ArrayList."<init>":(I)V
    2181: astore_0
    2182: getstatic     #6                  // Field org/thymeleaf/engine/ElementDefinitions$HTMLElementDefinitionSpec.ALL_SPECS:Ljava/util/List;
    2185: invokeinterface #9,  1            // InterfaceMethod java/util/List.iterator:()Ljava/util/Iterator;
    2190: astore_1
    2191: aload_1
    2192: invokeinterface #10,  1           // InterfaceMethod java/util/Iterator.hasNext:()Z
    2197: ifeq          2256
    2200: aload_1
    2201: invokeinterface #11,  1           // InterfaceMethod java/util/Iterator.next:()Ljava/lang/Object;
    2206: checkcast     #12                 // class org/thymeleaf/engine/ElementDefinitions$HTMLElementDefinitionSpec
    2209: astore_2
    2210: aload_2
    2211: getfield      #13                 // Field org/thymeleaf/engine/ElementDefinitions$HTMLElementDefinitionSpec.name:Lorg/thymeleaf/engine/HTMLElementName;
    2214: getfield      #336                // Field org/thymeleaf/engine/HTMLElementName.completeElementNames:[Ljava/lang/String;
    2217: astore_3
    2218: aload_3
    2219: arraylength
    2220: istore        4
    2222: iconst_0
    2223: istore        5
    2225: iload         5
    2227: iload         4
    2229: if_icmpge     2253
    2232: aload_3
    2233: iload         5
    2235: aaload
    2236: astore        6
    2238: aload_0
    2239: aload         6
    2241: invokeinterface #18,  2           // InterfaceMethod java/util/List.add:(Ljava/lang/Object;)Z
    2246: pop
    2247: iinc          5, 1
    2250: goto          2225
    2253: goto          2191
    2256: aload_0
    2257: invokestatic  #337                // Method java/util/Collections.sort:(Ljava/util/List;)V
    2260: new           #32                 // class java/util/LinkedHashSet
    2263: dup
    2264: aload_0
    2265: invokespecial #338                // Method java/util/LinkedHashSet."<init>":(Ljava/util/Collection;)V
    2268: invokestatic  #339                // Method java/util/Collections.unmodifiableSet:(Ljava/util/Set;)Ljava/util/Set;
    2271: putstatic     #340                // Field ALL_STANDARD_HTML_ELEMENT_NAMES:Ljava/util/Set;
    2274: return
}
