Compiled from "ReflectiveMethodResolver.java"
public class org.springframework.expression.spel.support.ReflectiveMethodResolver implements org.springframework.expression.MethodResolver {
  private final boolean useDistance;

  private java.util.Map<java.lang.Class<?>, org.springframework.expression.MethodFilter> filters;

  public org.springframework.expression.spel.support.ReflectiveMethodResolver();
    Code:
       0: aload_0
       1: invokespecial #1                  // Method java/lang/Object."<init>":()V
       4: aload_0
       5: iconst_1
       6: putfield      #2                  // Field useDistance:Z
       9: return

  public org.springframework.expression.spel.support.ReflectiveMethodResolver(boolean);
    Code:
       0: aload_0
       1: invokespecial #1                  // Method java/lang/Object."<init>":()V
       4: aload_0
       5: iload_1
       6: putfield      #2                  // Field useDistance:Z
       9: return

  public void registerMethodFilter(java.lang.Class<?>, org.springframework.expression.MethodFilter);
    Code:
       0: aload_0
       1: getfield      #3                  // Field filters:Ljava/util/Map;
       4: ifnonnull     18
       7: aload_0
       8: new           #4                  // class java/util/HashMap
      11: dup
      12: invokespecial #5                  // Method java/util/HashMap."<init>":()V
      15: putfield      #3                  // Field filters:Ljava/util/Map;
      18: aload_2
      19: ifnull        37
      22: aload_0
      23: getfield      #3                  // Field filters:Ljava/util/Map;
      26: aload_1
      27: aload_2
      28: invokeinterface #6,  3            // InterfaceMethod java/util/Map.put:(Ljava/lang/Object;Ljava/lang/Object;)Ljava/lang/Object;
      33: pop
      34: goto          48
      37: aload_0
      38: getfield      #3                  // Field filters:Ljava/util/Map;
      41: aload_1
      42: invokeinterface #7,  2            // InterfaceMethod java/util/Map.remove:(Ljava/lang/Object;)Ljava/lang/Object;
      47: pop
      48: return

  public org.springframework.expression.MethodExecutor resolve(org.springframework.expression.EvaluationContext, java.lang.Object, java.lang.String, java.util.List<org.springframework.core.convert.TypeDescriptor>) throws org.springframework.expression.AccessException;
    Code:
       0: aload_1
       1: invokeinterface #8,  1            // InterfaceMethod org/springframework/expression/EvaluationContext.getTypeConverter:()Lorg/springframework/expression/TypeConverter;
       6: astore        5
       8: aload_2
       9: instanceof    #9                  // class java/lang/Class
      12: ifeq          22
      15: aload_2
      16: checkcast     #9                  // class java/lang/Class
      19: goto          26
      22: aload_2
      23: invokevirtual #10                 // Method java/lang/Object.getClass:()Ljava/lang/Class;
      26: astore        6
      28: new           #11                 // class java/util/ArrayList
      31: dup
      32: aload_0
      33: aload         6
      35: aload_2
      36: invokespecial #12                 // Method getMethods:(Ljava/lang/Class;Ljava/lang/Object;)Ljava/util/Collection;
      39: invokespecial #13                 // Method java/util/ArrayList."<init>":(Ljava/util/Collection;)V
      42: astore        7
      44: aload_0
      45: getfield      #3                  // Field filters:Ljava/util/Map;
      48: ifnull        68
      51: aload_0
      52: getfield      #3                  // Field filters:Ljava/util/Map;
      55: aload         6
      57: invokeinterface #14,  2           // InterfaceMethod java/util/Map.get:(Ljava/lang/Object;)Ljava/lang/Object;
      62: checkcast     #15                 // class org/springframework/expression/MethodFilter
      65: goto          69
      68: aconst_null
      69: astore        8
      71: aload         8
      73: ifnull        111
      76: aload         8
      78: aload         7
      80: invokeinterface #16,  2           // InterfaceMethod org/springframework/expression/MethodFilter.filter:(Ljava/util/List;)Ljava/util/List;
      85: astore        9
      87: aload         9
      89: instanceof    #11                 // class java/util/ArrayList
      92: ifeq          100
      95: aload         9
      97: goto          109
     100: new           #11                 // class java/util/ArrayList
     103: dup
     104: aload         9
     106: invokespecial #13                 // Method java/util/ArrayList."<init>":(Ljava/util/Collection;)V
     109: astore        7
     111: aload         7
     113: invokeinterface #17,  1           // InterfaceMethod java/util/List.size:()I
     118: iconst_1
     119: if_icmple     135
     122: aload         7
     124: new           #18                 // class org/springframework/expression/spel/support/ReflectiveMethodResolver$1
     127: dup
     128: aload_0
     129: invokespecial #19                 // Method org/springframework/expression/spel/support/ReflectiveMethodResolver$1."<init>":(Lorg/springframework/expression/spel/support/ReflectiveMethodResolver;)V
     132: invokestatic  #20                 // Method java/util/Collections.sort:(Ljava/util/List;Ljava/util/Comparator;)V
     135: iconst_0
     136: istore        9
     138: iload         9
     140: aload         7
     142: invokeinterface #17,  1           // InterfaceMethod java/util/List.size:()I
     147: if_icmpge     181
     150: aload         7
     152: iload         9
     154: aload         7
     156: iload         9
     158: invokeinterface #21,  2           // InterfaceMethod java/util/List.get:(I)Ljava/lang/Object;
     163: checkcast     #22                 // class java/lang/reflect/Method
     166: invokestatic  #23                 // Method org/springframework/core/BridgeMethodResolver.findBridgedMethod:(Ljava/lang/reflect/Method;)Ljava/lang/reflect/Method;
     169: invokeinterface #24,  3           // InterfaceMethod java/util/List.set:(ILjava/lang/Object;)Ljava/lang/Object;
     174: pop
     175: iinc          9, 1
     178: goto          138
     181: new           #25                 // class java/util/LinkedHashSet
     184: dup
     185: aload         7
     187: invokespecial #26                 // Method java/util/LinkedHashSet."<init>":(Ljava/util/Collection;)V
     190: astore        9
     192: aconst_null
     193: astore        10
     195: ldc           #28                 // int 2147483647
     197: istore        11
     199: aconst_null
     200: astore        12
     202: iconst_0
     203: istore        13
     205: aload         9
     207: invokeinterface #29,  1           // InterfaceMethod java/util/Set.iterator:()Ljava/util/Iterator;
     212: astore        14
     214: aload         14
     216: invokeinterface #30,  1           // InterfaceMethod java/util/Iterator.hasNext:()Z
     221: ifeq          479
     224: aload         14
     226: invokeinterface #31,  1           // InterfaceMethod java/util/Iterator.next:()Ljava/lang/Object;
     231: checkcast     #22                 // class java/lang/reflect/Method
     234: astore        15
     236: aload         15
     238: invokevirtual #32                 // Method java/lang/reflect/Method.getName:()Ljava/lang/String;
     241: aload_3
     242: invokevirtual #33                 // Method java/lang/String.equals:(Ljava/lang/Object;)Z
     245: ifeq          476
     248: aload         15
     250: invokevirtual #34                 // Method java/lang/reflect/Method.getParameterTypes:()[Ljava/lang/Class;
     253: astore        16
     255: new           #11                 // class java/util/ArrayList
     258: dup
     259: aload         16
     261: arraylength
     262: invokespecial #35                 // Method java/util/ArrayList."<init>":(I)V
     265: astore        17
     267: iconst_0
     268: istore        18
     270: iload         18
     272: aload         16
     274: arraylength
     275: if_icmpge     310
     278: aload         17
     280: new           #36                 // class org/springframework/core/convert/TypeDescriptor
     283: dup
     284: new           #37                 // class org/springframework/core/MethodParameter
     287: dup
     288: aload         15
     290: iload         18
     292: invokespecial #38                 // Method org/springframework/core/MethodParameter."<init>":(Ljava/lang/reflect/Method;I)V
     295: invokespecial #39                 // Method org/springframework/core/convert/TypeDescriptor."<init>":(Lorg/springframework/core/MethodParameter;)V
     298: invokeinterface #40,  2           // InterfaceMethod java/util/List.add:(Ljava/lang/Object;)Z
     303: pop
     304: iinc          18, 1
     307: goto          270
     310: aconst_null
     311: astore        18
     313: aload         15
     315: invokevirtual #41                 // Method java/lang/reflect/Method.isVarArgs:()Z
     318: ifeq          350
     321: aload         4
     323: invokeinterface #17,  1           // InterfaceMethod java/util/List.size:()I
     328: aload         16
     330: arraylength
     331: iconst_1
     332: isub
     333: if_icmplt     350
     336: aload         17
     338: aload         4
     340: aload         5
     342: invokestatic  #42                 // Method org/springframework/expression/spel/support/ReflectionHelper.compareArgumentsVarargs:(Ljava/util/List;Ljava/util/List;Lorg/springframework/expression/TypeConverter;)Lorg/springframework/expression/spel/support/ReflectionHelper$ArgumentsMatchInfo;
     345: astore        18
     347: goto          374
     350: aload         16
     352: arraylength
     353: aload         4
     355: invokeinterface #17,  1           // InterfaceMethod java/util/List.size:()I
     360: if_icmpne     374
     363: aload         17
     365: aload         4
     367: aload         5
     369: invokestatic  #43                 // Method org/springframework/expression/spel/support/ReflectionHelper.compareArguments:(Ljava/util/List;Ljava/util/List;Lorg/springframework/expression/TypeConverter;)Lorg/springframework/expression/spel/support/ReflectionHelper$ArgumentsMatchInfo;
     372: astore        18
     374: aload         18
     376: ifnull        476
     379: aload         18
     381: invokevirtual #44                 // Method org/springframework/expression/spel/support/ReflectionHelper$ArgumentsMatchInfo.isExactMatch:()Z
     384: ifeq          397
     387: new           #45                 // class org/springframework/expression/spel/support/ReflectiveMethodExecutor
     390: dup
     391: aload         15
     393: invokespecial #46                 // Method org/springframework/expression/spel/support/ReflectiveMethodExecutor."<init>":(Ljava/lang/reflect/Method;)V
     396: areturn
     397: aload         18
     399: invokevirtual #47                 // Method org/springframework/expression/spel/support/ReflectionHelper$ArgumentsMatchInfo.isCloseMatch:()Z
     402: ifeq          456
     405: aload_0
     406: getfield      #2                  // Field useDistance:Z
     409: ifeq          444
     412: aload         17
     414: aload         4
     416: invokestatic  #48                 // Method org/springframework/expression/spel/support/ReflectionHelper.getTypeDifferenceWeight:(Ljava/util/List;Ljava/util/List;)I
     419: istore        19
     421: aload         10
     423: ifnull        433
     426: iload         19
     428: iload         11
     430: if_icmpge     441
     433: aload         15
     435: astore        10
     437: iload         19
     439: istore        11
     441: goto          476
     444: aload         10
     446: ifnonnull     476
     449: aload         15
     451: astore        10
     453: goto          476
     456: aload         18
     458: invokevirtual #49                 // Method org/springframework/expression/spel/support/ReflectionHelper$ArgumentsMatchInfo.isMatchRequiringConversion:()Z
     461: ifeq          476
     464: aload         12
     466: ifnull        472
     469: iconst_1
     470: istore        13
     472: aload         15
     474: astore        12
     476: goto          214
     479: aload         10
     481: ifnull        494
     484: new           #45                 // class org/springframework/expression/spel/support/ReflectiveMethodExecutor
     487: dup
     488: aload         10
     490: invokespecial #46                 // Method org/springframework/expression/spel/support/ReflectiveMethodExecutor."<init>":(Ljava/lang/reflect/Method;)V
     493: areturn
     494: aload         12
     496: ifnull        533
     499: iload         13
     501: ifeq          523
     504: new           #50                 // class org/springframework/expression/spel/SpelEvaluationException
     507: dup
     508: getstatic     #51                 // Field org/springframework/expression/spel/SpelMessage.MULTIPLE_POSSIBLE_METHODS:Lorg/springframework/expression/spel/SpelMessage;
     511: iconst_1
     512: anewarray     #52                 // class java/lang/Object
     515: dup
     516: iconst_0
     517: aload_3
     518: aastore
     519: invokespecial #53                 // Method org/springframework/expression/spel/SpelEvaluationException."<init>":(Lorg/springframework/expression/spel/SpelMessage;[Ljava/lang/Object;)V
     522: athrow
     523: new           #45                 // class org/springframework/expression/spel/support/ReflectiveMethodExecutor
     526: dup
     527: aload         12
     529: invokespecial #46                 // Method org/springframework/expression/spel/support/ReflectiveMethodExecutor."<init>":(Ljava/lang/reflect/Method;)V
     532: areturn
     533: aconst_null
     534: areturn
     535: astore        5
     537: new           #55                 // class org/springframework/expression/AccessException
     540: dup
     541: ldc           #56                 // String Failed to resolve method
     543: aload         5
     545: invokespecial #57                 // Method org/springframework/expression/AccessException."<init>":(Ljava/lang/String;Ljava/lang/Exception;)V
     548: athrow
    Exception table:
       from    to  target type
           0   396   535   Class org/springframework/expression/EvaluationException
         397   493   535   Class org/springframework/expression/EvaluationException
         494   532   535   Class org/springframework/expression/EvaluationException
         533   534   535   Class org/springframework/expression/EvaluationException

  private java.util.Collection<java.lang.reflect.Method> getMethods(java.lang.Class<?>, java.lang.Object);
    Code:
       0: aload_2
       1: instanceof    #9                  // class java/lang/Class
       4: ifeq          92
       7: new           #25                 // class java/util/LinkedHashSet
      10: dup
      11: invokespecial #58                 // Method java/util/LinkedHashSet."<init>":()V
      14: astore_3
      15: aload_0
      16: aload_1
      17: invokevirtual #59                 // Method getMethods:(Ljava/lang/Class;)[Ljava/lang/reflect/Method;
      20: astore        4
      22: aload         4
      24: astore        5
      26: aload         5
      28: arraylength
      29: istore        6
      31: iconst_0
      32: istore        7
      34: iload         7
      36: iload         6
      38: if_icmpge     74
      41: aload         5
      43: iload         7
      45: aaload
      46: astore        8
      48: aload         8
      50: invokevirtual #60                 // Method java/lang/reflect/Method.getModifiers:()I
      53: invokestatic  #61                 // Method java/lang/reflect/Modifier.isStatic:(I)Z
      56: ifeq          68
      59: aload_3
      60: aload         8
      62: invokeinterface #62,  2           // InterfaceMethod java/util/Set.add:(Ljava/lang/Object;)Z
      67: pop
      68: iinc          7, 1
      71: goto          34
      74: aload_3
      75: aload_0
      76: ldc           #9                  // class java/lang/Class
      78: invokevirtual #59                 // Method getMethods:(Ljava/lang/Class;)[Ljava/lang/reflect/Method;
      81: invokestatic  #63                 // Method java/util/Arrays.asList:([Ljava/lang/Object;)Ljava/util/List;
      84: invokeinterface #64,  2           // InterfaceMethod java/util/Set.addAll:(Ljava/util/Collection;)Z
      89: pop
      90: aload_3
      91: areturn
      92: aload_0
      93: aload_1
      94: invokevirtual #59                 // Method getMethods:(Ljava/lang/Class;)[Ljava/lang/reflect/Method;
      97: invokestatic  #63                 // Method java/util/Arrays.asList:([Ljava/lang/Object;)Ljava/util/List;
     100: areturn

  protected java.lang.reflect.Method[] getMethods(java.lang.Class<?>);
    Code:
       0: aload_1
       1: invokevirtual #65                 // Method java/lang/Class.getMethods:()[Ljava/lang/reflect/Method;
       4: areturn
}
