Compiled from "CamelConnectionFactory.java"
public class org.apache.activemq.camel.CamelConnectionFactory extends org.apache.activemq.spring.ActiveMQConnectionFactory implements org.apache.camel.CamelContextAware {
  private org.apache.camel.CamelContext camelContext;

  public org.apache.activemq.camel.CamelConnectionFactory();
    Code:
       0: aload_0
       1: invokespecial #1                  // Method org/apache/activemq/spring/ActiveMQConnectionFactory."<init>":()V
       4: return

  public org.apache.camel.CamelContext getCamelContext();
    Code:
       0: aload_0
       1: getfield      #2                  // Field camelContext:Lorg/apache/camel/CamelContext;
       4: areturn

  public void setCamelContext(org.apache.camel.CamelContext);
    Code:
       0: aload_0
       1: aload_1
       2: putfield      #2                  // Field camelContext:Lorg/apache/camel/CamelContext;
       5: return

  protected org.apache.activemq.camel.CamelConnection createActiveMQConnection(org.apache.activemq.transport.Transport, org.apache.activemq.management.JMSStatsImpl) throws java.lang.Exception;
    Code:
       0: new           #3                  // class org/apache/activemq/camel/CamelConnection
       3: dup
       4: aload_1
       5: aload_0
       6: invokevirtual #4                  // Method getClientIdGenerator:()Lorg/apache/activemq/util/IdGenerator;
       9: aload_0
      10: invokevirtual #5                  // Method getConnectionIdGenerator:()Lorg/apache/activemq/util/IdGenerator;
      13: aload_2
      14: invokespecial #6                  // Method org/apache/activemq/camel/CamelConnection."<init>":(Lorg/apache/activemq/transport/Transport;Lorg/apache/activemq/util/IdGenerator;Lorg/apache/activemq/util/IdGenerator;Lorg/apache/activemq/management/JMSStatsImpl;)V
      17: astore_3
      18: aload_0
      19: invokevirtual #7                  // Method getCamelContext:()Lorg/apache/camel/CamelContext;
      22: astore        4
      24: aload         4
      26: ifnull        35
      29: aload_3
      30: aload         4
      32: invokevirtual #8                  // Method org/apache/activemq/camel/CamelConnection.setCamelContext:(Lorg/apache/camel/CamelContext;)V
      35: aload_3
      36: areturn

  protected org.apache.activemq.ActiveMQConnection createActiveMQConnection(org.apache.activemq.transport.Transport, org.apache.activemq.management.JMSStatsImpl) throws java.lang.Exception;
    Code:
       0: aload_0
       1: aload_1
       2: aload_2
       3: invokevirtual #9                  // Method createActiveMQConnection:(Lorg/apache/activemq/transport/Transport;Lorg/apache/activemq/management/JMSStatsImpl;)Lorg/apache/activemq/camel/CamelConnection;
       6: areturn
}
