Compiled from "MybatisRegistrationsDao.java"
public final class org.restcomm.connect.dao.mybatis.MybatisRegistrationsDao implements org.restcomm.connect.dao.RegistrationsDao {
  private static final org.apache.log4j.Logger logger;

  private static final java.lang.String namespace;

  private final org.apache.ibatis.session.SqlSessionFactory sessions;

  public org.restcomm.connect.dao.mybatis.MybatisRegistrationsDao(org.apache.ibatis.session.SqlSessionFactory);
    Code:
       0: aload_0
       1: invokespecial #1                  // Method java/lang/Object."<init>":()V
       4: aload_0
       5: aload_1
       6: putfield      #2                  // Field sessions:Lorg/apache/ibatis/session/SqlSessionFactory;
       9: return

  public void addRegistration(org.restcomm.connect.dao.entities.Registration);
    Code:
       0: aload_0
       1: getfield      #2                  // Field sessions:Lorg/apache/ibatis/session/SqlSessionFactory;
       4: invokeinterface #3,  1            // InterfaceMethod org/apache/ibatis/session/SqlSessionFactory.openSession:()Lorg/apache/ibatis/session/SqlSession;
       9: astore_2
      10: aload_2
      11: ldc           #4                  // String org.mobicents.servlet.sip.restcomm.dao.RegistrationsDao.addRegistration
      13: aload_0
      14: aload_1
      15: invokespecial #5                  // Method toMap:(Lorg/restcomm/connect/dao/entities/Registration;)Ljava/util/Map;
      18: invokeinterface #6,  3            // InterfaceMethod org/apache/ibatis/session/SqlSession.insert:(Ljava/lang/String;Ljava/lang/Object;)I
      23: pop
      24: aload_2
      25: invokeinterface #7,  1            // InterfaceMethod org/apache/ibatis/session/SqlSession.commit:()V
      30: aload_2
      31: invokeinterface #8,  1            // InterfaceMethod org/apache/ibatis/session/SqlSession.close:()V
      36: goto          48
      39: astore_3
      40: aload_2
      41: invokeinterface #8,  1            // InterfaceMethod org/apache/ibatis/session/SqlSession.close:()V
      46: aload_3
      47: athrow
      48: return
    Exception table:
       from    to  target type
          10    30    39   any
          39    40    39   any

  public org.restcomm.connect.dao.entities.Registration getRegistration(java.lang.String);
    Code:
       0: aload_0
       1: getfield      #2                  // Field sessions:Lorg/apache/ibatis/session/SqlSessionFactory;
       4: invokeinterface #3,  1            // InterfaceMethod org/apache/ibatis/session/SqlSessionFactory.openSession:()Lorg/apache/ibatis/session/SqlSession;
       9: astore_2
      10: aload_2
      11: ldc           #9                  // String org.mobicents.servlet.sip.restcomm.dao.RegistrationsDao.getRegistration
      13: aload_1
      14: invokeinterface #10,  3           // InterfaceMethod org/apache/ibatis/session/SqlSession.selectList:(Ljava/lang/String;Ljava/lang/Object;)Ljava/util/List;
      19: astore_3
      20: new           #11                 // class java/util/ArrayList
      23: dup
      24: invokespecial #12                 // Method java/util/ArrayList."<init>":()V
      27: astore        4
      29: aload_3
      30: ifnull        138
      33: aload_3
      34: invokeinterface #13,  1           // InterfaceMethod java/util/List.isEmpty:()Z
      39: ifne          138
      42: aload_3
      43: invokeinterface #14,  1           // InterfaceMethod java/util/List.iterator:()Ljava/util/Iterator;
      48: astore        5
      50: aload         5
      52: invokeinterface #15,  1           // InterfaceMethod java/util/Iterator.hasNext:()Z
      57: ifeq          89
      60: aload         5
      62: invokeinterface #16,  1           // InterfaceMethod java/util/Iterator.next:()Ljava/lang/Object;
      67: checkcast     #17                 // class java/util/Map
      70: astore        6
      72: aload         4
      74: aload_0
      75: aload         6
      77: invokespecial #18                 // Method toPresenceRecord:(Ljava/util/Map;)Lorg/restcomm/connect/dao/entities/Registration;
      80: invokeinterface #19,  2           // InterfaceMethod java/util/List.add:(Ljava/lang/Object;)Z
      85: pop
      86: goto          50
      89: aload         4
      91: invokeinterface #13,  1           // InterfaceMethod java/util/List.isEmpty:()Z
      96: ifeq          111
      99: aconst_null
     100: astore        5
     102: aload_2
     103: invokeinterface #8,  1            // InterfaceMethod org/apache/ibatis/session/SqlSession.close:()V
     108: aload         5
     110: areturn
     111: aload         4
     113: invokestatic  #20                 // Method java/util/Collections.sort:(Ljava/util/List;)V
     116: aload         4
     118: iconst_0
     119: invokeinterface #21,  2           // InterfaceMethod java/util/List.get:(I)Ljava/lang/Object;
     124: checkcast     #22                 // class org/restcomm/connect/dao/entities/Registration
     127: astore        5
     129: aload_2
     130: invokeinterface #8,  1            // InterfaceMethod org/apache/ibatis/session/SqlSession.close:()V
     135: aload         5
     137: areturn
     138: aconst_null
     139: astore        5
     141: aload_2
     142: invokeinterface #8,  1            // InterfaceMethod org/apache/ibatis/session/SqlSession.close:()V
     147: aload         5
     149: areturn
     150: astore        7
     152: aload_2
     153: invokeinterface #8,  1            // InterfaceMethod org/apache/ibatis/session/SqlSession.close:()V
     158: aload         7
     160: athrow
    Exception table:
       from    to  target type
          10   102   150   any
         111   129   150   any
         138   141   150   any
         150   152   150   any

  public org.restcomm.connect.dao.entities.Registration getRegistrationByInstanceId(java.lang.String, java.lang.String);
    Code:
       0: aload_0
       1: getfield      #2                  // Field sessions:Lorg/apache/ibatis/session/SqlSessionFactory;
       4: invokeinterface #3,  1            // InterfaceMethod org/apache/ibatis/session/SqlSessionFactory.openSession:()Lorg/apache/ibatis/session/SqlSession;
       9: astore_3
      10: new           #23                 // class java/util/HashMap
      13: dup
      14: invokespecial #24                 // Method java/util/HashMap."<init>":()V
      17: astore        4
      19: aload         4
      21: ldc           #25                 // String user_name
      23: aload_1
      24: invokeinterface #26,  3           // InterfaceMethod java/util/Map.put:(Ljava/lang/Object;Ljava/lang/Object;)Ljava/lang/Object;
      29: pop
      30: aload         4
      32: ldc           #27                 // String instanceid
      34: aload_2
      35: invokeinterface #26,  3           // InterfaceMethod java/util/Map.put:(Ljava/lang/Object;Ljava/lang/Object;)Ljava/lang/Object;
      40: pop
      41: aload_3
      42: ldc           #28                 // String org.mobicents.servlet.sip.restcomm.dao.RegistrationsDao.getRegistrationByInstanceId
      44: aload         4
      46: invokeinterface #10,  3           // InterfaceMethod org/apache/ibatis/session/SqlSession.selectList:(Ljava/lang/String;Ljava/lang/Object;)Ljava/util/List;
      51: astore        5
      53: new           #11                 // class java/util/ArrayList
      56: dup
      57: invokespecial #12                 // Method java/util/ArrayList."<init>":()V
      60: astore        6
      62: aload         5
      64: ifnull        174
      67: aload         5
      69: invokeinterface #13,  1           // InterfaceMethod java/util/List.isEmpty:()Z
      74: ifne          174
      77: aload         5
      79: invokeinterface #14,  1           // InterfaceMethod java/util/List.iterator:()Ljava/util/Iterator;
      84: astore        7
      86: aload         7
      88: invokeinterface #15,  1           // InterfaceMethod java/util/Iterator.hasNext:()Z
      93: ifeq          125
      96: aload         7
      98: invokeinterface #16,  1           // InterfaceMethod java/util/Iterator.next:()Ljava/lang/Object;
     103: checkcast     #17                 // class java/util/Map
     106: astore        8
     108: aload         6
     110: aload_0
     111: aload         8
     113: invokespecial #18                 // Method toPresenceRecord:(Ljava/util/Map;)Lorg/restcomm/connect/dao/entities/Registration;
     116: invokeinterface #19,  2           // InterfaceMethod java/util/List.add:(Ljava/lang/Object;)Z
     121: pop
     122: goto          86
     125: aload         6
     127: invokeinterface #13,  1           // InterfaceMethod java/util/List.isEmpty:()Z
     132: ifeq          147
     135: aconst_null
     136: astore        7
     138: aload_3
     139: invokeinterface #8,  1            // InterfaceMethod org/apache/ibatis/session/SqlSession.close:()V
     144: aload         7
     146: areturn
     147: aload         6
     149: invokestatic  #20                 // Method java/util/Collections.sort:(Ljava/util/List;)V
     152: aload         6
     154: iconst_0
     155: invokeinterface #21,  2           // InterfaceMethod java/util/List.get:(I)Ljava/lang/Object;
     160: checkcast     #22                 // class org/restcomm/connect/dao/entities/Registration
     163: astore        7
     165: aload_3
     166: invokeinterface #8,  1            // InterfaceMethod org/apache/ibatis/session/SqlSession.close:()V
     171: aload         7
     173: areturn
     174: aconst_null
     175: astore        7
     177: aload_3
     178: invokeinterface #8,  1            // InterfaceMethod org/apache/ibatis/session/SqlSession.close:()V
     183: aload         7
     185: areturn
     186: astore        9
     188: aload_3
     189: invokeinterface #8,  1            // InterfaceMethod org/apache/ibatis/session/SqlSession.close:()V
     194: aload         9
     196: athrow
    Exception table:
       from    to  target type
          10   138   186   any
         147   165   186   any
         174   177   186   any
         186   188   186   any

  public java.util.List<org.restcomm.connect.dao.entities.Registration> getRegistrationsByInstanceId(java.lang.String);
    Code:
       0: aload_0
       1: getfield      #2                  // Field sessions:Lorg/apache/ibatis/session/SqlSessionFactory;
       4: invokeinterface #3,  1            // InterfaceMethod org/apache/ibatis/session/SqlSessionFactory.openSession:()Lorg/apache/ibatis/session/SqlSession;
       9: astore_2
      10: aload_2
      11: ldc           #29                 // String org.mobicents.servlet.sip.restcomm.dao.RegistrationsDao.getRegistrationsByInstanceId
      13: aload_1
      14: invokeinterface #10,  3           // InterfaceMethod org/apache/ibatis/session/SqlSession.selectList:(Ljava/lang/String;Ljava/lang/Object;)Ljava/util/List;
      19: astore_3
      20: new           #11                 // class java/util/ArrayList
      23: dup
      24: invokespecial #12                 // Method java/util/ArrayList."<init>":()V
      27: astore        4
      29: aload_3
      30: ifnull        104
      33: aload_3
      34: invokeinterface #13,  1           // InterfaceMethod java/util/List.isEmpty:()Z
      39: ifne          104
      42: aload_3
      43: invokeinterface #14,  1           // InterfaceMethod java/util/List.iterator:()Ljava/util/Iterator;
      48: astore        5
      50: aload         5
      52: invokeinterface #15,  1           // InterfaceMethod java/util/Iterator.hasNext:()Z
      57: ifeq          89
      60: aload         5
      62: invokeinterface #16,  1           // InterfaceMethod java/util/Iterator.next:()Ljava/lang/Object;
      67: checkcast     #17                 // class java/util/Map
      70: astore        6
      72: aload         4
      74: aload_0
      75: aload         6
      77: invokespecial #18                 // Method toPresenceRecord:(Ljava/util/Map;)Lorg/restcomm/connect/dao/entities/Registration;
      80: invokeinterface #19,  2           // InterfaceMethod java/util/List.add:(Ljava/lang/Object;)Z
      85: pop
      86: goto          50
      89: aload         4
      91: invokeinterface #13,  1           // InterfaceMethod java/util/List.isEmpty:()Z
      96: ifne          104
      99: aload         4
     101: invokestatic  #20                 // Method java/util/Collections.sort:(Ljava/util/List;)V
     104: aload         4
     106: astore        5
     108: aload_2
     109: invokeinterface #8,  1            // InterfaceMethod org/apache/ibatis/session/SqlSession.close:()V
     114: aload         5
     116: areturn
     117: astore        7
     119: aload_2
     120: invokeinterface #8,  1            // InterfaceMethod org/apache/ibatis/session/SqlSession.close:()V
     125: aload         7
     127: athrow
    Exception table:
       from    to  target type
          10   108   117   any
         117   119   117   any

  public java.util.List<org.restcomm.connect.dao.entities.Registration> getRegistrations(java.lang.String);
    Code:
       0: aload_0
       1: getfield      #2                  // Field sessions:Lorg/apache/ibatis/session/SqlSessionFactory;
       4: invokeinterface #3,  1            // InterfaceMethod org/apache/ibatis/session/SqlSessionFactory.openSession:()Lorg/apache/ibatis/session/SqlSession;
       9: astore_2
      10: aload_2
      11: ldc           #9                  // String org.mobicents.servlet.sip.restcomm.dao.RegistrationsDao.getRegistration
      13: aload_1
      14: invokeinterface #10,  3           // InterfaceMethod org/apache/ibatis/session/SqlSession.selectList:(Ljava/lang/String;Ljava/lang/Object;)Ljava/util/List;
      19: astore_3
      20: new           #11                 // class java/util/ArrayList
      23: dup
      24: invokespecial #12                 // Method java/util/ArrayList."<init>":()V
      27: astore        4
      29: aload_3
      30: ifnull        129
      33: aload_3
      34: invokeinterface #13,  1           // InterfaceMethod java/util/List.isEmpty:()Z
      39: ifne          129
      42: aload_3
      43: invokeinterface #14,  1           // InterfaceMethod java/util/List.iterator:()Ljava/util/Iterator;
      48: astore        5
      50: aload         5
      52: invokeinterface #15,  1           // InterfaceMethod java/util/Iterator.hasNext:()Z
      57: ifeq          89
      60: aload         5
      62: invokeinterface #16,  1           // InterfaceMethod java/util/Iterator.next:()Ljava/lang/Object;
      67: checkcast     #17                 // class java/util/Map
      70: astore        6
      72: aload         4
      74: aload_0
      75: aload         6
      77: invokespecial #18                 // Method toPresenceRecord:(Ljava/util/Map;)Lorg/restcomm/connect/dao/entities/Registration;
      80: invokeinterface #19,  2           // InterfaceMethod java/util/List.add:(Ljava/lang/Object;)Z
      85: pop
      86: goto          50
      89: aload         4
      91: invokeinterface #13,  1           // InterfaceMethod java/util/List.isEmpty:()Z
      96: ifeq          111
      99: aconst_null
     100: astore        5
     102: aload_2
     103: invokeinterface #8,  1            // InterfaceMethod org/apache/ibatis/session/SqlSession.close:()V
     108: aload         5
     110: areturn
     111: aload         4
     113: invokestatic  #20                 // Method java/util/Collections.sort:(Ljava/util/List;)V
     116: aload         4
     118: astore        5
     120: aload_2
     121: invokeinterface #8,  1            // InterfaceMethod org/apache/ibatis/session/SqlSession.close:()V
     126: aload         5
     128: areturn
     129: aconst_null
     130: astore        5
     132: aload_2
     133: invokeinterface #8,  1            // InterfaceMethod org/apache/ibatis/session/SqlSession.close:()V
     138: aload         5
     140: areturn
     141: astore        7
     143: aload_2
     144: invokeinterface #8,  1            // InterfaceMethod org/apache/ibatis/session/SqlSession.close:()V
     149: aload         7
     151: athrow
    Exception table:
       from    to  target type
          10   102   141   any
         111   120   141   any
         129   132   141   any
         141   143   141   any

  public java.util.List<org.restcomm.connect.dao.entities.Registration> getRegistrations();
    Code:
       0: aload_0
       1: getfield      #2                  // Field sessions:Lorg/apache/ibatis/session/SqlSessionFactory;
       4: invokeinterface #3,  1            // InterfaceMethod org/apache/ibatis/session/SqlSessionFactory.openSession:()Lorg/apache/ibatis/session/SqlSession;
       9: astore_1
      10: aload_1
      11: ldc           #30                 // String org.mobicents.servlet.sip.restcomm.dao.RegistrationsDao.getRegistrations
      13: invokeinterface #31,  2           // InterfaceMethod org/apache/ibatis/session/SqlSession.selectList:(Ljava/lang/String;)Ljava/util/List;
      18: astore_2
      19: new           #11                 // class java/util/ArrayList
      22: dup
      23: invokespecial #12                 // Method java/util/ArrayList."<init>":()V
      26: astore_3
      27: aload_2
      28: ifnull        86
      31: aload_2
      32: invokeinterface #13,  1           // InterfaceMethod java/util/List.isEmpty:()Z
      37: ifne          86
      40: aload_2
      41: invokeinterface #14,  1           // InterfaceMethod java/util/List.iterator:()Ljava/util/Iterator;
      46: astore        4
      48: aload         4
      50: invokeinterface #15,  1           // InterfaceMethod java/util/Iterator.hasNext:()Z
      55: ifeq          86
      58: aload         4
      60: invokeinterface #16,  1           // InterfaceMethod java/util/Iterator.next:()Ljava/lang/Object;
      65: checkcast     #17                 // class java/util/Map
      68: astore        5
      70: aload_3
      71: aload_0
      72: aload         5
      74: invokespecial #18                 // Method toPresenceRecord:(Ljava/util/Map;)Lorg/restcomm/connect/dao/entities/Registration;
      77: invokeinterface #19,  2           // InterfaceMethod java/util/List.add:(Ljava/lang/Object;)Z
      82: pop
      83: goto          48
      86: aload_3
      87: astore        4
      89: aload_1
      90: invokeinterface #8,  1            // InterfaceMethod org/apache/ibatis/session/SqlSession.close:()V
      95: aload         4
      97: areturn
      98: astore        6
     100: aload_1
     101: invokeinterface #8,  1            // InterfaceMethod org/apache/ibatis/session/SqlSession.close:()V
     106: aload         6
     108: athrow
    Exception table:
       from    to  target type
          10    89    98   any
          98   100    98   any

  public boolean hasRegistration(org.restcomm.connect.dao.entities.Registration);
    Code:
       0: aload_0
       1: getfield      #2                  // Field sessions:Lorg/apache/ibatis/session/SqlSessionFactory;
       4: invokeinterface #3,  1            // InterfaceMethod org/apache/ibatis/session/SqlSessionFactory.openSession:()Lorg/apache/ibatis/session/SqlSession;
       9: astore_2
      10: aload_2
      11: ldc           #32                 // String org.mobicents.servlet.sip.restcomm.dao.RegistrationsDao.hasRegistration
      13: aload_0
      14: aload_1
      15: invokespecial #5                  // Method toMap:(Lorg/restcomm/connect/dao/entities/Registration;)Ljava/util/Map;
      18: invokeinterface #33,  3           // InterfaceMethod org/apache/ibatis/session/SqlSession.selectOne:(Ljava/lang/String;Ljava/lang/Object;)Ljava/lang/Object;
      23: checkcast     #34                 // class java/lang/Integer
      26: astore_3
      27: aload_3
      28: ifnull        42
      31: aload_3
      32: invokevirtual #35                 // Method java/lang/Integer.intValue:()I
      35: ifle          42
      38: iconst_1
      39: goto          43
      42: iconst_0
      43: istore        4
      45: aload_2
      46: invokeinterface #8,  1            // InterfaceMethod org/apache/ibatis/session/SqlSession.close:()V
      51: iload         4
      53: ireturn
      54: astore        5
      56: aload_2
      57: invokeinterface #8,  1            // InterfaceMethod org/apache/ibatis/session/SqlSession.close:()V
      62: aload         5
      64: athrow
    Exception table:
       from    to  target type
          10    45    54   any
          54    56    54   any

  public void removeRegistration(org.restcomm.connect.dao.entities.Registration);
    Code:
       0: aload_0
       1: getfield      #2                  // Field sessions:Lorg/apache/ibatis/session/SqlSessionFactory;
       4: invokeinterface #3,  1            // InterfaceMethod org/apache/ibatis/session/SqlSessionFactory.openSession:()Lorg/apache/ibatis/session/SqlSession;
       9: astore_2
      10: aload_2
      11: ldc           #36                 // String org.mobicents.servlet.sip.restcomm.dao.RegistrationsDao.removeRegistration
      13: aload_0
      14: aload_1
      15: invokespecial #5                  // Method toMap:(Lorg/restcomm/connect/dao/entities/Registration;)Ljava/util/Map;
      18: invokeinterface #37,  3           // InterfaceMethod org/apache/ibatis/session/SqlSession.delete:(Ljava/lang/String;Ljava/lang/Object;)I
      23: pop
      24: aload_2
      25: invokeinterface #7,  1            // InterfaceMethod org/apache/ibatis/session/SqlSession.commit:()V
      30: aload_2
      31: invokeinterface #8,  1            // InterfaceMethod org/apache/ibatis/session/SqlSession.close:()V
      36: goto          48
      39: astore_3
      40: aload_2
      41: invokeinterface #8,  1            // InterfaceMethod org/apache/ibatis/session/SqlSession.close:()V
      46: aload_3
      47: athrow
      48: return
    Exception table:
       from    to  target type
          10    30    39   any
          39    40    39   any

  public void updateRegistration(org.restcomm.connect.dao.entities.Registration);
    Code:
       0: aload_0
       1: getfield      #2                  // Field sessions:Lorg/apache/ibatis/session/SqlSessionFactory;
       4: invokeinterface #3,  1            // InterfaceMethod org/apache/ibatis/session/SqlSessionFactory.openSession:()Lorg/apache/ibatis/session/SqlSession;
       9: astore_2
      10: aload_2
      11: ldc           #38                 // String org.mobicents.servlet.sip.restcomm.dao.RegistrationsDao.updateRegistration
      13: aload_0
      14: aload_1
      15: invokespecial #5                  // Method toMap:(Lorg/restcomm/connect/dao/entities/Registration;)Ljava/util/Map;
      18: invokeinterface #39,  3           // InterfaceMethod org/apache/ibatis/session/SqlSession.update:(Ljava/lang/String;Ljava/lang/Object;)I
      23: pop
      24: aload_2
      25: invokeinterface #7,  1            // InterfaceMethod org/apache/ibatis/session/SqlSession.commit:()V
      30: aload_2
      31: invokeinterface #8,  1            // InterfaceMethod org/apache/ibatis/session/SqlSession.close:()V
      36: goto          48
      39: astore_3
      40: aload_2
      41: invokeinterface #8,  1            // InterfaceMethod org/apache/ibatis/session/SqlSession.close:()V
      46: aload_3
      47: athrow
      48: return
    Exception table:
       from    to  target type
          10    30    39   any
          39    40    39   any

  private java.util.Map<java.lang.String, java.lang.Object> toMap(org.restcomm.connect.dao.entities.Registration);
    Code:
       0: new           #23                 // class java/util/HashMap
       3: dup
       4: invokespecial #24                 // Method java/util/HashMap."<init>":()V
       7: astore_2
       8: aload_2
       9: ldc           #40                 // String sid
      11: aload_1
      12: invokevirtual #41                 // Method org/restcomm/connect/dao/entities/Registration.getSid:()Lorg/restcomm/connect/commons/dao/Sid;
      15: invokestatic  #42                 // Method org/restcomm/connect/dao/DaoUtils.writeSid:(Lorg/restcomm/connect/commons/dao/Sid;)Ljava/lang/String;
      18: invokeinterface #26,  3           // InterfaceMethod java/util/Map.put:(Ljava/lang/Object;Ljava/lang/Object;)Ljava/lang/Object;
      23: pop
      24: aload_2
      25: ldc           #27                 // String instanceid
      27: aload_1
      28: invokevirtual #43                 // Method org/restcomm/connect/dao/entities/Registration.getInstanceId:()Ljava/lang/String;
      31: invokeinterface #26,  3           // InterfaceMethod java/util/Map.put:(Ljava/lang/Object;Ljava/lang/Object;)Ljava/lang/Object;
      36: pop
      37: aload_2
      38: ldc           #44                 // String date_created
      40: aload_1
      41: invokevirtual #45                 // Method org/restcomm/connect/dao/entities/Registration.getDateCreated:()Lorg/joda/time/DateTime;
      44: invokestatic  #46                 // Method org/restcomm/connect/dao/DaoUtils.writeDateTime:(Lorg/joda/time/DateTime;)Ljava/util/Date;
      47: invokeinterface #26,  3           // InterfaceMethod java/util/Map.put:(Ljava/lang/Object;Ljava/lang/Object;)Ljava/lang/Object;
      52: pop
      53: aload_2
      54: ldc           #47                 // String date_updated
      56: aload_1
      57: invokevirtual #48                 // Method org/restcomm/connect/dao/entities/Registration.getDateUpdated:()Lorg/joda/time/DateTime;
      60: invokestatic  #46                 // Method org/restcomm/connect/dao/DaoUtils.writeDateTime:(Lorg/joda/time/DateTime;)Ljava/util/Date;
      63: invokeinterface #26,  3           // InterfaceMethod java/util/Map.put:(Ljava/lang/Object;Ljava/lang/Object;)Ljava/lang/Object;
      68: pop
      69: aload_2
      70: ldc           #49                 // String date_expires
      72: aload_1
      73: invokevirtual #50                 // Method org/restcomm/connect/dao/entities/Registration.getDateExpires:()Lorg/joda/time/DateTime;
      76: invokestatic  #46                 // Method org/restcomm/connect/dao/DaoUtils.writeDateTime:(Lorg/joda/time/DateTime;)Ljava/util/Date;
      79: invokeinterface #26,  3           // InterfaceMethod java/util/Map.put:(Ljava/lang/Object;Ljava/lang/Object;)Ljava/lang/Object;
      84: pop
      85: aload_2
      86: ldc           #51                 // String address_of_record
      88: aload_1
      89: invokevirtual #52                 // Method org/restcomm/connect/dao/entities/Registration.getAddressOfRecord:()Ljava/lang/String;
      92: invokeinterface #26,  3           // InterfaceMethod java/util/Map.put:(Ljava/lang/Object;Ljava/lang/Object;)Ljava/lang/Object;
      97: pop
      98: aload_2
      99: ldc           #53                 // String display_name
     101: aload_1
     102: invokevirtual #54                 // Method org/restcomm/connect/dao/entities/Registration.getDisplayName:()Ljava/lang/String;
     105: invokeinterface #26,  3           // InterfaceMethod java/util/Map.put:(Ljava/lang/Object;Ljava/lang/Object;)Ljava/lang/Object;
     110: pop
     111: aload_2
     112: ldc           #25                 // String user_name
     114: aload_1
     115: invokevirtual #55                 // Method org/restcomm/connect/dao/entities/Registration.getUserName:()Ljava/lang/String;
     118: invokeinterface #26,  3           // InterfaceMethod java/util/Map.put:(Ljava/lang/Object;Ljava/lang/Object;)Ljava/lang/Object;
     123: pop
     124: aload_2
     125: ldc           #56                 // String location
     127: aload_1
     128: invokevirtual #57                 // Method org/restcomm/connect/dao/entities/Registration.getLocation:()Ljava/lang/String;
     131: invokeinterface #26,  3           // InterfaceMethod java/util/Map.put:(Ljava/lang/Object;Ljava/lang/Object;)Ljava/lang/Object;
     136: pop
     137: aload_2
     138: ldc           #58                 // String user_agent
     140: aload_1
     141: invokevirtual #59                 // Method org/restcomm/connect/dao/entities/Registration.getUserAgent:()Ljava/lang/String;
     144: invokeinterface #26,  3           // InterfaceMethod java/util/Map.put:(Ljava/lang/Object;Ljava/lang/Object;)Ljava/lang/Object;
     149: pop
     150: aload_2
     151: ldc           #60                 // String ttl
     153: aload_1
     154: invokevirtual #61                 // Method org/restcomm/connect/dao/entities/Registration.getTimeToLive:()I
     157: invokestatic  #62                 // Method java/lang/Integer.valueOf:(I)Ljava/lang/Integer;
     160: invokeinterface #26,  3           // InterfaceMethod java/util/Map.put:(Ljava/lang/Object;Ljava/lang/Object;)Ljava/lang/Object;
     165: pop
     166: aload_2
     167: ldc           #63                 // String webrtc
     169: aload_1
     170: invokevirtual #64                 // Method org/restcomm/connect/dao/entities/Registration.isWebRTC:()Z
     173: invokestatic  #65                 // Method java/lang/Boolean.valueOf:(Z)Ljava/lang/Boolean;
     176: invokeinterface #26,  3           // InterfaceMethod java/util/Map.put:(Ljava/lang/Object;Ljava/lang/Object;)Ljava/lang/Object;
     181: pop
     182: aload_2
     183: ldc           #66                 // String isLBPresent
     185: aload_1
     186: invokevirtual #67                 // Method org/restcomm/connect/dao/entities/Registration.isLBPresent:()Z
     189: invokestatic  #65                 // Method java/lang/Boolean.valueOf:(Z)Ljava/lang/Boolean;
     192: invokeinterface #26,  3           // InterfaceMethod java/util/Map.put:(Ljava/lang/Object;Ljava/lang/Object;)Ljava/lang/Object;
     197: pop
     198: aload_2
     199: areturn

  private org.restcomm.connect.dao.entities.Registration toPresenceRecord(java.util.Map<java.lang.String, java.lang.Object>);
    Code:
       0: aload_1
       1: ldc           #40                 // String sid
       3: invokeinterface #68,  2           // InterfaceMethod java/util/Map.get:(Ljava/lang/Object;)Ljava/lang/Object;
       8: invokestatic  #69                 // Method org/restcomm/connect/dao/DaoUtils.readSid:(Ljava/lang/Object;)Lorg/restcomm/connect/commons/dao/Sid;
      11: astore_2
      12: aload_1
      13: ldc           #27                 // String instanceid
      15: invokeinterface #68,  2           // InterfaceMethod java/util/Map.get:(Ljava/lang/Object;)Ljava/lang/Object;
      20: invokestatic  #70                 // Method org/restcomm/connect/dao/DaoUtils.readString:(Ljava/lang/Object;)Ljava/lang/String;
      23: astore_3
      24: aload_1
      25: ldc           #44                 // String date_created
      27: invokeinterface #68,  2           // InterfaceMethod java/util/Map.get:(Ljava/lang/Object;)Ljava/lang/Object;
      32: invokestatic  #71                 // Method org/restcomm/connect/dao/DaoUtils.readDateTime:(Ljava/lang/Object;)Lorg/joda/time/DateTime;
      35: astore        4
      37: aload_1
      38: ldc           #47                 // String date_updated
      40: invokeinterface #68,  2           // InterfaceMethod java/util/Map.get:(Ljava/lang/Object;)Ljava/lang/Object;
      45: invokestatic  #71                 // Method org/restcomm/connect/dao/DaoUtils.readDateTime:(Ljava/lang/Object;)Lorg/joda/time/DateTime;
      48: astore        5
      50: aload_1
      51: ldc           #49                 // String date_expires
      53: invokeinterface #68,  2           // InterfaceMethod java/util/Map.get:(Ljava/lang/Object;)Ljava/lang/Object;
      58: invokestatic  #71                 // Method org/restcomm/connect/dao/DaoUtils.readDateTime:(Ljava/lang/Object;)Lorg/joda/time/DateTime;
      61: astore        6
      63: aload_1
      64: ldc           #51                 // String address_of_record
      66: invokeinterface #68,  2           // InterfaceMethod java/util/Map.get:(Ljava/lang/Object;)Ljava/lang/Object;
      71: invokestatic  #70                 // Method org/restcomm/connect/dao/DaoUtils.readString:(Ljava/lang/Object;)Ljava/lang/String;
      74: astore        7
      76: aload_1
      77: ldc           #53                 // String display_name
      79: invokeinterface #68,  2           // InterfaceMethod java/util/Map.get:(Ljava/lang/Object;)Ljava/lang/Object;
      84: invokestatic  #70                 // Method org/restcomm/connect/dao/DaoUtils.readString:(Ljava/lang/Object;)Ljava/lang/String;
      87: astore        8
      89: aload_1
      90: ldc           #25                 // String user_name
      92: invokeinterface #68,  2           // InterfaceMethod java/util/Map.get:(Ljava/lang/Object;)Ljava/lang/Object;
      97: invokestatic  #70                 // Method org/restcomm/connect/dao/DaoUtils.readString:(Ljava/lang/Object;)Ljava/lang/String;
     100: astore        9
     102: aload_1
     103: ldc           #56                 // String location
     105: invokeinterface #68,  2           // InterfaceMethod java/util/Map.get:(Ljava/lang/Object;)Ljava/lang/Object;
     110: invokestatic  #70                 // Method org/restcomm/connect/dao/DaoUtils.readString:(Ljava/lang/Object;)Ljava/lang/String;
     113: astore        10
     115: aload_1
     116: ldc           #58                 // String user_agent
     118: invokeinterface #68,  2           // InterfaceMethod java/util/Map.get:(Ljava/lang/Object;)Ljava/lang/Object;
     123: invokestatic  #70                 // Method org/restcomm/connect/dao/DaoUtils.readString:(Ljava/lang/Object;)Ljava/lang/String;
     126: astore        11
     128: aload_1
     129: ldc           #60                 // String ttl
     131: invokeinterface #68,  2           // InterfaceMethod java/util/Map.get:(Ljava/lang/Object;)Ljava/lang/Object;
     136: invokestatic  #72                 // Method org/restcomm/connect/dao/DaoUtils.readInteger:(Ljava/lang/Object;)Ljava/lang/Integer;
     139: astore        12
     141: aload_1
     142: ldc           #63                 // String webrtc
     144: invokeinterface #68,  2           // InterfaceMethod java/util/Map.get:(Ljava/lang/Object;)Ljava/lang/Object;
     149: invokestatic  #73                 // Method org/restcomm/connect/dao/DaoUtils.readBoolean:(Ljava/lang/Object;)Ljava/lang/Boolean;
     152: astore        13
     154: iconst_0
     155: invokestatic  #65                 // Method java/lang/Boolean.valueOf:(Z)Ljava/lang/Boolean;
     158: astore        14
     160: aload_1
     161: ldc           #66                 // String isLBPresent
     163: invokeinterface #68,  2           // InterfaceMethod java/util/Map.get:(Ljava/lang/Object;)Ljava/lang/Object;
     168: invokestatic  #73                 // Method org/restcomm/connect/dao/DaoUtils.readBoolean:(Ljava/lang/Object;)Ljava/lang/Boolean;
     171: ifnull        187
     174: aload_1
     175: ldc           #66                 // String isLBPresent
     177: invokeinterface #68,  2           // InterfaceMethod java/util/Map.get:(Ljava/lang/Object;)Ljava/lang/Object;
     182: invokestatic  #73                 // Method org/restcomm/connect/dao/DaoUtils.readBoolean:(Ljava/lang/Object;)Ljava/lang/Boolean;
     185: astore        14
     187: new           #22                 // class org/restcomm/connect/dao/entities/Registration
     190: dup
     191: aload_2
     192: aload_3
     193: aload         4
     195: aload         5
     197: aload         6
     199: aload         7
     201: aload         8
     203: aload         9
     205: aload         11
     207: aload         12
     209: invokevirtual #35                 // Method java/lang/Integer.intValue:()I
     212: aload         10
     214: aload         13
     216: invokevirtual #74                 // Method java/lang/Boolean.booleanValue:()Z
     219: aload         14
     221: invokevirtual #74                 // Method java/lang/Boolean.booleanValue:()Z
     224: invokespecial #75                 // Method org/restcomm/connect/dao/entities/Registration."<init>":(Lorg/restcomm/connect/commons/dao/Sid;Ljava/lang/String;Lorg/joda/time/DateTime;Lorg/joda/time/DateTime;Lorg/joda/time/DateTime;Ljava/lang/String;Ljava/lang/String;Ljava/lang/String;Ljava/lang/String;ILjava/lang/String;ZZ)V
     227: areturn

  static {};
    Code:
       0: ldc_w         #76                 // class org/restcomm/connect/dao/mybatis/MybatisRegistrationsDao
       3: invokestatic  #77                 // Method org/apache/log4j/Logger.getLogger:(Ljava/lang/Class;)Lorg/apache/log4j/Logger;
       6: putstatic     #78                 // Field logger:Lorg/apache/log4j/Logger;
       9: return
}
