Compiled from "ArchiveHandler.java"
public class org.jboss.as.cli.handlers.ArchiveHandler extends org.jboss.as.cli.handlers.BatchModeCommandHandler {
  private final org.jboss.as.cli.impl.ArgumentWithoutValue path;

  private final org.jboss.as.cli.impl.ArgumentWithValue script;

  private final java.util.Random rng;

  public org.jboss.as.cli.handlers.ArchiveHandler(org.jboss.as.cli.CommandContext);
    Code:
       0: aload_0
       1: aload_1
       2: ldc           #1                  // String archive
       4: iconst_1
       5: invokespecial #2                  // Method org/jboss/as/cli/handlers/BatchModeCommandHandler."<init>":(Lorg/jboss/as/cli/CommandContext;Ljava/lang/String;Z)V
       8: aload_0
       9: new           #3                  // class java/util/Random
      12: dup
      13: invokespecial #4                  // Method java/util/Random."<init>":()V
      16: putfield      #5                  // Field rng:Ljava/util/Random;
      19: invokestatic  #6                  // Method org/jboss/as/cli/Util.isWindows:()Z
      22: ifeq          36
      25: new           #7                  // class org/jboss/as/cli/handlers/WindowsFilenameTabCompleter
      28: dup
      29: aload_1
      30: invokespecial #8                  // Method org/jboss/as/cli/handlers/WindowsFilenameTabCompleter."<init>":(Lorg/jboss/as/cli/CommandContext;)V
      33: goto          44
      36: new           #9                  // class org/jboss/as/cli/handlers/DefaultFilenameTabCompleter
      39: dup
      40: aload_1
      41: invokespecial #10                 // Method org/jboss/as/cli/handlers/DefaultFilenameTabCompleter."<init>":(Lorg/jboss/as/cli/CommandContext;)V
      44: astore_2
      45: aload_0
      46: new           #11                 // class org/jboss/as/cli/impl/FileSystemPathArgument
      49: dup
      50: aload_0
      51: aload_2
      52: iconst_0
      53: ldc           #12                 // String --path
      55: invokespecial #13                 // Method org/jboss/as/cli/impl/FileSystemPathArgument."<init>":(Lorg/jboss/as/cli/handlers/CommandHandlerWithArguments;Lorg/jboss/as/cli/handlers/FilenameTabCompleter;ILjava/lang/String;)V
      58: putfield      #14                 // Field path:Lorg/jboss/as/cli/impl/ArgumentWithoutValue;
      61: aload_0
      62: new           #15                 // class org/jboss/as/cli/impl/ArgumentWithValue
      65: dup
      66: aload_0
      67: ldc           #16                 // String --script
      69: invokespecial #17                 // Method org/jboss/as/cli/impl/ArgumentWithValue."<init>":(Lorg/jboss/as/cli/handlers/CommandHandlerWithArguments;Ljava/lang/String;)V
      72: putfield      #18                 // Field script:Lorg/jboss/as/cli/impl/ArgumentWithValue;
      75: aload_0
      76: getfield      #14                 // Field path:Lorg/jboss/as/cli/impl/ArgumentWithoutValue;
      79: aload_0
      80: getfield      #18                 // Field script:Lorg/jboss/as/cli/impl/ArgumentWithValue;
      83: invokevirtual #19                 // Method org/jboss/as/cli/impl/ArgumentWithoutValue.addCantAppearAfter:(Lorg/jboss/as/cli/CommandArgument;)V
      86: return

  public org.jboss.dmr.ModelNode buildRequestWithoutHeaders(org.jboss.as.cli.CommandContext) throws org.jboss.as.cli.CommandFormatException;
    Code:
       0: aload_1
       1: invokeinterface #20,  1           // InterfaceMethod org/jboss/as/cli/CommandContext.getParsedCommandLine:()Lorg/jboss/as/cli/operation/ParsedCommandLine;
       6: astore_2
       7: aload_0
       8: getfield      #14                 // Field path:Lorg/jboss/as/cli/impl/ArgumentWithoutValue;
      11: aload_2
      12: iconst_1
      13: invokevirtual #21                 // Method org/jboss/as/cli/impl/ArgumentWithoutValue.getValue:(Lorg/jboss/as/cli/operation/ParsedCommandLine;Z)Ljava/lang/String;
      16: astore_3
      17: new           #22                 // class java/io/File
      20: dup
      21: aload_3
      22: invokespecial #23                 // Method java/io/File."<init>":(Ljava/lang/String;)V
      25: astore        4
      27: aload         4
      29: invokevirtual #24                 // Method java/io/File.exists:()Z
      32: ifne          71
      35: new           #25                 // class org/jboss/as/cli/operation/OperationFormatException
      38: dup
      39: new           #26                 // class java/lang/StringBuilder
      42: dup
      43: invokespecial #27                 // Method java/lang/StringBuilder."<init>":()V
      46: ldc           #28                 // String Path
      48: invokevirtual #29                 // Method java/lang/StringBuilder.append:(Ljava/lang/String;)Ljava/lang/StringBuilder;
      51: aload         4
      53: invokevirtual #30                 // Method java/io/File.getAbsolutePath:()Ljava/lang/String;
      56: invokevirtual #29                 // Method java/lang/StringBuilder.append:(Ljava/lang/String;)Ljava/lang/StringBuilder;
      59: ldc           #31                 // String  doesn\'t exist.
      61: invokevirtual #29                 // Method java/lang/StringBuilder.append:(Ljava/lang/String;)Ljava/lang/StringBuilder;
      64: invokevirtual #32                 // Method java/lang/StringBuilder.toString:()Ljava/lang/String;
      67: invokespecial #33                 // Method org/jboss/as/cli/operation/OperationFormatException."<init>":(Ljava/lang/String;)V
      70: athrow
      71: aload         4
      73: invokevirtual #34                 // Method java/io/File.isDirectory:()Z
      76: ifeq          110
      79: new           #25                 // class org/jboss/as/cli/operation/OperationFormatException
      82: dup
      83: new           #26                 // class java/lang/StringBuilder
      86: dup
      87: invokespecial #27                 // Method java/lang/StringBuilder."<init>":()V
      90: aload         4
      92: invokevirtual #30                 // Method java/io/File.getAbsolutePath:()Ljava/lang/String;
      95: invokevirtual #29                 // Method java/lang/StringBuilder.append:(Ljava/lang/String;)Ljava/lang/StringBuilder;
      98: ldc           #35                 // String  is a directory.
     100: invokevirtual #29                 // Method java/lang/StringBuilder.append:(Ljava/lang/String;)Ljava/lang/StringBuilder;
     103: invokevirtual #32                 // Method java/lang/StringBuilder.toString:()Ljava/lang/String;
     106: invokespecial #33                 // Method org/jboss/as/cli/operation/OperationFormatException."<init>":(Ljava/lang/String;)V
     109: athrow
     110: aload_0
     111: aload         4
     113: invokespecial #36                 // Method extractArchive:(Ljava/io/File;)Ljava/io/File;
     116: astore        5
     118: goto          159
     121: astore        6
     123: new           #25                 // class org/jboss/as/cli/operation/OperationFormatException
     126: dup
     127: new           #26                 // class java/lang/StringBuilder
     130: dup
     131: invokespecial #27                 // Method java/lang/StringBuilder."<init>":()V
     134: ldc           #38                 // String Unable to extract archive \'
     136: invokevirtual #29                 // Method java/lang/StringBuilder.append:(Ljava/lang/String;)Ljava/lang/StringBuilder;
     139: aload         4
     141: invokevirtual #30                 // Method java/io/File.getAbsolutePath:()Ljava/lang/String;
     144: invokevirtual #29                 // Method java/lang/StringBuilder.append:(Ljava/lang/String;)Ljava/lang/StringBuilder;
     147: ldc           #39                 // String \' to temporary location
     149: invokevirtual #29                 // Method java/lang/StringBuilder.append:(Ljava/lang/String;)Ljava/lang/StringBuilder;
     152: invokevirtual #32                 // Method java/lang/StringBuilder.toString:()Ljava/lang/String;
     155: invokespecial #33                 // Method org/jboss/as/cli/operation/OperationFormatException."<init>":(Ljava/lang/String;)V
     158: athrow
     159: aload_1
     160: aload         5
     162: invokeinterface #40,  2           // InterfaceMethod org/jboss/as/cli/CommandContext.setCurrentDir:(Ljava/io/File;)V
     167: aload_0
     168: aload_1
     169: invokespecial #41                 // Method activateNewBatch:(Lorg/jboss/as/cli/CommandContext;)Ljava/lang/String;
     172: astore        6
     174: aload_0
     175: getfield      #18                 // Field script:Lorg/jboss/as/cli/impl/ArgumentWithValue;
     178: aload_2
     179: invokevirtual #42                 // Method org/jboss/as/cli/impl/ArgumentWithValue.getValue:(Lorg/jboss/as/cli/operation/ParsedCommandLine;)Ljava/lang/String;
     182: astore        7
     184: aload         7
     186: ifnonnull     193
     189: ldc           #43                 // String deploy.scr
     191: astore        7
     193: new           #22                 // class java/io/File
     196: dup
     197: aload_1
     198: invokeinterface #44,  1           // InterfaceMethod org/jboss/as/cli/CommandContext.getCurrentDir:()Ljava/io/File;
     203: aload         7
     205: invokespecial #45                 // Method java/io/File."<init>":(Ljava/io/File;Ljava/lang/String;)V
     208: astore        8
     210: aload         8
     212: invokevirtual #24                 // Method java/io/File.exists:()Z
     215: ifne          251
     218: new           #46                 // class org/jboss/as/cli/CommandFormatException
     221: dup
     222: new           #26                 // class java/lang/StringBuilder
     225: dup
     226: invokespecial #27                 // Method java/lang/StringBuilder."<init>":()V
     229: ldc           #47                 // String ERROR: script
     231: invokevirtual #29                 // Method java/lang/StringBuilder.append:(Ljava/lang/String;)Ljava/lang/StringBuilder;
     234: aload         7
     236: invokevirtual #29                 // Method java/lang/StringBuilder.append:(Ljava/lang/String;)Ljava/lang/StringBuilder;
     239: ldc           #48                 // String \' not found.
     241: invokevirtual #29                 // Method java/lang/StringBuilder.append:(Ljava/lang/String;)Ljava/lang/StringBuilder;
     244: invokevirtual #32                 // Method java/lang/StringBuilder.toString:()Ljava/lang/String;
     247: invokespecial #49                 // Method org/jboss/as/cli/CommandFormatException."<init>":(Ljava/lang/String;)V
     250: athrow
     251: aload_1
     252: new           #26                 // class java/lang/StringBuilder
     255: dup
     256: invokespecial #27                 // Method java/lang/StringBuilder."<init>":()V
     259: ldc           #50                 // String Processing script \'
     261: invokevirtual #29                 // Method java/lang/StringBuilder.append:(Ljava/lang/String;)Ljava/lang/StringBuilder;
     264: aload         7
     266: invokevirtual #29                 // Method java/lang/StringBuilder.append:(Ljava/lang/String;)Ljava/lang/StringBuilder;
     269: ldc           #51                 // String \'.
     271: invokevirtual #29                 // Method java/lang/StringBuilder.append:(Ljava/lang/String;)Ljava/lang/StringBuilder;
     274: invokevirtual #32                 // Method java/lang/StringBuilder.toString:()Ljava/lang/String;
     277: invokeinterface #52,  2           // InterfaceMethod org/jboss/as/cli/CommandContext.printLine:(Ljava/lang/String;)V
     282: new           #53                 // class java/io/BufferedReader
     285: dup
     286: new           #54                 // class java/io/FileReader
     289: dup
     290: aload         8
     292: invokespecial #55                 // Method java/io/FileReader."<init>":(Ljava/io/File;)V
     295: invokespecial #56                 // Method java/io/BufferedReader."<init>":(Ljava/io/Reader;)V
     298: astore        9
     300: aload         9
     302: invokevirtual #57                 // Method java/io/BufferedReader.readLine:()Ljava/lang/String;
     305: astore        10
     307: aload_1
     308: invokeinterface #58,  1           // InterfaceMethod org/jboss/as/cli/CommandContext.isTerminated:()Z
     313: ifne          339
     316: aload         10
     318: ifnull        339
     321: aload_1
     322: aload         10
     324: invokeinterface #59,  2           // InterfaceMethod org/jboss/as/cli/CommandContext.handle:(Ljava/lang/String;)V
     329: aload         9
     331: invokevirtual #57                 // Method java/io/BufferedReader.readLine:()Ljava/lang/String;
     334: astore        10
     336: goto          307
     339: goto          407
     342: astore        9
     344: new           #46                 // class org/jboss/as/cli/CommandFormatException
     347: dup
     348: new           #26                 // class java/lang/StringBuilder
     351: dup
     352: invokespecial #27                 // Method java/lang/StringBuilder."<init>":()V
     355: ldc           #47                 // String ERROR: script
     357: invokevirtual #29                 // Method java/lang/StringBuilder.append:(Ljava/lang/String;)Ljava/lang/StringBuilder;
     360: aload         7
     362: invokevirtual #29                 // Method java/lang/StringBuilder.append:(Ljava/lang/String;)Ljava/lang/StringBuilder;
     365: ldc           #48                 // String \' not found.
     367: invokevirtual #29                 // Method java/lang/StringBuilder.append:(Ljava/lang/String;)Ljava/lang/StringBuilder;
     370: invokevirtual #32                 // Method java/lang/StringBuilder.toString:()Ljava/lang/String;
     373: invokespecial #49                 // Method org/jboss/as/cli/CommandFormatException."<init>":(Ljava/lang/String;)V
     376: athrow
     377: astore        9
     379: new           #46                 // class org/jboss/as/cli/CommandFormatException
     382: dup
     383: aload         9
     385: invokevirtual #61                 // Method java/io/IOException.getMessage:()Ljava/lang/String;
     388: invokespecial #49                 // Method org/jboss/as/cli/CommandFormatException."<init>":(Ljava/lang/String;)V
     391: athrow
     392: astore        9
     394: new           #46                 // class org/jboss/as/cli/CommandFormatException
     397: dup
     398: aload         9
     400: invokevirtual #63                 // Method org/jboss/as/cli/CommandLineException.getMessage:()Ljava/lang/String;
     403: invokespecial #49                 // Method org/jboss/as/cli/CommandFormatException."<init>":(Ljava/lang/String;)V
     406: athrow
     407: aload_1
     408: invokeinterface #64,  1           // InterfaceMethod org/jboss/as/cli/CommandContext.getBatchManager:()Lorg/jboss/as/cli/batch/BatchManager;
     413: invokeinterface #65,  1           // InterfaceMethod org/jboss/as/cli/batch/BatchManager.getActiveBatch:()Lorg/jboss/as/cli/batch/Batch;
     418: invokeinterface #66,  1           // InterfaceMethod org/jboss/as/cli/batch/Batch.toRequest:()Lorg/jboss/dmr/ModelNode;
     423: astore        9
     425: aload         9
     427: astore        10
     429: aload_1
     430: new           #22                 // class java/io/File
     433: dup
     434: ldc           #67                 // String
     436: invokespecial #23                 // Method java/io/File."<init>":(Ljava/lang/String;)V
     439: invokeinterface #40,  2           // InterfaceMethod org/jboss/as/cli/CommandContext.setCurrentDir:(Ljava/io/File;)V
     444: aload_0
     445: aload_1
     446: aload         6
     448: invokespecial #68                 // Method discardBatch:(Lorg/jboss/as/cli/CommandContext;Ljava/lang/String;)V
     451: aload_0
     452: aload         5
     454: invokespecial #69                 // Method recursiveDelete:(Ljava/io/File;)V
     457: aload         10
     459: areturn
     460: astore        11
     462: aload_1
     463: new           #22                 // class java/io/File
     466: dup
     467: ldc           #67                 // String
     469: invokespecial #23                 // Method java/io/File."<init>":(Ljava/lang/String;)V
     472: invokeinterface #40,  2           // InterfaceMethod org/jboss/as/cli/CommandContext.setCurrentDir:(Ljava/io/File;)V
     477: aload_0
     478: aload_1
     479: aload         6
     481: invokespecial #68                 // Method discardBatch:(Lorg/jboss/as/cli/CommandContext;Ljava/lang/String;)V
     484: aload_0
     485: aload         5
     487: invokespecial #69                 // Method recursiveDelete:(Ljava/io/File;)V
     490: aload         11
     492: athrow
    Exception table:
       from    to  target type
         110   118   121   Class java/io/IOException
         282   339   342   Class java/io/FileNotFoundException
         282   339   377   Class java/io/IOException
         282   339   392   Class org/jboss/as/cli/CommandLineException
         174   429   460   any
         460   462   460   any

  protected void doHandle(org.jboss.as.cli.CommandContext) throws org.jboss.as.cli.CommandLineException;
    Code:
       0: aload_0
       1: aload_1
       2: invokevirtual #70                 // Method buildRequest:(Lorg/jboss/as/cli/CommandContext;)Lorg/jboss/dmr/ModelNode;
       5: astore_2
       6: goto          22
       9: astore_3
      10: new           #46                 // class org/jboss/as/cli/CommandFormatException
      13: dup
      14: aload_3
      15: invokevirtual #71                 // Method org/jboss/as/cli/CommandFormatException.getLocalizedMessage:()Ljava/lang/String;
      18: invokespecial #49                 // Method org/jboss/as/cli/CommandFormatException."<init>":(Ljava/lang/String;)V
      21: athrow
      22: aload_2
      23: ifnonnull     36
      26: new           #46                 // class org/jboss/as/cli/CommandFormatException
      29: dup
      30: ldc           #72                 // String Operation request wasn\'t built.
      32: invokespecial #49                 // Method org/jboss/as/cli/CommandFormatException."<init>":(Ljava/lang/String;)V
      35: athrow
      36: aload_1
      37: invokeinterface #73,  1           // InterfaceMethod org/jboss/as/cli/CommandContext.getModelControllerClient:()Lorg/jboss/as/controller/client/ModelControllerClient;
      42: aload_2
      43: invokeinterface #74,  2           // InterfaceMethod org/jboss/as/controller/client/ModelControllerClient.execute:(Lorg/jboss/dmr/ModelNode;)Lorg/jboss/dmr/ModelNode;
      48: astore_3
      49: aload_3
      50: invokestatic  #75                 // Method org/jboss/as/cli/Util.isSuccess:(Lorg/jboss/dmr/ModelNode;)Z
      53: ifeq          67
      56: aload_1
      57: ldc           #76                 // String The archive script executed successfully.
      59: invokeinterface #52,  2           // InterfaceMethod org/jboss/as/cli/CommandContext.printLine:(Ljava/lang/String;)V
      64: goto          97
      67: new           #46                 // class org/jboss/as/cli/CommandFormatException
      70: dup
      71: new           #26                 // class java/lang/StringBuilder
      74: dup
      75: invokespecial #27                 // Method java/lang/StringBuilder."<init>":()V
      78: ldc           #77                 // String Failed to execute archive script:
      80: invokevirtual #29                 // Method java/lang/StringBuilder.append:(Ljava/lang/String;)Ljava/lang/StringBuilder;
      83: aload_3
      84: invokestatic  #78                 // Method org/jboss/as/cli/Util.getFailureDescription:(Lorg/jboss/dmr/ModelNode;)Ljava/lang/String;
      87: invokevirtual #29                 // Method java/lang/StringBuilder.append:(Ljava/lang/String;)Ljava/lang/StringBuilder;
      90: invokevirtual #32                 // Method java/lang/StringBuilder.toString:()Ljava/lang/String;
      93: invokespecial #49                 // Method org/jboss/as/cli/CommandFormatException."<init>":(Ljava/lang/String;)V
      96: athrow
      97: goto          131
     100: astore_3
     101: new           #46                 // class org/jboss/as/cli/CommandFormatException
     104: dup
     105: new           #26                 // class java/lang/StringBuilder
     108: dup
     109: invokespecial #27                 // Method java/lang/StringBuilder."<init>":()V
     112: ldc           #77                 // String Failed to execute archive script:
     114: invokevirtual #29                 // Method java/lang/StringBuilder.append:(Ljava/lang/String;)Ljava/lang/StringBuilder;
     117: aload_3
     118: invokevirtual #80                 // Method java/lang/Exception.getLocalizedMessage:()Ljava/lang/String;
     121: invokevirtual #29                 // Method java/lang/StringBuilder.append:(Ljava/lang/String;)Ljava/lang/StringBuilder;
     124: invokevirtual #32                 // Method java/lang/StringBuilder.toString:()Ljava/lang/String;
     127: invokespecial #49                 // Method org/jboss/as/cli/CommandFormatException."<init>":(Ljava/lang/String;)V
     130: athrow
     131: return
    Exception table:
       from    to  target type
           0     6     9   Class org/jboss/as/cli/CommandFormatException
          36    97   100   Class java/lang/Exception

  private java.io.File extractArchive(java.io.File) throws java.io.IOException;
    Code:
       0: new           #22                 // class java/io/File
       3: dup
       4: ldc           #81                 // String java.io.tmpdir
       6: invokestatic  #82                 // Method java/lang/System.getProperty:(Ljava/lang/String;)Ljava/lang/String;
       9: invokespecial #23                 // Method java/io/File."<init>":(Ljava/lang/String;)V
      12: astore_2
      13: new           #22                 // class java/io/File
      16: dup
      17: aload_2
      18: new           #26                 // class java/lang/StringBuilder
      21: dup
      22: invokespecial #27                 // Method java/lang/StringBuilder."<init>":()V
      25: ldc           #83                 // String cli-
      27: invokevirtual #29                 // Method java/lang/StringBuilder.append:(Ljava/lang/String;)Ljava/lang/StringBuilder;
      30: aload_0
      31: getfield      #5                  // Field rng:Ljava/util/Random;
      34: invokevirtual #84                 // Method java/util/Random.nextLong:()J
      37: invokestatic  #85                 // Method java/lang/Long.toHexString:(J)Ljava/lang/String;
      40: invokevirtual #29                 // Method java/lang/StringBuilder.append:(Ljava/lang/String;)Ljava/lang/StringBuilder;
      43: invokevirtual #32                 // Method java/lang/StringBuilder.toString:()Ljava/lang/String;
      46: invokespecial #45                 // Method java/io/File."<init>":(Ljava/io/File;Ljava/lang/String;)V
      49: astore_3
      50: aload_3
      51: invokevirtual #86                 // Method java/io/File.mkdir:()Z
      54: pop
      55: new           #87                 // class java/util/jar/JarFile
      58: dup
      59: aload_1
      60: invokespecial #88                 // Method java/util/jar/JarFile."<init>":(Ljava/io/File;)V
      63: astore        4
      65: aload         4
      67: invokevirtual #89                 // Method java/util/jar/JarFile.entries:()Ljava/util/Enumeration;
      70: astore        5
      72: aload         5
      74: invokeinterface #90,  1           // InterfaceMethod java/util/Enumeration.hasMoreElements:()Z
      79: ifeq          225
      82: aload         5
      84: invokeinterface #91,  1           // InterfaceMethod java/util/Enumeration.nextElement:()Ljava/lang/Object;
      89: checkcast     #92                 // class java/util/jar/JarEntry
      92: astore        6
      94: new           #22                 // class java/io/File
      97: dup
      98: aload_3
      99: aload         6
     101: invokevirtual #93                 // Method java/util/jar/JarEntry.getName:()Ljava/lang/String;
     104: invokespecial #45                 // Method java/io/File."<init>":(Ljava/io/File;Ljava/lang/String;)V
     107: astore        7
     109: aload         6
     111: invokevirtual #94                 // Method java/util/jar/JarEntry.isDirectory:()Z
     114: ifeq          126
     117: aload         7
     119: invokevirtual #86                 // Method java/io/File.mkdir:()Z
     122: pop
     123: goto          72
     126: aconst_null
     127: astore        8
     129: aconst_null
     130: astore        9
     132: ldc           #95                 // int 65536
     134: istore        10
     136: iload         10
     138: newarray       byte
     140: astore        11
     142: aload         4
     144: aload         6
     146: invokevirtual #96                 // Method java/util/jar/JarFile.getInputStream:(Ljava/util/zip/ZipEntry;)Ljava/io/InputStream;
     149: astore        8
     151: new           #97                 // class java/io/FileOutputStream
     154: dup
     155: aload         7
     157: invokespecial #98                 // Method java/io/FileOutputStream."<init>":(Ljava/io/File;)V
     160: astore        9
     162: aload         8
     164: aload         11
     166: invokevirtual #99                 // Method java/io/InputStream.read:([B)I
     169: dup
     170: istore        12
     172: iconst_m1
     173: if_icmple     189
     176: aload         9
     178: aload         11
     180: iconst_0
     181: iload         12
     183: invokevirtual #100                // Method java/io/FileOutputStream.write:([BII)V
     186: goto          162
     189: aload         9
     191: invokevirtual #101                // Method java/io/FileOutputStream.flush:()V
     194: aload         8
     196: invokestatic  #102                // Method org/jboss/as/protocol/StreamUtils.safeClose:(Ljava/io/Closeable;)V
     199: aload         9
     201: invokestatic  #102                // Method org/jboss/as/protocol/StreamUtils.safeClose:(Ljava/io/Closeable;)V
     204: goto          222
     207: astore        13
     209: aload         8
     211: invokestatic  #102                // Method org/jboss/as/protocol/StreamUtils.safeClose:(Ljava/io/Closeable;)V
     214: aload         9
     216: invokestatic  #102                // Method org/jboss/as/protocol/StreamUtils.safeClose:(Ljava/io/Closeable;)V
     219: aload         13
     221: athrow
     222: goto          72
     225: aload_3
     226: areturn
    Exception table:
       from    to  target type
         132   194   207   any
         207   209   207   any

  private java.lang.String activateNewBatch(org.jboss.as.cli.CommandContext);
    Code:
       0: aconst_null
       1: astore_2
       2: aload_1
       3: invokeinterface #64,  1           // InterfaceMethod org/jboss/as/cli/CommandContext.getBatchManager:()Lorg/jboss/as/cli/batch/BatchManager;
       8: astore_3
       9: aload_3
      10: invokeinterface #103,  1          // InterfaceMethod org/jboss/as/cli/batch/BatchManager.isBatchActive:()Z
      15: ifeq          48
      18: new           #26                 // class java/lang/StringBuilder
      21: dup
      22: invokespecial #27                 // Method java/lang/StringBuilder."<init>":()V
      25: ldc           #104                // String batch
      27: invokevirtual #29                 // Method java/lang/StringBuilder.append:(Ljava/lang/String;)Ljava/lang/StringBuilder;
      30: invokestatic  #105                // Method java/lang/System.currentTimeMillis:()J
      33: invokevirtual #106                // Method java/lang/StringBuilder.append:(J)Ljava/lang/StringBuilder;
      36: invokevirtual #32                 // Method java/lang/StringBuilder.toString:()Ljava/lang/String;
      39: astore_2
      40: aload_3
      41: aload_2
      42: invokeinterface #107,  2          // InterfaceMethod org/jboss/as/cli/batch/BatchManager.holdbackActiveBatch:(Ljava/lang/String;)Z
      47: pop
      48: aload_3
      49: invokeinterface #108,  1          // InterfaceMethod org/jboss/as/cli/batch/BatchManager.activateNewBatch:()Z
      54: pop
      55: aload_2
      56: areturn

  private void discardBatch(org.jboss.as.cli.CommandContext, java.lang.String);
    Code:
       0: aload_1
       1: invokeinterface #64,  1           // InterfaceMethod org/jboss/as/cli/CommandContext.getBatchManager:()Lorg/jboss/as/cli/batch/BatchManager;
       6: astore_3
       7: aload_3
       8: invokeinterface #109,  1          // InterfaceMethod org/jboss/as/cli/batch/BatchManager.discardActiveBatch:()Z
      13: pop
      14: aload_2
      15: ifnull        26
      18: aload_3
      19: aload_2
      20: invokeinterface #110,  2          // InterfaceMethod org/jboss/as/cli/batch/BatchManager.activateHeldbackBatch:(Ljava/lang/String;)Z
      25: pop
      26: return

  private void recursiveDelete(java.io.File);
    Code:
       0: aload_1
       1: invokevirtual #34                 // Method java/io/File.isDirectory:()Z
       4: ifeq          49
       7: aload_1
       8: invokevirtual #111                // Method java/io/File.listFiles:()[Ljava/io/File;
      11: astore_2
      12: aload_2
      13: astore_3
      14: aload_3
      15: arraylength
      16: istore        4
      18: iconst_0
      19: istore        5
      21: iload         5
      23: iload         4
      25: if_icmpge     46
      28: aload_3
      29: iload         5
      31: aaload
      32: astore        6
      34: aload_0
      35: aload         6
      37: invokespecial #69                 // Method recursiveDelete:(Ljava/io/File;)V
      40: iinc          5, 1
      43: goto          21
      46: goto          54
      49: aload_1
      50: invokevirtual #112                // Method java/io/File.delete:()Z
      53: pop
      54: return
}
