Compiled from "ConnectHandler.java"
public class org.jboss.as.cli.handlers.ConnectHandler extends org.jboss.as.cli.handlers.CommandHandlerWithHelp {
  private final org.jboss.as.cli.impl.ArgumentWithValue arg;

  public org.jboss.as.cli.handlers.ConnectHandler();
    Code:
       0: aload_0
       1: ldc           #1                  // String connect
       3: invokespecial #2                  // Method "<init>":(Ljava/lang/String;)V
       6: return

  public org.jboss.as.cli.handlers.ConnectHandler(java.lang.String);
    Code:
       0: aload_0
       1: aload_1
       2: invokespecial #3                  // Method org/jboss/as/cli/handlers/CommandHandlerWithHelp."<init>":(Ljava/lang/String;)V
       5: aload_0
       6: new           #4                  // class org/jboss/as/cli/impl/ArgumentWithValue
       9: dup
      10: aload_0
      11: iconst_0
      12: ldc           #5                  // String --controller
      14: invokespecial #6                  // Method org/jboss/as/cli/impl/ArgumentWithValue."<init>":(Lorg/jboss/as/cli/handlers/CommandHandlerWithArguments;ILjava/lang/String;)V
      17: putfield      #7                  // Field arg:Lorg/jboss/as/cli/impl/ArgumentWithValue;
      20: return

  public boolean hasArgument(org.jboss.as.cli.CommandContext, int);
    Code:
       0: iload_2
       1: iconst_1
       2: if_icmpgt     9
       5: iconst_1
       6: goto          10
       9: iconst_0
      10: ireturn

  protected void recognizeArguments(org.jboss.as.cli.CommandContext) throws org.jboss.as.cli.CommandFormatException;
    Code:
       0: aload_1
       1: invokeinterface #8,  1            // InterfaceMethod org/jboss/as/cli/CommandContext.getParsedCommandLine:()Lorg/jboss/as/cli/operation/ParsedCommandLine;
       6: astore_2
       7: aload_2
       8: invokeinterface #9,  1            // InterfaceMethod org/jboss/as/cli/operation/ParsedCommandLine.getOtherProperties:()Ljava/util/List;
      13: invokeinterface #10,  1           // InterfaceMethod java/util/List.size:()I
      18: iconst_1
      19: if_icmple     54
      22: new           #11                 // class org/jboss/as/cli/CommandFormatException
      25: dup
      26: new           #12                 // class java/lang/StringBuilder
      29: dup
      30: invokespecial #13                 // Method java/lang/StringBuilder."<init>":()V
      33: ldc           #14                 // String The command accepts only one argument but received:
      35: invokevirtual #15                 // Method java/lang/StringBuilder.append:(Ljava/lang/String;)Ljava/lang/StringBuilder;
      38: aload_2
      39: invokeinterface #9,  1            // InterfaceMethod org/jboss/as/cli/operation/ParsedCommandLine.getOtherProperties:()Ljava/util/List;
      44: invokevirtual #16                 // Method java/lang/StringBuilder.append:(Ljava/lang/Object;)Ljava/lang/StringBuilder;
      47: invokevirtual #17                 // Method java/lang/StringBuilder.toString:()Ljava/lang/String;
      50: invokespecial #18                 // Method org/jboss/as/cli/CommandFormatException."<init>":(Ljava/lang/String;)V
      53: athrow
      54: return

  protected void doHandle(org.jboss.as.cli.CommandContext) throws org.jboss.as.cli.CommandLineException;
    Code:
       0: aload_1
       1: invokeinterface #8,  1            // InterfaceMethod org/jboss/as/cli/CommandContext.getParsedCommandLine:()Lorg/jboss/as/cli/operation/ParsedCommandLine;
       6: astore_2
       7: aload_0
       8: getfield      #7                  // Field arg:Lorg/jboss/as/cli/impl/ArgumentWithValue;
      11: aload_2
      12: invokevirtual #19                 // Method org/jboss/as/cli/impl/ArgumentWithValue.getValue:(Lorg/jboss/as/cli/operation/ParsedCommandLine;)Ljava/lang/String;
      15: astore_3
      16: aload_2
      17: invokeinterface #9,  1            // InterfaceMethod org/jboss/as/cli/operation/ParsedCommandLine.getOtherProperties:()Ljava/util/List;
      22: astore        4
      24: aload         4
      26: invokeinterface #20,  1           // InterfaceMethod java/util/List.isEmpty:()Z
      31: ifne          73
      34: aload         4
      36: invokeinterface #10,  1           // InterfaceMethod java/util/List.size:()I
      41: iconst_1
      42: if_icmpeq     73
      45: new           #11                 // class org/jboss/as/cli/CommandFormatException
      48: dup
      49: new           #12                 // class java/lang/StringBuilder
      52: dup
      53: invokespecial #13                 // Method java/lang/StringBuilder."<init>":()V
      56: ldc           #21                 // String The command expects only one argument but got
      58: invokevirtual #15                 // Method java/lang/StringBuilder.append:(Ljava/lang/String;)Ljava/lang/StringBuilder;
      61: aload         4
      63: invokevirtual #16                 // Method java/lang/StringBuilder.append:(Ljava/lang/Object;)Ljava/lang/StringBuilder;
      66: invokevirtual #17                 // Method java/lang/StringBuilder.toString:()Ljava/lang/String;
      69: invokespecial #18                 // Method org/jboss/as/cli/CommandFormatException."<init>":(Ljava/lang/String;)V
      72: athrow
      73: aload_1
      74: aload_3
      75: invokeinterface #22,  2           // InterfaceMethod org/jboss/as/cli/CommandContext.connectController:(Ljava/lang/String;)V
      80: return
}
