Compiled from "DeploymentType.java"
public final class org.jboss.as.ee.structure.DeploymentType extends java.lang.Enum<org.jboss.as.ee.structure.DeploymentType> {
  public static final org.jboss.as.ee.structure.DeploymentType EAR;

  public static final org.jboss.as.ee.structure.DeploymentType WAR;

  public static final org.jboss.as.ee.structure.DeploymentType EJB_JAR;

  public static final org.jboss.as.ee.structure.DeploymentType APPLICATION_CLIENT;

  private static final org.jboss.as.ee.structure.DeploymentType[] $VALUES;

  public static org.jboss.as.ee.structure.DeploymentType[] values();
    Code:
       0: getstatic     #1                  // Field $VALUES:[Lorg/jboss/as/ee/structure/DeploymentType;
       3: invokevirtual #2                  // Method "[Lorg/jboss/as/ee/structure/DeploymentType;".clone:()Ljava/lang/Object;
       6: checkcast     #3                  // class "[Lorg/jboss/as/ee/structure/DeploymentType;"
       9: areturn

  public static org.jboss.as.ee.structure.DeploymentType valueOf(java.lang.String);
    Code:
       0: ldc           #4                  // class org/jboss/as/ee/structure/DeploymentType
       2: aload_0
       3: invokestatic  #5                  // Method java/lang/Enum.valueOf:(Ljava/lang/Class;Ljava/lang/String;)Ljava/lang/Enum;
       6: checkcast     #4                  // class org/jboss/as/ee/structure/DeploymentType
       9: areturn

  private org.jboss.as.ee.structure.DeploymentType();
    Code:
       0: aload_0
       1: aload_1
       2: iload_2
       3: invokespecial #6                  // Method java/lang/Enum."<init>":(Ljava/lang/String;I)V
       6: return

  static {};
    Code:
       0: new           #4                  // class org/jboss/as/ee/structure/DeploymentType
       3: dup
       4: ldc           #7                  // String EAR
       6: iconst_0
       7: invokespecial #8                  // Method "<init>":(Ljava/lang/String;I)V
      10: putstatic     #9                  // Field EAR:Lorg/jboss/as/ee/structure/DeploymentType;
      13: new           #4                  // class org/jboss/as/ee/structure/DeploymentType
      16: dup
      17: ldc           #10                 // String WAR
      19: iconst_1
      20: invokespecial #8                  // Method "<init>":(Ljava/lang/String;I)V
      23: putstatic     #11                 // Field WAR:Lorg/jboss/as/ee/structure/DeploymentType;
      26: new           #4                  // class org/jboss/as/ee/structure/DeploymentType
      29: dup
      30: ldc           #12                 // String EJB_JAR
      32: iconst_2
      33: invokespecial #8                  // Method "<init>":(Ljava/lang/String;I)V
      36: putstatic     #13                 // Field EJB_JAR:Lorg/jboss/as/ee/structure/DeploymentType;
      39: new           #4                  // class org/jboss/as/ee/structure/DeploymentType
      42: dup
      43: ldc           #14                 // String APPLICATION_CLIENT
      45: iconst_3
      46: invokespecial #8                  // Method "<init>":(Ljava/lang/String;I)V
      49: putstatic     #15                 // Field APPLICATION_CLIENT:Lorg/jboss/as/ee/structure/DeploymentType;
      52: iconst_4
      53: anewarray     #4                  // class org/jboss/as/ee/structure/DeploymentType
      56: dup
      57: iconst_0
      58: getstatic     #9                  // Field EAR:Lorg/jboss/as/ee/structure/DeploymentType;
      61: aastore
      62: dup
      63: iconst_1
      64: getstatic     #11                 // Field WAR:Lorg/jboss/as/ee/structure/DeploymentType;
      67: aastore
      68: dup
      69: iconst_2
      70: getstatic     #13                 // Field EJB_JAR:Lorg/jboss/as/ee/structure/DeploymentType;
      73: aastore
      74: dup
      75: iconst_3
      76: getstatic     #15                 // Field APPLICATION_CLIENT:Lorg/jboss/as/ee/structure/DeploymentType;
      79: aastore
      80: putstatic     #1                  // Field $VALUES:[Lorg/jboss/as/ee/structure/DeploymentType;
      83: return
}
