Compiled from "EarMetaDataParsingProcessor.java"
public class org.jboss.as.ee.structure.EarMetaDataParsingProcessor implements org.jboss.as.server.deployment.DeploymentUnitProcessor {
  private static final java.lang.String APPLICATION_XML;

  private static final java.lang.String JBOSS_APP_XML;

  public org.jboss.as.ee.structure.EarMetaDataParsingProcessor();
    Code:
       0: aload_0
       1: invokespecial #1                  // Method java/lang/Object."<init>":()V
       4: return

  public void deploy(org.jboss.as.server.deployment.DeploymentPhaseContext) throws org.jboss.as.server.deployment.DeploymentUnitProcessingException;
    Code:
       0: aload_1
       1: invokeinterface #2,  1            // InterfaceMethod org/jboss/as/server/deployment/DeploymentPhaseContext.getDeploymentUnit:()Lorg/jboss/as/server/deployment/DeploymentUnit;
       6: astore_2
       7: getstatic     #3                  // Field org/jboss/as/ee/structure/DeploymentType.EAR:Lorg/jboss/as/ee/structure/DeploymentType;
      10: aload_2
      11: invokestatic  #4                  // Method org/jboss/as/ee/structure/DeploymentTypeMarker.isType:(Lorg/jboss/as/ee/structure/DeploymentType;Lorg/jboss/as/server/deployment/DeploymentUnit;)Z
      14: ifne          18
      17: return
      18: aload_2
      19: getstatic     #5                  // Field org/jboss/as/server/deployment/Attachments.DEPLOYMENT_ROOT:Lorg/jboss/as/server/deployment/AttachmentKey;
      22: invokeinterface #6,  2            // InterfaceMethod org/jboss/as/server/deployment/DeploymentUnit.getAttachment:(Lorg/jboss/as/server/deployment/AttachmentKey;)Ljava/lang/Object;
      27: checkcast     #7                  // class org/jboss/as/server/deployment/module/ResourceRoot
      30: astore_3
      31: aload_3
      32: invokevirtual #8                  // Method org/jboss/as/server/deployment/module/ResourceRoot.getRoot:()Lorg/jboss/vfs/VirtualFile;
      35: astore        4
      37: aload_0
      38: aload         4
      40: aload_2
      41: invokestatic  #9                  // Method org/jboss/as/ee/structure/SpecDescriptorPropertyReplacement.propertyReplacer:(Lorg/jboss/as/server/deployment/DeploymentUnit;)Lorg/jboss/metadata/property/PropertyReplacer;
      44: invokespecial #10                 // Method handleSpecMetadata:(Lorg/jboss/vfs/VirtualFile;Lorg/jboss/metadata/property/PropertyReplacer;)Lorg/jboss/metadata/ear/spec/EarMetaData;
      47: astore        5
      49: aload_0
      50: aload         4
      52: aload_2
      53: invokestatic  #11                 // Method org/jboss/as/ee/structure/JBossDescriptorPropertyReplacement.propertyReplacer:(Lorg/jboss/as/server/deployment/DeploymentUnit;)Lorg/jboss/metadata/property/PropertyReplacer;
      56: aload_2
      57: invokespecial #12                 // Method handleJbossMetadata:(Lorg/jboss/vfs/VirtualFile;Lorg/jboss/metadata/property/PropertyReplacer;Lorg/jboss/as/server/deployment/DeploymentUnit;)Lorg/jboss/metadata/ear/jboss/JBossAppMetaData;
      60: astore        6
      62: aload         5
      64: ifnonnull     73
      67: aload         6
      69: ifnonnull     73
      72: return
      73: aload         6
      75: ifnull        101
      78: aload         6
      80: invokevirtual #13                 // Method org/jboss/metadata/ear/jboss/JBossAppMetaData.getDistinctName:()Ljava/lang/String;
      83: ifnull        101
      86: aload_2
      87: getstatic     #14                 // Field org/jboss/as/ee/structure/Attachments.DISTINCT_NAME:Lorg/jboss/as/server/deployment/AttachmentKey;
      90: aload         6
      92: invokevirtual #13                 // Method org/jboss/metadata/ear/jboss/JBossAppMetaData.getDistinctName:()Ljava/lang/String;
      95: invokeinterface #15,  3           // InterfaceMethod org/jboss/as/server/deployment/DeploymentUnit.putAttachment:(Lorg/jboss/as/server/deployment/AttachmentKey;Ljava/lang/Object;)Ljava/lang/Object;
     100: pop
     101: aload         5
     103: ifnull        123
     106: new           #16                 // class org/jboss/metadata/ear/jboss/JBossAppMetaData
     109: dup
     110: aload         5
     112: invokevirtual #17                 // Method org/jboss/metadata/ear/spec/EarMetaData.getEarVersion:()Lorg/jboss/metadata/ear/spec/EarVersion;
     115: invokespecial #18                 // Method org/jboss/metadata/ear/jboss/JBossAppMetaData."<init>":(Lorg/jboss/metadata/ear/spec/EarVersion;)V
     118: astore        7
     120: goto          132
     123: new           #16                 // class org/jboss/metadata/ear/jboss/JBossAppMetaData
     126: dup
     127: invokespecial #19                 // Method org/jboss/metadata/ear/jboss/JBossAppMetaData."<init>":()V
     130: astore        7
     132: aload         7
     134: aload         6
     136: aload         5
     138: invokestatic  #20                 // Method org/jboss/metadata/merge/JBossAppMetaDataMerger.merge:(Lorg/jboss/metadata/ear/jboss/JBossAppMetaData;Lorg/jboss/metadata/ear/jboss/JBossAppMetaData;Lorg/jboss/metadata/ear/spec/EarMetaData;)V
     141: aload_2
     142: getstatic     #21                 // Field org/jboss/as/ee/structure/Attachments.EAR_METADATA:Lorg/jboss/as/server/deployment/AttachmentKey;
     145: aload         7
     147: invokeinterface #15,  3           // InterfaceMethod org/jboss/as/server/deployment/DeploymentUnit.putAttachment:(Lorg/jboss/as/server/deployment/AttachmentKey;Ljava/lang/Object;)Ljava/lang/Object;
     152: pop
     153: aload         7
     155: invokevirtual #22                 // Method org/jboss/metadata/ear/jboss/JBossAppMetaData.getEarEnvironmentRefsGroup:()Lorg/jboss/metadata/ear/spec/EarEnvironmentRefsGroupMetaData;
     158: ifnull        189
     161: new           #23                 // class org/jboss/as/ee/component/DeploymentDescriptorEnvironment
     164: dup
     165: ldc           #24                 // String java:app/env/
     167: aload         7
     169: invokevirtual #22                 // Method org/jboss/metadata/ear/jboss/JBossAppMetaData.getEarEnvironmentRefsGroup:()Lorg/jboss/metadata/ear/spec/EarEnvironmentRefsGroupMetaData;
     172: invokespecial #25                 // Method org/jboss/as/ee/component/DeploymentDescriptorEnvironment."<init>":(Ljava/lang/String;Lorg/jboss/metadata/javaee/spec/RemoteEnvironment;)V
     175: astore        8
     177: aload_2
     178: getstatic     #26                 // Field org/jboss/as/ee/component/Attachments.MODULE_DEPLOYMENT_DESCRIPTOR_ENVIRONMENT:Lorg/jboss/as/server/deployment/AttachmentKey;
     181: aload         8
     183: invokeinterface #15,  3           // InterfaceMethod org/jboss/as/server/deployment/DeploymentUnit.putAttachment:(Lorg/jboss/as/server/deployment/AttachmentKey;Ljava/lang/Object;)Ljava/lang/Object;
     188: pop
     189: return

  private org.jboss.metadata.ear.spec.EarMetaData handleSpecMetadata(org.jboss.vfs.VirtualFile, org.jboss.metadata.property.PropertyReplacer) throws org.jboss.as.server.deployment.DeploymentUnitProcessingException;
    Code:
       0: aload_1
       1: ldc           #28                 // String META-INF/application.xml
       3: invokevirtual #29                 // Method org/jboss/vfs/VirtualFile.getChild:(Ljava/lang/String;)Lorg/jboss/vfs/VirtualFile;
       6: astore_3
       7: aload_3
       8: invokevirtual #30                 // Method org/jboss/vfs/VirtualFile.exists:()Z
      11: ifne          16
      14: aconst_null
      15: areturn
      16: aconst_null
      17: astore        4
      19: aload_3
      20: invokevirtual #31                 // Method org/jboss/vfs/VirtualFile.openStream:()Ljava/io/InputStream;
      23: astore        4
      25: invokestatic  #32                 // Method javax/xml/stream/XMLInputFactory.newInstance:()Ljavax/xml/stream/XMLInputFactory;
      28: astore        5
      30: aload         5
      32: invokestatic  #33                 // Method org/jboss/metadata/parser/util/NoopXMLResolver.create:()Ljavax/xml/stream/XMLResolver;
      35: invokevirtual #34                 // Method javax/xml/stream/XMLInputFactory.setXMLResolver:(Ljavax/xml/stream/XMLResolver;)V
      38: aload         5
      40: aload         4
      42: invokevirtual #35                 // Method javax/xml/stream/XMLInputFactory.createXMLStreamReader:(Ljava/io/InputStream;)Ljavax/xml/stream/XMLStreamReader;
      45: astore        6
      47: getstatic     #36                 // Field org/jboss/metadata/parser/spec/EarMetaDataParser.INSTANCE:Lorg/jboss/metadata/parser/spec/EarMetaDataParser;
      50: aload         6
      52: aload_2
      53: invokevirtual #37                 // Method org/jboss/metadata/parser/spec/EarMetaDataParser.parse:(Ljavax/xml/stream/XMLStreamReader;Lorg/jboss/metadata/property/PropertyReplacer;)Lorg/jboss/metadata/ear/spec/EarMetaData;
      56: astore        7
      58: aload         4
      60: invokestatic  #38                 // Method org/jboss/vfs/VFSUtils.safeClose:(Ljava/io/Closeable;)V
      63: aload         7
      65: areturn
      66: astore        5
      68: getstatic     #40                 // Field org/jboss/as/ee/logging/EeLogger.ROOT_LOGGER:Lorg/jboss/as/ee/logging/EeLogger;
      71: aload         5
      73: aload_3
      74: invokeinterface #41,  3           // InterfaceMethod org/jboss/as/ee/logging/EeLogger.failedToParse:(Ljava/lang/Throwable;Lorg/jboss/vfs/VirtualFile;)Lorg/jboss/as/server/deployment/DeploymentUnitProcessingException;
      79: athrow
      80: astore        8
      82: aload         4
      84: invokestatic  #38                 // Method org/jboss/vfs/VFSUtils.safeClose:(Ljava/io/Closeable;)V
      87: aload         8
      89: athrow
    Exception table:
       from    to  target type
          19    58    66   Class java/lang/Exception
          19    58    80   any
          66    82    80   any

  private org.jboss.metadata.ear.jboss.JBossAppMetaData handleJbossMetadata(org.jboss.vfs.VirtualFile, org.jboss.metadata.property.PropertyReplacer, org.jboss.as.server.deployment.DeploymentUnit) throws org.jboss.as.server.deployment.DeploymentUnitProcessingException;
    Code:
       0: aload_1
       1: ldc           #42                 // String META-INF/jboss-app.xml
       3: invokevirtual #29                 // Method org/jboss/vfs/VirtualFile.getChild:(Ljava/lang/String;)Lorg/jboss/vfs/VirtualFile;
       6: astore        4
       8: aload         4
      10: invokevirtual #30                 // Method org/jboss/vfs/VirtualFile.exists:()Z
      13: ifne          29
      16: aload_3
      17: getstatic     #43                 // Field org/jboss/as/ee/structure/AppJBossAllParser.ATTACHMENT_KEY:Lorg/jboss/as/server/deployment/AttachmentKey;
      20: invokeinterface #6,  2            // InterfaceMethod org/jboss/as/server/deployment/DeploymentUnit.getAttachment:(Lorg/jboss/as/server/deployment/AttachmentKey;)Ljava/lang/Object;
      25: checkcast     #16                 // class org/jboss/metadata/ear/jboss/JBossAppMetaData
      28: areturn
      29: aconst_null
      30: astore        5
      32: aload         4
      34: invokevirtual #31                 // Method org/jboss/vfs/VirtualFile.openStream:()Ljava/io/InputStream;
      37: astore        5
      39: invokestatic  #32                 // Method javax/xml/stream/XMLInputFactory.newInstance:()Ljavax/xml/stream/XMLInputFactory;
      42: astore        6
      44: aload         6
      46: invokestatic  #33                 // Method org/jboss/metadata/parser/util/NoopXMLResolver.create:()Ljavax/xml/stream/XMLResolver;
      49: invokevirtual #34                 // Method javax/xml/stream/XMLInputFactory.setXMLResolver:(Ljavax/xml/stream/XMLResolver;)V
      52: aload         6
      54: aload         5
      56: invokevirtual #35                 // Method javax/xml/stream/XMLInputFactory.createXMLStreamReader:(Ljava/io/InputStream;)Ljavax/xml/stream/XMLStreamReader;
      59: astore        7
      61: getstatic     #44                 // Field org/jboss/metadata/parser/jboss/JBossAppMetaDataParser.INSTANCE:Lorg/jboss/metadata/parser/jboss/JBossAppMetaDataParser;
      64: aload         7
      66: aload_2
      67: invokevirtual #45                 // Method org/jboss/metadata/parser/jboss/JBossAppMetaDataParser.parse:(Ljavax/xml/stream/XMLStreamReader;Lorg/jboss/metadata/property/PropertyReplacer;)Lorg/jboss/metadata/ear/jboss/JBossAppMetaData;
      70: astore        8
      72: aload         5
      74: invokestatic  #38                 // Method org/jboss/vfs/VFSUtils.safeClose:(Ljava/io/Closeable;)V
      77: aload         8
      79: areturn
      80: astore        6
      82: getstatic     #40                 // Field org/jboss/as/ee/logging/EeLogger.ROOT_LOGGER:Lorg/jboss/as/ee/logging/EeLogger;
      85: aload         6
      87: aload         4
      89: invokeinterface #41,  3           // InterfaceMethod org/jboss/as/ee/logging/EeLogger.failedToParse:(Ljava/lang/Throwable;Lorg/jboss/vfs/VirtualFile;)Lorg/jboss/as/server/deployment/DeploymentUnitProcessingException;
      94: athrow
      95: astore        9
      97: aload         5
      99: invokestatic  #38                 // Method org/jboss/vfs/VFSUtils.safeClose:(Ljava/io/Closeable;)V
     102: aload         9
     104: athrow
    Exception table:
       from    to  target type
          32    72    80   Class java/lang/Exception
          32    72    95   any
          80    97    95   any

  public void undeploy(org.jboss.as.server.deployment.DeploymentUnit);
    Code:
       0: aload_1
       1: getstatic     #21                 // Field org/jboss/as/ee/structure/Attachments.EAR_METADATA:Lorg/jboss/as/server/deployment/AttachmentKey;
       4: invokeinterface #46,  2           // InterfaceMethod org/jboss/as/server/deployment/DeploymentUnit.removeAttachment:(Lorg/jboss/as/server/deployment/AttachmentKey;)Ljava/lang/Object;
       9: pop
      10: return
}
