Compiled from "TemplateResolvers.java"
abstract class org.apache.logging.log4j.layout.template.json.resolver.TemplateResolvers$UnresolvableTemplateResolver implements org.apache.logging.log4j.layout.template.json.resolver.TemplateResolver<java.lang.Object> {
  private org.apache.logging.log4j.layout.template.json.resolver.TemplateResolvers$UnresolvableTemplateResolver();
    Code:
       0: aload_0
       1: invokespecial #2                  // Method java/lang/Object."<init>":()V
       4: return

  public final boolean isResolvable();
    Code:
       0: iconst_0
       1: ireturn

  public final boolean isResolvable(java.lang.Object);
    Code:
       0: iconst_0
       1: ireturn

  org.apache.logging.log4j.layout.template.json.resolver.TemplateResolvers$UnresolvableTemplateResolver(org.apache.logging.log4j.layout.template.json.resolver.TemplateResolvers$1);
    Code:
       0: aload_0
       1: invokespecial #1                  // Method "<init>":()V
       4: return
}
