Compiled from "NettyTransport.scala"
public final class akka.remote.transport.netty.NettyTransportSettings$ {
  public static final akka.remote.transport.netty.NettyTransportSettings$ MODULE$;

  public static {};
    Code:
       0: new           #2                  // class akka/remote/transport/netty/NettyTransportSettings$
       3: invokespecial #12                 // Method "<init>":()V
       6: return

  private akka.remote.transport.netty.NettyTransportSettings$();
    Code:
       0: aload_0
       1: invokespecial #13                 // Method java/lang/Object."<init>":()V
       4: aload_0
       5: putstatic     #15                 // Field MODULE$:Lakka/remote/transport/netty/NettyTransportSettings$;
       8: return
}
