Compiled from "NettySSLSupport.scala"
public final class akka.remote.transport.netty.NettySSLSupport$ {
  public static final akka.remote.transport.netty.NettySSLSupport$ MODULE$;

  public static {};
    Code:
       0: new           #2                  // class akka/remote/transport/netty/NettySSLSupport$
       3: invokespecial #12                 // Method "<init>":()V
       6: return

  public org.jboss.netty.handler.ssl.SslHandler apply(akka.remote.transport.netty.SSLSettings, akka.event.LoggingAdapter, boolean);
    Code:
       0: iload_3
       1: ifeq          13
       4: aload_0
       5: aload_1
       6: aload_2
       7: invokevirtual #18                 // Method initializeClientSSL:(Lakka/remote/transport/netty/SSLSettings;Lakka/event/LoggingAdapter;)Lorg/jboss/netty/handler/ssl/SslHandler;
      10: goto          19
      13: aload_0
      14: aload_1
      15: aload_2
      16: invokevirtual #21                 // Method initializeServerSSL:(Lakka/remote/transport/netty/SSLSettings;Lakka/event/LoggingAdapter;)Lorg/jboss/netty/handler/ssl/SslHandler;
      19: areturn

  public java.security.SecureRandom initializeCustomSecureRandom(scala.Option<java.lang.String>, akka.event.LoggingAdapter);
    Code:
       0: iconst_0
       1: istore        4
       3: aconst_null
       4: astore        5
       6: aload_1
       7: astore        6
       9: aload         6
      11: instanceof    #34                 // class scala/Some
      14: ifeq          100
      17: iconst_1
      18: istore        4
      20: aload         6
      22: checkcast     #34                 // class scala/Some
      25: astore        5
      27: aload         5
      29: invokevirtual #38                 // Method scala/Some.x:()Ljava/lang/Object;
      32: checkcast     #40                 // class java/lang/String
      35: astore        7
      37: ldc           #42                 // String AES128CounterSecureRNG
      39: aload         7
      41: invokevirtual #46                 // Method java/lang/Object.equals:(Ljava/lang/Object;)Z
      44: ifeq          53
      47: iconst_1
      48: istore        8
      50: goto          72
      53: ldc           #48                 // String AES256CounterSecureRNG
      55: aload         7
      57: invokevirtual #46                 // Method java/lang/Object.equals:(Ljava/lang/Object;)Z
      60: ifeq          69
      63: iconst_1
      64: istore        8
      66: goto          72
      69: iconst_0
      70: istore        8
      72: iload         8
      74: ifeq          100
      77: aload_2
      78: ldc           #50                 // String SSL random number generator set to: {}
      80: aload         7
      82: invokeinterface #56,  3           // InterfaceMethod akka/event/LoggingAdapter.debug:(Ljava/lang/String;Ljava/lang/Object;)V
      87: aload         7
      89: getstatic     #61                 // Field akka/remote/security/provider/AkkaProvider$.MODULE$:Lakka/remote/security/provider/AkkaProvider$;
      92: invokestatic  #67                 // Method java/security/SecureRandom.getInstance:(Ljava/lang/String;Ljava/security/Provider;)Ljava/security/SecureRandom;
      95: astore        9
      97: goto          334
     100: iload         4
     102: ifeq          178
     105: aload         5
     107: invokevirtual #38                 // Method scala/Some.x:()Ljava/lang/Object;
     110: checkcast     #40                 // class java/lang/String
     113: astore        10
     115: ldc           #69                 // String AES128CounterInetRNG
     117: aload         10
     119: invokevirtual #46                 // Method java/lang/Object.equals:(Ljava/lang/Object;)Z
     122: ifeq          131
     125: iconst_1
     126: istore        11
     128: goto          150
     131: ldc           #71                 // String AES256CounterInetRNG
     133: aload         10
     135: invokevirtual #46                 // Method java/lang/Object.equals:(Ljava/lang/Object;)Z
     138: ifeq          147
     141: iconst_1
     142: istore        11
     144: goto          150
     147: iconst_0
     148: istore        11
     150: iload         11
     152: ifeq          178
     155: aload_2
     156: ldc           #73                 // String SSL random number generator {} is deprecated, use AES128CounterSecureRNG or AES256CounterSecureRNG instead
     158: aload         10
     160: invokeinterface #76,  3           // InterfaceMethod akka/event/LoggingAdapter.warning:(Ljava/lang/String;Ljava/lang/Object;)V
     165: aload         10
     167: getstatic     #61                 // Field akka/remote/security/provider/AkkaProvider$.MODULE$:Lakka/remote/security/provider/AkkaProvider$;
     170: invokestatic  #67                 // Method java/security/SecureRandom.getInstance:(Ljava/lang/String;Ljava/security/Provider;)Ljava/security/SecureRandom;
     173: astore        9
     175: goto          334
     178: iload         4
     180: ifeq          269
     183: aload         5
     185: invokevirtual #38                 // Method scala/Some.x:()Ljava/lang/Object;
     188: checkcast     #40                 // class java/lang/String
     191: astore        12
     193: ldc           #78                 // String SHA1PRNG
     195: aload         12
     197: invokevirtual #46                 // Method java/lang/Object.equals:(Ljava/lang/Object;)Z
     200: ifeq          209
     203: iconst_1
     204: istore        13
     206: goto          228
     209: ldc           #80                 // String NativePRNG
     211: aload         12
     213: invokevirtual #46                 // Method java/lang/Object.equals:(Ljava/lang/Object;)Z
     216: ifeq          225
     219: iconst_1
     220: istore        13
     222: goto          228
     225: iconst_0
     226: istore        13
     228: iload         13
     230: ifeq          269
     233: aload_2
     234: new           #82                 // class scala/collection/mutable/StringBuilder
     237: dup
     238: invokespecial #83                 // Method scala/collection/mutable/StringBuilder."<init>":()V
     241: ldc           #85                 // String SSL random number generator set to:
     243: invokevirtual #89                 // Method scala/collection/mutable/StringBuilder.append:(Ljava/lang/Object;)Lscala/collection/mutable/StringBuilder;
     246: aload         12
     248: invokevirtual #89                 // Method scala/collection/mutable/StringBuilder.append:(Ljava/lang/Object;)Lscala/collection/mutable/StringBuilder;
     251: invokevirtual #93                 // Method scala/collection/mutable/StringBuilder.toString:()Ljava/lang/String;
     254: invokeinterface #96,  2           // InterfaceMethod akka/event/LoggingAdapter.debug:(Ljava/lang/String;)V
     259: aload         12
     261: invokestatic  #99                 // Method java/security/SecureRandom.getInstance:(Ljava/lang/String;)Ljava/security/SecureRandom;
     264: astore        9
     266: goto          334
     269: iload         4
     271: ifeq          306
     274: aload         5
     276: invokevirtual #38                 // Method scala/Some.x:()Ljava/lang/Object;
     279: checkcast     #40                 // class java/lang/String
     282: astore        14
     284: aload_2
     285: ldc           #101                // String Unknown SSLRandomNumberGenerator [{}] falling back to SecureRandom
     287: aload         14
     289: invokeinterface #76,  3           // InterfaceMethod akka/event/LoggingAdapter.warning:(Ljava/lang/String;Ljava/lang/Object;)V
     294: new           #63                 // class java/security/SecureRandom
     297: dup
     298: invokespecial #102                // Method java/security/SecureRandom."<init>":()V
     301: astore        9
     303: goto          334
     306: getstatic     #107                // Field scala/None$.MODULE$:Lscala/None$;
     309: aload         6
     311: invokevirtual #46                 // Method java/lang/Object.equals:(Ljava/lang/Object;)Z
     314: ifeq          344
     317: aload_2
     318: ldc           #109                // String SSLRandomNumberGenerator not specified, falling back to SecureRandom
     320: invokeinterface #96,  2           // InterfaceMethod akka/event/LoggingAdapter.debug:(Ljava/lang/String;)V
     325: new           #63                 // class java/security/SecureRandom
     328: dup
     329: invokespecial #102                // Method java/security/SecureRandom."<init>":()V
     332: astore        9
     334: aload         9
     336: astore_3
     337: aload_3
     338: invokevirtual #113                // Method java/security/SecureRandom.nextInt:()I
     341: pop
     342: aload_3
     343: areturn
     344: new           #115                // class scala/MatchError
     347: dup
     348: aload         6
     350: invokespecial #118                // Method scala/MatchError."<init>":(Ljava/lang/Object;)V
     353: athrow

  public org.jboss.netty.handler.ssl.SslHandler initializeClientSSL(akka.remote.transport.netty.SSLSettings, akka.event.LoggingAdapter);
    Code:
       0: aload_2
       1: ldc           #130                // String Client SSL is enabled, initialising ...
       3: invokeinterface #96,  2           // InterfaceMethod akka/event/LoggingAdapter.debug:(Ljava/lang/String;)V
       8: new           #132                // class scala/Tuple3
      11: dup
      12: aload_1
      13: invokevirtual #138                // Method akka/remote/transport/netty/SSLSettings.SSLTrustStore:()Lscala/Option;
      16: aload_1
      17: invokevirtual #141                // Method akka/remote/transport/netty/SSLSettings.SSLTrustStorePassword:()Lscala/Option;
      20: aload_1
      21: invokevirtual #144                // Method akka/remote/transport/netty/SSLSettings.SSLProtocol:()Lscala/Option;
      24: invokespecial #147                // Method scala/Tuple3."<init>":(Ljava/lang/Object;Ljava/lang/Object;Ljava/lang/Object;)V
      27: astore        4
      29: aload         4
      31: ifnull        346
      34: aload         4
      36: invokevirtual #150                // Method scala/Tuple3._1:()Ljava/lang/Object;
      39: checkcast     #128                // class scala/Option
      42: astore        5
      44: aload         4
      46: invokevirtual #153                // Method scala/Tuple3._2:()Ljava/lang/Object;
      49: checkcast     #128                // class scala/Option
      52: astore        6
      54: aload         4
      56: invokevirtual #156                // Method scala/Tuple3._3:()Ljava/lang/Object;
      59: checkcast     #128                // class scala/Option
      62: astore        7
      64: aload         5
      66: instanceof    #34                 // class scala/Some
      69: ifeq          346
      72: aload         5
      74: checkcast     #34                 // class scala/Some
      77: astore        8
      79: aload         8
      81: invokevirtual #38                 // Method scala/Some.x:()Ljava/lang/Object;
      84: checkcast     #40                 // class java/lang/String
      87: astore        9
      89: aload         6
      91: instanceof    #34                 // class scala/Some
      94: ifeq          346
      97: aload         6
      99: checkcast     #34                 // class scala/Some
     102: astore        10
     104: aload         10
     106: invokevirtual #38                 // Method scala/Some.x:()Ljava/lang/Object;
     109: checkcast     #40                 // class java/lang/String
     112: astore        11
     114: aload         7
     116: instanceof    #34                 // class scala/Some
     119: ifeq          346
     122: aload         7
     124: checkcast     #34                 // class scala/Some
     127: astore        12
     129: aload         12
     131: invokevirtual #38                 // Method scala/Some.x:()Ljava/lang/Object;
     134: checkcast     #40                 // class java/lang/String
     137: astore        13
     139: aload_0
     140: aload_1
     141: aload_2
     142: aload         9
     144: aload         11
     146: aload         13
     148: invokespecial #160                // Method constructClientContext$1:(Lakka/remote/transport/netty/SSLSettings;Lakka/event/LoggingAdapter;Ljava/lang/String;Ljava/lang/String;Ljava/lang/String;)Lscala/Option;
     151: astore        14
     153: aload         14
     155: astore_3
     156: aload_3
     157: instanceof    #34                 // class scala/Some
     160: ifeq          270
     163: aload_3
     164: checkcast     #34                 // class scala/Some
     167: astore        18
     169: aload         18
     171: invokevirtual #38                 // Method scala/Some.x:()Ljava/lang/Object;
     174: checkcast     #162                // class javax/net/ssl/SSLContext
     177: astore        19
     179: aload_2
     180: ldc           #164                // String Using client SSL context to create SSLEngine ...
     182: invokeinterface #96,  2           // InterfaceMethod akka/event/LoggingAdapter.debug:(Ljava/lang/String;)V
     187: new           #30                 // class org/jboss/netty/handler/ssl/SslHandler
     190: dup
     191: aload         19
     193: invokevirtual #168                // Method javax/net/ssl/SSLContext.createSSLEngine:()Ljavax/net/ssl/SSLEngine;
     196: astore        21
     198: aload         21
     200: iconst_1
     201: invokevirtual #174                // Method javax/net/ssl/SSLEngine.setUseClientMode:(Z)V
     204: aload         21
     206: aload_1
     207: invokevirtual #178                // Method akka/remote/transport/netty/SSLSettings.SSLEnabledAlgorithms:()Lscala/collection/immutable/Set;
     210: getstatic     #183                // Field scala/reflect/ClassTag$.MODULE$:Lscala/reflect/ClassTag$;
     213: ldc           #40                 // class java/lang/String
     215: invokevirtual #186                // Method scala/reflect/ClassTag$.apply:(Ljava/lang/Class;)Lscala/reflect/ClassTag;
     218: invokeinterface #192,  2          // InterfaceMethod scala/collection/immutable/Set.toArray:(Lscala/reflect/ClassTag;)Ljava/lang/Object;
     223: checkcast     #194                // class "[Ljava/lang/String;"
     226: invokevirtual #198                // Method javax/net/ssl/SSLEngine.setEnabledCipherSuites:([Ljava/lang/String;)V
     229: aload         21
     231: getstatic     #203                // Field scala/Option$.MODULE$:Lscala/Option$;
     234: aload_1
     235: invokevirtual #144                // Method akka/remote/transport/netty/SSLSettings.SSLProtocol:()Lscala/Option;
     238: invokevirtual #207                // Method scala/Option$.option2Iterable:(Lscala/Option;)Lscala/collection/Iterable;
     241: getstatic     #183                // Field scala/reflect/ClassTag$.MODULE$:Lscala/reflect/ClassTag$;
     244: ldc           #40                 // class java/lang/String
     246: invokevirtual #186                // Method scala/reflect/ClassTag$.apply:(Ljava/lang/Class;)Lscala/reflect/ClassTag;
     249: invokeinterface #210,  2          // InterfaceMethod scala/collection/Iterable.toArray:(Lscala/reflect/ClassTag;)Ljava/lang/Object;
     254: checkcast     #194                // class "[Ljava/lang/String;"
     257: invokevirtual #213                // Method javax/net/ssl/SSLEngine.setEnabledProtocols:([Ljava/lang/String;)V
     260: aload         21
     262: invokespecial #216                // Method org/jboss/netty/handler/ssl/SslHandler."<init>":(Ljavax/net/ssl/SSLEngine;)V
     265: astore        20
     267: aload         20
     269: areturn
     270: getstatic     #107                // Field scala/None$.MODULE$:Lscala/None$;
     273: aload_3
     274: invokevirtual #46                 // Method java/lang/Object.equals:(Ljava/lang/Object;)Z
     277: ifeq          337
     280: new           #218                // class java/security/GeneralSecurityException
     283: dup
     284: new           #220                // class scala/collection/immutable/StringOps
     287: dup
     288: getstatic     #225                // Field scala/Predef$.MODULE$:Lscala/Predef$;
     291: ldc           #227                // String Failed to initialize client SSL because SSL context could not be found.\" +\n              \"Make sure your settings are correct: [trust-store: %s] [trust-store-password: %s] [protocol: %s]
     293: invokevirtual #231                // Method scala/Predef$.augmentString:(Ljava/lang/String;)Ljava/lang/String;
     296: invokespecial #233                // Method scala/collection/immutable/StringOps."<init>":(Ljava/lang/String;)V
     299: getstatic     #225                // Field scala/Predef$.MODULE$:Lscala/Predef$;
     302: iconst_3
     303: anewarray     #4                  // class java/lang/Object
     306: dup
     307: iconst_0
     308: aload_1
     309: invokevirtual #138                // Method akka/remote/transport/netty/SSLSettings.SSLTrustStore:()Lscala/Option;
     312: aastore
     313: dup
     314: iconst_1
     315: aload_1
     316: invokevirtual #141                // Method akka/remote/transport/netty/SSLSettings.SSLTrustStorePassword:()Lscala/Option;
     319: aastore
     320: dup
     321: iconst_2
     322: aload_1
     323: invokevirtual #144                // Method akka/remote/transport/netty/SSLSettings.SSLProtocol:()Lscala/Option;
     326: aastore
     327: invokevirtual #237                // Method scala/Predef$.genericWrapArray:(Ljava/lang/Object;)Lscala/collection/mutable/WrappedArray;
     330: invokevirtual #241                // Method scala/collection/immutable/StringOps.format:(Lscala/collection/Seq;)Ljava/lang/String;
     333: invokespecial #242                // Method java/security/GeneralSecurityException."<init>":(Ljava/lang/String;)V
     336: athrow
     337: new           #115                // class scala/MatchError
     340: dup
     341: aload_3
     342: invokespecial #118                // Method scala/MatchError."<init>":(Ljava/lang/Object;)V
     345: athrow
     346: aload         4
     348: ifnull        432
     351: aload         4
     353: invokevirtual #150                // Method scala/Tuple3._1:()Ljava/lang/Object;
     356: checkcast     #128                // class scala/Option
     359: astore        15
     361: aload         4
     363: invokevirtual #153                // Method scala/Tuple3._2:()Ljava/lang/Object;
     366: checkcast     #128                // class scala/Option
     369: astore        16
     371: aload         4
     373: invokevirtual #156                // Method scala/Tuple3._3:()Ljava/lang/Object;
     376: checkcast     #128                // class scala/Option
     379: astore        17
     381: new           #218                // class java/security/GeneralSecurityException
     384: dup
     385: new           #220                // class scala/collection/immutable/StringOps
     388: dup
     389: getstatic     #225                // Field scala/Predef$.MODULE$:Lscala/Predef$;
     392: ldc           #244                // String One or several SSL trust store settings are missing: [trust-store: %s] [trust-store-password: %s] [protocol: %s]
     394: invokevirtual #231                // Method scala/Predef$.augmentString:(Ljava/lang/String;)Ljava/lang/String;
     397: invokespecial #233                // Method scala/collection/immutable/StringOps."<init>":(Ljava/lang/String;)V
     400: getstatic     #225                // Field scala/Predef$.MODULE$:Lscala/Predef$;
     403: iconst_3
     404: anewarray     #4                  // class java/lang/Object
     407: dup
     408: iconst_0
     409: aload         15
     411: aastore
     412: dup
     413: iconst_1
     414: aload         16
     416: aastore
     417: dup
     418: iconst_2
     419: aload         17
     421: aastore
     422: invokevirtual #237                // Method scala/Predef$.genericWrapArray:(Ljava/lang/Object;)Lscala/collection/mutable/WrappedArray;
     425: invokevirtual #241                // Method scala/collection/immutable/StringOps.format:(Lscala/collection/Seq;)Ljava/lang/String;
     428: invokespecial #242                // Method java/security/GeneralSecurityException."<init>":(Ljava/lang/String;)V
     431: athrow
     432: new           #115                // class scala/MatchError
     435: dup
     436: aload         4
     438: invokespecial #118                // Method scala/MatchError."<init>":(Ljava/lang/Object;)V
     441: athrow

  public org.jboss.netty.handler.ssl.SslHandler initializeServerSSL(akka.remote.transport.netty.SSLSettings, akka.event.LoggingAdapter);
    Code:
       0: aload_2
       1: ldc           #253                // String Server SSL is enabled, initialising ...
       3: invokeinterface #96,  2           // InterfaceMethod akka/event/LoggingAdapter.debug:(Ljava/lang/String;)V
       8: new           #255                // class scala/Tuple4
      11: dup
      12: aload_1
      13: invokevirtual #258                // Method akka/remote/transport/netty/SSLSettings.SSLKeyStore:()Lscala/Option;
      16: aload_1
      17: invokevirtual #261                // Method akka/remote/transport/netty/SSLSettings.SSLKeyStorePassword:()Lscala/Option;
      20: aload_1
      21: invokevirtual #264                // Method akka/remote/transport/netty/SSLSettings.SSLKeyPassword:()Lscala/Option;
      24: aload_1
      25: invokevirtual #144                // Method akka/remote/transport/netty/SSLSettings.SSLProtocol:()Lscala/Option;
      28: invokespecial #267                // Method scala/Tuple4."<init>":(Ljava/lang/Object;Ljava/lang/Object;Ljava/lang/Object;Ljava/lang/Object;)V
      31: astore        4
      33: aload         4
      35: ifnull        358
      38: aload         4
      40: invokevirtual #268                // Method scala/Tuple4._1:()Ljava/lang/Object;
      43: checkcast     #128                // class scala/Option
      46: astore        5
      48: aload         4
      50: invokevirtual #269                // Method scala/Tuple4._2:()Ljava/lang/Object;
      53: checkcast     #128                // class scala/Option
      56: astore        6
      58: aload         4
      60: invokevirtual #270                // Method scala/Tuple4._3:()Ljava/lang/Object;
      63: checkcast     #128                // class scala/Option
      66: astore        7
      68: aload         4
      70: invokevirtual #273                // Method scala/Tuple4._4:()Ljava/lang/Object;
      73: checkcast     #128                // class scala/Option
      76: astore        8
      78: aload         5
      80: instanceof    #34                 // class scala/Some
      83: ifeq          358
      86: aload         5
      88: checkcast     #34                 // class scala/Some
      91: astore        9
      93: aload         9
      95: invokevirtual #38                 // Method scala/Some.x:()Ljava/lang/Object;
      98: checkcast     #40                 // class java/lang/String
     101: astore        10
     103: aload         6
     105: instanceof    #34                 // class scala/Some
     108: ifeq          358
     111: aload         6
     113: checkcast     #34                 // class scala/Some
     116: astore        11
     118: aload         11
     120: invokevirtual #38                 // Method scala/Some.x:()Ljava/lang/Object;
     123: checkcast     #40                 // class java/lang/String
     126: astore        12
     128: aload         7
     130: instanceof    #34                 // class scala/Some
     133: ifeq          358
     136: aload         7
     138: checkcast     #34                 // class scala/Some
     141: astore        13
     143: aload         13
     145: invokevirtual #38                 // Method scala/Some.x:()Ljava/lang/Object;
     148: checkcast     #40                 // class java/lang/String
     151: astore        14
     153: aload         8
     155: instanceof    #34                 // class scala/Some
     158: ifeq          358
     161: aload         8
     163: checkcast     #34                 // class scala/Some
     166: astore        15
     168: aload         15
     170: invokevirtual #38                 // Method scala/Some.x:()Ljava/lang/Object;
     173: checkcast     #40                 // class java/lang/String
     176: astore        16
     178: aload_0
     179: aload_1
     180: aload_2
     181: aload         10
     183: aload         12
     185: aload         14
     187: aload         16
     189: invokespecial #277                // Method constructServerContext$1:(Lakka/remote/transport/netty/SSLSettings;Lakka/event/LoggingAdapter;Ljava/lang/String;Ljava/lang/String;Ljava/lang/String;Ljava/lang/String;)Lscala/Option;
     192: astore        17
     194: aload         17
     196: astore_3
     197: aload_3
     198: instanceof    #34                 // class scala/Some
     201: ifeq          281
     204: aload_3
     205: checkcast     #34                 // class scala/Some
     208: astore        22
     210: aload         22
     212: invokevirtual #38                 // Method scala/Some.x:()Ljava/lang/Object;
     215: checkcast     #162                // class javax/net/ssl/SSLContext
     218: astore        23
     220: aload_2
     221: ldc_w         #279                // String Using server SSL context to create SSLEngine ...
     224: invokeinterface #96,  2           // InterfaceMethod akka/event/LoggingAdapter.debug:(Ljava/lang/String;)V
     229: aload         23
     231: invokevirtual #168                // Method javax/net/ssl/SSLContext.createSSLEngine:()Ljavax/net/ssl/SSLEngine;
     234: astore        25
     236: aload         25
     238: iconst_0
     239: invokevirtual #174                // Method javax/net/ssl/SSLEngine.setUseClientMode:(Z)V
     242: aload         25
     244: aload_1
     245: invokevirtual #178                // Method akka/remote/transport/netty/SSLSettings.SSLEnabledAlgorithms:()Lscala/collection/immutable/Set;
     248: getstatic     #183                // Field scala/reflect/ClassTag$.MODULE$:Lscala/reflect/ClassTag$;
     251: ldc           #40                 // class java/lang/String
     253: invokevirtual #186                // Method scala/reflect/ClassTag$.apply:(Ljava/lang/Class;)Lscala/reflect/ClassTag;
     256: invokeinterface #192,  2          // InterfaceMethod scala/collection/immutable/Set.toArray:(Lscala/reflect/ClassTag;)Ljava/lang/Object;
     261: checkcast     #194                // class "[Ljava/lang/String;"
     264: invokevirtual #198                // Method javax/net/ssl/SSLEngine.setEnabledCipherSuites:([Ljava/lang/String;)V
     267: new           #30                 // class org/jboss/netty/handler/ssl/SslHandler
     270: dup
     271: aload         25
     273: invokespecial #216                // Method org/jboss/netty/handler/ssl/SslHandler."<init>":(Ljavax/net/ssl/SSLEngine;)V
     276: astore        24
     278: aload         24
     280: areturn
     281: getstatic     #107                // Field scala/None$.MODULE$:Lscala/None$;
     284: aload_3
     285: invokevirtual #46                 // Method java/lang/Object.equals:(Ljava/lang/Object;)Z
     288: ifeq          349
     291: new           #218                // class java/security/GeneralSecurityException
     294: dup
     295: new           #220                // class scala/collection/immutable/StringOps
     298: dup
     299: getstatic     #225                // Field scala/Predef$.MODULE$:Lscala/Predef$;
     302: ldc_w         #281                // String Failed to initialize server SSL because SSL context could not be found.\n           Make sure your settings are correct: [key-store: %s] [key-store-password: %s] [protocol: %s]
     305: invokevirtual #231                // Method scala/Predef$.augmentString:(Ljava/lang/String;)Ljava/lang/String;
     308: invokespecial #233                // Method scala/collection/immutable/StringOps."<init>":(Ljava/lang/String;)V
     311: getstatic     #225                // Field scala/Predef$.MODULE$:Lscala/Predef$;
     314: iconst_3
     315: anewarray     #4                  // class java/lang/Object
     318: dup
     319: iconst_0
     320: aload_1
     321: invokevirtual #258                // Method akka/remote/transport/netty/SSLSettings.SSLKeyStore:()Lscala/Option;
     324: aastore
     325: dup
     326: iconst_1
     327: aload_1
     328: invokevirtual #261                // Method akka/remote/transport/netty/SSLSettings.SSLKeyStorePassword:()Lscala/Option;
     331: aastore
     332: dup
     333: iconst_2
     334: aload_1
     335: invokevirtual #144                // Method akka/remote/transport/netty/SSLSettings.SSLProtocol:()Lscala/Option;
     338: aastore
     339: invokevirtual #237                // Method scala/Predef$.genericWrapArray:(Ljava/lang/Object;)Lscala/collection/mutable/WrappedArray;
     342: invokevirtual #241                // Method scala/collection/immutable/StringOps.format:(Lscala/collection/Seq;)Ljava/lang/String;
     345: invokespecial #242                // Method java/security/GeneralSecurityException."<init>":(Ljava/lang/String;)V
     348: athrow
     349: new           #115                // class scala/MatchError
     352: dup
     353: aload_3
     354: invokespecial #118                // Method scala/MatchError."<init>":(Ljava/lang/Object;)V
     357: athrow
     358: aload         4
     360: ifnull        494
     363: aload         4
     365: invokevirtual #268                // Method scala/Tuple4._1:()Ljava/lang/Object;
     368: checkcast     #128                // class scala/Option
     371: astore        18
     373: aload         4
     375: invokevirtual #269                // Method scala/Tuple4._2:()Ljava/lang/Object;
     378: checkcast     #128                // class scala/Option
     381: astore        19
     383: aload         4
     385: invokevirtual #270                // Method scala/Tuple4._3:()Ljava/lang/Object;
     388: checkcast     #128                // class scala/Option
     391: astore        20
     393: aload         4
     395: invokevirtual #273                // Method scala/Tuple4._4:()Ljava/lang/Object;
     398: checkcast     #128                // class scala/Option
     401: astore        21
     403: new           #218                // class java/security/GeneralSecurityException
     406: dup
     407: new           #283                // class scala/StringContext
     410: dup
     411: getstatic     #225                // Field scala/Predef$.MODULE$:Lscala/Predef$;
     414: iconst_5
     415: anewarray     #40                 // class java/lang/String
     418: dup
     419: iconst_0
     420: ldc_w         #285                // String SSL key store settings went missing. [key-store:
     423: aastore
     424: dup
     425: iconst_1
     426: ldc_w         #287                // String ] [key-store-password:
     429: aastore
     430: dup
     431: iconst_2
     432: ldc_w         #289                // String ] [key-password:
     435: aastore
     436: dup
     437: iconst_3
     438: ldc_w         #291                // String ] [protocol:
     441: aastore
     442: dup
     443: iconst_4
     444: ldc_w         #293                // String ]
     447: aastore
     448: checkcast     #295                // class "[Ljava/lang/Object;"
     451: invokevirtual #299                // Method scala/Predef$.wrapRefArray:([Ljava/lang/Object;)Lscala/collection/mutable/WrappedArray;
     454: invokespecial #302                // Method scala/StringContext."<init>":(Lscala/collection/Seq;)V
     457: getstatic     #225                // Field scala/Predef$.MODULE$:Lscala/Predef$;
     460: iconst_4
     461: anewarray     #4                  // class java/lang/Object
     464: dup
     465: iconst_0
     466: aload         18
     468: aastore
     469: dup
     470: iconst_1
     471: aload         19
     473: aastore
     474: dup
     475: iconst_2
     476: aload         20
     478: aastore
     479: dup
     480: iconst_3
     481: aload         21
     483: aastore
     484: invokevirtual #237                // Method scala/Predef$.genericWrapArray:(Ljava/lang/Object;)Lscala/collection/mutable/WrappedArray;
     487: invokevirtual #304                // Method scala/StringContext.s:(Lscala/collection/Seq;)Ljava/lang/String;
     490: invokespecial #242                // Method java/security/GeneralSecurityException."<init>":(Ljava/lang/String;)V
     493: athrow
     494: new           #115                // class scala/MatchError
     497: dup
     498: aload         4
     500: invokespecial #118                // Method scala/MatchError."<init>":(Ljava/lang/Object;)V
     503: athrow

  private final scala.Option constructClientContext$1(akka.remote.transport.netty.SSLSettings, akka.event.LoggingAdapter, java.lang.String, java.lang.String, java.lang.String);
    Code:
       0: aload_0
       1: aload_1
       2: invokevirtual #314                // Method akka/remote/transport/netty/SSLSettings.SSLRandomNumberGenerator:()Lscala/Option;
       5: aload_2
       6: invokevirtual #316                // Method initializeCustomSecureRandom:(Lscala/Option;Lakka/event/LoggingAdapter;)Ljava/security/SecureRandom;
       9: astore        9
      11: invokestatic  #321                // Method javax/net/ssl/TrustManagerFactory.getDefaultAlgorithm:()Ljava/lang/String;
      14: invokestatic  #324                // Method javax/net/ssl/TrustManagerFactory.getInstance:(Ljava/lang/String;)Ljavax/net/ssl/TrustManagerFactory;
      17: astore        11
      19: aload         11
      21: invokestatic  #329                // Method java/security/KeyStore.getDefaultType:()Ljava/lang/String;
      24: invokestatic  #332                // Method java/security/KeyStore.getInstance:(Ljava/lang/String;)Ljava/security/KeyStore;
      27: astore        12
      29: new           #334                // class java/io/FileInputStream
      32: dup
      33: aload_3
      34: invokespecial #335                // Method java/io/FileInputStream."<init>":(Ljava/lang/String;)V
      37: astore        13
      39: aload         12
      41: aload         13
      43: aload         4
      45: invokevirtual #339                // Method java/lang/String.toCharArray:()[C
      48: invokevirtual #343                // Method java/security/KeyStore.load:(Ljava/io/InputStream;[C)V
      51: getstatic     #348                // Field scala/util/Try$.MODULE$:Lscala/util/Try$;
      54: new           #350                // class akka/remote/transport/netty/NettySSLSupport$$anonfun$1
      57: dup
      58: aload         13
      60: invokespecial #353                // Method akka/remote/transport/netty/NettySSLSupport$$anonfun$1."<init>":(Ljava/io/FileInputStream;)V
      63: invokevirtual #356                // Method scala/util/Try$.apply:(Lscala/Function0;)Lscala/util/Try;
      66: pop
      67: aload         12
      69: invokevirtual #360                // Method javax/net/ssl/TrustManagerFactory.init:(Ljava/security/KeyStore;)V
      72: aload         11
      74: invokevirtual #364                // Method javax/net/ssl/TrustManagerFactory.getTrustManagers:()[Ljavax/net/ssl/TrustManager;
      77: astore        10
      79: getstatic     #203                // Field scala/Option$.MODULE$:Lscala/Option$;
      82: aload         5
      84: invokestatic  #367                // Method javax/net/ssl/SSLContext.getInstance:(Ljava/lang/String;)Ljavax/net/ssl/SSLContext;
      87: invokevirtual #370                // Method scala/Option$.apply:(Ljava/lang/Object;)Lscala/Option;
      90: new           #372                // class akka/remote/transport/netty/NettySSLSupport$$anonfun$constructClientContext$1$1
      93: dup
      94: aload         9
      96: aload         10
      98: invokespecial #375                // Method akka/remote/transport/netty/NettySSLSupport$$anonfun$constructClientContext$1$1."<init>":(Ljava/security/SecureRandom;[Ljavax/net/ssl/TrustManager;)V
     101: invokevirtual #379                // Method scala/Option.map:(Lscala/Function1;)Lscala/Option;
     104: areturn
     105: astore        14
     107: getstatic     #348                // Field scala/util/Try$.MODULE$:Lscala/util/Try$;
     110: new           #350                // class akka/remote/transport/netty/NettySSLSupport$$anonfun$1
     113: dup
     114: aload         13
     116: invokespecial #353                // Method akka/remote/transport/netty/NettySSLSupport$$anonfun$1."<init>":(Ljava/io/FileInputStream;)V
     119: invokevirtual #356                // Method scala/util/Try$.apply:(Lscala/Function0;)Lscala/util/Try;
     122: pop
     123: aload         14
     125: athrow
     126: astore        6
     128: new           #381                // class akka/remote/RemoteTransportException
     131: dup
     132: ldc_w         #383                // String Client SSL connection could not be established because SSL context could not be constructed
     135: aload         6
     137: invokespecial #386                // Method akka/remote/RemoteTransportException."<init>":(Ljava/lang/String;Ljava/lang/Throwable;)V
     140: athrow
     141: astore        7
     143: new           #381                // class akka/remote/RemoteTransportException
     146: dup
     147: new           #82                 // class scala/collection/mutable/StringBuilder
     150: dup
     151: invokespecial #83                 // Method scala/collection/mutable/StringBuilder."<init>":()V
     154: ldc_w         #388                // String Client SSL connection could not be established because:
     157: invokevirtual #89                 // Method scala/collection/mutable/StringBuilder.append:(Ljava/lang/Object;)Lscala/collection/mutable/StringBuilder;
     160: aload         7
     162: invokevirtual #391                // Method java/io/IOException.getMessage:()Ljava/lang/String;
     165: invokevirtual #89                 // Method scala/collection/mutable/StringBuilder.append:(Ljava/lang/Object;)Lscala/collection/mutable/StringBuilder;
     168: invokevirtual #93                 // Method scala/collection/mutable/StringBuilder.toString:()Ljava/lang/String;
     171: aload         7
     173: invokespecial #386                // Method akka/remote/RemoteTransportException."<init>":(Ljava/lang/String;Ljava/lang/Throwable;)V
     176: athrow
     177: astore        8
     179: new           #381                // class akka/remote/RemoteTransportException
     182: dup
     183: ldc_w         #393                // String Client SSL connection could not be established because trust store could not be loaded
     186: aload         8
     188: invokespecial #386                // Method akka/remote/RemoteTransportException."<init>":(Ljava/lang/String;Ljava/lang/Throwable;)V
     191: athrow
    Exception table:
       from    to  target type
          39    51   105   any
         105   126   177   Class java/io/FileNotFoundException
           0   104   177   Class java/io/FileNotFoundException
         105   126   141   Class java/io/IOException
           0   104   141   Class java/io/IOException
         105   126   126   Class java/security/GeneralSecurityException
           0   104   126   Class java/security/GeneralSecurityException

  private final scala.Option constructServerContext$1(akka.remote.transport.netty.SSLSettings, akka.event.LoggingAdapter, java.lang.String, java.lang.String, java.lang.String, java.lang.String);
    Code:
       0: aload_0
       1: aload_1
       2: invokevirtual #314                // Method akka/remote/transport/netty/SSLSettings.SSLRandomNumberGenerator:()Lscala/Option;
       5: aload_2
       6: invokevirtual #316                // Method initializeCustomSecureRandom:(Lscala/Option;Lakka/event/LoggingAdapter;)Ljava/security/SecureRandom;
       9: astore        10
      11: invokestatic  #407                // Method javax/net/ssl/KeyManagerFactory.getDefaultAlgorithm:()Ljava/lang/String;
      14: invokestatic  #410                // Method javax/net/ssl/KeyManagerFactory.getInstance:(Ljava/lang/String;)Ljavax/net/ssl/KeyManagerFactory;
      17: astore        11
      19: aload         11
      21: invokestatic  #329                // Method java/security/KeyStore.getDefaultType:()Ljava/lang/String;
      24: invokestatic  #332                // Method java/security/KeyStore.getInstance:(Ljava/lang/String;)Ljava/security/KeyStore;
      27: astore        12
      29: new           #334                // class java/io/FileInputStream
      32: dup
      33: aload_3
      34: invokespecial #335                // Method java/io/FileInputStream."<init>":(Ljava/lang/String;)V
      37: astore        13
      39: aload         12
      41: aload         13
      43: aload         4
      45: invokevirtual #339                // Method java/lang/String.toCharArray:()[C
      48: invokevirtual #343                // Method java/security/KeyStore.load:(Ljava/io/InputStream;[C)V
      51: getstatic     #348                // Field scala/util/Try$.MODULE$:Lscala/util/Try$;
      54: new           #412                // class akka/remote/transport/netty/NettySSLSupport$$anonfun$constructServerContext$1$1
      57: dup
      58: aload         13
      60: invokespecial #413                // Method akka/remote/transport/netty/NettySSLSupport$$anonfun$constructServerContext$1$1."<init>":(Ljava/io/FileInputStream;)V
      63: invokevirtual #356                // Method scala/util/Try$.apply:(Lscala/Function0;)Lscala/util/Try;
      66: pop
      67: aload         12
      69: aload         5
      71: invokevirtual #339                // Method java/lang/String.toCharArray:()[C
      74: invokevirtual #416                // Method javax/net/ssl/KeyManagerFactory.init:(Ljava/security/KeyStore;[C)V
      77: aload_1
      78: invokevirtual #138                // Method akka/remote/transport/netty/SSLSettings.SSLTrustStore:()Lscala/Option;
      81: new           #418                // class akka/remote/transport/netty/NettySSLSupport$$anonfun$2
      84: dup
      85: aload_1
      86: invokespecial #421                // Method akka/remote/transport/netty/NettySSLSupport$$anonfun$2."<init>":(Lakka/remote/transport/netty/SSLSettings;)V
      89: invokevirtual #379                // Method scala/Option.map:(Lscala/Function1;)Lscala/Option;
      92: astore        15
      94: getstatic     #203                // Field scala/Option$.MODULE$:Lscala/Option$;
      97: aload         6
      99: invokestatic  #367                // Method javax/net/ssl/SSLContext.getInstance:(Ljava/lang/String;)Ljavax/net/ssl/SSLContext;
     102: invokevirtual #370                // Method scala/Option$.apply:(Ljava/lang/Object;)Lscala/Option;
     105: new           #423                // class akka/remote/transport/netty/NettySSLSupport$$anonfun$constructServerContext$1$2
     108: dup
     109: aload         10
     111: aload         11
     113: aload         15
     115: invokespecial #426                // Method akka/remote/transport/netty/NettySSLSupport$$anonfun$constructServerContext$1$2."<init>":(Ljava/security/SecureRandom;Ljavax/net/ssl/KeyManagerFactory;Lscala/Option;)V
     118: invokevirtual #379                // Method scala/Option.map:(Lscala/Function1;)Lscala/Option;
     121: areturn
     122: astore        14
     124: getstatic     #348                // Field scala/util/Try$.MODULE$:Lscala/util/Try$;
     127: new           #412                // class akka/remote/transport/netty/NettySSLSupport$$anonfun$constructServerContext$1$1
     130: dup
     131: aload         13
     133: invokespecial #413                // Method akka/remote/transport/netty/NettySSLSupport$$anonfun$constructServerContext$1$1."<init>":(Ljava/io/FileInputStream;)V
     136: invokevirtual #356                // Method scala/util/Try$.apply:(Lscala/Function0;)Lscala/util/Try;
     139: pop
     140: aload         14
     142: athrow
     143: astore        7
     145: new           #381                // class akka/remote/RemoteTransportException
     148: dup
     149: ldc_w         #428                // String Server SSL connection could not be established because SSL context could not be constructed
     152: aload         7
     154: invokespecial #386                // Method akka/remote/RemoteTransportException."<init>":(Ljava/lang/String;Ljava/lang/Throwable;)V
     157: athrow
     158: astore        8
     160: new           #381                // class akka/remote/RemoteTransportException
     163: dup
     164: new           #82                 // class scala/collection/mutable/StringBuilder
     167: dup
     168: invokespecial #83                 // Method scala/collection/mutable/StringBuilder."<init>":()V
     171: ldc_w         #430                // String Server SSL connection could not be established because:
     174: invokevirtual #89                 // Method scala/collection/mutable/StringBuilder.append:(Ljava/lang/Object;)Lscala/collection/mutable/StringBuilder;
     177: aload         8
     179: invokevirtual #391                // Method java/io/IOException.getMessage:()Ljava/lang/String;
     182: invokevirtual #89                 // Method scala/collection/mutable/StringBuilder.append:(Ljava/lang/Object;)Lscala/collection/mutable/StringBuilder;
     185: invokevirtual #93                 // Method scala/collection/mutable/StringBuilder.toString:()Ljava/lang/String;
     188: aload         8
     190: invokespecial #386                // Method akka/remote/RemoteTransportException."<init>":(Ljava/lang/String;Ljava/lang/Throwable;)V
     193: athrow
     194: astore        9
     196: new           #381                // class akka/remote/RemoteTransportException
     199: dup
     200: ldc_w         #432                // String Server SSL connection could not be established because key store could not be loaded
     203: aload         9
     205: invokespecial #386                // Method akka/remote/RemoteTransportException."<init>":(Ljava/lang/String;Ljava/lang/Throwable;)V
     208: athrow
    Exception table:
       from    to  target type
          39    51   122   any
         122   143   194   Class java/io/FileNotFoundException
           0   121   194   Class java/io/FileNotFoundException
         122   143   158   Class java/io/IOException
           0   121   158   Class java/io/IOException
         122   143   143   Class java/security/GeneralSecurityException
           0   121   143   Class java/security/GeneralSecurityException

  private akka.remote.transport.netty.NettySSLSupport$();
    Code:
       0: aload_0
       1: invokespecial #437                // Method java/lang/Object."<init>":()V
       4: aload_0
       5: putstatic     #439                // Field MODULE$:Lakka/remote/transport/netty/NettySSLSupport$;
       8: getstatic     #61                 // Field akka/remote/security/provider/AkkaProvider$.MODULE$:Lakka/remote/security/provider/AkkaProvider$;
      11: invokestatic  #445                // Method java/security/Security.addProvider:(Ljava/security/Provider;)I
      14: pop
      15: return
}
