Compiled from "SystemResource.java"
public class io.fabric8.gateway.apiman.rest.SystemResource implements io.apiman.gateway.api.rest.contract.ISystemResource {
  private io.apiman.gateway.engine.IEngine engine;

  public io.fabric8.gateway.apiman.rest.SystemResource(io.apiman.gateway.engine.IEngine);
    Code:
       0: aload_0
       1: invokespecial #1                  // Method java/lang/Object."<init>":()V
       4: aload_0
       5: aload_1
       6: putfield      #2                  // Field engine:Lio/apiman/gateway/engine/IEngine;
       9: return

  public io.apiman.gateway.engine.beans.SystemStatus getStatus();
    Code:
       0: new           #3                  // class io/apiman/gateway/engine/beans/SystemStatus
       3: dup
       4: invokespecial #4                  // Method io/apiman/gateway/engine/beans/SystemStatus."<init>":()V
       7: astore_1
       8: aload_0
       9: getfield      #2                  // Field engine:Lio/apiman/gateway/engine/IEngine;
      12: ifnull        36
      15: aload_1
      16: iconst_1
      17: invokevirtual #5                  // Method io/apiman/gateway/engine/beans/SystemStatus.setUp:(Z)V
      20: aload_1
      21: aload_0
      22: getfield      #2                  // Field engine:Lio/apiman/gateway/engine/IEngine;
      25: invokeinterface #6,  1            // InterfaceMethod io/apiman/gateway/engine/IEngine.getVersion:()Ljava/lang/String;
      30: invokevirtual #7                  // Method io/apiman/gateway/engine/beans/SystemStatus.setVersion:(Ljava/lang/String;)V
      33: goto          41
      36: aload_1
      37: iconst_0
      38: invokevirtual #5                  // Method io/apiman/gateway/engine/beans/SystemStatus.setUp:(Z)V
      41: aload_1
      42: areturn
}
