Compiled from "AbstractCdiBean.java"
abstract class io.lettuce.core.support.AbstractCdiBean<T> implements javax.enterprise.inject.spi.Bean<T> {
  protected final javax.enterprise.inject.spi.Bean<io.lettuce.core.RedisURI> redisURIBean;

  protected final javax.enterprise.inject.spi.Bean<io.lettuce.core.resource.ClientResources> clientResourcesBean;

  protected final javax.enterprise.inject.spi.BeanManager beanManager;

  protected final java.util.Set<java.lang.annotation.Annotation> qualifiers;

  protected final java.lang.String name;

  public io.lettuce.core.support.AbstractCdiBean(javax.enterprise.inject.spi.Bean<io.lettuce.core.RedisURI>, javax.enterprise.inject.spi.Bean<io.lettuce.core.resource.ClientResources>, javax.enterprise.inject.spi.BeanManager, java.util.Set<java.lang.annotation.Annotation>, java.lang.String);
    Code:
       0: aload_0
       1: invokespecial #1                  // Method java/lang/Object."<init>":()V
       4: aload_0
       5: aload_1
       6: putfield      #2                  // Field redisURIBean:Ljavax/enterprise/inject/spi/Bean;
       9: aload_0
      10: aload_2
      11: putfield      #3                  // Field clientResourcesBean:Ljavax/enterprise/inject/spi/Bean;
      14: aload_0
      15: aload_3
      16: putfield      #4                  // Field beanManager:Ljavax/enterprise/inject/spi/BeanManager;
      19: aload_0
      20: aload         4
      22: putfield      #5                  // Field qualifiers:Ljava/util/Set;
      25: aload_0
      26: aload         5
      28: putfield      #6                  // Field name:Ljava/lang/String;
      31: return

  public java.util.Set<java.lang.reflect.Type> getTypes();
    Code:
       0: aload_0
       1: invokevirtual #7                  // Method getBeanClass:()Ljava/lang/Class;
       4: invokestatic  #8                  // Method java/util/Collections.singleton:(Ljava/lang/Object;)Ljava/util/Set;
       7: areturn

  public java.util.Set<java.lang.annotation.Annotation> getQualifiers();
    Code:
       0: aload_0
       1: getfield      #5                  // Field qualifiers:Ljava/util/Set;
       4: areturn

  public java.lang.String getName();
    Code:
       0: aload_0
       1: getfield      #6                  // Field name:Ljava/lang/String;
       4: areturn

  public java.lang.Class<? extends java.lang.annotation.Annotation> getScope();
    Code:
       0: ldc           #9                  // class javax/enterprise/context/ApplicationScoped
       2: areturn

  public java.util.Set<java.lang.Class<? extends java.lang.annotation.Annotation>> getStereotypes();
    Code:
       0: new           #10                 // class java/util/HashSet
       3: dup
       4: invokespecial #11                 // Method java/util/HashSet."<init>":()V
       7: astore_1
       8: aload_0
       9: invokevirtual #12                 // Method getQualifiers:()Ljava/util/Set;
      12: invokeinterface #13,  1           // InterfaceMethod java/util/Set.iterator:()Ljava/util/Iterator;
      17: astore_2
      18: aload_2
      19: invokeinterface #14,  1           // InterfaceMethod java/util/Iterator.hasNext:()Z
      24: ifeq          67
      27: aload_2
      28: invokeinterface #15,  1           // InterfaceMethod java/util/Iterator.next:()Ljava/lang/Object;
      33: checkcast     #16                 // class java/lang/annotation/Annotation
      36: astore_3
      37: aload_3
      38: invokeinterface #17,  1           // InterfaceMethod java/lang/annotation/Annotation.annotationType:()Ljava/lang/Class;
      43: astore        4
      45: aload         4
      47: ldc           #18                 // class javax/enterprise/inject/Stereotype
      49: invokevirtual #19                 // Method java/lang/Class.isAnnotationPresent:(Ljava/lang/Class;)Z
      52: ifeq          64
      55: aload_1
      56: aload         4
      58: invokeinterface #20,  2           // InterfaceMethod java/util/Set.add:(Ljava/lang/Object;)Z
      63: pop
      64: goto          18
      67: aload_1
      68: areturn

  public boolean isAlternative();
    Code:
       0: iconst_0
       1: ireturn

  public boolean isNullable();
    Code:
       0: iconst_0
       1: ireturn

  public java.util.Set<javax.enterprise.inject.spi.InjectionPoint> getInjectionPoints();
    Code:
       0: invokestatic  #21                 // Method java/util/Collections.emptySet:()Ljava/util/Set;
       3: areturn
}
