Compiled from "MetricTargetFluentImpl.java"
public class io.fabric8.kubernetes.api.model.autoscaling.v2beta2.MetricTargetFluentImpl<A extends io.fabric8.kubernetes.api.model.autoscaling.v2beta2.MetricTargetFluent<A>> extends io.fabric8.kubernetes.api.builder.BaseFluent<A> implements io.fabric8.kubernetes.api.model.autoscaling.v2beta2.MetricTargetFluent<A> {
  private java.lang.Integer averageUtilization;

  private io.fabric8.kubernetes.api.model.Quantity averageValue;

  private java.lang.String type;

  private io.fabric8.kubernetes.api.model.Quantity value;

  public io.fabric8.kubernetes.api.model.autoscaling.v2beta2.MetricTargetFluentImpl();
    Code:
       0: aload_0
       1: invokespecial #1                  // Method io/fabric8/kubernetes/api/builder/BaseFluent."<init>":()V
       4: return

  public io.fabric8.kubernetes.api.model.autoscaling.v2beta2.MetricTargetFluentImpl(io.fabric8.kubernetes.api.model.autoscaling.v2beta2.MetricTarget);
    Code:
       0: aload_0
       1: invokespecial #1                  // Method io/fabric8/kubernetes/api/builder/BaseFluent."<init>":()V
       4: aload_0
       5: aload_1
       6: invokevirtual #2                  // Method io/fabric8/kubernetes/api/model/autoscaling/v2beta2/MetricTarget.getAverageUtilization:()Ljava/lang/Integer;
       9: invokevirtual #3                  // Method withAverageUtilization:(Ljava/lang/Integer;)Lio/fabric8/kubernetes/api/model/autoscaling/v2beta2/MetricTargetFluent;
      12: pop
      13: aload_0
      14: aload_1
      15: invokevirtual #4                  // Method io/fabric8/kubernetes/api/model/autoscaling/v2beta2/MetricTarget.getAverageValue:()Lio/fabric8/kubernetes/api/model/Quantity;
      18: invokevirtual #5                  // Method withAverageValue:(Lio/fabric8/kubernetes/api/model/Quantity;)Lio/fabric8/kubernetes/api/model/autoscaling/v2beta2/MetricTargetFluent;
      21: pop
      22: aload_0
      23: aload_1
      24: invokevirtual #6                  // Method io/fabric8/kubernetes/api/model/autoscaling/v2beta2/MetricTarget.getType:()Ljava/lang/String;
      27: invokevirtual #7                  // Method withType:(Ljava/lang/String;)Lio/fabric8/kubernetes/api/model/autoscaling/v2beta2/MetricTargetFluent;
      30: pop
      31: aload_0
      32: aload_1
      33: invokevirtual #8                  // Method io/fabric8/kubernetes/api/model/autoscaling/v2beta2/MetricTarget.getValue:()Lio/fabric8/kubernetes/api/model/Quantity;
      36: invokevirtual #9                  // Method withValue:(Lio/fabric8/kubernetes/api/model/Quantity;)Lio/fabric8/kubernetes/api/model/autoscaling/v2beta2/MetricTargetFluent;
      39: pop
      40: return

  public java.lang.Integer getAverageUtilization();
    Code:
       0: aload_0
       1: getfield      #10                 // Field averageUtilization:Ljava/lang/Integer;
       4: areturn

  public A withAverageUtilization(java.lang.Integer);
    Code:
       0: aload_0
       1: aload_1
       2: putfield      #10                 // Field averageUtilization:Ljava/lang/Integer;
       5: aload_0
       6: areturn

  public java.lang.Boolean hasAverageUtilization();
    Code:
       0: aload_0
       1: getfield      #10                 // Field averageUtilization:Ljava/lang/Integer;
       4: ifnull        11
       7: iconst_1
       8: goto          12
      11: iconst_0
      12: invokestatic  #11                 // Method java/lang/Boolean.valueOf:(Z)Ljava/lang/Boolean;
      15: areturn

  public io.fabric8.kubernetes.api.model.Quantity getAverageValue();
    Code:
       0: aload_0
       1: getfield      #12                 // Field averageValue:Lio/fabric8/kubernetes/api/model/Quantity;
       4: areturn

  public A withAverageValue(io.fabric8.kubernetes.api.model.Quantity);
    Code:
       0: aload_0
       1: aload_1
       2: putfield      #12                 // Field averageValue:Lio/fabric8/kubernetes/api/model/Quantity;
       5: aload_0
       6: areturn

  public java.lang.Boolean hasAverageValue();
    Code:
       0: aload_0
       1: getfield      #12                 // Field averageValue:Lio/fabric8/kubernetes/api/model/Quantity;
       4: ifnull        11
       7: iconst_1
       8: goto          12
      11: iconst_0
      12: invokestatic  #11                 // Method java/lang/Boolean.valueOf:(Z)Ljava/lang/Boolean;
      15: areturn

  public A withNewAverageValue(java.lang.String, java.lang.String);
    Code:
       0: aload_0
       1: new           #13                 // class io/fabric8/kubernetes/api/model/Quantity
       4: dup
       5: aload_1
       6: aload_2
       7: invokespecial #14                 // Method io/fabric8/kubernetes/api/model/Quantity."<init>":(Ljava/lang/String;Ljava/lang/String;)V
      10: invokevirtual #5                  // Method withAverageValue:(Lio/fabric8/kubernetes/api/model/Quantity;)Lio/fabric8/kubernetes/api/model/autoscaling/v2beta2/MetricTargetFluent;
      13: areturn

  public A withNewAverageValue(java.lang.String);
    Code:
       0: aload_0
       1: new           #13                 // class io/fabric8/kubernetes/api/model/Quantity
       4: dup
       5: aload_1
       6: invokespecial #15                 // Method io/fabric8/kubernetes/api/model/Quantity."<init>":(Ljava/lang/String;)V
       9: invokevirtual #5                  // Method withAverageValue:(Lio/fabric8/kubernetes/api/model/Quantity;)Lio/fabric8/kubernetes/api/model/autoscaling/v2beta2/MetricTargetFluent;
      12: areturn

  public java.lang.String getType();
    Code:
       0: aload_0
       1: getfield      #16                 // Field type:Ljava/lang/String;
       4: areturn

  public A withType(java.lang.String);
    Code:
       0: aload_0
       1: aload_1
       2: putfield      #16                 // Field type:Ljava/lang/String;
       5: aload_0
       6: areturn

  public java.lang.Boolean hasType();
    Code:
       0: aload_0
       1: getfield      #16                 // Field type:Ljava/lang/String;
       4: ifnull        11
       7: iconst_1
       8: goto          12
      11: iconst_0
      12: invokestatic  #11                 // Method java/lang/Boolean.valueOf:(Z)Ljava/lang/Boolean;
      15: areturn

  public A withNewType(java.lang.String);
    Code:
       0: aload_0
       1: new           #17                 // class java/lang/String
       4: dup
       5: aload_1
       6: invokespecial #18                 // Method java/lang/String."<init>":(Ljava/lang/String;)V
       9: invokevirtual #7                  // Method withType:(Ljava/lang/String;)Lio/fabric8/kubernetes/api/model/autoscaling/v2beta2/MetricTargetFluent;
      12: areturn

  public A withNewType(java.lang.StringBuilder);
    Code:
       0: aload_0
       1: new           #17                 // class java/lang/String
       4: dup
       5: aload_1
       6: invokespecial #19                 // Method java/lang/String."<init>":(Ljava/lang/StringBuilder;)V
       9: invokevirtual #7                  // Method withType:(Ljava/lang/String;)Lio/fabric8/kubernetes/api/model/autoscaling/v2beta2/MetricTargetFluent;
      12: areturn

  public A withNewType(java.lang.StringBuffer);
    Code:
       0: aload_0
       1: new           #17                 // class java/lang/String
       4: dup
       5: aload_1
       6: invokespecial #20                 // Method java/lang/String."<init>":(Ljava/lang/StringBuffer;)V
       9: invokevirtual #7                  // Method withType:(Ljava/lang/String;)Lio/fabric8/kubernetes/api/model/autoscaling/v2beta2/MetricTargetFluent;
      12: areturn

  public io.fabric8.kubernetes.api.model.Quantity getValue();
    Code:
       0: aload_0
       1: getfield      #21                 // Field value:Lio/fabric8/kubernetes/api/model/Quantity;
       4: areturn

  public A withValue(io.fabric8.kubernetes.api.model.Quantity);
    Code:
       0: aload_0
       1: aload_1
       2: putfield      #21                 // Field value:Lio/fabric8/kubernetes/api/model/Quantity;
       5: aload_0
       6: areturn

  public java.lang.Boolean hasValue();
    Code:
       0: aload_0
       1: getfield      #21                 // Field value:Lio/fabric8/kubernetes/api/model/Quantity;
       4: ifnull        11
       7: iconst_1
       8: goto          12
      11: iconst_0
      12: invokestatic  #11                 // Method java/lang/Boolean.valueOf:(Z)Ljava/lang/Boolean;
      15: areturn

  public A withNewValue(java.lang.String, java.lang.String);
    Code:
       0: aload_0
       1: new           #13                 // class io/fabric8/kubernetes/api/model/Quantity
       4: dup
       5: aload_1
       6: aload_2
       7: invokespecial #14                 // Method io/fabric8/kubernetes/api/model/Quantity."<init>":(Ljava/lang/String;Ljava/lang/String;)V
      10: invokevirtual #9                  // Method withValue:(Lio/fabric8/kubernetes/api/model/Quantity;)Lio/fabric8/kubernetes/api/model/autoscaling/v2beta2/MetricTargetFluent;
      13: areturn

  public A withNewValue(java.lang.String);
    Code:
       0: aload_0
       1: new           #13                 // class io/fabric8/kubernetes/api/model/Quantity
       4: dup
       5: aload_1
       6: invokespecial #15                 // Method io/fabric8/kubernetes/api/model/Quantity."<init>":(Ljava/lang/String;)V
       9: invokevirtual #9                  // Method withValue:(Lio/fabric8/kubernetes/api/model/Quantity;)Lio/fabric8/kubernetes/api/model/autoscaling/v2beta2/MetricTargetFluent;
      12: areturn

  public boolean equals(java.lang.Object);
    Code:
       0: aload_0
       1: aload_1
       2: if_acmpne     7
       5: iconst_1
       6: ireturn
       7: aload_1
       8: ifnull        22
      11: aload_0
      12: invokevirtual #22                 // Method java/lang/Object.getClass:()Ljava/lang/Class;
      15: aload_1
      16: invokevirtual #22                 // Method java/lang/Object.getClass:()Ljava/lang/Class;
      19: if_acmpeq     24
      22: iconst_0
      23: ireturn
      24: aload_1
      25: checkcast     #23                 // class io/fabric8/kubernetes/api/model/autoscaling/v2beta2/MetricTargetFluentImpl
      28: astore_2
      29: aload_0
      30: getfield      #10                 // Field averageUtilization:Ljava/lang/Integer;
      33: ifnull        53
      36: aload_0
      37: getfield      #10                 // Field averageUtilization:Ljava/lang/Integer;
      40: aload_2
      41: getfield      #10                 // Field averageUtilization:Ljava/lang/Integer;
      44: invokevirtual #24                 // Method java/lang/Integer.equals:(Ljava/lang/Object;)Z
      47: ifne          62
      50: goto          60
      53: aload_2
      54: getfield      #10                 // Field averageUtilization:Ljava/lang/Integer;
      57: ifnull        62
      60: iconst_0
      61: ireturn
      62: aload_0
      63: getfield      #12                 // Field averageValue:Lio/fabric8/kubernetes/api/model/Quantity;
      66: ifnull        86
      69: aload_0
      70: getfield      #12                 // Field averageValue:Lio/fabric8/kubernetes/api/model/Quantity;
      73: aload_2
      74: getfield      #12                 // Field averageValue:Lio/fabric8/kubernetes/api/model/Quantity;
      77: invokevirtual #25                 // Method io/fabric8/kubernetes/api/model/Quantity.equals:(Ljava/lang/Object;)Z
      80: ifne          95
      83: goto          93
      86: aload_2
      87: getfield      #12                 // Field averageValue:Lio/fabric8/kubernetes/api/model/Quantity;
      90: ifnull        95
      93: iconst_0
      94: ireturn
      95: aload_0
      96: getfield      #16                 // Field type:Ljava/lang/String;
      99: ifnull        119
     102: aload_0
     103: getfield      #16                 // Field type:Ljava/lang/String;
     106: aload_2
     107: getfield      #16                 // Field type:Ljava/lang/String;
     110: invokevirtual #26                 // Method java/lang/String.equals:(Ljava/lang/Object;)Z
     113: ifne          128
     116: goto          126
     119: aload_2
     120: getfield      #16                 // Field type:Ljava/lang/String;
     123: ifnull        128
     126: iconst_0
     127: ireturn
     128: aload_0
     129: getfield      #21                 // Field value:Lio/fabric8/kubernetes/api/model/Quantity;
     132: ifnull        152
     135: aload_0
     136: getfield      #21                 // Field value:Lio/fabric8/kubernetes/api/model/Quantity;
     139: aload_2
     140: getfield      #21                 // Field value:Lio/fabric8/kubernetes/api/model/Quantity;
     143: invokevirtual #25                 // Method io/fabric8/kubernetes/api/model/Quantity.equals:(Ljava/lang/Object;)Z
     146: ifne          161
     149: goto          159
     152: aload_2
     153: getfield      #21                 // Field value:Lio/fabric8/kubernetes/api/model/Quantity;
     156: ifnull        161
     159: iconst_0
     160: ireturn
     161: iconst_1
     162: ireturn
}
