Compiled from "CompactHashMap.java"
public class com.github.andrewoma.dexx.collection.internal.hashmap.CompactHashMap<K, V> {
  protected static final com.github.andrewoma.dexx.collection.internal.hashmap.CompactHashMap EMPTY;

  static final boolean $assertionsDisabled;

  public com.github.andrewoma.dexx.collection.internal.hashmap.CompactHashMap();
    Code:
       0: aload_0
       1: invokespecial #1                  // Method java/lang/Object."<init>":()V
       4: return

  public java.util.Iterator<com.github.andrewoma.dexx.collection.Pair<K, V>> iterator(com.github.andrewoma.dexx.collection.KeyFunction<K, V>);
    Code:
       0: invokestatic  #2                  // Method java/util/Collections.emptyList:()Ljava/util/List;
       3: invokeinterface #3,  1            // InterfaceMethod java/util/List.iterator:()Ljava/util/Iterator;
       8: areturn

  public int size();
    Code:
       0: iconst_0
       1: ireturn

  public static <K, V> com.github.andrewoma.dexx.collection.internal.hashmap.CompactHashMap<K, V> empty();
    Code:
       0: getstatic     #4                  // Field EMPTY:Lcom/github/andrewoma/dexx/collection/internal/hashmap/CompactHashMap;
       3: areturn

  public <U> void forEach(com.github.andrewoma.dexx.collection.Function<com.github.andrewoma.dexx.collection.Pair<K, V>, U>, com.github.andrewoma.dexx.collection.KeyFunction<K, V>);
    Code:
       0: return

  public V get(K, com.github.andrewoma.dexx.collection.KeyFunction<K, V>);
    Code:
       0: aload_0
       1: aload_1
       2: aload_0
       3: aload_1
       4: invokevirtual #5                  // Method computeHash:(Ljava/lang/Object;)I
       7: iconst_0
       8: aload_2
       9: invokevirtual #6                  // Method get0:(Ljava/lang/Object;IILcom/github/andrewoma/dexx/collection/KeyFunction;)Ljava/lang/Object;
      12: areturn

  public com.github.andrewoma.dexx.collection.internal.hashmap.CompactHashMap<K, V> put(K, V, com.github.andrewoma.dexx.collection.KeyFunction<K, V>);
    Code:
       0: getstatic     #7                  // Field $assertionsDisabled:Z
       3: ifne          28
       6: aload_1
       7: aload_3
       8: aload_2
       9: invokeinterface #8,  2            // InterfaceMethod com/github/andrewoma/dexx/collection/KeyFunction.key:(Ljava/lang/Object;)Ljava/lang/Object;
      14: invokevirtual #9                  // Method java/lang/Object.equals:(Ljava/lang/Object;)Z
      17: ifne          28
      20: new           #10                 // class java/lang/AssertionError
      23: dup
      24: invokespecial #11                 // Method java/lang/AssertionError."<init>":()V
      27: athrow
      28: aload_0
      29: aload_1
      30: aload_0
      31: aload_1
      32: invokevirtual #5                  // Method computeHash:(Ljava/lang/Object;)I
      35: iconst_0
      36: aload_2
      37: aconst_null
      38: aload_3
      39: invokevirtual #12                 // Method updated0:(Ljava/lang/Object;IILjava/lang/Object;Lcom/github/andrewoma/dexx/collection/Pair;Lcom/github/andrewoma/dexx/collection/KeyFunction;)Lcom/github/andrewoma/dexx/collection/internal/hashmap/CompactHashMap;
      42: areturn

  public com.github.andrewoma.dexx.collection.internal.hashmap.CompactHashMap<K, V> remove(K, com.github.andrewoma.dexx.collection.KeyFunction<K, V>);
    Code:
       0: aload_0
       1: aload_1
       2: aload_0
       3: aload_1
       4: invokevirtual #5                  // Method computeHash:(Ljava/lang/Object;)I
       7: iconst_0
       8: aload_2
       9: invokevirtual #13                 // Method removed0:(Ljava/lang/Object;IILcom/github/andrewoma/dexx/collection/KeyFunction;)Lcom/github/andrewoma/dexx/collection/internal/hashmap/CompactHashMap;
      12: areturn

  protected int elemHashCode(K);
    Code:
       0: aload_1
       1: invokevirtual #14                 // Method java/lang/Object.hashCode:()I
       4: ireturn

  protected final int improve(int);
    Code:
       0: iload_1
       1: iload_1
       2: bipush        9
       4: ishl
       5: iconst_m1
       6: ixor
       7: iadd
       8: istore_2
       9: iload_2
      10: iload_2
      11: bipush        14
      13: iushr
      14: ixor
      15: istore_2
      16: iload_2
      17: iload_2
      18: iconst_4
      19: ishl
      20: iadd
      21: istore_2
      22: iload_2
      23: iload_2
      24: bipush        10
      26: iushr
      27: ixor
      28: ireturn

  protected int computeHash(K);
    Code:
       0: aload_0
       1: aload_0
       2: aload_1
       3: invokevirtual #15                 // Method elemHashCode:(Ljava/lang/Object;)I
       6: invokevirtual #16                 // Method improve:(I)I
       9: ireturn

  protected V get0(K, int, int, com.github.andrewoma.dexx.collection.KeyFunction<K, V>);
    Code:
       0: aconst_null
       1: areturn

  protected com.github.andrewoma.dexx.collection.internal.hashmap.CompactHashMap<K, V> updated0(K, int, int, V, com.github.andrewoma.dexx.collection.Pair<K, V>, com.github.andrewoma.dexx.collection.KeyFunction<K, V>);
    Code:
       0: new           #17                 // class com/github/andrewoma/dexx/collection/internal/hashmap/HashMap1
       3: dup
       4: aload_1
       5: iload_2
       6: aload         4
       8: aload         5
      10: invokespecial #18                 // Method com/github/andrewoma/dexx/collection/internal/hashmap/HashMap1."<init>":(Ljava/lang/Object;ILjava/lang/Object;Lcom/github/andrewoma/dexx/collection/Pair;)V
      13: areturn

  protected com.github.andrewoma.dexx.collection.internal.hashmap.CompactHashMap<K, V> removed0(K, int, int, com.github.andrewoma.dexx.collection.KeyFunction<K, V>);
    Code:
       0: aload_0
       1: areturn

  protected static <K, V> com.github.andrewoma.dexx.collection.internal.hashmap.HashTrieMap<K, V> makeHashTrieMap(int, com.github.andrewoma.dexx.collection.internal.hashmap.CompactHashMap<K, V>, int, com.github.andrewoma.dexx.collection.internal.hashmap.CompactHashMap<K, V>, int, int);
    Code:
       0: iload_0
       1: iload         4
       3: iushr
       4: bipush        31
       6: iand
       7: istore        6
       9: iload_2
      10: iload         4
      12: iushr
      13: bipush        31
      15: iand
      16: istore        7
      18: iload         6
      20: iload         7
      22: if_icmpeq     98
      25: iconst_1
      26: iload         6
      28: ishl
      29: iconst_1
      30: iload         7
      32: ishl
      33: ior
      34: istore        8
      36: iconst_2
      37: anewarray     #19                 // class java/lang/Object
      40: astore        9
      42: iload         6
      44: iload         7
      46: if_icmpge     68
      49: aload         9
      51: iconst_0
      52: aload_1
      53: invokestatic  #20                 // Method unwrap:(Lcom/github/andrewoma/dexx/collection/internal/hashmap/CompactHashMap;)Ljava/lang/Object;
      56: aastore
      57: aload         9
      59: iconst_1
      60: aload_3
      61: invokestatic  #20                 // Method unwrap:(Lcom/github/andrewoma/dexx/collection/internal/hashmap/CompactHashMap;)Ljava/lang/Object;
      64: aastore
      65: goto          84
      68: aload         9
      70: iconst_0
      71: aload_3
      72: invokestatic  #20                 // Method unwrap:(Lcom/github/andrewoma/dexx/collection/internal/hashmap/CompactHashMap;)Ljava/lang/Object;
      75: aastore
      76: aload         9
      78: iconst_1
      79: aload_1
      80: invokestatic  #20                 // Method unwrap:(Lcom/github/andrewoma/dexx/collection/internal/hashmap/CompactHashMap;)Ljava/lang/Object;
      83: aastore
      84: new           #21                 // class com/github/andrewoma/dexx/collection/internal/hashmap/HashTrieMap
      87: dup
      88: iload         8
      90: aload         9
      92: iload         5
      94: invokespecial #22                 // Method com/github/andrewoma/dexx/collection/internal/hashmap/HashTrieMap."<init>":(I[Ljava/lang/Object;I)V
      97: areturn
      98: iconst_1
      99: anewarray     #19                 // class java/lang/Object
     102: astore        8
     104: iconst_1
     105: iload         6
     107: ishl
     108: istore        9
     110: aload         8
     112: iconst_0
     113: iload_0
     114: aload_1
     115: iload_2
     116: aload_3
     117: iload         4
     119: iconst_5
     120: iadd
     121: iload         5
     123: invokestatic  #23                 // Method makeHashTrieMap:(ILcom/github/andrewoma/dexx/collection/internal/hashmap/CompactHashMap;ILcom/github/andrewoma/dexx/collection/internal/hashmap/CompactHashMap;II)Lcom/github/andrewoma/dexx/collection/internal/hashmap/HashTrieMap;
     126: aastore
     127: new           #21                 // class com/github/andrewoma/dexx/collection/internal/hashmap/HashTrieMap
     130: dup
     131: iload         9
     133: aload         8
     135: iload         5
     137: invokespecial #22                 // Method com/github/andrewoma/dexx/collection/internal/hashmap/HashTrieMap."<init>":(I[Ljava/lang/Object;I)V
     140: areturn

  protected static <K, V> java.lang.Object unwrap(com.github.andrewoma.dexx.collection.internal.hashmap.CompactHashMap<K, V>);
    Code:
       0: aload_0
       1: instanceof    #17                 // class com/github/andrewoma/dexx/collection/internal/hashmap/HashMap1
       4: ifeq          15
       7: aload_0
       8: checkcast     #17                 // class com/github/andrewoma/dexx/collection/internal/hashmap/HashMap1
      11: getfield      #24                 // Field com/github/andrewoma/dexx/collection/internal/hashmap/HashMap1.value:Ljava/lang/Object;
      14: areturn
      15: aload_0
      16: areturn

  protected com.github.andrewoma.dexx.collection.internal.hashmap.CompactHashMap<K, V> wrap(java.lang.Object, com.github.andrewoma.dexx.collection.KeyFunction<K, V>);
    Code:
       0: aload_1
       1: instanceof    #25                 // class com/github/andrewoma/dexx/collection/internal/hashmap/CompactHashMap
       4: ifeq          12
       7: aload_1
       8: checkcast     #25                 // class com/github/andrewoma/dexx/collection/internal/hashmap/CompactHashMap
      11: areturn
      12: aload_1
      13: astore_3
      14: aload_2
      15: aload_3
      16: invokeinterface #8,  2            // InterfaceMethod com/github/andrewoma/dexx/collection/KeyFunction.key:(Ljava/lang/Object;)Ljava/lang/Object;
      21: astore        4
      23: new           #17                 // class com/github/andrewoma/dexx/collection/internal/hashmap/HashMap1
      26: dup
      27: aload         4
      29: aload_0
      30: aload         4
      32: invokevirtual #5                  // Method computeHash:(Ljava/lang/Object;)I
      35: aload_3
      36: aconst_null
      37: invokespecial #18                 // Method com/github/andrewoma/dexx/collection/internal/hashmap/HashMap1."<init>":(Ljava/lang/Object;ILjava/lang/Object;Lcom/github/andrewoma/dexx/collection/Pair;)V
      40: areturn

  static {};
    Code:
       0: ldc           #25                 // class com/github/andrewoma/dexx/collection/internal/hashmap/CompactHashMap
       2: invokevirtual #26                 // Method java/lang/Class.desiredAssertionStatus:()Z
       5: ifne          12
       8: iconst_1
       9: goto          13
      12: iconst_0
      13: putstatic     #7                  // Field $assertionsDisabled:Z
      16: new           #25                 // class com/github/andrewoma/dexx/collection/internal/hashmap/CompactHashMap
      19: dup
      20: invokespecial #27                 // Method "<init>":()V
      23: putstatic     #4                  // Field EMPTY:Lcom/github/andrewoma/dexx/collection/internal/hashmap/CompactHashMap;
      26: return
}
