Compiled from "JBossWSAuthConfigProvider.java"
public class org.jboss.wsf.stack.cxf.jaspi.config.JBossWSAuthConfigProvider implements javax.security.auth.message.config.AuthConfigProvider {
  private final java.util.Properties contextProperties;

  public org.jboss.wsf.stack.cxf.jaspi.config.JBossWSAuthConfigProvider(java.util.Properties, javax.security.auth.message.config.AuthConfigFactory);
    Code:
       0: aload_0
       1: invokespecial #1                  // Method java/lang/Object."<init>":()V
       4: aload_0
       5: aload_1
       6: putfield      #2                  // Field contextProperties:Ljava/util/Properties;
       9: aload_2
      10: ifnull        24
      13: aload_2
      14: aload_0
      15: ldc           #3                  // String soap
      17: aconst_null
      18: ldc           #4                  // String JBossWS AuthConfigProvider
      20: invokevirtual #5                  // Method javax/security/auth/message/config/AuthConfigFactory.registerConfigProvider:(Ljavax/security/auth/message/config/AuthConfigProvider;Ljava/lang/String;Ljava/lang/String;Ljava/lang/String;)Ljava/lang/String;
      23: pop
      24: return

  public javax.security.auth.message.config.ClientAuthConfig getClientAuthConfig(java.lang.String, java.lang.String, javax.security.auth.callback.CallbackHandler) throws javax.security.auth.message.AuthException, java.lang.SecurityException;
    Code:
       0: new           #6                  // class org/jboss/wsf/stack/cxf/jaspi/config/JBossWSClientAuthConfig
       3: dup
       4: aload_1
       5: aload_2
       6: aload_3
       7: aload_0
       8: getfield      #2                  // Field contextProperties:Ljava/util/Properties;
      11: invokespecial #7                  // Method org/jboss/wsf/stack/cxf/jaspi/config/JBossWSClientAuthConfig."<init>":(Ljava/lang/String;Ljava/lang/String;Ljavax/security/auth/callback/CallbackHandler;Ljava/util/Map;)V
      14: areturn

  public javax.security.auth.message.config.ServerAuthConfig getServerAuthConfig(java.lang.String, java.lang.String, javax.security.auth.callback.CallbackHandler) throws javax.security.auth.message.AuthException, java.lang.SecurityException;
    Code:
       0: new           #8                  // class org/jboss/wsf/stack/cxf/jaspi/config/JBossWSServerAuthConfig
       3: dup
       4: aload_1
       5: aload_2
       6: aload_3
       7: aload_0
       8: getfield      #2                  // Field contextProperties:Ljava/util/Properties;
      11: invokespecial #9                  // Method org/jboss/wsf/stack/cxf/jaspi/config/JBossWSServerAuthConfig."<init>":(Ljava/lang/String;Ljava/lang/String;Ljavax/security/auth/callback/CallbackHandler;Ljava/util/Map;)V
      14: areturn

  public void refresh();
    Code:
       0: return
}
