class org.bouncycastle.asn1.LazyEncodedSequence extends org.bouncycastle.asn1.ASN1Sequence {
  private byte[] encoded;

  org.bouncycastle.asn1.LazyEncodedSequence(byte[]) throws java.io.IOException;
    Code:
       0: aload_0
       1: invokespecial #90                 // Method org/bouncycastle/asn1/ASN1Sequence."<init>":()V
       4: aload_0
       5: aload_1
       6: putfield      #80                 // Field encoded:[B
       9: return

  public synchronized org.bouncycastle.asn1.ASN1Encodable getObjectAt(int);
    Code:
       0: aload_0
       1: invokespecial #99                 // Method force:()V
       4: aload_0
       5: iload_1
       6: invokespecial #95                 // Method org/bouncycastle/asn1/ASN1Sequence.getObjectAt:(I)Lorg/bouncycastle/asn1/ASN1Encodable;
       9: areturn

  public synchronized java.util.Enumeration getObjects();
    Code:
       0: aconst_null
       1: aload_0
       2: getfield      #80                 // Field encoded:[B
       5: if_acmpeq     20
       8: new           #46                 // class org/bouncycastle/asn1/LazyConstructionEnumeration
      11: dup
      12: aload_0
      13: getfield      #80                 // Field encoded:[B
      16: invokespecial #98                 // Method org/bouncycastle/asn1/LazyConstructionEnumeration."<init>":([B)V
      19: areturn
      20: aload_0
      21: invokespecial #91                 // Method org/bouncycastle/asn1/ASN1Sequence.getObjects:()Ljava/util/Enumeration;
      24: areturn

  public synchronized int hashCode();
    Code:
       0: aload_0
       1: invokespecial #99                 // Method force:()V
       4: aload_0
       5: invokespecial #88                 // Method org/bouncycastle/asn1/ASN1Sequence.hashCode:()I
       8: ireturn

  public synchronized java.util.Iterator<org.bouncycastle.asn1.ASN1Encodable> iterator();
    Code:
       0: aload_0
       1: invokespecial #99                 // Method force:()V
       4: aload_0
       5: invokespecial #92                 // Method org/bouncycastle/asn1/ASN1Sequence.iterator:()Ljava/util/Iterator;
       8: areturn

  public synchronized int size();
    Code:
       0: aload_0
       1: invokespecial #99                 // Method force:()V
       4: aload_0
       5: invokespecial #89                 // Method org/bouncycastle/asn1/ASN1Sequence.size:()I
       8: ireturn

  public synchronized org.bouncycastle.asn1.ASN1Encodable[] toArray();
    Code:
       0: aload_0
       1: invokespecial #99                 // Method force:()V
       4: aload_0
       5: invokespecial #93                 // Method org/bouncycastle/asn1/ASN1Sequence.toArray:()[Lorg/bouncycastle/asn1/ASN1Encodable;
       8: areturn

  org.bouncycastle.asn1.ASN1Encodable[] toArrayInternal();
    Code:
       0: aload_0
       1: invokespecial #99                 // Method force:()V
       4: aload_0
       5: invokespecial #94                 // Method org/bouncycastle/asn1/ASN1Sequence.toArrayInternal:()[Lorg/bouncycastle/asn1/ASN1Encodable;
       8: areturn

  synchronized int encodedLength() throws java.io.IOException;
    Code:
       0: aconst_null
       1: aload_0
       2: getfield      #80                 // Field encoded:[B
       5: if_acmpeq     25
       8: iconst_1
       9: aload_0
      10: getfield      #80                 // Field encoded:[B
      13: arraylength
      14: invokestatic  #100                // Method org/bouncycastle/asn1/StreamUtil.calculateBodyLength:(I)I
      17: iadd
      18: aload_0
      19: getfield      #80                 // Field encoded:[B
      22: arraylength
      23: iadd
      24: ireturn
      25: aload_0
      26: invokespecial #97                 // Method org/bouncycastle/asn1/ASN1Sequence.toDLObject:()Lorg/bouncycastle/asn1/ASN1Primitive;
      29: invokevirtual #86                 // Method org/bouncycastle/asn1/ASN1Primitive.encodedLength:()I
      32: ireturn

  synchronized void encode(org.bouncycastle.asn1.ASN1OutputStream, boolean) throws java.io.IOException;
    Code:
       0: aconst_null
       1: aload_0
       2: getfield      #80                 // Field encoded:[B
       5: if_acmpeq     22
       8: aload_1
       9: iload_2
      10: bipush        48
      12: aload_0
      13: getfield      #80                 // Field encoded:[B
      16: invokevirtual #85                 // Method org/bouncycastle/asn1/ASN1OutputStream.writeEncoded:(ZI[B)V
      19: goto          31
      22: aload_0
      23: invokespecial #97                 // Method org/bouncycastle/asn1/ASN1Sequence.toDLObject:()Lorg/bouncycastle/asn1/ASN1Primitive;
      26: aload_1
      27: iload_2
      28: invokevirtual #87                 // Method org/bouncycastle/asn1/ASN1Primitive.encode:(Lorg/bouncycastle/asn1/ASN1OutputStream;Z)V
      31: return

  synchronized org.bouncycastle.asn1.ASN1Primitive toDERObject();
    Code:
       0: aload_0
       1: invokespecial #99                 // Method force:()V
       4: aload_0
       5: invokespecial #96                 // Method org/bouncycastle/asn1/ASN1Sequence.toDERObject:()Lorg/bouncycastle/asn1/ASN1Primitive;
       8: areturn

  synchronized org.bouncycastle.asn1.ASN1Primitive toDLObject();
    Code:
       0: aload_0
       1: invokespecial #99                 // Method force:()V
       4: aload_0
       5: invokespecial #97                 // Method org/bouncycastle/asn1/ASN1Sequence.toDLObject:()Lorg/bouncycastle/asn1/ASN1Primitive;
       8: areturn

  private void force();
    Code:
       0: aconst_null
       1: aload_0
       2: getfield      #80                 // Field encoded:[B
       5: if_acmpeq     66
       8: new           #42                 // class org/bouncycastle/asn1/ASN1EncodableVector
      11: dup
      12: invokespecial #82                 // Method org/bouncycastle/asn1/ASN1EncodableVector."<init>":()V
      15: astore_1
      16: new           #46                 // class org/bouncycastle/asn1/LazyConstructionEnumeration
      19: dup
      20: aload_0
      21: getfield      #80                 // Field encoded:[B
      24: invokespecial #98                 // Method org/bouncycastle/asn1/LazyConstructionEnumeration."<init>":([B)V
      27: astore_2
      28: aload_2
      29: invokeinterface #101,  1          // InterfaceMethod java/util/Enumeration.hasMoreElements:()Z
      34: ifeq          53
      37: aload_1
      38: aload_2
      39: invokeinterface #102,  1          // InterfaceMethod java/util/Enumeration.nextElement:()Ljava/lang/Object;
      44: checkcast     #44                 // class org/bouncycastle/asn1/ASN1Primitive
      47: invokevirtual #84                 // Method org/bouncycastle/asn1/ASN1EncodableVector.add:(Lorg/bouncycastle/asn1/ASN1Encodable;)V
      50: goto          28
      53: aload_0
      54: aload_1
      55: invokevirtual #83                 // Method org/bouncycastle/asn1/ASN1EncodableVector.takeElements:()[Lorg/bouncycastle/asn1/ASN1Encodable;
      58: putfield      #81                 // Field elements:[Lorg/bouncycastle/asn1/ASN1Encodable;
      61: aload_0
      62: aconst_null
      63: putfield      #80                 // Field encoded:[B
      66: return
}
