Compiled from "HandleHolder.java"
class org.apache.curator.HandleHolder$1$1 implements org.apache.curator.HandleHolder$Helper {
  final org.apache.curator.HandleHolder$1 this$1;

  org.apache.curator.HandleHolder$1$1(org.apache.curator.HandleHolder$1);
    Code:
       0: aload_0
       1: aload_1
       2: putfield      #21                 // Field this$1:Lorg/apache/curator/HandleHolder$1;
       5: aload_0
       6: invokespecial #24                 // Method java/lang/Object."<init>":()V
       9: return

  public org.apache.zookeeper.ZooKeeper getZooKeeper() throws java.lang.Exception;
    Code:
       0: aload_0
       1: getfield      #21                 // Field this$1:Lorg/apache/curator/HandleHolder$1;
       4: invokestatic  #32                 // Method org/apache/curator/HandleHolder$1.access$600:(Lorg/apache/curator/HandleHolder$1;)Lorg/apache/zookeeper/ZooKeeper;
       7: areturn

  public java.lang.String getConnectionString();
    Code:
       0: aload_0
       1: getfield      #21                 // Field this$1:Lorg/apache/curator/HandleHolder$1;
       4: invokestatic  #38                 // Method org/apache/curator/HandleHolder$1.access$700:(Lorg/apache/curator/HandleHolder$1;)Ljava/lang/String;
       7: areturn
}
