Compiled from "SessionFailRetryLoop.java"
class org.apache.curator.SessionFailRetryLoop$1 implements org.apache.zookeeper.Watcher {
  final org.apache.curator.SessionFailRetryLoop this$0;

  org.apache.curator.SessionFailRetryLoop$1(org.apache.curator.SessionFailRetryLoop);
    Code:
       0: aload_0
       1: aload_1
       2: putfield      #21                 // Field this$0:Lorg/apache/curator/SessionFailRetryLoop;
       5: aload_0
       6: invokespecial #24                 // Method java/lang/Object."<init>":()V
       9: return

  public void process(org.apache.zookeeper.WatchedEvent);
    Code:
       0: aload_1
       1: invokevirtual #34                 // Method org/apache/zookeeper/WatchedEvent.getState:()Lorg/apache/zookeeper/Watcher$Event$KeeperState;
       4: getstatic     #38                 // Field org/apache/zookeeper/Watcher$Event$KeeperState.Expired:Lorg/apache/zookeeper/Watcher$Event$KeeperState;
       7: if_acmpne     37
      10: aload_0
      11: getfield      #21                 // Field this$0:Lorg/apache/curator/SessionFailRetryLoop;
      14: invokestatic  #42                 // Method org/apache/curator/SessionFailRetryLoop.access$000:(Lorg/apache/curator/SessionFailRetryLoop;)Ljava/util/concurrent/atomic/AtomicBoolean;
      17: iconst_1
      18: invokevirtual #48                 // Method java/util/concurrent/atomic/AtomicBoolean.set:(Z)V
      21: invokestatic  #52                 // Method org/apache/curator/SessionFailRetryLoop.access$200:()Ljava/util/Set;
      24: aload_0
      25: getfield      #21                 // Field this$0:Lorg/apache/curator/SessionFailRetryLoop;
      28: invokestatic  #56                 // Method org/apache/curator/SessionFailRetryLoop.access$100:(Lorg/apache/curator/SessionFailRetryLoop;)Ljava/lang/Thread;
      31: invokeinterface #62,  2           // InterfaceMethod java/util/Set.add:(Ljava/lang/Object;)Z
      36: pop
      37: return
}
