Compiled from "ValueClassExtractor.scala"
public class org.mockito.internal.NormalClassExtractor<T> implements org.mockito.internal.ValueClassExtractor<T> {
  public <T> T extractAs(T);
    Code:
       0: aload_0
       1: aload_1
       2: invokestatic  #18                 // Method org/mockito/internal/ValueClassExtractor$class.extractAs:(Lorg/mockito/internal/ValueClassExtractor;Ljava/lang/Object;)Ljava/lang/Object;
       5: areturn

  public boolean isValueClass();
    Code:
       0: iconst_0
       1: ireturn

  public java.lang.Object extract(T);
    Code:
       0: aload_1
       1: areturn

  public org.mockito.internal.NormalClassExtractor();
    Code:
       0: aload_0
       1: invokespecial #29                 // Method java/lang/Object."<init>":()V
       4: aload_0
       5: invokestatic  #33                 // Method org/mockito/internal/ValueClassExtractor$class.$init$:(Lorg/mockito/internal/ValueClassExtractor;)V
       8: return
}
