Compiled from "FunktionRouteBuilder.java"
public class io.fabric8.funktion.runtime.FunktionRouteBuilder extends org.apache.camel.builder.RouteBuilder {
  private static final transient org.slf4j.Logger LOG;

  private static final java.lang.String DEFAULT_TRIGGER_URL;

  private static final java.lang.String DEFAULT_HTTP_ENDPOINT_PREFIX;

  private java.util.Set<java.lang.String> localHosts;

  public io.fabric8.funktion.runtime.FunktionRouteBuilder();
    Code:
       0: aload_0
       1: invokespecial #1                  // Method org/apache/camel/builder/RouteBuilder."<init>":()V
       4: aload_0
       5: new           #2                  // class java/util/HashSet
       8: dup
       9: iconst_3
      10: anewarray     #3                  // class java/lang/String
      13: dup
      14: iconst_0
      15: ldc           #4                  // String localhost
      17: aastore
      18: dup
      19: iconst_1
      20: ldc           #5                  // String 0.0.0.0
      22: aastore
      23: dup
      24: iconst_2
      25: ldc           #6                  // String 127.0.0.1
      27: aastore
      28: invokestatic  #7                  // Method java/util/Arrays.asList:([Ljava/lang/Object;)Ljava/util/List;
      31: invokespecial #8                  // Method java/util/HashSet."<init>":(Ljava/util/Collection;)V
      34: putfield      #9                  // Field localHosts:Ljava/util/Set;
      37: return

  public static void main(java.lang.String[]);
    Code:
       0: aload_0
       1: invokestatic  #10                 // Method org/apache/camel/spring/boot/FatJarRouter.main:([Ljava/lang/String;)V
       4: return

  private static java.lang.String replacePrefix(java.lang.String, java.lang.String, java.lang.String);
    Code:
       0: aload_0
       1: aload_1
       2: invokevirtual #11                 // Method java/lang/String.startsWith:(Ljava/lang/String;)Z
       5: ifeq          34
       8: new           #12                 // class java/lang/StringBuilder
      11: dup
      12: invokespecial #13                 // Method java/lang/StringBuilder."<init>":()V
      15: aload_2
      16: invokevirtual #14                 // Method java/lang/StringBuilder.append:(Ljava/lang/String;)Ljava/lang/StringBuilder;
      19: aload_0
      20: aload_1
      21: invokevirtual #15                 // Method java/lang/String.length:()I
      24: invokevirtual #16                 // Method java/lang/String.substring:(I)Ljava/lang/String;
      27: invokevirtual #14                 // Method java/lang/StringBuilder.append:(Ljava/lang/String;)Ljava/lang/StringBuilder;
      30: invokevirtual #17                 // Method java/lang/StringBuilder.toString:()Ljava/lang/String;
      33: areturn
      34: aload_0
      35: areturn

  org.springframework.boot.web.servlet.ServletRegistrationBean camelServlet();
    Code:
       0: new           #18                 // class org/springframework/boot/web/servlet/ServletRegistrationBean
       3: dup
       4: invokespecial #19                 // Method org/springframework/boot/web/servlet/ServletRegistrationBean."<init>":()V
       7: astore_1
       8: aload_1
       9: ldc           #20                 // String CamelServlet
      11: invokevirtual #21                 // Method org/springframework/boot/web/servlet/ServletRegistrationBean.setName:(Ljava/lang/String;)V
      14: aload_1
      15: iconst_1
      16: invokevirtual #22                 // Method org/springframework/boot/web/servlet/ServletRegistrationBean.setLoadOnStartup:(I)V
      19: aload_1
      20: new           #23                 // class org/apache/camel/component/servlet/CamelHttpTransportServlet
      23: dup
      24: invokespecial #24                 // Method org/apache/camel/component/servlet/CamelHttpTransportServlet."<init>":()V
      27: invokevirtual #25                 // Method org/springframework/boot/web/servlet/ServletRegistrationBean.setServlet:(Ljavax/servlet/Servlet;)V
      30: aload_1
      31: iconst_1
      32: anewarray     #3                  // class java/lang/String
      35: dup
      36: iconst_0
      37: ldc           #26                 // String /camel/*
      39: aastore
      40: invokevirtual #27                 // Method org/springframework/boot/web/servlet/ServletRegistrationBean.addUrlMappings:([Ljava/lang/String;)V
      43: aload_1
      44: areturn

  public void configure() throws java.lang.Exception;
    Code:
       0: aload_0
       1: invokevirtual #28                 // Method loadFunktion:()Lio/fabric8/funktion/model/Funktion;
       4: astore_1
       5: iconst_0
       6: istore_2
       7: aload_1
       8: invokevirtual #29                 // Method io/fabric8/funktion/model/Funktion.getFlows:()Ljava/util/List;
      11: astore_3
      12: aload_3
      13: invokeinterface #30,  1           // InterfaceMethod java/util/List.iterator:()Ljava/util/Iterator;
      18: astore        4
      20: aload         4
      22: invokeinterface #31,  1           // InterfaceMethod java/util/Iterator.hasNext:()Z
      27: ifeq          55
      30: aload         4
      32: invokeinterface #32,  1           // InterfaceMethod java/util/Iterator.next:()Ljava/lang/Object;
      37: checkcast     #33                 // class io/fabric8/funktion/model/Flow
      40: astore        5
      42: aload_0
      43: aload         5
      45: iload_2
      46: iinc          2, 1
      49: invokevirtual #34                 // Method configureRule:(Lio/fabric8/funktion/model/Flow;I)V
      52: goto          20
      55: return

  protected io.fabric8.funktion.model.Funktion loadFunktion() throws java.io.IOException;
    Code:
       0: invokestatic  #35                 // Method io/fabric8/funktion/model/Funktions.load:()Lio/fabric8/funktion/model/Funktion;
       3: areturn

  protected void configureRule(io.fabric8.funktion.model.Flow, int) throws java.net.MalformedURLException;
    Code:
       0: aload_1
       1: invokevirtual #36                 // Method io/fabric8/funktion/model/Flow.isTraceEnabled:()Z
       4: ifeq          20
       7: aload_0
       8: invokevirtual #37                 // Method getContext:()Lorg/apache/camel/model/ModelCamelContext;
      11: iconst_1
      12: invokestatic  #38                 // Method java/lang/Boolean.valueOf:(Z)Ljava/lang/Boolean;
      15: invokeinterface #39,  2           // InterfaceMethod org/apache/camel/model/ModelCamelContext.setTracing:(Ljava/lang/Boolean;)V
      20: new           #12                 // class java/lang/StringBuilder
      23: dup
      24: ldc           #40                 // String FLOW
      26: invokespecial #41                 // Method java/lang/StringBuilder."<init>":(Ljava/lang/String;)V
      29: astore_3
      30: aload_1
      31: invokevirtual #42                 // Method io/fabric8/funktion/model/Flow.getName:()Ljava/lang/String;
      34: astore        4
      36: aload         4
      38: invokestatic  #43                 // Method io/fabric8/funktion/support/Strings.isEmpty:(Ljava/lang/String;)Z
      41: ifeq          73
      44: new           #12                 // class java/lang/StringBuilder
      47: dup
      48: invokespecial #13                 // Method java/lang/StringBuilder."<init>":()V
      51: ldc           #44                 // String flow
      53: invokevirtual #14                 // Method java/lang/StringBuilder.append:(Ljava/lang/String;)Ljava/lang/StringBuilder;
      56: iload_2
      57: iconst_1
      58: iadd
      59: invokevirtual #45                 // Method java/lang/StringBuilder.append:(I)Ljava/lang/StringBuilder;
      62: invokevirtual #17                 // Method java/lang/StringBuilder.toString:()Ljava/lang/String;
      65: astore        4
      67: aload_1
      68: aload         4
      70: invokevirtual #46                 // Method io/fabric8/funktion/model/Flow.setName:(Ljava/lang/String;)V
      73: aconst_null
      74: astore        5
      76: aload_1
      77: invokevirtual #47                 // Method io/fabric8/funktion/model/Flow.getSteps:()Ljava/util/List;
      80: astore        6
      82: iconst_0
      83: istore        7
      85: aload         6
      87: ifnull        600
      90: aload         6
      92: invokeinterface #30,  1           // InterfaceMethod java/util/List.iterator:()Ljava/util/Iterator;
      97: astore        8
      99: aload         8
     101: invokeinterface #31,  1           // InterfaceMethod java/util/Iterator.hasNext:()Z
     106: ifeq          600
     109: aload         8
     111: invokeinterface #32,  1           // InterfaceMethod java/util/Iterator.next:()Ljava/lang/Object;
     116: checkcast     #48                 // class io/fabric8/funktion/model/steps/Step
     119: astore        9
     121: aload         9
     123: instanceof    #49                 // class io/fabric8/funktion/model/steps/Function
     126: ifeq          327
     129: aload         9
     131: checkcast     #49                 // class io/fabric8/funktion/model/steps/Function
     134: astore        10
     136: aload         10
     138: invokevirtual #50                 // Method io/fabric8/funktion/model/steps/Function.getName:()Ljava/lang/String;
     141: astore        11
     143: aload         11
     145: invokestatic  #43                 // Method io/fabric8/funktion/support/Strings.isEmpty:(Ljava/lang/String;)Z
     148: ifne          324
     151: aload         5
     153: ifnull        164
     156: aload         5
     158: ldc           #51                 // String json:marshal
     160: invokevirtual #52                 // Method org/apache/camel/model/RouteDefinition.to:(Ljava/lang/String;)Lorg/apache/camel/model/ProcessorDefinition;
     163: pop
     164: aconst_null
     165: astore        12
     167: aload         11
     169: ldc           #53                 // String ::
     171: invokevirtual #54                 // Method java/lang/String.indexOf:(Ljava/lang/String;)I
     174: istore        13
     176: iload         13
     178: ifle          202
     181: aload         11
     183: iload         13
     185: iconst_2
     186: iadd
     187: invokevirtual #16                 // Method java/lang/String.substring:(I)Ljava/lang/String;
     190: astore        12
     192: aload         11
     194: iconst_0
     195: iload         13
     197: invokevirtual #55                 // Method java/lang/String.substring:(II)Ljava/lang/String;
     200: astore        11
     202: new           #12                 // class java/lang/StringBuilder
     205: dup
     206: invokespecial #13                 // Method java/lang/StringBuilder."<init>":()V
     209: ldc           #56                 // String class:
     211: invokevirtual #14                 // Method java/lang/StringBuilder.append:(Ljava/lang/String;)Ljava/lang/StringBuilder;
     214: aload         11
     216: invokevirtual #14                 // Method java/lang/StringBuilder.append:(Ljava/lang/String;)Ljava/lang/StringBuilder;
     219: invokevirtual #17                 // Method java/lang/StringBuilder.toString:()Ljava/lang/String;
     222: astore        14
     224: aload         12
     226: ifnull        256
     229: new           #12                 // class java/lang/StringBuilder
     232: dup
     233: invokespecial #13                 // Method java/lang/StringBuilder."<init>":()V
     236: aload         14
     238: invokevirtual #14                 // Method java/lang/StringBuilder.append:(Ljava/lang/String;)Ljava/lang/StringBuilder;
     241: ldc           #57                 // String ?method=
     243: invokevirtual #14                 // Method java/lang/StringBuilder.append:(Ljava/lang/String;)Ljava/lang/StringBuilder;
     246: aload         12
     248: invokevirtual #14                 // Method java/lang/StringBuilder.append:(Ljava/lang/String;)Ljava/lang/StringBuilder;
     251: invokevirtual #17                 // Method java/lang/StringBuilder.toString:()Ljava/lang/String;
     254: astore        14
     256: aload_0
     257: aload         5
     259: aload         4
     261: aload         14
     263: aload_3
     264: invokevirtual #58                 // Method fromOrTo:(Lorg/apache/camel/model/RouteDefinition;Ljava/lang/String;Ljava/lang/String;Ljava/lang/StringBuilder;)Lorg/apache/camel/model/RouteDefinition;
     267: astore        5
     269: aload_3
     270: aload         11
     272: invokevirtual #14                 // Method java/lang/StringBuilder.append:(Ljava/lang/String;)Ljava/lang/StringBuilder;
     275: pop
     276: aload         12
     278: ifnull        314
     281: aload_3
     282: new           #12                 // class java/lang/StringBuilder
     285: dup
     286: invokespecial #13                 // Method java/lang/StringBuilder."<init>":()V
     289: ldc           #59                 // String .
     291: invokevirtual #14                 // Method java/lang/StringBuilder.append:(Ljava/lang/String;)Ljava/lang/StringBuilder;
     294: aload         12
     296: invokevirtual #14                 // Method java/lang/StringBuilder.append:(Ljava/lang/String;)Ljava/lang/StringBuilder;
     299: ldc           #60                 // String ()
     301: invokevirtual #14                 // Method java/lang/StringBuilder.append:(Ljava/lang/String;)Ljava/lang/StringBuilder;
     304: invokevirtual #17                 // Method java/lang/StringBuilder.toString:()Ljava/lang/String;
     307: invokevirtual #14                 // Method java/lang/StringBuilder.append:(Ljava/lang/String;)Ljava/lang/StringBuilder;
     310: pop
     311: goto          321
     314: aload_3
     315: ldc           #61                 // String .main()
     317: invokevirtual #14                 // Method java/lang/StringBuilder.append:(Ljava/lang/String;)Ljava/lang/StringBuilder;
     320: pop
     321: iinc          7, 1
     324: goto          597
     327: aload         9
     329: instanceof    #62                 // class io/fabric8/funktion/model/steps/Endpoint
     332: ifeq          396
     335: aload         9
     337: checkcast     #62                 // class io/fabric8/funktion/model/steps/Endpoint
     340: astore        10
     342: aload         10
     344: invokevirtual #63                 // Method io/fabric8/funktion/model/steps/Endpoint.getUri:()Ljava/lang/String;
     347: astore        11
     349: aload         11
     351: invokestatic  #43                 // Method io/fabric8/funktion/support/Strings.isEmpty:(Ljava/lang/String;)Z
     354: ifne          393
     357: aload         5
     359: ifnull        370
     362: aload         5
     364: ldc           #51                 // String json:marshal
     366: invokevirtual #52                 // Method org/apache/camel/model/RouteDefinition.to:(Ljava/lang/String;)Lorg/apache/camel/model/ProcessorDefinition;
     369: pop
     370: aload_0
     371: aload         5
     373: aload         4
     375: aload         11
     377: aload_3
     378: invokevirtual #58                 // Method fromOrTo:(Lorg/apache/camel/model/RouteDefinition;Ljava/lang/String;Ljava/lang/String;Ljava/lang/StringBuilder;)Lorg/apache/camel/model/RouteDefinition;
     381: astore        5
     383: aload_3
     384: aload         11
     386: invokevirtual #14                 // Method java/lang/StringBuilder.append:(Ljava/lang/String;)Ljava/lang/StringBuilder;
     389: pop
     390: iinc          7, 1
     393: goto          597
     396: aload         9
     398: instanceof    #64                 // class io/fabric8/funktion/model/steps/SetBody
     401: ifeq          437
     404: aload         9
     406: checkcast     #64                 // class io/fabric8/funktion/model/steps/SetBody
     409: astore        10
     411: aload_0
     412: aload         5
     414: aload         9
     416: invokevirtual #65                 // Method assertRouteNotNull:(Lorg/apache/camel/model/RouteDefinition;Lio/fabric8/funktion/model/steps/Step;)V
     419: aload         5
     421: aload_0
     422: aload         10
     424: invokevirtual #66                 // Method io/fabric8/funktion/model/steps/SetBody.getBody:()Ljava/lang/String;
     427: invokevirtual #67                 // Method constant:(Ljava/lang/Object;)Lorg/apache/camel/builder/ValueBuilder;
     430: invokevirtual #68                 // Method org/apache/camel/model/RouteDefinition.setBody:(Lorg/apache/camel/Expression;)Lorg/apache/camel/model/ProcessorDefinition;
     433: pop
     434: goto          597
     437: aload         9
     439: instanceof    #69                 // class io/fabric8/funktion/model/steps/SetHeaders
     442: ifeq          553
     445: aload         9
     447: checkcast     #69                 // class io/fabric8/funktion/model/steps/SetHeaders
     450: astore        10
     452: aload_0
     453: aload         5
     455: aload         9
     457: invokevirtual #65                 // Method assertRouteNotNull:(Lorg/apache/camel/model/RouteDefinition;Lio/fabric8/funktion/model/steps/Step;)V
     460: aload         10
     462: invokevirtual #70                 // Method io/fabric8/funktion/model/steps/SetHeaders.getHeaders:()Ljava/util/Map;
     465: astore        11
     467: aload         11
     469: ifnull        550
     472: aload         11
     474: invokeinterface #71,  1           // InterfaceMethod java/util/Map.entrySet:()Ljava/util/Set;
     479: astore        12
     481: aload         12
     483: invokeinterface #72,  1           // InterfaceMethod java/util/Set.iterator:()Ljava/util/Iterator;
     488: astore        13
     490: aload         13
     492: invokeinterface #31,  1           // InterfaceMethod java/util/Iterator.hasNext:()Z
     497: ifeq          550
     500: aload         13
     502: invokeinterface #32,  1           // InterfaceMethod java/util/Iterator.next:()Ljava/lang/Object;
     507: checkcast     #73                 // class java/util/Map$Entry
     510: astore        14
     512: aload         14
     514: invokeinterface #74,  1           // InterfaceMethod java/util/Map$Entry.getKey:()Ljava/lang/Object;
     519: checkcast     #3                  // class java/lang/String
     522: astore        15
     524: aload         14
     526: invokeinterface #75,  1           // InterfaceMethod java/util/Map$Entry.getValue:()Ljava/lang/Object;
     531: astore        16
     533: aload         5
     535: aload         15
     537: aload_0
     538: aload         16
     540: invokevirtual #67                 // Method constant:(Ljava/lang/Object;)Lorg/apache/camel/builder/ValueBuilder;
     543: invokevirtual #76                 // Method org/apache/camel/model/RouteDefinition.setHeader:(Ljava/lang/String;Lorg/apache/camel/Expression;)Lorg/apache/camel/model/ProcessorDefinition;
     546: pop
     547: goto          490
     550: goto          597
     553: new           #77                 // class java/lang/IllegalStateException
     556: dup
     557: new           #12                 // class java/lang/StringBuilder
     560: dup
     561: invokespecial #13                 // Method java/lang/StringBuilder."<init>":()V
     564: ldc           #78                 // String Uknown step kind:
     566: invokevirtual #14                 // Method java/lang/StringBuilder.append:(Ljava/lang/String;)Ljava/lang/StringBuilder;
     569: aload         9
     571: invokevirtual #79                 // Method java/lang/StringBuilder.append:(Ljava/lang/Object;)Ljava/lang/StringBuilder;
     574: ldc           #80                 // String  of class:
     576: invokevirtual #14                 // Method java/lang/StringBuilder.append:(Ljava/lang/String;)Ljava/lang/StringBuilder;
     579: aload         9
     581: invokevirtual #81                 // Method java/lang/Object.getClass:()Ljava/lang/Class;
     584: invokevirtual #82                 // Method java/lang/Class.getName:()Ljava/lang/String;
     587: invokevirtual #14                 // Method java/lang/StringBuilder.append:(Ljava/lang/String;)Ljava/lang/StringBuilder;
     590: invokevirtual #17                 // Method java/lang/StringBuilder.toString:()Ljava/lang/String;
     593: invokespecial #83                 // Method java/lang/IllegalStateException."<init>":(Ljava/lang/String;)V
     596: athrow
     597: goto          99
     600: aload         5
     602: ifnull        610
     605: iload         7
     607: ifne          637
     610: new           #77                 // class java/lang/IllegalStateException
     613: dup
     614: new           #12                 // class java/lang/StringBuilder
     617: dup
     618: invokespecial #13                 // Method java/lang/StringBuilder."<init>":()V
     621: ldc           #84                 // String No valid steps! Invalid flow
     623: invokevirtual #14                 // Method java/lang/StringBuilder.append:(Ljava/lang/String;)Ljava/lang/StringBuilder;
     626: aload_1
     627: invokevirtual #79                 // Method java/lang/StringBuilder.append:(Ljava/lang/Object;)Ljava/lang/StringBuilder;
     630: invokevirtual #17                 // Method java/lang/StringBuilder.toString:()Ljava/lang/String;
     633: invokespecial #83                 // Method java/lang/IllegalStateException."<init>":(Ljava/lang/String;)V
     636: athrow
     637: aload_1
     638: invokevirtual #85                 // Method io/fabric8/funktion/model/Flow.isLogResultEnabled:()Z
     641: ifeq          696
     644: new           #12                 // class java/lang/StringBuilder
     647: dup
     648: invokespecial #13                 // Method java/lang/StringBuilder."<init>":()V
     651: ldc           #86                 // String log:
     653: invokevirtual #14                 // Method java/lang/StringBuilder.append:(Ljava/lang/String;)Ljava/lang/StringBuilder;
     656: aload         4
     658: invokevirtual #14                 // Method java/lang/StringBuilder.append:(Ljava/lang/String;)Ljava/lang/StringBuilder;
     661: ldc           #87                 // String ?showStreams=true
     663: invokevirtual #14                 // Method java/lang/StringBuilder.append:(Ljava/lang/String;)Ljava/lang/StringBuilder;
     666: invokevirtual #17                 // Method java/lang/StringBuilder.toString:()Ljava/lang/String;
     669: astore        8
     671: aload         5
     673: aload         8
     675: invokevirtual #52                 // Method org/apache/camel/model/RouteDefinition.to:(Ljava/lang/String;)Lorg/apache/camel/model/ProcessorDefinition;
     678: pop
     679: aload_3
     680: ldc           #88                 // String  =>
     682: invokevirtual #14                 // Method java/lang/StringBuilder.append:(Ljava/lang/String;)Ljava/lang/StringBuilder;
     685: pop
     686: aload_3
     687: aload         8
     689: invokevirtual #14                 // Method java/lang/StringBuilder.append:(Ljava/lang/String;)Ljava/lang/StringBuilder;
     692: pop
     693: iinc          7, 1
     696: getstatic     #89                 // Field LOG:Lorg/slf4j/Logger;
     699: aload_3
     700: invokevirtual #17                 // Method java/lang/StringBuilder.toString:()Ljava/lang/String;
     703: invokeinterface #90,  2           // InterfaceMethod org/slf4j/Logger.info:(Ljava/lang/String;)V
     708: aload_1
     709: invokevirtual #91                 // Method io/fabric8/funktion/model/Flow.isSingleMessageModeEnabled:()Z
     712: ifeq          741
     715: getstatic     #89                 // Field LOG:Lorg/slf4j/Logger;
     718: ldc           #92                 // String Enabling single message mode so that only one message is consumed for Design Mode
     720: invokeinterface #90,  2           // InterfaceMethod org/slf4j/Logger.info:(Ljava/lang/String;)V
     725: aload_0
     726: invokevirtual #37                 // Method getContext:()Lorg/apache/camel/model/ModelCamelContext;
     729: new           #93                 // class io/fabric8/funktion/runtime/designer/SingleMessageRoutePolicyFactory
     732: dup
     733: invokespecial #94                 // Method io/fabric8/funktion/runtime/designer/SingleMessageRoutePolicyFactory."<init>":()V
     736: invokeinterface #95,  2           // InterfaceMethod org/apache/camel/model/ModelCamelContext.addRoutePolicyFactory:(Lorg/apache/camel/spi/RoutePolicyFactory;)V
     741: return

  protected void assertRouteNotNull(org.apache.camel.model.RouteDefinition, io.fabric8.funktion.model.steps.Step);
    Code:
       0: aload_1
       1: ifnonnull     39
       4: new           #96                 // class java/lang/IllegalArgumentException
       7: dup
       8: new           #12                 // class java/lang/StringBuilder
      11: dup
      12: invokespecial #13                 // Method java/lang/StringBuilder."<init>":()V
      15: ldc           #97                 // String You cannot use a
      17: invokevirtual #14                 // Method java/lang/StringBuilder.append:(Ljava/lang/String;)Ljava/lang/StringBuilder;
      20: aload_2
      21: invokevirtual #98                 // Method io/fabric8/funktion/model/steps/Step.getKind:()Ljava/lang/String;
      24: invokevirtual #14                 // Method java/lang/StringBuilder.append:(Ljava/lang/String;)Ljava/lang/StringBuilder;
      27: ldc           #99                 // String  step before you have started a flow with an endpoint or function!
      29: invokevirtual #14                 // Method java/lang/StringBuilder.append:(Ljava/lang/String;)Ljava/lang/StringBuilder;
      32: invokevirtual #17                 // Method java/lang/StringBuilder.toString:()Ljava/lang/String;
      35: invokespecial #100                // Method java/lang/IllegalArgumentException."<init>":(Ljava/lang/String;)V
      38: athrow
      39: return

  protected org.apache.camel.model.RouteDefinition fromOrTo(org.apache.camel.model.RouteDefinition, java.lang.String, java.lang.String, java.lang.StringBuilder);
    Code:
       0: aload_1
       1: ifnonnull     302
       4: aload_3
       5: astore        5
       7: aload         5
       9: invokestatic  #43                 // Method io/fabric8/funktion/support/Strings.isEmpty:(Ljava/lang/String;)Z
      12: ifeq          19
      15: ldc           #102                // String http://0.0.0.0:8080/
      17: astore        5
      19: aload         4
      21: aload_2
      22: invokevirtual #14                 // Method java/lang/StringBuilder.append:(Ljava/lang/String;)Ljava/lang/StringBuilder;
      25: pop
      26: aload         4
      28: ldc           #103                // String ()
      30: invokevirtual #14                 // Method java/lang/StringBuilder.append:(Ljava/lang/String;)Ljava/lang/StringBuilder;
      33: pop
      34: aload         5
      36: ldc           #104                // String http
      38: invokevirtual #105                // Method java/lang/String.equals:(Ljava/lang/Object;)Z
      41: ifeq          51
      44: ldc           #106                // String servlet:funktion
      46: astore        5
      48: goto          286
      51: aload         5
      53: ldc           #107                // String http:
      55: invokevirtual #11                 // Method java/lang/String.startsWith:(Ljava/lang/String;)Z
      58: ifne          91
      61: aload         5
      63: ldc           #108                // String https:
      65: invokevirtual #11                 // Method java/lang/String.startsWith:(Ljava/lang/String;)Z
      68: ifne          91
      71: aload         5
      73: ldc           #109                // String http://
      75: invokevirtual #11                 // Method java/lang/String.startsWith:(Ljava/lang/String;)Z
      78: ifne          91
      81: aload         5
      83: ldc           #110                // String https://
      85: invokevirtual #11                 // Method java/lang/String.startsWith:(Ljava/lang/String;)Z
      88: ifeq          286
      91: aload_0
      92: aload         5
      94: invokespecial #111                // Method getURIHost:(Ljava/lang/String;)Ljava/lang/String;
      97: astore        6
      99: aload_0
     100: getfield      #9                  // Field localHosts:Ljava/util/Set;
     103: aload         6
     105: invokeinterface #112,  2          // InterfaceMethod java/util/Set.contains:(Ljava/lang/Object;)Z
     110: ifeq          120
     113: ldc           #106                // String servlet:funktion
     115: astore        5
     117: goto          286
     120: aload         5
     122: ldc           #108                // String https:
     124: invokevirtual #11                 // Method java/lang/String.startsWith:(Ljava/lang/String;)Z
     127: ifeq          140
     130: aload         5
     132: bipush        6
     134: invokevirtual #16                 // Method java/lang/String.substring:(I)Ljava/lang/String;
     137: goto          141
     140: aconst_null
     141: astore        7
     143: aload         7
     145: ifnonnull     170
     148: aload         5
     150: ldc           #107                // String http:
     152: invokevirtual #11                 // Method java/lang/String.startsWith:(Ljava/lang/String;)Z
     155: ifeq          167
     158: aload         5
     160: iconst_5
     161: invokevirtual #16                 // Method java/lang/String.substring:(I)Ljava/lang/String;
     164: goto          168
     167: aconst_null
     168: astore        7
     170: aload         7
     172: ifnonnull     198
     175: aload         5
     177: ldc           #110                // String https://
     179: invokevirtual #11                 // Method java/lang/String.startsWith:(Ljava/lang/String;)Z
     182: ifeq          195
     185: aload         5
     187: bipush        8
     189: invokevirtual #16                 // Method java/lang/String.substring:(I)Ljava/lang/String;
     192: goto          196
     195: aconst_null
     196: astore        7
     198: aload         7
     200: ifnonnull     226
     203: aload         5
     205: ldc           #109                // String http://
     207: invokevirtual #11                 // Method java/lang/String.startsWith:(Ljava/lang/String;)Z
     210: ifeq          223
     213: aload         5
     215: bipush        7
     217: invokevirtual #16                 // Method java/lang/String.substring:(I)Ljava/lang/String;
     220: goto          224
     223: aconst_null
     224: astore        7
     226: aload         7
     228: ifnull        255
     231: aload         7
     233: ldc           #113                // String /
     235: invokevirtual #114                // Method java/lang/String.contains:(Ljava/lang/CharSequence;)Z
     238: ifeq          255
     241: aload         7
     243: aload         7
     245: bipush        47
     247: invokevirtual #115                // Method java/lang/String.indexOf:(I)I
     250: invokevirtual #16                 // Method java/lang/String.substring:(I)Ljava/lang/String;
     253: astore        7
     255: aload         7
     257: ifnull        264
     260: aload         7
     262: astore        5
     264: new           #12                 // class java/lang/StringBuilder
     267: dup
     268: invokespecial #13                 // Method java/lang/StringBuilder."<init>":()V
     271: ldc           #116                // String servlet:funktion/
     273: invokevirtual #14                 // Method java/lang/StringBuilder.append:(Ljava/lang/String;)Ljava/lang/StringBuilder;
     276: aload         5
     278: invokevirtual #14                 // Method java/lang/StringBuilder.append:(Ljava/lang/String;)Ljava/lang/StringBuilder;
     281: invokevirtual #17                 // Method java/lang/StringBuilder.toString:()Ljava/lang/String;
     284: astore        5
     286: aload_0
     287: aload         5
     289: invokevirtual #117                // Method from:(Ljava/lang/String;)Lorg/apache/camel/model/RouteDefinition;
     292: astore_1
     293: aload_1
     294: aload_2
     295: invokevirtual #118                // Method org/apache/camel/model/RouteDefinition.id:(Ljava/lang/String;)Lorg/apache/camel/model/ProcessorDefinition;
     298: pop
     299: goto          381
     302: aload_3
     303: ldc           #107                // String http:
     305: invokevirtual #11                 // Method java/lang/String.startsWith:(Ljava/lang/String;)Z
     308: ifne          320
     311: aload_3
     312: ldc           #108                // String https:
     314: invokevirtual #11                 // Method java/lang/String.startsWith:(Ljava/lang/String;)Z
     317: ifeq          367
     320: aload_3
     321: ldc           #107                // String http:
     323: ldc           #119                // String http4:
     325: invokestatic  #120                // Method replacePrefix:(Ljava/lang/String;Ljava/lang/String;Ljava/lang/String;)Ljava/lang/String;
     328: astore_3
     329: aload_3
     330: ldc           #108                // String https:
     332: ldc           #121                // String https4:
     334: invokestatic  #120                // Method replacePrefix:(Ljava/lang/String;Ljava/lang/String;Ljava/lang/String;)Ljava/lang/String;
     337: astore_3
     338: aload_0
     339: aload_3
     340: ldc           #122                // class org/apache/camel/component/http4/HttpEndpoint
     342: invokevirtual #123                // Method endpoint:(Ljava/lang/String;Ljava/lang/Class;)Lorg/apache/camel/Endpoint;
     345: checkcast     #122                // class org/apache/camel/component/http4/HttpEndpoint
     348: astore        5
     350: aload         5
     352: ifnull        367
     355: aload         5
     357: iconst_1
     358: invokevirtual #124                // Method org/apache/camel/component/http4/HttpEndpoint.setBridgeEndpoint:(Z)V
     361: aload         5
     363: iconst_0
     364: invokevirtual #125                // Method org/apache/camel/component/http4/HttpEndpoint.setThrowExceptionOnFailure:(Z)V
     367: aload         4
     369: ldc           #88                 // String  =>
     371: invokevirtual #14                 // Method java/lang/StringBuilder.append:(Ljava/lang/String;)Ljava/lang/StringBuilder;
     374: pop
     375: aload_1
     376: aload_3
     377: invokevirtual #52                 // Method org/apache/camel/model/RouteDefinition.to:(Ljava/lang/String;)Lorg/apache/camel/model/ProcessorDefinition;
     380: pop
     381: aload_1
     382: areturn

  private java.lang.String getURIHost(java.lang.String);
    Code:
       0: new           #126                // class java/net/URI
       3: dup
       4: aload_1
       5: invokespecial #127                // Method java/net/URI."<init>":(Ljava/lang/String;)V
       8: invokevirtual #128                // Method java/net/URI.getHost:()Ljava/lang/String;
      11: areturn
      12: astore_2
      13: aconst_null
      14: areturn
    Exception table:
       from    to  target type
           0    11    12   Class java/net/URISyntaxException

  static {};
    Code:
       0: ldc           #101                // class io/fabric8/funktion/runtime/FunktionRouteBuilder
       2: invokestatic  #130                // Method org/slf4j/LoggerFactory.getLogger:(Ljava/lang/Class;)Lorg/slf4j/Logger;
       5: putstatic     #89                 // Field LOG:Lorg/slf4j/Logger;
       8: return
}
