Compiled from "SessionProperties.java"
public class org.springframework.boot.autoconfigure.session.SessionProperties$Mongo {
  private java.lang.String collectionName;

  public org.springframework.boot.autoconfigure.session.SessionProperties$Mongo();
    Code:
       0: aload_0
       1: invokespecial #1                  // Method java/lang/Object."<init>":()V
       4: aload_0
       5: ldc           #2                  // String sessions
       7: putfield      #3                  // Field collectionName:Ljava/lang/String;
      10: return

  public java.lang.String getCollectionName();
    Code:
       0: aload_0
       1: getfield      #3                  // Field collectionName:Ljava/lang/String;
       4: areturn

  public void setCollectionName(java.lang.String);
    Code:
       0: aload_0
       1: aload_1
       2: putfield      #3                  // Field collectionName:Ljava/lang/String;
       5: return
}
