Compiled from "PooledConnectionFactoryService.java"
public class org.wildfly.extension.messaging.activemq.jms.PooledConnectionFactoryService implements org.jboss.msc.service.Service<java.lang.Void> {
  private static final java.util.List<org.jboss.jca.common.api.metadata.spec.LocalizedXsdString> EMPTY_LOCL;

  public static final java.lang.String CONNECTOR_CLASSNAME;

  public static final java.lang.String CONNECTION_PARAMETERS;

  private static final java.lang.String ACTIVEMQ_ACTIVATION;

  private static final java.lang.String ACTIVEMQ_CONN_DEF;

  private static final java.lang.String ACTIVEMQ_RESOURCE_ADAPTER;

  private static final java.lang.String RAMANAGED_CONN_FACTORY;

  private static final java.lang.String RA_CONN_FACTORY;

  private static final java.lang.String RA_CONN_FACTORY_IMPL;

  private static final java.lang.String JMS_SESSION;

  private static final java.lang.String ACTIVEMQ_RA_SESSION;

  private static final java.lang.String BASIC_PASS;

  private static final java.lang.String JMS_QUEUE;

  private static final java.lang.String STRING_TYPE;

  private static final java.lang.String INTEGER_TYPE;

  private static final java.lang.String LONG_TYPE;

  private static final java.lang.String SESSION_DEFAULT_TYPE;

  private static final java.lang.String TRY_LOCK;

  private static final java.lang.String JMS_MESSAGE_LISTENER;

  private static final java.lang.String DEFAULT_MAX_RECONNECTS;

  public static final java.lang.String GROUP_ADDRESS;

  public static final java.lang.String DISCOVERY_INITIAL_WAIT_TIMEOUT;

  public static final java.lang.String GROUP_PORT;

  public static final java.lang.String REFRESH_TIMEOUT;

  public static final java.lang.String DISCOVERY_LOCAL_BIND_ADDRESS;

  public static final java.lang.String JGROUPS_CHANNEL_LOCATOR_CLASS;

  public static final java.lang.String JGROUPS_CHANNEL_NAME;

  public static final java.lang.String JGROUPS_CHANNEL_REF_NAME;

  private org.jboss.msc.inject.Injector<java.lang.Object> transactionManager;

  private java.util.List<java.lang.String> connectors;

  private java.lang.String discoveryGroupName;

  private java.util.List<org.wildfly.extension.messaging.activemq.jms.PooledConnectionFactoryConfigProperties> adapterParams;

  private java.lang.String name;

  private java.util.Map<java.lang.String, org.jboss.as.network.SocketBinding> socketBindings;

  private org.jboss.msc.value.InjectedValue<org.apache.activemq.artemis.core.server.ActiveMQServer> activeMQServer;

  private org.jboss.as.naming.deployment.ContextNames$BindInfo bindInfo;

  private final boolean pickAnyConnectors;

  private java.util.List<java.lang.String> jndiAliases;

  private java.lang.String txSupport;

  private int minPoolSize;

  private int maxPoolSize;

  private java.lang.String serverName;

  private final java.lang.String jgroupsChannelName;

  private final boolean createBinderService;

  private final java.lang.String managedConnectionPoolClassName;

  private final java.lang.Boolean enlistmentTrace;

  public org.wildfly.extension.messaging.activemq.jms.PooledConnectionFactoryService(java.lang.String, java.util.List<java.lang.String>, java.lang.String, java.lang.String, java.lang.String, java.util.List<org.wildfly.extension.messaging.activemq.jms.PooledConnectionFactoryConfigProperties>, java.util.List<java.lang.String>, java.lang.String, int, int, java.lang.String, java.lang.Boolean);
    Code:
       0: aload_0
       1: invokespecial #1                  // Method java/lang/Object."<init>":()V
       4: aload_0
       5: new           #2                  // class org/jboss/msc/value/InjectedValue
       8: dup
       9: invokespecial #3                  // Method org/jboss/msc/value/InjectedValue."<init>":()V
      12: putfield      #4                  // Field transactionManager:Lorg/jboss/msc/inject/Injector;
      15: aload_0
      16: new           #5                  // class java/util/HashMap
      19: dup
      20: invokespecial #6                  // Method java/util/HashMap."<init>":()V
      23: putfield      #7                  // Field socketBindings:Ljava/util/Map;
      26: aload_0
      27: new           #2                  // class org/jboss/msc/value/InjectedValue
      30: dup
      31: invokespecial #3                  // Method org/jboss/msc/value/InjectedValue."<init>":()V
      34: putfield      #8                  // Field activeMQServer:Lorg/jboss/msc/value/InjectedValue;
      37: aload_0
      38: aload_1
      39: putfield      #9                  // Field name:Ljava/lang/String;
      42: aload_0
      43: aload_2
      44: putfield      #10                 // Field connectors:Ljava/util/List;
      47: aload_0
      48: aload_3
      49: putfield      #11                 // Field discoveryGroupName:Ljava/lang/String;
      52: aload_0
      53: aload         4
      55: putfield      #12                 // Field serverName:Ljava/lang/String;
      58: aload_0
      59: aload         5
      61: putfield      #13                 // Field jgroupsChannelName:Ljava/lang/String;
      64: aload_0
      65: aload         6
      67: putfield      #14                 // Field adapterParams:Ljava/util/List;
      70: aload_0
      71: aload         7
      73: invokespecial #15                 // Method initJNDIBindings:(Ljava/util/List;)V
      76: aload_0
      77: iconst_1
      78: putfield      #16                 // Field createBinderService:Z
      81: aload_0
      82: aload         8
      84: putfield      #17                 // Field txSupport:Ljava/lang/String;
      87: aload_0
      88: iload         9
      90: putfield      #18                 // Field minPoolSize:I
      93: aload_0
      94: iload         10
      96: putfield      #19                 // Field maxPoolSize:I
      99: aload_0
     100: aload         11
     102: putfield      #20                 // Field managedConnectionPoolClassName:Ljava/lang/String;
     105: aload_0
     106: aload         12
     108: putfield      #21                 // Field enlistmentTrace:Ljava/lang/Boolean;
     111: aload_0
     112: iconst_0
     113: putfield      #22                 // Field pickAnyConnectors:Z
     116: return

  public org.wildfly.extension.messaging.activemq.jms.PooledConnectionFactoryService(java.lang.String, java.util.List<java.lang.String>, java.lang.String, java.lang.String, java.lang.String, java.util.List<org.wildfly.extension.messaging.activemq.jms.PooledConnectionFactoryConfigProperties>, org.jboss.as.naming.deployment.ContextNames$BindInfo, java.lang.String, int, int, java.lang.String, java.lang.Boolean, boolean);
    Code:
       0: aload_0
       1: invokespecial #1                  // Method java/lang/Object."<init>":()V
       4: aload_0
       5: new           #2                  // class org/jboss/msc/value/InjectedValue
       8: dup
       9: invokespecial #3                  // Method org/jboss/msc/value/InjectedValue."<init>":()V
      12: putfield      #4                  // Field transactionManager:Lorg/jboss/msc/inject/Injector;
      15: aload_0
      16: new           #5                  // class java/util/HashMap
      19: dup
      20: invokespecial #6                  // Method java/util/HashMap."<init>":()V
      23: putfield      #7                  // Field socketBindings:Ljava/util/Map;
      26: aload_0
      27: new           #2                  // class org/jboss/msc/value/InjectedValue
      30: dup
      31: invokespecial #3                  // Method org/jboss/msc/value/InjectedValue."<init>":()V
      34: putfield      #8                  // Field activeMQServer:Lorg/jboss/msc/value/InjectedValue;
      37: aload_0
      38: aload_1
      39: putfield      #9                  // Field name:Ljava/lang/String;
      42: aload_0
      43: aload_2
      44: putfield      #10                 // Field connectors:Ljava/util/List;
      47: aload_0
      48: aload_3
      49: putfield      #11                 // Field discoveryGroupName:Ljava/lang/String;
      52: aload_0
      53: aload         4
      55: putfield      #12                 // Field serverName:Ljava/lang/String;
      58: aload_0
      59: aload         5
      61: putfield      #13                 // Field jgroupsChannelName:Ljava/lang/String;
      64: aload_0
      65: aload         6
      67: putfield      #14                 // Field adapterParams:Ljava/util/List;
      70: aload_0
      71: aload         7
      73: putfield      #23                 // Field bindInfo:Lorg/jboss/as/naming/deployment/ContextNames$BindInfo;
      76: aload_0
      77: getstatic     #24                 // Field java/util/Collections.EMPTY_LIST:Ljava/util/List;
      80: putfield      #25                 // Field jndiAliases:Ljava/util/List;
      83: aload_0
      84: iconst_0
      85: putfield      #16                 // Field createBinderService:Z
      88: aload_0
      89: aload         8
      91: putfield      #17                 // Field txSupport:Ljava/lang/String;
      94: aload_0
      95: iload         9
      97: putfield      #18                 // Field minPoolSize:I
     100: aload_0
     101: iload         10
     103: putfield      #19                 // Field maxPoolSize:I
     106: aload_0
     107: aload         11
     109: putfield      #20                 // Field managedConnectionPoolClassName:Ljava/lang/String;
     112: aload_0
     113: aload         12
     115: putfield      #21                 // Field enlistmentTrace:Ljava/lang/Boolean;
     118: aload_0
     119: iload         13
     121: putfield      #22                 // Field pickAnyConnectors:Z
     124: return

  private void initJNDIBindings(java.util.List<java.lang.String>);
    Code:
       0: aload_1
       1: iconst_0
       2: invokeinterface #26,  2           // InterfaceMethod java/util/List.get:(I)Ljava/lang/Object;
       7: checkcast     #27                 // class java/lang/String
      10: astore_2
      11: aload_0
      12: aload_2
      13: invokestatic  #28                 // Method org/jboss/as/naming/deployment/ContextNames.bindInfoFor:(Ljava/lang/String;)Lorg/jboss/as/naming/deployment/ContextNames$BindInfo;
      16: putfield      #23                 // Field bindInfo:Lorg/jboss/as/naming/deployment/ContextNames$BindInfo;
      19: aload_0
      20: new           #29                 // class java/util/ArrayList
      23: dup
      24: invokespecial #30                 // Method java/util/ArrayList."<init>":()V
      27: putfield      #25                 // Field jndiAliases:Ljava/util/List;
      30: aload_1
      31: invokeinterface #31,  1           // InterfaceMethod java/util/List.size:()I
      36: iconst_1
      37: if_icmple     57
      40: aload_0
      41: aload_1
      42: iconst_1
      43: aload_1
      44: invokeinterface #31,  1           // InterfaceMethod java/util/List.size:()I
      49: invokeinterface #32,  3           // InterfaceMethod java/util/List.subList:(II)Ljava/util/List;
      54: putfield      #25                 // Field jndiAliases:Ljava/util/List;
      57: return

  public static void installService(org.jboss.msc.service.ServiceTarget, java.lang.String, java.lang.String, java.util.List<java.lang.String>, java.lang.String, java.lang.String, java.util.List<org.wildfly.extension.messaging.activemq.jms.PooledConnectionFactoryConfigProperties>, org.jboss.as.naming.deployment.ContextNames$BindInfo, java.lang.String, int, int, java.lang.String, java.lang.Boolean, boolean);
    Code:
       0: aload_2
       1: invokestatic  #33                 // Method org/wildfly/extension/messaging/activemq/MessagingServices.getActiveMQServiceName:(Ljava/lang/String;)Lorg/jboss/msc/service/ServiceName;
       4: astore        14
       6: aload         14
       8: invokestatic  #34                 // Method org/wildfly/extension/messaging/activemq/jms/JMSServices.getPooledConnectionFactoryBaseServiceName:(Lorg/jboss/msc/service/ServiceName;)Lorg/jboss/msc/service/ServiceName;
      11: iconst_1
      12: anewarray     #27                 // class java/lang/String
      15: dup
      16: iconst_0
      17: aload_1
      18: aastore
      19: invokevirtual #35                 // Method org/jboss/msc/service/ServiceName.append:([Ljava/lang/String;)Lorg/jboss/msc/service/ServiceName;
      22: astore        15
      24: new           #36                 // class org/wildfly/extension/messaging/activemq/jms/PooledConnectionFactoryService
      27: dup
      28: aload_1
      29: aload_3
      30: aload         4
      32: aload_2
      33: aload         5
      35: aload         6
      37: aload         7
      39: aload         8
      41: iload         9
      43: iload         10
      45: aload         11
      47: aload         12
      49: iload         13
      51: invokespecial #37                 // Method "<init>":(Ljava/lang/String;Ljava/util/List;Ljava/lang/String;Ljava/lang/String;Ljava/lang/String;Ljava/util/List;Lorg/jboss/as/naming/deployment/ContextNames$BindInfo;Ljava/lang/String;IILjava/lang/String;Ljava/lang/Boolean;Z)V
      54: astore        16
      56: aload_0
      57: aload         14
      59: aload         15
      61: aload         16
      63: invokestatic  #38                 // Method installService0:(Lorg/jboss/msc/service/ServiceTarget;Lorg/jboss/msc/service/ServiceName;Lorg/jboss/msc/service/ServiceName;Lorg/wildfly/extension/messaging/activemq/jms/PooledConnectionFactoryService;)V
      66: return

  public static void installService(org.jboss.msc.service.ServiceTarget, java.lang.String, java.lang.String, java.util.List<java.lang.String>, java.lang.String, java.lang.String, java.util.List<org.wildfly.extension.messaging.activemq.jms.PooledConnectionFactoryConfigProperties>, java.util.List<java.lang.String>, java.lang.String, int, int, java.lang.String, java.lang.Boolean);
    Code:
       0: aload_2
       1: invokestatic  #33                 // Method org/wildfly/extension/messaging/activemq/MessagingServices.getActiveMQServiceName:(Ljava/lang/String;)Lorg/jboss/msc/service/ServiceName;
       4: astore        13
       6: aload         13
       8: invokestatic  #34                 // Method org/wildfly/extension/messaging/activemq/jms/JMSServices.getPooledConnectionFactoryBaseServiceName:(Lorg/jboss/msc/service/ServiceName;)Lorg/jboss/msc/service/ServiceName;
      11: iconst_1
      12: anewarray     #27                 // class java/lang/String
      15: dup
      16: iconst_0
      17: aload_1
      18: aastore
      19: invokevirtual #35                 // Method org/jboss/msc/service/ServiceName.append:([Ljava/lang/String;)Lorg/jboss/msc/service/ServiceName;
      22: astore        14
      24: new           #36                 // class org/wildfly/extension/messaging/activemq/jms/PooledConnectionFactoryService
      27: dup
      28: aload_1
      29: aload_3
      30: aload         4
      32: aload_2
      33: aload         5
      35: aload         6
      37: aload         7
      39: aload         8
      41: iload         9
      43: iload         10
      45: aload         11
      47: aload         12
      49: invokespecial #39                 // Method "<init>":(Ljava/lang/String;Ljava/util/List;Ljava/lang/String;Ljava/lang/String;Ljava/lang/String;Ljava/util/List;Ljava/util/List;Ljava/lang/String;IILjava/lang/String;Ljava/lang/Boolean;)V
      52: astore        15
      54: aload_0
      55: aload         13
      57: aload         14
      59: aload         15
      61: invokestatic  #38                 // Method installService0:(Lorg/jboss/msc/service/ServiceTarget;Lorg/jboss/msc/service/ServiceName;Lorg/jboss/msc/service/ServiceName;Lorg/wildfly/extension/messaging/activemq/jms/PooledConnectionFactoryService;)V
      64: return

  private static void installService0(org.jboss.msc.service.ServiceTarget, org.jboss.msc.service.ServiceName, org.jboss.msc.service.ServiceName, org.wildfly.extension.messaging.activemq.jms.PooledConnectionFactoryService);
    Code:
       0: aload_0
       1: aload_2
       2: aload_3
       3: invokeinterface #40,  3           // InterfaceMethod org/jboss/msc/service/ServiceTarget.addService:(Lorg/jboss/msc/service/ServiceName;Lorg/jboss/msc/service/Service;)Lorg/jboss/msc/service/ServiceBuilder;
       8: getstatic     #41                 // Field org/jboss/as/txn/service/TxnServices.JBOSS_TXN_TRANSACTION_MANAGER:Lorg/jboss/msc/service/ServiceName;
      11: aload_3
      12: getfield      #4                  // Field transactionManager:Lorg/jboss/msc/inject/Injector;
      15: invokeinterface #42,  3           // InterfaceMethod org/jboss/msc/service/ServiceBuilder.addDependency:(Lorg/jboss/msc/service/ServiceName;Lorg/jboss/msc/inject/Injector;)Lorg/jboss/msc/service/ServiceBuilder;
      20: aload_1
      21: ldc           #43                 // class org/apache/activemq/artemis/core/server/ActiveMQServer
      23: aload_3
      24: getfield      #8                  // Field activeMQServer:Lorg/jboss/msc/value/InjectedValue;
      27: invokeinterface #44,  4           // InterfaceMethod org/jboss/msc/service/ServiceBuilder.addDependency:(Lorg/jboss/msc/service/ServiceName;Ljava/lang/Class;Lorg/jboss/msc/inject/Injector;)Lorg/jboss/msc/service/ServiceBuilder;
      32: aload_1
      33: invokestatic  #45                 // Method org/wildfly/extension/messaging/activemq/ActiveMQActivationService.getServiceName:(Lorg/jboss/msc/service/ServiceName;)Lorg/jboss/msc/service/ServiceName;
      36: invokeinterface #46,  2           // InterfaceMethod org/jboss/msc/service/ServiceBuilder.addDependency:(Lorg/jboss/msc/service/ServiceName;)Lorg/jboss/msc/service/ServiceBuilder;
      41: aload_1
      42: invokestatic  #47                 // Method org/wildfly/extension/messaging/activemq/jms/JMSServices.getJmsManagerBaseServiceName:(Lorg/jboss/msc/service/ServiceName;)Lorg/jboss/msc/service/ServiceName;
      45: invokeinterface #46,  2           // InterfaceMethod org/jboss/msc/service/ServiceBuilder.addDependency:(Lorg/jboss/msc/service/ServiceName;)Lorg/jboss/msc/service/ServiceBuilder;
      50: getstatic     #48                 // Field org/jboss/msc/service/ServiceController$Mode.PASSIVE:Lorg/jboss/msc/service/ServiceController$Mode;
      53: invokeinterface #49,  2           // InterfaceMethod org/jboss/msc/service/ServiceBuilder.setInitialMode:(Lorg/jboss/msc/service/ServiceController$Mode;)Lorg/jboss/msc/service/ServiceBuilder;
      58: astore        4
      60: aload         4
      62: invokeinterface #50,  1           // InterfaceMethod org/jboss/msc/service/ServiceBuilder.install:()Lorg/jboss/msc/service/ServiceController;
      67: pop
      68: return

  public java.lang.Void getValue() throws java.lang.IllegalStateException, java.lang.IllegalArgumentException;
    Code:
       0: aconst_null
       1: areturn

  public void start(org.jboss.msc.service.StartContext) throws org.jboss.msc.service.StartException;
    Code:
       0: aload_1
       1: invokeinterface #51,  1           // InterfaceMethod org/jboss/msc/service/StartContext.getChildTarget:()Lorg/jboss/msc/service/ServiceTarget;
       6: astore_2
       7: aload_0
       8: aload_2
       9: aload_1
      10: invokeinterface #52,  1           // InterfaceMethod org/jboss/msc/service/StartContext.getController:()Lorg/jboss/msc/service/ServiceController;
      15: invokeinterface #53,  1           // InterfaceMethod org/jboss/msc/service/ServiceController.getServiceContainer:()Lorg/jboss/msc/service/ServiceContainer;
      20: invokespecial #54                 // Method createService:(Lorg/jboss/msc/service/ServiceTarget;Lorg/jboss/msc/service/ServiceContainer;)V
      23: goto          39
      26: astore_3
      27: getstatic     #56                 // Field org/wildfly/extension/messaging/activemq/logging/MessagingLogger.ROOT_LOGGER:Lorg/wildfly/extension/messaging/activemq/logging/MessagingLogger;
      30: aload_3
      31: ldc           #57                 // String resource adapter
      33: invokeinterface #58,  3           // InterfaceMethod org/wildfly/extension/messaging/activemq/logging/MessagingLogger.failedToCreate:(Ljava/lang/Throwable;Ljava/lang/String;)Lorg/jboss/msc/service/StartException;
      38: athrow
      39: return
    Exception table:
       from    to  target type
           7    23    26   Class java/lang/Exception

  private void createService(org.jboss.msc.service.ServiceTarget, org.jboss.msc.service.ServiceContainer) throws java.lang.Exception;
    Code:
       0: aconst_null
       1: astore_3
       2: aconst_null
       3: astore        4
       5: new           #29                 // class java/util/ArrayList
       8: dup
       9: invokespecial #30                 // Method java/util/ArrayList."<init>":()V
      12: astore        5
      14: new           #59                 // class java/lang/StringBuilder
      17: dup
      18: invokespecial #60                 // Method java/lang/StringBuilder."<init>":()V
      21: astore        6
      23: new           #59                 // class java/lang/StringBuilder
      26: dup
      27: invokespecial #60                 // Method java/lang/StringBuilder."<init>":()V
      30: astore        7
      32: aload_0
      33: getfield      #11                 // Field discoveryGroupName:Ljava/lang/String;
      36: ifnonnull     138
      39: aload_0
      40: getfield      #10                 // Field connectors:Ljava/util/List;
      43: invokeinterface #61,  1           // InterfaceMethod java/util/List.isEmpty:()Z
      48: ifeq          138
      51: aload_0
      52: getfield      #22                 // Field pickAnyConnectors:Z
      55: ifeq          138
      58: aload_0
      59: getfield      #8                  // Field activeMQServer:Lorg/jboss/msc/value/InjectedValue;
      62: invokevirtual #62                 // Method org/jboss/msc/value/InjectedValue.getValue:()Ljava/lang/Object;
      65: checkcast     #43                 // class org/apache/activemq/artemis/core/server/ActiveMQServer
      68: invokeinterface #63,  1           // InterfaceMethod org/apache/activemq/artemis/core/server/ActiveMQServer.getConfiguration:()Lorg/apache/activemq/artemis/core/config/Configuration;
      73: invokeinterface #64,  1           // InterfaceMethod org/apache/activemq/artemis/core/config/Configuration.getConnectorConfigurations:()Ljava/util/Map;
      78: invokeinterface #65,  1           // InterfaceMethod java/util/Map.keySet:()Ljava/util/Set;
      83: astore        8
      85: aload         8
      87: invokeinterface #66,  1           // InterfaceMethod java/util/Set.size:()I
      92: ifle          138
      95: aload         8
      97: invokeinterface #67,  1           // InterfaceMethod java/util/Set.iterator:()Ljava/util/Iterator;
     102: invokeinterface #68,  1           // InterfaceMethod java/util/Iterator.next:()Ljava/lang/Object;
     107: checkcast     #27                 // class java/lang/String
     110: astore        9
     112: getstatic     #56                 // Field org/wildfly/extension/messaging/activemq/logging/MessagingLogger.ROOT_LOGGER:Lorg/wildfly/extension/messaging/activemq/logging/MessagingLogger;
     115: aload_0
     116: getfield      #9                  // Field name:Ljava/lang/String;
     119: aload         9
     121: invokeinterface #69,  3           // InterfaceMethod org/wildfly/extension/messaging/activemq/logging/MessagingLogger.connectorForPooledConnectionFactory:(Ljava/lang/String;Ljava/lang/String;)V
     126: aload_0
     127: getfield      #10                 // Field connectors:Ljava/util/List;
     130: aload         9
     132: invokeinterface #70,  2           // InterfaceMethod java/util/List.add:(Ljava/lang/Object;)Z
     137: pop
     138: aload_0
     139: getfield      #10                 // Field connectors:Ljava/util/List;
     142: invokeinterface #71,  1           // InterfaceMethod java/util/List.iterator:()Ljava/util/Iterator;
     147: astore        8
     149: aload         8
     151: invokeinterface #72,  1           // InterfaceMethod java/util/Iterator.hasNext:()Z
     156: ifeq          353
     159: aload         8
     161: invokeinterface #68,  1           // InterfaceMethod java/util/Iterator.next:()Ljava/lang/Object;
     166: checkcast     #27                 // class java/lang/String
     169: astore        9
     171: aload_0
     172: getfield      #8                  // Field activeMQServer:Lorg/jboss/msc/value/InjectedValue;
     175: invokevirtual #62                 // Method org/jboss/msc/value/InjectedValue.getValue:()Ljava/lang/Object;
     178: checkcast     #43                 // class org/apache/activemq/artemis/core/server/ActiveMQServer
     181: invokeinterface #63,  1           // InterfaceMethod org/apache/activemq/artemis/core/server/ActiveMQServer.getConfiguration:()Lorg/apache/activemq/artemis/core/config/Configuration;
     186: invokeinterface #64,  1           // InterfaceMethod org/apache/activemq/artemis/core/config/Configuration.getConnectorConfigurations:()Ljava/util/Map;
     191: aload         9
     193: invokeinterface #73,  2           // InterfaceMethod java/util/Map.get:(Ljava/lang/Object;)Ljava/lang/Object;
     198: checkcast     #74                 // class org/apache/activemq/artemis/api/core/TransportConfiguration
     201: astore        10
     203: aload         10
     205: ifnonnull     219
     208: getstatic     #56                 // Field org/wildfly/extension/messaging/activemq/logging/MessagingLogger.ROOT_LOGGER:Lorg/wildfly/extension/messaging/activemq/logging/MessagingLogger;
     211: aload         9
     213: invokeinterface #75,  2           // InterfaceMethod org/wildfly/extension/messaging/activemq/logging/MessagingLogger.connectorNotDefined:(Ljava/lang/String;)Ljava/lang/IllegalStateException;
     218: athrow
     219: aload         6
     221: invokevirtual #76                 // Method java/lang/StringBuilder.length:()I
     224: ifle          243
     227: aload         6
     229: ldc           #77                 // String ,
     231: invokevirtual #78                 // Method java/lang/StringBuilder.append:(Ljava/lang/String;)Ljava/lang/StringBuilder;
     234: pop
     235: aload         7
     237: ldc           #77                 // String ,
     239: invokevirtual #78                 // Method java/lang/StringBuilder.append:(Ljava/lang/String;)Ljava/lang/StringBuilder;
     242: pop
     243: aload         6
     245: aload         10
     247: invokevirtual #79                 // Method org/apache/activemq/artemis/api/core/TransportConfiguration.getFactoryClassName:()Ljava/lang/String;
     250: invokevirtual #78                 // Method java/lang/StringBuilder.append:(Ljava/lang/String;)Ljava/lang/StringBuilder;
     253: pop
     254: aload         10
     256: invokevirtual #80                 // Method org/apache/activemq/artemis/api/core/TransportConfiguration.getParams:()Ljava/util/Map;
     259: astore        11
     261: iconst_0
     262: istore        12
     264: aload         11
     266: invokeinterface #81,  1           // InterfaceMethod java/util/Map.entrySet:()Ljava/util/Set;
     271: invokeinterface #67,  1           // InterfaceMethod java/util/Set.iterator:()Ljava/util/Iterator;
     276: astore        13
     278: aload         13
     280: invokeinterface #72,  1           // InterfaceMethod java/util/Iterator.hasNext:()Z
     285: ifeq          350
     288: aload         13
     290: invokeinterface #68,  1           // InterfaceMethod java/util/Iterator.next:()Ljava/lang/Object;
     295: checkcast     #82                 // class java/util/Map$Entry
     298: astore        14
     300: iload         12
     302: ifeq          313
     305: aload         7
     307: ldc           #83                 // String ;
     309: invokevirtual #78                 // Method java/lang/StringBuilder.append:(Ljava/lang/String;)Ljava/lang/StringBuilder;
     312: pop
     313: aload         7
     315: aload         14
     317: invokeinterface #84,  1           // InterfaceMethod java/util/Map$Entry.getKey:()Ljava/lang/Object;
     322: checkcast     #27                 // class java/lang/String
     325: invokevirtual #78                 // Method java/lang/StringBuilder.append:(Ljava/lang/String;)Ljava/lang/StringBuilder;
     328: ldc           #85                 // String =
     330: invokevirtual #78                 // Method java/lang/StringBuilder.append:(Ljava/lang/String;)Ljava/lang/StringBuilder;
     333: aload         14
     335: invokeinterface #86,  1           // InterfaceMethod java/util/Map$Entry.getValue:()Ljava/lang/Object;
     340: invokevirtual #87                 // Method java/lang/StringBuilder.append:(Ljava/lang/Object;)Ljava/lang/StringBuilder;
     343: pop
     344: iconst_1
     345: istore        12
     347: goto          278
     350: goto          149
     353: aload         6
     355: invokevirtual #76                 // Method java/lang/StringBuilder.length:()I
     358: ifle          381
     361: aload         5
     363: ldc           #88                 // String connectorClassName
     365: ldc           #89                 // String java.lang.String
     367: aload         6
     369: invokevirtual #90                 // Method java/lang/StringBuilder.toString:()Ljava/lang/String;
     372: invokestatic  #91                 // Method simpleProperty15:(Ljava/lang/String;Ljava/lang/String;Ljava/lang/String;)Lorg/jboss/jca/common/api/metadata/spec/ConfigProperty;
     375: invokeinterface #70,  2           // InterfaceMethod java/util/List.add:(Ljava/lang/Object;)Z
     380: pop
     381: aload         7
     383: invokevirtual #76                 // Method java/lang/StringBuilder.length:()I
     386: ifle          409
     389: aload         5
     391: ldc           #92                 // String connectionParameters
     393: ldc           #89                 // String java.lang.String
     395: aload         7
     397: invokevirtual #90                 // Method java/lang/StringBuilder.toString:()Ljava/lang/String;
     400: invokestatic  #91                 // Method simpleProperty15:(Ljava/lang/String;Ljava/lang/String;Ljava/lang/String;)Lorg/jboss/jca/common/api/metadata/spec/ConfigProperty;
     403: invokeinterface #70,  2           // InterfaceMethod java/util/List.add:(Ljava/lang/Object;)Z
     408: pop
     409: aload_0
     410: getfield      #11                 // Field discoveryGroupName:Ljava/lang/String;
     413: ifnull        738
     416: aload_0
     417: getfield      #8                  // Field activeMQServer:Lorg/jboss/msc/value/InjectedValue;
     420: invokevirtual #62                 // Method org/jboss/msc/value/InjectedValue.getValue:()Ljava/lang/Object;
     423: checkcast     #43                 // class org/apache/activemq/artemis/core/server/ActiveMQServer
     426: invokeinterface #63,  1           // InterfaceMethod org/apache/activemq/artemis/core/server/ActiveMQServer.getConfiguration:()Lorg/apache/activemq/artemis/core/config/Configuration;
     431: invokeinterface #93,  1           // InterfaceMethod org/apache/activemq/artemis/core/config/Configuration.getDiscoveryGroupConfigurations:()Ljava/util/Map;
     436: aload_0
     437: getfield      #11                 // Field discoveryGroupName:Ljava/lang/String;
     440: invokeinterface #73,  2           // InterfaceMethod java/util/Map.get:(Ljava/lang/Object;)Ljava/lang/Object;
     445: checkcast     #94                 // class org/apache/activemq/artemis/api/core/DiscoveryGroupConfiguration
     448: astore        8
     450: aload         8
     452: invokevirtual #95                 // Method org/apache/activemq/artemis/api/core/DiscoveryGroupConfiguration.getBroadcastEndpointFactory:()Lorg/apache/activemq/artemis/api/core/BroadcastEndpointFactory;
     455: astore        9
     457: aload         9
     459: instanceof    #96                 // class org/apache/activemq/artemis/api/core/UDPBroadcastEndpointFactory
     462: ifeq          571
     465: aload         9
     467: checkcast     #96                 // class org/apache/activemq/artemis/api/core/UDPBroadcastEndpointFactory
     470: astore        10
     472: aload         5
     474: ldc           #97                 // String discoveryAddress
     476: ldc           #89                 // String java.lang.String
     478: aload         10
     480: invokevirtual #98                 // Method org/apache/activemq/artemis/api/core/UDPBroadcastEndpointFactory.getGroupAddress:()Ljava/lang/String;
     483: invokestatic  #91                 // Method simpleProperty15:(Ljava/lang/String;Ljava/lang/String;Ljava/lang/String;)Lorg/jboss/jca/common/api/metadata/spec/ConfigProperty;
     486: invokeinterface #70,  2           // InterfaceMethod java/util/List.add:(Ljava/lang/Object;)Z
     491: pop
     492: aload         5
     494: ldc           #99                 // String discoveryPort
     496: ldc           #100                // String java.lang.Integer
     498: new           #59                 // class java/lang/StringBuilder
     501: dup
     502: invokespecial #60                 // Method java/lang/StringBuilder."<init>":()V
     505: ldc           #101                // String
     507: invokevirtual #78                 // Method java/lang/StringBuilder.append:(Ljava/lang/String;)Ljava/lang/StringBuilder;
     510: aload         10
     512: invokevirtual #102                // Method org/apache/activemq/artemis/api/core/UDPBroadcastEndpointFactory.getGroupPort:()I
     515: invokevirtual #103                // Method java/lang/StringBuilder.append:(I)Ljava/lang/StringBuilder;
     518: invokevirtual #90                 // Method java/lang/StringBuilder.toString:()Ljava/lang/String;
     521: invokestatic  #91                 // Method simpleProperty15:(Ljava/lang/String;Ljava/lang/String;Ljava/lang/String;)Lorg/jboss/jca/common/api/metadata/spec/ConfigProperty;
     524: invokeinterface #70,  2           // InterfaceMethod java/util/List.add:(Ljava/lang/Object;)Z
     529: pop
     530: aload         5
     532: ldc           #104                // String discoveryLocalBindAddress
     534: ldc           #89                 // String java.lang.String
     536: new           #59                 // class java/lang/StringBuilder
     539: dup
     540: invokespecial #60                 // Method java/lang/StringBuilder."<init>":()V
     543: ldc           #101                // String
     545: invokevirtual #78                 // Method java/lang/StringBuilder.append:(Ljava/lang/String;)Ljava/lang/StringBuilder;
     548: aload         10
     550: invokevirtual #105                // Method org/apache/activemq/artemis/api/core/UDPBroadcastEndpointFactory.getLocalBindAddress:()Ljava/lang/String;
     553: invokevirtual #78                 // Method java/lang/StringBuilder.append:(Ljava/lang/String;)Ljava/lang/StringBuilder;
     556: invokevirtual #90                 // Method java/lang/StringBuilder.toString:()Ljava/lang/String;
     559: invokestatic  #91                 // Method simpleProperty15:(Ljava/lang/String;Ljava/lang/String;Ljava/lang/String;)Lorg/jboss/jca/common/api/metadata/spec/ConfigProperty;
     562: invokeinterface #70,  2           // InterfaceMethod java/util/List.add:(Ljava/lang/Object;)Z
     567: pop
     568: goto          662
     571: aload         9
     573: instanceof    #106                // class org/apache/activemq/artemis/api/core/ChannelBroadcastEndpointFactory
     576: ifeq          662
     579: aload         5
     581: ldc           #107                // String jgroupsChannelLocatorClass
     583: ldc           #89                 // String java.lang.String
     585: ldc           #108                // class org/wildfly/extension/messaging/activemq/JGroupsChannelLocator
     587: invokevirtual #109                // Method java/lang/Class.getName:()Ljava/lang/String;
     590: invokestatic  #91                 // Method simpleProperty15:(Ljava/lang/String;Ljava/lang/String;Ljava/lang/String;)Lorg/jboss/jca/common/api/metadata/spec/ConfigProperty;
     593: invokeinterface #70,  2           // InterfaceMethod java/util/List.add:(Ljava/lang/Object;)Z
     598: pop
     599: aload         5
     601: ldc           #110                // String jgroupsChannelName
     603: ldc           #89                 // String java.lang.String
     605: aload_0
     606: getfield      #13                 // Field jgroupsChannelName:Ljava/lang/String;
     609: invokestatic  #91                 // Method simpleProperty15:(Ljava/lang/String;Ljava/lang/String;Ljava/lang/String;)Lorg/jboss/jca/common/api/metadata/spec/ConfigProperty;
     612: invokeinterface #70,  2           // InterfaceMethod java/util/List.add:(Ljava/lang/Object;)Z
     617: pop
     618: aload         5
     620: ldc           #111                // String jgroupsChannelRefName
     622: ldc           #89                 // String java.lang.String
     624: new           #59                 // class java/lang/StringBuilder
     627: dup
     628: invokespecial #60                 // Method java/lang/StringBuilder."<init>":()V
     631: aload_0
     632: getfield      #12                 // Field serverName:Ljava/lang/String;
     635: invokevirtual #78                 // Method java/lang/StringBuilder.append:(Ljava/lang/String;)Ljava/lang/StringBuilder;
     638: bipush        47
     640: invokevirtual #112                // Method java/lang/StringBuilder.append:(C)Ljava/lang/StringBuilder;
     643: aload_0
     644: getfield      #13                 // Field jgroupsChannelName:Ljava/lang/String;
     647: invokevirtual #78                 // Method java/lang/StringBuilder.append:(Ljava/lang/String;)Ljava/lang/StringBuilder;
     650: invokevirtual #90                 // Method java/lang/StringBuilder.toString:()Ljava/lang/String;
     653: invokestatic  #91                 // Method simpleProperty15:(Ljava/lang/String;Ljava/lang/String;Ljava/lang/String;)Lorg/jboss/jca/common/api/metadata/spec/ConfigProperty;
     656: invokeinterface #70,  2           // InterfaceMethod java/util/List.add:(Ljava/lang/Object;)Z
     661: pop
     662: aload         5
     664: ldc           #113                // String discoveryInitialWaitTimeout
     666: ldc           #114                // String java.lang.Long
     668: new           #59                 // class java/lang/StringBuilder
     671: dup
     672: invokespecial #60                 // Method java/lang/StringBuilder."<init>":()V
     675: ldc           #101                // String
     677: invokevirtual #78                 // Method java/lang/StringBuilder.append:(Ljava/lang/String;)Ljava/lang/StringBuilder;
     680: aload         8
     682: invokevirtual #115                // Method org/apache/activemq/artemis/api/core/DiscoveryGroupConfiguration.getDiscoveryInitialWaitTimeout:()J
     685: invokevirtual #116                // Method java/lang/StringBuilder.append:(J)Ljava/lang/StringBuilder;
     688: invokevirtual #90                 // Method java/lang/StringBuilder.toString:()Ljava/lang/String;
     691: invokestatic  #91                 // Method simpleProperty15:(Ljava/lang/String;Ljava/lang/String;Ljava/lang/String;)Lorg/jboss/jca/common/api/metadata/spec/ConfigProperty;
     694: invokeinterface #70,  2           // InterfaceMethod java/util/List.add:(Ljava/lang/Object;)Z
     699: pop
     700: aload         5
     702: ldc           #117                // String discoveryRefreshTimeout
     704: ldc           #114                // String java.lang.Long
     706: new           #59                 // class java/lang/StringBuilder
     709: dup
     710: invokespecial #60                 // Method java/lang/StringBuilder."<init>":()V
     713: ldc           #101                // String
     715: invokevirtual #78                 // Method java/lang/StringBuilder.append:(Ljava/lang/String;)Ljava/lang/StringBuilder;
     718: aload         8
     720: invokevirtual #118                // Method org/apache/activemq/artemis/api/core/DiscoveryGroupConfiguration.getRefreshTimeout:()J
     723: invokevirtual #116                // Method java/lang/StringBuilder.append:(J)Ljava/lang/StringBuilder;
     726: invokevirtual #90                 // Method java/lang/StringBuilder.toString:()Ljava/lang/String;
     729: invokestatic  #91                 // Method simpleProperty15:(Ljava/lang/String;Ljava/lang/String;Ljava/lang/String;)Lorg/jboss/jca/common/api/metadata/spec/ConfigProperty;
     732: invokeinterface #70,  2           // InterfaceMethod java/util/List.add:(Ljava/lang/Object;)Z
     737: pop
     738: iconst_0
     739: istore        8
     741: ldc           #120                // String reconnectAttempts
     743: astore        9
     745: aload_0
     746: getfield      #14                 // Field adapterParams:Ljava/util/List;
     749: invokeinterface #71,  1           // InterfaceMethod java/util/List.iterator:()Ljava/util/Iterator;
     754: astore        10
     756: aload         10
     758: invokeinterface #72,  1           // InterfaceMethod java/util/Iterator.hasNext:()Z
     763: ifeq          822
     766: aload         10
     768: invokeinterface #68,  1           // InterfaceMethod java/util/Iterator.next:()Ljava/lang/Object;
     773: checkcast     #121                // class org/wildfly/extension/messaging/activemq/jms/PooledConnectionFactoryConfigProperties
     776: astore        11
     778: iload         8
     780: ldc           #120                // String reconnectAttempts
     782: aload         11
     784: invokevirtual #122                // Method org/wildfly/extension/messaging/activemq/jms/PooledConnectionFactoryConfigProperties.getName:()Ljava/lang/String;
     787: invokevirtual #123                // Method java/lang/String.equals:(Ljava/lang/Object;)Z
     790: ior
     791: istore        8
     793: aload         5
     795: aload         11
     797: invokevirtual #122                // Method org/wildfly/extension/messaging/activemq/jms/PooledConnectionFactoryConfigProperties.getName:()Ljava/lang/String;
     800: aload         11
     802: invokevirtual #124                // Method org/wildfly/extension/messaging/activemq/jms/PooledConnectionFactoryConfigProperties.getType:()Ljava/lang/String;
     805: aload         11
     807: invokevirtual #125                // Method org/wildfly/extension/messaging/activemq/jms/PooledConnectionFactoryConfigProperties.getValue:()Ljava/lang/String;
     810: invokestatic  #91                 // Method simpleProperty15:(Ljava/lang/String;Ljava/lang/String;Ljava/lang/String;)Lorg/jboss/jca/common/api/metadata/spec/ConfigProperty;
     813: invokeinterface #70,  2           // InterfaceMethod java/util/List.add:(Ljava/lang/Object;)Z
     818: pop
     819: goto          756
     822: iload         8
     824: ifne          847
     827: aload         5
     829: ldc           #120                // String reconnectAttempts
     831: ldc           #126                // class java/lang/Integer
     833: invokevirtual #109                // Method java/lang/Class.getName:()Ljava/lang/String;
     836: ldc           #127                // String 5
     838: invokestatic  #91                 // Method simpleProperty15:(Ljava/lang/String;Ljava/lang/String;Ljava/lang/String;)Lorg/jboss/jca/common/api/metadata/spec/ConfigProperty;
     841: invokeinterface #70,  2           // InterfaceMethod java/util/List.add:(Ljava/lang/Object;)Z
     846: pop
     847: aload_2
     848: putstatic     #128                // Field org/wildfly/extension/messaging/activemq/jms/WildFlyRecoveryRegistry.container:Lorg/jboss/msc/service/ServiceContainer;
     851: invokestatic  #129                // Method createOutbound:()Lorg/jboss/jca/common/api/metadata/spec/OutboundResourceAdapter;
     854: astore        10
     856: aload_0
     857: invokespecial #130                // Method createInbound:()Lorg/jboss/jca/common/api/metadata/spec/InboundResourceAdapter;
     860: astore        11
     862: aload_0
     863: aload         5
     865: aload         10
     867: aload         11
     869: invokespecial #131                // Method createResourceAdapter15:(Ljava/util/List;Lorg/jboss/jca/common/api/metadata/spec/OutboundResourceAdapter;Lorg/jboss/jca/common/api/metadata/spec/InboundResourceAdapter;)Lorg/jboss/jca/common/api/metadata/spec/ResourceAdapter;
     872: astore        12
     874: aload         12
     876: invokestatic  #132                // Method createConnector15:(Lorg/jboss/jca/common/api/metadata/spec/ResourceAdapter;)Lorg/jboss/jca/common/api/metadata/spec/Connector;
     879: astore        13
     881: aload_0
     882: getfield      #17                 // Field txSupport:Ljava/lang/String;
     885: invokestatic  #133                // Method getTransactionSupport:(Ljava/lang/String;)Lorg/jboss/jca/common/api/metadata/common/TransactionSupportEnum;
     888: astore        14
     890: aload         14
     892: aload_0
     893: getfield      #23                 // Field bindInfo:Lorg/jboss/as/naming/deployment/ContextNames$BindInfo;
     896: invokevirtual #134                // Method org/jboss/as/naming/deployment/ContextNames$BindInfo.getBindName:()Ljava/lang/String;
     899: aload_0
     900: getfield      #18                 // Field minPoolSize:I
     903: aload_0
     904: getfield      #19                 // Field maxPoolSize:I
     907: aload_0
     908: getfield      #20                 // Field managedConnectionPoolClassName:Ljava/lang/String;
     911: aload_0
     912: getfield      #21                 // Field enlistmentTrace:Ljava/lang/Boolean;
     915: invokestatic  #135                // Method createConnDef:(Lorg/jboss/jca/common/api/metadata/common/TransactionSupportEnum;Ljava/lang/String;IILjava/lang/String;Ljava/lang/Boolean;)Lorg/jboss/jca/common/api/metadata/resourceadapter/ConnectionDefinition;
     918: astore        15
     920: aload         15
     922: aload         14
     924: invokestatic  #136                // Method createActivation:(Lorg/jboss/jca/common/api/metadata/resourceadapter/ConnectionDefinition;Lorg/jboss/jca/common/api/metadata/common/TransactionSupportEnum;)Lorg/jboss/jca/common/api/metadata/resourceadapter/Activation;
     927: astore        16
     929: new           #137                // class org/jboss/as/connector/services/resourceadapters/ResourceAdapterActivatorService
     932: dup
     933: aload         13
     935: aload         16
     937: ldc           #36                 // class org/wildfly/extension/messaging/activemq/jms/PooledConnectionFactoryService
     939: invokevirtual #138                // Method java/lang/Class.getClassLoader:()Ljava/lang/ClassLoader;
     942: aload_0
     943: getfield      #9                  // Field name:Ljava/lang/String;
     946: invokespecial #139                // Method org/jboss/as/connector/services/resourceadapters/ResourceAdapterActivatorService."<init>":(Lorg/jboss/jca/common/api/metadata/spec/Connector;Lorg/jboss/jca/common/api/metadata/resourceadapter/Activation;Ljava/lang/ClassLoader;Ljava/lang/String;)V
     949: astore        17
     951: aload         17
     953: aload_0
     954: getfield      #23                 // Field bindInfo:Lorg/jboss/as/naming/deployment/ContextNames$BindInfo;
     957: invokevirtual #140                // Method org/jboss/as/connector/services/resourceadapters/ResourceAdapterActivatorService.setBindInfo:(Lorg/jboss/as/naming/deployment/ContextNames$BindInfo;)V
     960: aload         17
     962: aload_0
     963: getfield      #16                 // Field createBinderService:Z
     966: invokevirtual #141                // Method org/jboss/as/connector/services/resourceadapters/ResourceAdapterActivatorService.setCreateBinderService:(Z)V
     969: aload_1
     970: getstatic     #142                // Field org/jboss/as/connector/util/ConnectorServices.RESOURCE_ADAPTER_ACTIVATOR_SERVICE:Lorg/jboss/msc/service/ServiceName;
     973: iconst_1
     974: anewarray     #27                 // class java/lang/String
     977: dup
     978: iconst_0
     979: aload_0
     980: getfield      #9                  // Field name:Ljava/lang/String;
     983: aastore
     984: invokevirtual #35                 // Method org/jboss/msc/service/ServiceName.append:([Ljava/lang/String;)Lorg/jboss/msc/service/ServiceName;
     987: aload         17
     989: invokeinterface #40,  3           // InterfaceMethod org/jboss/msc/service/ServiceTarget.addService:(Lorg/jboss/msc/service/ServiceName;Lorg/jboss/msc/service/Service;)Lorg/jboss/msc/service/ServiceBuilder;
     994: aload         17
     996: invokevirtual #143                // Method org/jboss/as/connector/services/resourceadapters/ResourceAdapterActivatorService.getExecutorServiceInjector:()Lorg/jboss/msc/inject/Injector;
     999: iconst_0
    1000: invokestatic  #144                // Method org/jboss/as/server/Services.addServerExecutorDependency:(Lorg/jboss/msc/service/ServiceBuilder;Lorg/jboss/msc/inject/Injector;Z)Lorg/jboss/msc/service/ServiceBuilder;
    1003: aload_0
    1004: getfield      #12                 // Field serverName:Ljava/lang/String;
    1007: invokestatic  #33                 // Method org/wildfly/extension/messaging/activemq/MessagingServices.getActiveMQServiceName:(Ljava/lang/String;)Lorg/jboss/msc/service/ServiceName;
    1010: invokestatic  #45                 // Method org/wildfly/extension/messaging/activemq/ActiveMQActivationService.getServiceName:(Lorg/jboss/msc/service/ServiceName;)Lorg/jboss/msc/service/ServiceName;
    1013: invokeinterface #46,  2           // InterfaceMethod org/jboss/msc/service/ServiceBuilder.addDependency:(Lorg/jboss/msc/service/ServiceName;)Lorg/jboss/msc/service/ServiceBuilder;
    1018: getstatic     #145                // Field org/jboss/as/connector/util/ConnectorServices.IRONJACAMAR_MDR:Lorg/jboss/msc/service/ServiceName;
    1021: ldc           #146                // class org/jboss/as/connector/services/mdr/AS7MetadataRepository
    1023: aload         17
    1025: invokevirtual #147                // Method org/jboss/as/connector/services/resourceadapters/ResourceAdapterActivatorService.getMdrInjector:()Lorg/jboss/msc/inject/Injector;
    1028: invokeinterface #44,  4           // InterfaceMethod org/jboss/msc/service/ServiceBuilder.addDependency:(Lorg/jboss/msc/service/ServiceName;Ljava/lang/Class;Lorg/jboss/msc/inject/Injector;)Lorg/jboss/msc/service/ServiceBuilder;
    1033: getstatic     #148                // Field org/jboss/as/connector/util/ConnectorServices.RA_REPOSITORY_SERVICE:Lorg/jboss/msc/service/ServiceName;
    1036: ldc           #149                // class org/jboss/jca/core/spi/rar/ResourceAdapterRepository
    1038: aload         17
    1040: invokevirtual #150                // Method org/jboss/as/connector/services/resourceadapters/ResourceAdapterActivatorService.getRaRepositoryInjector:()Lorg/jboss/msc/inject/Injector;
    1043: invokeinterface #44,  4           // InterfaceMethod org/jboss/msc/service/ServiceBuilder.addDependency:(Lorg/jboss/msc/service/ServiceName;Ljava/lang/Class;Lorg/jboss/msc/inject/Injector;)Lorg/jboss/msc/service/ServiceBuilder;
    1048: getstatic     #151                // Field org/jboss/as/connector/util/ConnectorServices.MANAGEMENT_REPOSITORY_SERVICE:Lorg/jboss/msc/service/ServiceName;
    1051: ldc           #152                // class org/jboss/jca/core/api/management/ManagementRepository
    1053: aload         17
    1055: invokevirtual #153                // Method org/jboss/as/connector/services/resourceadapters/ResourceAdapterActivatorService.getManagementRepositoryInjector:()Lorg/jboss/msc/inject/Injector;
    1058: invokeinterface #44,  4           // InterfaceMethod org/jboss/msc/service/ServiceBuilder.addDependency:(Lorg/jboss/msc/service/ServiceName;Ljava/lang/Class;Lorg/jboss/msc/inject/Injector;)Lorg/jboss/msc/service/ServiceBuilder;
    1063: getstatic     #154                // Field org/jboss/as/connector/util/ConnectorServices.RESOURCE_ADAPTER_REGISTRY_SERVICE:Lorg/jboss/msc/service/ServiceName;
    1066: ldc           #155                // class org/jboss/as/connector/services/resourceadapters/deployment/registry/ResourceAdapterDeploymentRegistry
    1068: aload         17
    1070: invokevirtual #156                // Method org/jboss/as/connector/services/resourceadapters/ResourceAdapterActivatorService.getRegistryInjector:()Lorg/jboss/msc/inject/Injector;
    1073: invokeinterface #44,  4           // InterfaceMethod org/jboss/msc/service/ServiceBuilder.addDependency:(Lorg/jboss/msc/service/ServiceName;Ljava/lang/Class;Lorg/jboss/msc/inject/Injector;)Lorg/jboss/msc/service/ServiceBuilder;
    1078: getstatic     #157                // Field org/jboss/as/connector/util/ConnectorServices.TRANSACTION_INTEGRATION_SERVICE:Lorg/jboss/msc/service/ServiceName;
    1081: ldc           #158                // class org/jboss/jca/core/spi/transaction/TransactionIntegration
    1083: aload         17
    1085: invokevirtual #159                // Method org/jboss/as/connector/services/resourceadapters/ResourceAdapterActivatorService.getTxIntegrationInjector:()Lorg/jboss/msc/inject/Injector;
    1088: invokeinterface #44,  4           // InterfaceMethod org/jboss/msc/service/ServiceBuilder.addDependency:(Lorg/jboss/msc/service/ServiceName;Ljava/lang/Class;Lorg/jboss/msc/inject/Injector;)Lorg/jboss/msc/service/ServiceBuilder;
    1093: getstatic     #160                // Field org/jboss/as/connector/util/ConnectorServices.CONNECTOR_CONFIG_SERVICE:Lorg/jboss/msc/service/ServiceName;
    1096: ldc           #161                // class org/jboss/as/connector/subsystems/jca/JcaSubsystemConfiguration
    1098: aload         17
    1100: invokevirtual #162                // Method org/jboss/as/connector/services/resourceadapters/ResourceAdapterActivatorService.getConfigInjector:()Lorg/jboss/msc/inject/Injector;
    1103: invokeinterface #44,  4           // InterfaceMethod org/jboss/msc/service/ServiceBuilder.addDependency:(Lorg/jboss/msc/service/ServiceName;Ljava/lang/Class;Lorg/jboss/msc/inject/Injector;)Lorg/jboss/msc/service/ServiceBuilder;
    1108: getstatic     #163                // Field org/jboss/as/security/service/SubjectFactoryService.SERVICE_NAME:Lorg/jboss/msc/service/ServiceName;
    1111: ldc           #164                // class org/jboss/security/SubjectFactory
    1113: aload         17
    1115: invokevirtual #165                // Method org/jboss/as/connector/services/resourceadapters/ResourceAdapterActivatorService.getSubjectFactoryInjector:()Lorg/jboss/msc/inject/Injector;
    1118: invokeinterface #44,  4           // InterfaceMethod org/jboss/msc/service/ServiceBuilder.addDependency:(Lorg/jboss/msc/service/ServiceName;Ljava/lang/Class;Lorg/jboss/msc/inject/Injector;)Lorg/jboss/msc/service/ServiceBuilder;
    1123: getstatic     #166                // Field org/jboss/as/connector/util/ConnectorServices.CCM_SERVICE:Lorg/jboss/msc/service/ServiceName;
    1126: ldc           #167                // class org/jboss/jca/core/api/connectionmanager/ccm/CachedConnectionManager
    1128: aload         17
    1130: invokevirtual #168                // Method org/jboss/as/connector/services/resourceadapters/ResourceAdapterActivatorService.getCcmInjector:()Lorg/jboss/msc/inject/Injector;
    1133: invokeinterface #44,  4           // InterfaceMethod org/jboss/msc/service/ServiceBuilder.addDependency:(Lorg/jboss/msc/service/ServiceName;Ljava/lang/Class;Lorg/jboss/msc/inject/Injector;)Lorg/jboss/msc/service/ServiceBuilder;
    1138: getstatic     #169                // Field org/jboss/as/naming/service/NamingService.SERVICE_NAME:Lorg/jboss/msc/service/ServiceName;
    1141: invokeinterface #46,  2           // InterfaceMethod org/jboss/msc/service/ServiceBuilder.addDependency:(Lorg/jboss/msc/service/ServiceName;)Lorg/jboss/msc/service/ServiceBuilder;
    1146: getstatic     #41                 // Field org/jboss/as/txn/service/TxnServices.JBOSS_TXN_TRANSACTION_MANAGER:Lorg/jboss/msc/service/ServiceName;
    1149: invokeinterface #46,  2           // InterfaceMethod org/jboss/msc/service/ServiceBuilder.addDependency:(Lorg/jboss/msc/service/ServiceName;)Lorg/jboss/msc/service/ServiceBuilder;
    1154: getstatic     #170                // Field org/jboss/as/connector/util/ConnectorServices.BOOTSTRAP_CONTEXT_SERVICE:Lorg/jboss/msc/service/ServiceName;
    1157: iconst_1
    1158: anewarray     #27                 // class java/lang/String
    1161: dup
    1162: iconst_0
    1163: ldc           #171                // String default
    1165: aastore
    1166: invokevirtual #35                 // Method org/jboss/msc/service/ServiceName.append:([Ljava/lang/String;)Lorg/jboss/msc/service/ServiceName;
    1169: invokeinterface #46,  2           // InterfaceMethod org/jboss/msc/service/ServiceBuilder.addDependency:(Lorg/jboss/msc/service/ServiceName;)Lorg/jboss/msc/service/ServiceBuilder;
    1174: getstatic     #48                 // Field org/jboss/msc/service/ServiceController$Mode.PASSIVE:Lorg/jboss/msc/service/ServiceController$Mode;
    1177: invokeinterface #49,  2           // InterfaceMethod org/jboss/msc/service/ServiceBuilder.setInitialMode:(Lorg/jboss/msc/service/ServiceController$Mode;)Lorg/jboss/msc/service/ServiceBuilder;
    1182: invokeinterface #50,  1           // InterfaceMethod org/jboss/msc/service/ServiceBuilder.install:()Lorg/jboss/msc/service/ServiceController;
    1187: astore        18
    1189: aload_0
    1190: aload_0
    1191: getfield      #23                 // Field bindInfo:Lorg/jboss/as/naming/deployment/ContextNames$BindInfo;
    1194: aload_0
    1195: getfield      #25                 // Field jndiAliases:Ljava/util/List;
    1198: aload         18
    1200: invokespecial #172                // Method createJNDIAliases:(Lorg/jboss/as/naming/deployment/ContextNames$BindInfo;Ljava/util/List;Lorg/jboss/msc/service/ServiceController;)V
    1203: aload_1
    1204: getstatic     #173                // Field org/jboss/as/connector/util/ConnectorServices.RESOURCE_ADAPTER_DEPLOYER_SERVICE_PREFIX:Lorg/jboss/msc/service/ServiceName;
    1207: iconst_1
    1208: anewarray     #27                 // class java/lang/String
    1211: dup
    1212: iconst_0
    1213: aload_0
    1214: getfield      #9                  // Field name:Ljava/lang/String;
    1217: aastore
    1218: invokevirtual #35                 // Method org/jboss/msc/service/ServiceName.append:([Ljava/lang/String;)Lorg/jboss/msc/service/ServiceName;
    1221: getstatic     #174                // Field org/jboss/msc/service/Service.NULL:Lorg/jboss/msc/service/Service;
    1224: invokeinterface #40,  3           // InterfaceMethod org/jboss/msc/service/ServiceTarget.addService:(Lorg/jboss/msc/service/ServiceName;Lorg/jboss/msc/service/Service;)Lorg/jboss/msc/service/ServiceBuilder;
    1229: invokeinterface #50,  1           // InterfaceMethod org/jboss/msc/service/ServiceBuilder.install:()Lorg/jboss/msc/service/ServiceController;
    1234: pop
    1235: aload_3
    1236: ifnull        1243
    1239: aload_3
    1240: invokevirtual #175                // Method java/io/InputStream.close:()V
    1243: aload         4
    1245: ifnull        1279
    1248: aload         4
    1250: invokevirtual #175                // Method java/io/InputStream.close:()V
    1253: goto          1279
    1256: astore        19
    1258: aload_3
    1259: ifnull        1266
    1262: aload_3
    1263: invokevirtual #175                // Method java/io/InputStream.close:()V
    1266: aload         4
    1268: ifnull        1276
    1271: aload         4
    1273: invokevirtual #175                // Method java/io/InputStream.close:()V
    1276: aload         19
    1278: athrow
    1279: return
    Exception table:
       from    to  target type
          14  1235  1256   any
        1256  1258  1256   any

  private void createJNDIAliases(org.jboss.as.naming.deployment.ContextNames$BindInfo, java.util.List<java.lang.String>, org.jboss.msc.service.ServiceController<org.jboss.as.connector.metadata.deployment.ResourceAdapterDeployment>);
    Code:
       0: aload_2
       1: invokeinterface #71,  1           // InterfaceMethod java/util/List.iterator:()Ljava/util/Iterator;
       6: astore        4
       8: aload         4
      10: invokeinterface #72,  1           // InterfaceMethod java/util/Iterator.hasNext:()Z
      15: ifeq          67
      18: aload         4
      20: invokeinterface #68,  1           // InterfaceMethod java/util/Iterator.next:()Ljava/lang/Object;
      25: checkcast     #27                 // class java/lang/String
      28: astore        5
      30: aload_3
      31: invokeinterface #53,  1           // InterfaceMethod org/jboss/msc/service/ServiceController.getServiceContainer:()Lorg/jboss/msc/service/ServiceContainer;
      36: aload         5
      38: invokestatic  #28                 // Method org/jboss/as/naming/deployment/ContextNames.bindInfoFor:(Ljava/lang/String;)Lorg/jboss/as/naming/deployment/ContextNames$BindInfo;
      41: invokevirtual #176                // Method org/jboss/as/naming/deployment/ContextNames$BindInfo.getBinderServiceName:()Lorg/jboss/msc/service/ServiceName;
      44: invokeinterface #177,  2          // InterfaceMethod org/jboss/msc/service/ServiceContainer.getService:(Lorg/jboss/msc/service/ServiceName;)Lorg/jboss/msc/service/ServiceController;
      49: ifnonnull     64
      52: aload_3
      53: invokeinterface #53,  1           // InterfaceMethod org/jboss/msc/service/ServiceController.getServiceContainer:()Lorg/jboss/msc/service/ServiceContainer;
      58: aload_1
      59: aload         5
      61: invokestatic  #178                // Method org/wildfly/extension/messaging/activemq/BinderServiceUtil.installAliasBinderService:(Lorg/jboss/msc/service/ServiceTarget;Lorg/jboss/as/naming/deployment/ContextNames$BindInfo;Ljava/lang/String;)V
      64: goto          8
      67: return

  private static org.jboss.jca.common.api.metadata.common.TransactionSupportEnum getTransactionSupport(java.lang.String);
    Code:
       0: aload_0
       1: invokestatic  #179                // Method org/jboss/jca/common/api/metadata/common/TransactionSupportEnum.valueOf:(Ljava/lang/String;)Lorg/jboss/jca/common/api/metadata/common/TransactionSupportEnum;
       4: areturn
       5: astore_1
       6: getstatic     #181                // Field org/jboss/jca/common/api/metadata/common/TransactionSupportEnum.LocalTransaction:Lorg/jboss/jca/common/api/metadata/common/TransactionSupportEnum;
       9: areturn
    Exception table:
       from    to  target type
           0     4     5   Class java/lang/RuntimeException

  private static org.jboss.jca.common.api.metadata.resourceadapter.Activation createActivation(org.jboss.jca.common.api.metadata.resourceadapter.ConnectionDefinition, org.jboss.jca.common.api.metadata.common.TransactionSupportEnum);
    Code:
       0: aload_0
       1: invokestatic  #182                // Method java/util/Collections.singletonList:(Ljava/lang/Object;)Ljava/util/List;
       4: astore_2
       5: new           #183                // class org/jboss/jca/common/metadata/resourceadapter/ActivationImpl
       8: dup
       9: aconst_null
      10: aconst_null
      11: aload_1
      12: aload_2
      13: invokestatic  #184                // Method java/util/Collections.emptyList:()Ljava/util/List;
      16: invokestatic  #185                // Method java/util/Collections.emptyMap:()Ljava/util/Map;
      19: invokestatic  #184                // Method java/util/Collections.emptyList:()Ljava/util/List;
      22: aconst_null
      23: aconst_null
      24: invokespecial #186                // Method org/jboss/jca/common/metadata/resourceadapter/ActivationImpl."<init>":(Ljava/lang/String;Ljava/lang/String;Lorg/jboss/jca/common/api/metadata/common/TransactionSupportEnum;Ljava/util/List;Ljava/util/List;Ljava/util/Map;Ljava/util/List;Ljava/lang/String;Lorg/jboss/jca/common/api/metadata/resourceadapter/WorkManager;)V
      27: areturn

  private static org.jboss.jca.common.api.metadata.resourceadapter.ConnectionDefinition createConnDef(org.jboss.jca.common.api.metadata.common.TransactionSupportEnum, java.lang.String, int, int, java.lang.String, java.lang.Boolean) throws org.jboss.jca.common.api.validator.ValidateException;
    Code:
       0: iload_2
       1: iconst_m1
       2: if_icmpne     9
       5: aconst_null
       6: goto          13
       9: iload_2
      10: invokestatic  #187                // Method java/lang/Integer.valueOf:(I)Ljava/lang/Integer;
      13: astore        6
      15: iload_3
      16: iconst_m1
      17: if_icmpne     24
      20: aconst_null
      21: goto          28
      24: iload_3
      25: invokestatic  #187                // Method java/lang/Integer.valueOf:(I)Ljava/lang/Integer;
      28: astore        7
      30: iconst_0
      31: istore        8
      33: iconst_0
      34: istore        9
      36: getstatic     #188                // Field org/jboss/jca/common/api/metadata/common/FlushStrategy.FAILING_CONNECTION_ONLY:Lorg/jboss/jca/common/api/metadata/common/FlushStrategy;
      39: astore        10
      41: getstatic     #189                // Field java/lang/Boolean.FALSE:Ljava/lang/Boolean;
      44: astore        11
      46: aload_0
      47: getstatic     #190                // Field org/jboss/jca/common/api/metadata/common/TransactionSupportEnum.XATransaction:Lorg/jboss/jca/common/api/metadata/common/TransactionSupportEnum;
      50: if_acmpne     108
      53: new           #191                // class org/jboss/jca/common/metadata/common/XaPoolImpl
      56: dup
      57: aload         6
      59: getstatic     #192                // Field org/jboss/jca/common/api/metadata/Defaults.INITIAL_POOL_SIZE:Ljava/lang/Integer;
      62: aload         7
      64: iload         8
      66: invokestatic  #193                // Method java/lang/Boolean.valueOf:(Z)Ljava/lang/Boolean;
      69: iload         9
      71: invokestatic  #193                // Method java/lang/Boolean.valueOf:(Z)Ljava/lang/Boolean;
      74: aload         10
      76: aconst_null
      77: getstatic     #194                // Field org/jboss/jca/common/api/metadata/Defaults.FAIR:Ljava/lang/Boolean;
      80: getstatic     #195                // Field org/jboss/jca/common/api/metadata/Defaults.IS_SAME_RM_OVERRIDE:Ljava/lang/Boolean;
      83: getstatic     #196                // Field org/jboss/jca/common/api/metadata/Defaults.INTERLEAVING:Ljava/lang/Boolean;
      86: getstatic     #197                // Field org/jboss/jca/common/api/metadata/Defaults.PAD_XID:Ljava/lang/Boolean;
      89: getstatic     #198                // Field org/jboss/jca/common/api/metadata/Defaults.WRAP_XA_RESOURCE:Ljava/lang/Boolean;
      92: getstatic     #199                // Field org/jboss/jca/common/api/metadata/Defaults.NO_TX_SEPARATE_POOL:Ljava/lang/Boolean;
      95: invokespecial #200                // Method org/jboss/jca/common/metadata/common/XaPoolImpl."<init>":(Ljava/lang/Integer;Ljava/lang/Integer;Ljava/lang/Integer;Ljava/lang/Boolean;Ljava/lang/Boolean;Lorg/jboss/jca/common/api/metadata/common/FlushStrategy;Lorg/jboss/jca/common/api/metadata/common/Capacity;Ljava/lang/Boolean;Ljava/lang/Boolean;Ljava/lang/Boolean;Ljava/lang/Boolean;Ljava/lang/Boolean;Ljava/lang/Boolean;)V
      98: astore        12
     100: getstatic     #201                // Field java/lang/Boolean.TRUE:Ljava/lang/Boolean;
     103: astore        11
     105: goto          140
     108: new           #202                // class org/jboss/jca/common/metadata/common/PoolImpl
     111: dup
     112: aload         6
     114: getstatic     #192                // Field org/jboss/jca/common/api/metadata/Defaults.INITIAL_POOL_SIZE:Ljava/lang/Integer;
     117: aload         7
     119: iload         8
     121: invokestatic  #193                // Method java/lang/Boolean.valueOf:(Z)Ljava/lang/Boolean;
     124: iload         9
     126: invokestatic  #193                // Method java/lang/Boolean.valueOf:(Z)Ljava/lang/Boolean;
     129: aload         10
     131: aconst_null
     132: getstatic     #194                // Field org/jboss/jca/common/api/metadata/Defaults.FAIR:Ljava/lang/Boolean;
     135: invokespecial #203                // Method org/jboss/jca/common/metadata/common/PoolImpl."<init>":(Ljava/lang/Integer;Ljava/lang/Integer;Ljava/lang/Integer;Ljava/lang/Boolean;Ljava/lang/Boolean;Lorg/jboss/jca/common/api/metadata/common/FlushStrategy;Lorg/jboss/jca/common/api/metadata/common/Capacity;Ljava/lang/Boolean;)V
     138: astore        12
     140: new           #204                // class org/wildfly/extension/messaging/activemq/jms/PooledConnectionFactoryService$1
     143: dup
     144: aconst_null
     145: aconst_null
     146: aconst_null
     147: aconst_null
     148: aconst_null
     149: invokespecial #205                // Method org/wildfly/extension/messaging/activemq/jms/PooledConnectionFactoryService$1."<init>":(Ljava/lang/Long;Ljava/lang/Long;Ljava/lang/Integer;Ljava/lang/Long;Ljava/lang/Integer;)V
     152: astore        13
     154: new           #206                // class org/jboss/jca/common/metadata/common/SecurityImpl
     157: dup
     158: aconst_null
     159: aconst_null
     160: iconst_1
     161: invokespecial #207                // Method org/jboss/jca/common/metadata/common/SecurityImpl."<init>":(Ljava/lang/String;Ljava/lang/String;Z)V
     164: astore        14
     166: new           #208                // class org/jboss/jca/common/api/metadata/common/Recovery
     169: dup
     170: new           #209                // class org/jboss/jca/common/metadata/common/CredentialImpl
     173: dup
     174: aconst_null
     175: aconst_null
     176: aconst_null
     177: invokespecial #210                // Method org/jboss/jca/common/metadata/common/CredentialImpl."<init>":(Ljava/lang/String;Ljava/lang/String;Ljava/lang/String;)V
     180: aconst_null
     181: getstatic     #201                // Field java/lang/Boolean.TRUE:Ljava/lang/Boolean;
     184: invokespecial #211                // Method org/jboss/jca/common/api/metadata/common/Recovery."<init>":(Lorg/jboss/jca/common/api/metadata/common/Credential;Lorg/jboss/jca/common/api/metadata/common/Extension;Ljava/lang/Boolean;)V
     187: astore        15
     189: new           #212                // class org/jboss/jca/common/metadata/common/ValidationImpl
     192: dup
     193: getstatic     #213                // Field org/jboss/jca/common/api/metadata/Defaults.VALIDATE_ON_MATCH:Ljava/lang/Boolean;
     196: aconst_null
     197: aconst_null
     198: iconst_0
     199: invokestatic  #193                // Method java/lang/Boolean.valueOf:(Z)Ljava/lang/Boolean;
     202: invokespecial #214                // Method org/jboss/jca/common/metadata/common/ValidationImpl."<init>":(Ljava/lang/Boolean;Ljava/lang/Boolean;Ljava/lang/Long;Ljava/lang/Boolean;)V
     205: astore        16
     207: new           #215                // class org/jboss/jca/common/metadata/resourceadapter/ConnectionDefinitionImpl
     210: dup
     211: invokestatic  #185                // Method java/util/Collections.emptyMap:()Ljava/util/Map;
     214: ldc           #216                // String org.apache.activemq.artemis.ra.ActiveMQRAManagedConnectionFactory
     216: aload_1
     217: ldc           #217                // String ActiveMQConnectionDefinition
     219: iconst_1
     220: invokestatic  #193                // Method java/lang/Boolean.valueOf:(Z)Ljava/lang/Boolean;
     223: iconst_1
     224: invokestatic  #193                // Method java/lang/Boolean.valueOf:(Z)Ljava/lang/Boolean;
     227: iconst_1
     228: invokestatic  #193                // Method java/lang/Boolean.valueOf:(Z)Ljava/lang/Boolean;
     231: getstatic     #218                // Field org/jboss/jca/common/api/metadata/Defaults.SHARABLE:Ljava/lang/Boolean;
     234: getstatic     #219                // Field org/jboss/jca/common/api/metadata/Defaults.ENLISTMENT:Ljava/lang/Boolean;
     237: getstatic     #220                // Field org/jboss/jca/common/api/metadata/Defaults.CONNECTABLE:Ljava/lang/Boolean;
     240: iconst_0
     241: invokestatic  #193                // Method java/lang/Boolean.valueOf:(Z)Ljava/lang/Boolean;
     244: aload         4
     246: aload         5
     248: aload         12
     250: aload         13
     252: aload         16
     254: aload         14
     256: aload         15
     258: aload         11
     260: invokespecial #221                // Method org/jboss/jca/common/metadata/resourceadapter/ConnectionDefinitionImpl."<init>":(Ljava/util/Map;Ljava/lang/String;Ljava/lang/String;Ljava/lang/String;Ljava/lang/Boolean;Ljava/lang/Boolean;Ljava/lang/Boolean;Ljava/lang/Boolean;Ljava/lang/Boolean;Ljava/lang/Boolean;Ljava/lang/Boolean;Ljava/lang/String;Ljava/lang/Boolean;Lorg/jboss/jca/common/api/metadata/common/Pool;Lorg/jboss/jca/common/api/metadata/common/TimeOut;Lorg/jboss/jca/common/api/metadata/common/Validation;Lorg/jboss/jca/common/api/metadata/common/Security;Lorg/jboss/jca/common/api/metadata/common/Recovery;Ljava/lang/Boolean;)V
     263: areturn

  private static org.jboss.jca.common.api.metadata.spec.Connector createConnector15(org.jboss.jca.common.api.metadata.spec.ResourceAdapter);
    Code:
       0: new           #222                // class org/jboss/jca/common/metadata/spec/ConnectorImpl
       3: dup
       4: getstatic     #223                // Field org/jboss/jca/common/api/metadata/spec/Connector$Version.V_15:Lorg/jboss/jca/common/api/metadata/spec/Connector$Version;
       7: aconst_null
       8: ldc           #224                // String Red Hat
      10: invokestatic  #225                // Method str:(Ljava/lang/String;)Lorg/jboss/jca/common/api/metadata/spec/XsdString;
      13: ldc           #226                // String JMS 1.1 Server
      15: invokestatic  #225                // Method str:(Ljava/lang/String;)Lorg/jboss/jca/common/api/metadata/spec/XsdString;
      18: ldc           #227                // String 1.0
      20: invokestatic  #225                // Method str:(Ljava/lang/String;)Lorg/jboss/jca/common/api/metadata/spec/XsdString;
      23: aconst_null
      24: aload_0
      25: aconst_null
      26: iconst_0
      27: getstatic     #228                // Field EMPTY_LOCL:Ljava/util/List;
      30: getstatic     #228                // Field EMPTY_LOCL:Ljava/util/List;
      33: invokestatic  #184                // Method java/util/Collections.emptyList:()Ljava/util/List;
      36: aconst_null
      37: invokespecial #229                // Method org/jboss/jca/common/metadata/spec/ConnectorImpl."<init>":(Lorg/jboss/jca/common/api/metadata/spec/Connector$Version;Lorg/jboss/jca/common/api/metadata/spec/XsdString;Lorg/jboss/jca/common/api/metadata/spec/XsdString;Lorg/jboss/jca/common/api/metadata/spec/XsdString;Lorg/jboss/jca/common/api/metadata/spec/XsdString;Lorg/jboss/jca/common/api/metadata/spec/LicenseType;Lorg/jboss/jca/common/api/metadata/spec/ResourceAdapter;Ljava/util/List;ZLjava/util/List;Ljava/util/List;Ljava/util/List;Ljava/lang/String;)V
      40: areturn

  private org.jboss.jca.common.api.metadata.spec.ResourceAdapter createResourceAdapter15(java.util.List<org.jboss.jca.common.api.metadata.spec.ConfigProperty>, org.jboss.jca.common.api.metadata.spec.OutboundResourceAdapter, org.jboss.jca.common.api.metadata.spec.InboundResourceAdapter);
    Code:
       0: new           #230                // class org/jboss/jca/common/metadata/spec/ResourceAdapterImpl
       3: dup
       4: ldc           #231                // String org.apache.activemq.artemis.ra.ActiveMQResourceAdapter
       6: invokestatic  #225                // Method str:(Ljava/lang/String;)Lorg/jboss/jca/common/api/metadata/spec/XsdString;
       9: aload_1
      10: aload_2
      11: aload_3
      12: invokestatic  #184                // Method java/util/Collections.emptyList:()Ljava/util/List;
      15: invokestatic  #184                // Method java/util/Collections.emptyList:()Ljava/util/List;
      18: aconst_null
      19: invokespecial #232                // Method org/jboss/jca/common/metadata/spec/ResourceAdapterImpl."<init>":(Lorg/jboss/jca/common/api/metadata/spec/XsdString;Ljava/util/List;Lorg/jboss/jca/common/api/metadata/spec/OutboundResourceAdapter;Lorg/jboss/jca/common/api/metadata/spec/InboundResourceAdapter;Ljava/util/List;Ljava/util/List;Ljava/lang/String;)V
      22: areturn

  private org.jboss.jca.common.api.metadata.spec.InboundResourceAdapter createInbound();
    Code:
       0: new           #233                // class org/jboss/jca/common/metadata/spec/RequiredConfigPropertyImpl
       3: dup
       4: getstatic     #228                // Field EMPTY_LOCL:Ljava/util/List;
       7: ldc           #234                // String destination
       9: invokestatic  #225                // Method str:(Ljava/lang/String;)Lorg/jboss/jca/common/api/metadata/spec/XsdString;
      12: aconst_null
      13: invokespecial #235                // Method org/jboss/jca/common/metadata/spec/RequiredConfigPropertyImpl."<init>":(Ljava/util/List;Lorg/jboss/jca/common/api/metadata/spec/XsdString;Ljava/lang/String;)V
      16: invokestatic  #182                // Method java/util/Collections.singletonList:(Ljava/lang/Object;)Ljava/util/List;
      19: astore_1
      20: new           #236                // class org/jboss/jca/common/metadata/spec/ActivationSpecImpl
      23: dup
      24: ldc           #237                // String org.apache.activemq.artemis.ra.inflow.ActiveMQActivationSpec
      26: invokestatic  #225                // Method str:(Ljava/lang/String;)Lorg/jboss/jca/common/api/metadata/spec/XsdString;
      29: aload_1
      30: aconst_null
      31: aconst_null
      32: invokespecial #238                // Method org/jboss/jca/common/metadata/spec/ActivationSpecImpl."<init>":(Lorg/jboss/jca/common/api/metadata/spec/XsdString;Ljava/util/List;Ljava/util/List;Ljava/lang/String;)V
      35: astore_2
      36: new           #239                // class org/jboss/jca/common/metadata/spec/MessageListenerImpl
      39: dup
      40: ldc           #240                // String javax.jms.MessageListener
      42: invokestatic  #225                // Method str:(Ljava/lang/String;)Lorg/jboss/jca/common/api/metadata/spec/XsdString;
      45: aload_2
      46: aconst_null
      47: invokespecial #241                // Method org/jboss/jca/common/metadata/spec/MessageListenerImpl."<init>":(Lorg/jboss/jca/common/api/metadata/spec/XsdString;Lorg/jboss/jca/common/api/metadata/spec/Activationspec;Ljava/lang/String;)V
      50: invokestatic  #182                // Method java/util/Collections.singletonList:(Ljava/lang/Object;)Ljava/util/List;
      53: astore_3
      54: new           #242                // class org/jboss/jca/common/metadata/spec/MessageAdapterImpl
      57: dup
      58: aload_3
      59: aconst_null
      60: invokespecial #243                // Method org/jboss/jca/common/metadata/spec/MessageAdapterImpl."<init>":(Ljava/util/List;Ljava/lang/String;)V
      63: astore        4
      65: new           #244                // class org/jboss/jca/common/metadata/spec/InboundResourceAdapterImpl
      68: dup
      69: aload         4
      71: aconst_null
      72: invokespecial #245                // Method org/jboss/jca/common/metadata/spec/InboundResourceAdapterImpl."<init>":(Lorg/jboss/jca/common/api/metadata/spec/Messageadapter;Ljava/lang/String;)V
      75: areturn

  private static org.jboss.jca.common.api.metadata.spec.OutboundResourceAdapter createOutbound();
    Code:
       0: new           #29                 // class java/util/ArrayList
       3: dup
       4: invokespecial #30                 // Method java/util/ArrayList."<init>":()V
       7: astore_0
       8: new           #29                 // class java/util/ArrayList
      11: dup
      12: invokespecial #30                 // Method java/util/ArrayList."<init>":()V
      15: astore_1
      16: aload_1
      17: ldc           #246                // String SessionDefaultType
      19: ldc           #89                 // String java.lang.String
      21: ldc           #247                // String javax.jms.Queue
      23: invokestatic  #91                 // Method simpleProperty15:(Ljava/lang/String;Ljava/lang/String;Ljava/lang/String;)Lorg/jboss/jca/common/api/metadata/spec/ConfigProperty;
      26: invokeinterface #70,  2           // InterfaceMethod java/util/List.add:(Ljava/lang/Object;)Z
      31: pop
      32: aload_1
      33: ldc           #248                // String UseTryLock
      35: ldc           #100                // String java.lang.Integer
      37: ldc           #249                // String 0
      39: invokestatic  #91                 // Method simpleProperty15:(Ljava/lang/String;Ljava/lang/String;Ljava/lang/String;)Lorg/jboss/jca/common/api/metadata/spec/ConfigProperty;
      42: invokeinterface #70,  2           // InterfaceMethod java/util/List.add:(Ljava/lang/Object;)Z
      47: pop
      48: aload_0
      49: new           #250                // class org/jboss/jca/common/metadata/spec/ConnectionDefinitionImpl
      52: dup
      53: ldc           #216                // String org.apache.activemq.artemis.ra.ActiveMQRAManagedConnectionFactory
      55: invokestatic  #225                // Method str:(Ljava/lang/String;)Lorg/jboss/jca/common/api/metadata/spec/XsdString;
      58: aload_1
      59: ldc           #251                // String org.apache.activemq.artemis.ra.ActiveMQRAConnectionFactory
      61: invokestatic  #225                // Method str:(Ljava/lang/String;)Lorg/jboss/jca/common/api/metadata/spec/XsdString;
      64: ldc           #252                // String org.apache.activemq.artemis.ra.ActiveMQRAConnectionFactoryImpl
      66: invokestatic  #225                // Method str:(Ljava/lang/String;)Lorg/jboss/jca/common/api/metadata/spec/XsdString;
      69: ldc           #253                // String javax.jms.Session
      71: invokestatic  #225                // Method str:(Ljava/lang/String;)Lorg/jboss/jca/common/api/metadata/spec/XsdString;
      74: ldc           #254                // String org.apache.activemq.artemis.ra.ActiveMQRASession
      76: invokestatic  #225                // Method str:(Ljava/lang/String;)Lorg/jboss/jca/common/api/metadata/spec/XsdString;
      79: aconst_null
      80: invokespecial #255                // Method org/jboss/jca/common/metadata/spec/ConnectionDefinitionImpl."<init>":(Lorg/jboss/jca/common/api/metadata/spec/XsdString;Ljava/util/List;Lorg/jboss/jca/common/api/metadata/spec/XsdString;Lorg/jboss/jca/common/api/metadata/spec/XsdString;Lorg/jboss/jca/common/api/metadata/spec/XsdString;Lorg/jboss/jca/common/api/metadata/spec/XsdString;Ljava/lang/String;)V
      83: invokeinterface #70,  2           // InterfaceMethod java/util/List.add:(Ljava/lang/Object;)Z
      88: pop
      89: new           #256                // class org/jboss/jca/common/metadata/spec/AuthenticationMechanismImpl
      92: dup
      93: invokestatic  #184                // Method java/util/Collections.emptyList:()Ljava/util/List;
      96: ldc_w         #257                // String BasicPassword
      99: invokestatic  #225                // Method str:(Ljava/lang/String;)Lorg/jboss/jca/common/api/metadata/spec/XsdString;
     102: getstatic     #258                // Field org/jboss/jca/common/api/metadata/spec/CredentialInterfaceEnum.PasswordCredential:Lorg/jboss/jca/common/api/metadata/spec/CredentialInterfaceEnum;
     105: aconst_null
     106: aconst_null
     107: invokespecial #259                // Method org/jboss/jca/common/metadata/spec/AuthenticationMechanismImpl."<init>":(Ljava/util/List;Lorg/jboss/jca/common/api/metadata/spec/XsdString;Lorg/jboss/jca/common/api/metadata/spec/CredentialInterfaceEnum;Ljava/lang/String;Ljava/lang/String;)V
     110: astore_2
     111: new           #260                // class org/jboss/jca/common/metadata/spec/OutboundResourceAdapterImpl
     114: dup
     115: aload_0
     116: getstatic     #190                // Field org/jboss/jca/common/api/metadata/common/TransactionSupportEnum.XATransaction:Lorg/jboss/jca/common/api/metadata/common/TransactionSupportEnum;
     119: aload_2
     120: invokestatic  #182                // Method java/util/Collections.singletonList:(Ljava/lang/Object;)Ljava/util/List;
     123: iconst_0
     124: aconst_null
     125: aconst_null
     126: aconst_null
     127: invokespecial #261                // Method org/jboss/jca/common/metadata/spec/OutboundResourceAdapterImpl."<init>":(Ljava/util/List;Lorg/jboss/jca/common/api/metadata/common/TransactionSupportEnum;Ljava/util/List;ZLjava/lang/String;Ljava/lang/String;Ljava/lang/String;)V
     130: areturn

  private static org.jboss.jca.common.api.metadata.spec.XsdString str(java.lang.String);
    Code:
       0: new           #262                // class org/jboss/jca/common/api/metadata/spec/XsdString
       3: dup
       4: aload_0
       5: aconst_null
       6: invokespecial #263                // Method org/jboss/jca/common/api/metadata/spec/XsdString."<init>":(Ljava/lang/String;Ljava/lang/String;)V
       9: areturn

  private static org.jboss.jca.common.api.metadata.spec.ConfigProperty simpleProperty15(java.lang.String, java.lang.String, java.lang.String);
    Code:
       0: new           #264                // class org/jboss/jca/common/metadata/spec/ConfigPropertyImpl
       3: dup
       4: getstatic     #228                // Field EMPTY_LOCL:Ljava/util/List;
       7: aload_0
       8: invokestatic  #225                // Method str:(Ljava/lang/String;)Lorg/jboss/jca/common/api/metadata/spec/XsdString;
      11: aload_1
      12: invokestatic  #225                // Method str:(Ljava/lang/String;)Lorg/jboss/jca/common/api/metadata/spec/XsdString;
      15: aload_2
      16: invokestatic  #225                // Method str:(Ljava/lang/String;)Lorg/jboss/jca/common/api/metadata/spec/XsdString;
      19: aconst_null
      20: aconst_null
      21: aconst_null
      22: aconst_null
      23: iconst_0
      24: aconst_null
      25: aconst_null
      26: aconst_null
      27: aconst_null
      28: invokespecial #265                // Method org/jboss/jca/common/metadata/spec/ConfigPropertyImpl."<init>":(Ljava/util/List;Lorg/jboss/jca/common/api/metadata/spec/XsdString;Lorg/jboss/jca/common/api/metadata/spec/XsdString;Lorg/jboss/jca/common/api/metadata/spec/XsdString;Ljava/lang/Boolean;Ljava/lang/Boolean;Ljava/lang/Boolean;Ljava/lang/String;ZLjava/lang/String;Ljava/lang/String;Ljava/lang/String;Ljava/lang/String;)V
      31: areturn

  public void stop(org.jboss.msc.service.StopContext);
    Code:
       0: return

  public org.jboss.msc.inject.Injector<java.lang.Object> getTransactionManager();
    Code:
       0: aload_0
       1: getfield      #4                  // Field transactionManager:Lorg/jboss/msc/inject/Injector;
       4: areturn

  org.jboss.msc.inject.Injector<org.jboss.as.network.SocketBinding> getSocketBindingInjector(java.lang.String);
    Code:
       0: new           #266                // class org/jboss/msc/inject/MapInjector
       3: dup
       4: aload_0
       5: getfield      #7                  // Field socketBindings:Ljava/util/Map;
       8: aload_1
       9: invokespecial #267                // Method org/jboss/msc/inject/MapInjector."<init>":(Ljava/util/Map;Ljava/lang/Object;)V
      12: areturn

  public org.jboss.msc.inject.Injector<org.apache.activemq.artemis.core.server.ActiveMQServer> getActiveMQServer();
    Code:
       0: aload_0
       1: getfield      #8                  // Field activeMQServer:Lorg/jboss/msc/value/InjectedValue;
       4: areturn

  public java.lang.Object getValue() throws java.lang.IllegalStateException, java.lang.IllegalArgumentException;
    Code:
       0: aload_0
       1: invokevirtual #268                // Method getValue:()Ljava/lang/Void;
       4: areturn

  static {};
    Code:
       0: invokestatic  #184                // Method java/util/Collections.emptyList:()Ljava/util/List;
       3: putstatic     #228                // Field EMPTY_LOCL:Ljava/util/List;
       6: return
}
