Compiled from "PooledConnectionFactoryService.java"
final class org.wildfly.extension.messaging.activemq.jms.PooledConnectionFactoryService$1 extends org.jboss.jca.common.metadata.common.TimeOutImpl {
  org.wildfly.extension.messaging.activemq.jms.PooledConnectionFactoryService$1(java.lang.Long, java.lang.Long, java.lang.Integer, java.lang.Long, java.lang.Integer);
    Code:
       0: aload_0
       1: aload_1
       2: aload_2
       3: aload_3
       4: aload         4
       6: aload         5
       8: invokespecial #1                  // Method org/jboss/jca/common/metadata/common/TimeOutImpl."<init>":(Ljava/lang/Long;Ljava/lang/Long;Ljava/lang/Integer;Ljava/lang/Long;Ljava/lang/Integer;)V
      11: return
}
