Compiled from "LoggingInputStream.java"
class org.apache.http.impl.conn.LoggingInputStream extends java.io.InputStream {
  private final java.io.InputStream in;

  private final org.apache.http.impl.conn.Wire wire;

  public org.apache.http.impl.conn.LoggingInputStream(java.io.InputStream, org.apache.http.impl.conn.Wire);
    Code:
       0: aload_0
       1: invokespecial #1                  // Method java/io/InputStream."<init>":()V
       4: aload_0
       5: aload_1
       6: putfield      #2                  // Field in:Ljava/io/InputStream;
       9: aload_0
      10: aload_2
      11: putfield      #3                  // Field wire:Lorg/apache/http/impl/conn/Wire;
      14: return

  public int read() throws java.io.IOException;
    Code:
       0: aload_0
       1: getfield      #2                  // Field in:Ljava/io/InputStream;
       4: invokevirtual #4                  // Method java/io/InputStream.read:()I
       7: istore_1
       8: iload_1
       9: iconst_m1
      10: if_icmpne     25
      13: aload_0
      14: getfield      #3                  // Field wire:Lorg/apache/http/impl/conn/Wire;
      17: ldc           #5                  // String end of stream
      19: invokevirtual #6                  // Method org/apache/http/impl/conn/Wire.input:(Ljava/lang/String;)V
      22: goto          33
      25: aload_0
      26: getfield      #3                  // Field wire:Lorg/apache/http/impl/conn/Wire;
      29: iload_1
      30: invokevirtual #7                  // Method org/apache/http/impl/conn/Wire.input:(I)V
      33: iload_1
      34: ireturn
      35: astore_1
      36: aload_0
      37: getfield      #3                  // Field wire:Lorg/apache/http/impl/conn/Wire;
      40: new           #9                  // class java/lang/StringBuilder
      43: dup
      44: invokespecial #10                 // Method java/lang/StringBuilder."<init>":()V
      47: ldc           #11                 // String [read] I/O error:
      49: invokevirtual #12                 // Method java/lang/StringBuilder.append:(Ljava/lang/String;)Ljava/lang/StringBuilder;
      52: aload_1
      53: invokevirtual #13                 // Method java/io/IOException.getMessage:()Ljava/lang/String;
      56: invokevirtual #12                 // Method java/lang/StringBuilder.append:(Ljava/lang/String;)Ljava/lang/StringBuilder;
      59: invokevirtual #14                 // Method java/lang/StringBuilder.toString:()Ljava/lang/String;
      62: invokevirtual #6                  // Method org/apache/http/impl/conn/Wire.input:(Ljava/lang/String;)V
      65: aload_1
      66: athrow
    Exception table:
       from    to  target type
           0    34    35   Class java/io/IOException

  public int read(byte[]) throws java.io.IOException;
    Code:
       0: aload_0
       1: getfield      #2                  // Field in:Ljava/io/InputStream;
       4: aload_1
       5: invokevirtual #15                 // Method java/io/InputStream.read:([B)I
       8: istore_2
       9: iload_2
      10: iconst_m1
      11: if_icmpne     26
      14: aload_0
      15: getfield      #3                  // Field wire:Lorg/apache/http/impl/conn/Wire;
      18: ldc           #5                  // String end of stream
      20: invokevirtual #6                  // Method org/apache/http/impl/conn/Wire.input:(Ljava/lang/String;)V
      23: goto          40
      26: iload_2
      27: ifle          40
      30: aload_0
      31: getfield      #3                  // Field wire:Lorg/apache/http/impl/conn/Wire;
      34: aload_1
      35: iconst_0
      36: iload_2
      37: invokevirtual #16                 // Method org/apache/http/impl/conn/Wire.input:([BII)V
      40: iload_2
      41: ireturn
      42: astore_2
      43: aload_0
      44: getfield      #3                  // Field wire:Lorg/apache/http/impl/conn/Wire;
      47: new           #9                  // class java/lang/StringBuilder
      50: dup
      51: invokespecial #10                 // Method java/lang/StringBuilder."<init>":()V
      54: ldc           #11                 // String [read] I/O error:
      56: invokevirtual #12                 // Method java/lang/StringBuilder.append:(Ljava/lang/String;)Ljava/lang/StringBuilder;
      59: aload_2
      60: invokevirtual #13                 // Method java/io/IOException.getMessage:()Ljava/lang/String;
      63: invokevirtual #12                 // Method java/lang/StringBuilder.append:(Ljava/lang/String;)Ljava/lang/StringBuilder;
      66: invokevirtual #14                 // Method java/lang/StringBuilder.toString:()Ljava/lang/String;
      69: invokevirtual #6                  // Method org/apache/http/impl/conn/Wire.input:(Ljava/lang/String;)V
      72: aload_2
      73: athrow
    Exception table:
       from    to  target type
           0    41    42   Class java/io/IOException

  public int read(byte[], int, int) throws java.io.IOException;
    Code:
       0: aload_0
       1: getfield      #2                  // Field in:Ljava/io/InputStream;
       4: aload_1
       5: iload_2
       6: iload_3
       7: invokevirtual #17                 // Method java/io/InputStream.read:([BII)I
      10: istore        4
      12: iload         4
      14: iconst_m1
      15: if_icmpne     30
      18: aload_0
      19: getfield      #3                  // Field wire:Lorg/apache/http/impl/conn/Wire;
      22: ldc           #5                  // String end of stream
      24: invokevirtual #6                  // Method org/apache/http/impl/conn/Wire.input:(Ljava/lang/String;)V
      27: goto          46
      30: iload         4
      32: ifle          46
      35: aload_0
      36: getfield      #3                  // Field wire:Lorg/apache/http/impl/conn/Wire;
      39: aload_1
      40: iload_2
      41: iload         4
      43: invokevirtual #16                 // Method org/apache/http/impl/conn/Wire.input:([BII)V
      46: iload         4
      48: ireturn
      49: astore        4
      51: aload_0
      52: getfield      #3                  // Field wire:Lorg/apache/http/impl/conn/Wire;
      55: new           #9                  // class java/lang/StringBuilder
      58: dup
      59: invokespecial #10                 // Method java/lang/StringBuilder."<init>":()V
      62: ldc           #11                 // String [read] I/O error:
      64: invokevirtual #12                 // Method java/lang/StringBuilder.append:(Ljava/lang/String;)Ljava/lang/StringBuilder;
      67: aload         4
      69: invokevirtual #13                 // Method java/io/IOException.getMessage:()Ljava/lang/String;
      72: invokevirtual #12                 // Method java/lang/StringBuilder.append:(Ljava/lang/String;)Ljava/lang/StringBuilder;
      75: invokevirtual #14                 // Method java/lang/StringBuilder.toString:()Ljava/lang/String;
      78: invokevirtual #6                  // Method org/apache/http/impl/conn/Wire.input:(Ljava/lang/String;)V
      81: aload         4
      83: athrow
    Exception table:
       from    to  target type
           0    48    49   Class java/io/IOException

  public long skip(long) throws java.io.IOException;
    Code:
       0: aload_0
       1: lload_1
       2: invokespecial #18                 // Method java/io/InputStream.skip:(J)J
       5: lreturn
       6: astore_3
       7: aload_0
       8: getfield      #3                  // Field wire:Lorg/apache/http/impl/conn/Wire;
      11: new           #9                  // class java/lang/StringBuilder
      14: dup
      15: invokespecial #10                 // Method java/lang/StringBuilder."<init>":()V
      18: ldc           #19                 // String [skip] I/O error:
      20: invokevirtual #12                 // Method java/lang/StringBuilder.append:(Ljava/lang/String;)Ljava/lang/StringBuilder;
      23: aload_3
      24: invokevirtual #13                 // Method java/io/IOException.getMessage:()Ljava/lang/String;
      27: invokevirtual #12                 // Method java/lang/StringBuilder.append:(Ljava/lang/String;)Ljava/lang/StringBuilder;
      30: invokevirtual #14                 // Method java/lang/StringBuilder.toString:()Ljava/lang/String;
      33: invokevirtual #6                  // Method org/apache/http/impl/conn/Wire.input:(Ljava/lang/String;)V
      36: aload_3
      37: athrow
    Exception table:
       from    to  target type
           0     5     6   Class java/io/IOException

  public int available() throws java.io.IOException;
    Code:
       0: aload_0
       1: getfield      #2                  // Field in:Ljava/io/InputStream;
       4: invokevirtual #20                 // Method java/io/InputStream.available:()I
       7: ireturn
       8: astore_1
       9: aload_0
      10: getfield      #3                  // Field wire:Lorg/apache/http/impl/conn/Wire;
      13: new           #9                  // class java/lang/StringBuilder
      16: dup
      17: invokespecial #10                 // Method java/lang/StringBuilder."<init>":()V
      20: ldc           #21                 // String [available] I/O error :
      22: invokevirtual #12                 // Method java/lang/StringBuilder.append:(Ljava/lang/String;)Ljava/lang/StringBuilder;
      25: aload_1
      26: invokevirtual #13                 // Method java/io/IOException.getMessage:()Ljava/lang/String;
      29: invokevirtual #12                 // Method java/lang/StringBuilder.append:(Ljava/lang/String;)Ljava/lang/StringBuilder;
      32: invokevirtual #14                 // Method java/lang/StringBuilder.toString:()Ljava/lang/String;
      35: invokevirtual #6                  // Method org/apache/http/impl/conn/Wire.input:(Ljava/lang/String;)V
      38: aload_1
      39: athrow
    Exception table:
       from    to  target type
           0     7     8   Class java/io/IOException

  public void mark(int);
    Code:
       0: aload_0
       1: iload_1
       2: invokespecial #22                 // Method java/io/InputStream.mark:(I)V
       5: return

  public void reset() throws java.io.IOException;
    Code:
       0: aload_0
       1: invokespecial #23                 // Method java/io/InputStream.reset:()V
       4: return

  public boolean markSupported();
    Code:
       0: iconst_0
       1: ireturn

  public void close() throws java.io.IOException;
    Code:
       0: aload_0
       1: getfield      #2                  // Field in:Ljava/io/InputStream;
       4: invokevirtual #24                 // Method java/io/InputStream.close:()V
       7: goto          42
      10: astore_1
      11: aload_0
      12: getfield      #3                  // Field wire:Lorg/apache/http/impl/conn/Wire;
      15: new           #9                  // class java/lang/StringBuilder
      18: dup
      19: invokespecial #10                 // Method java/lang/StringBuilder."<init>":()V
      22: ldc           #25                 // String [close] I/O error:
      24: invokevirtual #12                 // Method java/lang/StringBuilder.append:(Ljava/lang/String;)Ljava/lang/StringBuilder;
      27: aload_1
      28: invokevirtual #13                 // Method java/io/IOException.getMessage:()Ljava/lang/String;
      31: invokevirtual #12                 // Method java/lang/StringBuilder.append:(Ljava/lang/String;)Ljava/lang/StringBuilder;
      34: invokevirtual #14                 // Method java/lang/StringBuilder.toString:()Ljava/lang/String;
      37: invokevirtual #6                  // Method org/apache/http/impl/conn/Wire.input:(Ljava/lang/String;)V
      40: aload_1
      41: athrow
      42: return
    Exception table:
       from    to  target type
           0     7    10   Class java/io/IOException
}
