Compiled from "DefaultLexRuntimeV2AsyncClientBuilder.java"
final class software.amazon.awssdk.services.lexruntimev2.DefaultLexRuntimeV2AsyncClientBuilder extends software.amazon.awssdk.services.lexruntimev2.DefaultLexRuntimeV2BaseClientBuilder<software.amazon.awssdk.services.lexruntimev2.LexRuntimeV2AsyncClientBuilder, software.amazon.awssdk.services.lexruntimev2.LexRuntimeV2AsyncClient> implements software.amazon.awssdk.services.lexruntimev2.LexRuntimeV2AsyncClientBuilder {
  software.amazon.awssdk.services.lexruntimev2.DefaultLexRuntimeV2AsyncClientBuilder();
    Code:
       0: aload_0
       1: invokespecial #1                  // Method software/amazon/awssdk/services/lexruntimev2/DefaultLexRuntimeV2BaseClientBuilder."<init>":()V
       4: return

  public software.amazon.awssdk.services.lexruntimev2.DefaultLexRuntimeV2AsyncClientBuilder endpointProvider(software.amazon.awssdk.services.lexruntimev2.endpoints.LexRuntimeV2EndpointProvider);
    Code:
       0: aload_0
       1: getfield      #2                  // Field clientConfiguration:Lsoftware/amazon/awssdk/core/client/config/SdkClientConfiguration$Builder;
       4: getstatic     #3                  // Field software/amazon/awssdk/core/client/config/SdkClientOption.ENDPOINT_PROVIDER:Lsoftware/amazon/awssdk/core/client/config/SdkClientOption;
       7: aload_1
       8: invokevirtual #4                  // Method software/amazon/awssdk/core/client/config/SdkClientConfiguration$Builder.option:(Lsoftware/amazon/awssdk/core/client/config/ClientOption;Ljava/lang/Object;)Lsoftware/amazon/awssdk/core/client/config/SdkClientConfiguration$Builder;
      11: pop
      12: aload_0
      13: areturn

  protected final software.amazon.awssdk.services.lexruntimev2.LexRuntimeV2AsyncClient buildClient();
    Code:
       0: aload_0
       1: invokespecial #5                  // Method software/amazon/awssdk/services/lexruntimev2/DefaultLexRuntimeV2BaseClientBuilder.asyncClientConfiguration:()Lsoftware/amazon/awssdk/core/client/config/SdkClientConfiguration;
       4: astore_1
       5: aload_0
       6: pop
       7: aload_1
       8: invokestatic  #6                  // Method validateClientOptions:(Lsoftware/amazon/awssdk/core/client/config/SdkClientConfiguration;)V
      11: new           #7                  // class software/amazon/awssdk/services/lexruntimev2/DefaultLexRuntimeV2AsyncClient
      14: dup
      15: aload_1
      16: invokespecial #8                  // Method software/amazon/awssdk/services/lexruntimev2/DefaultLexRuntimeV2AsyncClient."<init>":(Lsoftware/amazon/awssdk/core/client/config/SdkClientConfiguration;)V
      19: areturn

  protected java.lang.Object buildClient();
    Code:
       0: aload_0
       1: invokevirtual #9                  // Method buildClient:()Lsoftware/amazon/awssdk/services/lexruntimev2/LexRuntimeV2AsyncClient;
       4: areturn

  public software.amazon.awssdk.core.client.builder.SdkAsyncClientBuilder httpClientBuilder(software.amazon.awssdk.http.async.SdkAsyncHttpClient$Builder);
    Code:
       0: aload_0
       1: aload_1
       2: invokespecial #10                 // Method software/amazon/awssdk/services/lexruntimev2/DefaultLexRuntimeV2BaseClientBuilder.httpClientBuilder:(Lsoftware/amazon/awssdk/http/async/SdkAsyncHttpClient$Builder;)Lsoftware/amazon/awssdk/core/client/builder/SdkClientBuilder;
       5: checkcast     #11                 // class software/amazon/awssdk/core/client/builder/SdkAsyncClientBuilder
       8: areturn

  public software.amazon.awssdk.core.client.builder.SdkAsyncClientBuilder httpClient(software.amazon.awssdk.http.async.SdkAsyncHttpClient);
    Code:
       0: aload_0
       1: aload_1
       2: invokespecial #12                 // Method software/amazon/awssdk/services/lexruntimev2/DefaultLexRuntimeV2BaseClientBuilder.httpClient:(Lsoftware/amazon/awssdk/http/async/SdkAsyncHttpClient;)Lsoftware/amazon/awssdk/core/client/builder/SdkClientBuilder;
       5: checkcast     #11                 // class software/amazon/awssdk/core/client/builder/SdkAsyncClientBuilder
       8: areturn

  public software.amazon.awssdk.core.client.builder.SdkAsyncClientBuilder asyncConfiguration(software.amazon.awssdk.core.client.config.ClientAsyncConfiguration);
    Code:
       0: aload_0
       1: aload_1
       2: invokespecial #13                 // Method software/amazon/awssdk/services/lexruntimev2/DefaultLexRuntimeV2BaseClientBuilder.asyncConfiguration:(Lsoftware/amazon/awssdk/core/client/config/ClientAsyncConfiguration;)Lsoftware/amazon/awssdk/core/client/builder/SdkClientBuilder;
       5: checkcast     #11                 // class software/amazon/awssdk/core/client/builder/SdkAsyncClientBuilder
       8: areturn

  public software.amazon.awssdk.services.lexruntimev2.LexRuntimeV2BaseClientBuilder endpointProvider(software.amazon.awssdk.services.lexruntimev2.endpoints.LexRuntimeV2EndpointProvider);
    Code:
       0: aload_0
       1: aload_1
       2: invokevirtual #14                 // Method endpointProvider:(Lsoftware/amazon/awssdk/services/lexruntimev2/endpoints/LexRuntimeV2EndpointProvider;)Lsoftware/amazon/awssdk/services/lexruntimev2/DefaultLexRuntimeV2AsyncClientBuilder;
       5: areturn
}
