Compiled from "ConfigFileApplicationListener.java"
class org.springframework.boot.context.config.ConfigFileApplicationListener$Loader {
  private final org.apache.commons.logging.Log logger;

  private final org.springframework.core.env.ConfigurableEnvironment environment;

  private final org.springframework.boot.context.properties.bind.PropertySourcesPlaceholdersResolver placeholdersResolver;

  private final org.springframework.core.io.ResourceLoader resourceLoader;

  private final java.util.List<org.springframework.boot.env.PropertySourceLoader> propertySourceLoaders;

  private java.util.Deque<org.springframework.boot.context.config.ConfigFileApplicationListener$Profile> profiles;

  private java.util.List<org.springframework.boot.context.config.ConfigFileApplicationListener$Profile> processedProfiles;

  private boolean activatedProfiles;

  private java.util.Map<org.springframework.boot.context.config.ConfigFileApplicationListener$Profile, org.springframework.core.env.MutablePropertySources> loaded;

  private java.util.Map<org.springframework.boot.context.config.ConfigFileApplicationListener$DocumentsCacheKey, java.util.List<org.springframework.boot.context.config.ConfigFileApplicationListener$Document>> loadDocumentsCache;

  final org.springframework.boot.context.config.ConfigFileApplicationListener this$0;

  org.springframework.boot.context.config.ConfigFileApplicationListener$Loader(org.springframework.boot.context.config.ConfigFileApplicationListener, org.springframework.core.env.ConfigurableEnvironment, org.springframework.core.io.ResourceLoader);
    Code:
       0: aload_0
       1: aload_1
       2: putfield      #2                  // Field this$0:Lorg/springframework/boot/context/config/ConfigFileApplicationListener;
       5: aload_0
       6: invokespecial #3                  // Method java/lang/Object."<init>":()V
       9: aload_0
      10: aload_0
      11: getfield      #2                  // Field this$0:Lorg/springframework/boot/context/config/ConfigFileApplicationListener;
      14: invokestatic  #4                  // Method org/springframework/boot/context/config/ConfigFileApplicationListener.access$000:(Lorg/springframework/boot/context/config/ConfigFileApplicationListener;)Lorg/springframework/boot/logging/DeferredLog;
      17: putfield      #5                  // Field logger:Lorg/apache/commons/logging/Log;
      20: aload_0
      21: new           #6                  // class java/util/HashMap
      24: dup
      25: invokespecial #7                  // Method java/util/HashMap."<init>":()V
      28: putfield      #8                  // Field loadDocumentsCache:Ljava/util/Map;
      31: aload_0
      32: aload_2
      33: putfield      #9                  // Field environment:Lorg/springframework/core/env/ConfigurableEnvironment;
      36: aload_0
      37: new           #10                 // class org/springframework/boot/context/properties/bind/PropertySourcesPlaceholdersResolver
      40: dup
      41: aload_0
      42: getfield      #9                  // Field environment:Lorg/springframework/core/env/ConfigurableEnvironment;
      45: invokespecial #11                 // Method org/springframework/boot/context/properties/bind/PropertySourcesPlaceholdersResolver."<init>":(Lorg/springframework/core/env/Environment;)V
      48: putfield      #12                 // Field placeholdersResolver:Lorg/springframework/boot/context/properties/bind/PropertySourcesPlaceholdersResolver;
      51: aload_0
      52: aload_3
      53: ifnull        60
      56: aload_3
      57: goto          68
      60: new           #13                 // class org/springframework/core/io/DefaultResourceLoader
      63: dup
      64: aconst_null
      65: invokespecial #14                 // Method org/springframework/core/io/DefaultResourceLoader."<init>":(Ljava/lang/ClassLoader;)V
      68: putfield      #15                 // Field resourceLoader:Lorg/springframework/core/io/ResourceLoader;
      71: aload_0
      72: ldc           #16                 // class org/springframework/boot/env/PropertySourceLoader
      74: aload_0
      75: invokevirtual #17                 // Method java/lang/Object.getClass:()Ljava/lang/Class;
      78: invokevirtual #18                 // Method java/lang/Class.getClassLoader:()Ljava/lang/ClassLoader;
      81: invokestatic  #19                 // Method org/springframework/core/io/support/SpringFactoriesLoader.loadFactories:(Ljava/lang/Class;Ljava/lang/ClassLoader;)Ljava/util/List;
      84: putfield      #20                 // Field propertySourceLoaders:Ljava/util/List;
      87: return

  void load();
    Code:
       0: aload_0
       1: getfield      #9                  // Field environment:Lorg/springframework/core/env/ConfigurableEnvironment;
       4: ldc           #21                 // String defaultProperties
       6: invokestatic  #22                 // Method org/springframework/boot/context/config/ConfigFileApplicationListener.access$100:()Ljava/util/Set;
       9: aload_0
      10: invokedynamic #23,  0             // InvokeDynamic #0:accept:(Lorg/springframework/boot/context/config/ConfigFileApplicationListener$Loader;)Ljava/util/function/Consumer;
      15: invokestatic  #24                 // Method org/springframework/boot/context/config/FilteredPropertySource.apply:(Lorg/springframework/core/env/ConfigurableEnvironment;Ljava/lang/String;Ljava/util/Set;Ljava/util/function/Consumer;)V
      18: return

  private void initializeProfiles();
    Code:
       0: aload_0
       1: getfield      #25                 // Field profiles:Ljava/util/Deque;
       4: aconst_null
       5: invokeinterface #26,  2           // InterfaceMethod java/util/Deque.add:(Ljava/lang/Object;)Z
      10: pop
      11: aload_0
      12: getfield      #9                  // Field environment:Lorg/springframework/core/env/ConfigurableEnvironment;
      15: invokestatic  #27                 // Method org/springframework/boot/context/properties/bind/Binder.get:(Lorg/springframework/core/env/Environment;)Lorg/springframework/boot/context/properties/bind/Binder;
      18: astore_1
      19: aload_0
      20: aload_1
      21: ldc           #28                 // String spring.profiles.active
      23: invokespecial #29                 // Method getProfiles:(Lorg/springframework/boot/context/properties/bind/Binder;Ljava/lang/String;)Ljava/util/Set;
      26: astore_2
      27: aload_0
      28: aload_1
      29: ldc           #30                 // String spring.profiles.include
      31: invokespecial #29                 // Method getProfiles:(Lorg/springframework/boot/context/properties/bind/Binder;Ljava/lang/String;)Ljava/util/Set;
      34: astore_3
      35: aload_0
      36: aload_2
      37: aload_3
      38: invokespecial #31                 // Method getOtherActiveProfiles:(Ljava/util/Set;Ljava/util/Set;)Ljava/util/List;
      41: astore        4
      43: aload_0
      44: getfield      #25                 // Field profiles:Ljava/util/Deque;
      47: aload         4
      49: invokeinterface #32,  2           // InterfaceMethod java/util/Deque.addAll:(Ljava/util/Collection;)Z
      54: pop
      55: aload_0
      56: getfield      #25                 // Field profiles:Ljava/util/Deque;
      59: aload_3
      60: invokeinterface #32,  2           // InterfaceMethod java/util/Deque.addAll:(Ljava/util/Collection;)Z
      65: pop
      66: aload_0
      67: aload_2
      68: invokevirtual #33                 // Method addActiveProfiles:(Ljava/util/Set;)V
      71: aload_0
      72: getfield      #25                 // Field profiles:Ljava/util/Deque;
      75: invokeinterface #34,  1           // InterfaceMethod java/util/Deque.size:()I
      80: iconst_1
      81: if_icmpne     147
      84: aload_0
      85: getfield      #9                  // Field environment:Lorg/springframework/core/env/ConfigurableEnvironment;
      88: invokeinterface #35,  1           // InterfaceMethod org/springframework/core/env/ConfigurableEnvironment.getDefaultProfiles:()[Ljava/lang/String;
      93: astore        5
      95: aload         5
      97: arraylength
      98: istore        6
     100: iconst_0
     101: istore        7
     103: iload         7
     105: iload         6
     107: if_icmpge     147
     110: aload         5
     112: iload         7
     114: aaload
     115: astore        8
     117: new           #36                 // class org/springframework/boot/context/config/ConfigFileApplicationListener$Profile
     120: dup
     121: aload         8
     123: iconst_1
     124: invokespecial #37                 // Method org/springframework/boot/context/config/ConfigFileApplicationListener$Profile."<init>":(Ljava/lang/String;Z)V
     127: astore        9
     129: aload_0
     130: getfield      #25                 // Field profiles:Ljava/util/Deque;
     133: aload         9
     135: invokeinterface #26,  2           // InterfaceMethod java/util/Deque.add:(Ljava/lang/Object;)Z
     140: pop
     141: iinc          7, 1
     144: goto          103
     147: return

  private java.util.List<org.springframework.boot.context.config.ConfigFileApplicationListener$Profile> getOtherActiveProfiles(java.util.Set<org.springframework.boot.context.config.ConfigFileApplicationListener$Profile>, java.util.Set<org.springframework.boot.context.config.ConfigFileApplicationListener$Profile>);
    Code:
       0: aload_0
       1: getfield      #9                  // Field environment:Lorg/springframework/core/env/ConfigurableEnvironment;
       4: invokeinterface #38,  1           // InterfaceMethod org/springframework/core/env/ConfigurableEnvironment.getActiveProfiles:()[Ljava/lang/String;
       9: invokestatic  #39                 // Method java/util/Arrays.stream:([Ljava/lang/Object;)Ljava/util/stream/Stream;
      12: invokedynamic #40,  0             // InvokeDynamic #1:apply:()Ljava/util/function/Function;
      17: invokeinterface #41,  2           // InterfaceMethod java/util/stream/Stream.map:(Ljava/util/function/Function;)Ljava/util/stream/Stream;
      22: aload_1
      23: aload_2
      24: invokedynamic #42,  0             // InvokeDynamic #2:test:(Ljava/util/Set;Ljava/util/Set;)Ljava/util/function/Predicate;
      29: invokeinterface #43,  2           // InterfaceMethod java/util/stream/Stream.filter:(Ljava/util/function/Predicate;)Ljava/util/stream/Stream;
      34: invokestatic  #44                 // Method java/util/stream/Collectors.toList:()Ljava/util/stream/Collector;
      37: invokeinterface #45,  2           // InterfaceMethod java/util/stream/Stream.collect:(Ljava/util/stream/Collector;)Ljava/lang/Object;
      42: checkcast     #46                 // class java/util/List
      45: areturn

  void addActiveProfiles(java.util.Set<org.springframework.boot.context.config.ConfigFileApplicationListener$Profile>);
    Code:
       0: aload_1
       1: invokeinterface #47,  1           // InterfaceMethod java/util/Set.isEmpty:()Z
       6: ifeq          10
       9: return
      10: aload_0
      11: getfield      #48                 // Field activatedProfiles:Z
      14: ifeq          63
      17: aload_0
      18: getfield      #5                  // Field logger:Lorg/apache/commons/logging/Log;
      21: invokeinterface #49,  1           // InterfaceMethod org/apache/commons/logging/Log.isDebugEnabled:()Z
      26: ifeq          62
      29: aload_0
      30: getfield      #5                  // Field logger:Lorg/apache/commons/logging/Log;
      33: new           #50                 // class java/lang/StringBuilder
      36: dup
      37: invokespecial #51                 // Method java/lang/StringBuilder."<init>":()V
      40: ldc           #52                 // String Profiles already activated, \'
      42: invokevirtual #53                 // Method java/lang/StringBuilder.append:(Ljava/lang/String;)Ljava/lang/StringBuilder;
      45: aload_1
      46: invokevirtual #54                 // Method java/lang/StringBuilder.append:(Ljava/lang/Object;)Ljava/lang/StringBuilder;
      49: ldc           #55                 // String \' will not be applied
      51: invokevirtual #53                 // Method java/lang/StringBuilder.append:(Ljava/lang/String;)Ljava/lang/StringBuilder;
      54: invokevirtual #56                 // Method java/lang/StringBuilder.toString:()Ljava/lang/String;
      57: invokeinterface #57,  2           // InterfaceMethod org/apache/commons/logging/Log.debug:(Ljava/lang/Object;)V
      62: return
      63: aload_0
      64: getfield      #25                 // Field profiles:Ljava/util/Deque;
      67: aload_1
      68: invokeinterface #32,  2           // InterfaceMethod java/util/Deque.addAll:(Ljava/util/Collection;)Z
      73: pop
      74: aload_0
      75: getfield      #5                  // Field logger:Lorg/apache/commons/logging/Log;
      78: invokeinterface #49,  1           // InterfaceMethod org/apache/commons/logging/Log.isDebugEnabled:()Z
      83: ifeq          117
      86: aload_0
      87: getfield      #5                  // Field logger:Lorg/apache/commons/logging/Log;
      90: new           #50                 // class java/lang/StringBuilder
      93: dup
      94: invokespecial #51                 // Method java/lang/StringBuilder."<init>":()V
      97: ldc           #58                 // String Activated activeProfiles
      99: invokevirtual #53                 // Method java/lang/StringBuilder.append:(Ljava/lang/String;)Ljava/lang/StringBuilder;
     102: aload_1
     103: invokestatic  #59                 // Method org/springframework/util/StringUtils.collectionToCommaDelimitedString:(Ljava/util/Collection;)Ljava/lang/String;
     106: invokevirtual #53                 // Method java/lang/StringBuilder.append:(Ljava/lang/String;)Ljava/lang/StringBuilder;
     109: invokevirtual #56                 // Method java/lang/StringBuilder.toString:()Ljava/lang/String;
     112: invokeinterface #57,  2           // InterfaceMethod org/apache/commons/logging/Log.debug:(Ljava/lang/Object;)V
     117: aload_0
     118: iconst_1
     119: putfield      #48                 // Field activatedProfiles:Z
     122: aload_0
     123: invokespecial #60                 // Method removeUnprocessedDefaultProfiles:()V
     126: return

  private void removeUnprocessedDefaultProfiles();
    Code:
       0: aload_0
       1: getfield      #25                 // Field profiles:Ljava/util/Deque;
       4: invokedynamic #61,  0             // InvokeDynamic #3:test:()Ljava/util/function/Predicate;
       9: invokeinterface #62,  2           // InterfaceMethod java/util/Deque.removeIf:(Ljava/util/function/Predicate;)Z
      14: pop
      15: return

  private org.springframework.boot.context.config.ConfigFileApplicationListener$DocumentFilter getPositiveProfileFilter(org.springframework.boot.context.config.ConfigFileApplicationListener$Profile);
    Code:
       0: aload_0
       1: aload_1
       2: invokedynamic #63,  0             // InvokeDynamic #4:match:(Lorg/springframework/boot/context/config/ConfigFileApplicationListener$Loader;Lorg/springframework/boot/context/config/ConfigFileApplicationListener$Profile;)Lorg/springframework/boot/context/config/ConfigFileApplicationListener$DocumentFilter;
       7: areturn

  private org.springframework.boot.context.config.ConfigFileApplicationListener$DocumentFilter getNegativeProfileFilter(org.springframework.boot.context.config.ConfigFileApplicationListener$Profile);
    Code:
       0: aload_0
       1: aload_1
       2: invokedynamic #64,  0             // InvokeDynamic #5:match:(Lorg/springframework/boot/context/config/ConfigFileApplicationListener$Loader;Lorg/springframework/boot/context/config/ConfigFileApplicationListener$Profile;)Lorg/springframework/boot/context/config/ConfigFileApplicationListener$DocumentFilter;
       7: areturn

  private org.springframework.boot.context.config.ConfigFileApplicationListener$DocumentConsumer addToLoaded(java.util.function.BiConsumer<org.springframework.core.env.MutablePropertySources, org.springframework.core.env.PropertySource<?>>, boolean);
    Code:
       0: aload_0
       1: iload_2
       2: aload_1
       3: invokedynamic #65,  0             // InvokeDynamic #6:accept:(Lorg/springframework/boot/context/config/ConfigFileApplicationListener$Loader;ZLjava/util/function/BiConsumer;)Lorg/springframework/boot/context/config/ConfigFileApplicationListener$DocumentConsumer;
       8: areturn

  private void load(org.springframework.boot.context.config.ConfigFileApplicationListener$Profile, org.springframework.boot.context.config.ConfigFileApplicationListener$DocumentFilterFactory, org.springframework.boot.context.config.ConfigFileApplicationListener$DocumentConsumer);
    Code:
       0: aload_0
       1: invokespecial #66                 // Method getSearchLocations:()Ljava/util/Set;
       4: aload_0
       5: aload_1
       6: aload_2
       7: aload_3
       8: invokedynamic #67,  0             // InvokeDynamic #7:accept:(Lorg/springframework/boot/context/config/ConfigFileApplicationListener$Loader;Lorg/springframework/boot/context/config/ConfigFileApplicationListener$Profile;Lorg/springframework/boot/context/config/ConfigFileApplicationListener$DocumentFilterFactory;Lorg/springframework/boot/context/config/ConfigFileApplicationListener$DocumentConsumer;)Ljava/util/function/Consumer;
      13: invokeinterface #68,  2           // InterfaceMethod java/util/Set.forEach:(Ljava/util/function/Consumer;)V
      18: return

  private void load(java.lang.String, java.lang.String, org.springframework.boot.context.config.ConfigFileApplicationListener$Profile, org.springframework.boot.context.config.ConfigFileApplicationListener$DocumentFilterFactory, org.springframework.boot.context.config.ConfigFileApplicationListener$DocumentConsumer);
    Code:
       0: aload_2
       1: invokestatic  #69                 // Method org/springframework/util/StringUtils.hasText:(Ljava/lang/String;)Z
       4: ifne          104
       7: aload_0
       8: getfield      #20                 // Field propertySourceLoaders:Ljava/util/List;
      11: invokeinterface #70,  1           // InterfaceMethod java/util/List.iterator:()Ljava/util/Iterator;
      16: astore        6
      18: aload         6
      20: invokeinterface #71,  1           // InterfaceMethod java/util/Iterator.hasNext:()Z
      25: ifeq          72
      28: aload         6
      30: invokeinterface #72,  1           // InterfaceMethod java/util/Iterator.next:()Ljava/lang/Object;
      35: checkcast     #16                 // class org/springframework/boot/env/PropertySourceLoader
      38: astore        7
      40: aload_0
      41: aload         7
      43: aload_1
      44: invokespecial #73                 // Method canLoadFileExtension:(Lorg/springframework/boot/env/PropertySourceLoader;Ljava/lang/String;)Z
      47: ifeq          69
      50: aload_0
      51: aload         7
      53: aload_1
      54: aload_3
      55: aload         4
      57: aload_3
      58: invokeinterface #74,  2           // InterfaceMethod org/springframework/boot/context/config/ConfigFileApplicationListener$DocumentFilterFactory.getDocumentFilter:(Lorg/springframework/boot/context/config/ConfigFileApplicationListener$Profile;)Lorg/springframework/boot/context/config/ConfigFileApplicationListener$DocumentFilter;
      63: aload         5
      65: invokespecial #75                 // Method load:(Lorg/springframework/boot/env/PropertySourceLoader;Ljava/lang/String;Lorg/springframework/boot/context/config/ConfigFileApplicationListener$Profile;Lorg/springframework/boot/context/config/ConfigFileApplicationListener$DocumentFilter;Lorg/springframework/boot/context/config/ConfigFileApplicationListener$DocumentConsumer;)V
      68: return
      69: goto          18
      72: new           #76                 // class java/lang/IllegalStateException
      75: dup
      76: new           #50                 // class java/lang/StringBuilder
      79: dup
      80: invokespecial #51                 // Method java/lang/StringBuilder."<init>":()V
      83: ldc           #77                 // String File extension of config file location \'
      85: invokevirtual #53                 // Method java/lang/StringBuilder.append:(Ljava/lang/String;)Ljava/lang/StringBuilder;
      88: aload_1
      89: invokevirtual #53                 // Method java/lang/StringBuilder.append:(Ljava/lang/String;)Ljava/lang/StringBuilder;
      92: ldc           #78                 // String \' is not known to any PropertySourceLoader. If the location is meant to reference a directory, it must end in \'/\'
      94: invokevirtual #53                 // Method java/lang/StringBuilder.append:(Ljava/lang/String;)Ljava/lang/StringBuilder;
      97: invokevirtual #56                 // Method java/lang/StringBuilder.toString:()Ljava/lang/String;
     100: invokespecial #79                 // Method java/lang/IllegalStateException."<init>":(Ljava/lang/String;)V
     103: athrow
     104: new           #80                 // class java/util/HashSet
     107: dup
     108: invokespecial #81                 // Method java/util/HashSet."<init>":()V
     111: astore        6
     113: aload_0
     114: getfield      #20                 // Field propertySourceLoaders:Ljava/util/List;
     117: invokeinterface #70,  1           // InterfaceMethod java/util/List.iterator:()Ljava/util/Iterator;
     122: astore        7
     124: aload         7
     126: invokeinterface #71,  1           // InterfaceMethod java/util/Iterator.hasNext:()Z
     131: ifeq          247
     134: aload         7
     136: invokeinterface #72,  1           // InterfaceMethod java/util/Iterator.next:()Ljava/lang/Object;
     141: checkcast     #16                 // class org/springframework/boot/env/PropertySourceLoader
     144: astore        8
     146: aload         8
     148: invokeinterface #82,  1           // InterfaceMethod org/springframework/boot/env/PropertySourceLoader.getFileExtensions:()[Ljava/lang/String;
     153: astore        9
     155: aload         9
     157: arraylength
     158: istore        10
     160: iconst_0
     161: istore        11
     163: iload         11
     165: iload         10
     167: if_icmpge     244
     170: aload         9
     172: iload         11
     174: aaload
     175: astore        12
     177: aload         6
     179: aload         12
     181: invokeinterface #83,  2           // InterfaceMethod java/util/Set.add:(Ljava/lang/Object;)Z
     186: ifeq          238
     189: aload_0
     190: aload         8
     192: new           #50                 // class java/lang/StringBuilder
     195: dup
     196: invokespecial #51                 // Method java/lang/StringBuilder."<init>":()V
     199: aload_1
     200: invokevirtual #53                 // Method java/lang/StringBuilder.append:(Ljava/lang/String;)Ljava/lang/StringBuilder;
     203: aload_2
     204: invokevirtual #53                 // Method java/lang/StringBuilder.append:(Ljava/lang/String;)Ljava/lang/StringBuilder;
     207: invokevirtual #56                 // Method java/lang/StringBuilder.toString:()Ljava/lang/String;
     210: new           #50                 // class java/lang/StringBuilder
     213: dup
     214: invokespecial #51                 // Method java/lang/StringBuilder."<init>":()V
     217: ldc           #84                 // String .
     219: invokevirtual #53                 // Method java/lang/StringBuilder.append:(Ljava/lang/String;)Ljava/lang/StringBuilder;
     222: aload         12
     224: invokevirtual #53                 // Method java/lang/StringBuilder.append:(Ljava/lang/String;)Ljava/lang/StringBuilder;
     227: invokevirtual #56                 // Method java/lang/StringBuilder.toString:()Ljava/lang/String;
     230: aload_3
     231: aload         4
     233: aload         5
     235: invokespecial #85                 // Method loadForFileExtension:(Lorg/springframework/boot/env/PropertySourceLoader;Ljava/lang/String;Ljava/lang/String;Lorg/springframework/boot/context/config/ConfigFileApplicationListener$Profile;Lorg/springframework/boot/context/config/ConfigFileApplicationListener$DocumentFilterFactory;Lorg/springframework/boot/context/config/ConfigFileApplicationListener$DocumentConsumer;)V
     238: iinc          11, 1
     241: goto          163
     244: goto          124
     247: return

  private boolean canLoadFileExtension(org.springframework.boot.env.PropertySourceLoader, java.lang.String);
    Code:
       0: aload_1
       1: invokeinterface #82,  1           // InterfaceMethod org/springframework/boot/env/PropertySourceLoader.getFileExtensions:()[Ljava/lang/String;
       6: invokestatic  #39                 // Method java/util/Arrays.stream:([Ljava/lang/Object;)Ljava/util/stream/Stream;
       9: aload_2
      10: invokedynamic #86,  0             // InvokeDynamic #8:test:(Ljava/lang/String;)Ljava/util/function/Predicate;
      15: invokeinterface #87,  2           // InterfaceMethod java/util/stream/Stream.anyMatch:(Ljava/util/function/Predicate;)Z
      20: ireturn

  private void loadForFileExtension(org.springframework.boot.env.PropertySourceLoader, java.lang.String, java.lang.String, org.springframework.boot.context.config.ConfigFileApplicationListener$Profile, org.springframework.boot.context.config.ConfigFileApplicationListener$DocumentFilterFactory, org.springframework.boot.context.config.ConfigFileApplicationListener$DocumentConsumer);
    Code:
       0: aload         5
       2: aconst_null
       3: invokeinterface #74,  2           // InterfaceMethod org/springframework/boot/context/config/ConfigFileApplicationListener$DocumentFilterFactory.getDocumentFilter:(Lorg/springframework/boot/context/config/ConfigFileApplicationListener$Profile;)Lorg/springframework/boot/context/config/ConfigFileApplicationListener$DocumentFilter;
       8: astore        7
      10: aload         5
      12: aload         4
      14: invokeinterface #74,  2           // InterfaceMethod org/springframework/boot/context/config/ConfigFileApplicationListener$DocumentFilterFactory.getDocumentFilter:(Lorg/springframework/boot/context/config/ConfigFileApplicationListener$Profile;)Lorg/springframework/boot/context/config/ConfigFileApplicationListener$DocumentFilter;
      19: astore        8
      21: aload         4
      23: ifnull        166
      26: new           #50                 // class java/lang/StringBuilder
      29: dup
      30: invokespecial #51                 // Method java/lang/StringBuilder."<init>":()V
      33: aload_2
      34: invokevirtual #53                 // Method java/lang/StringBuilder.append:(Ljava/lang/String;)Ljava/lang/StringBuilder;
      37: ldc           #88                 // String -
      39: invokevirtual #53                 // Method java/lang/StringBuilder.append:(Ljava/lang/String;)Ljava/lang/StringBuilder;
      42: aload         4
      44: invokevirtual #54                 // Method java/lang/StringBuilder.append:(Ljava/lang/Object;)Ljava/lang/StringBuilder;
      47: aload_3
      48: invokevirtual #53                 // Method java/lang/StringBuilder.append:(Ljava/lang/String;)Ljava/lang/StringBuilder;
      51: invokevirtual #56                 // Method java/lang/StringBuilder.toString:()Ljava/lang/String;
      54: astore        9
      56: aload_0
      57: aload_1
      58: aload         9
      60: aload         4
      62: aload         7
      64: aload         6
      66: invokespecial #75                 // Method load:(Lorg/springframework/boot/env/PropertySourceLoader;Ljava/lang/String;Lorg/springframework/boot/context/config/ConfigFileApplicationListener$Profile;Lorg/springframework/boot/context/config/ConfigFileApplicationListener$DocumentFilter;Lorg/springframework/boot/context/config/ConfigFileApplicationListener$DocumentConsumer;)V
      69: aload_0
      70: aload_1
      71: aload         9
      73: aload         4
      75: aload         8
      77: aload         6
      79: invokespecial #75                 // Method load:(Lorg/springframework/boot/env/PropertySourceLoader;Ljava/lang/String;Lorg/springframework/boot/context/config/ConfigFileApplicationListener$Profile;Lorg/springframework/boot/context/config/ConfigFileApplicationListener$DocumentFilter;Lorg/springframework/boot/context/config/ConfigFileApplicationListener$DocumentConsumer;)V
      82: aload_0
      83: getfield      #89                 // Field processedProfiles:Ljava/util/List;
      86: invokeinterface #70,  1           // InterfaceMethod java/util/List.iterator:()Ljava/util/Iterator;
      91: astore        10
      93: aload         10
      95: invokeinterface #71,  1           // InterfaceMethod java/util/Iterator.hasNext:()Z
     100: ifeq          166
     103: aload         10
     105: invokeinterface #72,  1           // InterfaceMethod java/util/Iterator.next:()Ljava/lang/Object;
     110: checkcast     #36                 // class org/springframework/boot/context/config/ConfigFileApplicationListener$Profile
     113: astore        11
     115: aload         11
     117: ifnull        163
     120: new           #50                 // class java/lang/StringBuilder
     123: dup
     124: invokespecial #51                 // Method java/lang/StringBuilder."<init>":()V
     127: aload_2
     128: invokevirtual #53                 // Method java/lang/StringBuilder.append:(Ljava/lang/String;)Ljava/lang/StringBuilder;
     131: ldc           #88                 // String -
     133: invokevirtual #53                 // Method java/lang/StringBuilder.append:(Ljava/lang/String;)Ljava/lang/StringBuilder;
     136: aload         11
     138: invokevirtual #54                 // Method java/lang/StringBuilder.append:(Ljava/lang/Object;)Ljava/lang/StringBuilder;
     141: aload_3
     142: invokevirtual #53                 // Method java/lang/StringBuilder.append:(Ljava/lang/String;)Ljava/lang/StringBuilder;
     145: invokevirtual #56                 // Method java/lang/StringBuilder.toString:()Ljava/lang/String;
     148: astore        12
     150: aload_0
     151: aload_1
     152: aload         12
     154: aload         4
     156: aload         8
     158: aload         6
     160: invokespecial #75                 // Method load:(Lorg/springframework/boot/env/PropertySourceLoader;Ljava/lang/String;Lorg/springframework/boot/context/config/ConfigFileApplicationListener$Profile;Lorg/springframework/boot/context/config/ConfigFileApplicationListener$DocumentFilter;Lorg/springframework/boot/context/config/ConfigFileApplicationListener$DocumentConsumer;)V
     163: goto          93
     166: aload_0
     167: aload_1
     168: new           #50                 // class java/lang/StringBuilder
     171: dup
     172: invokespecial #51                 // Method java/lang/StringBuilder."<init>":()V
     175: aload_2
     176: invokevirtual #53                 // Method java/lang/StringBuilder.append:(Ljava/lang/String;)Ljava/lang/StringBuilder;
     179: aload_3
     180: invokevirtual #53                 // Method java/lang/StringBuilder.append:(Ljava/lang/String;)Ljava/lang/StringBuilder;
     183: invokevirtual #56                 // Method java/lang/StringBuilder.toString:()Ljava/lang/String;
     186: aload         4
     188: aload         8
     190: aload         6
     192: invokespecial #75                 // Method load:(Lorg/springframework/boot/env/PropertySourceLoader;Ljava/lang/String;Lorg/springframework/boot/context/config/ConfigFileApplicationListener$Profile;Lorg/springframework/boot/context/config/ConfigFileApplicationListener$DocumentFilter;Lorg/springframework/boot/context/config/ConfigFileApplicationListener$DocumentConsumer;)V
     195: return

  private void load(org.springframework.boot.env.PropertySourceLoader, java.lang.String, org.springframework.boot.context.config.ConfigFileApplicationListener$Profile, org.springframework.boot.context.config.ConfigFileApplicationListener$DocumentFilter, org.springframework.boot.context.config.ConfigFileApplicationListener$DocumentConsumer);
    Code:
       0: aload_0
       1: aload_2
       2: invokespecial #90                 // Method getResources:(Ljava/lang/String;)[Lorg/springframework/core/io/Resource;
       5: astore        6
       7: aload         6
       9: astore        7
      11: aload         7
      13: arraylength
      14: istore        8
      16: iconst_0
      17: istore        9
      19: iload         9
      21: iload         8
      23: if_icmpge     415
      26: aload         7
      28: iload         9
      30: aaload
      31: astore        10
      33: aload         10
      35: ifnull        48
      38: aload         10
      40: invokeinterface #91,  1           // InterfaceMethod org/springframework/core/io/Resource.exists:()Z
      45: ifne          86
      48: aload_0
      49: getfield      #5                  // Field logger:Lorg/apache/commons/logging/Log;
      52: invokeinterface #92,  1           // InterfaceMethod org/apache/commons/logging/Log.isTraceEnabled:()Z
      57: ifeq          83
      60: aload_0
      61: ldc           #93                 // String Skipped missing config
      63: aload_2
      64: aload         10
      66: aload_3
      67: invokespecial #94                 // Method getDescription:(Ljava/lang/String;Ljava/lang/String;Lorg/springframework/core/io/Resource;Lorg/springframework/boot/context/config/ConfigFileApplicationListener$Profile;)Ljava/lang/StringBuilder;
      70: astore        11
      72: aload_0
      73: getfield      #5                  // Field logger:Lorg/apache/commons/logging/Log;
      76: aload         11
      78: invokeinterface #95,  2           // InterfaceMethod org/apache/commons/logging/Log.trace:(Ljava/lang/Object;)V
      83: goto          409
      86: aload         10
      88: invokeinterface #96,  1           // InterfaceMethod org/springframework/core/io/Resource.getFilename:()Ljava/lang/String;
      93: invokestatic  #97                 // Method org/springframework/util/StringUtils.getFilenameExtension:(Ljava/lang/String;)Ljava/lang/String;
      96: invokestatic  #69                 // Method org/springframework/util/StringUtils.hasText:(Ljava/lang/String;)Z
      99: ifne          140
     102: aload_0
     103: getfield      #5                  // Field logger:Lorg/apache/commons/logging/Log;
     106: invokeinterface #92,  1           // InterfaceMethod org/apache/commons/logging/Log.isTraceEnabled:()Z
     111: ifeq          137
     114: aload_0
     115: ldc           #98                 // String Skipped empty config extension
     117: aload_2
     118: aload         10
     120: aload_3
     121: invokespecial #94                 // Method getDescription:(Ljava/lang/String;Ljava/lang/String;Lorg/springframework/core/io/Resource;Lorg/springframework/boot/context/config/ConfigFileApplicationListener$Profile;)Ljava/lang/StringBuilder;
     124: astore        11
     126: aload_0
     127: getfield      #5                  // Field logger:Lorg/apache/commons/logging/Log;
     130: aload         11
     132: invokeinterface #95,  2           // InterfaceMethod org/apache/commons/logging/Log.trace:(Ljava/lang/Object;)V
     137: goto          409
     140: new           #50                 // class java/lang/StringBuilder
     143: dup
     144: invokespecial #51                 // Method java/lang/StringBuilder."<init>":()V
     147: ldc           #99                 // String applicationConfig: [
     149: invokevirtual #53                 // Method java/lang/StringBuilder.append:(Ljava/lang/String;)Ljava/lang/StringBuilder;
     152: aload_0
     153: aload_2
     154: aload         10
     156: invokespecial #100                // Method getLocationName:(Ljava/lang/String;Lorg/springframework/core/io/Resource;)Ljava/lang/String;
     159: invokevirtual #53                 // Method java/lang/StringBuilder.append:(Ljava/lang/String;)Ljava/lang/StringBuilder;
     162: ldc           #101                // String ]
     164: invokevirtual #53                 // Method java/lang/StringBuilder.append:(Ljava/lang/String;)Ljava/lang/StringBuilder;
     167: invokevirtual #56                 // Method java/lang/StringBuilder.toString:()Ljava/lang/String;
     170: astore        11
     172: aload_0
     173: aload_1
     174: aload         11
     176: aload         10
     178: invokespecial #102                // Method loadDocuments:(Lorg/springframework/boot/env/PropertySourceLoader;Ljava/lang/String;Lorg/springframework/core/io/Resource;)Ljava/util/List;
     181: astore        12
     183: aload         12
     185: invokestatic  #103                // Method org/springframework/util/CollectionUtils.isEmpty:(Ljava/util/Collection;)Z
     188: ifeq          229
     191: aload_0
     192: getfield      #5                  // Field logger:Lorg/apache/commons/logging/Log;
     195: invokeinterface #92,  1           // InterfaceMethod org/apache/commons/logging/Log.isTraceEnabled:()Z
     200: ifeq          226
     203: aload_0
     204: ldc           #104                // String Skipped unloaded config
     206: aload_2
     207: aload         10
     209: aload_3
     210: invokespecial #94                 // Method getDescription:(Ljava/lang/String;Ljava/lang/String;Lorg/springframework/core/io/Resource;Lorg/springframework/boot/context/config/ConfigFileApplicationListener$Profile;)Ljava/lang/StringBuilder;
     213: astore        13
     215: aload_0
     216: getfield      #5                  // Field logger:Lorg/apache/commons/logging/Log;
     219: aload         13
     221: invokeinterface #95,  2           // InterfaceMethod org/apache/commons/logging/Log.trace:(Ljava/lang/Object;)V
     226: goto          409
     229: new           #105                // class java/util/ArrayList
     232: dup
     233: invokespecial #106                // Method java/util/ArrayList."<init>":()V
     236: astore        13
     238: aload         12
     240: invokeinterface #70,  1           // InterfaceMethod java/util/List.iterator:()Ljava/util/Iterator;
     245: astore        14
     247: aload         14
     249: invokeinterface #71,  1           // InterfaceMethod java/util/Iterator.hasNext:()Z
     254: ifeq          312
     257: aload         14
     259: invokeinterface #72,  1           // InterfaceMethod java/util/Iterator.next:()Ljava/lang/Object;
     264: checkcast     #107                // class org/springframework/boot/context/config/ConfigFileApplicationListener$Document
     267: astore        15
     269: aload         4
     271: aload         15
     273: invokeinterface #108,  2          // InterfaceMethod org/springframework/boot/context/config/ConfigFileApplicationListener$DocumentFilter.match:(Lorg/springframework/boot/context/config/ConfigFileApplicationListener$Document;)Z
     278: ifeq          309
     281: aload_0
     282: aload         15
     284: invokevirtual #109                // Method org/springframework/boot/context/config/ConfigFileApplicationListener$Document.getActiveProfiles:()Ljava/util/Set;
     287: invokevirtual #33                 // Method addActiveProfiles:(Ljava/util/Set;)V
     290: aload_0
     291: aload         15
     293: invokevirtual #110                // Method org/springframework/boot/context/config/ConfigFileApplicationListener$Document.getIncludeProfiles:()Ljava/util/Set;
     296: invokespecial #111                // Method addIncludedProfiles:(Ljava/util/Set;)V
     299: aload         13
     301: aload         15
     303: invokeinterface #112,  2          // InterfaceMethod java/util/List.add:(Ljava/lang/Object;)Z
     308: pop
     309: goto          247
     312: aload         13
     314: invokestatic  #113                // Method java/util/Collections.reverse:(Ljava/util/List;)V
     317: aload         13
     319: invokeinterface #114,  1          // InterfaceMethod java/util/List.isEmpty:()Z
     324: ifne          377
     327: aload         13
     329: aload         5
     331: aload_3
     332: invokedynamic #115,  0            // InvokeDynamic #9:accept:(Lorg/springframework/boot/context/config/ConfigFileApplicationListener$DocumentConsumer;Lorg/springframework/boot/context/config/ConfigFileApplicationListener$Profile;)Ljava/util/function/Consumer;
     337: invokeinterface #116,  2          // InterfaceMethod java/util/List.forEach:(Ljava/util/function/Consumer;)V
     342: aload_0
     343: getfield      #5                  // Field logger:Lorg/apache/commons/logging/Log;
     346: invokeinterface #49,  1           // InterfaceMethod org/apache/commons/logging/Log.isDebugEnabled:()Z
     351: ifeq          377
     354: aload_0
     355: ldc           #117                // String Loaded config file
     357: aload_2
     358: aload         10
     360: aload_3
     361: invokespecial #94                 // Method getDescription:(Ljava/lang/String;Ljava/lang/String;Lorg/springframework/core/io/Resource;Lorg/springframework/boot/context/config/ConfigFileApplicationListener$Profile;)Ljava/lang/StringBuilder;
     364: astore        14
     366: aload_0
     367: getfield      #5                  // Field logger:Lorg/apache/commons/logging/Log;
     370: aload         14
     372: invokeinterface #57,  2           // InterfaceMethod org/apache/commons/logging/Log.debug:(Ljava/lang/Object;)V
     377: goto          409
     380: astore        11
     382: aload_0
     383: ldc           #119                // String Failed to load property source from
     385: aload_2
     386: aload         10
     388: aload_3
     389: invokespecial #94                 // Method getDescription:(Ljava/lang/String;Ljava/lang/String;Lorg/springframework/core/io/Resource;Lorg/springframework/boot/context/config/ConfigFileApplicationListener$Profile;)Ljava/lang/StringBuilder;
     392: astore        12
     394: new           #76                 // class java/lang/IllegalStateException
     397: dup
     398: aload         12
     400: invokevirtual #56                 // Method java/lang/StringBuilder.toString:()Ljava/lang/String;
     403: aload         11
     405: invokespecial #120                // Method java/lang/IllegalStateException."<init>":(Ljava/lang/String;Ljava/lang/Throwable;)V
     408: athrow
     409: iinc          9, 1
     412: goto          19
     415: return
    Exception table:
       from    to  target type
          33    83   380   Class java/lang/Exception
          86   137   380   Class java/lang/Exception
         140   226   380   Class java/lang/Exception
         229   377   380   Class java/lang/Exception

  private java.lang.String getLocationName(java.lang.String, org.springframework.core.io.Resource);
    Code:
       0: aload_1
       1: ldc           #121                // String *
       3: invokevirtual #122                // Method java/lang/String.contains:(Ljava/lang/CharSequence;)Z
       6: ifne          11
       9: aload_1
      10: areturn
      11: aload_2
      12: instanceof    #123                // class org/springframework/core/io/FileSystemResource
      15: ifeq          26
      18: aload_2
      19: checkcast     #123                // class org/springframework/core/io/FileSystemResource
      22: invokevirtual #124                // Method org/springframework/core/io/FileSystemResource.getPath:()Ljava/lang/String;
      25: areturn
      26: aload_2
      27: invokeinterface #125,  1          // InterfaceMethod org/springframework/core/io/Resource.getDescription:()Ljava/lang/String;
      32: areturn

  private org.springframework.core.io.Resource[] getResources(java.lang.String);
    Code:
       0: aload_1
       1: ldc           #121                // String *
       3: invokevirtual #122                // Method java/lang/String.contains:(Ljava/lang/CharSequence;)Z
       6: ifeq          15
       9: aload_0
      10: aload_1
      11: invokespecial #126                // Method getResourcesFromPatternLocation:(Ljava/lang/String;)[Lorg/springframework/core/io/Resource;
      14: areturn
      15: iconst_1
      16: anewarray     #127                // class org/springframework/core/io/Resource
      19: dup
      20: iconst_0
      21: aload_0
      22: getfield      #15                 // Field resourceLoader:Lorg/springframework/core/io/ResourceLoader;
      25: aload_1
      26: invokeinterface #128,  2          // InterfaceMethod org/springframework/core/io/ResourceLoader.getResource:(Ljava/lang/String;)Lorg/springframework/core/io/Resource;
      31: aastore
      32: areturn
      33: astore_2
      34: invokestatic  #129                // Method org/springframework/boot/context/config/ConfigFileApplicationListener.access$200:()[Lorg/springframework/core/io/Resource;
      37: areturn
    Exception table:
       from    to  target type
           0    14    33   Class java/lang/Exception
          15    32    33   Class java/lang/Exception

  private org.springframework.core.io.Resource[] getResourcesFromPatternLocation(java.lang.String) throws java.io.IOException;
    Code:
       0: aload_1
       1: iconst_0
       2: aload_1
       3: ldc           #130                // String */
       5: invokevirtual #131                // Method java/lang/String.indexOf:(Ljava/lang/String;)I
       8: invokevirtual #132                // Method java/lang/String.substring:(II)Ljava/lang/String;
      11: astore_2
      12: aload_0
      13: getfield      #15                 // Field resourceLoader:Lorg/springframework/core/io/ResourceLoader;
      16: aload_2
      17: invokeinterface #128,  2          // InterfaceMethod org/springframework/core/io/ResourceLoader.getResource:(Ljava/lang/String;)Lorg/springframework/core/io/Resource;
      22: astore_3
      23: aload_3
      24: invokeinterface #133,  1          // InterfaceMethod org/springframework/core/io/Resource.getFile:()Ljava/io/File;
      29: invokedynamic #134,  0            // InvokeDynamic #10:accept:()Ljava/io/FileFilter;
      34: invokevirtual #135                // Method java/io/File.listFiles:(Ljava/io/FileFilter;)[Ljava/io/File;
      37: astore        4
      39: aload         4
      41: ifnull        127
      44: aload_1
      45: aload_1
      46: ldc           #136                // String /
      48: invokevirtual #137                // Method java/lang/String.lastIndexOf:(Ljava/lang/String;)I
      51: iconst_1
      52: iadd
      53: invokevirtual #138                // Method java/lang/String.substring:(I)Ljava/lang/String;
      56: astore        5
      58: aload         4
      60: invokestatic  #139                // Method org/springframework/boot/context/config/ConfigFileApplicationListener.access$300:()Ljava/util/Comparator;
      63: invokestatic  #140                // Method java/util/Arrays.sort:([Ljava/lang/Object;Ljava/util/Comparator;)V
      66: aload         4
      68: invokestatic  #39                 // Method java/util/Arrays.stream:([Ljava/lang/Object;)Ljava/util/stream/Stream;
      71: aload         5
      73: invokedynamic #141,  0            // InvokeDynamic #11:apply:(Ljava/lang/String;)Ljava/util/function/Function;
      78: invokeinterface #41,  2           // InterfaceMethod java/util/stream/Stream.map:(Ljava/util/function/Function;)Ljava/util/stream/Stream;
      83: invokedynamic #142,  0            // InvokeDynamic #12:test:()Ljava/util/function/Predicate;
      88: invokeinterface #43,  2           // InterfaceMethod java/util/stream/Stream.filter:(Ljava/util/function/Predicate;)Ljava/util/stream/Stream;
      93: invokedynamic #143,  0            // InvokeDynamic #13:apply:()Ljava/util/function/Function;
      98: invokeinterface #144,  2          // InterfaceMethod java/util/stream/Stream.flatMap:(Ljava/util/function/Function;)Ljava/util/stream/Stream;
     103: invokedynamic #145,  0            // InvokeDynamic #14:apply:()Ljava/util/function/Function;
     108: invokeinterface #41,  2           // InterfaceMethod java/util/stream/Stream.map:(Ljava/util/function/Function;)Ljava/util/stream/Stream;
     113: invokedynamic #146,  0            // InvokeDynamic #15:apply:()Ljava/util/function/IntFunction;
     118: invokeinterface #147,  2          // InterfaceMethod java/util/stream/Stream.toArray:(Ljava/util/function/IntFunction;)[Ljava/lang/Object;
     123: checkcast     #148                // class "[Lorg/springframework/core/io/Resource;"
     126: areturn
     127: invokestatic  #129                // Method org/springframework/boot/context/config/ConfigFileApplicationListener.access$200:()[Lorg/springframework/core/io/Resource;
     130: areturn

  private void addIncludedProfiles(java.util.Set<org.springframework.boot.context.config.ConfigFileApplicationListener$Profile>);
    Code:
       0: new           #149                // class java/util/LinkedList
       3: dup
       4: aload_0
       5: getfield      #25                 // Field profiles:Ljava/util/Deque;
       8: invokespecial #150                // Method java/util/LinkedList."<init>":(Ljava/util/Collection;)V
      11: astore_2
      12: aload_0
      13: getfield      #25                 // Field profiles:Ljava/util/Deque;
      16: invokeinterface #151,  1          // InterfaceMethod java/util/Deque.clear:()V
      21: aload_0
      22: getfield      #25                 // Field profiles:Ljava/util/Deque;
      25: aload_1
      26: invokeinterface #32,  2           // InterfaceMethod java/util/Deque.addAll:(Ljava/util/Collection;)Z
      31: pop
      32: aload_0
      33: getfield      #25                 // Field profiles:Ljava/util/Deque;
      36: aload_0
      37: getfield      #89                 // Field processedProfiles:Ljava/util/List;
      40: invokeinterface #152,  2          // InterfaceMethod java/util/Deque.removeAll:(Ljava/util/Collection;)Z
      45: pop
      46: aload_0
      47: getfield      #25                 // Field profiles:Ljava/util/Deque;
      50: aload_2
      51: invokeinterface #32,  2           // InterfaceMethod java/util/Deque.addAll:(Ljava/util/Collection;)Z
      56: pop
      57: return

  private java.util.List<org.springframework.boot.context.config.ConfigFileApplicationListener$Document> loadDocuments(org.springframework.boot.env.PropertySourceLoader, java.lang.String, org.springframework.core.io.Resource) throws java.io.IOException;
    Code:
       0: new           #153                // class org/springframework/boot/context/config/ConfigFileApplicationListener$DocumentsCacheKey
       3: dup
       4: aload_1
       5: aload_3
       6: invokespecial #154                // Method org/springframework/boot/context/config/ConfigFileApplicationListener$DocumentsCacheKey."<init>":(Lorg/springframework/boot/env/PropertySourceLoader;Lorg/springframework/core/io/Resource;)V
       9: astore        4
      11: aload_0
      12: getfield      #8                  // Field loadDocumentsCache:Ljava/util/Map;
      15: aload         4
      17: invokeinterface #155,  2          // InterfaceMethod java/util/Map.get:(Ljava/lang/Object;)Ljava/lang/Object;
      22: checkcast     #46                 // class java/util/List
      25: astore        5
      27: aload         5
      29: ifnonnull     64
      32: aload_1
      33: aload_2
      34: aload_3
      35: invokeinterface #156,  3          // InterfaceMethod org/springframework/boot/env/PropertySourceLoader.load:(Ljava/lang/String;Lorg/springframework/core/io/Resource;)Ljava/util/List;
      40: astore        6
      42: aload_0
      43: aload         6
      45: invokespecial #157                // Method asDocuments:(Ljava/util/List;)Ljava/util/List;
      48: astore        5
      50: aload_0
      51: getfield      #8                  // Field loadDocumentsCache:Ljava/util/Map;
      54: aload         4
      56: aload         5
      58: invokeinterface #158,  3          // InterfaceMethod java/util/Map.put:(Ljava/lang/Object;Ljava/lang/Object;)Ljava/lang/Object;
      63: pop
      64: aload         5
      66: areturn

  private java.util.List<org.springframework.boot.context.config.ConfigFileApplicationListener$Document> asDocuments(java.util.List<org.springframework.core.env.PropertySource<?>>);
    Code:
       0: aload_1
       1: ifnonnull     8
       4: invokestatic  #159                // Method java/util/Collections.emptyList:()Ljava/util/List;
       7: areturn
       8: aload_1
       9: invokeinterface #160,  1          // InterfaceMethod java/util/List.stream:()Ljava/util/stream/Stream;
      14: aload_0
      15: invokedynamic #161,  0            // InvokeDynamic #16:apply:(Lorg/springframework/boot/context/config/ConfigFileApplicationListener$Loader;)Ljava/util/function/Function;
      20: invokeinterface #41,  2           // InterfaceMethod java/util/stream/Stream.map:(Ljava/util/function/Function;)Ljava/util/stream/Stream;
      25: invokestatic  #44                 // Method java/util/stream/Collectors.toList:()Ljava/util/stream/Collector;
      28: invokeinterface #45,  2           // InterfaceMethod java/util/stream/Stream.collect:(Ljava/util/stream/Collector;)Ljava/lang/Object;
      33: checkcast     #46                 // class java/util/List
      36: areturn

  private java.lang.StringBuilder getDescription(java.lang.String, java.lang.String, org.springframework.core.io.Resource, org.springframework.boot.context.config.ConfigFileApplicationListener$Profile);
    Code:
       0: new           #50                 // class java/lang/StringBuilder
       3: dup
       4: aload_1
       5: invokespecial #162                // Method java/lang/StringBuilder."<init>":(Ljava/lang/String;)V
       8: astore        5
      10: aload_3
      11: ifnull        64
      14: aload_3
      15: invokeinterface #163,  1          // InterfaceMethod org/springframework/core/io/Resource.getURI:()Ljava/net/URI;
      20: invokevirtual #164                // Method java/net/URI.toASCIIString:()Ljava/lang/String;
      23: astore        6
      25: aload         5
      27: ldc           #165                // String \'
      29: invokevirtual #53                 // Method java/lang/StringBuilder.append:(Ljava/lang/String;)Ljava/lang/StringBuilder;
      32: pop
      33: aload         5
      35: aload         6
      37: invokevirtual #53                 // Method java/lang/StringBuilder.append:(Ljava/lang/String;)Ljava/lang/StringBuilder;
      40: pop
      41: aload         5
      43: ldc           #166                // String \' (
      45: invokevirtual #53                 // Method java/lang/StringBuilder.append:(Ljava/lang/String;)Ljava/lang/StringBuilder;
      48: pop
      49: aload         5
      51: aload_2
      52: invokevirtual #53                 // Method java/lang/StringBuilder.append:(Ljava/lang/String;)Ljava/lang/StringBuilder;
      55: pop
      56: aload         5
      58: ldc           #167                // String )
      60: invokevirtual #53                 // Method java/lang/StringBuilder.append:(Ljava/lang/String;)Ljava/lang/StringBuilder;
      63: pop
      64: goto          76
      67: astore        6
      69: aload         5
      71: aload_2
      72: invokevirtual #53                 // Method java/lang/StringBuilder.append:(Ljava/lang/String;)Ljava/lang/StringBuilder;
      75: pop
      76: aload         4
      78: ifnull        97
      81: aload         5
      83: ldc           #169                // String  for profile
      85: invokevirtual #53                 // Method java/lang/StringBuilder.append:(Ljava/lang/String;)Ljava/lang/StringBuilder;
      88: pop
      89: aload         5
      91: aload         4
      93: invokevirtual #54                 // Method java/lang/StringBuilder.append:(Ljava/lang/Object;)Ljava/lang/StringBuilder;
      96: pop
      97: aload         5
      99: areturn
    Exception table:
       from    to  target type
          10    64    67   Class java/io/IOException

  private java.util.Set<org.springframework.boot.context.config.ConfigFileApplicationListener$Profile> getProfiles(org.springframework.boot.context.properties.bind.Binder, java.lang.String);
    Code:
       0: aload_1
       1: aload_2
       2: invokestatic  #170                // Method org/springframework/boot/context/config/ConfigFileApplicationListener.access$400:()Lorg/springframework/boot/context/properties/bind/Bindable;
       5: invokevirtual #171                // Method org/springframework/boot/context/properties/bind/Binder.bind:(Ljava/lang/String;Lorg/springframework/boot/context/properties/bind/Bindable;)Lorg/springframework/boot/context/properties/bind/BindResult;
       8: aload_0
       9: invokedynamic #172,  0            // InvokeDynamic #17:apply:(Lorg/springframework/boot/context/config/ConfigFileApplicationListener$Loader;)Ljava/util/function/Function;
      14: invokevirtual #173                // Method org/springframework/boot/context/properties/bind/BindResult.map:(Ljava/util/function/Function;)Lorg/springframework/boot/context/properties/bind/BindResult;
      17: invokestatic  #174                // Method java/util/Collections.emptySet:()Ljava/util/Set;
      20: invokevirtual #175                // Method org/springframework/boot/context/properties/bind/BindResult.orElse:(Ljava/lang/Object;)Ljava/lang/Object;
      23: checkcast     #176                // class java/util/Set
      26: areturn

  private java.util.Set<org.springframework.boot.context.config.ConfigFileApplicationListener$Profile> asProfileSet(java.lang.String[]);
    Code:
       0: new           #105                // class java/util/ArrayList
       3: dup
       4: invokespecial #106                // Method java/util/ArrayList."<init>":()V
       7: astore_2
       8: aload_1
       9: astore_3
      10: aload_3
      11: arraylength
      12: istore        4
      14: iconst_0
      15: istore        5
      17: iload         5
      19: iload         4
      21: if_icmpge     52
      24: aload_3
      25: iload         5
      27: aaload
      28: astore        6
      30: aload_2
      31: new           #36                 // class org/springframework/boot/context/config/ConfigFileApplicationListener$Profile
      34: dup
      35: aload         6
      37: invokespecial #177                // Method org/springframework/boot/context/config/ConfigFileApplicationListener$Profile."<init>":(Ljava/lang/String;)V
      40: invokeinterface #112,  2          // InterfaceMethod java/util/List.add:(Ljava/lang/Object;)Z
      45: pop
      46: iinc          5, 1
      49: goto          17
      52: new           #178                // class java/util/LinkedHashSet
      55: dup
      56: aload_2
      57: invokespecial #179                // Method java/util/LinkedHashSet."<init>":(Ljava/util/Collection;)V
      60: areturn

  private void addProfileToEnvironment(java.lang.String);
    Code:
       0: aload_0
       1: getfield      #9                  // Field environment:Lorg/springframework/core/env/ConfigurableEnvironment;
       4: invokeinterface #38,  1           // InterfaceMethod org/springframework/core/env/ConfigurableEnvironment.getActiveProfiles:()[Ljava/lang/String;
       9: astore_2
      10: aload_2
      11: arraylength
      12: istore_3
      13: iconst_0
      14: istore        4
      16: iload         4
      18: iload_3
      19: if_icmpge     44
      22: aload_2
      23: iload         4
      25: aaload
      26: astore        5
      28: aload         5
      30: aload_1
      31: invokevirtual #180                // Method java/lang/String.equals:(Ljava/lang/Object;)Z
      34: ifeq          38
      37: return
      38: iinc          4, 1
      41: goto          16
      44: aload_0
      45: getfield      #9                  // Field environment:Lorg/springframework/core/env/ConfigurableEnvironment;
      48: aload_1
      49: invokeinterface #181,  2          // InterfaceMethod org/springframework/core/env/ConfigurableEnvironment.addActiveProfile:(Ljava/lang/String;)V
      54: return

  private java.util.Set<java.lang.String> getSearchLocations();
    Code:
       0: aload_0
       1: ldc           #182                // String spring.config.additional-location
       3: invokespecial #183                // Method getSearchLocations:(Ljava/lang/String;)Ljava/util/Set;
       6: astore_1
       7: aload_0
       8: getfield      #9                  // Field environment:Lorg/springframework/core/env/ConfigurableEnvironment;
      11: ldc           #184                // String spring.config.location
      13: invokeinterface #185,  2          // InterfaceMethod org/springframework/core/env/ConfigurableEnvironment.containsProperty:(Ljava/lang/String;)Z
      18: ifeq          37
      21: aload_1
      22: aload_0
      23: ldc           #184                // String spring.config.location
      25: invokespecial #183                // Method getSearchLocations:(Ljava/lang/String;)Ljava/util/Set;
      28: invokeinterface #186,  2          // InterfaceMethod java/util/Set.addAll:(Ljava/util/Collection;)Z
      33: pop
      34: goto          57
      37: aload_1
      38: aload_0
      39: aload_0
      40: getfield      #2                  // Field this$0:Lorg/springframework/boot/context/config/ConfigFileApplicationListener;
      43: invokestatic  #187                // Method org/springframework/boot/context/config/ConfigFileApplicationListener.access$500:(Lorg/springframework/boot/context/config/ConfigFileApplicationListener;)Ljava/lang/String;
      46: ldc           #188                // String classpath:/,classpath:/config/,file:./,file:./config/*/,file:./config/
      48: invokespecial #189                // Method asResolvedSet:(Ljava/lang/String;Ljava/lang/String;)Ljava/util/Set;
      51: invokeinterface #186,  2          // InterfaceMethod java/util/Set.addAll:(Ljava/util/Collection;)Z
      56: pop
      57: aload_1
      58: areturn

  private java.util.Set<java.lang.String> getSearchLocations(java.lang.String);
    Code:
       0: new           #178                // class java/util/LinkedHashSet
       3: dup
       4: invokespecial #190                // Method java/util/LinkedHashSet."<init>":()V
       7: astore_2
       8: aload_0
       9: getfield      #9                  // Field environment:Lorg/springframework/core/env/ConfigurableEnvironment;
      12: aload_1
      13: invokeinterface #185,  2          // InterfaceMethod org/springframework/core/env/ConfigurableEnvironment.containsProperty:(Ljava/lang/String;)Z
      18: ifeq          147
      21: aload_0
      22: aload_0
      23: getfield      #9                  // Field environment:Lorg/springframework/core/env/ConfigurableEnvironment;
      26: aload_1
      27: invokeinterface #191,  2          // InterfaceMethod org/springframework/core/env/ConfigurableEnvironment.getProperty:(Ljava/lang/String;)Ljava/lang/String;
      32: aconst_null
      33: invokespecial #189                // Method asResolvedSet:(Ljava/lang/String;Ljava/lang/String;)Ljava/util/Set;
      36: invokeinterface #192,  1          // InterfaceMethod java/util/Set.iterator:()Ljava/util/Iterator;
      41: astore_3
      42: aload_3
      43: invokeinterface #71,  1           // InterfaceMethod java/util/Iterator.hasNext:()Z
      48: ifeq          147
      51: aload_3
      52: invokeinterface #72,  1           // InterfaceMethod java/util/Iterator.next:()Ljava/lang/Object;
      57: checkcast     #193                // class java/lang/String
      60: astore        4
      62: aload         4
      64: ldc           #194                // String $
      66: invokevirtual #122                // Method java/lang/String.contains:(Ljava/lang/CharSequence;)Z
      69: ifne          135
      72: aload         4
      74: invokestatic  #195                // Method org/springframework/util/StringUtils.cleanPath:(Ljava/lang/String;)Ljava/lang/String;
      77: astore        4
      79: aload         4
      81: ldc           #197                // String classpath*:
      83: invokevirtual #198                // Method java/lang/String.startsWith:(Ljava/lang/String;)Z
      86: ifne          93
      89: iconst_1
      90: goto          94
      93: iconst_0
      94: ldc           #199                // String Classpath wildcard patterns cannot be used as a search location
      96: invokestatic  #200                // Method org/springframework/util/Assert.state:(ZLjava/lang/String;)V
      99: aload_0
     100: aload         4
     102: invokespecial #201                // Method validateWildcardLocation:(Ljava/lang/String;)V
     105: aload         4
     107: invokestatic  #202                // Method org/springframework/util/ResourceUtils.isUrl:(Ljava/lang/String;)Z
     110: ifne          135
     113: new           #50                 // class java/lang/StringBuilder
     116: dup
     117: invokespecial #51                 // Method java/lang/StringBuilder."<init>":()V
     120: ldc           #204                // String file:
     122: invokevirtual #53                 // Method java/lang/StringBuilder.append:(Ljava/lang/String;)Ljava/lang/StringBuilder;
     125: aload         4
     127: invokevirtual #53                 // Method java/lang/StringBuilder.append:(Ljava/lang/String;)Ljava/lang/StringBuilder;
     130: invokevirtual #56                 // Method java/lang/StringBuilder.toString:()Ljava/lang/String;
     133: astore        4
     135: aload_2
     136: aload         4
     138: invokeinterface #83,  2           // InterfaceMethod java/util/Set.add:(Ljava/lang/Object;)Z
     143: pop
     144: goto          42
     147: aload_2
     148: areturn

  private void validateWildcardLocation(java.lang.String);
    Code:
       0: aload_1
       1: ldc           #121                // String *
       3: invokevirtual #122                // Method java/lang/String.contains:(Ljava/lang/CharSequence;)Z
       6: ifeq          62
       9: aload_1
      10: ldc           #121                // String *
      12: invokestatic  #205                // Method org/springframework/util/StringUtils.countOccurrencesOf:(Ljava/lang/String;Ljava/lang/String;)I
      15: iconst_1
      16: if_icmpne     23
      19: iconst_1
      20: goto          24
      23: iconst_0
      24: aload_1
      25: invokedynamic #206,  0            // InvokeDynamic #18:get:(Ljava/lang/String;)Ljava/util/function/Supplier;
      30: invokestatic  #207                // Method org/springframework/util/Assert.state:(ZLjava/util/function/Supplier;)V
      33: aload_1
      34: iconst_0
      35: aload_1
      36: ldc           #136                // String /
      38: invokevirtual #137                // Method java/lang/String.lastIndexOf:(Ljava/lang/String;)I
      41: iconst_1
      42: iadd
      43: invokevirtual #132                // Method java/lang/String.substring:(II)Ljava/lang/String;
      46: astore_2
      47: aload_2
      48: ldc           #130                // String */
      50: invokevirtual #208                // Method java/lang/String.endsWith:(Ljava/lang/String;)Z
      53: aload_1
      54: invokedynamic #209,  0            // InvokeDynamic #19:get:(Ljava/lang/String;)Ljava/util/function/Supplier;
      59: invokestatic  #207                // Method org/springframework/util/Assert.state:(ZLjava/util/function/Supplier;)V
      62: return

  private java.util.Set<java.lang.String> getSearchNames();
    Code:
       0: aload_0
       1: getfield      #9                  // Field environment:Lorg/springframework/core/env/ConfigurableEnvironment;
       4: ldc           #210                // String spring.config.name
       6: invokeinterface #185,  2          // InterfaceMethod org/springframework/core/env/ConfigurableEnvironment.containsProperty:(Ljava/lang/String;)Z
      11: ifeq          47
      14: aload_0
      15: getfield      #9                  // Field environment:Lorg/springframework/core/env/ConfigurableEnvironment;
      18: ldc           #210                // String spring.config.name
      20: invokeinterface #191,  2          // InterfaceMethod org/springframework/core/env/ConfigurableEnvironment.getProperty:(Ljava/lang/String;)Ljava/lang/String;
      25: astore_1
      26: aload_0
      27: aload_1
      28: aconst_null
      29: invokespecial #189                // Method asResolvedSet:(Ljava/lang/String;Ljava/lang/String;)Ljava/util/Set;
      32: astore_2
      33: aload_2
      34: aload_0
      35: invokedynamic #211,  0            // InvokeDynamic #20:accept:(Lorg/springframework/boot/context/config/ConfigFileApplicationListener$Loader;)Ljava/util/function/Consumer;
      40: invokeinterface #68,  2           // InterfaceMethod java/util/Set.forEach:(Ljava/util/function/Consumer;)V
      45: aload_2
      46: areturn
      47: aload_0
      48: aload_0
      49: getfield      #2                  // Field this$0:Lorg/springframework/boot/context/config/ConfigFileApplicationListener;
      52: invokestatic  #212                // Method org/springframework/boot/context/config/ConfigFileApplicationListener.access$600:(Lorg/springframework/boot/context/config/ConfigFileApplicationListener;)Ljava/lang/String;
      55: ldc           #213                // String application
      57: invokespecial #189                // Method asResolvedSet:(Ljava/lang/String;Ljava/lang/String;)Ljava/util/Set;
      60: areturn

  private java.util.Set<java.lang.String> asResolvedSet(java.lang.String, java.lang.String);
    Code:
       0: aload_1
       1: ifnull        17
       4: aload_0
       5: getfield      #9                  // Field environment:Lorg/springframework/core/env/ConfigurableEnvironment;
       8: aload_1
       9: invokeinterface #214,  2          // InterfaceMethod org/springframework/core/env/ConfigurableEnvironment.resolvePlaceholders:(Ljava/lang/String;)Ljava/lang/String;
      14: goto          18
      17: aload_2
      18: invokestatic  #215                // Method org/springframework/util/StringUtils.commaDelimitedListToStringArray:(Ljava/lang/String;)[Ljava/lang/String;
      21: invokestatic  #216                // Method org/springframework/util/StringUtils.trimArrayElements:([Ljava/lang/String;)[Ljava/lang/String;
      24: invokestatic  #217                // Method java/util/Arrays.asList:([Ljava/lang/Object;)Ljava/util/List;
      27: astore_3
      28: aload_3
      29: invokestatic  #113                // Method java/util/Collections.reverse:(Ljava/util/List;)V
      32: new           #178                // class java/util/LinkedHashSet
      35: dup
      36: aload_3
      37: invokespecial #179                // Method java/util/LinkedHashSet."<init>":(Ljava/util/Collection;)V
      40: areturn

  private void assertValidConfigName(java.lang.String);
    Code:
       0: aload_1
       1: ldc           #121                // String *
       3: invokevirtual #122                // Method java/lang/String.contains:(Ljava/lang/CharSequence;)Z
       6: ifne          13
       9: iconst_1
      10: goto          14
      13: iconst_0
      14: aload_1
      15: invokedynamic #218,  0            // InvokeDynamic #21:get:(Ljava/lang/String;)Ljava/util/function/Supplier;
      20: invokestatic  #207                // Method org/springframework/util/Assert.state:(ZLjava/util/function/Supplier;)V
      23: return

  private void addLoadedPropertySources();
    Code:
       0: aload_0
       1: getfield      #9                  // Field environment:Lorg/springframework/core/env/ConfigurableEnvironment;
       4: invokeinterface #219,  1          // InterfaceMethod org/springframework/core/env/ConfigurableEnvironment.getPropertySources:()Lorg/springframework/core/env/MutablePropertySources;
       9: astore_1
      10: new           #105                // class java/util/ArrayList
      13: dup
      14: aload_0
      15: getfield      #220                // Field loaded:Ljava/util/Map;
      18: invokeinterface #221,  1          // InterfaceMethod java/util/Map.values:()Ljava/util/Collection;
      23: invokespecial #222                // Method java/util/ArrayList."<init>":(Ljava/util/Collection;)V
      26: astore_2
      27: aload_2
      28: invokestatic  #113                // Method java/util/Collections.reverse:(Ljava/util/List;)V
      31: aconst_null
      32: astore_3
      33: new           #80                 // class java/util/HashSet
      36: dup
      37: invokespecial #81                 // Method java/util/HashSet."<init>":()V
      40: astore        4
      42: aload_2
      43: invokeinterface #70,  1           // InterfaceMethod java/util/List.iterator:()Ljava/util/Iterator;
      48: astore        5
      50: aload         5
      52: invokeinterface #71,  1           // InterfaceMethod java/util/Iterator.hasNext:()Z
      57: ifeq          136
      60: aload         5
      62: invokeinterface #72,  1           // InterfaceMethod java/util/Iterator.next:()Ljava/lang/Object;
      67: checkcast     #223                // class org/springframework/core/env/MutablePropertySources
      70: astore        6
      72: aload         6
      74: invokevirtual #224                // Method org/springframework/core/env/MutablePropertySources.iterator:()Ljava/util/Iterator;
      77: astore        7
      79: aload         7
      81: invokeinterface #71,  1           // InterfaceMethod java/util/Iterator.hasNext:()Z
      86: ifeq          133
      89: aload         7
      91: invokeinterface #72,  1           // InterfaceMethod java/util/Iterator.next:()Ljava/lang/Object;
      96: checkcast     #225                // class org/springframework/core/env/PropertySource
      99: astore        8
     101: aload         4
     103: aload         8
     105: invokevirtual #226                // Method org/springframework/core/env/PropertySource.getName:()Ljava/lang/String;
     108: invokeinterface #83,  2           // InterfaceMethod java/util/Set.add:(Ljava/lang/Object;)Z
     113: ifeq          130
     116: aload_0
     117: aload_1
     118: aload_3
     119: aload         8
     121: invokespecial #227                // Method addLoadedPropertySource:(Lorg/springframework/core/env/MutablePropertySources;Ljava/lang/String;Lorg/springframework/core/env/PropertySource;)V
     124: aload         8
     126: invokevirtual #226                // Method org/springframework/core/env/PropertySource.getName:()Ljava/lang/String;
     129: astore_3
     130: goto          79
     133: goto          50
     136: return

  private void addLoadedPropertySource(org.springframework.core.env.MutablePropertySources, java.lang.String, org.springframework.core.env.PropertySource<?>);
    Code:
       0: aload_2
       1: ifnonnull     31
       4: aload_1
       5: ldc           #21                 // String defaultProperties
       7: invokevirtual #228                // Method org/springframework/core/env/MutablePropertySources.contains:(Ljava/lang/String;)Z
      10: ifeq          23
      13: aload_1
      14: ldc           #21                 // String defaultProperties
      16: aload_3
      17: invokevirtual #229                // Method org/springframework/core/env/MutablePropertySources.addBefore:(Ljava/lang/String;Lorg/springframework/core/env/PropertySource;)V
      20: goto          37
      23: aload_1
      24: aload_3
      25: invokevirtual #230                // Method org/springframework/core/env/MutablePropertySources.addLast:(Lorg/springframework/core/env/PropertySource;)V
      28: goto          37
      31: aload_1
      32: aload_2
      33: aload_3
      34: invokevirtual #231                // Method org/springframework/core/env/MutablePropertySources.addAfter:(Ljava/lang/String;Lorg/springframework/core/env/PropertySource;)V
      37: return

  private void applyActiveProfiles(org.springframework.core.env.PropertySource<?>);
    Code:
       0: new           #105                // class java/util/ArrayList
       3: dup
       4: invokespecial #106                // Method java/util/ArrayList."<init>":()V
       7: astore_2
       8: aload_1
       9: ifnull        70
      12: new           #232                // class org/springframework/boot/context/properties/bind/Binder
      15: dup
      16: aload_1
      17: invokestatic  #233                // Method org/springframework/boot/context/properties/source/ConfigurationPropertySources.from:(Lorg/springframework/core/env/PropertySource;)Ljava/lang/Iterable;
      20: new           #10                 // class org/springframework/boot/context/properties/bind/PropertySourcesPlaceholdersResolver
      23: dup
      24: aload_0
      25: getfield      #9                  // Field environment:Lorg/springframework/core/env/ConfigurableEnvironment;
      28: invokespecial #11                 // Method org/springframework/boot/context/properties/bind/PropertySourcesPlaceholdersResolver."<init>":(Lorg/springframework/core/env/Environment;)V
      31: invokespecial #234                // Method org/springframework/boot/context/properties/bind/Binder."<init>":(Ljava/lang/Iterable;Lorg/springframework/boot/context/properties/bind/PlaceholdersResolver;)V
      34: astore_3
      35: aload_2
      36: aload_0
      37: aload_3
      38: ldc           #30                 // String spring.profiles.include
      40: invokespecial #235                // Method getDefaultProfiles:(Lorg/springframework/boot/context/properties/bind/Binder;Ljava/lang/String;)Ljava/util/List;
      43: invokeinterface #236,  2          // InterfaceMethod java/util/List.addAll:(Ljava/util/Collection;)Z
      48: pop
      49: aload_0
      50: getfield      #48                 // Field activatedProfiles:Z
      53: ifne          70
      56: aload_2
      57: aload_0
      58: aload_3
      59: ldc           #28                 // String spring.profiles.active
      61: invokespecial #235                // Method getDefaultProfiles:(Lorg/springframework/boot/context/properties/bind/Binder;Ljava/lang/String;)Ljava/util/List;
      64: invokeinterface #236,  2          // InterfaceMethod java/util/List.addAll:(Ljava/util/Collection;)Z
      69: pop
      70: aload_0
      71: getfield      #89                 // Field processedProfiles:Ljava/util/List;
      74: invokeinterface #160,  1          // InterfaceMethod java/util/List.stream:()Ljava/util/stream/Stream;
      79: aload_0
      80: invokedynamic #237,  0            // InvokeDynamic #22:test:(Lorg/springframework/boot/context/config/ConfigFileApplicationListener$Loader;)Ljava/util/function/Predicate;
      85: invokeinterface #43,  2           // InterfaceMethod java/util/stream/Stream.filter:(Ljava/util/function/Predicate;)Ljava/util/stream/Stream;
      90: invokedynamic #238,  0            // InvokeDynamic #23:apply:()Ljava/util/function/Function;
      95: invokeinterface #41,  2           // InterfaceMethod java/util/stream/Stream.map:(Ljava/util/function/Function;)Ljava/util/stream/Stream;
     100: aload_2
     101: dup
     102: invokevirtual #17                 // Method java/lang/Object.getClass:()Ljava/lang/Class;
     105: pop
     106: invokedynamic #239,  0            // InvokeDynamic #24:accept:(Ljava/util/List;)Ljava/util/function/Consumer;
     111: invokeinterface #240,  2          // InterfaceMethod java/util/stream/Stream.forEach:(Ljava/util/function/Consumer;)V
     116: aload_0
     117: getfield      #9                  // Field environment:Lorg/springframework/core/env/ConfigurableEnvironment;
     120: aload_2
     121: iconst_0
     122: anewarray     #193                // class java/lang/String
     125: invokeinterface #241,  2          // InterfaceMethod java/util/List.toArray:([Ljava/lang/Object;)[Ljava/lang/Object;
     130: checkcast     #242                // class "[Ljava/lang/String;"
     133: invokeinterface #243,  2          // InterfaceMethod org/springframework/core/env/ConfigurableEnvironment.setActiveProfiles:([Ljava/lang/String;)V
     138: return

  private boolean isDefaultProfile(org.springframework.boot.context.config.ConfigFileApplicationListener$Profile);
    Code:
       0: aload_1
       1: ifnull        15
       4: aload_1
       5: invokevirtual #244                // Method org/springframework/boot/context/config/ConfigFileApplicationListener$Profile.isDefaultProfile:()Z
       8: ifne          15
      11: iconst_1
      12: goto          16
      15: iconst_0
      16: ireturn

  private java.util.List<java.lang.String> getDefaultProfiles(org.springframework.boot.context.properties.bind.Binder, java.lang.String);
    Code:
       0: aload_1
       1: aload_2
       2: invokestatic  #245                // Method org/springframework/boot/context/config/ConfigFileApplicationListener.access$700:()Lorg/springframework/boot/context/properties/bind/Bindable;
       5: invokevirtual #171                // Method org/springframework/boot/context/properties/bind/Binder.bind:(Ljava/lang/String;Lorg/springframework/boot/context/properties/bind/Bindable;)Lorg/springframework/boot/context/properties/bind/BindResult;
       8: invokestatic  #159                // Method java/util/Collections.emptyList:()Ljava/util/List;
      11: invokevirtual #175                // Method org/springframework/boot/context/properties/bind/BindResult.orElse:(Ljava/lang/Object;)Ljava/lang/Object;
      14: checkcast     #46                 // class java/util/List
      17: areturn

  private static java.lang.String lambda$assertValidConfigName$17(java.lang.String);
    Code:
       0: new           #50                 // class java/lang/StringBuilder
       3: dup
       4: invokespecial #51                 // Method java/lang/StringBuilder."<init>":()V
       7: ldc           #246                // String Config name \'
       9: invokevirtual #53                 // Method java/lang/StringBuilder.append:(Ljava/lang/String;)Ljava/lang/StringBuilder;
      12: aload_0
      13: invokevirtual #53                 // Method java/lang/StringBuilder.append:(Ljava/lang/String;)Ljava/lang/StringBuilder;
      16: ldc           #247                // String \' cannot contain wildcards
      18: invokevirtual #53                 // Method java/lang/StringBuilder.append:(Ljava/lang/String;)Ljava/lang/StringBuilder;
      21: invokevirtual #56                 // Method java/lang/StringBuilder.toString:()Ljava/lang/String;
      24: areturn

  private static java.lang.String lambda$validateWildcardLocation$16(java.lang.String);
    Code:
       0: new           #50                 // class java/lang/StringBuilder
       3: dup
       4: invokespecial #51                 // Method java/lang/StringBuilder."<init>":()V
       7: ldc           #248                // String Search location \'
       9: invokevirtual #53                 // Method java/lang/StringBuilder.append:(Ljava/lang/String;)Ljava/lang/StringBuilder;
      12: aload_0
      13: invokevirtual #53                 // Method java/lang/StringBuilder.append:(Ljava/lang/String;)Ljava/lang/StringBuilder;
      16: ldc           #249                // String \' must end with \'*/\'
      18: invokevirtual #53                 // Method java/lang/StringBuilder.append:(Ljava/lang/String;)Ljava/lang/StringBuilder;
      21: invokevirtual #56                 // Method java/lang/StringBuilder.toString:()Ljava/lang/String;
      24: areturn

  private static java.lang.String lambda$validateWildcardLocation$15(java.lang.String);
    Code:
       0: new           #50                 // class java/lang/StringBuilder
       3: dup
       4: invokespecial #51                 // Method java/lang/StringBuilder."<init>":()V
       7: ldc           #248                // String Search location \'
       9: invokevirtual #53                 // Method java/lang/StringBuilder.append:(Ljava/lang/String;)Ljava/lang/StringBuilder;
      12: aload_0
      13: invokevirtual #53                 // Method java/lang/StringBuilder.append:(Ljava/lang/String;)Ljava/lang/StringBuilder;
      16: ldc           #250                // String \' cannot contain multiple wildcards
      18: invokevirtual #53                 // Method java/lang/StringBuilder.append:(Ljava/lang/String;)Ljava/lang/StringBuilder;
      21: invokevirtual #56                 // Method java/lang/StringBuilder.toString:()Ljava/lang/String;
      24: areturn

  private org.springframework.boot.context.config.ConfigFileApplicationListener$Document lambda$asDocuments$14(org.springframework.core.env.PropertySource);
    Code:
       0: new           #232                // class org/springframework/boot/context/properties/bind/Binder
       3: dup
       4: aload_1
       5: invokestatic  #233                // Method org/springframework/boot/context/properties/source/ConfigurationPropertySources.from:(Lorg/springframework/core/env/PropertySource;)Ljava/lang/Iterable;
       8: aload_0
       9: getfield      #12                 // Field placeholdersResolver:Lorg/springframework/boot/context/properties/bind/PropertySourcesPlaceholdersResolver;
      12: invokespecial #234                // Method org/springframework/boot/context/properties/bind/Binder."<init>":(Ljava/lang/Iterable;Lorg/springframework/boot/context/properties/bind/PlaceholdersResolver;)V
      15: astore_2
      16: aload_2
      17: ldc           #251                // String spring.profiles
      19: invokestatic  #170                // Method org/springframework/boot/context/config/ConfigFileApplicationListener.access$400:()Lorg/springframework/boot/context/properties/bind/Bindable;
      22: invokevirtual #171                // Method org/springframework/boot/context/properties/bind/Binder.bind:(Ljava/lang/String;Lorg/springframework/boot/context/properties/bind/Bindable;)Lorg/springframework/boot/context/properties/bind/BindResult;
      25: aconst_null
      26: invokevirtual #175                // Method org/springframework/boot/context/properties/bind/BindResult.orElse:(Ljava/lang/Object;)Ljava/lang/Object;
      29: checkcast     #242                // class "[Ljava/lang/String;"
      32: astore_3
      33: aload_0
      34: aload_2
      35: ldc           #28                 // String spring.profiles.active
      37: invokespecial #29                 // Method getProfiles:(Lorg/springframework/boot/context/properties/bind/Binder;Ljava/lang/String;)Ljava/util/Set;
      40: astore        4
      42: aload_0
      43: aload_2
      44: ldc           #30                 // String spring.profiles.include
      46: invokespecial #29                 // Method getProfiles:(Lorg/springframework/boot/context/properties/bind/Binder;Ljava/lang/String;)Ljava/util/Set;
      49: astore        5
      51: new           #107                // class org/springframework/boot/context/config/ConfigFileApplicationListener$Document
      54: dup
      55: aload_1
      56: aload_3
      57: aload         4
      59: aload         5
      61: invokespecial #252                // Method org/springframework/boot/context/config/ConfigFileApplicationListener$Document."<init>":(Lorg/springframework/core/env/PropertySource;[Ljava/lang/String;Ljava/util/Set;Ljava/util/Set;)V
      64: areturn

  private static org.springframework.core.io.Resource[] lambda$getResourcesFromPatternLocation$13(int);
    Code:
       0: iload_0
       1: anewarray     #127                // class org/springframework/core/io/Resource
       4: areturn

  private static java.io.File[] lambda$getResourcesFromPatternLocation$12(java.lang.String, java.io.File);
    Code:
       0: aload_1
       1: aload_0
       2: invokedynamic #253,  0            // InvokeDynamic #25:accept:(Ljava/lang/String;)Ljava/io/FilenameFilter;
       7: invokevirtual #254                // Method java/io/File.listFiles:(Ljava/io/FilenameFilter;)[Ljava/io/File;
      10: areturn

  private static boolean lambda$null$11(java.lang.String, java.io.File, java.lang.String);
    Code:
       0: aload_2
       1: aload_0
       2: invokevirtual #180                // Method java/lang/String.equals:(Ljava/lang/Object;)Z
       5: ireturn

  private static void lambda$load$10(org.springframework.boot.context.config.ConfigFileApplicationListener$DocumentConsumer, org.springframework.boot.context.config.ConfigFileApplicationListener$Profile, org.springframework.boot.context.config.ConfigFileApplicationListener$Document);
    Code:
       0: aload_0
       1: aload_1
       2: aload_2
       3: invokeinterface #255,  3          // InterfaceMethod org/springframework/boot/context/config/ConfigFileApplicationListener$DocumentConsumer.accept:(Lorg/springframework/boot/context/config/ConfigFileApplicationListener$Profile;Lorg/springframework/boot/context/config/ConfigFileApplicationListener$Document;)V
       8: return

  private static boolean lambda$canLoadFileExtension$9(java.lang.String, java.lang.String);
    Code:
       0: aload_0
       1: aload_1
       2: invokestatic  #256                // Method org/springframework/util/StringUtils.endsWithIgnoreCase:(Ljava/lang/String;Ljava/lang/String;)Z
       5: ireturn

  private void lambda$load$8(org.springframework.boot.context.config.ConfigFileApplicationListener$Profile, org.springframework.boot.context.config.ConfigFileApplicationListener$DocumentFilterFactory, org.springframework.boot.context.config.ConfigFileApplicationListener$DocumentConsumer, java.lang.String);
    Code:
       0: aload         4
       2: ldc           #136                // String /
       4: invokevirtual #208                // Method java/lang/String.endsWith:(Ljava/lang/String;)Z
       7: istore        5
       9: iload         5
      11: ifeq          21
      14: aload_0
      15: invokespecial #257                // Method getSearchNames:()Ljava/util/Set;
      18: goto          24
      21: invokestatic  #258                // Method org/springframework/boot/context/config/ConfigFileApplicationListener.access$800:()Ljava/util/Set;
      24: astore        6
      26: aload         6
      28: aload_0
      29: aload         4
      31: aload_1
      32: aload_2
      33: aload_3
      34: invokedynamic #259,  0            // InvokeDynamic #26:accept:(Lorg/springframework/boot/context/config/ConfigFileApplicationListener$Loader;Ljava/lang/String;Lorg/springframework/boot/context/config/ConfigFileApplicationListener$Profile;Lorg/springframework/boot/context/config/ConfigFileApplicationListener$DocumentFilterFactory;Lorg/springframework/boot/context/config/ConfigFileApplicationListener$DocumentConsumer;)Ljava/util/function/Consumer;
      39: invokeinterface #68,  2           // InterfaceMethod java/util/Set.forEach:(Ljava/util/function/Consumer;)V
      44: return

  private void lambda$null$7(java.lang.String, org.springframework.boot.context.config.ConfigFileApplicationListener$Profile, org.springframework.boot.context.config.ConfigFileApplicationListener$DocumentFilterFactory, org.springframework.boot.context.config.ConfigFileApplicationListener$DocumentConsumer, java.lang.String);
    Code:
       0: aload_0
       1: aload_1
       2: aload         5
       4: aload_2
       5: aload_3
       6: aload         4
       8: invokespecial #260                // Method load:(Ljava/lang/String;Ljava/lang/String;Lorg/springframework/boot/context/config/ConfigFileApplicationListener$Profile;Lorg/springframework/boot/context/config/ConfigFileApplicationListener$DocumentFilterFactory;Lorg/springframework/boot/context/config/ConfigFileApplicationListener$DocumentConsumer;)V
      11: return

  private void lambda$addToLoaded$6(boolean, java.util.function.BiConsumer, org.springframework.boot.context.config.ConfigFileApplicationListener$Profile, org.springframework.boot.context.config.ConfigFileApplicationListener$Document);
    Code:
       0: iload_1
       1: ifeq          62
       4: aload_0
       5: getfield      #220                // Field loaded:Ljava/util/Map;
       8: invokeinterface #221,  1          // InterfaceMethod java/util/Map.values:()Ljava/util/Collection;
      13: invokeinterface #261,  1          // InterfaceMethod java/util/Collection.iterator:()Ljava/util/Iterator;
      18: astore        5
      20: aload         5
      22: invokeinterface #71,  1           // InterfaceMethod java/util/Iterator.hasNext:()Z
      27: ifeq          62
      30: aload         5
      32: invokeinterface #72,  1           // InterfaceMethod java/util/Iterator.next:()Ljava/lang/Object;
      37: checkcast     #223                // class org/springframework/core/env/MutablePropertySources
      40: astore        6
      42: aload         6
      44: aload         4
      46: invokevirtual #262                // Method org/springframework/boot/context/config/ConfigFileApplicationListener$Document.getPropertySource:()Lorg/springframework/core/env/PropertySource;
      49: invokevirtual #226                // Method org/springframework/core/env/PropertySource.getName:()Ljava/lang/String;
      52: invokevirtual #228                // Method org/springframework/core/env/MutablePropertySources.contains:(Ljava/lang/String;)Z
      55: ifeq          59
      58: return
      59: goto          20
      62: aload_0
      63: getfield      #220                // Field loaded:Ljava/util/Map;
      66: aload_3
      67: invokedynamic #263,  0            // InvokeDynamic #27:apply:()Ljava/util/function/Function;
      72: invokeinterface #264,  3          // InterfaceMethod java/util/Map.computeIfAbsent:(Ljava/lang/Object;Ljava/util/function/Function;)Ljava/lang/Object;
      77: checkcast     #223                // class org/springframework/core/env/MutablePropertySources
      80: astore        5
      82: aload_2
      83: aload         5
      85: aload         4
      87: invokevirtual #262                // Method org/springframework/boot/context/config/ConfigFileApplicationListener$Document.getPropertySource:()Lorg/springframework/core/env/PropertySource;
      90: invokeinterface #265,  3          // InterfaceMethod java/util/function/BiConsumer.accept:(Ljava/lang/Object;Ljava/lang/Object;)V
      95: return

  private static org.springframework.core.env.MutablePropertySources lambda$null$5(org.springframework.boot.context.config.ConfigFileApplicationListener$Profile);
    Code:
       0: new           #223                // class org/springframework/core/env/MutablePropertySources
       3: dup
       4: invokespecial #266                // Method org/springframework/core/env/MutablePropertySources."<init>":()V
       7: areturn

  private boolean lambda$getNegativeProfileFilter$4(org.springframework.boot.context.config.ConfigFileApplicationListener$Profile, org.springframework.boot.context.config.ConfigFileApplicationListener$Document);
    Code:
       0: aload_1
       1: ifnonnull     37
       4: aload_2
       5: invokevirtual #267                // Method org/springframework/boot/context/config/ConfigFileApplicationListener$Document.getProfiles:()[Ljava/lang/String;
       8: invokestatic  #268                // Method org/springframework/util/ObjectUtils.isEmpty:([Ljava/lang/Object;)Z
      11: ifne          37
      14: aload_0
      15: getfield      #9                  // Field environment:Lorg/springframework/core/env/ConfigurableEnvironment;
      18: aload_2
      19: invokevirtual #267                // Method org/springframework/boot/context/config/ConfigFileApplicationListener$Document.getProfiles:()[Ljava/lang/String;
      22: invokestatic  #269                // InterfaceMethod org/springframework/core/env/Profiles.of:([Ljava/lang/String;)Lorg/springframework/core/env/Profiles;
      25: invokeinterface #270,  2          // InterfaceMethod org/springframework/core/env/ConfigurableEnvironment.acceptsProfiles:(Lorg/springframework/core/env/Profiles;)Z
      30: ifeq          37
      33: iconst_1
      34: goto          38
      37: iconst_0
      38: ireturn

  private boolean lambda$getPositiveProfileFilter$3(org.springframework.boot.context.config.ConfigFileApplicationListener$Profile, org.springframework.boot.context.config.ConfigFileApplicationListener$Document);
    Code:
       0: aload_1
       1: ifnonnull     12
       4: aload_2
       5: invokevirtual #267                // Method org/springframework/boot/context/config/ConfigFileApplicationListener$Document.getProfiles:()[Ljava/lang/String;
       8: invokestatic  #268                // Method org/springframework/util/ObjectUtils.isEmpty:([Ljava/lang/Object;)Z
      11: ireturn
      12: aload_2
      13: invokevirtual #267                // Method org/springframework/boot/context/config/ConfigFileApplicationListener$Document.getProfiles:()[Ljava/lang/String;
      16: aload_1
      17: invokevirtual #271                // Method org/springframework/boot/context/config/ConfigFileApplicationListener$Profile.getName:()Ljava/lang/String;
      20: invokestatic  #272                // Method org/springframework/util/ObjectUtils.containsElement:([Ljava/lang/Object;Ljava/lang/Object;)Z
      23: ifeq          49
      26: aload_0
      27: getfield      #9                  // Field environment:Lorg/springframework/core/env/ConfigurableEnvironment;
      30: aload_2
      31: invokevirtual #267                // Method org/springframework/boot/context/config/ConfigFileApplicationListener$Document.getProfiles:()[Ljava/lang/String;
      34: invokestatic  #269                // InterfaceMethod org/springframework/core/env/Profiles.of:([Ljava/lang/String;)Lorg/springframework/core/env/Profiles;
      37: invokeinterface #270,  2          // InterfaceMethod org/springframework/core/env/ConfigurableEnvironment.acceptsProfiles:(Lorg/springframework/core/env/Profiles;)Z
      42: ifeq          49
      45: iconst_1
      46: goto          50
      49: iconst_0
      50: ireturn

  private static boolean lambda$removeUnprocessedDefaultProfiles$2(org.springframework.boot.context.config.ConfigFileApplicationListener$Profile);
    Code:
       0: aload_0
       1: ifnull        15
       4: aload_0
       5: invokevirtual #244                // Method org/springframework/boot/context/config/ConfigFileApplicationListener$Profile.isDefaultProfile:()Z
       8: ifeq          15
      11: iconst_1
      12: goto          16
      15: iconst_0
      16: ireturn

  private static boolean lambda$getOtherActiveProfiles$1(java.util.Set, java.util.Set, org.springframework.boot.context.config.ConfigFileApplicationListener$Profile);
    Code:
       0: aload_0
       1: aload_2
       2: invokeinterface #273,  2          // InterfaceMethod java/util/Set.contains:(Ljava/lang/Object;)Z
       7: ifne          24
      10: aload_1
      11: aload_2
      12: invokeinterface #273,  2          // InterfaceMethod java/util/Set.contains:(Ljava/lang/Object;)Z
      17: ifne          24
      20: iconst_1
      21: goto          25
      24: iconst_0
      25: ireturn

  private void lambda$load$0(org.springframework.core.env.PropertySource);
    Code:
       0: aload_0
       1: new           #149                // class java/util/LinkedList
       4: dup
       5: invokespecial #274                // Method java/util/LinkedList."<init>":()V
       8: putfield      #25                 // Field profiles:Ljava/util/Deque;
      11: aload_0
      12: new           #149                // class java/util/LinkedList
      15: dup
      16: invokespecial #274                // Method java/util/LinkedList."<init>":()V
      19: putfield      #89                 // Field processedProfiles:Ljava/util/List;
      22: aload_0
      23: iconst_0
      24: putfield      #48                 // Field activatedProfiles:Z
      27: aload_0
      28: new           #275                // class java/util/LinkedHashMap
      31: dup
      32: invokespecial #276                // Method java/util/LinkedHashMap."<init>":()V
      35: putfield      #220                // Field loaded:Ljava/util/Map;
      38: aload_0
      39: invokespecial #277                // Method initializeProfiles:()V
      42: aload_0
      43: getfield      #25                 // Field profiles:Ljava/util/Deque;
      46: invokeinterface #278,  1          // InterfaceMethod java/util/Deque.isEmpty:()Z
      51: ifne          118
      54: aload_0
      55: getfield      #25                 // Field profiles:Ljava/util/Deque;
      58: invokeinterface #279,  1          // InterfaceMethod java/util/Deque.poll:()Ljava/lang/Object;
      63: checkcast     #36                 // class org/springframework/boot/context/config/ConfigFileApplicationListener$Profile
      66: astore_2
      67: aload_0
      68: aload_2
      69: invokespecial #280                // Method isDefaultProfile:(Lorg/springframework/boot/context/config/ConfigFileApplicationListener$Profile;)Z
      72: ifeq          83
      75: aload_0
      76: aload_2
      77: invokevirtual #271                // Method org/springframework/boot/context/config/ConfigFileApplicationListener$Profile.getName:()Ljava/lang/String;
      80: invokespecial #281                // Method addProfileToEnvironment:(Ljava/lang/String;)V
      83: aload_0
      84: aload_2
      85: aload_0
      86: invokedynamic #282,  0            // InvokeDynamic #28:getDocumentFilter:(Lorg/springframework/boot/context/config/ConfigFileApplicationListener$Loader;)Lorg/springframework/boot/context/config/ConfigFileApplicationListener$DocumentFilterFactory;
      91: aload_0
      92: invokedynamic #283,  0            // InvokeDynamic #29:accept:()Ljava/util/function/BiConsumer;
      97: iconst_0
      98: invokespecial #284                // Method addToLoaded:(Ljava/util/function/BiConsumer;Z)Lorg/springframework/boot/context/config/ConfigFileApplicationListener$DocumentConsumer;
     101: invokespecial #285                // Method load:(Lorg/springframework/boot/context/config/ConfigFileApplicationListener$Profile;Lorg/springframework/boot/context/config/ConfigFileApplicationListener$DocumentFilterFactory;Lorg/springframework/boot/context/config/ConfigFileApplicationListener$DocumentConsumer;)V
     104: aload_0
     105: getfield      #89                 // Field processedProfiles:Ljava/util/List;
     108: aload_2
     109: invokeinterface #112,  2          // InterfaceMethod java/util/List.add:(Ljava/lang/Object;)Z
     114: pop
     115: goto          42
     118: aload_0
     119: aconst_null
     120: aload_0
     121: invokedynamic #286,  0            // InvokeDynamic #30:getDocumentFilter:(Lorg/springframework/boot/context/config/ConfigFileApplicationListener$Loader;)Lorg/springframework/boot/context/config/ConfigFileApplicationListener$DocumentFilterFactory;
     126: aload_0
     127: invokedynamic #287,  0            // InvokeDynamic #31:accept:()Ljava/util/function/BiConsumer;
     132: iconst_1
     133: invokespecial #284                // Method addToLoaded:(Ljava/util/function/BiConsumer;Z)Lorg/springframework/boot/context/config/ConfigFileApplicationListener$DocumentConsumer;
     136: invokespecial #285                // Method load:(Lorg/springframework/boot/context/config/ConfigFileApplicationListener$Profile;Lorg/springframework/boot/context/config/ConfigFileApplicationListener$DocumentFilterFactory;Lorg/springframework/boot/context/config/ConfigFileApplicationListener$DocumentConsumer;)V
     139: aload_0
     140: invokespecial #288                // Method addLoadedPropertySources:()V
     143: aload_0
     144: aload_1
     145: invokespecial #289                // Method applyActiveProfiles:(Lorg/springframework/core/env/PropertySource;)V
     148: return
}
