Compiled from "JsrWebSocketLogger.java"
public interface io.undertow.websockets.jsr.JsrWebSocketLogger extends org.jboss.logging.BasicLogger {
  public static final io.undertow.websockets.jsr.JsrWebSocketLogger ROOT_LOGGER;

  public static final io.undertow.websockets.jsr.JsrWebSocketLogger REQUEST_LOGGER;

  public abstract void endpointCreationFailed(java.lang.Exception);

  public abstract void couldNotInitializeConfiguration(java.lang.Class<?>, java.lang.Throwable);

  public abstract void addingAnnotatedServerEndpoint(java.lang.Class<?>, java.lang.String);

  public abstract void addingAnnotatedClientEndpoint(java.lang.Class<?>);

  public abstract void addingProgramaticEndpoint(java.lang.Class<?>, java.lang.String);

  public abstract void exceptionInWebSocketMethod(java.lang.Throwable);

  public abstract void pathTemplateNotFound(java.lang.Class<?>, jakarta.websocket.server.PathParam, java.lang.reflect.Method, java.util.Set<java.lang.String>);

  public abstract void couldNotCloseOnUndeploy(java.lang.Exception);

  public abstract void xnioWorkerWasNull();

  public abstract void bufferPoolWasNull();

  public abstract java.lang.IllegalArgumentException xnioWorkerWasNullAndNoDefault();

  public abstract java.lang.IllegalArgumentException bufferPoolWasNullAndNoDefault();

  static {};
    Code:
       0: ldc           #1                  // class io/undertow/websockets/jsr/JsrWebSocketLogger
       2: ldc           #1                  // class io/undertow/websockets/jsr/JsrWebSocketLogger
       4: invokevirtual #2                  // Method java/lang/Class.getPackage:()Ljava/lang/Package;
       7: invokevirtual #3                  // Method java/lang/Package.getName:()Ljava/lang/String;
      10: invokestatic  #4                  // Method org/jboss/logging/Logger.getMessageLogger:(Ljava/lang/Class;Ljava/lang/String;)Ljava/lang/Object;
      13: checkcast     #1                  // class io/undertow/websockets/jsr/JsrWebSocketLogger
      16: putstatic     #5                  // Field ROOT_LOGGER:Lio/undertow/websockets/jsr/JsrWebSocketLogger;
      19: ldc           #1                  // class io/undertow/websockets/jsr/JsrWebSocketLogger
      21: ldc           #1                  // class io/undertow/websockets/jsr/JsrWebSocketLogger
      23: invokevirtual #2                  // Method java/lang/Class.getPackage:()Ljava/lang/Package;
      26: invokevirtual #3                  // Method java/lang/Package.getName:()Ljava/lang/String;
      29: invokedynamic #6,  0              // InvokeDynamic #0:makeConcatWithConstants:(Ljava/lang/String;)Ljava/lang/String;
      34: invokestatic  #4                  // Method org/jboss/logging/Logger.getMessageLogger:(Ljava/lang/Class;Ljava/lang/String;)Ljava/lang/Object;
      37: checkcast     #1                  // class io/undertow/websockets/jsr/JsrWebSocketLogger
      40: putstatic     #7                  // Field REQUEST_LOGGER:Lio/undertow/websockets/jsr/JsrWebSocketLogger;
      43: return
}
