Compiled from "WebSocketDeploymentInfo.java"
public class io.undertow.websockets.jsr.WebSocketDeploymentInfo implements java.lang.Cloneable {
  public static final java.lang.String ATTRIBUTE_NAME;

  private java.util.function.Supplier<org.xnio.XnioWorker> worker;

  private io.undertow.connector.ByteBufferPool buffers;

  private boolean dispatchToWorkerThread;

  private final java.util.List<java.lang.Class<?>> annotatedEndpoints;

  private final java.util.List<jakarta.websocket.server.ServerEndpointConfig> programaticEndpoints;

  private final java.util.List<io.undertow.websockets.jsr.WebSocketDeploymentInfo$ContainerReadyListener> containerReadyListeners;

  private final java.util.List<io.undertow.websockets.extensions.ExtensionHandshake> extensions;

  private java.lang.String clientBindAddress;

  private io.undertow.websockets.jsr.WebSocketReconnectHandler reconnectHandler;

  public io.undertow.websockets.jsr.WebSocketDeploymentInfo();
    Code:
       0: aload_0
       1: invokespecial #1                  // Method java/lang/Object."<init>":()V
       4: aload_0
       5: new           #2                  // class io/undertow/websockets/jsr/WebSocketDeploymentInfo$1
       8: dup
       9: aload_0
      10: invokespecial #3                  // Method io/undertow/websockets/jsr/WebSocketDeploymentInfo$1."<init>":(Lio/undertow/websockets/jsr/WebSocketDeploymentInfo;)V
      13: putfield      #4                  // Field worker:Ljava/util/function/Supplier;
      16: aload_0
      17: iconst_0
      18: putfield      #5                  // Field dispatchToWorkerThread:Z
      21: aload_0
      22: new           #6                  // class java/util/ArrayList
      25: dup
      26: invokespecial #7                  // Method java/util/ArrayList."<init>":()V
      29: putfield      #8                  // Field annotatedEndpoints:Ljava/util/List;
      32: aload_0
      33: new           #6                  // class java/util/ArrayList
      36: dup
      37: invokespecial #7                  // Method java/util/ArrayList."<init>":()V
      40: putfield      #9                  // Field programaticEndpoints:Ljava/util/List;
      43: aload_0
      44: new           #6                  // class java/util/ArrayList
      47: dup
      48: invokespecial #7                  // Method java/util/ArrayList."<init>":()V
      51: putfield      #10                 // Field containerReadyListeners:Ljava/util/List;
      54: aload_0
      55: new           #6                  // class java/util/ArrayList
      58: dup
      59: invokespecial #7                  // Method java/util/ArrayList."<init>":()V
      62: putfield      #11                 // Field extensions:Ljava/util/List;
      65: aload_0
      66: aconst_null
      67: putfield      #12                 // Field clientBindAddress:Ljava/lang/String;
      70: return

  public java.util.function.Supplier<org.xnio.XnioWorker> getWorker();
    Code:
       0: aload_0
       1: getfield      #4                  // Field worker:Ljava/util/function/Supplier;
       4: areturn

  public io.undertow.websockets.jsr.WebSocketDeploymentInfo setWorker(java.util.function.Supplier<org.xnio.XnioWorker>);
    Code:
       0: aload_0
       1: aload_1
       2: putfield      #4                  // Field worker:Ljava/util/function/Supplier;
       5: aload_0
       6: areturn

  public io.undertow.websockets.jsr.WebSocketDeploymentInfo setWorker(org.xnio.XnioWorker);
    Code:
       0: aload_0
       1: new           #13                 // class io/undertow/websockets/jsr/WebSocketDeploymentInfo$2
       4: dup
       5: aload_0
       6: aload_1
       7: invokespecial #14                 // Method io/undertow/websockets/jsr/WebSocketDeploymentInfo$2."<init>":(Lio/undertow/websockets/jsr/WebSocketDeploymentInfo;Lorg/xnio/XnioWorker;)V
      10: putfield      #4                  // Field worker:Ljava/util/function/Supplier;
      13: aload_0
      14: areturn

  public io.undertow.connector.ByteBufferPool getBuffers();
    Code:
       0: aload_0
       1: getfield      #15                 // Field buffers:Lio/undertow/connector/ByteBufferPool;
       4: areturn

  public io.undertow.websockets.jsr.WebSocketDeploymentInfo setBuffers(org.xnio.Pool<java.nio.ByteBuffer>);
    Code:
       0: aload_0
       1: new           #16                 // class io/undertow/server/XnioByteBufferPool
       4: dup
       5: aload_1
       6: invokespecial #17                 // Method io/undertow/server/XnioByteBufferPool."<init>":(Lorg/xnio/Pool;)V
       9: invokevirtual #18                 // Method setBuffers:(Lio/undertow/connector/ByteBufferPool;)Lio/undertow/websockets/jsr/WebSocketDeploymentInfo;
      12: areturn

  public io.undertow.websockets.jsr.WebSocketDeploymentInfo setBuffers(io.undertow.connector.ByteBufferPool);
    Code:
       0: aload_0
       1: aload_1
       2: putfield      #15                 // Field buffers:Lio/undertow/connector/ByteBufferPool;
       5: aload_0
       6: areturn

  public io.undertow.websockets.jsr.WebSocketDeploymentInfo addEndpoint(java.lang.Class<?>);
    Code:
       0: aload_0
       1: getfield      #8                  // Field annotatedEndpoints:Ljava/util/List;
       4: aload_1
       5: invokeinterface #19,  2           // InterfaceMethod java/util/List.add:(Ljava/lang/Object;)Z
      10: pop
      11: aload_0
      12: areturn

  public io.undertow.websockets.jsr.WebSocketDeploymentInfo addAnnotatedEndpoints(java.util.Collection<java.lang.Class<?>>);
    Code:
       0: aload_0
       1: getfield      #8                  // Field annotatedEndpoints:Ljava/util/List;
       4: aload_1
       5: invokeinterface #20,  2           // InterfaceMethod java/util/List.addAll:(Ljava/util/Collection;)Z
      10: pop
      11: aload_0
      12: areturn

  public io.undertow.websockets.jsr.WebSocketDeploymentInfo addEndpoint(jakarta.websocket.server.ServerEndpointConfig);
    Code:
       0: aload_0
       1: getfield      #9                  // Field programaticEndpoints:Ljava/util/List;
       4: aload_1
       5: invokeinterface #19,  2           // InterfaceMethod java/util/List.add:(Ljava/lang/Object;)Z
      10: pop
      11: aload_0
      12: areturn

  public io.undertow.websockets.jsr.WebSocketDeploymentInfo addProgramaticEndpoints(java.util.Collection<jakarta.websocket.server.ServerEndpointConfig>);
    Code:
       0: aload_0
       1: getfield      #9                  // Field programaticEndpoints:Ljava/util/List;
       4: aload_1
       5: invokeinterface #20,  2           // InterfaceMethod java/util/List.addAll:(Ljava/util/Collection;)Z
      10: pop
      11: aload_0
      12: areturn

  public java.util.List<java.lang.Class<?>> getAnnotatedEndpoints();
    Code:
       0: aload_0
       1: getfield      #8                  // Field annotatedEndpoints:Ljava/util/List;
       4: areturn

  public java.util.List<jakarta.websocket.server.ServerEndpointConfig> getProgramaticEndpoints();
    Code:
       0: aload_0
       1: getfield      #9                  // Field programaticEndpoints:Ljava/util/List;
       4: areturn

  void containerReady(io.undertow.websockets.jsr.ServerWebSocketContainer);
    Code:
       0: aload_0
       1: getfield      #10                 // Field containerReadyListeners:Ljava/util/List;
       4: invokeinterface #21,  1           // InterfaceMethod java/util/List.iterator:()Ljava/util/Iterator;
       9: astore_2
      10: aload_2
      11: invokeinterface #22,  1           // InterfaceMethod java/util/Iterator.hasNext:()Z
      16: ifeq          39
      19: aload_2
      20: invokeinterface #23,  1           // InterfaceMethod java/util/Iterator.next:()Ljava/lang/Object;
      25: checkcast     #24                 // class io/undertow/websockets/jsr/WebSocketDeploymentInfo$ContainerReadyListener
      28: astore_3
      29: aload_3
      30: aload_1
      31: invokeinterface #25,  2           // InterfaceMethod io/undertow/websockets/jsr/WebSocketDeploymentInfo$ContainerReadyListener.ready:(Lio/undertow/websockets/jsr/ServerWebSocketContainer;)V
      36: goto          10
      39: return

  public io.undertow.websockets.jsr.WebSocketDeploymentInfo addListener(io.undertow.websockets.jsr.WebSocketDeploymentInfo$ContainerReadyListener);
    Code:
       0: aload_0
       1: getfield      #10                 // Field containerReadyListeners:Ljava/util/List;
       4: aload_1
       5: invokeinterface #19,  2           // InterfaceMethod java/util/List.add:(Ljava/lang/Object;)Z
      10: pop
      11: aload_0
      12: areturn

  public io.undertow.websockets.jsr.WebSocketDeploymentInfo addListeners(java.util.Collection<io.undertow.websockets.jsr.WebSocketDeploymentInfo$ContainerReadyListener>);
    Code:
       0: aload_0
       1: getfield      #10                 // Field containerReadyListeners:Ljava/util/List;
       4: aload_1
       5: invokeinterface #20,  2           // InterfaceMethod java/util/List.addAll:(Ljava/util/Collection;)Z
      10: pop
      11: aload_0
      12: areturn

  public java.util.List<io.undertow.websockets.jsr.WebSocketDeploymentInfo$ContainerReadyListener> getListeners();
    Code:
       0: aload_0
       1: getfield      #10                 // Field containerReadyListeners:Ljava/util/List;
       4: areturn

  public boolean isDispatchToWorkerThread();
    Code:
       0: aload_0
       1: getfield      #5                  // Field dispatchToWorkerThread:Z
       4: ireturn

  public io.undertow.websockets.jsr.WebSocketDeploymentInfo setDispatchToWorkerThread(boolean);
    Code:
       0: aload_0
       1: iload_1
       2: putfield      #5                  // Field dispatchToWorkerThread:Z
       5: aload_0
       6: areturn

  public io.undertow.websockets.jsr.WebSocketDeploymentInfo addExtension(io.undertow.websockets.extensions.ExtensionHandshake);
    Code:
       0: aconst_null
       1: aload_1
       2: if_acmpeq     16
       5: aload_0
       6: getfield      #11                 // Field extensions:Ljava/util/List;
       9: aload_1
      10: invokeinterface #19,  2           // InterfaceMethod java/util/List.add:(Ljava/lang/Object;)Z
      15: pop
      16: aload_0
      17: areturn

  public io.undertow.websockets.jsr.WebSocketDeploymentInfo addExtensions(java.util.Collection<io.undertow.websockets.extensions.ExtensionHandshake>);
    Code:
       0: aload_0
       1: getfield      #11                 // Field extensions:Ljava/util/List;
       4: aload_1
       5: invokeinterface #20,  2           // InterfaceMethod java/util/List.addAll:(Ljava/util/Collection;)Z
      10: pop
      11: aload_0
      12: areturn

  public java.util.List<io.undertow.websockets.extensions.ExtensionHandshake> getExtensions();
    Code:
       0: aload_0
       1: getfield      #11                 // Field extensions:Ljava/util/List;
       4: areturn

  public java.lang.String getClientBindAddress();
    Code:
       0: aload_0
       1: getfield      #12                 // Field clientBindAddress:Ljava/lang/String;
       4: areturn

  public io.undertow.websockets.jsr.WebSocketDeploymentInfo setClientBindAddress(java.lang.String);
    Code:
       0: aload_0
       1: aload_1
       2: putfield      #12                 // Field clientBindAddress:Ljava/lang/String;
       5: aload_0
       6: areturn

  public io.undertow.websockets.jsr.WebSocketReconnectHandler getReconnectHandler();
    Code:
       0: aload_0
       1: getfield      #26                 // Field reconnectHandler:Lio/undertow/websockets/jsr/WebSocketReconnectHandler;
       4: areturn

  public io.undertow.websockets.jsr.WebSocketDeploymentInfo setReconnectHandler(io.undertow.websockets.jsr.WebSocketReconnectHandler);
    Code:
       0: aload_0
       1: aload_1
       2: putfield      #26                 // Field reconnectHandler:Lio/undertow/websockets/jsr/WebSocketReconnectHandler;
       5: aload_0
       6: areturn

  public io.undertow.websockets.jsr.WebSocketDeploymentInfo clone();
    Code:
       0: new           #27                 // class io/undertow/websockets/jsr/WebSocketDeploymentInfo
       3: dup
       4: invokespecial #28                 // Method "<init>":()V
       7: aload_0
       8: getfield      #4                  // Field worker:Ljava/util/function/Supplier;
      11: invokevirtual #29                 // Method setWorker:(Ljava/util/function/Supplier;)Lio/undertow/websockets/jsr/WebSocketDeploymentInfo;
      14: aload_0
      15: getfield      #15                 // Field buffers:Lio/undertow/connector/ByteBufferPool;
      18: invokevirtual #18                 // Method setBuffers:(Lio/undertow/connector/ByteBufferPool;)Lio/undertow/websockets/jsr/WebSocketDeploymentInfo;
      21: aload_0
      22: getfield      #5                  // Field dispatchToWorkerThread:Z
      25: invokevirtual #30                 // Method setDispatchToWorkerThread:(Z)Lio/undertow/websockets/jsr/WebSocketDeploymentInfo;
      28: aload_0
      29: getfield      #8                  // Field annotatedEndpoints:Ljava/util/List;
      32: invokevirtual #31                 // Method addAnnotatedEndpoints:(Ljava/util/Collection;)Lio/undertow/websockets/jsr/WebSocketDeploymentInfo;
      35: aload_0
      36: getfield      #9                  // Field programaticEndpoints:Ljava/util/List;
      39: invokevirtual #32                 // Method addProgramaticEndpoints:(Ljava/util/Collection;)Lio/undertow/websockets/jsr/WebSocketDeploymentInfo;
      42: aload_0
      43: getfield      #10                 // Field containerReadyListeners:Ljava/util/List;
      46: invokevirtual #33                 // Method addListeners:(Ljava/util/Collection;)Lio/undertow/websockets/jsr/WebSocketDeploymentInfo;
      49: aload_0
      50: getfield      #11                 // Field extensions:Ljava/util/List;
      53: invokevirtual #34                 // Method addExtensions:(Ljava/util/Collection;)Lio/undertow/websockets/jsr/WebSocketDeploymentInfo;
      56: aload_0
      57: getfield      #12                 // Field clientBindAddress:Ljava/lang/String;
      60: invokevirtual #35                 // Method setClientBindAddress:(Ljava/lang/String;)Lio/undertow/websockets/jsr/WebSocketDeploymentInfo;
      63: aload_0
      64: getfield      #26                 // Field reconnectHandler:Lio/undertow/websockets/jsr/WebSocketReconnectHandler;
      67: invokevirtual #36                 // Method setReconnectHandler:(Lio/undertow/websockets/jsr/WebSocketReconnectHandler;)Lio/undertow/websockets/jsr/WebSocketDeploymentInfo;
      70: areturn

  public java.lang.Object clone() throws java.lang.CloneNotSupportedException;
    Code:
       0: aload_0
       1: invokevirtual #37                 // Method clone:()Lio/undertow/websockets/jsr/WebSocketDeploymentInfo;
       4: areturn
}
