Compiled from "ConstantPool.java"
public class org.eclipse.jdt.internal.compiler.codegen.ConstantPool implements org.eclipse.jdt.internal.compiler.classfmt.ClassFileConstants,org.eclipse.jdt.internal.compiler.lookup.TypeIds {
  public static final int DOUBLE_INITIAL_SIZE;

  public static final int FLOAT_INITIAL_SIZE;

  public static final int INT_INITIAL_SIZE;

  public static final int LONG_INITIAL_SIZE;

  public static final int UTF8_INITIAL_SIZE;

  public static final int STRING_INITIAL_SIZE;

  public static final int METHODS_AND_FIELDS_INITIAL_SIZE;

  public static final int CLASS_INITIAL_SIZE;

  public static final int NAMEANDTYPE_INITIAL_SIZE;

  public static final int CONSTANTPOOL_INITIAL_SIZE;

  public static final int CONSTANTPOOL_GROW_SIZE;

  protected org.eclipse.jdt.internal.compiler.codegen.DoubleCache doubleCache;

  protected org.eclipse.jdt.internal.compiler.codegen.FloatCache floatCache;

  protected org.eclipse.jdt.internal.compiler.codegen.IntegerCache intCache;

  protected org.eclipse.jdt.internal.compiler.codegen.LongCache longCache;

  public org.eclipse.jdt.internal.compiler.codegen.CharArrayCache UTF8Cache;

  protected org.eclipse.jdt.internal.compiler.codegen.CharArrayCache stringCache;

  protected org.eclipse.jdt.internal.compiler.util.HashtableOfObject methodsAndFieldsCache;

  protected org.eclipse.jdt.internal.compiler.codegen.CharArrayCache classCache;

  protected org.eclipse.jdt.internal.compiler.util.HashtableOfObject nameAndTypeCacheForFieldsAndMethods;

  public byte[] poolContent;

  public int currentIndex;

  public int currentOffset;

  public int[] offsets;

  public org.eclipse.jdt.internal.compiler.ClassFile classFile;

  public static final char[] Append;

  public static final char[] ARRAY_NEWINSTANCE_NAME;

  public static final char[] ARRAY_NEWINSTANCE_SIGNATURE;

  public static final char[] ArrayCopy;

  public static final char[] ArrayCopySignature;

  public static final char[] ArrayJavaLangClassConstantPoolName;

  public static final char[] ArrayJavaLangObjectConstantPoolName;

  public static final char[] booleanBooleanSignature;

  public static final char[] BooleanConstrSignature;

  public static final char[] BOOLEANVALUE_BOOLEAN_METHOD_NAME;

  public static final char[] BOOLEANVALUE_BOOLEAN_METHOD_SIGNATURE;

  public static final char[] byteByteSignature;

  public static final char[] ByteConstrSignature;

  public static final char[] BYTEVALUE_BYTE_METHOD_NAME;

  public static final char[] BYTEVALUE_BYTE_METHOD_SIGNATURE;

  public static final char[] charCharacterSignature;

  public static final char[] CharConstrSignature;

  public static final char[] CHARVALUE_CHARACTER_METHOD_NAME;

  public static final char[] CHARVALUE_CHARACTER_METHOD_SIGNATURE;

  public static final char[] Clinit;

  public static final char[] DefaultConstructorSignature;

  public static final char[] ClinitSignature;

  public static final char[] Close;

  public static final char[] CloseSignature;

  public static final char[] DesiredAssertionStatus;

  public static final char[] DesiredAssertionStatusSignature;

  public static final char[] DoubleConstrSignature;

  public static final char[] doubleDoubleSignature;

  public static final char[] DOUBLEVALUE_DOUBLE_METHOD_NAME;

  public static final char[] DOUBLEVALUE_DOUBLE_METHOD_SIGNATURE;

  public static final char[] EnumName;

  public static final char[] EnumOrdinal;

  public static final char[] Exit;

  public static final char[] ExitIntSignature;

  public static final char[] FloatConstrSignature;

  public static final char[] floatFloatSignature;

  public static final char[] FLOATVALUE_FLOAT_METHOD_NAME;

  public static final char[] FLOATVALUE_FLOAT_METHOD_SIGNATURE;

  public static final char[] ForName;

  public static final char[] ForNameSignature;

  public static final char[] GET_BOOLEAN_METHOD_NAME;

  public static final char[] GET_BOOLEAN_METHOD_SIGNATURE;

  public static final char[] GET_BYTE_METHOD_NAME;

  public static final char[] GET_BYTE_METHOD_SIGNATURE;

  public static final char[] GET_CHAR_METHOD_NAME;

  public static final char[] GET_CHAR_METHOD_SIGNATURE;

  public static final char[] GET_DOUBLE_METHOD_NAME;

  public static final char[] GET_DOUBLE_METHOD_SIGNATURE;

  public static final char[] GET_FLOAT_METHOD_NAME;

  public static final char[] GET_FLOAT_METHOD_SIGNATURE;

  public static final char[] GET_INT_METHOD_NAME;

  public static final char[] GET_INT_METHOD_SIGNATURE;

  public static final char[] GET_LONG_METHOD_NAME;

  public static final char[] GET_LONG_METHOD_SIGNATURE;

  public static final char[] GET_OBJECT_METHOD_NAME;

  public static final char[] GET_OBJECT_METHOD_SIGNATURE;

  public static final char[] GET_SHORT_METHOD_NAME;

  public static final char[] GET_SHORT_METHOD_SIGNATURE;

  public static final char[] GetClass;

  public static final char[] GetClassSignature;

  public static final char[] GetComponentType;

  public static final char[] GetComponentTypeSignature;

  public static final char[] GetConstructor;

  public static final char[] GetConstructorSignature;

  public static final char[] GETDECLAREDCONSTRUCTOR_NAME;

  public static final char[] GETDECLAREDCONSTRUCTOR_SIGNATURE;

  public static final char[] GETDECLAREDFIELD_NAME;

  public static final char[] GETDECLAREDFIELD_SIGNATURE;

  public static final char[] GETDECLAREDMETHOD_NAME;

  public static final char[] GETDECLAREDMETHOD_SIGNATURE;

  public static final char[] GetMessage;

  public static final char[] GetMessageSignature;

  public static final char[] HasNext;

  public static final char[] HasNextSignature;

  public static final char[] Init;

  public static final char[] IntConstrSignature;

  public static final char[] ITERATOR_NAME;

  public static final char[] ITERATOR_SIGNATURE;

  public static final char[] Intern;

  public static final char[] InternSignature;

  public static final char[] IntIntegerSignature;

  public static final char[] INTVALUE_INTEGER_METHOD_NAME;

  public static final char[] INTVALUE_INTEGER_METHOD_SIGNATURE;

  public static final char[] INVOKE_METHOD_METHOD_NAME;

  public static final char[] INVOKE_METHOD_METHOD_SIGNATURE;

  public static final char[][] JAVA_LANG_REFLECT_ACCESSIBLEOBJECT;

  public static final char[][] JAVA_LANG_REFLECT_ARRAY;

  public static final char[] IllegalArgumentExceptionConstructorSignature;

  public static final char[] JavaIoPrintStreamSignature;

  public static final char[] JavaLangAssertionErrorConstantPoolName;

  public static final char[] JavaLangBooleanConstantPoolName;

  public static final char[] JavaLangByteConstantPoolName;

  public static final char[] JavaLangCharacterConstantPoolName;

  public static final char[] JavaLangClassConstantPoolName;

  public static final char[] JavaLangClassNotFoundExceptionConstantPoolName;

  public static final char[] JavaLangClassSignature;

  public static final char[] JavaLangDoubleConstantPoolName;

  public static final char[] JavaLangEnumConstantPoolName;

  public static final char[] JavaLangErrorConstantPoolName;

  public static final char[] JavaLangExceptionConstantPoolName;

  public static final char[] JavaLangFloatConstantPoolName;

  public static final char[] JavaLangIntegerConstantPoolName;

  public static final char[] JavaLangLongConstantPoolName;

  public static final char[] JavaLangNoClassDefFoundErrorConstantPoolName;

  public static final char[] JavaLangNoSuchFieldErrorConstantPoolName;

  public static final char[] JavaLangObjectConstantPoolName;

  public static final char[] JAVALANGREFLECTACCESSIBLEOBJECT_CONSTANTPOOLNAME;

  public static final char[] JAVALANGREFLECTARRAY_CONSTANTPOOLNAME;

  public static final char[] JavaLangReflectConstructorConstantPoolName;

  public static final char[] JavaLangReflectConstructorNewInstanceSignature;

  public static final char[] JAVALANGREFLECTFIELD_CONSTANTPOOLNAME;

  public static final char[] JAVALANGREFLECTMETHOD_CONSTANTPOOLNAME;

  public static final char[] JavaLangShortConstantPoolName;

  public static final char[] JavaLangStringBufferConstantPoolName;

  public static final char[] JavaLangStringBuilderConstantPoolName;

  public static final char[] JavaLangStringConstantPoolName;

  public static final char[] JavaLangStringSignature;

  public static final char[] JavaLangObjectSignature;

  public static final char[] JavaLangSystemConstantPoolName;

  public static final char[] JavaLangThrowableConstantPoolName;

  public static final char[] JavaLangIllegalArgumentExceptionConstantPoolName;

  public static final char[] JavaLangVoidConstantPoolName;

  public static final char[] JavaUtilIteratorConstantPoolName;

  public static final char[] LongConstrSignature;

  public static final char[] longLongSignature;

  public static final char[] LONGVALUE_LONG_METHOD_NAME;

  public static final char[] LONGVALUE_LONG_METHOD_SIGNATURE;

  public static final char[] Name;

  public static final char[] NewInstance;

  public static final char[] NewInstanceSignature;

  public static final char[] Next;

  public static final char[] NextSignature;

  public static final char[] ObjectConstrSignature;

  public static final char[] ObjectSignature;

  public static final char[] Ordinal;

  public static final char[] OrdinalSignature;

  public static final char[] Out;

  public static final char[] SET_BOOLEAN_METHOD_NAME;

  public static final char[] SET_BOOLEAN_METHOD_SIGNATURE;

  public static final char[] SET_BYTE_METHOD_NAME;

  public static final char[] SET_BYTE_METHOD_SIGNATURE;

  public static final char[] SET_CHAR_METHOD_NAME;

  public static final char[] SET_CHAR_METHOD_SIGNATURE;

  public static final char[] SET_DOUBLE_METHOD_NAME;

  public static final char[] SET_DOUBLE_METHOD_SIGNATURE;

  public static final char[] SET_FLOAT_METHOD_NAME;

  public static final char[] SET_FLOAT_METHOD_SIGNATURE;

  public static final char[] SET_INT_METHOD_NAME;

  public static final char[] SET_INT_METHOD_SIGNATURE;

  public static final char[] SET_LONG_METHOD_NAME;

  public static final char[] SET_LONG_METHOD_SIGNATURE;

  public static final char[] SET_OBJECT_METHOD_NAME;

  public static final char[] SET_OBJECT_METHOD_SIGNATURE;

  public static final char[] SET_SHORT_METHOD_NAME;

  public static final char[] SET_SHORT_METHOD_SIGNATURE;

  public static final char[] SETACCESSIBLE_NAME;

  public static final char[] SETACCESSIBLE_SIGNATURE;

  public static final char[] ShortConstrSignature;

  public static final char[] shortShortSignature;

  public static final char[] SHORTVALUE_SHORT_METHOD_NAME;

  public static final char[] SHORTVALUE_SHORT_METHOD_SIGNATURE;

  public static final char[] StringBufferAppendBooleanSignature;

  public static final char[] StringBufferAppendCharSignature;

  public static final char[] StringBufferAppendDoubleSignature;

  public static final char[] StringBufferAppendFloatSignature;

  public static final char[] StringBufferAppendIntSignature;

  public static final char[] StringBufferAppendLongSignature;

  public static final char[] StringBufferAppendObjectSignature;

  public static final char[] StringBufferAppendStringSignature;

  public static final char[] StringBuilderAppendBooleanSignature;

  public static final char[] StringBuilderAppendCharSignature;

  public static final char[] StringBuilderAppendDoubleSignature;

  public static final char[] StringBuilderAppendFloatSignature;

  public static final char[] StringBuilderAppendIntSignature;

  public static final char[] StringBuilderAppendLongSignature;

  public static final char[] StringBuilderAppendObjectSignature;

  public static final char[] StringBuilderAppendStringSignature;

  public static final char[] StringConstructorSignature;

  public static final char[] This;

  public static final char[] ToString;

  public static final char[] ToStringSignature;

  public static final char[] TYPE;

  public static final char[] ValueOf;

  public static final char[] ValueOfBooleanSignature;

  public static final char[] ValueOfCharSignature;

  public static final char[] ValueOfDoubleSignature;

  public static final char[] ValueOfFloatSignature;

  public static final char[] ValueOfIntSignature;

  public static final char[] ValueOfLongSignature;

  public static final char[] ValueOfObjectSignature;

  public static final char[] ValueOfStringClassSignature;

  public static final char[] JAVA_LANG_ANNOTATION_DOCUMENTED;

  public static final char[] JAVA_LANG_ANNOTATION_ELEMENTTYPE;

  public static final char[] JAVA_LANG_ANNOTATION_RETENTION;

  public static final char[] JAVA_LANG_ANNOTATION_RETENTIONPOLICY;

  public static final char[] JAVA_LANG_ANNOTATION_TARGET;

  public static final char[] JAVA_LANG_DEPRECATED;

  public static final char[] JAVA_LANG_ANNOTATION_INHERITED;

  public static final char[] JAVA_LANG_SAFEVARARGS;

  public static final char[] JAVA_LANG_INVOKE_METHODHANDLE_POLYMORPHICSIGNATURE;

  public static final char[] METAFACTORY;

  public static final char[] JAVA_LANG_INVOKE_LAMBDAMETAFACTORY_METAFACTORY_SIGNATURE;

  public static final char[] ALTMETAFACTORY;

  public static final char[] JAVA_LANG_INVOKE_LAMBDAMETAFACTORY_ALTMETAFACTORY_SIGNATURE;

  public static final char[] JavaLangInvokeSerializedLambda;

  public static final char[] JavaLangInvokeSerializedLambdaConstantPoolName;

  public static final char[] GetImplMethodName;

  public static final char[] GetImplMethodNameSignature;

  public static final char[] GetImplMethodKind;

  public static final char[] GetImplMethodKindSignature;

  public static final char[] GetFunctionalInterfaceClass;

  public static final char[] GetFunctionalInterfaceClassSignature;

  public static final char[] GetFunctionalInterfaceMethodName;

  public static final char[] GetFunctionalInterfaceMethodNameSignature;

  public static final char[] GetFunctionalInterfaceMethodSignature;

  public static final char[] GetFunctionalInterfaceMethodSignatureSignature;

  public static final char[] GetImplClass;

  public static final char[] GetImplClassSignature;

  public static final char[] GetImplMethodSignature;

  public static final char[] GetImplMethodSignatureSignature;

  public static final char[] GetCapturedArg;

  public static final char[] GetCapturedArgSignature;

  public static final char[] JAVA_LANG_ANNOTATION_REPEATABLE;

  public static final char[] HashCode;

  public static final char[] HashCodeSignature;

  public static final char[] Equals;

  public static final char[] EqualsSignature;

  public static final char[] AddSuppressed;

  public static final char[] AddSuppressedSignature;

  public static final char[] Clone;

  public static final char[] CloneSignature;

  static {};
    Code:
       0: ldc_w         #291                // String append
       3: invokevirtual #293                // Method java/lang/String.toCharArray:()[C
       6: putstatic     #299                // Field Append:[C
       9: ldc_w         #301                // String newInstance
      12: invokevirtual #293                // Method java/lang/String.toCharArray:()[C
      15: putstatic     #303                // Field ARRAY_NEWINSTANCE_NAME:[C
      18: ldc_w         #305                // String (Ljava/lang/Class;[I)Ljava/lang/Object;
      21: invokevirtual #293                // Method java/lang/String.toCharArray:()[C
      24: putstatic     #307                // Field ARRAY_NEWINSTANCE_SIGNATURE:[C
      27: ldc_w         #309                // String arraycopy
      30: invokevirtual #293                // Method java/lang/String.toCharArray:()[C
      33: putstatic     #311                // Field ArrayCopy:[C
      36: ldc_w         #313                // String (Ljava/lang/Object;ILjava/lang/Object;II)V
      39: invokevirtual #293                // Method java/lang/String.toCharArray:()[C
      42: putstatic     #315                // Field ArrayCopySignature:[C
      45: ldc_w         #317                // String [Ljava/lang/Class;
      48: invokevirtual #293                // Method java/lang/String.toCharArray:()[C
      51: putstatic     #319                // Field ArrayJavaLangClassConstantPoolName:[C
      54: ldc_w         #321                // String [Ljava/lang/Object;
      57: invokevirtual #293                // Method java/lang/String.toCharArray:()[C
      60: putstatic     #323                // Field ArrayJavaLangObjectConstantPoolName:[C
      63: ldc_w         #325                // String (Z)Ljava/lang/Boolean;
      66: invokevirtual #293                // Method java/lang/String.toCharArray:()[C
      69: putstatic     #327                // Field booleanBooleanSignature:[C
      72: ldc_w         #329                // String (Z)V
      75: invokevirtual #293                // Method java/lang/String.toCharArray:()[C
      78: putstatic     #331                // Field BooleanConstrSignature:[C
      81: ldc_w         #333                // String booleanValue
      84: invokevirtual #293                // Method java/lang/String.toCharArray:()[C
      87: putstatic     #335                // Field BOOLEANVALUE_BOOLEAN_METHOD_NAME:[C
      90: ldc_w         #337                // String ()Z
      93: invokevirtual #293                // Method java/lang/String.toCharArray:()[C
      96: putstatic     #339                // Field BOOLEANVALUE_BOOLEAN_METHOD_SIGNATURE:[C
      99: ldc_w         #341                // String (B)Ljava/lang/Byte;
     102: invokevirtual #293                // Method java/lang/String.toCharArray:()[C
     105: putstatic     #343                // Field byteByteSignature:[C
     108: ldc_w         #345                // String (B)V
     111: invokevirtual #293                // Method java/lang/String.toCharArray:()[C
     114: putstatic     #347                // Field ByteConstrSignature:[C
     117: ldc_w         #349                // String byteValue
     120: invokevirtual #293                // Method java/lang/String.toCharArray:()[C
     123: putstatic     #351                // Field BYTEVALUE_BYTE_METHOD_NAME:[C
     126: ldc_w         #353                // String ()B
     129: invokevirtual #293                // Method java/lang/String.toCharArray:()[C
     132: putstatic     #355                // Field BYTEVALUE_BYTE_METHOD_SIGNATURE:[C
     135: ldc_w         #357                // String (C)Ljava/lang/Character;
     138: invokevirtual #293                // Method java/lang/String.toCharArray:()[C
     141: putstatic     #359                // Field charCharacterSignature:[C
     144: ldc_w         #361                // String (C)V
     147: invokevirtual #293                // Method java/lang/String.toCharArray:()[C
     150: putstatic     #363                // Field CharConstrSignature:[C
     153: ldc_w         #365                // String charValue
     156: invokevirtual #293                // Method java/lang/String.toCharArray:()[C
     159: putstatic     #367                // Field CHARVALUE_CHARACTER_METHOD_NAME:[C
     162: ldc_w         #369                // String ()C
     165: invokevirtual #293                // Method java/lang/String.toCharArray:()[C
     168: putstatic     #371                // Field CHARVALUE_CHARACTER_METHOD_SIGNATURE:[C
     171: ldc_w         #373                // String <clinit>
     174: invokevirtual #293                // Method java/lang/String.toCharArray:()[C
     177: putstatic     #374                // Field Clinit:[C
     180: ldc_w         #376                // String ()V
     183: invokevirtual #293                // Method java/lang/String.toCharArray:()[C
     186: putstatic     #377                // Field DefaultConstructorSignature:[C
     189: getstatic     #377                // Field DefaultConstructorSignature:[C
     192: putstatic     #379                // Field ClinitSignature:[C
     195: ldc_w         #381                // String close
     198: invokevirtual #293                // Method java/lang/String.toCharArray:()[C
     201: putstatic     #383                // Field Close:[C
     204: ldc_w         #376                // String ()V
     207: invokevirtual #293                // Method java/lang/String.toCharArray:()[C
     210: putstatic     #385                // Field CloseSignature:[C
     213: ldc_w         #387                // String desiredAssertionStatus
     216: invokevirtual #293                // Method java/lang/String.toCharArray:()[C
     219: putstatic     #389                // Field DesiredAssertionStatus:[C
     222: ldc_w         #337                // String ()Z
     225: invokevirtual #293                // Method java/lang/String.toCharArray:()[C
     228: putstatic     #391                // Field DesiredAssertionStatusSignature:[C
     231: ldc_w         #393                // String (D)V
     234: invokevirtual #293                // Method java/lang/String.toCharArray:()[C
     237: putstatic     #395                // Field DoubleConstrSignature:[C
     240: ldc_w         #397                // String (D)Ljava/lang/Double;
     243: invokevirtual #293                // Method java/lang/String.toCharArray:()[C
     246: putstatic     #399                // Field doubleDoubleSignature:[C
     249: ldc_w         #401                // String doubleValue
     252: invokevirtual #293                // Method java/lang/String.toCharArray:()[C
     255: putstatic     #403                // Field DOUBLEVALUE_DOUBLE_METHOD_NAME:[C
     258: ldc_w         #405                // String ()D
     261: invokevirtual #293                // Method java/lang/String.toCharArray:()[C
     264: putstatic     #407                // Field DOUBLEVALUE_DOUBLE_METHOD_SIGNATURE:[C
     267: ldc_w         #409                // String $enum$name
     270: invokevirtual #293                // Method java/lang/String.toCharArray:()[C
     273: putstatic     #411                // Field EnumName:[C
     276: ldc_w         #413                // String $enum$ordinal
     279: invokevirtual #293                // Method java/lang/String.toCharArray:()[C
     282: putstatic     #415                // Field EnumOrdinal:[C
     285: ldc_w         #417                // String exit
     288: invokevirtual #293                // Method java/lang/String.toCharArray:()[C
     291: putstatic     #419                // Field Exit:[C
     294: ldc_w         #421                // String (I)V
     297: invokevirtual #293                // Method java/lang/String.toCharArray:()[C
     300: putstatic     #423                // Field ExitIntSignature:[C
     303: ldc_w         #425                // String (F)V
     306: invokevirtual #293                // Method java/lang/String.toCharArray:()[C
     309: putstatic     #427                // Field FloatConstrSignature:[C
     312: ldc_w         #429                // String (F)Ljava/lang/Float;
     315: invokevirtual #293                // Method java/lang/String.toCharArray:()[C
     318: putstatic     #431                // Field floatFloatSignature:[C
     321: ldc_w         #433                // String floatValue
     324: invokevirtual #293                // Method java/lang/String.toCharArray:()[C
     327: putstatic     #435                // Field FLOATVALUE_FLOAT_METHOD_NAME:[C
     330: ldc_w         #437                // String ()F
     333: invokevirtual #293                // Method java/lang/String.toCharArray:()[C
     336: putstatic     #439                // Field FLOATVALUE_FLOAT_METHOD_SIGNATURE:[C
     339: ldc_w         #441                // String forName
     342: invokevirtual #293                // Method java/lang/String.toCharArray:()[C
     345: putstatic     #443                // Field ForName:[C
     348: ldc_w         #445                // String (Ljava/lang/String;)Ljava/lang/Class;
     351: invokevirtual #293                // Method java/lang/String.toCharArray:()[C
     354: putstatic     #447                // Field ForNameSignature:[C
     357: ldc_w         #449                // String getBoolean
     360: invokevirtual #293                // Method java/lang/String.toCharArray:()[C
     363: putstatic     #451                // Field GET_BOOLEAN_METHOD_NAME:[C
     366: ldc_w         #453                // String (Ljava/lang/Object;)Z
     369: invokevirtual #293                // Method java/lang/String.toCharArray:()[C
     372: putstatic     #455                // Field GET_BOOLEAN_METHOD_SIGNATURE:[C
     375: ldc_w         #457                // String getByte
     378: invokevirtual #293                // Method java/lang/String.toCharArray:()[C
     381: putstatic     #459                // Field GET_BYTE_METHOD_NAME:[C
     384: ldc_w         #461                // String (Ljava/lang/Object;)B
     387: invokevirtual #293                // Method java/lang/String.toCharArray:()[C
     390: putstatic     #463                // Field GET_BYTE_METHOD_SIGNATURE:[C
     393: ldc_w         #465                // String getChar
     396: invokevirtual #293                // Method java/lang/String.toCharArray:()[C
     399: putstatic     #467                // Field GET_CHAR_METHOD_NAME:[C
     402: ldc_w         #469                // String (Ljava/lang/Object;)C
     405: invokevirtual #293                // Method java/lang/String.toCharArray:()[C
     408: putstatic     #471                // Field GET_CHAR_METHOD_SIGNATURE:[C
     411: ldc_w         #473                // String getDouble
     414: invokevirtual #293                // Method java/lang/String.toCharArray:()[C
     417: putstatic     #475                // Field GET_DOUBLE_METHOD_NAME:[C
     420: ldc_w         #477                // String (Ljava/lang/Object;)D
     423: invokevirtual #293                // Method java/lang/String.toCharArray:()[C
     426: putstatic     #479                // Field GET_DOUBLE_METHOD_SIGNATURE:[C
     429: ldc_w         #481                // String getFloat
     432: invokevirtual #293                // Method java/lang/String.toCharArray:()[C
     435: putstatic     #483                // Field GET_FLOAT_METHOD_NAME:[C
     438: ldc_w         #485                // String (Ljava/lang/Object;)F
     441: invokevirtual #293                // Method java/lang/String.toCharArray:()[C
     444: putstatic     #487                // Field GET_FLOAT_METHOD_SIGNATURE:[C
     447: ldc_w         #489                // String getInt
     450: invokevirtual #293                // Method java/lang/String.toCharArray:()[C
     453: putstatic     #491                // Field GET_INT_METHOD_NAME:[C
     456: ldc_w         #493                // String (Ljava/lang/Object;)I
     459: invokevirtual #293                // Method java/lang/String.toCharArray:()[C
     462: putstatic     #495                // Field GET_INT_METHOD_SIGNATURE:[C
     465: ldc_w         #497                // String getLong
     468: invokevirtual #293                // Method java/lang/String.toCharArray:()[C
     471: putstatic     #499                // Field GET_LONG_METHOD_NAME:[C
     474: ldc_w         #501                // String (Ljava/lang/Object;)J
     477: invokevirtual #293                // Method java/lang/String.toCharArray:()[C
     480: putstatic     #503                // Field GET_LONG_METHOD_SIGNATURE:[C
     483: ldc_w         #505                // String get
     486: invokevirtual #293                // Method java/lang/String.toCharArray:()[C
     489: putstatic     #507                // Field GET_OBJECT_METHOD_NAME:[C
     492: ldc_w         #509                // String (Ljava/lang/Object;)Ljava/lang/Object;
     495: invokevirtual #293                // Method java/lang/String.toCharArray:()[C
     498: putstatic     #511                // Field GET_OBJECT_METHOD_SIGNATURE:[C
     501: ldc_w         #513                // String getShort
     504: invokevirtual #293                // Method java/lang/String.toCharArray:()[C
     507: putstatic     #515                // Field GET_SHORT_METHOD_NAME:[C
     510: ldc_w         #517                // String (Ljava/lang/Object;)S
     513: invokevirtual #293                // Method java/lang/String.toCharArray:()[C
     516: putstatic     #519                // Field GET_SHORT_METHOD_SIGNATURE:[C
     519: ldc_w         #521                // String getClass
     522: invokevirtual #293                // Method java/lang/String.toCharArray:()[C
     525: putstatic     #523                // Field GetClass:[C
     528: ldc_w         #525                // String ()Ljava/lang/Class;
     531: invokevirtual #293                // Method java/lang/String.toCharArray:()[C
     534: putstatic     #527                // Field GetClassSignature:[C
     537: ldc_w         #529                // String getComponentType
     540: invokevirtual #293                // Method java/lang/String.toCharArray:()[C
     543: putstatic     #531                // Field GetComponentType:[C
     546: getstatic     #527                // Field GetClassSignature:[C
     549: putstatic     #533                // Field GetComponentTypeSignature:[C
     552: ldc_w         #535                // String getConstructor
     555: invokevirtual #293                // Method java/lang/String.toCharArray:()[C
     558: putstatic     #537                // Field GetConstructor:[C
     561: ldc_w         #539                // String ([Ljava/lang/Class;)Ljava/lang/reflect/Constructor;
     564: invokevirtual #293                // Method java/lang/String.toCharArray:()[C
     567: putstatic     #541                // Field GetConstructorSignature:[C
     570: ldc_w         #543                // String getDeclaredConstructor
     573: invokevirtual #293                // Method java/lang/String.toCharArray:()[C
     576: putstatic     #545                // Field GETDECLAREDCONSTRUCTOR_NAME:[C
     579: ldc_w         #539                // String ([Ljava/lang/Class;)Ljava/lang/reflect/Constructor;
     582: invokevirtual #293                // Method java/lang/String.toCharArray:()[C
     585: putstatic     #547                // Field GETDECLAREDCONSTRUCTOR_SIGNATURE:[C
     588: ldc_w         #549                // String getDeclaredField
     591: invokevirtual #293                // Method java/lang/String.toCharArray:()[C
     594: putstatic     #551                // Field GETDECLAREDFIELD_NAME:[C
     597: ldc_w         #553                // String (Ljava/lang/String;)Ljava/lang/reflect/Field;
     600: invokevirtual #293                // Method java/lang/String.toCharArray:()[C
     603: putstatic     #555                // Field GETDECLAREDFIELD_SIGNATURE:[C
     606: ldc_w         #557                // String getDeclaredMethod
     609: invokevirtual #293                // Method java/lang/String.toCharArray:()[C
     612: putstatic     #559                // Field GETDECLAREDMETHOD_NAME:[C
     615: ldc_w         #561                // String (Ljava/lang/String;[Ljava/lang/Class;)Ljava/lang/reflect/Method;
     618: invokevirtual #293                // Method java/lang/String.toCharArray:()[C
     621: putstatic     #563                // Field GETDECLAREDMETHOD_SIGNATURE:[C
     624: ldc_w         #565                // String getMessage
     627: invokevirtual #293                // Method java/lang/String.toCharArray:()[C
     630: putstatic     #567                // Field GetMessage:[C
     633: ldc_w         #569                // String ()Ljava/lang/String;
     636: invokevirtual #293                // Method java/lang/String.toCharArray:()[C
     639: putstatic     #571                // Field GetMessageSignature:[C
     642: ldc_w         #573                // String hasNext
     645: invokevirtual #293                // Method java/lang/String.toCharArray:()[C
     648: putstatic     #575                // Field HasNext:[C
     651: ldc_w         #337                // String ()Z
     654: invokevirtual #293                // Method java/lang/String.toCharArray:()[C
     657: putstatic     #577                // Field HasNextSignature:[C
     660: ldc_w         #579                // String <init>
     663: invokevirtual #293                // Method java/lang/String.toCharArray:()[C
     666: putstatic     #581                // Field Init:[C
     669: ldc_w         #421                // String (I)V
     672: invokevirtual #293                // Method java/lang/String.toCharArray:()[C
     675: putstatic     #583                // Field IntConstrSignature:[C
     678: ldc_w         #585                // String iterator
     681: invokevirtual #293                // Method java/lang/String.toCharArray:()[C
     684: putstatic     #587                // Field ITERATOR_NAME:[C
     687: ldc_w         #589                // String ()Ljava/util/Iterator;
     690: invokevirtual #293                // Method java/lang/String.toCharArray:()[C
     693: putstatic     #591                // Field ITERATOR_SIGNATURE:[C
     696: ldc_w         #593                // String intern
     699: invokevirtual #293                // Method java/lang/String.toCharArray:()[C
     702: putstatic     #595                // Field Intern:[C
     705: getstatic     #571                // Field GetMessageSignature:[C
     708: putstatic     #597                // Field InternSignature:[C
     711: ldc_w         #599                // String (I)Ljava/lang/Integer;
     714: invokevirtual #293                // Method java/lang/String.toCharArray:()[C
     717: putstatic     #601                // Field IntIntegerSignature:[C
     720: ldc_w         #603                // String intValue
     723: invokevirtual #293                // Method java/lang/String.toCharArray:()[C
     726: putstatic     #605                // Field INTVALUE_INTEGER_METHOD_NAME:[C
     729: ldc_w         #607                // String ()I
     732: invokevirtual #293                // Method java/lang/String.toCharArray:()[C
     735: putstatic     #609                // Field INTVALUE_INTEGER_METHOD_SIGNATURE:[C
     738: ldc_w         #611                // String invoke
     741: invokevirtual #293                // Method java/lang/String.toCharArray:()[C
     744: putstatic     #613                // Field INVOKE_METHOD_METHOD_NAME:[C
     747: ldc_w         #615                // String (Ljava/lang/Object;[Ljava/lang/Object;)Ljava/lang/Object;
     750: invokevirtual #293                // Method java/lang/String.toCharArray:()[C
     753: putstatic     #617                // Field INVOKE_METHOD_METHOD_SIGNATURE:[C
     756: iconst_4
     757: anewarray     #619                // class "[C"
     760: dup
     761: iconst_0
     762: getstatic     #620                // Field org/eclipse/jdt/internal/compiler/lookup/TypeConstants.JAVA:[C
     765: aastore
     766: dup
     767: iconst_1
     768: getstatic     #625                // Field org/eclipse/jdt/internal/compiler/lookup/TypeConstants.LANG:[C
     771: aastore
     772: dup
     773: iconst_2
     774: getstatic     #628                // Field org/eclipse/jdt/internal/compiler/lookup/TypeConstants.REFLECT:[C
     777: aastore
     778: dup
     779: iconst_3
     780: ldc_w         #631                // String AccessibleObject
     783: invokevirtual #293                // Method java/lang/String.toCharArray:()[C
     786: aastore
     787: putstatic     #633                // Field JAVA_LANG_REFLECT_ACCESSIBLEOBJECT:[[C
     790: iconst_4
     791: anewarray     #619                // class "[C"
     794: dup
     795: iconst_0
     796: getstatic     #620                // Field org/eclipse/jdt/internal/compiler/lookup/TypeConstants.JAVA:[C
     799: aastore
     800: dup
     801: iconst_1
     802: getstatic     #625                // Field org/eclipse/jdt/internal/compiler/lookup/TypeConstants.LANG:[C
     805: aastore
     806: dup
     807: iconst_2
     808: getstatic     #628                // Field org/eclipse/jdt/internal/compiler/lookup/TypeConstants.REFLECT:[C
     811: aastore
     812: dup
     813: iconst_3
     814: ldc_w         #635                // String Array
     817: invokevirtual #293                // Method java/lang/String.toCharArray:()[C
     820: aastore
     821: putstatic     #637                // Field JAVA_LANG_REFLECT_ARRAY:[[C
     824: ldc_w         #639                // String (Ljava/lang/String;)V
     827: invokevirtual #293                // Method java/lang/String.toCharArray:()[C
     830: putstatic     #641                // Field IllegalArgumentExceptionConstructorSignature:[C
     833: ldc_w         #643                // String Ljava/io/PrintStream;
     836: invokevirtual #293                // Method java/lang/String.toCharArray:()[C
     839: putstatic     #645                // Field JavaIoPrintStreamSignature:[C
     842: ldc_w         #647                // String java/lang/AssertionError
     845: invokevirtual #293                // Method java/lang/String.toCharArray:()[C
     848: putstatic     #649                // Field JavaLangAssertionErrorConstantPoolName:[C
     851: ldc_w         #651                // String java/lang/Boolean
     854: invokevirtual #293                // Method java/lang/String.toCharArray:()[C
     857: putstatic     #653                // Field JavaLangBooleanConstantPoolName:[C
     860: ldc_w         #655                // String java/lang/Byte
     863: invokevirtual #293                // Method java/lang/String.toCharArray:()[C
     866: putstatic     #657                // Field JavaLangByteConstantPoolName:[C
     869: ldc_w         #659                // String java/lang/Character
     872: invokevirtual #293                // Method java/lang/String.toCharArray:()[C
     875: putstatic     #661                // Field JavaLangCharacterConstantPoolName:[C
     878: ldc_w         #663                // String java/lang/Class
     881: invokevirtual #293                // Method java/lang/String.toCharArray:()[C
     884: putstatic     #665                // Field JavaLangClassConstantPoolName:[C
     887: ldc_w         #667                // String java/lang/ClassNotFoundException
     890: invokevirtual #293                // Method java/lang/String.toCharArray:()[C
     893: putstatic     #669                // Field JavaLangClassNotFoundExceptionConstantPoolName:[C
     896: ldc_w         #671                // String Ljava/lang/Class;
     899: invokevirtual #293                // Method java/lang/String.toCharArray:()[C
     902: putstatic     #673                // Field JavaLangClassSignature:[C
     905: ldc_w         #675                // String java/lang/Double
     908: invokevirtual #293                // Method java/lang/String.toCharArray:()[C
     911: putstatic     #677                // Field JavaLangDoubleConstantPoolName:[C
     914: ldc_w         #679                // String java/lang/Enum
     917: invokevirtual #293                // Method java/lang/String.toCharArray:()[C
     920: putstatic     #681                // Field JavaLangEnumConstantPoolName:[C
     923: ldc_w         #683                // String java/lang/Error
     926: invokevirtual #293                // Method java/lang/String.toCharArray:()[C
     929: putstatic     #685                // Field JavaLangErrorConstantPoolName:[C
     932: ldc_w         #687                // String java/lang/Exception
     935: invokevirtual #293                // Method java/lang/String.toCharArray:()[C
     938: putstatic     #689                // Field JavaLangExceptionConstantPoolName:[C
     941: ldc_w         #691                // String java/lang/Float
     944: invokevirtual #293                // Method java/lang/String.toCharArray:()[C
     947: putstatic     #693                // Field JavaLangFloatConstantPoolName:[C
     950: ldc_w         #695                // String java/lang/Integer
     953: invokevirtual #293                // Method java/lang/String.toCharArray:()[C
     956: putstatic     #697                // Field JavaLangIntegerConstantPoolName:[C
     959: ldc_w         #699                // String java/lang/Long
     962: invokevirtual #293                // Method java/lang/String.toCharArray:()[C
     965: putstatic     #701                // Field JavaLangLongConstantPoolName:[C
     968: ldc_w         #703                // String java/lang/NoClassDefFoundError
     971: invokevirtual #293                // Method java/lang/String.toCharArray:()[C
     974: putstatic     #705                // Field JavaLangNoClassDefFoundErrorConstantPoolName:[C
     977: ldc_w         #707                // String java/lang/NoSuchFieldError
     980: invokevirtual #293                // Method java/lang/String.toCharArray:()[C
     983: putstatic     #709                // Field JavaLangNoSuchFieldErrorConstantPoolName:[C
     986: ldc_w         #711                // String java/lang/Object
     989: invokevirtual #293                // Method java/lang/String.toCharArray:()[C
     992: putstatic     #712                // Field JavaLangObjectConstantPoolName:[C
     995: ldc_w         #714                // String java/lang/reflect/AccessibleObject
     998: invokevirtual #293                // Method java/lang/String.toCharArray:()[C
    1001: putstatic     #716                // Field JAVALANGREFLECTACCESSIBLEOBJECT_CONSTANTPOOLNAME:[C
    1004: ldc_w         #718                // String java/lang/reflect/Array
    1007: invokevirtual #293                // Method java/lang/String.toCharArray:()[C
    1010: putstatic     #720                // Field JAVALANGREFLECTARRAY_CONSTANTPOOLNAME:[C
    1013: ldc_w         #722                // String java/lang/reflect/Constructor
    1016: invokevirtual #293                // Method java/lang/String.toCharArray:()[C
    1019: putstatic     #724                // Field JavaLangReflectConstructorConstantPoolName:[C
    1022: ldc_w         #726                // String ([Ljava/lang/Object;)Ljava/lang/Object;
    1025: invokevirtual #293                // Method java/lang/String.toCharArray:()[C
    1028: putstatic     #728                // Field JavaLangReflectConstructorNewInstanceSignature:[C
    1031: ldc_w         #730                // String java/lang/reflect/Field
    1034: invokevirtual #293                // Method java/lang/String.toCharArray:()[C
    1037: putstatic     #732                // Field JAVALANGREFLECTFIELD_CONSTANTPOOLNAME:[C
    1040: ldc_w         #734                // String java/lang/reflect/Method
    1043: invokevirtual #293                // Method java/lang/String.toCharArray:()[C
    1046: putstatic     #736                // Field JAVALANGREFLECTMETHOD_CONSTANTPOOLNAME:[C
    1049: ldc_w         #738                // String java/lang/Short
    1052: invokevirtual #293                // Method java/lang/String.toCharArray:()[C
    1055: putstatic     #740                // Field JavaLangShortConstantPoolName:[C
    1058: ldc_w         #742                // String java/lang/StringBuffer
    1061: invokevirtual #293                // Method java/lang/String.toCharArray:()[C
    1064: putstatic     #744                // Field JavaLangStringBufferConstantPoolName:[C
    1067: ldc_w         #746                // String java/lang/StringBuilder
    1070: invokevirtual #293                // Method java/lang/String.toCharArray:()[C
    1073: putstatic     #748                // Field JavaLangStringBuilderConstantPoolName:[C
    1076: ldc_w         #750                // String java/lang/String
    1079: invokevirtual #293                // Method java/lang/String.toCharArray:()[C
    1082: putstatic     #751                // Field JavaLangStringConstantPoolName:[C
    1085: ldc_w         #753                // String Ljava/lang/String;
    1088: invokevirtual #293                // Method java/lang/String.toCharArray:()[C
    1091: putstatic     #755                // Field JavaLangStringSignature:[C
    1094: ldc_w         #757                // String Ljava/lang/Object;
    1097: invokevirtual #293                // Method java/lang/String.toCharArray:()[C
    1100: putstatic     #759                // Field JavaLangObjectSignature:[C
    1103: ldc_w         #761                // String java/lang/System
    1106: invokevirtual #293                // Method java/lang/String.toCharArray:()[C
    1109: putstatic     #763                // Field JavaLangSystemConstantPoolName:[C
    1112: ldc_w         #765                // String java/lang/Throwable
    1115: invokevirtual #293                // Method java/lang/String.toCharArray:()[C
    1118: putstatic     #767                // Field JavaLangThrowableConstantPoolName:[C
    1121: ldc_w         #769                // String java/lang/IllegalArgumentException
    1124: invokevirtual #293                // Method java/lang/String.toCharArray:()[C
    1127: putstatic     #771                // Field JavaLangIllegalArgumentExceptionConstantPoolName:[C
    1130: ldc_w         #773                // String java/lang/Void
    1133: invokevirtual #293                // Method java/lang/String.toCharArray:()[C
    1136: putstatic     #775                // Field JavaLangVoidConstantPoolName:[C
    1139: ldc_w         #777                // String java/util/Iterator
    1142: invokevirtual #293                // Method java/lang/String.toCharArray:()[C
    1145: putstatic     #779                // Field JavaUtilIteratorConstantPoolName:[C
    1148: ldc_w         #781                // String (J)V
    1151: invokevirtual #293                // Method java/lang/String.toCharArray:()[C
    1154: putstatic     #783                // Field LongConstrSignature:[C
    1157: ldc_w         #785                // String (J)Ljava/lang/Long;
    1160: invokevirtual #293                // Method java/lang/String.toCharArray:()[C
    1163: putstatic     #787                // Field longLongSignature:[C
    1166: ldc_w         #789                // String longValue
    1169: invokevirtual #293                // Method java/lang/String.toCharArray:()[C
    1172: putstatic     #791                // Field LONGVALUE_LONG_METHOD_NAME:[C
    1175: ldc_w         #793                // String ()J
    1178: invokevirtual #293                // Method java/lang/String.toCharArray:()[C
    1181: putstatic     #795                // Field LONGVALUE_LONG_METHOD_SIGNATURE:[C
    1184: ldc_w         #797                // String name
    1187: invokevirtual #293                // Method java/lang/String.toCharArray:()[C
    1190: putstatic     #799                // Field Name:[C
    1193: ldc_w         #301                // String newInstance
    1196: invokevirtual #293                // Method java/lang/String.toCharArray:()[C
    1199: putstatic     #801                // Field NewInstance:[C
    1202: ldc_w         #305                // String (Ljava/lang/Class;[I)Ljava/lang/Object;
    1205: invokevirtual #293                // Method java/lang/String.toCharArray:()[C
    1208: putstatic     #803                // Field NewInstanceSignature:[C
    1211: ldc_w         #805                // String next
    1214: invokevirtual #293                // Method java/lang/String.toCharArray:()[C
    1217: putstatic     #807                // Field Next:[C
    1220: ldc_w         #809                // String ()Ljava/lang/Object;
    1223: invokevirtual #293                // Method java/lang/String.toCharArray:()[C
    1226: putstatic     #811                // Field NextSignature:[C
    1229: ldc_w         #813                // String (Ljava/lang/Object;)V
    1232: invokevirtual #293                // Method java/lang/String.toCharArray:()[C
    1235: putstatic     #815                // Field ObjectConstrSignature:[C
    1238: ldc_w         #757                // String Ljava/lang/Object;
    1241: invokevirtual #293                // Method java/lang/String.toCharArray:()[C
    1244: putstatic     #817                // Field ObjectSignature:[C
    1247: ldc_w         #819                // String ordinal
    1250: invokevirtual #293                // Method java/lang/String.toCharArray:()[C
    1253: putstatic     #821                // Field Ordinal:[C
    1256: ldc_w         #607                // String ()I
    1259: invokevirtual #293                // Method java/lang/String.toCharArray:()[C
    1262: putstatic     #823                // Field OrdinalSignature:[C
    1265: ldc_w         #825                // String out
    1268: invokevirtual #293                // Method java/lang/String.toCharArray:()[C
    1271: putstatic     #827                // Field Out:[C
    1274: ldc_w         #829                // String setBoolean
    1277: invokevirtual #293                // Method java/lang/String.toCharArray:()[C
    1280: putstatic     #831                // Field SET_BOOLEAN_METHOD_NAME:[C
    1283: ldc_w         #833                // String (Ljava/lang/Object;Z)V
    1286: invokevirtual #293                // Method java/lang/String.toCharArray:()[C
    1289: putstatic     #835                // Field SET_BOOLEAN_METHOD_SIGNATURE:[C
    1292: ldc_w         #837                // String setByte
    1295: invokevirtual #293                // Method java/lang/String.toCharArray:()[C
    1298: putstatic     #839                // Field SET_BYTE_METHOD_NAME:[C
    1301: ldc_w         #841                // String (Ljava/lang/Object;B)V
    1304: invokevirtual #293                // Method java/lang/String.toCharArray:()[C
    1307: putstatic     #843                // Field SET_BYTE_METHOD_SIGNATURE:[C
    1310: ldc_w         #845                // String setChar
    1313: invokevirtual #293                // Method java/lang/String.toCharArray:()[C
    1316: putstatic     #847                // Field SET_CHAR_METHOD_NAME:[C
    1319: ldc_w         #849                // String (Ljava/lang/Object;C)V
    1322: invokevirtual #293                // Method java/lang/String.toCharArray:()[C
    1325: putstatic     #851                // Field SET_CHAR_METHOD_SIGNATURE:[C
    1328: ldc_w         #853                // String setDouble
    1331: invokevirtual #293                // Method java/lang/String.toCharArray:()[C
    1334: putstatic     #855                // Field SET_DOUBLE_METHOD_NAME:[C
    1337: ldc_w         #857                // String (Ljava/lang/Object;D)V
    1340: invokevirtual #293                // Method java/lang/String.toCharArray:()[C
    1343: putstatic     #859                // Field SET_DOUBLE_METHOD_SIGNATURE:[C
    1346: ldc_w         #861                // String setFloat
    1349: invokevirtual #293                // Method java/lang/String.toCharArray:()[C
    1352: putstatic     #863                // Field SET_FLOAT_METHOD_NAME:[C
    1355: ldc_w         #865                // String (Ljava/lang/Object;F)V
    1358: invokevirtual #293                // Method java/lang/String.toCharArray:()[C
    1361: putstatic     #867                // Field SET_FLOAT_METHOD_SIGNATURE:[C
    1364: ldc_w         #869                // String setInt
    1367: invokevirtual #293                // Method java/lang/String.toCharArray:()[C
    1370: putstatic     #871                // Field SET_INT_METHOD_NAME:[C
    1373: ldc_w         #873                // String (Ljava/lang/Object;I)V
    1376: invokevirtual #293                // Method java/lang/String.toCharArray:()[C
    1379: putstatic     #875                // Field SET_INT_METHOD_SIGNATURE:[C
    1382: ldc_w         #877                // String setLong
    1385: invokevirtual #293                // Method java/lang/String.toCharArray:()[C
    1388: putstatic     #879                // Field SET_LONG_METHOD_NAME:[C
    1391: ldc_w         #881                // String (Ljava/lang/Object;J)V
    1394: invokevirtual #293                // Method java/lang/String.toCharArray:()[C
    1397: putstatic     #883                // Field SET_LONG_METHOD_SIGNATURE:[C
    1400: ldc_w         #885                // String set
    1403: invokevirtual #293                // Method java/lang/String.toCharArray:()[C
    1406: putstatic     #887                // Field SET_OBJECT_METHOD_NAME:[C
    1409: ldc_w         #889                // String (Ljava/lang/Object;Ljava/lang/Object;)V
    1412: invokevirtual #293                // Method java/lang/String.toCharArray:()[C
    1415: putstatic     #891                // Field SET_OBJECT_METHOD_SIGNATURE:[C
    1418: ldc_w         #893                // String setShort
    1421: invokevirtual #293                // Method java/lang/String.toCharArray:()[C
    1424: putstatic     #895                // Field SET_SHORT_METHOD_NAME:[C
    1427: ldc_w         #897                // String (Ljava/lang/Object;S)V
    1430: invokevirtual #293                // Method java/lang/String.toCharArray:()[C
    1433: putstatic     #899                // Field SET_SHORT_METHOD_SIGNATURE:[C
    1436: ldc_w         #901                // String setAccessible
    1439: invokevirtual #293                // Method java/lang/String.toCharArray:()[C
    1442: putstatic     #903                // Field SETACCESSIBLE_NAME:[C
    1445: ldc_w         #329                // String (Z)V
    1448: invokevirtual #293                // Method java/lang/String.toCharArray:()[C
    1451: putstatic     #905                // Field SETACCESSIBLE_SIGNATURE:[C
    1454: ldc_w         #907                // String (S)V
    1457: invokevirtual #293                // Method java/lang/String.toCharArray:()[C
    1460: putstatic     #909                // Field ShortConstrSignature:[C
    1463: ldc_w         #911                // String (S)Ljava/lang/Short;
    1466: invokevirtual #293                // Method java/lang/String.toCharArray:()[C
    1469: putstatic     #913                // Field shortShortSignature:[C
    1472: ldc_w         #915                // String shortValue
    1475: invokevirtual #293                // Method java/lang/String.toCharArray:()[C
    1478: putstatic     #917                // Field SHORTVALUE_SHORT_METHOD_NAME:[C
    1481: ldc_w         #919                // String ()S
    1484: invokevirtual #293                // Method java/lang/String.toCharArray:()[C
    1487: putstatic     #921                // Field SHORTVALUE_SHORT_METHOD_SIGNATURE:[C
    1490: ldc_w         #923                // String (Z)Ljava/lang/StringBuffer;
    1493: invokevirtual #293                // Method java/lang/String.toCharArray:()[C
    1496: putstatic     #925                // Field StringBufferAppendBooleanSignature:[C
    1499: ldc_w         #927                // String (C)Ljava/lang/StringBuffer;
    1502: invokevirtual #293                // Method java/lang/String.toCharArray:()[C
    1505: putstatic     #929                // Field StringBufferAppendCharSignature:[C
    1508: ldc_w         #931                // String (D)Ljava/lang/StringBuffer;
    1511: invokevirtual #293                // Method java/lang/String.toCharArray:()[C
    1514: putstatic     #933                // Field StringBufferAppendDoubleSignature:[C
    1517: ldc_w         #935                // String (F)Ljava/lang/StringBuffer;
    1520: invokevirtual #293                // Method java/lang/String.toCharArray:()[C
    1523: putstatic     #937                // Field StringBufferAppendFloatSignature:[C
    1526: ldc_w         #939                // String (I)Ljava/lang/StringBuffer;
    1529: invokevirtual #293                // Method java/lang/String.toCharArray:()[C
    1532: putstatic     #941                // Field StringBufferAppendIntSignature:[C
    1535: ldc_w         #943                // String (J)Ljava/lang/StringBuffer;
    1538: invokevirtual #293                // Method java/lang/String.toCharArray:()[C
    1541: putstatic     #945                // Field StringBufferAppendLongSignature:[C
    1544: ldc_w         #947                // String (Ljava/lang/Object;)Ljava/lang/StringBuffer;
    1547: invokevirtual #293                // Method java/lang/String.toCharArray:()[C
    1550: putstatic     #949                // Field StringBufferAppendObjectSignature:[C
    1553: ldc_w         #951                // String (Ljava/lang/String;)Ljava/lang/StringBuffer;
    1556: invokevirtual #293                // Method java/lang/String.toCharArray:()[C
    1559: putstatic     #953                // Field StringBufferAppendStringSignature:[C
    1562: ldc_w         #955                // String (Z)Ljava/lang/StringBuilder;
    1565: invokevirtual #293                // Method java/lang/String.toCharArray:()[C
    1568: putstatic     #957                // Field StringBuilderAppendBooleanSignature:[C
    1571: ldc_w         #959                // String (C)Ljava/lang/StringBuilder;
    1574: invokevirtual #293                // Method java/lang/String.toCharArray:()[C
    1577: putstatic     #961                // Field StringBuilderAppendCharSignature:[C
    1580: ldc_w         #963                // String (D)Ljava/lang/StringBuilder;
    1583: invokevirtual #293                // Method java/lang/String.toCharArray:()[C
    1586: putstatic     #965                // Field StringBuilderAppendDoubleSignature:[C
    1589: ldc_w         #967                // String (F)Ljava/lang/StringBuilder;
    1592: invokevirtual #293                // Method java/lang/String.toCharArray:()[C
    1595: putstatic     #969                // Field StringBuilderAppendFloatSignature:[C
    1598: ldc_w         #971                // String (I)Ljava/lang/StringBuilder;
    1601: invokevirtual #293                // Method java/lang/String.toCharArray:()[C
    1604: putstatic     #973                // Field StringBuilderAppendIntSignature:[C
    1607: ldc_w         #975                // String (J)Ljava/lang/StringBuilder;
    1610: invokevirtual #293                // Method java/lang/String.toCharArray:()[C
    1613: putstatic     #977                // Field StringBuilderAppendLongSignature:[C
    1616: ldc_w         #979                // String (Ljava/lang/Object;)Ljava/lang/StringBuilder;
    1619: invokevirtual #293                // Method java/lang/String.toCharArray:()[C
    1622: putstatic     #981                // Field StringBuilderAppendObjectSignature:[C
    1625: ldc_w         #983                // String (Ljava/lang/String;)Ljava/lang/StringBuilder;
    1628: invokevirtual #293                // Method java/lang/String.toCharArray:()[C
    1631: putstatic     #985                // Field StringBuilderAppendStringSignature:[C
    1634: ldc_w         #639                // String (Ljava/lang/String;)V
    1637: invokevirtual #293                // Method java/lang/String.toCharArray:()[C
    1640: putstatic     #987                // Field StringConstructorSignature:[C
    1643: ldc_w         #989                // String this
    1646: invokevirtual #293                // Method java/lang/String.toCharArray:()[C
    1649: putstatic     #991                // Field This:[C
    1652: ldc_w         #993                // String toString
    1655: invokevirtual #293                // Method java/lang/String.toCharArray:()[C
    1658: putstatic     #995                // Field ToString:[C
    1661: getstatic     #571                // Field GetMessageSignature:[C
    1664: putstatic     #997                // Field ToStringSignature:[C
    1667: ldc_w         #999                // String TYPE
    1670: invokevirtual #293                // Method java/lang/String.toCharArray:()[C
    1673: putstatic     #1000               // Field TYPE:[C
    1676: ldc_w         #1002               // String valueOf
    1679: invokevirtual #293                // Method java/lang/String.toCharArray:()[C
    1682: putstatic     #1004               // Field ValueOf:[C
    1685: ldc_w         #1006               // String (Z)Ljava/lang/String;
    1688: invokevirtual #293                // Method java/lang/String.toCharArray:()[C
    1691: putstatic     #1008               // Field ValueOfBooleanSignature:[C
    1694: ldc_w         #1010               // String (C)Ljava/lang/String;
    1697: invokevirtual #293                // Method java/lang/String.toCharArray:()[C
    1700: putstatic     #1012               // Field ValueOfCharSignature:[C
    1703: ldc_w         #1014               // String (D)Ljava/lang/String;
    1706: invokevirtual #293                // Method java/lang/String.toCharArray:()[C
    1709: putstatic     #1016               // Field ValueOfDoubleSignature:[C
    1712: ldc_w         #1018               // String (F)Ljava/lang/String;
    1715: invokevirtual #293                // Method java/lang/String.toCharArray:()[C
    1718: putstatic     #1020               // Field ValueOfFloatSignature:[C
    1721: ldc_w         #1022               // String (I)Ljava/lang/String;
    1724: invokevirtual #293                // Method java/lang/String.toCharArray:()[C
    1727: putstatic     #1024               // Field ValueOfIntSignature:[C
    1730: ldc_w         #1026               // String (J)Ljava/lang/String;
    1733: invokevirtual #293                // Method java/lang/String.toCharArray:()[C
    1736: putstatic     #1028               // Field ValueOfLongSignature:[C
    1739: ldc_w         #1030               // String (Ljava/lang/Object;)Ljava/lang/String;
    1742: invokevirtual #293                // Method java/lang/String.toCharArray:()[C
    1745: putstatic     #1032               // Field ValueOfObjectSignature:[C
    1748: ldc_w         #1034               // String (Ljava/lang/Class;Ljava/lang/String;)Ljava/lang/Enum;
    1751: invokevirtual #293                // Method java/lang/String.toCharArray:()[C
    1754: putstatic     #1036               // Field ValueOfStringClassSignature:[C
    1757: ldc_w         #1038               // String Ljava/lang/annotation/Documented;
    1760: invokevirtual #293                // Method java/lang/String.toCharArray:()[C
    1763: putstatic     #1040               // Field JAVA_LANG_ANNOTATION_DOCUMENTED:[C
    1766: ldc_w         #1042               // String Ljava/lang/annotation/ElementType;
    1769: invokevirtual #293                // Method java/lang/String.toCharArray:()[C
    1772: putstatic     #1044               // Field JAVA_LANG_ANNOTATION_ELEMENTTYPE:[C
    1775: ldc_w         #1046               // String Ljava/lang/annotation/Retention;
    1778: invokevirtual #293                // Method java/lang/String.toCharArray:()[C
    1781: putstatic     #1048               // Field JAVA_LANG_ANNOTATION_RETENTION:[C
    1784: ldc_w         #1050               // String Ljava/lang/annotation/RetentionPolicy;
    1787: invokevirtual #293                // Method java/lang/String.toCharArray:()[C
    1790: putstatic     #1052               // Field JAVA_LANG_ANNOTATION_RETENTIONPOLICY:[C
    1793: ldc_w         #1054               // String Ljava/lang/annotation/Target;
    1796: invokevirtual #293                // Method java/lang/String.toCharArray:()[C
    1799: putstatic     #1056               // Field JAVA_LANG_ANNOTATION_TARGET:[C
    1802: ldc_w         #1058               // String Ljava/lang/Deprecated;
    1805: invokevirtual #293                // Method java/lang/String.toCharArray:()[C
    1808: putstatic     #1060               // Field JAVA_LANG_DEPRECATED:[C
    1811: ldc_w         #1062               // String Ljava/lang/annotation/Inherited;
    1814: invokevirtual #293                // Method java/lang/String.toCharArray:()[C
    1817: putstatic     #1064               // Field JAVA_LANG_ANNOTATION_INHERITED:[C
    1820: ldc_w         #1066               // String Ljava/lang/SafeVarargs;
    1823: invokevirtual #293                // Method java/lang/String.toCharArray:()[C
    1826: putstatic     #1068               // Field JAVA_LANG_SAFEVARARGS:[C
    1829: ldc_w         #1070               // String Ljava/lang/invoke/MethodHandle$PolymorphicSignature;
    1832: invokevirtual #293                // Method java/lang/String.toCharArray:()[C
    1835: putstatic     #1072               // Field JAVA_LANG_INVOKE_METHODHANDLE_POLYMORPHICSIGNATURE:[C
    1838: ldc_w         #1074               // String metafactory
    1841: invokevirtual #293                // Method java/lang/String.toCharArray:()[C
    1844: putstatic     #1076               // Field METAFACTORY:[C
    1847: ldc_w         #1078               // String (Ljava/lang/invoke/MethodHandles$Lookup;Ljava/lang/String;Ljava/lang/invoke/MethodType;Ljava/lang/invoke/MethodType;Ljava/lang/invoke/MethodHandle;Ljava/lang/invoke/MethodType;)Ljava/lang/invoke/CallSite;
    1850: invokevirtual #293                // Method java/lang/String.toCharArray:()[C
    1853: putstatic     #1080               // Field JAVA_LANG_INVOKE_LAMBDAMETAFACTORY_METAFACTORY_SIGNATURE:[C
    1856: ldc_w         #1082               // String altMetafactory
    1859: invokevirtual #293                // Method java/lang/String.toCharArray:()[C
    1862: putstatic     #1084               // Field ALTMETAFACTORY:[C
    1865: ldc_w         #1086               // String (Ljava/lang/invoke/MethodHandles$Lookup;Ljava/lang/String;Ljava/lang/invoke/MethodType;[Ljava/lang/Object;)Ljava/lang/invoke/CallSite;
    1868: invokevirtual #293                // Method java/lang/String.toCharArray:()[C
    1871: putstatic     #1088               // Field JAVA_LANG_INVOKE_LAMBDAMETAFACTORY_ALTMETAFACTORY_SIGNATURE:[C
    1874: ldc_w         #1090               // String Ljava/lang/invoke/SerializedLambda;
    1877: invokevirtual #293                // Method java/lang/String.toCharArray:()[C
    1880: putstatic     #1092               // Field JavaLangInvokeSerializedLambda:[C
    1883: ldc_w         #1094               // String java/lang/invoke/SerializedLambda
    1886: invokevirtual #293                // Method java/lang/String.toCharArray:()[C
    1889: putstatic     #1096               // Field JavaLangInvokeSerializedLambdaConstantPoolName:[C
    1892: ldc_w         #1098               // String getImplMethodName
    1895: invokevirtual #293                // Method java/lang/String.toCharArray:()[C
    1898: putstatic     #1100               // Field GetImplMethodName:[C
    1901: ldc_w         #569                // String ()Ljava/lang/String;
    1904: invokevirtual #293                // Method java/lang/String.toCharArray:()[C
    1907: putstatic     #1102               // Field GetImplMethodNameSignature:[C
    1910: ldc_w         #1104               // String getImplMethodKind
    1913: invokevirtual #293                // Method java/lang/String.toCharArray:()[C
    1916: putstatic     #1106               // Field GetImplMethodKind:[C
    1919: ldc_w         #607                // String ()I
    1922: invokevirtual #293                // Method java/lang/String.toCharArray:()[C
    1925: putstatic     #1108               // Field GetImplMethodKindSignature:[C
    1928: ldc_w         #1110               // String getFunctionalInterfaceClass
    1931: invokevirtual #293                // Method java/lang/String.toCharArray:()[C
    1934: putstatic     #1112               // Field GetFunctionalInterfaceClass:[C
    1937: ldc_w         #569                // String ()Ljava/lang/String;
    1940: invokevirtual #293                // Method java/lang/String.toCharArray:()[C
    1943: putstatic     #1114               // Field GetFunctionalInterfaceClassSignature:[C
    1946: ldc_w         #1116               // String getFunctionalInterfaceMethodName
    1949: invokevirtual #293                // Method java/lang/String.toCharArray:()[C
    1952: putstatic     #1118               // Field GetFunctionalInterfaceMethodName:[C
    1955: ldc_w         #569                // String ()Ljava/lang/String;
    1958: invokevirtual #293                // Method java/lang/String.toCharArray:()[C
    1961: putstatic     #1120               // Field GetFunctionalInterfaceMethodNameSignature:[C
    1964: ldc_w         #1122               // String getFunctionalInterfaceMethodSignature
    1967: invokevirtual #293                // Method java/lang/String.toCharArray:()[C
    1970: putstatic     #1124               // Field GetFunctionalInterfaceMethodSignature:[C
    1973: ldc_w         #569                // String ()Ljava/lang/String;
    1976: invokevirtual #293                // Method java/lang/String.toCharArray:()[C
    1979: putstatic     #1126               // Field GetFunctionalInterfaceMethodSignatureSignature:[C
    1982: ldc_w         #1128               // String getImplClass
    1985: invokevirtual #293                // Method java/lang/String.toCharArray:()[C
    1988: putstatic     #1130               // Field GetImplClass:[C
    1991: ldc_w         #569                // String ()Ljava/lang/String;
    1994: invokevirtual #293                // Method java/lang/String.toCharArray:()[C
    1997: putstatic     #1132               // Field GetImplClassSignature:[C
    2000: ldc_w         #1134               // String getImplMethodSignature
    2003: invokevirtual #293                // Method java/lang/String.toCharArray:()[C
    2006: putstatic     #1136               // Field GetImplMethodSignature:[C
    2009: ldc_w         #569                // String ()Ljava/lang/String;
    2012: invokevirtual #293                // Method java/lang/String.toCharArray:()[C
    2015: putstatic     #1138               // Field GetImplMethodSignatureSignature:[C
    2018: ldc_w         #1140               // String getCapturedArg
    2021: invokevirtual #293                // Method java/lang/String.toCharArray:()[C
    2024: putstatic     #1142               // Field GetCapturedArg:[C
    2027: ldc_w         #1144               // String (I)Ljava/lang/Object;
    2030: invokevirtual #293                // Method java/lang/String.toCharArray:()[C
    2033: putstatic     #1146               // Field GetCapturedArgSignature:[C
    2036: ldc_w         #1148               // String Ljava/lang/annotation/Repeatable;
    2039: invokevirtual #293                // Method java/lang/String.toCharArray:()[C
    2042: putstatic     #1150               // Field JAVA_LANG_ANNOTATION_REPEATABLE:[C
    2045: ldc_w         #1152               // String hashCode
    2048: invokevirtual #293                // Method java/lang/String.toCharArray:()[C
    2051: putstatic     #1154               // Field HashCode:[C
    2054: ldc_w         #607                // String ()I
    2057: invokevirtual #293                // Method java/lang/String.toCharArray:()[C
    2060: putstatic     #1156               // Field HashCodeSignature:[C
    2063: ldc_w         #1158               // String equals
    2066: invokevirtual #293                // Method java/lang/String.toCharArray:()[C
    2069: putstatic     #1160               // Field Equals:[C
    2072: ldc_w         #453                // String (Ljava/lang/Object;)Z
    2075: invokevirtual #293                // Method java/lang/String.toCharArray:()[C
    2078: putstatic     #1162               // Field EqualsSignature:[C
    2081: ldc_w         #1164               // String addSuppressed
    2084: invokevirtual #293                // Method java/lang/String.toCharArray:()[C
    2087: putstatic     #1166               // Field AddSuppressed:[C
    2090: ldc_w         #1168               // String (Ljava/lang/Throwable;)V
    2093: invokevirtual #293                // Method java/lang/String.toCharArray:()[C
    2096: putstatic     #1170               // Field AddSuppressedSignature:[C
    2099: ldc_w         #1172               // String clone
    2102: invokevirtual #293                // Method java/lang/String.toCharArray:()[C
    2105: putstatic     #1174               // Field Clone:[C
    2108: ldc_w         #809                // String ()Ljava/lang/Object;
    2111: invokevirtual #293                // Method java/lang/String.toCharArray:()[C
    2114: putstatic     #1176               // Field CloneSignature:[C
    2117: return

  public org.eclipse.jdt.internal.compiler.codegen.ConstantPool(org.eclipse.jdt.internal.compiler.ClassFile);
    Code:
       0: aload_0
       1: invokespecial #1181               // Method java/lang/Object."<init>":()V
       4: aload_0
       5: iconst_1
       6: putfield      #1183               // Field currentIndex:I
       9: aload_0
      10: new           #1185               // class org/eclipse/jdt/internal/compiler/codegen/CharArrayCache
      13: dup
      14: sipush        778
      17: invokespecial #1187               // Method org/eclipse/jdt/internal/compiler/codegen/CharArrayCache."<init>":(I)V
      20: putfield      #1189               // Field UTF8Cache:Lorg/eclipse/jdt/internal/compiler/codegen/CharArrayCache;
      23: aload_0
      24: new           #1185               // class org/eclipse/jdt/internal/compiler/codegen/CharArrayCache
      27: dup
      28: sipush        761
      31: invokespecial #1187               // Method org/eclipse/jdt/internal/compiler/codegen/CharArrayCache."<init>":(I)V
      34: putfield      #1191               // Field stringCache:Lorg/eclipse/jdt/internal/compiler/codegen/CharArrayCache;
      37: aload_0
      38: new           #1193               // class org/eclipse/jdt/internal/compiler/util/HashtableOfObject
      41: dup
      42: sipush        450
      45: invokespecial #1195               // Method org/eclipse/jdt/internal/compiler/util/HashtableOfObject."<init>":(I)V
      48: putfield      #1196               // Field methodsAndFieldsCache:Lorg/eclipse/jdt/internal/compiler/util/HashtableOfObject;
      51: aload_0
      52: new           #1185               // class org/eclipse/jdt/internal/compiler/codegen/CharArrayCache
      55: dup
      56: bipush        86
      58: invokespecial #1187               // Method org/eclipse/jdt/internal/compiler/codegen/CharArrayCache."<init>":(I)V
      61: putfield      #1198               // Field classCache:Lorg/eclipse/jdt/internal/compiler/codegen/CharArrayCache;
      64: aload_0
      65: new           #1193               // class org/eclipse/jdt/internal/compiler/util/HashtableOfObject
      68: dup
      69: sipush        272
      72: invokespecial #1195               // Method org/eclipse/jdt/internal/compiler/util/HashtableOfObject."<init>":(I)V
      75: putfield      #1200               // Field nameAndTypeCacheForFieldsAndMethods:Lorg/eclipse/jdt/internal/compiler/util/HashtableOfObject;
      78: aload_0
      79: iconst_5
      80: newarray       int
      82: putfield      #1202               // Field offsets:[I
      85: aload_0
      86: aload_1
      87: invokevirtual #1204               // Method initialize:(Lorg/eclipse/jdt/internal/compiler/ClassFile;)V
      90: return

  public void initialize(org.eclipse.jdt.internal.compiler.ClassFile);
    Code:
       0: aload_0
       1: aload_1
       2: getfield      #1208               // Field org/eclipse/jdt/internal/compiler/ClassFile.header:[B
       5: putfield      #1213               // Field poolContent:[B
       8: aload_0
       9: aload_1
      10: getfield      #1215               // Field org/eclipse/jdt/internal/compiler/ClassFile.headerOffset:I
      13: putfield      #1218               // Field currentOffset:I
      16: aload_0
      17: iconst_1
      18: putfield      #1183               // Field currentIndex:I
      21: aload_0
      22: aload_1
      23: putfield      #1220               // Field classFile:Lorg/eclipse/jdt/internal/compiler/ClassFile;
      26: return

  public byte[] dumpBytes();
    Code:
       0: aload_0
       1: getfield      #1213               // Field poolContent:[B
       4: iconst_0
       5: aload_0
       6: aload_0
       7: getfield      #1218               // Field currentOffset:I
      10: newarray       byte
      12: dup_x1
      13: putfield      #1213               // Field poolContent:[B
      16: iconst_0
      17: aload_0
      18: getfield      #1218               // Field currentOffset:I
      21: invokestatic  #1225               // Method java/lang/System.arraycopy:(Ljava/lang/Object;ILjava/lang/Object;II)V
      24: aload_0
      25: getfield      #1213               // Field poolContent:[B
      28: areturn

  public int literalIndex(byte[], char[]);
    Code:
       0: aload_0
       1: getfield      #1189               // Field UTF8Cache:Lorg/eclipse/jdt/internal/compiler/codegen/CharArrayCache;
       4: aload_2
       5: aload_0
       6: getfield      #1183               // Field currentIndex:I
       9: invokevirtual #1230               // Method org/eclipse/jdt/internal/compiler/codegen/CharArrayCache.putIfAbsent:([CI)I
      12: dup
      13: istore_3
      14: ifge          211
      17: iload_3
      18: ineg
      19: dup
      20: istore_3
      21: ldc_w         #1234               // int 65535
      24: if_icmple     56
      27: aload_0
      28: getfield      #1220               // Field classFile:Lorg/eclipse/jdt/internal/compiler/ClassFile;
      31: getfield      #1235               // Field org/eclipse/jdt/internal/compiler/ClassFile.referenceBinding:Lorg/eclipse/jdt/internal/compiler/lookup/SourceTypeBinding;
      34: getfield      #1239               // Field org/eclipse/jdt/internal/compiler/lookup/SourceTypeBinding.scope:Lorg/eclipse/jdt/internal/compiler/lookup/ClassScope;
      37: invokevirtual #1245               // Method org/eclipse/jdt/internal/compiler/lookup/ClassScope.problemReporter:()Lorg/eclipse/jdt/internal/compiler/problem/ProblemReporter;
      40: aload_0
      41: getfield      #1220               // Field classFile:Lorg/eclipse/jdt/internal/compiler/ClassFile;
      44: getfield      #1235               // Field org/eclipse/jdt/internal/compiler/ClassFile.referenceBinding:Lorg/eclipse/jdt/internal/compiler/lookup/SourceTypeBinding;
      47: getfield      #1239               // Field org/eclipse/jdt/internal/compiler/lookup/SourceTypeBinding.scope:Lorg/eclipse/jdt/internal/compiler/lookup/ClassScope;
      50: invokevirtual #1251               // Method org/eclipse/jdt/internal/compiler/lookup/ClassScope.referenceType:()Lorg/eclipse/jdt/internal/compiler/ast/TypeDeclaration;
      53: invokevirtual #1255               // Method org/eclipse/jdt/internal/compiler/problem/ProblemReporter.noMoreAvailableSpaceInConstantPool:(Lorg/eclipse/jdt/internal/compiler/ast/TypeDeclaration;)V
      56: aload_0
      57: dup
      58: getfield      #1183               // Field currentIndex:I
      61: iconst_1
      62: iadd
      63: putfield      #1183               // Field currentIndex:I
      66: aload_0
      67: getfield      #1202               // Field offsets:[I
      70: arraylength
      71: istore        4
      73: iload         4
      75: iload_3
      76: if_icmpgt     100
      79: aload_0
      80: getfield      #1202               // Field offsets:[I
      83: iconst_0
      84: aload_0
      85: iload_3
      86: iconst_2
      87: imul
      88: newarray       int
      90: dup_x1
      91: putfield      #1202               // Field offsets:[I
      94: iconst_0
      95: iload         4
      97: invokestatic  #1225               // Method java/lang/System.arraycopy:(Ljava/lang/Object;ILjava/lang/Object;II)V
     100: aload_0
     101: getfield      #1202               // Field offsets:[I
     104: iload_3
     105: aload_0
     106: getfield      #1218               // Field currentOffset:I
     109: iastore
     110: aload_0
     111: iconst_1
     112: invokevirtual #1261               // Method writeU1:(I)V
     115: aload_1
     116: arraylength
     117: istore        5
     119: aload_0
     120: getfield      #1218               // Field currentOffset:I
     123: iconst_2
     124: iadd
     125: iload         5
     127: iadd
     128: aload_0
     129: getfield      #1213               // Field poolContent:[B
     132: arraylength
     133: if_icmplt     144
     136: aload_0
     137: iconst_2
     138: iload         5
     140: iadd
     141: invokespecial #1264               // Method resizePoolContents:(I)V
     144: aload_0
     145: getfield      #1213               // Field poolContent:[B
     148: aload_0
     149: dup
     150: getfield      #1218               // Field currentOffset:I
     153: dup_x1
     154: iconst_1
     155: iadd
     156: putfield      #1218               // Field currentOffset:I
     159: iload         5
     161: bipush        8
     163: ishr
     164: i2b
     165: bastore
     166: aload_0
     167: getfield      #1213               // Field poolContent:[B
     170: aload_0
     171: dup
     172: getfield      #1218               // Field currentOffset:I
     175: dup_x1
     176: iconst_1
     177: iadd
     178: putfield      #1218               // Field currentOffset:I
     181: iload         5
     183: i2b
     184: bastore
     185: aload_1
     186: iconst_0
     187: aload_0
     188: getfield      #1213               // Field poolContent:[B
     191: aload_0
     192: getfield      #1218               // Field currentOffset:I
     195: iload         5
     197: invokestatic  #1225               // Method java/lang/System.arraycopy:(Ljava/lang/Object;ILjava/lang/Object;II)V
     200: aload_0
     201: dup
     202: getfield      #1218               // Field currentOffset:I
     205: iload         5
     207: iadd
     208: putfield      #1218               // Field currentOffset:I
     211: iload_3
     212: ireturn

  public int literalIndex(org.eclipse.jdt.internal.compiler.lookup.TypeBinding);
    Code:
       0: aload_1
       1: invokevirtual #1274               // Method org/eclipse/jdt/internal/compiler/lookup/TypeBinding.leafComponentType:()Lorg/eclipse/jdt/internal/compiler/lookup/TypeBinding;
       4: astore_2
       5: aload_2
       6: getfield      #1280               // Field org/eclipse/jdt/internal/compiler/lookup/TypeBinding.tagBits:J
       9: ldc2_w        #1284               // long 2048l
      12: land
      13: lconst_0
      14: lcmp
      15: ifeq          26
      18: aload_0
      19: getfield      #1220               // Field classFile:Lorg/eclipse/jdt/internal/compiler/ClassFile;
      22: aload_2
      23: invokestatic  #1286               // Method org/eclipse/jdt/internal/compiler/util/Util.recordNestedType:(Lorg/eclipse/jdt/internal/compiler/ClassFile;Lorg/eclipse/jdt/internal/compiler/lookup/TypeBinding;)V
      26: aload_0
      27: aload_1
      28: invokevirtual #1292               // Method org/eclipse/jdt/internal/compiler/lookup/TypeBinding.signature:()[C
      31: invokevirtual #1295               // Method literalIndex:([C)I
      34: ireturn

  public int literalIndex(char[]);
    Code:
       0: aload_0
       1: getfield      #1189               // Field UTF8Cache:Lorg/eclipse/jdt/internal/compiler/codegen/CharArrayCache;
       4: aload_1
       5: aload_0
       6: getfield      #1183               // Field currentIndex:I
       9: invokevirtual #1230               // Method org/eclipse/jdt/internal/compiler/codegen/CharArrayCache.putIfAbsent:([CI)I
      12: dup
      13: istore_2
      14: ifge          390
      17: iload_2
      18: ineg
      19: dup
      20: istore_2
      21: ldc_w         #1234               // int 65535
      24: if_icmple     56
      27: aload_0
      28: getfield      #1220               // Field classFile:Lorg/eclipse/jdt/internal/compiler/ClassFile;
      31: getfield      #1235               // Field org/eclipse/jdt/internal/compiler/ClassFile.referenceBinding:Lorg/eclipse/jdt/internal/compiler/lookup/SourceTypeBinding;
      34: getfield      #1239               // Field org/eclipse/jdt/internal/compiler/lookup/SourceTypeBinding.scope:Lorg/eclipse/jdt/internal/compiler/lookup/ClassScope;
      37: invokevirtual #1245               // Method org/eclipse/jdt/internal/compiler/lookup/ClassScope.problemReporter:()Lorg/eclipse/jdt/internal/compiler/problem/ProblemReporter;
      40: aload_0
      41: getfield      #1220               // Field classFile:Lorg/eclipse/jdt/internal/compiler/ClassFile;
      44: getfield      #1235               // Field org/eclipse/jdt/internal/compiler/ClassFile.referenceBinding:Lorg/eclipse/jdt/internal/compiler/lookup/SourceTypeBinding;
      47: getfield      #1239               // Field org/eclipse/jdt/internal/compiler/lookup/SourceTypeBinding.scope:Lorg/eclipse/jdt/internal/compiler/lookup/ClassScope;
      50: invokevirtual #1251               // Method org/eclipse/jdt/internal/compiler/lookup/ClassScope.referenceType:()Lorg/eclipse/jdt/internal/compiler/ast/TypeDeclaration;
      53: invokevirtual #1255               // Method org/eclipse/jdt/internal/compiler/problem/ProblemReporter.noMoreAvailableSpaceInConstantPool:(Lorg/eclipse/jdt/internal/compiler/ast/TypeDeclaration;)V
      56: aload_0
      57: getfield      #1202               // Field offsets:[I
      60: arraylength
      61: istore_3
      62: iload_3
      63: iload_2
      64: if_icmpgt     87
      67: aload_0
      68: getfield      #1202               // Field offsets:[I
      71: iconst_0
      72: aload_0
      73: iload_2
      74: iconst_2
      75: imul
      76: newarray       int
      78: dup_x1
      79: putfield      #1202               // Field offsets:[I
      82: iconst_0
      83: iload_3
      84: invokestatic  #1225               // Method java/lang/System.arraycopy:(Ljava/lang/Object;ILjava/lang/Object;II)V
      87: aload_0
      88: getfield      #1202               // Field offsets:[I
      91: iload_2
      92: aload_0
      93: getfield      #1218               // Field currentOffset:I
      96: iastore
      97: aload_0
      98: iconst_1
      99: invokevirtual #1261               // Method writeU1:(I)V
     102: aload_0
     103: getfield      #1218               // Field currentOffset:I
     106: istore        4
     108: aload_0
     109: getfield      #1218               // Field currentOffset:I
     112: iconst_2
     113: iadd
     114: aload_0
     115: getfield      #1213               // Field poolContent:[B
     118: arraylength
     119: if_icmplt     127
     122: aload_0
     123: iconst_2
     124: invokespecial #1264               // Method resizePoolContents:(I)V
     127: aload_0
     128: dup
     129: getfield      #1218               // Field currentOffset:I
     132: iconst_2
     133: iadd
     134: putfield      #1218               // Field currentOffset:I
     137: iconst_0
     138: istore_3
     139: iconst_0
     140: istore        5
     142: goto          270
     145: aload_1
     146: iload         5
     148: caload
     149: istore        6
     151: iload         6
     153: iconst_1
     154: if_icmplt     176
     157: iload         6
     159: bipush        127
     161: if_icmpgt     176
     164: aload_0
     165: iload         6
     167: invokevirtual #1261               // Method writeU1:(I)V
     170: iinc          3, 1
     173: goto          267
     176: iload         6
     178: sipush        2047
     181: if_icmple     235
     184: iinc          3, 3
     187: aload_0
     188: sipush        224
     191: iload         6
     193: bipush        12
     195: ishr
     196: bipush        15
     198: iand
     199: ior
     200: invokevirtual #1261               // Method writeU1:(I)V
     203: aload_0
     204: sipush        128
     207: iload         6
     209: bipush        6
     211: ishr
     212: bipush        63
     214: iand
     215: ior
     216: invokevirtual #1261               // Method writeU1:(I)V
     219: aload_0
     220: sipush        128
     223: iload         6
     225: bipush        63
     227: iand
     228: ior
     229: invokevirtual #1261               // Method writeU1:(I)V
     232: goto          267
     235: iinc          3, 2
     238: aload_0
     239: sipush        192
     242: iload         6
     244: bipush        6
     246: ishr
     247: bipush        31
     249: iand
     250: ior
     251: invokevirtual #1261               // Method writeU1:(I)V
     254: aload_0
     255: sipush        128
     258: iload         6
     260: bipush        63
     262: iand
     263: ior
     264: invokevirtual #1261               // Method writeU1:(I)V
     267: iinc          5, 1
     270: iload         5
     272: aload_1
     273: arraylength
     274: if_icmplt     145
     277: iload_3
     278: ldc_w         #1234               // int 65535
     281: if_icmplt     321
     284: aload_0
     285: iload         4
     287: iconst_1
     288: isub
     289: putfield      #1218               // Field currentOffset:I
     292: aload_0
     293: getfield      #1220               // Field classFile:Lorg/eclipse/jdt/internal/compiler/ClassFile;
     296: getfield      #1235               // Field org/eclipse/jdt/internal/compiler/ClassFile.referenceBinding:Lorg/eclipse/jdt/internal/compiler/lookup/SourceTypeBinding;
     299: getfield      #1239               // Field org/eclipse/jdt/internal/compiler/lookup/SourceTypeBinding.scope:Lorg/eclipse/jdt/internal/compiler/lookup/ClassScope;
     302: invokevirtual #1245               // Method org/eclipse/jdt/internal/compiler/lookup/ClassScope.problemReporter:()Lorg/eclipse/jdt/internal/compiler/problem/ProblemReporter;
     305: aload_0
     306: getfield      #1220               // Field classFile:Lorg/eclipse/jdt/internal/compiler/ClassFile;
     309: getfield      #1235               // Field org/eclipse/jdt/internal/compiler/ClassFile.referenceBinding:Lorg/eclipse/jdt/internal/compiler/lookup/SourceTypeBinding;
     312: getfield      #1239               // Field org/eclipse/jdt/internal/compiler/lookup/SourceTypeBinding.scope:Lorg/eclipse/jdt/internal/compiler/lookup/ClassScope;
     315: invokevirtual #1251               // Method org/eclipse/jdt/internal/compiler/lookup/ClassScope.referenceType:()Lorg/eclipse/jdt/internal/compiler/ast/TypeDeclaration;
     318: invokevirtual #1301               // Method org/eclipse/jdt/internal/compiler/problem/ProblemReporter.noMoreAvailableSpaceForConstant:(Lorg/eclipse/jdt/internal/compiler/ast/TypeDeclaration;)V
     321: iload_2
     322: ldc_w         #1234               // int 65535
     325: if_icmple     357
     328: aload_0
     329: getfield      #1220               // Field classFile:Lorg/eclipse/jdt/internal/compiler/ClassFile;
     332: getfield      #1235               // Field org/eclipse/jdt/internal/compiler/ClassFile.referenceBinding:Lorg/eclipse/jdt/internal/compiler/lookup/SourceTypeBinding;
     335: getfield      #1239               // Field org/eclipse/jdt/internal/compiler/lookup/SourceTypeBinding.scope:Lorg/eclipse/jdt/internal/compiler/lookup/ClassScope;
     338: invokevirtual #1245               // Method org/eclipse/jdt/internal/compiler/lookup/ClassScope.problemReporter:()Lorg/eclipse/jdt/internal/compiler/problem/ProblemReporter;
     341: aload_0
     342: getfield      #1220               // Field classFile:Lorg/eclipse/jdt/internal/compiler/ClassFile;
     345: getfield      #1235               // Field org/eclipse/jdt/internal/compiler/ClassFile.referenceBinding:Lorg/eclipse/jdt/internal/compiler/lookup/SourceTypeBinding;
     348: getfield      #1239               // Field org/eclipse/jdt/internal/compiler/lookup/SourceTypeBinding.scope:Lorg/eclipse/jdt/internal/compiler/lookup/ClassScope;
     351: invokevirtual #1251               // Method org/eclipse/jdt/internal/compiler/lookup/ClassScope.referenceType:()Lorg/eclipse/jdt/internal/compiler/ast/TypeDeclaration;
     354: invokevirtual #1255               // Method org/eclipse/jdt/internal/compiler/problem/ProblemReporter.noMoreAvailableSpaceInConstantPool:(Lorg/eclipse/jdt/internal/compiler/ast/TypeDeclaration;)V
     357: aload_0
     358: dup
     359: getfield      #1183               // Field currentIndex:I
     362: iconst_1
     363: iadd
     364: putfield      #1183               // Field currentIndex:I
     367: aload_0
     368: getfield      #1213               // Field poolContent:[B
     371: iload         4
     373: iload_3
     374: bipush        8
     376: ishr
     377: i2b
     378: bastore
     379: aload_0
     380: getfield      #1213               // Field poolContent:[B
     383: iload         4
     385: iconst_1
     386: iadd
     387: iload_3
     388: i2b
     389: bastore
     390: iload_2
     391: ireturn

  public int literalIndex(char[], byte[]);
    Code:
       0: aload_0
       1: getfield      #1191               // Field stringCache:Lorg/eclipse/jdt/internal/compiler/codegen/CharArrayCache;
       4: aload_1
       5: aload_0
       6: getfield      #1183               // Field currentIndex:I
       9: invokevirtual #1230               // Method org/eclipse/jdt/internal/compiler/codegen/CharArrayCache.putIfAbsent:([CI)I
      12: dup
      13: istore_3
      14: ifge          185
      17: aload_0
      18: dup
      19: getfield      #1183               // Field currentIndex:I
      22: iconst_1
      23: iadd
      24: putfield      #1183               // Field currentIndex:I
      27: iload_3
      28: ineg
      29: dup
      30: istore_3
      31: ldc_w         #1234               // int 65535
      34: if_icmple     66
      37: aload_0
      38: getfield      #1220               // Field classFile:Lorg/eclipse/jdt/internal/compiler/ClassFile;
      41: getfield      #1235               // Field org/eclipse/jdt/internal/compiler/ClassFile.referenceBinding:Lorg/eclipse/jdt/internal/compiler/lookup/SourceTypeBinding;
      44: getfield      #1239               // Field org/eclipse/jdt/internal/compiler/lookup/SourceTypeBinding.scope:Lorg/eclipse/jdt/internal/compiler/lookup/ClassScope;
      47: invokevirtual #1245               // Method org/eclipse/jdt/internal/compiler/lookup/ClassScope.problemReporter:()Lorg/eclipse/jdt/internal/compiler/problem/ProblemReporter;
      50: aload_0
      51: getfield      #1220               // Field classFile:Lorg/eclipse/jdt/internal/compiler/ClassFile;
      54: getfield      #1235               // Field org/eclipse/jdt/internal/compiler/ClassFile.referenceBinding:Lorg/eclipse/jdt/internal/compiler/lookup/SourceTypeBinding;
      57: getfield      #1239               // Field org/eclipse/jdt/internal/compiler/lookup/SourceTypeBinding.scope:Lorg/eclipse/jdt/internal/compiler/lookup/ClassScope;
      60: invokevirtual #1251               // Method org/eclipse/jdt/internal/compiler/lookup/ClassScope.referenceType:()Lorg/eclipse/jdt/internal/compiler/ast/TypeDeclaration;
      63: invokevirtual #1255               // Method org/eclipse/jdt/internal/compiler/problem/ProblemReporter.noMoreAvailableSpaceInConstantPool:(Lorg/eclipse/jdt/internal/compiler/ast/TypeDeclaration;)V
      66: aload_0
      67: getfield      #1202               // Field offsets:[I
      70: arraylength
      71: istore        4
      73: iload         4
      75: iload_3
      76: if_icmpgt     100
      79: aload_0
      80: getfield      #1202               // Field offsets:[I
      83: iconst_0
      84: aload_0
      85: iload_3
      86: iconst_2
      87: imul
      88: newarray       int
      90: dup_x1
      91: putfield      #1202               // Field offsets:[I
      94: iconst_0
      95: iload         4
      97: invokestatic  #1225               // Method java/lang/System.arraycopy:(Ljava/lang/Object;ILjava/lang/Object;II)V
     100: aload_0
     101: getfield      #1202               // Field offsets:[I
     104: iload_3
     105: aload_0
     106: getfield      #1218               // Field currentOffset:I
     109: iastore
     110: aload_0
     111: bipush        8
     113: invokevirtual #1261               // Method writeU1:(I)V
     116: aload_0
     117: getfield      #1218               // Field currentOffset:I
     120: istore        5
     122: aload_0
     123: getfield      #1218               // Field currentOffset:I
     126: iconst_2
     127: iadd
     128: aload_0
     129: getfield      #1213               // Field poolContent:[B
     132: arraylength
     133: if_icmplt     141
     136: aload_0
     137: iconst_2
     138: invokespecial #1264               // Method resizePoolContents:(I)V
     141: aload_0
     142: dup
     143: getfield      #1218               // Field currentOffset:I
     146: iconst_2
     147: iadd
     148: putfield      #1218               // Field currentOffset:I
     151: aload_0
     152: aload_2
     153: aload_1
     154: invokevirtual #1310               // Method literalIndex:([B[C)I
     157: istore        6
     159: aload_0
     160: getfield      #1213               // Field poolContent:[B
     163: iload         5
     165: iinc          5, 1
     168: iload         6
     170: bipush        8
     172: ishr
     173: i2b
     174: bastore
     175: aload_0
     176: getfield      #1213               // Field poolContent:[B
     179: iload         5
     181: iload         6
     183: i2b
     184: bastore
     185: iload_3
     186: ireturn

  public int literalIndex(double);
    Code:
       0: aload_0
       1: getfield      #1315               // Field doubleCache:Lorg/eclipse/jdt/internal/compiler/codegen/DoubleCache;
       4: ifnonnull     19
       7: aload_0
       8: new           #1317               // class org/eclipse/jdt/internal/compiler/codegen/DoubleCache
      11: dup
      12: iconst_5
      13: invokespecial #1319               // Method org/eclipse/jdt/internal/compiler/codegen/DoubleCache."<init>":(I)V
      16: putfield      #1315               // Field doubleCache:Lorg/eclipse/jdt/internal/compiler/codegen/DoubleCache;
      19: aload_0
      20: getfield      #1315               // Field doubleCache:Lorg/eclipse/jdt/internal/compiler/codegen/DoubleCache;
      23: dload_1
      24: aload_0
      25: getfield      #1183               // Field currentIndex:I
      28: invokevirtual #1320               // Method org/eclipse/jdt/internal/compiler/codegen/DoubleCache.putIfAbsent:(DI)I
      31: dup
      32: istore_3
      33: ifge          347
      36: iload_3
      37: ineg
      38: dup
      39: istore_3
      40: ldc_w         #1234               // int 65535
      43: if_icmple     75
      46: aload_0
      47: getfield      #1220               // Field classFile:Lorg/eclipse/jdt/internal/compiler/ClassFile;
      50: getfield      #1235               // Field org/eclipse/jdt/internal/compiler/ClassFile.referenceBinding:Lorg/eclipse/jdt/internal/compiler/lookup/SourceTypeBinding;
      53: getfield      #1239               // Field org/eclipse/jdt/internal/compiler/lookup/SourceTypeBinding.scope:Lorg/eclipse/jdt/internal/compiler/lookup/ClassScope;
      56: invokevirtual #1245               // Method org/eclipse/jdt/internal/compiler/lookup/ClassScope.problemReporter:()Lorg/eclipse/jdt/internal/compiler/problem/ProblemReporter;
      59: aload_0
      60: getfield      #1220               // Field classFile:Lorg/eclipse/jdt/internal/compiler/ClassFile;
      63: getfield      #1235               // Field org/eclipse/jdt/internal/compiler/ClassFile.referenceBinding:Lorg/eclipse/jdt/internal/compiler/lookup/SourceTypeBinding;
      66: getfield      #1239               // Field org/eclipse/jdt/internal/compiler/lookup/SourceTypeBinding.scope:Lorg/eclipse/jdt/internal/compiler/lookup/ClassScope;
      69: invokevirtual #1251               // Method org/eclipse/jdt/internal/compiler/lookup/ClassScope.referenceType:()Lorg/eclipse/jdt/internal/compiler/ast/TypeDeclaration;
      72: invokevirtual #1255               // Method org/eclipse/jdt/internal/compiler/problem/ProblemReporter.noMoreAvailableSpaceInConstantPool:(Lorg/eclipse/jdt/internal/compiler/ast/TypeDeclaration;)V
      75: aload_0
      76: dup
      77: getfield      #1183               // Field currentIndex:I
      80: iconst_2
      81: iadd
      82: putfield      #1183               // Field currentIndex:I
      85: aload_0
      86: getfield      #1202               // Field offsets:[I
      89: arraylength
      90: istore        4
      92: iload         4
      94: iload_3
      95: if_icmpgt     119
      98: aload_0
      99: getfield      #1202               // Field offsets:[I
     102: iconst_0
     103: aload_0
     104: iload_3
     105: iconst_2
     106: imul
     107: newarray       int
     109: dup_x1
     110: putfield      #1202               // Field offsets:[I
     113: iconst_0
     114: iload         4
     116: invokestatic  #1225               // Method java/lang/System.arraycopy:(Ljava/lang/Object;ILjava/lang/Object;II)V
     119: aload_0
     120: getfield      #1202               // Field offsets:[I
     123: iload_3
     124: aload_0
     125: getfield      #1218               // Field currentOffset:I
     128: iastore
     129: aload_0
     130: bipush        6
     132: invokevirtual #1261               // Method writeU1:(I)V
     135: dload_1
     136: invokestatic  #1323               // Method java/lang/Double.doubleToLongBits:(D)J
     139: lstore        5
     141: aload_0
     142: getfield      #1213               // Field poolContent:[B
     145: arraylength
     146: istore        4
     148: aload_0
     149: getfield      #1218               // Field currentOffset:I
     152: bipush        8
     154: iadd
     155: iload         4
     157: if_icmplt     166
     160: aload_0
     161: bipush        8
     163: invokespecial #1264               // Method resizePoolContents:(I)V
     166: aload_0
     167: getfield      #1213               // Field poolContent:[B
     170: aload_0
     171: dup
     172: getfield      #1218               // Field currentOffset:I
     175: dup_x1
     176: iconst_1
     177: iadd
     178: putfield      #1218               // Field currentOffset:I
     181: lload         5
     183: bipush        56
     185: lushr
     186: l2i
     187: i2b
     188: bastore
     189: aload_0
     190: getfield      #1213               // Field poolContent:[B
     193: aload_0
     194: dup
     195: getfield      #1218               // Field currentOffset:I
     198: dup_x1
     199: iconst_1
     200: iadd
     201: putfield      #1218               // Field currentOffset:I
     204: lload         5
     206: bipush        48
     208: lushr
     209: l2i
     210: i2b
     211: bastore
     212: aload_0
     213: getfield      #1213               // Field poolContent:[B
     216: aload_0
     217: dup
     218: getfield      #1218               // Field currentOffset:I
     221: dup_x1
     222: iconst_1
     223: iadd
     224: putfield      #1218               // Field currentOffset:I
     227: lload         5
     229: bipush        40
     231: lushr
     232: l2i
     233: i2b
     234: bastore
     235: aload_0
     236: getfield      #1213               // Field poolContent:[B
     239: aload_0
     240: dup
     241: getfield      #1218               // Field currentOffset:I
     244: dup_x1
     245: iconst_1
     246: iadd
     247: putfield      #1218               // Field currentOffset:I
     250: lload         5
     252: bipush        32
     254: lushr
     255: l2i
     256: i2b
     257: bastore
     258: aload_0
     259: getfield      #1213               // Field poolContent:[B
     262: aload_0
     263: dup
     264: getfield      #1218               // Field currentOffset:I
     267: dup_x1
     268: iconst_1
     269: iadd
     270: putfield      #1218               // Field currentOffset:I
     273: lload         5
     275: bipush        24
     277: lushr
     278: l2i
     279: i2b
     280: bastore
     281: aload_0
     282: getfield      #1213               // Field poolContent:[B
     285: aload_0
     286: dup
     287: getfield      #1218               // Field currentOffset:I
     290: dup_x1
     291: iconst_1
     292: iadd
     293: putfield      #1218               // Field currentOffset:I
     296: lload         5
     298: bipush        16
     300: lushr
     301: l2i
     302: i2b
     303: bastore
     304: aload_0
     305: getfield      #1213               // Field poolContent:[B
     308: aload_0
     309: dup
     310: getfield      #1218               // Field currentOffset:I
     313: dup_x1
     314: iconst_1
     315: iadd
     316: putfield      #1218               // Field currentOffset:I
     319: lload         5
     321: bipush        8
     323: lushr
     324: l2i
     325: i2b
     326: bastore
     327: aload_0
     328: getfield      #1213               // Field poolContent:[B
     331: aload_0
     332: dup
     333: getfield      #1218               // Field currentOffset:I
     336: dup_x1
     337: iconst_1
     338: iadd
     339: putfield      #1218               // Field currentOffset:I
     342: lload         5
     344: l2i
     345: i2b
     346: bastore
     347: iload_3
     348: ireturn

  public int literalIndex(float);
    Code:
       0: aload_0
       1: getfield      #1332               // Field floatCache:Lorg/eclipse/jdt/internal/compiler/codegen/FloatCache;
       4: ifnonnull     19
       7: aload_0
       8: new           #1334               // class org/eclipse/jdt/internal/compiler/codegen/FloatCache
      11: dup
      12: iconst_3
      13: invokespecial #1336               // Method org/eclipse/jdt/internal/compiler/codegen/FloatCache."<init>":(I)V
      16: putfield      #1332               // Field floatCache:Lorg/eclipse/jdt/internal/compiler/codegen/FloatCache;
      19: aload_0
      20: getfield      #1332               // Field floatCache:Lorg/eclipse/jdt/internal/compiler/codegen/FloatCache;
      23: fload_1
      24: aload_0
      25: getfield      #1183               // Field currentIndex:I
      28: invokevirtual #1337               // Method org/eclipse/jdt/internal/compiler/codegen/FloatCache.putIfAbsent:(FI)I
      31: dup
      32: istore_2
      33: ifge          241
      36: iload_2
      37: ineg
      38: dup
      39: istore_2
      40: ldc_w         #1234               // int 65535
      43: if_icmple     75
      46: aload_0
      47: getfield      #1220               // Field classFile:Lorg/eclipse/jdt/internal/compiler/ClassFile;
      50: getfield      #1235               // Field org/eclipse/jdt/internal/compiler/ClassFile.referenceBinding:Lorg/eclipse/jdt/internal/compiler/lookup/SourceTypeBinding;
      53: getfield      #1239               // Field org/eclipse/jdt/internal/compiler/lookup/SourceTypeBinding.scope:Lorg/eclipse/jdt/internal/compiler/lookup/ClassScope;
      56: invokevirtual #1245               // Method org/eclipse/jdt/internal/compiler/lookup/ClassScope.problemReporter:()Lorg/eclipse/jdt/internal/compiler/problem/ProblemReporter;
      59: aload_0
      60: getfield      #1220               // Field classFile:Lorg/eclipse/jdt/internal/compiler/ClassFile;
      63: getfield      #1235               // Field org/eclipse/jdt/internal/compiler/ClassFile.referenceBinding:Lorg/eclipse/jdt/internal/compiler/lookup/SourceTypeBinding;
      66: getfield      #1239               // Field org/eclipse/jdt/internal/compiler/lookup/SourceTypeBinding.scope:Lorg/eclipse/jdt/internal/compiler/lookup/ClassScope;
      69: invokevirtual #1251               // Method org/eclipse/jdt/internal/compiler/lookup/ClassScope.referenceType:()Lorg/eclipse/jdt/internal/compiler/ast/TypeDeclaration;
      72: invokevirtual #1255               // Method org/eclipse/jdt/internal/compiler/problem/ProblemReporter.noMoreAvailableSpaceInConstantPool:(Lorg/eclipse/jdt/internal/compiler/ast/TypeDeclaration;)V
      75: aload_0
      76: dup
      77: getfield      #1183               // Field currentIndex:I
      80: iconst_1
      81: iadd
      82: putfield      #1183               // Field currentIndex:I
      85: aload_0
      86: getfield      #1202               // Field offsets:[I
      89: arraylength
      90: istore_3
      91: iload_3
      92: iload_2
      93: if_icmpgt     116
      96: aload_0
      97: getfield      #1202               // Field offsets:[I
     100: iconst_0
     101: aload_0
     102: iload_2
     103: iconst_2
     104: imul
     105: newarray       int
     107: dup_x1
     108: putfield      #1202               // Field offsets:[I
     111: iconst_0
     112: iload_3
     113: invokestatic  #1225               // Method java/lang/System.arraycopy:(Ljava/lang/Object;ILjava/lang/Object;II)V
     116: aload_0
     117: getfield      #1202               // Field offsets:[I
     120: iload_2
     121: aload_0
     122: getfield      #1218               // Field currentOffset:I
     125: iastore
     126: aload_0
     127: iconst_4
     128: invokevirtual #1261               // Method writeU1:(I)V
     131: fload_1
     132: invokestatic  #1340               // Method java/lang/Float.floatToIntBits:(F)I
     135: istore        4
     137: aload_0
     138: getfield      #1218               // Field currentOffset:I
     141: iconst_4
     142: iadd
     143: aload_0
     144: getfield      #1213               // Field poolContent:[B
     147: arraylength
     148: if_icmplt     156
     151: aload_0
     152: iconst_4
     153: invokespecial #1264               // Method resizePoolContents:(I)V
     156: aload_0
     157: getfield      #1213               // Field poolContent:[B
     160: aload_0
     161: dup
     162: getfield      #1218               // Field currentOffset:I
     165: dup_x1
     166: iconst_1
     167: iadd
     168: putfield      #1218               // Field currentOffset:I
     171: iload         4
     173: bipush        24
     175: iushr
     176: i2b
     177: bastore
     178: aload_0
     179: getfield      #1213               // Field poolContent:[B
     182: aload_0
     183: dup
     184: getfield      #1218               // Field currentOffset:I
     187: dup_x1
     188: iconst_1
     189: iadd
     190: putfield      #1218               // Field currentOffset:I
     193: iload         4
     195: bipush        16
     197: iushr
     198: i2b
     199: bastore
     200: aload_0
     201: getfield      #1213               // Field poolContent:[B
     204: aload_0
     205: dup
     206: getfield      #1218               // Field currentOffset:I
     209: dup_x1
     210: iconst_1
     211: iadd
     212: putfield      #1218               // Field currentOffset:I
     215: iload         4
     217: bipush        8
     219: iushr
     220: i2b
     221: bastore
     222: aload_0
     223: getfield      #1213               // Field poolContent:[B
     226: aload_0
     227: dup
     228: getfield      #1218               // Field currentOffset:I
     231: dup_x1
     232: iconst_1
     233: iadd
     234: putfield      #1218               // Field currentOffset:I
     237: iload         4
     239: i2b
     240: bastore
     241: iload_2
     242: ireturn

  public int literalIndex(int);
    Code:
       0: aload_0
       1: getfield      #1346               // Field intCache:Lorg/eclipse/jdt/internal/compiler/codegen/IntegerCache;
       4: ifnonnull     21
       7: aload_0
       8: new           #1348               // class org/eclipse/jdt/internal/compiler/codegen/IntegerCache
      11: dup
      12: sipush        248
      15: invokespecial #1350               // Method org/eclipse/jdt/internal/compiler/codegen/IntegerCache."<init>":(I)V
      18: putfield      #1346               // Field intCache:Lorg/eclipse/jdt/internal/compiler/codegen/IntegerCache;
      21: aload_0
      22: getfield      #1346               // Field intCache:Lorg/eclipse/jdt/internal/compiler/codegen/IntegerCache;
      25: iload_1
      26: aload_0
      27: getfield      #1183               // Field currentIndex:I
      30: invokevirtual #1351               // Method org/eclipse/jdt/internal/compiler/codegen/IntegerCache.putIfAbsent:(II)I
      33: dup
      34: istore_2
      35: ifge          233
      38: aload_0
      39: dup
      40: getfield      #1183               // Field currentIndex:I
      43: iconst_1
      44: iadd
      45: putfield      #1183               // Field currentIndex:I
      48: iload_2
      49: ineg
      50: dup
      51: istore_2
      52: ldc_w         #1234               // int 65535
      55: if_icmple     87
      58: aload_0
      59: getfield      #1220               // Field classFile:Lorg/eclipse/jdt/internal/compiler/ClassFile;
      62: getfield      #1235               // Field org/eclipse/jdt/internal/compiler/ClassFile.referenceBinding:Lorg/eclipse/jdt/internal/compiler/lookup/SourceTypeBinding;
      65: getfield      #1239               // Field org/eclipse/jdt/internal/compiler/lookup/SourceTypeBinding.scope:Lorg/eclipse/jdt/internal/compiler/lookup/ClassScope;
      68: invokevirtual #1245               // Method org/eclipse/jdt/internal/compiler/lookup/ClassScope.problemReporter:()Lorg/eclipse/jdt/internal/compiler/problem/ProblemReporter;
      71: aload_0
      72: getfield      #1220               // Field classFile:Lorg/eclipse/jdt/internal/compiler/ClassFile;
      75: getfield      #1235               // Field org/eclipse/jdt/internal/compiler/ClassFile.referenceBinding:Lorg/eclipse/jdt/internal/compiler/lookup/SourceTypeBinding;
      78: getfield      #1239               // Field org/eclipse/jdt/internal/compiler/lookup/SourceTypeBinding.scope:Lorg/eclipse/jdt/internal/compiler/lookup/ClassScope;
      81: invokevirtual #1251               // Method org/eclipse/jdt/internal/compiler/lookup/ClassScope.referenceType:()Lorg/eclipse/jdt/internal/compiler/ast/TypeDeclaration;
      84: invokevirtual #1255               // Method org/eclipse/jdt/internal/compiler/problem/ProblemReporter.noMoreAvailableSpaceInConstantPool:(Lorg/eclipse/jdt/internal/compiler/ast/TypeDeclaration;)V
      87: aload_0
      88: getfield      #1202               // Field offsets:[I
      91: arraylength
      92: istore_3
      93: iload_3
      94: iload_2
      95: if_icmpgt     118
      98: aload_0
      99: getfield      #1202               // Field offsets:[I
     102: iconst_0
     103: aload_0
     104: iload_2
     105: iconst_2
     106: imul
     107: newarray       int
     109: dup_x1
     110: putfield      #1202               // Field offsets:[I
     113: iconst_0
     114: iload_3
     115: invokestatic  #1225               // Method java/lang/System.arraycopy:(Ljava/lang/Object;ILjava/lang/Object;II)V
     118: aload_0
     119: getfield      #1202               // Field offsets:[I
     122: iload_2
     123: aload_0
     124: getfield      #1218               // Field currentOffset:I
     127: iastore
     128: aload_0
     129: iconst_3
     130: invokevirtual #1261               // Method writeU1:(I)V
     133: aload_0
     134: getfield      #1218               // Field currentOffset:I
     137: iconst_4
     138: iadd
     139: aload_0
     140: getfield      #1213               // Field poolContent:[B
     143: arraylength
     144: if_icmplt     152
     147: aload_0
     148: iconst_4
     149: invokespecial #1264               // Method resizePoolContents:(I)V
     152: aload_0
     153: getfield      #1213               // Field poolContent:[B
     156: aload_0
     157: dup
     158: getfield      #1218               // Field currentOffset:I
     161: dup_x1
     162: iconst_1
     163: iadd
     164: putfield      #1218               // Field currentOffset:I
     167: iload_1
     168: bipush        24
     170: iushr
     171: i2b
     172: bastore
     173: aload_0
     174: getfield      #1213               // Field poolContent:[B
     177: aload_0
     178: dup
     179: getfield      #1218               // Field currentOffset:I
     182: dup_x1
     183: iconst_1
     184: iadd
     185: putfield      #1218               // Field currentOffset:I
     188: iload_1
     189: bipush        16
     191: iushr
     192: i2b
     193: bastore
     194: aload_0
     195: getfield      #1213               // Field poolContent:[B
     198: aload_0
     199: dup
     200: getfield      #1218               // Field currentOffset:I
     203: dup_x1
     204: iconst_1
     205: iadd
     206: putfield      #1218               // Field currentOffset:I
     209: iload_1
     210: bipush        8
     212: iushr
     213: i2b
     214: bastore
     215: aload_0
     216: getfield      #1213               // Field poolContent:[B
     219: aload_0
     220: dup
     221: getfield      #1218               // Field currentOffset:I
     224: dup_x1
     225: iconst_1
     226: iadd
     227: putfield      #1218               // Field currentOffset:I
     230: iload_1
     231: i2b
     232: bastore
     233: iload_2
     234: ireturn

  public int literalIndex(long);
    Code:
       0: aload_0
       1: getfield      #1355               // Field longCache:Lorg/eclipse/jdt/internal/compiler/codegen/LongCache;
       4: ifnonnull     19
       7: aload_0
       8: new           #1357               // class org/eclipse/jdt/internal/compiler/codegen/LongCache
      11: dup
      12: iconst_5
      13: invokespecial #1359               // Method org/eclipse/jdt/internal/compiler/codegen/LongCache."<init>":(I)V
      16: putfield      #1355               // Field longCache:Lorg/eclipse/jdt/internal/compiler/codegen/LongCache;
      19: aload_0
      20: getfield      #1355               // Field longCache:Lorg/eclipse/jdt/internal/compiler/codegen/LongCache;
      23: lload_1
      24: aload_0
      25: getfield      #1183               // Field currentIndex:I
      28: invokevirtual #1360               // Method org/eclipse/jdt/internal/compiler/codegen/LongCache.putIfAbsent:(JI)I
      31: dup
      32: istore_3
      33: ifge          328
      36: iload_3
      37: ineg
      38: dup
      39: istore_3
      40: ldc_w         #1234               // int 65535
      43: if_icmple     75
      46: aload_0
      47: getfield      #1220               // Field classFile:Lorg/eclipse/jdt/internal/compiler/ClassFile;
      50: getfield      #1235               // Field org/eclipse/jdt/internal/compiler/ClassFile.referenceBinding:Lorg/eclipse/jdt/internal/compiler/lookup/SourceTypeBinding;
      53: getfield      #1239               // Field org/eclipse/jdt/internal/compiler/lookup/SourceTypeBinding.scope:Lorg/eclipse/jdt/internal/compiler/lookup/ClassScope;
      56: invokevirtual #1245               // Method org/eclipse/jdt/internal/compiler/lookup/ClassScope.problemReporter:()Lorg/eclipse/jdt/internal/compiler/problem/ProblemReporter;
      59: aload_0
      60: getfield      #1220               // Field classFile:Lorg/eclipse/jdt/internal/compiler/ClassFile;
      63: getfield      #1235               // Field org/eclipse/jdt/internal/compiler/ClassFile.referenceBinding:Lorg/eclipse/jdt/internal/compiler/lookup/SourceTypeBinding;
      66: getfield      #1239               // Field org/eclipse/jdt/internal/compiler/lookup/SourceTypeBinding.scope:Lorg/eclipse/jdt/internal/compiler/lookup/ClassScope;
      69: invokevirtual #1251               // Method org/eclipse/jdt/internal/compiler/lookup/ClassScope.referenceType:()Lorg/eclipse/jdt/internal/compiler/ast/TypeDeclaration;
      72: invokevirtual #1255               // Method org/eclipse/jdt/internal/compiler/problem/ProblemReporter.noMoreAvailableSpaceInConstantPool:(Lorg/eclipse/jdt/internal/compiler/ast/TypeDeclaration;)V
      75: aload_0
      76: dup
      77: getfield      #1183               // Field currentIndex:I
      80: iconst_2
      81: iadd
      82: putfield      #1183               // Field currentIndex:I
      85: aload_0
      86: getfield      #1202               // Field offsets:[I
      89: arraylength
      90: istore        4
      92: iload         4
      94: iload_3
      95: if_icmpgt     119
      98: aload_0
      99: getfield      #1202               // Field offsets:[I
     102: iconst_0
     103: aload_0
     104: iload_3
     105: iconst_2
     106: imul
     107: newarray       int
     109: dup_x1
     110: putfield      #1202               // Field offsets:[I
     113: iconst_0
     114: iload         4
     116: invokestatic  #1225               // Method java/lang/System.arraycopy:(Ljava/lang/Object;ILjava/lang/Object;II)V
     119: aload_0
     120: getfield      #1202               // Field offsets:[I
     123: iload_3
     124: aload_0
     125: getfield      #1218               // Field currentOffset:I
     128: iastore
     129: aload_0
     130: iconst_5
     131: invokevirtual #1261               // Method writeU1:(I)V
     134: aload_0
     135: getfield      #1218               // Field currentOffset:I
     138: bipush        8
     140: iadd
     141: aload_0
     142: getfield      #1213               // Field poolContent:[B
     145: arraylength
     146: if_icmplt     155
     149: aload_0
     150: bipush        8
     152: invokespecial #1264               // Method resizePoolContents:(I)V
     155: aload_0
     156: getfield      #1213               // Field poolContent:[B
     159: aload_0
     160: dup
     161: getfield      #1218               // Field currentOffset:I
     164: dup_x1
     165: iconst_1
     166: iadd
     167: putfield      #1218               // Field currentOffset:I
     170: lload_1
     171: bipush        56
     173: lushr
     174: l2i
     175: i2b
     176: bastore
     177: aload_0
     178: getfield      #1213               // Field poolContent:[B
     181: aload_0
     182: dup
     183: getfield      #1218               // Field currentOffset:I
     186: dup_x1
     187: iconst_1
     188: iadd
     189: putfield      #1218               // Field currentOffset:I
     192: lload_1
     193: bipush        48
     195: lushr
     196: l2i
     197: i2b
     198: bastore
     199: aload_0
     200: getfield      #1213               // Field poolContent:[B
     203: aload_0
     204: dup
     205: getfield      #1218               // Field currentOffset:I
     208: dup_x1
     209: iconst_1
     210: iadd
     211: putfield      #1218               // Field currentOffset:I
     214: lload_1
     215: bipush        40
     217: lushr
     218: l2i
     219: i2b
     220: bastore
     221: aload_0
     222: getfield      #1213               // Field poolContent:[B
     225: aload_0
     226: dup
     227: getfield      #1218               // Field currentOffset:I
     230: dup_x1
     231: iconst_1
     232: iadd
     233: putfield      #1218               // Field currentOffset:I
     236: lload_1
     237: bipush        32
     239: lushr
     240: l2i
     241: i2b
     242: bastore
     243: aload_0
     244: getfield      #1213               // Field poolContent:[B
     247: aload_0
     248: dup
     249: getfield      #1218               // Field currentOffset:I
     252: dup_x1
     253: iconst_1
     254: iadd
     255: putfield      #1218               // Field currentOffset:I
     258: lload_1
     259: bipush        24
     261: lushr
     262: l2i
     263: i2b
     264: bastore
     265: aload_0
     266: getfield      #1213               // Field poolContent:[B
     269: aload_0
     270: dup
     271: getfield      #1218               // Field currentOffset:I
     274: dup_x1
     275: iconst_1
     276: iadd
     277: putfield      #1218               // Field currentOffset:I
     280: lload_1
     281: bipush        16
     283: lushr
     284: l2i
     285: i2b
     286: bastore
     287: aload_0
     288: getfield      #1213               // Field poolContent:[B
     291: aload_0
     292: dup
     293: getfield      #1218               // Field currentOffset:I
     296: dup_x1
     297: iconst_1
     298: iadd
     299: putfield      #1218               // Field currentOffset:I
     302: lload_1
     303: bipush        8
     305: lushr
     306: l2i
     307: i2b
     308: bastore
     309: aload_0
     310: getfield      #1213               // Field poolContent:[B
     313: aload_0
     314: dup
     315: getfield      #1218               // Field currentOffset:I
     318: dup_x1
     319: iconst_1
     320: iadd
     321: putfield      #1218               // Field currentOffset:I
     324: lload_1
     325: l2i
     326: i2b
     327: bastore
     328: iload_3
     329: ireturn

  public int literalIndex(java.lang.String);
    Code:
       0: aload_1
       1: invokevirtual #293                // Method java/lang/String.toCharArray:()[C
       4: astore_3
       5: aload_0
       6: getfield      #1191               // Field stringCache:Lorg/eclipse/jdt/internal/compiler/codegen/CharArrayCache;
       9: aload_3
      10: aload_0
      11: getfield      #1183               // Field currentIndex:I
      14: invokevirtual #1230               // Method org/eclipse/jdt/internal/compiler/codegen/CharArrayCache.putIfAbsent:([CI)I
      17: dup
      18: istore_2
      19: ifge          189
      22: aload_0
      23: dup
      24: getfield      #1183               // Field currentIndex:I
      27: iconst_1
      28: iadd
      29: putfield      #1183               // Field currentIndex:I
      32: iload_2
      33: ineg
      34: dup
      35: istore_2
      36: ldc_w         #1234               // int 65535
      39: if_icmple     71
      42: aload_0
      43: getfield      #1220               // Field classFile:Lorg/eclipse/jdt/internal/compiler/ClassFile;
      46: getfield      #1235               // Field org/eclipse/jdt/internal/compiler/ClassFile.referenceBinding:Lorg/eclipse/jdt/internal/compiler/lookup/SourceTypeBinding;
      49: getfield      #1239               // Field org/eclipse/jdt/internal/compiler/lookup/SourceTypeBinding.scope:Lorg/eclipse/jdt/internal/compiler/lookup/ClassScope;
      52: invokevirtual #1245               // Method org/eclipse/jdt/internal/compiler/lookup/ClassScope.problemReporter:()Lorg/eclipse/jdt/internal/compiler/problem/ProblemReporter;
      55: aload_0
      56: getfield      #1220               // Field classFile:Lorg/eclipse/jdt/internal/compiler/ClassFile;
      59: getfield      #1235               // Field org/eclipse/jdt/internal/compiler/ClassFile.referenceBinding:Lorg/eclipse/jdt/internal/compiler/lookup/SourceTypeBinding;
      62: getfield      #1239               // Field org/eclipse/jdt/internal/compiler/lookup/SourceTypeBinding.scope:Lorg/eclipse/jdt/internal/compiler/lookup/ClassScope;
      65: invokevirtual #1251               // Method org/eclipse/jdt/internal/compiler/lookup/ClassScope.referenceType:()Lorg/eclipse/jdt/internal/compiler/ast/TypeDeclaration;
      68: invokevirtual #1255               // Method org/eclipse/jdt/internal/compiler/problem/ProblemReporter.noMoreAvailableSpaceInConstantPool:(Lorg/eclipse/jdt/internal/compiler/ast/TypeDeclaration;)V
      71: aload_0
      72: getfield      #1202               // Field offsets:[I
      75: arraylength
      76: istore        4
      78: iload         4
      80: iload_2
      81: if_icmpgt     105
      84: aload_0
      85: getfield      #1202               // Field offsets:[I
      88: iconst_0
      89: aload_0
      90: iload_2
      91: iconst_2
      92: imul
      93: newarray       int
      95: dup_x1
      96: putfield      #1202               // Field offsets:[I
      99: iconst_0
     100: iload         4
     102: invokestatic  #1225               // Method java/lang/System.arraycopy:(Ljava/lang/Object;ILjava/lang/Object;II)V
     105: aload_0
     106: getfield      #1202               // Field offsets:[I
     109: iload_2
     110: aload_0
     111: getfield      #1218               // Field currentOffset:I
     114: iastore
     115: aload_0
     116: bipush        8
     118: invokevirtual #1261               // Method writeU1:(I)V
     121: aload_0
     122: getfield      #1218               // Field currentOffset:I
     125: istore        5
     127: aload_0
     128: getfield      #1218               // Field currentOffset:I
     131: iconst_2
     132: iadd
     133: aload_0
     134: getfield      #1213               // Field poolContent:[B
     137: arraylength
     138: if_icmplt     146
     141: aload_0
     142: iconst_2
     143: invokespecial #1264               // Method resizePoolContents:(I)V
     146: aload_0
     147: dup
     148: getfield      #1218               // Field currentOffset:I
     151: iconst_2
     152: iadd
     153: putfield      #1218               // Field currentOffset:I
     156: aload_0
     157: aload_3
     158: invokevirtual #1295               // Method literalIndex:([C)I
     161: istore        6
     163: aload_0
     164: getfield      #1213               // Field poolContent:[B
     167: iload         5
     169: iinc          5, 1
     172: iload         6
     174: bipush        8
     176: ishr
     177: i2b
     178: bastore
     179: aload_0
     180: getfield      #1213               // Field poolContent:[B
     183: iload         5
     185: iload         6
     187: i2b
     188: bastore
     189: iload_2
     190: ireturn

  public int literalIndexForType(char[]);
    Code:
       0: aload_0
       1: getfield      #1198               // Field classCache:Lorg/eclipse/jdt/internal/compiler/codegen/CharArrayCache;
       4: aload_1
       5: aload_0
       6: getfield      #1183               // Field currentIndex:I
       9: invokevirtual #1230               // Method org/eclipse/jdt/internal/compiler/codegen/CharArrayCache.putIfAbsent:([CI)I
      12: dup
      13: istore_2
      14: ifge          181
      17: aload_0
      18: dup
      19: getfield      #1183               // Field currentIndex:I
      22: iconst_1
      23: iadd
      24: putfield      #1183               // Field currentIndex:I
      27: iload_2
      28: ineg
      29: dup
      30: istore_2
      31: ldc_w         #1234               // int 65535
      34: if_icmple     66
      37: aload_0
      38: getfield      #1220               // Field classFile:Lorg/eclipse/jdt/internal/compiler/ClassFile;
      41: getfield      #1235               // Field org/eclipse/jdt/internal/compiler/ClassFile.referenceBinding:Lorg/eclipse/jdt/internal/compiler/lookup/SourceTypeBinding;
      44: getfield      #1239               // Field org/eclipse/jdt/internal/compiler/lookup/SourceTypeBinding.scope:Lorg/eclipse/jdt/internal/compiler/lookup/ClassScope;
      47: invokevirtual #1245               // Method org/eclipse/jdt/internal/compiler/lookup/ClassScope.problemReporter:()Lorg/eclipse/jdt/internal/compiler/problem/ProblemReporter;
      50: aload_0
      51: getfield      #1220               // Field classFile:Lorg/eclipse/jdt/internal/compiler/ClassFile;
      54: getfield      #1235               // Field org/eclipse/jdt/internal/compiler/ClassFile.referenceBinding:Lorg/eclipse/jdt/internal/compiler/lookup/SourceTypeBinding;
      57: getfield      #1239               // Field org/eclipse/jdt/internal/compiler/lookup/SourceTypeBinding.scope:Lorg/eclipse/jdt/internal/compiler/lookup/ClassScope;
      60: invokevirtual #1251               // Method org/eclipse/jdt/internal/compiler/lookup/ClassScope.referenceType:()Lorg/eclipse/jdt/internal/compiler/ast/TypeDeclaration;
      63: invokevirtual #1255               // Method org/eclipse/jdt/internal/compiler/problem/ProblemReporter.noMoreAvailableSpaceInConstantPool:(Lorg/eclipse/jdt/internal/compiler/ast/TypeDeclaration;)V
      66: aload_0
      67: getfield      #1202               // Field offsets:[I
      70: arraylength
      71: istore_3
      72: iload_3
      73: iload_2
      74: if_icmpgt     97
      77: aload_0
      78: getfield      #1202               // Field offsets:[I
      81: iconst_0
      82: aload_0
      83: iload_2
      84: iconst_2
      85: imul
      86: newarray       int
      88: dup_x1
      89: putfield      #1202               // Field offsets:[I
      92: iconst_0
      93: iload_3
      94: invokestatic  #1225               // Method java/lang/System.arraycopy:(Ljava/lang/Object;ILjava/lang/Object;II)V
      97: aload_0
      98: getfield      #1202               // Field offsets:[I
     101: iload_2
     102: aload_0
     103: getfield      #1218               // Field currentOffset:I
     106: iastore
     107: aload_0
     108: bipush        7
     110: invokevirtual #1261               // Method writeU1:(I)V
     113: aload_0
     114: getfield      #1218               // Field currentOffset:I
     117: istore        4
     119: aload_0
     120: getfield      #1218               // Field currentOffset:I
     123: iconst_2
     124: iadd
     125: aload_0
     126: getfield      #1213               // Field poolContent:[B
     129: arraylength
     130: if_icmplt     138
     133: aload_0
     134: iconst_2
     135: invokespecial #1264               // Method resizePoolContents:(I)V
     138: aload_0
     139: dup
     140: getfield      #1218               // Field currentOffset:I
     143: iconst_2
     144: iadd
     145: putfield      #1218               // Field currentOffset:I
     148: aload_0
     149: aload_1
     150: invokevirtual #1295               // Method literalIndex:([C)I
     153: istore        5
     155: aload_0
     156: getfield      #1213               // Field poolContent:[B
     159: iload         4
     161: iinc          4, 1
     164: iload         5
     166: bipush        8
     168: ishr
     169: i2b
     170: bastore
     171: aload_0
     172: getfield      #1213               // Field poolContent:[B
     175: iload         4
     177: iload         5
     179: i2b
     180: bastore
     181: iload_2
     182: ireturn

  public int literalIndexForType(org.eclipse.jdt.internal.compiler.lookup.TypeBinding);
    Code:
       0: aload_1
       1: invokevirtual #1274               // Method org/eclipse/jdt/internal/compiler/lookup/TypeBinding.leafComponentType:()Lorg/eclipse/jdt/internal/compiler/lookup/TypeBinding;
       4: astore_2
       5: aload_2
       6: getfield      #1280               // Field org/eclipse/jdt/internal/compiler/lookup/TypeBinding.tagBits:J
       9: ldc2_w        #1284               // long 2048l
      12: land
      13: lconst_0
      14: lcmp
      15: ifeq          26
      18: aload_0
      19: getfield      #1220               // Field classFile:Lorg/eclipse/jdt/internal/compiler/ClassFile;
      22: aload_2
      23: invokestatic  #1286               // Method org/eclipse/jdt/internal/compiler/util/Util.recordNestedType:(Lorg/eclipse/jdt/internal/compiler/ClassFile;Lorg/eclipse/jdt/internal/compiler/lookup/TypeBinding;)V
      26: aload_0
      27: aload_1
      28: invokevirtual #1369               // Method org/eclipse/jdt/internal/compiler/lookup/TypeBinding.constantPoolName:()[C
      31: invokevirtual #1371               // Method literalIndexForType:([C)I
      34: ireturn

  public int literalIndexForMethod(char[], char[], char[], boolean);
    Code:
       0: aload_0
       1: aload_1
       2: aload_2
       3: aload_3
       4: aload_0
       5: getfield      #1183               // Field currentIndex:I
       8: invokespecial #1375               // Method putInCacheIfAbsent:([C[C[CI)I
      11: dup
      12: istore        5
      14: ifge          236
      17: aload_0
      18: dup
      19: getfield      #1183               // Field currentIndex:I
      22: iconst_1
      23: iadd
      24: putfield      #1183               // Field currentIndex:I
      27: iload         5
      29: ineg
      30: dup
      31: istore        5
      33: ldc_w         #1234               // int 65535
      36: if_icmple     68
      39: aload_0
      40: getfield      #1220               // Field classFile:Lorg/eclipse/jdt/internal/compiler/ClassFile;
      43: getfield      #1235               // Field org/eclipse/jdt/internal/compiler/ClassFile.referenceBinding:Lorg/eclipse/jdt/internal/compiler/lookup/SourceTypeBinding;
      46: getfield      #1239               // Field org/eclipse/jdt/internal/compiler/lookup/SourceTypeBinding.scope:Lorg/eclipse/jdt/internal/compiler/lookup/ClassScope;
      49: invokevirtual #1245               // Method org/eclipse/jdt/internal/compiler/lookup/ClassScope.problemReporter:()Lorg/eclipse/jdt/internal/compiler/problem/ProblemReporter;
      52: aload_0
      53: getfield      #1220               // Field classFile:Lorg/eclipse/jdt/internal/compiler/ClassFile;
      56: getfield      #1235               // Field org/eclipse/jdt/internal/compiler/ClassFile.referenceBinding:Lorg/eclipse/jdt/internal/compiler/lookup/SourceTypeBinding;
      59: getfield      #1239               // Field org/eclipse/jdt/internal/compiler/lookup/SourceTypeBinding.scope:Lorg/eclipse/jdt/internal/compiler/lookup/ClassScope;
      62: invokevirtual #1251               // Method org/eclipse/jdt/internal/compiler/lookup/ClassScope.referenceType:()Lorg/eclipse/jdt/internal/compiler/ast/TypeDeclaration;
      65: invokevirtual #1255               // Method org/eclipse/jdt/internal/compiler/problem/ProblemReporter.noMoreAvailableSpaceInConstantPool:(Lorg/eclipse/jdt/internal/compiler/ast/TypeDeclaration;)V
      68: aload_0
      69: getfield      #1202               // Field offsets:[I
      72: arraylength
      73: istore        6
      75: iload         6
      77: iload         5
      79: if_icmpgt     104
      82: aload_0
      83: getfield      #1202               // Field offsets:[I
      86: iconst_0
      87: aload_0
      88: iload         5
      90: iconst_2
      91: imul
      92: newarray       int
      94: dup_x1
      95: putfield      #1202               // Field offsets:[I
      98: iconst_0
      99: iload         6
     101: invokestatic  #1225               // Method java/lang/System.arraycopy:(Ljava/lang/Object;ILjava/lang/Object;II)V
     104: aload_0
     105: getfield      #1202               // Field offsets:[I
     108: iload         5
     110: aload_0
     111: getfield      #1218               // Field currentOffset:I
     114: iastore
     115: aload_0
     116: iload         4
     118: ifeq          126
     121: bipush        11
     123: goto          128
     126: bipush        10
     128: invokevirtual #1261               // Method writeU1:(I)V
     131: aload_0
     132: getfield      #1218               // Field currentOffset:I
     135: istore        7
     137: aload_0
     138: getfield      #1218               // Field currentOffset:I
     141: iconst_4
     142: iadd
     143: aload_0
     144: getfield      #1213               // Field poolContent:[B
     147: arraylength
     148: if_icmplt     156
     151: aload_0
     152: iconst_4
     153: invokespecial #1264               // Method resizePoolContents:(I)V
     156: aload_0
     157: dup
     158: getfield      #1218               // Field currentOffset:I
     161: iconst_4
     162: iadd
     163: putfield      #1218               // Field currentOffset:I
     166: aload_0
     167: aload_1
     168: invokevirtual #1371               // Method literalIndexForType:([C)I
     171: istore        8
     173: aload_0
     174: aload_2
     175: aload_3
     176: invokevirtual #1379               // Method literalIndexForNameAndType:([C[C)I
     179: istore        9
     181: aload_0
     182: getfield      #1213               // Field poolContent:[B
     185: iload         7
     187: iinc          7, 1
     190: iload         8
     192: bipush        8
     194: ishr
     195: i2b
     196: bastore
     197: aload_0
     198: getfield      #1213               // Field poolContent:[B
     201: iload         7
     203: iinc          7, 1
     206: iload         8
     208: i2b
     209: bastore
     210: aload_0
     211: getfield      #1213               // Field poolContent:[B
     214: iload         7
     216: iinc          7, 1
     219: iload         9
     221: bipush        8
     223: ishr
     224: i2b
     225: bastore
     226: aload_0
     227: getfield      #1213               // Field poolContent:[B
     230: iload         7
     232: iload         9
     234: i2b
     235: bastore
     236: iload         5
     238: ireturn

  public int literalIndexForMethod(org.eclipse.jdt.internal.compiler.lookup.TypeBinding, char[], char[], boolean);
    Code:
       0: aload_1
       1: getfield      #1280               // Field org/eclipse/jdt/internal/compiler/lookup/TypeBinding.tagBits:J
       4: ldc2_w        #1284               // long 2048l
       7: land
       8: lconst_0
       9: lcmp
      10: ifeq          21
      13: aload_0
      14: getfield      #1220               // Field classFile:Lorg/eclipse/jdt/internal/compiler/ClassFile;
      17: aload_1
      18: invokestatic  #1286               // Method org/eclipse/jdt/internal/compiler/util/Util.recordNestedType:(Lorg/eclipse/jdt/internal/compiler/ClassFile;Lorg/eclipse/jdt/internal/compiler/lookup/TypeBinding;)V
      21: aload_0
      22: aload_1
      23: invokevirtual #1369               // Method org/eclipse/jdt/internal/compiler/lookup/TypeBinding.constantPoolName:()[C
      26: aload_2
      27: aload_3
      28: iload         4
      30: invokevirtual #1391               // Method literalIndexForMethod:([C[C[CZ)I
      33: ireturn

  public int literalIndexForNameAndType(char[], char[]);
    Code:
       0: aload_0
       1: aload_1
       2: aload_2
       3: aload_0
       4: getfield      #1183               // Field currentIndex:I
       7: invokespecial #1393               // Method putInNameAndTypeCacheIfAbsent:([C[CI)I
      10: dup
      11: istore_3
      12: ifge          218
      15: aload_0
      16: dup
      17: getfield      #1183               // Field currentIndex:I
      20: iconst_1
      21: iadd
      22: putfield      #1183               // Field currentIndex:I
      25: iload_3
      26: ineg
      27: dup
      28: istore_3
      29: ldc_w         #1234               // int 65535
      32: if_icmple     64
      35: aload_0
      36: getfield      #1220               // Field classFile:Lorg/eclipse/jdt/internal/compiler/ClassFile;
      39: getfield      #1235               // Field org/eclipse/jdt/internal/compiler/ClassFile.referenceBinding:Lorg/eclipse/jdt/internal/compiler/lookup/SourceTypeBinding;
      42: getfield      #1239               // Field org/eclipse/jdt/internal/compiler/lookup/SourceTypeBinding.scope:Lorg/eclipse/jdt/internal/compiler/lookup/ClassScope;
      45: invokevirtual #1245               // Method org/eclipse/jdt/internal/compiler/lookup/ClassScope.problemReporter:()Lorg/eclipse/jdt/internal/compiler/problem/ProblemReporter;
      48: aload_0
      49: getfield      #1220               // Field classFile:Lorg/eclipse/jdt/internal/compiler/ClassFile;
      52: getfield      #1235               // Field org/eclipse/jdt/internal/compiler/ClassFile.referenceBinding:Lorg/eclipse/jdt/internal/compiler/lookup/SourceTypeBinding;
      55: getfield      #1239               // Field org/eclipse/jdt/internal/compiler/lookup/SourceTypeBinding.scope:Lorg/eclipse/jdt/internal/compiler/lookup/ClassScope;
      58: invokevirtual #1251               // Method org/eclipse/jdt/internal/compiler/lookup/ClassScope.referenceType:()Lorg/eclipse/jdt/internal/compiler/ast/TypeDeclaration;
      61: invokevirtual #1255               // Method org/eclipse/jdt/internal/compiler/problem/ProblemReporter.noMoreAvailableSpaceInConstantPool:(Lorg/eclipse/jdt/internal/compiler/ast/TypeDeclaration;)V
      64: aload_0
      65: getfield      #1202               // Field offsets:[I
      68: arraylength
      69: istore        4
      71: iload         4
      73: iload_3
      74: if_icmpgt     98
      77: aload_0
      78: getfield      #1202               // Field offsets:[I
      81: iconst_0
      82: aload_0
      83: iload_3
      84: iconst_2
      85: imul
      86: newarray       int
      88: dup_x1
      89: putfield      #1202               // Field offsets:[I
      92: iconst_0
      93: iload         4
      95: invokestatic  #1225               // Method java/lang/System.arraycopy:(Ljava/lang/Object;ILjava/lang/Object;II)V
      98: aload_0
      99: getfield      #1202               // Field offsets:[I
     102: iload_3
     103: aload_0
     104: getfield      #1218               // Field currentOffset:I
     107: iastore
     108: aload_0
     109: bipush        12
     111: invokevirtual #1261               // Method writeU1:(I)V
     114: aload_0
     115: getfield      #1218               // Field currentOffset:I
     118: istore        5
     120: aload_0
     121: getfield      #1218               // Field currentOffset:I
     124: iconst_4
     125: iadd
     126: aload_0
     127: getfield      #1213               // Field poolContent:[B
     130: arraylength
     131: if_icmplt     139
     134: aload_0
     135: iconst_4
     136: invokespecial #1264               // Method resizePoolContents:(I)V
     139: aload_0
     140: dup
     141: getfield      #1218               // Field currentOffset:I
     144: iconst_4
     145: iadd
     146: putfield      #1218               // Field currentOffset:I
     149: aload_0
     150: aload_1
     151: invokevirtual #1295               // Method literalIndex:([C)I
     154: istore        6
     156: aload_0
     157: aload_2
     158: invokevirtual #1295               // Method literalIndex:([C)I
     161: istore        7
     163: aload_0
     164: getfield      #1213               // Field poolContent:[B
     167: iload         5
     169: iinc          5, 1
     172: iload         6
     174: bipush        8
     176: ishr
     177: i2b
     178: bastore
     179: aload_0
     180: getfield      #1213               // Field poolContent:[B
     183: iload         5
     185: iinc          5, 1
     188: iload         6
     190: i2b
     191: bastore
     192: aload_0
     193: getfield      #1213               // Field poolContent:[B
     196: iload         5
     198: iinc          5, 1
     201: iload         7
     203: bipush        8
     205: ishr
     206: i2b
     207: bastore
     208: aload_0
     209: getfield      #1213               // Field poolContent:[B
     212: iload         5
     214: iload         7
     216: i2b
     217: bastore
     218: iload_3
     219: ireturn

  public int literalIndexForMethodHandle(org.eclipse.jdt.internal.compiler.lookup.MethodBinding);
    Code:
       0: aload_1
       1: getfield      #1400               // Field org/eclipse/jdt/internal/compiler/lookup/MethodBinding.declaringClass:Lorg/eclipse/jdt/internal/compiler/lookup/ReferenceBinding;
       4: invokevirtual #1405               // Method org/eclipse/jdt/internal/compiler/lookup/ReferenceBinding.isInterface:()Z
       7: istore_2
       8: iload_2
       9: ifeq          41
      12: aload_1
      13: invokevirtual #1409               // Method org/eclipse/jdt/internal/compiler/lookup/MethodBinding.isStatic:()Z
      16: ifeq          24
      19: bipush        6
      21: goto          78
      24: aload_1
      25: invokevirtual #1412               // Method org/eclipse/jdt/internal/compiler/lookup/MethodBinding.isPrivate:()Z
      28: ifeq          36
      31: bipush        7
      33: goto          78
      36: bipush        9
      38: goto          78
      41: aload_1
      42: invokevirtual #1415               // Method org/eclipse/jdt/internal/compiler/lookup/MethodBinding.isConstructor:()Z
      45: ifeq          53
      48: bipush        8
      50: goto          78
      53: aload_1
      54: invokevirtual #1409               // Method org/eclipse/jdt/internal/compiler/lookup/MethodBinding.isStatic:()Z
      57: ifeq          65
      60: bipush        6
      62: goto          78
      65: aload_1
      66: invokevirtual #1412               // Method org/eclipse/jdt/internal/compiler/lookup/MethodBinding.isPrivate:()Z
      69: ifeq          77
      72: bipush        7
      74: goto          78
      77: iconst_5
      78: istore_3
      79: aload_0
      80: iload_3
      81: aload_1
      82: getfield      #1400               // Field org/eclipse/jdt/internal/compiler/lookup/MethodBinding.declaringClass:Lorg/eclipse/jdt/internal/compiler/lookup/ReferenceBinding;
      85: aload_1
      86: getfield      #1418               // Field org/eclipse/jdt/internal/compiler/lookup/MethodBinding.selector:[C
      89: aload_1
      90: invokevirtual #1420               // Method org/eclipse/jdt/internal/compiler/lookup/MethodBinding.signature:()[C
      93: iload_2
      94: invokevirtual #1421               // Method literalIndexForMethodHandle:(ILorg/eclipse/jdt/internal/compiler/lookup/TypeBinding;[C[CZ)I
      97: ireturn

  public int literalIndexForMethodHandle(int, org.eclipse.jdt.internal.compiler.lookup.TypeBinding, char[], char[], boolean);
    Code:
       0: aload_0
       1: aload_2
       2: aload_3
       3: aload         4
       5: iload         5
       7: invokevirtual #1426               // Method literalIndexForMethod:(Lorg/eclipse/jdt/internal/compiler/lookup/TypeBinding;[C[CZ)I
      10: istore        6
      12: aload_0
      13: dup
      14: getfield      #1183               // Field currentIndex:I
      17: dup_x1
      18: iconst_1
      19: iadd
      20: putfield      #1183               // Field currentIndex:I
      23: istore        7
      25: aload_0
      26: getfield      #1202               // Field offsets:[I
      29: arraylength
      30: istore        8
      32: iload         8
      34: iload         7
      36: if_icmpgt     61
      39: aload_0
      40: getfield      #1202               // Field offsets:[I
      43: iconst_0
      44: aload_0
      45: iload         7
      47: iconst_2
      48: imul
      49: newarray       int
      51: dup_x1
      52: putfield      #1202               // Field offsets:[I
      55: iconst_0
      56: iload         8
      58: invokestatic  #1225               // Method java/lang/System.arraycopy:(Ljava/lang/Object;ILjava/lang/Object;II)V
      61: aload_0
      62: getfield      #1202               // Field offsets:[I
      65: iload         7
      67: aload_0
      68: getfield      #1218               // Field currentOffset:I
      71: iastore
      72: aload_0
      73: bipush        15
      75: invokevirtual #1261               // Method writeU1:(I)V
      78: aload_0
      79: iload_1
      80: invokevirtual #1261               // Method writeU1:(I)V
      83: aload_0
      84: iload         6
      86: invokevirtual #1428               // Method writeU2:(I)V
      89: iload         7
      91: ireturn

  public int literalIndexForMethodType(char[]);
    Code:
       0: aload_0
       1: aload_1
       2: invokevirtual #1295               // Method literalIndex:([C)I
       5: istore_2
       6: aload_0
       7: dup
       8: getfield      #1183               // Field currentIndex:I
      11: dup_x1
      12: iconst_1
      13: iadd
      14: putfield      #1183               // Field currentIndex:I
      17: istore_3
      18: aload_0
      19: getfield      #1202               // Field offsets:[I
      22: arraylength
      23: istore        4
      25: iload         4
      27: iload_3
      28: if_icmpgt     52
      31: aload_0
      32: getfield      #1202               // Field offsets:[I
      35: iconst_0
      36: aload_0
      37: iload_3
      38: iconst_2
      39: imul
      40: newarray       int
      42: dup_x1
      43: putfield      #1202               // Field offsets:[I
      46: iconst_0
      47: iload         4
      49: invokestatic  #1225               // Method java/lang/System.arraycopy:(Ljava/lang/Object;ILjava/lang/Object;II)V
      52: aload_0
      53: getfield      #1202               // Field offsets:[I
      56: iload_3
      57: aload_0
      58: getfield      #1218               // Field currentOffset:I
      61: iastore
      62: aload_0
      63: bipush        16
      65: invokevirtual #1261               // Method writeU1:(I)V
      68: aload_0
      69: iload_2
      70: invokevirtual #1428               // Method writeU2:(I)V
      73: iload_3
      74: ireturn

  public int literalIndexForInvokeDynamic(int, char[], char[]);
    Code:
       0: aload_0
       1: aload_2
       2: aload_3
       3: invokevirtual #1379               // Method literalIndexForNameAndType:([C[C)I
       6: istore        4
       8: aload_0
       9: dup
      10: getfield      #1183               // Field currentIndex:I
      13: dup_x1
      14: iconst_1
      15: iadd
      16: putfield      #1183               // Field currentIndex:I
      19: istore        5
      21: aload_0
      22: getfield      #1202               // Field offsets:[I
      25: arraylength
      26: istore        6
      28: iload         6
      30: iload         5
      32: if_icmpgt     57
      35: aload_0
      36: getfield      #1202               // Field offsets:[I
      39: iconst_0
      40: aload_0
      41: iload         5
      43: iconst_2
      44: imul
      45: newarray       int
      47: dup_x1
      48: putfield      #1202               // Field offsets:[I
      51: iconst_0
      52: iload         6
      54: invokestatic  #1225               // Method java/lang/System.arraycopy:(Ljava/lang/Object;ILjava/lang/Object;II)V
      57: aload_0
      58: getfield      #1202               // Field offsets:[I
      61: iload         5
      63: aload_0
      64: getfield      #1218               // Field currentOffset:I
      67: iastore
      68: aload_0
      69: bipush        18
      71: invokevirtual #1261               // Method writeU1:(I)V
      74: aload_0
      75: iload_1
      76: invokevirtual #1428               // Method writeU2:(I)V
      79: aload_0
      80: iload         4
      82: invokevirtual #1428               // Method writeU2:(I)V
      85: iload         5
      87: ireturn

  public int literalIndexForField(char[], char[], char[]);
    Code:
       0: aload_0
       1: aload_1
       2: aload_2
       3: aload_3
       4: aload_0
       5: getfield      #1183               // Field currentIndex:I
       8: invokespecial #1375               // Method putInCacheIfAbsent:([C[C[CI)I
      11: dup
      12: istore        4
      14: ifge          226
      17: aload_0
      18: dup
      19: getfield      #1183               // Field currentIndex:I
      22: iconst_1
      23: iadd
      24: putfield      #1183               // Field currentIndex:I
      27: iload         4
      29: ineg
      30: dup
      31: istore        4
      33: ldc_w         #1234               // int 65535
      36: if_icmple     68
      39: aload_0
      40: getfield      #1220               // Field classFile:Lorg/eclipse/jdt/internal/compiler/ClassFile;
      43: getfield      #1235               // Field org/eclipse/jdt/internal/compiler/ClassFile.referenceBinding:Lorg/eclipse/jdt/internal/compiler/lookup/SourceTypeBinding;
      46: getfield      #1239               // Field org/eclipse/jdt/internal/compiler/lookup/SourceTypeBinding.scope:Lorg/eclipse/jdt/internal/compiler/lookup/ClassScope;
      49: invokevirtual #1245               // Method org/eclipse/jdt/internal/compiler/lookup/ClassScope.problemReporter:()Lorg/eclipse/jdt/internal/compiler/problem/ProblemReporter;
      52: aload_0
      53: getfield      #1220               // Field classFile:Lorg/eclipse/jdt/internal/compiler/ClassFile;
      56: getfield      #1235               // Field org/eclipse/jdt/internal/compiler/ClassFile.referenceBinding:Lorg/eclipse/jdt/internal/compiler/lookup/SourceTypeBinding;
      59: getfield      #1239               // Field org/eclipse/jdt/internal/compiler/lookup/SourceTypeBinding.scope:Lorg/eclipse/jdt/internal/compiler/lookup/ClassScope;
      62: invokevirtual #1251               // Method org/eclipse/jdt/internal/compiler/lookup/ClassScope.referenceType:()Lorg/eclipse/jdt/internal/compiler/ast/TypeDeclaration;
      65: invokevirtual #1255               // Method org/eclipse/jdt/internal/compiler/problem/ProblemReporter.noMoreAvailableSpaceInConstantPool:(Lorg/eclipse/jdt/internal/compiler/ast/TypeDeclaration;)V
      68: aload_0
      69: getfield      #1202               // Field offsets:[I
      72: arraylength
      73: istore        5
      75: iload         5
      77: iload         4
      79: if_icmpgt     104
      82: aload_0
      83: getfield      #1202               // Field offsets:[I
      86: iconst_0
      87: aload_0
      88: iload         4
      90: iconst_2
      91: imul
      92: newarray       int
      94: dup_x1
      95: putfield      #1202               // Field offsets:[I
      98: iconst_0
      99: iload         5
     101: invokestatic  #1225               // Method java/lang/System.arraycopy:(Ljava/lang/Object;ILjava/lang/Object;II)V
     104: aload_0
     105: getfield      #1202               // Field offsets:[I
     108: iload         4
     110: aload_0
     111: getfield      #1218               // Field currentOffset:I
     114: iastore
     115: aload_0
     116: bipush        9
     118: invokevirtual #1261               // Method writeU1:(I)V
     121: aload_0
     122: getfield      #1218               // Field currentOffset:I
     125: istore        6
     127: aload_0
     128: getfield      #1218               // Field currentOffset:I
     131: iconst_4
     132: iadd
     133: aload_0
     134: getfield      #1213               // Field poolContent:[B
     137: arraylength
     138: if_icmplt     146
     141: aload_0
     142: iconst_4
     143: invokespecial #1264               // Method resizePoolContents:(I)V
     146: aload_0
     147: dup
     148: getfield      #1218               // Field currentOffset:I
     151: iconst_4
     152: iadd
     153: putfield      #1218               // Field currentOffset:I
     156: aload_0
     157: aload_1
     158: invokevirtual #1371               // Method literalIndexForType:([C)I
     161: istore        7
     163: aload_0
     164: aload_2
     165: aload_3
     166: invokevirtual #1379               // Method literalIndexForNameAndType:([C[C)I
     169: istore        8
     171: aload_0
     172: getfield      #1213               // Field poolContent:[B
     175: iload         6
     177: iinc          6, 1
     180: iload         7
     182: bipush        8
     184: ishr
     185: i2b
     186: bastore
     187: aload_0
     188: getfield      #1213               // Field poolContent:[B
     191: iload         6
     193: iinc          6, 1
     196: iload         7
     198: i2b
     199: bastore
     200: aload_0
     201: getfield      #1213               // Field poolContent:[B
     204: iload         6
     206: iinc          6, 1
     209: iload         8
     211: bipush        8
     213: ishr
     214: i2b
     215: bastore
     216: aload_0
     217: getfield      #1213               // Field poolContent:[B
     220: iload         6
     222: iload         8
     224: i2b
     225: bastore
     226: iload         4
     228: ireturn

  public int literalIndexForLdc(char[]);
    Code:
       0: aload_0
       1: getfield      #1183               // Field currentIndex:I
       4: istore_2
       5: aload_0
       6: getfield      #1218               // Field currentOffset:I
       9: istore_3
      10: aload_0
      11: getfield      #1191               // Field stringCache:Lorg/eclipse/jdt/internal/compiler/codegen/CharArrayCache;
      14: aload_1
      15: aload_0
      16: getfield      #1183               // Field currentIndex:I
      19: invokevirtual #1230               // Method org/eclipse/jdt/internal/compiler/codegen/CharArrayCache.putIfAbsent:([CI)I
      22: dup
      23: istore        4
      25: ifge          687
      28: iload         4
      30: ineg
      31: dup
      32: istore        4
      34: ldc_w         #1234               // int 65535
      37: if_icmple     69
      40: aload_0
      41: getfield      #1220               // Field classFile:Lorg/eclipse/jdt/internal/compiler/ClassFile;
      44: getfield      #1235               // Field org/eclipse/jdt/internal/compiler/ClassFile.referenceBinding:Lorg/eclipse/jdt/internal/compiler/lookup/SourceTypeBinding;
      47: getfield      #1239               // Field org/eclipse/jdt/internal/compiler/lookup/SourceTypeBinding.scope:Lorg/eclipse/jdt/internal/compiler/lookup/ClassScope;
      50: invokevirtual #1245               // Method org/eclipse/jdt/internal/compiler/lookup/ClassScope.problemReporter:()Lorg/eclipse/jdt/internal/compiler/problem/ProblemReporter;
      53: aload_0
      54: getfield      #1220               // Field classFile:Lorg/eclipse/jdt/internal/compiler/ClassFile;
      57: getfield      #1235               // Field org/eclipse/jdt/internal/compiler/ClassFile.referenceBinding:Lorg/eclipse/jdt/internal/compiler/lookup/SourceTypeBinding;
      60: getfield      #1239               // Field org/eclipse/jdt/internal/compiler/lookup/SourceTypeBinding.scope:Lorg/eclipse/jdt/internal/compiler/lookup/ClassScope;
      63: invokevirtual #1251               // Method org/eclipse/jdt/internal/compiler/lookup/ClassScope.referenceType:()Lorg/eclipse/jdt/internal/compiler/ast/TypeDeclaration;
      66: invokevirtual #1255               // Method org/eclipse/jdt/internal/compiler/problem/ProblemReporter.noMoreAvailableSpaceInConstantPool:(Lorg/eclipse/jdt/internal/compiler/ast/TypeDeclaration;)V
      69: aload_0
      70: dup
      71: getfield      #1183               // Field currentIndex:I
      74: iconst_1
      75: iadd
      76: putfield      #1183               // Field currentIndex:I
      79: aload_0
      80: getfield      #1202               // Field offsets:[I
      83: arraylength
      84: istore        5
      86: iload         5
      88: iload         4
      90: if_icmpgt     115
      93: aload_0
      94: getfield      #1202               // Field offsets:[I
      97: iconst_0
      98: aload_0
      99: iload         4
     101: iconst_2
     102: imul
     103: newarray       int
     105: dup_x1
     106: putfield      #1202               // Field offsets:[I
     109: iconst_0
     110: iload         5
     112: invokestatic  #1225               // Method java/lang/System.arraycopy:(Ljava/lang/Object;ILjava/lang/Object;II)V
     115: aload_0
     116: getfield      #1202               // Field offsets:[I
     119: iload         4
     121: aload_0
     122: getfield      #1218               // Field currentOffset:I
     125: iastore
     126: aload_0
     127: bipush        8
     129: invokevirtual #1261               // Method writeU1:(I)V
     132: aload_0
     133: getfield      #1218               // Field currentOffset:I
     136: istore        6
     138: aload_0
     139: getfield      #1218               // Field currentOffset:I
     142: iconst_2
     143: iadd
     144: aload_0
     145: getfield      #1213               // Field poolContent:[B
     148: arraylength
     149: if_icmplt     157
     152: aload_0
     153: iconst_2
     154: invokespecial #1264               // Method resizePoolContents:(I)V
     157: aload_0
     158: dup
     159: getfield      #1218               // Field currentOffset:I
     162: iconst_2
     163: iadd
     164: putfield      #1218               // Field currentOffset:I
     167: aload_0
     168: getfield      #1189               // Field UTF8Cache:Lorg/eclipse/jdt/internal/compiler/codegen/CharArrayCache;
     171: aload_1
     172: aload_0
     173: getfield      #1183               // Field currentIndex:I
     176: invokevirtual #1230               // Method org/eclipse/jdt/internal/compiler/codegen/CharArrayCache.putIfAbsent:([CI)I
     179: dup
     180: istore        7
     182: ifge          661
     185: iload         7
     187: ineg
     188: dup
     189: istore        7
     191: ldc_w         #1234               // int 65535
     194: if_icmple     226
     197: aload_0
     198: getfield      #1220               // Field classFile:Lorg/eclipse/jdt/internal/compiler/ClassFile;
     201: getfield      #1235               // Field org/eclipse/jdt/internal/compiler/ClassFile.referenceBinding:Lorg/eclipse/jdt/internal/compiler/lookup/SourceTypeBinding;
     204: getfield      #1239               // Field org/eclipse/jdt/internal/compiler/lookup/SourceTypeBinding.scope:Lorg/eclipse/jdt/internal/compiler/lookup/ClassScope;
     207: invokevirtual #1245               // Method org/eclipse/jdt/internal/compiler/lookup/ClassScope.problemReporter:()Lorg/eclipse/jdt/internal/compiler/problem/ProblemReporter;
     210: aload_0
     211: getfield      #1220               // Field classFile:Lorg/eclipse/jdt/internal/compiler/ClassFile;
     214: getfield      #1235               // Field org/eclipse/jdt/internal/compiler/ClassFile.referenceBinding:Lorg/eclipse/jdt/internal/compiler/lookup/SourceTypeBinding;
     217: getfield      #1239               // Field org/eclipse/jdt/internal/compiler/lookup/SourceTypeBinding.scope:Lorg/eclipse/jdt/internal/compiler/lookup/ClassScope;
     220: invokevirtual #1251               // Method org/eclipse/jdt/internal/compiler/lookup/ClassScope.referenceType:()Lorg/eclipse/jdt/internal/compiler/ast/TypeDeclaration;
     223: invokevirtual #1255               // Method org/eclipse/jdt/internal/compiler/problem/ProblemReporter.noMoreAvailableSpaceInConstantPool:(Lorg/eclipse/jdt/internal/compiler/ast/TypeDeclaration;)V
     226: aload_0
     227: dup
     228: getfield      #1183               // Field currentIndex:I
     231: iconst_1
     232: iadd
     233: putfield      #1183               // Field currentIndex:I
     236: aload_0
     237: getfield      #1202               // Field offsets:[I
     240: arraylength
     241: istore        5
     243: iload         5
     245: iload         7
     247: if_icmpgt     272
     250: aload_0
     251: getfield      #1202               // Field offsets:[I
     254: iconst_0
     255: aload_0
     256: iload         7
     258: iconst_2
     259: imul
     260: newarray       int
     262: dup_x1
     263: putfield      #1202               // Field offsets:[I
     266: iconst_0
     267: iload         5
     269: invokestatic  #1225               // Method java/lang/System.arraycopy:(Ljava/lang/Object;ILjava/lang/Object;II)V
     272: aload_0
     273: getfield      #1202               // Field offsets:[I
     276: iload         7
     278: aload_0
     279: getfield      #1218               // Field currentOffset:I
     282: iastore
     283: aload_0
     284: iconst_1
     285: invokevirtual #1261               // Method writeU1:(I)V
     288: aload_0
     289: getfield      #1218               // Field currentOffset:I
     292: istore        8
     294: aload_0
     295: getfield      #1218               // Field currentOffset:I
     298: iconst_2
     299: iadd
     300: aload_0
     301: getfield      #1213               // Field poolContent:[B
     304: arraylength
     305: if_icmplt     313
     308: aload_0
     309: iconst_2
     310: invokespecial #1264               // Method resizePoolContents:(I)V
     313: aload_0
     314: dup
     315: getfield      #1218               // Field currentOffset:I
     318: iconst_2
     319: iadd
     320: putfield      #1218               // Field currentOffset:I
     323: iconst_0
     324: istore        5
     326: iconst_0
     327: istore        9
     329: goto          592
     332: aload_1
     333: iload         9
     335: caload
     336: istore        10
     338: iload         10
     340: iconst_1
     341: if_icmplt     395
     344: iload         10
     346: bipush        127
     348: if_icmpgt     395
     351: iinc          5, 1
     354: aload_0
     355: getfield      #1218               // Field currentOffset:I
     358: iconst_1
     359: iadd
     360: aload_0
     361: getfield      #1213               // Field poolContent:[B
     364: arraylength
     365: if_icmplt     373
     368: aload_0
     369: iconst_1
     370: invokespecial #1264               // Method resizePoolContents:(I)V
     373: aload_0
     374: getfield      #1213               // Field poolContent:[B
     377: aload_0
     378: dup
     379: getfield      #1218               // Field currentOffset:I
     382: dup_x1
     383: iconst_1
     384: iadd
     385: putfield      #1218               // Field currentOffset:I
     388: iload         10
     390: i2b
     391: bastore
     392: goto          589
     395: iload         10
     397: sipush        2047
     400: if_icmple     512
     403: iinc          5, 3
     406: aload_0
     407: getfield      #1218               // Field currentOffset:I
     410: iconst_3
     411: iadd
     412: aload_0
     413: getfield      #1213               // Field poolContent:[B
     416: arraylength
     417: if_icmplt     425
     420: aload_0
     421: iconst_3
     422: invokespecial #1264               // Method resizePoolContents:(I)V
     425: aload_0
     426: getfield      #1213               // Field poolContent:[B
     429: aload_0
     430: dup
     431: getfield      #1218               // Field currentOffset:I
     434: dup_x1
     435: iconst_1
     436: iadd
     437: putfield      #1218               // Field currentOffset:I
     440: sipush        224
     443: iload         10
     445: bipush        12
     447: ishr
     448: bipush        15
     450: iand
     451: ior
     452: i2b
     453: bastore
     454: aload_0
     455: getfield      #1213               // Field poolContent:[B
     458: aload_0
     459: dup
     460: getfield      #1218               // Field currentOffset:I
     463: dup_x1
     464: iconst_1
     465: iadd
     466: putfield      #1218               // Field currentOffset:I
     469: sipush        128
     472: iload         10
     474: bipush        6
     476: ishr
     477: bipush        63
     479: iand
     480: ior
     481: i2b
     482: bastore
     483: aload_0
     484: getfield      #1213               // Field poolContent:[B
     487: aload_0
     488: dup
     489: getfield      #1218               // Field currentOffset:I
     492: dup_x1
     493: iconst_1
     494: iadd
     495: putfield      #1218               // Field currentOffset:I
     498: sipush        128
     501: iload         10
     503: bipush        63
     505: iand
     506: ior
     507: i2b
     508: bastore
     509: goto          589
     512: aload_0
     513: getfield      #1218               // Field currentOffset:I
     516: iconst_2
     517: iadd
     518: aload_0
     519: getfield      #1213               // Field poolContent:[B
     522: arraylength
     523: if_icmplt     531
     526: aload_0
     527: iconst_2
     528: invokespecial #1264               // Method resizePoolContents:(I)V
     531: iinc          5, 2
     534: aload_0
     535: getfield      #1213               // Field poolContent:[B
     538: aload_0
     539: dup
     540: getfield      #1218               // Field currentOffset:I
     543: dup_x1
     544: iconst_1
     545: iadd
     546: putfield      #1218               // Field currentOffset:I
     549: sipush        192
     552: iload         10
     554: bipush        6
     556: ishr
     557: bipush        31
     559: iand
     560: ior
     561: i2b
     562: bastore
     563: aload_0
     564: getfield      #1213               // Field poolContent:[B
     567: aload_0
     568: dup
     569: getfield      #1218               // Field currentOffset:I
     572: dup_x1
     573: iconst_1
     574: iadd
     575: putfield      #1218               // Field currentOffset:I
     578: sipush        128
     581: iload         10
     583: bipush        63
     585: iand
     586: ior
     587: i2b
     588: bastore
     589: iinc          9, 1
     592: iload         9
     594: aload_1
     595: arraylength
     596: if_icmplt     332
     599: iload         5
     601: ldc_w         #1234               // int 65535
     604: if_icmplt     635
     607: aload_0
     608: iload_3
     609: putfield      #1218               // Field currentOffset:I
     612: aload_0
     613: iload_2
     614: putfield      #1183               // Field currentIndex:I
     617: aload_0
     618: getfield      #1191               // Field stringCache:Lorg/eclipse/jdt/internal/compiler/codegen/CharArrayCache;
     621: aload_1
     622: invokevirtual #1441               // Method org/eclipse/jdt/internal/compiler/codegen/CharArrayCache.remove:([C)V
     625: aload_0
     626: getfield      #1189               // Field UTF8Cache:Lorg/eclipse/jdt/internal/compiler/codegen/CharArrayCache;
     629: aload_1
     630: invokevirtual #1441               // Method org/eclipse/jdt/internal/compiler/codegen/CharArrayCache.remove:([C)V
     633: iconst_0
     634: ireturn
     635: aload_0
     636: getfield      #1213               // Field poolContent:[B
     639: iload         8
     641: iinc          8, 1
     644: iload         5
     646: bipush        8
     648: ishr
     649: i2b
     650: bastore
     651: aload_0
     652: getfield      #1213               // Field poolContent:[B
     655: iload         8
     657: iload         5
     659: i2b
     660: bastore
     661: aload_0
     662: getfield      #1213               // Field poolContent:[B
     665: iload         6
     667: iinc          6, 1
     670: iload         7
     672: bipush        8
     674: ishr
     675: i2b
     676: bastore
     677: aload_0
     678: getfield      #1213               // Field poolContent:[B
     681: iload         6
     683: iload         7
     685: i2b
     686: bastore
     687: iload         4
     689: ireturn

  private int putInNameAndTypeCacheIfAbsent(char[], char[], int);
    Code:
       0: aload_0
       1: getfield      #1200               // Field nameAndTypeCacheForFieldsAndMethods:Lorg/eclipse/jdt/internal/compiler/util/HashtableOfObject;
       4: aload_1
       5: invokevirtual #1447               // Method org/eclipse/jdt/internal/compiler/util/HashtableOfObject.get:([C)Ljava/lang/Object;
       8: astore        5
      10: aload         5
      12: ifnonnull     44
      15: new           #1450               // class org/eclipse/jdt/internal/compiler/codegen/CachedIndexEntry
      18: dup
      19: aload_2
      20: iload_3
      21: invokespecial #1452               // Method org/eclipse/jdt/internal/compiler/codegen/CachedIndexEntry."<init>":([CI)V
      24: astore        6
      26: iload_3
      27: ineg
      28: istore        4
      30: aload_0
      31: getfield      #1200               // Field nameAndTypeCacheForFieldsAndMethods:Lorg/eclipse/jdt/internal/compiler/util/HashtableOfObject;
      34: aload_1
      35: aload         6
      37: invokevirtual #1455               // Method org/eclipse/jdt/internal/compiler/util/HashtableOfObject.put:([CLjava/lang/Object;)Ljava/lang/Object;
      40: pop
      41: goto          145
      44: aload         5
      46: instanceof    #1450               // class org/eclipse/jdt/internal/compiler/codegen/CachedIndexEntry
      49: ifeq          129
      52: aload         5
      54: checkcast     #1450               // class org/eclipse/jdt/internal/compiler/codegen/CachedIndexEntry
      57: astore        6
      59: aload_2
      60: aload         6
      62: getfield      #1459               // Field org/eclipse/jdt/internal/compiler/codegen/CachedIndexEntry.signature:[C
      65: invokestatic  #1461               // Method org/eclipse/jdt/core/compiler/CharOperation.equals:([C[C)Z
      68: ifeq          81
      71: aload         6
      73: getfield      #1466               // Field org/eclipse/jdt/internal/compiler/codegen/CachedIndexEntry.index:I
      76: istore        4
      78: goto          145
      81: new           #1185               // class org/eclipse/jdt/internal/compiler/codegen/CharArrayCache
      84: dup
      85: invokespecial #1468               // Method org/eclipse/jdt/internal/compiler/codegen/CharArrayCache."<init>":()V
      88: astore        7
      90: aload         7
      92: aload         6
      94: getfield      #1459               // Field org/eclipse/jdt/internal/compiler/codegen/CachedIndexEntry.signature:[C
      97: aload         6
      99: getfield      #1466               // Field org/eclipse/jdt/internal/compiler/codegen/CachedIndexEntry.index:I
     102: invokevirtual #1230               // Method org/eclipse/jdt/internal/compiler/codegen/CharArrayCache.putIfAbsent:([CI)I
     105: pop
     106: aload         7
     108: aload_2
     109: iload_3
     110: invokevirtual #1230               // Method org/eclipse/jdt/internal/compiler/codegen/CharArrayCache.putIfAbsent:([CI)I
     113: istore        4
     115: aload_0
     116: getfield      #1200               // Field nameAndTypeCacheForFieldsAndMethods:Lorg/eclipse/jdt/internal/compiler/util/HashtableOfObject;
     119: aload_1
     120: aload         7
     122: invokevirtual #1455               // Method org/eclipse/jdt/internal/compiler/util/HashtableOfObject.put:([CLjava/lang/Object;)Ljava/lang/Object;
     125: pop
     126: goto          145
     129: aload         5
     131: checkcast     #1185               // class org/eclipse/jdt/internal/compiler/codegen/CharArrayCache
     134: astore        6
     136: aload         6
     138: aload_2
     139: iload_3
     140: invokevirtual #1230               // Method org/eclipse/jdt/internal/compiler/codegen/CharArrayCache.putIfAbsent:([CI)I
     143: istore        4
     145: iload         4
     147: ireturn

  private int putInCacheIfAbsent(char[], char[], char[], int);
    Code:
       0: aload_0
       1: getfield      #1196               // Field methodsAndFieldsCache:Lorg/eclipse/jdt/internal/compiler/util/HashtableOfObject;
       4: aload_1
       5: invokevirtual #1447               // Method org/eclipse/jdt/internal/compiler/util/HashtableOfObject.get:([C)Ljava/lang/Object;
       8: checkcast     #1193               // class org/eclipse/jdt/internal/compiler/util/HashtableOfObject
      11: astore        6
      13: aload         6
      15: ifnonnull     67
      18: new           #1193               // class org/eclipse/jdt/internal/compiler/util/HashtableOfObject
      21: dup
      22: invokespecial #1477               // Method org/eclipse/jdt/internal/compiler/util/HashtableOfObject."<init>":()V
      25: astore        6
      27: aload_0
      28: getfield      #1196               // Field methodsAndFieldsCache:Lorg/eclipse/jdt/internal/compiler/util/HashtableOfObject;
      31: aload_1
      32: aload         6
      34: invokevirtual #1455               // Method org/eclipse/jdt/internal/compiler/util/HashtableOfObject.put:([CLjava/lang/Object;)Ljava/lang/Object;
      37: pop
      38: new           #1450               // class org/eclipse/jdt/internal/compiler/codegen/CachedIndexEntry
      41: dup
      42: aload_3
      43: iload         4
      45: invokespecial #1452               // Method org/eclipse/jdt/internal/compiler/codegen/CachedIndexEntry."<init>":([CI)V
      48: astore        7
      50: iload         4
      52: ineg
      53: istore        5
      55: aload         6
      57: aload_2
      58: aload         7
      60: invokevirtual #1455               // Method org/eclipse/jdt/internal/compiler/util/HashtableOfObject.put:([CLjava/lang/Object;)Ljava/lang/Object;
      63: pop
      64: goto          210
      67: aload         6
      69: aload_2
      70: invokevirtual #1447               // Method org/eclipse/jdt/internal/compiler/util/HashtableOfObject.get:([C)Ljava/lang/Object;
      73: astore        7
      75: aload         7
      77: ifnonnull     109
      80: new           #1450               // class org/eclipse/jdt/internal/compiler/codegen/CachedIndexEntry
      83: dup
      84: aload_3
      85: iload         4
      87: invokespecial #1452               // Method org/eclipse/jdt/internal/compiler/codegen/CachedIndexEntry."<init>":([CI)V
      90: astore        8
      92: iload         4
      94: ineg
      95: istore        5
      97: aload         6
      99: aload_2
     100: aload         8
     102: invokevirtual #1455               // Method org/eclipse/jdt/internal/compiler/util/HashtableOfObject.put:([CLjava/lang/Object;)Ljava/lang/Object;
     105: pop
     106: goto          210
     109: aload         7
     111: instanceof    #1450               // class org/eclipse/jdt/internal/compiler/codegen/CachedIndexEntry
     114: ifeq          193
     117: aload         7
     119: checkcast     #1450               // class org/eclipse/jdt/internal/compiler/codegen/CachedIndexEntry
     122: astore        8
     124: aload_3
     125: aload         8
     127: getfield      #1459               // Field org/eclipse/jdt/internal/compiler/codegen/CachedIndexEntry.signature:[C
     130: invokestatic  #1461               // Method org/eclipse/jdt/core/compiler/CharOperation.equals:([C[C)Z
     133: ifeq          146
     136: aload         8
     138: getfield      #1466               // Field org/eclipse/jdt/internal/compiler/codegen/CachedIndexEntry.index:I
     141: istore        5
     143: goto          210
     146: new           #1185               // class org/eclipse/jdt/internal/compiler/codegen/CharArrayCache
     149: dup
     150: invokespecial #1468               // Method org/eclipse/jdt/internal/compiler/codegen/CharArrayCache."<init>":()V
     153: astore        9
     155: aload         9
     157: aload         8
     159: getfield      #1459               // Field org/eclipse/jdt/internal/compiler/codegen/CachedIndexEntry.signature:[C
     162: aload         8
     164: getfield      #1466               // Field org/eclipse/jdt/internal/compiler/codegen/CachedIndexEntry.index:I
     167: invokevirtual #1230               // Method org/eclipse/jdt/internal/compiler/codegen/CharArrayCache.putIfAbsent:([CI)I
     170: pop
     171: aload         9
     173: aload_3
     174: iload         4
     176: invokevirtual #1230               // Method org/eclipse/jdt/internal/compiler/codegen/CharArrayCache.putIfAbsent:([CI)I
     179: istore        5
     181: aload         6
     183: aload_2
     184: aload         9
     186: invokevirtual #1455               // Method org/eclipse/jdt/internal/compiler/util/HashtableOfObject.put:([CLjava/lang/Object;)Ljava/lang/Object;
     189: pop
     190: goto          210
     193: aload         7
     195: checkcast     #1185               // class org/eclipse/jdt/internal/compiler/codegen/CharArrayCache
     198: astore        8
     200: aload         8
     202: aload_3
     203: iload         4
     205: invokevirtual #1230               // Method org/eclipse/jdt/internal/compiler/codegen/CharArrayCache.putIfAbsent:([CI)I
     208: istore        5
     210: iload         5
     212: ireturn

  public void resetForClinit(int, int);
    Code:
       0: aload_0
       1: iload_1
       2: putfield      #1183               // Field currentIndex:I
       5: aload_0
       6: iload_2
       7: putfield      #1218               // Field currentOffset:I
      10: aload_0
      11: getfield      #1189               // Field UTF8Cache:Lorg/eclipse/jdt/internal/compiler/codegen/CharArrayCache;
      14: getstatic     #1482               // Field org/eclipse/jdt/internal/compiler/codegen/AttributeNamesConstants.CodeName:[C
      17: invokevirtual #1487               // Method org/eclipse/jdt/internal/compiler/codegen/CharArrayCache.get:([C)I
      20: iload_1
      21: if_icmplt     34
      24: aload_0
      25: getfield      #1189               // Field UTF8Cache:Lorg/eclipse/jdt/internal/compiler/codegen/CharArrayCache;
      28: getstatic     #1482               // Field org/eclipse/jdt/internal/compiler/codegen/AttributeNamesConstants.CodeName:[C
      31: invokevirtual #1441               // Method org/eclipse/jdt/internal/compiler/codegen/CharArrayCache.remove:([C)V
      34: aload_0
      35: getfield      #1189               // Field UTF8Cache:Lorg/eclipse/jdt/internal/compiler/codegen/CharArrayCache;
      38: getstatic     #379                // Field ClinitSignature:[C
      41: invokevirtual #1487               // Method org/eclipse/jdt/internal/compiler/codegen/CharArrayCache.get:([C)I
      44: iload_1
      45: if_icmplt     58
      48: aload_0
      49: getfield      #1189               // Field UTF8Cache:Lorg/eclipse/jdt/internal/compiler/codegen/CharArrayCache;
      52: getstatic     #379                // Field ClinitSignature:[C
      55: invokevirtual #1441               // Method org/eclipse/jdt/internal/compiler/codegen/CharArrayCache.remove:([C)V
      58: aload_0
      59: getfield      #1189               // Field UTF8Cache:Lorg/eclipse/jdt/internal/compiler/codegen/CharArrayCache;
      62: getstatic     #374                // Field Clinit:[C
      65: invokevirtual #1487               // Method org/eclipse/jdt/internal/compiler/codegen/CharArrayCache.get:([C)I
      68: iload_1
      69: if_icmplt     82
      72: aload_0
      73: getfield      #1189               // Field UTF8Cache:Lorg/eclipse/jdt/internal/compiler/codegen/CharArrayCache;
      76: getstatic     #374                // Field Clinit:[C
      79: invokevirtual #1441               // Method org/eclipse/jdt/internal/compiler/codegen/CharArrayCache.remove:([C)V
      82: return

  private final void resizePoolContents(int);
    Code:
       0: aload_0
       1: getfield      #1213               // Field poolContent:[B
       4: arraylength
       5: istore_2
       6: iload_2
       7: istore_3
       8: iload_3
       9: iload_1
      10: if_icmpge     15
      13: iload_1
      14: istore_3
      15: aload_0
      16: getfield      #1213               // Field poolContent:[B
      19: iconst_0
      20: aload_0
      21: iload_2
      22: iload_3
      23: iadd
      24: newarray       byte
      26: dup_x1
      27: putfield      #1213               // Field poolContent:[B
      30: iconst_0
      31: iload_2
      32: invokestatic  #1225               // Method java/lang/System.arraycopy:(Ljava/lang/Object;ILjava/lang/Object;II)V
      35: return

  protected final void writeU1(int);
    Code:
       0: aload_0
       1: getfield      #1218               // Field currentOffset:I
       4: iconst_1
       5: iadd
       6: aload_0
       7: getfield      #1213               // Field poolContent:[B
      10: arraylength
      11: if_icmplt     19
      14: aload_0
      15: iconst_1
      16: invokespecial #1264               // Method resizePoolContents:(I)V
      19: aload_0
      20: getfield      #1213               // Field poolContent:[B
      23: aload_0
      24: dup
      25: getfield      #1218               // Field currentOffset:I
      28: dup_x1
      29: iconst_1
      30: iadd
      31: putfield      #1218               // Field currentOffset:I
      34: iload_1
      35: i2b
      36: bastore
      37: return

  protected final void writeU2(int);
    Code:
       0: aload_0
       1: getfield      #1218               // Field currentOffset:I
       4: iconst_2
       5: iadd
       6: aload_0
       7: getfield      #1213               // Field poolContent:[B
      10: arraylength
      11: if_icmplt     19
      14: aload_0
      15: iconst_2
      16: invokespecial #1264               // Method resizePoolContents:(I)V
      19: aload_0
      20: getfield      #1213               // Field poolContent:[B
      23: aload_0
      24: dup
      25: getfield      #1218               // Field currentOffset:I
      28: dup_x1
      29: iconst_1
      30: iadd
      31: putfield      #1218               // Field currentOffset:I
      34: iload_1
      35: bipush        8
      37: iushr
      38: i2b
      39: bastore
      40: aload_0
      41: getfield      #1213               // Field poolContent:[B
      44: aload_0
      45: dup
      46: getfield      #1218               // Field currentOffset:I
      49: dup_x1
      50: iconst_1
      51: iadd
      52: putfield      #1218               // Field currentOffset:I
      55: iload_1
      56: i2b
      57: bastore
      58: return

  public void reset();
    Code:
       0: aload_0
       1: getfield      #1315               // Field doubleCache:Lorg/eclipse/jdt/internal/compiler/codegen/DoubleCache;
       4: ifnull        14
       7: aload_0
       8: getfield      #1315               // Field doubleCache:Lorg/eclipse/jdt/internal/compiler/codegen/DoubleCache;
      11: invokevirtual #1494               // Method org/eclipse/jdt/internal/compiler/codegen/DoubleCache.clear:()V
      14: aload_0
      15: getfield      #1332               // Field floatCache:Lorg/eclipse/jdt/internal/compiler/codegen/FloatCache;
      18: ifnull        28
      21: aload_0
      22: getfield      #1332               // Field floatCache:Lorg/eclipse/jdt/internal/compiler/codegen/FloatCache;
      25: invokevirtual #1497               // Method org/eclipse/jdt/internal/compiler/codegen/FloatCache.clear:()V
      28: aload_0
      29: getfield      #1346               // Field intCache:Lorg/eclipse/jdt/internal/compiler/codegen/IntegerCache;
      32: ifnull        42
      35: aload_0
      36: getfield      #1346               // Field intCache:Lorg/eclipse/jdt/internal/compiler/codegen/IntegerCache;
      39: invokevirtual #1498               // Method org/eclipse/jdt/internal/compiler/codegen/IntegerCache.clear:()V
      42: aload_0
      43: getfield      #1355               // Field longCache:Lorg/eclipse/jdt/internal/compiler/codegen/LongCache;
      46: ifnull        56
      49: aload_0
      50: getfield      #1355               // Field longCache:Lorg/eclipse/jdt/internal/compiler/codegen/LongCache;
      53: invokevirtual #1499               // Method org/eclipse/jdt/internal/compiler/codegen/LongCache.clear:()V
      56: aload_0
      57: getfield      #1189               // Field UTF8Cache:Lorg/eclipse/jdt/internal/compiler/codegen/CharArrayCache;
      60: invokevirtual #1500               // Method org/eclipse/jdt/internal/compiler/codegen/CharArrayCache.clear:()V
      63: aload_0
      64: getfield      #1191               // Field stringCache:Lorg/eclipse/jdt/internal/compiler/codegen/CharArrayCache;
      67: invokevirtual #1500               // Method org/eclipse/jdt/internal/compiler/codegen/CharArrayCache.clear:()V
      70: aload_0
      71: getfield      #1196               // Field methodsAndFieldsCache:Lorg/eclipse/jdt/internal/compiler/util/HashtableOfObject;
      74: invokevirtual #1501               // Method org/eclipse/jdt/internal/compiler/util/HashtableOfObject.clear:()V
      77: aload_0
      78: getfield      #1198               // Field classCache:Lorg/eclipse/jdt/internal/compiler/codegen/CharArrayCache;
      81: invokevirtual #1500               // Method org/eclipse/jdt/internal/compiler/codegen/CharArrayCache.clear:()V
      84: aload_0
      85: getfield      #1200               // Field nameAndTypeCacheForFieldsAndMethods:Lorg/eclipse/jdt/internal/compiler/util/HashtableOfObject;
      88: invokevirtual #1501               // Method org/eclipse/jdt/internal/compiler/util/HashtableOfObject.clear:()V
      91: aload_0
      92: iconst_1
      93: putfield      #1183               // Field currentIndex:I
      96: aload_0
      97: iconst_0
      98: putfield      #1218               // Field currentOffset:I
     101: return

  public void resetForAttributeName(char[], int, int);
    Code:
       0: aload_0
       1: iload_2
       2: putfield      #1183               // Field currentIndex:I
       5: aload_0
       6: iload_3
       7: putfield      #1218               // Field currentOffset:I
      10: aload_0
      11: getfield      #1189               // Field UTF8Cache:Lorg/eclipse/jdt/internal/compiler/codegen/CharArrayCache;
      14: aload_1
      15: invokevirtual #1487               // Method org/eclipse/jdt/internal/compiler/codegen/CharArrayCache.get:([C)I
      18: iload_2
      19: if_icmplt     30
      22: aload_0
      23: getfield      #1189               // Field UTF8Cache:Lorg/eclipse/jdt/internal/compiler/codegen/CharArrayCache;
      26: aload_1
      27: invokevirtual #1441               // Method org/eclipse/jdt/internal/compiler/codegen/CharArrayCache.remove:([C)V
      30: return
}
