Compiled from "AnalysisSourceEntity.java"
final class software.amazon.awssdk.services.quicksight.model.AnalysisSourceEntity$BuilderImpl implements software.amazon.awssdk.services.quicksight.model.AnalysisSourceEntity$Builder {
  private software.amazon.awssdk.services.quicksight.model.AnalysisSourceTemplate sourceTemplate;

  private software.amazon.awssdk.services.quicksight.model.AnalysisSourceEntity$BuilderImpl();
    Code:
       0: aload_0
       1: invokespecial #4                  // Method java/lang/Object."<init>":()V
       4: return

  private software.amazon.awssdk.services.quicksight.model.AnalysisSourceEntity$BuilderImpl(software.amazon.awssdk.services.quicksight.model.AnalysisSourceEntity);
    Code:
       0: aload_0
       1: invokespecial #4                  // Method java/lang/Object."<init>":()V
       4: aload_0
       5: aload_1
       6: invokestatic  #5                  // Method software/amazon/awssdk/services/quicksight/model/AnalysisSourceEntity.access$300:(Lsoftware/amazon/awssdk/services/quicksight/model/AnalysisSourceEntity;)Lsoftware/amazon/awssdk/services/quicksight/model/AnalysisSourceTemplate;
       9: invokevirtual #6                  // Method sourceTemplate:(Lsoftware/amazon/awssdk/services/quicksight/model/AnalysisSourceTemplate;)Lsoftware/amazon/awssdk/services/quicksight/model/AnalysisSourceEntity$Builder;
      12: pop
      13: return

  public final software.amazon.awssdk.services.quicksight.model.AnalysisSourceTemplate$Builder getSourceTemplate();
    Code:
       0: aload_0
       1: getfield      #3                  // Field sourceTemplate:Lsoftware/amazon/awssdk/services/quicksight/model/AnalysisSourceTemplate;
       4: ifnull        17
       7: aload_0
       8: getfield      #3                  // Field sourceTemplate:Lsoftware/amazon/awssdk/services/quicksight/model/AnalysisSourceTemplate;
      11: invokevirtual #7                  // Method software/amazon/awssdk/services/quicksight/model/AnalysisSourceTemplate.toBuilder:()Lsoftware/amazon/awssdk/services/quicksight/model/AnalysisSourceTemplate$Builder;
      14: goto          18
      17: aconst_null
      18: areturn

  public final software.amazon.awssdk.services.quicksight.model.AnalysisSourceEntity$Builder sourceTemplate(software.amazon.awssdk.services.quicksight.model.AnalysisSourceTemplate);
    Code:
       0: aload_0
       1: aload_1
       2: putfield      #3                  // Field sourceTemplate:Lsoftware/amazon/awssdk/services/quicksight/model/AnalysisSourceTemplate;
       5: aload_0
       6: areturn

  public final void setSourceTemplate(software.amazon.awssdk.services.quicksight.model.AnalysisSourceTemplate$BuilderImpl);
    Code:
       0: aload_0
       1: aload_1
       2: ifnull        12
       5: aload_1
       6: invokevirtual #8                  // Method software/amazon/awssdk/services/quicksight/model/AnalysisSourceTemplate$BuilderImpl.build:()Lsoftware/amazon/awssdk/services/quicksight/model/AnalysisSourceTemplate;
       9: goto          13
      12: aconst_null
      13: putfield      #3                  // Field sourceTemplate:Lsoftware/amazon/awssdk/services/quicksight/model/AnalysisSourceTemplate;
      16: return

  public software.amazon.awssdk.services.quicksight.model.AnalysisSourceEntity build();
    Code:
       0: new           #9                  // class software/amazon/awssdk/services/quicksight/model/AnalysisSourceEntity
       3: dup
       4: aload_0
       5: aconst_null
       6: invokespecial #10                 // Method software/amazon/awssdk/services/quicksight/model/AnalysisSourceEntity."<init>":(Lsoftware/amazon/awssdk/services/quicksight/model/AnalysisSourceEntity$BuilderImpl;Lsoftware/amazon/awssdk/services/quicksight/model/AnalysisSourceEntity$1;)V
       9: areturn

  public java.util.List<software.amazon.awssdk.core.SdkField<?>> sdkFields();
    Code:
       0: invokestatic  #11                 // Method software/amazon/awssdk/services/quicksight/model/AnalysisSourceEntity.access$500:()Ljava/util/List;
       3: areturn

  public java.lang.Object build();
    Code:
       0: aload_0
       1: invokevirtual #12                 // Method build:()Lsoftware/amazon/awssdk/services/quicksight/model/AnalysisSourceEntity;
       4: areturn

  static software.amazon.awssdk.services.quicksight.model.AnalysisSourceTemplate access$000(software.amazon.awssdk.services.quicksight.model.AnalysisSourceEntity$BuilderImpl);
    Code:
       0: aload_0
       1: getfield      #3                  // Field sourceTemplate:Lsoftware/amazon/awssdk/services/quicksight/model/AnalysisSourceTemplate;
       4: areturn

  software.amazon.awssdk.services.quicksight.model.AnalysisSourceEntity$BuilderImpl(software.amazon.awssdk.services.quicksight.model.AnalysisSourceEntity, software.amazon.awssdk.services.quicksight.model.AnalysisSourceEntity$1);
    Code:
       0: aload_0
       1: aload_1
       2: invokespecial #2                  // Method "<init>":(Lsoftware/amazon/awssdk/services/quicksight/model/AnalysisSourceEntity;)V
       5: return

  software.amazon.awssdk.services.quicksight.model.AnalysisSourceEntity$BuilderImpl(software.amazon.awssdk.services.quicksight.model.AnalysisSourceEntity$1);
    Code:
       0: aload_0
       1: invokespecial #1                  // Method "<init>":()V
       4: return
}
