Compiled from "ColumnLevelPermissionRule.java"
final class software.amazon.awssdk.services.quicksight.model.ColumnLevelPermissionRule$BuilderImpl implements software.amazon.awssdk.services.quicksight.model.ColumnLevelPermissionRule$Builder {
  private java.util.List<java.lang.String> principals;

  private java.util.List<java.lang.String> columnNames;

  private software.amazon.awssdk.services.quicksight.model.ColumnLevelPermissionRule$BuilderImpl();
    Code:
       0: aload_0
       1: invokespecial #5                  // Method java/lang/Object."<init>":()V
       4: aload_0
       5: invokestatic  #6                  // Method software/amazon/awssdk/core/util/DefaultSdkAutoConstructList.getInstance:()Lsoftware/amazon/awssdk/core/util/DefaultSdkAutoConstructList;
       8: putfield      #4                  // Field principals:Ljava/util/List;
      11: aload_0
      12: invokestatic  #6                  // Method software/amazon/awssdk/core/util/DefaultSdkAutoConstructList.getInstance:()Lsoftware/amazon/awssdk/core/util/DefaultSdkAutoConstructList;
      15: putfield      #3                  // Field columnNames:Ljava/util/List;
      18: return

  private software.amazon.awssdk.services.quicksight.model.ColumnLevelPermissionRule$BuilderImpl(software.amazon.awssdk.services.quicksight.model.ColumnLevelPermissionRule);
    Code:
       0: aload_0
       1: invokespecial #5                  // Method java/lang/Object."<init>":()V
       4: aload_0
       5: invokestatic  #6                  // Method software/amazon/awssdk/core/util/DefaultSdkAutoConstructList.getInstance:()Lsoftware/amazon/awssdk/core/util/DefaultSdkAutoConstructList;
       8: putfield      #4                  // Field principals:Ljava/util/List;
      11: aload_0
      12: invokestatic  #6                  // Method software/amazon/awssdk/core/util/DefaultSdkAutoConstructList.getInstance:()Lsoftware/amazon/awssdk/core/util/DefaultSdkAutoConstructList;
      15: putfield      #3                  // Field columnNames:Ljava/util/List;
      18: aload_0
      19: aload_1
      20: invokestatic  #7                  // Method software/amazon/awssdk/services/quicksight/model/ColumnLevelPermissionRule.access$400:(Lsoftware/amazon/awssdk/services/quicksight/model/ColumnLevelPermissionRule;)Ljava/util/List;
      23: invokevirtual #8                  // Method principals:(Ljava/util/Collection;)Lsoftware/amazon/awssdk/services/quicksight/model/ColumnLevelPermissionRule$Builder;
      26: pop
      27: aload_0
      28: aload_1
      29: invokestatic  #9                  // Method software/amazon/awssdk/services/quicksight/model/ColumnLevelPermissionRule.access$500:(Lsoftware/amazon/awssdk/services/quicksight/model/ColumnLevelPermissionRule;)Ljava/util/List;
      32: invokevirtual #10                 // Method columnNames:(Ljava/util/Collection;)Lsoftware/amazon/awssdk/services/quicksight/model/ColumnLevelPermissionRule$Builder;
      35: pop
      36: return

  public final java.util.Collection<java.lang.String> getPrincipals();
    Code:
       0: aload_0
       1: getfield      #4                  // Field principals:Ljava/util/List;
       4: instanceof    #11                 // class software/amazon/awssdk/core/util/SdkAutoConstructList
       7: ifeq          12
      10: aconst_null
      11: areturn
      12: aload_0
      13: getfield      #4                  // Field principals:Ljava/util/List;
      16: areturn

  public final software.amazon.awssdk.services.quicksight.model.ColumnLevelPermissionRule$Builder principals(java.util.Collection<java.lang.String>);
    Code:
       0: aload_0
       1: aload_1
       2: invokestatic  #12                 // Method software/amazon/awssdk/services/quicksight/model/PrincipalListCopier.copy:(Ljava/util/Collection;)Ljava/util/List;
       5: putfield      #4                  // Field principals:Ljava/util/List;
       8: aload_0
       9: areturn

  public final software.amazon.awssdk.services.quicksight.model.ColumnLevelPermissionRule$Builder principals(java.lang.String...);
    Code:
       0: aload_0
       1: aload_1
       2: invokestatic  #13                 // Method java/util/Arrays.asList:([Ljava/lang/Object;)Ljava/util/List;
       5: invokevirtual #8                  // Method principals:(Ljava/util/Collection;)Lsoftware/amazon/awssdk/services/quicksight/model/ColumnLevelPermissionRule$Builder;
       8: pop
       9: aload_0
      10: areturn

  public final void setPrincipals(java.util.Collection<java.lang.String>);
    Code:
       0: aload_0
       1: aload_1
       2: invokestatic  #12                 // Method software/amazon/awssdk/services/quicksight/model/PrincipalListCopier.copy:(Ljava/util/Collection;)Ljava/util/List;
       5: putfield      #4                  // Field principals:Ljava/util/List;
       8: return

  public final java.util.Collection<java.lang.String> getColumnNames();
    Code:
       0: aload_0
       1: getfield      #3                  // Field columnNames:Ljava/util/List;
       4: instanceof    #11                 // class software/amazon/awssdk/core/util/SdkAutoConstructList
       7: ifeq          12
      10: aconst_null
      11: areturn
      12: aload_0
      13: getfield      #3                  // Field columnNames:Ljava/util/List;
      16: areturn

  public final software.amazon.awssdk.services.quicksight.model.ColumnLevelPermissionRule$Builder columnNames(java.util.Collection<java.lang.String>);
    Code:
       0: aload_0
       1: aload_1
       2: invokestatic  #14                 // Method software/amazon/awssdk/services/quicksight/model/ColumnNameListCopier.copy:(Ljava/util/Collection;)Ljava/util/List;
       5: putfield      #3                  // Field columnNames:Ljava/util/List;
       8: aload_0
       9: areturn

  public final software.amazon.awssdk.services.quicksight.model.ColumnLevelPermissionRule$Builder columnNames(java.lang.String...);
    Code:
       0: aload_0
       1: aload_1
       2: invokestatic  #13                 // Method java/util/Arrays.asList:([Ljava/lang/Object;)Ljava/util/List;
       5: invokevirtual #10                 // Method columnNames:(Ljava/util/Collection;)Lsoftware/amazon/awssdk/services/quicksight/model/ColumnLevelPermissionRule$Builder;
       8: pop
       9: aload_0
      10: areturn

  public final void setColumnNames(java.util.Collection<java.lang.String>);
    Code:
       0: aload_0
       1: aload_1
       2: invokestatic  #14                 // Method software/amazon/awssdk/services/quicksight/model/ColumnNameListCopier.copy:(Ljava/util/Collection;)Ljava/util/List;
       5: putfield      #3                  // Field columnNames:Ljava/util/List;
       8: return

  public software.amazon.awssdk.services.quicksight.model.ColumnLevelPermissionRule build();
    Code:
       0: new           #15                 // class software/amazon/awssdk/services/quicksight/model/ColumnLevelPermissionRule
       3: dup
       4: aload_0
       5: aconst_null
       6: invokespecial #16                 // Method software/amazon/awssdk/services/quicksight/model/ColumnLevelPermissionRule."<init>":(Lsoftware/amazon/awssdk/services/quicksight/model/ColumnLevelPermissionRule$BuilderImpl;Lsoftware/amazon/awssdk/services/quicksight/model/ColumnLevelPermissionRule$1;)V
       9: areturn

  public java.util.List<software.amazon.awssdk.core.SdkField<?>> sdkFields();
    Code:
       0: invokestatic  #17                 // Method software/amazon/awssdk/services/quicksight/model/ColumnLevelPermissionRule.access$700:()Ljava/util/List;
       3: areturn

  public java.lang.Object build();
    Code:
       0: aload_0
       1: invokevirtual #18                 // Method build:()Lsoftware/amazon/awssdk/services/quicksight/model/ColumnLevelPermissionRule;
       4: areturn

  static java.util.List access$000(software.amazon.awssdk.services.quicksight.model.ColumnLevelPermissionRule$BuilderImpl);
    Code:
       0: aload_0
       1: getfield      #4                  // Field principals:Ljava/util/List;
       4: areturn

  static java.util.List access$100(software.amazon.awssdk.services.quicksight.model.ColumnLevelPermissionRule$BuilderImpl);
    Code:
       0: aload_0
       1: getfield      #3                  // Field columnNames:Ljava/util/List;
       4: areturn

  software.amazon.awssdk.services.quicksight.model.ColumnLevelPermissionRule$BuilderImpl(software.amazon.awssdk.services.quicksight.model.ColumnLevelPermissionRule, software.amazon.awssdk.services.quicksight.model.ColumnLevelPermissionRule$1);
    Code:
       0: aload_0
       1: aload_1
       2: invokespecial #2                  // Method "<init>":(Lsoftware/amazon/awssdk/services/quicksight/model/ColumnLevelPermissionRule;)V
       5: return

  software.amazon.awssdk.services.quicksight.model.ColumnLevelPermissionRule$BuilderImpl(software.amazon.awssdk.services.quicksight.model.ColumnLevelPermissionRule$1);
    Code:
       0: aload_0
       1: invokespecial #1                  // Method "<init>":()V
       4: return
}
