Compiled from "ColumnTag.java"
final class software.amazon.awssdk.services.quicksight.model.ColumnTag$BuilderImpl implements software.amazon.awssdk.services.quicksight.model.ColumnTag$Builder {
  private java.lang.String columnGeographicRole;

  private software.amazon.awssdk.services.quicksight.model.ColumnDescription columnDescription;

  private software.amazon.awssdk.services.quicksight.model.ColumnTag$BuilderImpl();
    Code:
       0: aload_0
       1: invokespecial #5                  // Method java/lang/Object."<init>":()V
       4: return

  private software.amazon.awssdk.services.quicksight.model.ColumnTag$BuilderImpl(software.amazon.awssdk.services.quicksight.model.ColumnTag);
    Code:
       0: aload_0
       1: invokespecial #5                  // Method java/lang/Object."<init>":()V
       4: aload_0
       5: aload_1
       6: invokestatic  #6                  // Method software/amazon/awssdk/services/quicksight/model/ColumnTag.access$400:(Lsoftware/amazon/awssdk/services/quicksight/model/ColumnTag;)Ljava/lang/String;
       9: invokevirtual #7                  // Method columnGeographicRole:(Ljava/lang/String;)Lsoftware/amazon/awssdk/services/quicksight/model/ColumnTag$Builder;
      12: pop
      13: aload_0
      14: aload_1
      15: invokestatic  #8                  // Method software/amazon/awssdk/services/quicksight/model/ColumnTag.access$500:(Lsoftware/amazon/awssdk/services/quicksight/model/ColumnTag;)Lsoftware/amazon/awssdk/services/quicksight/model/ColumnDescription;
      18: invokevirtual #9                  // Method columnDescription:(Lsoftware/amazon/awssdk/services/quicksight/model/ColumnDescription;)Lsoftware/amazon/awssdk/services/quicksight/model/ColumnTag$Builder;
      21: pop
      22: return

  public final java.lang.String getColumnGeographicRole();
    Code:
       0: aload_0
       1: getfield      #4                  // Field columnGeographicRole:Ljava/lang/String;
       4: areturn

  public final software.amazon.awssdk.services.quicksight.model.ColumnTag$Builder columnGeographicRole(java.lang.String);
    Code:
       0: aload_0
       1: aload_1
       2: putfield      #4                  // Field columnGeographicRole:Ljava/lang/String;
       5: aload_0
       6: areturn

  public final software.amazon.awssdk.services.quicksight.model.ColumnTag$Builder columnGeographicRole(software.amazon.awssdk.services.quicksight.model.GeoSpatialDataRole);
    Code:
       0: aload_0
       1: aload_1
       2: ifnonnull     9
       5: aconst_null
       6: goto          13
       9: aload_1
      10: invokevirtual #10                 // Method software/amazon/awssdk/services/quicksight/model/GeoSpatialDataRole.toString:()Ljava/lang/String;
      13: invokevirtual #7                  // Method columnGeographicRole:(Ljava/lang/String;)Lsoftware/amazon/awssdk/services/quicksight/model/ColumnTag$Builder;
      16: pop
      17: aload_0
      18: areturn

  public final void setColumnGeographicRole(java.lang.String);
    Code:
       0: aload_0
       1: aload_1
       2: putfield      #4                  // Field columnGeographicRole:Ljava/lang/String;
       5: return

  public final software.amazon.awssdk.services.quicksight.model.ColumnDescription$Builder getColumnDescription();
    Code:
       0: aload_0
       1: getfield      #3                  // Field columnDescription:Lsoftware/amazon/awssdk/services/quicksight/model/ColumnDescription;
       4: ifnull        17
       7: aload_0
       8: getfield      #3                  // Field columnDescription:Lsoftware/amazon/awssdk/services/quicksight/model/ColumnDescription;
      11: invokevirtual #11                 // Method software/amazon/awssdk/services/quicksight/model/ColumnDescription.toBuilder:()Lsoftware/amazon/awssdk/services/quicksight/model/ColumnDescription$Builder;
      14: goto          18
      17: aconst_null
      18: areturn

  public final software.amazon.awssdk.services.quicksight.model.ColumnTag$Builder columnDescription(software.amazon.awssdk.services.quicksight.model.ColumnDescription);
    Code:
       0: aload_0
       1: aload_1
       2: putfield      #3                  // Field columnDescription:Lsoftware/amazon/awssdk/services/quicksight/model/ColumnDescription;
       5: aload_0
       6: areturn

  public final void setColumnDescription(software.amazon.awssdk.services.quicksight.model.ColumnDescription$BuilderImpl);
    Code:
       0: aload_0
       1: aload_1
       2: ifnull        12
       5: aload_1
       6: invokevirtual #12                 // Method software/amazon/awssdk/services/quicksight/model/ColumnDescription$BuilderImpl.build:()Lsoftware/amazon/awssdk/services/quicksight/model/ColumnDescription;
       9: goto          13
      12: aconst_null
      13: putfield      #3                  // Field columnDescription:Lsoftware/amazon/awssdk/services/quicksight/model/ColumnDescription;
      16: return

  public software.amazon.awssdk.services.quicksight.model.ColumnTag build();
    Code:
       0: new           #13                 // class software/amazon/awssdk/services/quicksight/model/ColumnTag
       3: dup
       4: aload_0
       5: aconst_null
       6: invokespecial #14                 // Method software/amazon/awssdk/services/quicksight/model/ColumnTag."<init>":(Lsoftware/amazon/awssdk/services/quicksight/model/ColumnTag$BuilderImpl;Lsoftware/amazon/awssdk/services/quicksight/model/ColumnTag$1;)V
       9: areturn

  public java.util.List<software.amazon.awssdk.core.SdkField<?>> sdkFields();
    Code:
       0: invokestatic  #15                 // Method software/amazon/awssdk/services/quicksight/model/ColumnTag.access$700:()Ljava/util/List;
       3: areturn

  public java.lang.Object build();
    Code:
       0: aload_0
       1: invokevirtual #16                 // Method build:()Lsoftware/amazon/awssdk/services/quicksight/model/ColumnTag;
       4: areturn

  static java.lang.String access$000(software.amazon.awssdk.services.quicksight.model.ColumnTag$BuilderImpl);
    Code:
       0: aload_0
       1: getfield      #4                  // Field columnGeographicRole:Ljava/lang/String;
       4: areturn

  static software.amazon.awssdk.services.quicksight.model.ColumnDescription access$100(software.amazon.awssdk.services.quicksight.model.ColumnTag$BuilderImpl);
    Code:
       0: aload_0
       1: getfield      #3                  // Field columnDescription:Lsoftware/amazon/awssdk/services/quicksight/model/ColumnDescription;
       4: areturn

  software.amazon.awssdk.services.quicksight.model.ColumnTag$BuilderImpl(software.amazon.awssdk.services.quicksight.model.ColumnTag, software.amazon.awssdk.services.quicksight.model.ColumnTag$1);
    Code:
       0: aload_0
       1: aload_1
       2: invokespecial #2                  // Method "<init>":(Lsoftware/amazon/awssdk/services/quicksight/model/ColumnTag;)V
       5: return

  software.amazon.awssdk.services.quicksight.model.ColumnTag$BuilderImpl(software.amazon.awssdk.services.quicksight.model.ColumnTag$1);
    Code:
       0: aload_0
       1: invokespecial #1                  // Method "<init>":()V
       4: return
}
