Compiled from "DescribeIamPolicyAssignmentResponse.java"
public interface software.amazon.awssdk.services.quicksight.model.DescribeIamPolicyAssignmentResponse$Builder extends software.amazon.awssdk.services.quicksight.model.QuickSightResponse$Builder, software.amazon.awssdk.core.SdkPojo, software.amazon.awssdk.utils.builder.CopyableBuilder<software.amazon.awssdk.services.quicksight.model.DescribeIamPolicyAssignmentResponse$Builder, software.amazon.awssdk.services.quicksight.model.DescribeIamPolicyAssignmentResponse> {
  public abstract software.amazon.awssdk.services.quicksight.model.DescribeIamPolicyAssignmentResponse$Builder iamPolicyAssignment(software.amazon.awssdk.services.quicksight.model.IAMPolicyAssignment);

  public default software.amazon.awssdk.services.quicksight.model.DescribeIamPolicyAssignmentResponse$Builder iamPolicyAssignment(java.util.function.Consumer<software.amazon.awssdk.services.quicksight.model.IAMPolicyAssignment$Builder>);
    Code:
       0: aload_0
       1: invokestatic  #1                  // Method software/amazon/awssdk/services/quicksight/model/IAMPolicyAssignment.builder:()Lsoftware/amazon/awssdk/services/quicksight/model/IAMPolicyAssignment$Builder;
       4: aload_1
       5: invokeinterface #2,  2            // InterfaceMethod software/amazon/awssdk/services/quicksight/model/IAMPolicyAssignment$Builder.applyMutation:(Ljava/util/function/Consumer;)Lsoftware/amazon/awssdk/utils/builder/SdkBuilder;
      10: checkcast     #3                  // class software/amazon/awssdk/services/quicksight/model/IAMPolicyAssignment$Builder
      13: invokeinterface #4,  1            // InterfaceMethod software/amazon/awssdk/services/quicksight/model/IAMPolicyAssignment$Builder.build:()Ljava/lang/Object;
      18: checkcast     #5                  // class software/amazon/awssdk/services/quicksight/model/IAMPolicyAssignment
      21: invokeinterface #6,  2            // InterfaceMethod iamPolicyAssignment:(Lsoftware/amazon/awssdk/services/quicksight/model/IAMPolicyAssignment;)Lsoftware/amazon/awssdk/services/quicksight/model/DescribeIamPolicyAssignmentResponse$Builder;
      26: areturn

  public abstract software.amazon.awssdk.services.quicksight.model.DescribeIamPolicyAssignmentResponse$Builder requestId(java.lang.String);

  public abstract software.amazon.awssdk.services.quicksight.model.DescribeIamPolicyAssignmentResponse$Builder status(java.lang.Integer);
}
