Compiled from "DescribeThemeResponse.java"
public interface software.amazon.awssdk.services.quicksight.model.DescribeThemeResponse$Builder extends software.amazon.awssdk.services.quicksight.model.QuickSightResponse$Builder, software.amazon.awssdk.core.SdkPojo, software.amazon.awssdk.utils.builder.CopyableBuilder<software.amazon.awssdk.services.quicksight.model.DescribeThemeResponse$Builder, software.amazon.awssdk.services.quicksight.model.DescribeThemeResponse> {
  public abstract software.amazon.awssdk.services.quicksight.model.DescribeThemeResponse$Builder theme(software.amazon.awssdk.services.quicksight.model.Theme);

  public default software.amazon.awssdk.services.quicksight.model.DescribeThemeResponse$Builder theme(java.util.function.Consumer<software.amazon.awssdk.services.quicksight.model.Theme$Builder>);
    Code:
       0: aload_0
       1: invokestatic  #1                  // Method software/amazon/awssdk/services/quicksight/model/Theme.builder:()Lsoftware/amazon/awssdk/services/quicksight/model/Theme$Builder;
       4: aload_1
       5: invokeinterface #2,  2            // InterfaceMethod software/amazon/awssdk/services/quicksight/model/Theme$Builder.applyMutation:(Ljava/util/function/Consumer;)Lsoftware/amazon/awssdk/utils/builder/SdkBuilder;
      10: checkcast     #3                  // class software/amazon/awssdk/services/quicksight/model/Theme$Builder
      13: invokeinterface #4,  1            // InterfaceMethod software/amazon/awssdk/services/quicksight/model/Theme$Builder.build:()Ljava/lang/Object;
      18: checkcast     #5                  // class software/amazon/awssdk/services/quicksight/model/Theme
      21: invokeinterface #6,  2            // InterfaceMethod theme:(Lsoftware/amazon/awssdk/services/quicksight/model/Theme;)Lsoftware/amazon/awssdk/services/quicksight/model/DescribeThemeResponse$Builder;
      26: areturn

  public abstract software.amazon.awssdk.services.quicksight.model.DescribeThemeResponse$Builder status(java.lang.Integer);

  public abstract software.amazon.awssdk.services.quicksight.model.DescribeThemeResponse$Builder requestId(java.lang.String);
}
