Compiled from "LogicalTable.java"
public interface software.amazon.awssdk.services.quicksight.model.LogicalTable$Builder extends software.amazon.awssdk.core.SdkPojo, software.amazon.awssdk.utils.builder.CopyableBuilder<software.amazon.awssdk.services.quicksight.model.LogicalTable$Builder, software.amazon.awssdk.services.quicksight.model.LogicalTable> {
  public abstract software.amazon.awssdk.services.quicksight.model.LogicalTable$Builder alias(java.lang.String);

  public abstract software.amazon.awssdk.services.quicksight.model.LogicalTable$Builder dataTransforms(java.util.Collection<software.amazon.awssdk.services.quicksight.model.TransformOperation>);

  public abstract software.amazon.awssdk.services.quicksight.model.LogicalTable$Builder dataTransforms(software.amazon.awssdk.services.quicksight.model.TransformOperation...);

  public abstract software.amazon.awssdk.services.quicksight.model.LogicalTable$Builder dataTransforms(java.util.function.Consumer<software.amazon.awssdk.services.quicksight.model.TransformOperation$Builder>...);

  public abstract software.amazon.awssdk.services.quicksight.model.LogicalTable$Builder source(software.amazon.awssdk.services.quicksight.model.LogicalTableSource);

  public default software.amazon.awssdk.services.quicksight.model.LogicalTable$Builder source(java.util.function.Consumer<software.amazon.awssdk.services.quicksight.model.LogicalTableSource$Builder>);
    Code:
       0: aload_0
       1: invokestatic  #1                  // Method software/amazon/awssdk/services/quicksight/model/LogicalTableSource.builder:()Lsoftware/amazon/awssdk/services/quicksight/model/LogicalTableSource$Builder;
       4: aload_1
       5: invokeinterface #2,  2            // InterfaceMethod software/amazon/awssdk/services/quicksight/model/LogicalTableSource$Builder.applyMutation:(Ljava/util/function/Consumer;)Lsoftware/amazon/awssdk/utils/builder/SdkBuilder;
      10: checkcast     #3                  // class software/amazon/awssdk/services/quicksight/model/LogicalTableSource$Builder
      13: invokeinterface #4,  1            // InterfaceMethod software/amazon/awssdk/services/quicksight/model/LogicalTableSource$Builder.build:()Ljava/lang/Object;
      18: checkcast     #5                  // class software/amazon/awssdk/services/quicksight/model/LogicalTableSource
      21: invokeinterface #6,  2            // InterfaceMethod source:(Lsoftware/amazon/awssdk/services/quicksight/model/LogicalTableSource;)Lsoftware/amazon/awssdk/services/quicksight/model/LogicalTable$Builder;
      26: areturn
}
