Compiled from "RegisterUserRequest.java"
public interface software.amazon.awssdk.services.quicksight.model.RegisterUserRequest$Builder extends software.amazon.awssdk.services.quicksight.model.QuickSightRequest$Builder, software.amazon.awssdk.core.SdkPojo, software.amazon.awssdk.utils.builder.CopyableBuilder<software.amazon.awssdk.services.quicksight.model.RegisterUserRequest$Builder, software.amazon.awssdk.services.quicksight.model.RegisterUserRequest> {
  public abstract software.amazon.awssdk.services.quicksight.model.RegisterUserRequest$Builder identityType(java.lang.String);

  public abstract software.amazon.awssdk.services.quicksight.model.RegisterUserRequest$Builder identityType(software.amazon.awssdk.services.quicksight.model.IdentityType);

  public abstract software.amazon.awssdk.services.quicksight.model.RegisterUserRequest$Builder email(java.lang.String);

  public abstract software.amazon.awssdk.services.quicksight.model.RegisterUserRequest$Builder userRole(java.lang.String);

  public abstract software.amazon.awssdk.services.quicksight.model.RegisterUserRequest$Builder userRole(software.amazon.awssdk.services.quicksight.model.UserRole);

  public abstract software.amazon.awssdk.services.quicksight.model.RegisterUserRequest$Builder iamArn(java.lang.String);

  public abstract software.amazon.awssdk.services.quicksight.model.RegisterUserRequest$Builder sessionName(java.lang.String);

  public abstract software.amazon.awssdk.services.quicksight.model.RegisterUserRequest$Builder awsAccountId(java.lang.String);

  public abstract software.amazon.awssdk.services.quicksight.model.RegisterUserRequest$Builder namespace(java.lang.String);

  public abstract software.amazon.awssdk.services.quicksight.model.RegisterUserRequest$Builder userName(java.lang.String);

  public abstract software.amazon.awssdk.services.quicksight.model.RegisterUserRequest$Builder customPermissionsName(java.lang.String);

  public abstract software.amazon.awssdk.services.quicksight.model.RegisterUserRequest$Builder overrideConfiguration(software.amazon.awssdk.awscore.AwsRequestOverrideConfiguration);

  public abstract software.amazon.awssdk.services.quicksight.model.RegisterUserRequest$Builder overrideConfiguration(java.util.function.Consumer<software.amazon.awssdk.awscore.AwsRequestOverrideConfiguration$Builder>);

  public default software.amazon.awssdk.awscore.AwsRequest$Builder overrideConfiguration(java.util.function.Consumer);
    Code:
       0: aload_0
       1: aload_1
       2: invokeinterface #1,  2            // InterfaceMethod overrideConfiguration:(Ljava/util/function/Consumer;)Lsoftware/amazon/awssdk/services/quicksight/model/RegisterUserRequest$Builder;
       7: areturn

  public default software.amazon.awssdk.awscore.AwsRequest$Builder overrideConfiguration(software.amazon.awssdk.awscore.AwsRequestOverrideConfiguration);
    Code:
       0: aload_0
       1: aload_1
       2: invokeinterface #2,  2            // InterfaceMethod overrideConfiguration:(Lsoftware/amazon/awssdk/awscore/AwsRequestOverrideConfiguration;)Lsoftware/amazon/awssdk/services/quicksight/model/RegisterUserRequest$Builder;
       7: areturn
}
