Compiled from "UpdateIamPolicyAssignmentRequest.java"
public interface software.amazon.awssdk.services.quicksight.model.UpdateIamPolicyAssignmentRequest$Builder extends software.amazon.awssdk.services.quicksight.model.QuickSightRequest$Builder, software.amazon.awssdk.core.SdkPojo, software.amazon.awssdk.utils.builder.CopyableBuilder<software.amazon.awssdk.services.quicksight.model.UpdateIamPolicyAssignmentRequest$Builder, software.amazon.awssdk.services.quicksight.model.UpdateIamPolicyAssignmentRequest> {
  public abstract software.amazon.awssdk.services.quicksight.model.UpdateIamPolicyAssignmentRequest$Builder awsAccountId(java.lang.String);

  public abstract software.amazon.awssdk.services.quicksight.model.UpdateIamPolicyAssignmentRequest$Builder assignmentName(java.lang.String);

  public abstract software.amazon.awssdk.services.quicksight.model.UpdateIamPolicyAssignmentRequest$Builder namespace(java.lang.String);

  public abstract software.amazon.awssdk.services.quicksight.model.UpdateIamPolicyAssignmentRequest$Builder assignmentStatus(java.lang.String);

  public abstract software.amazon.awssdk.services.quicksight.model.UpdateIamPolicyAssignmentRequest$Builder assignmentStatus(software.amazon.awssdk.services.quicksight.model.AssignmentStatus);

  public abstract software.amazon.awssdk.services.quicksight.model.UpdateIamPolicyAssignmentRequest$Builder policyArn(java.lang.String);

  public abstract software.amazon.awssdk.services.quicksight.model.UpdateIamPolicyAssignmentRequest$Builder identities(java.util.Map<java.lang.String, ? extends java.util.Collection<java.lang.String>>);

  public abstract software.amazon.awssdk.services.quicksight.model.UpdateIamPolicyAssignmentRequest$Builder overrideConfiguration(software.amazon.awssdk.awscore.AwsRequestOverrideConfiguration);

  public abstract software.amazon.awssdk.services.quicksight.model.UpdateIamPolicyAssignmentRequest$Builder overrideConfiguration(java.util.function.Consumer<software.amazon.awssdk.awscore.AwsRequestOverrideConfiguration$Builder>);

  public default software.amazon.awssdk.awscore.AwsRequest$Builder overrideConfiguration(java.util.function.Consumer);
    Code:
       0: aload_0
       1: aload_1
       2: invokeinterface #1,  2            // InterfaceMethod overrideConfiguration:(Ljava/util/function/Consumer;)Lsoftware/amazon/awssdk/services/quicksight/model/UpdateIamPolicyAssignmentRequest$Builder;
       7: areturn

  public default software.amazon.awssdk.awscore.AwsRequest$Builder overrideConfiguration(software.amazon.awssdk.awscore.AwsRequestOverrideConfiguration);
    Code:
       0: aload_0
       1: aload_1
       2: invokeinterface #2,  2            // InterfaceMethod overrideConfiguration:(Lsoftware/amazon/awssdk/awscore/AwsRequestOverrideConfiguration;)Lsoftware/amazon/awssdk/services/quicksight/model/UpdateIamPolicyAssignmentRequest$Builder;
       7: areturn
}
