Compiled from "OptionFactoryImpl.java"
public class org.apache.bookkeeper.api.kv.impl.options.OptionFactoryImpl<K> implements org.apache.bookkeeper.api.kv.options.OptionFactory<K> {
  private final io.netty.util.Recycler<org.apache.bookkeeper.api.kv.impl.options.RangeOptionImpl<K>> rangeOptionRecycler;

  private final io.netty.util.Recycler<org.apache.bookkeeper.api.kv.impl.options.RangeOptionBuilderImpl<K>> rangeOptionBuilderRecycler;

  private final io.netty.util.Recycler<org.apache.bookkeeper.api.kv.impl.options.PutOptionImpl<K>> putOptionRecycler;

  private final io.netty.util.Recycler<org.apache.bookkeeper.api.kv.impl.options.PutOptionBuilderImpl<K>> putOptionBuilderRecycler;

  private final io.netty.util.Recycler<org.apache.bookkeeper.api.kv.impl.options.DeleteOptionImpl<K>> deleteOptionRecycler;

  private final io.netty.util.Recycler<org.apache.bookkeeper.api.kv.impl.options.DeleteOptionBuilderImpl<K>> deleteOptionBuilderRecycler;

  private final io.netty.util.Recycler<org.apache.bookkeeper.api.kv.impl.options.IncrementOptionImpl<K>> incrementOptionRecycler;

  private final io.netty.util.Recycler<org.apache.bookkeeper.api.kv.impl.options.IncrementOptionBuilderImpl<K>> incrementOptionBuilderRecycler;

  public org.apache.bookkeeper.api.kv.impl.options.OptionFactoryImpl();
    Code:
       0: aload_0
       1: invokespecial #5                  // Method java/lang/Object."<init>":()V
       4: aload_0
       5: new           #6                  // class org/apache/bookkeeper/api/kv/impl/options/OptionFactoryImpl$1
       8: dup
       9: aload_0
      10: invokespecial #7                  // Method org/apache/bookkeeper/api/kv/impl/options/OptionFactoryImpl$1."<init>":(Lorg/apache/bookkeeper/api/kv/impl/options/OptionFactoryImpl;)V
      13: putfield      #4                  // Field rangeOptionRecycler:Lio/netty/util/Recycler;
      16: aload_0
      17: new           #8                  // class org/apache/bookkeeper/api/kv/impl/options/OptionFactoryImpl$2
      20: dup
      21: aload_0
      22: invokespecial #9                  // Method org/apache/bookkeeper/api/kv/impl/options/OptionFactoryImpl$2."<init>":(Lorg/apache/bookkeeper/api/kv/impl/options/OptionFactoryImpl;)V
      25: putfield      #10                 // Field rangeOptionBuilderRecycler:Lio/netty/util/Recycler;
      28: aload_0
      29: new           #11                 // class org/apache/bookkeeper/api/kv/impl/options/OptionFactoryImpl$3
      32: dup
      33: aload_0
      34: invokespecial #12                 // Method org/apache/bookkeeper/api/kv/impl/options/OptionFactoryImpl$3."<init>":(Lorg/apache/bookkeeper/api/kv/impl/options/OptionFactoryImpl;)V
      37: putfield      #3                  // Field putOptionRecycler:Lio/netty/util/Recycler;
      40: aload_0
      41: new           #13                 // class org/apache/bookkeeper/api/kv/impl/options/OptionFactoryImpl$4
      44: dup
      45: aload_0
      46: invokespecial #14                 // Method org/apache/bookkeeper/api/kv/impl/options/OptionFactoryImpl$4."<init>":(Lorg/apache/bookkeeper/api/kv/impl/options/OptionFactoryImpl;)V
      49: putfield      #15                 // Field putOptionBuilderRecycler:Lio/netty/util/Recycler;
      52: aload_0
      53: new           #16                 // class org/apache/bookkeeper/api/kv/impl/options/OptionFactoryImpl$5
      56: dup
      57: aload_0
      58: invokespecial #17                 // Method org/apache/bookkeeper/api/kv/impl/options/OptionFactoryImpl$5."<init>":(Lorg/apache/bookkeeper/api/kv/impl/options/OptionFactoryImpl;)V
      61: putfield      #2                  // Field deleteOptionRecycler:Lio/netty/util/Recycler;
      64: aload_0
      65: new           #18                 // class org/apache/bookkeeper/api/kv/impl/options/OptionFactoryImpl$6
      68: dup
      69: aload_0
      70: invokespecial #19                 // Method org/apache/bookkeeper/api/kv/impl/options/OptionFactoryImpl$6."<init>":(Lorg/apache/bookkeeper/api/kv/impl/options/OptionFactoryImpl;)V
      73: putfield      #20                 // Field deleteOptionBuilderRecycler:Lio/netty/util/Recycler;
      76: aload_0
      77: new           #21                 // class org/apache/bookkeeper/api/kv/impl/options/OptionFactoryImpl$7
      80: dup
      81: aload_0
      82: invokespecial #22                 // Method org/apache/bookkeeper/api/kv/impl/options/OptionFactoryImpl$7."<init>":(Lorg/apache/bookkeeper/api/kv/impl/options/OptionFactoryImpl;)V
      85: putfield      #1                  // Field incrementOptionRecycler:Lio/netty/util/Recycler;
      88: aload_0
      89: new           #23                 // class org/apache/bookkeeper/api/kv/impl/options/OptionFactoryImpl$8
      92: dup
      93: aload_0
      94: invokespecial #24                 // Method org/apache/bookkeeper/api/kv/impl/options/OptionFactoryImpl$8."<init>":(Lorg/apache/bookkeeper/api/kv/impl/options/OptionFactoryImpl;)V
      97: putfield      #25                 // Field incrementOptionBuilderRecycler:Lio/netty/util/Recycler;
     100: return

  public org.apache.bookkeeper.api.kv.options.PutOptionBuilder<K> newPutOption();
    Code:
       0: aload_0
       1: getfield      #15                 // Field putOptionBuilderRecycler:Lio/netty/util/Recycler;
       4: invokestatic  #26                 // Method org/apache/bookkeeper/api/kv/impl/options/PutOptionBuilderImpl.create:(Lio/netty/util/Recycler;)Lorg/apache/bookkeeper/api/kv/impl/options/PutOptionBuilderImpl;
       7: areturn

  public org.apache.bookkeeper.api.kv.options.RangeOptionBuilder<K> newRangeOption();
    Code:
       0: aload_0
       1: getfield      #10                 // Field rangeOptionBuilderRecycler:Lio/netty/util/Recycler;
       4: invokestatic  #27                 // Method org/apache/bookkeeper/api/kv/impl/options/RangeOptionBuilderImpl.create:(Lio/netty/util/Recycler;)Lorg/apache/bookkeeper/api/kv/impl/options/RangeOptionBuilderImpl;
       7: areturn

  public org.apache.bookkeeper.api.kv.options.DeleteOptionBuilder<K> newDeleteOption();
    Code:
       0: aload_0
       1: getfield      #20                 // Field deleteOptionBuilderRecycler:Lio/netty/util/Recycler;
       4: invokestatic  #28                 // Method org/apache/bookkeeper/api/kv/impl/options/DeleteOptionBuilderImpl.create:(Lio/netty/util/Recycler;)Lorg/apache/bookkeeper/api/kv/impl/options/DeleteOptionBuilderImpl;
       7: areturn

  public org.apache.bookkeeper.api.kv.options.IncrementOptionBuilder<K> newIncrementOption();
    Code:
       0: aload_0
       1: getfield      #25                 // Field incrementOptionBuilderRecycler:Lio/netty/util/Recycler;
       4: invokestatic  #29                 // Method org/apache/bookkeeper/api/kv/impl/options/IncrementOptionBuilderImpl.create:(Lio/netty/util/Recycler;)Lorg/apache/bookkeeper/api/kv/impl/options/IncrementOptionBuilderImpl;
       7: areturn

  static io.netty.util.Recycler access$000(org.apache.bookkeeper.api.kv.impl.options.OptionFactoryImpl);
    Code:
       0: aload_0
       1: getfield      #4                  // Field rangeOptionRecycler:Lio/netty/util/Recycler;
       4: areturn

  static io.netty.util.Recycler access$100(org.apache.bookkeeper.api.kv.impl.options.OptionFactoryImpl);
    Code:
       0: aload_0
       1: getfield      #3                  // Field putOptionRecycler:Lio/netty/util/Recycler;
       4: areturn

  static io.netty.util.Recycler access$200(org.apache.bookkeeper.api.kv.impl.options.OptionFactoryImpl);
    Code:
       0: aload_0
       1: getfield      #2                  // Field deleteOptionRecycler:Lio/netty/util/Recycler;
       4: areturn

  static io.netty.util.Recycler access$300(org.apache.bookkeeper.api.kv.impl.options.OptionFactoryImpl);
    Code:
       0: aload_0
       1: getfield      #1                  // Field incrementOptionRecycler:Lio/netty/util/Recycler;
       4: areturn
}
