Compiled from "CircuitStats.java"
public interface net.jodah.failsafe.internal.CircuitStats {
  public static net.jodah.failsafe.internal.CircuitStats create(net.jodah.failsafe.CircuitBreaker, int, boolean, net.jodah.failsafe.internal.CircuitStats);
    Code:
       0: iload_2
       1: ifeq          33
       4: aload_0
       5: invokevirtual #1                  // Method net/jodah/failsafe/CircuitBreaker.getFailureThresholdingPeriod:()Ljava/time/Duration;
       8: ifnull        33
      11: new           #2                  // class net/jodah/failsafe/internal/TimedCircuitStats
      14: dup
      15: bipush        10
      17: aload_0
      18: invokevirtual #1                  // Method net/jodah/failsafe/CircuitBreaker.getFailureThresholdingPeriod:()Ljava/time/Duration;
      21: new           #3                  // class net/jodah/failsafe/internal/TimedCircuitStats$Clock
      24: dup
      25: invokespecial #4                  // Method net/jodah/failsafe/internal/TimedCircuitStats$Clock."<init>":()V
      28: aload_3
      29: invokespecial #5                  // Method net/jodah/failsafe/internal/TimedCircuitStats."<init>":(ILjava/time/Duration;Lnet/jodah/failsafe/internal/TimedCircuitStats$Clock;Lnet/jodah/failsafe/internal/CircuitStats;)V
      32: areturn
      33: iload_1
      34: iconst_1
      35: if_icmple     48
      38: new           #6                  // class net/jodah/failsafe/internal/CountingCircuitStats
      41: dup
      42: iload_1
      43: aload_3
      44: invokespecial #7                  // Method net/jodah/failsafe/internal/CountingCircuitStats."<init>":(ILnet/jodah/failsafe/internal/CircuitStats;)V
      47: areturn
      48: new           #8                  // class net/jodah/failsafe/internal/DefaultCircuitStats
      51: dup
      52: invokespecial #9                  // Method net/jodah/failsafe/internal/DefaultCircuitStats."<init>":()V
      55: areturn

  public default void copyExecutions(net.jodah.failsafe.internal.CircuitStats);
    Code:
       0: iconst_0
       1: istore_2
       2: iload_2
       3: aload_1
       4: invokeinterface #10,  1           // InterfaceMethod getSuccessCount:()I
       9: if_icmpge     24
      12: aload_0
      13: invokeinterface #11,  1           // InterfaceMethod recordSuccess:()V
      18: iinc          2, 1
      21: goto          2
      24: iconst_0
      25: istore_2
      26: iload_2
      27: aload_1
      28: invokeinterface #12,  1           // InterfaceMethod getFailureCount:()I
      33: if_icmpge     48
      36: aload_0
      37: invokeinterface #11,  1           // InterfaceMethod recordSuccess:()V
      42: iinc          2, 1
      45: goto          26
      48: return

  public abstract int getFailureCount();

  public abstract int getExecutionCount();

  public abstract int getSuccessCount();

  public abstract int getFailureRate();

  public abstract int getSuccessRate();

  public abstract void recordFailure();

  public abstract void recordSuccess();
}
